{
  "type": "Feature",
  "properties": {
    "addr:full":"2480 Dixie Hwy S Radcliff KY 40160",
    "addr:housenumber":"2480",
    "addr:postcode":"40160",
    "addr:street":"Dixie Hwy S",
    "iso:country":"US",
    "sg:address":"2480 Dixie Hwy S",
    "sg:city":"Radcliff",
    "sg:classifiers":[
        {
            "category":"Home & Garden",
            "subcategory":"Building Materials",
            "type":"Retail Goods"
        }
    ],
    "sg:phone":"+1 270 351 7800",
    "sg:postcode":"40160",
    "sg:province":"KY",
    "sg:tags":[
        "equipment",
        "electric",
        "supply"
    ],
    "wof:name":"Radcliff Electrical Supply",
    "wof:placetype":"venue"
},
  "geometry": {"coordinates":[-85.919833,37.806273],"type":"Point"}
}