{
  "type": "Feature",
  "properties": {
    "iso:country":"US",
    "sg:address":"1706 State Hwy 185",
    "sg:city":"Bowling Green",
    "sg:classifiers":[
        {
            "category":"Building & Trades",
            "subcategory":"Plumbing",
            "type":"Services"
        }
    ],
    "sg:phone":"+1 270 843 4982",
    "sg:postcode":"42101",
    "sg:province":"KY",
    "sg:tags":[
        "plumbing",
        "contractor"
    ],
    "wof:name":"Southern Kentucky Mechanical",
    "wof:placetype":"venue"
},
  "geometry": {"coordinates":[-86.44321600000001,37.015988],"type":"Point"}
}