{
  "type": "Feature",
  "properties": {
    "iso:country":"US",
    "sg:address":"201 E Brown St",
    "sg:city":"Nicholasville",
    "sg:classifiers":[
        {
            "category":"Government",
            "subcategory":"Office",
            "type":"Public Place"
        }
    ],
    "sg:phone":"+1 859 885 5695",
    "sg:postcode":"40356",
    "sg:province":"KY",
    "sg:tags":[
        "village"
    ],
    "wof:name":"Nicholasville Sewage Treatment",
    "wof:placetype":"venue"
},
  "geometry": {"coordinates":[-84.569138,37.876173],"type":"Point"}
}