{
  "type": "Feature",
  "properties": {
    "iso:country":"US",
    "sg:address":"1501 Broadway St",
    "sg:city":"Paducah",
    "sg:classifiers":[
        {
            "category":"Professional",
            "subcategory":"Business Services",
            "type":"Services"
        }
    ],
    "sg:phone":"+1 270 443 2423",
    "sg:postcode":"42001",
    "sg:province":"KY",
    "sg:tags":[
        "recording",
        "studio"
    ],
    "sg:website":"www.paradiserecording.com",
    "wof:name":"Paradise Recording Studio",
    "wof:placetype":"venue"
},
  "geometry": {"coordinates":[-88.613563,37.080456],"type":"Point"}
}