{
  "type": "Feature",
  "properties": {
    "addr:full":"4903 Ginev Way Louisville KY 40219",
    "addr:housenumber":"4903",
    "addr:postcode":"40219",
    "addr:street":"Ginev Way",
    "iso:country":"US",
    "sg:address":"4903 Ginev Way",
    "sg:city":"Louisville",
    "sg:classifiers":[
        {
            "category":"Building & Trades",
            "subcategory":"Construction",
            "type":"Services"
        }
    ],
    "sg:phone":"+1 502 964 0133",
    "sg:postcode":"40219",
    "sg:province":"KY",
    "sg:tags":[
        "hanging",
        "contractor"
    ],
    "wof:name":"Murphy Painting Matt",
    "wof:placetype":"venue"
},
  "geometry": {"coordinates":[-85.666957,38.133847],"type":"Point"}
}