{
  "type": "Feature",
  "properties": {
    "iso:country":"US",
    "sg:address":"325 Odessa Way",
    "sg:city":"Paducah",
    "sg:classifiers":[
        {
            "category":"Travel",
            "subcategory":"Travel Agent",
            "type":"Entertainment"
        }
    ],
    "sg:phone":"+1 270 444 6333",
    "sg:postcode":"42001",
    "sg:province":"KY",
    "sg:tags":[
        "agency",
        "bureau"
    ],
    "wof:name":"Worldwide Travel & Cruise Inc",
    "wof:placetype":"venue"
},
  "geometry": {"coordinates":[-88.72474200000001,37.022235],"type":"Point"}
}