{
  "type": "Feature",
  "properties": {
    "addr:full":"440 Chestnut St Berea KY 40403",
    "addr:housenumber":"440",
    "addr:postcode":"40403",
    "addr:street":"Chestnut St",
    "iso:country":"US",
    "sg:address":"440 Chestnut St",
    "sg:city":"Berea",
    "sg:classifiers":[
        {
            "category":"Restaurant",
            "type":"Food & Drink"
        }
    ],
    "sg:phone":"+1 859 986 8597",
    "sg:postcode":"40403",
    "sg:province":"KY",
    "sg:tags":[
        "shop",
        "coffee"
    ],
    "wof:name":"Coffee Conspiracy",
    "wof:placetype":"venue"
},
  "geometry": {"coordinates":[-84.29637099999999,37.568538],"type":"Point"}
}