{
  "type": "Feature",
  "properties": {
    "addr:full":"1753 Monmouth St Newport KY 41071",
    "addr:housenumber":"1753",
    "addr:postcode":"41071",
    "addr:street":"Monmouth St",
    "iso:country":"US",
    "sg:address":"1753 Monmouth St",
    "sg:city":"Newport",
    "sg:classifiers":[
        {
            "category":"Shopping",
            "subcategory":"Clothing, Apparel, & Fashions",
            "type":"Retail Goods"
        }
    ],
    "sg:phone":"+1 859 431 1700",
    "sg:postcode":"41071",
    "sg:province":"KY",
    "sg:tags":[
        "sport"
    ],
    "wof:name":"Transfer Station",
    "wof:placetype":"venue"
},
  "geometry": {"coordinates":[-84.48223,39.08263],"type":"Point"}
}