{
  "type": "Feature",
  "properties": {
    "iso:country":"US",
    "sg:address":"2635 S 11th St",
    "sg:city":"Ironton",
    "sg:classifiers":[
        {
            "category":"Personal",
            "subcategory":"Beauty Salon",
            "type":"Services"
        }
    ],
    "sg:phone":"+1 740 532 2757",
    "sg:postcode":"45638",
    "sg:province":"OH",
    "wof:name":"House Of James",
    "wof:placetype":"venue"
},
  "geometry": {"coordinates":[-82.65853199999999,38.5167],"type":"Point"}
}