{
  "type": "Feature",
  "properties": {
    "iso:country":"US",
    "sg:address":"1137 Saint Gregory St",
    "sg:city":"Cincinnati",
    "sg:classifiers":[
        {
            "category":"Personal",
            "subcategory":"Beauty Salon",
            "type":"Services"
        }
    ],
    "sg:phone":"+1 513 721 4247",
    "sg:postcode":"45202",
    "sg:province":"OH",
    "wof:name":"Cashions Hair Studio",
    "wof:placetype":"venue"
},
  "geometry": {"coordinates":[-84.497629,39.109107],"type":"Point"}
}