{
  "type": "Feature",
  "properties": {
    "iso:country":"US",
    "sg:address":"116 Park Ave",
    "sg:city":"Greensburg",
    "sg:classifiers":[
        {
            "category":"Freight",
            "type":"Transportation"
        }
    ],
    "sg:phone":"+1 270 932 9707",
    "sg:postcode":"42743",
    "sg:province":"KY",
    "sg:tags":[
        "operator",
        "trucking"
    ],
    "wof:name":"V L I Transportation Inc",
    "wof:placetype":"venue"
},
  "geometry": {"coordinates":[-85.497472,37.246151],"type":"Point"}
}