{
  "type": "Feature",
  "properties": {
    "iso:country":"US",
    "sg:address":"469 Roberts Ave",
    "sg:city":"Louisville",
    "sg:classifiers":[
        {
            "category":"Retail",
            "subcategory":"Repair Shop",
            "type":"Services"
        }
    ],
    "sg:phone":"+1 502 368 8011",
    "sg:postcode":"40214",
    "sg:province":"KY",
    "sg:tags":[
        "welding"
    ],
    "wof:name":"Jack Brown Engineering",
    "wof:placetype":"venue"
},
  "geometry": {"coordinates":[-85.761827,38.155976],"type":"Point"}
}