{
  "type": "Feature",
  "properties": {
    "iso:country":"US",
    "sg:address":"309 1st St",
    "sg:city":"Vine Grove",
    "sg:classifiers":[
        {
            "category":"Education",
            "subcategory":"School",
            "type":"Public Place"
        }
    ],
    "sg:phone":"+1 270 877 5410",
    "sg:postcode":"40175",
    "sg:province":"KY",
    "wof:name":"Vine Grove Elementary School",
    "wof:placetype":"venue"
},
  "geometry": {"coordinates":[-85.986249,37.806854],"type":"Point"}
}