{
  "type": "Feature",
  "properties": {
    "iso:country":"US",
    "sg:address":"720 North Dr",
    "sg:city":"Hopkinsville",
    "sg:classifiers":[
        {
            "category":"Education",
            "subcategory":"College",
            "type":"Public Place"
        }
    ],
    "sg:phone":"+1 270 881 9220",
    "sg:postcode":"42240",
    "sg:province":"KY",
    "sg:tags":[
        "academic",
        "school"
    ],
    "wof:name":"Trevecca Nazarene University",
    "wof:placetype":"venue"
},
  "geometry": {"coordinates":[-87.4933,36.881847],"type":"Point"}
}