{
  "type": "Feature",
  "properties": {
    "iso:country":"US",
    "sg:address":"902 N 15th St",
    "sg:city":"Mayfield",
    "sg:classifiers":[
        {
            "category":"Organizations",
            "subcategory":"Community Association",
            "type":"Services"
        }
    ],
    "sg:phone":"+1 270 623 8180",
    "sg:postcode":"42066",
    "sg:province":"KY",
    "sg:tags":[
        "military"
    ],
    "wof:name":"Disabled American Veterans",
    "wof:placetype":"venue"
},
  "geometry": {"coordinates":[-88.64531599999999,36.749362],"type":"Point"}
}