{
  "type": "Feature",
  "properties": {
    "addr:full":"4004 Preston Hwy Louisville KY 40213",
    "addr:housenumber":"4004",
    "addr:postcode":"40213",
    "addr:street":"Preston Hwy",
    "iso:country":"US",
    "sg:address":"4004 Preston Hwy",
    "sg:city":"Louisville",
    "sg:classifiers":[
        {
            "category":"Health Services",
            "subcategory":"Doctor",
            "type":"Services"
        }
    ],
    "sg:phone":"+1 502 363 4600",
    "sg:postcode":"40213",
    "sg:province":"KY",
    "sg:tags":[
        "dentist"
    ],
    "wof:name":"Hope Dental Ctr",
    "wof:placetype":"venue"
},
  "geometry": {"coordinates":[-85.72918900000001,38.193871],"type":"Point"}
}