{
  "type": "Feature",
  "properties": {
    "iso:country":"US",
    "sg:address":"4540 Brooks Rd",
    "sg:city":"Catlettsburg",
    "sg:classifiers":[
        {
            "category":"Building & Trades",
            "subcategory":"Construction",
            "type":"Services"
        }
    ],
    "sg:phone":"+1 606 928 3421",
    "sg:postcode":"41168",
    "sg:province":"KY",
    "sg:tags":[
        "house"
    ],
    "wof:name":"Marcum Const",
    "wof:placetype":"venue"
},
  "geometry": {"coordinates":[-82.646782,38.304162],"type":"Point"}
}