{
  "type": "Feature",
  "properties": {
    "addr:full":"2835 Fort Campbell Blvd Hopkinsville KY 42240",
    "addr:housenumber":"2835",
    "addr:postcode":"42240",
    "addr:street":"Fort Campbell Blvd",
    "iso:country":"US",
    "sg:address":"2835 Fort Campbell Blvd",
    "sg:city":"Hopkinsville",
    "sg:classifiers":[
        {
            "category":"Retail",
            "subcategory":"Car Wash",
            "type":"Services"
        }
    ],
    "sg:phone":"+1 270 889 9309",
    "sg:postcode":"42240",
    "sg:province":"KY",
    "wof:name":"Super Subs",
    "wof:placetype":"venue"
},
  "geometry": {"coordinates":[-87.480442,36.839027],"type":"Point"}
}