{
  "type": "Feature",
  "properties": {
    "iso:country":"US",
    "sg:address":"349 S Shore Rd",
    "sg:city":"South Shore",
    "sg:classifiers":[
        {
            "category":"Banks & Credit Unions",
            "subcategory":"Bank",
            "type":"Services"
        }
    ],
    "sg:phone":"+1 606 932 3108",
    "sg:postcode":"41175",
    "sg:province":"KY",
    "wof:name":"Peoples Bank",
    "wof:placetype":"venue"
},
  "geometry": {"coordinates":[-82.975234,38.721326],"type":"Point"}
}