{
  "type": "Feature",
  "properties": {
    "addr:full":"1939 Goldsmith Ln Louisville KY 40218",
    "addr:housenumber":"1939",
    "addr:postcode":"40218",
    "addr:street":"Goldsmith Ln",
    "iso:country":"US",
    "sg:address":"1939 Goldsmith Ln",
    "sg:city":"Louisville",
    "sg:classifiers":[
        {
            "category":"Health Services",
            "subcategory":"Medical Lab",
            "type":"Services"
        }
    ],
    "sg:phone":"+1 502 451 2224",
    "sg:postcode":"40218",
    "sg:province":"KY",
    "sg:tags":[
        "laboratory",
        "testing"
    ],
    "wof:name":"Ceramic Arts Dental Laboratory",
    "wof:placetype":"venue"
},
  "geometry": {"coordinates":[-85.680412,38.202438],"type":"Point"}
}