{
  "type": "Feature",
  "properties": {
    "iso:country":"US",
    "sg:address":"8201 Port Royal Rd",
    "sg:city":"Port Royal",
    "sg:classifiers":[
        {
            "category":"Food & Beverages",
            "subcategory":"Groceries & Convenience Stores",
            "type":"Retail Goods"
        }
    ],
    "sg:phone":"+1 502 947 5147",
    "sg:postcode":"40075",
    "sg:province":"KY",
    "sg:tags":[
        "grocer"
    ],
    "wof:name":"Port Royal Grocery",
    "wof:placetype":"venue"
},
  "geometry": {"coordinates":[-85.086276,38.552534],"type":"Point"}
}