{
  "type": "Feature",
  "properties": {
    "addr:full":"7628 Dixie Hwy Florence KY 41042",
    "addr:housenumber":"7628",
    "addr:postcode":"41042",
    "addr:street":"Dixie Hwy",
    "iso:country":"US",
    "sg:address":"7628 Dixie Hwy",
    "sg:city":"Florence",
    "sg:classifiers":[
        {
            "category":"Professional",
            "subcategory":"Accounting & Tax Preparation",
            "type":"Services"
        }
    ],
    "sg:phone":"+1 859 283 2910",
    "sg:postcode":"41042",
    "sg:province":"KY",
    "sg:tags":[
        "accountant"
    ],
    "sg:website":"www.accountingbookkeepingservices.com",
    "wof:name":"Accounting & Bookkeeping Svc",
    "wof:placetype":"venue"
},
  "geometry": {"coordinates":[-84.62375,38.991464],"type":"Point"}
}