{
  "type": "Feature",
  "properties": {
    "iso:country":"US",
    "sg:address":"4346 Bullittsville Rd",
    "sg:city":"Burlington",
    "sg:classifiers":[
        {
            "category":"Building & Trades",
            "subcategory":"Construction",
            "type":"Services"
        }
    ],
    "sg:phone":"+1 859 586 9142",
    "sg:postcode":"41005",
    "sg:province":"KY",
    "sg:tags":[
        "excavating",
        "contractor"
    ],
    "wof:name":"Affordable Repairs Inc",
    "wof:placetype":"venue"
},
  "geometry": {"coordinates":[-84.723612,39.056884],"type":"Point"}
}