{
  "type": "Feature",
  "properties": {
    "addr:full":"9451 Morgantown Rd Russellville KY 42276",
    "addr:housenumber":"9451",
    "addr:postcode":"42276",
    "addr:street":"Morgantown Rd",
    "iso:country":"US",
    "sg:address":"9451 Morgantown Rd",
    "sg:city":"Russellville",
    "sg:classifiers":[
        {
            "category":"Farming",
            "subcategory":"Farm",
            "type":"Manufacturing & Wholesale Goods"
        }
    ],
    "sg:phone":"+1 270 542 6552",
    "sg:postcode":"42276",
    "sg:province":"KY",
    "sg:tags":[
        "crop",
        "general"
    ],
    "wof:name":"Curtis Looper",
    "wof:placetype":"venue"
},
  "geometry": {"coordinates":[-86.79525,36.947329],"type":"Point"}
}