{
  "type": "Feature",
  "properties": {
    "addr:full":"13689 Falls of Rough Rd Falls Of Rough KY 40119",
    "addr:housenumber":"13689",
    "addr:postcode":"40119",
    "addr:street":"Falls Of Rough Rd",
    "iso:country":"US",
    "sg:address":"13689 Falls of Rough Rd",
    "sg:city":"Falls Of Rough",
    "sg:classifiers":[
        {
            "category":"Travel",
            "subcategory":"Hotels & Motels",
            "type":"Entertainment"
        }
    ],
    "sg:phone":"+1 270 257 2771",
    "sg:postcode":"40119",
    "sg:province":"KY",
    "wof:name":"Pine Tree Inn",
    "wof:placetype":"venue"
},
  "geometry": {"coordinates":[-86.513183,37.596488],"type":"Point"}
}