{
  "type": "Feature",
  "properties": {
    "iso:country":"US",
    "sg:address":"1101 Washington St",
    "sg:city":"Shelbyville",
    "sg:classifiers":[
        {
            "category":"Autos & Motor Vehicles",
            "subcategory":"Motorcycle Sales",
            "type":"Retail Goods"
        }
    ],
    "sg:phone":"+1 502 647 1759",
    "sg:postcode":"40065",
    "sg:province":"KY",
    "sg:tags":[
        "all",
        "terrain"
    ],
    "wof:name":"Shelby Powersports",
    "wof:placetype":"venue"
},
  "geometry": {"coordinates":[-85.226083,38.212666],"type":"Point"}
}