{
  "type": "Feature",
  "properties": {
    "iso:country":"US",
    "sg:address":"563 S Limestone St",
    "sg:city":"Lexington",
    "sg:classifiers":[
        {
            "category":"Shopping",
            "subcategory":"Books",
            "type":"Retail Goods"
        }
    ],
    "sg:phone":"+1 859 225 7771",
    "sg:postcode":"40508",
    "sg:province":"KY",
    "sg:tags":[
        "dealer"
    ],
    "sg:website":"www.wildcattext.com",
    "wof:name":"Wildcat Text Books",
    "wof:placetype":"venue"
},
  "geometry": {"coordinates":[-84.507373,38.037793],"type":"Point"}
}