{
  "type": "Feature",
  "properties": {
    "addr:full":"7155 Houston Rd Florence KY 41042",
    "addr:housenumber":"7155",
    "addr:postcode":"41042",
    "addr:street":"Houston Rd",
    "iso:country":"US",
    "sg:address":"7155 Houston Rd",
    "sg:city":"Florence",
    "sg:classifiers":[
        {
            "category":"Banks & Credit Unions",
            "subcategory":"Bank",
            "type":"Services"
        }
    ],
    "sg:phone":"+1 859 817 3200",
    "sg:postcode":"41042",
    "sg:province":"KY",
    "sg:website":"www.integrabank.com",
    "wof:name":"Integra Bank",
    "wof:placetype":"venue"
},
  "geometry": {"coordinates":[-84.65024200000001,39.007919],"type":"Point"}
}