{
  "type": "Feature",
  "properties": {
    "addr:full":"871 Hawkins - Cummins Rd Paris KY 40361",
    "addr:housenumber":"871",
    "addr:postcode":"40361",
    "addr:street":"Hawkins Cummins Rd",
    "iso:country":"US",
    "sg:address":"871 Hawkins - Cummins Rd",
    "sg:city":"Paris",
    "sg:classifiers":[
        {
            "category":"Farming",
            "subcategory":"Farm",
            "type":"Manufacturing & Wholesale Goods"
        }
    ],
    "sg:phone":"+1 859 987 0076",
    "sg:postcode":"40361",
    "sg:province":"KY",
    "wof:name":"Haven Farm",
    "wof:placetype":"venue"
},
  "geometry": {"coordinates":[-84.25689199999999,38.212652],"type":"Point"}
}