{
  "type": "Feature",
  "properties": {
    "iso:country":"US",
    "sg:address":"6701 Outer Loop",
    "sg:city":"Louisville",
    "sg:classifiers":[
        {
            "category":"Social Services",
            "subcategory":"Child Care",
            "type":"Services"
        }
    ],
    "sg:phone":"+1 502 239 7423",
    "sg:postcode":"40228",
    "sg:province":"KY",
    "wof:name":"Learning Tree Nursery School",
    "wof:placetype":"venue"
},
  "geometry": {"coordinates":[-85.636477,38.137789],"type":"Point"}
}