{
  "type": "Feature",
  "properties": {
    "iso:country":"US",
    "sg:address":"6511 Bardstown Rd",
    "sg:city":"Louisville",
    "sg:classifiers":[
        {
            "category":"Wholesale",
            "subcategory":"Jewelry",
            "type":"Manufacturing & Wholesale Goods"
        }
    ],
    "sg:phone":"+1 502 239 1231",
    "sg:postcode":"40291",
    "sg:province":"KY",
    "sg:tags":[
        "jeweler"
    ],
    "wof:name":"Edlin Co Fine Jewelry",
    "wof:placetype":"venue"
},
  "geometry": {"coordinates":[-85.58725200000001,38.1501],"type":"Point"}
}