{
  "type": "Feature",
  "properties": {
    "addr:full":"291 McElvain Rd Hanson KY 42413",
    "addr:housenumber":"291",
    "addr:postcode":"42413",
    "addr:street":"Mcelvain Rd",
    "iso:country":"US",
    "sg:address":"291 McElvain Rd",
    "sg:city":"Hanson",
    "sg:classifiers":[
        {
            "category":"Building & Trades",
            "subcategory":"Plumbing",
            "type":"Services"
        }
    ],
    "sg:phone":"+1 270 322 8089",
    "sg:postcode":"42413",
    "sg:province":"KY",
    "sg:tags":[
        "plumbing",
        "contractor"
    ],
    "wof:name":"Scott Plumbing",
    "wof:placetype":"venue"
},
  "geometry": {"coordinates":[-87.448379,37.419272],"type":"Point"}
}