{
  "type": "Feature",
  "properties": {
    "iso:country":"US",
    "sg:address":"4812 Middlesex Dr",
    "sg:city":"Louisville",
    "sg:classifiers":[
        {
            "category":"Professional",
            "subcategory":"Management & Consulting",
            "type":"Services"
        }
    ],
    "sg:phone":"+1 502 327 6216",
    "sg:postcode":"40245",
    "sg:province":"KY",
    "wof:name":"Response Marketing Inc",
    "wof:placetype":"venue"
},
  "geometry": {"coordinates":[-85.52159399999999,38.309649],"type":"Point"}
}