{
  "type": "Feature",
  "properties": {
    "addr:full":"111 Faubush-Norfleet Rd Faubush KY 42544",
    "addr:housenumber":"111",
    "addr:postcode":"42544",
    "addr:street":"Faubush-Norfleet Rd",
    "iso:country":"US",
    "sg:address":"111 Faubush-Norfleet Rd",
    "sg:city":"Faubush",
    "sg:classifiers":[
        {
            "category":"Building & Trades",
            "subcategory":"Construction",
            "type":"Services"
        }
    ],
    "sg:phone":"+1 606 871 7682",
    "sg:postcode":"42544",
    "sg:province":"KY",
    "sg:tags":[
        "roofing",
        "contractor"
    ],
    "wof:name":"Pulaski Roofing",
    "wof:placetype":"venue"
},
  "geometry": {"coordinates":[-84.831773,37.055564],"type":"Point"}
}