{
  "type": "Feature",
  "properties": {
    "addr:full":"410 Moxley Rd Hawesville KY 42348",
    "addr:housenumber":"410",
    "addr:postcode":"42348",
    "addr:street":"Moxley Rd",
    "iso:country":"US",
    "sg:address":"410 Moxley Rd",
    "sg:city":"Hawesville",
    "sg:classifiers":[
        {
            "category":"Farming",
            "subcategory":"Livestock Farm",
            "type":"Manufacturing & Wholesale Goods"
        }
    ],
    "sg:phone":"+1 270 927 8163",
    "sg:postcode":"42348",
    "sg:province":"KY",
    "sg:tags":[
        "beef",
        "feedlot",
        "cattle"
    ],
    "wof:name":"Harship Hills Farm",
    "wof:placetype":"venue"
},
  "geometry": {"coordinates":[-86.77090200000001,37.773577],"type":"Point"}
}