{
  "type": "Feature",
  "properties": {
    "iso:country":"US",
    "sg:address":"9403 Mill Brook Rd",
    "sg:city":"Louisville",
    "sg:classifiers":[
        {
            "category":"Wholesale",
            "subcategory":"Medical Equipment & Supplies",
            "type":"Manufacturing & Wholesale Goods"
        }
    ],
    "sg:phone":"+1 502 425 0662",
    "sg:postcode":"40223",
    "sg:province":"KY",
    "sg:tags":[
        "hospital"
    ],
    "wof:name":"Health Procurement Svc",
    "wof:placetype":"venue"
},
  "geometry": {"coordinates":[-85.575682,38.265035],"type":"Point"}
}