{
  "type": "Feature",
  "properties": {
    "addr:full":"1154 Burlington Pike Florence KY 41042",
    "addr:housenumber":"1154",
    "addr:postcode":"41042",
    "addr:street":"Burlington Pike",
    "iso:country":"US",
    "sg:address":"1154 Burlington Pike",
    "sg:city":"Florence",
    "sg:classifiers":[
        {
            "category":"Autos & Motor Vehicles",
            "subcategory":"Automobile Sales",
            "type":"Retail Goods"
        },
        {
            "category":"Retail",
            "subcategory":"Auto Repair",
            "type":"Services"
        }
    ],
    "sg:phone":"+1 859 525 8001",
    "sg:postcode":"41042",
    "sg:province":"KY",
    "sg:tags":[
        "car"
    ],
    "sg:website":"jeffwylerflorencebuickgmc.com",
    "wof:name":"Jeff Wyler Florence Buick GMC",
    "wof:placetype":"venue"
},
  "geometry": {"coordinates":[-84.665993,39.010594],"type":"Point"}
}