{
  "type": "Feature",
  "properties": {
    "addr:full":"540 Madison Ave Covington KY 41011",
    "addr:housenumber":"540",
    "addr:postcode":"41011",
    "addr:street":"Madison Ave",
    "iso:country":"US",
    "sg:address":"540 Madison Ave",
    "sg:city":"Covington",
    "sg:classifiers":[
        {
            "category":"Banks & Credit Unions",
            "subcategory":"Bank",
            "type":"Services"
        }
    ],
    "sg:phone":"+1 859 292 7610",
    "sg:postcode":"41011",
    "sg:province":"KY",
    "wof:name":"Huntington National Bank",
    "wof:placetype":"venue"
},
  "geometry": {"coordinates":[-84.510372,39.084801],"type":"Point"}
}