{
  "type": "Feature",
  "properties": {
    "addr:full":"433 Dixie Hwy E Elizabethtown KY 42701",
    "addr:housenumber":"433",
    "addr:postcode":"42701",
    "addr:street":"Dixie Hwy E",
    "iso:country":"US",
    "sg:address":"433 Dixie Hwy E",
    "sg:city":"Elizabethtown",
    "sg:classifiers":[
        {
            "category":"Professional",
            "type":"Services"
        }
    ],
    "sg:phone":"+1 270 765 2112",
    "sg:postcode":"42701",
    "sg:province":"KY",
    "wof:name":"Meers Service Ctr",
    "wof:placetype":"venue"
},
  "geometry": {"coordinates":[-85.85356299999999,37.688559],"type":"Point"}
}