{
  "type": "Feature",
  "properties": {
    "iso:country":"US",
    "sg:address":"1636 W Oak St",
    "sg:city":"Louisville",
    "sg:classifiers":[
        {
            "category":"Personal",
            "subcategory":"Barber",
            "type":"Services"
        }
    ],
    "sg:phone":"+1 502 637 8857",
    "sg:postcode":"40210",
    "sg:province":"KY",
    "wof:name":"Young Styles Barber Shop",
    "wof:placetype":"venue"
},
  "geometry": {"coordinates":[-85.782302,38.23692],"type":"Point"}
}