{
  "type": "Feature",
  "properties": {
    "iso:country":"US",
    "sg:address":"321 N Madison Ave",
    "sg:city":"Richmond",
    "sg:classifiers":[
        {
            "category":"Government",
            "subcategory":"Office",
            "type":"Public Place"
        }
    ],
    "sg:phone":"+1 859 624 4734",
    "sg:postcode":"40475",
    "sg:province":"KY",
    "wof:name":"Madison County 911 Street Addr",
    "wof:placetype":"venue"
},
  "geometry": {"coordinates":[-84.291878,37.748453],"type":"Point"}
}