{
  "type": "Feature",
  "properties": {
    "iso:country":"US",
    "sg:address":"101 W Washington St",
    "sg:city":"Princeton",
    "sg:classifiers":[
        {
            "category":"Banks & Credit Unions",
            "subcategory":"Bank",
            "type":"Services"
        }
    ],
    "sg:phone":"+1 270 365 3545",
    "sg:postcode":"42445",
    "sg:province":"KY",
    "wof:name":"First Bank & Trust Co",
    "wof:placetype":"venue"
},
  "geometry": {"coordinates":[-87.883877,37.1085],"type":"Point"}
}