{
  "type": "Feature",
  "properties": {
    "addr:full":"630 Barret Ave Louisville KY 40204",
    "addr:housenumber":"630",
    "addr:postcode":"40204",
    "addr:street":"Barret Ave",
    "iso:country":"US",
    "sg:address":"630 Barret Ave",
    "sg:city":"Louisville",
    "sg:classifiers":[
        {
            "category":"Restaurant",
            "type":"Food & Drink"
        }
    ],
    "sg:phone":"+1 502 589 9090",
    "sg:postcode":"40204",
    "sg:province":"KY",
    "wof:name":"Jillian's",
    "wof:placetype":"venue"
},
  "geometry": {"coordinates":[-85.733296,38.245011],"type":"Point"}
}