{
  "type": "Feature",
  "properties": {
    "iso:country":"US",
    "sg:address":"5 May Village Rd",
    "sg:city":"Allen",
    "sg:classifiers":[
        {
            "category":"Freight",
            "type":"Transportation"
        }
    ],
    "sg:phone":"+1 606 874 9481",
    "sg:postcode":"41603",
    "sg:province":"KY",
    "sg:tags":[
        "operator",
        "local",
        "trucking"
    ],
    "wof:name":"Mercy Trucking Company Inc",
    "wof:placetype":"venue"
},
  "geometry": {"coordinates":[-82.71365,37.614727],"type":"Point"}
}