{
  "type": "Feature",
  "properties": {
    "addr:full":"321 S Ashland Ave Lexington KY 40502",
    "addr:housenumber":"321",
    "addr:postcode":"40502",
    "addr:street":"S Ashland Ave",
    "iso:country":"US",
    "sg:address":"321 S Ashland Ave",
    "sg:city":"Lexington",
    "sg:classifiers":[
        {
            "category":"Restaurant",
            "type":"Food & Drink"
        }
    ],
    "sg:phone":"+1 859 335 6826",
    "sg:postcode":"40502",
    "sg:province":"KY",
    "wof:name":"Royal Fasica Christine",
    "wof:placetype":"venue"
},
  "geometry": {"coordinates":[-84.491165,38.030532],"type":"Point"}
}