{
  "type": "Feature",
  "properties": {
    "iso:country":"US",
    "sg:address":"849 Clintonville Rd",
    "sg:city":"Paris",
    "sg:classifiers":[
        {
            "category":"Building & Trades",
            "subcategory":"Electrical",
            "type":"Services"
        }
    ],
    "sg:phone":"+1 859 987 3259",
    "sg:postcode":"40361",
    "sg:province":"KY",
    "sg:tags":[
        "electric",
        "contractor"
    ],
    "wof:name":"Crump Electric Svc",
    "wof:placetype":"venue"
},
  "geometry": {"coordinates":[-84.258306,38.174039],"type":"Point"}
}