{
  "type": "Feature",
  "properties": {
    "iso:country":"US",
    "sg:address":"2763 N Main St",
    "sg:city":"Hazard",
    "sg:classifiers":[
        {
            "category":"Shopping",
            "subcategory":"Discount & Variety Stores",
            "type":"Retail Goods"
        }
    ],
    "sg:phone":"+1 606 439 1665",
    "sg:postcode":"41701",
    "sg:province":"KY",
    "sg:tags":[
        "post",
        "trading"
    ],
    "wof:name":"Brewer's Trading Post",
    "wof:placetype":"venue"
},
  "geometry": {"coordinates":[-83.190365,37.270372],"type":"Point"}
}