{
  "type": "Feature",
  "properties": {
    "addr:full":"224 Main St Irvine KY 40336",
    "addr:housenumber":"224",
    "addr:postcode":"40336",
    "addr:street":"Main St",
    "iso:country":"US",
    "sg:address":"224 Main St",
    "sg:city":"Irvine",
    "sg:classifiers":[
        {
            "category":"Retail",
            "subcategory":"Funeral Services",
            "type":"Services"
        }
    ],
    "sg:phone":"+1 606 723 2151",
    "sg:postcode":"40336",
    "sg:province":"KY",
    "sg:tags":[
        "director"
    ],
    "wof:name":"Lewis Funeral Home Inc",
    "wof:placetype":"venue"
},
  "geometry": {"coordinates":[-83.975413,37.701708],"type":"Point"}
}