{
  "type": "Feature",
  "properties": {
    "iso:country":"US",
    "sg:address":"718 Shelby St",
    "sg:city":"Frankfort",
    "sg:classifiers":[
        {
            "category":"Professional",
            "subcategory":"Business Services",
            "type":"Services"
        }
    ],
    "sg:phone":"+1 502 223 4181",
    "sg:postcode":"40601",
    "sg:province":"KY",
    "sg:tags":[
        "water",
        "conservation"
    ],
    "wof:name":"Kentucky Rural Water Assoc",
    "wof:placetype":"venue"
},
  "geometry": {"coordinates":[-84.87695100000001,38.188151],"type":"Point"}
}