{
  "type": "Feature",
  "properties": {
    "addr:full":"22728 US Hwy 421 Hyden KY 41749",
    "addr:postcode":"22728;41749",
    "addr:street":"Us Hwy 421",
    "iso:country":"US",
    "sg:address":"22728 US Hwy 421",
    "sg:city":"Hyden",
    "sg:classifiers":[
        {
            "category":"Health Services",
            "subcategory":"Clinic",
            "type":"Services"
        }
    ],
    "sg:phone":"+1 606 672 2262",
    "sg:postcode":"41749",
    "sg:province":"KY",
    "wof:name":"Kentucky Home Place",
    "wof:placetype":"venue"
},
  "geometry": {"coordinates":[-83.39006500000001,37.152207],"type":"Point"}
}