{
  "type": "Feature",
  "properties": {
    "iso:country":"US",
    "sg:address":"215 Outer Loop",
    "sg:city":"Louisville",
    "sg:classifiers":[
        {
            "category":"Professional",
            "subcategory":"Advertising",
            "type":"Services"
        }
    ],
    "sg:phone":"+1 502 368 4356",
    "sg:postcode":"40214",
    "sg:province":"KY",
    "sg:tags":[
        "distribution"
    ],
    "wof:name":"Doyle Distributors",
    "wof:placetype":"venue"
},
  "geometry": {"coordinates":[-85.76756899999999,38.125869],"type":"Point"}
}