{
  "type": "Feature",
  "properties": {
    "iso:country":"US",
    "sg:address":"4304 Alexandria Pike",
    "sg:city":"Cold Spring",
    "sg:classifiers":[
        {
            "category":"Retail",
            "subcategory":"Repair Shop",
            "type":"Services"
        }
    ],
    "sg:phone":"+1 859 441 0149",
    "sg:postcode":"41076",
    "sg:province":"KY",
    "sg:tags":[
        "television",
        "radio"
    ],
    "wof:name":"Goetz's TV",
    "wof:placetype":"venue"
},
  "geometry": {"coordinates":[-84.43494800000001,39.017223],"type":"Point"}
}