{
  "type": "Feature",
  "properties": {
    "addr:full":"2508 Watterson Trl Louisville KY 40299",
    "addr:housenumber":"2508",
    "addr:postcode":"40299",
    "addr:street":"Watterson Trl",
    "iso:country":"US",
    "sg:address":"2508 Watterson Trl",
    "sg:city":"Louisville",
    "sg:classifiers":[
        {
            "category":"Wholesale",
            "subcategory":"Auto Parts",
            "type":"Manufacturing & Wholesale Goods"
        }
    ],
    "sg:phone":"+1 502 240 9918",
    "sg:postcode":"40299",
    "sg:province":"KY",
    "sg:tags":[
        "tire"
    ],
    "wof:name":"United Supply Group",
    "wof:placetype":"venue"
},
  "geometry": {"coordinates":[-85.55915899999999,38.208162],"type":"Point"}
}