{
  "type": "Feature",
  "properties": {
    "iso:country":"US",
    "sg:address":"636 Madison Ave",
    "sg:city":"Covington",
    "sg:classifiers":[
        {
            "category":"Government",
            "subcategory":"Office",
            "type":"Public Place"
        }
    ],
    "sg:phone":"+1 859 292 6513",
    "sg:postcode":"41011",
    "sg:province":"KY",
    "sg:tags":[
        "state",
        "resource"
    ],
    "wof:name":"Vocational Rehabilitation Dept",
    "wof:placetype":"venue"
},
  "geometry": {"coordinates":[-84.510077,39.083607],"type":"Point"}
}