{
  "type": "Feature",
  "properties": {
    "iso:country":"US",
    "sg:address":"36 Preston Cates",
    "sg:city":"Sebree",
    "sg:classifiers":[
        {
            "category":"Personal",
            "subcategory":"Beauty Salon",
            "type":"Services"
        }
    ],
    "sg:phone":"+1 270 884 3411",
    "sg:postcode":"42455",
    "sg:province":"KY",
    "sg:tags":[
        "shop"
    ],
    "wof:name":"Hair Affair",
    "wof:placetype":"venue"
},
  "geometry": {"coordinates":[-87.437231,37.55634],"type":"Point"}
}