{
  "type": "Feature",
  "properties": {
    "iso:country":"US",
    "sg:address":"541 Buttermilk Pike",
    "sg:city":"Covington",
    "sg:classifiers":[
        {
            "category":"Insurance",
            "subcategory":"Hazard Insurance",
            "type":"Services"
        }
    ],
    "sg:phone":"+1 859 426 1204",
    "sg:postcode":"41017",
    "sg:province":"KY",
    "sg:tags":[
        "carrier",
        "surety"
    ],
    "wof:name":"Primerica",
    "wof:placetype":"venue"
},
  "geometry": {"coordinates":[-84.576519,39.049593],"type":"Point"}
}