{
  "type": "Feature",
  "properties": {
    "iso:country":"US",
    "sg:address":"4412 Outer Loop",
    "sg:city":"Okolona",
    "sg:classifiers":[
        {
            "category":"Banks & Credit Unions",
            "subcategory":"Bank",
            "type":"Services"
        }
    ],
    "sg:phone":"+1 502 966 9877",
    "sg:postcode":"40219",
    "sg:province":"KY",
    "sg:tags":[
        "cashing",
        "check"
    ],
    "wof:name":"Advance America",
    "wof:placetype":"venue"
},
  "geometry": {"coordinates":[-85.67702800000001,38.137983],"type":"Point"}
}