{
  "type": "Feature",
  "properties": {
    "addr:full":"9803 Taylorsville Rd Louisville KY 40299",
    "addr:housenumber":"9803",
    "addr:postcode":"40299",
    "addr:street":"Taylorsville Rd",
    "iso:country":"US",
    "sg:address":"9803 Taylorsville Rd",
    "sg:city":"Louisville",
    "sg:classifiers":[
        {
            "category":"Autos & Motor Vehicles",
            "subcategory":"Auto Supplies",
            "type":"Retail Goods"
        },
        {
            "category":"Retail",
            "subcategory":"Auto Repair",
            "type":"Services"
        }
    ],
    "sg:phone":"+1 502 267 8558",
    "sg:postcode":"40299",
    "sg:province":"KY",
    "sg:tags":[
        "automobile",
        "part",
        "truck"
    ],
    "sg:website":"http://clickserve.dartsearch.net/link/click?lid=43000000313868392&ds_s_kwgid=58000000006820725&ds_e_matchtype={MatchType}&ds_e_kwdid={OrderItemId}&ds_e_adid={AdId}&ds_url_v=2",
    "wof:name":"Jeffersontown Auto Electric, Current Solutions DBA",
    "wof:placetype":"venue"
},
  "geometry": {"coordinates":[-85.57495900000001,38.202438],"type":"Point"}
}