{
  "type": "Feature",
  "properties": {
    "iso:country":"US",
    "sg:address":"205 Fairfield Ave",
    "sg:city":"Bellevue",
    "sg:classifiers":[
        {
            "category":"Personal",
            "subcategory":"Beauty Salon",
            "type":"Services"
        }
    ],
    "sg:phone":"+1 859 581 9944",
    "sg:postcode":"41073",
    "sg:province":"KY",
    "sg:tags":[
        "shop"
    ],
    "wof:name":"Ave Salon of Beauty",
    "wof:placetype":"venue"
},
  "geometry": {"coordinates":[-84.48399499999999,39.105783],"type":"Point"}
}