{
  "type": "Feature",
  "properties": {
    "iso:country":"US",
    "sg:address":"110 Thomas St",
    "sg:city":"Fort Thomas",
    "sg:classifiers":[
        {
            "category":"Food & Beverages",
            "subcategory":"Liquor & Beverages",
            "type":"Retail Goods"
        }
    ],
    "sg:phone":"+1 859 441 4900",
    "sg:postcode":"41042",
    "sg:province":"KY",
    "wof:name":"Fort Thomas Wine & Spirits",
    "wof:placetype":"venue"
},
  "geometry": {"coordinates":[-84.634242,39.005706],"type":"Point"}
}