{
  "type": "Feature",
  "properties": {
    "iso:country":"US",
    "sg:address":"231 Main St",
    "sg:city":"Benham",
    "sg:classifiers":[
        {
            "category":"Museum",
            "type":"Entertainment"
        }
    ],
    "sg:phone":"+1 606 848 1530",
    "sg:postcode":"40807",
    "sg:province":"KY",
    "wof:name":"Kentucky Coal Mining Museum",
    "wof:placetype":"venue"
},
  "geometry": {"coordinates":[-82.95079,36.964027],"type":"Point"}
}