{
  "type": "Feature",
  "properties": {
    "addr:full":"368 US Hwy 27 Somerset KY 42503",
    "addr:housenumber":"368",
    "addr:postcode":"42503",
    "addr:street":"Us Hwy 27",
    "iso:country":"US",
    "sg:address":"368 US Hwy 27",
    "sg:city":"Somerset",
    "sg:classifiers":[
        {
            "category":"Banks & Credit Unions",
            "subcategory":"Investment Brokerage",
            "type":"Services"
        }
    ],
    "sg:phone":"+1 606 679 7050",
    "sg:postcode":"42503",
    "sg:province":"KY",
    "sg:tags":[
        "funds",
        "mutual"
    ],
    "wof:name":"Edward Jones Co",
    "wof:placetype":"venue"
},
  "geometry": {"coordinates":[-84.629341,37.141761],"type":"Point"}
}