{
  "type": "Feature",
  "properties": {
    "addr:full":"213 W 19th St Covington KY 41014",
    "addr:housenumber":"213",
    "addr:postcode":"41014",
    "addr:street":"W 19Th St",
    "iso:country":"US",
    "sg:address":"213 W 19th St",
    "sg:city":"Covington",
    "sg:classifiers":[
        {
            "category":"Bars & Pubs",
            "type":"Food & Drink"
        }
    ],
    "sg:phone":"+1 859 581 9200",
    "sg:postcode":"41014",
    "sg:province":"KY",
    "sg:tags":[
        "drinking"
    ],
    "wof:name":"Last Chance Saloon",
    "wof:placetype":"venue"
},
  "geometry": {"coordinates":[-84.509902,39.066581],"type":"Point"}
}