{
  "type": "Feature",
  "properties": {
    "iso:country":"US",
    "sg:address":"11545 Decoursey Pike",
    "sg:city":"Covington",
    "sg:classifiers":[
        {
            "category":"Food & Beverages",
            "subcategory":"Groceries & Convenience Stores",
            "type":"Retail Goods"
        }
    ],
    "sg:phone":"+1 859 356 9877",
    "sg:postcode":"41015",
    "sg:province":"KY",
    "sg:tags":[
        "grocer"
    ],
    "wof:name":"Visalia Market",
    "wof:placetype":"venue"
},
  "geometry": {"coordinates":[-84.452394,38.917973],"type":"Point"}
}