{
  "type": "Feature",
  "properties": {
    "addr:full":"527 N Main St Franklin KY 42134",
    "addr:housenumber":"527",
    "addr:postcode":"42134",
    "addr:street":"N Main St",
    "iso:country":"US",
    "sg:address":"527 N Main St",
    "sg:city":"Franklin",
    "sg:classifiers":[
        {
            "category":"Restaurant",
            "type":"Food & Drink"
        }
    ],
    "sg:menulink":"http://www.allmenus.com/ky/franklin/173586-wendys/menu/",
    "sg:phone":"+1 270 586 9358",
    "sg:postcode":"42134",
    "sg:province":"KY",
    "sg:tags":[
        "burger",
        "american",
        "soup"
    ],
    "wof:name":"Wendy's",
    "wof:placetype":"venue"
},
  "geometry": {"coordinates":[-86.57800899999999,36.727548],"type":"Point"}
}