{
  "type": "Feature",
  "properties": {
    "addr:full":"177 Melvina Dr Pikeville KY 41501",
    "addr:housenumber":"177",
    "addr:postcode":"41501",
    "addr:street":"Melvina Dr",
    "iso:country":"US",
    "sg:address":"177 Melvina Dr",
    "sg:city":"Pikeville",
    "sg:classifiers":[
        {
            "category":"Shopping",
            "subcategory":"Gifts & Souvenirs",
            "type":"Retail Goods"
        }
    ],
    "sg:phone":"+1 606 437 2345",
    "sg:postcode":"41501",
    "sg:province":"KY",
    "wof:name":"Case A Basket",
    "wof:placetype":"venue"
},
  "geometry": {"coordinates":[-82.50317699999999,37.478213],"type":"Point"}
}