{
  "type": "Feature",
  "properties": {
    "iso:country":"US",
    "sg:address":"516 Bales Mill Rd",
    "sg:city":"Greensburg",
    "sg:classifiers":[
        {
            "category":"Building & Trades",
            "subcategory":"Construction",
            "type":"Services"
        }
    ],
    "sg:phone":"+1 270 932 4450",
    "sg:postcode":"42743",
    "sg:province":"KY",
    "sg:tags":[
        "barn"
    ],
    "wof:name":"Sturdi Built Barns",
    "wof:placetype":"venue"
},
  "geometry": {"coordinates":[-85.561378,37.296455],"type":"Point"}
}