{
  "type": "Feature",
  "properties": {
    "iso:country":"US",
    "sg:address":"142 Olympia Dr",
    "sg:city":"Bardstown",
    "sg:classifiers":[
        {
            "category":"Retail",
            "subcategory":"Repair Shop",
            "type":"Services"
        }
    ],
    "sg:phone":"+1 502 348 6489",
    "sg:postcode":"40004",
    "sg:province":"KY",
    "wof:name":"Lanham Marine Machine",
    "wof:placetype":"venue"
},
  "geometry": {"coordinates":[-85.44579400000001,37.804514],"type":"Point"}
}