{
  "type": "Feature",
  "properties": {
    "iso:country":"US",
    "sg:address":"1260 Fox Creek Rd",
    "sg:city":"Lawrenceburg",
    "sg:classifiers":[
        {
            "category":"Home & Garden",
            "subcategory":"Hardware",
            "type":"Retail Goods"
        }
    ],
    "sg:phone":"+1 502 839 1928",
    "sg:postcode":"40342",
    "sg:province":"KY",
    "sg:tags":[
        "saw"
    ],
    "wof:name":"Coast To Coast Store",
    "wof:placetype":"venue"
},
  "geometry": {"coordinates":[-84.911751,38.019312],"type":"Point"}
}