{
  "type": "Feature",
  "properties": {
    "addr:full":"2950 Shepherdsville Rd Elizabethtown KY 42701",
    "addr:housenumber":"2950",
    "addr:postcode":"42701",
    "addr:street":"Shepherdsville Rd",
    "iso:country":"US",
    "sg:address":"2950 Shepherdsville Rd",
    "sg:city":"Elizabethtown",
    "sg:classifiers":[
        {
            "category":"Organizations",
            "subcategory":"Religious Organization",
            "type":"Services"
        }
    ],
    "sg:phone":"+1 270 737 5037",
    "sg:postcode":"42701",
    "sg:province":"KY",
    "wof:name":"Corporation of President of Th",
    "wof:placetype":"venue"
},
  "geometry": {"coordinates":[-85.843245,37.73438],"type":"Point"}
}