{
  "type": "Feature",
  "properties": {
    "iso:country":"US",
    "sg:address":"2005 S Hwy 53",
    "sg:city":"La Grange",
    "sg:classifiers":[
        {
            "category":"Health Services",
            "subcategory":"Doctor",
            "type":"Services"
        }
    ],
    "sg:phone":"+1 502 222 4613",
    "sg:postcode":"40031",
    "sg:province":"KY",
    "sg:tags":[
        "dentist"
    ],
    "wof:name":"Engilman Orthodontics",
    "wof:placetype":"venue"
},
  "geometry": {"coordinates":[-85.361856,38.383063],"type":"Point"}
}