{
  "type": "Feature",
  "properties": {
    "addr:full":"51 State Hwy 2034 Whitesburg KY 41858",
    "addr:housenumber":"51",
    "addr:postcode":"2034;41858",
    "addr:street":"State Hwy",
    "iso:country":"US",
    "sg:address":"51 State Hwy 2034",
    "sg:city":"Whitesburg",
    "sg:phone":"+1 606 633 2525",
    "sg:postcode":"41858",
    "sg:province":"KY",
    "sg:tags":[
        "oil"
    ],
    "sg:website":"www.doublekwik.com",
    "wof:name":"Childers Oil Co",
    "wof:placetype":"venue"
},
  "geometry": {"coordinates":[-82.802598,37.112837],"type":"Point"}
}