{
  "type": "Feature",
  "properties": {
    "addr:full":"231 Scott Blvd Covington KY 41011",
    "addr:housenumber":"231",
    "addr:postcode":"41011",
    "addr:street":"Scott Blvd",
    "iso:country":"US",
    "sg:address":"231 Scott Blvd",
    "sg:city":"Covington",
    "sg:classifiers":[
        {
            "category":"Professional",
            "subcategory":"Accounting & Tax Preparation",
            "type":"Services"
        }
    ],
    "sg:phone":"+1 859 655 2300",
    "sg:postcode":"41011",
    "sg:province":"KY",
    "sg:tags":[
        "accountant"
    ],
    "wof:name":"Munninghoff Lange & Co",
    "wof:placetype":"venue"
},
  "geometry": {"coordinates":[-84.51009000000001,39.089627],"type":"Point"}
}