{
  "type": "Feature",
  "properties": {
    "iso:country":"US",
    "sg:address":"989 Manns Rd",
    "sg:city":"Harrodsburg",
    "sg:classifiers":[
        {
            "category":"Organizations",
            "subcategory":"Religious Organization",
            "type":"Services"
        }
    ],
    "sg:phone":"+1 859 366 5531",
    "sg:postcode":"40330",
    "sg:province":"KY",
    "sg:tags":[
        "church"
    ],
    "wof:name":"Cornishville Baptist Church",
    "wof:placetype":"venue"
},
  "geometry": {"coordinates":[-84.967585,37.807063],"type":"Point"}
}