{
  "type": "Feature",
  "properties": {
    "addr:full":"3700 Hinkleville Rd Paducah KY 42001",
    "addr:housenumber":"3700",
    "addr:postcode":"42001",
    "addr:street":"Hinkleville Rd",
    "iso:country":"US",
    "sg:address":"3700 Hinkleville Rd",
    "sg:city":"Paducah",
    "sg:classifiers":[
        {
            "category":"Real Estate",
            "subcategory":"Real Estate Operator",
            "type":"Services"
        }
    ],
    "sg:phone":"+1 270 488 3148",
    "sg:postcode":"42001",
    "sg:province":"KY",
    "sg:tags":[
        "apartment"
    ],
    "wof:name":"Wayncath Apts",
    "wof:placetype":"venue"
},
  "geometry": {"coordinates":[-88.664546,37.083299],"type":"Point"}
}