{
  "type": "Feature",
  "properties": {
    "iso:country":"US",
    "sg:address":"9300 Shelbyville Rd # 402",
    "sg:city":"Louisville",
    "sg:classifiers":[
        {
            "category":"Banks & Credit Unions",
            "subcategory":"Financial Services",
            "type":"Services"
        }
    ],
    "sg:phone":"+1 502 326 4300",
    "sg:postcode":"40222",
    "sg:province":"KY",
    "sg:tags":[
        "purchasing"
    ],
    "sg:website":"http://www.directsourcing.com",
    "wof:name":"Dssi",
    "wof:placetype":"venue"
},
  "geometry": {"coordinates":[-85.579033,38.246559],"type":"Point"}
}