{
  "type": "Feature",
  "properties": {
    "addr:full":"125 Kingswood Dr Campbellsville KY 42718",
    "addr:housenumber":"125",
    "addr:postcode":"42718",
    "addr:street":"Kingswood Dr",
    "iso:country":"US",
    "sg:address":"125 Kingswood Dr",
    "sg:city":"Campbellsville",
    "sg:classifiers":[
        {
            "category":"Health Services",
            "subcategory":"Doctor",
            "type":"Services"
        }
    ],
    "sg:phone":"+1 270 465 0632",
    "sg:postcode":"42718",
    "sg:province":"KY",
    "sg:tags":[
        "physician",
        "surgeon"
    ],
    "wof:name":"Chong Min Park MD",
    "wof:placetype":"venue"
},
  "geometry": {"coordinates":[-85.33713,37.36575],"type":"Point"}
}