{
  "type": "Feature",
  "properties": {
    "addr:full":"321 Kentucky Home Sq Bardstown KY 40004",
    "addr:housenumber":"321",
    "addr:postcode":"40004",
    "addr:street":"Kentucky Home Sq",
    "iso:country":"US",
    "sg:address":"321 Kentucky Home Sq",
    "sg:city":"Bardstown",
    "sg:classifiers":[
        {
            "category":"Restaurant",
            "type":"Food & Drink"
        }
    ],
    "sg:menulink":"http://www.allmenus.com/ky/bardstown/79649-pizza-hut/menu/",
    "sg:phone":"+1 502 348 6967",
    "sg:postcode":"40004",
    "sg:province":"KY",
    "sg:tags":[
        "american",
        "pizza"
    ],
    "wof:name":"Pizza Hut",
    "wof:placetype":"venue"
},
  "geometry": {"coordinates":[-85.470083,37.821874],"type":"Point"}
}