{
  "type": "Feature",
  "properties": {
    "iso:country":"US",
    "sg:address":"440 Phillipstown Rd",
    "sg:city":"Central City",
    "sg:classifiers":[
        {
            "category":"Real Estate",
            "subcategory":"Real Estate Operator",
            "type":"Services"
        }
    ],
    "sg:phone":"+1 270 757 9479",
    "sg:postcode":"42325",
    "sg:province":"KY",
    "sg:tags":[
        "mobile",
        "home",
        "community"
    ],
    "wof:name":"Willow Creek Community",
    "wof:placetype":"venue"
},
  "geometry": {"coordinates":[-87.301473,37.321033],"type":"Point"}
}