{
  "type": "Feature",
  "properties": {
    "iso:country":"US",
    "sg:address":"306 N Ashland Ave",
    "sg:city":"Lexington",
    "sg:classifiers":[
        {
            "category":"Building & Trades",
            "subcategory":"Cleaning & Sanitation",
            "type":"Services"
        }
    ],
    "sg:phone":"+1 859 252 8884",
    "sg:postcode":"40502",
    "sg:province":"KY",
    "sg:tags":[
        "janitor"
    ],
    "wof:name":"SSC Svc Solutions",
    "wof:placetype":"venue"
},
  "geometry": {"coordinates":[-84.477805,38.039639],"type":"Point"}
}