{
  "type": "Feature",
  "properties": {
    "addr:full":"1915 N 10th St Paducah KY 42001",
    "addr:housenumber":"1915",
    "addr:postcode":"42001",
    "addr:street":"N 10Th St",
    "iso:country":"US",
    "sg:address":"1915 N 10th St",
    "sg:city":"Paducah",
    "sg:classifiers":[
        {
            "category":"Place Of Worship",
            "subcategory":"Church",
            "type":"Public Place"
        },
        {
            "category":"Place Of Worship",
            "type":"Public Place"
        }
    ],
    "sg:phone":"+1 270 575 9800",
    "sg:postcode":"42001",
    "sg:province":"KY",
    "sg:tags":[
        "churches-baptist-general",
        "churches-baptist-missionary",
        "churches-baptist"
    ],
    "wof:name":"Mt Sinai M B Church Inc",
    "wof:placetype":"venue"
},
  "geometry": {"coordinates":[-88.62756400000001,37.094963],"type":"Point"}
}