{
  "type": "Feature",
  "properties": {
    "iso:country":"US",
    "sg:address":"811 S 2nd St",
    "sg:city":"Louisville",
    "sg:classifiers":[
        {
            "category":"Professional",
            "subcategory":"Credit Reporting & Collection",
            "type":"Services"
        }
    ],
    "sg:phone":"+1 502 589 2027",
    "sg:postcode":"40203",
    "sg:province":"KY",
    "sg:tags":[
        "agency"
    ],
    "sg:website":"www.cstcoinc.com",
    "wof:name":"CST Co",
    "wof:placetype":"venue"
},
  "geometry": {"coordinates":[-85.75570399999999,38.241704],"type":"Point"}
}