{
  "type": "Feature",
  "properties": {
    "addr:full":"4813 Redman Ct Louisville KY 40291",
    "addr:housenumber":"4813",
    "addr:postcode":"40291",
    "addr:street":"Redman Ct",
    "iso:country":"US",
    "sg:address":"4813 Redman Ct",
    "sg:city":"Louisville",
    "sg:classifiers":[
        {
            "category":"Freight",
            "type":"Transportation"
        }
    ],
    "sg:phone":"+1 502 231 2699",
    "sg:postcode":"40291",
    "sg:province":"KY",
    "sg:tags":[
        "operator",
        "trucking"
    ],
    "wof:name":"Wolverine Transportation Inc",
    "wof:placetype":"venue"
},
  "geometry": {"coordinates":[-85.59007,38.175595],"type":"Point"}
}