{
  "type": "Feature",
  "properties": {
    "iso:country":"US",
    "sg:address":"4331 Robards Ln",
    "sg:city":"Louisville",
    "sg:classifiers":[
        {
            "category":"Wholesale",
            "subcategory":"Hardware",
            "type":"Manufacturing & Wholesale Goods"
        }
    ],
    "sg:phone":"+1 502 454 0003",
    "sg:postcode":"40218",
    "sg:province":"KY",
    "sg:tags":[
        "heating",
        "system",
        "electric"
    ],
    "wof:name":"Southland Electrical Supply",
    "wof:placetype":"venue"
},
  "geometry": {"coordinates":[-85.69190999999999,38.196605],"type":"Point"}
}