{
  "type": "Feature",
  "properties": {
    "addr:full":"918 N Green St Henderson KY 42420",
    "addr:housenumber":"918",
    "addr:postcode":"42420",
    "addr:street":"N Green St",
    "iso:country":"US",
    "sg:address":"918 N Green St",
    "sg:city":"Henderson",
    "sg:classifiers":[
        {
            "category":"Autos & Motor Vehicles",
            "subcategory":"Automobile Sales",
            "type":"Retail Goods"
        }
    ],
    "sg:phone":"+1 270 827 9922",
    "sg:postcode":"42420",
    "sg:province":"KY",
    "sg:tags":[
        "car",
        "dealer"
    ],
    "wof:name":"Gene Powers Motors",
    "wof:placetype":"venue"
},
  "geometry": {"coordinates":[-87.582308,37.848813],"type":"Point"}
}