{
  "type": "Feature",
  "properties": {
    "iso:country":"US",
    "sg:address":"3737 Leighwood Dr",
    "sg:city":"Ashland",
    "sg:classifiers":[
        {
            "category":"Professional",
            "subcategory":"Business Services",
            "type":"Services"
        }
    ],
    "sg:phone":"+1 606 329 8456",
    "sg:postcode":"41102",
    "sg:province":"KY",
    "wof:name":"Linda John Interior Design",
    "wof:placetype":"venue"
},
  "geometry": {"coordinates":[-82.65075299999999,38.443484],"type":"Point"}
}