{
  "type": "Feature",
  "properties": {
    "iso:country":"US",
    "sg:address":"2755 New Haven Rd",
    "sg:city":"Bardstown",
    "sg:classifiers":[
        {
            "category":"Professional",
            "subcategory":"Accounting & Tax Preparation",
            "type":"Services"
        }
    ],
    "sg:phone":"+1 502 348 0739",
    "sg:postcode":"40004",
    "sg:province":"KY",
    "sg:tags":[
        "return",
        "filing"
    ],
    "wof:name":"Sutherland Business Systems",
    "wof:placetype":"venue"
},
  "geometry": {"coordinates":[-85.495969,37.775291],"type":"Point"}
}