{
  "type": "Feature",
  "properties": {
    "addr:full":"6508 Bardstown Rd Louisville KY 40291",
    "addr:housenumber":"6508",
    "addr:postcode":"40291",
    "addr:street":"Bardstown Rd",
    "iso:country":"US",
    "sg:address":"6508 Bardstown Rd",
    "sg:city":"Louisville",
    "sg:classifiers":[
        {
            "category":"Personal",
            "subcategory":"Beauty Salon",
            "type":"Services"
        }
    ],
    "sg:phone":"+1 502 231 3855",
    "sg:postcode":"40291",
    "sg:province":"KY",
    "wof:name":"Big League Haircuts",
    "wof:placetype":"venue"
},
  "geometry": {"coordinates":[-85.587344,38.149964],"type":"Point"}
}