{
  "type": "Feature",
  "properties": {
    "iso:country":"US",
    "sg:address":"405 S Green St",
    "sg:city":"Henderson",
    "sg:classifiers":[
        {
            "category":"Shopping",
            "subcategory":"Tobacco",
            "type":"Retail Goods"
        }
    ],
    "sg:phone":"+1 270 844 0150",
    "sg:postcode":"42420",
    "sg:province":"KY",
    "sg:tags":[
        "cigarette",
        "cigar",
        "dealer"
    ],
    "wof:name":"South Green Tobacco Outlet",
    "wof:placetype":"venue"
},
  "geometry": {"coordinates":[-87.594224,37.83289],"type":"Point"}
}