{
  "type": "Feature",
  "properties": {
    "addr:full":"701 E 4th St London KY 40741",
    "addr:housenumber":"701",
    "addr:postcode":"40741",
    "addr:street":"E 4Th St",
    "iso:country":"US",
    "sg:address":"701 E 4th St",
    "sg:city":"London",
    "sg:classifiers":[
        {
            "category":"Food & Beverages",
            "subcategory":"Groceries & Convenience Stores",
            "type":"Retail Goods"
        }
    ],
    "sg:phone":"+1 606 878 7133",
    "sg:postcode":"40741",
    "sg:province":"KY",
    "wof:name":"Curry Express Mart",
    "wof:placetype":"venue"
},
  "geometry": {"coordinates":[-84.074718,37.131111],"type":"Point"}
}