{
  "type": "Feature",
  "properties": {
    "iso:country":"US",
    "sg:address":"525 E 23rd St",
    "sg:city":"Owensboro",
    "sg:classifiers":[
        {
            "category":"Education",
            "subcategory":"School",
            "type":"Public Place"
        }
    ],
    "sg:phone":"+1 270 683 6989",
    "sg:postcode":"42303",
    "sg:province":"KY",
    "wof:name":"St Angela Merici School",
    "wof:placetype":"venue"
},
  "geometry": {"coordinates":[-87.102677,37.754021],"type":"Point"}
}