{
  "type": "Feature",
  "properties": {
    "iso:country":"US",
    "sg:address":"48 Southwind St",
    "sg:city":"London",
    "sg:classifiers":[
        {
            "category":"Banks & Credit Unions",
            "subcategory":"Bank",
            "type":"Services"
        }
    ],
    "sg:phone":"+1 606 877 5980",
    "sg:postcode":"40744",
    "sg:province":"KY",
    "sg:tags":[
        "loan"
    ],
    "wof:name":"B C",
    "wof:placetype":"venue"
},
  "geometry": {"coordinates":[-84.156682,37.01958],"type":"Point"}
}