{
  "type": "Feature",
  "properties": {
    "addr:full":"1172 Industrial Blvd Okolona KY 40219",
    "addr:housenumber":"1172",
    "addr:postcode":"40219",
    "addr:street":"Industrial Blvd",
    "iso:country":"US",
    "sg:address":"1172 Industrial Blvd",
    "sg:city":"Okolona",
    "sg:classifiers":[
        {
            "category":"Manufacturing",
            "subcategory":"Metals",
            "type":"Manufacturing & Wholesale Goods"
        }
    ],
    "sg:phone":"+1 502 969 1327",
    "sg:postcode":"40219",
    "sg:province":"KY",
    "sg:tags":[
        "forming"
    ],
    "sg:website":"www.rollerdie.com",
    "wof:name":"Roller Die & Forming Co",
    "wof:placetype":"venue"
},
  "geometry": {"coordinates":[-85.70506,38.152656],"type":"Point"}
}