{
  "type": "Feature",
  "properties": {
    "iso:country":"US",
    "sg:address":"10235 Timberwood Cir",
    "sg:city":"Louisville",
    "sg:classifiers":[
        {
            "category":"Sports & Exercise",
            "subcategory":"Sports Center",
            "type":"Entertainment"
        },
        {
            "category":"Arena",
            "subcategory":"Sports Club",
            "type":"Entertainment"
        }
    ],
    "sg:phone":"+1 502 244 4974",
    "sg:postcode":"40223",
    "sg:province":"KY",
    "wof:name":"Plainview Swim Club",
    "wof:placetype":"venue"
},
  "geometry": {"coordinates":[-85.565738,38.230325],"type":"Point"}
}