{
  "type": "Feature",
  "properties": {
    "addr:full":"4840 Craven Dr West Paducah KY 42086",
    "addr:housenumber":"4840",
    "addr:postcode":"42086",
    "addr:street":"Craven Dr West",
    "iso:country":"US",
    "sg:address":"4840 Craven Dr",
    "sg:city":"West Paducah",
    "sg:classifiers":[
        {
            "category":"Building & Trades",
            "subcategory":"Plumbing",
            "type":"Services"
        }
    ],
    "sg:phone":"+1 270 444 9906",
    "sg:postcode":"42086",
    "sg:province":"KY",
    "sg:tags":[
        "contractor"
    ],
    "wof:name":"Moore Mechanical Inc",
    "wof:placetype":"venue"
},
  "geometry": {"coordinates":[-88.739153,37.087584],"type":"Point"}
}