{
  "type": "Feature",
  "properties": {
    "addr:full":"4607 Clayton Ter Louisville KY 40214",
    "addr:housenumber":"4607",
    "addr:postcode":"40214",
    "addr:street":"Clayton Ter",
    "iso:country":"US",
    "sg:address":"4607 Clayton Ter",
    "sg:city":"Louisville",
    "sg:classifiers":[
        {
            "category":"Communications",
            "subcategory":"Film & Video Production",
            "type":"Services"
        }
    ],
    "sg:phone":"+1 502 933 7331",
    "sg:postcode":"40214",
    "sg:province":"KY",
    "sg:tags":[
        "motion",
        "organization",
        "religious"
    ],
    "wof:name":"Sound Creations",
    "wof:placetype":"venue"
},
  "geometry": {"coordinates":[-85.815922,38.13765],"type":"Point"}
}