{
  "type": "Feature",
  "properties": {
    "iso:country":"US",
    "sg:address":"3419 Stony Spring Cir",
    "sg:city":"Louisville",
    "sg:classifiers":[
        {
            "category":"Insurance",
            "subcategory":"Title Insurance",
            "type":"Services"
        }
    ],
    "sg:phone":"+1 502 491 9029",
    "sg:postcode":"40220",
    "sg:province":"KY",
    "sg:tags":[
        "mortgage"
    ],
    "wof:name":"Kentuckiana Title Agency",
    "wof:placetype":"venue"
},
  "geometry": {"coordinates":[-85.60385100000001,38.200018],"type":"Point"}
}