{
  "type": "Feature",
  "properties": {
    "addr:full":"534 N 7th St Paducah KY 42001",
    "addr:housenumber":"534",
    "addr:postcode":"42001",
    "addr:street":"N 7Th St",
    "iso:country":"US",
    "sg:address":"534 N 7th St",
    "sg:city":"Paducah",
    "sg:classifiers":[
        {
            "category":"Home & Garden",
            "subcategory":"Household Appliances",
            "type":"Retail Goods"
        },
        {
            "category":"Home & Garden",
            "subcategory":"Building Materials",
            "type":"Retail Goods"
        },
        {
            "category":"Building & Trades",
            "subcategory":"Construction",
            "type":"Services"
        }
    ],
    "sg:phone":"+1 270 443 1765",
    "sg:postcode":"42001",
    "sg:province":"KY",
    "sg:tags":[
        "repair",
        "systems-repairing",
        "system",
        "specialty",
        "equipment",
        "heat",
        "heating",
        "pump",
        "contractor",
        "air conditioning"
    ],
    "sg:website":"http://www.paulinemartin.com",
    "wof:name":"A AA Heating & Air Conditioning Co",
    "wof:placetype":"venue"
},
  "geometry": {"coordinates":[-88.604562,37.089611],"type":"Point"}
}