{
  "type": "Feature",
  "properties": {
    "addr:full":"383 State Hwy 483 Hickory KY 42051",
    "addr:housenumber":"383",
    "addr:postcode":"42051",
    "addr:street":"State Hwy 483",
    "iso:country":"US",
    "sg:address":"383 State Hwy 483",
    "sg:city":"Hickory",
    "sg:classifiers":[
        {
            "category":"Real Estate",
            "subcategory":"Real Estate Operator",
            "type":"Services"
        }
    ],
    "sg:phone":"+1 270 658 3355",
    "sg:postcode":"42051",
    "sg:province":"KY",
    "sg:tags":[
        "property",
        "lessor"
    ],
    "wof:name":"Claude Wilkerson",
    "wof:placetype":"venue"
},
  "geometry": {"coordinates":[-88.582531,36.82536],"type":"Point"}
}