{
  "type": "Feature",
  "properties": {
    "iso:country":"US",
    "sg:address":"455 N Buckman St",
    "sg:city":"Shepherdsville",
    "sg:classifiers":[
        {
            "category":"Manufacturing",
            "subcategory":"Printing",
            "type":"Manufacturing & Wholesale Goods"
        }
    ],
    "sg:phone":"+1 502 955 9701",
    "sg:postcode":"40165",
    "sg:province":"KY",
    "sg:tags":[
        "printer"
    ],
    "wof:name":"Standard Publishing",
    "wof:placetype":"venue"
},
  "geometry": {"coordinates":[-85.708077,38.007],"type":"Point"}
}