{
  "type": "Feature",
  "properties": {
    "iso:country":"US",
    "sg:address":"25 Ellen Kay Dr",
    "sg:city":"Dry Ridge",
    "sg:classifiers":[
        {
            "category":"Professional",
            "type":"Services"
        }
    ],
    "sg:phone":"+1 859 824 0889",
    "sg:postcode":"41035",
    "sg:province":"KY",
    "wof:name":"JW Custom Bobcat Service",
    "wof:placetype":"venue"
},
  "geometry": {"coordinates":[-84.62094,38.674641],"type":"Point"}
}