{
  "type": "Feature",
  "properties": {
    "addr:full":"8127 la Grange Rd Louisville KY 40222",
    "addr:housenumber":"8127",
    "addr:postcode":"40222",
    "addr:street":"La Grange Rd",
    "iso:country":"US",
    "sg:address":"8127 la Grange Rd",
    "sg:city":"Louisville",
    "sg:classifiers":[
        {
            "category":"Professional",
            "subcategory":"Business Services",
            "type":"Services"
        },
        {
            "category":"Government",
            "subcategory":"Post Office",
            "type":"Public Place"
        }
    ],
    "sg:phone":"+1 800 275 8777",
    "sg:postcode":"40222",
    "sg:province":"KY",
    "sg:tags":[
        "mail",
        "shipping"
    ],
    "sg:website":"http://www.usps.com",
    "wof:name":"USPS - United States Post Office - Lyndon Branch",
    "wof:placetype":"venue"
},
  "geometry": {"coordinates":[-85.603745,38.262862],"type":"Point"}
}