{
  "type": "Feature",
  "properties": {
    "iso:country":"US",
    "sg:address":"4337 S Danville Byp",
    "sg:city":"Danville",
    "sg:phone":"+1 859 236 6463",
    "sg:postcode":"40422",
    "sg:province":"KY",
    "sg:tags":[
        "oil"
    ],
    "wof:name":"Little Oil Co",
    "wof:placetype":"venue"
},
  "geometry": {"coordinates":[-84.734861,37.619796],"type":"Point"}
}