{
  "type": "Feature",
  "properties": {
    "addr:full":"7669 National Tpke Louisville KY 40214",
    "addr:housenumber":"7669",
    "addr:postcode":"40214",
    "addr:street":"National Tpke",
    "iso:country":"US",
    "sg:address":"7669 National Tpke",
    "sg:city":"Louisville",
    "sg:classifiers":[
        {
            "category":"Wholesale",
            "subcategory":"Durable Goods & Equipment",
            "type":"Manufacturing & Wholesale Goods"
        }
    ],
    "sg:phone":"+1 502 361 1640",
    "sg:postcode":"40214",
    "sg:province":"KY",
    "sg:tags":[
        "importer"
    ],
    "wof:name":"Fateh Imports",
    "wof:placetype":"venue"
},
  "geometry": {"coordinates":[-85.75394900000001,38.139975],"type":"Point"}
}