{
  "type": "Feature",
  "properties": {
    "iso:country":"US",
    "sg:address":"860 Bardstown Rd",
    "sg:city":"Springfield",
    "sg:classifiers":[
        {
            "category":"Restaurant",
            "type":"Food & Drink"
        }
    ],
    "sg:phone":"+1 859 336 2221",
    "sg:postcode":"40069",
    "sg:province":"KY",
    "wof:name":"El Camino Real Mexican Rstrnt",
    "wof:placetype":"venue"
},
  "geometry": {"coordinates":[-85.23601600000001,37.691731],"type":"Point"}
}