{
  "type": "Feature",
  "properties": {
    "iso:country":"US",
    "sg:address":"3891 State Hwy 1826",
    "sg:city":"Clinton",
    "sg:phone":"+1 270 653 6026",
    "sg:postcode":"42031",
    "sg:province":"KY",
    "sg:tags":[
        "farm",
        "corn",
        "soybean"
    ],
    "wof:name":"Roy Cooper",
    "wof:placetype":"venue"
},
  "geometry": {"coordinates":[-89.042768,36.672177],"type":"Point"}
}