{
  "type": "Feature",
  "properties": {
    "addr:full":"958 Logan St Louisville KY 40204",
    "addr:housenumber":"958",
    "addr:postcode":"40204",
    "addr:street":"Logan St",
    "iso:country":"US",
    "sg:address":"958 Logan St",
    "sg:city":"Louisville",
    "sg:classifiers":[
        {
            "category":"Building & Trades",
            "subcategory":"Construction",
            "type":"Services"
        }
    ],
    "sg:phone":"+1 502 561 7860",
    "sg:postcode":"40204",
    "sg:province":"KY",
    "sg:tags":[
        "general",
        "contractor"
    ],
    "wof:name":"Amstar Corp",
    "wof:placetype":"venue"
},
  "geometry": {"coordinates":[-85.73953899999999,38.237287],"type":"Point"}
}