{
  "type": "Feature",
  "properties": {
    "addr:full":"13010 Middletown Ind Blvd Louisville KY 40223",
    "addr:housenumber":"13010",
    "addr:postcode":"40223",
    "addr:street":"Middletown Ind Blvd",
    "iso:country":"US",
    "sg:address":"13010 Middletown Ind Blvd",
    "sg:city":"Louisville",
    "sg:classifiers":[
        {
            "category":"Building & Trades",
            "subcategory":"Construction",
            "type":"Services"
        }
    ],
    "sg:phone":"+1 502 244 8483",
    "sg:postcode":"40223",
    "sg:province":"KY",
    "sg:tags":[
        "foundation"
    ],
    "wof:name":"River City Foundations",
    "wof:placetype":"venue"
},
  "geometry": {"coordinates":[-85.505353,38.250349],"type":"Point"}
}