{
  "type": "Feature",
  "properties": {
    "addr:full":"13185 US Hwy 62 Central City KY 42330",
    "addr:housenumber":"13185",
    "addr:postcode":"42330",
    "addr:street":"Us Hwy 62",
    "iso:country":"US",
    "sg:address":"13185 US Hwy 62",
    "sg:city":"Central City",
    "sg:classifiers":[
        {
            "category":"Manufacturing",
            "subcategory":"Lumber",
            "type":"Manufacturing & Wholesale Goods"
        }
    ],
    "sg:phone":"+1 270 754 1807",
    "sg:postcode":"42330",
    "sg:province":"KY",
    "sg:tags":[
        "sawmill"
    ],
    "wof:name":"Vaught Brothers Lumber Co",
    "wof:placetype":"venue"
},
  "geometry": {"coordinates":[-87.039051,37.320114],"type":"Point"}
}