{
  "type": "Feature",
  "properties": {
    "addr:full":"501 Marsailles Rd Versailles KY 40383",
    "addr:housenumber":"501",
    "addr:postcode":"40383",
    "addr:street":"Marsailles Rd",
    "iso:country":"US",
    "sg:address":"501 Marsailles Rd",
    "sg:city":"Versailles",
    "sg:classifiers":[
        {
            "category":"Shopping",
            "subcategory":"Department Store",
            "type":"Retail Goods"
        }
    ],
    "sg:phone":"+1 859 873 3287",
    "sg:postcode":"40383",
    "sg:province":"KY",
    "wof:name":"Kmart",
    "wof:placetype":"venue"
},
  "geometry": {"coordinates":[-84.70941999999999,38.050012],"type":"Point"}
}