{
  "type": "Feature",
  "properties": {
    "addr:full":"33 Elmwood Ave Fort Thomas KY 41075",
    "addr:housenumber":"33",
    "addr:postcode":"41075",
    "addr:street":"Elmwood Ave",
    "iso:country":"US",
    "sg:address":"33 Elmwood Ave",
    "sg:city":"Fort Thomas",
    "sg:classifiers":[
        {
            "category":"Health Services",
            "subcategory":"Health Practitioner",
            "type":"Services"
        }
    ],
    "sg:phone":"+1 859 781 6264",
    "sg:postcode":"41075",
    "sg:province":"KY",
    "wof:name":"Articulate Expressions LLC",
    "wof:placetype":"venue"
},
  "geometry": {"coordinates":[-84.45147799999999,39.082234],"type":"Point"}
}