{
  "type": "Feature",
  "properties": {
    "iso:country":"US",
    "sg:address":"209 S Main Cross St",
    "sg:city":"Flemingsburg",
    "sg:classifiers":[
        {
            "category":"Shopping",
            "subcategory":"Pharmacy",
            "type":"Retail Goods"
        }
    ],
    "sg:phone":"+1 606 845 2101",
    "sg:postcode":"41041",
    "sg:province":"KY",
    "wof:name":"Colonial Village Pharmacy",
    "wof:placetype":"venue"
},
  "geometry": {"coordinates":[-83.73595899999999,38.41998],"type":"Point"}
}