{
  "type": "Feature",
  "properties": {
    "iso:country":"US",
    "sg:address":"113 2nd St",
    "sg:city":"Falmouth",
    "sg:classifiers":[
        {
            "category":"Retail",
            "subcategory":"Laundry & Dry Cleaning",
            "type":"Services"
        }
    ],
    "sg:phone":"+1 859 654 3353",
    "sg:postcode":"41040",
    "sg:province":"KY",
    "sg:tags":[
        "cleaners"
    ],
    "wof:name":"De Luxe Cleaners",
    "wof:placetype":"venue"
},
  "geometry": {"coordinates":[-84.33049800000001,38.678391],"type":"Point"}
}