{
  "type": "Feature",
  "properties": {
    "addr:full":"7041 Hinkleville Rd La Center KY 42056",
    "addr:housenumber":"7041",
    "addr:postcode":"42056",
    "addr:street":"Hinkleville Rd",
    "iso:country":"US",
    "sg:address":"7041 Hinkleville Rd",
    "sg:city":"La Center",
    "sg:classifiers":[
        {
            "category":"Retail",
            "subcategory":"Animal Services",
            "type":"Services"
        }
    ],
    "sg:phone":"+1 270 665 5983",
    "sg:postcode":"42056",
    "sg:province":"KY",
    "wof:name":"Desert Fire Kennels",
    "wof:placetype":"venue"
},
  "geometry": {"coordinates":[-88.933522,37.056671],"type":"Point"}
}