{
  "type": "Feature",
  "properties": {
    "iso:country":"US",
    "sg:address":"529 Main St",
    "sg:city":"Shelbyville",
    "sg:classifiers":[
        {
            "category":"Communications",
            "subcategory":"Radio Station",
            "type":"Services"
        }
    ],
    "sg:phone":"+1 502 647 1010",
    "sg:postcode":"40065",
    "sg:province":"KY",
    "sg:tags":[
        "company",
        "broadcasting"
    ],
    "wof:name":"Chuckie Broadcasting",
    "wof:placetype":"venue"
},
  "geometry": {"coordinates":[-85.216903,38.211106],"type":"Point"}
}