{
  "type": "Feature",
  "properties": {
    "iso:country":"US",
    "sg:address":"700 Interstate Dr",
    "sg:city":"Bowling Green",
    "sg:classifiers":[
        {
            "category":"Travel",
            "subcategory":"Hotels & Motels",
            "type":"Entertainment"
        }
    ],
    "sg:phone":"+1 270 781 5200",
    "sg:postcode":"42101",
    "sg:province":"KY",
    "sg:website":"www.hotels.com",
    "wof:name":"Continental Inn",
    "wof:placetype":"venue"
},
  "geometry": {"coordinates":[-86.370954,37.007235],"type":"Point"}
}