{
  "type": "Feature",
  "properties": {
    "iso:country":"US",
    "sg:address":"1211 Fariston Rd",
    "sg:city":"London",
    "sg:classifiers":[
        {
            "category":"Food & Beverages",
            "subcategory":"Groceries & Convenience Stores",
            "type":"Retail Goods"
        }
    ],
    "sg:phone":"+1 606 862 8595",
    "sg:postcode":"40744",
    "sg:province":"KY",
    "sg:tags":[
        "grocer"
    ],
    "wof:name":"Fariston Grocery",
    "wof:placetype":"venue"
},
  "geometry": {"coordinates":[-84.064452,37.054578],"type":"Point"}
}