{
  "type": "Feature",
  "properties": {
    "iso:country":"US",
    "sg:address":"8385 State Hwy 36",
    "sg:city":"Sanders",
    "sg:classifiers":[
        {
            "category":"Farming",
            "subcategory":"Farm",
            "type":"Manufacturing & Wholesale Goods"
        }
    ],
    "sg:phone":"+1 502 347 9389",
    "sg:postcode":"41083",
    "sg:province":"KY",
    "sg:tags":[
        "crop",
        "general"
    ],
    "wof:name":"Carroll Hackett",
    "wof:placetype":"venue"
},
  "geometry": {"coordinates":[-85.038864,38.660609],"type":"Point"}
}