{
  "type": "Feature",
  "properties": {
    "iso:country":"US",
    "sg:address":"1280 Fairway St",
    "sg:city":"Bowling Green",
    "sg:classifiers":[
        {
            "category":"Banks & Credit Unions",
            "subcategory":"Bank",
            "type":"Services"
        }
    ],
    "sg:phone":"+1 270 782 8824",
    "sg:postcode":"42103",
    "sg:province":"KY",
    "sg:tags":[
        "loan"
    ],
    "sg:website":"www.meyermortgagecorp.com",
    "wof:name":"Meyer Mortgage Corp",
    "wof:placetype":"venue"
},
  "geometry": {"coordinates":[-86.432029,36.969316],"type":"Point"}
}