{
  "type": "Feature",
  "properties": {
    "iso:country":"US",
    "sg:address":"1120 US Hwy 68",
    "sg:city":"Maysville",
    "sg:classifiers":[
        {
            "category":"Personal",
            "type":"Services"
        }
    ],
    "sg:phone":"+1 606 564 5020",
    "sg:postcode":"41056",
    "sg:province":"KY",
    "wof:name":"Bodies In Motion",
    "wof:placetype":"venue"
},
  "geometry": {"coordinates":[-83.782826,38.641201],"type":"Point"}
}