{
  "type": "Feature",
  "properties": {
    "iso:country":"US",
    "sg:address":"17 Construction Dr",
    "sg:city":"Mayfield",
    "sg:classifiers":[
        {
            "category":"Health Services",
            "subcategory":"Clinic",
            "type":"Services"
        }
    ],
    "sg:phone":"+1 270 247 3155",
    "sg:postcode":"42066",
    "sg:province":"KY",
    "sg:tags":[
        "home"
    ],
    "wof:name":"Purchase District Home Health",
    "wof:placetype":"venue"
},
  "geometry": {"coordinates":[-88.643196,36.760195],"type":"Point"}
}