{
  "type": "Feature",
  "properties": {
    "iso:country":"US",
    "sg:address":"3707 Alameter Dr",
    "sg:city":"Louisville",
    "sg:classifiers":[
        {
            "category":"Real Estate",
            "subcategory":"Real Estate Agent",
            "type":"Services"
        }
    ],
    "sg:phone":"+1 502 935 2000",
    "sg:postcode":"40258",
    "sg:province":"KY",
    "wof:name":"Re/Max",
    "wof:placetype":"venue"
},
  "geometry": {"coordinates":[-85.827831,38.149813],"type":"Point"}
}