{
  "type": "Feature",
  "properties": {
    "addr:full":"118 W South St Mayfield KY 42066",
    "addr:housenumber":"118",
    "addr:postcode":"42066",
    "addr:street":"W South St",
    "iso:country":"US",
    "sg:address":"118 W South St",
    "sg:city":"Mayfield",
    "sg:classifiers":[
        {
            "category":"Organizations",
            "subcategory":"Religious Organization",
            "type":"Services"
        }
    ],
    "sg:phone":"+1 270 247 2992",
    "sg:postcode":"42066",
    "sg:province":"KY",
    "sg:tags":[
        "church"
    ],
    "sg:website":"www.firstmayfield.com",
    "wof:name":"First Baptist Church",
    "wof:placetype":"venue"
},
  "geometry": {"coordinates":[-88.636878,36.740573],"type":"Point"}
}