{
  "type": "Feature",
  "properties": {
    "addr:full":"660 N Yarnallton Pike Lexington KY 40511",
    "addr:housenumber":"660",
    "addr:postcode":"40511",
    "addr:street":"N Yarnallton Pike",
    "iso:country":"US",
    "sg:address":"660 N Yarnallton Pike",
    "sg:city":"Lexington",
    "sg:classifiers":[
        {
            "category":"Retail",
            "subcategory":"Veterinary Services",
            "type":"Services"
        }
    ],
    "sg:phone":"+1 859 231 1747",
    "sg:postcode":"40511",
    "sg:province":"KY",
    "sg:tags":[
        "veterinarian",
        "specialty"
    ],
    "wof:name":"Mundy George D DVM",
    "wof:placetype":"venue"
},
  "geometry": {"coordinates":[-84.57819499999999,38.116345],"type":"Point"}
}