{
  "type": "Feature",
  "properties": {
    "iso:country":"US",
    "sg:address":"8103 Preston Hwy",
    "sg:city":"Louisville",
    "sg:classifiers":[
        {
            "category":"Transit Center",
            "subcategory":"Freight",
            "type":"Transportation"
        }
    ],
    "sg:phone":"+1 502 962 7666",
    "sg:postcode":"40219",
    "sg:province":"KY",
    "sg:tags":[
        "trucking-light",
        "hauling"
    ],
    "wof:name":"G & S Delivery Service Inc",
    "wof:placetype":"venue"
},
  "geometry": {"coordinates":[-85.68466600000001,38.134683],"type":"Point"}
}