{
  "type": "Feature",
  "properties": {
    "iso:country":"US",
    "sg:address":"124 Rose Hill Ave",
    "sg:city":"Versailles",
    "sg:classifiers":[
        {
            "category":"Social Services",
            "type":"Services"
        }
    ],
    "sg:phone":"+1 859 873 6670",
    "sg:postcode":"40383",
    "sg:province":"KY",
    "sg:tags":[
        "youth",
        "organization",
        "center"
    ],
    "wof:name":"Woodford County Little League",
    "wof:placetype":"venue"
},
  "geometry": {"coordinates":[-84.731488,38.051461],"type":"Point"}
}