{
  "type": "Feature",
  "properties": {
    "iso:country":"US",
    "sg:address":"1050 Hustonville Rd",
    "sg:city":"Danville",
    "sg:phone":"+1 859 238 7775",
    "sg:postcode":"40422",
    "sg:province":"KY",
    "sg:tags":[
        "equipment",
        "station"
    ],
    "wof:name":"Chambers Marathon",
    "wof:placetype":"venue"
},
  "geometry": {"coordinates":[-84.774731,37.629209],"type":"Point"}
}