{
  "type": "Feature",
  "properties": {
    "iso:country":"US",
    "sg:address":"3970 Frederica St",
    "sg:city":"Owensboro",
    "sg:classifiers":[
        {
            "category":"Restaurant",
            "type":"Food & Drink"
        }
    ],
    "sg:menulink":"http://www.allmenus.com/ky/owensboro/136349-waffle-house/menu/",
    "sg:phone":"+1 270 852 3720",
    "sg:postcode":"42301",
    "sg:province":"KY",
    "sg:tags":[
        "american"
    ],
    "wof:name":"Waffle House",
    "wof:placetype":"venue"
},
  "geometry": {"coordinates":[-87.120681,37.733409],"type":"Point"}
}