{
  "type": "Feature",
  "properties": {
    "iso:country":"US",
    "sg:address":"401 Gould Ave",
    "sg:city":"Paducah",
    "sg:classifiers":[
        {
            "category":"Education",
            "subcategory":"School",
            "type":"Public Place"
        }
    ],
    "sg:phone":"+1 270 444 5635",
    "sg:postcode":"42003",
    "sg:province":"KY",
    "sg:tags":[
        "district"
    ],
    "sg:website":"http://www.paducah.kyschools.us/",
    "wof:name":"Paducah Public Schools - Transportation Department",
    "wof:placetype":"venue"
},
  "geometry": {"coordinates":[-88.60463,37.080238],"type":"Point"}
}