{
  "type": "Feature",
  "properties": {
    "addr:full":"102 Court St Greenville KY 42345",
    "addr:housenumber":"102",
    "addr:postcode":"42345",
    "addr:street":"Court St",
    "iso:country":"US",
    "sg:address":"102 Court St",
    "sg:city":"Greenville",
    "sg:classifiers":[
        {
            "category":"Government",
            "subcategory":"Post Office",
            "type":"Public Place"
        }
    ],
    "sg:phone":"+1 270 338 4900",
    "sg:postcode":"42345",
    "sg:province":"KY",
    "wof:name":"US Post Office",
    "wof:placetype":"venue"
},
  "geometry": {"coordinates":[-87.177521,37.201162],"type":"Point"}
}