{
  "type": "Feature",
  "properties": {
    "addr:full":"110 N Water St Georgetown KY 40324",
    "addr:housenumber":"110",
    "addr:postcode":"40324",
    "addr:street":"N Water St",
    "iso:country":"US",
    "sg:address":"110 N Water St",
    "sg:city":"Georgetown",
    "sg:classifiers":[
        {
            "category":"Manufacturing",
            "subcategory":"Furniture",
            "type":"Manufacturing & Wholesale Goods"
        }
    ],
    "sg:phone":"+1 502 863 1897",
    "sg:postcode":"40324",
    "sg:province":"KY",
    "sg:tags":[
        "upholstered",
        "wood"
    ],
    "wof:name":"D & H Woodworking",
    "wof:placetype":"venue"
},
  "geometry": {"coordinates":[-84.561447,38.211086],"type":"Point"}
}