{
  "type": "Feature",
  "properties": {
    "iso:country":"US",
    "sg:address":"16476 Fort Campbell Blvd",
    "sg:city":"Oak Grove",
    "sg:classifiers":[
        {
            "category":"Professional",
            "subcategory":"Accounting & Tax Preparation",
            "type":"Services"
        }
    ],
    "sg:phone":"+1 270 640 0738",
    "sg:postcode":"42262",
    "sg:province":"KY",
    "sg:tags":[
        "return",
        "filing"
    ],
    "sg:website":"www.hrblock.com",
    "wof:name":"H & R Block Tax Svc",
    "wof:placetype":"venue"
},
  "geometry": {"coordinates":[-87.436201,36.642881],"type":"Point"}
}