{
  "type": "Feature",
  "properties": {
    "iso:country":"US",
    "sg:address":"9070 Dixie Hwy",
    "sg:city":"Louisville",
    "sg:classifiers":[
        {
            "category":"Shopping",
            "subcategory":"Department Store",
            "type":"Retail Goods"
        }
    ],
    "sg:phone":"+1 502 935 7220",
    "sg:postcode":"40258",
    "sg:province":"KY",
    "sg:tags":[
        "shop"
    ],
    "wof:name":"Dollar Tree",
    "wof:placetype":"venue"
},
  "geometry": {"coordinates":[-85.85217900000001,38.125562],"type":"Point"}
}