{
  "type": "Feature",
  "properties": {
    "iso:country":"US",
    "sg:address":"604 Poplar St",
    "sg:city":"Bellevue",
    "sg:classifiers":[
        {
            "category":"Travel",
            "subcategory":"Hotels & Motels",
            "type":"Entertainment"
        }
    ],
    "sg:phone":"+1 859 491 9354",
    "sg:postcode":"41073",
    "sg:province":"KY",
    "sg:tags":[
        "breakfast",
        "accommodation",
        "bed"
    ],
    "wof:name":"Christopher's Bed & Breakfast",
    "wof:placetype":"venue"
},
  "geometry": {"coordinates":[-84.479032,39.106302],"type":"Point"}
}