{
  "type": "Feature",
  "properties": {
    "iso:country":"US",
    "sg:address":"2333 Carlton Ter",
    "sg:city":"Louisville",
    "sg:classifiers":[
        {
            "category":"Shopping",
            "subcategory":"Used Merchandise",
            "type":"Retail Goods"
        }
    ],
    "sg:phone":"+1 502 456 5268",
    "sg:postcode":"40205",
    "sg:province":"KY",
    "wof:name":"Rh Antiques",
    "wof:placetype":"venue"
},
  "geometry": {"coordinates":[-85.696274,38.218137],"type":"Point"}
}