{
  "type": "Feature",
  "properties": {
    "iso:country":"US",
    "sg:address":"651 Red Mile Rd",
    "sg:city":"Lexington",
    "sg:classifiers":[
        {
            "category":"Retail",
            "subcategory":"Car Wash",
            "type":"Services"
        }
    ],
    "sg:phone":"+1 859 233 1736",
    "sg:postcode":"40504",
    "sg:province":"KY",
    "sg:tags":[
        "polishing",
        "washing"
    ],
    "wof:name":"Red Mile Car Wash",
    "wof:placetype":"venue"
},
  "geometry": {"coordinates":[-84.523353,38.047956],"type":"Point"}
}