{
  "type": "Feature",
  "properties": {
    "iso:country":"US",
    "sg:address":"250 Spring St",
    "sg:city":"Auburn",
    "sg:classifiers":[
        {
            "category":"Government",
            "subcategory":"Office",
            "type":"Public Place"
        }
    ],
    "sg:phone":"+1 270 542 7379",
    "sg:postcode":"42206",
    "sg:province":"KY",
    "sg:tags":[
        "village"
    ],
    "wof:name":"Auburn Park House",
    "wof:placetype":"venue"
},
  "geometry": {"coordinates":[-86.708439,36.860569],"type":"Point"}
}