{
  "type": "Feature",
  "properties": {
    "iso:country":"US",
    "sg:address":"45 Fairfield Ave",
    "sg:city":"Bellevue",
    "sg:classifiers":[
        {
            "category":"Restaurant",
            "type":"Food & Drink"
        }
    ],
    "sg:menulink":"http://www.allmenus.com/ky/newport/197372-burger-king/menu/",
    "sg:phone":"+1 859 431 6064",
    "sg:postcode":"41073",
    "sg:province":"KY",
    "sg:tags":[
        "burger",
        "american"
    ],
    "wof:name":"Burger King",
    "wof:placetype":"venue"
},
  "geometry": {"coordinates":[-84.487981,39.102393],"type":"Point"}
}