{
  "type": "Feature",
  "properties": {
    "addr:full":"3785 Jamaica Ct Lexington KY 40509",
    "addr:housenumber":"3785",
    "addr:postcode":"40509",
    "addr:street":"Jamaica Ct",
    "iso:country":"US",
    "sg:address":"3785 Jamaica Ct",
    "sg:city":"Lexington",
    "sg:classifiers":[
        {
            "category":"Organizations",
            "subcategory":"Membership Organization",
            "type":"Services"
        }
    ],
    "sg:phone":"+1 859 299 8758",
    "sg:postcode":"40509",
    "sg:province":"KY",
    "wof:name":"Clawson Fmly Chrtble Fundation",
    "wof:placetype":"venue"
},
  "geometry": {"coordinates":[-84.38008600000001,38.02089],"type":"Point"}
}