{
  "type": "Feature",
  "properties": {
    "iso:country":"US",
    "sg:address":"3580 Cincinnati Rd",
    "sg:city":"Georgetown",
    "sg:classifiers":[
        {
            "category":"Organizations",
            "subcategory":"Religious Organization",
            "type":"Services"
        }
    ],
    "sg:phone":"+1 502 863 5344",
    "sg:postcode":"40324",
    "sg:province":"KY",
    "sg:tags":[
        "church"
    ],
    "wof:name":"Mallard Point Baptist Church",
    "wof:placetype":"venue"
},
  "geometry": {"coordinates":[-84.575388,38.334555],"type":"Point"}
}