{
  "type": "Feature",
  "properties": {
    "iso:country":"US",
    "sg:address":"255 Chad Dr",
    "sg:city":"Mayfield",
    "sg:classifiers":[
        {
            "category":"Restaurant",
            "type":"Food & Drink"
        }
    ],
    "sg:phone":"+1 270 247 2761",
    "sg:postcode":"42066",
    "sg:province":"KY",
    "sg:tags":[
        "delicatessen"
    ],
    "wof:name":"Linda's Market",
    "wof:placetype":"venue"
},
  "geometry": {"coordinates":[-88.63758,36.699162],"type":"Point"}
}