{
  "type": "Feature",
  "properties": {
    "iso:country":"US",
    "sg:address":"1801 Edenside Ave",
    "sg:city":"Louisville",
    "sg:classifiers":[
        {
            "category":"Real Estate",
            "subcategory":"Real Estate Agent",
            "type":"Services"
        }
    ],
    "sg:phone":"+1 502 456 1942",
    "sg:postcode":"40204",
    "sg:province":"KY",
    "wof:name":"Carlos-Celletti Properties",
    "wof:placetype":"venue"
},
  "geometry": {"coordinates":[-85.71346200000001,38.231107],"type":"Point"}
}