{
  "type": "Feature",
  "properties": {
    "iso:country":"US",
    "sg:address":"212 Broadway St",
    "sg:city":"Paducah",
    "sg:classifiers":[
        {
            "category":"Shopping",
            "subcategory":"Gifts & Souvenirs",
            "type":"Retail Goods"
        }
    ],
    "sg:phone":"+1 270 441 7670",
    "sg:postcode":"42001",
    "sg:province":"KY",
    "sg:tags":[
        "balloon",
        "artist"
    ],
    "wof:name":"Melrhea Balloon Creations",
    "wof:placetype":"venue"
},
  "geometry": {"coordinates":[-88.595923,37.087494],"type":"Point"}
}