{
  "type": "Feature",
  "properties": {
    "iso:country":"US",
    "sg:address":"156 Deweese St",
    "sg:city":"Lexington",
    "sg:classifiers":[
        {
            "category":"Shopping",
            "subcategory":"Catalog Store",
            "type":"Retail Goods"
        }
    ],
    "sg:phone":"+1 859 388 9255",
    "sg:postcode":"40507",
    "sg:province":"KY",
    "sg:tags":[
        "mail",
        "order"
    ],
    "wof:name":"Stress Away Systems Inc",
    "wof:placetype":"venue"
},
  "geometry": {"coordinates":[-84.49142000000001,38.044658],"type":"Point"}
}