{
  "type": "Feature",
  "properties": {
    "iso:country":"US",
    "sg:address":"728 13th St",
    "sg:city":"Ashland",
    "sg:classifiers":[
        {
            "category":"Shopping",
            "type":"Retail Goods"
        }
    ],
    "sg:phone":"+1 606 325 2597",
    "sg:postcode":"41101",
    "sg:province":"KY",
    "sg:tags":[
        "art",
        "gallery",
        "dealer"
    ],
    "wof:name":"Aladdin's Art Gallery",
    "wof:placetype":"venue"
},
  "geometry": {"coordinates":[-82.64644800000001,38.475976],"type":"Point"}
}