{
  "type": "Feature",
  "properties": {
    "iso:country":"US",
    "sg:address":"3335 Rickman Rd",
    "sg:city":"West Paducah",
    "sg:classifiers":[
        {
            "category":"Organizations",
            "subcategory":"Religious Organization",
            "type":"Services"
        }
    ],
    "sg:phone":"+1 270 744 9298",
    "sg:postcode":"42086",
    "sg:province":"KY",
    "sg:tags":[
        "church"
    ],
    "sg:website":"www.rickmanroad.org",
    "wof:name":"Rickman Road Missionary Church",
    "wof:placetype":"venue"
},
  "geometry": {"coordinates":[-88.75799600000001,37.070148],"type":"Point"}
}