{
  "type": "Feature",
  "properties": {
    "iso:country":"US",
    "sg:address":"4185 Algonquin Pkwy",
    "sg:city":"Louisville",
    "sg:classifiers":[
        {
            "category":"Manufacturing",
            "subcategory":"Chemicals & Compounds",
            "type":"Manufacturing & Wholesale Goods"
        }
    ],
    "sg:phone":"+1 502 778 7323",
    "sg:postcode":"40211",
    "sg:province":"KY",
    "sg:website":"www.ashland.com",
    "wof:name":"Ashland Chemical Co",
    "wof:placetype":"venue"
},
  "geometry": {"coordinates":[-85.823763,38.22601],"type":"Point"}
}