{
  "type": "Feature",
  "properties": {
    "iso:country":"US",
    "sg:address":"3811 Nashville Rd",
    "sg:city":"Franklin",
    "sg:classifiers":[
        {
            "category":"Travel",
            "subcategory":"Hotels & Motels",
            "type":"Entertainment"
        }
    ],
    "sg:phone":"+1 270 586 5090",
    "sg:postcode":"42134",
    "sg:province":"KY",
    "wof:name":"Super 8 Motel",
    "wof:placetype":"venue"
},
  "geometry": {"coordinates":[-86.5582,36.670096],"type":"Point"}
}