{
  "type": "Feature",
  "properties": {
    "addr:full":"99 Jewell City Rd Slaughters KY 42456",
    "addr:housenumber":"99",
    "addr:postcode":"42456",
    "addr:street":"Jewell City Rd",
    "iso:country":"US",
    "sg:address":"99 Jewell City Rd",
    "sg:city":"Slaughters",
    "sg:classifiers":[
        {
            "category":"Insurance",
            "subcategory":"Insurance Agent",
            "type":"Services"
        }
    ],
    "sg:phone":"+1 270 884 7381",
    "sg:postcode":"42456",
    "sg:province":"KY",
    "wof:name":"Shelter Insurance",
    "wof:placetype":"venue"
},
  "geometry": {"coordinates":[-87.494508,37.488874],"type":"Point"}
}