{
  "type": "Feature",
  "properties": {
    "iso:country":"US",
    "sg:address":"3025 Shirlee Ct",
    "sg:city":"Lexington",
    "sg:classifiers":[
        {
            "category":"Wholesale",
            "subcategory":"Groceries",
            "type":"Manufacturing & Wholesale Goods"
        }
    ],
    "sg:phone":"+1 859 277 7652",
    "sg:postcode":"40502",
    "sg:province":"KY",
    "wof:name":"Jim Mazzoni Distributing",
    "wof:placetype":"venue"
},
  "geometry": {"coordinates":[-84.501104,38.006508],"type":"Point"}
}