{
  "type": "Feature",
  "properties": {
    "iso:country":"US",
    "sg:address":"323 Romany Rd",
    "sg:city":"Lexington",
    "sg:classifiers":[
        {
            "category":"Shopping",
            "type":"Retail Goods"
        }
    ],
    "sg:phone":"+1 859 266 8006",
    "sg:postcode":"40502",
    "sg:province":"KY",
    "sg:tags":[
        "pet",
        "shop"
    ],
    "wof:name":"Janna's Pet Grooming On Romany",
    "wof:placetype":"venue"
},
  "geometry": {"coordinates":[-84.486498,38.018772],"type":"Point"}
}