{
  "type": "Feature",
  "properties": {
    "iso:country":"US",
    "sg:address":"116 Shoppers Village Dr",
    "sg:city":"Winchester",
    "sg:classifiers":[
        {
            "category":"Food & Beverages",
            "subcategory":"Groceries & Convenience Stores",
            "type":"Retail Goods"
        }
    ],
    "sg:phone":"+1 859 744 9555",
    "sg:postcode":"40391",
    "sg:province":"KY",
    "sg:tags":[
        "grocer"
    ],
    "wof:name":"Mi Pueblo Two",
    "wof:placetype":"venue"
},
  "geometry": {"coordinates":[-84.212709,38.007468],"type":"Point"}
}