{
  "type": "Feature",
  "properties": {
    "iso:country":"US",
    "sg:address":"110 S Clay St",
    "sg:city":"Louisa",
    "sg:classifiers":[
        {
            "category":"Real Estate",
            "subcategory":"Real Estate Agent",
            "type":"Services"
        }
    ],
    "sg:phone":"+1 606 638 9667",
    "sg:postcode":"41230",
    "sg:province":"KY",
    "wof:name":"Hometown Realty",
    "wof:placetype":"venue"
},
  "geometry": {"coordinates":[-82.60534800000001,38.114683],"type":"Point"}
}