{
  "type": "Feature",
  "properties": {
    "iso:country":"US",
    "sg:address":"95 Trout Town Ln",
    "sg:city":"Stone",
    "sg:classifiers":[
        {
            "category":"Organizations",
            "subcategory":"Religious Organization",
            "type":"Services"
        }
    ],
    "sg:phone":"+1 606 353 7768",
    "sg:postcode":"41567",
    "sg:province":"KY",
    "sg:tags":[
        "church"
    ],
    "wof:name":"Stone United Methodist",
    "wof:placetype":"venue"
},
  "geometry": {"coordinates":[-82.271186,37.585974],"type":"Point"}
}