{
  "type": "Feature",
  "properties": {
    "iso:country":"US",
    "sg:address":"145 E Center St",
    "sg:city":"Madisonville",
    "sg:classifiers":[
        {
            "category":"Organizations",
            "subcategory":"Professional Association",
            "type":"Services"
        }
    ],
    "sg:phone":"+1 270 824 0320",
    "sg:postcode":"42431",
    "sg:province":"KY",
    "wof:name":"KEA Madisonville",
    "wof:placetype":"venue"
},
  "geometry": {"coordinates":[-87.49639500000001,37.327829],"type":"Point"}
}