{
  "type": "Feature",
  "properties": {
    "iso:country":"US",
    "sg:address":"719 Allendale Dr",
    "sg:city":"Lexington",
    "sg:classifiers":[
        {
            "category":"Retail",
            "subcategory":"Repair Shop",
            "type":"Services"
        }
    ],
    "sg:phone":"+1 859 277 4467",
    "sg:postcode":"40503",
    "sg:province":"KY",
    "sg:tags":[
        "upholsterer"
    ],
    "wof:name":"Marsha's Upholstery",
    "wof:placetype":"venue"
},
  "geometry": {"coordinates":[-84.534042,38.027138],"type":"Point"}
}