{
  "type": "Feature",
  "properties": {
    "iso:country":"US",
    "sg:address":"216 Crab Orchard Rd",
    "sg:city":"Lancaster",
    "sg:classifiers":[
        {
            "category":"Organizations",
            "subcategory":"Religious Organization",
            "type":"Services"
        }
    ],
    "sg:phone":"+1 859 792 3523",
    "sg:postcode":"40444",
    "sg:province":"KY",
    "sg:tags":[
        "clergy"
    ],
    "wof:name":"B Samuel Miller",
    "wof:placetype":"venue"
},
  "geometry": {"coordinates":[-84.57564000000001,37.615522],"type":"Point"}
}