{
  "type": "Feature",
  "properties": {
    "iso:country":"US",
    "sg:address":"7300 Turfway Rd",
    "sg:city":"Florence",
    "sg:classifiers":[
        {
            "category":"Education",
            "subcategory":"Vocational School",
            "type":"Public Place"
        }
    ],
    "sg:phone":"+1 859 525 8777",
    "sg:postcode":"41042",
    "sg:province":"KY",
    "sg:tags":[
        "training",
        "computer"
    ],
    "wof:name":"Spectrum Learning Ctr",
    "wof:placetype":"venue"
},
  "geometry": {"coordinates":[-84.62939799999999,39.011922],"type":"Point"}
}