{
  "type": "Feature",
  "properties": {
    "iso:country":"US",
    "sg:address":"207 E Locust St",
    "sg:city":"Scottsville",
    "sg:classifiers":[
        {
            "category":"Government",
            "subcategory":"Office",
            "type":"Public Place"
        }
    ],
    "sg:phone":"+1 270 237 5206",
    "sg:postcode":"42164",
    "sg:province":"KY",
    "wof:name":"Plumbing Inspector",
    "wof:placetype":"venue"
},
  "geometry": {"coordinates":[-86.190257,36.751341],"type":"Point"}
}