{
  "type": "Feature",
  "properties": {
    "iso:country":"US",
    "sg:address":"3223 Old Big Spring Rd",
    "sg:city":"Lewisburg",
    "sg:classifiers":[
        {
            "category":"Building & Trades",
            "subcategory":"Construction",
            "type":"Services"
        }
    ],
    "sg:phone":"+1 270 934 4301",
    "sg:postcode":"42256",
    "sg:province":"KY",
    "sg:tags":[
        "excavation",
        "contractor"
    ],
    "wof:name":"Givens Backhoe Service",
    "wof:placetype":"venue"
},
  "geometry": {"coordinates":[-86.817275,37.114292],"type":"Point"}
}