{
  "type": "Feature",
  "properties": {
    "addr:full":"3668 State Hwy 582 Pine Top KY 41843",
    "addr:housenumber":"3668",
    "addr:postcode":"41843",
    "addr:street":"State Hwy 582 Pine Top",
    "iso:country":"US",
    "sg:address":"3668 State Hwy 582",
    "sg:city":"Pine Top",
    "sg:classifiers":[
        {
            "category":"Food & Beverages",
            "subcategory":"Groceries & Convenience Stores",
            "type":"Retail Goods"
        }
    ],
    "sg:phone":"+1 606 785 3869",
    "sg:postcode":"41843",
    "sg:province":"KY",
    "sg:tags":[
        "grocer"
    ],
    "wof:name":"Shot's Market",
    "wof:placetype":"venue"
},
  "geometry": {"coordinates":[-82.897902,37.275403],"type":"Point"}
}