{
  "type": "Feature",
  "properties": {
    "iso:country":"US",
    "sg:address":"309 11th St",
    "sg:city":"Carrollton",
    "sg:classifiers":[
        {
            "category":"Health Services",
            "subcategory":"Doctor",
            "type":"Services"
        }
    ],
    "sg:phone":"+1 502 732 4321",
    "sg:postcode":"41008",
    "sg:province":"KY",
    "sg:tags":[
        "physician",
        "surgeon"
    ],
    "wof:name":"Commonwealth Ear Nose & Throat",
    "wof:placetype":"venue"
},
  "geometry": {"coordinates":[-85.16931099999999,38.679824],"type":"Point"}
}