{
  "type": "Feature",
  "properties": {
    "iso:country":"US",
    "sg:address":"502 N Main St",
    "sg:city":"Nicholasville",
    "sg:classifiers":[
        {
            "category":"Restaurant",
            "type":"Food & Drink"
        }
    ],
    "sg:phone":"+1 859 881 8225",
    "sg:postcode":"40356",
    "sg:province":"KY",
    "wof:name":"Three Suns Bistro",
    "wof:placetype":"venue"
},
  "geometry": {"coordinates":[-84.570916,37.885401],"type":"Point"}
}