{
  "type": "Feature",
  "properties": {
    "iso:country":"US",
    "sg:address":"325 S Main St",
    "sg:city":"Greenville",
    "sg:classifiers":[
        {
            "category":"Retail",
            "subcategory":"Laundry & Dry Cleaning",
            "type":"Services"
        }
    ],
    "sg:phone":"+1 270 338 7711",
    "sg:postcode":"42345",
    "sg:province":"KY",
    "sg:tags":[
        "cleaners"
    ],
    "wof:name":"Best Way Dry Cleaning & Lndry",
    "wof:placetype":"venue"
},
  "geometry": {"coordinates":[-87.17654,37.195935],"type":"Point"}
}