{
  "type": "Feature",
  "properties": {
    "iso:country":"US",
    "sg:address":"1166 Broadway St",
    "sg:city":"Paducah",
    "sg:classifiers":[
        {
            "category":"Freight",
            "type":"Transportation"
        }
    ],
    "sg:phone":"+1 270 554 8657",
    "sg:postcode":"42001",
    "sg:province":"KY",
    "sg:tags":[
        "commercial",
        "storage"
    ],
    "wof:name":"M & J Storage",
    "wof:placetype":"venue"
},
  "geometry": {"coordinates":[-88.608726,37.082287],"type":"Point"}
}