{
  "type": "Feature",
  "properties": {
    "iso:country":"US",
    "sg:address":"4513 Lincoln Rd",
    "sg:city":"Louisville",
    "sg:classifiers":[
        {
            "category":"Professional",
            "subcategory":"Management & Consulting",
            "type":"Services"
        }
    ],
    "sg:phone":"+1 502 473 0606",
    "sg:postcode":"40220",
    "sg:province":"KY",
    "wof:name":"Beasley Weigel Diana J",
    "wof:placetype":"venue"
},
  "geometry": {"coordinates":[-85.611318,38.230839],"type":"Point"}
}