{
  "type": "Feature",
  "properties": {
    "addr:full":"5796 Old Mayfield Rd Paducah KY 42003",
    "addr:housenumber":"5796",
    "addr:postcode":"42003",
    "addr:street":"Old Mayfield Rd",
    "iso:country":"US",
    "sg:address":"5796 Old Mayfield Rd",
    "sg:city":"Paducah",
    "sg:classifiers":[
        {
            "category":"Retail",
            "subcategory":"Animal Services",
            "type":"Services"
        }
    ],
    "sg:phone":"+1 270 554 4547",
    "sg:postcode":"42003",
    "sg:province":"KY",
    "sg:tags":[
        "pet",
        "boarding",
        "sitting"
    ],
    "sg:website":"www.hotdawgs.net",
    "wof:name":"Hot Dawgs Kennel",
    "wof:placetype":"venue"
},
  "geometry": {"coordinates":[-88.62735600000001,37.015242],"type":"Point"}
}