{
  "type": "Feature",
  "properties": {
    "addr:full":"13 Goodman Ave Shelbyville KY 40065",
    "addr:housenumber":"13",
    "addr:postcode":"40065",
    "addr:street":"Goodman Ave",
    "iso:country":"US",
    "sg:address":"13 Goodman Ave",
    "sg:city":"Shelbyville",
    "sg:classifiers":[
        {
            "category":"Professional",
            "type":"Services"
        }
    ],
    "sg:phone":"+1 502 647 9443",
    "sg:postcode":"40065",
    "sg:province":"KY",
    "sg:tags":[
        "establishment"
    ],
    "wof:name":"Dynamis Group",
    "wof:placetype":"venue"
},
  "geometry": {"coordinates":[-85.20997800000001,38.2086],"type":"Point"}
}