{
  "type": "Feature",
  "properties": {
    "iso:country":"US",
    "sg:address":"147 Fairfield Ave",
    "sg:city":"Bellevue",
    "sg:classifiers":[
        {
            "category":"Retail",
            "subcategory":"Auto Repair",
            "type":"Services"
        }
    ],
    "sg:phone":"+1 859 282 8868",
    "sg:postcode":"41073",
    "sg:province":"KY",
    "sg:tags":[
        "repairing",
        "automobile"
    ],
    "wof:name":"Clint Bradley",
    "wof:placetype":"venue"
},
  "geometry": {"coordinates":[-84.485878,39.104193],"type":"Point"}
}