{
  "type": "Feature",
  "properties": {
    "iso:country":"US",
    "sg:address":"901 US Hwy 68",
    "sg:city":"Maysville",
    "sg:classifiers":[
        {
            "category":"Manufacturing",
            "subcategory":"Printing",
            "type":"Manufacturing & Wholesale Goods"
        }
    ],
    "sg:phone":"+1 606 563 9554",
    "sg:postcode":"41056",
    "sg:province":"KY",
    "sg:tags":[
        "newspaper"
    ],
    "wof:name":"Midweek News",
    "wof:placetype":"venue"
},
  "geometry": {"coordinates":[-83.772555,38.642834],"type":"Point"}
}