{
  "type": "Feature",
  "properties": {
    "iso:country":"US",
    "sg:address":"3966 US Hwy 641 N",
    "sg:city":"Benton",
    "sg:classifiers":[
        {
            "category":"Organizations",
            "subcategory":"Religious Organization",
            "type":"Services"
        }
    ],
    "sg:phone":"+1 270 527 9082",
    "sg:postcode":"42025",
    "sg:province":"KY",
    "sg:tags":[
        "church"
    ],
    "wof:name":"St Matthew By The Lake Preschl",
    "wof:placetype":"venue"
},
  "geometry": {"coordinates":[-88.32766599999999,36.936537],"type":"Point"}
}