{
  "type": "Feature",
  "properties": {
    "iso:country":"US",
    "sg:address":"5350 Foxdale Ct",
    "sg:city":"Independence",
    "sg:classifiers":[
        {
            "category":"Shopping",
            "subcategory":"Musical Instruments",
            "type":"Retail Goods"
        }
    ],
    "sg:phone":"+1 859 356 3999",
    "sg:postcode":"41051",
    "sg:province":"KY",
    "wof:name":"Metrologic Instruments Inc",
    "wof:placetype":"venue"
},
  "geometry": {"coordinates":[-84.53807399999999,38.93749],"type":"Point"}
}