{
  "type": "Feature",
  "properties": {
    "addr:full":"524 E Main St Hazard KY 41701",
    "addr:housenumber":"524",
    "addr:postcode":"41701",
    "addr:street":"E Main St",
    "iso:country":"US",
    "sg:address":"524 E Main St",
    "sg:city":"Hazard",
    "sg:classifiers":[
        {
            "category":"Health Services",
            "subcategory":"Health Practitioner",
            "type":"Services"
        }
    ],
    "sg:phone":"+1 606 435 1737",
    "sg:postcode":"41701",
    "sg:province":"KY",
    "sg:tags":[
        "pathologist",
        "speech"
    ],
    "wof:name":"East Kentucky Therapy Clinic",
    "wof:placetype":"venue"
},
  "geometry": {"coordinates":[-83.185534,37.24644],"type":"Point"}
}