{
  "type": "Feature",
  "properties": {
    "iso:country":"US",
    "sg:address":"2911 Taylorsville Rd",
    "sg:city":"Louisville",
    "sg:classifiers":[
        {
            "category":"Airline",
            "type":"Transportation"
        }
    ],
    "sg:phone":"+1 502 451 8180",
    "sg:postcode":"40205",
    "sg:province":"KY",
    "sg:tags":[
        "helicopter",
        "rental"
    ],
    "wof:name":"U S Helicopters",
    "wof:placetype":"venue"
},
  "geometry": {"coordinates":[-85.66486500000001,38.2227],"type":"Point"}
}