{
  "type": "Feature",
  "properties": {
    "iso:country":"US",
    "sg:address":"291 N Hubbards Ln",
    "sg:city":"St Matthews",
    "sg:classifiers":[
        {
            "category":"Restaurant",
            "type":"Food & Drink"
        }
    ],
    "sg:phone":"+1 502 899 7188",
    "sg:postcode":"40207",
    "sg:province":"KY",
    "wof:name":"King Wok",
    "wof:placetype":"venue"
},
  "geometry": {"coordinates":[-85.63975000000001,38.258254],"type":"Point"}
}