{
  "type": "Feature",
  "properties": {
    "iso:country":"US",
    "sg:address":"46 Lawson Ln",
    "sg:city":"Shelbyville",
    "sg:classifiers":[
        {
            "category":"Organizations",
            "subcategory":"Religious Organization",
            "type":"Services"
        }
    ],
    "sg:phone":"+1 502 633 6395",
    "sg:postcode":"40065",
    "sg:province":"KY",
    "sg:tags":[
        "church"
    ],
    "wof:name":"Clayvillage Baptist Church",
    "wof:placetype":"venue"
},
  "geometry": {"coordinates":[-85.108017,38.192974],"type":"Point"}
}