{
  "type": "Feature",
  "properties": {
    "iso:country":"US",
    "sg:address":"510 Plummer Ln",
    "sg:city":"Vanceburg",
    "sg:classifiers":[
        {
            "category":"Home & Garden",
            "subcategory":"Building Materials",
            "type":"Retail Goods"
        }
    ],
    "sg:phone":"+1 606 796 3144",
    "sg:postcode":"41179",
    "sg:province":"KY",
    "sg:tags":[
        "mixed",
        "concrete"
    ],
    "wof:name":"Wells Group LLC",
    "wof:placetype":"venue"
},
  "geometry": {"coordinates":[-83.322198,38.595782],"type":"Point"}
}