{
  "type": "Feature",
  "properties": {
    "addr:full":"522 Codell Dr Lexington KY 40509",
    "addr:housenumber":"522",
    "addr:postcode":"40509",
    "addr:street":"Codell Dr",
    "iso:country":"US",
    "sg:address":"522 Codell Dr",
    "sg:city":"Lexington",
    "sg:classifiers":[
        {
            "category":"Wholesale",
            "subcategory":"Machinery & Supplies",
            "type":"Manufacturing & Wholesale Goods"
        }
    ],
    "sg:phone":"+1 859 268 4239",
    "sg:postcode":"40509",
    "sg:province":"KY",
    "sg:tags":[
        "industrial",
        "miscellaneous"
    ],
    "wof:name":"Ibex Contractors Equipment",
    "wof:placetype":"venue"
},
  "geometry": {"coordinates":[-84.451071,38.022839],"type":"Point"}
}