{
  "type": "Feature",
  "properties": {
    "addr:full":"1120 High Point Dr Nicholasville KY 40356",
    "addr:housenumber":"1120",
    "addr:postcode":"40356",
    "addr:street":"High Point Dr",
    "iso:country":"US",
    "sg:address":"1120 High Point Dr",
    "sg:city":"Nicholasville",
    "sg:classifiers":[
        {
            "category":"Building & Trades",
            "subcategory":"Construction",
            "type":"Services"
        }
    ],
    "sg:phone":"+1 859 885 0269",
    "sg:postcode":"40356",
    "sg:province":"KY",
    "sg:tags":[
        "hanging",
        "contractor"
    ],
    "wof:name":"Bfx Painting & Pressure",
    "wof:placetype":"venue"
},
  "geometry": {"coordinates":[-84.48436,37.886384],"type":"Point"}
}