{
  "type": "Feature",
  "properties": {
    "addr:full":"2001 Greenup St Covington KY 41014",
    "addr:housenumber":"2001",
    "addr:postcode":"41014",
    "addr:street":"Greenup St",
    "iso:country":"US",
    "sg:address":"2001 Greenup St",
    "sg:city":"Covington",
    "sg:classifiers":[
        {
            "category":"Home & Garden",
            "subcategory":"Household Appliances",
            "type":"Retail Goods"
        }
    ],
    "sg:phone":"+1 859 491 2748",
    "sg:postcode":"41014",
    "sg:province":"KY",
    "sg:tags":[
        "cleaners",
        "vacuum"
    ],
    "wof:name":"All Vacuum Ctr",
    "wof:placetype":"venue"
},
  "geometry": {"coordinates":[-84.50247299999999,39.065456],"type":"Point"}
}