{
  "type": "Feature",
  "properties": {
    "addr:full":"1414 Galbraith Rd Frankfort KY 40601",
    "addr:housenumber":"1414",
    "addr:postcode":"40601",
    "addr:street":"Galbraith Rd",
    "iso:country":"US",
    "sg:address":"1414 Galbraith Rd",
    "sg:city":"Frankfort",
    "sg:classifiers":[
        {
            "category":"Manufacturing",
            "subcategory":"Metals",
            "type":"Manufacturing & Wholesale Goods"
        }
    ],
    "sg:phone":"+1 502 695 5715",
    "sg:postcode":"40601",
    "sg:province":"KY",
    "sg:tags":[
        "steel"
    ],
    "wof:name":"Samson Steel Corp",
    "wof:placetype":"venue"
},
  "geometry": {"coordinates":[-84.82638900000001,38.181285],"type":"Point"}
}