{
  "type": "Feature",
  "properties": {
    "iso:country":"US",
    "sg:address":"636 US Hwy 41A",
    "sg:city":"Henderson",
    "sg:classifiers":[
        {
            "category":"Building & Trades",
            "subcategory":"Construction",
            "type":"Services"
        }
    ],
    "sg:phone":"+1 270 826 0476",
    "sg:postcode":"42420",
    "sg:province":"KY",
    "sg:tags":[
        "concrete",
        "contractor"
    ],
    "wof:name":"D & D Foundation Supply",
    "wof:placetype":"venue"
},
  "geometry": {"coordinates":[-87.622276,37.807156],"type":"Point"}
}