{
  "type": "Feature",
  "properties": {
    "addr:full":"654 Main St West Liberty KY 41472",
    "addr:housenumber":"654",
    "addr:postcode":"41472",
    "addr:street":"Main St West",
    "iso:country":"US",
    "sg:address":"654 Main St",
    "sg:city":"West Liberty",
    "sg:classifiers":[
        {
            "category":"Shopping",
            "subcategory":"Clothing, Apparel, & Fashions",
            "type":"Retail Goods"
        }
    ],
    "sg:phone":"+1 606 743 9031",
    "sg:postcode":"41472",
    "sg:province":"KY",
    "wof:name":"West Liberty Outer Wear",
    "wof:placetype":"venue"
},
  "geometry": {"coordinates":[-83.259516,37.922823],"type":"Point"}
}