{
  "type": "Feature",
  "properties": {
    "addr:full":"4420 Dixie Hwy Louisville KY 40216",
    "addr:housenumber":"4420",
    "addr:postcode":"40216",
    "addr:street":"Dixie Hwy",
    "iso:country":"US",
    "sg:address":"4420 Dixie Hwy",
    "sg:city":"Louisville",
    "sg:classifiers":[
        {
            "category":"Shopping",
            "subcategory":"Department Store",
            "type":"Retail Goods"
        }
    ],
    "sg:phone":"+1 502 449 1361",
    "sg:postcode":"40216",
    "sg:province":"KY",
    "wof:name":"Dillard's",
    "wof:placetype":"venue"
},
  "geometry": {"coordinates":[-85.815971,38.181218],"type":"Point"}
}