{
  "type": "Feature",
  "properties": {
    "iso:country":"US",
    "sg:address":"12700 Shelbyville Rd",
    "sg:city":"Louisville",
    "sg:classifiers":[
        {
            "category":"Real Estate",
            "subcategory":"Real Estate Operator",
            "type":"Services"
        },
        {
            "category":"Manufacturing",
            "subcategory":"Tools & Machinery",
            "type":"Manufacturing & Wholesale Goods"
        }
    ],
    "sg:phone":"+1 502 254 6130",
    "sg:postcode":"40243",
    "sg:province":"KY",
    "sg:tags":[
        "control",
        "building",
        "mfg",
        "parks",
        "air",
        "equipment",
        "design",
        "pollution"
    ],
    "wof:name":"Procedair Industries Corp",
    "wof:placetype":"venue"
},
  "geometry": {"coordinates":[-85.51844800000001,38.2435],"type":"Point"}
}