{
  "type": "Feature",
  "properties": {
    "addr:full":"100 W Render St Hartford KY 42347",
    "addr:housenumber":"100",
    "addr:postcode":"42347",
    "addr:street":"W Render St",
    "iso:country":"US",
    "sg:address":"100 W Render St",
    "sg:city":"Hartford",
    "sg:classifiers":[
        {
            "category":"Education",
            "subcategory":"School",
            "type":"Public Place"
        }
    ],
    "sg:phone":"+1 270 298 9092",
    "sg:postcode":"42347",
    "sg:province":"KY",
    "wof:name":"Render Education Ctr",
    "wof:placetype":"venue"
},
  "geometry": {"coordinates":[-86.90344399999999,37.446711],"type":"Point"}
}