{
  "type": "Feature",
  "properties": {
    "iso:country":"US",
    "sg:address":"317 W Main St",
    "sg:city":"Danville",
    "sg:classifiers":[
        {
            "category":"Professional",
            "subcategory":"Business Services",
            "type":"Services"
        }
    ],
    "sg:phone":"+1 859 236 1852",
    "sg:postcode":"40422",
    "sg:province":"KY",
    "sg:tags":[
        "auctioneer"
    ],
    "wof:name":"VIP Auction Co",
    "wof:placetype":"venue"
},
  "geometry": {"coordinates":[-84.773794,37.64598],"type":"Point"}
}