{
  "type": "Feature",
  "properties": {
    "iso:country":"US",
    "sg:address":"789 Eastern Byp",
    "sg:city":"Richmond",
    "sg:classifiers":[
        {
            "category":"Health Services",
            "subcategory":"Doctor",
            "type":"Services"
        }
    ],
    "sg:phone":"+1 859 624 9843",
    "sg:postcode":"40475",
    "sg:province":"KY",
    "sg:tags":[
        "physician",
        "surgeon"
    ],
    "wof:name":"Dora A Picon MD",
    "wof:placetype":"venue"
},
  "geometry": {"coordinates":[-84.286545,37.731186],"type":"Point"}
}