{
  "type": "Feature",
  "properties": {
    "iso:country":"US",
    "sg:address":"954 Heavrin Rd",
    "sg:city":"Sturgis",
    "sg:classifiers":[
        {
            "category":"Farming",
            "subcategory":"Farm",
            "type":"Manufacturing & Wholesale Goods"
        }
    ],
    "sg:phone":"+1 270 333 4836",
    "sg:postcode":"42459",
    "sg:province":"KY",
    "sg:tags":[
        "crop",
        "general"
    ],
    "wof:name":"Homer Dossett Farm",
    "wof:placetype":"venue"
},
  "geometry": {"coordinates":[-88.050715,37.594097],"type":"Point"}
}