{
  "type": "Feature",
  "properties": {
    "iso:country":"US",
    "sg:address":"5860 Cumberland Falls Hwy",
    "sg:city":"Corbin",
    "sg:classifiers":[
        {
            "category":"Autos & Motor Vehicles",
            "subcategory":"Automobile Sales",
            "type":"Retail Goods"
        }
    ],
    "sg:phone":"+1 606 523 9725",
    "sg:postcode":"40701",
    "sg:province":"KY",
    "sg:tags":[
        "car",
        "dealer"
    ],
    "wof:name":"Falls Road Auto Sales",
    "wof:placetype":"venue"
},
  "geometry": {"coordinates":[-84.173028,36.900746],"type":"Point"}
}