{
  "type": "Feature",
  "properties": {
    "addr:full":"651 Prince Royal Dr Berea KY 40403",
    "addr:housenumber":"651",
    "addr:postcode":"40403",
    "addr:street":"Prince Royal Dr",
    "iso:country":"US",
    "sg:address":"651 Prince Royal Dr",
    "sg:city":"Berea",
    "sg:classifiers":[
        {
            "category":"Shopping",
            "subcategory":"Department Store",
            "type":"Retail Goods"
        }
    ],
    "sg:phone":"+1 859 986 7500",
    "sg:postcode":"40403",
    "sg:province":"KY",
    "sg:tags":[
        "shop"
    ],
    "wof:name":"Dollar General",
    "wof:placetype":"venue"
},
  "geometry": {"coordinates":[-84.31031900000001,37.572885],"type":"Point"}
}