{
  "type": "Feature",
  "properties": {
    "iso:country":"US",
    "sg:address":"1132 E Laurel Rd",
    "sg:city":"London",
    "sg:classifiers":[
        {
            "category":"Retail",
            "subcategory":"Portrait Studio",
            "type":"Services"
        }
    ],
    "sg:phone":"+1 606 862 8000",
    "sg:postcode":"40741",
    "sg:province":"KY",
    "sg:tags":[
        "photographer"
    ],
    "wof:name":"KNOX Studio",
    "wof:placetype":"venue"
},
  "geometry": {"coordinates":[-84.005258,37.104995],"type":"Point"}
}