{
  "type": "Feature",
  "properties": {
    "iso:country":"US",
    "sg:address":"1447 Asa Flats Rd",
    "sg:city":"Annville",
    "sg:classifiers":[
        {
            "category":"Organizations",
            "subcategory":"Religious Organization",
            "type":"Services"
        }
    ],
    "sg:phone":"+1 606 364 3750",
    "sg:postcode":"40402",
    "sg:province":"KY",
    "sg:tags":[
        "church"
    ],
    "wof:name":"Seven Pines Pentecostal Church",
    "wof:placetype":"venue"
},
  "geometry": {"coordinates":[-84.020686,37.312476],"type":"Point"}
}