{
  "type": "Feature",
  "properties": {
    "iso:country":"US",
    "sg:address":"4600 Harrodsburg Rd",
    "sg:city":"Lexington",
    "sg:classifiers":[
        {
            "category":"Real Estate",
            "subcategory":"Developer",
            "type":"Services"
        }
    ],
    "sg:phone":"+1 859 223 8093",
    "sg:postcode":"40513",
    "sg:province":"KY",
    "wof:name":"English Station Development",
    "wof:placetype":"venue"
},
  "geometry": {"coordinates":[-84.58925499999999,37.992003],"type":"Point"}
}