{
  "type": "Feature",
  "properties": {
    "iso:country":"US",
    "sg:address":"237 E 10th St",
    "sg:city":"Newport",
    "sg:classifiers":[
        {
            "category":"Health Services",
            "subcategory":"Doctor",
            "type":"Services"
        }
    ],
    "sg:phone":"+1 859 431 2212",
    "sg:postcode":"41071",
    "sg:province":"KY",
    "sg:tags":[
        "physician",
        "surgeon"
    ],
    "wof:name":"Vinoo M Cholera MD",
    "wof:placetype":"venue"
},
  "geometry": {"coordinates":[-84.48721500000001,39.088193],"type":"Point"}
}