{
  "type": "Feature",
  "properties": {
    "iso:country":"US",
    "sg:address":"1419 Selinda Ave",
    "sg:city":"Louisville",
    "sg:classifiers":[
        {
            "category":"Manufacturing",
            "subcategory":"Chemicals & Compounds",
            "type":"Manufacturing & Wholesale Goods"
        },
        {
            "category":"Building & Trades",
            "subcategory":"Cleaning & Sanitation",
            "type":"Services"
        },
        {
            "category":"Wholesale",
            "subcategory":"Construction Materials",
            "type":"Manufacturing & Wholesale Goods"
        },
        {
            "category":"Food & Beverages",
            "subcategory":"Groceries & Convenience Stores",
            "type":"Retail Goods"
        }
    ],
    "sg:phone":"+1 502 454 4473",
    "sg:postcode":"40213",
    "sg:province":"KY",
    "sg:tags":[
        "coatings-protective",
        "removing",
        "coating",
        "cleaning-exterior",
        "paint",
        "sandblasting",
        "powder",
        "processing-industrial",
        "cleaners-interior"
    ],
    "sg:website":"http://www.kypowdercoating.com",
    "wof:name":"Epic Concepts",
    "wof:placetype":"venue"
},
  "geometry": {"coordinates":[-85.70095000000001,38.189259],"type":"Point"}
}