{
  "type": "Feature",
  "properties": {
    "iso:country":"US",
    "sg:address":"115 Home Way",
    "sg:city":"La Grange",
    "sg:classifiers":[
        {
            "category":"Building & Trades",
            "subcategory":"Construction",
            "type":"Services"
        }
    ],
    "sg:phone":"+1 502 222 8954",
    "sg:postcode":"40031",
    "sg:province":"KY",
    "sg:tags":[
        "marking",
        "maintenance",
        "parking"
    ],
    "wof:name":"LA Grange City Public Works",
    "wof:placetype":"venue"
},
  "geometry": {"coordinates":[-85.38250499999999,38.41504],"type":"Point"}
}