{
  "type": "Feature",
  "properties": {
    "addr:full":"230 Lexington Green Cir Lexington KY 40503",
    "addr:housenumber":"230",
    "addr:postcode":"40503",
    "addr:street":"Lexington Green Cir",
    "iso:country":"US",
    "sg:address":"230 Lexington Green Cir",
    "sg:city":"Lexington",
    "sg:classifiers":[
        {
            "category":"Professional",
            "subcategory":"Employment Agencies",
            "type":"Services"
        }
    ],
    "sg:phone":"+1 859 971 0120",
    "sg:postcode":"40503",
    "sg:province":"KY",
    "sg:tags":[
        "consultant",
        "search",
        "executive"
    ],
    "wof:name":"Venator Partners",
    "wof:placetype":"venue"
},
  "geometry": {"coordinates":[-84.525868,37.995491],"type":"Point"}
}