{
  "type": "Feature",
  "properties": {
    "addr:full":"716 R S Bradley Blvd Clarksville KY 37042",
    "addr:housenumber":"716",
    "addr:postcode":"37042",
    "addr:street":"R S Bradley Blvd",
    "iso:country":"US",
    "sg:address":"716 R S Bradley Blvd",
    "sg:city":"Clarksville",
    "sg:classifiers":[
        {
            "category":"Health Services",
            "subcategory":"Health Practitioner",
            "type":"Services"
        }
    ],
    "sg:phone":"+1 931 431 7084",
    "sg:postcode":"37042",
    "sg:province":"KY",
    "sg:tags":[
        "dental"
    ],
    "wof:name":"Christina Murphy",
    "wof:placetype":"venue"
},
  "geometry": {"coordinates":[-87.42830499999999,36.568494],"type":"Point"}
}