{
  "type": "Feature",
  "properties": {
    "addr:full":"1236 Texas Ave Louisville KY 40204",
    "addr:housenumber":"1236",
    "addr:postcode":"40204",
    "addr:street":"Texas Ave",
    "iso:country":"US",
    "sg:address":"1236 Texas Ave",
    "sg:city":"Louisville",
    "sg:classifiers":[
        {
            "category":"Communications",
            "subcategory":"Film & Video Production",
            "type":"Services"
        }
    ],
    "sg:phone":"+1 502 637 7840",
    "sg:postcode":"40204",
    "sg:province":"KY",
    "sg:tags":[
        "taping"
    ],
    "wof:name":"Atkinson Morgan/Duckworks Inc",
    "wof:placetype":"venue"
},
  "geometry": {"coordinates":[-85.73334,38.226039],"type":"Point"}
}