{
  "type": "Feature",
  "properties": {
    "iso:country":"US",
    "sg:address":"6112 Richie Wayne Dr",
    "sg:city":"Louisville",
    "sg:classifiers":[
        {
            "category":"Professional",
            "subcategory":"Business Services",
            "type":"Services"
        }
    ],
    "sg:phone":"+1 502 962 4394",
    "sg:postcode":"40219",
    "sg:province":"KY",
    "wof:name":"Gina Robles",
    "wof:placetype":"venue"
},
  "geometry": {"coordinates":[-85.644042,38.130182],"type":"Point"}
}