{
  "type": "Feature",
  "properties": {
    "iso:country":"US",
    "sg:address":"AA Hwy",
    "sg:city":"Alexandria",
    "sg:classifiers":[
        {
            "category":"Restaurant",
            "type":"Food & Drink"
        }
    ],
    "sg:phone":"+1 859 635 8700",
    "sg:postcode":"41001",
    "sg:province":"KY",
    "sg:tags":[
        "pizza"
    ],
    "wof:name":"Angilo's Pizza",
    "wof:placetype":"venue"
},
  "geometry": {"coordinates":[-84.3965,38.9562],"type":"Point"}
}