{
  "type": "Feature",
  "properties": {
    "iso:country":"US",
    "sg:address":"1079 Lakeview Dr",
    "sg:city":"Paducah",
    "sg:classifiers":[
        {
            "category":"Recreation",
            "type":"Entertainment"
        }
    ],
    "sg:phone":"+1 270 554 5221",
    "sg:postcode":"42003",
    "sg:province":"KY",
    "sg:tags":[
        "club",
        "membership"
    ],
    "wof:name":"Four Rivers Corvette Club Inc",
    "wof:placetype":"venue"
},
  "geometry": {"coordinates":[-88.641268,37.037864],"type":"Point"}
}