{
  "type": "Feature",
  "properties": {
    "iso:country":"US",
    "sg:address":"4900 Mark Jones Way",
    "sg:city":"Shively",
    "sg:classifiers":[
        {
            "category":"Building & Trades",
            "subcategory":"Construction",
            "type":"Services"
        }
    ],
    "sg:phone":"+1 502 449 5010",
    "sg:postcode":"40216",
    "sg:province":"KY",
    "sg:tags":[
        "marking",
        "maintenance",
        "parking"
    ],
    "wof:name":"Shively Public Works",
    "wof:placetype":"venue"
},
  "geometry": {"coordinates":[-85.84849199999999,38.175779],"type":"Point"}
}