{
  "type": "Feature",
  "properties": {
    "addr:full":"800 Main St Benton KY 42025",
    "addr:housenumber":"800",
    "addr:postcode":"42025",
    "addr:street":"Main St",
    "iso:country":"US",
    "sg:address":"800 Main St",
    "sg:city":"Benton",
    "sg:classifiers":[
        {
            "category":"Personal",
            "subcategory":"Beauty Salon",
            "type":"Services"
        }
    ],
    "sg:phone":"+1 270 527 1983",
    "sg:postcode":"42025",
    "sg:province":"KY",
    "wof:name":"Komelias Hair Shoppes",
    "wof:placetype":"venue"
},
  "geometry": {"coordinates":[-88.350909,36.860649],"type":"Point"}
}