{
  "type": "Feature",
  "properties": {
    "iso:country":"US",
    "sg:address":"4521 Outer Loop",
    "sg:city":"Louisville",
    "sg:classifiers":[
        {
            "category":"Shopping",
            "subcategory":"Hobbies, Toys, & Games",
            "type":"Retail Goods"
        }
    ],
    "sg:phone":"+1 502 968 1144",
    "sg:postcode":"40219",
    "sg:province":"KY",
    "wof:name":"Dees Crafts Inc",
    "wof:placetype":"venue"
},
  "geometry": {"coordinates":[-85.678583,38.138217],"type":"Point"}
}