{
  "type": "Feature",
  "properties": {
    "iso:country":"US",
    "sg:address":"341 Harrison St",
    "sg:city":"Ashland",
    "sg:classifiers":[
        {
            "category":"Wholesale",
            "subcategory":"Electrical",
            "type":"Manufacturing & Wholesale Goods"
        }
    ],
    "sg:phone":"+1 606 324 1593",
    "sg:postcode":"41101",
    "sg:province":"KY",
    "sg:tags":[
        "control",
        "security",
        "system"
    ],
    "wof:name":"Ashland Central Monitoring Inc",
    "wof:placetype":"venue"
},
  "geometry": {"coordinates":[-82.659769,38.475356],"type":"Point"}
}