{
  "type": "Feature",
  "properties": {
    "iso:country":"US",
    "sg:address":"118 Begley Ln",
    "sg:city":"Baxter",
    "sg:phone":"+1 606 573 5961",
    "sg:postcode":"40806",
    "sg:province":"KY",
    "sg:tags":[
        "product",
        "petroleum"
    ],
    "wof:name":"Doss Fuelco Inc",
    "wof:placetype":"venue"
},
  "geometry": {"coordinates":[-83.288438,36.881488],"type":"Point"}
}