{
  "type": "Feature",
  "properties": {
    "iso:country":"US",
    "sg:address":"1235 Cumberland Falls Hwy",
    "sg:city":"Corbin",
    "sg:classifiers":[
        {
            "category":"Shopping",
            "subcategory":"Clothing, Apparel, & Fashions",
            "type":"Retail Goods"
        }
    ],
    "sg:phone":"+1 606 528 0505",
    "sg:postcode":"40701",
    "sg:province":"KY",
    "sg:tags":[
        "item",
        "boutique"
    ],
    "wof:name":"Norma's Boutique & Beauty",
    "wof:placetype":"venue"
},
  "geometry": {"coordinates":[-84.108199,36.928221],"type":"Point"}
}