{
  "type": "Feature",
  "properties": {
    "addr:full":"5000 Frederica St Owensboro KY 42301",
    "addr:housenumber":"5000",
    "addr:postcode":"42301",
    "addr:street":"Frederica St",
    "iso:country":"US",
    "sg:address":"5000 Frederica St",
    "sg:city":"Owensboro",
    "sg:classifiers":[
        {
            "category":"Shopping",
            "subcategory":"Clothing, Apparel, & Fashions",
            "type":"Retail Goods"
        }
    ],
    "sg:phone":"+1 270 926 2116",
    "sg:postcode":"42301",
    "sg:province":"KY",
    "sg:tags":[
        "t"
    ],
    "wof:name":"Picasso's Airbrush Express",
    "wof:placetype":"venue"
},
  "geometry": {"coordinates":[-87.12565499999999,37.716506],"type":"Point"}
}