{
  "type": "Feature",
  "properties": {
    "iso:country":"US",
    "sg:address":"1609 Hillsboro Rd",
    "sg:city":"Campbellsburg",
    "sg:classifiers":[
        {
            "category":"Professional",
            "subcategory":"Business Services",
            "type":"Services"
        }
    ],
    "sg:phone":"+1 502 532 6190",
    "sg:postcode":"40011",
    "sg:province":"KY",
    "sg:tags":[
        "tank",
        "testing",
        "inspection"
    ],
    "wof:name":"Wet Or Dry Tank Inspections",
    "wof:placetype":"venue"
},
  "geometry": {"coordinates":[-85.19962200000001,38.507134],"type":"Point"}
}