{
  "type": "Feature",
  "properties": {
    "iso:country":"US",
    "sg:address":"205 W Cedar St",
    "sg:city":"Franklin",
    "sg:classifiers":[
        {
            "category":"Shopping",
            "subcategory":"Used Merchandise",
            "type":"Retail Goods"
        }
    ],
    "sg:phone":"+1 270 586 8340",
    "sg:postcode":"42134",
    "sg:province":"KY",
    "sg:tags":[
        "furniture"
    ],
    "wof:name":"P J's General Store",
    "wof:placetype":"venue"
},
  "geometry": {"coordinates":[-86.580258,36.722291],"type":"Point"}
}