{
  "type": "Feature",
  "properties": {
    "iso:country":"US",
    "sg:address":"2505 Crittenden Dr",
    "sg:city":"Louisville",
    "sg:classifiers":[
        {
            "category":"Wholesale",
            "subcategory":"Construction Materials",
            "type":"Manufacturing & Wholesale Goods"
        }
    ],
    "sg:phone":"+1 502 636 3861",
    "sg:postcode":"40217",
    "sg:province":"KY",
    "sg:tags":[
        "brick",
        "common",
        "face"
    ],
    "sg:website":"www.boralbricks.com",
    "wof:name":"Boral Bricks Direct",
    "wof:placetype":"venue"
},
  "geometry": {"coordinates":[-85.751057,38.208653],"type":"Point"}
}