{
  "type": "Feature",
  "properties": {
    "iso:country":"US",
    "sg:address":"325 Salem Dr",
    "sg:city":"Owensboro",
    "sg:classifiers":[
        {
            "category":"Wholesale",
            "subcategory":"Construction Materials",
            "type":"Manufacturing & Wholesale Goods"
        }
    ],
    "sg:phone":"+1 270 926 3323",
    "sg:postcode":"42303",
    "sg:province":"KY",
    "sg:tags":[
        "concrete",
        "product"
    ],
    "wof:name":"Etc",
    "wof:placetype":"venue"
},
  "geometry": {"coordinates":[-87.11542,37.726312],"type":"Point"}
}