{
  "type": "Feature",
  "properties": {
    "iso:country":"US",
    "sg:address":"3334 Frankfort Ave",
    "sg:city":"Louisville",
    "sg:classifiers":[
        {
            "category":"Restaurant",
            "type":"Food & Drink"
        }
    ],
    "sg:menulink":"http://www.allmenus.com/ky/louisville-east/4412-tony-boombozz/menu/",
    "sg:phone":"+1 502 896 9090",
    "sg:postcode":"40206",
    "sg:province":"KY",
    "sg:tags":[
        "italian"
    ],
    "wof:name":"Tony Boombozz",
    "wof:placetype":"venue"
},
  "geometry": {"coordinates":[-85.67164,38.254124],"type":"Point"}
}