{
  "type": "Feature",
  "properties": {
    "iso:country":"US",
    "sg:address":"415 Chair Ave",
    "sg:city":"Lexington",
    "sg:classifiers":[
        {
            "category":"Manufacturing",
            "subcategory":"Furniture",
            "type":"Manufacturing & Wholesale Goods"
        }
    ],
    "sg:phone":"+1 859 254 5614",
    "sg:postcode":"40508",
    "sg:province":"KY",
    "sg:tags":[
        "metal"
    ],
    "wof:name":"Hughes Metalsmithing",
    "wof:placetype":"venue"
},
  "geometry": {"coordinates":[-84.50932,38.044439],"type":"Point"}
}