{
  "type": "Feature",
  "properties": {
    "addr:full":"111 US Hwy 27 Somerset KY 42501",
    "addr:housenumber":"111",
    "addr:postcode":"42501",
    "addr:street":"Us Hwy 27",
    "iso:country":"US",
    "sg:address":"111 US Hwy 27",
    "sg:city":"Somerset",
    "sg:classifiers":[
        {
            "category":"Autos & Motor Vehicles",
            "subcategory":"Fuel & Gas Station",
            "type":"Retail Goods"
        }
    ],
    "sg:phone":"+1 606 679 1628",
    "sg:postcode":"42501",
    "sg:province":"KY",
    "sg:tags":[
        "oil"
    ],
    "wof:name":"Speedway",
    "wof:placetype":"venue"
},
  "geometry": {"coordinates":[-84.630033,37.143434],"type":"Point"}
}