{
  "type": "Feature",
  "properties": {
    "addr:full":"531 S 4th St Louisville KY 40202",
    "addr:housenumber":"531",
    "addr:postcode":"40202",
    "addr:street":"S 4Th St",
    "iso:country":"US",
    "sg:address":"531 S 4th St",
    "sg:city":"Louisville",
    "sg:classifiers":[
        {
            "category":"Restaurant",
            "type":"Food & Drink"
        }
    ],
    "sg:phone":"+1 502 561 0098",
    "sg:postcode":"40202",
    "sg:province":"KY",
    "wof:name":"Brian's Deli",
    "wof:placetype":"venue"
},
  "geometry": {"coordinates":[-85.757667,38.250137],"type":"Point"}
}