{
  "type": "Feature",
  "properties": {
    "iso:country":"US",
    "sg:address":"1139 Guy Rd",
    "sg:city":"Morgantown",
    "sg:classifiers":[
        {
            "category":"Building & Trades",
            "subcategory":"Construction",
            "type":"Services"
        }
    ],
    "sg:phone":"+1 270 526 9375",
    "sg:postcode":"42101",
    "sg:province":"KY",
    "sg:tags":[
        "house"
    ],
    "wof:name":"Whittinghill Home Improvement",
    "wof:placetype":"venue"
},
  "geometry": {"coordinates":[-86.63714,37.134432],"type":"Point"}
}