{
  "type": "Feature",
  "properties": {
    "iso:country":"US",
    "sg:address":"1512 W Main St",
    "sg:city":"Louisville",
    "sg:phone":"+1 502 585 1907",
    "sg:postcode":"40203",
    "sg:province":"KY",
    "sg:tags":[
        "equipment",
        "supply"
    ],
    "wof:name":"Chef Supply",
    "wof:placetype":"venue"
},
  "geometry": {"coordinates":[-85.77624,38.258713],"type":"Point"}
}