{
  "type": "Feature",
  "properties": {
    "iso:country":"US",
    "sg:address":"4428 E Fork Rd",
    "sg:city":"Owingsville",
    "sg:classifiers":[
        {
            "category":"Organizations",
            "subcategory":"Religious Organization",
            "type":"Services"
        }
    ],
    "sg:phone":"+1 606 247 5888",
    "sg:postcode":"40360",
    "sg:province":"KY",
    "sg:tags":[
        "church"
    ],
    "wof:name":"East Fork Church Of God",
    "wof:placetype":"venue"
},
  "geometry": {"coordinates":[-83.790256,38.232903],"type":"Point"}
}