{
  "type": "Feature",
  "properties": {
    "iso:country":"US",
    "sg:address":"1975 Blair Schoolhouse Rd",
    "sg:city":"Russell Springs",
    "sg:classifiers":[
        {
            "category":"Professional",
            "subcategory":"Computer Services",
            "type":"Services"
        }
    ],
    "sg:phone":"+1 270 866 6457",
    "sg:postcode":"42642",
    "sg:province":"KY",
    "sg:tags":[
        "programing",
        "custom"
    ],
    "wof:name":"Support Group Inc",
    "wof:placetype":"venue"
},
  "geometry": {"coordinates":[-85.15673099999999,37.031322],"type":"Point"}
}