{
  "type": "Feature",
  "properties": {
    "iso:country":"US",
    "sg:address":"1554 Bardstown Rd",
    "sg:city":"Louisville",
    "sg:classifiers":[
        {
            "category":"Professional",
            "subcategory":"Advertising",
            "type":"Services"
        }
    ],
    "sg:phone":"+1 502 459 8755",
    "sg:postcode":"40205",
    "sg:province":"KY",
    "sg:tags":[
        "specialty"
    ],
    "sg:website":"http://www.spaldingcompanies.com",
    "wof:name":"Specialties By Spalding",
    "wof:placetype":"venue"
},
  "geometry": {"coordinates":[-85.70635799999999,38.231235],"type":"Point"}
}