{
  "type": "Feature",
  "properties": {
    "iso:country":"US",
    "sg:address":"5151 Tom Cat Trl",
    "sg:city":"London",
    "sg:classifiers":[
        {
            "category":"Building & Trades",
            "subcategory":"Cleaning & Sanitation",
            "type":"Services"
        }
    ],
    "sg:phone":"+1 606 864 0024",
    "sg:postcode":"40741",
    "sg:province":"KY",
    "sg:tags":[
        "janitor"
    ],
    "wof:name":"Verda's Cleaning Svc",
    "wof:placetype":"venue"
},
  "geometry": {"coordinates":[-83.942283,37.101036],"type":"Point"}
}