{
  "type": "Feature",
  "properties": {
    "iso:country":"US",
    "sg:address":"2106 Buechel Bank Rd",
    "sg:city":"Louisville",
    "sg:classifiers":[
        {
            "category":"Sports & Exercise",
            "subcategory":"Gym",
            "type":"Entertainment"
        }
    ],
    "sg:phone":"+1 502 671 0007",
    "sg:postcode":"40218",
    "sg:province":"KY",
    "sg:tags":[
        "spa",
        "health"
    ],
    "wof:name":"Diamond Spa",
    "wof:placetype":"venue"
},
  "geometry": {"coordinates":[-85.647881,38.18695],"type":"Point"}
}