{
  "type": "Feature",
  "properties": {
    "iso:country":"US",
    "sg:address":"7340 Industrial Rd",
    "sg:city":"Florence",
    "sg:classifiers":[
        {
            "category":"Restaurant",
            "type":"Food & Drink"
        }
    ],
    "sg:phone":"+1 859 282 4929",
    "sg:postcode":"41042",
    "sg:province":"KY",
    "wof:name":"Skyline Chili Restaurants",
    "wof:placetype":"venue"
},
  "geometry": {"coordinates":[-84.62235,38.979562],"type":"Point"}
}