{
  "type": "Feature",
  "properties": {
    "addr:full":"2095 Litton Ln Hebron KY 41048",
    "addr:housenumber":"2095",
    "addr:postcode":"41048",
    "addr:street":"Litton Ln",
    "iso:country":"US",
    "sg:address":"2095 Litton Ln",
    "sg:city":"Hebron",
    "sg:classifiers":[
        {
            "category":"Fast Food",
            "type":"Food & Drink"
        },
        {
            "category":"Food & Beverages",
            "subcategory":"Meat & Fish",
            "type":"Retail Goods"
        }
    ],
    "sg:phone":"+1 859 689 7747",
    "sg:postcode":"41048",
    "sg:province":"KY",
    "sg:tags":[
        "burger",
        "hot",
        "dog"
    ],
    "wof:name":"Bruster's Real Ice Cream & Nathan's Hot Dogs",
    "wof:placetype":"venue"
},
  "geometry": {"coordinates":[-84.70696100000001,39.077943],"type":"Point"}
}