{
  "type": "Feature",
  "properties": {
    "addr:full":"2810 Tates Creek Rd Richmond KY 40475",
    "addr:housenumber":"2810",
    "addr:postcode":"40475",
    "addr:street":"Tates Creek Rd",
    "iso:country":"US",
    "sg:address":"2810 Tates Creek Rd",
    "sg:city":"Richmond",
    "sg:classifiers":[
        {
            "category":"Building & Trades",
            "subcategory":"Construction",
            "type":"Services"
        }
    ],
    "sg:phone":"+1 859 200 1773",
    "sg:postcode":"40475",
    "sg:province":"KY",
    "sg:tags":[
        "contractor"
    ],
    "wof:name":"Johnnys Drywall",
    "wof:placetype":"venue"
},
  "geometry": {"coordinates":[-84.419417,37.832271],"type":"Point"}
}