{
  "type": "Feature",
  "properties": {
    "addr:full":"400 Park Ave Paducah KY 42001",
    "addr:housenumber":"400",
    "addr:postcode":"42001",
    "addr:street":"Park Ave",
    "iso:country":"US",
    "sg:address":"400 Park Ave",
    "sg:city":"Paducah",
    "sg:classifiers":[
        {
            "category":"Health Services",
            "subcategory":"Doctor",
            "type":"Services"
        }
    ],
    "sg:phone":"+1 270 443 3651",
    "sg:postcode":"42001",
    "sg:province":"KY",
    "sg:tags":[
        "clinic"
    ],
    "wof:name":"Kentucky Commission-Children",
    "wof:placetype":"venue"
},
  "geometry": {"coordinates":[-88.60116499999999,37.09164],"type":"Point"}
}