{
  "type": "Feature",
  "properties": {
    "iso:country":"US",
    "sg:address":"5252 State Hwy 97",
    "sg:city":"Sedalia",
    "sg:classifiers":[
        {
            "category":"Education",
            "subcategory":"School",
            "type":"Public Place"
        }
    ],
    "sg:phone":"+1 270 328 4850",
    "sg:postcode":"42066",
    "sg:province":"KY",
    "wof:name":"Sedalia Elementary School",
    "wof:placetype":"venue"
},
  "geometry": {"coordinates":[-88.605824,36.647476],"type":"Point"}
}