{
  "type": "Feature",
  "properties": {
    "addr:full":"101 Bullitt Ln Louisville KY 40222",
    "addr:housenumber":"101",
    "addr:postcode":"40222",
    "addr:street":"Bullitt Ln",
    "iso:country":"US",
    "sg:address":"101 Bullitt Ln",
    "sg:city":"Louisville",
    "sg:classifiers":[
        {
            "category":"Wholesale",
            "subcategory":"Electrical",
            "type":"Manufacturing & Wholesale Goods"
        }
    ],
    "sg:phone":"+1 502 425 8363",
    "sg:postcode":"40222",
    "sg:province":"KY",
    "sg:tags":[
        "equipment"
    ],
    "wof:name":"Schneider Electric 418",
    "wof:placetype":"venue"
},
  "geometry": {"coordinates":[-85.61738699999999,38.246973],"type":"Point"}
}