{
  "type": "Feature",
  "properties": {
    "iso:country":"US",
    "sg:address":"6633 US Hwy 25",
    "sg:city":"Corbin",
    "sg:classifiers":[
        {
            "category":"Manufacturing",
            "subcategory":"Watercraft",
            "type":"Manufacturing & Wholesale Goods"
        }
    ],
    "sg:phone":"+1 606 523 2593",
    "sg:postcode":"40701",
    "sg:province":"KY",
    "sg:tags":[
        "boat"
    ],
    "wof:name":"Nu-Legend Boat Co",
    "wof:placetype":"venue"
},
  "geometry": {"coordinates":[-84.070652,37.015944],"type":"Point"}
}