{
  "type": "Feature",
  "properties": {
    "addr:full":"118 Jefferson St Winchester KY 40391",
    "addr:housenumber":"118",
    "addr:postcode":"40391",
    "addr:street":"Jefferson St",
    "iso:country":"US",
    "sg:address":"118 Jefferson St",
    "sg:city":"Winchester",
    "sg:classifiers":[
        {
            "category":"Building & Trades",
            "subcategory":"Pest Control",
            "type":"Services"
        }
    ],
    "sg:phone":"+1 859 744 1139",
    "sg:postcode":"40391",
    "sg:province":"KY",
    "wof:name":"Pestco Exterminating Co",
    "wof:placetype":"venue"
},
  "geometry": {"coordinates":[-84.17032,37.99429],"type":"Point"}
}