{
  "type": "Feature",
  "properties": {
    "iso:country":"US",
    "sg:address":"324 3rd Ave",
    "sg:city":"Dayton",
    "sg:classifiers":[
        {
            "category":"Building & Trades",
            "subcategory":"Construction",
            "type":"Services"
        }
    ],
    "sg:phone":"+1 859 581 6740",
    "sg:postcode":"41074",
    "sg:province":"KY",
    "sg:tags":[
        "hanging",
        "contractor"
    ],
    "wof:name":"Asher Painting",
    "wof:placetype":"venue"
},
  "geometry": {"coordinates":[-84.47788300000001,39.113181],"type":"Point"}
}