{
  "type": "Feature",
  "properties": {
    "addr:full":"111 W Main St Scottsville KY 42164",
    "addr:housenumber":"111",
    "addr:postcode":"42164",
    "addr:street":"W Main St",
    "iso:country":"US",
    "sg:address":"111 W Main St",
    "sg:city":"Scottsville",
    "sg:classifiers":[
        {
            "category":"Shopping",
            "subcategory":"Department Store",
            "type":"Retail Goods"
        }
    ],
    "sg:phone":"+1 270 237 3728",
    "sg:postcode":"42164",
    "sg:province":"KY",
    "sg:tags":[
        "shop"
    ],
    "wof:name":"Dollar General",
    "wof:placetype":"venue"
},
  "geometry": {"coordinates":[-86.190789,36.753387],"type":"Point"}
}