{
  "type": "Feature",
  "properties": {
    "iso:country":"US",
    "sg:address":"1304 Johnson Blvd",
    "sg:city":"Murray",
    "sg:classifiers":[
        {
            "category":"Health Services",
            "subcategory":"Doctor",
            "type":"Services"
        }
    ],
    "sg:phone":"+1 270 753 8368",
    "sg:postcode":"42071",
    "sg:province":"KY",
    "sg:tags":[
        "dentist"
    ],
    "wof:name":"David G Fitch DDS",
    "wof:placetype":"venue"
},
  "geometry": {"coordinates":[-88.318907,36.599028],"type":"Point"}
}