{
  "type": "Feature",
  "properties": {
    "iso:country":"US",
    "sg:address":"1000 Cumberland Falls Hwy",
    "sg:city":"Corbin",
    "sg:classifiers":[
        {
            "category":"Banks & Credit Unions",
            "subcategory":"Bank",
            "type":"Services"
        }
    ],
    "sg:phone":"+1 606 523 8311",
    "sg:postcode":"40701",
    "sg:province":"KY",
    "sg:tags":[
        "cashing",
        "check"
    ],
    "wof:name":"Check Into Cash",
    "wof:placetype":"venue"
},
  "geometry": {"coordinates":[-84.10227999999999,36.930136],"type":"Point"}
}