{
  "type": "Feature",
  "properties": {
    "iso:country":"US",
    "sg:address":"627 Lafayette Rd",
    "sg:city":"Clarksville",
    "sg:classifiers":[
        {
            "category":"Social Services",
            "subcategory":"Child Care",
            "type":"Services"
        }
    ],
    "sg:phone":"+1 931 647 1937",
    "sg:postcode":"37042",
    "sg:province":"KY",
    "sg:tags":[
        "day"
    ],
    "wof:name":"Mrs Lindas Family Childcare",
    "wof:placetype":"venue"
},
  "geometry": {"coordinates":[-87.42527200000001,36.570814],"type":"Point"}
}