{
  "type": "Feature",
  "properties": {
    "iso:country":"US",
    "sg:address":"930 Happy Valley Rd",
    "sg:city":"Glasgow",
    "sg:classifiers":[
        {
            "category":"Health Services",
            "subcategory":"Doctor",
            "type":"Services"
        }
    ],
    "sg:phone":"+1 270 659 2530",
    "sg:postcode":"42141",
    "sg:province":"KY",
    "sg:tags":[
        "physician",
        "surgeon"
    ],
    "wof:name":"Sujata Reddy MD",
    "wof:placetype":"venue"
},
  "geometry": {"coordinates":[-85.92511,37.011928],"type":"Point"}
}