{
  "type": "Feature",
  "properties": {
    "iso:country":"US",
    "sg:address":"522 E Main St",
    "sg:city":"Lexington",
    "sg:classifiers":[
        {
            "category":"Professional",
            "subcategory":"Advertising",
            "type":"Services"
        }
    ],
    "sg:phone":"+1 859 231 7473",
    "sg:postcode":"40508",
    "sg:province":"KY",
    "sg:tags":[
        "counselor"
    ],
    "sg:website":"www.saybrookadvertising.com",
    "wof:name":"Saybrook Advertising Agency",
    "wof:placetype":"venue"
},
  "geometry": {"coordinates":[-84.488613,38.038905],"type":"Point"}
}