{
  "type": "Feature",
  "properties": {
    "addr:full":"4757 Jewell Ln Paducah KY 42001",
    "addr:housenumber":"4757",
    "addr:postcode":"42001",
    "addr:street":"Jewell Ln",
    "iso:country":"US",
    "sg:address":"4757 Jewell Ln",
    "sg:city":"Paducah",
    "sg:classifiers":[
        {
            "category":"Building & Trades",
            "subcategory":"Plumbing",
            "type":"Services"
        }
    ],
    "sg:phone":"+1 270 554 7513",
    "sg:postcode":"42001",
    "sg:province":"KY",
    "sg:tags":[
        "conditioning",
        "air",
        "system",
        "contractor"
    ],
    "wof:name":"Stearns Heating & Air Cond",
    "wof:placetype":"venue"
},
  "geometry": {"coordinates":[-88.710588,37.000301],"type":"Point"}
}