{
  "type": "Feature",
  "properties": {
    "iso:country":"US",
    "sg:address":"1111 Dixie Hwy S",
    "sg:city":"Elizabethtown",
    "sg:classifiers":[
        {
            "category":"Shopping",
            "subcategory":"Clothing, Apparel, & Fashions",
            "type":"Retail Goods"
        }
    ],
    "sg:phone":"+1 270 765 6262",
    "sg:postcode":"42701",
    "sg:province":"KY",
    "sg:tags":[
        "uniform"
    ],
    "wof:name":"St John Uniforms & More",
    "wof:placetype":"venue"
},
  "geometry": {"coordinates":[-85.877658,37.714648],"type":"Point"}
}