{
  "type": "Feature",
  "properties": {
    "iso:country":"US",
    "sg:address":"439 Main St",
    "sg:city":"Hazard",
    "sg:classifiers":[
        {
            "category":"Shopping",
            "subcategory":"Stationery & Office Supplies",
            "type":"Retail Goods"
        }
    ],
    "sg:phone":"+1 606 439 2233",
    "sg:postcode":"41701",
    "sg:province":"KY",
    "sg:tags":[
        "equipment"
    ],
    "sg:website":"http://wb003.britlink.com/bl5/areaofficesupply",
    "wof:name":"Area Office Supply Inc",
    "wof:placetype":"venue"
},
  "geometry": {"coordinates":[-83.196094,37.249509],"type":"Point"}
}