{
  "type": "Feature",
  "properties": {
    "addr:full":"9340 Ogden Landing Rd West Paducah KY 42086",
    "addr:housenumber":"9340",
    "addr:postcode":"42086",
    "addr:street":"Ogden Landing Rd",
    "iso:country":"US",
    "sg:address":"9340 Ogden Landing Rd",
    "sg:city":"West Paducah",
    "sg:classifiers":[
        {
            "category":"Government",
            "subcategory":"Office",
            "type":"Public Place"
        }
    ],
    "sg:phone":"+1 270 488 2513",
    "sg:postcode":"42086",
    "sg:province":"KY",
    "sg:tags":[
        "national",
        "security"
    ],
    "wof:name":"Emergncy Response Unitkentucky",
    "wof:placetype":"venue"
},
  "geometry": {"coordinates":[-88.78115099999999,37.107288],"type":"Point"}
}