{
  "type": "Feature",
  "properties": {
    "iso:country":"US",
    "sg:address":"905 Fairdale Rd",
    "sg:city":"Fairdale",
    "sg:classifiers":[
        {
            "category":"Social Services",
            "subcategory":"Child Care",
            "type":"Services"
        }
    ],
    "sg:phone":"+1 502 366 6611",
    "sg:postcode":"40118",
    "sg:province":"KY",
    "wof:name":"Fairdale Daycare Ctr",
    "wof:placetype":"venue"
},
  "geometry": {"coordinates":[-85.754537,38.107849],"type":"Point"}
}