{
  "type": "Feature",
  "properties": {
    "iso:country":"US",
    "sg:address":"401 S Jefferson St",
    "sg:city":"Princeton",
    "sg:classifiers":[
        {
            "category":"Health Services",
            "subcategory":"Doctor",
            "type":"Services"
        }
    ],
    "sg:phone":"+1 270 365 7588",
    "sg:postcode":"42445",
    "sg:province":"KY",
    "sg:tags":[
        "clinic"
    ],
    "wof:name":"Caldwell County Dialysis Clnc",
    "wof:placetype":"venue"
},
  "geometry": {"coordinates":[-87.88489199999999,37.104479],"type":"Point"}
}