{
  "type": "Feature",
  "properties": {
    "iso:country":"US",
    "sg:address":"1950 Pondsville Rd",
    "sg:city":"Smiths Grove",
    "sg:classifiers":[
        {
            "category":"Building & Trades",
            "subcategory":"Construction",
            "type":"Services"
        }
    ],
    "sg:phone":"+1 270 563 4571",
    "sg:postcode":"42171",
    "sg:province":"KY",
    "sg:tags":[
        "house"
    ],
    "wof:name":"Todd Lawrence Construction",
    "wof:placetype":"venue"
},
  "geometry": {"coordinates":[-86.15140599999999,36.998896],"type":"Point"}
}