{
  "type": "Feature",
  "properties": {
    "iso:country":"US",
    "sg:address":"242 Helena Dr",
    "sg:city":"Mount Sterling",
    "sg:classifiers":[
        {
            "category":"Retail",
            "subcategory":"Repair Shop",
            "type":"Services"
        }
    ],
    "sg:phone":"+1 859 585 2556",
    "sg:postcode":"40353",
    "sg:province":"KY",
    "wof:name":"McKinley Co",
    "wof:placetype":"venue"
},
  "geometry": {"coordinates":[-83.969651,38.035395],"type":"Point"}
}