{
  "type": "Feature",
  "properties": {
    "iso:country":"US",
    "sg:address":"1009 Hustonville Rd",
    "sg:city":"Danville",
    "sg:classifiers":[
        {
            "category":"Utilities",
            "subcategory":"Electric",
            "type":"Services"
        }
    ],
    "sg:phone":"+1 859 236 4561",
    "sg:postcode":"40422",
    "sg:province":"KY",
    "sg:tags":[
        "company"
    ],
    "sg:website":"www.intercountyenergy.net",
    "wof:name":"INTER-County Energy",
    "wof:placetype":"venue"
},
  "geometry": {"coordinates":[-84.77489799999999,37.629859],"type":"Point"}
}