{
  "type": "Feature",
  "properties": {
    "iso:country":"US",
    "sg:address":"1009 Paris Rd",
    "sg:city":"Mayfield",
    "sg:classifiers":[
        {
            "category":"Autos & Motor Vehicles",
            "subcategory":"Fuel & Gas Station",
            "type":"Retail Goods"
        }
    ],
    "sg:phone":"+1 270 247 9621",
    "sg:postcode":"42066",
    "sg:province":"KY",
    "sg:tags":[
        "oil"
    ],
    "wof:name":"Pocket's Shell Food Mart",
    "wof:placetype":"venue"
},
  "geometry": {"coordinates":[-88.63097500000001,36.728611],"type":"Point"}
}