{
  "type": "Feature",
  "properties": {
    "iso:country":"US",
    "sg:address":"1350 Harp Innis Rd",
    "sg:city":"Lexington",
    "sg:classifiers":[
        {
            "category":"Retail",
            "subcategory":"Animal Services",
            "type":"Services"
        }
    ],
    "sg:phone":"+1 859 299 9311",
    "sg:postcode":"40511",
    "sg:province":"KY",
    "sg:tags":[
        "breeder",
        "horse"
    ],
    "wof:name":"Highclere",
    "wof:placetype":"venue"
},
  "geometry": {"coordinates":[-84.39788299999999,38.149633],"type":"Point"}
}