{
  "type": "Feature",
  "properties": {
    "iso:country":"US",
    "sg:address":"5310 Morgantown Rd",
    "sg:city":"Bowling Green",
    "sg:classifiers":[
        {
            "category":"Travel",
            "subcategory":"Hotels & Motels",
            "type":"Entertainment"
        }
    ],
    "sg:phone":"+1 270 843 4846",
    "sg:postcode":"42101",
    "sg:province":"KY",
    "sg:tags":[
        "breakfast",
        "accommodation",
        "bed"
    ],
    "wof:name":"Alpine Lodge",
    "wof:placetype":"venue"
},
  "geometry": {"coordinates":[-86.536484,36.996092],"type":"Point"}
}