{
  "type": "Feature",
  "properties": {
    "addr:full":"4000 Dixie Hwy Louisville KY 40216",
    "addr:housenumber":"4000",
    "addr:postcode":"40216",
    "addr:street":"Dixie Hwy",
    "iso:country":"US",
    "sg:address":"4000 Dixie Hwy",
    "sg:city":"Louisville",
    "sg:phone":"+1 502 448 4334",
    "sg:postcode":"40216",
    "sg:province":"KY",
    "sg:website":"http://www.penn-station.com",
    "wof:name":"Penn Station",
    "wof:placetype":"venue"
},
  "geometry": {"coordinates":[-85.80802199999999,38.192039],"type":"Point"}
}