{
  "type": "Feature",
  "properties": {
    "iso:country":"US",
    "sg:address":"1639 Tyler Pkwy",
    "sg:city":"Louisville",
    "sg:classifiers":[
        {
            "category":"Building & Trades",
            "subcategory":"Construction",
            "type":"Services"
        }
    ],
    "sg:phone":"+1 502 458 9759",
    "sg:postcode":"40204",
    "sg:province":"KY",
    "sg:tags":[
        "general",
        "contractor"
    ],
    "wof:name":"Hopkins Interior Constr Inc",
    "wof:placetype":"venue"
},
  "geometry": {"coordinates":[-85.712739,38.233418],"type":"Point"}
}