{
  "type": "Feature",
  "properties": {
    "addr:full":"2379 Burkesville Rd Glasgow KY 42141",
    "addr:housenumber":"2379",
    "addr:postcode":"42141",
    "addr:street":"Burkesville Rd",
    "iso:country":"US",
    "sg:address":"2379 Burkesville Rd",
    "sg:city":"Glasgow",
    "sg:classifiers":[
        {
            "category":"Home & Garden",
            "subcategory":"Building Materials",
            "type":"Retail Goods"
        }
    ],
    "sg:phone":"+1 270 651 5321",
    "sg:postcode":"42141",
    "sg:province":"KY",
    "sg:tags":[
        "door"
    ],
    "wof:name":"Barren County Glass Co Inc",
    "wof:placetype":"venue"
},
  "geometry": {"coordinates":[-85.88203,36.969346],"type":"Point"}
}