{
  "type": "Feature",
  "properties": {
    "addr:full":"1111 Dixie Hwy S Elizabethtown KY 42701",
    "addr:housenumber":"1111",
    "addr:postcode":"42701",
    "addr:street":"Dixie Hwy S",
    "iso:country":"US",
    "sg:address":"1111 Dixie Hwy S",
    "sg:city":"Elizabethtown",
    "sg:classifiers":[
        {
            "category":"Shopping",
            "subcategory":"Bicycles & Sporting Goods",
            "type":"Retail Goods"
        }
    ],
    "sg:phone":"+1 270 763 8274",
    "sg:postcode":"42701",
    "sg:province":"KY",
    "sg:tags":[
        "equipment",
        "skateboard"
    ],
    "wof:name":"Sparky's Skate Shop",
    "wof:placetype":"venue"
},
  "geometry": {"coordinates":[-85.877658,37.714648],"type":"Point"}
}