{
  "type": "Feature",
  "properties": {
    "iso:country":"US",
    "sg:address":"3813 Dixie Hwy",
    "sg:city":"Elsmere",
    "sg:classifiers":[
        {
            "category":"Organizations",
            "subcategory":"Religious Organization",
            "type":"Services"
        }
    ],
    "sg:phone":"+1 859 727 2035",
    "sg:postcode":"41018",
    "sg:province":"KY",
    "sg:tags":[
        "church"
    ],
    "sg:website":"www.sthenryel.com",
    "wof:name":"St Henry Church",
    "wof:placetype":"venue"
},
  "geometry": {"coordinates":[-84.604975,39.013872],"type":"Point"}
}