{
  "type": "Feature",
  "properties": {
    "iso:country":"US",
    "sg:address":"4851 Old Richmond Rd",
    "sg:city":"Lexington",
    "sg:classifiers":[
        {
            "category":"Farming",
            "subcategory":"Farm",
            "type":"Manufacturing & Wholesale Goods"
        }
    ],
    "sg:phone":"+1 859 264 1461",
    "sg:postcode":"40515",
    "sg:province":"KY",
    "wof:name":"Woods Edge Farm",
    "wof:placetype":"venue"
},
  "geometry": {"coordinates":[-84.412976,37.952969],"type":"Point"}
}