{
  "type": "Feature",
  "properties": {
    "iso:country":"US",
    "sg:address":"1401 Cold Spring Rd",
    "sg:city":"Louisville",
    "sg:classifiers":[
        {
            "category":"Home & Garden",
            "subcategory":"Building Materials",
            "type":"Retail Goods"
        }
    ],
    "sg:phone":"+1 502 767 4761",
    "sg:postcode":"40223",
    "sg:province":"KY",
    "sg:tags":[
        "plywood",
        "veneer"
    ],
    "wof:name":"Oakleaf Veneer Inc",
    "wof:placetype":"venue"
},
  "geometry": {"coordinates":[-85.529246,38.265443],"type":"Point"}
}