{
  "type": "Feature",
  "properties": {
    "iso:country":"US",
    "sg:address":"3035 Preston Hwy",
    "sg:city":"Louisville",
    "sg:classifiers":[
        {
            "category":"Deli",
            "type":"Food & Drink"
        },
        {
            "category":"Restaurant",
            "type":"Food & Drink"
        },
        {
            "category":"Food & Beverages",
            "subcategory":"Groceries & Convenience Stores",
            "type":"Retail Goods"
        }
    ],
    "sg:phone":"+1 502 634 5656",
    "sg:postcode":"40217",
    "sg:province":"KY",
    "sg:tags":[
        "shop",
        "delicatessen",
        "sandwich"
    ],
    "wof:name":"Penn Station",
    "wof:placetype":"venue"
},
  "geometry": {"coordinates":[-85.736684,38.205517],"type":"Point"}
}