{
  "type": "Feature",
  "properties": {
    "iso:country":"US",
    "sg:address":"1718 Franklin Ave",
    "sg:city":"Henderson",
    "sg:classifiers":[
        {
            "category":"Professional",
            "subcategory":"Business Services",
            "type":"Services"
        }
    ],
    "sg:phone":"+1 270 826 7171",
    "sg:postcode":"42420",
    "sg:province":"KY",
    "sg:tags":[
        "appraiser"
    ],
    "wof:name":"Fryer Realty Auction & Apprsls",
    "wof:placetype":"venue"
},
  "geometry": {"coordinates":[-87.570832,37.829393],"type":"Point"}
}