{
  "type": "Feature",
  "properties": {
    "iso:country":"US",
    "sg:address":"10845 Bluegrass Pkwy",
    "sg:city":"Louisville",
    "sg:classifiers":[
        {
            "category":"Health Services",
            "subcategory":"Medical Lab",
            "type":"Services"
        }
    ],
    "sg:phone":"+1 502 266 6617",
    "sg:postcode":"40299",
    "sg:province":"KY",
    "sg:tags":[
        "laboratory"
    ],
    "wof:name":"Yates Crown & Bridge Dental",
    "wof:placetype":"venue"
},
  "geometry": {"coordinates":[-85.553815,38.221346],"type":"Point"}
}