{
  "type": "Feature",
  "properties": {
    "iso:country":"US",
    "sg:address":"3690 State Hwy 1380",
    "sg:city":"Central City",
    "sg:classifiers":[
        {
            "category":"Government",
            "subcategory":"Office",
            "type":"Public Place"
        }
    ],
    "sg:phone":"+1 270 338 3124",
    "sg:postcode":"42330",
    "sg:province":"KY",
    "wof:name":"Muhlenberg UK Extension Ofc",
    "wof:placetype":"venue"
},
  "geometry": {"coordinates":[-87.122377,37.219555],"type":"Point"}
}