{
  "type": "Feature",
  "properties": {
    "iso:country":"US",
    "sg:address":"907 Barret Ave",
    "sg:city":"Louisville",
    "sg:classifiers":[
        {
            "category":"Professional",
            "subcategory":"Management & Consulting",
            "type":"Services"
        }
    ],
    "sg:phone":"+1 502 583 8222",
    "sg:postcode":"40204",
    "sg:province":"KY",
    "sg:tags":[
        "consultant"
    ],
    "sg:website":"http://www.mckinneyspeakers.com",
    "wof:name":"Mckinney Associates, Inc.",
    "wof:placetype":"venue"
},
  "geometry": {"coordinates":[-85.730993,38.240073],"type":"Point"}
}