{
  "type": "Feature",
  "properties": {
    "addr:full":"227 Saint Ann St Owensboro KY 42303",
    "addr:housenumber":"227",
    "addr:postcode":"42303",
    "addr:street":"Saint Ann St",
    "iso:country":"US",
    "sg:address":"227 Saint Ann St",
    "sg:city":"Owensboro",
    "sg:classifiers":[
        {
            "category":"Professional",
            "subcategory":"Computer Services",
            "type":"Services"
        }
    ],
    "sg:phone":"+1 270 691 1121",
    "sg:postcode":"42303",
    "sg:province":"KY",
    "sg:website":"www.tcserve.com",
    "wof:name":"Technical Computer Svc",
    "wof:placetype":"venue"
},
  "geometry": {"coordinates":[-87.11220400000001,37.774015],"type":"Point"}
}