{
  "type": "Feature",
  "properties": {
    "iso:country":"US",
    "sg:address":"458 Lexington Rd",
    "sg:city":"Versailles",
    "sg:classifiers":[
        {
            "category":"Restaurant",
            "type":"Food & Drink"
        }
    ],
    "sg:menulink":"http://www.allmenus.com/ky/versailles/120744-subway/menu/",
    "sg:phone":"+1 859 873 1040",
    "sg:postcode":"40383",
    "sg:province":"KY",
    "sg:tags":[
        "american",
        "sandwich"
    ],
    "wof:name":"Subway",
    "wof:placetype":"venue"
},
  "geometry": {"coordinates":[-84.716992,38.051272],"type":"Point"}
}