{
  "type": "Feature",
  "properties": {
    "iso:country":"US",
    "sg:address":"13909 Aiken Rd",
    "sg:city":"Louisville",
    "sg:classifiers":[
        {
            "category":"Home & Garden",
            "subcategory":"Garden Supply",
            "type":"Retail Goods"
        }
    ],
    "sg:phone":"+1 502 245 0465",
    "sg:postcode":"40245",
    "sg:province":"KY",
    "sg:tags":[
        "landscaping",
        "equipment"
    ],
    "wof:name":"John Deere Landscapes",
    "wof:placetype":"venue"
},
  "geometry": {"coordinates":[-85.487025,38.26631],"type":"Point"}
}