{
  "type": "Feature",
  "properties": {
    "addr:full":"200 Poplar St Murray KY 42071",
    "addr:housenumber":"200",
    "addr:postcode":"42071",
    "addr:street":"Poplar St",
    "iso:country":"US",
    "sg:address":"200 Poplar St",
    "sg:city":"Murray",
    "sg:classifiers":[
        {
            "category":"Professional",
            "subcategory":"Business Services",
            "type":"Services"
        }
    ],
    "sg:phone":"+1 270 753 6361",
    "sg:postcode":"42071",
    "sg:province":"KY",
    "sg:tags":[
        "interior",
        "consultant",
        "design",
        "decorator"
    ],
    "wof:name":"Reed Interiors",
    "wof:placetype":"venue"
},
  "geometry": {"coordinates":[-88.300358,36.608677],"type":"Point"}
}