{
  "type": "Feature",
  "properties": {
    "addr:full":"429 Massey Rd Bowling Green KY 42101",
    "addr:housenumber":"429",
    "addr:postcode":"42101",
    "addr:street":"Massey Rd",
    "iso:country":"US",
    "sg:address":"429 Massey Rd",
    "sg:city":"Bowling Green",
    "sg:classifiers":[
        {
            "category":"Building & Trades",
            "subcategory":"Construction",
            "type":"Services"
        }
    ],
    "sg:phone":"+1 270 842 5567",
    "sg:postcode":"42101",
    "sg:province":"KY",
    "sg:tags":[
        "roofing",
        "contractor"
    ],
    "wof:name":"James J Burch",
    "wof:placetype":"venue"
},
  "geometry": {"coordinates":[-86.407084,37.048805],"type":"Point"}
}