{
  "type": "Feature",
  "properties": {
    "iso:country":"US",
    "sg:address":"2611 Louisa St",
    "sg:city":"Catlettsburg",
    "sg:classifiers":[
        {
            "category":"Building & Trades",
            "subcategory":"Construction",
            "type":"Services"
        }
    ],
    "sg:phone":"+1 606 739 6575",
    "sg:postcode":"41129",
    "sg:province":"KY",
    "sg:tags":[
        "tile",
        "dealer"
    ],
    "wof:name":"Michael Conley Inc",
    "wof:placetype":"venue"
},
  "geometry": {"coordinates":[-82.597449,38.417106],"type":"Point"}
}