{
  "type": "Feature",
  "properties": {
    "iso:country":"US",
    "sg:address":"201 E Main St",
    "sg:city":"Springfield",
    "sg:classifiers":[
        {
            "category":"Organizations",
            "subcategory":"Religious Organization",
            "type":"Services"
        }
    ],
    "sg:phone":"+1 859 336 7457",
    "sg:postcode":"40069",
    "sg:province":"KY",
    "sg:tags":[
        "church"
    ],
    "wof:name":"Springfield Christian Church",
    "wof:placetype":"venue"
},
  "geometry": {"coordinates":[-85.22053,37.684672],"type":"Point"}
}