{
  "type": "Feature",
  "properties": {
    "addr:full":"2508 Preston Hwy Louisville KY 40217",
    "addr:housenumber":"2508",
    "addr:postcode":"40217",
    "addr:street":"Preston Hwy",
    "iso:country":"US",
    "sg:address":"2508 Preston Hwy",
    "sg:city":"Louisville",
    "sg:classifiers":[
        {
            "category":"Restaurant",
            "type":"Food & Drink"
        }
    ],
    "sg:phone":"+1 502 634 8322",
    "sg:postcode":"40217",
    "sg:province":"KY",
    "wof:name":"Pizza Hut",
    "wof:placetype":"venue"
},
  "geometry": {"coordinates":[-85.741153,38.212348],"type":"Point"}
}