{
  "type": "Feature",
  "properties": {
    "iso:country":"US",
    "sg:address":"114 S Main St",
    "sg:city":"Versailles",
    "sg:classifiers":[
        {
            "category":"Mining & Drilling",
            "type":"Manufacturing & Wholesale Goods"
        }
    ],
    "sg:phone":"+1 859 258 9595",
    "sg:postcode":"40383",
    "sg:province":"KY",
    "sg:tags":[
        "coal",
        "shipping"
    ],
    "wof:name":"Coal Combustion",
    "wof:placetype":"venue"
},
  "geometry": {"coordinates":[-84.730271,38.052687],"type":"Point"}
}