{
  "type": "Feature",
  "properties": {
    "iso:country":"US",
    "sg:address":"577 Clay Ridge Rd",
    "sg:city":"Alexandria",
    "sg:classifiers":[
        {
            "category":"Retail",
            "subcategory":"Repair Shop",
            "type":"Services"
        }
    ],
    "sg:phone":"+1 859 635 3547",
    "sg:postcode":"41001",
    "sg:province":"KY",
    "wof:name":"Barnwells Upholstery",
    "wof:placetype":"venue"
},
  "geometry": {"coordinates":[-84.418657,38.840278],"type":"Point"}
}