{
  "type": "Feature",
  "properties": {
    "iso:country":"US",
    "sg:address":"1301 Winchester Rd",
    "sg:city":"Lexington",
    "sg:classifiers":[
        {
            "category":"Professional",
            "subcategory":"Accounting & Tax Preparation",
            "type":"Services"
        }
    ],
    "sg:phone":"+1 859 381 1040",
    "sg:postcode":"40505",
    "sg:province":"KY",
    "sg:tags":[
        "return",
        "filing"
    ],
    "wof:name":"Liberty Tax Svc",
    "wof:placetype":"venue"
},
  "geometry": {"coordinates":[-84.456604,38.042972],"type":"Point"}
}