{
  "type": "Feature",
  "properties": {
    "iso:country":"US",
    "sg:address":"2750 7th Street Rd",
    "sg:city":"Louisville",
    "sg:classifiers":[
        {
            "category":"Sports & Exercise",
            "subcategory":"Bowling",
            "type":"Entertainment"
        }
    ],
    "sg:phone":"+1 502 634 8371",
    "sg:postcode":"40215",
    "sg:province":"KY",
    "sg:tags":[
        "center"
    ],
    "wof:name":"Fellowship Lanes",
    "wof:placetype":"venue"
},
  "geometry": {"coordinates":[-85.78560899999999,38.211963],"type":"Point"}
}