{
  "type": "Feature",
  "properties": {
    "iso:country":"US",
    "sg:address":"240 Boone Ave",
    "sg:city":"Winchester",
    "sg:classifiers":[
        {
            "category":"Wholesale",
            "subcategory":"Computers",
            "type":"Manufacturing & Wholesale Goods"
        }
    ],
    "sg:phone":"+1 859 737 2244",
    "sg:postcode":"40391",
    "sg:province":"KY",
    "wof:name":"Craig Gorham",
    "wof:placetype":"venue"
},
  "geometry": {"coordinates":[-84.18382800000001,37.988504],"type":"Point"}
}