{
  "type": "Feature",
  "properties": {
    "iso:country":"US",
    "sg:address":"10642 Dixie Hwy",
    "sg:city":"Louisville",
    "sg:classifiers":[
        {
            "category":"Professional",
            "subcategory":"Business Services",
            "type":"Services"
        },
        {
            "category":"Government",
            "subcategory":"Post Office",
            "type":"Public Place"
        }
    ],
    "sg:phone":"+1 800 275 8777",
    "sg:postcode":"40272",
    "sg:province":"KY",
    "sg:tags":[
        "mail",
        "shipping"
    ],
    "sg:website":"http://www.usps.com",
    "wof:name":"USPS - United States Post Office - Valley Station Branch",
    "wof:placetype":"venue"
},
  "geometry": {"coordinates":[-85.871393,38.099933],"type":"Point"}
}