{
  "type": "Feature",
  "properties": {
    "iso:country":"US",
    "sg:address":"515 S 3rd St",
    "sg:city":"Louisville",
    "sg:classifiers":[
        {
            "category":"Communications",
            "subcategory":"Radio Station",
            "type":"Services"
        }
    ],
    "sg:phone":"+1 502 571 1240",
    "sg:postcode":"40202",
    "sg:province":"KY",
    "sg:tags":[
        "broadcast"
    ],
    "wof:name":"W LLV Radio 1240",
    "wof:placetype":"venue"
},
  "geometry": {"coordinates":[-85.755993,38.250025],"type":"Point"}
}