{
  "type": "Feature",
  "properties": {
    "iso:country":"US",
    "sg:address":"11400 Decimal Dr",
    "sg:city":"Louisville",
    "sg:classifiers":[
        {
            "category":"Shopping",
            "subcategory":"Computers & Home Electronics",
            "type":"Retail Goods"
        }
    ],
    "sg:phone":"+1 502 266 9201",
    "sg:postcode":"40299",
    "sg:province":"KY",
    "sg:tags":[
        "parts",
        "supply"
    ],
    "wof:name":"MCPC",
    "wof:placetype":"venue"
},
  "geometry": {"coordinates":[-85.550326,38.217022],"type":"Point"}
}