{
  "type": "Feature",
  "properties": {
    "addr:full":"2330 Gardnersville Rd Crittenden KY 41030",
    "addr:housenumber":"2330",
    "addr:postcode":"41030",
    "addr:street":"Gardnersville Rd",
    "iso:country":"US",
    "sg:address":"2330 Gardnersville Rd",
    "sg:city":"Crittenden",
    "sg:phone":"+1 859 428 2421",
    "sg:postcode":"41030",
    "sg:province":"KY",
    "sg:tags":[
        "farm",
        "tobacco"
    ],
    "wof:name":"Spillman Farms",
    "wof:placetype":"venue"
},
  "geometry": {"coordinates":[-84.556815,38.775426],"type":"Point"}
}