{
  "type": "Feature",
  "properties": {
    "iso:country":"US",
    "sg:address":"430 28th St",
    "sg:city":"Ashland",
    "sg:classifiers":[
        {
            "category":"Government",
            "subcategory":"Office",
            "type":"Public Place"
        }
    ],
    "sg:phone":"+1 606 327 2039",
    "sg:postcode":"41101",
    "sg:province":"KY",
    "sg:tags":[
        "village"
    ],
    "wof:name":"Ashland Sewer Maintenance",
    "wof:placetype":"venue"
},
  "geometry": {"coordinates":[-82.625871,38.469794],"type":"Point"}
}