{
  "type": "Feature",
  "properties": {
    "addr:full":"511 Garden Ct Simpsonville KY 40067",
    "addr:housenumber":"511",
    "addr:postcode":"40067",
    "addr:street":"Garden Ct",
    "iso:country":"US",
    "sg:address":"511 Garden Ct",
    "sg:city":"Simpsonville",
    "sg:classifiers":[
        {
            "category":"Building & Trades",
            "subcategory":"Landscaping Services",
            "type":"Services"
        }
    ],
    "sg:phone":"+1 502 722 0302",
    "sg:postcode":"40067",
    "sg:province":"KY",
    "sg:tags":[
        "landscape"
    ],
    "wof:name":"Green Thumz LLC",
    "wof:placetype":"venue"
},
  "geometry": {"coordinates":[-85.355165,38.218432],"type":"Point"}
}