{
  "type": "Feature",
  "properties": {
    "addr:full":"601 Sego Rd Mt Eden KY 40046",
    "addr:housenumber":"601",
    "addr:postcode":"40046",
    "addr:street":"Sego Rd",
    "iso:country":"US",
    "sg:address":"601 Sego Rd",
    "sg:city":"Mt Eden",
    "sg:classifiers":[
        {
            "category":"Building & Trades",
            "subcategory":"Construction",
            "type":"Services"
        }
    ],
    "sg:phone":"+1 502 477 5952",
    "sg:postcode":"40046",
    "sg:province":"KY",
    "sg:tags":[
        "concrete",
        "contractor"
    ],
    "wof:name":"Murphy Concrete Constr Inc",
    "wof:placetype":"venue"
},
  "geometry": {"coordinates":[-85.211315,38.030035],"type":"Point"}
}