{
  "type": "Feature",
  "properties": {
    "iso:country":"US",
    "sg:address":"113 Willow Ln",
    "sg:city":"Georgetown",
    "sg:classifiers":[
        {
            "category":"Sports & Exercise",
            "subcategory":"Bowling",
            "type":"Entertainment"
        }
    ],
    "sg:phone":"+1 502 867 4808",
    "sg:postcode":"40324",
    "sg:province":"KY",
    "sg:tags":[
        "center"
    ],
    "wof:name":"Lanes Run Properties LLC",
    "wof:placetype":"venue"
},
  "geometry": {"coordinates":[-84.580853,38.199736],"type":"Point"}
}