{
  "type": "Feature",
  "properties": {
    "iso:country":"US",
    "sg:address":"113 Plaza Dr",
    "sg:city":"Bardstown",
    "sg:classifiers":[
        {
            "category":"Professional",
            "type":"Services"
        }
    ],
    "sg:phone":"+1 502 348 1437",
    "sg:postcode":"40004",
    "sg:province":"KY",
    "sg:tags":[
        "establishment"
    ],
    "wof:name":"Tri-Step Of Kentucky Inc",
    "wof:placetype":"venue"
},
  "geometry": {"coordinates":[-85.450653,37.806373],"type":"Point"}
}