{
  "type": "Feature",
  "properties": {
    "iso:country":"US",
    "sg:address":"5915 Bay Pine Dr",
    "sg:city":"Louisville",
    "sg:classifiers":[
        {
            "category":"Building & Trades",
            "subcategory":"Construction",
            "type":"Services"
        }
    ],
    "sg:phone":"+1 502 966 8623",
    "sg:postcode":"40219",
    "sg:province":"KY",
    "sg:tags":[
        "contractor"
    ],
    "wof:name":"Djs Pool Installation",
    "wof:placetype":"venue"
},
  "geometry": {"coordinates":[-85.650361,38.130481],"type":"Point"}
}