{
  "type": "Feature",
  "properties": {
    "addr:full":"1350 Clay St Hartford KY 42347",
    "addr:housenumber":"1350",
    "addr:postcode":"42347",
    "addr:street":"Clay St",
    "iso:country":"US",
    "sg:address":"1350 Clay St",
    "sg:city":"Hartford",
    "sg:classifiers":[
        {
            "category":"Organizations",
            "subcategory":"Professional Association",
            "type":"Services"
        }
    ],
    "sg:phone":"+1 270 298 3551",
    "sg:postcode":"42347",
    "sg:province":"KY",
    "sg:tags":[
        "chambers",
        "commerce"
    ],
    "wof:name":"Chamber Of Commerce",
    "wof:placetype":"venue"
},
  "geometry": {"coordinates":[-86.891497,37.450149],"type":"Point"}
}