{
  "type": "Feature",
  "properties": {
    "iso:country":"US",
    "sg:address":"1831 Falls of Rough Rd",
    "sg:city":"Caneyville",
    "sg:classifiers":[
        {
            "category":"Autos & Motor Vehicles",
            "subcategory":"Automobile Sales",
            "type":"Retail Goods"
        }
    ],
    "sg:phone":"+1 270 879 0228",
    "sg:postcode":"42721",
    "sg:province":"KY",
    "sg:tags":[
        "car",
        "dealer"
    ],
    "wof:name":"Highway 79 Auto Sales & Slvg",
    "wof:placetype":"venue"
},
  "geometry": {"coordinates":[-86.48643,37.449096],"type":"Point"}
}