{
  "type": "Feature",
  "properties": {
    "iso:country":"US",
    "sg:address":"314 Albany Rd",
    "sg:city":"Monticello",
    "sg:classifiers":[
        {
            "category":"Education",
            "subcategory":"School",
            "type":"Public Place"
        }
    ],
    "sg:phone":"+1 606 348 6691",
    "sg:postcode":"42633",
    "sg:province":"KY",
    "wof:name":"A J Lloyd Middle School",
    "wof:placetype":"venue"
},
  "geometry": {"coordinates":[-84.85781299999999,36.825621],"type":"Point"}
}