{
  "type": "Feature",
  "properties": {
    "iso:country":"US",
    "sg:address":"620 Paige Ct",
    "sg:city":"Versailles",
    "sg:classifiers":[
        {
            "category":"Building & Trades",
            "subcategory":"Plumbing",
            "type":"Services"
        }
    ],
    "sg:phone":"+1 859 873 9861",
    "sg:postcode":"40383",
    "sg:province":"KY",
    "sg:tags":[
        "conditioning",
        "air",
        "system",
        "contractor"
    ],
    "wof:name":"Roberts Refrigeration",
    "wof:placetype":"venue"
},
  "geometry": {"coordinates":[-84.736064,38.069466],"type":"Point"}
}