{
  "type": "Feature",
  "properties": {
    "iso:country":"US",
    "sg:address":"2765 Onton Rd",
    "sg:city":"Slaughters",
    "sg:classifiers":[
        {
            "category":"Farming",
            "subcategory":"Farm",
            "type":"Manufacturing & Wholesale Goods"
        }
    ],
    "sg:phone":"+1 270 884 7500",
    "sg:postcode":"42456",
    "sg:province":"KY",
    "sg:tags":[
        "crop",
        "general"
    ],
    "wof:name":"Underwood Farms",
    "wof:placetype":"venue"
},
  "geometry": {"coordinates":[-87.40490200000001,37.529236],"type":"Point"}
}