{
  "type": "Feature",
  "properties": {
    "addr:full":"222 Langdon St Somerset KY 42501",
    "addr:housenumber":"222",
    "addr:postcode":"42501",
    "addr:street":"Langdon St",
    "iso:country":"US",
    "sg:address":"222 Langdon St",
    "sg:city":"Somerset",
    "sg:classifiers":[
        {
            "category":"Education",
            "subcategory":"School",
            "type":"Public Place"
        }
    ],
    "sg:phone":"+1 606 678 4100",
    "sg:postcode":"42501",
    "sg:province":"KY",
    "sg:website":"www.pulaski.net",
    "wof:name":"Pulaski Memorial School",
    "wof:placetype":"venue"
},
  "geometry": {"coordinates":[-84.613844,37.085207],"type":"Point"}
}