{
  "type": "Feature",
  "properties": {
    "addr:full":"809 N 12th St Murray KY 42071",
    "addr:housenumber":"809",
    "addr:postcode":"42071",
    "addr:street":"N 12Th St",
    "iso:country":"US",
    "sg:address":"809 N 12th St",
    "sg:city":"Murray",
    "sg:classifiers":[
        {
            "category":"Professional",
            "subcategory":"Accounting & Tax Preparation",
            "type":"Services"
        }
    ],
    "sg:phone":"+1 270 762 0792",
    "sg:postcode":"42071",
    "sg:province":"KY",
    "sg:tags":[
        "return",
        "filing"
    ],
    "wof:name":"Jackson Hewitt Tax Svc",
    "wof:placetype":"venue"
},
  "geometry": {"coordinates":[-88.31424199999999,36.627122],"type":"Point"}
}