{
  "type": "Feature",
  "properties": {
    "iso:country":"US",
    "sg:address":"700 Marquette Dr",
    "sg:city":"Louisville",
    "sg:classifiers":[
        {
            "category":"Professional",
            "subcategory":"Management & Consulting",
            "type":"Services"
        }
    ],
    "sg:phone":"+1 502 425 0566",
    "sg:postcode":"40222",
    "sg:province":"KY",
    "sg:tags":[
        "consultant",
        "educational"
    ],
    "wof:name":"Resources For Better Living",
    "wof:placetype":"venue"
},
  "geometry": {"coordinates":[-85.621155,38.259575],"type":"Point"}
}