{
  "type": "Feature",
  "properties": {
    "iso:country":"US",
    "sg:address":"240 Plaza Dr",
    "sg:city":"Lexington",
    "sg:classifiers":[
        {
            "category":"Organizations",
            "subcategory":"Religious Organization",
            "type":"Services"
        }
    ],
    "sg:phone":"+1 859 278 2014",
    "sg:postcode":"40503",
    "sg:province":"KY",
    "sg:tags":[
        "church"
    ],
    "wof:name":"Oak Grove Covenant Church",
    "wof:placetype":"venue"
},
  "geometry": {"coordinates":[-84.520651,38.014185],"type":"Point"}
}