{
  "type": "Feature",
  "properties": {
    "iso:country":"US",
    "sg:address":"800 Louisville Rd",
    "sg:city":"Frankfort",
    "sg:classifiers":[
        {
            "category":"Recreation",
            "type":"Entertainment"
        }
    ],
    "sg:phone":"+1 502 875 8579",
    "sg:postcode":"40601",
    "sg:province":"KY",
    "sg:tags":[
        "pool",
        "swimming"
    ],
    "wof:name":"Juniper Hills Swimming Pool",
    "wof:placetype":"venue"
},
  "geometry": {"coordinates":[-84.88564599999999,38.18548],"type":"Point"}
}