{
  "type": "Feature",
  "properties": {
    "iso:country":"US",
    "sg:address":"304 Main St",
    "sg:city":"Murray",
    "sg:classifiers":[
        {
            "category":"Local Transit",
            "type":"Transportation"
        }
    ],
    "sg:phone":"+1 270 759 5000",
    "sg:postcode":"42071",
    "sg:province":"KY",
    "sg:tags":[
        "limousine"
    ],
    "wof:name":"Mr J's Limousine & Van Svc",
    "wof:placetype":"venue"
},
  "geometry": {"coordinates":[-88.30205599999999,36.610663],"type":"Point"}
}