{
  "type": "Feature",
  "properties": {
    "iso:country":"US",
    "sg:address":"110 N Main St",
    "sg:city":"Tompkinsville",
    "sg:classifiers":[
        {
            "category":"Health Services",
            "subcategory":"Doctor",
            "type":"Services"
        }
    ],
    "sg:phone":"+1 270 487 6263",
    "sg:postcode":"42167",
    "sg:province":"KY",
    "sg:tags":[
        "dentist"
    ],
    "wof:name":"Gordon W Mc Alpin DDS",
    "wof:placetype":"venue"
},
  "geometry": {"coordinates":[-85.692925,36.700535],"type":"Point"}
}