{
  "type": "Feature",
  "properties": {
    "iso:country":"US",
    "sg:address":"10501 State Hwy 582",
    "sg:city":"Kite",
    "sg:classifiers":[
        {
            "category":"Mining & Drilling",
            "type":"Manufacturing & Wholesale Goods"
        }
    ],
    "sg:phone":"+1 606 447 3037",
    "sg:postcode":"41828",
    "sg:province":"KY",
    "sg:tags":[
        "coal",
        "shipping"
    ],
    "wof:name":"Knott County Coal Corp",
    "wof:placetype":"venue"
},
  "geometry": {"coordinates":[-82.813225,37.291112],"type":"Point"}
}