{
  "type": "Feature",
  "properties": {
    "iso:country":"US",
    "sg:address":"124 Richmond Rd",
    "sg:city":"Manchester",
    "sg:classifiers":[
        {
            "category":"Shopping",
            "subcategory":"Florist",
            "type":"Retail Goods"
        }
    ],
    "sg:phone":"+1 606 598 2211",
    "sg:postcode":"40962",
    "sg:province":"KY",
    "wof:name":"Corum Flower Shop",
    "wof:placetype":"venue"
},
  "geometry": {"coordinates":[-83.763132,37.155102],"type":"Point"}
}