{
  "type": "Feature",
  "properties": {
    "iso:country":"US",
    "sg:address":"1001 Cornell Ct",
    "sg:city":"Crestwood",
    "sg:classifiers":[
        {
            "category":"Real Estate",
            "subcategory":"Real Estate Agent",
            "type":"Services"
        }
    ],
    "sg:phone":"+1 502 241 7741",
    "sg:postcode":"40014",
    "sg:province":"KY",
    "sg:tags":[
        "investment"
    ],
    "wof:name":"Purple Sage Inc",
    "wof:placetype":"venue"
},
  "geometry": {"coordinates":[-85.394553,38.355153],"type":"Point"}
}