{
  "type": "Feature",
  "properties": {
    "iso:country":"US",
    "sg:address":"812 Columbia Ave",
    "sg:city":"Glasgow",
    "sg:classifiers":[
        {
            "category":"Building & Trades",
            "subcategory":"Construction",
            "type":"Services"
        }
    ],
    "sg:phone":"+1 270 651 7271",
    "sg:postcode":"42141",
    "sg:province":"KY",
    "sg:tags":[
        "maker",
        "cabinet"
    ],
    "wof:name":"Wilson's Cabinet Shop",
    "wof:placetype":"venue"
},
  "geometry": {"coordinates":[-85.89757299999999,37.002495],"type":"Point"}
}