{
  "type": "Feature",
  "properties": {
    "addr:full":"1361 Dixie Hwy S Elizabethtown KY 42701",
    "addr:housenumber":"1361",
    "addr:postcode":"42701",
    "addr:street":"Dixie Hwy S",
    "iso:country":"US",
    "sg:address":"1361 Dixie Hwy S",
    "sg:city":"Elizabethtown",
    "sg:classifiers":[
        {
            "category":"Real Estate",
            "subcategory":"Real Estate Agent",
            "type":"Services"
        }
    ],
    "sg:phone":"+1 270 737 9819",
    "sg:postcode":"42701",
    "sg:province":"KY",
    "wof:name":"First Choice",
    "wof:placetype":"venue"
},
  "geometry": {"coordinates":[-85.880888,37.722099],"type":"Point"}
}