{
  "type": "Feature",
  "properties": {
    "iso:country":"US",
    "sg:address":"545 S Limestone St",
    "sg:city":"Lexington",
    "sg:classifiers":[
        {
            "category":"Manufacturing",
            "subcategory":"Printing",
            "type":"Manufacturing & Wholesale Goods"
        }
    ],
    "sg:phone":"+1 859 255 7030",
    "sg:postcode":"40508",
    "sg:province":"KY",
    "sg:tags":[
        "screen"
    ],
    "sg:website":"www.inkspotusa.com",
    "wof:name":"Inkspot Custom Printed T-Shirt",
    "wof:placetype":"venue"
},
  "geometry": {"coordinates":[-84.507229,38.038224],"type":"Point"}
}