{
  "type": "Feature",
  "properties": {
    "addr:full":"476 S Mayo Trl Pikeville KY 41501",
    "addr:housenumber":"476",
    "addr:postcode":"41501",
    "addr:street":"S Mayo Trl",
    "iso:country":"US",
    "sg:address":"476 S Mayo Trl",
    "sg:city":"Pikeville",
    "sg:classifiers":[
        {
            "category":"Restaurant",
            "type":"Food & Drink"
        }
    ],
    "sg:phone":"+1 606 433 0314",
    "sg:postcode":"41501",
    "sg:province":"KY",
    "wof:name":"Paul's Place",
    "wof:placetype":"venue"
},
  "geometry": {"coordinates":[-82.52790299999999,37.465664],"type":"Point"}
}