{
  "type": "Feature",
  "properties": {
    "iso:country":"US",
    "sg:address":"401 E Main St",
    "sg:city":"La Grange",
    "sg:classifiers":[
        {
            "category":"Recreation",
            "type":"Entertainment"
        }
    ],
    "sg:phone":"+1 502 212 2287",
    "sg:postcode":"40031",
    "sg:province":"KY",
    "sg:tags":[
        "club",
        "baseball"
    ],
    "wof:name":"Louisville Bats",
    "wof:placetype":"venue"
},
  "geometry": {"coordinates":[-85.374915,38.408425],"type":"Point"}
}