{
  "type": "Feature",
  "properties": {
    "iso:country":"US",
    "sg:address":"300 Fountain Ave",
    "sg:city":"Paducah",
    "sg:classifiers":[
        {
            "category":"Place Of Worship",
            "subcategory":"Church",
            "type":"Public Place"
        },
        {
            "category":"Place Of Worship",
            "type":"Public Place"
        }
    ],
    "sg:phone":"+1 270 443 1724",
    "sg:postcode":"42001",
    "sg:province":"KY",
    "sg:tags":[
        "churches-united",
        "methodist",
        "churches-methodist"
    ],
    "sg:website":"http://www.fountainaveumc.com",
    "wof:name":"Fountain Avenue United Methodist Church",
    "wof:placetype":"venue"
},
  "geometry": {"coordinates":[-88.618629,37.08091],"type":"Point"}
}