{
  "type": "Feature",
  "properties": {
    "iso:country":"US",
    "sg:address":"276 US Hwy 421",
    "sg:city":"Baxter",
    "sg:classifiers":[
        {
            "category":"Wholesale",
            "subcategory":"Toys & Hobbies",
            "type":"Manufacturing & Wholesale Goods"
        }
    ],
    "sg:phone":"+1 606 573 6424",
    "sg:postcode":"40806",
    "sg:province":"KY",
    "sg:tags":[
        "wholesaler"
    ],
    "wof:name":"Wholesale Furniture & More",
    "wof:placetype":"venue"
},
  "geometry": {"coordinates":[-83.323547,36.863134],"type":"Point"}
}