{
  "type": "Feature",
  "properties": {
    "iso:country":"US",
    "sg:address":"806 Main St",
    "sg:city":"Paris",
    "sg:classifiers":[
        {
            "category":"Wholesale",
            "subcategory":"Sporting Goods",
            "type":"Manufacturing & Wholesale Goods"
        }
    ],
    "sg:phone":"+1 859 987 1775",
    "sg:postcode":"40361",
    "sg:province":"KY",
    "sg:tags":[
        "equipment",
        "pool",
        "swimming"
    ],
    "wof:name":"Paris Pool Supply",
    "wof:placetype":"venue"
},
  "geometry": {"coordinates":[-84.252258,38.209431],"type":"Point"}
}