{
  "type": "Feature",
  "properties": {
    "addr:full":"139 The Masters Georgetown KY 40324",
    "addr:housenumber":"139",
    "addr:postcode":"40324",
    "addr:street":"The Masters",
    "iso:country":"US",
    "sg:address":"139 The Masters",
    "sg:city":"Georgetown",
    "sg:classifiers":[
        {
            "category":"Real Estate",
            "subcategory":"Real Estate Agent",
            "type":"Services"
        }
    ],
    "sg:phone":"+1 859 339 1241",
    "sg:postcode":"40324",
    "sg:province":"KY",
    "wof:name":"Campbell Markl Realtor Inc",
    "wof:placetype":"venue"
},
  "geometry": {"coordinates":[-84.591613,38.212633],"type":"Point"}
}