{
  "type": "Feature",
  "properties": {
    "iso:country":"US",
    "sg:address":"85 N Grand Ave",
    "sg:city":"Fort Thomas",
    "sg:classifiers":[
        {
            "category":"Banks & Credit Unions",
            "subcategory":"Bank",
            "type":"Services"
        }
    ],
    "sg:phone":"+1 859 572 3526",
    "sg:postcode":"41075",
    "sg:province":"KY",
    "sg:tags":[
        "federally",
        "chartered"
    ],
    "wof:name":"Slh Federal Credit Union",
    "wof:placetype":"venue"
},
  "geometry": {"coordinates":[-84.464394,39.077861],"type":"Point"}
}