{
  "type": "Feature",
  "properties": {
    "iso:country":"US",
    "sg:address":"136 Langdon St",
    "sg:city":"Somerset",
    "sg:classifiers":[
        {
            "category":"Professional",
            "subcategory":"Accounting & Tax Preparation",
            "type":"Services"
        }
    ],
    "sg:phone":"+1 606 678 2622",
    "sg:postcode":"42501",
    "sg:province":"KY",
    "sg:tags":[
        "bookkeeping",
        "general"
    ],
    "wof:name":"Colyer Mark Bokkeeping Tax Svc",
    "wof:placetype":"venue"
},
  "geometry": {"coordinates":[-84.613164,37.084267],"type":"Point"}
}