{
  "type": "Feature",
  "properties": {
    "iso:country":"US",
    "sg:address":"500 Stoner-Ephesus Rd",
    "sg:city":"Winchester",
    "sg:classifiers":[
        {
            "category":"Organizations",
            "subcategory":"Religious Organization",
            "type":"Services"
        }
    ],
    "sg:phone":"+1 859 842 4051",
    "sg:postcode":"40391",
    "sg:province":"KY",
    "wof:name":"Ephesus Baptist Church",
    "wof:placetype":"venue"
},
  "geometry": {"coordinates":[-84.072312,37.981008],"type":"Point"}
}