{
  "type": "Feature",
  "properties": {
    "addr:full":"103 Main St Glencoe KY 41046",
    "addr:housenumber":"103",
    "addr:postcode":"41046",
    "addr:street":"Main St",
    "iso:country":"US",
    "sg:address":"103 Main St",
    "sg:city":"Glencoe",
    "sg:classifiers":[
        {
            "category":"Government",
            "subcategory":"Post Office",
            "type":"Public Place"
        }
    ],
    "sg:phone":"+1 859 000 1111",
    "sg:postcode":"41046",
    "sg:province":"KY",
    "wof:name":"US Post Office",
    "wof:placetype":"venue"
},
  "geometry": {"coordinates":[-84.82299999999999,38.7142],"type":"Point"}
}