{
  "type": "Feature",
  "properties": {
    "addr:full":"357 Charles Dr Mayfield KY 42066",
    "addr:housenumber":"357",
    "addr:postcode":"42066",
    "addr:street":"Charles Dr",
    "iso:country":"US",
    "sg:address":"357 Charles Dr",
    "sg:city":"Mayfield",
    "sg:classifiers":[
        {
            "category":"Shopping",
            "subcategory":"Clothing, Apparel, & Fashions",
            "type":"Retail Goods"
        }
    ],
    "sg:phone":"+1 270 251 9200",
    "sg:postcode":"42066",
    "sg:province":"KY",
    "wof:name":"Cato",
    "wof:placetype":"venue"
},
  "geometry": {"coordinates":[-88.628203,36.718524],"type":"Point"}
}