{
  "type": "Feature",
  "properties": {
    "addr:full":"207 Eiler Ave Louisville KY 40214",
    "addr:housenumber":"207",
    "addr:postcode":"40214",
    "addr:street":"Eiler Ave",
    "iso:country":"US",
    "sg:address":"207 Eiler Ave",
    "sg:city":"Louisville",
    "sg:classifiers":[
        {
            "category":"Wholesale",
            "subcategory":"Machinery & Supplies",
            "type":"Manufacturing & Wholesale Goods"
        }
    ],
    "sg:phone":"+1 502 366 0326",
    "sg:postcode":"40214",
    "sg:province":"KY",
    "sg:tags":[
        "fitting",
        "hose",
        "coupling"
    ],
    "sg:website":"www.branhamcorp.com",
    "wof:name":"Branham Corp",
    "wof:placetype":"venue"
},
  "geometry": {"coordinates":[-85.75570399999999,38.165526],"type":"Point"}
}