{
  "type": "Feature",
  "properties": {
    "addr:full":"3228 Crums Ln Shively KY 40216",
    "addr:housenumber":"3228",
    "addr:postcode":"40216",
    "addr:street":"Crums Ln",
    "iso:country":"US",
    "sg:address":"3228 Crums Ln",
    "sg:city":"Shively",
    "sg:classifiers":[
        {
            "category":"Restaurant",
            "type":"Food & Drink"
        }
    ],
    "sg:phone":"+1 502 448 1360",
    "sg:postcode":"40216",
    "sg:province":"KY",
    "wof:name":"Chinese Express",
    "wof:placetype":"venue"
},
  "geometry": {"coordinates":[-85.836673,38.198814],"type":"Point"}
}