{
  "type": "Feature",
  "properties": {
    "iso:country":"US",
    "sg:address":"5033 Jacks Creek Pike",
    "sg:city":"Lexington",
    "sg:classifiers":[
        {
            "category":"Farming",
            "subcategory":"Farm",
            "type":"Manufacturing & Wholesale Goods"
        }
    ],
    "sg:phone":"+1 859 272 3700",
    "sg:postcode":"40515",
    "sg:province":"KY",
    "sg:tags":[
        "crop",
        "general"
    ],
    "wof:name":"Paytons Farm",
    "wof:placetype":"venue"
},
  "geometry": {"coordinates":[-84.418357,37.896334],"type":"Point"}
}