{
  "type": "Feature",
  "properties": {
    "addr:full":"42 W 2nd St Maysville KY 41056",
    "addr:housenumber":"42",
    "addr:postcode":"41056",
    "addr:street":"W 2Nd St",
    "iso:country":"US",
    "sg:address":"42 W 2nd St",
    "sg:city":"Maysville",
    "sg:classifiers":[
        {
            "category":"Home & Garden",
            "subcategory":"Furniture",
            "type":"Retail Goods"
        }
    ],
    "sg:phone":"+1 606 564 5092",
    "sg:postcode":"41056",
    "sg:province":"KY",
    "wof:name":"C L Mains & Son Furniture",
    "wof:placetype":"venue"
},
  "geometry": {"coordinates":[-83.765427,38.648156],"type":"Point"}
}