{
  "type": "Feature",
  "properties": {
    "iso:country":"US",
    "sg:address":"326 Sickle Ct",
    "sg:city":"Frankfort",
    "sg:classifiers":[
        {
            "category":"Real Estate",
            "subcategory":"Architect",
            "type":"Services"
        }
    ],
    "sg:phone":"+1 502 696 9000",
    "sg:postcode":"40601",
    "sg:province":"KY",
    "wof:name":"Greystone Architects Inc",
    "wof:placetype":"venue"
},
  "geometry": {"coordinates":[-84.879541,38.17236],"type":"Point"}
}