{
  "type": "Feature",
  "properties": {
    "iso:country":"US",
    "sg:address":"313 Burley Ave",
    "sg:city":"Lexington",
    "sg:classifiers":[
        {
            "category":"Organizations",
            "subcategory":"Religious Organization",
            "type":"Services"
        }
    ],
    "sg:phone":"+1 859 254 7025",
    "sg:postcode":"40503",
    "sg:province":"KY",
    "sg:tags":[
        "church"
    ],
    "wof:name":"Jehovah's Witnesses",
    "wof:placetype":"venue"
},
  "geometry": {"coordinates":[-84.51818799999999,38.035114],"type":"Point"}
}