{
  "type": "Feature",
  "properties": {
    "addr:full":"305 Broadway St South Fulton KY 38257",
    "addr:housenumber":"305",
    "addr:postcode":"38257",
    "addr:street":"Broadway St",
    "iso:country":"US",
    "sg:address":"305 Broadway St",
    "sg:city":"South Fulton",
    "sg:classifiers":[
        {
            "category":"Retail",
            "subcategory":"Laundry & Dry Cleaning",
            "type":"Services"
        }
    ],
    "sg:phone":"+1 731 479 1651",
    "sg:postcode":"38257",
    "sg:province":"KY",
    "sg:tags":[
        "garment",
        "agent"
    ],
    "wof:name":"South Fulton Cleaners",
    "wof:placetype":"venue"
},
  "geometry": {"coordinates":[-88.87571199999999,36.498039],"type":"Point"}
}