{
  "type": "Feature",
  "properties": {
    "iso:country":"US",
    "sg:address":"2294 Dry Ridge Rd",
    "sg:city":"Liberty",
    "sg:classifiers":[
        {
            "category":"Wholesale",
            "subcategory":"Construction Materials",
            "type":"Manufacturing & Wholesale Goods"
        }
    ],
    "sg:phone":"+1 606 787 9537",
    "sg:postcode":"42539",
    "sg:province":"KY",
    "sg:tags":[
        "gates"
    ],
    "wof:name":"Robert Lynn Gates",
    "wof:placetype":"venue"
},
  "geometry": {"coordinates":[-84.90402,37.301003],"type":"Point"}
}