{
  "type": "Feature",
  "properties": {
    "addr:full":"300 E 4th St Augusta KY 41002",
    "addr:housenumber":"300",
    "addr:postcode":"41002",
    "addr:street":"E 4Th St",
    "iso:country":"US",
    "sg:address":"300 E 4th St",
    "sg:city":"Augusta",
    "sg:classifiers":[
        {
            "category":"Organizations",
            "subcategory":"Religious Organization",
            "type":"Services"
        }
    ],
    "sg:phone":"+1 606 756 2120",
    "sg:postcode":"41002",
    "sg:province":"KY",
    "sg:tags":[
        "church"
    ],
    "wof:name":"First Baptist Church-Augusta",
    "wof:placetype":"venue"
},
  "geometry": {"coordinates":[-84.001897,38.771694],"type":"Point"}
}