{
  "type": "Feature",
  "properties": {
    "iso:country":"US",
    "sg:address":"102 High St",
    "sg:city":"Burkesville",
    "sg:classifiers":[
        {
            "category":"Organizations",
            "subcategory":"Religious Organization",
            "type":"Services"
        }
    ],
    "sg:phone":"+1 270 864 3115",
    "sg:postcode":"42717",
    "sg:province":"KY",
    "sg:tags":[
        "church"
    ],
    "wof:name":"Faith Bible Church",
    "wof:placetype":"venue"
},
  "geometry": {"coordinates":[-85.37106,36.791514],"type":"Point"}
}