{
  "type": "Feature",
  "properties": {
    "iso:country":"US",
    "sg:address":"3359 Montavesta Rd",
    "sg:city":"Lexington",
    "sg:classifiers":[
        {
            "category":"Real Estate",
            "subcategory":"Real Estate Operator",
            "type":"Services"
        }
    ],
    "sg:phone":"+1 859 268 4631",
    "sg:postcode":"40502",
    "sg:province":"KY",
    "sg:tags":[
        "apartment"
    ],
    "wof:name":"Townhouses Of Merrick",
    "wof:placetype":"venue"
},
  "geometry": {"coordinates":[-84.492178,37.996933],"type":"Point"}
}