{
  "type": "Feature",
  "properties": {
    "addr:full":"566 Old Mammoth Cave Rd Cave City KY 42127",
    "addr:housenumber":"566",
    "addr:postcode":"42127",
    "addr:street":"Old Mammoth Cave Rd",
    "iso:country":"US",
    "sg:address":"566 Old Mammoth Cave Rd",
    "sg:city":"Cave City",
    "sg:classifiers":[
        {
            "category":"Shopping",
            "subcategory":"Gifts & Souvenirs",
            "type":"Retail Goods"
        }
    ],
    "sg:phone":"+1 270 773 5144",
    "sg:postcode":"42127",
    "sg:province":"KY",
    "sg:tags":[
        "shop"
    ],
    "wof:name":"Big Mike's Rock & Gift Shop",
    "wof:placetype":"venue"
},
  "geometry": {"coordinates":[-86.038219,37.142756],"type":"Point"}
}