{
  "type": "Feature",
  "properties": {
    "iso:country":"US",
    "sg:address":"416 W Jefferson St",
    "sg:city":"Louisville",
    "sg:classifiers":[
        {
            "category":"Banks & Credit Unions",
            "subcategory":"Bank",
            "type":"Services"
        }
    ],
    "sg:phone":"+1 502 566 2002",
    "sg:postcode":"40202",
    "sg:province":"KY",
    "wof:name":"Banc One",
    "wof:placetype":"venue"
},
  "geometry": {"coordinates":[-85.75726299999999,38.253885],"type":"Point"}
}