{
  "type": "Feature",
  "properties": {
    "iso:country":"US",
    "sg:address":"14109 Spring Mill Rd",
    "sg:city":"Louisville",
    "sg:classifiers":[
        {
            "category":"Insurance",
            "subcategory":"Insurance Agent",
            "type":"Services"
        }
    ],
    "sg:phone":"+1 502 243 9966",
    "sg:postcode":"40245",
    "sg:province":"KY",
    "wof:name":"Fireman's Fund Insurance",
    "wof:placetype":"venue"
},
  "geometry": {"coordinates":[-85.496173,38.295422],"type":"Point"}
}