{
  "type": "Feature",
  "properties": {
    "addr:full":"4026 Taylorsville Rd Louisville KY 40220",
    "addr:housenumber":"4026",
    "addr:postcode":"40220",
    "addr:street":"Taylorsville Rd",
    "iso:country":"US",
    "sg:address":"4026 Taylorsville Rd",
    "sg:city":"Louisville",
    "sg:classifiers":[
        {
            "category":"Ice Cream",
            "type":"Food & Drink"
        }
    ],
    "sg:menulink":"http://www.allmenus.com/ky/jefferson-southeast/161469-dairy-queen/menu/",
    "sg:phone":"+1 502 454 0409",
    "sg:postcode":"40220",
    "sg:province":"KY",
    "sg:tags":[
        "burger",
        "american"
    ],
    "wof:name":"Dairy Queen",
    "wof:placetype":"venue"
},
  "geometry": {"coordinates":[-85.627666,38.219884],"type":"Point"}
}