{
  "type": "Feature",
  "properties": {
    "iso:country":"US",
    "sg:address":"930 2nd Ave",
    "sg:city":"Dayton",
    "sg:classifiers":[
        {
            "category":"Manufacturing",
            "subcategory":"Retail Goods",
            "type":"Manufacturing & Wholesale Goods"
        }
    ],
    "sg:phone":"+1 859 431 6800",
    "sg:postcode":"41074",
    "sg:province":"KY",
    "sg:tags":[
        "lamp",
        "machinery",
        "shade"
    ],
    "wof:name":"Willow Green Co",
    "wof:placetype":"venue"
},
  "geometry": {"coordinates":[-84.466571,39.116669],"type":"Point"}
}