{
  "type": "Feature",
  "properties": {
    "iso:country":"US",
    "sg:address":"2435 N Laurel Rd",
    "sg:city":"London",
    "sg:classifiers":[
        {
            "category":"Shopping",
            "subcategory":"Crafts & Fabrics",
            "type":"Retail Goods"
        }
    ],
    "sg:phone":"+1 606 843 6610",
    "sg:postcode":"40741",
    "sg:province":"KY",
    "sg:tags":[
        "shop"
    ],
    "wof:name":"Sexton's Fabrics",
    "wof:placetype":"venue"
},
  "geometry": {"coordinates":[-84.11962,37.166989],"type":"Point"}
}