{
  "type": "Feature",
  "properties": {
    "addr:full":"4001 Dutchmans Ln Louisville KY 40207",
    "addr:housenumber":"4001",
    "addr:postcode":"40207",
    "addr:street":"Dutchmans Ln",
    "iso:country":"US",
    "sg:address":"4001 Dutchmans Ln",
    "sg:city":"Louisville",
    "sg:classifiers":[
        {
            "category":"Health Services",
            "subcategory":"Doctor",
            "type":"Services"
        },
        {
            "category":"Health Services",
            "subcategory":"Clinic",
            "type":"Services"
        }
    ],
    "sg:phone":"+1 502 893 7744",
    "sg:postcode":"40207",
    "sg:province":"KY",
    "sg:tags":[
        "physician",
        "stomach",
        "gastroenterology",
        "surgeons",
        "proctology",
        "intestines"
    ],
    "sg:website":"http://www.realpagessites.com/gastrodoctor",
    "wof:name":"Kyana Gi",
    "wof:placetype":"venue"
},
  "geometry": {"coordinates":[-85.63376100000001,38.233949],"type":"Point"}
}