{
  "type": "Feature",
  "properties": {
    "iso:country":"US",
    "sg:address":"205 Timberwood Trce",
    "sg:city":"Georgetown",
    "sg:classifiers":[
        {
            "category":"Professional",
            "subcategory":"Art Services",
            "type":"Services"
        }
    ],
    "sg:phone":"+1 502 868 0577",
    "sg:postcode":"40324",
    "sg:province":"KY",
    "sg:tags":[
        "graphic",
        "designer"
    ],
    "wof:name":"At Design",
    "wof:placetype":"venue"
},
  "geometry": {"coordinates":[-84.523366,38.21457],"type":"Point"}
}