{
  "type": "Feature",
  "properties": {
    "addr:full":"1553 Alexandria Dr Lexington KY 40504",
    "addr:housenumber":"1553",
    "addr:postcode":"40504",
    "addr:street":"Alexandria Dr",
    "iso:country":"US",
    "sg:address":"1553 Alexandria Dr",
    "sg:city":"Lexington",
    "sg:classifiers":[
        {
            "category":"Real Estate",
            "subcategory":"Real Estate Operator",
            "type":"Services"
        }
    ],
    "sg:phone":"+1 859 277 8311",
    "sg:postcode":"40504",
    "sg:province":"KY",
    "sg:tags":[
        "apartment"
    ],
    "wof:name":"Hadden & Assoc",
    "wof:placetype":"venue"
},
  "geometry": {"coordinates":[-84.551917,38.046732],"type":"Point"}
}