{
  "type": "Feature",
  "properties": {
    "iso:country":"US",
    "sg:address":"70 Monroe Ln",
    "sg:city":"Campbellsburg",
    "sg:classifiers":[
        {
            "category":"Building & Trades",
            "subcategory":"Construction",
            "type":"Services"
        }
    ],
    "sg:phone":"+1 502 743 9548",
    "sg:postcode":"40011",
    "sg:province":"KY",
    "sg:tags":[
        "home",
        "builder"
    ],
    "wof:name":"Just-N-Til Homes Inc",
    "wof:placetype":"venue"
},
  "geometry": {"coordinates":[-85.20944,38.525016],"type":"Point"}
}