{
  "type": "Feature",
  "properties": {
    "iso:country":"US",
    "sg:address":"916 Ford Ave",
    "sg:city":"Owensboro",
    "sg:classifiers":[
        {
            "category":"Real Estate",
            "subcategory":"Real Estate Agent",
            "type":"Services"
        }
    ],
    "sg:phone":"+1 270 926 0786",
    "sg:postcode":"42301",
    "sg:province":"KY",
    "sg:tags":[
        "inspection"
    ],
    "wof:name":"Nathan Mock Home Inspections",
    "wof:placetype":"venue"
},
  "geometry": {"coordinates":[-87.12126600000001,37.753941],"type":"Point"}
}