{
  "type": "Feature",
  "properties": {
    "addr:full":"2091 N Bend Rd Ste 120 Hebron KY 41048",
    "addr:housenumber":"2091",
    "addr:postcode":"41048",
    "addr:street":"N Bend Rd Ste 120",
    "iso:country":"US",
    "sg:address":"2091 N Bend Rd Ste 120",
    "sg:city":"Hebron",
    "sg:classifiers":[
        {
            "category":"Restaurant",
            "type":"Food & Drink"
        },
        {
            "category":"Food & Beverages",
            "subcategory":"Bakery",
            "type":"Retail Goods"
        }
    ],
    "sg:phone":"+1 859 534 5444",
    "sg:postcode":"41048",
    "sg:province":"KY",
    "sg:tags":[
        "sandwich",
        "pizza"
    ],
    "wof:name":"Edwardo's Pizza and Subs",
    "wof:placetype":"venue"
},
  "geometry": {"coordinates":[-84.71207,39.086897],"type":"Point"}
}