{
  "type": "Feature",
  "properties": {
    "iso:country":"US",
    "sg:address":"519 N Morgan St",
    "sg:city":"Morganfield",
    "sg:classifiers":[
        {
            "category":"Social Services",
            "subcategory":"Child Care",
            "type":"Services"
        }
    ],
    "sg:phone":"+1 270 389 0209",
    "sg:postcode":"42437",
    "sg:province":"KY",
    "sg:tags":[
        "nursery",
        "day"
    ],
    "wof:name":"S C C Enterprises",
    "wof:placetype":"venue"
},
  "geometry": {"coordinates":[-87.911461,37.68815],"type":"Point"}
}