{
  "type": "Feature",
  "properties": {
    "iso:country":"US",
    "sg:address":"133 S Water St",
    "sg:city":"Henderson",
    "sg:classifiers":[
        {
            "category":"Education",
            "subcategory":"School",
            "type":"Public Place"
        }
    ],
    "sg:phone":"+1 270 827 3674",
    "sg:postcode":"42420",
    "sg:province":"KY",
    "wof:name":"Riverview School",
    "wof:placetype":"venue"
},
  "geometry": {"coordinates":[-87.59539599999999,37.838582],"type":"Point"}
}