{
  "type": "Feature",
  "properties": {
    "addr:full":"8113 SE Licking River Rd Salyersville KY 41465",
    "addr:housenumber":"8113",
    "addr:postcode":"41465",
    "addr:street":"Se Licking River Rd",
    "iso:country":"US",
    "sg:address":"8113 SE Licking River Rd",
    "sg:city":"Salyersville",
    "sg:classifiers":[
        {
            "category":"Personal",
            "subcategory":"Beauty Salon",
            "type":"Services"
        }
    ],
    "sg:phone":"+1 606 884 2392",
    "sg:postcode":"41465",
    "sg:province":"KY",
    "wof:name":"Donna's Country Cuttin",
    "wof:placetype":"venue"
},
  "geometry": {"coordinates":[-83.018018,37.671042],"type":"Point"}
}