{
  "type": "Feature",
  "properties": {
    "iso:country":"US",
    "sg:address":"40 Highway Ave",
    "sg:city":"Covington",
    "sg:classifiers":[
        {
            "category":"Wholesale",
            "subcategory":"Vending Machines",
            "type":"Manufacturing & Wholesale Goods"
        }
    ],
    "sg:phone":"+1 859 261 1799",
    "sg:postcode":"41016",
    "sg:province":"KY",
    "sg:tags":[
        "operator"
    ],
    "wof:name":"Volpehneim Vending",
    "wof:placetype":"venue"
},
  "geometry": {"coordinates":[-84.542828,39.095124],"type":"Point"}
}