{
  "type": "Feature",
  "properties": {
    "iso:country":"US",
    "sg:address":"6410 Bardstown Rd",
    "sg:city":"Fern Creek",
    "sg:classifiers":[
        {
            "category":"Retail",
            "subcategory":"Veterinary Services",
            "type":"Services"
        }
    ],
    "sg:phone":"+1 502 239 5176",
    "sg:postcode":"40291",
    "sg:province":"KY",
    "sg:tags":[
        "veterinarian"
    ],
    "wof:name":"Kenneth J Sims & Assoc",
    "wof:placetype":"venue"
},
  "geometry": {"coordinates":[-85.588703,38.152795],"type":"Point"}
}