{
  "type": "Feature",
  "properties": {
    "iso:country":"US",
    "sg:address":"401 S 4th St",
    "sg:city":"Louisville",
    "sg:classifiers":[
        {
            "category":"Professional",
            "subcategory":"Lawyer & Legal Services",
            "type":"Services"
        }
    ],
    "sg:phone":"+1 502 584 1135",
    "sg:postcode":"40202",
    "sg:province":"KY",
    "sg:tags":[
        "attorney",
        "copyright",
        "patent",
        "trademark",
        "law"
    ],
    "wof:name":"Eichenberger, Robert H",
    "wof:placetype":"venue"
},
  "geometry": {"coordinates":[-85.75711800000001,38.253059],"type":"Point"}
}