{
  "type": "Feature",
  "properties": {
    "addr:full":"1739 Scherm Rd Owensboro KY 42301",
    "addr:housenumber":"1739",
    "addr:postcode":"42301",
    "addr:street":"Scherm Rd",
    "iso:country":"US",
    "sg:address":"1739 Scherm Rd",
    "sg:city":"Owensboro",
    "sg:classifiers":[
        {
            "category":"Wholesale",
            "subcategory":"Office Equipment",
            "type":"Manufacturing & Wholesale Goods"
        }
    ],
    "sg:phone":"+1 270 684 0684",
    "sg:postcode":"42301",
    "sg:province":"KY",
    "sg:tags":[
        "machine",
        "duplicating",
        "copying"
    ],
    "wof:name":"Ikon Office Solutions Inc",
    "wof:placetype":"venue"
},
  "geometry": {"coordinates":[-87.129154,37.741799],"type":"Point"}
}