{
  "type": "Feature",
  "properties": {
    "iso:country":"US",
    "sg:address":"4210 Hickoryview Dr",
    "sg:city":"Louisville",
    "sg:classifiers":[
        {
            "category":"Building & Trades",
            "subcategory":"Cleaning & Sanitation",
            "type":"Services"
        }
    ],
    "sg:phone":"+1 502 809 1383",
    "sg:postcode":"40299",
    "sg:province":"KY",
    "sg:tags":[
        "maintenance"
    ],
    "wof:name":"SJS Commercial Cleaning Servic",
    "wof:placetype":"venue"
},
  "geometry": {"coordinates":[-85.558646,38.183407],"type":"Point"}
}