{
  "type": "Feature",
  "properties": {
    "addr:full":"401 Hoffman Dr Henderson KY 42420",
    "addr:housenumber":"401",
    "addr:postcode":"42420",
    "addr:street":"Hoffman Dr",
    "iso:country":"US",
    "sg:address":"401 Hoffman Dr",
    "sg:city":"Henderson",
    "sg:classifiers":[
        {
            "category":"Organizations",
            "subcategory":"Non-profit Organization",
            "type":"Services"
        }
    ],
    "sg:phone":"+1 270 830 7121",
    "sg:postcode":"42420",
    "sg:province":"KY",
    "sg:tags":[
        "information",
        "alcoholism",
        "treatment"
    ],
    "wof:name":"Alcoholics Anonymous Weaverton",
    "wof:placetype":"venue"
},
  "geometry": {"coordinates":[-87.568399,37.836411],"type":"Point"}
}