{
  "type": "Feature",
  "properties": {
    "iso:country":"US",
    "sg:address":"2036 Madison St",
    "sg:city":"Henderson",
    "sg:classifiers":[
        {
            "category":"Restaurant",
            "type":"Food & Drink"
        }
    ],
    "sg:phone":"+1 270 826 1207",
    "sg:postcode":"42420",
    "sg:province":"KY",
    "wof:name":"Bon Ton Mini Mart",
    "wof:placetype":"venue"
},
  "geometry": {"coordinates":[-87.578549,37.810051],"type":"Point"}
}