{
  "type": "Feature",
  "properties": {
    "iso:country":"US",
    "sg:address":"131 N 4th St",
    "sg:city":"Nicholasville",
    "sg:classifiers":[
        {
            "category":"Shopping",
            "subcategory":"Hobbies, Toys, & Games",
            "type":"Retail Goods"
        }
    ],
    "sg:phone":"+1 859 887 3540",
    "sg:postcode":"40356",
    "sg:province":"KY",
    "sg:tags":[
        "shop",
        "hobby",
        "model",
        "supply"
    ],
    "sg:website":"http://www.badhobbies.com",
    "wof:name":"Bad Hobbies",
    "wof:placetype":"venue"
},
  "geometry": {"coordinates":[-84.57710299999999,37.88414],"type":"Point"}
}