{
  "type": "Feature",
  "properties": {
    "iso:country":"US",
    "sg:address":"38824 State Hwy 194 E",
    "sg:city":"Phelps",
    "sg:classifiers":[
        {
            "category":"Food & Beverages",
            "subcategory":"Groceries & Convenience Stores",
            "type":"Retail Goods"
        }
    ],
    "sg:phone":"+1 606 456 7726",
    "sg:postcode":"41553",
    "sg:province":"KY",
    "wof:name":"Jo-Mart",
    "wof:placetype":"venue"
},
  "geometry": {"coordinates":[-82.157858,37.523729],"type":"Point"}
}