{
  "type": "Feature",
  "properties": {
    "iso:country":"US",
    "sg:address":"7 Theater Sq",
    "sg:city":"Louisville",
    "sg:classifiers":[
        {
            "category":"Communications",
            "subcategory":"Film & Video Production",
            "type":"Services"
        }
    ],
    "sg:phone":"+1 502 595 8177",
    "sg:postcode":"40202",
    "sg:province":"KY",
    "sg:tags":[
        "tv",
        "services-commercial",
        "companies-film",
        "radio"
    ],
    "wof:name":"Athenaeum Production",
    "wof:placetype":"venue"
},
  "geometry": {"coordinates":[-85.758585,38.24696],"type":"Point"}
}