{
  "type": "Feature",
  "properties": {
    "addr:full":"600 S Broadway Rd Lexington KY 40508",
    "addr:housenumber":"600",
    "addr:postcode":"40508",
    "addr:street":"S Broadway Rd",
    "iso:country":"US",
    "sg:address":"600 S Broadway Rd",
    "sg:city":"Lexington",
    "sg:classifiers":[
        {
            "category":"Shopping",
            "type":"Retail Goods"
        }
    ],
    "sg:phone":"+1 859 253 3885",
    "sg:postcode":"40508",
    "sg:province":"KY",
    "sg:tags":[
        "picture",
        "frame"
    ],
    "wof:name":"Gallery",
    "wof:placetype":"venue"
},
  "geometry": {"coordinates":[-84.50744299999999,38.043651],"type":"Point"}
}