{
  "type": "Feature",
  "properties": {
    "iso:country":"US",
    "sg:address":"512 S Clay St",
    "sg:city":"Hopkinsville",
    "sg:classifiers":[
        {
            "category":"Education",
            "subcategory":"Special Training",
            "type":"Public Place"
        }
    ],
    "sg:phone":"+1 270 886 3718",
    "sg:postcode":"42240",
    "sg:province":"KY",
    "sg:tags":[
        "school",
        "interest"
    ],
    "wof:name":"Western Kentucky Ctr For Arts",
    "wof:placetype":"venue"
},
  "geometry": {"coordinates":[-87.484897,36.865769],"type":"Point"}
}