{
  "type": "Feature",
  "properties": {
    "addr:full":"832 Dorsey Ln Louisville KY 40223",
    "addr:housenumber":"832",
    "addr:postcode":"40223",
    "addr:street":"Dorsey Ln",
    "iso:country":"US",
    "sg:address":"832 Dorsey Ln",
    "sg:city":"Louisville",
    "sg:classifiers":[
        {
            "category":"Building & Trades",
            "subcategory":"Cleaning & Sanitation",
            "type":"Services"
        }
    ],
    "sg:phone":"+1 502 245 2628",
    "sg:postcode":"40223",
    "sg:province":"KY",
    "sg:tags":[
        "maintenance"
    ],
    "wof:name":"Ntg Properties LLC",
    "wof:placetype":"venue"
},
  "geometry": {"coordinates":[-85.561519,38.259843],"type":"Point"}
}