{
  "type": "Feature",
  "properties": {
    "addr:full":"1601 Vest Talcum Rd Vest KY 41831",
    "addr:housenumber":"1601",
    "addr:postcode":"41831",
    "addr:street":"Vest Talcum Rd",
    "iso:country":"US",
    "sg:address":"1601 Vest Talcum Rd",
    "sg:city":"Vest",
    "sg:classifiers":[
        {
            "category":"Recreation",
            "type":"Entertainment"
        }
    ],
    "sg:phone":"+1 606 785 5741",
    "sg:postcode":"41831",
    "sg:province":"KY",
    "sg:tags":[
        "pond",
        "fishing",
        "lake"
    ],
    "wof:name":"Vest Pay Lake",
    "wof:placetype":"venue"
},
  "geometry": {"coordinates":[-83.014929,37.400179],"type":"Point"}
}