{
  "type": "Feature",
  "properties": {
    "iso:country":"US",
    "sg:address":"1433 Story Ave",
    "sg:city":"Louisville",
    "sg:classifiers":[
        {
            "category":"Building & Trades",
            "subcategory":"Construction",
            "type":"Services"
        }
    ],
    "sg:phone":"+1 502 589 1735",
    "sg:postcode":"40206",
    "sg:province":"KY",
    "sg:tags":[
        "concrete",
        "contractor"
    ],
    "wof:name":"Stoll Construction & Paving Co",
    "wof:placetype":"venue"
},
  "geometry": {"coordinates":[-85.725398,38.257159],"type":"Point"}
}