{
  "type": "Feature",
  "properties": {
    "iso:country":"US",
    "sg:address":"2310 Langdon Dr",
    "sg:city":"Louisville",
    "sg:classifiers":[
        {
            "category":"Real Estate",
            "subcategory":"Real Estate Agent",
            "type":"Services"
        }
    ],
    "sg:phone":"+1 502 425 1457",
    "sg:postcode":"40242",
    "sg:province":"KY",
    "wof:name":"OBryan Realty",
    "wof:placetype":"venue"
},
  "geometry": {"coordinates":[-85.579404,38.281192],"type":"Point"}
}