{
  "type": "Feature",
  "properties": {
    "iso:country":"US",
    "sg:address":"501 Shipp Rd",
    "sg:city":"Magnolia",
    "sg:classifiers":[
        {
            "category":"Professional",
            "subcategory":"Lawyer & Legal Services",
            "type":"Services"
        }
    ],
    "sg:phone":"+1 270 324 2901",
    "sg:postcode":"42757",
    "sg:province":"KY",
    "sg:tags":[
        "attorney"
    ],
    "wof:name":"Reed Law Office",
    "wof:placetype":"venue"
},
  "geometry": {"coordinates":[-85.71530199999999,37.465335],"type":"Point"}
}