{
  "type": "Feature",
  "properties": {
    "addr:full":"4112 Hunting Creek Dr Owensboro KY 42303",
    "addr:housenumber":"4112",
    "addr:postcode":"42303",
    "addr:street":"Hunting Creek Dr",
    "iso:country":"US",
    "sg:address":"4112 Hunting Creek Dr",
    "sg:city":"Owensboro",
    "sg:classifiers":[
        {
            "category":"Professional",
            "subcategory":"Management & Consulting",
            "type":"Services"
        }
    ],
    "sg:phone":"+1 270 926 2780",
    "sg:postcode":"42303",
    "sg:province":"KY",
    "wof:name":"Harreld Management Svcs LLC",
    "wof:placetype":"venue"
},
  "geometry": {"coordinates":[-87.08863100000001,37.726938],"type":"Point"}
}