{
  "type": "Feature",
  "properties": {
    "iso:country":"US",
    "sg:address":"1028 Bristow Rd",
    "sg:city":"Independence",
    "sg:classifiers":[
        {
            "category":"Wholesale",
            "subcategory":"Non-durable Goods",
            "type":"Manufacturing & Wholesale Goods"
        }
    ],
    "sg:phone":"+1 859 282 8228",
    "sg:postcode":"41051",
    "sg:province":"KY",
    "sg:tags":[
        "advertising",
        "specialty"
    ],
    "wof:name":"Stuntebeck's Ad Specialties",
    "wof:placetype":"venue"
},
  "geometry": {"coordinates":[-84.596379,38.963452],"type":"Point"}
}