{
  "type": "Feature",
  "properties": {
    "iso:country":"US",
    "sg:address":"117 N Hord St",
    "sg:city":"Grayson",
    "sg:classifiers":[
        {
            "category":"Shopping",
            "subcategory":"Clothing, Apparel, & Fashions",
            "type":"Retail Goods"
        }
    ],
    "sg:phone":"+1 606 474 5353",
    "sg:postcode":"41143",
    "sg:province":"KY",
    "wof:name":"Wilma Shop",
    "wof:placetype":"venue"
},
  "geometry": {"coordinates":[-82.94873699999999,38.333034],"type":"Point"}
}