{
  "type": "Feature",
  "properties": {
    "iso:country":"US",
    "sg:address":"1800 Williamson Court",
    "sg:city":"Louisville ",
    "sg:classifiers":[
        {
            "category":"Professional",
            "subcategory":"Computer Services",
            "type":"Services"
        }
    ],
    "sg:phone":"+1 800 462 8195",
    "sg:postcode":"40223",
    "sg:province":"KY",
    "sg:tags":[
        "used-medical-equipment",
        "medical-equipment"
    ],
    "sg:website":"http://www.DreMed.com",
    "wof:name":"Dre Medical",
    "wof:placetype":"venue"
},
  "geometry": {"coordinates":[-85.50503500000001,38.26988],"type":"Point"}
}