{
  "type": "Feature",
  "properties": {
    "addr:full":"145 Fowler Rd Madisonville KY 42431",
    "addr:housenumber":"145",
    "addr:postcode":"42431",
    "addr:street":"Fowler Rd",
    "iso:country":"US",
    "sg:address":"145 Fowler Rd",
    "sg:city":"Madisonville",
    "sg:classifiers":[
        {
            "category":"Insurance",
            "subcategory":"Insurance Agent",
            "type":"Services"
        }
    ],
    "sg:phone":"+1 270 825 0110",
    "sg:postcode":"42431",
    "sg:province":"KY",
    "wof:name":"Mc Dowell Insurance",
    "wof:placetype":"venue"
},
  "geometry": {"coordinates":[-87.482736,37.381148],"type":"Point"}
}