{
  "type": "Feature",
  "properties": {
    "iso:country":"US",
    "sg:address":"519 Enterprise Dr",
    "sg:city":"Erlanger",
    "sg:classifiers":[
        {
            "category":"Local Transit",
            "type":"Transportation"
        }
    ],
    "sg:phone":"+1 859 344 6800",
    "sg:postcode":"41017",
    "sg:province":"KY",
    "sg:tags":[
        "limousine"
    ],
    "wof:name":"Executive Services Group",
    "wof:placetype":"venue"
},
  "geometry": {"coordinates":[-84.585292,39.046923],"type":"Point"}
}