{
  "type": "Feature",
  "properties": {
    "iso:country":"US",
    "sg:address":"8164 State Hwy 122",
    "sg:city":"Drift",
    "sg:classifiers":[
        {
            "category":"Wholesale",
            "subcategory":"Machinery & Supplies",
            "type":"Manufacturing & Wholesale Goods"
        }
    ],
    "sg:phone":"+1 606 377 6737",
    "sg:postcode":"41619",
    "sg:province":"KY",
    "sg:tags":[
        "equipment",
        "mining"
    ],
    "wof:name":"D C Controls Inc",
    "wof:placetype":"venue"
},
  "geometry": {"coordinates":[-82.751504,37.520119],"type":"Point"}
}