{
  "type": "Feature",
  "properties": {
    "iso:country":"US",
    "sg:address":"1204 E Railroad St",
    "sg:city":"Robards",
    "sg:classifiers":[
        {
            "category":"Government",
            "subcategory":"Post Office",
            "type":"Public Place"
        }
    ],
    "sg:phone":"+1 270 521 7504",
    "sg:postcode":"42452",
    "sg:province":"KY",
    "wof:name":"US Post Office",
    "wof:placetype":"venue"
},
  "geometry": {"coordinates":[-87.54696,37.673833],"type":"Point"}
}