{
  "type": "Feature",
  "properties": {
    "iso:country":"US",
    "sg:address":"3904 Bishop Ln",
    "sg:city":"Louisville",
    "sg:classifiers":[
        {
            "category":"Manufacturing",
            "subcategory":"Tools & Machinery",
            "type":"Manufacturing & Wholesale Goods"
        }
    ],
    "sg:phone":"+1 502 966 3400",
    "sg:postcode":"40218",
    "sg:province":"KY",
    "sg:tags":[
        "control"
    ],
    "wof:name":"Varitech Inc",
    "wof:placetype":"venue"
},
  "geometry": {"coordinates":[-85.695779,38.18676],"type":"Point"}
}