{
  "type": "Feature",
  "properties": {
    "iso:country":"US",
    "sg:address":"3501 Randolph Good Luck Rd",
    "sg:city":"Summer Shade",
    "sg:classifiers":[
        {
            "category":"Professional",
            "subcategory":"Management & Consulting",
            "type":"Services"
        },
        {
            "category":"Restaurant",
            "type":"Food & Drink"
        }
    ],
    "sg:phone":"+1 270 428 3761",
    "sg:postcode":"42166",
    "sg:province":"KY",
    "wof:name":"Fergie's Inc",
    "wof:placetype":"venue"
},
  "geometry": {"coordinates":[-85.69345800000001,36.937354],"type":"Point"}
}