{
  "type": "Feature",
  "properties": {
    "iso:country":"US",
    "sg:address":"120 Max Hurt Dr",
    "sg:city":"Murray",
    "sg:classifiers":[
        {
            "category":"Manufacturing",
            "subcategory":"Tools & Machinery",
            "type":"Manufacturing & Wholesale Goods"
        }
    ],
    "sg:phone":"+1 270 753 2269",
    "sg:postcode":"42071",
    "sg:province":"KY",
    "sg:tags":[
        "physician",
        "surgeon"
    ],
    "wof:name":"Pulmo Dose Inc",
    "wof:placetype":"venue"
},
  "geometry": {"coordinates":[-88.30412800000001,36.658776],"type":"Point"}
}