{
  "type": "Feature",
  "properties": {
    "iso:country":"US",
    "sg:address":"493 Gerhard Dr",
    "sg:city":"Covington",
    "sg:classifiers":[
        {
            "category":"Manufacturing",
            "subcategory":"Apparel",
            "type":"Manufacturing & Wholesale Goods"
        }
    ],
    "sg:phone":"+1 859 344 1502",
    "sg:postcode":"41017",
    "sg:province":"KY",
    "sg:tags":[
        "blind",
        "curtain",
        "shades",
        "manufacturer"
    ],
    "wof:name":"Rooms",
    "wof:placetype":"venue"
},
  "geometry": {"coordinates":[-84.550366,38.995483],"type":"Point"}
}