{
  "type": "Feature",
  "properties": {
    "iso:country":"US",
    "sg:address":"7725 N Jackson Hwy",
    "sg:city":"Magnolia",
    "sg:classifiers":[
        {
            "category":"Organizations",
            "subcategory":"Religious Organization",
            "type":"Services"
        }
    ],
    "sg:phone":"+1 270 528 5916",
    "sg:postcode":"42757",
    "sg:province":"KY",
    "sg:tags":[
        "church"
    ],
    "wof:name":"Believers United Church",
    "wof:placetype":"venue"
},
  "geometry": {"coordinates":[-85.758499,37.358885],"type":"Point"}
}