{
  "type": "Feature",
  "properties": {
    "iso:country":"US",
    "sg:address":"11530 Herrick Ln",
    "sg:city":"Louisville",
    "sg:classifiers":[
        {
            "category":"Health Services",
            "subcategory":"Nursing And Care Facility",
            "type":"Services"
        }
    ],
    "sg:phone":"+1 502 254 1799",
    "sg:postcode":"40243",
    "sg:province":"KY",
    "sg:tags":[
        "retirement",
        "hotel",
        "apartment",
        "community",
        "home"
    ],
    "wof:name":"Christian Middletown Village",
    "wof:placetype":"venue"
},
  "geometry": {"coordinates":[-85.54245,38.239552],"type":"Point"}
}