{
  "type": "Feature",
  "properties": {
    "iso:country":"US",
    "sg:address":"12 Price Ave",
    "sg:city":"Erlanger",
    "sg:classifiers":[
        {
            "category":"Retail",
            "subcategory":"Laundry & Dry Cleaning",
            "type":"Services"
        }
    ],
    "sg:phone":"+1 859 727 1344",
    "sg:postcode":"41018",
    "sg:province":"KY",
    "wof:name":"Twin Shirt Laundry",
    "wof:placetype":"venue"
},
  "geometry": {"coordinates":[-84.60649600000001,39.01738],"type":"Point"}
}