{
  "type": "Feature",
  "properties": {
    "addr:full":"505 Chinoe Rd Lexington KY 40502",
    "addr:housenumber":"505",
    "addr:postcode":"40502",
    "addr:street":"Chinoe Rd",
    "iso:country":"US",
    "sg:address":"505 Chinoe Rd",
    "sg:city":"Lexington",
    "sg:classifiers":[
        {
            "category":"Professional",
            "subcategory":"Business Services",
            "type":"Services"
        }
    ],
    "sg:phone":"+1 859 335 6282",
    "sg:postcode":"40502",
    "sg:province":"KY",
    "wof:name":"Market Solutions",
    "wof:placetype":"venue"
},
  "geometry": {"coordinates":[-84.48328600000001,38.017244],"type":"Point"}
}