{
  "type": "Feature",
  "properties": {
    "addr:full":"8500 Pine Valley Trl Louisville KY 40229",
    "addr:housenumber":"8500",
    "addr:postcode":"40229",
    "addr:street":"Pine Valley Trl",
    "iso:country":"US",
    "sg:address":"8500 Pine Valley Trl",
    "sg:city":"Louisville",
    "sg:classifiers":[
        {
            "category":"Banks & Credit Unions",
            "subcategory":"Bank",
            "type":"Services"
        }
    ],
    "sg:phone":"+1 502 239 3869",
    "sg:postcode":"40229",
    "sg:province":"KY",
    "sg:tags":[
        "loan",
        "real estate"
    ],
    "wof:name":"Crestar Mortgage Corp",
    "wof:placetype":"venue"
},
  "geometry": {"coordinates":[-85.609442,38.086307],"type":"Point"}
}