{
  "type": "Feature",
  "properties": {
    "iso:country":"US",
    "sg:address":"600 Fairfield Rd",
    "sg:city":"Coxs Creek",
    "sg:classifiers":[
        {
            "category":"Education",
            "subcategory":"School",
            "type":"Public Place"
        }
    ],
    "sg:phone":"+1 502 350 4685",
    "sg:postcode":"40013",
    "sg:province":"KY",
    "wof:name":"Cox's Creek Christian Academy",
    "wof:placetype":"venue"
},
  "geometry": {"coordinates":[-85.459885,37.903462],"type":"Point"}
}