{
  "type": "Feature",
  "properties": {
    "addr:full":"1018 E New Circle Rd Lexington KY 40505",
    "addr:housenumber":"1018",
    "addr:postcode":"40505",
    "addr:street":"E New Circle Rd",
    "iso:country":"US",
    "sg:address":"1018 E New Circle Rd",
    "sg:city":"Lexington",
    "sg:classifiers":[
        {
            "category":"Professional",
            "subcategory":"Management & Consulting",
            "type":"Services"
        }
    ],
    "sg:phone":"+1 859 253 2783",
    "sg:postcode":"40505",
    "sg:province":"KY",
    "wof:name":"United Methodist Church",
    "wof:placetype":"venue"
},
  "geometry": {"coordinates":[-84.454492,38.03704],"type":"Point"}
}