{
  "type": "Feature",
  "properties": {
    "addr:full":"337 Terry Ln Ft Mitchell KY 41017",
    "addr:housenumber":"337",
    "addr:postcode":"41017",
    "addr:street":"Terry Ln",
    "iso:country":"US",
    "sg:address":"337 Terry Ln",
    "sg:city":"Ft Mitchell",
    "sg:classifiers":[
        {
            "category":"Restaurant",
            "type":"Food & Drink"
        }
    ],
    "sg:menulink":"http://www.allmenus.com/ky/covington/197361-burger-king/menu/",
    "sg:phone":"+1 606 341 1621",
    "sg:postcode":"41017",
    "sg:province":"KY",
    "sg:tags":[
        "burger",
        "american"
    ],
    "wof:name":"Burger King",
    "wof:placetype":"venue"
},
  "geometry": {"coordinates":[-84.578756,39.047094],"type":"Point"}
}