{
  "type": "Feature",
  "properties": {
    "iso:country":"US",
    "sg:address":"68 Audrey Ave",
    "sg:city":"Cadiz",
    "sg:classifiers":[
        {
            "category":"Education",
            "subcategory":"Special Training",
            "type":"Public Place"
        }
    ],
    "sg:phone":"+1 270 924 9609",
    "sg:postcode":"42211",
    "sg:province":"KY",
    "wof:name":"Online Tutoring 4u",
    "wof:placetype":"venue"
},
  "geometry": {"coordinates":[-87.966176,36.816919],"type":"Point"}
}