{
  "type": "Feature",
  "properties": {
    "iso:country":"US",
    "sg:address":"9050 Dixie Hwy",
    "sg:city":"Louisville",
    "sg:classifiers":[
        {
            "category":"Banks & Credit Unions",
            "subcategory":"Bank",
            "type":"Services"
        }
    ],
    "sg:phone":"+1 502 933 4024",
    "sg:postcode":"40258",
    "sg:province":"KY",
    "sg:tags":[
        "state",
        "commercial"
    ],
    "wof:name":"BB&T",
    "wof:placetype":"venue"
},
  "geometry": {"coordinates":[-85.85261800000001,38.125052],"type":"Point"}
}