{
  "type": "Feature",
  "properties": {
    "addr:full":"618 Bob Posey St Henderson KY 42420",
    "addr:housenumber":"618",
    "addr:postcode":"42420",
    "addr:street":"Bob Posey St",
    "iso:country":"US",
    "sg:address":"618 Bob Posey St",
    "sg:city":"Henderson",
    "sg:classifiers":[
        {
            "category":"Professional",
            "subcategory":"Testing Lab",
            "type":"Services"
        }
    ],
    "sg:phone":"+1 270 827 1187",
    "sg:postcode":"42420",
    "sg:province":"KY",
    "sg:tags":[
        "laboratory"
    ],
    "wof:name":"Commercial Testing & Engnrng",
    "wof:placetype":"venue"
},
  "geometry": {"coordinates":[-87.57566300000001,37.840946],"type":"Point"}
}