{
  "type": "Feature",
  "properties": {
    "iso:country":"US",
    "sg:address":"2236 Winchester Ave",
    "sg:city":"Ashland",
    "sg:classifiers":[
        {
            "category":"Manufacturing",
            "subcategory":"Printing",
            "type":"Manufacturing & Wholesale Goods"
        }
    ],
    "sg:phone":"+1 606 324 8222",
    "sg:postcode":"41101",
    "sg:province":"KY",
    "sg:tags":[
        "commercial"
    ],
    "wof:name":"Readmond Printing Inc",
    "wof:placetype":"venue"
},
  "geometry": {"coordinates":[-82.631162,38.474367],"type":"Point"}
}