{
  "type": "Feature",
  "properties": {
    "iso:country":"US",
    "sg:address":"103 S Broad St",
    "sg:city":"London",
    "sg:classifiers":[
        {
            "category":"Government",
            "subcategory":"Office",
            "type":"Public Place"
        }
    ],
    "sg:phone":"+1 606 864 2863",
    "sg:postcode":"40741",
    "sg:province":"KY",
    "sg:website":"www.kycourts.net",
    "wof:name":"Laurel County Circuit Ct Clerk",
    "wof:placetype":"venue"
},
  "geometry": {"coordinates":[-84.08447700000001,37.128366],"type":"Point"}
}