{
  "type": "Feature",
  "properties": {
    "addr:full":"139 Sanders Rd Campbellsville KY 42718",
    "addr:housenumber":"139",
    "addr:postcode":"42718",
    "addr:street":"Sanders Rd",
    "iso:country":"US",
    "sg:address":"139 Sanders Rd",
    "sg:city":"Campbellsville",
    "sg:classifiers":[
        {
            "category":"Farming",
            "subcategory":"Farm",
            "type":"Manufacturing & Wholesale Goods"
        }
    ],
    "sg:phone":"+1 270 465 3337",
    "sg:postcode":"42718",
    "sg:province":"KY",
    "wof:name":"Deener Farms Inc",
    "wof:placetype":"venue"
},
  "geometry": {"coordinates":[-85.39040900000001,37.424971],"type":"Point"}
}