{
  "type": "Feature",
  "properties": {
    "iso:country":"US",
    "sg:address":"1301 Crestmore Dr",
    "sg:city":"Franklin",
    "sg:classifiers":[
        {
            "category":"Social Services",
            "type":"Services"
        }
    ],
    "sg:phone":"+1 270 586 9411",
    "sg:postcode":"42134",
    "sg:province":"KY",
    "sg:tags":[
        "organization",
        "welfare"
    ],
    "wof:name":"Franklin Senior Ctr",
    "wof:placetype":"venue"
},
  "geometry": {"coordinates":[-86.56586299999999,36.711422],"type":"Point"}
}