{
  "type": "Feature",
  "properties": {
    "iso:country":"US",
    "sg:address":"160 N Eagle Creek Dr Ste 101",
    "sg:city":"Lexington",
    "sg:classifiers":[
        {
            "category":"Health Services",
            "subcategory":"Hospital",
            "type":"Services"
        },
        {
            "category":"Government",
            "subcategory":"Office",
            "type":"Public Place"
        },
        {
            "category":"Health Services",
            "subcategory":"Clinic",
            "type":"Services"
        }
    ],
    "sg:phone":"+1 859 967 5613",
    "sg:postcode":"40509",
    "sg:province":"KY",
    "sg:tags":[
        "state",
        "government-united",
        "cancer",
        "treatment"
    ],
    "sg:website":"http://www.saintjosephbreastcenter.org",
    "wof:name":"Saint Joseph Breast Center",
    "wof:placetype":"venue"
},
  "geometry": {"coordinates":[-84.439972,38.000629],"type":"Point"}
}