{
  "type": "Feature",
  "properties": {
    "iso:country":"US",
    "sg:address":"9482 Brownsboro Rd",
    "sg:city":"Louisville",
    "sg:classifiers":[
        {
            "category":"Retail",
            "subcategory":"Veterinary Services",
            "type":"Services"
        }
    ],
    "sg:phone":"+1 502 412 6322",
    "sg:postcode":"40241",
    "sg:province":"KY",
    "sg:tags":[
        "veterinarian"
    ],
    "wof:name":"Dr John's Pet Care Clinic",
    "wof:placetype":"venue"
},
  "geometry": {"coordinates":[-85.574855,38.307129],"type":"Point"}
}