{
  "type": "Feature",
  "properties": {
    "iso:country":"US",
    "sg:address":"240 Dixie Hwy S",
    "sg:city":"Radcliff",
    "sg:classifiers":[
        {
            "category":"Retail",
            "subcategory":"Auto Repair",
            "type":"Services"
        }
    ],
    "sg:phone":"+1 270 351 5505",
    "sg:postcode":"40160",
    "sg:province":"KY",
    "sg:tags":[
        "repairing",
        "automobile"
    ],
    "wof:name":"L & R Automotive",
    "wof:placetype":"venue"
},
  "geometry": {"coordinates":[-85.936305,37.837931],"type":"Point"}
}