{
  "type": "Feature",
  "properties": {
    "addr:full":"1293 N Main St Monticello KY 42633",
    "addr:housenumber":"1293",
    "addr:postcode":"42633",
    "addr:street":"N Main St",
    "iso:country":"US",
    "sg:address":"1293 N Main St",
    "sg:city":"Monticello",
    "sg:classifiers":[
        {
            "category":"Shopping",
            "subcategory":"Florist",
            "type":"Retail Goods"
        }
    ],
    "sg:phone":"+1 606 348 9923",
    "sg:postcode":"42633",
    "sg:province":"KY",
    "wof:name":"Klassic Bouquet Florist",
    "wof:placetype":"venue"
},
  "geometry": {"coordinates":[-84.836761,36.847913],"type":"Point"}
}