{
  "type": "Feature",
  "properties": {
    "addr:full":"6801 Dixie Hwy Louisville KY 40258",
    "addr:housenumber":"6801",
    "addr:postcode":"40258",
    "addr:street":"Dixie Hwy",
    "iso:country":"US",
    "sg:address":"6801 Dixie Hwy",
    "sg:city":"Louisville",
    "sg:classifiers":[
        {
            "category":"Restaurant",
            "type":"Food & Drink"
        }
    ],
    "sg:menulink":"http://www.allmenus.com/ky/jefferson-southwest/163697-skyline-chili/menu/",
    "sg:phone":"+1 502 937 4020",
    "sg:postcode":"40258",
    "sg:province":"KY",
    "sg:tags":[
        "mexican"
    ],
    "wof:name":"Skyline Chili",
    "wof:placetype":"venue"
},
  "geometry": {"coordinates":[-85.836438,38.151835],"type":"Point"}
}