{
  "type": "Feature",
  "properties": {
    "iso:country":"US",
    "sg:address":"12404 Ledges Dr",
    "sg:city":"Louisville",
    "sg:classifiers":[
        {
            "category":"Building & Trades",
            "subcategory":"Construction",
            "type":"Services"
        }
    ],
    "sg:phone":"+1 502 244 4931",
    "sg:postcode":"40243",
    "sg:province":"KY",
    "sg:tags":[
        "house"
    ],
    "wof:name":"Brenda Baumler LLC",
    "wof:placetype":"venue"
},
  "geometry": {"coordinates":[-85.523916,38.235724],"type":"Point"}
}