{
  "type": "Feature",
  "properties": {
    "iso:country":"US",
    "sg:address":"1016 Summitt Rd",
    "sg:city":"Ashland",
    "sg:classifiers":[
        {
            "category":"Education",
            "subcategory":"Library",
            "type":"Public Place"
        }
    ],
    "sg:phone":"+1 606 928 3366",
    "sg:postcode":"41102",
    "sg:province":"KY",
    "wof:name":"Boyd County Public Library",
    "wof:placetype":"venue"
},
  "geometry": {"coordinates":[-82.69957599999999,38.432187],"type":"Point"}
}