{
  "type": "Feature",
  "properties": {
    "iso:country":"US",
    "sg:address":"644 Plum Springs Rd",
    "sg:city":"Bowling Green",
    "sg:classifiers":[
        {
            "category":"Building & Trades",
            "subcategory":"Construction",
            "type":"Services"
        }
    ],
    "sg:phone":"+1 270 781 9171",
    "sg:postcode":"42101",
    "sg:province":"KY",
    "sg:tags":[
        "hanging",
        "contractor"
    ],
    "wof:name":"Kr Painting LLC",
    "wof:placetype":"venue"
},
  "geometry": {"coordinates":[-86.383543,37.019958],"type":"Point"}
}