{
  "type": "Feature",
  "properties": {
    "iso:country":"US",
    "sg:address":"2804 Dumesnil St",
    "sg:city":"Louisville",
    "sg:classifiers":[
        {
            "category":"Personal",
            "subcategory":"Barber",
            "type":"Services"
        }
    ],
    "sg:phone":"+1 502 778 1867",
    "sg:postcode":"40211",
    "sg:province":"KY",
    "wof:name":"Shontee's Barber Shop",
    "wof:placetype":"venue"
},
  "geometry": {"coordinates":[-85.800967,38.236729],"type":"Point"}
}