{
  "type": "Feature",
  "properties": {
    "iso:country":"US",
    "sg:address":"641 E 4th St",
    "sg:city":"Russellville",
    "sg:classifiers":[
        {
            "category":"Real Estate",
            "subcategory":"Real Estate Agent",
            "type":"Services"
        }
    ],
    "sg:phone":"+1 270 542 7653",
    "sg:postcode":"42276",
    "sg:province":"KY",
    "wof:name":"Remax Realty Team",
    "wof:placetype":"venue"
},
  "geometry": {"coordinates":[-86.878784,36.847593],"type":"Point"}
}