{
  "type": "Feature",
  "properties": {
    "iso:country":"US",
    "sg:address":"465 Purdy-Sano Rd",
    "sg:city":"Columbia",
    "sg:classifiers":[
        {
            "category":"Freight",
            "type":"Transportation"
        }
    ],
    "sg:phone":"+1 270 384 4748",
    "sg:postcode":"42728",
    "sg:province":"KY",
    "sg:tags":[
        "operator",
        "mover",
        "local",
        "trucking"
    ],
    "wof:name":"Burton's Moving",
    "wof:placetype":"venue"
},
  "geometry": {"coordinates":[-85.175831,37.14872],"type":"Point"}
}