{
  "type": "Feature",
  "properties": {
    "addr:full":"115 E Main St Princeton KY 42445",
    "addr:housenumber":"115",
    "addr:postcode":"42445",
    "addr:street":"E Main St",
    "iso:country":"US",
    "sg:address":"115 E Main St",
    "sg:city":"Princeton",
    "sg:classifiers":[
        {
            "category":"Shopping",
            "type":"Retail Goods"
        }
    ],
    "sg:phone":"+1 270 365 3959",
    "sg:postcode":"42445",
    "sg:province":"KY",
    "sg:tags":[
        "art",
        "gallery",
        "dealer"
    ],
    "wof:name":"Princeton Art Guild",
    "wof:placetype":"venue"
},
  "geometry": {"coordinates":[-87.881877,37.108613],"type":"Point"}
}