{
  "type": "Feature",
  "properties": {
    "addr:full":"1589 Production Dr Burlington KY 41005",
    "addr:housenumber":"1589",
    "addr:postcode":"41005",
    "addr:street":"Production Dr",
    "iso:country":"US",
    "sg:address":"1589 Production Dr",
    "sg:city":"Burlington",
    "sg:classifiers":[
        {
            "category":"Banks & Credit Unions",
            "subcategory":"Bank",
            "type":"Services"
        }
    ],
    "sg:phone":"+1 859 282 7111",
    "sg:postcode":"41005",
    "sg:province":"KY",
    "sg:tags":[
        "loan",
        "real estate"
    ],
    "wof:name":"T D Stout Preservation",
    "wof:placetype":"venue"
},
  "geometry": {"coordinates":[-84.68763800000001,39.022113],"type":"Point"}
}