{
  "type": "Feature",
  "properties": {
    "iso:country":"US",
    "sg:address":"5326 US Hwy 60",
    "sg:city":"Owingsville",
    "sg:classifiers":[
        {
            "category":"Wholesale",
            "subcategory":"Auto Parts",
            "type":"Manufacturing & Wholesale Goods"
        }
    ],
    "sg:phone":"+1 606 674 6155",
    "sg:postcode":"40360",
    "sg:province":"KY",
    "sg:tags":[
        "automobile",
        "rebuilt"
    ],
    "wof:name":"Vance's Auto Parts",
    "wof:placetype":"venue"
},
  "geometry": {"coordinates":[-83.676773,38.136605],"type":"Point"}
}