{
  "type": "Feature",
  "properties": {
    "iso:country":"US",
    "sg:address":"2960 Fawn Dr",
    "sg:city":"Burlington",
    "sg:classifiers":[
        {
            "category":"Building & Trades",
            "subcategory":"Construction",
            "type":"Services"
        }
    ],
    "sg:phone":"+1 859 586 4002",
    "sg:postcode":"41005",
    "sg:province":"KY",
    "sg:tags":[
        "house"
    ],
    "wof:name":"Gibson Construction Inc",
    "wof:placetype":"venue"
},
  "geometry": {"coordinates":[-84.72324399999999,39.058955],"type":"Point"}
}