{
  "type": "Feature",
  "properties": {
    "iso:country":"US",
    "sg:address":"407 W Shelby St",
    "sg:city":"Falmouth",
    "sg:classifiers":[
        {
            "category":"Retail",
            "subcategory":"Funeral Services",
            "type":"Services"
        }
    ],
    "sg:phone":"+1 859 654 6942",
    "sg:postcode":"41040",
    "sg:province":"KY",
    "sg:tags":[
        "director"
    ],
    "wof:name":"Peoples Funeral Home Inc",
    "wof:placetype":"venue"
},
  "geometry": {"coordinates":[-84.33395299999999,38.678104],"type":"Point"}
}