{
  "type": "Feature",
  "properties": {
    "addr:full":"602 Main St Elsmere KY 41018",
    "addr:housenumber":"602",
    "addr:postcode":"41018",
    "addr:street":"Main St",
    "iso:country":"US",
    "sg:address":"602 Main St",
    "sg:city":"Elsmere",
    "sg:classifiers":[
        {
            "category":"Manufacturing",
            "subcategory":"Tools & Machinery",
            "type":"Manufacturing & Wholesale Goods"
        }
    ],
    "sg:phone":"+1 859 727 9900",
    "sg:postcode":"41018",
    "sg:province":"KY",
    "sg:tags":[
        "machine",
        "shop"
    ],
    "wof:name":"Martin Machining Svc",
    "wof:placetype":"venue"
},
  "geometry": {"coordinates":[-84.603807,39.005803],"type":"Point"}
}