{
  "type": "Feature",
  "properties": {
    "iso:country":"US",
    "sg:address":"254 S Buckman St",
    "sg:city":"Shepherdsville",
    "sg:classifiers":[
        {
            "category":"Organizations",
            "subcategory":"Religious Organization",
            "type":"Services"
        }
    ],
    "sg:phone":"+1 502 543 7721",
    "sg:postcode":"40165",
    "sg:province":"KY",
    "sg:tags":[
        "church"
    ],
    "sg:website":"www.shepfbc.org",
    "wof:name":"First Baptist Church",
    "wof:placetype":"venue"
},
  "geometry": {"coordinates":[-85.716294,37.988869],"type":"Point"}
}