{
  "type": "Feature",
  "properties": {
    "iso:country":"US",
    "sg:address":"1815 Kingsford Dr",
    "sg:city":"Louisville",
    "sg:classifiers":[
        {
            "category":"Building & Trades",
            "subcategory":"Construction",
            "type":"Services"
        }
    ],
    "sg:phone":"+1 502 447 9898",
    "sg:postcode":"40216",
    "sg:province":"KY",
    "sg:tags":[
        "house"
    ],
    "wof:name":"Bryan Building & Remodeling",
    "wof:placetype":"venue"
},
  "geometry": {"coordinates":[-85.825123,38.17306],"type":"Point"}
}