{
  "type": "Feature",
  "properties": {
    "iso:country":"US",
    "sg:address":"209 2nd St",
    "sg:city":"Pikeville",
    "sg:classifiers":[
        {
            "category":"Professional",
            "subcategory":"Lawyer & Legal Services",
            "type":"Services"
        }
    ],
    "sg:phone":"+1 606 437 0911",
    "sg:postcode":"41501",
    "sg:province":"KY",
    "sg:tags":[
        "attorney"
    ],
    "wof:name":"Lon M Johnson Jr",
    "wof:placetype":"venue"
},
  "geometry": {"coordinates":[-82.518078,37.480163],"type":"Point"}
}