{
  "type": "Feature",
  "properties": {
    "iso:country":"US",
    "sg:address":"877 E 11th Ave",
    "sg:city":"Bowling Green",
    "sg:classifiers":[
        {
            "category":"Education",
            "subcategory":"School",
            "type":"Public Place"
        }
    ],
    "sg:phone":"+1 270 746 2321",
    "sg:postcode":"42101",
    "sg:province":"KY",
    "wof:name":"Eleventh Street Alt School",
    "wof:placetype":"venue"
},
  "geometry": {"coordinates":[-86.438299,36.985627],"type":"Point"}
}