{
  "type": "Feature",
  "properties": {
    "iso:country":"US",
    "sg:address":"9918 Pentel Ln",
    "sg:city":"Louisville",
    "sg:classifiers":[
        {
            "category":"Building & Trades",
            "subcategory":"Construction",
            "type":"Services"
        }
    ],
    "sg:phone":"+1 502 817 6485",
    "sg:postcode":"40291",
    "sg:province":"KY",
    "sg:tags":[
        "restoration",
        "cleaning",
        "patio",
        "deck"
    ],
    "wof:name":"Cardinal Pressure Cleaning",
    "wof:placetype":"venue"
},
  "geometry": {"coordinates":[-85.57242100000001,38.1667],"type":"Point"}
}