{
  "type": "Feature",
  "properties": {
    "iso:country":"US",
    "sg:address":"2365 State Hwy 721",
    "sg:city":"Hazard",
    "sg:classifiers":[
        {
            "category":"Manufacturing",
            "subcategory":"Lumber",
            "type":"Manufacturing & Wholesale Goods"
        }
    ],
    "sg:phone":"+1 606 251 3946",
    "sg:postcode":"41701",
    "sg:province":"KY",
    "sg:tags":[
        "company",
        "logging"
    ],
    "wof:name":"Jerry Smith Logging",
    "wof:placetype":"venue"
},
  "geometry": {"coordinates":[-83.100792,37.326005],"type":"Point"}
}