{
  "type": "Feature",
  "properties": {
    "addr:full":"11901 Standiford Plaza Dr Louisville KY 40229",
    "addr:housenumber":"11901",
    "addr:postcode":"40229",
    "addr:street":"Standiford Plaza Dr",
    "iso:country":"US",
    "sg:address":"11901 Standiford Plaza Dr",
    "sg:city":"Louisville",
    "sg:classifiers":[
        {
            "category":"Retail",
            "subcategory":"Portrait Studio",
            "type":"Services"
        },
        {
            "category":"Professional",
            "subcategory":"Art Services",
            "type":"Services"
        }
    ],
    "sg:phone":"+1 502 968 4347",
    "sg:postcode":"40229",
    "sg:province":"KY",
    "sg:tags":[
        "rental",
        "photographers-portrait",
        "photographic",
        "darkroom"
    ],
    "sg:website":"http://www.cpicorp.com",
    "wof:name":"Cpi Corp.",
    "wof:placetype":"venue"
},
  "geometry": {"coordinates":[-85.667641,38.089859],"type":"Point"}
}