{
  "type": "Feature",
  "properties": {
    "addr:full":"571 Charlemagne Blvd Elizabethtown KY 42701",
    "addr:housenumber":"571",
    "addr:postcode":"42701",
    "addr:street":"Charlemagne Blvd",
    "iso:country":"US",
    "sg:address":"571 Charlemagne Blvd",
    "sg:city":"Elizabethtown",
    "sg:classifiers":[
        {
            "category":"Wholesale",
            "subcategory":"Furniture",
            "type":"Manufacturing & Wholesale Goods"
        }
    ],
    "sg:phone":"+1 270 769 6399",
    "sg:postcode":"42701",
    "sg:province":"KY",
    "wof:name":"Heartland Furniture Distr",
    "wof:placetype":"venue"
},
  "geometry": {"coordinates":[-85.88919799999999,37.691906],"type":"Point"}
}