{
  "type": "Feature",
  "properties": {
    "iso:country":"US",
    "sg:address":"3340 Old Mill Rd",
    "sg:city":"Brandenburg",
    "sg:classifiers":[
        {
            "category":"Personal",
            "subcategory":"Beauty Salon",
            "type":"Services"
        }
    ],
    "sg:phone":"+1 270 828 2728",
    "sg:postcode":"40108",
    "sg:province":"KY",
    "wof:name":"Jean's Beauty Boutique",
    "wof:placetype":"venue"
},
  "geometry": {"coordinates":[-86.097781,37.950984],"type":"Point"}
}