{
  "type": "Feature",
  "properties": {
    "iso:country":"US",
    "sg:address":"331 Country Manor Ln",
    "sg:city":"Shepherdsville",
    "sg:classifiers":[
        {
            "category":"Insurance",
            "subcategory":"Insurance Agent",
            "type":"Services"
        }
    ],
    "sg:phone":"+1 502 955 6717",
    "sg:postcode":"40165",
    "sg:province":"KY",
    "wof:name":"Modern Woodmen Of America",
    "wof:placetype":"venue"
},
  "geometry": {"coordinates":[-85.609385,37.972965],"type":"Point"}
}