{
  "type": "Feature",
  "properties": {
    "addr:full":"950 Breckenridge Ln Louisville KY 40207",
    "addr:housenumber":"950",
    "addr:postcode":"40207",
    "addr:street":"Breckenridge Ln",
    "iso:country":"US",
    "sg:address":"950 Breckenridge Ln",
    "sg:city":"Louisville",
    "sg:classifiers":[
        {
            "category":"Insurance",
            "subcategory":"Insurance Agent",
            "type":"Services"
        }
    ],
    "sg:phone":"+1 502 899 7033",
    "sg:postcode":"40207",
    "sg:province":"KY",
    "wof:name":"Shorman Stevens & Associates",
    "wof:placetype":"venue"
},
  "geometry": {"coordinates":[-85.641385,38.235568],"type":"Point"}
}