{
  "type": "Feature",
  "properties": {
    "addr:full":"11406 Ballardsville Rd Louisville KY 40241",
    "addr:housenumber":"11406",
    "addr:postcode":"40241",
    "addr:street":"Ballardsville Rd",
    "iso:country":"US",
    "sg:address":"11406 Ballardsville Rd",
    "sg:city":"Louisville",
    "sg:classifiers":[
        {
            "category":"Organizations",
            "subcategory":"Religious Organization",
            "type":"Services"
        }
    ],
    "sg:phone":"+1 502 241 7659",
    "sg:postcode":"40241",
    "sg:province":"KY",
    "sg:tags":[
        "church"
    ],
    "wof:name":"Hillcrest Baptist Church",
    "wof:placetype":"venue"
},
  "geometry": {"coordinates":[-85.535462,38.317539],"type":"Point"}
}