{
  "type": "Feature",
  "properties": {
    "iso:country":"US",
    "sg:address":"275 Richmond St",
    "sg:city":"Mt Vernon",
    "sg:classifiers":[
        {
            "category":"Retail",
            "subcategory":"Auto Repair",
            "type":"Services"
        }
    ],
    "sg:phone":"+1 606 256 4210",
    "sg:postcode":"40456",
    "sg:province":"KY",
    "sg:tags":[
        "body",
        "automobile",
        "painting"
    ],
    "wof:name":"Central Body Svc",
    "wof:placetype":"venue"
},
  "geometry": {"coordinates":[-84.339893,37.356487],"type":"Point"}
}