{
  "type": "Feature",
  "properties": {
    "iso:country":"US",
    "sg:address":"802 Scott Blvd",
    "sg:city":"Covington",
    "sg:classifiers":[
        {
            "category":"Health Services",
            "subcategory":"Doctor",
            "type":"Services"
        }
    ],
    "sg:phone":"+1 859 581 2212",
    "sg:postcode":"41011",
    "sg:province":"KY",
    "sg:tags":[
        "physician",
        "surgeon"
    ],
    "wof:name":"Tri-State Centers For Sight",
    "wof:placetype":"venue"
},
  "geometry": {"coordinates":[-84.508022,39.082176],"type":"Point"}
}