{
  "type": "Feature",
  "properties": {
    "addr:full":"501 E Main St Stanford KY 40484",
    "addr:housenumber":"501",
    "addr:postcode":"40484",
    "addr:street":"E Main St",
    "iso:country":"US",
    "sg:address":"501 E Main St",
    "sg:city":"Stanford",
    "sg:classifiers":[
        {
            "category":"Personal",
            "subcategory":"Beauty Salon",
            "type":"Services"
        }
    ],
    "sg:phone":"+1 606 365 9745",
    "sg:postcode":"40484",
    "sg:province":"KY",
    "wof:name":"Magic Wand Beauty Salon",
    "wof:placetype":"venue"
},
  "geometry": {"coordinates":[-84.65858900000001,37.52972],"type":"Point"}
}