{
  "type": "Feature",
  "properties": {
    "iso:country":"US",
    "sg:address":"6213 S Watterson Trl",
    "sg:city":"Louisville",
    "sg:classifiers":[
        {
            "category":"Building & Trades",
            "subcategory":"Construction",
            "type":"Services"
        }
    ],
    "sg:phone":"+1 502 231 8383",
    "sg:postcode":"40291",
    "sg:province":"KY",
    "sg:tags":[
        "home",
        "improvement"
    ],
    "wof:name":"Burkhead & Son Remodeling",
    "wof:placetype":"venue"
},
  "geometry": {"coordinates":[-85.61456200000001,38.156564],"type":"Point"}
}