{
  "type": "Feature",
  "properties": {
    "iso:country":"US",
    "sg:address":"3213 Rosewedge Way",
    "sg:city":"Louisville",
    "sg:classifiers":[
        {
            "category":"Wholesale",
            "subcategory":"Hardware",
            "type":"Manufacturing & Wholesale Goods"
        }
    ],
    "sg:phone":"+1 502 449 3646",
    "sg:postcode":"40216",
    "sg:province":"KY",
    "sg:tags":[
        "refrigerating"
    ],
    "wof:name":"Jordan Refrigeration Co Inc",
    "wof:placetype":"venue"
},
  "geometry": {"coordinates":[-85.84924700000001,38.18375],"type":"Point"}
}