{
  "type": "Feature",
  "properties": {
    "iso:country":"US",
    "sg:address":"3400 State Hwy 1498",
    "sg:city":"Bevinsville",
    "sg:classifiers":[
        {
            "category":"Organizations",
            "subcategory":"Religious Organization",
            "type":"Services"
        }
    ],
    "sg:phone":"+1 606 452 2721",
    "sg:postcode":"41606",
    "sg:province":"KY",
    "wof:name":"Little Rock Church",
    "wof:placetype":"venue"
},
  "geometry": {"coordinates":[-82.74382900000001,37.348281],"type":"Point"}
}