{
  "type": "Feature",
  "properties": {
    "addr:full":"321 E Breckinridge St Louisville KY 40203",
    "addr:housenumber":"321",
    "addr:postcode":"40203",
    "addr:street":"E Breckinridge St",
    "iso:country":"US",
    "sg:address":"321 E Breckinridge St",
    "sg:city":"Louisville",
    "sg:classifiers":[
        {
            "category":"Professional",
            "subcategory":"Computer Services",
            "type":"Services"
        }
    ],
    "sg:phone":"+1 502 589 4638",
    "sg:postcode":"40203",
    "sg:province":"KY",
    "sg:tags":[
        "internet"
    ],
    "sg:website":"www.bluegrass.net",
    "wof:name":"Bluegrass Net",
    "wof:placetype":"venue"
},
  "geometry": {"coordinates":[-85.748673,38.240849],"type":"Point"}
}