{
  "type": "Feature",
  "properties": {
    "iso:country":"US",
    "sg:address":"514 Taylorsville Rd",
    "sg:city":"Taylorsville",
    "sg:classifiers":[
        {
            "category":"Social Services",
            "type":"Services"
        }
    ],
    "sg:phone":"+1 502 477 3222",
    "sg:postcode":"40071",
    "sg:province":"KY",
    "sg:tags":[
        "government"
    ],
    "wof:name":"Spencer County Youth Svc Ctr",
    "wof:placetype":"venue"
},
  "geometry": {"coordinates":[-85.340749,38.035611],"type":"Point"}
}