{
  "type": "Feature",
  "properties": {
    "iso:country":"US",
    "sg:address":"2066 Corinth Cemetary Rd",
    "sg:city":"Corbin",
    "sg:classifiers":[
        {
            "category":"Building & Trades",
            "subcategory":"Construction",
            "type":"Services"
        }
    ],
    "sg:phone":"+1 606 523 0208",
    "sg:postcode":"40701",
    "sg:province":"KY",
    "sg:tags":[
        "house",
        "ma"
    ],
    "wof:name":"Watkins Fencing",
    "wof:placetype":"venue"
},
  "geometry": {"coordinates":[-84.145927,36.882215],"type":"Point"}
}