{
  "type": "Feature",
  "properties": {
    "iso:country":"US",
    "sg:address":"436 Stone Rd",
    "sg:city":"Paris",
    "sg:classifiers":[
        {
            "category":"Building & Trades",
            "subcategory":"Construction",
            "type":"Services"
        }
    ],
    "sg:phone":"+1 859 362 9203",
    "sg:postcode":"40361",
    "sg:province":"KY",
    "sg:tags":[
        "house"
    ],
    "wof:name":"H&H Construction",
    "wof:placetype":"venue"
},
  "geometry": {"coordinates":[-84.063126,38.199186],"type":"Point"}
}