{
  "type": "Feature",
  "properties": {
    "iso:country":"US",
    "sg:address":"304 W Main St",
    "sg:city":"Danville",
    "sg:classifiers":[
        {
            "category":"Banks & Credit Unions",
            "subcategory":"Financial Services",
            "type":"Services"
        }
    ],
    "sg:phone":"+1 859 236 2926",
    "sg:postcode":"40422",
    "sg:province":"KY",
    "sg:tags":[
        "company",
        "holding"
    ],
    "wof:name":"Boyle Bancorp",
    "wof:placetype":"venue"
},
  "geometry": {"coordinates":[-84.773983,37.645844],"type":"Point"}
}