{
  "type": "Feature",
  "properties": {
    "addr:full":"21739 US Hwy 60 Olive Hill KY 41164",
    "addr:postcode":"21739;41164",
    "addr:street":"Us Hwy 60 Olive Hill",
    "iso:country":"US",
    "sg:address":"21739 US Hwy 60",
    "sg:city":"Olive Hill",
    "sg:classifiers":[
        {
            "category":"Autos & Motor Vehicles",
            "subcategory":"Automobile Sales",
            "type":"Retail Goods"
        }
    ],
    "sg:phone":"+1 606 286 5746",
    "sg:postcode":"41164",
    "sg:province":"KY",
    "sg:tags":[
        "used"
    ],
    "wof:name":"U-Save Auto Rental",
    "wof:placetype":"venue"
},
  "geometry": {"coordinates":[-83.297264,38.286426],"type":"Point"}
}