{
  "type": "Feature",
  "properties": {
    "iso:country":"US",
    "sg:address":"501 S 4th Ave",
    "sg:city":"Louisville",
    "sg:classifiers":[
        {
            "category":"Social Services",
            "subcategory":"Adult Care",
            "type":"Services"
        }
    ],
    "sg:phone":"+1 502 719 1600",
    "sg:postcode":"40202",
    "sg:province":"KY",
    "sg:tags":[
        "home",
        "residential"
    ],
    "wof:name":"Atria Senior Living Group",
    "wof:placetype":"venue"
},
  "geometry": {"coordinates":[-85.757667,38.250137],"type":"Point"}
}