{
  "type": "Feature",
  "properties": {
    "addr:full":"16147 Owensboro Rd Falls Of Rough KY 40119",
    "addr:postcode":"16147;40119",
    "addr:street":"Owensboro Rd",
    "iso:country":"US",
    "sg:address":"16147 Owensboro Rd",
    "sg:city":"Falls Of Rough",
    "sg:phone":"+1 270 879 8739",
    "sg:postcode":"40119",
    "sg:province":"KY",
    "sg:tags":[
        "farm",
        "tobacco"
    ],
    "wof:name":"Eugene Duggins",
    "wof:placetype":"venue"
},
  "geometry": {"coordinates":[-86.55370499999999,37.522297],"type":"Point"}
}