{
  "type": "Feature",
  "properties": {
    "iso:country":"US",
    "sg:address":"119 Hunters Trce",
    "sg:city":"Frankfort",
    "sg:classifiers":[
        {
            "category":"Autos & Motor Vehicles",
            "subcategory":"Automobile Sales",
            "type":"Retail Goods"
        }
    ],
    "sg:phone":"+1 502 695 6100",
    "sg:postcode":"40601",
    "sg:province":"KY",
    "sg:tags":[
        "car",
        "dealer"
    ],
    "sg:website":"www.hondaoffrankfort.com",
    "wof:name":"Honda Of Frankfort",
    "wof:placetype":"venue"
},
  "geometry": {"coordinates":[-84.936784,38.176237],"type":"Point"}
}