{
  "type": "Feature",
  "properties": {
    "iso:country":"US",
    "sg:address":"945 Dawson Rd",
    "sg:city":"Princeton",
    "sg:classifiers":[
        {
            "category":"Organizations",
            "subcategory":"Non-profit Organization",
            "type":"Services"
        }
    ],
    "sg:phone":"+1 270 365 9416",
    "sg:postcode":"42445",
    "sg:province":"KY",
    "wof:name":"Pennyroyal Industries Inc",
    "wof:placetype":"venue"
},
  "geometry": {"coordinates":[-87.862689,37.118673],"type":"Point"}
}