{
  "type": "Feature",
  "properties": {
    "iso:country":"US",
    "sg:address":"513 Highland Ave",
    "sg:city":"Carrollton",
    "sg:classifiers":[
        {
            "category":"Professional",
            "subcategory":"Accounting & Tax Preparation",
            "type":"Services"
        }
    ],
    "sg:phone":"+1 502 732 6655",
    "sg:postcode":"41008",
    "sg:province":"KY",
    "sg:tags":[
        "accountant"
    ],
    "sg:website":"www.rzwcpas.com",
    "wof:name":"Raisor Zapp & Woods",
    "wof:placetype":"venue"
},
  "geometry": {"coordinates":[-85.178231,38.681273],"type":"Point"}
}