{
  "type": "Feature",
  "properties": {
    "iso:country":"US",
    "sg:address":"201 E Broadway St",
    "sg:city":"Campbellsville",
    "sg:classifiers":[
        {
            "category":"Insurance",
            "subcategory":"Insurance Agent",
            "type":"Services"
        }
    ],
    "sg:phone":"+1 270 465 5502",
    "sg:postcode":"42718",
    "sg:province":"KY",
    "wof:name":"Jessie Insurance",
    "wof:placetype":"venue"
},
  "geometry": {"coordinates":[-85.343935,37.342372],"type":"Point"}
}