{
  "type": "Feature",
  "properties": {
    "addr:full":"201 Filter Plant Rd Franklin KY 42134",
    "addr:housenumber":"201",
    "addr:postcode":"42134",
    "addr:street":"Filter Plant Rd",
    "iso:country":"US",
    "sg:address":"201 Filter Plant Rd",
    "sg:city":"Franklin",
    "sg:classifiers":[
        {
            "category":"Manufacturing",
            "subcategory":"Tools & Machinery",
            "type":"Manufacturing & Wholesale Goods"
        }
    ],
    "sg:phone":"+1 270 586 0744",
    "sg:postcode":"42134",
    "sg:province":"KY",
    "sg:tags":[
        "machine"
    ],
    "wof:name":"A & S Tool & Gage",
    "wof:placetype":"venue"
},
  "geometry": {"coordinates":[-86.553939,36.722063],"type":"Point"}
}