{
  "type": "Feature",
  "properties": {
    "addr:full":"101 Grayson Way Georgetown KY 40324",
    "addr:housenumber":"101",
    "addr:postcode":"40324",
    "addr:street":"Grayson Way",
    "iso:country":"US",
    "sg:address":"101 Grayson Way",
    "sg:city":"Georgetown",
    "sg:classifiers":[
        {
            "category":"Organizations",
            "subcategory":"Religious Organization",
            "type":"Services"
        }
    ],
    "sg:phone":"+1 502 863 1261",
    "sg:postcode":"40324",
    "sg:province":"KY",
    "wof:name":"Georgetown Evang Free Church",
    "wof:placetype":"venue"
},
  "geometry": {"coordinates":[-84.608361,38.179221],"type":"Point"}
}