{
  "type": "Feature",
  "properties": {
    "iso:country":"US",
    "sg:address":"324 S Main St",
    "sg:city":"Versailles",
    "sg:classifiers":[
        {
            "category":"Retail",
            "subcategory":"Animal Services",
            "type":"Services"
        }
    ],
    "sg:phone":"+1 859 259 0079",
    "sg:postcode":"40383",
    "sg:province":"KY",
    "sg:tags":[
        "pet",
        "training"
    ],
    "wof:name":"Best Friends Obedience Inc",
    "wof:placetype":"venue"
},
  "geometry": {"coordinates":[-84.729671,38.046617],"type":"Point"}
}