{
  "type": "Feature",
  "properties": {
    "iso:country":"US",
    "sg:address":"95 Harlan St",
    "sg:city":"Crittenden",
    "sg:classifiers":[
        {
            "category":"Shopping",
            "subcategory":"Clothing, Apparel, & Fashions",
            "type":"Retail Goods"
        }
    ],
    "sg:phone":"+1 859 428 2796",
    "sg:postcode":"41030",
    "sg:province":"KY",
    "sg:tags":[
        "sportswear"
    ],
    "wof:name":"Extreme Sportswear Inc",
    "wof:placetype":"venue"
},
  "geometry": {"coordinates":[-84.604755,38.781637],"type":"Point"}
}