{
  "type": "Feature",
  "properties": {
    "addr:full":"7100 Alexandria Pike Alexandria KY 41001",
    "addr:housenumber":"7100",
    "addr:postcode":"41001",
    "addr:street":"Alexandria Pike",
    "iso:country":"US",
    "sg:address":"7100 Alexandria Pike",
    "sg:city":"Alexandria",
    "sg:classifiers":[
        {
            "category":"Restaurant",
            "type":"Food & Drink"
        }
    ],
    "sg:phone":"+1 859 635 4400",
    "sg:postcode":"41001",
    "sg:province":"KY",
    "sg:tags":[
        "mexican"
    ],
    "sg:website":"www.skylinechili.com",
    "wof:name":"Skyline Chili",
    "wof:placetype":"venue"
},
  "geometry": {"coordinates":[-84.400434,38.983556],"type":"Point"}
}