{
  "type": "Feature",
  "properties": {
    "iso:country":"US",
    "sg:address":"304 N 2nd St",
    "sg:city":"Ironton",
    "sg:classifiers":[
        {
            "category":"Health Services",
            "subcategory":"Doctor",
            "type":"Services"
        }
    ],
    "sg:phone":"+1 740 532 2282",
    "sg:postcode":"45638",
    "sg:province":"OH",
    "sg:tags":[
        "physician",
        "surgeon",
        "medical"
    ],
    "wof:name":"Ironton Family Medical Centers",
    "wof:placetype":"venue"
},
  "geometry": {"coordinates":[-82.68898799999999,38.538479],"type":"Point"}
}