{
  "type": "Feature",
  "properties": {
    "iso:country":"US",
    "sg:address":"3894 Bacon Creek Rd",
    "sg:city":"Bonnieville",
    "sg:classifiers":[
        {
            "category":"Building & Trades",
            "subcategory":"Construction",
            "type":"Services"
        }
    ],
    "sg:phone":"+1 270 531 6633",
    "sg:postcode":"42713",
    "sg:province":"KY",
    "sg:tags":[
        "general",
        "contractor"
    ],
    "wof:name":"Hilltop Construction",
    "wof:placetype":"venue"
},
  "geometry": {"coordinates":[-85.845805,37.403052],"type":"Point"}
}