{
  "type": "Feature",
  "properties": {
    "addr:full":"305 W Walters Rd Horse Cave KY 42749",
    "addr:housenumber":"305",
    "addr:postcode":"42749",
    "addr:street":"W Walters Rd",
    "iso:country":"US",
    "sg:address":"305 W Walters Rd",
    "sg:city":"Horse Cave",
    "sg:classifiers":[
        {
            "category":"Farming",
            "subcategory":"Livestock Farm",
            "type":"Manufacturing & Wholesale Goods"
        }
    ],
    "sg:phone":"+1 270 786 1786",
    "sg:postcode":"42749",
    "sg:province":"KY",
    "sg:tags":[
        "beef",
        "feedlot",
        "tobacco",
        "cattle"
    ],
    "wof:name":"Melvin Rountree Farm",
    "wof:placetype":"venue"
},
  "geometry": {"coordinates":[-85.991816,37.236782],"type":"Point"}
}