{
  "type": "Feature",
  "properties": {
    "iso:country":"US",
    "sg:address":"309 Oaks Rd",
    "sg:city":"Paducah",
    "sg:classifiers":[
        {
            "category":"Autos & Motor Vehicles",
            "subcategory":"Automobile Sales",
            "type":"Retail Goods"
        }
    ],
    "sg:phone":"+1 270 444 9296",
    "sg:postcode":"42003",
    "sg:province":"KY",
    "sg:tags":[
        "car",
        "dealer"
    ],
    "wof:name":"Campbell's Used Cars",
    "wof:placetype":"venue"
},
  "geometry": {"coordinates":[-88.569149,37.043132],"type":"Point"}
}