{
  "type": "Feature",
  "properties": {
    "addr:full":"863 N Wilson Rd Radcliff KY 40160",
    "addr:housenumber":"863",
    "addr:postcode":"40160",
    "addr:street":"N Wilson Rd",
    "iso:country":"US",
    "sg:address":"863 N Wilson Rd",
    "sg:city":"Radcliff",
    "sg:classifiers":[
        {
            "category":"Restaurant",
            "type":"Food & Drink"
        }
    ],
    "sg:phone":"+1 270 351 2000",
    "sg:postcode":"40160",
    "sg:province":"KY",
    "wof:name":"Autumn Gardens",
    "wof:placetype":"venue"
},
  "geometry": {"coordinates":[-85.94485299999999,37.848751],"type":"Point"}
}