{
  "type": "Feature",
  "properties": {
    "addr:full":"57 High St Walton KY 41094",
    "addr:housenumber":"57",
    "addr:postcode":"41094",
    "addr:street":"High St",
    "iso:country":"US",
    "sg:address":"57 High St",
    "sg:city":"Walton",
    "sg:classifiers":[
        {
            "category":"Building & Trades",
            "subcategory":"Construction",
            "type":"Services"
        }
    ],
    "sg:phone":"+1 859 485 7010",
    "sg:postcode":"41094",
    "sg:province":"KY",
    "sg:tags":[
        "house"
    ],
    "wof:name":"A Swanson Builders Inc",
    "wof:placetype":"venue"
},
  "geometry": {"coordinates":[-84.60728400000001,38.864684],"type":"Point"}
}