{
  "type": "Feature",
  "properties": {
    "iso:country":"US",
    "sg:address":"71 Matney Rd",
    "sg:city":"Elizabethtown",
    "sg:classifiers":[
        {
            "category":"Retail",
            "subcategory":"Auto Rental",
            "type":"Services"
        }
    ],
    "sg:phone":"+1 270 769 7308",
    "sg:postcode":"42743",
    "sg:province":"KY",
    "sg:tags":[
        "renting",
        "truck",
        "leasing"
    ],
    "wof:name":"U-Haul Co",
    "wof:placetype":"venue"
},
  "geometry": {"coordinates":[-85.54285299999999,37.157182],"type":"Point"}
}