{
  "type": "Feature",
  "properties": {
    "iso:country":"US",
    "sg:address":"3041 Dixie Hwy",
    "sg:city":"Edgewood",
    "sg:classifiers":[
        {
            "category":"Restaurant",
            "type":"Food & Drink"
        }
    ],
    "sg:phone":"+1 859 331 6767",
    "sg:postcode":"41017",
    "sg:province":"KY",
    "sg:tags":[
        "mexican"
    ],
    "wof:name":"El-Coyote Tex-Mex Cafe",
    "wof:placetype":"venue"
},
  "geometry": {"coordinates":[-84.58771400000001,39.021517],"type":"Point"}
}