{
  "type": "Feature",
  "properties": {
    "iso:country":"US",
    "sg:address":"238 N Colony Dr",
    "sg:city":"Edgewood",
    "sg:classifiers":[
        {
            "category":"Professional",
            "subcategory":"Management & Consulting",
            "type":"Services"
        }
    ],
    "sg:phone":"+1 859 341 7190",
    "sg:postcode":"41017",
    "sg:province":"KY",
    "sg:tags":[
        "consultant",
        "automation"
    ],
    "wof:name":"Automation Control Elec Spec",
    "wof:placetype":"venue"
},
  "geometry": {"coordinates":[-84.578209,39.010477],"type":"Point"}
}