{
  "type": "Feature",
  "properties": {
    "addr:full":"3130 Mapleleaf Dr Ste 101 Lexington KY 40509",
    "addr:housenumber":"3130",
    "addr:postcode":"40509",
    "addr:street":"Mapleleaf Dr Ste 101",
    "iso:country":"US",
    "sg:address":"3130 Mapleleaf Dr Ste 101",
    "sg:city":"Lexington",
    "sg:classifiers":[
        {
            "category":"Shopping",
            "subcategory":"Department Store",
            "type":"Retail Goods"
        },
        {
            "category":"Shopping",
            "type":"Retail Goods"
        },
        {
            "category":"Shopping",
            "subcategory":"Discount & Variety Stores",
            "type":"Retail Goods"
        }
    ],
    "sg:phone":"+1 859 543 8210",
    "sg:postcode":"40509",
    "sg:province":"KY",
    "sg:tags":[
        "merchandise"
    ],
    "sg:website":"http://www.dollartree.com/",
    "wof:name":"Dollar Tree",
    "wof:placetype":"venue"
},
  "geometry": {"coordinates":[-84.425054,38.006305],"type":"Point"}
}