{
  "type": "Feature",
  "properties": {
    "iso:country":"US",
    "sg:address":"633 Chestnut St",
    "sg:city":"Berea",
    "sg:classifiers":[
        {
            "category":"Shopping",
            "type":"Retail Goods"
        }
    ],
    "sg:phone":"+1 859 986 1866",
    "sg:postcode":"40403",
    "sg:province":"KY",
    "sg:tags":[
        "art",
        "gallery",
        "dealer"
    ],
    "sg:website":"www.mitchelltolle.com",
    "wof:name":"Tolle Gallery",
    "wof:placetype":"venue"
},
  "geometry": {"coordinates":[-84.303692,37.567985],"type":"Point"}
}