{
  "type": "Feature",
  "properties": {
    "iso:country":"US",
    "sg:address":"2660 Russell Rd",
    "sg:city":"Utica",
    "sg:classifiers":[
        {
            "category":"Farming",
            "subcategory":"Livestock Farm",
            "type":"Manufacturing & Wholesale Goods"
        }
    ],
    "sg:phone":"+1 270 275 4956",
    "sg:postcode":"42376",
    "sg:province":"KY",
    "sg:tags":[
        "beef",
        "feedlot",
        "cattle"
    ],
    "wof:name":"Ed Ezell",
    "wof:placetype":"venue"
},
  "geometry": {"coordinates":[-87.02666600000001,37.594536],"type":"Point"}
}