{
  "type": "Feature",
  "properties": {
    "iso:country":"US",
    "sg:address":"326 N Mulberry St",
    "sg:city":"Elizabethtown",
    "sg:classifiers":[
        {
            "category":"Personal",
            "subcategory":"Beauty Salon",
            "type":"Services"
        }
    ],
    "sg:phone":"+1 270 766 1166",
    "sg:postcode":"42701",
    "sg:province":"KY",
    "wof:name":"Amazing Creations Hair Salon",
    "wof:placetype":"venue"
},
  "geometry": {"coordinates":[-85.855434,37.69827],"type":"Point"}
}