{
  "type": "Feature",
  "properties": {
    "iso:country":"US",
    "sg:address":"1096 US Hwy 60",
    "sg:city":"Owingsville",
    "sg:classifiers":[
        {
            "category":"Autos & Motor Vehicles",
            "subcategory":"Automobile Sales",
            "type":"Retail Goods"
        }
    ],
    "sg:phone":"+1 606 674 6501",
    "sg:postcode":"40360",
    "sg:province":"KY",
    "sg:tags":[
        "car",
        "dealer"
    ],
    "wof:name":"Cecil Williams Used Cars",
    "wof:placetype":"venue"
},
  "geometry": {"coordinates":[-83.75089,38.148825],"type":"Point"}
}