{
  "type": "Feature",
  "properties": {
    "iso:country":"US",
    "sg:address":"1172 Florence Mall",
    "sg:city":"Florence",
    "sg:classifiers":[
        {
            "category":"Shopping",
            "subcategory":"Bicycles & Sporting Goods",
            "type":"Retail Goods"
        }
    ],
    "sg:phone":"+1 859 371 3549",
    "sg:postcode":"41042",
    "sg:province":"KY",
    "sg:website":"www.finishline.com",
    "wof:name":"Finish Line",
    "wof:placetype":"venue"
},
  "geometry": {"coordinates":[-84.65239699999999,38.998501],"type":"Point"}
}