{
  "type": "Feature",
  "properties": {
    "addr:full":"514 Boyd St Russell KY 41169",
    "addr:housenumber":"514",
    "addr:postcode":"41169",
    "addr:street":"Boyd St",
    "iso:country":"US",
    "sg:address":"514 Boyd St",
    "sg:city":"Russell",
    "sg:classifiers":[
        {
            "category":"Government",
            "subcategory":"Post Office",
            "type":"Public Place"
        }
    ],
    "sg:phone":"+1 606 836 3155",
    "sg:postcode":"41169",
    "sg:province":"KY",
    "wof:name":"US Post Office",
    "wof:placetype":"venue"
},
  "geometry": {"coordinates":[-82.69522600000001,38.531584],"type":"Point"}
}