{
  "type": "Feature",
  "properties": {
    "iso:country":"US",
    "sg:address":"2990 Trimble St",
    "sg:city":"Paducah",
    "sg:classifiers":[
        {
            "category":"Social Services",
            "type":"Services"
        }
    ],
    "sg:phone":"+1 270 443 7575",
    "sg:postcode":"42001",
    "sg:province":"KY",
    "sg:tags":[
        "organization",
        "welfare"
    ],
    "wof:name":"Salvation Army Citadel Corps",
    "wof:placetype":"venue"
},
  "geometry": {"coordinates":[-88.639276,37.077579],"type":"Point"}
}