{
  "type": "Feature",
  "properties": {
    "addr:full":"933 Steel Rd La Center KY 42056",
    "addr:housenumber":"933",
    "addr:postcode":"42056",
    "addr:street":"Steel Rd",
    "iso:country":"US",
    "sg:address":"933 Steel Rd",
    "sg:city":"La Center",
    "sg:classifiers":[
        {
            "category":"Real Estate",
            "subcategory":"Real Estate Operator",
            "type":"Services"
        }
    ],
    "sg:phone":"+1 270 876 7176",
    "sg:postcode":"42056",
    "sg:province":"KY",
    "sg:tags":[
        "property",
        "lessor"
    ],
    "wof:name":"Moss Farm",
    "wof:placetype":"venue"
},
  "geometry": {"coordinates":[-88.913786,37.003056],"type":"Point"}
}