{
  "type": "Feature",
  "properties": {
    "iso:country":"US",
    "sg:address":"445 Highway 15 S",
    "sg:city":"Jackson",
    "sg:classifiers":[
        {
            "category":"Restaurant",
            "type":"Food & Drink"
        }
    ],
    "sg:menulink":"http://www.allmenus.com/ky/haddix/120568-subway/menu/",
    "sg:phone":"+1 606 666 7178",
    "sg:postcode":"41339",
    "sg:province":"KY",
    "sg:tags":[
        "american",
        "sandwich"
    ],
    "wof:name":"Subway",
    "wof:placetype":"venue"
},
  "geometry": {"coordinates":[-83.35628800000001,37.498172],"type":"Point"}
}