{
  "type": "Feature",
  "properties": {
    "addr:full":"1938 Thyme Ave Carrollton KY 41008",
    "addr:housenumber":"1938",
    "addr:postcode":"41008",
    "addr:street":"Thyme Ave",
    "iso:country":"US",
    "sg:address":"1938 Thyme Ave",
    "sg:city":"Carrollton",
    "sg:classifiers":[
        {
            "category":"Real Estate",
            "subcategory":"Real Estate Operator",
            "type":"Services"
        }
    ],
    "sg:phone":"+1 502 732 5718",
    "sg:postcode":"41008",
    "sg:province":"KY",
    "sg:tags":[
        "apartment"
    ],
    "wof:name":"Camellia Court Apts",
    "wof:placetype":"venue"
},
  "geometry": {"coordinates":[-85.13975600000001,38.666324],"type":"Point"}
}