{
  "type": "Feature",
  "properties": {
    "addr:full":"1254 Helck Ave Louisville KY 40213",
    "addr:housenumber":"1254",
    "addr:postcode":"40213",
    "addr:street":"Helck Ave",
    "iso:country":"US",
    "sg:address":"1254 Helck Ave",
    "sg:city":"Louisville",
    "sg:classifiers":[
        {
            "category":"Building & Trades",
            "subcategory":"Plumbing",
            "type":"Services"
        }
    ],
    "sg:phone":"+1 502 964 8354",
    "sg:postcode":"40213",
    "sg:province":"KY",
    "sg:tags":[
        "plumbing",
        "contractor"
    ],
    "wof:name":"Ready Sewer Svc",
    "wof:placetype":"venue"
},
  "geometry": {"coordinates":[-85.706102,38.176015],"type":"Point"}
}