{
  "type": "Feature",
  "properties": {
    "addr:full":"3953 Parkers Mill Rd Lexington KY 40513",
    "addr:housenumber":"3953",
    "addr:postcode":"40513",
    "addr:street":"Parkers Mill Rd",
    "iso:country":"US",
    "sg:address":"3953 Parkers Mill Rd",
    "sg:city":"Lexington",
    "sg:classifiers":[
        {
            "category":"Organizations",
            "subcategory":"Community Association",
            "type":"Services"
        }
    ],
    "sg:phone":"+1 859 252 6046",
    "sg:postcode":"40513",
    "sg:province":"KY",
    "sg:tags":[
        "membership"
    ],
    "wof:name":"Gold Wing Road Riders Assn",
    "wof:placetype":"venue"
},
  "geometry": {"coordinates":[-84.600336,38.027085],"type":"Point"}
}