{
  "type": "Feature",
  "properties": {
    "addr:full":"209 Towne Dr Elizabethtown KY 42701",
    "addr:housenumber":"209",
    "addr:postcode":"42701",
    "addr:street":"Towne Dr",
    "iso:country":"US",
    "sg:address":"209 Towne Dr",
    "sg:city":"Elizabethtown",
    "sg:classifiers":[
        {
            "category":"Shopping",
            "subcategory":"Clothing, Apparel, & Fashions",
            "type":"Retail Goods"
        },
        {
            "category":"Banks & Credit Unions",
            "subcategory":"Bank",
            "type":"Services"
        },
        {
            "category":"Shopping",
            "subcategory":"Used Merchandise",
            "type":"Retail Goods"
        },
        {
            "category":"Shopping",
            "subcategory":"Bicycles & Sporting Goods",
            "type":"Retail Goods"
        },
        {
            "category":"Sports & Exercise",
            "subcategory":"Gym",
            "type":"Entertainment"
        },
        {
            "category":"Sports & Exercise",
            "subcategory":"Sports Center",
            "type":"Entertainment"
        }
    ],
    "sg:phone":"+1 270 982 7529",
    "sg:postcode":"42701",
    "sg:province":"KY",
    "sg:tags":[
        "skating",
        "shop",
        "golf",
        "supply",
        "rental",
        "fitness",
        "skateboard",
        "second",
        "hand",
        "resale",
        "equipment",
        "snowboard",
        "hockey",
        "skiing",
        "ski",
        "sportswear"
    ],
    "sg:website":"http://www.playitagainsports.com",
    "wof:name":"Play It Again Sports",
    "wof:placetype":"venue"
},
  "geometry": {"coordinates":[-85.889098,37.733337],"type":"Point"}
}