{
  "type": "Feature",
  "properties": {
    "iso:country":"US",
    "sg:address":"325 River Rd",
    "sg:city":"Dunnville",
    "sg:classifiers":[
        {
            "category":"Organizations",
            "subcategory":"Religious Organization",
            "type":"Services"
        }
    ],
    "sg:phone":"+1 606 787 9903",
    "sg:postcode":"42528",
    "sg:province":"KY",
    "sg:tags":[
        "church"
    ],
    "wof:name":"Christian Dunnville Church",
    "wof:placetype":"venue"
},
  "geometry": {"coordinates":[-85.010102,37.199953],"type":"Point"}
}