{
  "type": "Feature",
  "properties": {
    "iso:country":"US",
    "sg:address":"1575 Distribution Dr",
    "sg:city":"Burlington",
    "sg:classifiers":[
        {
            "category":"Wholesale",
            "subcategory":"Scrap",
            "type":"Manufacturing & Wholesale Goods"
        }
    ],
    "sg:phone":"+1 859 283 9560",
    "sg:postcode":"41005",
    "sg:province":"KY",
    "sg:tags":[
        "recycling",
        "center"
    ],
    "wof:name":"Blue Grass Recycling",
    "wof:placetype":"venue"
},
  "geometry": {"coordinates":[-84.686211,39.025807],"type":"Point"}
}