{
  "type": "Feature",
  "properties": {
    "iso:country":"US",
    "sg:address":"411 Webb St",
    "sg:city":"Olive Hill",
    "sg:classifiers":[
        {
            "category":"Building & Trades",
            "subcategory":"Construction",
            "type":"Services"
        }
    ],
    "sg:phone":"+1 606 286 6634",
    "sg:postcode":"41164",
    "sg:province":"KY",
    "sg:tags":[
        "house"
    ],
    "wof:name":"Dixon Construction",
    "wof:placetype":"venue"
},
  "geometry": {"coordinates":[-83.177241,38.295205],"type":"Point"}
}