{
  "type": "Feature",
  "properties": {
    "iso:country":"US",
    "sg:address":"510 Glades Rd",
    "sg:city":"Berea",
    "sg:classifiers":[
        {
            "category":"Personal",
            "subcategory":"Beauty Salon",
            "type":"Services"
        }
    ],
    "sg:phone":"+1 859 985 7900",
    "sg:postcode":"40403",
    "sg:province":"KY",
    "wof:name":"Perfect Ten Hair & Nails",
    "wof:placetype":"venue"
},
  "geometry": {"coordinates":[-84.279753,37.585891],"type":"Point"}
}