{
  "type": "Feature",
  "properties": {
    "iso:country":"US",
    "sg:address":"417 Madison Ave",
    "sg:city":"Covington",
    "sg:classifiers":[
        {
            "category":"Restaurant",
            "type":"Food & Drink"
        }
    ],
    "sg:phone":"+1 513 347 1111",
    "sg:postcode":"41011",
    "sg:province":"KY",
    "wof:name":"LA Rosa's Inc",
    "wof:placetype":"venue"
},
  "geometry": {"coordinates":[-84.51071899999999,39.085837],"type":"Point"}
}