{
  "type": "Feature",
  "properties": {
    "iso:country":"US",
    "sg:address":"12001 Shelbyville Rd",
    "sg:city":"Louisville",
    "sg:classifiers":[
        {
            "category":"Sports & Exercise",
            "subcategory":"Gym",
            "type":"Entertainment"
        }
    ],
    "sg:phone":"+1 502 245 9893",
    "sg:postcode":"40243",
    "sg:province":"KY",
    "sg:tags":[
        "gymnasium"
    ],
    "wof:name":"Powerhouse Gym",
    "wof:placetype":"venue"
},
  "geometry": {"coordinates":[-85.53465300000001,38.24865],"type":"Point"}
}