{
  "type": "Feature",
  "properties": {
    "iso:country":"US",
    "sg:address":"3429 Montavesta Rd",
    "sg:city":"Lexington",
    "sg:classifiers":[
        {
            "category":"Travel",
            "subcategory":"Travel Agent",
            "type":"Entertainment"
        }
    ],
    "sg:phone":"+1 859 268 2906",
    "sg:postcode":"40502",
    "sg:province":"KY",
    "sg:tags":[
        "tours",
        "promoter"
    ],
    "wof:name":"Horse Farm Tours Inc",
    "wof:placetype":"venue"
},
  "geometry": {"coordinates":[-84.487199,37.998457],"type":"Point"}
}