{
  "type": "Feature",
  "properties": {
    "addr:full":"16270 Linton Rd Canton KY 42211",
    "addr:housenumber":"16270",
    "addr:postcode":"42211",
    "addr:street":"Linton Rd",
    "iso:country":"US",
    "sg:address":"16270 Linton Rd",
    "sg:city":"Canton",
    "sg:classifiers":[
        {
            "category":"Shopping",
            "subcategory":"Clothing, Apparel, & Fashions",
            "type":"Retail Goods"
        }
    ],
    "sg:phone":"+1 270 924 5015",
    "sg:postcode":"42211",
    "sg:province":"KY",
    "sg:tags":[
        "hosiery"
    ],
    "wof:name":"Knit-Well Hosiery Mill",
    "wof:placetype":"venue"
},
  "geometry": {"coordinates":[-87.958286,36.798589],"type":"Point"}
}