{
  "type": "Feature",
  "properties": {
    "iso:country":"US",
    "sg:address":"2106 Russellville Rd",
    "sg:city":"Bowling Green",
    "sg:classifiers":[
        {
            "category":"Wholesale",
            "subcategory":"Furniture",
            "type":"Manufacturing & Wholesale Goods"
        }
    ],
    "sg:phone":"+1 270 796 6760",
    "sg:postcode":"42101",
    "sg:province":"KY",
    "wof:name":"Dunagan Office Equipment",
    "wof:placetype":"venue"
},
  "geometry": {"coordinates":[-86.472661,36.974828],"type":"Point"}
}