{
  "type": "Feature",
  "properties": {
    "addr:full":"5832 River Rd Hebron KY 41048",
    "addr:housenumber":"5832",
    "addr:postcode":"41048",
    "addr:street":"River Rd",
    "iso:country":"US",
    "sg:address":"5832 River Rd",
    "sg:city":"Hebron",
    "sg:classifiers":[
        {
            "category":"Wholesale",
            "subcategory":"Fruits & Vegetables",
            "type":"Manufacturing & Wholesale Goods"
        }
    ],
    "sg:phone":"+1 859 689 5229",
    "sg:postcode":"41048",
    "sg:province":"KY",
    "sg:tags":[
        "veggie"
    ],
    "sg:website":"www.mcglassonfarms.com/",
    "wof:name":"McGlasson Farms",
    "wof:placetype":"venue"
},
  "geometry": {"coordinates":[-84.67371,39.091938],"type":"Point"}
}