{
  "type": "Feature",
  "properties": {
    "addr:full":"7900 Shelbyville Rd Louisville KY 40222",
    "addr:housenumber":"7900",
    "addr:postcode":"40222",
    "addr:street":"Shelbyville Rd",
    "iso:country":"US",
    "sg:address":"7900 Shelbyville Rd",
    "sg:city":"Louisville",
    "sg:classifiers":[
        {
            "category":"Shopping",
            "subcategory":"Books",
            "type":"Retail Goods"
        }
    ],
    "sg:phone":"+1 502 423 1596",
    "sg:postcode":"40222",
    "sg:province":"KY",
    "sg:tags":[
        "dealer"
    ],
    "wof:name":"Waldenbooks",
    "wof:placetype":"venue"
},
  "geometry": {"coordinates":[-85.60583699999999,38.248771],"type":"Point"}
}