{
  "type": "Feature",
  "properties": {
    "iso:country":"US",
    "sg:address":"520 Fairgrounds St",
    "sg:city":"Munfordville",
    "sg:classifiers":[
        {
            "category":"Professional",
            "type":"Services"
        }
    ],
    "sg:phone":"+1 270 524 2143",
    "sg:postcode":"42728",
    "sg:province":"KY",
    "sg:tags":[
        "establishment"
    ],
    "wof:name":"AOC Pretrial",
    "wof:placetype":"venue"
},
  "geometry": {"coordinates":[-85.295108,37.103804],"type":"Point"}
}