{
  "type": "Feature",
  "properties": {
    "iso:country":"US",
    "sg:address":"1542 Baier Rd",
    "sg:city":"Grayson",
    "sg:classifiers":[
        {
            "category":"Building & Trades",
            "subcategory":"Construction",
            "type":"Services"
        }
    ],
    "sg:phone":"+1 606 923 9104",
    "sg:postcode":"41143",
    "sg:province":"KY",
    "sg:tags":[
        "general",
        "contractor"
    ],
    "wof:name":"Bryan Welch Construction",
    "wof:placetype":"venue"
},
  "geometry": {"coordinates":[-82.921662,38.258489],"type":"Point"}
}