{
  "type": "Feature",
  "properties": {
    "iso:country":"US",
    "sg:address":"9900 Corporate Campus Dr",
    "sg:city":"Louisville",
    "sg:classifiers":[
        {
            "category":"Professional",
            "type":"Services"
        }
    ],
    "sg:phone":"+1 502 657 6460",
    "sg:postcode":"40223",
    "sg:province":"KY",
    "sg:tags":[
        "establishment"
    ],
    "wof:name":"Integrity Asset Management",
    "wof:placetype":"venue"
},
  "geometry": {"coordinates":[-85.56863199999999,38.266509],"type":"Point"}
}