{
  "type": "Feature",
  "properties": {
    "addr:full":"2501 Dixie Hwy Fort Mitchell KY 41017",
    "addr:housenumber":"2501",
    "addr:postcode":"41017",
    "addr:street":"Dixie Hwy",
    "iso:country":"US",
    "sg:address":"2501 Dixie Hwy",
    "sg:city":"Fort Mitchell",
    "sg:classifiers":[
        {
            "category":"Restaurant",
            "type":"Food & Drink"
        }
    ],
    "sg:phone":"+1 859 331 2200",
    "sg:postcode":"41017",
    "sg:province":"KY",
    "sg:tags":[
        "delicatessen"
    ],
    "wof:name":"Remke Markets",
    "wof:placetype":"venue"
},
  "geometry": {"coordinates":[-84.561391,39.03598],"type":"Point"}
}