{
  "type": "Feature",
  "properties": {
    "iso:country":"US",
    "sg:address":"3656 Blue Lick Rd",
    "sg:city":"Louisville",
    "sg:classifiers":[
        {
            "category":"Manufacturing",
            "subcategory":"Printing",
            "type":"Manufacturing & Wholesale Goods"
        }
    ],
    "sg:phone":"+1 502 955 1341",
    "sg:postcode":"40229",
    "sg:province":"KY",
    "sg:tags":[
        "printer"
    ],
    "wof:name":"Advanced Print Solutions Inc",
    "wof:placetype":"venue"
},
  "geometry": {"coordinates":[-85.696217,38.080116],"type":"Point"}
}