{
  "type": "Feature",
  "properties": {
    "iso:country":"US",
    "sg:address":"117 Campbell Ct",
    "sg:city":"Mayfield",
    "sg:classifiers":[
        {
            "category":"Farming",
            "subcategory":"Farm",
            "type":"Manufacturing & Wholesale Goods"
        }
    ],
    "sg:phone":"+1 270 247 3374",
    "sg:postcode":"42066",
    "sg:province":"KY",
    "sg:tags":[
        "crop",
        "general"
    ],
    "wof:name":"Lewis W Wheeler",
    "wof:placetype":"venue"
},
  "geometry": {"coordinates":[-88.65533000000001,36.744549],"type":"Point"}
}