{
  "type": "Feature",
  "properties": {
    "iso:country":"US",
    "sg:address":"1428 Hustonville Rd",
    "sg:city":"Danville",
    "sg:classifiers":[
        {
            "category":"Restaurant",
            "type":"Food & Drink"
        }
    ],
    "sg:phone":"+1 859 238 7790",
    "sg:postcode":"40422",
    "sg:province":"KY",
    "wof:name":"Taco Bell",
    "wof:placetype":"venue"
},
  "geometry": {"coordinates":[-84.774591,37.62369],"type":"Point"}
}