{
  "type": "Feature",
  "properties": {
    "addr:full":"204 N Washington St Munfordville KY 42765",
    "addr:housenumber":"204",
    "addr:postcode":"42765",
    "addr:street":"N Washington St",
    "iso:country":"US",
    "sg:address":"204 N Washington St",
    "sg:city":"Munfordville",
    "sg:classifiers":[
        {
            "category":"Personal",
            "subcategory":"Beauty Salon",
            "type":"Services"
        }
    ],
    "sg:phone":"+1 270 524 2887",
    "sg:postcode":"42765",
    "sg:province":"KY",
    "sg:tags":[
        "shop"
    ],
    "wof:name":"Country Cuts",
    "wof:placetype":"venue"
},
  "geometry": {"coordinates":[-85.89075800000001,37.270664],"type":"Point"}
}