{
  "type": "Feature",
  "properties": {
    "iso:country":"US",
    "sg:address":"3214 Preston Hwy",
    "sg:city":"Louisville",
    "sg:classifiers":[
        {
            "category":"Retail",
            "subcategory":"Auto Repair",
            "type":"Services"
        }
    ],
    "sg:phone":"+1 502 636 0202",
    "sg:postcode":"40213",
    "sg:province":"KY",
    "sg:tags":[
        "repairing",
        "automobile"
    ],
    "wof:name":"Spencer's Auto Svc Inc",
    "wof:placetype":"venue"
},
  "geometry": {"coordinates":[-85.734188,38.201574],"type":"Point"}
}