{
  "type": "Feature",
  "properties": {
    "addr:full":"1979 S Hurstbourne Pkwy Louisville KY 40220",
    "addr:housenumber":"1979",
    "addr:postcode":"40220",
    "addr:street":"S Hurstbourne Pkwy",
    "iso:country":"US",
    "sg:address":"1979 S Hurstbourne Pkwy",
    "sg:city":"Louisville",
    "sg:classifiers":[
        {
            "category":"Manufacturing",
            "subcategory":"Signs",
            "type":"Manufacturing & Wholesale Goods"
        }
    ],
    "sg:phone":"+1 502 491 8180",
    "sg:postcode":"40220",
    "sg:province":"KY",
    "wof:name":"Signs Now",
    "wof:placetype":"venue"
},
  "geometry": {"coordinates":[-85.58651500000001,38.217642],"type":"Point"}
}