{
  "type": "Feature",
  "properties": {
    "iso:country":"US",
    "sg:address":"1144 Main St",
    "sg:city":"Jackson",
    "sg:classifiers":[
        {
            "category":"Freight",
            "type":"Transportation"
        }
    ],
    "sg:phone":"+1 606 666 2341",
    "sg:postcode":"41339",
    "sg:province":"KY",
    "sg:tags":[
        "delivery"
    ],
    "wof:name":"White Flash Restaurant",
    "wof:placetype":"venue"
},
  "geometry": {"coordinates":[-83.383971,37.553936],"type":"Point"}
}