{
  "type": "Feature",
  "properties": {
    "addr:full":"3161 Dixie Hwy Erlanger KY 41018",
    "addr:housenumber":"3161",
    "addr:postcode":"41018",
    "addr:street":"Dixie Hwy",
    "iso:country":"US",
    "sg:address":"3161 Dixie Hwy",
    "sg:city":"Erlanger",
    "sg:classifiers":[
        {
            "category":"Building & Trades",
            "subcategory":"Cleaning & Sanitation",
            "type":"Services"
        }
    ],
    "sg:phone":"+1 859 341 2110",
    "sg:postcode":"41018",
    "sg:province":"KY",
    "sg:tags":[
        "house"
    ],
    "wof:name":"Molly Maids",
    "wof:placetype":"venue"
},
  "geometry": {"coordinates":[-84.59320700000001,39.020092],"type":"Point"}
}