{
  "type": "Feature",
  "properties": {
    "addr:full":"430 N Main St Cynthiana KY 41031",
    "addr:housenumber":"430",
    "addr:postcode":"41031",
    "addr:street":"N Main St",
    "iso:country":"US",
    "sg:address":"430 N Main St",
    "sg:city":"Cynthiana",
    "sg:classifiers":[
        {
            "category":"Wholesale",
            "subcategory":"Farm Supplies",
            "type":"Manufacturing & Wholesale Goods"
        }
    ],
    "sg:phone":"+1 859 234 2122",
    "sg:postcode":"41031",
    "sg:province":"KY",
    "sg:tags":[
        "fertilizer"
    ],
    "wof:name":"Miles Farm Supply Inc",
    "wof:placetype":"venue"
},
  "geometry": {"coordinates":[-84.296907,38.39467],"type":"Point"}
}