{
  "type": "Feature",
  "properties": {
    "addr:full":"5293 State Hwy 80 Wooton KY 41776",
    "addr:housenumber":"5293",
    "addr:postcode":"41776",
    "addr:street":"State Hwy 80",
    "iso:country":"US",
    "sg:address":"5293 State Hwy 80",
    "sg:city":"Wooton",
    "sg:classifiers":[
        {
            "category":"Personal",
            "subcategory":"Beauty Salon",
            "type":"Services"
        }
    ],
    "sg:phone":"+1 606 279 3136",
    "sg:postcode":"41776",
    "sg:province":"KY",
    "wof:name":"Beauty Boutique",
    "wof:placetype":"venue"
},
  "geometry": {"coordinates":[-83.307652,37.166322],"type":"Point"}
}