{
  "type": "Feature",
  "properties": {
    "iso:country":"US",
    "sg:address":"3160 Hyde Park Dr",
    "sg:city":"Lexington",
    "sg:classifiers":[
        {
            "category":"Professional",
            "subcategory":"Research",
            "type":"Services"
        }
    ],
    "sg:phone":"+1 859 260 1812",
    "sg:postcode":"40503",
    "sg:province":"KY",
    "sg:tags":[
        "environmental",
        "ecological"
    ],
    "wof:name":"Progressive Environmental Svc",
    "wof:placetype":"venue"
},
  "geometry": {"coordinates":[-84.553195,38.008066],"type":"Point"}
}