{
  "type": "Feature",
  "properties": {
    "addr:full":"496 Southland Dr Lexington KY 40503",
    "addr:housenumber":"496",
    "addr:postcode":"40503",
    "addr:street":"Southland Dr",
    "iso:country":"US",
    "sg:address":"496 Southland Dr",
    "sg:city":"Lexington",
    "sg:classifiers":[
        {
            "category":"Manufacturing",
            "subcategory":"Jewelry",
            "type":"Manufacturing & Wholesale Goods"
        }
    ],
    "sg:phone":"+1 859 277 4113",
    "sg:postcode":"40503",
    "sg:province":"KY",
    "wof:name":"Strictly Natural Jewelry",
    "wof:placetype":"venue"
},
  "geometry": {"coordinates":[-84.528465,38.020458],"type":"Point"}
}