{
  "type": "Feature",
  "properties": {
    "iso:country":"US",
    "sg:address":"1600 Fort Campbell Blvd",
    "sg:city":"Clarksville",
    "sg:classifiers":[
        {
            "category":"Home & Garden",
            "subcategory":"Furniture",
            "type":"Retail Goods"
        }
    ],
    "sg:phone":"+1 931 906 3091",
    "sg:postcode":"37042",
    "sg:province":"KY",
    "wof:name":"Chucks Furniture Depot Inc",
    "wof:placetype":"venue"
},
  "geometry": {"coordinates":[-87.409323,36.5787],"type":"Point"}
}