{
  "type": "Feature",
  "properties": {
    "iso:country":"US",
    "sg:address":"701 Fairhill Dr",
    "sg:city":"Louisville",
    "sg:classifiers":[
        {
            "category":"Professional",
            "subcategory":"Management & Consulting",
            "type":"Services"
        }
    ],
    "sg:phone":"+1 502 894 9844",
    "sg:postcode":"40207",
    "sg:province":"KY",
    "wof:name":"Community Emrgncy MGT Cnsultan",
    "wof:placetype":"venue"
},
  "geometry": {"coordinates":[-85.690929,38.268269],"type":"Point"}
}