{
  "type": "Feature",
  "properties": {
    "iso:country":"US",
    "sg:address":"500 John C Watts Dr",
    "sg:city":"Nicholasville",
    "sg:classifiers":[
        {
            "category":"Manufacturing",
            "subcategory":"Metals",
            "type":"Manufacturing & Wholesale Goods"
        }
    ],
    "sg:phone":"+1 859 885 6988",
    "sg:postcode":"40356",
    "sg:province":"KY",
    "sg:tags":[
        "stamping"
    ],
    "sg:website":"www.racota.com",
    "wof:name":"Racota Manufacturing",
    "wof:placetype":"venue"
},
  "geometry": {"coordinates":[-84.578048,37.861909],"type":"Point"}
}