{
  "type": "Feature",
  "properties": {
    "addr:full":"2175 Hodgenville Rd Campbellsville KY 42718",
    "addr:housenumber":"2175",
    "addr:postcode":"42718",
    "addr:street":"Hodgenville Rd",
    "iso:country":"US",
    "sg:address":"2175 Hodgenville Rd",
    "sg:city":"Campbellsville",
    "sg:classifiers":[
        {
            "category":"Government",
            "subcategory":"Office",
            "type":"Public Place"
        }
    ],
    "sg:phone":"+1 270 465 7651",
    "sg:postcode":"42718",
    "sg:province":"KY",
    "wof:name":"Taylor County Animal Shelter",
    "wof:placetype":"venue"
},
  "geometry": {"coordinates":[-85.376508,37.353366],"type":"Point"}
}