{
  "type": "Feature",
  "properties": {
    "iso:country":"US",
    "sg:address":"425 S 6th St",
    "sg:city":"Paducah",
    "sg:classifiers":[
        {
            "category":"Professional",
            "subcategory":"Lawyer & Legal Services",
            "type":"Services"
        }
    ],
    "sg:phone":"+1 270 442 9237",
    "sg:postcode":"42003",
    "sg:province":"KY",
    "sg:tags":[
        "attorney"
    ],
    "wof:name":"Boswell Sims & Vasseur",
    "wof:placetype":"venue"
},
  "geometry": {"coordinates":[-88.598541,37.082325],"type":"Point"}
}