{
  "type": "Feature",
  "properties": {
    "iso:country":"US",
    "sg:address":"11 N Main St",
    "sg:city":"Madisonville",
    "sg:classifiers":[
        {
            "category":"Utilities",
            "subcategory":"Mobile Phone",
            "type":"Services"
        }
    ],
    "sg:phone":"+1 270 825 8525",
    "sg:postcode":"42431",
    "sg:province":"KY",
    "sg:tags":[
        "telephone",
        "cellular"
    ],
    "wof:name":"Mid America Mobile",
    "wof:placetype":"venue"
},
  "geometry": {"coordinates":[-87.49880899999999,37.328888],"type":"Point"}
}