{
  "type": "Feature",
  "properties": {
    "addr:full":"2314 Paris Pike Lexington KY 40505",
    "addr:housenumber":"2314",
    "addr:postcode":"40505",
    "addr:street":"Paris Pike",
    "iso:country":"US",
    "sg:address":"2314 Paris Pike",
    "sg:city":"Lexington",
    "sg:classifiers":[
        {
            "category":"Retail",
            "subcategory":"Auto Repair",
            "type":"Services"
        }
    ],
    "sg:phone":"+1 859 299 7585",
    "sg:postcode":"40505",
    "sg:province":"KY",
    "sg:tags":[
        "general"
    ],
    "wof:name":"Cottons Transmission Service",
    "wof:placetype":"venue"
},
  "geometry": {"coordinates":[-84.449809,38.078907],"type":"Point"}
}