{
  "type": "Feature",
  "properties": {
    "iso:country":"US",
    "sg:address":"14 Alta Ln",
    "sg:city":"Harlan",
    "sg:classifiers":[
        {
            "category":"Organizations",
            "subcategory":"Religious Organization",
            "type":"Services"
        }
    ],
    "sg:phone":"+1 606 573 1897",
    "sg:postcode":"40831",
    "sg:province":"KY",
    "sg:tags":[
        "church"
    ],
    "wof:name":"Mount Olive Baptist Church",
    "wof:placetype":"venue"
},
  "geometry": {"coordinates":[-83.30293899999999,36.851643],"type":"Point"}
}