{
  "type": "Feature",
  "properties": {
    "addr:full":"205 Mount Vernon Rd Berea KY 40403",
    "addr:housenumber":"205",
    "addr:postcode":"40403",
    "addr:street":"Mount Vernon Rd",
    "iso:country":"US",
    "sg:address":"205 Mount Vernon Rd",
    "sg:city":"Berea",
    "sg:classifiers":[
        {
            "category":"Insurance",
            "subcategory":"Insurance Agent",
            "type":"Services"
        }
    ],
    "sg:phone":"+1 859 986 7298",
    "sg:postcode":"40403",
    "sg:province":"KY",
    "wof:name":"National Health Administrators",
    "wof:placetype":"venue"
},
  "geometry": {"coordinates":[-84.305363,37.564823],"type":"Point"}
}