{
  "type": "Feature",
  "properties": {
    "iso:country":"US",
    "sg:address":"1109 Tates Creek Rd",
    "sg:city":"Richmond",
    "sg:classifiers":[
        {
            "category":"Building & Trades",
            "subcategory":"Construction",
            "type":"Services"
        }
    ],
    "sg:phone":"+1 859 623 8604",
    "sg:postcode":"40475",
    "sg:province":"KY",
    "sg:tags":[
        "excavating",
        "contractor"
    ],
    "wof:name":"Reo Rader Excavating",
    "wof:placetype":"venue"
},
  "geometry": {"coordinates":[-84.368836,37.767031],"type":"Point"}
}