{
  "type": "Feature",
  "properties": {
    "iso:country":"US",
    "sg:address":"125 Deaton St",
    "sg:city":"Hazard",
    "sg:classifiers":[
        {
            "category":"Wholesale",
            "subcategory":"Motor Vehicles",
            "type":"Manufacturing & Wholesale Goods"
        }
    ],
    "sg:phone":"+1 606 436 3775",
    "sg:postcode":"41701",
    "sg:province":"KY",
    "sg:tags":[
        "automobile",
        "truck",
        "broker"
    ],
    "wof:name":"Ritchie D Collins Truck Broker",
    "wof:placetype":"venue"
},
  "geometry": {"coordinates":[-83.19083000000001,37.252741],"type":"Point"}
}