{
  "type": "Feature",
  "properties": {
    "addr:full":"320 Reynolds Rd Glasgow KY 42141",
    "addr:housenumber":"320",
    "addr:postcode":"42141",
    "addr:street":"Reynolds Rd",
    "iso:country":"US",
    "sg:address":"320 Reynolds Rd",
    "sg:city":"Glasgow",
    "sg:classifiers":[
        {
            "category":"Retail",
            "subcategory":"Auto Repair",
            "type":"Services"
        }
    ],
    "sg:phone":"+1 270 678 7700",
    "sg:postcode":"42141",
    "sg:province":"KY",
    "sg:tags":[
        "wrecker"
    ],
    "wof:name":"Shoopman's Radiator & Wrecker",
    "wof:placetype":"venue"
},
  "geometry": {"coordinates":[-85.93226,37.013364],"type":"Point"}
}