{
  "type": "Feature",
  "properties": {
    "iso:country":"US",
    "sg:address":"3413 Collins Ln",
    "sg:city":"Louisville",
    "sg:classifiers":[
        {
            "category":"Manufacturing",
            "subcategory":"Building Materials",
            "type":"Manufacturing & Wholesale Goods"
        }
    ],
    "sg:phone":"+1 502 241 3034",
    "sg:postcode":"40245",
    "sg:province":"KY",
    "wof:name":"Trimline Interior Trim & Door",
    "wof:placetype":"venue"
},
  "geometry": {"coordinates":[-85.51822300000001,38.292436],"type":"Point"}
}