{
  "type": "Feature",
  "properties": {
    "iso:country":"US",
    "sg:address":"8223 US Highway 42",
    "sg:city":"Florence",
    "sg:classifiers":[
        {
            "category":"Food & Beverages",
            "subcategory":"Liquor & Beverages",
            "type":"Retail Goods"
        }
    ],
    "sg:phone":"+1 859 371 1053",
    "sg:postcode":"41042",
    "sg:province":"KY",
    "sg:tags":[
        "beer",
        "spirit",
        "wine"
    ],
    "wof:name":"Shamrock Liquor",
    "wof:placetype":"venue"
},
  "geometry": {"coordinates":[-84.65389999999999,38.9879],"type":"Point"}
}