{
  "type": "Feature",
  "properties": {
    "iso:country":"US",
    "sg:address":"8202 Cadence Pl",
    "sg:city":"Louisville",
    "sg:classifiers":[
        {
            "category":"Building & Trades",
            "subcategory":"Plumbing",
            "type":"Services"
        },
        {
            "category":"Utilities",
            "subcategory":"Sewage",
            "type":"Services"
        }
    ],
    "sg:phone":"+1 502 552 5142",
    "sg:postcode":"40222",
    "sg:province":"KY",
    "sg:tags":[
        "consultant",
        "drain",
        "sewer",
        "contractor"
    ],
    "wof:name":"Trutest",
    "wof:placetype":"venue"
},
  "geometry": {"coordinates":[-85.600229,38.269466],"type":"Point"}
}