{
  "type": "Feature",
  "properties": {
    "iso:country":"US",
    "sg:address":"500 W Broadway St",
    "sg:city":"Lawrenceburg",
    "sg:classifiers":[
        {
            "category":"Health Services",
            "subcategory":"Optometrist",
            "type":"Services"
        }
    ],
    "sg:phone":"+1 502 839 5113",
    "sg:postcode":"40342",
    "sg:province":"KY",
    "wof:name":"Family Eye Care Ctr",
    "wof:placetype":"venue"
},
  "geometry": {"coordinates":[-84.899867,38.027124],"type":"Point"}
}