{
  "type": "Feature",
  "properties": {
    "addr:full":"100 Fountain Ave Paducah KY 42001",
    "addr:housenumber":"100",
    "addr:postcode":"42001",
    "addr:street":"Fountain Ave",
    "iso:country":"US",
    "sg:address":"100 Fountain Ave",
    "sg:city":"Paducah",
    "sg:classifiers":[
        {
            "category":"Banks & Credit Unions",
            "subcategory":"Bank",
            "type":"Services"
        }
    ],
    "sg:phone":"+1 270 442 7557",
    "sg:postcode":"42001",
    "sg:province":"KY",
    "sg:tags":[
        "loan",
        "real estate"
    ],
    "wof:name":"Pathway Financial Svc",
    "wof:placetype":"venue"
},
  "geometry": {"coordinates":[-88.618003,37.079955],"type":"Point"}
}