{
  "type": "Feature",
  "properties": {
    "iso:country":"US",
    "sg:address":"800 Stone Creek Pkwy",
    "sg:city":"Louisville",
    "sg:classifiers":[
        {
            "category":"Government",
            "subcategory":"Department Of Motor Vehicles",
            "type":"Public Place"
        }
    ],
    "sg:phone":"+1 502 327 5455",
    "sg:postcode":"40223",
    "sg:province":"KY",
    "sg:tags":[
        "ozone",
        "machine"
    ],
    "wof:name":"A2Z Ozone Systems",
    "wof:placetype":"venue"
},
  "geometry": {"coordinates":[-85.57398999999999,38.235859],"type":"Point"}
}