{
  "type": "Feature",
  "properties": {
    "iso:country":"US",
    "sg:address":"219 E Main St",
    "sg:city":"Hodgenville",
    "sg:classifiers":[
        {
            "category":"Shopping",
            "subcategory":"Computers & Home Electronics",
            "type":"Retail Goods"
        }
    ],
    "sg:phone":"+1 270 358 8404",
    "sg:postcode":"42748",
    "sg:province":"KY",
    "sg:tags":[
        "equipment",
        "dealer"
    ],
    "sg:website":"www.plugandplaypc.com",
    "wof:name":"Plug & Play PC",
    "wof:placetype":"venue"
},
  "geometry": {"coordinates":[-85.737798,37.573822],"type":"Point"}
}