{
  "type": "Feature",
  "properties": {
    "iso:country":"US",
    "sg:address":"5975 US Hwy 60",
    "sg:city":"Ashland",
    "sg:classifiers":[
        {
            "category":"Government",
            "subcategory":"Police Station",
            "type":"Public Place"
        }
    ],
    "sg:phone":"+1 606 928 6421",
    "sg:postcode":"41102",
    "sg:province":"KY",
    "sg:tags":[
        "state"
    ],
    "wof:name":"State Police",
    "wof:placetype":"venue"
},
  "geometry": {"coordinates":[-82.690544,38.43647],"type":"Point"}
}