{
  "type": "Feature",
  "properties": {
    "iso:country":"US",
    "sg:address":"4401 Fegenbush Ln",
    "sg:city":"Louisville",
    "sg:classifiers":[
        {
            "category":"Retail",
            "subcategory":"Car Wash",
            "type":"Services"
        }
    ],
    "sg:phone":"+1 502 491 3005",
    "sg:postcode":"40228",
    "sg:province":"KY",
    "sg:tags":[
        "polishing",
        "washing"
    ],
    "wof:name":"National Express Car Wash",
    "wof:placetype":"venue"
},
  "geometry": {"coordinates":[-85.63810100000001,38.185859],"type":"Point"}
}