{
  "type": "Feature",
  "properties": {
    "addr:full":"151 N Eagle Creek Dr Lexington KY 40509",
    "addr:housenumber":"151",
    "addr:postcode":"40509",
    "addr:street":"N Eagle Creek Dr",
    "iso:country":"US",
    "sg:address":"151 N Eagle Creek Dr",
    "sg:city":"Lexington",
    "sg:classifiers":[
        {
            "category":"Health Services",
            "subcategory":"Doctor",
            "type":"Services"
        },
        {
            "category":"Health Services",
            "subcategory":"Clinic",
            "type":"Services"
        },
        {
            "category":"Health Services",
            "subcategory":"Health Practitioner",
            "type":"Services"
        }
    ],
    "sg:phone":"+1 859 263 5318",
    "sg:postcode":"40509",
    "sg:province":"KY",
    "sg:tags":[
        "physician",
        "injury",
        "surgeons",
        "therapist",
        "treatment",
        "medicine",
        "surgeon",
        "sport",
        "rehabilitation",
        "physical"
    ],
    "sg:website":"http://www.realpagessites.com/lexphysicalmed",
    "wof:name":"Lexington Physical Medicine and Rehabilitation",
    "wof:placetype":"venue"
},
  "geometry": {"coordinates":[-84.439837,38.000764],"type":"Point"}
}