{
  "type": "Feature",
  "properties": {
    "iso:country":"US",
    "sg:address":"713 W Main St Ste 300",
    "sg:city":"Louisville",
    "sg:classifiers":[
        {
            "category":"Professional",
            "subcategory":"Engineering",
            "type":"Services"
        }
    ],
    "sg:phone":"+1 502 585 9944",
    "sg:postcode":"40202",
    "sg:province":"KY",
    "sg:tags":[
        "consulting",
        "engineer"
    ],
    "wof:name":"Paiki",
    "wof:placetype":"venue"
},
  "geometry": {"coordinates":[-85.761486,38.25713],"type":"Point"}
}