{
  "type": "Feature",
  "properties": {
    "addr:full":"135 W Muhammad Ali Blvd Louisville KY 40202",
    "addr:housenumber":"135",
    "addr:postcode":"40202",
    "addr:street":"W Muhammad Ali Blvd",
    "iso:country":"US",
    "sg:address":"135 W Muhammad Ali Blvd",
    "sg:city":"Louisville",
    "sg:classifiers":[
        {
            "category":"Banks & Credit Unions",
            "subcategory":"Bank",
            "type":"Services"
        }
    ],
    "sg:phone":"+1 502 587 1899",
    "sg:postcode":"40202",
    "sg:province":"KY",
    "wof:name":"First Bankers Trust",
    "wof:placetype":"venue"
},
  "geometry": {"coordinates":[-85.7531,38.250673],"type":"Point"}
}