{
  "type": "Feature",
  "properties": {
    "addr:full":"1001 W Kentucky St Louisville KY 40210",
    "addr:housenumber":"1001",
    "addr:postcode":"40210",
    "addr:street":"W Kentucky St",
    "iso:country":"US",
    "sg:address":"1001 W Kentucky St",
    "sg:city":"Louisville",
    "sg:classifiers":[
        {
            "category":"Local Transit",
            "type":"Transportation"
        }
    ],
    "sg:phone":"+1 502 589 5801",
    "sg:postcode":"40210",
    "sg:province":"KY",
    "wof:name":"Three Seeds Transportation",
    "wof:placetype":"venue"
},
  "geometry": {"coordinates":[-85.770972,38.240679],"type":"Point"}
}