{
  "type": "Feature",
  "properties": {
    "iso:country":"US",
    "sg:address":"2641 Veach Rd",
    "sg:city":"Owensboro",
    "sg:classifiers":[
        {
            "category":"Health Services",
            "subcategory":"Clinic",
            "type":"Services"
        }
    ],
    "sg:phone":"+1 270 852 5299",
    "sg:postcode":"42303",
    "sg:province":"KY",
    "wof:name":"Freedom Health Care",
    "wof:placetype":"venue"
},
  "geometry": {"coordinates":[-87.101871,37.749901],"type":"Point"}
}