{
  "type": "Feature",
  "properties": {
    "iso:country":"US",
    "sg:address":"12900 Fenwick Center Dr",
    "sg:city":"Louisville",
    "sg:classifiers":[
        {
            "category":"Recreation",
            "subcategory":"Boat Charter",
            "type":"Entertainment"
        },
        {
            "category":"Structure",
            "subcategory":"Warehouse",
            "type":"Public Place"
        },
        {
            "category":"Retail",
            "subcategory":"Storage",
            "type":"Services"
        }
    ],
    "sg:phone":"+1 502 254 9902",
    "sg:postcode":"40223",
    "sg:province":"KY",
    "sg:tags":[
        "yard",
        "warehouses-public-commercial",
        "automobile",
        "household",
        "recreational",
        "commercial",
        "campers-storage",
        "vehicle",
        "self"
    ],
    "wof:name":"Fenwick Storage",
    "wof:placetype":"venue"
},
  "geometry": {"coordinates":[-85.51383,38.25127],"type":"Point"}
}