{
  "type": "Feature",
  "properties": {
    "iso:country":"US",
    "sg:address":"384 Avawam Dr",
    "sg:city":"Richmond",
    "sg:classifiers":[
        {
            "category":"Shopping",
            "subcategory":"Pharmacy",
            "type":"Retail Goods"
        }
    ],
    "sg:phone":"+1 859 626 8775",
    "sg:postcode":"40475",
    "sg:province":"KY",
    "sg:tags":[
        "pharmaceutical",
        "consultant"
    ],
    "wof:name":"Pharmacy Management & Consltng",
    "wof:placetype":"venue"
},
  "geometry": {"coordinates":[-84.378666,37.898487],"type":"Point"}
}