{
  "type": "Feature",
  "properties": {
    "iso:country":"US",
    "sg:address":"1111 Versailles Rd",
    "sg:city":"Lawrenceburg",
    "sg:classifiers":[
        {
            "category":"Utilities",
            "subcategory":"Telephone",
            "type":"Services"
        }
    ],
    "sg:phone":"+1 502 839 1477",
    "sg:postcode":"40342",
    "sg:province":"KY",
    "sg:tags":[
        "company"
    ],
    "wof:name":"Columbia Tel Co",
    "wof:placetype":"venue"
},
  "geometry": {"coordinates":[-84.88558500000001,38.040896],"type":"Point"}
}