{
  "type": "Feature",
  "properties": {
    "addr:full":"157 US Hwy 27 Somerset KY 42501",
    "addr:housenumber":"157",
    "addr:postcode":"42501",
    "addr:street":"Us Hwy 27",
    "iso:country":"US",
    "sg:address":"157 US Hwy 27",
    "sg:city":"Somerset",
    "sg:classifiers":[
        {
            "category":"Restaurant",
            "type":"Food & Drink"
        }
    ],
    "sg:phone":"+1 606 679 4918",
    "sg:postcode":"42501",
    "sg:province":"KY",
    "wof:name":"Wendy's",
    "wof:placetype":"venue"
},
  "geometry": {"coordinates":[-84.629986,37.143254],"type":"Point"}
}