{
  "type": "Feature",
  "properties": {
    "addr:full":"918 2nd St Henderson KY 42420",
    "addr:housenumber":"918",
    "addr:postcode":"42420",
    "addr:street":"2Nd St",
    "iso:country":"US",
    "sg:address":"918 2nd St",
    "sg:city":"Henderson",
    "sg:classifiers":[
        {
            "category":"Health Services",
            "subcategory":"Health Practitioner",
            "type":"Services"
        }
    ],
    "sg:phone":"+1 270 826 4544",
    "sg:postcode":"42420",
    "sg:province":"KY",
    "wof:name":"Wellness Center",
    "wof:placetype":"venue"
},
  "geometry": {"coordinates":[-87.581019,37.836393],"type":"Point"}
}