{
  "type": "Feature",
  "properties": {
    "iso:country":"US",
    "sg:address":"154 E Main St",
    "sg:city":"Grayson",
    "sg:classifiers":[
        {
            "category":"Shopping",
            "subcategory":"Catalog Store",
            "type":"Retail Goods"
        }
    ],
    "sg:phone":"+1 606 474 7852",
    "sg:postcode":"41143",
    "sg:province":"KY",
    "sg:tags":[
        "mail",
        "order"
    ],
    "wof:name":"J C Penney Catalog",
    "wof:placetype":"venue"
},
  "geometry": {"coordinates":[-82.947188,38.33221],"type":"Point"}
}