{
  "type": "Feature",
  "properties": {
    "iso:country":"US",
    "sg:address":"201 Center St",
    "sg:city":"Caneyville",
    "sg:classifiers":[
        {
            "category":"Professional",
            "type":"Services"
        }
    ],
    "sg:phone":"+1 270 879 4506",
    "sg:postcode":"42721",
    "sg:province":"KY",
    "sg:tags":[
        "establishment"
    ],
    "wof:name":"Goldenbury Lorrtisha",
    "wof:placetype":"venue"
},
  "geometry": {"coordinates":[-86.49326600000001,37.419899],"type":"Point"}
}