{
  "type": "Feature",
  "properties": {
    "iso:country":"US",
    "sg:address":"7659 Turfway Rd",
    "sg:city":"Florence",
    "sg:classifiers":[
        {
            "category":"Retail",
            "subcategory":"Auto Repair",
            "type":"Services"
        }
    ],
    "sg:phone":"+1 859 525 6927",
    "sg:postcode":"41042",
    "sg:province":"KY",
    "sg:tags":[
        "body",
        "automobile",
        "painting"
    ],
    "wof:name":"JAJ Auto Repair",
    "wof:placetype":"venue"
},
  "geometry": {"coordinates":[-84.640154,39.022684],"type":"Point"}
}