{
  "type": "Feature",
  "properties": {
    "iso:country":"US",
    "sg:address":"211 Grandview Dr",
    "sg:city":"Covington",
    "sg:classifiers":[
        {
            "category":"Ferry",
            "type":"Transportation"
        }
    ],
    "sg:phone":"+1 859 341 4161",
    "sg:postcode":"41017",
    "sg:province":"KY",
    "sg:tags":[
        "company",
        "steamship"
    ],
    "wof:name":"Maersk Inc",
    "wof:placetype":"venue"
},
  "geometry": {"coordinates":[-84.563535,39.051963],"type":"Point"}
}