{
  "type": "Feature",
  "properties": {
    "iso:country":"US",
    "sg:address":"906 S Main St",
    "sg:city":"Nicholasville",
    "sg:classifiers":[
        {
            "category":"Shopping",
            "subcategory":"Florist",
            "type":"Retail Goods"
        }
    ],
    "sg:phone":"+1 859 885 9077",
    "sg:postcode":"40356",
    "sg:province":"KY",
    "wof:name":"Designs By Kim Florists & Gfts",
    "wof:placetype":"venue"
},
  "geometry": {"coordinates":[-84.57797100000001,37.867597],"type":"Point"}
}