{
  "type": "Feature",
  "properties": {
    "iso:country":"US",
    "sg:address":"5171 Scottsville Rd",
    "sg:city":"Glasgow",
    "sg:classifiers":[
        {
            "category":"Retail",
            "subcategory":"Repair Shop",
            "type":"Services"
        }
    ],
    "sg:phone":"+1 270 646 2674",
    "sg:postcode":"42141",
    "sg:province":"KY",
    "sg:tags":[
        "industrial",
        "merchandise"
    ],
    "wof:name":"Needmore Lane Repair",
    "wof:placetype":"venue"
},
  "geometry": {"coordinates":[-85.976108,36.943644],"type":"Point"}
}