{
  "type": "Feature",
  "properties": {
    "addr:full":"1848 Triplett St Owensboro KY 42303",
    "addr:housenumber":"1848",
    "addr:postcode":"42303",
    "addr:street":"Triplett St",
    "iso:country":"US",
    "sg:address":"1848 Triplett St",
    "sg:city":"Owensboro",
    "sg:classifiers":[
        {
            "category":"Shopping",
            "subcategory":"Used Merchandise",
            "type":"Retail Goods"
        }
    ],
    "sg:phone":"+1 270 683 1060",
    "sg:postcode":"42303",
    "sg:province":"KY",
    "sg:tags":[
        "shop",
        "thrift"
    ],
    "wof:name":"St Vincent De Paul Store",
    "wof:placetype":"venue"
},
  "geometry": {"coordinates":[-87.102833,37.75838],"type":"Point"}
}