{
  "type": "Feature",
  "properties": {
    "addr:full":"7151 Austin Tracy Rd Fountain Run KY 42133",
    "addr:housenumber":"7151",
    "addr:postcode":"42133",
    "addr:street":"Austin Tracy Rd",
    "iso:country":"US",
    "sg:address":"7151 Austin Tracy Rd",
    "sg:city":"Fountain Run",
    "sg:classifiers":[
        {
            "category":"Food & Beverages",
            "subcategory":"Groceries & Convenience Stores",
            "type":"Retail Goods"
        }
    ],
    "sg:phone":"+1 270 434 3688",
    "sg:postcode":"42133",
    "sg:province":"KY",
    "sg:tags":[
        "grocer"
    ],
    "wof:name":"Tracy General Store",
    "wof:placetype":"venue"
},
  "geometry": {"coordinates":[-85.96986,36.798048],"type":"Point"}
}