{
  "type": "Feature",
  "properties": {
    "iso:country":"US",
    "sg:address":"1725 Ashley Cir",
    "sg:city":"Bowling Green",
    "sg:classifiers":[
        {
            "category":"Shopping",
            "subcategory":"Jewelry",
            "type":"Retail Goods"
        }
    ],
    "sg:phone":"+1 270 780 0019",
    "sg:postcode":"42104",
    "sg:province":"KY",
    "sg:tags":[
        "designer"
    ],
    "wof:name":"Nest Featherings",
    "wof:placetype":"venue"
},
  "geometry": {"coordinates":[-86.437078,36.967449],"type":"Point"}
}