{
  "type": "Feature",
  "properties": {
    "iso:country":"US",
    "sg:address":"1218 Diuguid Dr",
    "sg:city":"Murray",
    "sg:classifiers":[
        {
            "category":"Autos & Motor Vehicles",
            "subcategory":"Automobile Sales",
            "type":"Retail Goods"
        }
    ],
    "sg:phone":"+1 270 753 8763",
    "sg:postcode":"42071",
    "sg:province":"KY",
    "sg:tags":[
        "car",
        "dealer"
    ],
    "wof:name":"Jerry West Used Cars",
    "wof:placetype":"venue"
},
  "geometry": {"coordinates":[-88.31385,36.634652],"type":"Point"}
}