{
  "type": "Feature",
  "properties": {
    "iso:country":"US",
    "sg:address":"803 State Hwy 510",
    "sg:city":"Bledsoe",
    "sg:classifiers":[
        {
            "category":"Freight",
            "type":"Transportation"
        }
    ],
    "sg:phone":"+1 606 558 3292",
    "sg:postcode":"40810",
    "sg:province":"KY",
    "sg:tags":[
        "operator",
        "local",
        "trucking"
    ],
    "wof:name":"J&B Trucking",
    "wof:placetype":"venue"
},
  "geometry": {"coordinates":[-83.18560600000001,36.94974],"type":"Point"}
}