{
  "type": "Feature",
  "properties": {
    "iso:country":"US",
    "sg:address":"2980 State Hwy 44 E",
    "sg:city":"Shepherdsville",
    "sg:classifiers":[
        {
            "category":"Health Services",
            "subcategory":"Doctor",
            "type":"Services"
        }
    ],
    "sg:phone":"+1 502 543 7999",
    "sg:postcode":"40165",
    "sg:province":"KY",
    "sg:tags":[
        "dentist"
    ],
    "wof:name":"Williams Dental Clinic",
    "wof:placetype":"venue"
},
  "geometry": {"coordinates":[-85.66763899999999,38.008858],"type":"Point"}
}