{
  "type": "Feature",
  "properties": {
    "addr:full":"5733 Preston Hwy Louisville KY 40219",
    "addr:housenumber":"5733",
    "addr:postcode":"40219",
    "addr:street":"Preston Hwy",
    "iso:country":"US",
    "sg:address":"5733 Preston Hwy",
    "sg:city":"Louisville",
    "sg:classifiers":[
        {
            "category":"Banks & Credit Unions",
            "subcategory":"Bank",
            "type":"Services"
        }
    ],
    "sg:phone":"+1 502 969 0329",
    "sg:postcode":"40219",
    "sg:province":"KY",
    "wof:name":"US Bank",
    "wof:placetype":"venue"
},
  "geometry": {"coordinates":[-85.705665,38.168049],"type":"Point"}
}