{
  "type": "Feature",
  "properties": {
    "addr:full":"8101 Connector Dr Florence KY 41042",
    "addr:housenumber":"8101",
    "addr:postcode":"41042",
    "addr:street":"Connector Dr",
    "iso:country":"US",
    "sg:address":"8101 Connector Dr",
    "sg:city":"Florence",
    "sg:classifiers":[
        {
            "category":"Restaurant",
            "type":"Food & Drink"
        }
    ],
    "sg:phone":"+1 859 525 8222",
    "sg:postcode":"41042",
    "sg:province":"KY",
    "sg:tags":[
        "mexican"
    ],
    "wof:name":"Rio Grande Mexican Restaurant",
    "wof:placetype":"venue"
},
  "geometry": {"coordinates":[-84.652199,38.988201],"type":"Point"}
}