{
  "type": "Feature",
  "properties": {
    "iso:country":"US",
    "sg:address":"1217 Everett Ave",
    "sg:city":"Louisville",
    "sg:classifiers":[
        {
            "category":"Professional",
            "subcategory":"Business Services",
            "type":"Services"
        }
    ],
    "sg:phone":"+1 502 451 6241",
    "sg:postcode":"40204",
    "sg:province":"KY",
    "sg:tags":[
        "auctioneer"
    ],
    "sg:website":"http://www.usamusement.com",
    "wof:name":"United States Amusement Auctio",
    "wof:placetype":"venue"
},
  "geometry": {"coordinates":[-85.715512,38.238527],"type":"Point"}
}