{
  "type": "Feature",
  "properties": {
    "iso:country":"US",
    "sg:address":"933 Clarks Ln",
    "sg:city":"Louisville",
    "sg:classifiers":[
        {
            "category":"Social Services",
            "type":"Services"
        }
    ],
    "sg:phone":"+1 502 635 2766",
    "sg:postcode":"40217",
    "sg:province":"KY",
    "sg:tags":[
        "worker"
    ],
    "wof:name":"Cheryl Ades Lcsw",
    "wof:placetype":"venue"
},
  "geometry": {"coordinates":[-85.733559,38.217287],"type":"Point"}
}