{
  "type": "Feature",
  "properties": {
    "iso:country":"US",
    "sg:address":"1436 Eastern Pkwy",
    "sg:city":"Louisville",
    "sg:classifiers":[
        {
            "category":"Social Services",
            "subcategory":"Child Care",
            "type":"Services"
        }
    ],
    "sg:phone":"+1 502 458 3318",
    "sg:postcode":"40204",
    "sg:province":"KY",
    "wof:name":"Highlands Educational Ctr Inc",
    "wof:placetype":"venue"
},
  "geometry": {"coordinates":[-85.716542,38.228242],"type":"Point"}
}