{
  "type": "Feature",
  "properties": {
    "iso:country":"US",
    "sg:address":"602 Fairview Ave",
    "sg:city":"Eddyville",
    "sg:classifiers":[
        {
            "category":"Organizations",
            "subcategory":"Religious Organization",
            "type":"Services"
        }
    ],
    "sg:phone":"+1 270 388 9087",
    "sg:postcode":"42038",
    "sg:province":"KY",
    "sg:tags":[
        "church"
    ],
    "wof:name":"Israel Chapel Fwb Church",
    "wof:placetype":"venue"
},
  "geometry": {"coordinates":[-88.087459,37.090319],"type":"Point"}
}