{
  "type": "Feature",
  "properties": {
    "iso:country":"US",
    "sg:address":"720 Sparta Pike",
    "sg:city":"Warsaw",
    "sg:classifiers":[
        {
            "category":"Government",
            "subcategory":"Office",
            "type":"Public Place"
        }
    ],
    "sg:phone":"+1 859 567 6300",
    "sg:postcode":"41095",
    "sg:province":"KY",
    "sg:tags":[
        "govt",
        "city"
    ],
    "wof:name":"Warsaw Water & Sewer Supt",
    "wof:placetype":"venue"
},
  "geometry": {"coordinates":[-84.8984,38.777328],"type":"Point"}
}