{
  "type": "Feature",
  "properties": {
    "iso:country":"US",
    "sg:address":"814 Cindy Blair Way",
    "sg:city":"Lexington",
    "sg:classifiers":[
        {
            "category":"Building & Trades",
            "subcategory":"Construction",
            "type":"Services"
        }
    ],
    "sg:phone":"+1 859 223 7546",
    "sg:postcode":"40503",
    "sg:province":"KY",
    "sg:tags":[
        "house"
    ],
    "wof:name":"Curtis Art Builders",
    "wof:placetype":"venue"
},
  "geometry": {"coordinates":[-84.565153,37.999695],"type":"Point"}
}