{
  "type": "Feature",
  "properties": {
    "iso:country":"US",
    "sg:address":"406 Main St",
    "sg:city":"Greenup",
    "sg:classifiers":[
        {
            "category":"Shopping",
            "subcategory":"Used Merchandise",
            "type":"Retail Goods"
        }
    ],
    "sg:phone":"+1 606 473 3388",
    "sg:postcode":"41144",
    "sg:province":"KY",
    "sg:tags":[
        "antique"
    ],
    "wof:name":"Cheryl's Coffee Shop",
    "wof:placetype":"venue"
},
  "geometry": {"coordinates":[-82.836353,38.577584],"type":"Point"}
}