{
  "type": "Feature",
  "properties": {
    "iso:country":"US",
    "sg:address":"122 Electric Ave",
    "sg:city":"Southgate",
    "sg:classifiers":[
        {
            "category":"Government",
            "subcategory":"Fire Station",
            "type":"Public Place"
        }
    ],
    "sg:phone":"+1 859 781 5598",
    "sg:postcode":"41071",
    "sg:province":"KY",
    "sg:tags":[
        "department"
    ],
    "wof:name":"Fire Chief",
    "wof:placetype":"venue"
},
  "geometry": {"coordinates":[-84.473795,39.071397],"type":"Point"}
}