{
  "type": "Feature",
  "properties": {
    "addr:full":"110 Park Ave Glasgow KY 42141",
    "addr:housenumber":"110",
    "addr:postcode":"42141",
    "addr:street":"Park Ave",
    "iso:country":"US",
    "sg:address":"110 Park Ave",
    "sg:city":"Glasgow",
    "sg:classifiers":[
        {
            "category":"Sports & Exercise",
            "subcategory":"Bowling",
            "type":"Entertainment"
        }
    ],
    "sg:phone":"+1 270 651 9020",
    "sg:postcode":"42141",
    "sg:province":"KY",
    "sg:tags":[
        "center"
    ],
    "wof:name":"Highlander Bowl",
    "wof:placetype":"venue"
},
  "geometry": {"coordinates":[-85.900108,37.001175],"type":"Point"}
}