{
  "type": "Feature",
  "properties": {
    "addr:full":"3390 Old Fulton Harris Rd South Fulton KY 38257",
    "addr:housenumber":"3390",
    "addr:postcode":"38257",
    "addr:street":"Old Fulton Harris Rd",
    "iso:country":"US",
    "sg:address":"3390 Old Fulton Harris Rd",
    "sg:city":"South Fulton",
    "sg:classifiers":[
        {
            "category":"Farming",
            "subcategory":"Farm",
            "type":"Manufacturing & Wholesale Goods"
        }
    ],
    "sg:phone":"+1 731 479 9992",
    "sg:postcode":"38257",
    "sg:province":"KY",
    "sg:tags":[
        "livestock",
        "crop",
        "general"
    ],
    "wof:name":"John L McConnell",
    "wof:placetype":"venue"
},
  "geometry": {"coordinates":[-88.909043,36.4344],"type":"Point"}
}