{
  "type": "Feature",
  "properties": {
    "iso:country":"US",
    "sg:address":"2933 Bowman Ave",
    "sg:city":"Louisville",
    "sg:classifiers":[
        {
            "category":"Professional",
            "subcategory":"Lawyer & Legal Services",
            "type":"Services"
        }
    ],
    "sg:phone":"+1 502 451 3030",
    "sg:postcode":"40205",
    "sg:province":"KY",
    "sg:tags":[
        "attorney"
    ],
    "wof:name":"Wetterer & Clare",
    "wof:placetype":"venue"
},
  "geometry": {"coordinates":[-85.653372,38.221988],"type":"Point"}
}