{
  "type": "Feature",
  "properties": {
    "iso:country":"US",
    "sg:address":"6311 Jacks Creek Pike",
    "sg:city":"Lexington",
    "sg:classifiers":[
        {
            "category":"Manufacturing",
            "subcategory":"Tools & Machinery",
            "type":"Manufacturing & Wholesale Goods"
        }
    ],
    "sg:phone":"+1 859 271 6837",
    "sg:postcode":"40515",
    "sg:province":"KY",
    "sg:tags":[
        "equipment",
        "industrial",
        "mold",
        "mfg"
    ],
    "wof:name":"Sundance Mold Co",
    "wof:placetype":"venue"
},
  "geometry": {"coordinates":[-84.385813,37.877388],"type":"Point"}
}