{
  "type": "Feature",
  "properties": {
    "iso:country":"US",
    "sg:address":"5243 Idlewild Rd",
    "sg:city":"Burlington",
    "sg:classifiers":[
        {
            "category":"Retail",
            "subcategory":"Repair Shop",
            "type":"Services"
        }
    ],
    "sg:phone":"+1 859 586 8836",
    "sg:postcode":"41005",
    "sg:province":"KY",
    "sg:tags":[
        "welding"
    ],
    "wof:name":"Haggard Affordable Mobile",
    "wof:placetype":"venue"
},
  "geometry": {"coordinates":[-84.74101,39.038732],"type":"Point"}
}