{
  "type": "Feature",
  "properties": {
    "iso:country":"US",
    "sg:address":"2005 Versailles Rd",
    "sg:city":"Lexington",
    "sg:classifiers":[
        {
            "category":"Food & Beverages",
            "subcategory":"Liquor & Beverages",
            "type":"Retail Goods"
        }
    ],
    "sg:phone":"+1 859 254 0358",
    "sg:postcode":"40504",
    "sg:province":"KY",
    "wof:name":"Thoroughbred Shop",
    "wof:placetype":"venue"
},
  "geometry": {"coordinates":[-84.54236400000001,38.047778],"type":"Point"}
}