{
  "type": "Feature",
  "properties": {
    "iso:country":"US",
    "sg:address":"620 North Dr",
    "sg:city":"Hopkinsville",
    "sg:classifiers":[
        {
            "category":"Building & Trades",
            "subcategory":"Construction",
            "type":"Services"
        }
    ],
    "sg:phone":"+1 270 885 4010",
    "sg:postcode":"42240",
    "sg:province":"KY",
    "sg:tags":[
        "contractor",
        "metal",
        "fabrication",
        "structural"
    ],
    "wof:name":"Quality Sheet Metal LLC",
    "wof:placetype":"venue"
},
  "geometry": {"coordinates":[-87.49566900000001,36.8781],"type":"Point"}
}