{
  "type": "Feature",
  "properties": {
    "addr:full":"207 Main St Crab Orchard KY 40419",
    "addr:housenumber":"207",
    "addr:postcode":"40419",
    "addr:street":"Main St",
    "iso:country":"US",
    "sg:address":"207 Main St",
    "sg:city":"Crab Orchard",
    "sg:classifiers":[
        {
            "category":"Health Services",
            "subcategory":"Doctor",
            "type":"Services"
        }
    ],
    "sg:phone":"+1 606 355 7300",
    "sg:postcode":"40419",
    "sg:province":"KY",
    "sg:tags":[
        "physician",
        "surgeon"
    ],
    "wof:name":"Crab Orchard Family Practice",
    "wof:placetype":"venue"
},
  "geometry": {"coordinates":[-84.50650899999999,37.462644],"type":"Point"}
}