{
  "type": "Feature",
  "properties": {
    "addr:full":"12583 Airline Rd Henderson KY 42420",
    "addr:housenumber":"12583",
    "addr:postcode":"42420",
    "addr:street":"Airline Rd",
    "iso:country":"US",
    "sg:address":"12583 Airline Rd",
    "sg:city":"Henderson",
    "sg:classifiers":[
        {
            "category":"Building & Trades",
            "subcategory":"Construction",
            "type":"Services"
        }
    ],
    "sg:phone":"+1 270 830 7309",
    "sg:postcode":"42420",
    "sg:province":"KY",
    "sg:tags":[
        "hanging",
        "contractor"
    ],
    "wof:name":"Excellent Painting",
    "wof:placetype":"venue"
},
  "geometry": {"coordinates":[-87.48417000000001,37.766973],"type":"Point"}
}