{
  "type": "Feature",
  "properties": {
    "addr:full":"2432 Greenup Ave Ashland KY 41101",
    "addr:housenumber":"2432",
    "addr:postcode":"41101",
    "addr:street":"Greenup Ave",
    "iso:country":"US",
    "sg:address":"2432 Greenup Ave",
    "sg:city":"Ashland",
    "sg:classifiers":[
        {
            "category":"Wholesale",
            "subcategory":"Hardware",
            "type":"Manufacturing & Wholesale Goods"
        }
    ],
    "sg:phone":"+1 606 324 0232",
    "sg:postcode":"41101",
    "sg:province":"KY",
    "sg:tags":[
        "refrigerating"
    ],
    "wof:name":"Slone Refrigeration Co",
    "wof:placetype":"venue"
},
  "geometry": {"coordinates":[-82.62879700000001,38.474563],"type":"Point"}
}