{
  "type": "Feature",
  "properties": {
    "addr:full":"2050 E Blue Lick Rd Shepherdsville KY 40165",
    "addr:housenumber":"2050",
    "addr:postcode":"40165",
    "addr:street":"E Blue Lick Rd",
    "iso:country":"US",
    "sg:address":"2050 E Blue Lick Rd",
    "sg:city":"Shepherdsville",
    "sg:classifiers":[
        {
            "category":"Restaurant",
            "type":"Food & Drink"
        }
    ],
    "sg:menulink":"http://www.allmenus.com/ky/shepherdsville-northwest/120725-subway/menu/",
    "sg:phone":"+1 502 955 5049",
    "sg:postcode":"40165",
    "sg:province":"KY",
    "sg:tags":[
        "american",
        "sandwich"
    ],
    "wof:name":"Subway",
    "wof:placetype":"venue"
},
  "geometry": {"coordinates":[-85.70009,38.051474],"type":"Point"}
}