{
  "type": "Feature",
  "properties": {
    "addr:full":"3320 Nicholasville Rd Lexington KY 40503",
    "addr:housenumber":"3320",
    "addr:postcode":"40503",
    "addr:street":"Nicholasville Rd",
    "iso:country":"US",
    "sg:address":"3320 Nicholasville Rd",
    "sg:city":"Lexington",
    "sg:classifiers":[
        {
            "category":"Shopping",
            "type":"Retail Goods"
        }
    ],
    "sg:phone":"+1 859 272 1022",
    "sg:postcode":"40503",
    "sg:province":"KY",
    "sg:tags":[
        "cosmetic",
        "perfume"
    ],
    "wof:name":"Ulta 3 Cosmetics",
    "wof:placetype":"venue"
},
  "geometry": {"coordinates":[-84.523616,37.990917],"type":"Point"}
}