{
  "type": "Feature",
  "properties": {
    "iso:country":"US",
    "sg:address":"423 Givens Rd",
    "sg:city":"Morganfield",
    "sg:classifiers":[
        {
            "category":"Professional",
            "subcategory":"Business Services",
            "type":"Services"
        }
    ],
    "sg:phone":"+1 270 639 9370",
    "sg:postcode":"42437",
    "sg:province":"KY",
    "wof:name":"Chandley Enterprises",
    "wof:placetype":"venue"
},
  "geometry": {"coordinates":[-87.786311,37.591079],"type":"Point"}
}