{
  "type": "Feature",
  "properties": {
    "iso:country":"US",
    "sg:address":"872 Bypass Rd",
    "sg:city":"Winchester",
    "sg:classifiers":[
        {
            "category":"Professional",
            "subcategory":"Business Services",
            "type":"Services"
        }
    ],
    "sg:phone":"+1 859 737 3544",
    "sg:postcode":"40391",
    "sg:province":"KY",
    "sg:tags":[
        "packaging"
    ],
    "wof:name":"Mailboxes & More",
    "wof:placetype":"venue"
},
  "geometry": {"coordinates":[-84.212745,38.001927],"type":"Point"}
}