{
  "type": "Feature",
  "properties": {
    "iso:country":"US",
    "sg:address":"204 W Main St",
    "sg:city":"Taylorsville",
    "sg:classifiers":[
        {
            "category":"Health Services",
            "subcategory":"Doctor",
            "type":"Services"
        }
    ],
    "sg:phone":"+1 502 477 8088",
    "sg:postcode":"40071",
    "sg:province":"KY",
    "sg:tags":[
        "dentist"
    ],
    "wof:name":"John M Edwards Inc",
    "wof:placetype":"venue"
},
  "geometry": {"coordinates":[-85.348215,38.030533],"type":"Point"}
}