{
  "type": "Feature",
  "properties": {
    "addr:full":"675 W Miller Rd Alexandria KY 41001",
    "addr:housenumber":"675",
    "addr:postcode":"41001",
    "addr:street":"W Miller Rd",
    "iso:country":"US",
    "sg:address":"675 W Miller Rd",
    "sg:city":"Alexandria",
    "sg:classifiers":[
        {
            "category":"Organizations",
            "subcategory":"Religious Organization",
            "type":"Services"
        }
    ],
    "sg:phone":"+1 859 635 4720",
    "sg:postcode":"41001",
    "sg:province":"KY",
    "sg:tags":[
        "church"
    ],
    "wof:name":"Bethel Baptist Church",
    "wof:placetype":"venue"
},
  "geometry": {"coordinates":[-84.408539,38.927783],"type":"Point"}
}