{
  "type": "Feature",
  "properties": {
    "addr:full":"1608 W Stockton St Edmonton KY 42129",
    "addr:housenumber":"1608",
    "addr:postcode":"42129",
    "addr:street":"W Stockton St",
    "iso:country":"US",
    "sg:address":"1608 W Stockton St",
    "sg:city":"Edmonton",
    "sg:classifiers":[
        {
            "category":"Recreation",
            "type":"Entertainment"
        }
    ],
    "sg:phone":"+1 270 432 7204",
    "sg:postcode":"42129",
    "sg:province":"KY",
    "sg:tags":[
        "center"
    ],
    "wof:name":"Bowling Park",
    "wof:placetype":"venue"
},
  "geometry": {"coordinates":[-85.65057400000001,36.988579],"type":"Point"}
}