{
  "type": "Feature",
  "properties": {
    "addr:full":"1041 Fred Fackler Rd Brandenburg KY 40108",
    "addr:housenumber":"1041",
    "addr:postcode":"40108",
    "addr:street":"Fred Fackler Rd",
    "iso:country":"US",
    "sg:address":"1041 Fred Fackler Rd",
    "sg:city":"Brandenburg",
    "sg:classifiers":[
        {
            "category":"Building & Trades",
            "subcategory":"Construction",
            "type":"Services"
        }
    ],
    "sg:phone":"+1 270 422 3859",
    "sg:postcode":"40108",
    "sg:province":"KY",
    "sg:tags":[
        "general",
        "contractor"
    ],
    "wof:name":"Bill Wood Construction",
    "wof:placetype":"venue"
},
  "geometry": {"coordinates":[-86.21345100000001,37.963369],"type":"Point"}
}