{
  "type": "Feature",
  "properties": {
    "iso:country":"US",
    "sg:address":"3414 Broeck Pointe Cir",
    "sg:city":"Louisville",
    "sg:classifiers":[
        {
            "category":"Retail",
            "subcategory":"Repair Shop",
            "type":"Services"
        }
    ],
    "sg:phone":"+1 502 429 8419",
    "sg:postcode":"40241",
    "sg:province":"KY",
    "wof:name":"Rita Louise Myers",
    "wof:placetype":"venue"
},
  "geometry": {"coordinates":[-85.587491,38.295744],"type":"Point"}
}