{
  "type": "Feature",
  "properties": {
    "iso:country":"US",
    "sg:address":"4500 Bowling Blvd",
    "sg:city":"Louisville",
    "sg:classifiers":[
        {
            "category":"Manufacturing",
            "subcategory":"Metals",
            "type":"Manufacturing & Wholesale Goods"
        }
    ],
    "sg:phone":"+1 502 894 6052",
    "sg:postcode":"40207",
    "sg:province":"KY",
    "sg:tags":[
        "stevedoring",
        "contractor"
    ],
    "wof:name":"Cincinnati Bulk Terminals",
    "wof:placetype":"venue"
},
  "geometry": {"coordinates":[-85.63131,38.240528],"type":"Point"}
}