{
  "type": "Feature",
  "properties": {
    "iso:country":"US",
    "sg:address":"1501 Daviess St",
    "sg:city":"Owensboro",
    "sg:classifiers":[
        {
            "category":"Home & Garden",
            "subcategory":"Hardware",
            "type":"Retail Goods"
        }
    ],
    "sg:phone":"+1 270 684 9438",
    "sg:postcode":"42303",
    "sg:province":"KY",
    "sg:website":"www.thriftway.net",
    "wof:name":"Thriftway Home Ctr",
    "wof:placetype":"venue"
},
  "geometry": {"coordinates":[-87.10894500000001,37.762647],"type":"Point"}
}