{
  "type": "Feature",
  "properties": {
    "iso:country":"US",
    "sg:address":"1369 Jones St",
    "sg:city":"Radcliff",
    "sg:classifiers":[
        {
            "category":"Retail",
            "subcategory":"Repair Shop",
            "type":"Services"
        }
    ],
    "sg:phone":"+1 270 351 3365",
    "sg:postcode":"40160",
    "sg:province":"KY",
    "sg:tags":[
        "upholsterer"
    ],
    "wof:name":"Ike's Upholstery",
    "wof:placetype":"venue"
},
  "geometry": {"coordinates":[-85.918459,37.826495],"type":"Point"}
}