{
  "type": "Feature",
  "properties": {
    "addr:full":"905 Lovers Ln Bowling Green KY 42103",
    "addr:housenumber":"905",
    "addr:postcode":"42103",
    "addr:street":"Lovers Ln",
    "iso:country":"US",
    "sg:address":"905 Lovers Ln",
    "sg:city":"Bowling Green",
    "sg:classifiers":[
        {
            "category":"Real Estate",
            "subcategory":"Real Estate Agent",
            "type":"Services"
        }
    ],
    "sg:phone":"+1 270 781 3767",
    "sg:postcode":"42103",
    "sg:province":"KY",
    "sg:tags":[
        "appraiser"
    ],
    "wof:name":"Graham Appraisal Co",
    "wof:placetype":"venue"
},
  "geometry": {"coordinates":[-86.415201,36.956101],"type":"Point"}
}