{
  "type": "Feature",
  "properties": {
    "addr:full":"600 Watertower Byp Campbellsville KY 42718",
    "addr:housenumber":"600",
    "addr:postcode":"42718",
    "addr:street":"Watertower Byp",
    "iso:country":"US",
    "sg:address":"600 Watertower Byp",
    "sg:city":"Campbellsville",
    "sg:classifiers":[
        {
            "category":"Home & Garden",
            "subcategory":"Furniture",
            "type":"Retail Goods"
        }
    ],
    "sg:phone":"+1 270 789 1741",
    "sg:postcode":"42718",
    "sg:province":"KY",
    "wof:name":"Campbellsville Handmade Cherry",
    "wof:placetype":"venue"
},
  "geometry": {"coordinates":[-85.320936,37.339204],"type":"Point"}
}