{
  "type": "Feature",
  "properties": {
    "iso:country":"US",
    "sg:address":"5400 Chaffee Ave",
    "sg:city":"Fort Knox",
    "sg:classifiers":[
        {
            "category":"Manufacturing",
            "subcategory":"Rubber & Plastics",
            "type":"Manufacturing & Wholesale Goods"
        }
    ],
    "sg:phone":"+1 502 943 9010",
    "sg:postcode":"40121",
    "sg:province":"KY",
    "wof:name":"Kira Inc",
    "wof:placetype":"venue"
},
  "geometry": {"coordinates":[-85.987859,37.90013],"type":"Point"}
}