{
  "type": "Feature",
  "properties": {
    "addr:full":"4800 Houston Rd Florence KY 41042",
    "addr:housenumber":"4800",
    "addr:postcode":"41042",
    "addr:street":"Houston Rd",
    "iso:country":"US",
    "sg:address":"4800 Houston Rd",
    "sg:city":"Florence",
    "sg:classifiers":[
        {
            "category":"Home & Garden",
            "subcategory":"Household Appliances",
            "type":"Retail Goods"
        },
        {
            "category":"Retail",
            "subcategory":"Repair Shop",
            "type":"Services"
        },
        {
            "category":"Home & Garden",
            "subcategory":"Building Materials",
            "type":"Retail Goods"
        },
        {
            "category":"Building & Trades",
            "subcategory":"Construction",
            "type":"Services"
        },
        {
            "category":"Home & Garden",
            "subcategory":"Carpets & Floor Coverings",
            "type":"Retail Goods"
        }
    ],
    "sg:phone":"+1 877 471 9739",
    "sg:postcode":"41042",
    "sg:province":"KY",
    "sg:tags":[
        "heater",
        "major",
        "rug",
        "improvement",
        "water",
        "maintenance",
        "tile-contractors",
        "small",
        "contractor"
    ],
    "sg:website":"http://www.lowesstores.com",
    "wof:name":"Lowe's? Home Improvement",
    "wof:placetype":"venue"
},
  "geometry": {"coordinates":[-84.626503,39.022099],"type":"Point"}
}