{
  "type": "Feature",
  "properties": {
    "iso:country":"US",
    "sg:address":"3793 Poplar Level Rd",
    "sg:city":"Louisville",
    "sg:classifiers":[
        {
            "category":"Health Services",
            "subcategory":"Doctor",
            "type":"Services"
        }
    ],
    "sg:phone":"+1 502 452 1916",
    "sg:postcode":"40213",
    "sg:province":"KY",
    "sg:tags":[
        "physician",
        "surgeon"
    ],
    "wof:name":"Pediatric Accute Care",
    "wof:placetype":"venue"
},
  "geometry": {"coordinates":[-85.713499,38.206327],"type":"Point"}
}