{
  "type": "Feature",
  "properties": {
    "addr:full":"801 Mammoth Cave St Cave City KY 42127",
    "addr:housenumber":"801",
    "addr:postcode":"42127",
    "addr:street":"Mammoth Cave St",
    "iso:country":"US",
    "sg:address":"801 Mammoth Cave St",
    "sg:city":"Cave City",
    "sg:classifiers":[
        {
            "category":"Travel",
            "subcategory":"Hotels & Motels",
            "type":"Entertainment"
        }
    ],
    "sg:phone":"+1 270 773 2030",
    "sg:postcode":"42127",
    "sg:province":"KY",
    "wof:name":"Comfort Inn Cave City",
    "wof:placetype":"venue"
},
  "geometry": {"coordinates":[-85.972646,37.138258],"type":"Point"}
}