{
  "type": "Feature",
  "properties": {
    "iso:country":"US",
    "sg:address":"3333 Irvin Cobb Dr",
    "sg:city":"Paducah",
    "sg:classifiers":[
        {
            "category":"Restaurant",
            "type":"Food & Drink"
        }
    ],
    "sg:phone":"+1 270 442 9784",
    "sg:postcode":"42003",
    "sg:province":"KY",
    "sg:tags":[
        "out"
    ],
    "wof:name":"Holman House Cafeteria",
    "wof:placetype":"venue"
},
  "geometry": {"coordinates":[-88.567724,37.051449],"type":"Point"}
}