{
  "type": "Feature",
  "properties": {
    "iso:country":"US",
    "sg:address":"236 2nd St",
    "sg:city":"Henderson",
    "sg:classifiers":[
        {
            "category":"Professional",
            "subcategory":"Lawyer & Legal Services",
            "type":"Services"
        }
    ],
    "sg:phone":"+1 270 830 7881",
    "sg:postcode":"42420",
    "sg:province":"KY",
    "sg:tags":[
        "attorney"
    ],
    "wof:name":"Kenneth S Kasacavage",
    "wof:placetype":"venue"
},
  "geometry": {"coordinates":[-87.591166,37.840459],"type":"Point"}
}