{
  "type": "Feature",
  "properties": {
    "iso:country":"US",
    "sg:address":"20 Russell Plaza Dr",
    "sg:city":"Ashland",
    "sg:classifiers":[
        {
            "category":"Restaurant",
            "type":"Food & Drink"
        }
    ],
    "sg:phone":"+1 606 324 5522",
    "sg:postcode":"41101",
    "sg:province":"KY",
    "wof:name":"Arby's",
    "wof:placetype":"venue"
},
  "geometry": {"coordinates":[-82.70433300000001,38.510541],"type":"Point"}
}