{
  "type": "Feature",
  "properties": {
    "addr:full":"232 S Chiles St Harrodsburg KY 40330",
    "addr:housenumber":"232",
    "addr:postcode":"40330",
    "addr:street":"S Chiles St",
    "iso:country":"US",
    "sg:address":"232 S Chiles St",
    "sg:city":"Harrodsburg",
    "sg:classifiers":[
        {
            "category":"Real Estate",
            "subcategory":"Real Estate Agent",
            "type":"Services"
        }
    ],
    "sg:phone":"+1 859 734 7766",
    "sg:postcode":"40330",
    "sg:province":"KY",
    "sg:website":"www.ronaldhurst.com",
    "wof:name":"Ronald Hurst & Co Real Estate",
    "wof:placetype":"venue"
},
  "geometry": {"coordinates":[-84.84470899999999,37.760724],"type":"Point"}
}