{
  "type": "Feature",
  "properties": {
    "iso:country":"US",
    "sg:address":"4006 Goldstein Ln",
    "sg:city":"Valley Station",
    "sg:classifiers":[
        {
            "category":"Government",
            "subcategory":"Office",
            "type":"Public Place"
        }
    ],
    "sg:phone":"+1 502 935 8368",
    "sg:postcode":"40272",
    "sg:province":"KY",
    "wof:name":"Jefferson County Justice-Peace",
    "wof:placetype":"venue"
},
  "geometry": {"coordinates":[-85.83936,38.103098],"type":"Point"}
}