{
  "type": "Feature",
  "properties": {
    "addr:full":"9721 Ormsby Station Rd Louisville KY 40223",
    "addr:housenumber":"9721",
    "addr:postcode":"40223",
    "addr:street":"Ormsby Station Rd",
    "iso:country":"US",
    "sg:address":"9721 Ormsby Station Rd",
    "sg:city":"Louisville",
    "sg:classifiers":[
        {
            "category":"Health Services",
            "subcategory":"Doctor",
            "type":"Services"
        }
    ],
    "sg:phone":"+1 502 429 7778",
    "sg:postcode":"40223",
    "sg:province":"KY",
    "sg:tags":[
        "physician",
        "surgeon"
    ],
    "wof:name":"Health Essentials Inc",
    "wof:placetype":"venue"
},
  "geometry": {"coordinates":[-85.57240299999999,38.267478],"type":"Point"}
}