{
  "type": "Feature",
  "properties": {
    "iso:country":"US",
    "sg:address":"207 W Main St",
    "sg:city":"Morganfield",
    "sg:classifiers":[
        {
            "category":"Health Services",
            "subcategory":"Optometrist",
            "type":"Services"
        }
    ],
    "sg:phone":"+1 270 389 1864",
    "sg:postcode":"42437",
    "sg:province":"KY",
    "wof:name":"M Troutman & L Wright",
    "wof:placetype":"venue"
},
  "geometry": {"coordinates":[-87.917784,37.684485],"type":"Point"}
}