{
  "type": "Feature",
  "properties": {
    "iso:country":"US",
    "sg:address":"601 Saint Bernard Ave",
    "sg:city":"Providence",
    "sg:classifiers":[
        {
            "category":"Building & Trades",
            "subcategory":"Landscaping Services",
            "type":"Services"
        }
    ],
    "sg:phone":"+1 270 667 7358",
    "sg:postcode":"42450",
    "sg:province":"KY",
    "sg:tags":[
        "tree"
    ],
    "wof:name":"Anthony's Tree Svc",
    "wof:placetype":"venue"
},
  "geometry": {"coordinates":[-87.75109399999999,37.396148],"type":"Point"}
}