{
  "type": "Feature",
  "properties": {
    "iso:country":"US",
    "sg:address":"223 E Main St",
    "sg:city":"Georgetown",
    "sg:classifiers":[
        {
            "category":"Real Estate",
            "subcategory":"Real Estate Agent",
            "type":"Services"
        }
    ],
    "sg:phone":"+1 502 863 6513",
    "sg:postcode":"40324",
    "sg:province":"KY",
    "wof:name":"Heritage Insurance",
    "wof:placetype":"venue"
},
  "geometry": {"coordinates":[-84.55779699999999,38.209845],"type":"Point"}
}