{
  "type": "Feature",
  "properties": {
    "iso:country":"US",
    "sg:address":"601 W Jefferson St",
    "sg:city":"Louisville",
    "sg:classifiers":[
        {
            "category":"Government",
            "subcategory":"Office",
            "type":"Public Place"
        }
    ],
    "sg:phone":"+1 502 574 3111",
    "sg:postcode":"40202",
    "sg:province":"KY",
    "sg:tags":[
        "business"
    ],
    "wof:name":"Public Works- Admin",
    "wof:placetype":"venue"
},
  "geometry": {"coordinates":[-85.76197500000001,38.254379],"type":"Point"}
}