{
  "type": "Feature",
  "properties": {
    "addr:full":"1170 Old Elizabethtown Rd Hodgenville KY 42748",
    "addr:housenumber":"1170",
    "addr:postcode":"42748",
    "addr:street":"Old Elizabethtown Rd",
    "iso:country":"US",
    "sg:address":"1170 Old Elizabethtown Rd",
    "sg:city":"Hodgenville",
    "sg:classifiers":[
        {
            "category":"Organizations",
            "subcategory":"Religious Organization",
            "type":"Services"
        }
    ],
    "sg:phone":"+1 270 358 4106",
    "sg:postcode":"42748",
    "sg:province":"KY",
    "sg:tags":[
        "church"
    ],
    "wof:name":"Freedom's Way",
    "wof:placetype":"venue"
},
  "geometry": {"coordinates":[-85.741839,37.586641],"type":"Point"}
}