{
  "type": "Feature",
  "properties": {
    "iso:country":"US",
    "sg:address":"249 N Main St",
    "sg:city":"Monticello",
    "sg:classifiers":[
        {
            "category":"Professional",
            "subcategory":"Lawyer & Legal Services",
            "type":"Services"
        }
    ],
    "sg:phone":"+1 606 340 8334",
    "sg:postcode":"42633",
    "sg:province":"KY",
    "sg:tags":[
        "attorney"
    ],
    "wof:name":"Larry E Rogers Law Offices",
    "wof:placetype":"venue"
},
  "geometry": {"coordinates":[-84.84806,36.831104],"type":"Point"}
}