{
  "type": "Feature",
  "properties": {
    "addr:full":"7180 Bloomfield Rd Bardstown KY 40004",
    "addr:housenumber":"7180",
    "addr:postcode":"40004",
    "addr:street":"Bloomfield Rd",
    "iso:country":"US",
    "sg:address":"7180 Bloomfield Rd",
    "sg:city":"Bardstown",
    "sg:classifiers":[
        {
            "category":"Farming",
            "subcategory":"Livestock Farm",
            "type":"Manufacturing & Wholesale Goods"
        }
    ],
    "sg:phone":"+1 502 252 5501",
    "sg:postcode":"40004",
    "sg:province":"KY",
    "sg:tags":[
        "beef",
        "feedlot",
        "cattle"
    ],
    "wof:name":"Drake Farms Limosuen",
    "wof:placetype":"venue"
},
  "geometry": {"coordinates":[-85.34439999999999,37.853681],"type":"Point"}
}