{
  "type": "Feature",
  "properties": {
    "addr:full":"700 N Green St Henderson KY 42420",
    "addr:housenumber":"700",
    "addr:postcode":"42420",
    "addr:street":"N Green St",
    "iso:country":"US",
    "sg:address":"700 N Green St",
    "sg:city":"Henderson",
    "sg:classifiers":[
        {
            "category":"Shopping",
            "subcategory":"Pharmacy",
            "type":"Retail Goods"
        }
    ],
    "sg:phone":"+1 270 826 3957",
    "sg:postcode":"42420",
    "sg:province":"KY",
    "wof:name":"BARRYS HALLMARK PHARMACY",
    "wof:placetype":"venue"
},
  "geometry": {"coordinates":[-87.58381799999999,37.84665],"type":"Point"}
}