{
  "type": "Feature",
  "properties": {
    "iso:country":"US",
    "sg:address":"4682 US Hwy 62",
    "sg:city":"Greenville",
    "sg:classifiers":[
        {
            "category":"Social Services",
            "subcategory":"Job Training",
            "type":"Services"
        }
    ],
    "sg:phone":"+1 270 338 3653",
    "sg:postcode":"42345",
    "sg:province":"KY",
    "sg:tags":[
        "rehabilitation"
    ],
    "wof:name":"Enduracare",
    "wof:placetype":"venue"
},
  "geometry": {"coordinates":[-87.242346,37.216671],"type":"Point"}
}