{
  "type": "Feature",
  "properties": {
    "iso:country":"US",
    "sg:address":"11800 Shelbyville Rd",
    "sg:city":"Louisville",
    "sg:classifiers":[
        {
            "category":"Shopping",
            "subcategory":"Bicycles & Sporting Goods",
            "type":"Retail Goods"
        },
        {
            "category":"Wholesale",
            "subcategory":"Chemicals & Plastics",
            "type":"Manufacturing & Wholesale Goods"
        },
        {
            "category":"Government",
            "subcategory":"Post Office",
            "type":"Public Place"
        },
        {
            "category":"Sports & Exercise",
            "subcategory":"Swimming Pool",
            "type":"Entertainment"
        }
    ],
    "sg:phone":"+1 502 245 9811",
    "sg:postcode":"40243",
    "sg:province":"KY",
    "sg:tags":[
        "supply",
        "swimwear",
        "accessory",
        "equipment",
        "distributor",
        "supplies-wholesale",
        "manufacturer"
    ],
    "sg:website":"http://www.pannellswimshop.com",
    "wof:name":"Pannell Swim Shop, Inc",
    "wof:placetype":"venue"
},
  "geometry": {"coordinates":[-85.538101,38.247421],"type":"Point"}
}