{
  "type": "Feature",
  "properties": {
    "addr:full":"204 Cross St Glasgow KY 42141",
    "addr:housenumber":"204",
    "addr:postcode":"42141",
    "addr:street":"Cross St",
    "iso:country":"US",
    "sg:address":"204 Cross St",
    "sg:city":"Glasgow",
    "sg:classifiers":[
        {
            "category":"Professional",
            "subcategory":"Business Services",
            "type":"Services"
        }
    ],
    "sg:phone":"+1 606 387 7531",
    "sg:postcode":"42141",
    "sg:province":"KY",
    "sg:tags":[
        "water",
        "treatment"
    ],
    "wof:name":"Albany Water Treatment Plant",
    "wof:placetype":"venue"
},
  "geometry": {"coordinates":[-85.926479,37.000096],"type":"Point"}
}