{
  "type": "Feature",
  "properties": {
    "addr:full":"3109 Roundway Down Ln Lexington KY 40509",
    "addr:housenumber":"3109",
    "addr:postcode":"40509",
    "addr:street":"Roundway Down Ln",
    "iso:country":"US",
    "sg:address":"3109 Roundway Down Ln",
    "sg:city":"Lexington",
    "sg:classifiers":[
        {
            "category":"Sports & Exercise",
            "subcategory":"Bowling",
            "type":"Entertainment"
        }
    ],
    "sg:phone":"+1 859 294 7454",
    "sg:postcode":"40509",
    "sg:province":"KY",
    "wof:name":"Karla Bowling",
    "wof:placetype":"venue"
},
  "geometry": {"coordinates":[-84.405269,38.021104],"type":"Point"}
}