{
  "type": "Feature",
  "properties": {
    "iso:country":"US",
    "sg:address":"799 Graham Rd",
    "sg:city":"Campbellsville",
    "sg:classifiers":[
        {
            "category":"Building & Trades",
            "subcategory":"Construction",
            "type":"Services"
        }
    ],
    "sg:phone":"+1 270 465 7930",
    "sg:postcode":"42718",
    "sg:province":"KY",
    "sg:tags":[
        "wallcoverings-installation",
        "wallpaper",
        "painting",
        "contractor"
    ],
    "wof:name":"A&B Painting",
    "wof:placetype":"venue"
},
  "geometry": {"coordinates":[-85.400434,37.44537],"type":"Point"}
}