{
  "type": "Feature",
  "properties": {
    "iso:country":"US",
    "sg:address":"9802 Longwood Cir",
    "sg:city":"Louisville",
    "sg:classifiers":[
        {
            "category":"Science Facility",
            "type":"Public Place"
        }
    ],
    "sg:phone":"+1 502 423 1671",
    "sg:postcode":"40223",
    "sg:province":"KY",
    "sg:tags":[
        "development",
        "energy",
        "solar",
        "research"
    ],
    "wof:name":"Jd Pickard Inc",
    "wof:placetype":"venue"
},
  "geometry": {"coordinates":[-85.57443499999999,38.249199],"type":"Point"}
}