{
  "type": "Feature",
  "properties": {
    "addr:full":"2105 Appleton Ln Louisville KY 40216",
    "addr:housenumber":"2105",
    "addr:postcode":"40216",
    "addr:street":"Appleton Ln",
    "iso:country":"US",
    "sg:address":"2105 Appleton Ln",
    "sg:city":"Louisville",
    "sg:phone":"+1 502 447 6795",
    "sg:postcode":"40216",
    "sg:province":"KY",
    "wof:name":"Dr Electric",
    "wof:placetype":"venue"
},
  "geometry": {"coordinates":[-85.80954699999999,38.203841],"type":"Point"}
}