{
  "type": "Feature",
  "properties": {
    "iso:country":"US",
    "sg:address":"1633 Rangeland Rd",
    "sg:city":"Louisville",
    "sg:classifiers":[
        {
            "category":"Retail",
            "subcategory":"Laundry & Dry Cleaning",
            "type":"Services"
        }
    ],
    "sg:phone":"+1 502 968 3529",
    "sg:postcode":"40219",
    "sg:province":"KY",
    "wof:name":"D A Merriweather",
    "wof:placetype":"venue"
},
  "geometry": {"coordinates":[-85.67488899999999,38.166934],"type":"Point"}
}