{
  "type": "Feature",
  "properties": {
    "iso:country":"US",
    "sg:address":"1152 Lexington Rd",
    "sg:city":"Georgetown",
    "sg:classifiers":[
        {
            "category":"Health Services",
            "subcategory":"Doctor",
            "type":"Services"
        }
    ],
    "sg:phone":"+1 502 570 4003",
    "sg:postcode":"40324",
    "sg:province":"KY",
    "sg:tags":[
        "physician",
        "surgeon"
    ],
    "wof:name":"Uk Kentucky Clinic Georgetown",
    "wof:placetype":"venue"
},
  "geometry": {"coordinates":[-84.562585,38.187735],"type":"Point"}
}