{
  "type": "Feature",
  "properties": {
    "iso:country":"US",
    "sg:address":"15 Old Shelbiana Rd",
    "sg:city":"Pikeville",
    "sg:classifiers":[
        {
            "category":"Building & Trades",
            "subcategory":"Cleaning & Sanitation",
            "type":"Services"
        }
    ],
    "sg:phone":"+1 606 433 9060",
    "sg:postcode":"41501",
    "sg:province":"KY",
    "sg:tags":[
        "janitor"
    ],
    "wof:name":"Justice Cleaning Svc",
    "wof:placetype":"venue"
},
  "geometry": {"coordinates":[-82.511145,37.432344],"type":"Point"}
}