{
  "type": "Feature",
  "properties": {
    "iso:country":"US",
    "sg:address":"4801 Outer Loop",
    "sg:city":"Louisville",
    "sg:classifiers":[
        {
            "category":"Restaurant",
            "type":"Food & Drink"
        }
    ],
    "sg:menulink":"http://www.allmenus.com/ky/jefferson-central/180024-chick-fil-a/menu/",
    "sg:phone":"+1 502 968 7904",
    "sg:postcode":"40219",
    "sg:province":"KY",
    "sg:tags":[
        "wrap",
        "soup",
        "american",
        "sandwich",
        "salad"
    ],
    "wof:name":"Chick-fil-A",
    "wof:placetype":"venue"
},
  "geometry": {"coordinates":[-85.673377,38.13812],"type":"Point"}
}