{
  "type": "Feature",
  "properties": {
    "addr:full":"12521 Chamberlain Ln Louisville KY 40245",
    "addr:housenumber":"12521",
    "addr:postcode":"40245",
    "addr:street":"Chamberlain Ln",
    "iso:country":"US",
    "sg:address":"12521 Chamberlain Ln",
    "sg:city":"Louisville",
    "sg:classifiers":[
        {
            "category":"Insurance",
            "subcategory":"Insurance Agent",
            "type":"Services"
        }
    ],
    "sg:phone":"+1 502 421 7072",
    "sg:postcode":"40245",
    "sg:province":"KY",
    "wof:name":"David Walker",
    "wof:placetype":"venue"
},
  "geometry": {"coordinates":[-85.519757,38.287949],"type":"Point"}
}