{
  "type": "Feature",
  "properties": {
    "iso:country":"US",
    "sg:address":"443 S Main St",
    "sg:city":"Brownsville",
    "sg:classifiers":[
        {
            "category":"Restaurant",
            "type":"Food & Drink"
        }
    ],
    "sg:menulink":"http://www.allmenus.com/ky/brownsville/120460-subway/menu/",
    "sg:phone":"+1 270 597 3269",
    "sg:postcode":"42210",
    "sg:province":"KY",
    "sg:tags":[
        "american",
        "sandwich"
    ],
    "wof:name":"Subway",
    "wof:placetype":"venue"
},
  "geometry": {"coordinates":[-86.263924,37.190137],"type":"Point"}
}