{
  "type": "Feature",
  "properties": {
    "iso:country":"US",
    "sg:address":"1854 Hinkston Pike",
    "sg:city":"Mount Sterling",
    "sg:classifiers":[
        {
            "category":"Farming",
            "subcategory":"Farm",
            "type":"Manufacturing & Wholesale Goods"
        }
    ],
    "sg:phone":"+1 859 498 5420",
    "sg:postcode":"40353",
    "sg:province":"KY",
    "sg:tags":[
        "crop",
        "general"
    ],
    "wof:name":"Ison Brother",
    "wof:placetype":"venue"
},
  "geometry": {"coordinates":[-83.92502500000001,38.093138],"type":"Point"}
}