{
  "type": "Feature",
  "properties": {
    "addr:full":"320 Ridgeway Ave Falmouth KY 41040",
    "addr:housenumber":"320",
    "addr:postcode":"41040",
    "addr:street":"Ridgeway Ave",
    "iso:country":"US",
    "sg:address":"320 Ridgeway Ave",
    "sg:city":"Falmouth",
    "sg:classifiers":[
        {
            "category":"Shopping",
            "subcategory":"Department Store",
            "type":"Retail Goods"
        }
    ],
    "sg:phone":"+1 859 654 2907",
    "sg:postcode":"41040",
    "sg:province":"KY",
    "wof:name":"Dollar General",
    "wof:placetype":"venue"
},
  "geometry": {"coordinates":[-84.333811,38.667624],"type":"Point"}
}