{
  "type": "Feature",
  "properties": {
    "addr:full":"1720 Wildcat Blvd S Burlington KY 41005",
    "addr:housenumber":"1720",
    "addr:postcode":"41005",
    "addr:street":"Wildcat Blvd S",
    "iso:country":"US",
    "sg:address":"1720 Wildcat Blvd S",
    "sg:city":"Burlington",
    "sg:classifiers":[
        {
            "category":"Food & Beverages",
            "subcategory":"Liquor & Beverages",
            "type":"Retail Goods"
        }
    ],
    "sg:phone":"+1 859 525 8180",
    "sg:postcode":"41005",
    "sg:province":"KY",
    "sg:tags":[
        "beer",
        "spirit",
        "wine"
    ],
    "wof:name":"Oak Brook Liquor & Tobacco",
    "wof:placetype":"venue"
},
  "geometry": {"coordinates":[-84.689808,39.019721],"type":"Point"}
}