{
  "type": "Feature",
  "properties": {
    "iso:country":"US",
    "sg:address":"190 N Main St",
    "sg:city":"Versailles",
    "sg:classifiers":[
        {
            "category":"Personal",
            "type":"Services"
        }
    ],
    "sg:phone":"+1 859 879 2008",
    "sg:postcode":"40383",
    "sg:province":"KY",
    "sg:tags":[
        "therapist",
        "massage"
    ],
    "wof:name":"Shiatzu Massage Ctr",
    "wof:placetype":"venue"
},
  "geometry": {"coordinates":[-84.73022400000001,38.053013],"type":"Point"}
}