{
  "type": "Feature",
  "properties": {
    "iso:country":"US",
    "sg:address":"624 Emory Dr",
    "sg:city":"Owensboro",
    "sg:classifiers":[
        {
            "category":"Wholesale",
            "subcategory":"Painting Supplies",
            "type":"Manufacturing & Wholesale Goods"
        }
    ],
    "sg:phone":"+1 270 926 1262",
    "sg:postcode":"42301",
    "sg:province":"KY",
    "sg:tags":[
        "paint"
    ],
    "wof:name":"PPG Porter Paints",
    "wof:placetype":"venue"
},
  "geometry": {"coordinates":[-87.116035,37.748336],"type":"Point"}
}