{
  "type": "Feature",
  "properties": {
    "addr:full":"911 Palatka Rd Louisville KY 40214",
    "addr:housenumber":"911",
    "addr:postcode":"40214",
    "addr:street":"Palatka Rd",
    "iso:country":"US",
    "sg:address":"911 Palatka Rd",
    "sg:city":"Louisville",
    "sg:classifiers":[
        {
            "category":"Health Services",
            "subcategory":"Doctor",
            "type":"Services"
        }
    ],
    "sg:phone":"+1 502 366 2448",
    "sg:postcode":"40214",
    "sg:province":"KY",
    "sg:tags":[
        "dentist"
    ],
    "wof:name":"Mortenson Family Dental",
    "wof:placetype":"venue"
},
  "geometry": {"coordinates":[-85.778265,38.151003],"type":"Point"}
}