{
  "type": "Feature",
  "properties": {
    "iso:country":"US",
    "sg:address":"2620 Frankfort Ave",
    "sg:city":"Louisville",
    "sg:classifiers":[
        {
            "category":"Government",
            "subcategory":"Fire Station",
            "type":"Public Place"
        }
    ],
    "sg:phone":"+1 502 896 9291",
    "sg:postcode":"40206",
    "sg:province":"KY",
    "sg:tags":[
        "department"
    ],
    "wof:name":"Louisville Fire Quad Co 6",
    "wof:placetype":"venue"
},
  "geometry": {"coordinates":[-85.696461,38.254194],"type":"Point"}
}