{
  "type": "Feature",
  "properties": {
    "addr:full":"570 Highpoint Dr Hopkinsville KY 42240",
    "addr:housenumber":"570",
    "addr:postcode":"42240",
    "addr:street":"Highpoint Dr",
    "iso:country":"US",
    "sg:address":"570 Highpoint Dr",
    "sg:city":"Hopkinsville",
    "sg:classifiers":[
        {
            "category":"Building & Trades",
            "subcategory":"Construction",
            "type":"Services"
        }
    ],
    "sg:phone":"+1 270 887 8447",
    "sg:postcode":"42240",
    "sg:province":"KY",
    "sg:tags":[
        "general",
        "contractor"
    ],
    "wof:name":"Lachance Construction",
    "wof:placetype":"venue"
},
  "geometry": {"coordinates":[-87.507718,36.889669],"type":"Point"}
}