{
  "type": "Feature",
  "properties": {
    "addr:full":"2223 Scottsville Rd Glasgow KY 42141",
    "addr:housenumber":"2223",
    "addr:postcode":"42141",
    "addr:street":"Scottsville Rd",
    "iso:country":"US",
    "sg:address":"2223 Scottsville Rd",
    "sg:city":"Glasgow",
    "sg:classifiers":[
        {
            "category":"Retail",
            "subcategory":"Auto Repair",
            "type":"Services"
        }
    ],
    "sg:phone":"+1 270 629 2886",
    "sg:postcode":"42141",
    "sg:province":"KY",
    "sg:tags":[
        "van",
        "conversion",
        "truck",
        "accessory"
    ],
    "wof:name":"K C Trucks",
    "wof:placetype":"venue"
},
  "geometry": {"coordinates":[-85.93773,36.974832],"type":"Point"}
}