{
  "type": "Feature",
  "properties": {
    "iso:country":"US",
    "sg:address":"840 W Main St",
    "sg:city":"Morehead",
    "sg:classifiers":[
        {
            "category":"Building & Trades",
            "subcategory":"Construction",
            "type":"Services"
        }
    ],
    "sg:phone":"+1 606 784 4520",
    "sg:postcode":"40351",
    "sg:province":"KY",
    "sg:tags":[
        "paving",
        "contractor"
    ],
    "wof:name":"R & R Paving Corp",
    "wof:placetype":"venue"
},
  "geometry": {"coordinates":[-83.44031200000001,38.172328],"type":"Point"}
}