{
  "type": "Feature",
  "properties": {
    "addr:full":"1713 Crimson Dr Worthington KY 41183",
    "addr:housenumber":"1713",
    "addr:postcode":"41183",
    "addr:street":"Crimson Dr",
    "iso:country":"US",
    "sg:address":"1713 Crimson Dr",
    "sg:city":"Worthington",
    "sg:classifiers":[
        {
            "category":"Organizations",
            "subcategory":"Professional Association",
            "type":"Services"
        }
    ],
    "sg:phone":"+1 606 836 6731",
    "sg:postcode":"41183",
    "sg:province":"KY",
    "wof:name":"Waring Family Cemetery Assn",
    "wof:placetype":"venue"
},
  "geometry": {"coordinates":[-82.75616599999999,38.553752],"type":"Point"}
}