{
  "type": "Feature",
  "properties": {
    "iso:country":"US",
    "sg:address":"544 Beecher St",
    "sg:city":"Louisville",
    "sg:classifiers":[
        {
            "category":"Structure",
            "subcategory":"Office Building",
            "type":"Public Place"
        }
    ],
    "sg:phone":"+1 502 366 0739",
    "sg:postcode":"40215",
    "sg:province":"KY",
    "sg:tags":[
        "park"
    ],
    "wof:name":"Peterson Popham Properties",
    "wof:placetype":"venue"
},
  "geometry": {"coordinates":[-85.76894799999999,38.19205],"type":"Point"}
}