{
  "type": "Feature",
  "properties": {
    "iso:country":"US",
    "sg:address":"120 S Main St",
    "sg:city":"Lawrenceburg",
    "sg:classifiers":[
        {
            "category":"Home & Garden",
            "subcategory":"Furniture",
            "type":"Retail Goods"
        }
    ],
    "sg:phone":"+1 502 839 6700",
    "sg:postcode":"40342",
    "sg:province":"KY",
    "wof:name":"Newbys Furniture",
    "wof:placetype":"venue"
},
  "geometry": {"coordinates":[-84.896006,38.035898],"type":"Point"}
}