{
  "type": "Feature",
  "properties": {
    "addr:full":"1005 Walnut St Greenup KY 41144",
    "addr:housenumber":"1005",
    "addr:postcode":"41144",
    "addr:street":"Walnut St",
    "iso:country":"US",
    "sg:address":"1005 Walnut St",
    "sg:city":"Greenup",
    "sg:classifiers":[
        {
            "category":"Utilities",
            "subcategory":"Water",
            "type":"Services"
        }
    ],
    "sg:phone":"+1 606 473 7331",
    "sg:postcode":"41144",
    "sg:province":"KY",
    "sg:tags":[
        "company",
        "sewage"
    ],
    "wof:name":"Greenup Water Dept Office",
    "wof:placetype":"venue"
},
  "geometry": {"coordinates":[-82.83075700000001,38.573319],"type":"Point"}
}