{
  "type": "Feature",
  "properties": {
    "iso:country":"US",
    "sg:address":"2270 Garrett Rd",
    "sg:city":"Brandenburg",
    "sg:classifiers":[
        {
            "category":"Freight",
            "type":"Transportation"
        }
    ],
    "sg:phone":"+1 270 828 3416",
    "sg:postcode":"40108",
    "sg:province":"KY",
    "sg:tags":[
        "trucking"
    ],
    "wof:name":"Jim Stephens Trucking",
    "wof:placetype":"venue"
},
  "geometry": {"coordinates":[-86.08298499999999,37.911487],"type":"Point"}
}