{
  "type": "Feature",
  "properties": {
    "iso:country":"US",
    "sg:address":"274 Cassidy Blvd",
    "sg:city":"Pikeville",
    "sg:classifiers":[
        {
            "category":"Fast Food",
            "type":"Food & Drink"
        },
        {
            "category":"Restaurant",
            "type":"Food & Drink"
        }
    ],
    "sg:phone":"+1 606 437 6211",
    "sg:postcode":"41501",
    "sg:province":"KY",
    "sg:tags":[
        "take",
        "pizza"
    ],
    "sg:website":"http://www.mrgattis.com",
    "wof:name":"Gatti's Pizza",
    "wof:placetype":"venue"
},
  "geometry": {"coordinates":[-82.536873,37.505139],"type":"Point"}
}