{
  "type": "Feature",
  "properties": {
    "addr:full":"1006 Ulrich Ave Louisville KY 40219",
    "addr:housenumber":"1006",
    "addr:postcode":"40219",
    "addr:street":"Ulrich Ave",
    "iso:country":"US",
    "sg:address":"1006 Ulrich Ave",
    "sg:city":"Louisville",
    "sg:classifiers":[
        {
            "category":"Retail",
            "subcategory":"Auto Repair",
            "type":"Services"
        }
    ],
    "sg:phone":"+1 502 968 7500",
    "sg:postcode":"40219",
    "sg:province":"KY",
    "sg:tags":[
        "engine",
        "engines-rebuild",
        "rebuilding",
        "truck",
        "exchange"
    ],
    "sg:website":"http://www.advancedengineX.com",
    "wof:name":"Advanced Engine Exchange",
    "wof:placetype":"venue"
},
  "geometry": {"coordinates":[-85.702241,38.158227],"type":"Point"}
}