{
  "type": "Feature",
  "properties": {
    "iso:country":"US",
    "sg:address":"943 S 1st St",
    "sg:city":"Louisville",
    "sg:classifiers":[
        {
            "category":"Professional",
            "subcategory":"Accounting & Tax Preparation",
            "type":"Services"
        }
    ],
    "sg:phone":"+1 502 584 9793",
    "sg:postcode":"40203",
    "sg:province":"KY",
    "sg:tags":[
        "accountant"
    ],
    "sg:website":"www.ablw-cpas.net",
    "wof:name":"Anderson Bryant Lasky Winslow",
    "wof:placetype":"venue"
},
  "geometry": {"coordinates":[-85.75458,38.238433],"type":"Point"}
}