{
  "type": "Feature",
  "properties": {
    "iso:country":"US",
    "sg:address":"1439 Magnolia St",
    "sg:city":"Bowling Green",
    "sg:classifiers":[
        {
            "category":"Social Services",
            "type":"Services"
        }
    ],
    "sg:phone":"+1 270 781 5050",
    "sg:postcode":"42104",
    "sg:province":"KY",
    "sg:tags":[
        "organization",
        "welfare"
    ],
    "wof:name":"Pregnancy Support Ctr",
    "wof:placetype":"venue"
},
  "geometry": {"coordinates":[-86.443445,36.980181],"type":"Point"}
}