{
  "type": "Feature",
  "properties": {
    "iso:country":"US",
    "sg:address":"227 W Broadway St",
    "sg:city":"Frankfort",
    "sg:classifiers":[
        {
            "category":"Shopping",
            "subcategory":"Used Merchandise",
            "type":"Retail Goods"
        }
    ],
    "sg:phone":"+1 502 223 5466",
    "sg:postcode":"40601",
    "sg:province":"KY",
    "sg:tags":[
        "antique"
    ],
    "wof:name":"Ron-Jo's Antiques & Clctbls",
    "wof:placetype":"venue"
},
  "geometry": {"coordinates":[-84.876459,38.199277],"type":"Point"}
}