{
  "type": "Feature",
  "properties": {
    "iso:country":"US",
    "sg:address":"1557 Flora Glen Way",
    "sg:city":"Lexington",
    "sg:classifiers":[
        {
            "category":"Shopping",
            "subcategory":"Clothing, Apparel, & Fashions",
            "type":"Retail Goods"
        }
    ],
    "sg:phone":"+1 859 273 0255",
    "sg:postcode":"40515",
    "sg:province":"KY",
    "sg:tags":[
        "alteration"
    ],
    "wof:name":"Marcy Mitchell",
    "wof:placetype":"venue"
},
  "geometry": {"coordinates":[-84.464871,37.974405],"type":"Point"}
}