{
  "type": "Feature",
  "properties": {
    "addr:full":"4657 Outer Loop Louisville KY 40219",
    "addr:housenumber":"4657",
    "addr:postcode":"40219",
    "addr:street":"Outer Loop",
    "iso:country":"US",
    "sg:address":"4657 Outer Loop",
    "sg:city":"Louisville",
    "sg:classifiers":[
        {
            "category":"Restaurant",
            "type":"Food & Drink"
        }
    ],
    "sg:phone":"+1 502 969 5545",
    "sg:postcode":"40219",
    "sg:province":"KY",
    "wof:name":"Spaghetti Shop",
    "wof:placetype":"venue"
},
  "geometry": {"coordinates":[-85.67444,38.138062],"type":"Point"}
}