{
  "type": "Feature",
  "properties": {
    "iso:country":"US",
    "sg:address":"34 E 3rd St",
    "sg:city":"Maysville",
    "sg:classifiers":[
        {
            "category":"Personal",
            "subcategory":"Beauty Salon",
            "type":"Services"
        }
    ],
    "sg:phone":"+1 606 564 4297",
    "sg:postcode":"41056",
    "sg:province":"KY",
    "sg:tags":[
        "shop"
    ],
    "wof:name":"Gantley",
    "wof:placetype":"venue"
},
  "geometry": {"coordinates":[-83.763846,38.646167],"type":"Point"}
}