{
  "type": "Feature",
  "properties": {
    "addr:full":"38 Ivy Creek Ivel KY 41642",
    "addr:housenumber":"38",
    "addr:postcode":"41642",
    "addr:street":"Ivy Creek",
    "iso:country":"US",
    "sg:address":"38 Ivy Creek",
    "sg:city":"Ivel",
    "sg:classifiers":[
        {
            "category":"Building & Trades",
            "subcategory":"Equipment Rental",
            "type":"Services"
        }
    ],
    "sg:phone":"+1 606 478 1391",
    "sg:postcode":"41642",
    "sg:province":"KY",
    "sg:tags":[
        "yard"
    ],
    "wof:name":"TEM Equipment Co",
    "wof:placetype":"venue"
},
  "geometry": {"coordinates":[-82.645775,37.600072],"type":"Point"}
}