{
  "type": "Feature",
  "properties": {
    "iso:country":"US",
    "sg:address":"11 Forest Ave",
    "sg:city":"Fort Thomas",
    "sg:classifiers":[
        {
            "category":"Travel",
            "subcategory":"Travel Agent",
            "type":"Entertainment"
        }
    ],
    "sg:phone":"+1 859 441 7992",
    "sg:postcode":"41075",
    "sg:province":"KY",
    "sg:tags":[
        "agency",
        "bureau"
    ],
    "wof:name":"Community Travel",
    "wof:placetype":"venue"
},
  "geometry": {"coordinates":[-84.45332999999999,39.081253],"type":"Point"}
}