{
  "type": "Feature",
  "properties": {
    "iso:country":"US",
    "sg:address":"2215 Hamburg Rd",
    "sg:city":"Kevil",
    "sg:classifiers":[
        {
            "category":"Farming",
            "subcategory":"Farm",
            "type":"Manufacturing & Wholesale Goods"
        }
    ],
    "sg:phone":"+1 270 876 7550",
    "sg:postcode":"42053",
    "sg:province":"KY",
    "wof:name":"Coyote Valley Farm",
    "wof:placetype":"venue"
},
  "geometry": {"coordinates":[-88.852341,37.00241],"type":"Point"}
}