{
  "type": "Feature",
  "properties": {
    "addr:full":"1038 Florence Mall Florence KY 41042",
    "addr:housenumber":"1038",
    "addr:postcode":"41042",
    "addr:street":"Florence Mall",
    "iso:country":"US",
    "sg:address":"1038 Florence Mall",
    "sg:city":"Florence",
    "sg:classifiers":[
        {
            "category":"Shopping",
            "subcategory":"Clothing, Apparel, & Fashions",
            "type":"Retail Goods"
        }
    ],
    "sg:phone":"+1 859 371 3745",
    "sg:postcode":"41042",
    "sg:province":"KY",
    "sg:tags":[
        "children's",
        "clothing"
    ],
    "sg:website":"www.gymboree.com",
    "wof:name":"Gymboree",
    "wof:placetype":"venue"
},
  "geometry": {"coordinates":[-84.654099,38.9986],"type":"Point"}
}