{
  "type": "Feature",
  "properties": {
    "iso:country":"US",
    "sg:address":"1108 Cuba Rd",
    "sg:city":"Mayfield",
    "sg:classifiers":[
        {
            "category":"Shopping",
            "subcategory":"Tobacco",
            "type":"Retail Goods"
        }
    ],
    "sg:phone":"+1 270 247 2447",
    "sg:postcode":"42066",
    "sg:province":"KY",
    "sg:tags":[
        "cigarette",
        "cigar",
        "dealer"
    ],
    "wof:name":"Cigarettes For Less",
    "wof:placetype":"venue"
},
  "geometry": {"coordinates":[-88.631865,36.72784],"type":"Point"}
}