{
  "type": "Feature",
  "properties": {
    "iso:country":"US",
    "sg:address":"3109 Thomas Ln",
    "sg:city":"Louisville",
    "sg:classifiers":[
        {
            "category":"Organizations",
            "subcategory":"Religious Organization",
            "type":"Services"
        }
    ],
    "sg:phone":"+1 502 495 0035",
    "sg:postcode":"40299",
    "sg:province":"KY",
    "sg:tags":[
        "church"
    ],
    "wof:name":"Louisville Sda Hispanic Church",
    "wof:placetype":"venue"
},
  "geometry": {"coordinates":[-85.585374,38.201239],"type":"Point"}
}