{
  "type": "Feature",
  "properties": {
    "iso:country":"US",
    "sg:address":"1030 Winchester Rd",
    "sg:city":"Irvine",
    "sg:classifiers":[
        {
            "category":"Communications",
            "subcategory":"Radio Station",
            "type":"Services"
        }
    ],
    "sg:phone":"+1 606 723 5138",
    "sg:postcode":"40336",
    "sg:province":"KY",
    "sg:tags":[
        "company",
        "broadcasting"
    ],
    "sg:website":"www.wcyo.com",
    "wof:name":"WYCO Richmond Studio",
    "wof:placetype":"venue"
},
  "geometry": {"coordinates":[-83.976133,37.711928],"type":"Point"}
}