{
  "type": "Feature",
  "properties": {
    "iso:country":"US",
    "sg:address":"3751 Pamela Rae Dr",
    "sg:city":"Louisville",
    "sg:classifiers":[
        {
            "category":"Autos & Motor Vehicles",
            "subcategory":"Auto Supplies",
            "type":"Retail Goods"
        },
        {
            "category":"Retail",
            "subcategory":"Auto Repair",
            "type":"Services"
        }
    ],
    "sg:phone":"+1 502 412 1119",
    "sg:postcode":"40241",
    "sg:province":"KY",
    "sg:tags":[
        "wheel",
        "oil",
        "tire",
        "retread",
        "lube",
        "balancing",
        "wheels-aligning",
        "recap",
        "brake"
    ],
    "sg:website":"http://www.bigotires.com",
    "wof:name":"Big O Tires",
    "wof:placetype":"venue"
},
  "geometry": {"coordinates":[-85.54269499999999,38.300983],"type":"Point"}
}