{
  "type": "Feature",
  "properties": {
    "addr:full":"506 Fairgrounds St Columbia KY 42728",
    "addr:housenumber":"506",
    "addr:postcode":"42728",
    "addr:street":"Fairgrounds St",
    "iso:country":"US",
    "sg:address":"506 Fairgrounds St",
    "sg:city":"Columbia",
    "sg:classifiers":[
        {
            "category":"Building & Trades",
            "subcategory":"Construction",
            "type":"Services"
        }
    ],
    "sg:phone":"+1 270 384 8992",
    "sg:postcode":"42728",
    "sg:province":"KY",
    "sg:tags":[
        "planning",
        "remodeling",
        "kitchen"
    ],
    "wof:name":"Kitchen Customs",
    "wof:placetype":"venue"
},
  "geometry": {"coordinates":[-85.29531900000001,37.103849],"type":"Point"}
}