{
  "type": "Feature",
  "properties": {
    "iso:country":"US",
    "sg:address":"7020 Flaherty Rd",
    "sg:city":"Vine Grove",
    "sg:classifiers":[
        {
            "category":"Food & Beverages",
            "subcategory":"Liquor & Beverages",
            "type":"Retail Goods"
        }
    ],
    "sg:phone":"+1 270 828 2669",
    "sg:postcode":"40175",
    "sg:province":"KY",
    "wof:name":"Berry's Package Liquor Store",
    "wof:placetype":"venue"
},
  "geometry": {"coordinates":[-86.007333,37.818573],"type":"Point"}
}