{
  "type": "Feature",
  "properties": {
    "iso:country":"US",
    "sg:address":"200 Cornelius Ave",
    "sg:city":"Russellville",
    "sg:classifiers":[
        {
            "category":"Government",
            "subcategory":"Office",
            "type":"Public Place"
        }
    ],
    "sg:phone":"+1 270 726 6541",
    "sg:postcode":"42276",
    "sg:province":"KY",
    "sg:tags":[
        "housing",
        "program"
    ],
    "wof:name":"Russellville Sub Station",
    "wof:placetype":"venue"
},
  "geometry": {"coordinates":[-86.894356,36.846134],"type":"Point"}
}