{
  "type": "Feature",
  "properties": {
    "iso:country":"US",
    "sg:address":"2339 Wonderland Rd",
    "sg:city":"Upton",
    "sg:classifiers":[
        {
            "category":"Building & Trades",
            "subcategory":"Construction",
            "type":"Services"
        }
    ],
    "sg:phone":"+1 270 737 9982",
    "sg:postcode":"42784",
    "sg:province":"KY",
    "sg:tags":[
        "designer",
        "dealer",
        "pool",
        "swimming"
    ],
    "wof:name":"Back Yard Fun",
    "wof:placetype":"venue"
},
  "geometry": {"coordinates":[-85.863607,37.478155],"type":"Point"}
}