{
  "type": "Feature",
  "properties": {
    "addr:full":"20 E 5th St Paris KY 40361",
    "addr:housenumber":"20",
    "addr:postcode":"40361",
    "addr:street":"E 5Th St",
    "iso:country":"US",
    "sg:address":"20 E 5th St",
    "sg:city":"Paris",
    "sg:classifiers":[
        {
            "category":"Insurance",
            "subcategory":"Insurance Agent",
            "type":"Services"
        }
    ],
    "sg:phone":"+1 859 987 1667",
    "sg:postcode":"40361",
    "sg:province":"KY",
    "wof:name":"Mc Clure-Hill-Case Insurance",
    "wof:placetype":"venue"
},
  "geometry": {"coordinates":[-84.250377,38.211551],"type":"Point"}
}