{
  "type": "Feature",
  "properties": {
    "iso:country":"US",
    "sg:address":"222 E Main St",
    "sg:city":"Morehead",
    "sg:classifiers":[
        {
            "category":"Personal",
            "subcategory":"Barber",
            "type":"Services"
        }
    ],
    "sg:phone":"+1 606 784 7435",
    "sg:postcode":"40351",
    "sg:province":"KY",
    "wof:name":"New Image Hair Styling & Spa",
    "wof:placetype":"venue"
},
  "geometry": {"coordinates":[-83.43264499999999,38.184819],"type":"Point"}
}