{
  "type": "Feature",
  "properties": {
    "addr:full":"5262 Madison Pike Independence KY 41051",
    "addr:housenumber":"5262",
    "addr:postcode":"41051",
    "addr:street":"Madison Pike",
    "iso:country":"US",
    "sg:address":"5262 Madison Pike",
    "sg:city":"Independence",
    "sg:classifiers":[
        {
            "category":"Banks & Credit Unions",
            "subcategory":"Bank",
            "type":"Services"
        }
    ],
    "sg:phone":"+1 859 363 4300",
    "sg:postcode":"41051",
    "sg:province":"KY",
    "wof:name":"US Bank",
    "wof:placetype":"venue"
},
  "geometry": {"coordinates":[-84.544394,38.943428],"type":"Point"}
}