{
  "type": "Feature",
  "properties": {
    "addr:full":"200 5th St Henderson KY 42420",
    "addr:housenumber":"200",
    "addr:postcode":"42420",
    "addr:street":"5Th St",
    "iso:country":"US",
    "sg:address":"200 5th St",
    "sg:city":"Henderson",
    "sg:classifiers":[
        {
            "category":"Insurance",
            "subcategory":"Insurance Agent",
            "type":"Services"
        }
    ],
    "sg:phone":"+1 270 826 7265",
    "sg:postcode":"42420",
    "sg:province":"KY",
    "wof:name":"Nelson Insurance",
    "wof:placetype":"venue"
},
  "geometry": {"coordinates":[-87.589186,37.844559],"type":"Point"}
}