{
  "type": "Feature",
  "properties": {
    "iso:country":"US",
    "sg:address":"274 Southland Dr",
    "sg:city":"Lexington",
    "sg:classifiers":[
        {
            "category":"Personal",
            "type":"Services"
        }
    ],
    "sg:phone":"+1 859 277 2985",
    "sg:postcode":"40503",
    "sg:province":"KY",
    "wof:name":"United Advg Publications Inc",
    "wof:placetype":"venue"
},
  "geometry": {"coordinates":[-84.52256800000001,38.014588],"type":"Point"}
}