{
  "type": "Feature",
  "properties": {
    "addr:full":"321 S Main St Williamstown KY 41097",
    "addr:housenumber":"321",
    "addr:postcode":"41097",
    "addr:street":"S Main St",
    "iso:country":"US",
    "sg:address":"321 S Main St",
    "sg:city":"Williamstown",
    "sg:classifiers":[
        {
            "category":"Railroad",
            "type":"Transportation"
        }
    ],
    "sg:phone":"+1 859 823 5484",
    "sg:postcode":"41097",
    "sg:province":"KY",
    "wof:name":"Norfolk Southern Railway Co",
    "wof:placetype":"venue"
},
  "geometry": {"coordinates":[-84.562853,38.635435],"type":"Point"}
}