{
  "type": "Feature",
  "properties": {
    "iso:country":"US",
    "sg:address":"540 Main St",
    "sg:city":"Shelbyville",
    "sg:classifiers":[
        {
            "category":"Health Services",
            "subcategory":"Nursing And Care Facility",
            "type":"Services"
        }
    ],
    "sg:phone":"+1 502 647 2400",
    "sg:postcode":"40065",
    "sg:province":"KY",
    "sg:tags":[
        "hospice"
    ],
    "wof:name":"Hospice Of Shelbyville",
    "wof:placetype":"venue"
},
  "geometry": {"coordinates":[-85.216765,38.210946],"type":"Point"}
}