{
  "type": "Feature",
  "properties": {
    "iso:country":"US",
    "sg:address":"1463 S Fort Thomas Ave",
    "sg:city":"Fort Thomas",
    "sg:classifiers":[
        {
            "category":"Health Services",
            "subcategory":"Dentist",
            "type":"Services"
        }
    ],
    "sg:phone":"+1 859 781 4000",
    "sg:postcode":"41075",
    "sg:province":"KY",
    "wof:name":"Becker John M DMD",
    "wof:placetype":"venue"
},
  "geometry": {"coordinates":[-84.450897,39.060101],"type":"Point"}
}