{
  "type": "Feature",
  "properties": {
    "iso:country":"US",
    "sg:address":"345 Nellie Way",
    "sg:city":"Brooks",
    "sg:classifiers":[
        {
            "category":"Farming",
            "subcategory":"Nursery",
            "type":"Manufacturing & Wholesale Goods"
        }
    ],
    "sg:phone":"+1 502 955 7546",
    "sg:postcode":"40109",
    "sg:province":"KY",
    "sg:tags":[
        "greenhouse"
    ],
    "wof:name":"My Little Greenhouse Inc",
    "wof:placetype":"venue"
},
  "geometry": {"coordinates":[-85.72271000000001,38.059388],"type":"Point"}
}