{
  "type": "Feature",
  "properties": {
    "addr:full":"1500 Leestown Rd Lexington KY 40511",
    "addr:housenumber":"1500",
    "addr:postcode":"40511",
    "addr:street":"Leestown Rd",
    "iso:country":"US",
    "sg:address":"1500 Leestown Rd",
    "sg:city":"Lexington",
    "sg:classifiers":[
        {
            "category":"Social Services",
            "type":"Services"
        }
    ],
    "sg:phone":"+1 859 381 0837",
    "sg:postcode":"40511",
    "sg:province":"KY",
    "sg:tags":[
        "organization",
        "welfare"
    ],
    "wof:name":"Teen Pop",
    "wof:placetype":"venue"
},
  "geometry": {"coordinates":[-84.52560699999999,38.067147],"type":"Point"}
}