{
  "type": "Feature",
  "properties": {
    "iso:country":"US",
    "sg:address":"525 W Broadway",
    "sg:city":"Louisville",
    "sg:classifiers":[
        {
            "category":"Manufacturing",
            "subcategory":"Printing",
            "type":"Manufacturing & Wholesale Goods"
        }
    ],
    "sg:phone":"+1 502 582 4711",
    "sg:postcode":"40202",
    "sg:province":"KY",
    "sg:tags":[
        "newspaper"
    ],
    "sg:website":"www.courierjournal.com",
    "wof:name":"Courier Journal",
    "wof:placetype":"venue"
},
  "geometry": {"coordinates":[-85.761636,38.246389],"type":"Point"}
}