{
  "type": "Feature",
  "properties": {
    "addr:full":"100 W A Jenkins Rd Elizabethtown KY 42701",
    "addr:housenumber":"100",
    "addr:postcode":"42701",
    "addr:street":"W A Jenkins Rd",
    "iso:country":"US",
    "sg:address":"100 W A Jenkins Rd",
    "sg:city":"Elizabethtown",
    "sg:classifiers":[
        {
            "category":"Banks & Credit Unions",
            "subcategory":"Bank",
            "type":"Services"
        }
    ],
    "sg:phone":"+1 270 234 8555",
    "sg:postcode":"42701",
    "sg:province":"KY",
    "sg:tags":[
        "loan"
    ],
    "wof:name":"Pioneer Credit Co",
    "wof:placetype":"venue"
},
  "geometry": {"coordinates":[-85.899681,37.757064],"type":"Point"}
}