{
  "type": "Feature",
  "properties": {
    "iso:country":"US",
    "sg:address":"1135 Main St",
    "sg:city":"Millersburg",
    "sg:classifiers":[
        {
            "category":"Utilities",
            "subcategory":"Telephone",
            "type":"Services"
        }
    ],
    "sg:phone":"+1 859 484 9326",
    "sg:postcode":"40348",
    "sg:province":"KY",
    "sg:tags":[
        "company"
    ],
    "wof:name":"Columbia Tel Co",
    "wof:placetype":"venue"
},
  "geometry": {"coordinates":[-84.146097,38.303818],"type":"Point"}
}