{
  "type": "Feature",
  "properties": {
    "addr:full":"6651 US Hwy 127 Jamestown KY 42629",
    "addr:housenumber":"6651",
    "addr:postcode":"42629",
    "addr:street":"Us Hwy 127",
    "iso:country":"US",
    "sg:address":"6651 US Hwy 127",
    "sg:city":"Jamestown",
    "sg:classifiers":[
        {
            "category":"Autos & Motor Vehicles",
            "subcategory":"Boat Sales",
            "type":"Retail Goods"
        },
        {
            "category":"Professional",
            "type":"Services"
        }
    ],
    "sg:phone":"+1 270 343 4829",
    "sg:postcode":"42629",
    "sg:province":"KY",
    "sg:tags":[
        "dealer",
        "sales"
    ],
    "wof:name":"Bill's Boat Barn Inc",
    "wof:placetype":"venue"
},
  "geometry": {"coordinates":[-85.101074,36.916122],"type":"Point"}
}