{
  "type": "Feature",
  "properties": {
    "iso:country":"US",
    "sg:address":"1418 15th Ave SE",
    "sg:city":"Calvert City",
    "sg:classifiers":[
        {
            "category":"Farming",
            "subcategory":"Nursery",
            "type":"Manufacturing & Wholesale Goods"
        }
    ],
    "sg:phone":"+1 270 395 4503",
    "sg:postcode":"42029",
    "sg:province":"KY",
    "sg:tags":[
        "ornamental"
    ],
    "wof:name":"Pecks Nursery",
    "wof:placetype":"venue"
},
  "geometry": {"coordinates":[-88.346052,37.00971],"type":"Point"}
}