{
  "type": "Feature",
  "properties": {
    "iso:country":"US",
    "sg:address":"11 E Hiseville Main St",
    "sg:city":"Glasgow",
    "sg:classifiers":[
        {
            "category":"Banks & Credit Unions",
            "subcategory":"Bank",
            "type":"Services"
        }
    ],
    "sg:phone":"+1 270 453 2501",
    "sg:postcode":"42127",
    "sg:province":"KY",
    "wof:name":"B B & T",
    "wof:placetype":"venue"
},
  "geometry": {"coordinates":[-85.81401,37.100697],"type":"Point"}
}