{
  "type": "Feature",
  "properties": {
    "iso:country":"US",
    "sg:address":"109 Larkspur Dr",
    "sg:city":"Mount Sterling",
    "sg:classifiers":[
        {
            "category":"Building & Trades",
            "subcategory":"Electrical",
            "type":"Services"
        }
    ],
    "sg:phone":"+1 859 498 7651",
    "sg:postcode":"40353",
    "sg:province":"KY",
    "sg:tags":[
        "electrical",
        "contractor"
    ],
    "wof:name":"Superior Electrical",
    "wof:placetype":"venue"
},
  "geometry": {"coordinates":[-83.941232,38.07086],"type":"Point"}
}