{
  "type": "Feature",
  "properties": {
    "iso:country":"US",
    "sg:address":"310 W Main St",
    "sg:city":"Cumberland",
    "sg:classifiers":[
        {
            "category":"Education",
            "subcategory":"Library",
            "type":"Public Place"
        }
    ],
    "sg:phone":"+1 606 589 2409",
    "sg:postcode":"40823",
    "sg:province":"KY",
    "wof:name":"Rebecca Caudill Public Library",
    "wof:placetype":"venue"
},
  "geometry": {"coordinates":[-82.992285,36.975263],"type":"Point"}
}