{
  "type": "Feature",
  "properties": {
    "addr:full":"9800 Preston Hwy Louisville KY 40229",
    "addr:housenumber":"9800",
    "addr:postcode":"40229",
    "addr:street":"Preston Hwy",
    "iso:country":"US",
    "sg:address":"9800 Preston Hwy",
    "sg:city":"Louisville",
    "sg:classifiers":[
        {
            "category":"Home & Garden",
            "subcategory":"Building Materials",
            "type":"Retail Goods"
        }
    ],
    "sg:phone":"+1 502 810 0116",
    "sg:postcode":"40229",
    "sg:province":"KY",
    "sg:tags":[
        "center"
    ],
    "sg:website":"www.lowes.com",
    "wof:name":"Lowe's",
    "wof:placetype":"venue"
},
  "geometry": {"coordinates":[-85.673498,38.105512],"type":"Point"}
}