{
  "type": "Feature",
  "properties": {
    "iso:country":"US",
    "sg:address":"1742 Frankfort Ave",
    "sg:city":"Louisville",
    "sg:classifiers":[
        {
            "category":"Professional",
            "subcategory":"Lawyer & Legal Services",
            "type":"Services"
        }
    ],
    "sg:phone":"+1 502 896 9093",
    "sg:postcode":"40206",
    "sg:province":"KY",
    "sg:tags":[
        "attorney"
    ],
    "wof:name":"Robert M Josephson",
    "wof:placetype":"venue"
},
  "geometry": {"coordinates":[-85.716717,38.256742],"type":"Point"}
}