{
  "type": "Feature",
  "properties": {
    "iso:country":"US",
    "sg:address":"1435 Aiken Rd",
    "sg:city":"Versailles",
    "sg:classifiers":[
        {
            "category":"Retail",
            "subcategory":"Animal Services",
            "type":"Services"
        }
    ],
    "sg:phone":"+1 859 873 0815",
    "sg:postcode":"40383",
    "sg:province":"KY",
    "sg:tags":[
        "breeder",
        "horse"
    ],
    "wof:name":"Chanteclair Farm Inc",
    "wof:placetype":"venue"
},
  "geometry": {"coordinates":[-84.73562699999999,38.111216],"type":"Point"}
}