{
  "type": "Feature",
  "properties": {
    "iso:country":"US",
    "sg:address":"110 Pocahontas Trl",
    "sg:city":"Georgetown",
    "sg:classifiers":[
        {
            "category":"Health Services",
            "subcategory":"Doctor",
            "type":"Services"
        }
    ],
    "sg:phone":"+1 502 863 4651",
    "sg:postcode":"40324",
    "sg:province":"KY",
    "sg:tags":[
        "dentist"
    ],
    "wof:name":"Jack W Shepherd DDS",
    "wof:placetype":"venue"
},
  "geometry": {"coordinates":[-84.563142,38.196816],"type":"Point"}
}