{
  "type": "Feature",
  "properties": {
    "iso:country":"US",
    "sg:address":"107 Union St",
    "sg:city":"Madisonville",
    "sg:classifiers":[
        {
            "category":"Social Services",
            "type":"Services"
        }
    ],
    "sg:phone":"+1 270 821 3986",
    "sg:postcode":"42431",
    "sg:province":"KY",
    "sg:tags":[
        "organization",
        "welfare"
    ],
    "wof:name":"Historical Society Of Hopkins",
    "wof:placetype":"venue"
},
  "geometry": {"coordinates":[-87.49795,37.32723],"type":"Point"}
}