{
  "type": "Feature",
  "properties": {
    "addr:city":"Madisonville",
    "addr:full":"107 Union Street Madisonville, Ky 42431",
    "addr:house_number":"107",
    "addr:housenumber":"107",
    "addr:postcode":"42431",
    "addr:road":"Union Street",
    "addr:state":"KY",
    "addr:street":"Union St",
    "iso:country":"US",
    "sg:address":"107 Union St",
    "sg:city":"Madisonville",
    "sg:classifiers":[
        {
            "category":"Social Services",
            "type":"Services"
        }
    ],
    "sg:phone":"+1 270 821 3986",
    "sg:postcode":"42431",
    "sg:province":"KY",
    "sg:tags":[
        "organization",
        "welfare"
    ],
    "wof:name":"Historical Society Of Hopkins County",
    "wof:placetype":"venue"
},
  "geometry": {"coordinates":[-87.4982,37.32576],"type":"Point"}
}