{
  "type": "Feature",
  "properties": {
    "iso:country":"US",
    "sg:address":"2439 Nicholasville Rd",
    "sg:city":"Lexington",
    "sg:phone":"+1 859 278 3043",
    "sg:postcode":"40503",
    "sg:province":"KY",
    "wof:name":"Autosound Inc",
    "wof:placetype":"venue"
},
  "geometry": {"coordinates":[-84.519768,38.00242],"type":"Point"}
}