{
  "type": "Feature",
  "properties": {
    "addr:full":"236 N Lake Dr Prestonsburg KY 41653",
    "addr:housenumber":"236",
    "addr:postcode":"41653",
    "addr:street":"N Lake Dr",
    "iso:country":"US",
    "sg:address":"236 N Lake Dr",
    "sg:city":"Prestonsburg",
    "sg:classifiers":[
        {
            "category":"Social Services",
            "subcategory":"Child Care",
            "type":"Services"
        }
    ],
    "sg:phone":"+1 606 886 8145",
    "sg:postcode":"41653",
    "sg:province":"KY",
    "sg:tags":[
        "kindergarten",
        "academic",
        "school"
    ],
    "wof:name":"Prestonsburg Headstart",
    "wof:placetype":"venue"
},
  "geometry": {"coordinates":[-82.775814,37.671566],"type":"Point"}
}