{
  "type": "Feature",
  "properties": {
    "iso:country":"US",
    "sg:address":"1104 Julianna Ct",
    "sg:city":"Elizabethtown",
    "sg:classifiers":[
        {
            "category":"Banks & Credit Unions",
            "subcategory":"Investment Brokerage",
            "type":"Services"
        }
    ],
    "sg:phone":"+1 270 737 6144",
    "sg:postcode":"42701",
    "sg:province":"KY",
    "wof:name":"Highland Professional Group",
    "wof:placetype":"venue"
},
  "geometry": {"coordinates":[-85.838229,37.729026],"type":"Point"}
}