{
  "type": "Feature",
  "properties": {
    "iso:country":"US",
    "sg:address":"2489 Old Dixie Hwy",
    "sg:city":"Horse Cave",
    "sg:phone":"+1 270 773 3751",
    "sg:postcode":"42749",
    "sg:province":"KY",
    "sg:tags":[
        "farm",
        "tobacco"
    ],
    "wof:name":"Ellis Hogan",
    "wof:placetype":"venue"
},
  "geometry": {"coordinates":[-85.93956300000001,37.152764],"type":"Point"}
}