{
  "type": "Feature",
  "properties": {
    "addr:full":"124 E Depot St Marion KY 42064",
    "addr:housenumber":"124",
    "addr:postcode":"42064",
    "addr:street":"E Depot St",
    "iso:country":"US",
    "sg:address":"124 E Depot St",
    "sg:city":"Marion",
    "sg:classifiers":[
        {
            "category":"Travel",
            "subcategory":"Hotels & Motels",
            "type":"Entertainment"
        }
    ],
    "sg:phone":"+1 270 965 3731",
    "sg:postcode":"42064",
    "sg:province":"KY",
    "sg:tags":[
        "breakfast",
        "accommodation",
        "bed"
    ],
    "wof:name":"Myers Bed & Breakfast",
    "wof:placetype":"venue"
},
  "geometry": {"coordinates":[-88.08100899999999,37.331074],"type":"Point"}
}