{
  "type": "Feature",
  "properties": {
    "iso:country":"US",
    "sg:address":"2297 Executive Dr",
    "sg:city":"Lexington",
    "sg:classifiers":[
        {
            "category":"Professional",
            "type":"Services"
        }
    ],
    "sg:phone":"+1 859 294 4154",
    "sg:postcode":"40505",
    "sg:province":"KY",
    "sg:tags":[
        "establishment"
    ],
    "wof:name":"Patel Batshavisha",
    "wof:placetype":"venue"
},
  "geometry": {"coordinates":[-84.428611,38.042227],"type":"Point"}
}