{
  "type": "Feature",
  "properties": {
    "addr:full":"566 Kendall Springs Rd Owingsville KY 40360",
    "addr:housenumber":"566",
    "addr:postcode":"40360",
    "addr:street":"Kendall Springs Rd",
    "iso:country":"US",
    "sg:address":"566 Kendall Springs Rd",
    "sg:city":"Owingsville",
    "sg:classifiers":[
        {
            "category":"Utilities",
            "subcategory":"Refuse",
            "type":"Services"
        }
    ],
    "sg:phone":"+1 606 674 6294",
    "sg:postcode":"40360",
    "sg:province":"KY",
    "sg:tags":[
        "garbage",
        "collection"
    ],
    "wof:name":"BFI",
    "wof:placetype":"venue"
},
  "geometry": {"coordinates":[-83.771822,38.123741],"type":"Point"}
}