{
  "type": "Feature",
  "properties": {
    "addr:full":"39 Canoe Creek Rd Liberty KY 42539",
    "addr:housenumber":"39",
    "addr:postcode":"42539",
    "addr:street":"Canoe Creek Rd",
    "iso:country":"US",
    "sg:address":"39 Canoe Creek Rd",
    "sg:city":"Liberty",
    "sg:classifiers":[
        {
            "category":"Professional",
            "subcategory":"Business Services",
            "type":"Services"
        }
    ],
    "sg:phone":"+1 606 787 1445",
    "sg:postcode":"42539",
    "sg:province":"KY",
    "wof:name":"Lang & Assoc",
    "wof:placetype":"venue"
},
  "geometry": {"coordinates":[-84.99414400000001,37.30378],"type":"Point"}
}