{
  "type": "Feature",
  "properties": {
    "addr:full":"10420 Covered Bridge Rd Prospect KY 40059",
    "addr:housenumber":"10420",
    "addr:postcode":"40059",
    "addr:street":"Covered Bridge Rd",
    "iso:country":"US",
    "sg:address":"10420 Covered Bridge Rd",
    "sg:city":"Prospect",
    "sg:classifiers":[
        {
            "category":"Professional",
            "subcategory":"Business Services",
            "type":"Services"
        }
    ],
    "sg:phone":"+1 502 228 6009",
    "sg:postcode":"40059",
    "sg:province":"KY",
    "wof:name":"Thunder Over Louisville",
    "wof:placetype":"venue"
},
  "geometry": {"coordinates":[-85.57529700000001,38.360868],"type":"Point"}
}