{
  "type": "Feature",
  "properties": {
    "addr:full":"101 Crestwood Dr Frankfort KY 40601",
    "addr:housenumber":"101",
    "addr:postcode":"40601",
    "addr:street":"Crestwood Dr",
    "iso:country":"US",
    "sg:address":"101 Crestwood Dr",
    "sg:city":"Frankfort",
    "sg:classifiers":[
        {
            "category":"Retail",
            "subcategory":"Repair Shop",
            "type":"Services"
        }
    ],
    "sg:phone":"+1 502 875 2297",
    "sg:postcode":"40601",
    "sg:province":"KY",
    "sg:tags":[
        "repairing",
        "piano",
        "refinishing"
    ],
    "wof:name":"Griffith Piano Svc",
    "wof:placetype":"venue"
},
  "geometry": {"coordinates":[-84.83802300000001,38.210664],"type":"Point"}
}