{
  "type": "Feature",
  "properties": {
    "iso:country":"US",
    "sg:address":"256 N Kentucky Ave",
    "sg:city":"Madisonville",
    "sg:classifiers":[
        {
            "category":"Banks & Credit Unions",
            "subcategory":"Bank",
            "type":"Services"
        }
    ],
    "sg:phone":"+1 270 821 6668",
    "sg:postcode":"42431",
    "sg:province":"KY",
    "sg:tags":[
        "loan",
        "real estate"
    ],
    "wof:name":"Statewide Mortgage",
    "wof:placetype":"venue"
},
  "geometry": {"coordinates":[-87.49285399999999,37.332748],"type":"Point"}
}