{
  "type": "Feature",
  "properties": {
    "addr:full":"334 Production Ct Louisville KY 40299",
    "addr:housenumber":"334",
    "addr:postcode":"40299",
    "addr:street":"Production Ct",
    "iso:country":"US",
    "sg:address":"334 Production Ct",
    "sg:city":"Louisville",
    "sg:classifiers":[
        {
            "category":"Professional",
            "subcategory":"Art Services",
            "type":"Services"
        }
    ],
    "sg:phone":"+1 502 491 0340",
    "sg:postcode":"40299",
    "sg:province":"KY",
    "sg:tags":[
        "photographer"
    ],
    "sg:website":"www.sigstudios.com",
    "wof:name":"Signature Studios",
    "wof:placetype":"venue"
},
  "geometry": {"coordinates":[-85.56539600000001,38.221849],"type":"Point"}
}