{
  "type": "Feature",
  "properties": {
    "addr:full":"270 Old Porter Pike Bowling Green KY 42103",
    "addr:housenumber":"270",
    "addr:postcode":"42103",
    "addr:street":"Old Porter Pike",
    "iso:country":"US",
    "sg:address":"270 Old Porter Pike",
    "sg:city":"Bowling Green",
    "sg:classifiers":[
        {
            "category":"Retail",
            "subcategory":"Auto Repair",
            "type":"Services"
        }
    ],
    "sg:phone":"+1 270 842 0342",
    "sg:postcode":"42103",
    "sg:province":"KY",
    "sg:tags":[
        "truck"
    ],
    "wof:name":"Carl's Truck & Equip Sales Svc",
    "wof:placetype":"venue"
},
  "geometry": {"coordinates":[-86.397728,37.008071],"type":"Point"}
}