{
  "type": "Feature",
  "properties": {
    "iso:country":"US",
    "sg:address":"1720 Marie Dr",
    "sg:city":"Hopkinsville",
    "sg:classifiers":[
        {
            "category":"Restaurant",
            "type":"Food & Drink"
        }
    ],
    "sg:phone":"+1 270 886 3100",
    "sg:postcode":"42240",
    "sg:province":"KY",
    "wof:name":"Shintomi Japanese Restaurant",
    "wof:placetype":"venue"
},
  "geometry": {"coordinates":[-87.475081,36.840221],"type":"Point"}
}