{
  "type": "Feature",
  "properties": {
    "iso:country":"US",
    "sg:address":"78 Levi Rd",
    "sg:city":"London",
    "sg:classifiers":[
        {
            "category":"Home & Garden",
            "subcategory":"Building Materials",
            "type":"Retail Goods"
        }
    ],
    "sg:phone":"+1 606 864 2772",
    "sg:postcode":"40744",
    "sg:province":"KY",
    "sg:tags":[
        "plywood",
        "veneer"
    ],
    "wof:name":"Cumberland Forest Products Inc",
    "wof:placetype":"venue"
},
  "geometry": {"coordinates":[-84.056466,37.06816],"type":"Point"}
}