{
  "type": "Feature",
  "properties": {
    "addr:full":"1715 Brentmoor Ln Louisville KY 40223",
    "addr:housenumber":"1715",
    "addr:postcode":"40223",
    "addr:street":"Brentmoor Ln",
    "iso:country":"US",
    "sg:address":"1715 Brentmoor Ln",
    "sg:city":"Louisville",
    "sg:classifiers":[
        {
            "category":"Utilities",
            "type":"Services"
        }
    ],
    "sg:phone":"+1 502 423 7555",
    "sg:postcode":"40223",
    "sg:province":"KY",
    "sg:tags":[
        "locating"
    ],
    "wof:name":"Midwest Marking Inc",
    "wof:placetype":"venue"
},
  "geometry": {"coordinates":[-85.579302,38.2744],"type":"Point"}
}