{
  "type": "Feature",
  "properties": {
    "iso:country":"US",
    "sg:address":"750 Kelly Harris Rd",
    "sg:city":"Bowling Green",
    "sg:classifiers":[
        {
            "category":"Building & Trades",
            "subcategory":"Plumbing",
            "type":"Services"
        }
    ],
    "sg:phone":"+1 270 843 3628",
    "sg:postcode":"42101",
    "sg:province":"KY",
    "sg:tags":[
        "plumbing",
        "contractor"
    ],
    "wof:name":"Walton Brothers Plumbing",
    "wof:placetype":"venue"
},
  "geometry": {"coordinates":[-86.571645,37.009752],"type":"Point"}
}