{
  "type": "Feature",
  "properties": {
    "addr:full":"2435 Carolina Ave Louisville KY 40205",
    "addr:housenumber":"2435",
    "addr:postcode":"40205",
    "addr:street":"Carolina Ave",
    "iso:country":"US",
    "sg:address":"2435 Carolina Ave",
    "sg:city":"Louisville",
    "sg:classifiers":[
        {
            "category":"Education",
            "subcategory":"School",
            "type":"Public Place"
        }
    ],
    "sg:phone":"+1 502 454 7444",
    "sg:postcode":"40205",
    "sg:province":"KY",
    "sg:tags":[
        "bags-specialty"
    ],
    "wof:name":"Synergist",
    "wof:placetype":"venue"
},
  "geometry": {"coordinates":[-85.681746,38.226699],"type":"Point"}
}