{
  "type": "Feature",
  "properties": {
    "addr:full":"17 Grand Ave Florence KY 41042",
    "addr:housenumber":"17",
    "addr:postcode":"41042",
    "addr:street":"Grand Ave",
    "iso:country":"US",
    "sg:address":"17 Grand Ave",
    "sg:city":"Florence",
    "sg:classifiers":[
        {
            "category":"Retail",
            "subcategory":"Repair Shop",
            "type":"Services"
        }
    ],
    "sg:phone":"+1 859 261 1234",
    "sg:postcode":"41042",
    "sg:province":"KY",
    "sg:tags":[
        "scooter",
        "motorcycle",
        "motor"
    ],
    "wof:name":"Sons Of Thunder",
    "wof:placetype":"venue"
},
  "geometry": {"coordinates":[-84.632898,38.991788],"type":"Point"}
}