{
  "type": "Feature",
  "properties": {
    "iso:country":"US",
    "sg:address":"3304 Gondola Ct",
    "sg:city":"Lexington",
    "sg:classifiers":[
        {
            "category":"Cinema",
            "subcategory":"Movie Theater",
            "type":"Entertainment"
        }
    ],
    "sg:phone":"+1 859 296 5998",
    "sg:postcode":"40513",
    "sg:province":"KY",
    "wof:name":"Bluegrass Theatres Inc",
    "wof:placetype":"venue"
},
  "geometry": {"coordinates":[-84.56844,38.011341],"type":"Point"}
}