{
  "type": "Feature",
  "properties": {
    "iso:country":"US",
    "sg:address":"1000 Bypass N",
    "sg:city":"Lawrenceburg",
    "sg:classifiers":[
        {
            "category":"Restaurant",
            "type":"Food & Drink"
        }
    ],
    "sg:menulink":"http://www.allmenus.com/ky/lawrenceburg/120572-subway/menu/",
    "sg:phone":"+1 502 859 2123",
    "sg:postcode":"40342",
    "sg:province":"KY",
    "sg:tags":[
        "american",
        "sandwich"
    ],
    "wof:name":"Subway",
    "wof:placetype":"venue"
},
  "geometry": {"coordinates":[-84.912122,38.03547],"type":"Point"}
}