{
  "type": "Feature",
  "properties": {
    "iso:country":"US",
    "sg:address":"407 S 3rd St",
    "sg:city":"Bardstown",
    "sg:classifiers":[
        {
            "category":"Education",
            "subcategory":"School",
            "type":"Public Place"
        }
    ],
    "sg:phone":"+1 502 331 8809",
    "sg:postcode":"40004",
    "sg:province":"KY",
    "wof:name":"Bardstown Adult Learning Ctr",
    "wof:placetype":"venue"
},
  "geometry": {"coordinates":[-85.46913000000001,37.801591],"type":"Point"}
}