{
  "type": "Feature",
  "properties": {
    "iso:country":"US",
    "sg:address":"3220 Crums Ln",
    "sg:city":"Shively",
    "sg:classifiers":[
        {
            "category":"Food & Beverages",
            "subcategory":"Groceries & Convenience Stores",
            "type":"Retail Goods"
        }
    ],
    "sg:phone":"+1 502 448 9713",
    "sg:postcode":"40216",
    "sg:province":"KY",
    "sg:tags":[
        "grocer"
    ],
    "wof:name":"Beuhlers",
    "wof:placetype":"venue"
},
  "geometry": {"coordinates":[-85.83688600000001,38.198938],"type":"Point"}
}