{
  "type": "Feature",
  "properties": {
    "iso:country":"US",
    "sg:address":"1250 Bardstown Rd",
    "sg:city":"Louisville",
    "sg:classifiers":[
        {
            "category":"Sports & Exercise",
            "subcategory":"Gym",
            "type":"Entertainment"
        }
    ],
    "sg:phone":"+1 502 458 7282",
    "sg:postcode":"40204",
    "sg:province":"KY",
    "sg:tags":[
        "gymnasium"
    ],
    "wof:name":"Jim Cain's Mid City Fitness",
    "wof:placetype":"venue"
},
  "geometry": {"coordinates":[-85.71608999999999,38.235717],"type":"Point"}
}