{
  "type": "Feature",
  "properties": {
    "iso:country":"US",
    "sg:address":"3801 Mud Ln",
    "sg:city":"Louisville",
    "sg:classifiers":[
        {
            "category":"Freight",
            "type":"Transportation"
        }
    ],
    "sg:phone":"+1 502 964 9559",
    "sg:postcode":"40229",
    "sg:province":"KY",
    "sg:tags":[
        "operator",
        "local",
        "trucking"
    ],
    "wof:name":"Raisor Trucking Co Inc",
    "wof:placetype":"venue"
},
  "geometry": {"coordinates":[-85.697192,38.089144],"type":"Point"}
}