{
  "type": "Feature",
  "properties": {
    "iso:country":"US",
    "sg:address":"9920 State Hwy 1676",
    "sg:city":"Science Hill",
    "sg:classifiers":[
        {
            "category":"Health Services",
            "subcategory":"Doctor",
            "type":"Services"
        }
    ],
    "sg:phone":"+1 606 423 9390",
    "sg:postcode":"42553",
    "sg:province":"KY",
    "sg:tags":[
        "physician",
        "surgeon"
    ],
    "wof:name":"Stanley Archer MD",
    "wof:placetype":"venue"
},
  "geometry": {"coordinates":[-84.775116,37.174474],"type":"Point"}
}