{
  "type": "Feature",
  "properties": {
    "iso:country":"US",
    "sg:address":"110 Dilcrest Dr",
    "sg:city":"Florence",
    "sg:classifiers":[
        {
            "category":"Professional",
            "subcategory":"Management & Consulting",
            "type":"Services"
        }
    ],
    "sg:phone":"+1 859 371 2755",
    "sg:postcode":"41042",
    "sg:province":"KY",
    "sg:tags":[
        "consultant",
        "educational"
    ],
    "wof:name":"Michael C King & Assoc Inc",
    "wof:placetype":"venue"
},
  "geometry": {"coordinates":[-84.649995,38.981673],"type":"Point"}
}