{
  "type": "Feature",
  "properties": {
    "iso:country":"US",
    "sg:address":"12700 Shelbyville Rd",
    "sg:city":"Louisville",
    "sg:classifiers":[
        {
            "category":"Insurance",
            "subcategory":"Hazard Insurance",
            "type":"Services"
        }
    ],
    "sg:phone":"+1 502 459 4414",
    "sg:postcode":"40243",
    "sg:province":"KY",
    "sg:tags":[
        "profit",
        "sharing",
        "pension",
        "plan"
    ],
    "wof:name":"Alexander Investment Svc",
    "wof:placetype":"venue"
},
  "geometry": {"coordinates":[-85.51844800000001,38.2435],"type":"Point"}
}