{
  "type": "Feature",
  "properties": {
    "addr:full":"2509 Plantside Dr Jeffersontown KY 40299",
    "addr:housenumber":"2509",
    "addr:postcode":"40299",
    "addr:street":"Plantside Dr",
    "iso:country":"US",
    "sg:address":"2509 Plantside Dr",
    "sg:city":"Jeffersontown",
    "sg:classifiers":[
        {
            "category":"Professional",
            "type":"Services"
        }
    ],
    "sg:phone":"+1 502 493 0603",
    "sg:postcode":"40299",
    "sg:province":"KY",
    "sg:tags":[
        "establishment"
    ],
    "wof:name":"United American Of Kentucky",
    "wof:placetype":"venue"
},
  "geometry": {"coordinates":[-85.564076,38.209574],"type":"Point"}
}