{
  "type": "Feature",
  "properties": {
    "addr:full":"465 Summer Hill Dr Somerset KY 42503",
    "addr:housenumber":"465",
    "addr:postcode":"42503",
    "addr:street":"Summer Hill Dr",
    "iso:country":"US",
    "sg:address":"465 Summer Hill Dr",
    "sg:city":"Somerset",
    "sg:classifiers":[
        {
            "category":"Communications",
            "type":"Services"
        }
    ],
    "sg:phone":"+1 606 678 5678",
    "sg:postcode":"42503",
    "sg:province":"KY",
    "wof:name":"Advanced Communication",
    "wof:placetype":"venue"
},
  "geometry": {"coordinates":[-84.64025599999999,37.043509],"type":"Point"}
}