{
  "type": "Feature",
  "properties": {
    "iso:country":"US",
    "sg:address":"1114 State Hwy 1247",
    "sg:city":"Somerset",
    "sg:classifiers":[
        {
            "category":"Food & Beverages",
            "subcategory":"Groceries & Convenience Stores",
            "type":"Retail Goods"
        }
    ],
    "sg:phone":"+1 606 679 7744",
    "sg:postcode":"42503",
    "sg:province":"KY",
    "wof:name":"Purcell's Food Mart Inc",
    "wof:placetype":"venue"
},
  "geometry": {"coordinates":[-84.603082,37.058656],"type":"Point"}
}