{
  "type": "Feature",
  "properties": {
    "iso:country":"US",
    "sg:address":"7478 Falls of Rough Rd",
    "sg:city":"Caneyville",
    "sg:classifiers":[
        {
            "category":"Real Estate",
            "subcategory":"Real Estate Operator",
            "type":"Services"
        }
    ],
    "sg:phone":"+1 270 879 9775",
    "sg:postcode":"42721",
    "sg:province":"KY",
    "sg:tags":[
        "property",
        "lessor"
    ],
    "wof:name":"Wayne Patterson",
    "wof:placetype":"venue"
},
  "geometry": {"coordinates":[-86.472126,37.518132],"type":"Point"}
}