{
  "type": "Feature",
  "properties": {
    "iso:country":"US",
    "sg:address":"816 S Broadway St",
    "sg:city":"Georgetown",
    "sg:classifiers":[
        {
            "category":"Recreation",
            "type":"Entertainment"
        }
    ],
    "sg:phone":"+1 502 863 5010",
    "sg:postcode":"40324",
    "sg:province":"KY",
    "sg:tags":[
        "skating",
        "rink"
    ],
    "wof:name":"Wilsons Roller Skating Rink",
    "wof:placetype":"venue"
},
  "geometry": {"coordinates":[-84.561458,38.194587],"type":"Point"}
}