{
  "type": "Feature",
  "properties": {
    "addr:full":"1082 Bethlehem Church Rd Wickliffe KY 42087",
    "addr:housenumber":"1082",
    "addr:postcode":"42087",
    "addr:street":"Bethlehem Church Rd",
    "iso:country":"US",
    "sg:address":"1082 Bethlehem Church Rd",
    "sg:city":"Wickliffe",
    "sg:classifiers":[
        {
            "category":"Building & Trades",
            "subcategory":"Landscaping Services",
            "type":"Services"
        }
    ],
    "sg:phone":"+1 270 335 5192",
    "sg:postcode":"42087",
    "sg:province":"KY",
    "sg:tags":[
        "landscape",
        "contractor"
    ],
    "wof:name":"M & M Tree Svc",
    "wof:placetype":"venue"
},
  "geometry": {"coordinates":[-89.043363,36.952509],"type":"Point"}
}