{
  "type": "Feature",
  "properties": {
    "iso:country":"US",
    "sg:address":"3280 Mills Rd",
    "sg:city":"Covington",
    "sg:classifiers":[
        {
            "category":"Organizations",
            "subcategory":"Religious Organization",
            "type":"Services"
        }
    ],
    "sg:phone":"+1 859 356 5151",
    "sg:postcode":"41015",
    "sg:province":"KY",
    "sg:tags":[
        "church"
    ],
    "wof:name":"St Patrick Church",
    "wof:placetype":"venue"
},
  "geometry": {"coordinates":[-84.504228,38.94656],"type":"Point"}
}