{
  "type": "Feature",
  "properties": {
    "addr:full":"901 Meader St Campbellsville KY 42718",
    "addr:housenumber":"901",
    "addr:postcode":"42718",
    "addr:street":"Meader St",
    "iso:country":"US",
    "sg:address":"901 Meader St",
    "sg:city":"Campbellsville",
    "sg:classifiers":[
        {
            "category":"Home & Garden",
            "subcategory":"Hardware",
            "type":"Retail Goods"
        }
    ],
    "sg:phone":"+1 270 465 4139",
    "sg:postcode":"42718",
    "sg:province":"KY",
    "sg:tags":[
        "renting",
        "equipment",
        "lawn",
        "supply"
    ],
    "sg:website":"http://www.stihldealer.net/default-dealer-001783.aspx",
    "wof:name":"Caulk Hardware Co.",
    "wof:placetype":"venue"
},
  "geometry": {"coordinates":[-85.35887,37.34563],"type":"Point"}
}