{
  "type": "Feature",
  "properties": {
    "iso:country":"US",
    "sg:address":"3367 Nicholasville Rd",
    "sg:city":"Lexington",
    "sg:classifiers":[
        {
            "category":"Restaurant",
            "type":"Food & Drink"
        }
    ],
    "sg:phone":"+1 859 273 2298",
    "sg:postcode":"40503",
    "sg:province":"KY",
    "sg:tags":[
        "eating"
    ],
    "wof:name":"Chao Praya Chinese Eatery",
    "wof:placetype":"venue"
},
  "geometry": {"coordinates":[-84.52404799999999,37.990914],"type":"Point"}
}