{
  "type": "Feature",
  "properties": {
    "addr:full":"147 Bryan St Pikeville KY 41501",
    "addr:housenumber":"147",
    "addr:postcode":"41501",
    "addr:street":"Bryan St",
    "iso:country":"US",
    "sg:address":"147 Bryan St",
    "sg:city":"Pikeville",
    "sg:classifiers":[
        {
            "category":"Education",
            "subcategory":"School",
            "type":"Public Place"
        }
    ],
    "sg:phone":"+1 606 437 6117",
    "sg:postcode":"41501",
    "sg:province":"KY",
    "wof:name":"St Francis Catholic School",
    "wof:placetype":"venue"
},
  "geometry": {"coordinates":[-82.53408399999999,37.499301],"type":"Point"}
}