{
  "type": "Feature",
  "properties": {
    "iso:country":"US",
    "sg:address":"1820 Oakview Rd",
    "sg:city":"Ashland",
    "sg:classifiers":[
        {
            "category":"Health Services",
            "subcategory":"Nursing And Care Facility",
            "type":"Services"
        }
    ],
    "sg:phone":"+1 606 325 5200",
    "sg:postcode":"41101",
    "sg:province":"KY",
    "sg:tags":[
        "home",
        "convalescent"
    ],
    "wof:name":"Woodland Oaks",
    "wof:placetype":"venue"
},
  "geometry": {"coordinates":[-82.64908699999999,38.466939],"type":"Point"}
}