{
  "type": "Feature",
  "properties": {
    "addr:full":"12 River Hill Rd St Matthews KY 40207",
    "addr:housenumber":"12",
    "addr:postcode":"40207",
    "addr:street":"River Hill Rd",
    "iso:country":"US",
    "sg:address":"12 River Hill Rd",
    "sg:city":"St Matthews",
    "sg:classifiers":[
        {
            "category":"Professional",
            "subcategory":"Accounting & Tax Preparation",
            "type":"Services"
        }
    ],
    "sg:phone":"+1 502 897 5065",
    "sg:postcode":"40207",
    "sg:province":"KY",
    "sg:tags":[
        "accountant"
    ],
    "wof:name":"Douglas P Sumner",
    "wof:placetype":"venue"
},
  "geometry": {"coordinates":[-85.667112,38.282989],"type":"Point"}
}