{
  "type": "Feature",
  "properties": {
    "iso:country":"US",
    "sg:address":"515 Bellefonte St",
    "sg:city":"Russell",
    "sg:classifiers":[
        {
            "category":"Shopping",
            "subcategory":"Used Merchandise",
            "type":"Retail Goods"
        }
    ],
    "sg:phone":"+1 606 836 4213",
    "sg:postcode":"41169",
    "sg:province":"KY",
    "sg:tags":[
        "furniture"
    ],
    "wof:name":"Town & Country Furniture",
    "wof:placetype":"venue"
},
  "geometry": {"coordinates":[-82.694323,38.531938],"type":"Point"}
}