{
  "type": "Feature",
  "properties": {
    "iso:country":"US",
    "sg:address":"426 E 4th St",
    "sg:city":"Russellville",
    "sg:classifiers":[
        {
            "category":"Insurance",
            "subcategory":"Insurance Agent",
            "type":"Services"
        }
    ],
    "sg:phone":"+1 270 726 9539",
    "sg:postcode":"42276",
    "sg:province":"KY",
    "wof:name":"Farm Bureau Insurance",
    "wof:placetype":"venue"
},
  "geometry": {"coordinates":[-86.88285999999999,36.846467],"type":"Point"}
}