{
  "type": "Feature",
  "properties": {
    "iso:country":"US",
    "sg:address":"1060 Elizabeth St",
    "sg:city":"Nicholasville",
    "sg:classifiers":[
        {
            "category":"Professional",
            "subcategory":"Management & Consulting",
            "type":"Services"
        }
    ],
    "sg:phone":"+1 859 887 1116",
    "sg:postcode":"40356",
    "sg:province":"KY",
    "sg:tags":[
        "consultant"
    ],
    "wof:name":"EHI Consultants",
    "wof:placetype":"venue"
},
  "geometry": {"coordinates":[-84.5595,37.919004],"type":"Point"}
}