{
  "type": "Feature",
  "properties": {
    "iso:country":"US",
    "sg:address":"8413 Ambrosse Ln",
    "sg:city":"Louisville",
    "sg:classifiers":[
        {
            "category":"Building & Trades",
            "subcategory":"Construction",
            "type":"Services"
        }
    ],
    "sg:phone":"+1 502 418 5823",
    "sg:postcode":"40299",
    "sg:province":"KY",
    "sg:tags":[
        "contractor"
    ],
    "wof:name":"American Group Jefferson",
    "wof:placetype":"venue"
},
  "geometry": {"coordinates":[-85.602615,38.195609],"type":"Point"}
}