{
  "type": "Feature",
  "properties": {
    "iso:country":"US",
    "sg:address":"6345 State Hwy 910",
    "sg:city":"Russell Springs",
    "sg:classifiers":[
        {
            "category":"Wholesale",
            "subcategory":"Machinery & Supplies",
            "type":"Manufacturing & Wholesale Goods"
        }
    ],
    "sg:phone":"+1 270 866 6651",
    "sg:postcode":"42642",
    "sg:province":"KY",
    "sg:tags":[
        "equipment",
        "dairy"
    ],
    "wof:name":"Wilson Dairy Supply",
    "wof:placetype":"venue"
},
  "geometry": {"coordinates":[-84.92954400000001,37.087813],"type":"Point"}
}