{
  "type": "Feature",
  "properties": {
    "iso:country":"US",
    "sg:address":"309 Townepark Cir",
    "sg:city":"Louisville",
    "sg:classifiers":[
        {
            "category":"Wholesale",
            "subcategory":"Medical Equipment & Supplies",
            "type":"Manufacturing & Wholesale Goods"
        }
    ],
    "sg:phone":"+1 502 489 5233",
    "sg:postcode":"40243",
    "sg:province":"KY",
    "sg:tags":[
        "physician",
        "surgeon"
    ],
    "wof:name":"Preferred Medical Network",
    "wof:placetype":"venue"
},
  "geometry": {"coordinates":[-85.51826699999999,38.241033],"type":"Point"}
}