{
  "type": "Feature",
  "properties": {
    "iso:country":"US",
    "sg:address":"8800 Shelbyville Rd",
    "sg:city":"Louisville",
    "sg:classifiers":[
        {
            "category":"Organizations",
            "subcategory":"Religious Organization",
            "type":"Services"
        }
    ],
    "sg:phone":"+1 502 426 2444",
    "sg:postcode":"40222",
    "sg:province":"KY",
    "sg:tags":[
        "church"
    ],
    "sg:website":"www.hurstbourne-baptist.org",
    "wof:name":"Hurstbourne Baptist Church",
    "wof:placetype":"venue"
},
  "geometry": {"coordinates":[-85.591043,38.247522],"type":"Point"}
}