{
  "type": "Feature",
  "properties": {
    "addr:full":"2220 Gay Evans Rd Winchester KY 40391",
    "addr:housenumber":"2220",
    "addr:postcode":"40391",
    "addr:street":"Gay Evans Rd",
    "iso:country":"US",
    "sg:address":"2220 Gay Evans Rd",
    "sg:city":"Winchester",
    "sg:classifiers":[
        {
            "category":"Food & Beverages",
            "subcategory":"Specialty",
            "type":"Retail Goods"
        }
    ],
    "sg:phone":"+1 859 737 2634",
    "sg:postcode":"40391",
    "sg:province":"KY",
    "wof:name":"Earth Star Inc",
    "wof:placetype":"venue"
},
  "geometry": {"coordinates":[-84.13951299999999,38.04812],"type":"Point"}
}