{
  "type": "Feature",
  "properties": {
    "addr:full":"1620 Scottsville Rd Bowling Green KY 42104",
    "addr:housenumber":"1620",
    "addr:postcode":"42104",
    "addr:street":"Scottsville Rd",
    "iso:country":"US",
    "sg:address":"1620 Scottsville Rd",
    "sg:city":"Bowling Green",
    "sg:classifiers":[
        {
            "category":"Personal",
            "subcategory":"Beauty Salon",
            "type":"Services"
        }
    ],
    "sg:phone":"+1 270 793 9050",
    "sg:postcode":"42104",
    "sg:province":"KY",
    "sg:tags":[
        "shop"
    ],
    "wof:name":"Nail Studio",
    "wof:placetype":"venue"
},
  "geometry": {"coordinates":[-86.43455,36.971073],"type":"Point"}
}