{
  "type": "Feature",
  "properties": {
    "iso:country":"US",
    "sg:address":"595 Fords Mill Rd",
    "sg:city":"Versailles",
    "sg:classifiers":[
        {
            "category":"Building & Trades",
            "subcategory":"Construction",
            "type":"Services"
        }
    ],
    "sg:phone":"+1 859 873 0153",
    "sg:postcode":"40383",
    "sg:province":"KY",
    "sg:tags":[
        "floor",
        "laying",
        "contractor"
    ],
    "wof:name":"A S Tile",
    "wof:placetype":"venue"
},
  "geometry": {"coordinates":[-84.740748,37.949548],"type":"Point"}
}