{
  "type": "Feature",
  "properties": {
    "addr:full":"11093 Clay Dr Walton KY 41094",
    "addr:housenumber":"11093",
    "addr:postcode":"41094",
    "addr:street":"Clay Dr",
    "iso:country":"US",
    "sg:address":"11093 Clay Dr",
    "sg:city":"Walton",
    "sg:classifiers":[
        {
            "category":"Retail",
            "subcategory":"Laundry & Dry Cleaning",
            "type":"Services"
        }
    ],
    "sg:phone":"+1 859 485 1701",
    "sg:postcode":"41094",
    "sg:province":"KY",
    "sg:tags":[
        "cleaners"
    ],
    "wof:name":"Braxton's",
    "wof:placetype":"venue"
},
  "geometry": {"coordinates":[-84.63351400000001,38.915719],"type":"Point"}
}