{
  "type": "Feature",
  "properties": {
    "addr:full":"407 E Main St Hazard KY 41701",
    "addr:housenumber":"407",
    "addr:postcode":"41701",
    "addr:street":"E Main St",
    "iso:country":"US",
    "sg:address":"407 E Main St",
    "sg:city":"Hazard",
    "sg:classifiers":[
        {
            "category":"Retail",
            "subcategory":"Laundry & Dry Cleaning",
            "type":"Services"
        }
    ],
    "sg:phone":"+1 606 436 3466",
    "sg:postcode":"41701",
    "sg:province":"KY",
    "sg:tags":[
        "cleaners"
    ],
    "wof:name":"Custom Cleaners",
    "wof:placetype":"venue"
},
  "geometry": {"coordinates":[-83.186288,37.246179],"type":"Point"}
}