{
  "type": "Feature",
  "properties": {
    "addr:city":"Morganfield",
    "addr:full":"1116 Village Square Rd Morganfield, Ky 42437",
    "addr:house_number":"1116",
    "addr:housenumber":"1116",
    "addr:phone":"+1 270-389-4420",
    "addr:postcode":"42437",
    "addr:road":"Village Square Rd",
    "addr:state":"KY",
    "addr:street":"Village Square Rd",
    "iso:country":"US",
    "sg:address":"1116 Village Square Rd",
    "sg:city":"Morganfield",
    "sg:classifiers":[
        {
            "category":"Museum",
            "type":"Entertainment"
        }
    ],
    "sg:phone":"+1 270 389 4420",
    "sg:postcode":"42437",
    "sg:province":"KY",
    "wof:name":"Camp Breckenridge Museum And Art",
    "wof:placetype":"venue"
},
  "geometry": {"coordinates":[-87.88934,37.6762],"type":"Point"}
}