{
  "type": "Feature",
  "properties": {
    "addr:full":"1116 Village Square Rd Morganfield KY 42437",
    "addr:housenumber":"1116",
    "addr:postcode":"42437",
    "addr:street":"Village Square Rd",
    "iso:country":"US",
    "sg:address":"1116 Village Square Rd",
    "sg:city":"Morganfield",
    "sg:classifiers":[
        {
            "category":"Museum",
            "type":"Entertainment"
        }
    ],
    "sg:phone":"+1 270 389 4420",
    "sg:postcode":"42437",
    "sg:province":"KY",
    "wof:name":"Camp Breckenridge Museum & Art",
    "wof:placetype":"venue"
},
  "geometry": {"coordinates":[-87.88143599999999,37.679577],"type":"Point"}
}