{
  "type": "Feature",
  "properties": {
    "iso:country":"US",
    "sg:address":"1602 Westen St",
    "sg:city":"Bowling Green",
    "sg:classifiers":[
        {
            "category":"Health Services",
            "subcategory":"Doctor",
            "type":"Services"
        }
    ],
    "sg:phone":"+1 270 781 1706",
    "sg:postcode":"42104",
    "sg:province":"KY",
    "sg:tags":[
        "dentist"
    ],
    "wof:name":"Tim W Whitaker DDS",
    "wof:placetype":"venue"
},
  "geometry": {"coordinates":[-86.44533800000001,36.964936],"type":"Point"}
}