{
  "type": "Feature",
  "properties": {
    "iso:country":"US",
    "sg:address":"1004 Dark Star Way",
    "sg:city":"Goshen",
    "sg:classifiers":[
        {
            "category":"Professional",
            "subcategory":"Advertising",
            "type":"Services"
        }
    ],
    "sg:phone":"+1 502 228 9043",
    "sg:postcode":"40026",
    "sg:province":"KY",
    "sg:tags":[
        "counselor"
    ],
    "wof:name":"Friday Associates Inc",
    "wof:placetype":"venue"
},
  "geometry": {"coordinates":[-85.585784,38.398718],"type":"Point"}
}