{
  "type": "Feature",
  "properties": {
    "iso:country":"US",
    "sg:address":"212 W Main St",
    "sg:city":"Lebanon",
    "sg:classifiers":[
        {
            "category":"Restaurant",
            "type":"Food & Drink"
        }
    ],
    "sg:phone":"+1 270 692 3970",
    "sg:postcode":"40033",
    "sg:province":"KY",
    "wof:name":"Big Jim's Bar & Grill",
    "wof:placetype":"venue"
},
  "geometry": {"coordinates":[-85.254546,37.569058],"type":"Point"}
}