{
  "type": "Feature",
  "properties": {
    "iso:country":"US",
    "sg:address":"1002 Lexington Rd",
    "sg:city":"Georgetown",
    "sg:classifiers":[
        {
            "category":"Professional",
            "subcategory":"Employment Agencies",
            "type":"Services"
        }
    ],
    "sg:phone":"+1 502 570 0900",
    "sg:postcode":"40324",
    "sg:province":"KY",
    "sg:tags":[
        "opportunity"
    ],
    "wof:name":"Kelly Services Inc",
    "wof:placetype":"venue"
},
  "geometry": {"coordinates":[-84.56216999999999,38.189971],"type":"Point"}
}