{
  "type": "Feature",
  "properties": {
    "iso:country":"US",
    "sg:address":"1644 Redbud Cir",
    "sg:city":"Radcliff",
    "sg:classifiers":[
        {
            "category":"Real Estate",
            "subcategory":"Real Estate Agent",
            "type":"Services"
        }
    ],
    "sg:phone":"+1 270 352 2200",
    "sg:postcode":"40160",
    "sg:province":"KY",
    "wof:name":"Home Towne Rentals",
    "wof:placetype":"venue"
},
  "geometry": {"coordinates":[-85.96625899999999,37.834413],"type":"Point"}
}