{
  "type": "Feature",
  "properties": {
    "iso:country":"US",
    "sg:address":"1048 Brockley Way",
    "sg:city":"Bowling Green",
    "sg:classifiers":[
        {
            "category":"Home & Garden",
            "subcategory":"Hardware",
            "type":"Retail Goods"
        }
    ],
    "sg:phone":"+1 270 843 3594",
    "sg:postcode":"42103",
    "sg:province":"KY",
    "sg:tags":[
        "saw"
    ],
    "wof:name":"Chain Saw World-Bowling Green",
    "wof:placetype":"venue"
},
  "geometry": {"coordinates":[-86.426211,36.993174],"type":"Point"}
}