{
  "type": "Feature",
  "properties": {
    "iso:country":"US",
    "sg:address":"644 Slate Branch Rd",
    "sg:city":"Somerset",
    "sg:classifiers":[
        {
            "category":"Retail",
            "subcategory":"Auto Repair",
            "type":"Services"
        }
    ],
    "sg:phone":"+1 606 678 2826",
    "sg:postcode":"42503",
    "sg:province":"KY",
    "sg:tags":[
        "body",
        "automobile",
        "painting"
    ],
    "wof:name":"Nelson Auto Body",
    "wof:placetype":"venue"
},
  "geometry": {"coordinates":[-84.638785,37.031921],"type":"Point"}
}