{
  "type": "Feature",
  "properties": {
    "iso:country":"US",
    "sg:address":"209 E Irvine St",
    "sg:city":"Richmond",
    "sg:classifiers":[
        {
            "category":"Organizations",
            "subcategory":"Religious Organization",
            "type":"Services"
        }
    ],
    "sg:phone":"+1 859 623 5828",
    "sg:postcode":"40475",
    "sg:province":"KY",
    "sg:tags":[
        "church"
    ],
    "wof:name":"Richmond Predestinarian Baptst",
    "wof:placetype":"venue"
},
  "geometry": {"coordinates":[-84.291522,37.747335],"type":"Point"}
}