{
  "type": "Feature",
  "properties": {
    "iso:country":"US",
    "sg:address":"1501 Broadway St",
    "sg:city":"Paducah",
    "sg:classifiers":[
        {
            "category":"Insurance",
            "subcategory":"Insurance Agent",
            "type":"Services"
        }
    ],
    "sg:phone":"+1 270 442 1697",
    "sg:postcode":"42001",
    "sg:province":"KY",
    "wof:name":"Gower Insurance",
    "wof:placetype":"venue"
},
  "geometry": {"coordinates":[-88.613563,37.080456],"type":"Point"}
}