{
  "type": "Feature",
  "properties": {
    "addr:full":"767 Chinoe Rd Lexington KY 40502",
    "addr:housenumber":"767",
    "addr:postcode":"40502",
    "addr:street":"Chinoe Rd",
    "iso:country":"US",
    "sg:address":"767 Chinoe Rd",
    "sg:city":"Lexington",
    "sg:classifiers":[
        {
            "category":"Retail",
            "subcategory":"Veterinary Services",
            "type":"Services"
        }
    ],
    "sg:phone":"+1 859 266 2426",
    "sg:postcode":"40502",
    "sg:province":"KY",
    "sg:tags":[
        "veterinarian"
    ],
    "wof:name":"M K Snyder DVM",
    "wof:placetype":"venue"
},
  "geometry": {"coordinates":[-84.484649,38.010983],"type":"Point"}
}