{
  "type": "Feature",
  "properties": {
    "iso:country":"US",
    "sg:address":"4150 Alexandria Pike",
    "sg:city":"Newport",
    "sg:classifiers":[
        {
            "category":"Travel",
            "subcategory":"Travel Agent",
            "type":"Entertainment"
        }
    ],
    "sg:phone":"+1 859 781 7888",
    "sg:postcode":"41076",
    "sg:province":"KY",
    "sg:tags":[
        "agency"
    ],
    "wof:name":"Freedom Travel",
    "wof:placetype":"venue"
},
  "geometry": {"coordinates":[-84.435845,39.018345],"type":"Point"}
}