{
  "type": "Feature",
  "properties": {
    "iso:country":"US",
    "sg:address":"6104 Cherry Ln",
    "sg:city":"Crestwood",
    "sg:classifiers":[
        {
            "category":"Farming",
            "subcategory":"Nursery",
            "type":"Manufacturing & Wholesale Goods"
        }
    ],
    "sg:phone":"+1 502 241 5207",
    "sg:postcode":"40014",
    "sg:province":"KY",
    "sg:tags":[
        "ornamental",
        "supply"
    ],
    "wof:name":"J Whyland Nurseries",
    "wof:placetype":"venue"
},
  "geometry": {"coordinates":[-85.469836,38.31237],"type":"Point"}
}