{
  "type": "Feature",
  "properties": {
    "addr:full":"5227 Lexington Rd Winchester KY 40391",
    "addr:housenumber":"5227",
    "addr:postcode":"40391",
    "addr:street":"Lexington Rd",
    "iso:country":"US",
    "sg:address":"5227 Lexington Rd",
    "sg:city":"Winchester",
    "sg:classifiers":[
        {
            "category":"Utilities",
            "subcategory":"Mobile Phone",
            "type":"Services"
        }
    ],
    "sg:phone":"+1 859 745 5809",
    "sg:postcode":"40391",
    "sg:province":"KY",
    "sg:tags":[
        "telephone",
        "cellular"
    ],
    "wof:name":"Contel Cellular",
    "wof:placetype":"venue"
},
  "geometry": {"coordinates":[-84.261481,38.023126],"type":"Point"}
}