{
  "type": "Feature",
  "properties": {
    "iso:country":"US",
    "sg:address":"3031 Loretto Rd",
    "sg:city":"Springfield",
    "sg:classifiers":[
        {
            "category":"Building & Trades",
            "subcategory":"Construction",
            "type":"Services"
        }
    ],
    "sg:phone":"+1 859 336 3337",
    "sg:postcode":"40069",
    "sg:province":"KY",
    "sg:tags":[
        "maker",
        "cabinet"
    ],
    "wof:name":"Smith's Cabinet Craft",
    "wof:placetype":"venue"
},
  "geometry": {"coordinates":[-85.310627,37.685551],"type":"Point"}
}