{
  "type": "Feature",
  "properties": {
    "addr:full":"1120 Deer Haven Ln Lexington KY 40509",
    "addr:housenumber":"1120",
    "addr:postcode":"40509",
    "addr:street":"Deer Haven Ln",
    "iso:country":"US",
    "sg:address":"1120 Deer Haven Ln",
    "sg:city":"Lexington",
    "sg:classifiers":[
        {
            "category":"Building & Trades",
            "subcategory":"Construction",
            "type":"Services"
        }
    ],
    "sg:phone":"+1 859 543 0903",
    "sg:postcode":"40509",
    "sg:province":"KY",
    "sg:tags":[
        "house"
    ],
    "wof:name":"Generations Construction LLC",
    "wof:placetype":"venue"
},
  "geometry": {"coordinates":[-84.397277,37.9974],"type":"Point"}
}