{
  "type": "Feature",
  "properties": {
    "addr:full":"115 N Locust Hill Dr Lexington KY 40509",
    "addr:housenumber":"115",
    "addr:postcode":"40509",
    "addr:street":"N Locust Hill Dr",
    "iso:country":"US",
    "sg:address":"115 N Locust Hill Dr",
    "sg:city":"Lexington",
    "sg:classifiers":[
        {
            "category":"Professional",
            "type":"Services"
        },
        {
            "category":"Restaurant",
            "type":"Food & Drink"
        },
        {
            "category":"Fast Food",
            "type":"Food & Drink"
        }
    ],
    "sg:phone":"+1 859 269 0999",
    "sg:postcode":"40509",
    "sg:province":"KY",
    "sg:tags":[
        "delivery",
        "take",
        "pizza"
    ],
    "sg:website":"http://www.littlecaesars.com",
    "wof:name":"Little Caesars Pizza",
    "wof:placetype":"venue"
},
  "geometry": {"coordinates":[-84.44499500000001,38.004851],"type":"Point"}
}