{
  "type": "Feature",
  "properties": {
    "iso:country":"US",
    "sg:address":"218 W Main St",
    "sg:city":"Vine Grove",
    "sg:classifiers":[
        {
            "category":"Retail",
            "subcategory":"Auto Repair",
            "type":"Services"
        }
    ],
    "sg:phone":"+1 270 877 5322",
    "sg:postcode":"40175",
    "sg:province":"KY",
    "sg:tags":[
        "body",
        "automobile",
        "painting"
    ],
    "wof:name":"Vine Grove Body Shop",
    "wof:placetype":"venue"
},
  "geometry": {"coordinates":[-85.983615,37.810501],"type":"Point"}
}