{
  "type": "Feature",
  "properties": {
    "addr:full":"5418 Sir Barton Dr Louisville KY 40272",
    "addr:housenumber":"5418",
    "addr:postcode":"40272",
    "addr:street":"Sir Barton Dr",
    "iso:country":"US",
    "sg:address":"5418 Sir Barton Dr",
    "sg:city":"Louisville",
    "sg:classifiers":[
        {
            "category":"Social Services",
            "type":"Services"
        }
    ],
    "sg:phone":"+1 502 995 0204",
    "sg:postcode":"40272",
    "sg:province":"KY",
    "sg:tags":[
        "disabled",
        "need",
        "product",
        "special",
        "developmentally"
    ],
    "wof:name":"Louisville Independent Case Management",
    "wof:placetype":"venue"
},
  "geometry": {"coordinates":[-85.867648,38.114088],"type":"Point"}
}