{
  "type": "Feature",
  "properties": {
    "addr:full":"244 Daniel Boone Dr Barbourville KY 40906",
    "addr:housenumber":"244",
    "addr:postcode":"40906",
    "addr:street":"Daniel Boone Dr",
    "iso:country":"US",
    "sg:address":"244 Daniel Boone Dr",
    "sg:city":"Barbourville",
    "sg:classifiers":[
        {
            "category":"Banks & Credit Unions",
            "subcategory":"Bank",
            "type":"Services"
        }
    ],
    "sg:phone":"+1 606 546 4994",
    "sg:postcode":"40906",
    "sg:province":"KY",
    "sg:tags":[
        "depository",
        "banking"
    ],
    "wof:name":"Check Express",
    "wof:placetype":"venue"
},
  "geometry": {"coordinates":[-83.887767,36.865585],"type":"Point"}
}