{
  "type": "Feature",
  "properties": {
    "iso:country":"US",
    "sg:address":"219 Lake St",
    "sg:city":"Richmond",
    "sg:classifiers":[
        {
            "category":"Retail",
            "subcategory":"Auto Repair",
            "type":"Services"
        }
    ],
    "sg:phone":"+1 859 624 2919",
    "sg:postcode":"40475",
    "sg:province":"KY",
    "sg:tags":[
        "wrecker"
    ],
    "wof:name":"Perry's Wrecker Svc",
    "wof:placetype":"venue"
},
  "geometry": {"coordinates":[-84.276679,37.741933],"type":"Point"}
}