{
  "type": "Feature",
  "properties": {
    "addr:full":"301 N Main St Harlan KY 40831",
    "addr:housenumber":"301",
    "addr:postcode":"40831",
    "addr:street":"N Main St",
    "iso:country":"US",
    "sg:address":"301 N Main St",
    "sg:city":"Harlan",
    "sg:classifiers":[
        {
            "category":"Organizations",
            "subcategory":"Non-profit Organization",
            "type":"Services"
        }
    ],
    "sg:phone":"+1 606 573 9853",
    "sg:postcode":"40831",
    "sg:province":"KY",
    "wof:name":"COAP Inc",
    "wof:placetype":"venue"
},
  "geometry": {"coordinates":[-83.32258400000001,36.849318],"type":"Point"}
}