{
  "type": "Feature",
  "properties": {
    "addr:full":"35 Kathryn Ave Florence KY 41042",
    "addr:housenumber":"35",
    "addr:postcode":"41042",
    "addr:street":"Kathryn Ave",
    "iso:country":"US",
    "sg:address":"35 Kathryn Ave",
    "sg:city":"Florence",
    "sg:classifiers":[
        {
            "category":"Retail",
            "subcategory":"Animal Services",
            "type":"Services"
        }
    ],
    "sg:phone":"+1 859 371 2023",
    "sg:postcode":"41042",
    "sg:province":"KY",
    "wof:name":"Jennifers Shear Image LLC",
    "wof:placetype":"venue"
},
  "geometry": {"coordinates":[-84.63833099999999,39.003777],"type":"Point"}
}