{
  "type": "Feature",
  "properties": {
    "addr:full":"101 Water Works Ave Cynthiana KY 41031",
    "addr:housenumber":"101",
    "addr:postcode":"41031",
    "addr:street":"Water Works Ave",
    "iso:country":"US",
    "sg:address":"101 Water Works Ave",
    "sg:city":"Cynthiana",
    "sg:classifiers":[
        {
            "category":"Restaurant",
            "type":"Food & Drink"
        }
    ],
    "sg:menulink":"http://www.allmenus.com/ky/cynthiana/83720-papa-johns-pizza/menu/",
    "sg:phone":"+1 859 235 9900",
    "sg:postcode":"41031",
    "sg:province":"KY",
    "sg:tags":[
        "american",
        "pizza"
    ],
    "wof:name":"Papa John's Pizza",
    "wof:placetype":"venue"
},
  "geometry": {"coordinates":[-84.298675,38.381069],"type":"Point"}
}