{
  "type": "Feature",
  "properties": {
    "addr:full":"2337 Bridge St Paducah KY 42003",
    "addr:housenumber":"2337",
    "addr:postcode":"42003",
    "addr:street":"Bridge St",
    "iso:country":"US",
    "sg:address":"2337 Bridge St",
    "sg:city":"Paducah",
    "sg:classifiers":[
        {
            "category":"Shopping",
            "subcategory":"Clothing, Apparel, & Fashions",
            "type":"Retail Goods"
        }
    ],
    "sg:phone":"+1 270 443 2194",
    "sg:postcode":"42003",
    "sg:province":"KY",
    "sg:tags":[
        "alteration"
    ],
    "wof:name":"Dee Alterations",
    "wof:placetype":"venue"
},
  "geometry": {"coordinates":[-88.579719,37.055528],"type":"Point"}
}