{
  "type": "Feature",
  "properties": {
    "addr:full":"407 Poplar St Murray KY 42071",
    "addr:housenumber":"407",
    "addr:postcode":"42071",
    "addr:street":"Poplar St",
    "iso:country":"US",
    "sg:address":"407 Poplar St",
    "sg:city":"Murray",
    "sg:classifiers":[
        {
            "category":"Government",
            "subcategory":"Police Station",
            "type":"Public Place"
        }
    ],
    "sg:phone":"+1 270 762 0312",
    "sg:postcode":"42071",
    "sg:province":"KY",
    "sg:tags":[
        "department"
    ],
    "wof:name":"Murray City Investigations",
    "wof:placetype":"venue"
},
  "geometry": {"coordinates":[-88.302925,36.608596],"type":"Point"}
}