{
  "type": "Feature",
  "properties": {
    "iso:country":"US",
    "sg:address":"1058 Wagner Ave",
    "sg:city":"Louisville",
    "sg:classifiers":[
        {
            "category":"Building & Trades",
            "subcategory":"Construction",
            "type":"Services"
        }
    ],
    "sg:phone":"+1 502 424 2116",
    "sg:postcode":"40217",
    "sg:province":"KY",
    "sg:tags":[
        "wallcoverings-installation",
        "wallpaper",
        "painting",
        "contractor"
    ],
    "wof:name":"Larry Foster Painting",
    "wof:placetype":"venue"
},
  "geometry": {"coordinates":[-85.73281,38.224156],"type":"Point"}
}