{
  "type": "Feature",
  "properties": {
    "iso:country":"US",
    "sg:address":"3375 State Hwy 491",
    "sg:city":"De Mossville",
    "sg:classifiers":[
        {
            "category":"Home & Garden",
            "subcategory":"Garden Supply",
            "type":"Retail Goods"
        }
    ],
    "sg:phone":"+1 859 472 2246",
    "sg:postcode":"41030",
    "sg:province":"KY",
    "sg:tags":[
        "lawn",
        "mower"
    ],
    "wof:name":"Bowen Farm Supply",
    "wof:placetype":"venue"
},
  "geometry": {"coordinates":[-84.53445600000001,38.772297],"type":"Point"}
}