{
  "type": "Feature",
  "properties": {
    "addr:full":"805 Campbellsville Rd Columbia KY 42728",
    "addr:housenumber":"805",
    "addr:postcode":"42728",
    "addr:street":"Campbellsville Rd",
    "iso:country":"US",
    "sg:address":"805 Campbellsville Rd",
    "sg:city":"Columbia",
    "sg:classifiers":[
        {
            "category":"Home & Garden",
            "subcategory":"Furniture",
            "type":"Retail Goods"
        }
    ],
    "sg:phone":"+1 270 384 5008",
    "sg:postcode":"42728",
    "sg:province":"KY",
    "wof:name":"Williams Furniture & Bedding",
    "wof:placetype":"venue"
},
  "geometry": {"coordinates":[-85.3019,37.111498],"type":"Point"}
}