{
  "type": "Feature",
  "properties": {
    "iso:country":"US",
    "sg:address":"599 Lower Concord Rd",
    "sg:city":"Carlisle",
    "sg:classifiers":[
        {
            "category":"Shopping",
            "subcategory":"Bicycles & Sporting Goods",
            "type":"Retail Goods"
        }
    ],
    "sg:phone":"+1 859 289 5410",
    "sg:postcode":"40311",
    "sg:province":"KY",
    "wof:name":"Reefline Scuba",
    "wof:placetype":"venue"
},
  "geometry": {"coordinates":[-84.017544,38.28227],"type":"Point"}
}