{
  "type": "Feature",
  "properties": {
    "iso:country":"US",
    "sg:address":"9204 Taylorsville Rd",
    "sg:city":"Louisville",
    "sg:classifiers":[
        {
            "category":"Personal",
            "subcategory":"Beauty Salon",
            "type":"Services"
        }
    ],
    "sg:phone":"+1 502 671 7270",
    "sg:postcode":"40299",
    "sg:province":"KY",
    "wof:name":"Hair Bangers",
    "wof:placetype":"venue"
},
  "geometry": {"coordinates":[-85.587363,38.212247],"type":"Point"}
}