{
  "type": "Feature",
  "properties": {
    "addr:full":"4647 Outer Loop Louisville KY 40219",
    "addr:housenumber":"4647",
    "addr:postcode":"40219",
    "addr:street":"Outer Loop",
    "iso:country":"US",
    "sg:address":"4647 Outer Loop",
    "sg:city":"Louisville",
    "sg:classifiers":[
        {
            "category":"Banks & Credit Unions",
            "subcategory":"Bank",
            "type":"Services"
        }
    ],
    "sg:phone":"+1 502 964 7210",
    "sg:postcode":"40219",
    "sg:province":"KY",
    "sg:tags":[
        "financing"
    ],
    "wof:name":"Wells Fargo Financial Accptnce",
    "wof:placetype":"venue"
},
  "geometry": {"coordinates":[-85.675526,38.138089],"type":"Point"}
}