{
  "type": "Feature",
  "properties": {
    "addr:full":"3910 Medley Rd Owensboro KY 42301",
    "addr:housenumber":"3910",
    "addr:postcode":"42301",
    "addr:street":"Medley Rd",
    "iso:country":"US",
    "sg:address":"3910 Medley Rd",
    "sg:city":"Owensboro",
    "sg:classifiers":[
        {
            "category":"Social Services",
            "type":"Services"
        }
    ],
    "sg:phone":"+1 270 683 1430",
    "sg:postcode":"42301",
    "sg:province":"KY",
    "sg:tags":[
        "organization",
        "welfare"
    ],
    "wof:name":"Junior League Of Owensboro",
    "wof:placetype":"venue"
},
  "geometry": {"coordinates":[-87.166147,37.791668],"type":"Point"}
}