{
  "type": "Feature",
  "properties": {
    "iso:country":"US",
    "sg:address":"400 Campbellsville Byp",
    "sg:city":"Campbellsville",
    "sg:classifiers":[
        {
            "category":"Restaurant",
            "type":"Food & Drink"
        }
    ],
    "sg:phone":"+1 270 789 3910",
    "sg:postcode":"42718",
    "sg:province":"KY",
    "sg:tags":[
        "eating"
    ],
    "wof:name":"Little Caesars",
    "wof:placetype":"venue"
},
  "geometry": {"coordinates":[-85.372652,37.347059],"type":"Point"}
}