{
  "type": "Feature",
  "properties": {
    "iso:country":"US",
    "sg:address":"9405 Mill Brook Rd",
    "sg:city":"Louisville",
    "sg:classifiers":[
        {
            "category":"Real Estate",
            "subcategory":"Real Estate Agent",
            "type":"Services"
        }
    ],
    "sg:phone":"+1 502 228 4004",
    "sg:postcode":"40223",
    "sg:province":"KY",
    "wof:name":"Re/Max Associates",
    "wof:placetype":"venue"
},
  "geometry": {"coordinates":[-85.57576,38.265053],"type":"Point"}
}