{
  "type": "Feature",
  "properties": {
    "addr:full":"2301 River Rd Ste 302 Louisville KY 40206",
    "addr:housenumber":"2301",
    "addr:postcode":"40206",
    "addr:street":"River Rd Ste 302",
    "iso:country":"US",
    "sg:address":"2301 River Rd Ste 302",
    "sg:city":"Louisville",
    "sg:classifiers":[
        {
            "category":"Health Services",
            "subcategory":"Doctor",
            "type":"Services"
        },
        {
            "category":"Health Services",
            "subcategory":"Hospital",
            "type":"Services"
        }
    ],
    "sg:phone":"+1 502 426 9680",
    "sg:postcode":"40206",
    "sg:province":"KY",
    "sg:tags":[
        "consultant",
        "medical",
        "practice",
        "nursing",
        "home"
    ],
    "sg:website":"http://www.phdelivery.com",
    "wof:name":"Precision Healthcare Delivery",
    "wof:placetype":"venue"
},
  "geometry": {"coordinates":[-85.708603,38.271721],"type":"Point"}
}