{
  "type": "Feature",
  "properties": {
    "addr:full":"12414 Lagrange Rd Louisville KY 40245",
    "addr:housenumber":"12414",
    "addr:postcode":"40245",
    "addr:street":"Lagrange Rd",
    "iso:country":"US",
    "sg:address":"12414 Lagrange Rd",
    "sg:city":"Louisville",
    "sg:classifiers":[
        {
            "category":"Restaurant",
            "type":"Food & Drink"
        }
    ],
    "sg:menulink":"http://www.allmenus.com/ky/jefferson-northeast/186905-mcdonalds/menu/",
    "sg:phone":"+1 502 241 0930",
    "sg:postcode":"40245",
    "sg:province":"KY",
    "sg:tags":[
        "burger",
        "american"
    ],
    "wof:name":"McDonald's",
    "wof:placetype":"venue"
},
  "geometry": {"coordinates":[-85.51181,38.290025],"type":"Point"}
}