{
  "type": "Feature",
  "properties": {
    "addr:full":"962 Bloomfield Rd Bardstown KY 40004",
    "addr:housenumber":"962",
    "addr:postcode":"40004",
    "addr:street":"Bloomfield Rd",
    "iso:country":"US",
    "sg:address":"962 Bloomfield Rd",
    "sg:city":"Bardstown",
    "sg:classifiers":[
        {
            "category":"Wholesale",
            "subcategory":"Machinery & Supplies",
            "type":"Manufacturing & Wholesale Goods"
        }
    ],
    "sg:phone":"+1 502 348 9077",
    "sg:postcode":"40004",
    "sg:province":"KY",
    "sg:tags":[
        "farm",
        "equipment"
    ],
    "wof:name":"J & G Equipment",
    "wof:placetype":"venue"
},
  "geometry": {"coordinates":[-85.438264,37.82507],"type":"Point"}
}