{
  "type": "Feature",
  "properties": {
    "iso:country":"US",
    "sg:address":"2415 Greenville Rd",
    "sg:city":"Hopkinsville",
    "sg:classifiers":[
        {
            "category":"Food & Beverages",
            "subcategory":"Groceries & Convenience Stores",
            "type":"Retail Goods"
        }
    ],
    "sg:phone":"+1 270 886 4628",
    "sg:postcode":"42240",
    "sg:province":"KY",
    "wof:name":"Dyno Mart",
    "wof:placetype":"venue"
},
  "geometry": {"coordinates":[-87.461737,36.877424],"type":"Point"}
}