{
  "type": "Feature",
  "properties": {
    "iso:country":"US",
    "sg:address":"589 Pine Creek Rd",
    "sg:city":"Shepherdsville",
    "sg:classifiers":[
        {
            "category":"Shopping",
            "subcategory":"Bicycles & Sporting Goods",
            "type":"Retail Goods"
        }
    ],
    "sg:phone":"+1 502 543 9809",
    "sg:postcode":"40165",
    "sg:province":"KY",
    "wof:name":"JJ Archery",
    "wof:placetype":"venue"
},
  "geometry": {"coordinates":[-85.620329,37.97627],"type":"Point"}
}