{
  "type": "Feature",
  "properties": {
    "iso:country":"US",
    "sg:address":"2391 New Haven Rd",
    "sg:city":"Bardstown",
    "sg:classifiers":[
        {
            "category":"Government",
            "subcategory":"Office",
            "type":"Public Place"
        }
    ],
    "sg:phone":"+1 502 348 4334",
    "sg:postcode":"40004",
    "sg:province":"KY",
    "sg:tags":[
        "county"
    ],
    "wof:name":"Nelson County Fairgrounds",
    "wof:placetype":"venue"
},
  "geometry": {"coordinates":[-85.49363099999999,37.780548],"type":"Point"}
}