{
  "type": "Feature",
  "properties": {
    "iso:country":"US",
    "sg:address":"3480 Richmond Rd",
    "sg:city":"Lexington",
    "sg:classifiers":[
        {
            "category":"Retail",
            "subcategory":"Laundry & Dry Cleaning",
            "type":"Services"
        }
    ],
    "sg:phone":"+1 859 543 0088",
    "sg:postcode":"40509",
    "sg:province":"KY",
    "sg:tags":[
        "cleaners"
    ],
    "wof:name":"Newport Cleaners 2",
    "wof:placetype":"venue"
},
  "geometry": {"coordinates":[-84.44174700000001,37.997423],"type":"Point"}
}