{
  "type": "Feature",
  "properties": {
    "iso:country":"US",
    "sg:address":"836 S 6th St",
    "sg:city":"Louisville",
    "sg:classifiers":[
        {
            "category":"Wholesale",
            "subcategory":"Machinery & Supplies",
            "type":"Manufacturing & Wholesale Goods"
        }
    ],
    "sg:phone":"+1 502 584 2223",
    "sg:postcode":"40203",
    "sg:province":"KY",
    "sg:tags":[
        "equipment",
        "material",
        "handling"
    ],
    "wof:name":"Kelley Dock & Equipment",
    "wof:placetype":"venue"
},
  "geometry": {"coordinates":[-85.762136,38.243804],"type":"Point"}
}