{
  "type": "Feature",
  "properties": {
    "iso:country":"US",
    "sg:address":"5901 Bluffington Ct",
    "sg:city":"Louisville",
    "sg:classifiers":[
        {
            "category":"Building & Trades",
            "subcategory":"Electrical",
            "type":"Services"
        }
    ],
    "sg:phone":"+1 502 491 7450",
    "sg:postcode":"40291",
    "sg:province":"KY",
    "sg:tags":[
        "electric",
        "contractor"
    ],
    "wof:name":"Efficient Electric Co",
    "wof:placetype":"venue"
},
  "geometry": {"coordinates":[-85.623447,38.163222],"type":"Point"}
}