{
  "type": "Feature",
  "properties": {
    "iso:country":"US",
    "sg:address":"215 E 21st St",
    "sg:city":"Hopkinsville",
    "sg:classifiers":[
        {
            "category":"Insurance",
            "subcategory":"Hazard Insurance",
            "type":"Services"
        }
    ],
    "sg:phone":"+1 270 886 5434",
    "sg:postcode":"42240",
    "sg:province":"KY",
    "sg:website":"http://www.kyfbins.com",
    "wof:name":"Kentucky Farm Bureau Insurance Companies",
    "wof:placetype":"venue"
},
  "geometry": {"coordinates":[-87.49263000000001,36.85527],"type":"Point"}
}