{
  "type": "Feature",
  "properties": {
    "iso:country":"US",
    "sg:address":"7144 State Hwy 88",
    "sg:city":"Greensburg",
    "sg:classifiers":[
        {
            "category":"Organizations",
            "subcategory":"Religious Organization",
            "type":"Services"
        }
    ],
    "sg:phone":"+1 270 932 4032",
    "sg:postcode":"42743",
    "sg:province":"KY",
    "sg:tags":[
        "clergy"
    ],
    "wof:name":"Jerry Judd",
    "wof:placetype":"venue"
},
  "geometry": {"coordinates":[-85.622829,37.238744],"type":"Point"}
}