{
  "type": "Feature",
  "properties": {
    "iso:country":"US",
    "sg:address":"15 E 3rd St",
    "sg:city":"Maysville",
    "sg:classifiers":[
        {
            "category":"Health Services",
            "subcategory":"Optometrist",
            "type":"Services"
        }
    ],
    "sg:phone":"+1 606 564 3650",
    "sg:postcode":"41056",
    "sg:province":"KY",
    "wof:name":"Sherman & Taylor",
    "wof:placetype":"venue"
},
  "geometry": {"coordinates":[-83.765046,38.646829],"type":"Point"}
}