{
  "type": "Feature",
  "properties": {
    "iso:country":"US",
    "sg:address":"123 Oak Wood Ln",
    "sg:city":"Leitchfield",
    "sg:classifiers":[
        {
            "category":"Retail",
            "subcategory":"Veterinary Services",
            "type":"Services"
        }
    ],
    "sg:phone":"+1 270 230 8895",
    "sg:postcode":"42754",
    "sg:province":"KY",
    "sg:tags":[
        "veterinarian"
    ],
    "wof:name":"Twin Lakes Animal Hospital",
    "wof:placetype":"venue"
},
  "geometry": {"coordinates":[-86.25129800000001,37.487794],"type":"Point"}
}