{
  "type": "Feature",
  "properties": {
    "iso:country":"US",
    "sg:address":"3181 Beaumont Centre Cir",
    "sg:city":"Lexington",
    "sg:classifiers":[
        {
            "category":"Restaurant",
            "type":"Food & Drink"
        }
    ],
    "sg:phone":"+1 859 223 8788",
    "sg:postcode":"40513",
    "sg:province":"KY",
    "wof:name":"Peking Bistro Chinese Rstrnt",
    "wof:placetype":"venue"
},
  "geometry": {"coordinates":[-84.55684100000001,38.020679],"type":"Point"}
}