{
  "type": "Feature",
  "properties": {
    "iso:country":"US",
    "sg:address":"720 Patton Rd",
    "sg:city":"Bowling Green",
    "sg:classifiers":[
        {
            "category":"Professional",
            "subcategory":"Business Services",
            "type":"Services"
        }
    ],
    "sg:phone":"+1 270 320 8862",
    "sg:postcode":"42141",
    "sg:province":"KY",
    "wof:name":"Hamilton Technologies LLC",
    "wof:placetype":"venue"
},
  "geometry": {"coordinates":[-85.864673,36.931422],"type":"Point"}
}