{
  "type": "Feature",
  "properties": {
    "addr:full":"3135 Dixie Hwy Erlanger KY 41018",
    "addr:housenumber":"3135",
    "addr:postcode":"41018",
    "addr:street":"Dixie Hwy",
    "iso:country":"US",
    "sg:address":"3135 Dixie Hwy",
    "sg:city":"Erlanger",
    "sg:classifiers":[
        {
            "category":"Government",
            "subcategory":"Post Office",
            "type":"Public Place"
        }
    ],
    "sg:phone":"+1 859 426 7071",
    "sg:postcode":"41018",
    "sg:province":"KY",
    "wof:name":"US Post Office",
    "wof:placetype":"venue"
},
  "geometry": {"coordinates":[-84.590193,39.020659],"type":"Point"}
}