{
  "type": "Feature",
  "properties": {
    "addr:full":"949 Lincoln Park Rd Springfield KY 40069",
    "addr:housenumber":"949",
    "addr:postcode":"40069",
    "addr:street":"Lincoln Park Rd",
    "iso:country":"US",
    "sg:address":"949 Lincoln Park Rd",
    "sg:city":"Springfield",
    "sg:classifiers":[
        {
            "category":"Restaurant",
            "type":"Food & Drink"
        }
    ],
    "sg:phone":"+1 859 336 3611",
    "sg:postcode":"40069",
    "sg:province":"KY",
    "wof:name":"Pizza Hut",
    "wof:placetype":"venue"
},
  "geometry": {"coordinates":[-85.22071200000001,37.69724],"type":"Point"}
}