{
  "type": "Feature",
  "properties": {
    "addr:full":"850 US Hwy 231 Beaver Dam KY 42320",
    "addr:housenumber":"850",
    "addr:postcode":"42320",
    "addr:street":"Us Hwy 231",
    "iso:country":"US",
    "sg:address":"850 US Hwy 231",
    "sg:city":"Beaver Dam",
    "sg:classifiers":[
        {
            "category":"Retail",
            "subcategory":"Repair Shop",
            "type":"Services"
        }
    ],
    "sg:phone":"+1 270 274 7115",
    "sg:postcode":"42320",
    "sg:province":"KY",
    "sg:tags":[
        "textile"
    ],
    "wof:name":"American Nonwoven Corp",
    "wof:placetype":"venue"
},
  "geometry": {"coordinates":[-86.87646599999999,37.410344],"type":"Point"}
}