{
  "type": "Feature",
  "properties": {
    "iso:country":"US",
    "sg:address":"3401 Park Ave",
    "sg:city":"Paducah",
    "sg:classifiers":[
        {
            "category":"Shopping",
            "subcategory":"Music",
            "type":"Retail Goods"
        }
    ],
    "sg:phone":"+1 270 444 3927",
    "sg:postcode":"42001",
    "sg:province":"KY",
    "sg:tags":[
        "compact",
        "record",
        "disc",
        "tape"
    ],
    "wof:name":"P Mac Music",
    "wof:placetype":"venue"
},
  "geometry": {"coordinates":[-88.656938,37.083814],"type":"Point"}
}