{
  "type": "Feature",
  "properties": {
    "addr:full":"111 W Broadway St Mayfield KY 42066",
    "addr:housenumber":"111",
    "addr:postcode":"42066",
    "addr:street":"W Broadway St",
    "iso:country":"US",
    "sg:address":"111 W Broadway St",
    "sg:city":"Mayfield",
    "sg:classifiers":[
        {
            "category":"Insurance",
            "subcategory":"Insurance Agent",
            "type":"Services"
        }
    ],
    "sg:phone":"+1 270 247 4852",
    "sg:postcode":"42066",
    "sg:province":"KY",
    "wof:name":"Peel & Holland Inc",
    "wof:placetype":"venue"
},
  "geometry": {"coordinates":[-88.63694599999999,36.741721],"type":"Point"}
}