{
  "type": "Feature",
  "properties": {
    "addr:full":"2735 Fort Campbell Blvd Hopkinsville KY 42240",
    "addr:housenumber":"2735",
    "addr:postcode":"42240",
    "addr:street":"Fort Campbell Blvd",
    "iso:country":"US",
    "sg:address":"2735 Fort Campbell Blvd",
    "sg:city":"Hopkinsville",
    "sg:classifiers":[
        {
            "category":"Shopping",
            "subcategory":"Used Merchandise",
            "type":"Retail Goods"
        }
    ],
    "sg:phone":"+1 270 885 7028",
    "sg:postcode":"42240",
    "sg:province":"KY",
    "sg:tags":[
        "book",
        "rare",
        "dealer"
    ],
    "wof:name":"Book Rack",
    "wof:placetype":"venue"
},
  "geometry": {"coordinates":[-87.48208,36.840246],"type":"Point"}
}