{
  "type": "Feature",
  "properties": {
    "iso:country":"US",
    "sg:address":"406 Red Fern Rd",
    "sg:city":"Campbellsville",
    "sg:classifiers":[
        {
            "category":"Manufacturing",
            "subcategory":"Wood Products",
            "type":"Manufacturing & Wholesale Goods"
        }
    ],
    "sg:phone":"+1 270 465 8868",
    "sg:postcode":"42718",
    "sg:province":"KY",
    "sg:tags":[
        "mfg"
    ],
    "wof:name":"Sawdust Factory",
    "wof:placetype":"venue"
},
  "geometry": {"coordinates":[-85.341916,37.387657],"type":"Point"}
}