{
  "type": "Feature",
  "properties": {
    "addr:full":"49 McWhorter Rd London KY 40741",
    "addr:housenumber":"49",
    "addr:postcode":"40741",
    "addr:street":"Mcwhorter Rd",
    "iso:country":"US",
    "sg:address":"49 McWhorter Rd",
    "sg:city":"London",
    "sg:classifiers":[
        {
            "category":"Food & Beverages",
            "subcategory":"Groceries & Convenience Stores",
            "type":"Retail Goods"
        }
    ],
    "sg:phone":"+1 606 864 7803",
    "sg:postcode":"40741",
    "sg:province":"KY",
    "wof:name":"Quick Stop",
    "wof:placetype":"venue"
},
  "geometry": {"coordinates":[-84.064058,37.139685],"type":"Point"}
}