{
  "type": "Feature",
  "properties": {
    "addr:full":"880 Sparta Ct Lexington KY 40504",
    "addr:housenumber":"880",
    "addr:postcode":"40504",
    "addr:street":"Sparta Ct",
    "iso:country":"US",
    "sg:address":"880 Sparta Ct",
    "sg:city":"Lexington",
    "sg:classifiers":[
        {
            "category":"Professional",
            "subcategory":"Accounting & Tax Preparation",
            "type":"Services"
        }
    ],
    "sg:phone":"+1 859 225 8184",
    "sg:postcode":"40504",
    "sg:province":"KY",
    "sg:tags":[
        "return"
    ],
    "wof:name":"Compro Tax",
    "wof:placetype":"venue"
},
  "geometry": {"coordinates":[-84.522496,38.048908],"type":"Point"}
}