{
  "type": "Feature",
  "properties": {
    "iso:country":"US",
    "sg:address":"332 Fairview Dr",
    "sg:city":"Paducah",
    "sg:classifiers":[
        {
            "category":"Real Estate",
            "subcategory":"Real Estate Agent",
            "type":"Services"
        }
    ],
    "sg:phone":"+1 270 554 8291",
    "sg:postcode":"42001",
    "sg:province":"KY",
    "sg:tags":[
        "inspection"
    ],
    "wof:name":"Ameri Spec Home Inspection Svc",
    "wof:placetype":"venue"
},
  "geometry": {"coordinates":[-88.68836400000001,37.026441],"type":"Point"}
}