{
  "type": "Feature",
  "properties": {
    "addr:full":"2700 Gast Blvd Louisville KY 40205",
    "addr:housenumber":"2700",
    "addr:postcode":"40205",
    "addr:street":"Gast Blvd",
    "iso:country":"US",
    "sg:address":"2700 Gast Blvd",
    "sg:city":"Louisville",
    "sg:classifiers":[
        {
            "category":"Place Of Worship",
            "type":"Public Place"
        },
        {
            "category":"Airline",
            "type":"Transportation"
        },
        {
            "category":"Landmark",
            "subcategory":"Tourist Attraction",
            "type":"Public Place"
        },
        {
            "category":"Landmark",
            "subcategory":"Tourist Information",
            "type":"Public Place"
        }
    ],
    "sg:phone":"+1 502 836 5252",
    "sg:postcode":"40205",
    "sg:province":"KY",
    "sg:tags":[
        "leasing",
        "tours-operators",
        "aircraft-charter",
        "promoter",
        "tour",
        "interest",
        "rental",
        "sightseeing"
    ],
    "sg:website":"http://www.classicbiplanetours.com",
    "wof:name":"Classic Biplane Tours",
    "wof:placetype":"venue"
},
  "geometry": {"coordinates":[-85.65770000000001,38.227982],"type":"Point"}
}