{
  "type": "Feature",
  "properties": {
    "iso:country":"US",
    "sg:address":"1833 River Rd",
    "sg:city":"Louisville",
    "sg:classifiers":[
        {
            "category":"Wholesale",
            "subcategory":"Construction Materials",
            "type":"Manufacturing & Wholesale Goods"
        }
    ],
    "sg:phone":"+1 502 584 0158",
    "sg:postcode":"40206",
    "sg:province":"KY",
    "sg:tags":[
        "sand",
        "gravel"
    ],
    "sg:website":"www.nugentsand.com",
    "wof:name":"Nugent Sand Co",
    "wof:placetype":"venue"
},
  "geometry": {"coordinates":[-85.715608,38.268352],"type":"Point"}
}