{
  "type": "Feature",
  "properties": {
    "iso:country":"US",
    "sg:address":"411 N Main St",
    "sg:city":"Nicholasville",
    "sg:classifiers":[
        {
            "category":"Shopping",
            "type":"Retail Goods"
        }
    ],
    "sg:phone":"+1 859 885 6485",
    "sg:postcode":"40356",
    "sg:province":"KY",
    "sg:tags":[
        "picture",
        "frame"
    ],
    "wof:name":"Frames By James",
    "wof:placetype":"venue"
},
  "geometry": {"coordinates":[-84.571293,37.884513],"type":"Point"}
}