{
  "type": "Feature",
  "properties": {
    "iso:country":"US",
    "sg:address":"7681 Dixie Hwy",
    "sg:city":"Louisville",
    "sg:classifiers":[
        {
            "category":"Retail",
            "subcategory":"Auto Repair",
            "type":"Services"
        }
    ],
    "sg:phone":"+1 502 935 1415",
    "sg:postcode":"40258",
    "sg:province":"KY",
    "sg:tags":[
        "automobile",
        "customizing"
    ],
    "wof:name":"Auto Customizing",
    "wof:placetype":"venue"
},
  "geometry": {"coordinates":[-85.841954,38.13936],"type":"Point"}
}