{
  "type": "Feature",
  "properties": {
    "addr:full":"1080 S Broadway Lexington KY 40504",
    "addr:housenumber":"1080",
    "addr:postcode":"40504",
    "addr:street":"S Broadway",
    "iso:country":"US",
    "sg:address":"1080 S Broadway",
    "sg:city":"Lexington",
    "sg:classifiers":[
        {
            "category":"Restaurant",
            "type":"Food & Drink"
        }
    ],
    "sg:menulink":"http://www.allmenus.com/ky/fayette/90086-penn-station/menu/",
    "sg:phone":"+1 859 254 7366",
    "sg:postcode":"40504",
    "sg:province":"KY",
    "sg:tags":[
        "wrap",
        "american",
        "sandwich"
    ],
    "wof:name":"Penn Station",
    "wof:placetype":"venue"
},
  "geometry": {"coordinates":[-84.51731700000001,38.036711],"type":"Point"}
}