{
  "type": "Feature",
  "properties": {
    "iso:country":"US",
    "sg:address":"119 Needmore Rd",
    "sg:city":"Benton",
    "sg:classifiers":[
        {
            "category":"Building & Trades",
            "subcategory":"Construction",
            "type":"Services"
        }
    ],
    "sg:phone":"+1 270 527 8303",
    "sg:postcode":"42029",
    "sg:province":"KY",
    "sg:tags":[
        "dry wall",
        "contractor"
    ],
    "wof:name":"Russell Drywall",
    "wof:placetype":"venue"
},
  "geometry": {"coordinates":[-88.378338,36.967958],"type":"Point"}
}