{
  "type": "Feature",
  "properties": {
    "iso:country":"US",
    "sg:address":"2153 Hovious Ridge Rd",
    "sg:city":"Casey Creek",
    "sg:classifiers":[
        {
            "category":"Manufacturing",
            "subcategory":"Furniture",
            "type":"Manufacturing & Wholesale Goods"
        }
    ],
    "sg:phone":"+1 270 465 8060",
    "sg:postcode":"42728",
    "sg:province":"KY",
    "wof:name":"Gary Humphress & Sons",
    "wof:placetype":"venue"
},
  "geometry": {"coordinates":[-85.217671,37.252841],"type":"Point"}
}