{
  "type": "Feature",
  "properties": {
    "iso:country":"US",
    "sg:address":"4241 Irish Bottom Rd",
    "sg:city":"Burkesville",
    "sg:classifiers":[
        {
            "category":"Professional",
            "subcategory":"Business Services",
            "type":"Services"
        }
    ],
    "sg:phone":"+1 270 433 7553",
    "sg:postcode":"42717",
    "sg:province":"KY",
    "wof:name":"Randall Morgan",
    "wof:placetype":"venue"
},
  "geometry": {"coordinates":[-85.249326,36.838875],"type":"Point"}
}