{
  "type": "Feature",
  "properties": {
    "addr:full":"203 N Main St Marion KY 42064",
    "addr:housenumber":"203",
    "addr:postcode":"42064",
    "addr:street":"N Main St",
    "iso:country":"US",
    "sg:address":"203 N Main St",
    "sg:city":"Marion",
    "sg:classifiers":[
        {
            "category":"Banks & Credit Unions",
            "subcategory":"Bank",
            "type":"Services"
        }
    ],
    "sg:phone":"+1 270 965 3106",
    "sg:postcode":"42064",
    "sg:province":"KY",
    "sg:tags":[
        "state",
        "commercial"
    ],
    "wof:name":"Farmers Bank & Trust Co",
    "wof:placetype":"venue"
},
  "geometry": {"coordinates":[-88.081034,37.33537],"type":"Point"}
}