{
  "type": "Feature",
  "properties": {
    "addr:full":"550 Waterworks Rd Fort Thomas KY 41075",
    "addr:housenumber":"550",
    "addr:postcode":"41075",
    "addr:street":"Waterworks Rd",
    "iso:country":"US",
    "sg:address":"550 Waterworks Rd",
    "sg:city":"Fort Thomas",
    "sg:classifiers":[
        {
            "category":"Professional",
            "subcategory":"Computer Services",
            "type":"Services"
        }
    ],
    "sg:phone":"+1 859 441 8042",
    "sg:postcode":"41075",
    "sg:province":"KY",
    "sg:tags":[
        "repair"
    ],
    "wof:name":"Computer Repair Svc",
    "wof:placetype":"venue"
},
  "geometry": {"coordinates":[-84.459152,39.089481],"type":"Point"}
}