{
  "type": "Feature",
  "properties": {
    "addr:full":"438 Bellechase Ln Nicholasville KY 40356",
    "addr:housenumber":"438",
    "addr:postcode":"40356",
    "addr:street":"Bellechase Ln",
    "iso:country":"US",
    "sg:address":"438 Bellechase Ln",
    "sg:city":"Nicholasville",
    "sg:classifiers":[
        {
            "category":"Wholesale",
            "subcategory":"Hardware",
            "type":"Manufacturing & Wholesale Goods"
        }
    ],
    "sg:phone":"+1 859 885 5541",
    "sg:postcode":"40356",
    "sg:province":"KY",
    "sg:tags":[
        "beverage",
        "dispensing"
    ],
    "wof:name":"Beverage Systems Of Ky Inc",
    "wof:placetype":"venue"
},
  "geometry": {"coordinates":[-84.585244,37.87039],"type":"Point"}
}