{
  "type": "Feature",
  "properties": {
    "addr:full":"3332 Gilmore Industrial Blvd Louisville KY 40213",
    "addr:housenumber":"3332",
    "addr:postcode":"40213",
    "addr:street":"Gilmore Industrial Blvd",
    "iso:country":"US",
    "sg:address":"3332 Gilmore Industrial Blvd",
    "sg:city":"Louisville",
    "sg:classifiers":[
        {
            "category":"Professional",
            "type":"Services"
        }
    ],
    "sg:phone":"+1 502 968 8900",
    "sg:postcode":"40213",
    "sg:province":"KY",
    "sg:tags":[
        "establishment"
    ],
    "wof:name":"I Tra",
    "wof:placetype":"venue"
},
  "geometry": {"coordinates":[-85.70195,38.177382],"type":"Point"}
}