{
  "type": "Feature",
  "properties": {
    "iso:country":"US",
    "sg:address":"250 Campsie Pl",
    "sg:city":"Lexington",
    "sg:classifiers":[
        {
            "category":"Professional",
            "subcategory":"Management & Consulting",
            "type":"Services"
        }
    ],
    "sg:phone":"+1 859 231 8308",
    "sg:postcode":"40508",
    "sg:province":"KY",
    "sg:tags":[
        "consultant",
        "business"
    ],
    "wof:name":"Roberts & Kay Inc",
    "wof:placetype":"venue"
},
  "geometry": {"coordinates":[-84.488826,38.048351],"type":"Point"}
}