{
  "type": "Feature",
  "properties": {
    "iso:country":"US",
    "sg:address":"419 Moraja Ln",
    "sg:city":"Springfield",
    "sg:classifiers":[
        {
            "category":"Real Estate",
            "subcategory":"Real Estate Operator",
            "type":"Services"
        }
    ],
    "sg:phone":"+1 859 336 0868",
    "sg:postcode":"40069",
    "sg:province":"KY",
    "sg:tags":[
        "property",
        "lessor"
    ],
    "wof:name":"Ralph Hamilton",
    "wof:placetype":"venue"
},
  "geometry": {"coordinates":[-85.254267,37.641677],"type":"Point"}
}