{
  "type": "Feature",
  "properties": {
    "iso:country":"US",
    "sg:address":"252 Pearce Industrial Rd",
    "sg:city":"Shelbyville",
    "sg:classifiers":[
        {
            "category":"Manufacturing",
            "subcategory":"Paper Products",
            "type":"Manufacturing & Wholesale Goods"
        }
    ],
    "sg:phone":"+1 502 633 1081",
    "sg:postcode":"40065",
    "sg:province":"KY",
    "sg:tags":[
        "envelope"
    ],
    "sg:website":"www.atlanticenvelope.com",
    "wof:name":"Atlantic Envelope Co",
    "wof:placetype":"venue"
},
  "geometry": {"coordinates":[-85.260739,38.202875],"type":"Point"}
}