{
  "type": "Feature",
  "properties": {
    "addr:full":"245 Main St Sadieville KY 40370",
    "addr:housenumber":"245",
    "addr:postcode":"40370",
    "addr:street":"Main St",
    "iso:country":"US",
    "sg:address":"245 Main St",
    "sg:city":"Sadieville",
    "sg:classifiers":[
        {
            "category":"Organizations",
            "subcategory":"Religious Organization",
            "type":"Services"
        }
    ],
    "sg:phone":"+1 502 857 4404",
    "sg:postcode":"40370",
    "sg:province":"KY",
    "sg:tags":[
        "church"
    ],
    "wof:name":"Sadieville Christian Church",
    "wof:placetype":"venue"
},
  "geometry": {"coordinates":[-84.535782,38.39243],"type":"Point"}
}