{
  "type": "Feature",
  "properties": {
    "iso:country":"US",
    "sg:address":"404 S 1st St",
    "sg:city":"Louisville",
    "sg:classifiers":[
        {
            "category":"Shopping",
            "subcategory":"Beauty & Cosmetics",
            "type":"Retail Goods"
        }
    ],
    "sg:phone":"+1 502 585 4824",
    "sg:postcode":"40202",
    "sg:province":"KY",
    "sg:tags":[
        "perfume",
        "salons-equipment",
        "supply"
    ],
    "wof:name":"Physicians Preferred Cosmetics",
    "wof:placetype":"venue"
},
  "geometry": {"coordinates":[-85.752286,38.251993],"type":"Point"}
}