{
  "type": "Feature",
  "properties": {
    "addr:full":"6511 Glenridge Park Pl Louisville KY 40222",
    "addr:housenumber":"6511",
    "addr:postcode":"40222",
    "addr:street":"Glenridge Park Pl",
    "iso:country":"US",
    "sg:address":"6511 Glenridge Park Pl",
    "sg:city":"Louisville",
    "sg:classifiers":[
        {
            "category":"Professional",
            "subcategory":"Lawyer & Legal Services",
            "type":"Services"
        }
    ],
    "sg:phone":"+1 502 429 9790",
    "sg:postcode":"40222",
    "sg:province":"KY",
    "sg:tags":[
        "attorney",
        "practice",
        "real estate"
    ],
    "sg:website":"http://www.hebelhornung.com",
    "wof:name":"Hebel & Hornung Psc",
    "wof:placetype":"venue"
},
  "geometry": {"coordinates":[-85.629434,38.285239],"type":"Point"}
}