{
  "type": "Feature",
  "properties": {
    "iso:country":"US",
    "sg:address":"1210 Wilkinson Blvd",
    "sg:city":"Frankfort",
    "sg:classifiers":[
        {
            "category":"Government",
            "subcategory":"Post Office",
            "type":"Public Place"
        }
    ],
    "sg:phone":"+1 502 223 3447",
    "sg:postcode":"40601",
    "sg:province":"KY",
    "wof:name":"US Post Office",
    "wof:placetype":"venue"
},
  "geometry": {"coordinates":[-84.86175900000001,38.217152],"type":"Point"}
}