{
  "type": "Feature",
  "properties": {
    "addr:full":"827 E Broadway St Madisonville KY 42431",
    "addr:housenumber":"827",
    "addr:postcode":"42431",
    "addr:street":"E Broadway St",
    "iso:country":"US",
    "sg:address":"827 E Broadway St",
    "sg:city":"Madisonville",
    "sg:classifiers":[
        {
            "category":"Retail",
            "subcategory":"Repair Shop",
            "type":"Services"
        }
    ],
    "sg:phone":"+1 270 825 0638",
    "sg:postcode":"42431",
    "sg:province":"KY",
    "sg:tags":[
        "related"
    ],
    "wof:name":"Bill's Repairs",
    "wof:placetype":"venue"
},
  "geometry": {"coordinates":[-87.482917,37.323878],"type":"Point"}
}