{
  "type": "Feature",
  "properties": {
    "iso:country":"US",
    "sg:address":"8607 Charing Cross Rd",
    "sg:city":"Louisville",
    "sg:classifiers":[
        {
            "category":"Professional",
            "subcategory":"Business Services",
            "type":"Services"
        }
    ],
    "sg:phone":"+1 502 423 7194",
    "sg:postcode":"40222",
    "sg:province":"KY",
    "wof:name":"James Nicholas Steinhauer (not",
    "wof:placetype":"venue"
},
  "geometry": {"coordinates":[-85.59381399999999,38.25064],"type":"Point"}
}