{
  "type": "Feature",
  "properties": {
    "iso:country":"US",
    "sg:address":"720 Steeplechase Way",
    "sg:city":"Bowling Green",
    "sg:classifiers":[
        {
            "category":"Real Estate",
            "subcategory":"Real Estate Agent",
            "type":"Services"
        }
    ],
    "sg:phone":"+1 270 782 1730",
    "sg:postcode":"42103",
    "sg:province":"KY",
    "sg:tags":[
        "appraiser"
    ],
    "wof:name":"Cooper Appraisals",
    "wof:placetype":"venue"
},
  "geometry": {"coordinates":[-86.401436,36.976022],"type":"Point"}
}