{
  "type": "Feature",
  "properties": {
    "iso:country":"US",
    "sg:address":"201 County Exn",
    "sg:city":"London",
    "sg:classifiers":[
        {
            "category":"Professional",
            "type":"Services"
        }
    ],
    "sg:phone":"+1 606 862 9662",
    "sg:postcode":"40741",
    "sg:province":"KY",
    "sg:tags":[
        "establishment"
    ],
    "wof:name":"Wiedemann Square LTD",
    "wof:placetype":"venue"
},
  "geometry": {"coordinates":[-84.077974,37.122341],"type":"Point"}
}