{
  "type": "Feature",
  "properties": {
    "addr:full":"2806 New Hartford Rd Owensboro KY 42303",
    "addr:housenumber":"2806",
    "addr:postcode":"42303",
    "addr:street":"New Hartford Rd",
    "iso:country":"US",
    "sg:address":"2806 New Hartford Rd",
    "sg:city":"Owensboro",
    "sg:classifiers":[
        {
            "category":"Shopping",
            "subcategory":"Pharmacy",
            "type":"Retail Goods"
        }
    ],
    "sg:phone":"+1 270 683 3314",
    "sg:postcode":"42303",
    "sg:province":"KY",
    "sg:tags":[
        "pharmaceutical",
        "consultant"
    ],
    "wof:name":"Ridge View Pharm & Wellness",
    "wof:placetype":"venue"
},
  "geometry": {"coordinates":[-87.098338,37.74872],"type":"Point"}
}