{
  "type": "Feature",
  "properties": {
    "addr:full":"1240 C Stokes Rd Elkton KY 42220",
    "addr:housenumber":"1240 c",
    "addr:postcode":"42220",
    "addr:street":"Stokes Rd",
    "iso:country":"US",
    "sg:address":"1240 C Stokes Rd",
    "sg:city":"Elkton",
    "sg:classifiers":[
        {
            "category":"Freight",
            "type":"Transportation"
        }
    ],
    "sg:phone":"+1 270 265 5382",
    "sg:postcode":"42220",
    "sg:province":"KY",
    "sg:tags":[
        "operator",
        "local",
        "trucking"
    ],
    "wof:name":"Rocking B Cattle Express LLC",
    "wof:placetype":"venue"
},
  "geometry": {"coordinates":[-87.126321,36.848248],"type":"Point"}
}