{
  "type": "Feature",
  "properties": {
    "iso:country":"US",
    "sg:address":"1001 Louisville Rd",
    "sg:city":"Frankfort",
    "sg:classifiers":[
        {
            "category":"Autos & Motor Vehicles",
            "subcategory":"Fuel & Gas Station",
            "type":"Retail Goods"
        }
    ],
    "sg:phone":"+1 502 223 0848",
    "sg:postcode":"40601",
    "sg:province":"KY",
    "sg:tags":[
        "oil"
    ],
    "wof:name":"Super America",
    "wof:placetype":"venue"
},
  "geometry": {"coordinates":[-84.89475400000001,38.180366],"type":"Point"}
}