{
  "type": "Feature",
  "properties": {
    "iso:country":"US",
    "sg:address":"308 W Market St",
    "sg:city":"Leitchfield",
    "sg:classifiers":[
        {
            "category":"Professional",
            "subcategory":"Employment Agencies",
            "type":"Services"
        }
    ],
    "sg:phone":"+1 270 259 3469",
    "sg:postcode":"42754",
    "sg:province":"KY",
    "sg:tags":[
        "opportunity"
    ],
    "wof:name":"Superior Staffing Svc Inc",
    "wof:placetype":"venue"
},
  "geometry": {"coordinates":[-86.29833000000001,37.479088],"type":"Point"}
}