{
  "type": "Feature",
  "properties": {
    "iso:country":"US",
    "sg:address":"1929 Triplett St",
    "sg:city":"Owensboro",
    "sg:classifiers":[
        {
            "category":"Professional",
            "subcategory":"Business Services",
            "type":"Services"
        }
    ],
    "sg:phone":"+1 270 926 6737",
    "sg:postcode":"42303",
    "sg:province":"KY",
    "sg:tags":[
        "interior",
        "consultant",
        "design",
        "decorator"
    ],
    "wof:name":"Ravels Limited",
    "wof:placetype":"venue"
},
  "geometry": {"coordinates":[-87.10257,37.757226],"type":"Point"}
}