{
  "type": "Feature",
  "properties": {
    "iso:country":"US",
    "sg:address":"402 Main St",
    "sg:city":"Williamsburg",
    "sg:classifiers":[
        {
            "category":"Communications",
            "subcategory":"Radio Station",
            "type":"Services"
        }
    ],
    "sg:phone":"+1 606 549 3000",
    "sg:postcode":"40769",
    "sg:province":"KY",
    "sg:tags":[
        "company",
        "broadcasting"
    ],
    "wof:name":"WEKC",
    "wof:placetype":"venue"
},
  "geometry": {"coordinates":[-84.160706,36.742264],"type":"Point"}
}