{
  "type": "Feature",
  "properties": {
    "iso:country":"US",
    "sg:address":"1102 Paducah Rd",
    "sg:city":"Mayfield",
    "sg:classifiers":[
        {
            "category":"Retail",
            "subcategory":"Repair Shop",
            "type":"Services"
        }
    ],
    "sg:phone":"+1 270 247 5320",
    "sg:postcode":"42066",
    "sg:province":"KY",
    "sg:tags":[
        "related"
    ],
    "wof:name":"Tri State Irrigation",
    "wof:placetype":"venue"
},
  "geometry": {"coordinates":[-88.64107199999999,36.758067],"type":"Point"}
}