{
  "type": "Feature",
  "properties": {
    "iso:country":"US",
    "sg:address":"1824 McDonalds Ln",
    "sg:city":"London",
    "sg:classifiers":[
        {
            "category":"Professional",
            "subcategory":"Detective & Security Services",
            "type":"Services"
        }
    ],
    "sg:phone":"+1 606 877 2554",
    "sg:postcode":"40741",
    "sg:province":"KY",
    "sg:tags":[
        "investigator"
    ],
    "wof:name":"London Collections",
    "wof:placetype":"venue"
},
  "geometry": {"coordinates":[-84.09739999999999,37.13989],"type":"Point"}
}