{
  "type": "Feature",
  "properties": {
    "iso:country":"US",
    "sg:address":"501 Main St",
    "sg:city":"Shelbyville",
    "sg:classifiers":[
        {
            "category":"Government",
            "subcategory":"Court House",
            "type":"Public Place"
        }
    ],
    "sg:phone":"+1 502 633 4736",
    "sg:postcode":"40065",
    "sg:province":"KY",
    "sg:tags":[
        "county"
    ],
    "wof:name":"Shelby County District Clerk",
    "wof:placetype":"venue"
},
  "geometry": {"coordinates":[-85.217281,38.211058],"type":"Point"}
}