{
  "type": "Feature",
  "properties": {
    "addr:full":"1546 Grandview Rd Alexandria KY 41001",
    "addr:housenumber":"1546",
    "addr:postcode":"41001",
    "addr:street":"Grandview Rd",
    "iso:country":"US",
    "sg:address":"1546 Grandview Rd",
    "sg:city":"Alexandria",
    "sg:classifiers":[
        {
            "category":"Building & Trades",
            "subcategory":"Construction",
            "type":"Services"
        }
    ],
    "sg:phone":"+1 859 743 6713",
    "sg:postcode":"41001",
    "sg:province":"KY",
    "sg:tags":[
        "excavating",
        "contractor"
    ],
    "wof:name":"Chuck's Bobcat Svc",
    "wof:placetype":"venue"
},
  "geometry": {"coordinates":[-84.37797,38.956701],"type":"Point"}
}