{
  "type": "Feature",
  "properties": {
    "iso:country":"US",
    "sg:address":"711 Boatlanding Rd",
    "sg:city":"Bowling Green",
    "sg:classifiers":[
        {
            "category":"Food & Beverages",
            "subcategory":"Liquor & Beverages",
            "type":"Retail Goods"
        }
    ],
    "sg:phone":"+1 270 843 3395",
    "sg:postcode":"42101",
    "sg:province":"KY",
    "wof:name":"Kinnarney's Drive In Liquors",
    "wof:placetype":"venue"
},
  "geometry": {"coordinates":[-86.442604,37.008955],"type":"Point"}
}