{
  "type": "Feature",
  "properties": {
    "iso:country":"US",
    "sg:address":"210 Oxfordshire Ln",
    "sg:city":"Louisville",
    "sg:classifiers":[
        {
            "category":"Education",
            "subcategory":"School",
            "type":"Public Place"
        }
    ],
    "sg:phone":"+1 502 485 8293",
    "sg:postcode":"40222",
    "sg:province":"KY",
    "sg:website":"www.jefferson.k12.ky.us",
    "wof:name":"Lowe Elementary School",
    "wof:placetype":"venue"
},
  "geometry": {"coordinates":[-85.591183,38.245504],"type":"Point"}
}