{
  "type": "Feature",
  "properties": {
    "addr:full":"1226 Aviation Blvd Hebron KY 41048",
    "addr:housenumber":"1226",
    "addr:postcode":"41048",
    "addr:street":"Aviation Blvd",
    "iso:country":"US",
    "sg:address":"1226 Aviation Blvd",
    "sg:city":"Hebron",
    "sg:classifiers":[
        {
            "category":"Professional",
            "subcategory":"Business Services",
            "type":"Services"
        }
    ],
    "sg:phone":"+1 859 488 4050",
    "sg:postcode":"41048",
    "sg:province":"KY",
    "sg:tags":[
        "provides"
    ],
    "wof:name":"Innotrac Corporation",
    "wof:placetype":"venue"
},
  "geometry": {"coordinates":[-84.673016,39.078265],"type":"Point"}
}