{
  "type": "Feature",
  "properties": {
    "iso:country":"US",
    "sg:address":"817 Oak Fairway Ct",
    "sg:city":"Maysville",
    "sg:classifiers":[
        {
            "category":"Professional",
            "subcategory":"Business Services",
            "type":"Services"
        }
    ],
    "sg:phone":"+1 606 759 1413",
    "sg:postcode":"41056",
    "sg:province":"KY",
    "sg:tags":[
        "appraiser"
    ],
    "wof:name":"Sweeney Appraisals",
    "wof:placetype":"venue"
},
  "geometry": {"coordinates":[-83.82390100000001,38.605009],"type":"Point"}
}