{
  "type": "Feature",
  "properties": {
    "iso:country":"US",
    "sg:address":"102 Sterling Ave",
    "sg:city":"Mt Sterling",
    "sg:classifiers":[
        {
            "category":"Autos & Motor Vehicles",
            "subcategory":"Fuel & Gas Station",
            "type":"Retail Goods"
        }
    ],
    "sg:phone":"+1 859 498 2670",
    "sg:postcode":"40353",
    "sg:province":"KY",
    "sg:tags":[
        "oil"
    ],
    "wof:name":"Shell Food Mart",
    "wof:placetype":"venue"
},
  "geometry": {"coordinates":[-83.947318,38.061658],"type":"Point"}
}