{
  "type": "Feature",
  "properties": {
    "iso:country":"US",
    "sg:address":"226 N Elm St",
    "sg:city":"Henderson",
    "sg:classifiers":[
        {
            "category":"Professional",
            "subcategory":"Lawyer & Legal Services",
            "type":"Services"
        }
    ],
    "sg:phone":"+1 270 827 4725",
    "sg:postcode":"42420",
    "sg:province":"KY",
    "sg:tags":[
        "attorney"
    ],
    "wof:name":"Francis Law Office",
    "wof:placetype":"venue"
},
  "geometry": {"coordinates":[-87.589326,37.841],"type":"Point"}
}