{
  "type": "Feature",
  "properties": {
    "iso:country":"US",
    "sg:address":"520 S Columbia Ave",
    "sg:city":"Campbellsville",
    "sg:classifiers":[
        {
            "category":"Retail",
            "subcategory":"Auto Repair",
            "type":"Services"
        }
    ],
    "sg:phone":"+1 270 465 6606",
    "sg:postcode":"42718",
    "sg:province":"KY",
    "sg:tags":[
        "repairing",
        "automobile"
    ],
    "wof:name":"Johnson Motor Co",
    "wof:placetype":"venue"
},
  "geometry": {"coordinates":[-85.345894,37.334638],"type":"Point"}
}