{
  "type": "Feature",
  "properties": {
    "iso:country":"US",
    "sg:address":"4485 Clarks River Rd",
    "sg:city":"Paducah",
    "sg:classifiers":[
        {
            "category":"Manufacturing",
            "subcategory":"Buildings",
            "type":"Manufacturing & Wholesale Goods"
        },
        {
            "category":"Building & Trades",
            "subcategory":"Construction",
            "type":"Services"
        }
    ],
    "sg:phone":"+1 270 898 2339",
    "sg:postcode":"42003",
    "sg:province":"KY",
    "sg:tags":[
        "home",
        "builder",
        "contractor"
    ],
    "wof:name":"D & R Steel Builders",
    "wof:placetype":"venue"
},
  "geometry": {"coordinates":[-88.563053,37.048296],"type":"Point"}
}