{
  "type": "Feature",
  "properties": {
    "addr:full":"779 State Hwy 413 Baxter KY 40806",
    "addr:housenumber":"779",
    "addr:postcode":"40806",
    "addr:street":"State Hwy 413",
    "iso:country":"US",
    "sg:address":"779 State Hwy 413",
    "sg:city":"Baxter",
    "sg:classifiers":[
        {
            "category":"Retail",
            "subcategory":"Animal Services",
            "type":"Services"
        }
    ],
    "sg:phone":"+1 606 574 1086",
    "sg:postcode":"40806",
    "sg:province":"KY",
    "sg:tags":[
        "pet"
    ],
    "wof:name":"Michelle's Petshop",
    "wof:placetype":"venue"
},
  "geometry": {"coordinates":[-83.317015,36.867101],"type":"Point"}
}