{
  "type": "Feature",
  "properties": {
    "addr:full":"237 State Hwy 1955 Mc Kee KY 40447",
    "addr:housenumber":"237",
    "addr:postcode":"40447",
    "addr:street":"State Hwy 1955 Mc Kee",
    "iso:country":"US",
    "sg:address":"237 State Hwy 1955",
    "sg:city":"Mc Kee",
    "sg:classifiers":[
        {
            "category":"Social Services",
            "subcategory":"Child Care",
            "type":"Services"
        }
    ],
    "sg:phone":"+1 606 965 3312",
    "sg:postcode":"40447",
    "sg:province":"KY",
    "sg:tags":[
        "kindergarten",
        "academic",
        "school"
    ],
    "wof:name":"Pine Grove Head Start",
    "wof:placetype":"venue"
},
  "geometry": {"coordinates":[-84.153245,37.482415],"type":"Point"}
}