{
  "type": "Feature",
  "properties": {
    "iso:country":"US",
    "sg:address":"1 Hudson Hollow Rd",
    "sg:city":"Frankfort",
    "sg:classifiers":[
        {
            "category":"Social Services",
            "subcategory":"Child Care",
            "type":"Services"
        }
    ],
    "sg:phone":"+1 502 223 2483",
    "sg:postcode":"40601",
    "sg:province":"KY",
    "wof:name":"Little Lamb Pre-School",
    "wof:placetype":"venue"
},
  "geometry": {"coordinates":[-84.893107,38.180921],"type":"Point"}
}