{
  "type": "Feature",
  "properties": {
    "iso:country":"US",
    "sg:address":"300 E 10th St",
    "sg:city":"Newport",
    "sg:classifiers":[
        {
            "category":"Bars & Pubs",
            "type":"Food & Drink"
        }
    ],
    "sg:phone":"+1 859 261 5427",
    "sg:postcode":"41071",
    "sg:province":"KY",
    "wof:name":"Liars Club",
    "wof:placetype":"venue"
},
  "geometry": {"coordinates":[-84.486267,39.088646],"type":"Point"}
}