{
  "type": "Feature",
  "properties": {
    "addr:full":"2130 Portland Ave Louisville KY 40212",
    "addr:housenumber":"2130",
    "addr:postcode":"40212",
    "addr:street":"Portland Ave",
    "iso:country":"US",
    "sg:address":"2130 Portland Ave",
    "sg:city":"Louisville",
    "sg:classifiers":[
        {
            "category":"Organizations",
            "subcategory":"Professional Association",
            "type":"Services"
        }
    ],
    "sg:phone":"+1 502 775 4041",
    "sg:postcode":"40212",
    "sg:province":"KY",
    "wof:name":"Community Farm Alliance",
    "wof:placetype":"venue"
},
  "geometry": {"coordinates":[-85.78375699999999,38.268725],"type":"Point"}
}