{
  "type": "Feature",
  "properties": {
    "addr:full":"4610 Cane Run Rd Louisville KY 40216",
    "addr:housenumber":"4610",
    "addr:postcode":"40216",
    "addr:street":"Cane Run Rd",
    "iso:country":"US",
    "sg:address":"4610 Cane Run Rd",
    "sg:city":"Louisville",
    "sg:classifiers":[
        {
            "category":"Manufacturing",
            "subcategory":"Motor Vehicles & Parts",
            "type":"Manufacturing & Wholesale Goods"
        }
    ],
    "sg:phone":"+1 502 447 3413",
    "sg:postcode":"40216",
    "sg:province":"KY",
    "sg:tags":[
        "automobile",
        "supply"
    ],
    "wof:name":"Charlie Saling's Auto Supplies",
    "wof:placetype":"venue"
},
  "geometry": {"coordinates":[-85.847216,38.192011],"type":"Point"}
}