{
  "type": "Feature",
  "properties": {
    "iso:country":"US",
    "sg:address":"720 Hospital Dr",
    "sg:city":"Shelbyville",
    "sg:classifiers":[
        {
            "category":"Health Services",
            "subcategory":"Doctor",
            "type":"Services"
        }
    ],
    "sg:phone":"+1 502 633 6062",
    "sg:postcode":"40065",
    "sg:province":"KY",
    "sg:tags":[
        "physician",
        "surgeon"
    ],
    "wof:name":"Surgical Associates",
    "wof:placetype":"venue"
},
  "geometry": {"coordinates":[-85.236152,38.210399],"type":"Point"}
}