{
  "type": "Feature",
  "properties": {
    "addr:full":"1961 Richmond Dr Louisville KY 40205",
    "addr:housenumber":"1961",
    "addr:postcode":"40205",
    "addr:street":"Richmond Dr",
    "iso:country":"US",
    "sg:address":"1961 Richmond Dr",
    "sg:city":"Louisville",
    "sg:classifiers":[
        {
            "category":"Personal",
            "subcategory":"Barber",
            "type":"Services"
        }
    ],
    "sg:phone":"+1 502 459 3738",
    "sg:postcode":"40205",
    "sg:province":"KY",
    "wof:name":"Razor Investments",
    "wof:placetype":"venue"
},
  "geometry": {"coordinates":[-85.70290799999999,38.22479],"type":"Point"}
}