{
  "type": "Feature",
  "properties": {
    "addr:full":"4261 Produce Rd Louisville KY 40218",
    "addr:housenumber":"4261",
    "addr:postcode":"40218",
    "addr:street":"Produce Rd",
    "iso:country":"US",
    "sg:address":"4261 Produce Rd",
    "sg:city":"Louisville",
    "sg:classifiers":[
        {
            "category":"Wholesale",
            "subcategory":"Durable Goods & Equipment",
            "type":"Manufacturing & Wholesale Goods"
        }
    ],
    "sg:phone":"+1 502 966 0200",
    "sg:postcode":"40218",
    "sg:province":"KY",
    "sg:tags":[
        "representative",
        "manufacturer"
    ],
    "wof:name":"Air Mechanical Sales Inc",
    "wof:placetype":"venue"
},
  "geometry": {"coordinates":[-85.680271,38.185775],"type":"Point"}
}