{
  "type": "Feature",
  "properties": {
    "iso:country":"US",
    "sg:address":"2017 Brownsboro Rd",
    "sg:city":"Louisville",
    "sg:classifiers":[
        {
            "category":"Restaurant",
            "type":"Food & Drink"
        }
    ],
    "sg:menulink":"http://www.allmenus.com/ky/louisville-east/209692-taste-of-jamaica/menu/",
    "sg:phone":"+1 502 896 1055",
    "sg:postcode":"40206",
    "sg:province":"KY",
    "sg:tags":[
        "jamaican"
    ],
    "wof:name":"Taste Of Jamaica",
    "wof:placetype":"venue"
},
  "geometry": {"coordinates":[-85.707328,38.259685],"type":"Point"}
}