{
  "type": "Feature",
  "properties": {
    "iso:country":"US",
    "sg:address":"1357 Dorchester Dr",
    "sg:city":"Georgetown",
    "sg:classifiers":[
        {
            "category":"Personal",
            "subcategory":"Beauty Salon",
            "type":"Services"
        }
    ],
    "sg:phone":"+1 502 863 9481",
    "sg:postcode":"40324",
    "sg:province":"KY",
    "sg:tags":[
        "shop"
    ],
    "wof:name":"Sheri Stacy",
    "wof:placetype":"venue"
},
  "geometry": {"coordinates":[-84.551272,38.188784],"type":"Point"}
}