{
  "type": "Feature",
  "properties": {
    "addr:full":"920 N Main St Elizabethtown KY 42701",
    "addr:housenumber":"920",
    "addr:postcode":"42701",
    "addr:street":"N Main St",
    "iso:country":"US",
    "sg:address":"920 N Main St",
    "sg:city":"Elizabethtown",
    "sg:classifiers":[
        {
            "category":"Personal",
            "subcategory":"Beauty Salon",
            "type":"Services"
        }
    ],
    "sg:phone":"+1 270 737 2570",
    "sg:postcode":"42701",
    "sg:province":"KY",
    "wof:name":"Hair Masters",
    "wof:placetype":"venue"
},
  "geometry": {"coordinates":[-85.84241299999999,37.705728],"type":"Point"}
}