{
  "type": "Feature",
  "properties": {
    "addr:full":"12307 Midland Trail Rd Ashland KY 41102",
    "addr:housenumber":"12307",
    "addr:postcode":"41102",
    "addr:street":"Midland Trail Rd",
    "iso:country":"US",
    "sg:address":"12307 Midland Trail Rd",
    "sg:city":"Ashland",
    "sg:classifiers":[
        {
            "category":"Education",
            "subcategory":"School",
            "type":"Public Place"
        }
    ],
    "sg:phone":"+1 606 928 7100",
    "sg:postcode":"41102",
    "sg:province":"KY",
    "sg:website":"www.boyd.k12.ky.us",
    "wof:name":"Boyd County High School",
    "wof:placetype":"venue"
},
  "geometry": {"coordinates":[-82.702608,38.379604],"type":"Point"}
}