{
  "type": "Feature",
  "properties": {
    "iso:country":"US",
    "sg:address":"37 E Center St",
    "sg:city":"Madisonville",
    "sg:classifiers":[
        {
            "category":"Government",
            "subcategory":"Office",
            "type":"Public Place"
        }
    ],
    "sg:phone":"+1 270 824 2105",
    "sg:postcode":"42431",
    "sg:province":"KY",
    "sg:tags":[
        "village"
    ],
    "wof:name":"Madisonville City Adm Officer",
    "wof:placetype":"venue"
},
  "geometry": {"coordinates":[-87.497784,37.327981],"type":"Point"}
}