{
  "type": "Feature",
  "properties": {
    "iso:country":"US",
    "sg:address":"504 Watson Ln",
    "sg:city":"Henderson",
    "sg:classifiers":[
        {
            "category":"Food & Beverages",
            "subcategory":"Groceries & Convenience Stores",
            "type":"Retail Goods"
        }
    ],
    "sg:phone":"+1 270 826 3292",
    "sg:postcode":"42420",
    "sg:province":"KY",
    "sg:tags":[
        "grocer"
    ],
    "wof:name":"Sureway Food Store",
    "wof:placetype":"venue"
},
  "geometry": {"coordinates":[-87.566356,37.874973],"type":"Point"}
}