{
  "type": "Feature",
  "properties": {
    "iso:country":"US",
    "sg:address":"1595 State Hwy 721",
    "sg:city":"Hazard",
    "sg:classifiers":[
        {
            "category":"Organizations",
            "subcategory":"Religious Organization",
            "type":"Services"
        }
    ],
    "sg:phone":"+1 606 785 4534",
    "sg:postcode":"41701",
    "sg:province":"KY",
    "sg:tags":[
        "church"
    ],
    "wof:name":"Lotts Creek Ev Free Church",
    "wof:placetype":"venue"
},
  "geometry": {"coordinates":[-83.10078799999999,37.326024],"type":"Point"}
}