{
  "type": "Feature",
  "properties": {
    "iso:country":"US",
    "sg:address":"9043 Rose Creek Rd",
    "sg:city":"Nebo",
    "sg:classifiers":[
        {
            "category":"Wholesale",
            "subcategory":"Farm Supplies",
            "type":"Manufacturing & Wholesale Goods"
        }
    ],
    "sg:phone":"+1 270 249 3605",
    "sg:postcode":"42441",
    "sg:province":"KY",
    "wof:name":"Island View Farm Supply",
    "wof:placetype":"venue"
},
  "geometry": {"coordinates":[-87.69712800000001,37.356312],"type":"Point"}
}