{
  "type": "Feature",
  "properties": {
    "iso:country":"US",
    "sg:address":"873 Sand Hill Rd",
    "sg:city":"Irvine",
    "sg:classifiers":[
        {
            "category":"Shopping",
            "subcategory":"Gifts & Souvenirs",
            "type":"Retail Goods"
        }
    ],
    "sg:phone":"+1 606 723 8454",
    "sg:postcode":"40336",
    "sg:province":"KY",
    "wof:name":"Cusick Creations",
    "wof:placetype":"venue"
},
  "geometry": {"coordinates":[-84.02033,37.715888],"type":"Point"}
}