{
  "type": "Feature",
  "properties": {
    "iso:country":"US",
    "sg:address":"600 Pekin Rd",
    "sg:city":"Wilmore",
    "sg:classifiers":[
        {
            "category":"Professional",
            "subcategory":"Management & Consulting",
            "type":"Services"
        }
    ],
    "sg:phone":"+1 859 858 8058",
    "sg:postcode":"40390",
    "sg:province":"KY",
    "sg:tags":[
        "business"
    ],
    "wof:name":"Bluegrass Health & Safety Inc",
    "wof:placetype":"venue"
},
  "geometry": {"coordinates":[-84.692216,37.870267],"type":"Point"}
}