{
  "type": "Feature",
  "properties": {
    "iso:country":"US",
    "sg:address":"215 N Keeneland Dr",
    "sg:city":"Richmond",
    "sg:classifiers":[
        {
            "category":"Home & Garden",
            "subcategory":"Building Materials",
            "type":"Retail Goods"
        }
    ],
    "sg:phone":"+1 859 623 4939",
    "sg:postcode":"40475",
    "sg:province":"KY",
    "sg:tags":[
        "wallpaper"
    ],
    "wof:name":"Andersons Wallpaper & Fabric",
    "wof:placetype":"venue"
},
  "geometry": {"coordinates":[-84.320536,37.782684],"type":"Point"}
}