{
  "type": "Feature",
  "properties": {
    "iso:country":"US",
    "sg:address":"2288 Shannawood Dr",
    "sg:city":"Lexington",
    "sg:classifiers":[
        {
            "category":"Professional",
            "subcategory":"Management & Consulting",
            "type":"Services"
        }
    ],
    "sg:phone":"+1 859 224 2190",
    "sg:postcode":"40513",
    "sg:province":"KY",
    "sg:tags":[
        "public",
        "relations"
    ],
    "wof:name":"Barbara S Ellis",
    "wof:placetype":"venue"
},
  "geometry": {"coordinates":[-84.579273,38.004801],"type":"Point"}
}