{
  "type": "Feature",
  "properties": {
    "iso:country":"US",
    "sg:address":"973 Baxter Ave",
    "sg:city":"Louisville",
    "sg:classifiers":[
        {
            "category":"Restaurant",
            "type":"Food & Drink"
        }
    ],
    "sg:phone":"+1 502 456 1559",
    "sg:postcode":"40204",
    "sg:province":"KY",
    "wof:name":"Wick's Pub",
    "wof:placetype":"venue"
},
  "geometry": {"coordinates":[-85.72470300000001,38.240973],"type":"Point"}
}