{
  "type": "Feature",
  "properties": {
    "iso:country":"US",
    "sg:address":"1751 Old Columbia Rd",
    "sg:city":"Campbellsville",
    "sg:classifiers":[
        {
            "category":"Building & Trades",
            "subcategory":"Construction",
            "type":"Services"
        }
    ],
    "sg:phone":"+1 270 789 4166",
    "sg:postcode":"42718",
    "sg:province":"KY",
    "sg:tags":[
        "specialty"
    ],
    "sg:website":"www.polyprollc.com",
    "wof:name":"Poly Pro LLC",
    "wof:placetype":"venue"
},
  "geometry": {"coordinates":[-85.358311,37.320035],"type":"Point"}
}