{
  "type": "Feature",
  "properties": {
    "addr:full":"9500 Ormsby Station Rd Louisville KY 40223",
    "addr:housenumber":"9500",
    "addr:postcode":"40223",
    "addr:street":"Ormsby Station Rd",
    "iso:country":"US",
    "sg:address":"9500 Ormsby Station Rd",
    "sg:city":"Louisville",
    "sg:classifiers":[
        {
            "category":"Insurance",
            "subcategory":"Title Insurance",
            "type":"Services"
        }
    ],
    "sg:phone":"+1 502 423 9814",
    "sg:postcode":"40223",
    "sg:province":"KY",
    "wof:name":"Chicago Title Insurance Co",
    "wof:placetype":"venue"
},
  "geometry": {"coordinates":[-85.574699,38.26297],"type":"Point"}
}