{
  "type": "Feature",
  "properties": {
    "addr:full":"71 S Main St Winchester KY 40391",
    "addr:housenumber":"71",
    "addr:postcode":"40391",
    "addr:street":"S Main St",
    "iso:country":"US",
    "sg:address":"71 S Main St",
    "sg:city":"Winchester",
    "sg:classifiers":[
        {
            "category":"Shopping",
            "subcategory":"Gifts & Souvenirs",
            "type":"Retail Goods"
        }
    ],
    "sg:phone":"+1 859 737 3688",
    "sg:postcode":"40391",
    "sg:province":"KY",
    "sg:tags":[
        "shop"
    ],
    "wof:name":"Marlena's Home Decoratives",
    "wof:placetype":"venue"
},
  "geometry": {"coordinates":[-84.17749499999999,37.99215],"type":"Point"}
}