{
  "type": "Feature",
  "properties": {
    "iso:country":"US",
    "sg:address":"36 N Highland St",
    "sg:city":"Winchester",
    "sg:classifiers":[
        {
            "category":"Professional",
            "type":"Services"
        }
    ],
    "sg:phone":"+1 859 744 9433",
    "sg:postcode":"40391",
    "sg:province":"KY",
    "sg:tags":[
        "establishment"
    ],
    "wof:name":"Stan A Pedestal",
    "wof:placetype":"venue"
},
  "geometry": {"coordinates":[-84.174851,37.993959],"type":"Point"}
}