{
  "type": "Feature",
  "properties": {
    "addr:full":"5557 Forest Lake Dr Prospect KY 40059",
    "addr:housenumber":"5557",
    "addr:postcode":"40059",
    "addr:street":"Forest Lake Dr",
    "iso:country":"US",
    "sg:address":"5557 Forest Lake Dr",
    "sg:city":"Prospect",
    "sg:classifiers":[
        {
            "category":"Professional",
            "type":"Services"
        }
    ],
    "sg:phone":"+1 502 228 4222",
    "sg:postcode":"40059",
    "sg:province":"KY",
    "wof:name":"Foley Vikie",
    "wof:placetype":"venue"
},
  "geometry": {"coordinates":[-85.623593,38.330316],"type":"Point"}
}