{
  "type": "Feature",
  "properties": {
    "iso:country":"US",
    "sg:address":"8025 Burlington Pike",
    "sg:city":"Florence",
    "sg:classifiers":[
        {
            "category":"Autos & Motor Vehicles",
            "subcategory":"Fuel & Gas Station",
            "type":"Retail Goods"
        }
    ],
    "sg:phone":"+1 859 282 7935",
    "sg:postcode":"41042",
    "sg:province":"KY",
    "sg:tags":[
        "oil"
    ],
    "wof:name":"Procare Automotive Svc Ctr",
    "wof:placetype":"venue"
},
  "geometry": {"coordinates":[-84.65064099999999,39.002365],"type":"Point"}
}