{
  "type": "Feature",
  "properties": {
    "iso:country":"US",
    "sg:address":"1233 Woodland Dr",
    "sg:city":"Elizabethtown",
    "sg:classifiers":[
        {
            "category":"Shopping",
            "type":"Retail Goods"
        }
    ],
    "sg:phone":"+1 270 769 1176",
    "sg:postcode":"42701",
    "sg:province":"KY",
    "sg:tags":[
        "merchandise"
    ],
    "wof:name":"Avada Audiology & Hearing Care",
    "wof:placetype":"venue"
},
  "geometry": {"coordinates":[-85.882639,37.71881],"type":"Point"}
}