{
  "type": "Feature",
  "properties": {
    "iso:country":"US",
    "sg:address":"2887 Holloway Ln",
    "sg:city":"Henderson",
    "sg:classifiers":[
        {
            "category":"Building & Trades",
            "subcategory":"Electrical",
            "type":"Services"
        }
    ],
    "sg:phone":"+1 270 827 9764",
    "sg:postcode":"42420",
    "sg:province":"KY",
    "sg:tags":[
        "electric",
        "contractor"
    ],
    "wof:name":"Caton Electrical Svc",
    "wof:placetype":"venue"
},
  "geometry": {"coordinates":[-87.52775699999999,37.824724],"type":"Point"}
}