{
  "type": "Feature",
  "properties": {
    "iso:country":"US",
    "sg:address":"204 Park St",
    "sg:city":"Falmouth",
    "sg:classifiers":[
        {
            "category":"Retail",
            "subcategory":"Veterinary Services",
            "type":"Services"
        }
    ],
    "sg:phone":"+1 859 654 1031",
    "sg:postcode":"41040",
    "sg:province":"KY",
    "sg:tags":[
        "veterinarian"
    ],
    "wof:name":"Pendleton County Veterinary",
    "wof:placetype":"venue"
},
  "geometry": {"coordinates":[-84.333296,38.679078],"type":"Point"}
}