{
  "type": "Feature",
  "properties": {
    "addr:full":"4505 Dove Park Blvd Louisville KY 40299",
    "addr:housenumber":"4505",
    "addr:postcode":"40299",
    "addr:street":"Dove Park Blvd",
    "iso:country":"US",
    "sg:address":"4505 Dove Park Blvd",
    "sg:city":"Louisville",
    "sg:classifiers":[
        {
            "category":"Professional",
            "subcategory":"Management & Consulting",
            "type":"Services"
        }
    ],
    "sg:phone":"+1 502 297 8783",
    "sg:postcode":"40299",
    "sg:province":"KY",
    "sg:tags":[
        "business"
    ],
    "wof:name":"Greenleaf Evironmental Mgmt",
    "wof:placetype":"venue"
},
  "geometry": {"coordinates":[-85.531249,38.181336],"type":"Point"}
}