{
  "type": "Feature",
  "properties": {
    "iso:country":"US",
    "sg:address":"900 Beasley St",
    "sg:city":"Lexington",
    "sg:classifiers":[
        {
            "category":"Health Services",
            "subcategory":"Doctor",
            "type":"Services"
        }
    ],
    "sg:phone":"+1 859 294 8617",
    "sg:postcode":"40509",
    "sg:province":"KY",
    "sg:tags":[
        "physician",
        "surgeon"
    ],
    "wof:name":"Andrea Thomas MD",
    "wof:placetype":"venue"
},
  "geometry": {"coordinates":[-84.45190100000001,38.0418],"type":"Point"}
}