{
  "type": "Feature",
  "properties": {
    "iso:country":"US",
    "sg:address":"52 Hopkinsville St",
    "sg:city":"Russellville",
    "sg:classifiers":[
        {
            "category":"Autos & Motor Vehicles",
            "subcategory":"Automobile Sales",
            "type":"Retail Goods"
        }
    ],
    "sg:phone":"+1 270 726 9553",
    "sg:postcode":"42276",
    "sg:province":"KY",
    "sg:tags":[
        "new",
        "used",
        "car"
    ],
    "sg:website":"http://www.mansfieldchevybuick.com",
    "wof:name":"Mansfield Chevrolet-Buick Inc",
    "wof:placetype":"venue"
},
  "geometry": {"coordinates":[-86.894639,36.843574],"type":"Point"}
}