{
  "type": "Feature",
  "properties": {
    "iso:country":"US",
    "sg:address":"2382 Peyton Ridge Rd",
    "sg:city":"Liberty",
    "sg:classifiers":[
        {
            "category":"Shopping",
            "subcategory":"Used Merchandise",
            "type":"Retail Goods"
        }
    ],
    "sg:phone":"+1 606 787 6480",
    "sg:postcode":"42539",
    "sg:province":"KY",
    "sg:tags":[
        "furniture"
    ],
    "wof:name":"Out Of The Way Used Furniture",
    "wof:placetype":"venue"
},
  "geometry": {"coordinates":[-84.975195,37.407803],"type":"Point"}
}