{
  "type": "Feature",
  "properties": {
    "iso:country":"US",
    "sg:address":"5205 Frederica St",
    "sg:city":"Owensboro",
    "sg:classifiers":[
        {
            "category":"Restaurant",
            "type":"Food & Drink"
        }
    ],
    "sg:phone":"+1 270 686 8780",
    "sg:postcode":"42301",
    "sg:province":"KY",
    "sg:website":"www.ocharleys.com",
    "wof:name":"O'Charley's",
    "wof:placetype":"venue"
},
  "geometry": {"coordinates":[-87.12532,37.716073],"type":"Point"}
}