{
  "type": "Feature",
  "properties": {
    "iso:country":"US",
    "sg:address":"4209 Gilbertsville Hwy",
    "sg:city":"Calvert City",
    "sg:classifiers":[
        {
            "category":"Building & Trades",
            "subcategory":"Equipment Rental",
            "type":"Services"
        }
    ],
    "sg:phone":"+1 270 395 7068",
    "sg:postcode":"42029",
    "sg:province":"KY",
    "sg:tags":[
        "compressor"
    ],
    "sg:website":"www.aggreko.com",
    "wof:name":"Aggreko Inc",
    "wof:placetype":"venue"
},
  "geometry": {"coordinates":[-88.32733399999999,37.036113],"type":"Point"}
}