{
  "type": "Feature",
  "properties": {
    "iso:country":"US",
    "sg:address":"843 S Main St",
    "sg:city":"Burkesville",
    "sg:classifiers":[
        {
            "category":"Real Estate",
            "subcategory":"Real Estate Agent",
            "type":"Services"
        }
    ],
    "sg:phone":"+1 270 864 4300",
    "sg:postcode":"42717",
    "sg:province":"KY",
    "wof:name":"Taylor Realty & Auction Co",
    "wof:placetype":"venue"
},
  "geometry": {"coordinates":[-85.374409,36.783281],"type":"Point"}
}