{
  "type": "Feature",
  "properties": {
    "iso:country":"US",
    "sg:address":"603 Highland Ave",
    "sg:city":"Carrollton",
    "sg:classifiers":[
        {
            "category":"Personal",
            "subcategory":"Beauty Salon",
            "type":"Services"
        }
    ],
    "sg:phone":"+1 502 732 9502",
    "sg:postcode":"41008",
    "sg:province":"KY",
    "wof:name":"Tammy's Glamourama",
    "wof:placetype":"venue"
},
  "geometry": {"coordinates":[-85.17742,38.681331],"type":"Point"}
}