{
  "type": "Feature",
  "properties": {
    "addr:full":"3810 Alexandria Pike Newport KY 41076",
    "addr:housenumber":"3810",
    "addr:postcode":"41076",
    "addr:street":"Alexandria Pike",
    "iso:country":"US",
    "sg:address":"3810 Alexandria Pike",
    "sg:city":"Newport",
    "sg:classifiers":[
        {
            "category":"Organizations",
            "subcategory":"Religious Organization",
            "type":"Services"
        }
    ],
    "sg:phone":"+1 859 781 7877",
    "sg:postcode":"41076",
    "sg:province":"KY",
    "wof:name":"Rolling Hills Christian Church",
    "wof:placetype":"venue"
},
  "geometry": {"coordinates":[-84.444712,39.024986],"type":"Point"}
}