{
  "type": "Feature",
  "properties": {
    "addr:full":"3015 Gentry Ln Danville KY 40422",
    "addr:housenumber":"3015",
    "addr:postcode":"40422",
    "addr:street":"Gentry Ln",
    "iso:country":"US",
    "sg:address":"3015 Gentry Ln",
    "sg:city":"Danville",
    "sg:classifiers":[
        {
            "category":"Professional",
            "subcategory":"Lawyer & Legal Services",
            "type":"Services"
        }
    ],
    "sg:phone":"+1 859 238 7673",
    "sg:postcode":"40422",
    "sg:province":"KY",
    "sg:tags":[
        "attorney"
    ],
    "wof:name":"J James Rogan",
    "wof:placetype":"venue"
},
  "geometry": {"coordinates":[-84.84744499999999,37.695162],"type":"Point"}
}