{
  "type": "Feature",
  "properties": {
    "iso:country":"US",
    "sg:address":"104 Aberdeen Dr",
    "sg:city":"Danville",
    "sg:classifiers":[
        {
            "category":"Professional",
            "subcategory":"Secretarial Services",
            "type":"Services"
        }
    ],
    "sg:phone":"+1 859 238 4164",
    "sg:postcode":"40422",
    "sg:province":"KY",
    "sg:tags":[
        "transcription",
        "medical"
    ],
    "wof:name":"Pfeifer Transcription Inc",
    "wof:placetype":"venue"
},
  "geometry": {"coordinates":[-84.786051,37.661861],"type":"Point"}
}