{
  "type": "Feature",
  "properties": {
    "addr:full":"228 E Reynolds Rd Lexington KY 40517",
    "addr:housenumber":"228",
    "addr:postcode":"40517",
    "addr:street":"E Reynolds Rd",
    "iso:country":"US",
    "sg:address":"228 E Reynolds Rd",
    "sg:city":"Lexington",
    "sg:classifiers":[
        {
            "category":"Professional",
            "subcategory":"Management & Consulting",
            "type":"Services"
        }
    ],
    "sg:phone":"+1 859 271 6153",
    "sg:postcode":"40517",
    "sg:province":"KY",
    "sg:tags":[
        "marketing",
        "consultant"
    ],
    "wof:name":"Third Wave Marketing",
    "wof:placetype":"venue"
},
  "geometry": {"coordinates":[-84.517798,37.989489],"type":"Point"}
}