{
  "type": "Feature",
  "properties": {
    "iso:country":"US",
    "sg:address":"73 Cavalier Blvd",
    "sg:city":"Florence",
    "sg:classifiers":[
        {
            "category":"Professional",
            "subcategory":"Lawyer & Legal Services",
            "type":"Services"
        }
    ],
    "sg:phone":"+1 859 647 0146",
    "sg:postcode":"41042",
    "sg:province":"KY",
    "wof:name":"Legal Nurse Consltnts of Greater Cinti",
    "wof:placetype":"venue"
},
  "geometry": {"coordinates":[-84.63510100000001,39.007801],"type":"Point"}
}