{
  "type": "Feature",
  "properties": {
    "iso:country":"US",
    "sg:address":"201 Dixie Hwy E",
    "sg:city":"Elizabethtown",
    "sg:classifiers":[
        {
            "category":"Museum",
            "type":"Entertainment"
        }
    ],
    "sg:phone":"+1 270 763 8339",
    "sg:postcode":"42701",
    "sg:province":"KY",
    "wof:name":"Hardin County History Museum",
    "wof:placetype":"venue"
},
  "geometry": {"coordinates":[-85.856538,37.69216],"type":"Point"}
}