{
  "type": "Feature",
  "properties": {
    "addr:full":"224 Barrow Rd Lexington KY 40502",
    "addr:housenumber":"224",
    "addr:postcode":"40502",
    "addr:street":"Barrow Rd",
    "iso:country":"US",
    "sg:address":"224 Barrow Rd",
    "sg:city":"Lexington",
    "sg:classifiers":[
        {
            "category":"Farming",
            "subcategory":"Farm",
            "type":"Manufacturing & Wholesale Goods"
        }
    ],
    "sg:phone":"+1 859 269 4730",
    "sg:postcode":"40502",
    "sg:province":"KY",
    "sg:tags":[
        "crop",
        "general"
    ],
    "wof:name":"Ike Vanmeter",
    "wof:placetype":"venue"
},
  "geometry": {"coordinates":[-84.47958,38.024691],"type":"Point"}
}