{
  "type": "Feature",
  "properties": {
    "addr:full":"2527 Bluebird Dr Villa Hills KY 41017",
    "addr:housenumber":"2527",
    "addr:postcode":"41017",
    "addr:street":"Bluebird Dr",
    "iso:country":"US",
    "sg:address":"2527 Bluebird Dr",
    "sg:city":"Villa Hills",
    "sg:classifiers":[
        {
            "category":"Wholesale",
            "subcategory":"Durable Goods & Equipment",
            "type":"Manufacturing & Wholesale Goods"
        }
    ],
    "sg:phone":"+1 859 341 5327",
    "sg:postcode":"41017",
    "sg:province":"KY",
    "sg:tags":[
        "representative",
        "manufacturer"
    ],
    "wof:name":"Crawford Sales Solutions Inc",
    "wof:placetype":"venue"
},
  "geometry": {"coordinates":[-84.587734,39.053396],"type":"Point"}
}