{
  "type": "Feature",
  "properties": {
    "iso:country":"US",
    "sg:address":"145 N Main St",
    "sg:city":"Henderson",
    "sg:classifiers":[
        {
            "category":"Professional",
            "type":"Services"
        }
    ],
    "sg:phone":"+1 270 869 0875",
    "sg:postcode":"42420",
    "sg:province":"KY",
    "sg:tags":[
        "establishment"
    ],
    "wof:name":"Bl North American Hard",
    "wof:placetype":"venue"
},
  "geometry": {"coordinates":[-87.591978,37.840205],"type":"Point"}
}