{
  "type": "Feature",
  "properties": {
    "iso:country":"US",
    "sg:address":"1923 Cedar Ridge Rd",
    "sg:city":"Bowling Green",
    "sg:classifiers":[
        {
            "category":"Banks & Credit Unions",
            "subcategory":"Financial Services",
            "type":"Services"
        }
    ],
    "sg:phone":"+1 270 781 1075",
    "sg:postcode":"42101",
    "sg:province":"KY",
    "sg:tags":[
        "company",
        "holding"
    ],
    "wof:name":"Pennsylvania Land Co Inc",
    "wof:placetype":"venue"
},
  "geometry": {"coordinates":[-86.462554,36.976921],"type":"Point"}
}