{
  "type": "Feature",
  "properties": {
    "iso:country":"US",
    "sg:address":"109 S 4th St",
    "sg:city":"Paducah",
    "sg:classifiers":[
        {
            "category":"Professional",
            "subcategory":"Lawyer & Legal Services",
            "type":"Services"
        }
    ],
    "sg:phone":"+1 270 444 6644",
    "sg:postcode":"42001",
    "sg:province":"KY",
    "sg:tags":[
        "attorney"
    ],
    "wof:name":"Craig Housman",
    "wof:placetype":"venue"
},
  "geometry": {"coordinates":[-88.598084,37.086601],"type":"Point"}
}