{
  "type": "Feature",
  "properties": {
    "iso:country":"US",
    "sg:address":"963 Old Preston Hwy S",
    "sg:city":"Shepherdsville",
    "sg:classifiers":[
        {
            "category":"Building & Trades",
            "subcategory":"Plumbing",
            "type":"Services"
        }
    ],
    "sg:phone":"+1 502 543 2127",
    "sg:postcode":"40165",
    "sg:province":"KY",
    "sg:tags":[
        "plumbing",
        "contractor"
    ],
    "wof:name":"Philip R Thompson Inc",
    "wof:placetype":"venue"
},
  "geometry": {"coordinates":[-85.71151999999999,37.977849],"type":"Point"}
}