{
  "type": "Feature",
  "properties": {
    "iso:country":"US",
    "sg:address":"4005 Shelbyville Rd",
    "sg:city":"Louisville",
    "sg:classifiers":[
        {
            "category":"Restaurant",
            "type":"Food & Drink"
        }
    ],
    "sg:menulink":"http://www.allmenus.com/ky/louisville-east/82557-snappy-tomato-pizza/menu/",
    "sg:phone":"+1 502 895 7511",
    "sg:postcode":"40207",
    "sg:province":"KY",
    "sg:tags":[
        "american",
        "pizza"
    ],
    "wof:name":"Snappy Tomato Pizza",
    "wof:placetype":"venue"
},
  "geometry": {"coordinates":[-85.652612,38.252636],"type":"Point"}
}