{
  "type": "Feature",
  "properties": {
    "addr:full":"4133 Shelbyville Rd St Matthews KY 40207",
    "addr:housenumber":"4133",
    "addr:postcode":"40207",
    "addr:street":"Shelbyville Rd",
    "iso:country":"US",
    "sg:address":"4133 Shelbyville Rd",
    "sg:city":"St Matthews",
    "sg:classifiers":[
        {
            "category":"Shopping",
            "subcategory":"Jewelry",
            "type":"Retail Goods"
        }
    ],
    "sg:phone":"+1 502 895 1175",
    "sg:postcode":"40207",
    "sg:province":"KY",
    "sg:tags":[
        "jeweler"
    ],
    "wof:name":"Cash America Pawn",
    "wof:placetype":"venue"
},
  "geometry": {"coordinates":[-85.642458,38.251923],"type":"Point"}
}