{
  "type": "Feature",
  "properties": {
    "iso:country":"US",
    "sg:address":"832 Meadow Crest Cir",
    "sg:city":"Washington",
    "sg:classifiers":[
        {
            "category":"Organizations",
            "subcategory":"Religious Organization",
            "type":"Services"
        }
    ],
    "sg:phone":"+1 606 759 7982",
    "sg:postcode":"41056",
    "sg:province":"KY",
    "sg:tags":[
        "church"
    ],
    "wof:name":"Trinity Methodist Church",
    "wof:placetype":"venue"
},
  "geometry": {"coordinates":[-83.82250500000001,38.614707],"type":"Point"}
}