{
  "type": "Feature",
  "properties": {
    "addr:full":"2345 State Hwy 181 Greenville KY 42345",
    "addr:housenumber":"2345",
    "addr:postcode":"42345",
    "addr:street":"State Hwy 181;Ky",
    "iso:country":"US",
    "sg:address":"2345 State Hwy 181",
    "sg:city":"Greenville",
    "sg:classifiers":[
        {
            "category":"Wholesale",
            "subcategory":"Scrap",
            "type":"Manufacturing & Wholesale Goods"
        }
    ],
    "sg:phone":"+1 270 338 3968",
    "sg:postcode":"42345",
    "sg:province":"KY",
    "sg:tags":[
        "recycling",
        "center"
    ],
    "wof:name":"Greenville Recycling Ctr",
    "wof:placetype":"venue"
},
  "geometry": {"coordinates":[-87.152687,37.176795],"type":"Point"}
}