{
  "type": "Feature",
  "properties": {
    "addr:city":"Georgetown",
    "addr:full":"229 E Main St Georgetown, Ky 40324-1759",
    "addr:house_number":"229",
    "addr:housenumber":"229",
    "addr:phone":"+1 502-863-6201",
    "addr:postcode":"40324-1759",
    "addr:road":"E Main St",
    "addr:state":"KY",
    "addr:street":"E Main St",
    "iso:country":"US",
    "sg:address":"229 E Main St",
    "sg:city":"Georgetown",
    "sg:classifiers":[
        {
            "category":"Recreation",
            "type":"Entertainment"
        }
    ],
    "sg:phone":"+1 502 863 6201",
    "sg:postcode":"40324",
    "sg:province":"KY",
    "sg:tags":[
        "amusement"
    ],
    "wof:airports":[
        102524721
    ],
    "wof:name":"Georgetown-Scott County Museum",
    "wof:placetype":"venue"
},
  "geometry": {"coordinates":[-84.55719000000001,38.20989],"type":"Point"}
}