{
  "type": "Feature",
  "properties": {
    "iso:country":"US",
    "sg:address":"229 E Main St",
    "sg:city":"Georgetown",
    "sg:classifiers":[
        {
            "category":"Recreation",
            "type":"Entertainment"
        }
    ],
    "sg:phone":"+1 502 863 6201",
    "sg:postcode":"40324",
    "sg:province":"KY",
    "sg:tags":[
        "amusement"
    ],
    "wof:name":"Georgetown Scott County Museum",
    "wof:placetype":"venue"
},
  "geometry": {"coordinates":[-84.557796,38.209908],"type":"Point"}
}