{
  "type": "Feature",
  "properties": {
    "addr:full":"75 Cavalier Blvd Florence KY 41042",
    "addr:housenumber":"75",
    "addr:postcode":"41042",
    "addr:street":"Cavalier Blvd",
    "iso:country":"US",
    "sg:address":"75 Cavalier Blvd",
    "sg:city":"Florence",
    "sg:classifiers":[
        {
            "category":"Shopping",
            "type":"Retail Goods"
        }
    ],
    "sg:phone":"+1 859 371 2350",
    "sg:postcode":"41042",
    "sg:province":"KY",
    "sg:tags":[
        "equipment",
        "telephone",
        "supply"
    ],
    "sg:website":"www.strategiccommunication.net",
    "wof:name":"Strategic Communications LLC",
    "wof:placetype":"venue"
},
  "geometry": {"coordinates":[-84.63321000000001,39.009164],"type":"Point"}
}