{
  "type": "Feature",
  "properties": {
    "iso:country":"US",
    "sg:address":"428 Madison Ave",
    "sg:city":"Covington",
    "sg:classifiers":[
        {
            "category":"Home & Garden",
            "subcategory":"Carpets & Floor Coverings",
            "type":"Retail Goods"
        }
    ],
    "sg:phone":"+1 859 261 9608",
    "sg:postcode":"41011",
    "sg:province":"KY",
    "sg:tags":[
        "dealer",
        "rug"
    ],
    "wof:name":"Earl Franks & Sons Flooring",
    "wof:placetype":"venue"
},
  "geometry": {"coordinates":[-84.510655,39.085897],"type":"Point"}
}