{
  "type": "Feature",
  "properties": {
    "addr:full":"232 W New Circle Rd Lexington KY 40505",
    "addr:housenumber":"232",
    "addr:postcode":"40505",
    "addr:street":"W New Circle Rd",
    "iso:country":"US",
    "sg:address":"232 W New Circle Rd",
    "sg:city":"Lexington",
    "sg:classifiers":[
        {
            "category":"Autos & Motor Vehicles",
            "subcategory":"Automobile Sales",
            "type":"Retail Goods"
        }
    ],
    "sg:phone":"+1 859 299 2772",
    "sg:postcode":"40505",
    "sg:province":"KY",
    "sg:tags":[
        "car",
        "dealer"
    ],
    "wof:name":"Rod Hatfield Chevrolet",
    "wof:placetype":"venue"
},
  "geometry": {"coordinates":[-84.47349199999999,38.068208],"type":"Point"}
}