{
  "type": "Feature",
  "properties": {
    "iso:country":"US",
    "sg:address":"2000 US Hwy 41",
    "sg:city":"Henderson",
    "sg:classifiers":[
        {
            "category":"Communications",
            "type":"Services"
        }
    ],
    "sg:phone":"+1 270 827 8122",
    "sg:postcode":"42420",
    "sg:province":"KY",
    "sg:tags":[
        "carrier"
    ],
    "wof:name":"CPMC",
    "wof:placetype":"venue"
},
  "geometry": {"coordinates":[-87.572344,37.867008],"type":"Point"}
}