{
  "type": "Feature",
  "properties": {
    "iso:country":"US",
    "sg:address":"2400 Alexandria Pike",
    "sg:city":"Southgate",
    "sg:classifiers":[
        {
            "category":"Wholesale",
            "subcategory":"Electrical",
            "type":"Manufacturing & Wholesale Goods"
        }
    ],
    "sg:phone":"+1 859 572 0000",
    "sg:postcode":"41071",
    "sg:province":"KY",
    "sg:tags":[
        "mobile",
        "telephone"
    ],
    "wof:name":"My Wireless",
    "wof:placetype":"venue"
},
  "geometry": {"coordinates":[-84.47139199999999,39.072556],"type":"Point"}
}