{
  "type": "Feature",
  "properties": {
    "addr:full":"120 N Eagle Creek Dr Lexington KY 40509",
    "addr:housenumber":"120",
    "addr:postcode":"40509",
    "addr:street":"N Eagle Creek Dr",
    "iso:country":"US",
    "sg:address":"120 N Eagle Creek Dr",
    "sg:city":"Lexington",
    "sg:classifiers":[
        {
            "category":"Health Services",
            "subcategory":"Doctor",
            "type":"Services"
        }
    ],
    "sg:phone":"+1 859 263 1280",
    "sg:postcode":"40509",
    "sg:province":"KY",
    "sg:tags":[
        "physician",
        "pediatrics",
        "surgeons",
        "internal",
        "medicine",
        "surgeon"
    ],
    "wof:name":"WMA Internal Medicine and Pediatrics",
    "wof:placetype":"venue"
},
  "geometry": {"coordinates":[-84.442183,37.998693],"type":"Point"}
}