{
  "type": "Feature",
  "properties": {
    "iso:country":"US",
    "sg:address":"2600 Paynes Mill Rd",
    "sg:city":"Versailles",
    "sg:classifiers":[
        {
            "category":"Professional",
            "subcategory":"Lawyer & Legal Services",
            "type":"Services"
        }
    ],
    "sg:phone":"+1 859 873 6166",
    "sg:postcode":"40383",
    "sg:province":"KY",
    "sg:tags":[
        "attorney"
    ],
    "wof:name":"Tavner B Dunlap",
    "wof:placetype":"venue"
},
  "geometry": {"coordinates":[-84.669794,38.068446],"type":"Point"}
}