{
  "type": "Feature",
  "properties": {
    "addr:full":"8404 Zelma Fields Ave Louisville KY 40228",
    "addr:housenumber":"8404",
    "addr:postcode":"40228",
    "addr:street":"Zelma Fields Ave",
    "iso:country":"US",
    "sg:address":"8404 Zelma Fields Ave",
    "sg:city":"Louisville",
    "sg:classifiers":[
        {
            "category":"Professional",
            "type":"Services"
        }
    ],
    "sg:phone":"+1 502 231 4040",
    "sg:postcode":"40228",
    "sg:province":"KY",
    "wof:name":"Wendy Peavler",
    "wof:placetype":"venue"
},
  "geometry": {"coordinates":[-85.604637,38.131156],"type":"Point"}
}