{
  "type": "Feature",
  "properties": {
    "addr:full":"8002 Shepherdsville Rd Okolona KY 40219",
    "addr:housenumber":"8002",
    "addr:postcode":"40219",
    "addr:street":"Shepherdsville Rd",
    "iso:country":"US",
    "sg:address":"8002 Shepherdsville Rd",
    "sg:city":"Okolona",
    "sg:classifiers":[
        {
            "category":"Shopping",
            "type":"Retail Goods"
        }
    ],
    "sg:phone":"+1 502 966 8694",
    "sg:postcode":"40219",
    "sg:province":"KY",
    "sg:tags":[
        "trophy",
        "medal",
        "award"
    ],
    "wof:name":"Awards America",
    "wof:placetype":"venue"
},
  "geometry": {"coordinates":[-85.65912400000001,38.133937],"type":"Point"}
}