{
  "type": "Feature",
  "properties": {
    "addr:full":"9109 Galene Dr Jeffersontown KY 40299",
    "addr:housenumber":"9109",
    "addr:postcode":"40299",
    "addr:street":"Galene Dr",
    "iso:country":"US",
    "sg:address":"9109 Galene Dr",
    "sg:city":"Jeffersontown",
    "sg:classifiers":[
        {
            "category":"Food & Beverages",
            "subcategory":"Candy",
            "type":"Retail Goods"
        }
    ],
    "sg:phone":"+1 502 267 1924",
    "sg:postcode":"40299",
    "sg:province":"KY",
    "sg:tags":[
        "popcorn",
        "supply"
    ],
    "sg:website":"www.knoopspopcorn.com",
    "wof:name":"Knoop's Popcorn Station Inc",
    "wof:placetype":"venue"
},
  "geometry": {"coordinates":[-85.58954300000001,38.198257],"type":"Point"}
}