{
  "type": "Feature",
  "properties": {
    "addr:full":"1940 Balls Hill Rd Nebo KY 42441",
    "addr:housenumber":"1940",
    "addr:postcode":"42441",
    "addr:street":"Balls Hill Rd",
    "iso:country":"US",
    "sg:address":"1940 Balls Hill Rd",
    "sg:city":"Nebo",
    "sg:classifiers":[
        {
            "category":"Building & Trades",
            "subcategory":"Construction",
            "type":"Services"
        }
    ],
    "sg:phone":"+1 270 249 3990",
    "sg:postcode":"42441",
    "sg:province":"KY",
    "sg:tags":[
        "home",
        "industrial",
        "general",
        "contractor"
    ],
    "wof:name":"Blanchard Construction Co",
    "wof:placetype":"venue"
},
  "geometry": {"coordinates":[-87.63567399999999,37.410776],"type":"Point"}
}