{
  "type": "Feature",
  "properties": {
    "iso:country":"US",
    "sg:address":"615 Bark Cove",
    "sg:city":"Owensboro",
    "sg:classifiers":[
        {
            "category":"Manufacturing",
            "subcategory":"Tools & Machinery",
            "type":"Manufacturing & Wholesale Goods"
        }
    ],
    "sg:phone":"+1 270 684 1084",
    "sg:postcode":"42303",
    "sg:province":"KY",
    "sg:tags":[
        "machine",
        "shop"
    ],
    "wof:name":"Toolco Inc",
    "wof:placetype":"venue"
},
  "geometry": {"coordinates":[-87.062957,37.7877],"type":"Point"}
}