{
  "type": "Feature",
  "properties": {
    "iso:country":"US",
    "sg:address":"1293 N Main St",
    "sg:city":"Monticello",
    "sg:classifiers":[
        {
            "category":"Health Services",
            "subcategory":"Doctor",
            "type":"Services"
        }
    ],
    "sg:phone":"+1 606 340 8825",
    "sg:postcode":"42633",
    "sg:province":"KY",
    "sg:tags":[
        "physician",
        "surgeon"
    ],
    "wof:name":"Rolling Hills Medical Ctr",
    "wof:placetype":"venue"
},
  "geometry": {"coordinates":[-84.836761,36.847913],"type":"Point"}
}