{
  "type": "Feature",
  "properties": {
    "iso:country":"US",
    "sg:address":"3703 Eastside Dr",
    "sg:city":"Louisville",
    "sg:classifiers":[
        {
            "category":"Personal",
            "type":"Services"
        }
    ],
    "sg:phone":"+1 502 744 4375",
    "sg:postcode":"40220",
    "sg:province":"KY",
    "sg:tags":[
        "facility",
        "banquet",
        "reception",
        "hall"
    ],
    "wof:name":"Ray's Tents",
    "wof:placetype":"venue"
},
  "geometry": {"coordinates":[-85.612264,38.20862],"type":"Point"}
}