{
  "type": "Feature",
  "properties": {
    "iso:country":"US",
    "sg:address":"96 Wells Fork Rd",
    "sg:city":"Viper",
    "sg:classifiers":[
        {
            "category":"Organizations",
            "subcategory":"Religious Organization",
            "type":"Services"
        }
    ],
    "sg:phone":"+1 606 436 2553",
    "sg:postcode":"41774",
    "sg:province":"KY",
    "sg:tags":[
        "clergy"
    ],
    "wof:name":"Larry D Caudill",
    "wof:placetype":"venue"
},
  "geometry": {"coordinates":[-83.20063500000001,37.153139],"type":"Point"}
}