{
  "type": "Feature",
  "properties": {
    "addr:full":"124 Marketplace Dr Lexington KY 40503",
    "addr:housenumber":"124",
    "addr:postcode":"40503",
    "addr:street":"Marketplace Dr",
    "iso:country":"US",
    "sg:address":"124 Marketplace Dr",
    "sg:city":"Lexington",
    "sg:classifiers":[
        {
            "category":"Restaurant",
            "type":"Food & Drink"
        }
    ],
    "sg:phone":"+1 859 971 9427",
    "sg:postcode":"40503",
    "sg:province":"KY",
    "sg:website":"www.ontheborder.com",
    "wof:name":"On The Border Mexican Cafe",
    "wof:placetype":"venue"
},
  "geometry": {"coordinates":[-84.53011100000001,37.978201],"type":"Point"}
}