{
  "type": "Feature",
  "properties": {
    "iso:country":"US",
    "sg:address":"300 Marimon Ave",
    "sg:city":"Harrodsburg",
    "sg:classifiers":[
        {
            "category":"Building & Trades",
            "subcategory":"Electrical",
            "type":"Services"
        }
    ],
    "sg:phone":"+1 859 734 9800",
    "sg:postcode":"40330",
    "sg:province":"KY",
    "sg:tags":[
        "electric",
        "contractor"
    ],
    "wof:name":"Commercial Electric Co",
    "wof:placetype":"venue"
},
  "geometry": {"coordinates":[-84.83870899999999,37.758895],"type":"Point"}
}