{
  "type": "Feature",
  "properties": {
    "addr:full":"749 Liberty Rd West Liberty KY 41472",
    "addr:housenumber":"749",
    "addr:postcode":"41472",
    "addr:street":"Liberty Rd",
    "iso:country":"US",
    "sg:address":"749 Liberty Rd",
    "sg:city":"West Liberty",
    "sg:classifiers":[
        {
            "category":"Shopping",
            "subcategory":"Catalog Store",
            "type":"Retail Goods"
        }
    ],
    "sg:phone":"+1 606 743 2131",
    "sg:postcode":"41472",
    "sg:province":"KY",
    "sg:tags":[
        "mail",
        "order"
    ],
    "wof:name":"J C Penney Catalog",
    "wof:placetype":"venue"
},
  "geometry": {"coordinates":[-83.275632,37.924564],"type":"Point"}
}