{
  "type": "Feature",
  "properties": {
    "iso:country":"US",
    "sg:address":"1732 Longbow Ct",
    "sg:city":"Clarksville",
    "sg:classifiers":[
        {
            "category":"Professional",
            "subcategory":"Management & Consulting",
            "type":"Services"
        }
    ],
    "sg:phone":"+1 931 906 9525",
    "sg:postcode":"37042",
    "sg:province":"KY",
    "sg:tags":[
        "business"
    ],
    "wof:name":"It Business Consulting",
    "wof:placetype":"venue"
},
  "geometry": {"coordinates":[-87.43892700000001,36.515462],"type":"Point"}
}