{
  "type": "Feature",
  "properties": {
    "addr:full":"1311 Monmouth St Newport KY 41071",
    "addr:housenumber":"1311",
    "addr:postcode":"41071",
    "addr:street":"Monmouth St",
    "iso:country":"US",
    "sg:address":"1311 Monmouth St",
    "sg:city":"Newport",
    "sg:classifiers":[
        {
            "category":"Shopping",
            "subcategory":"Clothing, Apparel, & Fashions",
            "type":"Retail Goods"
        }
    ],
    "sg:phone":"+1 859 261 7113",
    "sg:postcode":"41071",
    "sg:province":"KY",
    "wof:name":"Cato",
    "wof:placetype":"venue"
},
  "geometry": {"coordinates":[-84.48492899999999,39.084298],"type":"Point"}
}