{
  "type": "Feature",
  "properties": {
    "iso:country":"US",
    "sg:address":"2005 Park Central Ave",
    "sg:city":"Nicholasville",
    "sg:classifiers":[
        {
            "category":"Manufacturing",
            "subcategory":"Glass & Minerals",
            "type":"Manufacturing & Wholesale Goods"
        }
    ],
    "sg:phone":"+1 859 885 5950",
    "sg:postcode":"40356",
    "sg:province":"KY",
    "sg:tags":[
        "fabricator",
        "fiber"
    ],
    "wof:name":"Polymer Components",
    "wof:placetype":"venue"
},
  "geometry": {"coordinates":[-84.54805500000001,37.9359],"type":"Point"}
}