{
  "type": "Feature",
  "properties": {
    "iso:country":"US",
    "sg:address":"134 Temperance Rd",
    "sg:city":"Greensburg",
    "sg:classifiers":[
        {
            "category":"Wholesale",
            "subcategory":"Auto Parts",
            "type":"Manufacturing & Wholesale Goods"
        }
    ],
    "sg:phone":"+1 270 932 7417",
    "sg:postcode":"42743",
    "sg:province":"KY",
    "sg:tags":[
        "automobile",
        "rebuilt"
    ],
    "wof:name":"Paxton Auto Salvage",
    "wof:placetype":"venue"
},
  "geometry": {"coordinates":[-85.469396,37.212457],"type":"Point"}
}