{
  "type": "Feature",
  "properties": {
    "addr:full":"13060 Factory Ln Louisville KY 40245",
    "addr:housenumber":"13060",
    "addr:postcode":"40245",
    "addr:street":"Factory Ln",
    "iso:country":"US",
    "sg:address":"13060 Factory Ln",
    "sg:city":"Louisville",
    "sg:classifiers":[
        {
            "category":"Organizations",
            "subcategory":"Religious Organization",
            "type":"Services"
        }
    ],
    "sg:phone":"+1 502 241 2991",
    "sg:postcode":"40245",
    "sg:province":"KY",
    "sg:tags":[
        "church"
    ],
    "sg:website":"www.experiencegracefree.org",
    "wof:name":"Grace Evangelical Free Church",
    "wof:placetype":"venue"
},
  "geometry": {"coordinates":[-85.50695399999999,38.287614],"type":"Point"}
}