{
  "type": "Feature",
  "properties": {
    "iso:country":"US",
    "sg:address":"25 W 7th St",
    "sg:city":"Covington",
    "sg:classifiers":[
        {
            "category":"Restaurant",
            "type":"Food & Drink"
        }
    ],
    "sg:phone":"+1 859 655 4800",
    "sg:postcode":"41011",
    "sg:province":"KY",
    "sg:tags":[
        "banquet",
        "rooms"
    ],
    "wof:name":"Variety Room",
    "wof:placetype":"venue"
},
  "geometry": {"coordinates":[-84.511387,39.083143],"type":"Point"}
}