{
  "type": "Feature",
  "properties": {
    "iso:country":"US",
    "sg:address":"932 Campbellsville St",
    "sg:city":"Liberty",
    "sg:classifiers":[
        {
            "category":"Home & Garden",
            "subcategory":"Building Materials",
            "type":"Retail Goods"
        }
    ],
    "sg:phone":"+1 606 787 7151",
    "sg:postcode":"42539",
    "sg:province":"KY",
    "sg:tags":[
        "paint"
    ],
    "wof:name":"Green River Builders Supply",
    "wof:placetype":"venue"
},
  "geometry": {"coordinates":[-84.942555,37.319042],"type":"Point"}
}