{
  "type": "Feature",
  "properties": {
    "iso:country":"US",
    "sg:address":"2338 Ridge Rd",
    "sg:city":"Pendleton",
    "sg:classifiers":[
        {
            "category":"Museum",
            "subcategory":"Botanical Garden",
            "type":"Entertainment"
        }
    ],
    "sg:phone":"+1 502 225 9469",
    "sg:postcode":"40055",
    "sg:province":"KY",
    "wof:name":"Sassa Critters and Co",
    "wof:placetype":"venue"
},
  "geometry": {"coordinates":[-85.344478,38.496722],"type":"Point"}
}