{
  "type": "Feature",
  "properties": {
    "iso:country":"US",
    "sg:address":"617 Monmouth St",
    "sg:city":"Newport",
    "sg:classifiers":[
        {
            "category":"Shopping",
            "subcategory":"Clothing, Apparel, & Fashions",
            "type":"Retail Goods"
        }
    ],
    "sg:phone":"+1 859 261 4433",
    "sg:postcode":"41071",
    "sg:province":"KY",
    "sg:tags":[
        "dancing",
        "supply"
    ],
    "wof:name":"New Attitude",
    "wof:placetype":"venue"
},
  "geometry": {"coordinates":[-84.492475,39.090562],"type":"Point"}
}