{
  "type": "Feature",
  "properties": {
    "iso:country":"US",
    "sg:address":"100 N 12th St",
    "sg:city":"Murray",
    "sg:classifiers":[
        {
            "category":"Shopping",
            "subcategory":"Pharmacy",
            "type":"Retail Goods"
        }
    ],
    "sg:phone":"+1 270 753 2044",
    "sg:postcode":"42071",
    "sg:province":"KY",
    "wof:name":"CVS Pharmacy",
    "wof:placetype":"venue"
},
  "geometry": {"coordinates":[-88.315212,36.61164],"type":"Point"}
}