{
  "type": "Feature",
  "properties": {
    "iso:country":"US",
    "sg:address":"2575 Danville Rd",
    "sg:city":"Nicholasville",
    "sg:classifiers":[
        {
            "category":"Social Services",
            "type":"Services"
        }
    ],
    "sg:phone":"+1 859 881 5010",
    "sg:postcode":"40356",
    "sg:province":"KY",
    "sg:tags":[
        "pregnancy",
        "counseling",
        "information"
    ],
    "wof:name":"All Gods Children Inc",
    "wof:placetype":"venue"
},
  "geometry": {"coordinates":[-84.58761199999999,37.844416],"type":"Point"}
}