{
  "type": "Feature",
  "properties": {
    "addr:full":"1100 N Race St Glasgow KY 42141",
    "addr:housenumber":"1100",
    "addr:postcode":"42141",
    "addr:street":"N Race St",
    "iso:country":"US",
    "sg:address":"1100 N Race St",
    "sg:city":"Glasgow",
    "sg:classifiers":[
        {
            "category":"Organizations",
            "subcategory":"Religious Organization",
            "type":"Services"
        }
    ],
    "sg:phone":"+1 270 651 6164",
    "sg:postcode":"42141",
    "sg:province":"KY",
    "sg:tags":[
        "church"
    ],
    "sg:website":"www.firstchristianchurch.com",
    "wof:name":"First Christian Church",
    "wof:placetype":"venue"
},
  "geometry": {"coordinates":[-85.904134,37.008556],"type":"Point"}
}