{
  "type": "Feature",
  "properties": {
    "iso:country":"US",
    "sg:address":"6710 Shepherdsville Rd",
    "sg:city":"Louisville",
    "sg:classifiers":[
        {
            "category":"Retail",
            "subcategory":"Auto Repair",
            "type":"Services"
        }
    ],
    "sg:phone":"+1 502 969 8626",
    "sg:postcode":"40228",
    "sg:province":"KY",
    "sg:tags":[
        "repairing",
        "automobile"
    ],
    "wof:name":"Blunks Auto Svc",
    "wof:placetype":"venue"
},
  "geometry": {"coordinates":[-85.659761,38.152838],"type":"Point"}
}