{
  "type": "Feature",
  "properties": {
    "addr:full":"255 N Morgan St Morganfield KY 42437",
    "addr:housenumber":"255",
    "addr:postcode":"42437",
    "addr:street":"N Morgan St",
    "iso:country":"US",
    "sg:address":"255 N Morgan St",
    "sg:city":"Morganfield",
    "sg:classifiers":[
        {
            "category":"Retail",
            "subcategory":"Auto Repair",
            "type":"Services"
        }
    ],
    "sg:phone":"+1 270 389 4950",
    "sg:postcode":"42437",
    "sg:province":"KY",
    "sg:tags":[
        "station",
        "gasoline",
        "general"
    ],
    "wof:name":"Conoco",
    "wof:placetype":"venue"
},
  "geometry": {"coordinates":[-87.914816,37.685498],"type":"Point"}
}