{
  "type": "Feature",
  "properties": {
    "addr:full":"1185 Richardsville Rd Bowling Green KY 42101",
    "addr:housenumber":"1185",
    "addr:postcode":"42101",
    "addr:street":"Richardsville Rd",
    "iso:country":"US",
    "sg:address":"1185 Richardsville Rd",
    "sg:city":"Bowling Green",
    "sg:classifiers":[
        {
            "category":"Government",
            "subcategory":"Fire Station",
            "type":"Public Place"
        }
    ],
    "sg:phone":"+1 270 777 9991",
    "sg:postcode":"42101",
    "sg:province":"KY",
    "sg:tags":[
        "department"
    ],
    "wof:name":"Richardsville Vol Fire Dept",
    "wof:placetype":"venue"
},
  "geometry": {"coordinates":[-86.46388,37.096381],"type":"Point"}
}