{
  "type": "Feature",
  "properties": {
    "iso:country":"US",
    "sg:address":"107 Trafton St",
    "sg:city":"Lexington",
    "sg:classifiers":[
        {
            "category":"Retail",
            "subcategory":"Car Wash",
            "type":"Services"
        }
    ],
    "sg:phone":"+1 859 258 9682",
    "sg:postcode":"40504",
    "sg:province":"KY",
    "sg:tags":[
        "automobile",
        "detail",
        "clean"
    ],
    "wof:name":"Rickin Rides Auto Detailing",
    "wof:placetype":"venue"
},
  "geometry": {"coordinates":[-84.525379,38.052042],"type":"Point"}
}