{
  "type": "Feature",
  "properties": {
    "iso:country":"US",
    "sg:address":"920 S 12th St",
    "sg:city":"Murray",
    "sg:classifiers":[
        {
            "category":"Shopping",
            "subcategory":"Music",
            "type":"Retail Goods"
        }
    ],
    "sg:phone":"+1 270 753 8926",
    "sg:postcode":"42071",
    "sg:province":"KY",
    "sg:tags":[
        "compact",
        "record",
        "disc",
        "tape"
    ],
    "wof:name":"Terrapin Station",
    "wof:placetype":"venue"
},
  "geometry": {"coordinates":[-88.31533399999999,36.598873],"type":"Point"}
}