{
  "type": "Feature",
  "properties": {
    "iso:country":"US",
    "sg:address":"6094 Limaburg Rd",
    "sg:city":"Burlington",
    "sg:classifiers":[
        {
            "category":"Restaurant",
            "type":"Food & Drink"
        }
    ],
    "sg:menulink":"http://www.allmenus.com/ky/florence/90079-penn-station/menu/",
    "sg:phone":"+1 859 647 7366",
    "sg:postcode":"41005",
    "sg:province":"KY",
    "sg:tags":[
        "wrap",
        "american",
        "sandwich"
    ],
    "wof:name":"Penn Station",
    "wof:placetype":"venue"
},
  "geometry": {"coordinates":[-84.68782299999999,39.016813],"type":"Point"}
}