{
  "type": "Feature",
  "properties": {
    "iso:country":"US",
    "sg:address":"5157 N Mayo Trl",
    "sg:city":"Pikeville",
    "sg:classifiers":[
        {
            "category":"Shopping",
            "subcategory":"Gifts & Souvenirs",
            "type":"Retail Goods"
        }
    ],
    "sg:phone":"+1 606 432 5000",
    "sg:postcode":"41501",
    "sg:province":"KY",
    "sg:tags":[
        "shop"
    ],
    "wof:name":"J & T Photo Gifts",
    "wof:placetype":"venue"
},
  "geometry": {"coordinates":[-82.579711,37.536037],"type":"Point"}
}