{
  "type": "Feature",
  "properties": {
    "iso:country":"US",
    "sg:address":"3297 Carriage Ln",
    "sg:city":"Lexington",
    "sg:classifiers":[
        {
            "category":"Building & Trades",
            "subcategory":"Construction",
            "type":"Services"
        }
    ],
    "sg:phone":"+1 859 272 4261",
    "sg:postcode":"40517",
    "sg:province":"KY",
    "sg:tags":[
        "carpentry",
        "contractor"
    ],
    "wof:name":"Russell Rudd",
    "wof:placetype":"venue"
},
  "geometry": {"coordinates":[-84.46486899999999,37.985379],"type":"Point"}
}