{
  "type": "Feature",
  "properties": {
    "iso:country":"US",
    "sg:address":"10611 W Manslick Rd",
    "sg:city":"Fairdale",
    "sg:classifiers":[
        {
            "category":"Restaurant",
            "type":"Food & Drink"
        }
    ],
    "sg:phone":"+1 502 368 7744",
    "sg:postcode":"40118",
    "sg:province":"KY",
    "wof:name":"Wise Guy's Pizza",
    "wof:placetype":"venue"
},
  "geometry": {"coordinates":[-85.762181,38.108154],"type":"Point"}
}