{
  "type": "Feature",
  "properties": {
    "iso:country":"US",
    "sg:address":"256 Midland Trl",
    "sg:city":"Mt Sterling",
    "sg:classifiers":[
        {
            "category":"Freight",
            "type":"Transportation"
        }
    ],
    "sg:phone":"+1 859 498 8886",
    "sg:postcode":"40353",
    "sg:province":"KY",
    "sg:tags":[
        "trucking"
    ],
    "wof:name":"Dr Transportation",
    "wof:placetype":"venue"
},
  "geometry": {"coordinates":[-83.923034,38.080834],"type":"Point"}
}