{
  "type": "Feature",
  "properties": {
    "iso:country":"US",
    "sg:address":"4727 S L and N Tpke",
    "sg:city":"Magnolia",
    "sg:classifiers":[
        {
            "category":"Organizations",
            "subcategory":"Religious Organization",
            "type":"Services"
        }
    ],
    "sg:phone":"+1 270 324 3536",
    "sg:postcode":"42757",
    "sg:province":"KY",
    "sg:tags":[
        "church"
    ],
    "wof:name":"Magnolia Baptist Church",
    "wof:placetype":"venue"
},
  "geometry": {"coordinates":[-85.74038400000001,37.446697],"type":"Point"}
}