{
  "type": "Feature",
  "properties": {
    "iso:country":"US",
    "sg:address":"810 Barret Ave",
    "sg:city":"Louisville",
    "sg:classifiers":[
        {
            "category":"Government",
            "subcategory":"Office",
            "type":"Public Place"
        }
    ],
    "sg:phone":"+1 502 574 6596",
    "sg:postcode":"40204",
    "sg:province":"KY",
    "wof:name":"Jefferson County Coroner",
    "wof:placetype":"venue"
},
  "geometry": {"coordinates":[-85.732038,38.241558],"type":"Point"}
}