{
  "type": "Feature",
  "properties": {
    "addr:full":"305 E High St Lexington KY 40507",
    "addr:housenumber":"305",
    "addr:postcode":"40507",
    "addr:street":"E High St",
    "iso:country":"US",
    "sg:address":"305 E High St",
    "sg:city":"Lexington",
    "sg:classifiers":[
        {
            "category":"Retail",
            "subcategory":"Auto Repair",
            "type":"Services"
        }
    ],
    "sg:phone":"+1 859 254 1973",
    "sg:postcode":"40507",
    "sg:province":"KY",
    "sg:tags":[
        "repairing",
        "automobile",
        "general"
    ],
    "wof:name":"Perfect Auto Care Inc",
    "wof:placetype":"venue"
},
  "geometry": {"coordinates":[-84.494111,38.040407],"type":"Point"}
}