{
  "type": "Feature",
  "properties": {
    "iso:country":"US",
    "sg:address":"306 E 9th St",
    "sg:city":"Hopkinsville",
    "sg:classifiers":[
        {
            "category":"Government",
            "subcategory":"Office",
            "type":"Public Place"
        }
    ],
    "sg:phone":"+1 270 887 8365",
    "sg:postcode":"42240",
    "sg:province":"KY",
    "wof:name":"Christian County Historian",
    "wof:placetype":"venue"
},
  "geometry": {"coordinates":[-87.486025,36.864347],"type":"Point"}
}