{
  "type": "Feature",
  "properties": {
    "iso:country":"US",
    "sg:address":"146 N Triangle Ln",
    "sg:city":"Louisville",
    "sg:classifiers":[
        {
            "category":"Real Estate",
            "subcategory":"Real Estate Operator",
            "type":"Services"
        }
    ],
    "sg:phone":"+1 502 955 2088",
    "sg:postcode":"40229",
    "sg:province":"KY",
    "sg:tags":[
        "building",
        "apartment"
    ],
    "wof:name":"Brooks Run Apartments",
    "wof:placetype":"venue"
},
  "geometry": {"coordinates":[-85.696774,38.079929],"type":"Point"}
}