{
  "type": "Feature",
  "properties": {
    "iso:country":"US",
    "sg:address":"4740 Inman Dr",
    "sg:city":"Lexington",
    "sg:classifiers":[
        {
            "category":"Professional",
            "subcategory":"Business Services",
            "type":"Services"
        }
    ],
    "sg:phone":"+1 859 224 8474",
    "sg:postcode":"40513",
    "sg:province":"KY",
    "wof:name":"Suzanne Designs",
    "wof:placetype":"venue"
},
  "geometry": {"coordinates":[-84.593723,37.994244],"type":"Point"}
}