{
  "type": "Feature",
  "properties": {
    "iso:country":"US",
    "sg:address":"17 W 18th St",
    "sg:city":"Covington",
    "sg:classifiers":[
        {
            "category":"Autos & Motor Vehicles",
            "subcategory":"Automobile Sales",
            "type":"Retail Goods"
        }
    ],
    "sg:phone":"+1 859 291 7637",
    "sg:postcode":"41011",
    "sg:province":"KY",
    "sg:tags":[
        "classic"
    ],
    "wof:name":"Fanatics",
    "wof:placetype":"venue"
},
  "geometry": {"coordinates":[-84.50745000000001,39.069109],"type":"Point"}
}