{
  "type": "Feature",
  "properties": {
    "iso:country":"US",
    "sg:address":"1985 Little Barren Rd",
    "sg:city":"Greensburg",
    "sg:classifiers":[
        {
            "category":"Food & Beverages",
            "subcategory":"Groceries & Convenience Stores",
            "type":"Retail Goods"
        }
    ],
    "sg:phone":"+1 270 565 4756",
    "sg:postcode":"42743",
    "sg:province":"KY",
    "sg:tags":[
        "grocer"
    ],
    "wof:name":"Little Barren Grocery",
    "wof:placetype":"venue"
},
  "geometry": {"coordinates":[-85.603212,37.128799],"type":"Point"}
}