{
  "type": "Feature",
  "properties": {
    "addr:full":"1325 W Broadway Louisville KY 40203",
    "addr:housenumber":"1325",
    "addr:postcode":"40203",
    "addr:street":"W Broadway",
    "iso:country":"US",
    "sg:address":"1325 W Broadway",
    "sg:city":"Louisville",
    "sg:classifiers":[
        {
            "category":"Wholesale",
            "subcategory":"Machinery & Supplies",
            "type":"Manufacturing & Wholesale Goods"
        }
    ],
    "sg:phone":"+1 502 584 7354",
    "sg:postcode":"40203",
    "sg:province":"KY",
    "sg:tags":[
        "printer",
        "cartridge"
    ],
    "sg:website":"www.offsetsupply.com",
    "wof:name":"Reliable Litho & Photo Supply",
    "wof:placetype":"venue"
},
  "geometry": {"coordinates":[-85.77450399999999,38.248025],"type":"Point"}
}