{
  "type": "Feature",
  "properties": {
    "addr:full":"104 N Keeneland Dr Richmond KY 40475",
    "addr:housenumber":"104",
    "addr:postcode":"40475",
    "addr:street":"N Keeneland Dr",
    "iso:country":"US",
    "sg:address":"104 N Keeneland Dr",
    "sg:city":"Richmond",
    "sg:classifiers":[
        {
            "category":"Restaurant",
            "type":"Food & Drink"
        }
    ],
    "sg:menulink":"http://www.allmenus.com/ky/richmond/136353-waffle-house/menu/",
    "sg:phone":"+1 859 623 3255",
    "sg:postcode":"40475",
    "sg:province":"KY",
    "sg:tags":[
        "american"
    ],
    "wof:name":"Waffle House",
    "wof:placetype":"venue"
},
  "geometry": {"coordinates":[-84.31917199999999,37.776306],"type":"Point"}
}