{
  "type": "Feature",
  "properties": {
    "iso:country":"US",
    "sg:address":"1114 Bardstown Rd",
    "sg:city":"Louisville",
    "sg:classifiers":[
        {
            "category":"Restaurant",
            "type":"Food & Drink"
        }
    ],
    "sg:phone":"+1 502 584 3354",
    "sg:postcode":"40204",
    "sg:province":"KY",
    "wof:name":"Stevens & Stevens Deli",
    "wof:placetype":"venue"
},
  "geometry": {"coordinates":[-85.72031699999999,38.238016],"type":"Point"}
}