{
  "type": "Feature",
  "properties": {
    "iso:country":"US",
    "sg:address":"210 Summit Dr",
    "sg:city":"Paducah",
    "sg:classifiers":[
        {
            "category":"Building & Trades",
            "subcategory":"Electrical",
            "type":"Services"
        }
    ],
    "sg:phone":"+1 270 554 5014",
    "sg:postcode":"42003",
    "sg:province":"KY",
    "sg:tags":[
        "electric",
        "contractor"
    ],
    "wof:name":"Hayden Electric",
    "wof:placetype":"venue"
},
  "geometry": {"coordinates":[-88.630522,37.041124],"type":"Point"}
}