{
  "type": "Feature",
  "properties": {
    "iso:country":"US",
    "sg:address":"480 Lexington Rd",
    "sg:city":"Versailles",
    "sg:classifiers":[
        {
            "category":"Building & Trades",
            "subcategory":"Cleaning & Sanitation",
            "type":"Services"
        }
    ],
    "sg:phone":"+1 859 879 1145",
    "sg:postcode":"40383",
    "sg:province":"KY",
    "sg:tags":[
        "janitor"
    ],
    "wof:name":"Cleaning Specialist-Bluegrass",
    "wof:placetype":"venue"
},
  "geometry": {"coordinates":[-84.71607899999999,38.051063],"type":"Point"}
}