{
  "type": "Feature",
  "properties": {
    "iso:country":"US",
    "sg:address":"6386 London Pike Spr",
    "sg:city":"Philpot",
    "sg:classifiers":[
        {
            "category":"Building & Trades",
            "subcategory":"Construction",
            "type":"Services"
        }
    ],
    "sg:phone":"+1 270 729 4333",
    "sg:postcode":"42366",
    "sg:province":"KY",
    "sg:tags":[
        "home",
        "builder"
    ],
    "wof:name":"Rinaldi Contracting Inc",
    "wof:placetype":"venue"
},
  "geometry": {"coordinates":[-87.02477500000001,37.691135],"type":"Point"}
}