{
  "type": "Feature",
  "properties": {
    "iso:country":"US",
    "sg:address":"83 US Hwy 68 W",
    "sg:city":"Benton",
    "sg:classifiers":[
        {
            "category":"Food & Beverages",
            "subcategory":"Groceries & Convenience Stores",
            "type":"Retail Goods"
        }
    ],
    "sg:phone":"+1 270 527 1755",
    "sg:postcode":"42025",
    "sg:province":"KY",
    "wof:name":"Fivestar Foodmart",
    "wof:placetype":"venue"
},
  "geometry": {"coordinates":[-88.343705,36.925809],"type":"Point"}
}