{
  "type": "Feature",
  "properties": {
    "iso:country":"US",
    "sg:address":"7222 State Hwy 56",
    "sg:city":"Owensboro",
    "sg:classifiers":[
        {
            "category":"Organizations",
            "subcategory":"Religious Organization",
            "type":"Services"
        }
    ],
    "sg:phone":"+1 270 771 4436",
    "sg:postcode":"42301",
    "sg:province":"KY",
    "sg:tags":[
        "church"
    ],
    "wof:name":"St Mary Magdalene Church",
    "wof:placetype":"venue"
},
  "geometry": {"coordinates":[-87.253449,37.749647],"type":"Point"}
}