{
  "type": "Feature",
  "properties": {
    "addr:full":"720 Oakwood Dr Hartford KY 42347",
    "addr:housenumber":"720",
    "addr:postcode":"42347",
    "addr:street":"Oakwood Dr",
    "iso:country":"US",
    "sg:address":"720 Oakwood Dr",
    "sg:city":"Hartford",
    "sg:classifiers":[
        {
            "category":"Personal",
            "subcategory":"Beauty Salon",
            "type":"Services"
        }
    ],
    "sg:phone":"+1 270 298 4722",
    "sg:postcode":"42347",
    "sg:province":"KY",
    "sg:tags":[
        "shop"
    ],
    "wof:name":"Sues Beauty Shop",
    "wof:placetype":"venue"
},
  "geometry": {"coordinates":[-86.901022,37.455563],"type":"Point"}
}