{
  "type": "Feature",
  "properties": {
    "addr:full":"2517 N Friendship Rd Paducah KY 42001",
    "addr:housenumber":"2517",
    "addr:postcode":"42001",
    "addr:street":"N Friendship Rd",
    "iso:country":"US",
    "sg:address":"2517 N Friendship Rd",
    "sg:city":"Paducah",
    "sg:classifiers":[
        {
            "category":"Health Services",
            "subcategory":"Health Practitioner",
            "type":"Services"
        }
    ],
    "sg:phone":"+1 270 534 8828",
    "sg:postcode":"42001",
    "sg:province":"KY",
    "sg:tags":[
        "pathologist",
        "speech"
    ],
    "wof:name":"All'Bout Children's Success",
    "wof:placetype":"venue"
},
  "geometry": {"coordinates":[-88.688492,37.06061],"type":"Point"}
}