{
  "type": "Feature",
  "properties": {
    "iso:country":"US",
    "sg:address":"331 Vanderbilt Dr",
    "sg:city":"Bowling Green",
    "sg:classifiers":[
        {
            "category":"Manufacturing",
            "subcategory":"Tools & Machinery",
            "type":"Manufacturing & Wholesale Goods"
        }
    ],
    "sg:phone":"+1 270 842 6195",
    "sg:postcode":"42103",
    "sg:province":"KY",
    "sg:tags":[
        "bearing"
    ],
    "sg:website":"www.motion.com",
    "wof:name":"Motion Industries Inc",
    "wof:placetype":"venue"
},
  "geometry": {"coordinates":[-86.404777,36.92702],"type":"Point"}
}