{
  "type": "Feature",
  "properties": {
    "iso:country":"US",
    "sg:address":"3129 Weymouth Ct",
    "sg:city":"Lexington",
    "sg:classifiers":[
        {
            "category":"Professional",
            "subcategory":"Business Services",
            "type":"Services"
        }
    ],
    "sg:phone":"+1 859 543 9930",
    "sg:postcode":"40509",
    "sg:province":"KY",
    "wof:name":"Tc Enterprises",
    "wof:placetype":"venue"
},
  "geometry": {"coordinates":[-84.418446,38.012927],"type":"Point"}
}