{
  "type": "Feature",
  "properties": {
    "iso:country":"US",
    "sg:address":"4880 Houston Rd",
    "sg:city":"Florence",
    "sg:classifiers":[
        {
            "category":"Travel",
            "subcategory":"Hotels & Motels",
            "type":"Entertainment"
        },
        {
            "category":"Real Estate",
            "subcategory":"Real Estate Operator",
            "type":"Services"
        }
    ],
    "sg:phone":"+1 859 525 9997",
    "sg:postcode":"41042",
    "sg:province":"KY",
    "sg:tags":[
        "apartment"
    ],
    "sg:website":"www.ashleyquarters.com",
    "wof:name":"Ashley Quarters",
    "wof:placetype":"venue"
},
  "geometry": {"coordinates":[-84.63159899999999,39.0186],"type":"Point"}
}