{
  "type": "Feature",
  "properties": {
    "addr:full":"116 N Main St Franklin KY 42134",
    "addr:housenumber":"116",
    "addr:postcode":"42134",
    "addr:street":"N Main St",
    "iso:country":"US",
    "sg:address":"116 N Main St",
    "sg:city":"Franklin",
    "sg:classifiers":[
        {
            "category":"Shopping",
            "type":"Retail Goods"
        }
    ],
    "sg:phone":"+1 270 586 6990",
    "sg:postcode":"42134",
    "sg:province":"KY",
    "sg:tags":[
        "trophy",
        "plaque"
    ],
    "wof:name":"Trophy Shop",
    "wof:placetype":"venue"
},
  "geometry": {"coordinates":[-86.577776,36.722927],"type":"Point"}
}