{
  "type": "Feature",
  "properties": {
    "iso:country":"US",
    "sg:address":"2331 Woodhill Dr",
    "sg:city":"Lexington",
    "sg:classifiers":[
        {
            "category":"Bars & Pubs",
            "type":"Food & Drink"
        }
    ],
    "sg:phone":"+1 859 266 0911",
    "sg:postcode":"40509",
    "sg:province":"KY",
    "wof:name":"Club Liquid",
    "wof:placetype":"venue"
},
  "geometry": {"coordinates":[-84.45552600000001,38.017555],"type":"Point"}
}