{
  "type": "Feature",
  "properties": {
    "addr:full":"1542 Clay St Henderson KY 42420",
    "addr:housenumber":"1542",
    "addr:postcode":"42420",
    "addr:street":"Clay St",
    "iso:country":"US",
    "sg:address":"1542 Clay St",
    "sg:city":"Henderson",
    "sg:classifiers":[
        {
            "category":"Autos & Motor Vehicles",
            "subcategory":"Automobile Sales",
            "type":"Retail Goods"
        }
    ],
    "sg:phone":"+1 270 827 4933",
    "sg:postcode":"42420",
    "sg:province":"KY",
    "sg:tags":[
        "car",
        "dealer"
    ],
    "wof:name":"Southside Auto Sales",
    "wof:placetype":"venue"
},
  "geometry": {"coordinates":[-87.578441,37.8249],"type":"Point"}
}