{
  "type": "Feature",
  "properties": {
    "iso:country":"US",
    "sg:address":"1029 W Russell St",
    "sg:city":"Elkhorn City",
    "sg:classifiers":[
        {
            "category":"Autos & Motor Vehicles",
            "subcategory":"Fuel & Gas Station",
            "type":"Retail Goods"
        }
    ],
    "sg:phone":"+1 606 754 8827",
    "sg:postcode":"41522",
    "sg:province":"KY",
    "sg:tags":[
        "oil"
    ],
    "wof:name":"Jack's Garage",
    "wof:placetype":"venue"
},
  "geometry": {"coordinates":[-82.36233,37.295762],"type":"Point"}
}