{
  "type": "Feature",
  "properties": {
    "addr:full":"1595 Hustonville Rd Danville KY 40422",
    "addr:housenumber":"1595",
    "addr:postcode":"40422",
    "addr:street":"Hustonville Rd",
    "iso:country":"US",
    "sg:address":"1595 Hustonville Rd",
    "sg:city":"Danville",
    "sg:classifiers":[
        {
            "category":"Home & Garden",
            "subcategory":"Carpets & Floor Coverings",
            "type":"Retail Goods"
        }
    ],
    "sg:phone":"+1 859 238 7100",
    "sg:postcode":"40422",
    "sg:province":"KY",
    "sg:tags":[
        "material"
    ],
    "wof:name":"Magic Carpet Floor Covering",
    "wof:placetype":"venue"
},
  "geometry": {"coordinates":[-84.77467300000001,37.621384],"type":"Point"}
}