{
  "type": "Feature",
  "properties": {
    "iso:country":"US",
    "sg:address":"110 N Water St",
    "sg:city":"Henderson",
    "sg:classifiers":[
        {
            "category":"Health Services",
            "subcategory":"Doctor",
            "type":"Services"
        }
    ],
    "sg:phone":"+1 270 827 2080",
    "sg:postcode":"42420",
    "sg:province":"KY",
    "sg:tags":[
        "physician",
        "surgeon"
    ],
    "wof:name":"Pravin C Mehta MD",
    "wof:placetype":"venue"
},
  "geometry": {"coordinates":[-87.593523,37.840624],"type":"Point"}
}