{
  "type": "Feature",
  "properties": {
    "iso:country":"US",
    "sg:address":"421 Winterberry Ct",
    "sg:city":"Versailles",
    "sg:classifiers":[
        {
            "category":"Building & Trades",
            "subcategory":"Plumbing",
            "type":"Services"
        }
    ],
    "sg:phone":"+1 859 873 6336",
    "sg:postcode":"40383",
    "sg:province":"KY",
    "sg:tags":[
        "plumbing",
        "contractor"
    ],
    "wof:name":"John Hackney Plumbing",
    "wof:placetype":"venue"
},
  "geometry": {"coordinates":[-84.730217,38.067862],"type":"Point"}
}