{
  "type": "Feature",
  "properties": {
    "iso:country":"US",
    "sg:address":"109 S 15th St",
    "sg:city":"Murray",
    "sg:classifiers":[
        {
            "category":"Social Services",
            "subcategory":"Child Care",
            "type":"Services"
        }
    ],
    "sg:phone":"+1 270 753 5227",
    "sg:postcode":"42071",
    "sg:province":"KY",
    "wof:name":"Wee Care Child Development Ctr",
    "wof:placetype":"venue"
},
  "geometry": {"coordinates":[-88.321817,36.60957],"type":"Point"}
}