{
  "type": "Feature",
  "properties": {
    "iso:country":"US",
    "sg:address":"805 Middle Fork Rd",
    "sg:city":"Asher",
    "sg:classifiers":[
        {
            "category":"Health Services",
            "subcategory":"Hospital",
            "type":"Services"
        }
    ],
    "sg:phone":"+1 606 374 3393",
    "sg:postcode":"40874",
    "sg:province":"KY",
    "wof:name":"Beech Fork Clinic",
    "wof:placetype":"venue"
},
  "geometry": {"coordinates":[-83.428513,37.014737],"type":"Point"}
}