{
  "type": "Feature",
  "properties": {
    "iso:country":"US",
    "sg:address":"8408 Mary Ct",
    "sg:city":"Crestwood",
    "sg:classifiers":[
        {
            "category":"Personal",
            "type":"Services"
        }
    ],
    "sg:phone":"+1 502 243 3868",
    "sg:postcode":"40014",
    "sg:province":"KY",
    "wof:name":"Kalyptra Ltd",
    "wof:placetype":"venue"
},
  "geometry": {"coordinates":[-85.510515,38.32753],"type":"Point"}
}