{
  "type": "Feature",
  "properties": {
    "iso:country":"US",
    "sg:address":"11385 Liberty Rd",
    "sg:city":"Elk Horn",
    "sg:classifiers":[
        {
            "category":"Personal",
            "subcategory":"Beauty Salon",
            "type":"Services"
        }
    ],
    "sg:phone":"+1 270 789 0505",
    "sg:postcode":"42733",
    "sg:province":"KY",
    "wof:name":"Echo Valley Cut & Style",
    "wof:placetype":"venue"
},
  "geometry": {"coordinates":[-85.172955,37.360398],"type":"Point"}
}