{
  "type": "Feature",
  "properties": {
    "iso:country":"US",
    "sg:address":"370 Webb Rd",
    "sg:city":"Franklin",
    "sg:phone":"+1 270 586 6482",
    "sg:postcode":"42134",
    "sg:province":"KY",
    "sg:tags":[
        "farm",
        "grain",
        "cash"
    ],
    "wof:name":"Mike Stratton",
    "wof:placetype":"venue"
},
  "geometry": {"coordinates":[-86.483828,36.668153],"type":"Point"}
}