{
  "type": "Feature",
  "properties": {
    "iso:country":"US",
    "sg:address":"1121 Bardstown Rd",
    "sg:city":"Louisville",
    "sg:classifiers":[
        {
            "category":"Personal",
            "subcategory":"Beauty Salon",
            "type":"Services"
        }
    ],
    "sg:phone":"+1 502 451 9100",
    "sg:postcode":"40204",
    "sg:province":"KY",
    "wof:name":"Salon Bacco",
    "wof:placetype":"venue"
},
  "geometry": {"coordinates":[-85.720151,38.238083],"type":"Point"}
}