{
  "type": "Feature",
  "properties": {
    "iso:country":"US",
    "sg:address":"380 Shorland Dr",
    "sg:city":"Walton",
    "sg:classifiers":[
        {
            "category":"Manufacturing",
            "subcategory":"Retail Goods",
            "type":"Manufacturing & Wholesale Goods"
        }
    ],
    "sg:phone":"+1 859 485 9300",
    "sg:postcode":"41094",
    "sg:province":"KY",
    "sg:tags":[
        "manufacturer"
    ],
    "wof:name":"Specialty Products Plant",
    "wof:placetype":"venue"
},
  "geometry": {"coordinates":[-84.613637,38.922853],"type":"Point"}
}