{
  "type": "Feature",
  "properties": {
    "addr:full":"974 Diederich Blvd Russell KY 41169",
    "addr:housenumber":"974",
    "addr:postcode":"41169",
    "addr:street":"Diederich Blvd",
    "iso:country":"US",
    "sg:address":"974 Diederich Blvd",
    "sg:city":"Russell",
    "sg:classifiers":[
        {
            "category":"Insurance",
            "subcategory":"Insurance Agent",
            "type":"Services"
        }
    ],
    "sg:phone":"+1 606 836 9673",
    "sg:postcode":"41169",
    "sg:province":"KY",
    "wof:name":"Allstate Insurance",
    "wof:placetype":"venue"
},
  "geometry": {"coordinates":[-82.68402500000001,38.504235],"type":"Point"}
}