{
  "type": "Feature",
  "properties": {
    "iso:country":"US",
    "sg:address":"1241 Maysville Rd",
    "sg:city":"Scottsville",
    "sg:classifiers":[
        {
            "category":"Retail",
            "subcategory":"Repair Shop",
            "type":"Services"
        },
        {
            "category":"Manufacturing",
            "subcategory":"Wood Products",
            "type":"Manufacturing & Wholesale Goods"
        }
    ],
    "sg:phone":"+1 270 622 4150",
    "sg:postcode":"42164",
    "sg:province":"KY",
    "sg:tags":[
        "picture",
        "framing",
        "mfg"
    ],
    "wof:name":"Copas Frame & Craft Shop",
    "wof:placetype":"venue"
},
  "geometry": {"coordinates":[-86.164241,36.74413],"type":"Point"}
}