{
  "type": "Feature",
  "properties": {
    "iso:country":"US",
    "sg:address":"222 W Main St",
    "sg:city":"Danville",
    "sg:classifiers":[
        {
            "category":"Professional",
            "subcategory":"Business Services",
            "type":"Services"
        }
    ],
    "sg:phone":"+1 859 236 0224",
    "sg:postcode":"40422",
    "sg:province":"KY",
    "sg:tags":[
        "embroidery"
    ],
    "wof:name":"Thoroughbred Threads",
    "wof:placetype":"venue"
},
  "geometry": {"coordinates":[-84.77215700000001,37.645718],"type":"Point"}
}