{
  "type": "Feature",
  "properties": {
    "addr:full":"2929 Dixie Hwy Crestview Hills KY 41017",
    "addr:housenumber":"2929",
    "addr:postcode":"41017",
    "addr:street":"Dixie Hwy",
    "iso:country":"US",
    "sg:address":"2929 Dixie Hwy",
    "sg:city":"Crestview Hills",
    "sg:classifiers":[
        {
            "category":"Shopping",
            "subcategory":"Shoes",
            "type":"Retail Goods"
        }
    ],
    "sg:phone":"+1 859 341 1401",
    "sg:postcode":"41017",
    "sg:province":"KY",
    "wof:name":"Payless Shoe Source",
    "wof:placetype":"venue"
},
  "geometry": {"coordinates":[-84.58283900000001,39.024911],"type":"Point"}
}