{
  "type": "Feature",
  "properties": {
    "iso:country":"US",
    "sg:address":"372 Smallwood Rd",
    "sg:city":"Stanton",
    "sg:classifiers":[
        {
            "category":"Building & Trades",
            "subcategory":"Construction",
            "type":"Services"
        }
    ],
    "sg:phone":"+1 606 663 2917",
    "sg:postcode":"40380",
    "sg:province":"KY",
    "sg:tags":[
        "contractor"
    ],
    "wof:name":"Sons Contracting",
    "wof:placetype":"venue"
},
  "geometry": {"coordinates":[-83.845061,37.866177],"type":"Point"}
}