{
  "type": "Feature",
  "properties": {
    "iso:country":"US",
    "sg:address":"141 N Main St",
    "sg:city":"Williamstown",
    "sg:classifiers":[
        {
            "category":"Social Services",
            "type":"Services"
        }
    ],
    "sg:phone":"+1 859 824 7697",
    "sg:postcode":"41097",
    "sg:province":"KY",
    "wof:name":"Hot Line",
    "wof:placetype":"venue"
},
  "geometry": {"coordinates":[-84.56052099999999,38.638054],"type":"Point"}
}