{
  "type": "Feature",
  "properties": {
    "iso:country":"US",
    "sg:address":"643 Cecil Ave",
    "sg:city":"Louisville",
    "sg:classifiers":[
        {
            "category":"Professional",
            "subcategory":"Business Services",
            "type":"Services"
        }
    ],
    "sg:phone":"+1 502 778 7167",
    "sg:postcode":"40211",
    "sg:province":"KY",
    "wof:name":"Krown Enterprises",
    "wof:placetype":"venue"
},
  "geometry": {"coordinates":[-85.82127699999999,38.25044],"type":"Point"}
}