{
  "type": "Feature",
  "properties": {
    "iso:country":"US",
    "sg:address":"830 Bondurant Ln",
    "sg:city":"Benton",
    "sg:classifiers":[
        {
            "category":"Farming",
            "subcategory":"Farm & Veterinary Services",
            "type":"Manufacturing & Wholesale Goods"
        }
    ],
    "sg:phone":"+1 270 527 1773",
    "sg:postcode":"42025",
    "sg:province":"KY",
    "sg:tags":[
        "livestock"
    ],
    "wof:name":"Bivin Farms",
    "wof:placetype":"venue"
},
  "geometry": {"coordinates":[-88.42982600000001,36.842994],"type":"Point"}
}