{
  "type": "Feature",
  "properties": {
    "addr:full":"6307 Preston Hwy Louisville KY 40219",
    "addr:housenumber":"6307",
    "addr:postcode":"40219",
    "addr:street":"Preston Hwy",
    "iso:country":"US",
    "sg:address":"6307 Preston Hwy",
    "sg:city":"Louisville",
    "sg:classifiers":[
        {
            "category":"Autos & Motor Vehicles",
            "subcategory":"Automobile Sales",
            "type":"Retail Goods"
        }
    ],
    "sg:phone":"+1 502 961 0814",
    "sg:postcode":"40219",
    "sg:province":"KY",
    "sg:tags":[
        "used",
        "car",
        "dealers-used",
        "new",
        "cars-wholesale"
    ],
    "wof:name":"Noel's Auto Sales",
    "wof:placetype":"venue"
},
  "geometry": {"coordinates":[-85.698441,38.159491],"type":"Point"}
}