{
  "type": "Feature",
  "properties": {
    "iso:country":"US",
    "sg:address":"2405 Fluhr Ln",
    "sg:city":"Louisville",
    "sg:classifiers":[
        {
            "category":"Freight",
            "type":"Transportation"
        }
    ],
    "sg:phone":"+1 502 448 1342",
    "sg:postcode":"40216",
    "sg:province":"KY",
    "sg:tags":[
        "operator",
        "local",
        "trucking"
    ],
    "wof:name":"Houchin Trucking Co Inc",
    "wof:placetype":"venue"
},
  "geometry": {"coordinates":[-85.83999,38.166304],"type":"Point"}
}