{
  "type": "Feature",
  "properties": {
    "addr:full":"9000 Limehouse Ln Louisville Louisville KY 40220",
    "addr:housenumber":"9000",
    "addr:postcode":"40220",
    "addr:street":"Limehouse Ln",
    "iso:country":"US",
    "sg:address":"9000 Limehouse Ln Louisville",
    "sg:city":"Louisville",
    "sg:classifiers":[
        {
            "category":"Organizations",
            "subcategory":"Membership Organization",
            "type":"Services"
        }
    ],
    "sg:phone":"+1 502 491 9127",
    "sg:postcode":"40220",
    "sg:province":"KY",
    "sg:tags":[
        "club",
        "private"
    ],
    "sg:website":"http://www.oxmoorcc.com",
    "wof:name":"Oxmoor Country Club Pool",
    "wof:placetype":"venue"
},
  "geometry": {"coordinates":[-85.60317999999999,38.22818],"type":"Point"}
}