{
  "type": "Feature",
  "properties": {
    "addr:full":"2516 Scottsville Rd Bowling Green KY 42104",
    "addr:housenumber":"2516",
    "addr:postcode":"42104",
    "addr:street":"Scottsville Rd",
    "iso:country":"US",
    "sg:address":"2516 Scottsville Rd",
    "sg:city":"Bowling Green",
    "sg:classifiers":[
        {
            "category":"Home & Garden",
            "subcategory":"Building Materials",
            "type":"Retail Goods"
        }
    ],
    "sg:phone":"+1 270 781 7901",
    "sg:postcode":"42104",
    "sg:province":"KY",
    "sg:tags":[
        "glass",
        "window",
        "plate"
    ],
    "wof:name":"A G Glass Co",
    "wof:placetype":"venue"
},
  "geometry": {"coordinates":[-86.425963,36.952537],"type":"Point"}
}