{
  "type": "Feature",
  "properties": {
    "iso:country":"US",
    "sg:address":"1670 S 17th St",
    "sg:city":"Louisville",
    "sg:classifiers":[
        {
            "category":"Bars & Pubs",
            "type":"Food & Drink"
        }
    ],
    "sg:phone":"+1 502 772 0607",
    "sg:postcode":"40210",
    "sg:province":"KY",
    "wof:name":"Steve's Bar & Grill Inc",
    "wof:placetype":"venue"
},
  "geometry": {"coordinates":[-85.78496,38.226898],"type":"Point"}
}