{
  "type": "Feature",
  "properties": {
    "iso:country":"US",
    "sg:address":"624 N 4th St",
    "sg:city":"Murray",
    "sg:classifiers":[
        {
            "category":"Retail",
            "subcategory":"Auto Repair",
            "type":"Services"
        }
    ],
    "sg:phone":"+1 270 753 0593",
    "sg:postcode":"42071",
    "sg:province":"KY",
    "sg:tags":[
        "machine",
        "automobile",
        "shop"
    ],
    "wof:name":"Gary's Engine Machine Shop",
    "wof:placetype":"venue"
},
  "geometry": {"coordinates":[-88.30189799999999,36.62255],"type":"Point"}
}