{
  "type": "Feature",
  "properties": {
    "iso:country":"US",
    "sg:address":"3435 US Hwy 27",
    "sg:city":"Somerset",
    "sg:classifiers":[
        {
            "category":"Autos & Motor Vehicles",
            "subcategory":"Automobile Sales",
            "type":"Retail Goods"
        }
    ],
    "sg:phone":"+1 606 678 8936",
    "sg:postcode":"42501",
    "sg:province":"KY",
    "sg:tags":[
        "car",
        "dealer"
    ],
    "wof:name":"Hall Glenn W Used Cars",
    "wof:placetype":"venue"
},
  "geometry": {"coordinates":[-84.618319,37.07443],"type":"Point"}
}