{
  "type": "Feature",
  "properties": {
    "addr:full":"9716 Nordic Dr Louisville KY 40272",
    "addr:housenumber":"9716",
    "addr:postcode":"40272",
    "addr:street":"Nordic Dr",
    "iso:country":"US",
    "sg:address":"9716 Nordic Dr",
    "sg:city":"Louisville",
    "sg:classifiers":[
        {
            "category":"Wholesale",
            "subcategory":"Machinery & Supplies",
            "type":"Manufacturing & Wholesale Goods"
        }
    ],
    "sg:phone":"+1 502 933 8567",
    "sg:postcode":"40272",
    "sg:province":"KY",
    "sg:tags":[
        "cleaning"
    ],
    "wof:name":"D & H Pressure Wash Inc",
    "wof:placetype":"venue"
},
  "geometry": {"coordinates":[-85.834711,38.112001],"type":"Point"}
}