{
  "type": "Feature",
  "properties": {
    "iso:country":"US",
    "sg:address":"1235 Paris Rd",
    "sg:city":"Mayfield",
    "sg:classifiers":[
        {
            "category":"Shopping",
            "subcategory":"Used Merchandise",
            "type":"Retail Goods"
        }
    ],
    "sg:phone":"+1 270 251 2500",
    "sg:postcode":"42066",
    "sg:province":"KY",
    "sg:tags":[
        "shop",
        "thrift"
    ],
    "wof:name":"Goodwill Industries",
    "wof:placetype":"venue"
},
  "geometry": {"coordinates":[-88.628293,36.724367],"type":"Point"}
}