{
  "type": "Feature",
  "properties": {
    "addr:full":"201 E Jefferson St Louisville KY 40202",
    "addr:housenumber":"201",
    "addr:postcode":"40202",
    "addr:street":"E Jefferson St",
    "iso:country":"US",
    "sg:address":"201 E Jefferson St",
    "sg:city":"Louisville",
    "sg:classifiers":[
        {
            "category":"Health Services",
            "subcategory":"Doctor",
            "type":"Services"
        }
    ],
    "sg:phone":"+1 502 569 2065",
    "sg:postcode":"40202",
    "sg:province":"KY",
    "sg:tags":[
        "physician",
        "surgeon"
    ],
    "wof:name":"Iasis",
    "wof:placetype":"venue"
},
  "geometry": {"coordinates":[-85.75039700000001,38.253139],"type":"Point"}
}