{
  "type": "Feature",
  "properties": {
    "iso:country":"US",
    "sg:address":"420 US Hwy 62",
    "sg:city":"Princeton",
    "sg:classifiers":[
        {
            "category":"Restaurant",
            "type":"Food & Drink"
        }
    ],
    "sg:phone":"+1 270 365 9920",
    "sg:postcode":"42445",
    "sg:province":"KY",
    "wof:name":"Great Wall",
    "wof:placetype":"venue"
},
  "geometry": {"coordinates":[-87.87993899999999,37.112038],"type":"Point"}
}