{
  "type": "Feature",
  "properties": {
    "addr:full":"3830 Ruckriegel Pkwy Jeffersontown KY 40299",
    "addr:housenumber":"3830",
    "addr:postcode":"40299",
    "addr:street":"Ruckriegel Pkwy",
    "iso:country":"US",
    "sg:address":"3830 Ruckriegel Pkwy",
    "sg:city":"Jeffersontown",
    "sg:classifiers":[
        {
            "category":"Professional",
            "subcategory":"Accounting & Tax Preparation",
            "type":"Services"
        }
    ],
    "sg:phone":"+1 502 267 9900",
    "sg:postcode":"40299",
    "sg:province":"KY",
    "sg:tags":[
        "return",
        "filing"
    ],
    "wof:name":"Jackson Hewitt Tax Svc",
    "wof:placetype":"venue"
},
  "geometry": {"coordinates":[-85.566298,38.188954],"type":"Point"}
}