{
  "type": "Feature",
  "properties": {
    "addr:full":"1718 Bardstown Rd Louisville KY 40205",
    "addr:housenumber":"1718",
    "addr:postcode":"40205",
    "addr:street":"Bardstown Rd",
    "iso:country":"US",
    "sg:address":"1718 Bardstown Rd",
    "sg:city":"Louisville",
    "sg:classifiers":[
        {
            "category":"Banks & Credit Unions",
            "subcategory":"Investment Brokerage",
            "type":"Services"
        },
        {
            "category":"Banks & Credit Unions",
            "subcategory":"Bank",
            "type":"Services"
        },
        {
            "category":"Banks & Credit Unions",
            "subcategory":"Financial Services",
            "type":"Services"
        }
    ],
    "sg:phone":"+1 502 566 2161",
    "sg:postcode":"40205",
    "sg:province":"KY",
    "sg:tags":[
        "loan"
    ],
    "sg:website":"https://www.chase.com",
    "wof:name":"Chase -Highland Deerwood",
    "wof:placetype":"venue"
},
  "geometry": {"coordinates":[-85.703209,38.229839],"type":"Point"}
}