{
  "type": "Feature",
  "properties": {
    "iso:country":"US",
    "sg:address":"204 Tedford Ct",
    "sg:city":"Fort Knox",
    "sg:classifiers":[
        {
            "category":"Professional",
            "subcategory":"Computer Services",
            "type":"Services"
        }
    ],
    "sg:phone":"+1 502 942 7933",
    "sg:postcode":"40121",
    "sg:province":"KY",
    "sg:tags":[
        "related"
    ],
    "wof:name":"Barbara Wiley",
    "wof:placetype":"venue"
},
  "geometry": {"coordinates":[-85.974216,37.887761],"type":"Point"}
}