{
  "type": "Feature",
  "properties": {
    "iso:country":"US",
    "sg:address":"150 Kentucky St",
    "sg:city":"Vine Grove",
    "sg:classifiers":[
        {
            "category":"Building & Trades",
            "subcategory":"Construction",
            "type":"Services"
        }
    ],
    "sg:phone":"+1 270 828 6708",
    "sg:postcode":"40175",
    "sg:province":"KY",
    "sg:tags":[
        "general",
        "contractor"
    ],
    "wof:name":"Dunbar's Framing & Carpentry",
    "wof:placetype":"venue"
},
  "geometry": {"coordinates":[-85.979029,37.807302],"type":"Point"}
}