{
  "type": "Feature",
  "properties": {
    "iso:country":"US",
    "sg:address":"7560 Red River Rd",
    "sg:city":"Winchester",
    "sg:classifiers":[
        {
            "category":"Farming",
            "subcategory":"Farm",
            "type":"Manufacturing & Wholesale Goods"
        }
    ],
    "sg:phone":"+1 859 745 4281",
    "sg:postcode":"40391",
    "sg:province":"KY",
    "wof:name":"Fred A Devary",
    "wof:placetype":"venue"
},
  "geometry": {"coordinates":[-84.07781,37.867492],"type":"Point"}
}