{
  "type": "Feature",
  "properties": {
    "iso:country":"US",
    "sg:address":"804 Stone Creek Pkwy",
    "sg:city":"Louisville",
    "sg:classifiers":[
        {
            "category":"Real Estate",
            "subcategory":"Real Estate Services",
            "type":"Services"
        },
        {
            "category":"Professional",
            "subcategory":"Research",
            "type":"Services"
        },
        {
            "category":"Insurance",
            "subcategory":"Title Insurance",
            "type":"Services"
        }
    ],
    "sg:phone":"+1 502 420 9980",
    "sg:postcode":"40223",
    "sg:province":"KY",
    "sg:tags":[
        "abstracter",
        "management"
    ],
    "wof:name":"Integrity Title Services",
    "wof:placetype":"venue"
},
  "geometry": {"coordinates":[-85.57408599999999,38.235639],"type":"Point"}
}