{
  "type": "Feature",
  "properties": {
    "addr:full":"5001 Harrodsburg Rd Nicholasville KY 40356",
    "addr:housenumber":"5001",
    "addr:postcode":"40356",
    "addr:street":"Harrodsburg Rd",
    "iso:country":"US",
    "sg:address":"5001 Harrodsburg Rd",
    "sg:city":"Nicholasville",
    "sg:classifiers":[
        {
            "category":"Organizations",
            "subcategory":"Religious Organization",
            "type":"Services"
        }
    ],
    "sg:phone":"+1 859 224 1600",
    "sg:postcode":"40356",
    "sg:province":"KY",
    "sg:tags":[
        "church"
    ],
    "sg:website":"www.southlandchristian.org",
    "wof:name":"Southland Christian Chr Crprt",
    "wof:placetype":"venue"
},
  "geometry": {"coordinates":[-84.596158,37.963468],"type":"Point"}
}