{
  "type": "Feature",
  "properties": {
    "iso:country":"US",
    "sg:address":"781 Crooked Creek Dr",
    "sg:city":"London",
    "sg:classifiers":[
        {
            "category":"Professional",
            "type":"Services"
        }
    ],
    "sg:phone":"+1 606 877 1664",
    "sg:postcode":"40744",
    "sg:province":"KY",
    "sg:tags":[
        "establishment"
    ],
    "wof:name":"Crooked Creek Swimming Pool",
    "wof:placetype":"venue"
},
  "geometry": {"coordinates":[-84.02627,37.084604],"type":"Point"}
}