{
  "type": "Feature",
  "properties": {
    "iso:country":"US",
    "sg:address":"4106 Summertime Pkwy",
    "sg:city":"Louisville",
    "sg:classifiers":[
        {
            "category":"Building & Trades",
            "subcategory":"Cleaning & Sanitation",
            "type":"Services"
        }
    ],
    "sg:phone":"+1 502 418 7254",
    "sg:postcode":"40272",
    "sg:province":"KY",
    "sg:tags":[
        "maintenance"
    ],
    "wof:name":"Cynthia A Lega",
    "wof:placetype":"venue"
},
  "geometry": {"coordinates":[-85.873698,38.072395],"type":"Point"}
}