{
  "type": "Feature",
  "properties": {
    "addr:full":"809 Time Dr Owensboro KY 42303",
    "addr:housenumber":"809",
    "addr:postcode":"42303",
    "addr:street":"Time Dr",
    "iso:country":"US",
    "sg:address":"809 Time Dr",
    "sg:city":"Owensboro",
    "sg:classifiers":[
        {
            "category":"Personal",
            "subcategory":"Beauty Salon",
            "type":"Services"
        }
    ],
    "sg:phone":"+1 270 685 1236",
    "sg:postcode":"42303",
    "sg:province":"KY",
    "wof:name":"Guys & Dolls Hair Do",
    "wof:placetype":"venue"
},
  "geometry": {"coordinates":[-87.121449,37.731223],"type":"Point"}
}