{
  "type": "Feature",
  "properties": {
    "addr:full":"29 Carousel Rd Mayking KY 41837",
    "addr:housenumber":"29",
    "addr:postcode":"41837",
    "addr:street":"Carousel Rd",
    "iso:country":"US",
    "sg:address":"29 Carousel Rd",
    "sg:city":"Mayking",
    "sg:classifiers":[
        {
            "category":"Shopping",
            "subcategory":"Jewelry",
            "type":"Retail Goods"
        }
    ],
    "sg:phone":"+1 606 632 0583",
    "sg:postcode":"41837",
    "sg:province":"KY",
    "wof:name":"De Vaughns Jewelry Box",
    "wof:placetype":"venue"
},
  "geometry": {"coordinates":[-82.743117,37.126239],"type":"Point"}
}