{
  "type": "Feature",
  "properties": {
    "iso:country":"US",
    "sg:address":"4546 Taylorsville Rd",
    "sg:city":"Louisville",
    "sg:classifiers":[
        {
            "category":"Health Services",
            "subcategory":"Chiropractor",
            "type":"Services"
        }
    ],
    "sg:phone":"+1 502 493 1040",
    "sg:postcode":"40220",
    "sg:province":"KY",
    "wof:name":"Spine Ctr",
    "wof:placetype":"venue"
},
  "geometry": {"coordinates":[-85.598795,38.218381],"type":"Point"}
}