{
  "type": "Feature",
  "properties": {
    "addr:full":"849 S Liberty Church Rd Clarksville KY 37042",
    "addr:housenumber":"849",
    "addr:postcode":"37042",
    "addr:street":"S Liberty Church Rd",
    "iso:country":"US",
    "sg:address":"849 S Liberty Church Rd",
    "sg:city":"Clarksville",
    "sg:classifiers":[
        {
            "category":"Education",
            "subcategory":"School",
            "type":"Public Place"
        }
    ],
    "sg:phone":"+1 931 905 5729",
    "sg:postcode":"37042",
    "sg:province":"KY",
    "sg:website":"www.cmcss.net",
    "wof:name":"Liberty Elementary School",
    "wof:placetype":"venue"
},
  "geometry": {"coordinates":[-87.45089400000001,36.5498],"type":"Point"}
}