{
  "type": "Feature",
  "properties": {
    "iso:country":"US",
    "sg:address":"128 E White Oak St",
    "sg:city":"Leitchfield",
    "sg:classifiers":[
        {
            "category":"Government",
            "subcategory":"Jail",
            "type":"Public Place"
        }
    ],
    "sg:phone":"+1 270 259 3636",
    "sg:postcode":"42754",
    "sg:province":"KY",
    "sg:tags":[
        "county",
        "govt",
        "institution"
    ],
    "wof:name":"Grayson County Jail",
    "wof:placetype":"venue"
},
  "geometry": {"coordinates":[-86.293065,37.477215],"type":"Point"}
}