{
  "type": "Feature",
  "properties": {
    "addr:full":"2701 S 4th St Louisville KY 40208",
    "addr:housenumber":"2701",
    "addr:postcode":"40208",
    "addr:street":"S 4Th St",
    "iso:country":"US",
    "sg:address":"2701 S 4th St",
    "sg:city":"Louisville",
    "sg:classifiers":[
        {
            "category":"Shopping",
            "subcategory":"Pharmacy",
            "type":"Retail Goods"
        }
    ],
    "sg:phone":"+1 502 636 2631",
    "sg:postcode":"40208",
    "sg:province":"KY",
    "sg:website":"www.walgreens.com",
    "wof:name":"Walgreens",
    "wof:placetype":"venue"
},
  "geometry": {"coordinates":[-85.764883,38.209021],"type":"Point"}
}