{
  "type": "Feature",
  "properties": {
    "iso:country":"US",
    "sg:address":"3106 Marlin Rd",
    "sg:city":"Louisville",
    "sg:classifiers":[
        {
            "category":"Professional",
            "subcategory":"Management & Consulting",
            "type":"Services"
        }
    ],
    "sg:phone":"+1 502 479 5525",
    "sg:postcode":"40220",
    "sg:province":"KY",
    "wof:name":"Sheila H Josnston",
    "wof:placetype":"venue"
},
  "geometry": {"coordinates":[-85.61229299999999,38.213208],"type":"Point"}
}