{
  "type": "Feature",
  "properties": {
    "iso:country":"US",
    "sg:address":"215 W Main St",
    "sg:city":"Lexington",
    "sg:classifiers":[
        {
            "category":"Museum",
            "type":"Entertainment"
        }
    ],
    "sg:phone":"+1 859 254 0530",
    "sg:postcode":"40507",
    "sg:province":"KY",
    "sg:website":"www.lexingtonhistorymuseum.org",
    "wof:name":"Lexington History Museum",
    "wof:placetype":"venue"
},
  "geometry": {"coordinates":[-84.49839299999999,38.04768],"type":"Point"}
}