{
  "type": "Feature",
  "properties": {
    "addr:city":"Lexington",
    "addr:full":"215 W Main St Lexington, Ky 40507-1305",
    "addr:house_number":"215",
    "addr:housenumber":"215",
    "addr:postcode":"40507-1305",
    "addr:road":"W Main St",
    "addr:state":"KY",
    "addr:street":"W Main St",
    "iso:country":"US",
    "sg:address":"215 W Main St",
    "sg:city":"Lexington",
    "sg:classifiers":[
        {
            "category":"Museum",
            "type":"Entertainment"
        }
    ],
    "sg:phone":"+1 859 254 0530",
    "sg:postcode":"40507",
    "sg:province":"KY",
    "sg:website":"www.lexingtonhistorymuseum.org",
    "wof:airports":[
        102524721
    ],
    "wof:name":"Lexington History Museum",
    "wof:placetype":"venue"
},
  "geometry": {"coordinates":[-84.49824,38.04747],"type":"Point"}
}