{
  "type": "Feature",
  "properties": {
    "addr:full":"2960 Breckenridge Ln Louisville KY 40220",
    "addr:housenumber":"2960",
    "addr:postcode":"40220",
    "addr:street":"Breckenridge Ln",
    "iso:country":"US",
    "sg:address":"2960 Breckenridge Ln",
    "sg:city":"Louisville",
    "sg:classifiers":[
        {
            "category":"Fast Food",
            "type":"Food & Drink"
        },
        {
            "category":"Restaurant",
            "type":"Food & Drink"
        }
    ],
    "sg:phone":"+1 502 456 4261",
    "sg:postcode":"40220",
    "sg:province":"KY",
    "sg:tags":[
        "american",
        "style",
        "seafood",
        "family"
    ],
    "sg:website":"http://www.captainds.com",
    "wof:name":"Captain D's Seafood Kitchen",
    "wof:placetype":"venue"
},
  "geometry": {"coordinates":[-85.630252,38.219877],"type":"Point"}
}