{
  "type": "Feature",
  "properties": {
    "iso:country":"US",
    "sg:address":"5565 Old Lebanon Rd",
    "sg:city":"Campbellsville",
    "sg:classifiers":[
        {
            "category":"Home & Garden",
            "subcategory":"Carpets & Floor Coverings",
            "type":"Retail Goods"
        }
    ],
    "sg:phone":"+1 270 465 3008",
    "sg:postcode":"42718",
    "sg:province":"KY",
    "sg:tags":[
        "dealer",
        "rug"
    ],
    "wof:name":"Brockman Carpets Inc",
    "wof:placetype":"venue"
},
  "geometry": {"coordinates":[-85.368555,37.413066],"type":"Point"}
}