{
  "type": "Feature",
  "properties": {
    "iso:country":"US",
    "sg:address":"1000 Diederich Blvd",
    "sg:city":"Russell",
    "sg:classifiers":[
        {
            "category":"Professional",
            "type":"Services"
        }
    ],
    "sg:phone":"+1 606 833 5731",
    "sg:postcode":"41169",
    "sg:province":"KY",
    "wof:name":"A Tm Svc",
    "wof:placetype":"venue"
},
  "geometry": {"coordinates":[-82.692959,38.5045],"type":"Point"}
}