{
  "type": "Feature",
  "properties": {
    "iso:country":"US",
    "sg:address":"8 Muirfield Pl",
    "sg:city":"Louisville",
    "sg:classifiers":[
        {
            "category":"Insurance",
            "subcategory":"Insurance Agent",
            "type":"Services"
        }
    ],
    "sg:phone":"+1 502 423 1144",
    "sg:postcode":"40222",
    "sg:province":"KY",
    "wof:name":"Schneider & Assoc",
    "wof:placetype":"venue"
},
  "geometry": {"coordinates":[-85.584833,38.240159],"type":"Point"}
}