{
  "type": "Feature",
  "properties": {
    "iso:country":"US",
    "sg:address":"87 Upper Elcomb Dr",
    "sg:city":"Harlan",
    "sg:classifiers":[
        {
            "category":"Freight",
            "type":"Transportation"
        }
    ],
    "sg:phone":"+1 606 573 4185",
    "sg:postcode":"40831",
    "sg:province":"KY",
    "sg:tags":[
        "hauling",
        "trucking"
    ],
    "wof:name":"Red River Trucking",
    "wof:placetype":"venue"
},
  "geometry": {"coordinates":[-83.340214,36.816447],"type":"Point"}
}