{
  "type": "Feature",
  "properties": {
    "addr:full":"210 Main St Augusta KY 41002",
    "addr:housenumber":"210",
    "addr:postcode":"41002",
    "addr:street":"Main St",
    "iso:country":"US",
    "sg:address":"210 Main St",
    "sg:city":"Augusta",
    "sg:classifiers":[
        {
            "category":"Personal",
            "subcategory":"Beauty Salon",
            "type":"Services"
        }
    ],
    "sg:phone":"+1 606 756 3664",
    "sg:postcode":"41002",
    "sg:province":"KY",
    "wof:name":"Cuttin Loose",
    "wof:placetype":"venue"
},
  "geometry": {"coordinates":[-84.007576,38.772951],"type":"Point"}
}