{
  "type": "Feature",
  "properties": {
    "iso:country":"US",
    "sg:address":"10301 Stone School Rd",
    "sg:city":"Prospect",
    "sg:classifiers":[
        {
            "category":"Professional",
            "subcategory":"Research",
            "type":"Services"
        }
    ],
    "sg:phone":"+1 502 425 5608",
    "sg:postcode":"40059",
    "sg:province":"KY",
    "sg:tags":[
        "environmental",
        "ecological"
    ],
    "wof:name":"ERM Cvs",
    "wof:placetype":"venue"
},
  "geometry": {"coordinates":[-85.557525,38.324235],"type":"Point"}
}