{
  "type": "Feature",
  "properties": {
    "iso:country":"US",
    "sg:address":"3705 Mattingly Rd",
    "sg:city":"Buckner",
    "sg:classifiers":[
        {
            "category":"Manufacturing",
            "subcategory":"Tools & Machinery",
            "type":"Manufacturing & Wholesale Goods"
        }
    ],
    "sg:phone":"+1 502 222 5764",
    "sg:postcode":"40010",
    "sg:province":"KY",
    "sg:tags":[
        "machine",
        "shop"
    ],
    "wof:name":"Toolcraft Co",
    "wof:placetype":"venue"
},
  "geometry": {"coordinates":[-85.43867299999999,38.379032],"type":"Point"}
}