{
  "type": "Feature",
  "properties": {
    "addr:full":"3209 Clintonville Rd Winchester KY 40391",
    "addr:housenumber":"3209",
    "addr:postcode":"40391",
    "addr:street":"Clintonville Rd",
    "iso:country":"US",
    "sg:address":"3209 Clintonville Rd",
    "sg:city":"Winchester",
    "sg:classifiers":[
        {
            "category":"Building & Trades",
            "subcategory":"Construction",
            "type":"Services"
        }
    ],
    "sg:phone":"+1 859 745 1439",
    "sg:postcode":"40391",
    "sg:province":"KY",
    "sg:tags":[
        "contractor"
    ],
    "wof:name":"Ronald Mc Peek Custom Homes",
    "wof:placetype":"venue"
},
  "geometry": {"coordinates":[-84.27041199999999,38.066621],"type":"Point"}
}