{
  "type": "Feature",
  "properties": {
    "iso:country":"US",
    "sg:address":"6090 Hurricane Rd",
    "sg:city":"Pikeville",
    "sg:classifiers":[
        {
            "category":"Utilities",
            "subcategory":"Natural Gas",
            "type":"Services"
        }
    ],
    "sg:phone":"+1 606 478 9683",
    "sg:postcode":"41501",
    "sg:province":"KY",
    "sg:tags":[
        "company"
    ],
    "wof:name":"Columbia Gas",
    "wof:placetype":"venue"
},
  "geometry": {"coordinates":[-82.61696000000001,37.530457],"type":"Point"}
}