{
  "type": "Feature",
  "properties": {
    "iso:country":"US",
    "sg:address":"565 Maple St",
    "sg:city":"Stanton",
    "sg:classifiers":[
        {
            "category":"Building & Trades",
            "subcategory":"Construction",
            "type":"Services"
        }
    ],
    "sg:phone":"+1 606 663 1516",
    "sg:postcode":"40380",
    "sg:province":"KY",
    "sg:tags":[
        "home",
        "builder"
    ],
    "wof:name":"Huber's Home Remodeling & Rpr",
    "wof:placetype":"venue"
},
  "geometry": {"coordinates":[-83.867383,37.85488],"type":"Point"}
}