{
  "type": "Feature",
  "properties": {
    "iso:country":"US",
    "sg:address":"165 Autumn Way",
    "sg:city":"Bowling Green",
    "sg:classifiers":[
        {
            "category":"Professional",
            "subcategory":"Computer Services",
            "type":"Services"
        }
    ],
    "sg:phone":"+1 270 842 5582",
    "sg:postcode":"42104",
    "sg:province":"KY",
    "sg:tags":[
        "related"
    ],
    "wof:name":"J&L Computer Services",
    "wof:placetype":"venue"
},
  "geometry": {"coordinates":[-86.422456,36.877871],"type":"Point"}
}