{
  "type": "Feature",
  "properties": {
    "iso:country":"US",
    "sg:address":"546 Park St",
    "sg:city":"Bowling Green",
    "sg:classifiers":[
        {
            "category":"Health Services",
            "subcategory":"Doctor",
            "type":"Services"
        }
    ],
    "sg:phone":"+1 270 843 5103",
    "sg:postcode":"42101",
    "sg:province":"KY",
    "sg:tags":[
        "physician",
        "surgeon"
    ],
    "wof:name":"Psychiatric Associates",
    "wof:placetype":"venue"
},
  "geometry": {"coordinates":[-86.43434999999999,36.9937],"type":"Point"}
}