{
  "type": "Feature",
  "properties": {
    "iso:country":"US",
    "sg:address":"1160 Neale Trl",
    "sg:city":"Murray",
    "sg:classifiers":[
        {
            "category":"Real Estate",
            "subcategory":"Real Estate Operator",
            "type":"Services"
        }
    ],
    "sg:phone":"+1 270 753 5499",
    "sg:postcode":"42071",
    "sg:province":"KY",
    "sg:tags":[
        "property",
        "lessor"
    ],
    "wof:name":"Tommy Parker",
    "wof:placetype":"venue"
},
  "geometry": {"coordinates":[-88.268591,36.568662],"type":"Point"}
}