{
  "type": "Feature",
  "properties": {
    "iso:country":"US",
    "sg:address":"2151 Old Frankfort Pike",
    "sg:city":"Lexington",
    "sg:classifiers":[
        {
            "category":"Government",
            "subcategory":"Office",
            "type":"Public Place"
        }
    ],
    "sg:phone":"+1 859 246 2059",
    "sg:postcode":"40510",
    "sg:province":"KY",
    "sg:tags":[
        "state",
        "program"
    ],
    "wof:name":"Transportation Dept Mntnc",
    "wof:placetype":"venue"
},
  "geometry": {"coordinates":[-84.552879,38.066051],"type":"Point"}
}