{
  "type": "Feature",
  "properties": {
    "iso:country":"US",
    "sg:address":"7746 3rd Street Rd",
    "sg:city":"Louisville",
    "sg:classifiers":[
        {
            "category":"Professional",
            "subcategory":"Management & Consulting",
            "type":"Services"
        }
    ],
    "sg:phone":"+1 502 361 2500",
    "sg:postcode":"40214",
    "sg:province":"KY",
    "wof:name":"Aacm Inc",
    "wof:placetype":"venue"
},
  "geometry": {"coordinates":[-85.789283,38.134292],"type":"Point"}
}