{
  "type": "Feature",
  "properties": {
    "iso:country":"US",
    "sg:address":"12394 State Hwy 39",
    "sg:city":"Somerset",
    "sg:classifiers":[
        {
            "category":"Wholesale",
            "subcategory":"Farm Supplies",
            "type":"Manufacturing & Wholesale Goods"
        }
    ],
    "sg:phone":"+1 606 379 6212",
    "sg:postcode":"42503",
    "sg:province":"KY",
    "wof:name":"D & J Farm Supply",
    "wof:placetype":"venue"
},
  "geometry": {"coordinates":[-84.50102699999999,37.299474],"type":"Point"}
}