{
  "type": "Feature",
  "properties": {
    "iso:country":"US",
    "sg:address":"101 Burnett Rd",
    "sg:city":"Williamsburg",
    "sg:classifiers":[
        {
            "category":"Organizations",
            "subcategory":"Religious Organization",
            "type":"Services"
        }
    ],
    "sg:phone":"+1 606 549 8772",
    "sg:postcode":"40769",
    "sg:province":"KY",
    "wof:name":"Apostolic Light House Church",
    "wof:placetype":"venue"
},
  "geometry": {"coordinates":[-84.15146900000001,36.75464],"type":"Point"}
}