{
  "type": "Feature",
  "properties": {
    "iso:country":"US",
    "sg:address":"8228 Orangeburg Rd",
    "sg:city":"Maysville",
    "sg:classifiers":[
        {
            "category":"Organizations",
            "subcategory":"Religious Organization",
            "type":"Services"
        }
    ],
    "sg:phone":"+1 606 759 5752",
    "sg:postcode":"41056",
    "sg:province":"KY",
    "sg:tags":[
        "clergy"
    ],
    "wof:name":"James Robinson",
    "wof:placetype":"venue"
},
  "geometry": {"coordinates":[-83.715244,38.611705],"type":"Point"}
}