{
  "type": "Feature",
  "properties": {
    "iso:country":"US",
    "sg:address":"563 Country Club Ct",
    "sg:city":"Winchester",
    "sg:classifiers":[
        {
            "category":"Building & Trades",
            "subcategory":"Landscaping Services",
            "type":"Services"
        }
    ],
    "sg:phone":"+1 859 745 6187",
    "sg:postcode":"40391",
    "sg:province":"KY",
    "wof:name":"Simpsons Tree Service",
    "wof:placetype":"venue"
},
  "geometry": {"coordinates":[-84.195105,37.973321],"type":"Point"}
}