{
  "type": "Feature",
  "properties": {
    "addr:full":"401 Madison Square Dr Madisonville KY 42431",
    "addr:housenumber":"401",
    "addr:postcode":"42431",
    "addr:street":"Madison Square Dr",
    "iso:country":"US",
    "sg:address":"401 Madison Square Dr",
    "sg:city":"Madisonville",
    "sg:classifiers":[
        {
            "category":"Shopping",
            "subcategory":"Department Store",
            "type":"Retail Goods"
        }
    ],
    "sg:phone":"+1 270 825 1907",
    "sg:postcode":"42431",
    "sg:province":"KY",
    "wof:name":"Dawahare's",
    "wof:placetype":"venue"
},
  "geometry": {"coordinates":[-87.480797,37.326868],"type":"Point"}
}