{
  "type": "Feature",
  "properties": {
    "iso:country":"US",
    "sg:address":"3708 Dearman Ct",
    "sg:city":"Lexington",
    "sg:classifiers":[
        {
            "category":"Organizations",
            "subcategory":"Religious Organization",
            "type":"Services"
        }
    ],
    "sg:phone":"+1 859 543 0602",
    "sg:postcode":"40509",
    "sg:province":"KY",
    "sg:tags":[
        "clergy"
    ],
    "wof:name":"Felix F Williams III",
    "wof:placetype":"venue"
},
  "geometry": {"coordinates":[-84.414046,37.993394],"type":"Point"}
}