{
  "type": "Feature",
  "properties": {
    "addr:full":"481 Moody Dr Maysville KY 41056",
    "addr:housenumber":"481",
    "addr:postcode":"41056",
    "addr:street":"Moody Dr",
    "iso:country":"US",
    "sg:address":"481 Moody Dr",
    "sg:city":"Maysville",
    "sg:classifiers":[
        {
            "category":"Retail",
            "subcategory":"Portrait Studio",
            "type":"Services"
        }
    ],
    "sg:phone":"+1 606 564 9527",
    "sg:postcode":"41056",
    "sg:province":"KY",
    "sg:tags":[
        "photographer"
    ],
    "wof:name":"Photo Shoppe",
    "wof:placetype":"venue"
},
  "geometry": {"coordinates":[-83.77522399999999,38.641244],"type":"Point"}
}