{
  "type": "Feature",
  "properties": {
    "addr:full":"7101 Intermodal Dr Louisville KY 40258",
    "addr:housenumber":"7101",
    "addr:postcode":"40258",
    "addr:street":"Intermodal Dr",
    "iso:country":"US",
    "sg:address":"7101 Intermodal Dr",
    "sg:city":"Louisville",
    "sg:classifiers":[
        {
            "category":"Manufacturing",
            "subcategory":"Toys & Sporting Goods",
            "type":"Manufacturing & Wholesale Goods"
        }
    ],
    "sg:phone":"+1 502 935 5505",
    "sg:postcode":"40258",
    "sg:province":"KY",
    "sg:tags":[
        "goods-wholesale",
        "manufacturer"
    ],
    "sg:website":"http://www.finishingplusinc.com",
    "wof:name":"Scorpion Sports, Inc.",
    "wof:placetype":"venue"
},
  "geometry": {"coordinates":[-85.885704,38.157348],"type":"Point"}
}