{
  "type": "Feature",
  "properties": {
    "addr:full":"34 S Adams St Henderson KY 42420",
    "addr:housenumber":"34",
    "addr:postcode":"42420",
    "addr:street":"S Adams St",
    "iso:country":"US",
    "sg:address":"34 S Adams St",
    "sg:city":"Henderson",
    "sg:classifiers":[
        {
            "category":"Social Services",
            "subcategory":"Child Care",
            "type":"Services"
        }
    ],
    "sg:phone":"+1 270 827 7744",
    "sg:postcode":"42420",
    "sg:province":"KY",
    "wof:name":"Pidder Padder Preschool & Chld",
    "wof:placetype":"venue"
},
  "geometry": {"coordinates":[-87.587611,37.835509],"type":"Point"}
}