{
  "type": "Feature",
  "properties": {
    "addr:full":"2300 W Broadway Louisville KY 40211",
    "addr:housenumber":"2300",
    "addr:postcode":"40211",
    "addr:street":"W Broadway",
    "iso:country":"US",
    "sg:address":"2300 W Broadway",
    "sg:city":"Louisville",
    "sg:classifiers":[
        {
            "category":"Personal",
            "subcategory":"Beauty Salon",
            "type":"Services"
        }
    ],
    "sg:phone":"+1 502 774 5291",
    "sg:postcode":"40211",
    "sg:province":"KY",
    "wof:name":"Golden Comb Beauty Salon",
    "wof:placetype":"venue"
},
  "geometry": {"coordinates":[-85.79156399999999,38.249333],"type":"Point"}
}