{
  "type": "Feature",
  "properties": {
    "addr:full":"202 Tweed Ct Versailles KY 40383",
    "addr:housenumber":"202",
    "addr:postcode":"40383",
    "addr:street":"Tweed Ct",
    "iso:country":"US",
    "sg:address":"202 Tweed Ct",
    "sg:city":"Versailles",
    "sg:classifiers":[
        {
            "category":"Building & Trades",
            "subcategory":"Construction",
            "type":"Services"
        }
    ],
    "sg:phone":"+1 859 873 8008",
    "sg:postcode":"40383",
    "sg:province":"KY",
    "sg:tags":[
        "painter"
    ],
    "wof:name":"Dunn Painting",
    "wof:placetype":"venue"
},
  "geometry": {"coordinates":[-84.739411,38.037771],"type":"Point"}
}