{
  "type": "Feature",
  "properties": {
    "iso:country":"US",
    "sg:address":"408 Donnelley Dr",
    "sg:city":"Glasgow",
    "sg:classifiers":[
        {
            "category":"Building & Trades",
            "subcategory":"Construction",
            "type":"Services"
        }
    ],
    "sg:phone":"+1 270 678 9323",
    "sg:postcode":"42141",
    "sg:province":"KY",
    "sg:tags":[
        "concrete",
        "contractor"
    ],
    "wof:name":"Kenway Concrete Of Ky LLC",
    "wof:placetype":"venue"
},
  "geometry": {"coordinates":[-85.959399,36.99922],"type":"Point"}
}