{
  "type": "Feature",
  "properties": {
    "iso:country":"US",
    "sg:address":"930 Camargo Rd",
    "sg:city":"Mt Sterling",
    "sg:classifiers":[
        {
            "category":"Sports & Exercise",
            "subcategory":"Bowling",
            "type":"Entertainment"
        }
    ],
    "sg:phone":"+1 859 498 7755",
    "sg:postcode":"40353",
    "sg:province":"KY",
    "sg:tags":[
        "center"
    ],
    "wof:name":"Sterling Lanes",
    "wof:placetype":"venue"
},
  "geometry": {"coordinates":[-83.941007,38.049836],"type":"Point"}
}