{
  "type": "Feature",
  "properties": {
    "iso:country":"US",
    "sg:address":"308 N 12th St",
    "sg:city":"Murray",
    "sg:classifiers":[
        {
            "category":"Professional",
            "subcategory":"Business Services",
            "type":"Services"
        }
    ],
    "sg:phone":"+1 270 753 7743",
    "sg:postcode":"42071",
    "sg:province":"KY",
    "sg:tags":[
        "embroidery"
    ],
    "wof:name":"Faye's Custom Embroidery & Ptg",
    "wof:placetype":"venue"
},
  "geometry": {"coordinates":[-88.315163,36.613963],"type":"Point"}
}