{
  "type": "Feature",
  "properties": {
    "iso:country":"US",
    "sg:address":"310 Langdon St",
    "sg:city":"Somerset",
    "sg:classifiers":[
        {
            "category":"Health Services",
            "subcategory":"Medical Lab",
            "type":"Services"
        }
    ],
    "sg:phone":"+1 606 679 7139",
    "sg:postcode":"42503",
    "sg:province":"KY",
    "sg:tags":[
        "laboratory"
    ],
    "wof:name":"Laboratory Corp Of America",
    "wof:placetype":"venue"
},
  "geometry": {"coordinates":[-84.61887,37.088674],"type":"Point"}
}