{
  "type": "Feature",
  "properties": {
    "iso:country":"US",
    "sg:address":"1237 Clay St",
    "sg:city":"Paducah",
    "sg:classifiers":[
        {
            "category":"Shopping",
            "subcategory":"Department Store",
            "type":"Retail Goods"
        }
    ],
    "sg:phone":"+1 270 444 9878",
    "sg:postcode":"42001",
    "sg:province":"KY",
    "sg:website":"http://www.familydollar.com",
    "wof:name":"Family Dollar Store",
    "wof:placetype":"venue"
},
  "geometry": {"coordinates":[-88.62245,37.0832],"type":"Point"}
}