{
  "type": "Feature",
  "properties": {
    "addr:full":"225 Washington St Stanton KY 40380",
    "addr:housenumber":"225",
    "addr:postcode":"40380",
    "addr:street":"Washington St",
    "iso:country":"US",
    "sg:address":"225 Washington St",
    "sg:city":"Stanton",
    "sg:classifiers":[
        {
            "category":"Health Services",
            "subcategory":"Doctor",
            "type":"Services"
        }
    ],
    "sg:phone":"+1 606 663 2256",
    "sg:postcode":"40380",
    "sg:province":"KY",
    "sg:tags":[
        "physician",
        "surgeon"
    ],
    "wof:name":"Sam E Cecil MD",
    "wof:placetype":"venue"
},
  "geometry": {"coordinates":[-83.86015999999999,37.850987],"type":"Point"}
}