{
  "type": "Feature",
  "properties": {
    "iso:country":"US",
    "sg:address":"12201 Bluegrass Pkwy",
    "sg:city":"Louisville",
    "sg:classifiers":[
        {
            "category":"Professional",
            "subcategory":"Research",
            "type":"Services"
        }
    ],
    "sg:phone":"+1 502 568 7800",
    "sg:postcode":"40299",
    "sg:province":"KY",
    "sg:tags":[
        "analysis",
        "market"
    ],
    "wof:name":"International Center For Long Term Care Innovation",
    "wof:placetype":"venue"
},
  "geometry": {"coordinates":[-85.536278,38.217178],"type":"Point"}
}