{
  "type": "Feature",
  "properties": {
    "addr:full":"2160 Sir Barton Way Lexington KY 40509",
    "addr:housenumber":"2160",
    "addr:postcode":"40509",
    "addr:street":"Sir Barton Way",
    "iso:country":"US",
    "sg:address":"2160 Sir Barton Way",
    "sg:city":"Lexington",
    "sg:classifiers":[
        {
            "category":"Manufacturing",
            "subcategory":"Apparel",
            "type":"Manufacturing & Wholesale Goods"
        }
    ],
    "sg:phone":"+1 859 264 7472",
    "sg:postcode":"40509",
    "sg:province":"KY",
    "sg:tags":[
        "sewing",
        "contractor"
    ],
    "wof:name":"Sew A Lot Lexington Inc",
    "wof:placetype":"venue"
},
  "geometry": {"coordinates":[-84.41854499999999,38.020654],"type":"Point"}
}