{
  "type": "Feature",
  "properties": {
    "iso:country":"US",
    "sg:address":"1131 Tatesbrook Dr",
    "sg:city":"Lexington",
    "sg:classifiers":[
        {
            "category":"Building & Trades",
            "subcategory":"Plumbing",
            "type":"Services"
        }
    ],
    "sg:phone":"+1 859 273 4255",
    "sg:postcode":"40517",
    "sg:province":"KY",
    "sg:tags":[
        "heat",
        "pump"
    ],
    "wof:name":"M & M Heat Pump Svc",
    "wof:placetype":"venue"
},
  "geometry": {"coordinates":[-84.486898,37.972676],"type":"Point"}
}