{
  "type": "Feature",
  "properties": {
    "iso:country":"US",
    "sg:address":"22 Thomas St",
    "sg:city":"Fort Thomas",
    "sg:classifiers":[
        {
            "category":"Personal",
            "subcategory":"Barber",
            "type":"Services"
        }
    ],
    "sg:phone":"+1 859 441 3024",
    "sg:postcode":"41008",
    "sg:province":"KY",
    "sg:tags":[
        "shop"
    ],
    "wof:name":"Smitty's Barber Shop",
    "wof:placetype":"venue"
},
  "geometry": {"coordinates":[-85.126563,38.668802],"type":"Point"}
}