{
  "type": "Feature",
  "properties": {
    "iso:country":"US",
    "sg:address":"11001 Bluegrass Pkwy",
    "sg:city":"Jeffersontown",
    "sg:classifiers":[
        {
            "category":"Manufacturing",
            "subcategory":"Printing",
            "type":"Manufacturing & Wholesale Goods"
        }
    ],
    "sg:phone":"+1 502 895 7718",
    "sg:postcode":"40299",
    "sg:province":"KY",
    "sg:tags":[
        "newspaper"
    ],
    "wof:name":"USA Today",
    "wof:placetype":"venue"
},
  "geometry": {"coordinates":[-85.55018200000001,38.220597],"type":"Point"}
}