{
  "type": "Feature",
  "properties": {
    "addr:full":"2456 Fortune Dr Lexington KY 40509",
    "addr:housenumber":"2456",
    "addr:postcode":"40509",
    "addr:street":"Fortune Dr",
    "iso:country":"US",
    "sg:address":"2456 Fortune Dr",
    "sg:city":"Lexington",
    "sg:classifiers":[
        {
            "category":"Utilities",
            "subcategory":"Telephone",
            "type":"Services"
        }
    ],
    "sg:phone":"+1 859 294 7280",
    "sg:postcode":"40509",
    "sg:province":"KY",
    "sg:tags":[
        "telecommunication"
    ],
    "wof:name":"Lucent Technologies",
    "wof:placetype":"venue"
},
  "geometry": {"coordinates":[-84.447053,38.034171],"type":"Point"}
}