{
  "type": "Feature",
  "properties": {
    "iso:country":"US",
    "sg:address":"1 Audubon Plaza Dr",
    "sg:city":"Louisville",
    "sg:classifiers":[
        {
            "category":"Health Services",
            "subcategory":"Doctor",
            "type":"Services"
        }
    ],
    "sg:phone":"+1 502 636 7176",
    "sg:postcode":"40217",
    "sg:province":"KY",
    "sg:tags":[
        "physician",
        "surgeon"
    ],
    "wof:name":"Clinical Associates",
    "wof:placetype":"venue"
},
  "geometry": {"coordinates":[-85.717806,38.213268],"type":"Point"}
}