{
  "type": "Feature",
  "properties": {
    "iso:country":"US",
    "sg:address":"1920 Goldsmith Ln",
    "sg:city":"Louisville",
    "sg:classifiers":[
        {
            "category":"Professional",
            "subcategory":"Employment Agencies",
            "type":"Services"
        }
    ],
    "sg:phone":"+1 502 456 1150",
    "sg:postcode":"40218",
    "sg:province":"KY",
    "sg:tags":[
        "opportunity"
    ],
    "sg:website":"www.om5ky.com",
    "wof:name":"Om5",
    "wof:placetype":"venue"
},
  "geometry": {"coordinates":[-85.68342,38.200505],"type":"Point"}
}