{
  "type": "Feature",
  "properties": {
    "addr:full":"6702 Zebulon Hwy Pikeville KY 41501",
    "addr:housenumber":"6702",
    "addr:postcode":"41501",
    "addr:street":"Zebulon Hwy",
    "iso:country":"US",
    "sg:address":"6702 Zebulon Hwy",
    "sg:city":"Pikeville",
    "sg:classifiers":[
        {
            "category":"Retail",
            "subcategory":"Repair Shop",
            "type":"Services"
        }
    ],
    "sg:phone":"+1 606 631 9859",
    "sg:postcode":"41501",
    "sg:province":"KY",
    "sg:tags":[
        "water",
        "equipment",
        "softening"
    ],
    "wof:name":"East Kentucky Water",
    "wof:placetype":"venue"
},
  "geometry": {"coordinates":[-82.45499700000001,37.553163],"type":"Point"}
}