{
  "type": "Feature",
  "properties": {
    "iso:country":"US",
    "sg:address":"3450 Richmond Rd",
    "sg:city":"Lexington",
    "sg:classifiers":[
        {
            "category":"Health Services",
            "subcategory":"Clinic",
            "type":"Services"
        }
    ],
    "sg:phone":"+1 859 263 5444",
    "sg:postcode":"40509",
    "sg:province":"KY",
    "wof:name":"Lexington Health & Fitness",
    "wof:placetype":"venue"
},
  "geometry": {"coordinates":[-84.44126199999999,37.996902],"type":"Point"}
}