{
  "type": "Feature",
  "properties": {
    "iso:country":"US",
    "sg:address":"207 Davies St",
    "sg:city":"Covington",
    "sg:classifiers":[
        {
            "category":"Wholesale",
            "subcategory":"Vending Machines",
            "type":"Manufacturing & Wholesale Goods"
        }
    ],
    "sg:phone":"+1 859 261 3296",
    "sg:postcode":"41016",
    "sg:province":"KY",
    "sg:tags":[
        "operator"
    ],
    "wof:name":"Dan Laughlin Vending",
    "wof:placetype":"venue"
},
  "geometry": {"coordinates":[-84.547707,39.092454],"type":"Point"}
}