{
  "type": "Feature",
  "properties": {
    "addr:full":"455 Madison Square Dr Madisonville KY 42431",
    "addr:housenumber":"455",
    "addr:postcode":"42431",
    "addr:street":"Madison Square Dr",
    "iso:country":"US",
    "sg:address":"455 Madison Square Dr",
    "sg:city":"Madisonville",
    "sg:classifiers":[
        {
            "category":"Cinema",
            "subcategory":"Movie Theater",
            "type":"Entertainment"
        }
    ],
    "sg:phone":"+1 270 821 1600",
    "sg:postcode":"42431",
    "sg:province":"KY",
    "wof:name":"Capitol Theaters",
    "wof:placetype":"venue"
},
  "geometry": {"coordinates":[-87.480166,37.327656],"type":"Point"}
}