{
  "type": "Feature",
  "properties": {
    "addr:full":"178 Pleasant Hope Church Rd Calhoun KY 42327",
    "addr:housenumber":"178",
    "addr:postcode":"42327",
    "addr:street":"Pleasant Hope Church Rd",
    "iso:country":"US",
    "sg:address":"178 Pleasant Hope Church Rd",
    "sg:city":"Calhoun",
    "sg:classifiers":[
        {
            "category":"Organizations",
            "subcategory":"Religious Organization",
            "type":"Services"
        }
    ],
    "sg:phone":"+1 270 278 2609",
    "sg:postcode":"42327",
    "sg:province":"KY",
    "sg:tags":[
        "church"
    ],
    "wof:name":"Pleasant Hope General Baptist",
    "wof:placetype":"venue"
},
  "geometry": {"coordinates":[-87.17013300000001,37.550827],"type":"Point"}
}