{
  "type": "Feature",
  "properties": {
    "addr:full":"3105 Commander Dr Louisville KY 40220",
    "addr:housenumber":"3105",
    "addr:postcode":"40220",
    "addr:street":"Commander Dr",
    "iso:country":"US",
    "sg:address":"3105 Commander Dr",
    "sg:city":"Louisville",
    "sg:classifiers":[
        {
            "category":"Professional",
            "subcategory":"Business Services",
            "type":"Services"
        }
    ],
    "sg:phone":"+1 502 451 3154",
    "sg:postcode":"40220",
    "sg:province":"KY",
    "sg:tags":[
        "appraiser"
    ],
    "wof:name":"Dew Appraisals Inc",
    "wof:placetype":"venue"
},
  "geometry": {"coordinates":[-85.65537,38.218426],"type":"Point"}
}