{
  "type": "Feature",
  "properties": {
    "iso:country":"US",
    "sg:address":"918 S 1st St",
    "sg:city":"Ironton",
    "sg:classifiers":[
        {
            "category":"Manufacturing",
            "subcategory":"Retail Goods",
            "type":"Manufacturing & Wholesale Goods"
        }
    ],
    "sg:phone":"+1 740 533 9182",
    "sg:postcode":"45638",
    "sg:province":"OH",
    "sg:tags":[
        "carbon",
        "grinding"
    ],
    "wof:name":"Jims Grinding",
    "wof:placetype":"venue"
},
  "geometry": {"coordinates":[-82.683503,38.529963],"type":"Point"}
}