{
  "type": "Feature",
  "properties": {
    "addr:full":"102 S Mayo Trl Pikeville KY 41501",
    "addr:housenumber":"102",
    "addr:postcode":"41501",
    "addr:street":"S Mayo Trl",
    "iso:country":"US",
    "sg:address":"102 S Mayo Trl",
    "sg:city":"Pikeville",
    "sg:classifiers":[
        {
            "category":"Restaurant",
            "type":"Food & Drink"
        }
    ],
    "sg:phone":"+1 606 432 3246",
    "sg:postcode":"41501",
    "sg:province":"KY",
    "wof:name":"KFC",
    "wof:placetype":"venue"
},
  "geometry": {"coordinates":[-82.52692399999999,37.472333],"type":"Point"}
}