{
  "type": "Feature",
  "properties": {
    "iso:country":"US",
    "sg:address":"1032 E New Circle Rd",
    "sg:city":"Lexington",
    "sg:classifiers":[
        {
            "category":"Building & Trades",
            "subcategory":"Cleaning & Sanitation",
            "type":"Services"
        }
    ],
    "sg:phone":"+1 859 233 4446",
    "sg:postcode":"40505",
    "sg:province":"KY",
    "sg:tags":[
        "chemical"
    ],
    "wof:name":"KABCO-Ky Automotive Bying",
    "wof:placetype":"venue"
},
  "geometry": {"coordinates":[-84.454578,38.037598],"type":"Point"}
}