{
  "type": "Feature",
  "properties": {
    "iso:country":"US",
    "sg:address":"1801 Priority Way",
    "sg:city":"Louisville",
    "sg:classifiers":[
        {
            "category":"Restaurant",
            "type":"Food & Drink"
        }
    ],
    "sg:phone":"+1 502 266 8886",
    "sg:postcode":"40299",
    "sg:province":"KY",
    "wof:name":"King Buffet",
    "wof:placetype":"venue"
},
  "geometry": {"coordinates":[-85.54136699999999,38.217238],"type":"Point"}
}