{
  "type": "Feature",
  "properties": {
    "iso:country":"US",
    "sg:address":"204 E Main St",
    "sg:city":"Princeton",
    "sg:classifiers":[
        {
            "category":"Building & Trades",
            "subcategory":"Plumbing",
            "type":"Services"
        }
    ],
    "sg:phone":"+1 270 365 6141",
    "sg:postcode":"42445",
    "sg:province":"KY",
    "sg:tags":[
        "conditioning",
        "air",
        "system",
        "contractor"
    ],
    "wof:name":"Lusby Heating & Air",
    "wof:placetype":"venue"
},
  "geometry": {"coordinates":[-87.88098599999999,37.108157],"type":"Point"}
}