{
  "type": "Feature",
  "properties": {
    "addr:full":"80 Maple Dr Mt Vernon KY 40456",
    "addr:housenumber":"80",
    "addr:postcode":"40456",
    "addr:street":"Maple Dr",
    "iso:country":"US",
    "sg:address":"80 Maple Dr",
    "sg:city":"Mt Vernon",
    "sg:classifiers":[
        {
            "category":"Retail",
            "subcategory":"Funeral Services",
            "type":"Services"
        }
    ],
    "sg:phone":"+1 606 256 2345",
    "sg:postcode":"40456",
    "sg:province":"KY",
    "sg:tags":[
        "director"
    ],
    "wof:name":"Cox Funeral Home Inc",
    "wof:placetype":"venue"
},
  "geometry": {"coordinates":[-84.33753,37.355684],"type":"Point"}
}