{
  "type": "Feature",
  "properties": {
    "iso:country":"US",
    "sg:address":"2236 Amboy Dr",
    "sg:city":"Shively",
    "sg:classifiers":[
        {
            "category":"Communications",
            "subcategory":"Film & Video Production",
            "type":"Services"
        }
    ],
    "sg:phone":"+1 502 448 6050",
    "sg:postcode":"40216",
    "sg:province":"KY",
    "sg:tags":[
        "taping"
    ],
    "wof:name":"Shamrock Productions",
    "wof:placetype":"venue"
},
  "geometry": {"coordinates":[-85.819768,38.20307],"type":"Point"}
}