{
  "type": "Feature",
  "properties": {
    "iso:country":"US",
    "sg:address":"1001 Kenwood Dr",
    "sg:city":"Russell",
    "sg:classifiers":[
        {
            "category":"Organizations",
            "subcategory":"Religious Organization",
            "type":"Services"
        }
    ],
    "sg:phone":"+1 606 836 1272",
    "sg:postcode":"41169",
    "sg:province":"KY",
    "wof:name":"Chrch Jesus Chrst Lttr Day STS",
    "wof:placetype":"venue"
},
  "geometry": {"coordinates":[-82.69560199999999,38.509063],"type":"Point"}
}