{
  "type": "Feature",
  "properties": {
    "addr:full":"721 N Main St Hopkinsville KY 42240",
    "addr:housenumber":"721",
    "addr:postcode":"42240",
    "addr:street":"N Main St",
    "iso:country":"US",
    "sg:address":"721 N Main St",
    "sg:city":"Hopkinsville",
    "sg:classifiers":[
        {
            "category":"Wholesale",
            "subcategory":"Auto Parts",
            "type":"Manufacturing & Wholesale Goods"
        }
    ],
    "sg:phone":"+1 270 886 6615",
    "sg:postcode":"42240",
    "sg:province":"KY",
    "sg:tags":[
        "automobile",
        "rebuilt"
    ],
    "wof:name":"North Side Auto Parts",
    "wof:placetype":"venue"
},
  "geometry": {"coordinates":[-87.482726,36.877867],"type":"Point"}
}