{
  "type": "Feature",
  "properties": {
    "addr:full":"3545 Lovelaceville Rd Paducah KY 42001",
    "addr:housenumber":"3545",
    "addr:postcode":"42001",
    "addr:street":"Lovelaceville Rd",
    "iso:country":"US",
    "sg:address":"3545 Lovelaceville Rd",
    "sg:city":"Paducah",
    "sg:classifiers":[
        {
            "category":"Organizations",
            "subcategory":"Religious Organization",
            "type":"Services"
        }
    ],
    "sg:phone":"+1 270 554 8241",
    "sg:postcode":"42001",
    "sg:province":"KY",
    "wof:name":"Calvary Apostolic Church",
    "wof:placetype":"venue"
},
  "geometry": {"coordinates":[-88.673653,37.031854],"type":"Point"}
}