{
  "type": "Feature",
  "properties": {
    "addr:full":"420 Cooper Cir Princeton KY 42445",
    "addr:housenumber":"420",
    "addr:postcode":"42445",
    "addr:street":"Cooper Cir",
    "iso:country":"US",
    "sg:address":"420 Cooper Cir",
    "sg:city":"Princeton",
    "sg:classifiers":[
        {
            "category":"Real Estate",
            "subcategory":"Real Estate Operator",
            "type":"Services"
        }
    ],
    "sg:phone":"+1 270 365 2365",
    "sg:postcode":"42445",
    "sg:province":"KY",
    "sg:tags":[
        "apartment"
    ],
    "wof:name":"Princeton Greens Apartments",
    "wof:placetype":"venue"
},
  "geometry": {"coordinates":[-87.869102,37.109278],"type":"Point"}
}