{
  "type": "Feature",
  "properties": {
    "addr:full":"109 Robbins Dr Richmond KY 40475",
    "addr:housenumber":"109",
    "addr:postcode":"40475",
    "addr:street":"Robbins Dr",
    "iso:country":"US",
    "sg:address":"109 Robbins Dr",
    "sg:city":"Richmond",
    "sg:classifiers":[
        {
            "category":"Building & Trades",
            "subcategory":"Construction",
            "type":"Services"
        }
    ],
    "sg:phone":"+1 859 626 7723",
    "sg:postcode":"40475",
    "sg:province":"KY",
    "sg:tags":[
        "painter"
    ],
    "wof:name":"Countryside Painting Co",
    "wof:placetype":"venue"
},
  "geometry": {"coordinates":[-84.311869,37.742375],"type":"Point"}
}