{
  "type": "Feature",
  "properties": {
    "addr:full":"1016 Winchester Rd Irvine KY 40336",
    "addr:housenumber":"1016",
    "addr:postcode":"40336",
    "addr:street":"Winchester Rd",
    "iso:country":"US",
    "sg:address":"1016 Winchester Rd",
    "sg:city":"Irvine",
    "sg:classifiers":[
        {
            "category":"Shopping",
            "subcategory":"Department Store",
            "type":"Retail Goods"
        }
    ],
    "sg:phone":"+1 606 723 0081",
    "sg:postcode":"40336",
    "sg:province":"KY",
    "sg:tags":[
        "shop"
    ],
    "wof:name":"Family Dollar Store",
    "wof:placetype":"venue"
},
  "geometry": {"coordinates":[-83.976136,37.711931],"type":"Point"}
}