{
  "type": "Feature",
  "properties": {
    "iso:country":"US",
    "sg:address":"717 N 2nd St",
    "sg:city":"Central City",
    "sg:classifiers":[
        {
            "category":"Organizations",
            "subcategory":"Religious Organization",
            "type":"Services"
        }
    ],
    "sg:phone":"+1 270 754 3908",
    "sg:postcode":"42330",
    "sg:province":"KY",
    "sg:tags":[
        "clergy"
    ],
    "wof:name":"Nazarene Parsonage",
    "wof:placetype":"venue"
},
  "geometry": {"coordinates":[-87.12947800000001,37.30207],"type":"Point"}
}