{
  "type": "Feature",
  "properties": {
    "iso:country":"US",
    "sg:address":"1409 S Columbia Ave",
    "sg:city":"Campbellsville",
    "sg:classifiers":[
        {
            "category":"Travel",
            "subcategory":"Hotels & Motels",
            "type":"Entertainment"
        }
    ],
    "sg:phone":"+1 270 465 8196",
    "sg:postcode":"42718",
    "sg:province":"KY",
    "wof:name":"Lucky Vista Motel",
    "wof:placetype":"venue"
},
  "geometry": {"coordinates":[-85.354691,37.323818],"type":"Point"}
}