{
  "type": "Feature",
  "properties": {
    "iso:country":"US",
    "sg:address":"522 W Maxwell St",
    "sg:city":"Lexington",
    "sg:classifiers":[
        {
            "category":"Freight",
            "type":"Transportation"
        }
    ],
    "sg:phone":"+1 859 252 6210",
    "sg:postcode":"40508",
    "sg:province":"KY",
    "sg:tags":[
        "warehouse",
        "tobacco"
    ],
    "wof:name":"Maxwell Street Tobacco",
    "wof:placetype":"venue"
},
  "geometry": {"coordinates":[-84.506164,38.047642],"type":"Point"}
}