{
  "type": "Feature",
  "properties": {
    "addr:full":"174 Plummer St Campton KY 41301",
    "addr:housenumber":"174",
    "addr:postcode":"41301",
    "addr:street":"Plummer St",
    "iso:country":"US",
    "sg:address":"174 Plummer St",
    "sg:city":"Campton",
    "sg:classifiers":[
        {
            "category":"Organizations",
            "subcategory":"Religious Organization",
            "type":"Services"
        }
    ],
    "sg:phone":"+1 606 668 3229",
    "sg:postcode":"41301",
    "sg:province":"KY",
    "sg:tags":[
        "church"
    ],
    "wof:name":"United Methodist Church",
    "wof:placetype":"venue"
},
  "geometry": {"coordinates":[-83.55436899999999,37.735602],"type":"Point"}
}