{
  "type": "Feature",
  "properties": {
    "iso:country":"US",
    "sg:address":"126 Barnwood Dr",
    "sg:city":"Edgewood",
    "sg:classifiers":[
        {
            "category":"Bars & Pubs",
            "type":"Food & Drink"
        }
    ],
    "sg:phone":"+1 859 344 9887",
    "sg:postcode":"41017",
    "sg:province":"KY",
    "wof:name":"Edgewood Tavern",
    "wof:placetype":"venue"
},
  "geometry": {"coordinates":[-84.575518,39.018606],"type":"Point"}
}