{
  "type": "Feature",
  "properties": {
    "iso:country":"US",
    "sg:address":"4082 Canton Rd",
    "sg:city":"Cadiz",
    "sg:classifiers":[
        {
            "category":"Retail",
            "subcategory":"Repair Shop",
            "type":"Services"
        }
    ],
    "sg:phone":"+1 270 522 9554",
    "sg:postcode":"42211",
    "sg:province":"KY",
    "sg:tags":[
        "scooter",
        "motorcycle",
        "motor"
    ],
    "wof:name":"WFO Motorcycle & Off Road",
    "wof:placetype":"venue"
},
  "geometry": {"coordinates":[-87.900719,36.810395],"type":"Point"}
}