{
  "type": "Feature",
  "properties": {
    "iso:country":"US",
    "sg:address":"428 W Ormsby Ave Ste 1",
    "sg:city":"Louisville",
    "sg:classifiers":[
        {
            "category":"Manufacturing",
            "subcategory":"Soap",
            "type":"Manufacturing & Wholesale Goods"
        }
    ],
    "sg:phone":"+1 502 637 6086",
    "sg:postcode":"40203",
    "sg:province":"KY",
    "sg:tags":[
        "detergents-wholesale",
        "manufacturer"
    ],
    "sg:website":"http://www.thelioncompany.com",
    "wof:name":"The Lion Company Inc",
    "wof:placetype":"venue"
},
  "geometry": {"coordinates":[-85.761189,38.232909],"type":"Point"}
}