{
  "type": "Feature",
  "properties": {
    "iso:country":"US",
    "sg:address":"300 Dishman Ln",
    "sg:city":"Bowling Green",
    "sg:classifiers":[
        {
            "category":"Wholesale",
            "subcategory":"Machinery & Supplies",
            "type":"Manufacturing & Wholesale Goods"
        }
    ],
    "sg:phone":"+1 270 842 5511",
    "sg:postcode":"42101",
    "sg:province":"KY",
    "sg:tags":[
        "director",
        "funeral"
    ],
    "wof:name":"Mid-South Casket Distributors",
    "wof:placetype":"venue"
},
  "geometry": {"coordinates":[-86.485022,36.957122],"type":"Point"}
}