{
  "type": "Feature",
  "properties": {
    "iso:country":"US",
    "sg:address":"3932 Clarks River Rd",
    "sg:city":"Paducah",
    "sg:classifiers":[
        {
            "category":"Shopping",
            "type":"Retail Goods"
        }
    ],
    "sg:phone":"+1 270 442 6017",
    "sg:postcode":"42003",
    "sg:province":"KY",
    "sg:tags":[
        "spa",
        "hot",
        "tub"
    ],
    "wof:name":"Paducah Pools & Spas",
    "wof:placetype":"venue"
},
  "geometry": {"coordinates":[-88.55766,37.047046],"type":"Point"}
}