{
  "type": "Feature",
  "properties": {
    "iso:country":"US",
    "sg:address":"425 Fogg Pike",
    "sg:city":"Mt Sterling",
    "sg:classifiers":[
        {
            "category":"Professional",
            "subcategory":"Employment Agencies",
            "type":"Services"
        }
    ],
    "sg:phone":"+1 859 498 0387",
    "sg:postcode":"40353",
    "sg:province":"KY",
    "wof:name":"Big Shots Inc",
    "wof:placetype":"venue"
},
  "geometry": {"coordinates":[-83.954716,38.041413],"type":"Point"}
}