{
  "type": "Feature",
  "properties": {
    "iso:country":"US",
    "sg:address":"1370 Big Brushy Rd",
    "sg:city":"Morehead",
    "sg:classifiers":[
        {
            "category":"Farming",
            "subcategory":"Farm",
            "type":"Manufacturing & Wholesale Goods"
        }
    ],
    "sg:phone":"+1 606 784 8620",
    "sg:postcode":"40351",
    "sg:province":"KY",
    "sg:tags":[
        "work",
        "custom"
    ],
    "wof:name":"Nathan Pecco",
    "wof:placetype":"venue"
},
  "geometry": {"coordinates":[-83.48988900000001,38.245258],"type":"Point"}
}