{
  "type": "Feature",
  "properties": {
    "iso:country":"US",
    "sg:address":"4800 Mandarin Pl",
    "sg:city":"Lexington",
    "sg:classifiers":[
        {
            "category":"Home & Garden",
            "subcategory":"Building Materials",
            "type":"Retail Goods"
        }
    ],
    "sg:phone":"+1 859 224 3981",
    "sg:postcode":"40514",
    "sg:province":"KY",
    "wof:name":"AAA Ohd Lexington KY Inc",
    "wof:placetype":"venue"
},
  "geometry": {"coordinates":[-84.585093,37.984764],"type":"Point"}
}