{
  "type": "Feature",
  "properties": {
    "addr:full":"70 Legrande School Rd Horse Cave KY 42749",
    "addr:housenumber":"70",
    "addr:postcode":"42749",
    "addr:street":"Legrande School Rd",
    "iso:country":"US",
    "sg:address":"70 Legrande School Rd",
    "sg:city":"Horse Cave",
    "sg:classifiers":[
        {
            "category":"Education",
            "subcategory":"Special Training",
            "type":"Public Place"
        }
    ],
    "sg:phone":"+1 270 786 4045",
    "sg:postcode":"42749",
    "sg:province":"KY",
    "sg:tags":[
        "educational"
    ],
    "wof:name":"Helping Hands FRC",
    "wof:placetype":"venue"
},
  "geometry": {"coordinates":[-85.79473,37.171761],"type":"Point"}
}