{
  "type": "Feature",
  "properties": {
    "addr:full":"395 Berryman Rd Brandenburg KY 40108",
    "addr:housenumber":"395",
    "addr:postcode":"40108",
    "addr:street":"Berryman Rd",
    "iso:country":"US",
    "sg:address":"395 Berryman Rd",
    "sg:city":"Brandenburg",
    "sg:classifiers":[
        {
            "category":"Retail",
            "subcategory":"Repair Shop",
            "type":"Services"
        }
    ],
    "sg:phone":"+1 270 422 3085",
    "sg:postcode":"40108",
    "sg:province":"KY",
    "sg:tags":[
        "plumbing",
        "drain",
        "cleaning",
        "sewer"
    ],
    "wof:name":"Knott's Sewer Svc",
    "wof:placetype":"venue"
},
  "geometry": {"coordinates":[-86.14783799999999,37.976575],"type":"Point"}
}