{
  "type": "Feature",
  "properties": {
    "addr:full":"315 S 9th St Mayfield KY 42066",
    "addr:housenumber":"315",
    "addr:postcode":"42066",
    "addr:street":"S 9Th St",
    "iso:country":"US",
    "sg:address":"315 S 9th St",
    "sg:city":"Mayfield",
    "sg:classifiers":[
        {
            "category":"Shopping",
            "subcategory":"Florist",
            "type":"Retail Goods"
        }
    ],
    "sg:phone":"+1 270 247 4511",
    "sg:postcode":"42066",
    "sg:province":"KY",
    "wof:name":"Jeannette's Flower Shoppe Inc",
    "wof:placetype":"venue"
},
  "geometry": {"coordinates":[-88.638642,36.739431],"type":"Point"}
}