{
  "type": "Feature",
  "properties": {
    "addr:full":"9916 Shelbyville Rd Louisville KY 40223",
    "addr:housenumber":"9916",
    "addr:postcode":"40223",
    "addr:street":"Shelbyville Rd",
    "iso:country":"US",
    "sg:address":"9916 Shelbyville Rd",
    "sg:city":"Louisville",
    "sg:classifiers":[
        {
            "category":"Wholesale",
            "subcategory":"Durable Goods & Equipment",
            "type":"Manufacturing & Wholesale Goods"
        }
    ],
    "sg:phone":"+1 502 245 0927",
    "sg:postcode":"40223",
    "sg:province":"KY",
    "sg:tags":[
        "importer"
    ],
    "wof:name":"Kbc Global LLC",
    "wof:placetype":"venue"
},
  "geometry": {"coordinates":[-85.570027,38.245772],"type":"Point"}
}