{
  "type": "Feature",
  "properties": {
    "addr:full":"2271 Twenty Grand Ave Owensboro KY 42301",
    "addr:housenumber":"2271",
    "addr:postcode":"42301",
    "addr:street":"Twenty Grand Ave",
    "iso:country":"US",
    "sg:address":"2271 Twenty Grand Ave",
    "sg:city":"Owensboro",
    "sg:classifiers":[
        {
            "category":"Organizations",
            "subcategory":"Religious Organization",
            "type":"Services"
        }
    ],
    "sg:phone":"+1 270 926 3088",
    "sg:postcode":"42301",
    "sg:province":"KY",
    "sg:tags":[
        "church"
    ],
    "wof:name":"Lync Ministries Inc",
    "wof:placetype":"venue"
},
  "geometry": {"coordinates":[-87.13999699999999,37.745515],"type":"Point"}
}