{
  "type": "Feature",
  "properties": {
    "addr:full":"Grove & N Jefrsn Alexandria KY 41001",
    "addr:postcode":"41001",
    "iso:country":"US",
    "sg:address":"Grove & N Jefrsn",
    "sg:city":"Alexandria",
    "sg:classifiers":[
        {
            "category":"Education",
            "subcategory":"School",
            "type":"Public Place"
        }
    ],
    "sg:phone":"+1 859 635 3790",
    "sg:postcode":"41001",
    "sg:province":"KY",
    "wof:name":"Bishop Brossart High Schl",
    "wof:placetype":"venue"
},
  "geometry": {"coordinates":[-84.3965,38.9562],"type":"Point"}
}