{
  "type": "Feature",
  "properties": {
    "iso:country":"US",
    "sg:address":"306 Joan Ave",
    "sg:city":"Elizabethtown",
    "sg:classifiers":[
        {
            "category":"Professional",
            "subcategory":"Computer Services",
            "type":"Services"
        }
    ],
    "sg:phone":"+1 270 765 6449",
    "sg:postcode":"42701",
    "sg:province":"KY",
    "sg:tags":[
        "website",
        "design"
    ],
    "wof:name":"Xtremewebz",
    "wof:placetype":"venue"
},
  "geometry": {"coordinates":[-85.857011,37.709494],"type":"Point"}
}