{
  "type": "Feature",
  "properties": {
    "iso:country":"US",
    "sg:address":"9710 Taylorsville Rd",
    "sg:city":"Louisville",
    "sg:classifiers":[
        {
            "category":"Autos & Motor Vehicles",
            "subcategory":"Auto Supplies",
            "type":"Retail Goods"
        }
    ],
    "sg:phone":"+1 502 266 5877",
    "sg:postcode":"40299",
    "sg:province":"KY",
    "sg:tags":[
        "automobile",
        "part"
    ],
    "wof:name":"Doug S Acquisition Company No 1",
    "wof:placetype":"venue"
},
  "geometry": {"coordinates":[-85.576897,38.20359],"type":"Point"}
}