{
  "type": "Feature",
  "properties": {
    "addr:full":"PO Box 76183 Highland Heights KY 41076",
    "addr:housenumber":"po box 76183",
    "addr:postcode":"41076",
    "iso:country":"US",
    "sg:address":"PO Box 76183",
    "sg:city":"Highland Heights",
    "sg:classifiers":[
        {
            "category":"Sports & Exercise",
            "subcategory":"Gym",
            "type":"Entertainment"
        }
    ],
    "sg:phone":"+1 859 442 7441",
    "sg:postcode":"41076",
    "sg:province":"KY",
    "sg:tags":[
        "trainer"
    ],
    "wof:name":"Curves For Women",
    "wof:placetype":"venue"
},
  "geometry": {"coordinates":[-84.447197,39.025902],"type":"Point"}
}