{
  "type": "Feature",
  "properties": {
    "iso:country":"US",
    "sg:address":"301 Main Cross St",
    "sg:city":"Taylorsville",
    "sg:classifiers":[
        {
            "category":"Government",
            "subcategory":"Fire Station",
            "type":"Public Place"
        }
    ],
    "sg:phone":"+1 502 477 5533",
    "sg:postcode":"40071",
    "sg:province":"KY",
    "sg:tags":[
        "department"
    ],
    "wof:name":"Spencer County Fire Dept",
    "wof:placetype":"venue"
},
  "geometry": {"coordinates":[-85.344881,38.031786],"type":"Point"}
}