{
  "type": "Feature",
  "properties": {
    "iso:country":"US",
    "sg:address":"302 Reynolds Rd",
    "sg:city":"Glasgow",
    "sg:classifiers":[
        {
            "category":"Building & Trades",
            "subcategory":"Landscaping Services",
            "type":"Services"
        }
    ],
    "sg:phone":"+1 270 678 7738",
    "sg:postcode":"42141",
    "sg:province":"KY",
    "sg:tags":[
        "designer",
        "landscape"
    ],
    "wof:name":"Triple J Nursery & Landscape",
    "wof:placetype":"venue"
},
  "geometry": {"coordinates":[-85.932063,37.013468],"type":"Point"}
}