{
  "type": "Feature",
  "properties": {
    "iso:country":"US",
    "sg:address":"148 N Seminary St",
    "sg:city":"Madisonville",
    "sg:classifiers":[
        {
            "category":"Building & Trades",
            "subcategory":"Construction",
            "type":"Services"
        }
    ],
    "sg:phone":"+1 270 825 4146",
    "sg:postcode":"42431",
    "sg:province":"KY",
    "sg:tags":[
        "handyman"
    ],
    "wof:name":"M & R Odd Jobs",
    "wof:placetype":"venue"
},
  "geometry": {"coordinates":[-87.501735,37.331178],"type":"Point"}
}