{
  "type": "Feature",
  "properties": {
    "iso:country":"US",
    "sg:address":"257 Meathouse Rd",
    "sg:city":"Canada",
    "sg:classifiers":[
        {
            "category":"Organizations",
            "subcategory":"Religious Organization",
            "type":"Services"
        }
    ],
    "sg:phone":"+1 606 353 4049",
    "sg:postcode":"41539",
    "sg:province":"KY",
    "sg:tags":[
        "church"
    ],
    "wof:name":"Canada Freewill Baptist Church",
    "wof:placetype":"venue"
},
  "geometry": {"coordinates":[-82.365838,37.530827],"type":"Point"}
}