{
  "type": "Feature",
  "properties": {
    "iso:country":"US",
    "sg:address":"2136 Wilkes Way",
    "sg:city":"Lexington",
    "sg:classifiers":[
        {
            "category":"Shopping",
            "subcategory":"Books",
            "type":"Retail Goods"
        }
    ],
    "sg:phone":"+1 859 299 1599",
    "sg:postcode":"40505",
    "sg:province":"KY",
    "wof:name":"Living Waters Worship Center",
    "wof:placetype":"venue"
},
  "geometry": {"coordinates":[-84.42596500000001,38.046334],"type":"Point"}
}