{
  "type": "Feature",
  "properties": {
    "addr:full":"278 Town Mountain Rd Pikeville KY 41501",
    "addr:housenumber":"278",
    "addr:postcode":"41501",
    "addr:street":"Town Mountain Rd",
    "iso:country":"US",
    "sg:address":"278 Town Mountain Rd",
    "sg:city":"Pikeville",
    "sg:classifiers":[
        {
            "category":"Restaurant",
            "type":"Food & Drink"
        }
    ],
    "sg:phone":"+1 606 437 6662",
    "sg:postcode":"41501",
    "sg:province":"KY",
    "wof:name":"Mona's Creative Catering",
    "wof:placetype":"venue"
},
  "geometry": {"coordinates":[-82.50831100000001,37.486582],"type":"Point"}
}