{
  "type": "Feature",
  "properties": {
    "addr:full":"9500 State Hwy 44 E Mt Washington KY 40047",
    "addr:housenumber":"9500",
    "addr:postcode":"40047",
    "addr:street":"State Hwy 44 E",
    "iso:country":"US",
    "sg:address":"9500 State Hwy 44 E",
    "sg:city":"Mt Washington",
    "sg:classifiers":[
        {
            "category":"Retail",
            "subcategory":"Funeral Services",
            "type":"Services"
        }
    ],
    "sg:phone":"+1 502 538 7084",
    "sg:postcode":"40047",
    "sg:province":"KY",
    "sg:tags":[
        "director"
    ],
    "wof:name":"Schmid Funeral Home",
    "wof:placetype":"venue"
},
  "geometry": {"coordinates":[-85.556613,38.058253],"type":"Point"}
}