{
  "type": "Feature",
  "properties": {
    "addr:full":"306 Matlock Old Union Rd Bowling Green KY 42104",
    "addr:housenumber":"306",
    "addr:postcode":"42104",
    "addr:street":"Matlock Old Union Rd",
    "iso:country":"US",
    "sg:address":"306 Matlock Old Union Rd",
    "sg:city":"Bowling Green",
    "sg:classifiers":[
        {
            "category":"Organizations",
            "subcategory":"Membership Organization",
            "type":"Services"
        }
    ],
    "sg:phone":"+1 270 782 6496",
    "sg:postcode":"42104",
    "sg:province":"KY",
    "wof:name":"New Beginngs Therputc",
    "wof:placetype":"venue"
},
  "geometry": {"coordinates":[-86.432841,36.845748],"type":"Point"}
}