{
  "type": "Feature",
  "properties": {
    "iso:country":"US",
    "sg:address":"12410 Warner Dr",
    "sg:city":"Goshen",
    "sg:classifiers":[
        {
            "category":"Professional",
            "subcategory":"Art Services",
            "type":"Services"
        }
    ],
    "sg:phone":"+1 502 228 0713",
    "sg:postcode":"40026",
    "sg:province":"KY",
    "sg:tags":[
        "commercial",
        "design"
    ],
    "wof:name":"Accusign & Graphics Inc",
    "wof:placetype":"venue"
},
  "geometry": {"coordinates":[-85.584935,38.398602],"type":"Point"}
}