{
  "type": "Feature",
  "properties": {
    "addr:full":"433 E Main St Glendale KY 42740",
    "addr:housenumber":"433",
    "addr:postcode":"42740",
    "addr:street":"E Main St",
    "iso:country":"US",
    "sg:address":"433 E Main St",
    "sg:city":"Glendale",
    "sg:classifiers":[
        {
            "category":"Shopping",
            "subcategory":"Used Merchandise",
            "type":"Retail Goods"
        }
    ],
    "sg:phone":"+1 270 369 7943",
    "sg:postcode":"42740",
    "sg:province":"KY",
    "sg:tags":[
        "antique"
    ],
    "wof:name":"Green Top Antique & Collectbls",
    "wof:placetype":"venue"
},
  "geometry": {"coordinates":[-85.902619,37.601433],"type":"Point"}
}