{
  "type": "Feature",
  "properties": {
    "iso:country":"US",
    "sg:address":"1604 State Hwy 121",
    "sg:city":"Murray",
    "sg:classifiers":[
        {
            "category":"Building & Trades",
            "subcategory":"Pest Control",
            "type":"Services"
        }
    ],
    "sg:phone":"+1 270 753 6433",
    "sg:postcode":"42071",
    "sg:province":"KY",
    "wof:name":"Servall Termite & Pest Control",
    "wof:placetype":"venue"
},
  "geometry": {"coordinates":[-88.325214,36.622597],"type":"Point"}
}