{
  "type": "Feature",
  "properties": {
    "iso:country":"US",
    "sg:address":"1109 Versailles Rd",
    "sg:city":"Lexington",
    "sg:classifiers":[
        {
            "category":"Recreation",
            "type":"Entertainment"
        }
    ],
    "sg:phone":"+1 859 225 9555",
    "sg:postcode":"40504",
    "sg:province":"KY",
    "wof:name":"Eddie Brooks Baseball Academy",
    "wof:placetype":"venue"
},
  "geometry": {"coordinates":[-84.517245,38.050148],"type":"Point"}
}