{
  "type": "Feature",
  "properties": {
    "iso:country":"US",
    "sg:address":"111 Bunche Ave",
    "sg:city":"Glasgow",
    "sg:classifiers":[
        {
            "category":"Professional",
            "subcategory":"Management & Consulting",
            "type":"Services"
        }
    ],
    "sg:phone":"+1 270 651 9834",
    "sg:postcode":"42141",
    "sg:province":"KY",
    "sg:tags":[
        "town",
        "city",
        "regional",
        "planner"
    ],
    "wof:name":"Glasgow Community Development",
    "wof:placetype":"venue"
},
  "geometry": {"coordinates":[-85.91542099999999,36.989828],"type":"Point"}
}