{
  "type": "Feature",
  "properties": {
    "iso:country":"US",
    "sg:address":"219 Wall St",
    "sg:city":"Maysville",
    "sg:classifiers":[
        {
            "category":"Shopping",
            "subcategory":"Computers & Home Electronics",
            "type":"Retail Goods"
        }
    ],
    "sg:phone":"+1 606 759 0506",
    "sg:postcode":"41056",
    "sg:province":"KY",
    "sg:tags":[
        "game",
        "video"
    ],
    "wof:name":"Gamestop",
    "wof:placetype":"venue"
},
  "geometry": {"coordinates":[-83.768782,38.648701],"type":"Point"}
}