{
  "type": "Feature",
  "properties": {
    "iso:country":"US",
    "sg:address":"1169 Nest Egg Rd",
    "sg:city":"Mount Sterling",
    "sg:classifiers":[
        {
            "category":"Professional",
            "subcategory":"Business Services",
            "type":"Services"
        }
    ],
    "sg:phone":"+1 859 498 4637",
    "sg:postcode":"40353",
    "sg:province":"KY",
    "wof:name":"Gateway Cleaning Service",
    "wof:placetype":"venue"
},
  "geometry": {"coordinates":[-83.963651,37.960791],"type":"Point"}
}