{
  "type": "Feature",
  "properties": {
    "iso:country":"US",
    "sg:address":"10590 Hardinsburg Rd",
    "sg:city":"Cecilia",
    "sg:classifiers":[
        {
            "category":"Retail",
            "subcategory":"Auto Repair",
            "type":"Services"
        }
    ],
    "sg:phone":"+1 270 862 3667",
    "sg:postcode":"42724",
    "sg:province":"KY",
    "sg:tags":[
        "general"
    ],
    "wof:name":"86 Auto Service",
    "wof:placetype":"venue"
},
  "geometry": {"coordinates":[-86.122606,37.689034],"type":"Point"}
}