{
  "type": "Feature",
  "properties": {
    "iso:country":"US",
    "sg:address":"420 Wyatt Cemetery Rd",
    "sg:city":"Drakesboro",
    "sg:classifiers":[
        {
            "category":"Mining & Drilling",
            "type":"Manufacturing & Wholesale Goods"
        }
    ],
    "sg:phone":"+1 270 476 7009",
    "sg:postcode":"42337",
    "sg:province":"KY",
    "sg:tags":[
        "coal",
        "shipping"
    ],
    "wof:name":"C & R Coal Co",
    "wof:placetype":"venue"
},
  "geometry": {"coordinates":[-87.07314100000001,37.18533],"type":"Point"}
}