{
  "type": "Feature",
  "properties": {
    "iso:country":"US",
    "sg:address":"11360 Bluegrass Pkwy",
    "sg:city":"Jeffersontown",
    "sg:classifiers":[
        {
            "category":"Manufacturing",
            "subcategory":"Printing",
            "type":"Manufacturing & Wholesale Goods"
        }
    ],
    "sg:phone":"+1 502 266 6008",
    "sg:postcode":"40299",
    "sg:province":"KY",
    "sg:tags":[
        "commercial"
    ],
    "wof:name":"Impressions Inc",
    "wof:placetype":"venue"
},
  "geometry": {"coordinates":[-85.544743,38.220451],"type":"Point"}
}