{
  "type": "Feature",
  "properties": {
    "iso:country":"US",
    "sg:address":"1450 S 15th St",
    "sg:city":"Louisville",
    "sg:classifiers":[
        {
            "category":"Manufacturing",
            "subcategory":"Metals",
            "type":"Manufacturing & Wholesale Goods"
        },
        {
            "category":"Building & Trades",
            "subcategory":"Construction",
            "type":"Services"
        },
        {
            "category":"Manufacturing",
            "subcategory":"Building Materials",
            "type":"Manufacturing & Wholesale Goods"
        }
    ],
    "sg:phone":"+1 502 635 2655",
    "sg:postcode":"40210",
    "sg:province":"KY",
    "sg:tags":[
        "sheet",
        "work",
        "contractor",
        "mechanical",
        "work-manufacturers",
        "fabricator"
    ],
    "sg:website":"http://www.kirkblum.com",
    "wof:name":"Kirk & Blum",
    "wof:placetype":"venue"
},
  "geometry": {"coordinates":[-85.779437,38.230538],"type":"Point"}
}