{
  "type": "Feature",
  "properties": {
    "addr:full":"3110 Preston Hwy Louisville KY 40213",
    "addr:housenumber":"3110",
    "addr:postcode":"40213",
    "addr:street":"Preston Hwy",
    "iso:country":"US",
    "sg:address":"3110 Preston Hwy",
    "sg:city":"Louisville",
    "sg:classifiers":[
        {
            "category":"Home & Garden",
            "subcategory":"Kitchen Supply",
            "type":"Retail Goods"
        }
    ],
    "sg:phone":"+1 502 637 3232",
    "sg:postcode":"40213",
    "sg:province":"KY",
    "sg:tags":[
        "equipment",
        "restaurant"
    ],
    "wof:name":"The Restaurant Store",
    "wof:placetype":"venue"
},
  "geometry": {"coordinates":[-85.736008,38.204485],"type":"Point"}
}