{
  "type": "Feature",
  "properties": {
    "addr:full":"3057 Village Dr Covington KY 41017",
    "addr:housenumber":"3057",
    "addr:postcode":"41017",
    "addr:street":"Village Dr",
    "iso:country":"US",
    "sg:address":"3057 Village Dr",
    "sg:city":"Covington",
    "sg:classifiers":[
        {
            "category":"Professional",
            "type":"Services"
        }
    ],
    "sg:phone":"+1 859 341 6841",
    "sg:postcode":"41017",
    "sg:province":"KY",
    "wof:name":"Schutzman Computer Service",
    "wof:placetype":"venue"
},
  "geometry": {"coordinates":[-84.55852899999999,39.004109],"type":"Point"}
}