{
  "type": "Feature",
  "properties": {
    "addr:full":"802 Hoods Creek Pike Ashland KY 41101",
    "addr:housenumber":"802",
    "addr:postcode":"41101",
    "addr:street":"Hoods Creek Pike",
    "iso:country":"US",
    "sg:address":"802 Hoods Creek Pike",
    "sg:city":"Ashland",
    "sg:classifiers":[
        {
            "category":"Home & Garden",
            "subcategory":"Building Materials",
            "type":"Retail Goods"
        }
    ],
    "sg:phone":"+1 606 325 3994",
    "sg:postcode":"41101",
    "sg:province":"KY",
    "sg:tags":[
        "paint"
    ],
    "wof:name":"Pittsburg Paints",
    "wof:placetype":"venue"
},
  "geometry": {"coordinates":[-82.668238,38.490847],"type":"Point"}
}