{
  "type": "Feature",
  "properties": {
    "iso:country":"US",
    "sg:address":"1320 US Hwy 68 W",
    "sg:city":"Benton",
    "sg:classifiers":[
        {
            "category":"Autos & Motor Vehicles",
            "subcategory":"Automobile Sales",
            "type":"Retail Goods"
        }
    ],
    "sg:phone":"+1 270 527 9938",
    "sg:postcode":"42025",
    "sg:province":"KY",
    "sg:tags":[
        "car",
        "dealer"
    ],
    "wof:name":"Edwards Auto Sales",
    "wof:placetype":"venue"
},
  "geometry": {"coordinates":[-88.358593,36.938462],"type":"Point"}
}