{
  "type": "Feature",
  "properties": {
    "iso:country":"US",
    "sg:address":"829 Marcellus Dr",
    "sg:city":"Lexington",
    "sg:classifiers":[
        {
            "category":"Professional",
            "subcategory":"Computer Services",
            "type":"Services"
        }
    ],
    "sg:phone":"+1 859 255 1969",
    "sg:postcode":"40505",
    "sg:province":"KY",
    "sg:tags":[
        "datum"
    ],
    "wof:name":"Curveys World",
    "wof:placetype":"venue"
},
  "geometry": {"coordinates":[-84.469622,38.051004],"type":"Point"}
}