{
  "type": "Feature",
  "properties": {
    "addr:full":"3540 Tulipwood Dr Paducah KY 42003",
    "addr:postcode":"3540;42003",
    "addr:street":"Tulipwood Dr",
    "iso:country":"US",
    "sg:address":"3540 Tulipwood Dr",
    "sg:city":"Paducah",
    "sg:classifiers":[
        {
            "category":"Wholesale",
            "subcategory":"Machinery & Supplies",
            "type":"Manufacturing & Wholesale Goods"
        }
    ],
    "sg:phone":"+1 270 442 3654",
    "sg:postcode":"42003",
    "sg:province":"KY",
    "sg:tags":[
        "valve"
    ],
    "wof:name":"Schrader-Bellows",
    "wof:placetype":"venue"
},
  "geometry": {"coordinates":[-88.63251700000001,37.05388],"type":"Point"}
}