{
  "type": "Feature",
  "properties": {
    "addr:full":"6327 Midland Industrial Dr Shelbyville KY 40065",
    "addr:housenumber":"6327",
    "addr:postcode":"40065",
    "addr:street":"Midland Industrial Dr",
    "iso:country":"US",
    "sg:address":"6327 Midland Industrial Dr",
    "sg:city":"Shelbyville",
    "sg:classifiers":[
        {
            "category":"Professional",
            "type":"Services"
        }
    ],
    "sg:phone":"+1 502 647 5220",
    "sg:postcode":"40065",
    "sg:province":"KY",
    "sg:tags":[
        "establishment"
    ],
    "wof:name":"Ryan Young Products",
    "wof:placetype":"venue"
},
  "geometry": {"coordinates":[-85.252621,38.221203],"type":"Point"}
}