{
  "type": "Feature",
  "properties": {
    "addr:full":"9706 Taylorsville Rd Louisville KY 40299",
    "addr:housenumber":"9706",
    "addr:postcode":"40299",
    "addr:street":"Taylorsville Rd",
    "iso:country":"US",
    "sg:address":"9706 Taylorsville Rd",
    "sg:city":"Louisville",
    "sg:classifiers":[
        {
            "category":"Health Services",
            "subcategory":"Chiropractor",
            "type":"Services"
        }
    ],
    "sg:phone":"+1 502 267 5100",
    "sg:postcode":"40299",
    "sg:province":"KY",
    "wof:name":"David J Buerger Dr",
    "wof:placetype":"venue"
},
  "geometry": {"coordinates":[-85.576089,38.203028],"type":"Point"}
}