{
  "type": "Feature",
  "properties": {
    "addr:full":"801 Eastern Pkwy Louisville KY 40217",
    "addr:housenumber":"801",
    "addr:postcode":"40217",
    "addr:street":"Eastern Pkwy",
    "iso:country":"US",
    "sg:address":"801 Eastern Pkwy",
    "sg:city":"Louisville",
    "sg:classifiers":[
        {
            "category":"Banks & Credit Unions",
            "subcategory":"Bank",
            "type":"Services"
        }
    ],
    "sg:phone":"+1 502 581 5410",
    "sg:postcode":"40217",
    "sg:province":"KY",
    "sg:website":"http://www.nationalcity.com",
    "wof:name":"National City",
    "wof:placetype":"venue"
},
  "geometry": {"coordinates":[-85.742653,38.214828],"type":"Point"}
}