{
  "type": "Feature",
  "properties": {
    "addr:full":"5151 Charter Oak Dr Paducah KY 42001",
    "addr:housenumber":"5151",
    "addr:postcode":"42001",
    "addr:street":"Charter Oak Dr",
    "iso:country":"US",
    "sg:address":"5151 Charter Oak Dr",
    "sg:city":"Paducah",
    "sg:classifiers":[
        {
            "category":"Freight",
            "type":"Transportation"
        }
    ],
    "sg:phone":"+1 270 442 7544",
    "sg:postcode":"42001",
    "sg:province":"KY",
    "sg:tags":[
        "trucking"
    ],
    "sg:website":"www.yellowcorp.com",
    "wof:name":"Yellow Transportation Inc",
    "wof:placetype":"venue"
},
  "geometry": {"coordinates":[-88.67949900000001,37.092601],"type":"Point"}
}