{
  "type": "Feature",
  "properties": {
    "iso:country":"US",
    "sg:address":"9700 Park Plaza Ave",
    "sg:city":"Louisville",
    "sg:classifiers":[
        {
            "category":"Health Services",
            "subcategory":"Health Practitioner",
            "type":"Services"
        }
    ],
    "sg:phone":"+1 502 426 2034",
    "sg:postcode":"40241",
    "sg:province":"KY",
    "sg:tags":[
        "homeopathic"
    ],
    "wof:name":"Homeopathy Study Group & Referral Service",
    "wof:placetype":"venue"
},
  "geometry": {"coordinates":[-85.57933,38.309109],"type":"Point"}
}