{
  "type": "Feature",
  "properties": {
    "addr:full":"1569 Production Dr Burlington KY 41005",
    "addr:housenumber":"1569",
    "addr:postcode":"41005",
    "addr:street":"Production Dr",
    "iso:country":"US",
    "sg:address":"1569 Production Dr",
    "sg:city":"Burlington",
    "sg:classifiers":[
        {
            "category":"Building & Trades",
            "subcategory":"Construction",
            "type":"Services"
        }
    ],
    "sg:phone":"+1 859 282 0555",
    "sg:postcode":"41005",
    "sg:province":"KY",
    "sg:tags":[
        "painter"
    ],
    "wof:name":"Powder Coating Supply",
    "wof:placetype":"venue"
},
  "geometry": {"coordinates":[-84.684196,39.023701],"type":"Point"}
}