{
  "type": "Feature",
  "properties": {
    "addr:full":"10214 Landwood Dr Louisville KY 40291",
    "addr:housenumber":"10214",
    "addr:postcode":"40291",
    "addr:street":"Landwood Dr",
    "iso:country":"US",
    "sg:address":"10214 Landwood Dr",
    "sg:city":"Louisville",
    "sg:classifiers":[
        {
            "category":"Communications",
            "subcategory":"Newspaper",
            "type":"Services"
        }
    ],
    "sg:phone":"+1 502 231 8653",
    "sg:postcode":"40291",
    "sg:province":"KY",
    "wof:name":"Kevin Lee Rhea",
    "wof:placetype":"venue"
},
  "geometry": {"coordinates":[-85.57493599999999,38.120125],"type":"Point"}
}