{
  "type": "Feature",
  "properties": {
    "iso:country":"US",
    "sg:address":"813 Fleming Rd",
    "sg:city":"Maysville",
    "sg:classifiers":[
        {
            "category":"Wholesale",
            "subcategory":"Dairy",
            "type":"Manufacturing & Wholesale Goods"
        }
    ],
    "sg:phone":"+1 606 564 4540",
    "sg:postcode":"41056",
    "sg:province":"KY",
    "sg:tags":[
        "product"
    ],
    "wof:name":"G & W Distributing Co",
    "wof:placetype":"venue"
},
  "geometry": {"coordinates":[-83.753963,38.636831],"type":"Point"}
}