{
  "type": "Feature",
  "properties": {
    "iso:country":"US",
    "sg:address":"230 Gabe Rd",
    "sg:city":"Greensburg",
    "sg:classifiers":[
        {
            "category":"Organizations",
            "subcategory":"Religious Organization",
            "type":"Services"
        }
    ],
    "sg:phone":"+1 270 932 4372",
    "sg:postcode":"42743",
    "sg:province":"KY",
    "sg:tags":[
        "church"
    ],
    "sg:website":"www.sumnaz.com",
    "wof:name":"Summerville Church-Nazarene",
    "wof:placetype":"venue"
},
  "geometry": {"coordinates":[-85.54660699999999,37.325182],"type":"Point"}
}