{
  "type": "Feature",
  "properties": {
    "iso:country":"US",
    "sg:address":"12004 Alpine Way",
    "sg:city":"Goshen",
    "sg:classifiers":[
        {
            "category":"Building & Trades",
            "subcategory":"Landscaping Services",
            "type":"Services"
        }
    ],
    "sg:phone":"+1 502 228 0240",
    "sg:postcode":"40026",
    "sg:province":"KY",
    "wof:name":"Eagle Lawn LLC",
    "wof:placetype":"venue"
},
  "geometry": {"coordinates":[-85.581242,38.410529],"type":"Point"}
}