{
  "type": "Feature",
  "properties": {
    "iso:country":"US",
    "sg:address":"5136 State Hwy 351",
    "sg:city":"Henderson",
    "sg:classifiers":[
        {
            "category":"Professional",
            "subcategory":"Business Services",
            "type":"Services"
        }
    ],
    "sg:phone":"+1 270 826 4878",
    "sg:postcode":"42420",
    "sg:province":"KY",
    "sg:tags":[
        "recording",
        "studio"
    ],
    "wof:name":"KMG Recording Studios",
    "wof:placetype":"venue"
},
  "geometry": {"coordinates":[-87.53195700000001,37.822651],"type":"Point"}
}