{
  "type": "Feature",
  "properties": {
    "iso:country":"US",
    "sg:address":"3920 Willis Ave",
    "sg:city":"St Matthews",
    "sg:classifiers":[
        {
            "category":"Real Estate",
            "subcategory":"Real Estate Agent",
            "type":"Services"
        }
    ],
    "sg:phone":"+1 502 897 7161",
    "sg:postcode":"40207",
    "sg:province":"KY",
    "wof:name":"Cherokee Realty Co",
    "wof:placetype":"venue"
},
  "geometry": {"coordinates":[-85.65291499999999,38.252004],"type":"Point"}
}