{
  "type": "Feature",
  "properties": {
    "iso:country":"US",
    "sg:address":"5424 New Cut Rd",
    "sg:city":"Louisville",
    "sg:classifiers":[
        {
            "category":"Insurance",
            "subcategory":"Insurance Agent",
            "type":"Services"
        },
        {
            "category":"Insurance",
            "subcategory":"Hazard Insurance",
            "type":"Services"
        }
    ],
    "sg:phone":"+1 502 361 8435",
    "sg:postcode":"40214",
    "sg:province":"KY",
    "sg:tags":[
        "auto"
    ],
    "wof:name":"Able Insurance Services Inc",
    "wof:placetype":"venue"
},
  "geometry": {"coordinates":[-85.776005,38.148975],"type":"Point"}
}