{
  "type": "Feature",
  "properties": {
    "iso:country":"US",
    "sg:address":"226 Peterson Dr",
    "sg:city":"Elizabethtown",
    "sg:classifiers":[
        {
            "category":"Wholesale",
            "subcategory":"Hardware",
            "type":"Manufacturing & Wholesale Goods"
        }
    ],
    "sg:phone":"+1 270 234 1990",
    "sg:postcode":"42701",
    "sg:province":"KY",
    "sg:tags":[
        "fastener"
    ],
    "wof:name":"Van Note Supply Inc",
    "wof:placetype":"venue"
},
  "geometry": {"coordinates":[-85.899806,37.682357],"type":"Point"}
}