{
  "type": "Feature",
  "properties": {
    "iso:country":"US",
    "sg:address":"126 S 4th St",
    "sg:city":"Danville",
    "sg:classifiers":[
        {
            "category":"Restaurant",
            "type":"Food & Drink"
        }
    ],
    "sg:phone":"+1 859 236 9884",
    "sg:postcode":"40422",
    "sg:province":"KY",
    "wof:name":"Freddie's Restaurant",
    "wof:placetype":"venue"
},
  "geometry": {"coordinates":[-84.773989,37.645617],"type":"Point"}
}