{
  "type": "Feature",
  "properties": {
    "iso:country":"US",
    "sg:address":"113 Ray St",
    "sg:city":"Midway",
    "sg:classifiers":[
        {
            "category":"Shopping",
            "subcategory":"Gifts & Souvenirs",
            "type":"Retail Goods"
        }
    ],
    "sg:phone":"+1 859 846 4873",
    "sg:postcode":"40311",
    "sg:province":"KY",
    "sg:tags":[
        "shop"
    ],
    "wof:name":"Breckenridge Shop",
    "wof:placetype":"venue"
},
  "geometry": {"coordinates":[-84.01358999999999,38.318811],"type":"Point"}
}