{
  "type": "Feature",
  "properties": {
    "iso:country":"US",
    "sg:address":"7918 Fegenbush Ln",
    "sg:city":"Louisville",
    "sg:classifiers":[
        {
            "category":"Recreation",
            "type":"Entertainment"
        }
    ],
    "sg:phone":"+1 502 762 1515",
    "sg:postcode":"40228",
    "sg:province":"KY",
    "wof:name":"Olympic Karate Studio",
    "wof:placetype":"venue"
},
  "geometry": {"coordinates":[-85.616181,38.138903],"type":"Point"}
}