{
  "type": "Feature",
  "properties": {
    "iso:country":"US",
    "sg:address":"1110 Hathaway Ave",
    "sg:city":"Louisville",
    "sg:classifiers":[
        {
            "category":"Real Estate",
            "subcategory":"Real Estate Agent",
            "type":"Services"
        }
    ],
    "sg:phone":"+1 502 290 3588",
    "sg:postcode":"40215",
    "sg:province":"KY",
    "sg:tags":[
        "inspection"
    ],
    "wof:name":"Homesure",
    "wof:placetype":"venue"
},
  "geometry": {"coordinates":[-85.781656,38.195206],"type":"Point"}
}