{
  "type": "Feature",
  "properties": {
    "iso:country":"US",
    "sg:address":"4653 Astor Rd",
    "sg:city":"Louisville",
    "sg:classifiers":[
        {
            "category":"Manufacturing",
            "subcategory":"Metals",
            "type":"Manufacturing & Wholesale Goods"
        }
    ],
    "sg:phone":"+1 502 968 3454",
    "sg:postcode":"40218",
    "sg:province":"KY",
    "sg:tags":[
        "work"
    ],
    "wof:name":"A-1 Ornamental Iron Inc",
    "wof:placetype":"venue"
},
  "geometry": {"coordinates":[-85.69018699999999,38.185762],"type":"Point"}
}