{
  "type": "Feature",
  "properties": {
    "addr:full":"112 Stewarts Rd Somerset KY 42501",
    "addr:housenumber":"112",
    "addr:postcode":"42501",
    "addr:street":"Stewarts Rd",
    "iso:country":"US",
    "sg:address":"112 Stewarts Rd",
    "sg:city":"Somerset",
    "sg:classifiers":[
        {
            "category":"Retail",
            "subcategory":"Animal Services",
            "type":"Services"
        }
    ],
    "sg:phone":"+1 606 451 0038",
    "sg:postcode":"42501",
    "sg:province":"KY",
    "wof:name":"Pampered Pooch",
    "wof:placetype":"venue"
},
  "geometry": {"coordinates":[-84.602891,37.105242],"type":"Point"}
}