{
  "type": "Feature",
  "properties": {
    "iso:country":"US",
    "sg:address":"9479 State Hwy 550",
    "sg:city":"Mousie",
    "sg:classifiers":[
        {
            "category":"Government",
            "subcategory":"Post Office",
            "type":"Public Place"
        }
    ],
    "sg:phone":"+1 606 946 2448",
    "sg:postcode":"41839",
    "sg:province":"KY",
    "wof:name":"US Post Office",
    "wof:placetype":"venue"
},
  "geometry": {"coordinates":[-82.876695,37.397355],"type":"Point"}
}