{
  "type": "Feature",
  "properties": {
    "iso:country":"US",
    "sg:address":"1503 Dixie Hwy S",
    "sg:city":"Elizabethtown",
    "sg:classifiers":[
        {
            "category":"Organizations",
            "subcategory":"Non-profit Organization",
            "type":"Services"
        }
    ],
    "sg:phone":"+1 270 765 5145",
    "sg:postcode":"42701",
    "sg:province":"KY",
    "sg:tags":[
        "info",
        "addiction",
        "abuse",
        "treatment",
        "drug"
    ],
    "sg:website":"www.communicare.org",
    "wof:name":"Communicare Alcohol & Drug Svc",
    "wof:placetype":"venue"
},
  "geometry": {"coordinates":[-85.882622,37.725247],"type":"Point"}
}