{
  "type": "Feature",
  "properties": {
    "addr:full":"251 AA Hwy Highland Heights KY 41076",
    "addr:housenumber":"251",
    "addr:postcode":"41076",
    "addr:street":"Aa Hwy",
    "iso:country":"US",
    "sg:address":"251 AA Hwy",
    "sg:city":"Highland Heights",
    "sg:classifiers":[
        {
            "category":"Restaurant",
            "type":"Food & Drink"
        }
    ],
    "sg:phone":"+1 859 781 5678",
    "sg:postcode":"41076",
    "sg:province":"KY",
    "wof:name":"Waffle House",
    "wof:placetype":"venue"
},
  "geometry": {"coordinates":[-84.44499999999999,39.004902],"type":"Point"}
}