{
  "type": "Feature",
  "properties": {
    "iso:country":"US",
    "sg:address":"220 Center Park Dr",
    "sg:city":"Florence",
    "sg:classifiers":[
        {
            "category":"Shopping",
            "subcategory":"Jewelry",
            "type":"Retail Goods"
        }
    ],
    "sg:phone":"+1 859 525 6524",
    "sg:postcode":"41042",
    "sg:province":"KY",
    "sg:tags":[
        "jeweler"
    ],
    "wof:name":"Master Jeweler",
    "wof:placetype":"venue"
},
  "geometry": {"coordinates":[-84.63928799999999,38.99794],"type":"Point"}
}