{
  "type": "Feature",
  "properties": {
    "iso:country":"US",
    "sg:address":"1308 W Shelby St",
    "sg:city":"Falmouth",
    "sg:classifiers":[
        {
            "category":"Home & Garden",
            "subcategory":"Building Materials",
            "type":"Retail Goods"
        }
    ],
    "sg:phone":"+1 859 654 8737",
    "sg:postcode":"41040",
    "sg:province":"KY",
    "sg:tags":[
        "wallpaper"
    ],
    "wof:name":"Ammerman True Value Hardware",
    "wof:placetype":"venue"
},
  "geometry": {"coordinates":[-84.343969,38.67856],"type":"Point"}
}