{
  "type": "Feature",
  "properties": {
    "iso:country":"US",
    "sg:address":"384 Highland Lakes Dr",
    "sg:city":"Richmond",
    "sg:classifiers":[
        {
            "category":"Wholesale",
            "subcategory":"Drugs",
            "type":"Manufacturing & Wholesale Goods"
        },
        {
            "category":"Shopping",
            "type":"Retail Goods"
        }
    ],
    "sg:phone":"+1 859 623 7987",
    "sg:postcode":"40475",
    "sg:province":"KY",
    "sg:tags":[
        "cosmetic",
        "perfume"
    ],
    "wof:name":"Peek Cosmetics LLC",
    "wof:placetype":"venue"
},
  "geometry": {"coordinates":[-84.26516599999999,37.738856],"type":"Point"}
}