{
  "type": "Feature",
  "properties": {
    "addr:full":"371 Cutters Hill Ct Lexington KY 40509",
    "addr:housenumber":"371",
    "addr:postcode":"40509",
    "addr:street":"Cutters Hill Ct",
    "iso:country":"US",
    "sg:address":"371 Cutters Hill Ct",
    "sg:city":"Lexington",
    "sg:classifiers":[
        {
            "category":"Retail",
            "subcategory":"Auto Repair",
            "type":"Services"
        }
    ],
    "sg:phone":"+1 859 263 3312",
    "sg:postcode":"40509",
    "sg:province":"KY",
    "sg:tags":[
        "trailer"
    ],
    "wof:name":"Transport Specialist",
    "wof:placetype":"venue"
},
  "geometry": {"coordinates":[-84.37367,37.966736],"type":"Point"}
}