{
  "type": "Feature",
  "properties": {
    "iso:country":"US",
    "sg:address":"10168 Hempsteade Dr",
    "sg:city":"Union",
    "sg:classifiers":[
        {
            "category":"Professional",
            "subcategory":"Business Services",
            "type":"Services"
        }
    ],
    "sg:phone":"+1 859 384 0258",
    "sg:postcode":"41091",
    "sg:province":"KY",
    "wof:name":"Adhesion Solutions LLC",
    "wof:placetype":"venue"
},
  "geometry": {"coordinates":[-84.65060699999999,38.946221],"type":"Point"}
}