{
  "type": "Feature",
  "properties": {
    "addr:full":"291 Main St Murray KY 42071",
    "addr:housenumber":"291",
    "addr:postcode":"42071",
    "addr:street":"Main St",
    "iso:country":"US",
    "sg:address":"291 Main St",
    "sg:city":"Murray",
    "sg:classifiers":[
        {
            "category":"Professional",
            "subcategory":"Lawyer & Legal Services",
            "type":"Services"
        }
    ],
    "sg:phone":"+1 270 753 1292",
    "sg:postcode":"42071",
    "sg:province":"KY",
    "sg:tags":[
        "attorney"
    ],
    "wof:name":"Overbey & Adams",
    "wof:placetype":"venue"
},
  "geometry": {"coordinates":[-88.300614,36.610525],"type":"Point"}
}