{
  "type": "Feature",
  "properties": {
    "iso:country":"US",
    "sg:address":"4000 Crittenden Dr",
    "sg:city":"Louisville",
    "sg:classifiers":[
        {
            "category":"Manufacturing",
            "subcategory":"Glass & Minerals",
            "type":"Manufacturing & Wholesale Goods"
        }
    ],
    "sg:phone":"+1 502 367 6431",
    "sg:postcode":"40209",
    "sg:province":"KY",
    "sg:tags":[
        "concrete",
        "brick"
    ],
    "wof:name":"A C Krebs Co",
    "wof:placetype":"venue"
},
  "geometry": {"coordinates":[-85.75087000000001,38.196169],"type":"Point"}
}