{
  "type": "Feature",
  "properties": {
    "iso:country":"US",
    "sg:address":"110 Cleveland Dr",
    "sg:city":"Paris",
    "sg:classifiers":[
        {
            "category":"Restaurant",
            "type":"Food & Drink"
        },
        {
            "category":"Manufacturing",
            "subcategory":"Pet Food",
            "type":"Manufacturing & Wholesale Goods"
        }
    ],
    "sg:phone":"+1 859 987 5482",
    "sg:postcode":"40361",
    "sg:province":"KY",
    "sg:tags":[
        "pizza",
        "pizza-wholesale",
        "manufacturer"
    ],
    "wof:name":"Pizza Wholesale Co",
    "wof:placetype":"venue"
},
  "geometry": {"coordinates":[-84.289952,38.216805],"type":"Point"}
}