{
  "type": "Feature",
  "properties": {
    "iso:country":"US",
    "sg:address":"407 Jordan Rd",
    "sg:city":"Clarksville",
    "sg:classifiers":[
        {
            "category":"Personal",
            "subcategory":"Beauty Salon",
            "type":"Services"
        }
    ],
    "sg:phone":"+1 931 648 2136",
    "sg:postcode":"37042",
    "sg:province":"KY",
    "sg:tags":[
        "shop"
    ],
    "wof:name":"April's Hair Fashions",
    "wof:placetype":"venue"
},
  "geometry": {"coordinates":[-87.419837,36.585174],"type":"Point"}
}