{
  "type": "Feature",
  "properties": {
    "addr:full":"12 Jefferson St Winchester KY 40391",
    "addr:housenumber":"12",
    "addr:postcode":"40391",
    "addr:street":"Jefferson St",
    "iso:country":"US",
    "sg:address":"12 Jefferson St",
    "sg:city":"Winchester",
    "sg:classifiers":[
        {
            "category":"Manufacturing",
            "subcategory":"Tools & Machinery",
            "type":"Manufacturing & Wholesale Goods"
        }
    ],
    "sg:phone":"+1 859 745 1020",
    "sg:postcode":"40391",
    "sg:province":"KY",
    "sg:tags":[
        "die",
        "maker"
    ],
    "wof:name":"M J Machining",
    "wof:placetype":"venue"
},
  "geometry": {"coordinates":[-84.172545,37.99502],"type":"Point"}
}