{
  "type": "Feature",
  "properties": {
    "iso:country":"US",
    "sg:address":"3479 Old Dukedom Rd",
    "sg:city":"Mayfield",
    "sg:classifiers":[
        {
            "category":"Home & Garden",
            "subcategory":"Mobile Homes",
            "type":"Retail Goods"
        }
    ],
    "sg:phone":"+1 270 328 8411",
    "sg:postcode":"42066",
    "sg:province":"KY",
    "wof:name":"Noff's Homes Inc",
    "wof:placetype":"venue"
},
  "geometry": {"coordinates":[-88.669912,36.681835],"type":"Point"}
}