{
  "type": "Feature",
  "properties": {
    "iso:country":"US",
    "sg:address":"2428 State Hwy 80",
    "sg:city":"Somerset",
    "sg:classifiers":[
        {
            "category":"Farming",
            "subcategory":"Livestock Farm",
            "type":"Manufacturing & Wholesale Goods"
        }
    ],
    "sg:phone":"+1 606 679 1035",
    "sg:postcode":"42503",
    "sg:province":"KY",
    "sg:tags":[
        "beef",
        "feedlot",
        "cattle"
    ],
    "wof:name":"TNT Farms",
    "wof:placetype":"venue"
},
  "geometry": {"coordinates":[-84.65418699999999,37.088238],"type":"Point"}
}