{
  "type": "Feature",
  "properties": {
    "iso:country":"US",
    "sg:address":"1679 N Preston Hwy",
    "sg:city":"Shepherdsville",
    "sg:classifiers":[
        {
            "category":"Recreation",
            "type":"Entertainment"
        }
    ],
    "sg:phone":"+1 502 957 2712",
    "sg:postcode":"40165",
    "sg:province":"KY",
    "sg:tags":[
        "amusement"
    ],
    "wof:name":"N 2 Sports Inc",
    "wof:placetype":"venue"
},
  "geometry": {"coordinates":[-85.697469,38.021428],"type":"Point"}
}