{
  "type": "Feature",
  "properties": {
    "iso:country":"US",
    "sg:address":"3344 Hiseville-Park Rd",
    "sg:city":"Horse Cave",
    "sg:classifiers":[
        {
            "category":"Farming",
            "subcategory":"Livestock Farm",
            "type":"Manufacturing & Wholesale Goods"
        }
    ],
    "sg:phone":"+1 270 453 2849",
    "sg:postcode":"42749",
    "sg:province":"KY",
    "sg:tags":[
        "beef",
        "feedlot",
        "cattle"
    ],
    "wof:name":"Debbie & Eric Walton",
    "wof:placetype":"venue"
},
  "geometry": {"coordinates":[-85.772947,37.142154],"type":"Point"}
}