{
  "type": "Feature",
  "properties": {
    "iso:country":"US",
    "sg:address":"295 State Hwy 413",
    "sg:city":"Baxter",
    "sg:classifiers":[
        {
            "category":"Government",
            "subcategory":"Post Office",
            "type":"Public Place"
        }
    ],
    "sg:phone":"+1 606 573 1927",
    "sg:postcode":"40806",
    "sg:province":"KY",
    "wof:name":"US Post Office",
    "wof:placetype":"venue"
},
  "geometry": {"coordinates":[-83.32474000000001,36.863992],"type":"Point"}
}