{
  "type": "Feature",
  "properties": {
    "iso:country":"US",
    "sg:address":"1750 Campbell Ln",
    "sg:city":"Bowling Green",
    "sg:classifiers":[
        {
            "category":"Shopping",
            "subcategory":"Gifts & Souvenirs",
            "type":"Retail Goods"
        }
    ],
    "sg:phone":"+1 270 796 3606",
    "sg:postcode":"42104",
    "sg:province":"KY",
    "sg:tags":[
        "party",
        "supply"
    ],
    "wof:name":"Steamboat Salvage & Co",
    "wof:placetype":"venue"
},
  "geometry": {"coordinates":[-86.433059,36.952703],"type":"Point"}
}