{
  "type": "Feature",
  "properties": {
    "addr:full":"1021 Frankfort Rd Shelbyville KY 40065",
    "addr:housenumber":"1021",
    "addr:postcode":"40065",
    "addr:street":"Frankfort Rd",
    "iso:country":"US",
    "sg:address":"1021 Frankfort Rd",
    "sg:city":"Shelbyville",
    "sg:classifiers":[
        {
            "category":"Retail",
            "subcategory":"Auto Repair",
            "type":"Services"
        }
    ],
    "sg:phone":"+1 502 647 6259",
    "sg:postcode":"40065",
    "sg:province":"KY",
    "sg:tags":[
        "repairing",
        "engine"
    ],
    "wof:name":"Enhance Small Engine Repair",
    "wof:placetype":"venue"
},
  "geometry": {"coordinates":[-85.19962099999999,38.211386],"type":"Point"}
}