{
  "type": "Feature",
  "properties": {
    "addr:full":"3779 Madison Pike Covington KY 41017",
    "addr:housenumber":"3779",
    "addr:postcode":"41017",
    "addr:street":"Madison Pike",
    "iso:country":"US",
    "sg:address":"3779 Madison Pike",
    "sg:city":"Covington",
    "sg:classifiers":[
        {
            "category":"Retail",
            "subcategory":"Auto Repair",
            "type":"Services"
        }
    ],
    "sg:phone":"+1 859 356 9620",
    "sg:postcode":"41017",
    "sg:province":"KY",
    "sg:tags":[
        "repairing",
        "automobile"
    ],
    "wof:name":"D & F Svc Ctr",
    "wof:placetype":"venue"
},
  "geometry": {"coordinates":[-84.52959,39.016863],"type":"Point"}
}