{
  "type": "Feature",
  "properties": {
    "iso:country":"US",
    "sg:address":"2290 Alexandria Pike",
    "sg:city":"Southgate",
    "sg:classifiers":[
        {
            "category":"Banks & Credit Unions",
            "subcategory":"Bank",
            "type":"Services"
        }
    ],
    "sg:phone":"+1 859 781 3978",
    "sg:postcode":"41071",
    "sg:province":"KY",
    "sg:tags":[
        "automobile",
        "loan",
        "title"
    ],
    "wof:name":"Fast Auto & Payday Loans",
    "wof:placetype":"venue"
},
  "geometry": {"coordinates":[-84.47806300000001,39.076663],"type":"Point"}
}