{
  "type": "Feature",
  "properties": {
    "iso:country":"US",
    "sg:address":"220 E Main St",
    "sg:city":"Campbellsville",
    "sg:classifiers":[
        {
            "category":"Personal",
            "subcategory":"Barber",
            "type":"Services"
        }
    ],
    "sg:phone":"+1 270 465 6973",
    "sg:postcode":"42718",
    "sg:province":"KY",
    "wof:name":"Main Street Barber Shop",
    "wof:placetype":"venue"
},
  "geometry": {"coordinates":[-85.343317,37.341292],"type":"Point"}
}