{
  "type": "Feature",
  "properties": {
    "addr:full":"8607 Timberline Dr Louisville KY 40291",
    "addr:housenumber":"8607",
    "addr:postcode":"40291",
    "addr:street":"Timberline Dr",
    "iso:country":"US",
    "sg:address":"8607 Timberline Dr",
    "sg:city":"Louisville",
    "sg:classifiers":[
        {
            "category":"Professional",
            "subcategory":"Management & Consulting",
            "type":"Services"
        }
    ],
    "sg:phone":"+1 502 239 4555",
    "sg:postcode":"40291",
    "sg:province":"KY",
    "wof:name":"Med-Rec Assist LLC",
    "wof:placetype":"venue"
},
  "geometry": {"coordinates":[-85.599638,38.146211],"type":"Point"}
}