{
  "type": "Feature",
  "properties": {
    "addr:full":"13400 W Highway 42 # 290 Prospect KY 40059",
    "addr:housenumber":"13400",
    "addr:postcode":"40059",
    "addr:street":"W Highway 42 # 290",
    "iso:country":"US",
    "sg:address":"13400 W Highway 42 # 290",
    "sg:city":"Prospect",
    "sg:classifiers":[
        {
            "category":"Utilities",
            "subcategory":"Natural Gas",
            "type":"Services"
        }
    ],
    "sg:phone":"+1 502 228 9698",
    "sg:postcode":"40059",
    "sg:province":"KY",
    "wof:name":"Central Kentucky Gas Sales Inc",
    "wof:placetype":"venue"
},
  "geometry": {"coordinates":[-85.605569,38.363768],"type":"Point"}
}