{
  "type": "Feature",
  "properties": {
    "addr:full":"615 S 12th St Murray KY 42071",
    "addr:housenumber":"615",
    "addr:postcode":"42071",
    "addr:street":"S 12Th St",
    "iso:country":"US",
    "sg:address":"615 S 12th St",
    "sg:city":"Murray",
    "sg:classifiers":[
        {
            "category":"Building & Trades",
            "subcategory":"Cleaning & Sanitation",
            "type":"Services"
        }
    ],
    "sg:phone":"+1 270 759 4222",
    "sg:postcode":"42071",
    "sg:province":"KY",
    "sg:tags":[
        "janitor"
    ],
    "wof:name":"Have Mop Will Travel",
    "wof:placetype":"venue"
},
  "geometry": {"coordinates":[-88.315183,36.598946],"type":"Point"}
}