{
  "type": "Feature",
  "properties": {
    "addr:full":"1605 Scherm Rd Owensboro KY 42301",
    "addr:housenumber":"1605",
    "addr:postcode":"42301",
    "addr:street":"Scherm Rd",
    "iso:country":"US",
    "sg:address":"1605 Scherm Rd",
    "sg:city":"Owensboro",
    "sg:classifiers":[
        {
            "category":"Insurance",
            "subcategory":"Insurance Agent",
            "type":"Services"
        }
    ],
    "sg:phone":"+1 270 683 7343",
    "sg:postcode":"42301",
    "sg:province":"KY",
    "wof:name":"Allstate Insurance",
    "wof:placetype":"venue"
},
  "geometry": {"coordinates":[-87.12817800000001,37.742297],"type":"Point"}
}