{
  "type": "Feature",
  "properties": {
    "iso:country":"US",
    "sg:address":"220 S Chiles St",
    "sg:city":"Harrodsburg",
    "sg:classifiers":[
        {
            "category":"Museum",
            "type":"Entertainment"
        }
    ],
    "sg:phone":"+1 859 734 5985",
    "sg:postcode":"40330",
    "sg:province":"KY",
    "wof:name":"Harrodsburg Historical Society",
    "wof:placetype":"venue"
},
  "geometry": {"coordinates":[-84.84469,37.760873],"type":"Point"}
}