{
  "type": "Feature",
  "properties": {
    "iso:country":"US",
    "sg:address":"7660 la Grange Rd",
    "sg:city":"Louisville",
    "sg:classifiers":[
        {
            "category":"Building & Trades",
            "subcategory":"Construction",
            "type":"Services"
        }
    ],
    "sg:phone":"+1 502 473 1223",
    "sg:postcode":"40222",
    "sg:province":"KY",
    "sg:tags":[
        "contractor",
        "fence-sales"
    ],
    "wof:name":"Nationwide Fence & Farm Supply",
    "wof:placetype":"venue"
},
  "geometry": {"coordinates":[-85.602524,38.26318],"type":"Point"}
}