{
  "type": "Feature",
  "properties": {
    "addr:full":"2951 US Hwy 41 Henderson KY 42420",
    "addr:housenumber":"2951",
    "addr:postcode":"42420",
    "addr:street":"Us Hwy 41",
    "iso:country":"US",
    "sg:address":"2951 US Hwy 41",
    "sg:city":"Henderson",
    "sg:classifiers":[
        {
            "category":"Banks & Credit Unions",
            "subcategory":"Bank",
            "type":"Services"
        }
    ],
    "sg:phone":"+1 270 826 3362",
    "sg:postcode":"42420",
    "sg:province":"KY",
    "sg:tags":[
        "machine",
        "teller",
        "automated"
    ],
    "wof:name":"Parkco Atm",
    "wof:placetype":"venue"
},
  "geometry": {"coordinates":[-87.564565,37.881298],"type":"Point"}
}