{
  "type": "Feature",
  "properties": {
    "iso:country":"US",
    "sg:address":"4100 Cane Run Rd",
    "sg:city":"Shively",
    "sg:classifiers":[
        {
            "category":"Freight",
            "type":"Transportation"
        }
    ],
    "sg:phone":"+1 502 449 1222",
    "sg:postcode":"40216",
    "sg:province":"KY",
    "sg:tags":[
        "commercial",
        "storage"
    ],
    "wof:name":"Stor-All Mini Storage",
    "wof:placetype":"venue"
},
  "geometry": {"coordinates":[-85.83137499999999,38.203855],"type":"Point"}
}