{
  "type": "Feature",
  "properties": {
    "iso:country":"US",
    "sg:address":"2337 Woodhill Dr",
    "sg:city":"Lexington",
    "sg:classifiers":[
        {
            "category":"Organizations",
            "subcategory":"Community Association",
            "type":"Services"
        }
    ],
    "sg:phone":"+1 859 269 0599",
    "sg:postcode":"40509",
    "sg:province":"KY",
    "sg:tags":[
        "club"
    ],
    "wof:name":"Racing Photo Club",
    "wof:placetype":"venue"
},
  "geometry": {"coordinates":[-84.455547,38.017662],"type":"Point"}
}