{
  "type": "Feature",
  "properties": {
    "iso:country":"US",
    "sg:address":"324 E Main St",
    "sg:city":"Morehead",
    "sg:classifiers":[
        {
            "category":"Manufacturing",
            "subcategory":"Apparel",
            "type":"Manufacturing & Wholesale Goods"
        },
        {
            "category":"Shopping",
            "subcategory":"Clothing, Apparel, & Fashions",
            "type":"Retail Goods"
        }
    ],
    "sg:phone":"+1 606 780 9383",
    "sg:postcode":"40351",
    "sg:province":"KY",
    "sg:tags":[
        "boutique",
        "clothes",
        "lady",
        "accessory"
    ],
    "wof:name":"Pink Flamingo The",
    "wof:placetype":"venue"
},
  "geometry": {"coordinates":[-83.431945,38.185571],"type":"Point"}
}