{
  "type": "Feature",
  "properties": {
    "iso:country":"US",
    "sg:address":"19 Lexis Ct",
    "sg:city":"Bedford",
    "sg:classifiers":[
        {
            "category":"Building & Trades",
            "subcategory":"Construction",
            "type":"Services"
        }
    ],
    "sg:phone":"+1 502 255 0745",
    "sg:postcode":"40006",
    "sg:province":"KY",
    "sg:tags":[
        "hanging",
        "painter",
        "contractor"
    ],
    "wof:name":"Scholl Painting LLC",
    "wof:placetype":"venue"
},
  "geometry": {"coordinates":[-85.363355,38.609466],"type":"Point"}
}