{
  "type": "Feature",
  "properties": {
    "addr:full":"213 Main St Carrollton KY 41008",
    "addr:housenumber":"213",
    "addr:postcode":"41008",
    "addr:street":"Main St",
    "iso:country":"US",
    "sg:address":"213 Main St",
    "sg:city":"Carrollton",
    "sg:classifiers":[
        {
            "category":"Restaurant",
            "type":"Food & Drink"
        }
    ],
    "sg:phone":"+1 502 732 4000",
    "sg:postcode":"41008",
    "sg:province":"KY",
    "wof:name":"Mama Cello's",
    "wof:placetype":"venue"
},
  "geometry": {"coordinates":[-85.1853,38.682034],"type":"Point"}
}