{
  "type": "Feature",
  "properties": {
    "addr:full":"3552 Saint Andrews Village Cir Louisville KY 40241",
    "addr:housenumber":"3552",
    "addr:postcode":"40241",
    "addr:street":"Saint Andrews Village Cir",
    "iso:country":"US",
    "sg:address":"3552 Saint Andrews Village Cir",
    "sg:city":"Louisville",
    "sg:classifiers":[
        {
            "category":"Manufacturing",
            "subcategory":"Wood Products",
            "type":"Manufacturing & Wholesale Goods"
        },
        {
            "category":"Manufacturing",
            "subcategory":"Building Materials",
            "type":"Manufacturing & Wholesale Goods"
        }
    ],
    "sg:phone":"+1 502 426 1666",
    "sg:postcode":"40241",
    "sg:province":"KY",
    "sg:tags":[
        "veneers-wholesale",
        "materials-wholesale",
        "plywood",
        "manufacturer"
    ],
    "wof:name":"Rodahoffer Veneers",
    "wof:placetype":"venue"
},
  "geometry": {"coordinates":[-85.597599,38.29353],"type":"Point"}
}