{
  "type": "Feature",
  "properties": {
    "iso:country":"US",
    "sg:address":"502 Locust Ln",
    "sg:city":"Shelbyville",
    "sg:classifiers":[
        {
            "category":"Farming",
            "subcategory":"Farm",
            "type":"Manufacturing & Wholesale Goods"
        }
    ],
    "sg:phone":"+1 502 633 4977",
    "sg:postcode":"40065",
    "sg:province":"KY",
    "sg:tags":[
        "crop",
        "general"
    ],
    "wof:name":"Lynn Hirsch",
    "wof:placetype":"venue"
},
  "geometry": {"coordinates":[-85.258781,38.249154],"type":"Point"}
}