{
  "type": "Feature",
  "properties": {
    "iso:country":"US",
    "sg:address":"6223 Gamaliel Rd",
    "sg:city":"Gamaliel",
    "sg:classifiers":[
        {
            "category":"Farming",
            "subcategory":"Farm",
            "type":"Manufacturing & Wholesale Goods"
        }
    ],
    "sg:phone":"+1 270 457 2988",
    "sg:postcode":"42140",
    "sg:province":"KY",
    "wof:name":"William C Harlin Farm",
    "wof:placetype":"venue"
},
  "geometry": {"coordinates":[-85.767922,36.636383],"type":"Point"}
}