{
  "type": "Feature",
  "properties": {
    "iso:country":"US",
    "sg:address":"600 High St",
    "sg:city":"Hazard",
    "sg:classifiers":[
        {
            "category":"Professional",
            "subcategory":"Lawyer & Legal Services",
            "type":"Services"
        }
    ],
    "sg:phone":"+1 606 439 5131",
    "sg:postcode":"41701",
    "sg:province":"KY",
    "sg:tags":[
        "attorney"
    ],
    "wof:name":"John C Shackelford Law Office",
    "wof:placetype":"venue"
},
  "geometry": {"coordinates":[-83.195099,37.251161],"type":"Point"}
}