{
  "type": "Feature",
  "properties": {
    "iso:country":"US",
    "sg:address":"391 Gibson Ln",
    "sg:city":"Richmond",
    "sg:classifiers":[
        {
            "category":"Real Estate",
            "subcategory":"Real Estate Operator",
            "type":"Services"
        }
    ],
    "sg:phone":"+1 859 623 3556",
    "sg:postcode":"40475",
    "sg:province":"KY",
    "sg:tags":[
        "apartment"
    ],
    "wof:name":"Katelyn Court Apartments",
    "wof:placetype":"venue"
},
  "geometry": {"coordinates":[-84.287502,37.733804],"type":"Point"}
}