{
  "type": "Feature",
  "properties": {
    "addr:full":"1430 Dixie Hwy Park Hills KY 41011",
    "addr:housenumber":"1430",
    "addr:postcode":"41011",
    "addr:street":"Dixie Hwy",
    "iso:country":"US",
    "sg:address":"1430 Dixie Hwy",
    "sg:city":"Park Hills",
    "sg:classifiers":[
        {
            "category":"Travel",
            "subcategory":"Hotels & Motels",
            "type":"Entertainment"
        }
    ],
    "sg:phone":"+1 859 431 9998",
    "sg:postcode":"41011",
    "sg:province":"KY",
    "wof:name":"Den Lou Motel",
    "wof:placetype":"venue"
},
  "geometry": {"coordinates":[-84.52611,39.07191],"type":"Point"}
}