{
  "type": "Feature",
  "properties": {
    "iso:country":"US",
    "sg:address":"9700 Park Plaza Ave",
    "sg:city":"Louisville",
    "sg:classifiers":[
        {
            "category":"Social Services",
            "type":"Services"
        },
        {
            "category":"Personal",
            "type":"Services"
        },
        {
            "category":"Health Services",
            "subcategory":"Health Practitioner",
            "type":"Services"
        }
    ],
    "sg:phone":"+1 502 327 0209",
    "sg:postcode":"40241",
    "sg:province":"KY",
    "sg:tags":[
        "individual",
        "family",
        "psychotherapist",
        "counselors-licensed",
        "therapist",
        "marriage",
        "child",
        "professional",
        "counselor"
    ],
    "wof:name":"Bailey, Linda AAMFT LCSW PhD",
    "wof:placetype":"venue"
},
  "geometry": {"coordinates":[-85.57933,38.309109],"type":"Point"}
}