{
  "type": "Feature",
  "properties": {
    "addr:full":"1332 Ashford Dr Florence KY 41042",
    "addr:housenumber":"1332",
    "addr:postcode":"41042",
    "addr:street":"Ashford Dr",
    "iso:country":"US",
    "sg:address":"1332 Ashford Dr",
    "sg:city":"Florence",
    "sg:classifiers":[
        {
            "category":"Professional",
            "subcategory":"Computer Services",
            "type":"Services"
        }
    ],
    "sg:phone":"+1 859 746 2046",
    "sg:postcode":"41042",
    "sg:province":"KY",
    "sg:tags":[
        "internet"
    ],
    "wof:name":"On Time Media",
    "wof:placetype":"venue"
},
  "geometry": {"coordinates":[-84.675461,38.995132],"type":"Point"}
}