{
  "type": "Feature",
  "properties": {
    "iso:country":"US",
    "sg:address":"14 Michigan Ave",
    "sg:city":"Whitesburg",
    "sg:classifiers":[
        {
            "category":"Professional",
            "type":"Services"
        }
    ],
    "sg:phone":"+1 606 632 0060",
    "sg:postcode":"41858",
    "sg:province":"KY",
    "sg:tags":[
        "establishment"
    ],
    "wof:name":"Staff Residence",
    "wof:placetype":"venue"
},
  "geometry": {"coordinates":[-82.826156,37.114751],"type":"Point"}
}