{
  "type": "Feature",
  "properties": {
    "iso:country":"US",
    "sg:address":"1056 Goochtown Loop",
    "sg:city":"Eubank",
    "sg:classifiers":[
        {
            "category":"Professional",
            "subcategory":"Business Services",
            "type":"Services"
        }
    ],
    "sg:phone":"+1 606 379 5265",
    "sg:postcode":"42567",
    "sg:province":"KY",
    "wof:name":"Dexter L Johnson",
    "wof:placetype":"venue"
},
  "geometry": {"coordinates":[-84.60001,37.320876],"type":"Point"}
}