{
  "type": "Feature",
  "properties": {
    "iso:country":"US",
    "sg:address":"908 Center Rd",
    "sg:city":"Clarksville",
    "sg:classifiers":[
        {
            "category":"Retail",
            "subcategory":"Repair Shop",
            "type":"Services"
        }
    ],
    "sg:phone":"+1 931 542 0194",
    "sg:postcode":"37042",
    "sg:province":"KY",
    "sg:tags":[
        "bathtub",
        "sink",
        "refinishing"
    ],
    "wof:name":"Bath Tub Tiles & Bathroom",
    "wof:placetype":"venue"
},
  "geometry": {"coordinates":[-87.434865,36.591918],"type":"Point"}
}