{
  "type": "Feature",
  "properties": {
    "iso:country":"US",
    "sg:address":"1389 Alexandria Dr",
    "sg:city":"Lexington",
    "sg:classifiers":[
        {
            "category":"Wholesale",
            "subcategory":"Medical Equipment & Supplies",
            "type":"Manufacturing & Wholesale Goods"
        }
    ],
    "sg:phone":"+1 859 388 9499",
    "sg:postcode":"40504",
    "sg:province":"KY",
    "sg:tags":[
        "physician",
        "surgeon"
    ],
    "wof:name":"Mobility Plus",
    "wof:placetype":"venue"
},
  "geometry": {"coordinates":[-84.55235399999999,38.049165],"type":"Point"}
}