{
  "type": "Feature",
  "properties": {
    "addr:full":"11690 Utopia Rd Owensboro KY 42301",
    "addr:housenumber":"11690",
    "addr:postcode":"42301",
    "addr:street":"Utopia Rd",
    "iso:country":"US",
    "sg:address":"11690 Utopia Rd",
    "sg:city":"Owensboro",
    "sg:classifiers":[
        {
            "category":"Wholesale",
            "subcategory":"Farm Supplies",
            "type":"Manufacturing & Wholesale Goods"
        }
    ],
    "sg:phone":"+1 270 229 9196",
    "sg:postcode":"42301",
    "sg:province":"KY",
    "sg:tags":[
        "livestock"
    ],
    "wof:name":"Utopian Pullets Inc",
    "wof:placetype":"venue"
},
  "geometry": {"coordinates":[-87.36837300000001,37.728867],"type":"Point"}
}