{
  "type": "Feature",
  "properties": {
    "addr:full":"2162 State Hwy 80 Somerset KY 42503",
    "addr:housenumber":"2162",
    "addr:postcode":"42503",
    "addr:street":"State Hwy 80",
    "iso:country":"US",
    "sg:address":"2162 State Hwy 80",
    "sg:city":"Somerset",
    "sg:classifiers":[
        {
            "category":"Autos & Motor Vehicles",
            "subcategory":"Auto Supplies",
            "type":"Retail Goods"
        }
    ],
    "sg:phone":"+1 606 679 8953",
    "sg:postcode":"42503",
    "sg:province":"KY",
    "sg:tags":[
        "battery"
    ],
    "wof:name":"Interstate Battery System",
    "wof:placetype":"venue"
},
  "geometry": {"coordinates":[-84.643788,37.089517],"type":"Point"}
}