{
  "type": "Feature",
  "properties": {
    "iso:country":"US",
    "sg:address":"4226 Allmond Ave",
    "sg:city":"Louisville",
    "sg:classifiers":[
        {
            "category":"Home & Garden",
            "subcategory":"Carpets & Floor Coverings",
            "type":"Retail Goods"
        }
    ],
    "sg:phone":"+1 502 637 7858",
    "sg:postcode":"40209",
    "sg:province":"KY",
    "sg:tags":[
        "marking",
        "pavement"
    ],
    "wof:name":"Pavement Marking Systems Inc",
    "wof:placetype":"venue"
},
  "geometry": {"coordinates":[-85.758837,38.192935],"type":"Point"}
}