{
  "type": "Feature",
  "properties": {
    "iso:country":"US",
    "sg:address":"101 S Main St",
    "sg:city":"Franklin",
    "sg:classifiers":[
        {
            "category":"Banks & Credit Unions",
            "subcategory":"Bank",
            "type":"Services"
        }
    ],
    "sg:phone":"+1 270 586 8668",
    "sg:postcode":"42134",
    "sg:province":"KY",
    "sg:tags":[
        "loan",
        "real estate"
    ],
    "wof:name":"Kentucky Mortgage Source",
    "wof:placetype":"venue"
},
  "geometry": {"coordinates":[-86.57801000000001,36.722085],"type":"Point"}
}