{
  "type": "Feature",
  "properties": {
    "iso:country":"US",
    "sg:address":"110 E Hamilton St",
    "sg:city":"Edmonton",
    "sg:classifiers":[
        {
            "category":"Manufacturing",
            "subcategory":"Apparel",
            "type":"Manufacturing & Wholesale Goods"
        }
    ],
    "sg:phone":"+1 270 432 2281",
    "sg:postcode":"42129",
    "sg:province":"KY",
    "sg:tags":[
        "accessory"
    ],
    "wof:name":"Topps Safety Apparel Inc",
    "wof:placetype":"venue"
},
  "geometry": {"coordinates":[-85.61201,36.978663],"type":"Point"}
}