{
  "type": "Feature",
  "properties": {
    "iso:country":"US",
    "sg:address":"1733 E McMillan St",
    "sg:city":"Cincinnati",
    "sg:classifiers":[
        {
            "category":"Real Estate",
            "subcategory":"Architect",
            "type":"Services"
        }
    ],
    "sg:phone":"+1 513 662 3622",
    "sg:postcode":"45206",
    "sg:province":"OH",
    "wof:name":"Arend & Arend",
    "wof:placetype":"venue"
},
  "geometry": {"coordinates":[-84.472372,39.126128],"type":"Point"}
}