{
  "type": "Feature",
  "properties": {
    "iso:country":"US",
    "sg:address":"3522 Dixie Hwy",
    "sg:city":"Erlanger",
    "sg:classifiers":[
        {
            "category":"Banks & Credit Unions",
            "subcategory":"Bank",
            "type":"Services"
        }
    ],
    "sg:phone":"+1 859 727 3712",
    "sg:postcode":"41018",
    "sg:province":"KY",
    "wof:name":"Advantage Bank",
    "wof:placetype":"venue"
},
  "geometry": {"coordinates":[-84.60162,39.016367],"type":"Point"}
}