{
  "type": "Feature",
  "properties": {
    "iso:country":"US",
    "sg:address":"1925 Blankenbaker Pkwy",
    "sg:city":"Louisville",
    "sg:classifiers":[
        {
            "category":"Health Services",
            "subcategory":"Clinic",
            "type":"Services"
        },
        {
            "category":"Health Services",
            "subcategory":"Health Practitioner",
            "type":"Services"
        }
    ],
    "sg:phone":"+1 502 267 4851",
    "sg:postcode":"40299",
    "sg:province":"KY",
    "sg:tags":[
        "therapist",
        "therapy",
        "physical"
    ],
    "sg:website":"http://www.apexptky.com",
    "wof:name":"Apex Physical Therapy Blankenbaker",
    "wof:placetype":"venue"
},
  "geometry": {"coordinates":[-85.538918,38.213962],"type":"Point"}
}