{
  "type": "Feature",
  "properties": {
    "addr:full":"351 Main St Whitesburg KY 41838",
    "addr:housenumber":"351",
    "addr:postcode":"41838",
    "addr:street":"Main St",
    "iso:country":"US",
    "sg:address":"351 Main St",
    "sg:city":"Whitesburg",
    "sg:classifiers":[
        {
            "category":"Professional",
            "subcategory":"Lawyer & Legal Services",
            "type":"Services"
        }
    ],
    "sg:phone":"+1 606 633 2231",
    "sg:postcode":"41838",
    "sg:province":"KY",
    "sg:tags":[
        "attorney"
    ],
    "wof:name":"Darrell Hall",
    "wof:placetype":"venue"
},
  "geometry": {"coordinates":[-82.74160999999999,37.198212],"type":"Point"}
}