{
  "type": "Feature",
  "properties": {
    "iso:country":"US",
    "sg:address":"86 Old Harrodsburg Rd",
    "sg:city":"Frankfort",
    "sg:phone":"+1 502 223 1106",
    "sg:postcode":"40601",
    "sg:province":"KY",
    "sg:tags":[
        "oil"
    ],
    "wof:name":"Pitts Petroleum Products",
    "wof:placetype":"venue"
},
  "geometry": {"coordinates":[-84.89806799999999,38.151634],"type":"Point"}
}