{
  "type": "Feature",
  "properties": {
    "addr:full":"200 Old Morgantown Rd Bowling Green KY 42101",
    "addr:housenumber":"200",
    "addr:postcode":"42101",
    "addr:street":"Old Morgantown Rd",
    "iso:country":"US",
    "sg:address":"200 Old Morgantown Rd",
    "sg:city":"Bowling Green",
    "sg:classifiers":[
        {
            "category":"Professional",
            "subcategory":"Advertising",
            "type":"Services"
        }
    ],
    "sg:phone":"+1 270 781 8805",
    "sg:postcode":"42101",
    "sg:province":"KY",
    "sg:website":"www.clipit.com",
    "wof:name":"Clip-It Publication",
    "wof:placetype":"venue"
},
  "geometry": {"coordinates":[-86.457956,36.988766],"type":"Point"}
}