{
  "type": "Feature",
  "properties": {
    "addr:full":"253 Wallace Ave Kevil KY 42053",
    "addr:housenumber":"253",
    "addr:postcode":"42053",
    "addr:street":"Wallace Ave",
    "iso:country":"US",
    "sg:address":"253 Wallace Ave",
    "sg:city":"Kevil",
    "sg:classifiers":[
        {
            "category":"Government",
            "subcategory":"Post Office",
            "type":"Public Place"
        }
    ],
    "sg:phone":"+1 270 462 3425",
    "sg:postcode":"42053",
    "sg:province":"KY",
    "sg:tags":[
        "government-united",
        "state"
    ],
    "sg:website":"http://www.usps.com",
    "wof:name":"Us Post Office",
    "wof:placetype":"venue"
},
  "geometry": {"coordinates":[-88.886974,37.083865],"type":"Point"}
}