{
  "type": "Feature",
  "properties": {
    "addr:full":"160 Sulphur Spring Rd Lebanon KY 40033",
    "addr:housenumber":"160",
    "addr:postcode":"40033",
    "addr:street":"Sulphur Spring Rd",
    "iso:country":"US",
    "sg:address":"160 Sulphur Spring Rd",
    "sg:city":"Lebanon",
    "sg:classifiers":[
        {
            "category":"Building & Trades",
            "subcategory":"Construction",
            "type":"Services"
        }
    ],
    "sg:phone":"+1 270 692 3174",
    "sg:postcode":"40033",
    "sg:province":"KY",
    "sg:tags":[
        "painting",
        "contractor"
    ],
    "wof:name":"Camaco Inc",
    "wof:placetype":"venue"
},
  "geometry": {"coordinates":[-85.234369,37.573876],"type":"Point"}
}