{
  "type": "Feature",
  "properties": {
    "iso:country":"US",
    "sg:address":"7373 Turfway Rd",
    "sg:city":"Florence",
    "sg:phone":"+1 859 371 4400",
    "sg:postcode":"41042",
    "sg:province":"KY",
    "sg:website":"http://www1.hilton.com/",
    "wof:name":"Hilton Cincinnati Airport",
    "wof:placetype":"venue"
},
  "geometry": {"coordinates":[-84.63293899999999,39.015349],"type":"Point"}
}