{
  "type": "Feature",
  "properties": {
    "iso:country":"US",
    "sg:address":"108 Wallace Ct",
    "sg:city":"Lexington",
    "sg:classifiers":[
        {
            "category":"Building & Trades",
            "subcategory":"Construction",
            "type":"Services"
        }
    ],
    "sg:phone":"+1 859 272 5500",
    "sg:postcode":"40517",
    "sg:province":"KY",
    "sg:tags":[
        "tile",
        "dealer"
    ],
    "wof:name":"Mc Ginnis Tile Co",
    "wof:placetype":"venue"
},
  "geometry": {"coordinates":[-84.522231,37.988171],"type":"Point"}
}