{
  "type": "Feature",
  "properties": {
    "iso:country":"US",
    "sg:address":"123 S Chiles St",
    "sg:city":"Harrodsburg",
    "sg:classifiers":[
        {
            "category":"Autos & Motor Vehicles",
            "subcategory":"Auto Supplies",
            "type":"Retail Goods"
        }
    ],
    "sg:phone":"+1 859 734 3321",
    "sg:postcode":"40330",
    "sg:province":"KY",
    "sg:tags":[
        "automobile",
        "parts"
    ],
    "wof:name":"Harrodsburg Automotive Supply",
    "wof:placetype":"venue"
},
  "geometry": {"coordinates":[-84.844404,37.762131],"type":"Point"}
}