{
  "type": "Feature",
  "properties": {
    "iso:country":"US",
    "sg:address":"258 W Buford St",
    "sg:city":"Lancaster",
    "sg:classifiers":[
        {
            "category":"Government",
            "subcategory":"Office",
            "type":"Public Place"
        }
    ],
    "sg:phone":"+1 859 792 2162",
    "sg:postcode":"40444",
    "sg:province":"KY",
    "sg:tags":[
        "village"
    ],
    "wof:name":"Sewerage Disposal Plant",
    "wof:placetype":"venue"
},
  "geometry": {"coordinates":[-84.584687,37.617329],"type":"Point"}
}