{
  "type": "Feature",
  "properties": {
    "iso:country":"US",
    "sg:address":"1501 W 5th St",
    "sg:city":"London",
    "sg:classifiers":[
        {
            "category":"Real Estate",
            "subcategory":"Real Estate Agent",
            "type":"Services"
        }
    ],
    "sg:phone":"+1 606 878 7965",
    "sg:postcode":"40741",
    "sg:province":"KY",
    "wof:name":"Hodges Real Estate",
    "wof:placetype":"venue"
},
  "geometry": {"coordinates":[-84.093779,37.121108],"type":"Point"}
}