{
  "type": "Feature",
  "properties": {
    "iso:country":"US",
    "sg:address":"424 Letcher Ave",
    "sg:city":"Richmond",
    "sg:classifiers":[
        {
            "category":"Retail",
            "subcategory":"Laundry & Dry Cleaning",
            "type":"Services"
        }
    ],
    "sg:phone":"+1 859 624 0491",
    "sg:postcode":"40475",
    "sg:province":"KY",
    "wof:name":"Stanley Steemer Carpet Clg Svc",
    "wof:placetype":"venue"
},
  "geometry": {"coordinates":[-84.30624,37.755131],"type":"Point"}
}