{
  "type": "Feature",
  "properties": {
    "addr:full":"124 S Johnson St Louisville KY 40206",
    "addr:housenumber":"124",
    "addr:postcode":"40206",
    "addr:street":"S Johnson St",
    "iso:country":"US",
    "sg:address":"124 S Johnson St",
    "sg:city":"Louisville",
    "sg:classifiers":[
        {
            "category":"Wholesale",
            "subcategory":"Machinery & Supplies",
            "type":"Manufacturing & Wholesale Goods"
        }
    ],
    "sg:phone":"+1 502 583 0204",
    "sg:postcode":"40206",
    "sg:province":"KY",
    "sg:tags":[
        "equipment",
        "dairy"
    ],
    "wof:name":"Stockyard Farm & Dairy Supply",
    "wof:placetype":"venue"
},
  "geometry": {"coordinates":[-85.73153600000001,38.252834],"type":"Point"}
}