{
  "type": "Feature",
  "properties": {
    "iso:country":"US",
    "sg:address":"3101 13th St",
    "sg:city":"Ashland",
    "sg:classifiers":[
        {
            "category":"Retail",
            "subcategory":"Veterinary Services",
            "type":"Services"
        }
    ],
    "sg:phone":"+1 606 324 2984",
    "sg:postcode":"41102",
    "sg:province":"KY",
    "sg:tags":[
        "veterinarian"
    ],
    "wof:name":"Ashland Animal Clinic",
    "wof:placetype":"venue"
},
  "geometry": {"coordinates":[-82.66540999999999,38.458964],"type":"Point"}
}