{
  "type": "Feature",
  "properties": {
    "addr:full":"292 N Hubbards Ln St Matthews KY 40207",
    "addr:housenumber":"292",
    "addr:postcode":"40207",
    "addr:street":"N Hubbards Ln",
    "iso:country":"US",
    "sg:address":"292 N Hubbards Ln",
    "sg:city":"St Matthews",
    "sg:classifiers":[
        {
            "category":"Autos & Motor Vehicles",
            "subcategory":"Fuel & Gas Station",
            "type":"Retail Goods"
        }
    ],
    "sg:phone":"+1 502 893 7239",
    "sg:postcode":"40207",
    "sg:province":"KY",
    "sg:tags":[
        "oil"
    ],
    "wof:name":"Hubbards Lane Chevron",
    "wof:placetype":"venue"
},
  "geometry": {"coordinates":[-85.640171,38.258607],"type":"Point"}
}