{
  "type": "Feature",
  "properties": {
    "iso:country":"US",
    "sg:address":"112 S Main St",
    "sg:city":"Corbin",
    "sg:classifiers":[
        {
            "category":"Shopping",
            "subcategory":"Musical Instruments",
            "type":"Retail Goods"
        }
    ],
    "sg:phone":"+1 606 528 1354",
    "sg:postcode":"40701",
    "sg:province":"KY",
    "wof:name":"Gibson's Music",
    "wof:placetype":"venue"
},
  "geometry": {"coordinates":[-84.09645999999999,36.94715],"type":"Point"}
}