{
  "type": "Feature",
  "properties": {
    "addr:full":"109 Woodbine St Hopkinsville KY 42240",
    "addr:housenumber":"109",
    "addr:postcode":"42240",
    "addr:street":"Woodbine St",
    "iso:country":"US",
    "sg:address":"109 Woodbine St",
    "sg:city":"Hopkinsville",
    "sg:classifiers":[
        {
            "category":"Organizations",
            "subcategory":"Religious Organization",
            "type":"Services"
        }
    ],
    "sg:phone":"+1 270 269 9623",
    "sg:postcode":"42240",
    "sg:province":"KY",
    "sg:tags":[
        "church"
    ],
    "wof:name":"Victory Baptist Church",
    "wof:placetype":"venue"
},
  "geometry": {"coordinates":[-87.45689400000001,36.872228],"type":"Point"}
}