{
  "type": "Feature",
  "properties": {
    "iso:country":"US",
    "sg:address":"5720 Alexandria Pike",
    "sg:city":"Cold Spring",
    "sg:classifiers":[
        {
            "category":"Shopping",
            "subcategory":"Party Supplies",
            "type":"Retail Goods"
        }
    ],
    "sg:phone":"+1 859 635 2988",
    "sg:postcode":"41076",
    "sg:province":"KY",
    "wof:name":"Nelson's Tents Inc",
    "wof:placetype":"venue"
},
  "geometry": {"coordinates":[-84.41739699999999,38.9977],"type":"Point"}
}