{
  "type": "Feature",
  "properties": {
    "iso:country":"US",
    "sg:address":"501 W Main St",
    "sg:city":"Lexington",
    "sg:classifiers":[
        {
            "category":"Parking",
            "type":"Transportation"
        }
    ],
    "sg:phone":"+1 859 252 0762",
    "sg:postcode":"40507",
    "sg:province":"KY",
    "sg:tags":[
        "automobile"
    ],
    "wof:name":"Premier Parking",
    "wof:placetype":"venue"
},
  "geometry": {"coordinates":[-84.50137599999999,38.050273],"type":"Point"}
}