{
  "type": "Feature",
  "properties": {
    "iso:country":"US",
    "sg:address":"1845 Lone Oak Rd",
    "sg:city":"Paducah",
    "sg:classifiers":[
        {
            "category":"Government",
            "subcategory":"Office",
            "type":"Public Place"
        }
    ],
    "sg:phone":"+1 270 554 2077",
    "sg:postcode":"42003",
    "sg:province":"KY",
    "wof:name":"Whitehaven Welcome Ctr",
    "wof:placetype":"venue"
},
  "geometry": {"coordinates":[-88.652514,37.050302],"type":"Point"}
}