{
  "type": "Feature",
  "properties": {
    "addr:city":"Paducah",
    "addr:full":"1845 Lone Oak Rd Paducah, Ky 42003",
    "addr:house_number":"1845",
    "addr:housenumber":"1845",
    "addr:phone":"+1 270-554-2077",
    "addr:postcode":"42003",
    "addr:road":"Lone Oak Rd",
    "addr:state":"KY",
    "addr:street":"Lone Oak Rd",
    "iso:country":"US",
    "sg:address":"1845 Lone Oak Rd",
    "sg:city":"Paducah",
    "sg:classifiers":[
        {
            "category":"Government",
            "subcategory":"Office",
            "type":"Public Place"
        }
    ],
    "sg:phone":"+1 270 554 2077",
    "sg:postcode":"42003",
    "sg:province":"KY",
    "wof:airports":[
        102529565
    ],
    "wof:name":"Whitehaven Welcome Center",
    "wof:placetype":"venue"
},
  "geometry": {"coordinates":[-88.65222,37.05056],"type":"Point"}
}