{
  "type": "Feature",
  "properties": {
    "iso:country":"US",
    "sg:address":"8401 Shelbyville Rd # 203",
    "sg:city":"Louisville",
    "sg:classifiers":[
        {
            "category":"Home & Garden",
            "subcategory":"Kitchen Supply",
            "type":"Retail Goods"
        }
    ],
    "sg:phone":"+1 502 459 1868",
    "sg:postcode":"40222",
    "sg:province":"KY",
    "sg:tags":[
        "food",
        "equipment",
        "processing",
        "restaurant"
    ],
    "sg:website":"http://www.primesourcefse.com",
    "wof:name":"Primesource Foodservice Equipment, Inc.",
    "wof:placetype":"venue"
},
  "geometry": {"coordinates":[-85.598877,38.24818],"type":"Point"}
}