{
  "type": "Feature",
  "properties": {
    "iso:country":"US",
    "sg:address":"9200 Shelbyville Rd",
    "sg:city":"Louisville",
    "sg:classifiers":[
        {
            "category":"Government",
            "subcategory":"Office",
            "type":"Public Place"
        }
    ],
    "sg:phone":"+1 502 429 3422",
    "sg:postcode":"40222",
    "sg:province":"KY",
    "sg:tags":[
        "federal",
        "taxation"
    ],
    "wof:name":"US Comptroller Of The Currency",
    "wof:placetype":"venue"
},
  "geometry": {"coordinates":[-85.582323,38.246752],"type":"Point"}
}