{
  "type": "Feature",
  "properties": {
    "addr:full":"310 W Walnut St Lebanon KY 40033",
    "addr:housenumber":"310",
    "addr:postcode":"40033",
    "addr:street":"W Walnut St",
    "iso:country":"US",
    "sg:address":"310 W Walnut St",
    "sg:city":"Lebanon",
    "sg:classifiers":[
        {
            "category":"Food & Beverages",
            "subcategory":"Groceries & Convenience Stores",
            "type":"Retail Goods"
        }
    ],
    "sg:phone":"+1 270 699 2366",
    "sg:postcode":"40033",
    "sg:province":"KY",
    "sg:tags":[
        "grocer"
    ],
    "wof:name":"Mac's Convenience Store",
    "wof:placetype":"venue"
},
  "geometry": {"coordinates":[-85.258544,37.570473],"type":"Point"}
}