{
  "type": "Feature",
  "properties": {
    "iso:country":"US",
    "sg:address":"738 Priceville Rd",
    "sg:city":"Bonnieville",
    "sg:classifiers":[
        {
            "category":"Personal",
            "subcategory":"Beauty Salon",
            "type":"Services"
        }
    ],
    "sg:phone":"+1 270 531 3536",
    "sg:postcode":"42713",
    "sg:province":"KY",
    "wof:name":"Raye Ann's Country Style Salon",
    "wof:placetype":"venue"
},
  "geometry": {"coordinates":[-85.917708,37.382848],"type":"Point"}
}