{
  "type": "Feature",
  "properties": {
    "iso:country":"US",
    "sg:address":"159 S Main St",
    "sg:city":"Monticello",
    "sg:classifiers":[
        {
            "category":"Organizations",
            "subcategory":"Community Association",
            "type":"Services"
        }
    ],
    "sg:phone":"+1 606 340 0064",
    "sg:postcode":"42633",
    "sg:province":"KY",
    "sg:tags":[
        "educational"
    ],
    "wof:name":"Wayne County Literacy Program",
    "wof:placetype":"venue"
},
  "geometry": {"coordinates":[-84.85057500000001,36.828511],"type":"Point"}
}