{
  "type": "Feature",
  "properties": {
    "iso:country":"US",
    "sg:address":"33 Miller Dr",
    "sg:city":"Owingsville",
    "sg:classifiers":[
        {
            "category":"Restaurant",
            "type":"Food & Drink"
        }
    ],
    "sg:phone":"+1 606 674 6152",
    "sg:postcode":"40380",
    "sg:province":"KY",
    "wof:name":"Tom's Pizza Shops",
    "wof:placetype":"venue"
},
  "geometry": {"coordinates":[-83.86632299999999,37.855595],"type":"Point"}
}