{
  "type": "Feature",
  "properties": {
    "addr:full":"229 Churchill Dr Richmond KY 40475",
    "addr:housenumber":"229",
    "addr:postcode":"40475",
    "addr:street":"Churchill Dr",
    "iso:country":"US",
    "sg:address":"229 Churchill Dr",
    "sg:city":"Richmond",
    "sg:classifiers":[
        {
            "category":"Health Services",
            "subcategory":"Health Practitioner",
            "type":"Services"
        }
    ],
    "sg:phone":"+1 859 623 5096",
    "sg:postcode":"40475",
    "sg:province":"KY",
    "sg:tags":[
        "dietitian"
    ],
    "sg:website":"www.dietaryconsultants.com",
    "wof:name":"Dietary Consultants Inc",
    "wof:placetype":"venue"
},
  "geometry": {"coordinates":[-84.319891,37.773347],"type":"Point"}
}