{
  "type": "Feature",
  "properties": {
    "addr:full":"705 Werne Dr Lexington KY 40504",
    "addr:housenumber":"705",
    "addr:postcode":"40504",
    "addr:street":"Werne Dr",
    "iso:country":"US",
    "sg:address":"705 Werne Dr",
    "sg:city":"Lexington",
    "sg:classifiers":[
        {
            "category":"Building & Trades",
            "subcategory":"Pest Control",
            "type":"Services"
        }
    ],
    "sg:phone":"+1 859 253 1668",
    "sg:postcode":"40504",
    "sg:province":"KY",
    "wof:name":"Louisville-Lexington Extrmntng",
    "wof:placetype":"venue"
},
  "geometry": {"coordinates":[-84.54437,38.059404],"type":"Point"}
}