{
  "type": "Feature",
  "properties": {
    "addr:full":"2812 Portland Ave Louisville KY 40212",
    "addr:housenumber":"2812",
    "addr:postcode":"40212",
    "addr:street":"Portland Ave",
    "iso:country":"US",
    "sg:address":"2812 Portland Ave",
    "sg:city":"Louisville",
    "sg:classifiers":[
        {
            "category":"Personal",
            "subcategory":"Tanning Parlor",
            "type":"Services"
        }
    ],
    "sg:phone":"+1 502 776 1748",
    "sg:postcode":"40212",
    "sg:province":"KY",
    "sg:tags":[
        "salon"
    ],
    "wof:name":"Case's All Year Tanning",
    "wof:placetype":"venue"
},
  "geometry": {"coordinates":[-85.794056,38.272524],"type":"Point"}
}