{
  "type": "Feature",
  "properties": {
    "addr:full":"7505 Fegenbush Ln Louisville KY 40228",
    "addr:housenumber":"7505",
    "addr:postcode":"40228",
    "addr:street":"Fegenbush Ln",
    "iso:country":"US",
    "sg:address":"7505 Fegenbush Ln",
    "sg:city":"Louisville",
    "sg:classifiers":[
        {
            "category":"Building & Trades",
            "subcategory":"Construction",
            "type":"Services"
        }
    ],
    "sg:phone":"+1 502 968 1960",
    "sg:postcode":"40228",
    "sg:province":"KY",
    "sg:tags":[
        "waterproofing",
        "contractor"
    ],
    "wof:name":"Olshan Foundation Repair",
    "wof:placetype":"venue"
},
  "geometry": {"coordinates":[-85.62054500000001,38.141599],"type":"Point"}
}