{
  "type": "Feature",
  "properties": {
    "iso:country":"US",
    "sg:address":"3950 Park Dr",
    "sg:city":"Shively",
    "sg:classifiers":[
        {
            "category":"Shopping",
            "subcategory":"Bicycles & Sporting Goods",
            "type":"Retail Goods"
        }
    ],
    "sg:phone":"+1 502 448 3626",
    "sg:postcode":"40216",
    "sg:province":"KY",
    "sg:tags":[
        "apparel",
        "bowling",
        "accessory"
    ],
    "wof:name":"Thelma Lanes Pro Shop",
    "wof:placetype":"venue"
},
  "geometry": {"coordinates":[-85.809302,38.194158],"type":"Point"}
}