{
  "type": "Feature",
  "properties": {
    "addr:full":"505 Lexington St Maysville KY 41056",
    "addr:housenumber":"505",
    "addr:postcode":"41056",
    "addr:street":"Lexington St",
    "iso:country":"US",
    "sg:address":"505 Lexington St",
    "sg:city":"Maysville",
    "sg:classifiers":[
        {
            "category":"Retail",
            "subcategory":"Auto Repair",
            "type":"Services"
        }
    ],
    "sg:phone":"+1 606 564 7900",
    "sg:postcode":"41056",
    "sg:province":"KY",
    "sg:tags":[
        "wrecker"
    ],
    "wof:name":"B & J Towing",
    "wof:placetype":"venue"
},
  "geometry": {"coordinates":[-83.752135,38.640508],"type":"Point"}
}