{
  "type": "Feature",
  "properties": {
    "iso:country":"US",
    "sg:address":"4511 Lincoln Rd",
    "sg:city":"Louisville",
    "sg:classifiers":[
        {
            "category":"Building & Trades",
            "subcategory":"Construction",
            "type":"Services"
        }
    ],
    "sg:phone":"+1 502 479 3190",
    "sg:postcode":"40220",
    "sg:province":"KY",
    "sg:tags":[
        "house"
    ],
    "wof:name":"Isaac Renovations LLC",
    "wof:placetype":"venue"
},
  "geometry": {"coordinates":[-85.61123499999999,38.230805],"type":"Point"}
}