{
  "type": "Feature",
  "properties": {
    "iso:country":"US",
    "sg:address":"717 Malabu Dr",
    "sg:city":"Lexington",
    "sg:classifiers":[
        {
            "category":"Organizations",
            "subcategory":"Political Organization",
            "type":"Services"
        }
    ],
    "sg:phone":"+1 859 277 8051",
    "sg:postcode":"40502",
    "sg:province":"KY",
    "wof:name":"Isabel Yates Campaign For",
    "wof:placetype":"venue"
},
  "geometry": {"coordinates":[-84.50837,37.994658],"type":"Point"}
}