{
  "type": "Feature",
  "properties": {
    "iso:country":"US",
    "sg:address":"406 2nd St",
    "sg:city":"Carlisle",
    "sg:classifiers":[
        {
            "category":"Professional",
            "subcategory":"Computer Services",
            "type":"Services"
        }
    ],
    "sg:phone":"+1 859 289 2622",
    "sg:postcode":"40311",
    "sg:province":"KY",
    "sg:tags":[
        "programing",
        "custom"
    ],
    "wof:name":"Bb Shareware",
    "wof:placetype":"venue"
},
  "geometry": {"coordinates":[-84.033044,38.318623],"type":"Point"}
}