{
  "type": "Feature",
  "properties": {
    "iso:country":"US",
    "sg:address":"1815 Plantside Dr",
    "sg:city":"Louisville",
    "sg:classifiers":[
        {
            "category":"Manufacturing",
            "subcategory":"Tools & Machinery",
            "type":"Manufacturing & Wholesale Goods"
        }
    ],
    "sg:phone":"+1 502 491 3440",
    "sg:postcode":"40299",
    "sg:province":"KY",
    "sg:tags":[
        "optical"
    ],
    "sg:website":"www.dosc.com",
    "wof:name":"Dispensers Optical Svc",
    "wof:placetype":"venue"
},
  "geometry": {"coordinates":[-85.572594,38.21704],"type":"Point"}
}