{
  "type": "Feature",
  "properties": {
    "addr:full":"909 E Main St Stanford KY 40484",
    "addr:housenumber":"909",
    "addr:postcode":"40484",
    "addr:street":"E Main St",
    "iso:country":"US",
    "sg:address":"909 E Main St",
    "sg:city":"Stanford",
    "sg:classifiers":[
        {
            "category":"Organizations",
            "subcategory":"Community Association",
            "type":"Services"
        }
    ],
    "sg:phone":"+1 606 365 3751",
    "sg:postcode":"40484",
    "sg:province":"KY",
    "sg:tags":[
        "military"
    ],
    "wof:name":"American Legion",
    "wof:placetype":"venue"
},
  "geometry": {"coordinates":[-84.645652,37.529882],"type":"Point"}
}