{
  "type": "Feature",
  "properties": {
    "iso:country":"US",
    "sg:address":"6821 Brighton Springs Ln",
    "sg:city":"Louisville",
    "sg:classifiers":[
        {
            "category":"Building & Trades",
            "subcategory":"Construction",
            "type":"Services"
        }
    ],
    "sg:phone":"+1 502 231 5575",
    "sg:postcode":"40291",
    "sg:province":"KY",
    "sg:tags":[
        "house"
    ],
    "wof:name":"Brookebuilt Homes LLC",
    "wof:placetype":"venue"
},
  "geometry": {"coordinates":[-85.576812,38.145748],"type":"Point"}
}