{
  "type": "Feature",
  "properties": {
    "addr:full":"2180 Madisonville Rd Hopkinsville KY 42240",
    "addr:housenumber":"2180",
    "addr:postcode":"42240",
    "addr:street":"Madisonville Rd",
    "iso:country":"US",
    "sg:address":"2180 Madisonville Rd",
    "sg:city":"Hopkinsville",
    "sg:classifiers":[
        {
            "category":"Shopping",
            "subcategory":"Gifts & Souvenirs",
            "type":"Retail Goods"
        }
    ],
    "sg:phone":"+1 270 881 3859",
    "sg:postcode":"42240",
    "sg:province":"KY",
    "wof:name":"Grape Vine",
    "wof:placetype":"venue"
},
  "geometry": {"coordinates":[-87.481011,36.900602],"type":"Point"}
}