{
  "type": "Feature",
  "properties": {
    "iso:country":"US",
    "sg:address":"5460 Hudgins Hwy",
    "sg:city":"Summersville",
    "sg:classifiers":[
        {
            "category":"Retail",
            "subcategory":"Auto Repair",
            "type":"Services"
        }
    ],
    "sg:phone":"+1 270 324 2873",
    "sg:postcode":"42782",
    "sg:province":"KY",
    "sg:tags":[
        "truck"
    ],
    "wof:name":"Perkins Equipment Co",
    "wof:placetype":"venue"
},
  "geometry": {"coordinates":[-85.66187600000001,37.34768],"type":"Point"}
}