{
  "type": "Feature",
  "properties": {
    "iso:country":"US",
    "sg:address":"8000 State Hwy 7",
    "sg:city":"Topmost",
    "sg:classifiers":[
        {
            "category":"Education",
            "subcategory":"School",
            "type":"Public Place"
        }
    ],
    "sg:phone":"+1 606 447 2111",
    "sg:postcode":"41862",
    "sg:province":"KY",
    "wof:name":"Beaver Creek Headstart Ctr",
    "wof:placetype":"venue"
},
  "geometry": {"coordinates":[-82.811892,37.353078],"type":"Point"}
}