{
  "type": "Feature",
  "properties": {
    "addr:full":"1126 S 3rd St Louisville KY 40203",
    "addr:housenumber":"1126",
    "addr:postcode":"40203",
    "addr:street":"S 3Rd St",
    "iso:country":"US",
    "sg:address":"1126 S 3rd St",
    "sg:city":"Louisville",
    "sg:classifiers":[
        {
            "category":"Health Services",
            "subcategory":"Doctor",
            "type":"Services"
        }
    ],
    "sg:phone":"+1 502 587 0280",
    "sg:postcode":"40203",
    "sg:province":"KY",
    "sg:tags":[
        "dentist"
    ],
    "wof:name":"Old Louisville Dental Ctr",
    "wof:placetype":"venue"
},
  "geometry": {"coordinates":[-85.758503,38.236445],"type":"Point"}
}