{
  "type": "Feature",
  "properties": {
    "addr:full":"8017 Catherine Ln Ste 1 Louisville KY 40222",
    "addr:housenumber":"8017",
    "addr:postcode":"40222",
    "addr:street":"Catherine Ln Ste 1",
    "iso:country":"US",
    "sg:address":"8017 Catherine Ln Ste 1",
    "sg:city":"Louisville",
    "sg:classifiers":[
        {
            "category":"Manufacturing",
            "subcategory":"Metals",
            "type":"Manufacturing & Wholesale Goods"
        }
    ],
    "sg:phone":"+1 502 426 2008",
    "sg:postcode":"40222",
    "sg:province":"KY",
    "sg:tags":[
        "steel",
        "erectors"
    ],
    "wof:name":"Javier Steel Corp",
    "wof:placetype":"venue"
},
  "geometry": {"coordinates":[-85.60637699999999,38.258917],"type":"Point"}
}