{
  "type": "Feature",
  "properties": {
    "addr:full":"133 Cleveland Ave Hazard KY 41701",
    "addr:housenumber":"133",
    "addr:postcode":"41701",
    "addr:street":"Cleveland Ave",
    "iso:country":"US",
    "sg:address":"133 Cleveland Ave",
    "sg:city":"Hazard",
    "sg:classifiers":[
        {
            "category":"Building & Trades",
            "subcategory":"Construction",
            "type":"Services"
        }
    ],
    "sg:phone":"+1 606 436 3802",
    "sg:postcode":"41701",
    "sg:province":"KY",
    "sg:tags":[
        "roofing",
        "contractor"
    ],
    "wof:name":"Hurt Roofing",
    "wof:placetype":"venue"
},
  "geometry": {"coordinates":[-83.19408900000001,37.265718],"type":"Point"}
}