{
  "type": "Feature",
  "properties": {
    "iso:country":"US",
    "sg:address":"305 Wyatt Dr",
    "sg:city":"Mayfield",
    "sg:classifiers":[
        {
            "category":"Utilities",
            "subcategory":"Mobile Phone",
            "type":"Services"
        }
    ],
    "sg:phone":"+1 270 247 4871",
    "sg:postcode":"42066",
    "sg:province":"KY",
    "sg:tags":[
        "telephone",
        "cellular"
    ],
    "wof:name":"Cingular Wireless",
    "wof:placetype":"venue"
},
  "geometry": {"coordinates":[-88.627438,36.722596],"type":"Point"}
}