{
  "type": "Feature",
  "properties": {
    "iso:country":"US",
    "sg:address":"1196 W Old Volney Rd",
    "sg:city":"Olmstead",
    "sg:classifiers":[
        {
            "category":"Autos & Motor Vehicles",
            "subcategory":"Auto Supplies",
            "type":"Retail Goods"
        }
    ],
    "sg:phone":"+1 270 726 3430",
    "sg:postcode":"42265",
    "sg:province":"KY",
    "sg:tags":[
        "parts"
    ],
    "wof:name":"A1 Auto Parts & Muffler Shop",
    "wof:placetype":"venue"
},
  "geometry": {"coordinates":[-87.026602,36.782771],"type":"Point"}
}