{
  "type": "Feature",
  "properties": {
    "iso:country":"US",
    "sg:address":"822 State Hwy 2034",
    "sg:city":"Ermine",
    "sg:classifiers":[
        {
            "category":"Government",
            "subcategory":"Post Office",
            "type":"Public Place"
        }
    ],
    "sg:phone":"+1 606 633 0391",
    "sg:postcode":"41815",
    "sg:province":"KY",
    "wof:name":"US Post Office",
    "wof:placetype":"venue"
},
  "geometry": {"coordinates":[-82.792804,37.134446],"type":"Point"}
}