{
  "type": "Feature",
  "properties": {
    "addr:full":"102 Madison Square Dr Madisonville KY 42431",
    "addr:housenumber":"102",
    "addr:postcode":"42431",
    "addr:street":"Madison Square Dr",
    "iso:country":"US",
    "sg:address":"102 Madison Square Dr",
    "sg:city":"Madisonville",
    "sg:classifiers":[
        {
            "category":"Personal",
            "subcategory":"Beauty Salon",
            "type":"Services"
        }
    ],
    "sg:phone":"+1 270 821 2424",
    "sg:postcode":"42431",
    "sg:province":"KY",
    "sg:tags":[
        "manicuring"
    ],
    "wof:name":"Nail Spa",
    "wof:placetype":"venue"
},
  "geometry": {"coordinates":[-87.479198,37.322887],"type":"Point"}
}