{
  "type": "Feature",
  "properties": {
    "iso:country":"US",
    "sg:address":"301 United Ct",
    "sg:city":"Lexington",
    "sg:classifiers":[
        {
            "category":"Building & Trades",
            "subcategory":"Electrical",
            "type":"Services"
        }
    ],
    "sg:phone":"+1 859 263 0770",
    "sg:postcode":"40509",
    "sg:province":"KY",
    "sg:tags":[
        "electric",
        "contractor"
    ],
    "wof:name":"R & S",
    "wof:placetype":"venue"
},
  "geometry": {"coordinates":[-84.37556499999999,37.968441],"type":"Point"}
}