{
  "type": "Feature",
  "properties": {
    "iso:country":"US",
    "sg:address":"4687 Chenault Bridge Rd",
    "sg:city":"Danville",
    "sg:classifiers":[
        {
            "category":"Building & Trades",
            "subcategory":"Plumbing",
            "type":"Services"
        }
    ],
    "sg:phone":"+1 859 236 4545",
    "sg:postcode":"40422",
    "sg:province":"KY",
    "sg:tags":[
        "plumbing",
        "contractor"
    ],
    "wof:name":"Underwood Plumbing",
    "wof:placetype":"venue"
},
  "geometry": {"coordinates":[-84.700461,37.671825],"type":"Point"}
}