{
  "type": "Feature",
  "properties": {
    "addr:full":"340 US Hwy 41 Henderson KY 42420",
    "addr:housenumber":"340",
    "addr:postcode":"42420",
    "addr:street":"Us Hwy 41",
    "iso:country":"US",
    "sg:address":"340 US Hwy 41",
    "sg:city":"Henderson",
    "sg:classifiers":[
        {
            "category":"Wholesale",
            "subcategory":"Farm Supplies",
            "type":"Manufacturing & Wholesale Goods"
        }
    ],
    "sg:phone":"+1 270 827 5787",
    "sg:postcode":"42420",
    "sg:province":"KY",
    "sg:tags":[
        "bulb",
        "seed"
    ],
    "wof:name":"Fyngenta Seeds",
    "wof:placetype":"venue"
},
  "geometry": {"coordinates":[-87.569475,37.819397],"type":"Point"}
}