{
  "type": "Feature",
  "properties": {
    "addr:full":"2741 Turkeyfoot Rd Crestview Hills KY 41017",
    "addr:housenumber":"2741",
    "addr:postcode":"41017",
    "addr:street":"Turkeyfoot Rd",
    "iso:country":"US",
    "sg:address":"2741 Turkeyfoot Rd",
    "sg:city":"Crestview Hills",
    "sg:classifiers":[
        {
            "category":"Banks & Credit Unions",
            "subcategory":"Bank",
            "type":"Services"
        }
    ],
    "sg:phone":"+1 859 578 6040",
    "sg:postcode":"41017",
    "sg:province":"KY",
    "wof:name":"US Bank",
    "wof:placetype":"venue"
},
  "geometry": {"coordinates":[-84.568654,39.027329],"type":"Point"}
}