{
  "type": "Feature",
  "properties": {
    "iso:country":"US",
    "sg:address":"1192 Liberty Rd",
    "sg:city":"West Liberty",
    "sg:classifiers":[
        {
            "category":"Building & Trades",
            "subcategory":"Construction",
            "type":"Services"
        }
    ],
    "sg:phone":"+1 606 743 4563",
    "sg:postcode":"41472",
    "sg:province":"KY",
    "sg:tags":[
        "house"
    ],
    "wof:name":"Sargent Builders",
    "wof:placetype":"venue"
},
  "geometry": {"coordinates":[-83.27422900000001,37.924049],"type":"Point"}
}