{
  "type": "Feature",
  "properties": {
    "addr:full":"1439 Bosley Rd Owensboro KY 42301",
    "addr:housenumber":"1439",
    "addr:postcode":"42301",
    "addr:street":"Bosley Rd",
    "iso:country":"US",
    "sg:address":"1439 Bosley Rd",
    "sg:city":"Owensboro",
    "sg:classifiers":[
        {
            "category":"Professional",
            "subcategory":"Accounting & Tax Preparation",
            "type":"Services"
        }
    ],
    "sg:phone":"+1 270 926 4598",
    "sg:postcode":"42301",
    "sg:province":"KY",
    "sg:tags":[
        "accountant"
    ],
    "sg:website":"www.bradencpa.com",
    "wof:name":"Braden & Assoc",
    "wof:placetype":"venue"
},
  "geometry": {"coordinates":[-87.134801,37.760286],"type":"Point"}
}