{
  "type": "Feature",
  "properties": {
    "addr:full":"460 S College St Woodburn KY 42170",
    "addr:housenumber":"460",
    "addr:postcode":"42170",
    "addr:street":"S College St",
    "iso:country":"US",
    "sg:address":"460 S College St",
    "sg:city":"Woodburn",
    "sg:classifiers":[
        {
            "category":"Health Services",
            "subcategory":"Nursing And Care Facility",
            "type":"Services"
        }
    ],
    "sg:phone":"+1 270 529 2853",
    "sg:postcode":"42170",
    "sg:province":"KY",
    "sg:tags":[
        "home",
        "convalescent"
    ],
    "wof:name":"Hopkins Nursing Facility",
    "wof:placetype":"venue"
},
  "geometry": {"coordinates":[-86.528103,36.836482],"type":"Point"}
}