{
  "type": "Feature",
  "properties": {
    "iso:country":"US",
    "sg:address":"1705 Irvine Rd",
    "sg:city":"Richmond",
    "sg:classifiers":[
        {
            "category":"Organizations",
            "subcategory":"Religious Organization",
            "type":"Services"
        }
    ],
    "sg:phone":"+1 859 625 5366",
    "sg:postcode":"40475",
    "sg:province":"KY",
    "sg:tags":[
        "church"
    ],
    "wof:name":"Abundant Life Ministries",
    "wof:placetype":"venue"
},
  "geometry": {"coordinates":[-84.25721799999999,37.743877],"type":"Point"}
}