{
  "type": "Feature",
  "properties": {
    "iso:country":"US",
    "sg:address":"10936 Dixie Hwy",
    "sg:city":"Louisville",
    "sg:classifiers":[
        {
            "category":"Real Estate",
            "subcategory":"Real Estate Operator",
            "type":"Services"
        }
    ],
    "sg:phone":"+1 502 935 0310",
    "sg:postcode":"40272",
    "sg:province":"KY",
    "sg:tags":[
        "building",
        "nonresidential"
    ],
    "wof:name":"Metro United Way Inc",
    "wof:placetype":"venue"
},
  "geometry": {"coordinates":[-85.87595399999999,38.09207],"type":"Point"}
}