{
  "type": "Feature",
  "properties": {
    "addr:full":"130 E Woodlawn Ave Louisville KY 40214",
    "addr:housenumber":"130",
    "addr:postcode":"40214",
    "addr:street":"E Woodlawn Ave",
    "iso:country":"US",
    "sg:address":"130 E Woodlawn Ave",
    "sg:city":"Louisville",
    "sg:classifiers":[
        {
            "category":"Shopping",
            "subcategory":"Clothing, Apparel, & Fashions",
            "type":"Retail Goods"
        }
    ],
    "sg:phone":"+1 502 363 0068",
    "sg:postcode":"40214",
    "sg:province":"KY",
    "sg:tags":[
        "t"
    ],
    "wof:name":"Patriot Screen Printing",
    "wof:placetype":"venue"
},
  "geometry": {"coordinates":[-85.760183,38.180828],"type":"Point"}
}