{
  "type": "Feature",
  "properties": {
    "iso:country":"US",
    "sg:address":"1973 Bardstown Rd",
    "sg:city":"Springfield",
    "sg:classifiers":[
        {
            "category":"Home & Garden",
            "subcategory":"Carpets & Floor Coverings",
            "type":"Retail Goods"
        }
    ],
    "sg:phone":"+1 859 336 5157",
    "sg:postcode":"40069",
    "sg:province":"KY",
    "sg:tags":[
        "dealer",
        "rug"
    ],
    "wof:name":"Discount Carpets",
    "wof:placetype":"venue"
},
  "geometry": {"coordinates":[-85.24925,37.699261],"type":"Point"}
}