{
  "type": "Feature",
  "properties": {
    "addr:full":"5324 S 3rd St Louisville KY 40214",
    "addr:housenumber":"5324",
    "addr:postcode":"40214",
    "addr:street":"S 3Rd St",
    "iso:country":"US",
    "sg:address":"5324 S 3rd St",
    "sg:city":"Louisville",
    "sg:classifiers":[
        {
            "category":"Shopping",
            "subcategory":"Discount & Variety Stores",
            "type":"Retail Goods"
        }
    ],
    "sg:phone":"+1 502 368 0490",
    "sg:postcode":"40214",
    "sg:province":"KY",
    "sg:tags":[
        "merchandise",
        "general"
    ],
    "wof:name":"Wow Que Barato",
    "wof:placetype":"venue"
},
  "geometry": {"coordinates":[-85.768186,38.170896],"type":"Point"}
}