{
  "type": "Feature",
  "properties": {
    "addr:full":"3511 Main St Stamping Ground KY 40379",
    "addr:housenumber":"3511",
    "addr:postcode":"40379",
    "addr:street":"Main St",
    "iso:country":"US",
    "sg:address":"3511 Main St",
    "sg:city":"Stamping Ground",
    "sg:classifiers":[
        {
            "category":"Manufacturing",
            "subcategory":"Tools & Machinery",
            "type":"Manufacturing & Wholesale Goods"
        }
    ],
    "sg:phone":"+1 502 535 4430",
    "sg:postcode":"40379",
    "sg:province":"KY",
    "sg:tags":[
        "machine",
        "shop"
    ],
    "sg:website":"www.commonwealthtool.com",
    "wof:name":"Commonwealth Tool & Machine",
    "wof:placetype":"venue"
},
  "geometry": {"coordinates":[-84.69484300000001,38.274279],"type":"Point"}
}