{
  "type": "Feature",
  "properties": {
    "iso:country":"US",
    "sg:address":"110 N Hubbards Ln",
    "sg:city":"St Matthews",
    "sg:classifiers":[
        {
            "category":"Health Services",
            "subcategory":"Podiatrist",
            "type":"Services"
        }
    ],
    "sg:phone":"+1 502 897 2047",
    "sg:postcode":"40207",
    "sg:province":"KY",
    "wof:name":"C A Nava Jr DPM",
    "wof:placetype":"venue"
},
  "geometry": {"coordinates":[-85.63977199999999,38.253886],"type":"Point"}
}