{
  "type": "Feature",
  "properties": {
    "iso:country":"US",
    "sg:address":"909 Hustonville Rd",
    "sg:city":"Danville",
    "sg:classifiers":[
        {
            "category":"Food & Beverages",
            "subcategory":"Groceries & Convenience Stores",
            "type":"Retail Goods"
        }
    ],
    "sg:phone":"+1 859 000 1111",
    "sg:postcode":"40422",
    "sg:province":"KY",
    "sg:tags":[
        "grocer"
    ],
    "wof:name":"Aldi",
    "wof:placetype":"venue"
},
  "geometry": {"coordinates":[-84.774951,37.631233],"type":"Point"}
}