{
  "type": "Feature",
  "properties": {
    "addr:full":"2738 Frederica St Owensboro KY 42301",
    "addr:housenumber":"2738",
    "addr:postcode":"42301",
    "addr:street":"Frederica St",
    "iso:country":"US",
    "sg:address":"2738 Frederica St",
    "sg:city":"Owensboro",
    "sg:classifiers":[
        {
            "category":"Personal",
            "subcategory":"Beauty Salon",
            "type":"Services"
        }
    ],
    "sg:phone":"+1 270 683 0800",
    "sg:postcode":"42301",
    "sg:province":"KY",
    "wof:name":"Excursions",
    "wof:placetype":"venue"
},
  "geometry": {"coordinates":[-87.11333,37.74824],"type":"Point"}
}