{
  "type": "Feature",
  "properties": {
    "iso:country":"US",
    "sg:address":"3145 Old Frankfort Pike",
    "sg:city":"Owenton",
    "sg:classifiers":[
        {
            "category":"Freight",
            "type":"Transportation"
        }
    ],
    "sg:phone":"+1 502 484 2287",
    "sg:postcode":"40359",
    "sg:province":"KY",
    "sg:tags":[
        "trucking"
    ],
    "wof:name":"B T Specialized Transport",
    "wof:placetype":"venue"
},
  "geometry": {"coordinates":[-84.86453899999999,38.402309],"type":"Point"}
}