{
  "type": "Feature",
  "properties": {
    "iso:country":"US",
    "sg:address":"131 Nahm St",
    "sg:city":"Paducah",
    "sg:classifiers":[
        {
            "category":"Education",
            "subcategory":"Special Training",
            "type":"Public Place"
        }
    ],
    "sg:phone":"+1 270 443 3733",
    "sg:postcode":"42001",
    "sg:province":"KY",
    "sg:tags":[
        "instruction",
        "driving"
    ],
    "wof:name":"Fred Myers School Of Driving",
    "wof:placetype":"venue"
},
  "geometry": {"coordinates":[-88.63567999999999,37.071128],"type":"Point"}
}