{
  "type": "Feature",
  "properties": {
    "iso:country":"US",
    "sg:address":"304 Kings Daughters Dr",
    "sg:city":"Frankfort",
    "sg:classifiers":[
        {
            "category":"Social Services",
            "type":"Services"
        }
    ],
    "sg:phone":"+1 502 223 0640",
    "sg:postcode":"40601",
    "sg:province":"KY",
    "sg:tags":[
        "counselor",
        "marriage",
        "family"
    ],
    "wof:name":"Mary A Whitehead PHD",
    "wof:placetype":"venue"
},
  "geometry": {"coordinates":[-84.902119,38.166271],"type":"Point"}
}