{
  "type": "Feature",
  "properties": {
    "addr:full":"205 State St Elizabethtown KY 42701",
    "addr:housenumber":"205",
    "addr:postcode":"42701",
    "addr:street":"State St",
    "iso:country":"US",
    "sg:address":"205 State St",
    "sg:city":"Elizabethtown",
    "sg:classifiers":[
        {
            "category":"Building & Trades",
            "subcategory":"Landscaping Services",
            "type":"Services"
        }
    ],
    "sg:phone":"+1 502 962 7704",
    "sg:postcode":"42701",
    "sg:province":"KY",
    "wof:name":"Development Brook LLC Poplar",
    "wof:placetype":"venue"
},
  "geometry": {"coordinates":[-85.88146500000001,37.714715],"type":"Point"}
}