{
  "type": "Feature",
  "properties": {
    "iso:country":"US",
    "sg:address":"2040 Frankfort Ave",
    "sg:city":"Louisville",
    "sg:classifiers":[
        {
            "category":"Shopping",
            "subcategory":"Florist",
            "type":"Retail Goods"
        }
    ],
    "sg:phone":"+1 502 894 3266",
    "sg:postcode":"40206",
    "sg:province":"KY",
    "sg:website":"http://www.theflowershoppeoflouisville.com",
    "wof:name":"Flower Shoppe Of Louisville",
    "wof:placetype":"venue"
},
  "geometry": {"coordinates":[-85.708893,38.25431],"type":"Point"}
}