{
  "type": "Feature",
  "properties": {
    "addr:full":"595 N Hubbards Ln St Matthews KY 40207",
    "addr:housenumber":"595",
    "addr:postcode":"40207",
    "addr:street":"N Hubbards Ln",
    "iso:country":"US",
    "sg:address":"595 N Hubbards Ln",
    "sg:city":"St Matthews",
    "sg:classifiers":[
        {
            "category":"Government",
            "subcategory":"Office",
            "type":"Public Place"
        }
    ],
    "sg:phone":"+1 502 893 5126",
    "sg:postcode":"40207",
    "sg:province":"KY",
    "sg:website":"www.loukymetro.org",
    "wof:name":"Jefferson County Road Mntnc",
    "wof:placetype":"venue"
},
  "geometry": {"coordinates":[-85.64851899999999,38.268699],"type":"Point"}
}