{
  "type": "Feature",
  "properties": {
    "iso:country":"US",
    "sg:address":"6169 Old Hwy 54",
    "sg:city":"Philpot",
    "sg:classifiers":[
        {
            "category":"Autos & Motor Vehicles",
            "subcategory":"Automobile Sales",
            "type":"Retail Goods"
        }
    ],
    "sg:phone":"+1 270 729 9999",
    "sg:postcode":"42366",
    "sg:province":"KY",
    "sg:tags":[
        "used"
    ],
    "wof:name":"Muscle Motors",
    "wof:placetype":"venue"
},
  "geometry": {"coordinates":[-86.98607800000001,37.732565],"type":"Point"}
}