{
  "type": "Feature",
  "properties": {
    "iso:country":"US",
    "sg:address":"1335 Main St",
    "sg:city":"Paris",
    "sg:classifiers":[
        {
            "category":"Personal",
            "subcategory":"Barber",
            "type":"Services"
        }
    ],
    "sg:phone":"+1 859 987 8040",
    "sg:postcode":"40361",
    "sg:province":"KY",
    "wof:name":"Combs Barber Shop",
    "wof:placetype":"venue"
},
  "geometry": {"coordinates":[-84.255852,38.20594],"type":"Point"}
}