{
  "type": "Feature",
  "properties": {
    "iso:country":"US",
    "sg:address":"655 Knox Blvd",
    "sg:city":"Radcliff",
    "sg:classifiers":[
        {
            "category":"Recreation",
            "type":"Entertainment"
        }
    ],
    "sg:phone":"+1 270 352 2221",
    "sg:postcode":"40160",
    "sg:province":"KY",
    "sg:tags":[
        "martial",
        "arts",
        "instruction"
    ],
    "wof:name":"Chang-Hun Taekwon-Do Institute",
    "wof:placetype":"venue"
},
  "geometry": {"coordinates":[-85.951138,37.861047],"type":"Point"}
}