{
  "type": "Feature",
  "properties": {
    "iso:country":"US",
    "sg:address":"520 Highland Ave",
    "sg:city":"Carrollton",
    "sg:classifiers":[
        {
            "category":"Government",
            "subcategory":"Post Office",
            "type":"Public Place"
        }
    ],
    "sg:phone":"+1 502 732 5316",
    "sg:postcode":"41008",
    "sg:province":"KY",
    "wof:name":"US Post Office",
    "wof:placetype":"venue"
},
  "geometry": {"coordinates":[-85.17815400000001,38.681128],"type":"Point"}
}