{
  "type": "Feature",
  "properties": {
    "iso:country":"US",
    "sg:address":"1048 Riverview Farm Pl",
    "sg:city":"Covington",
    "sg:classifiers":[
        {
            "category":"Professional",
            "subcategory":"Management & Consulting",
            "type":"Services"
        }
    ],
    "sg:phone":"+1 859 344 9600",
    "sg:postcode":"41017",
    "sg:province":"KY",
    "wof:name":"Bell Marketing Resources LLC",
    "wof:placetype":"venue"
},
  "geometry": {"coordinates":[-84.579606,39.073954],"type":"Point"}
}