{
  "type": "Feature",
  "properties": {
    "iso:country":"US",
    "sg:address":"300 Sportsman Lake Rd",
    "sg:city":"Elizabethtown",
    "sg:classifiers":[
        {
            "category":"Home & Garden",
            "subcategory":"Building Materials",
            "type":"Retail Goods"
        }
    ],
    "sg:phone":"+1 270 358 4274",
    "sg:postcode":"42701",
    "sg:province":"KY",
    "sg:tags":[
        "mixed",
        "concrete"
    ],
    "wof:name":"Lincoln Trail Concrete",
    "wof:placetype":"venue"
},
  "geometry": {"coordinates":[-85.840521,37.663679],"type":"Point"}
}