{
  "type": "Feature",
  "properties": {
    "iso:country":"US",
    "sg:address":"2307 Old Main St",
    "sg:city":"Maysville",
    "sg:classifiers":[
        {
            "category":"Personal",
            "subcategory":"Beauty Salon",
            "type":"Services"
        }
    ],
    "sg:phone":"+1 606 759 9100",
    "sg:postcode":"41056",
    "sg:province":"KY",
    "wof:name":"Reflections On Main",
    "wof:placetype":"venue"
},
  "geometry": {"coordinates":[-83.81068399999999,38.603373],"type":"Point"}
}