{
  "type": "Feature",
  "properties": {
    "iso:country":"US",
    "sg:address":"58 S Franklin St",
    "sg:city":"Madisonville",
    "sg:classifiers":[
        {
            "category":"Professional",
            "subcategory":"Accounting & Tax Preparation",
            "type":"Services"
        }
    ],
    "sg:phone":"+1 270 821 4824",
    "sg:postcode":"42431",
    "sg:province":"KY",
    "sg:tags":[
        "accountant"
    ],
    "wof:name":"Alexander Toney & Co",
    "wof:placetype":"venue"
},
  "geometry": {"coordinates":[-87.497134,37.326831],"type":"Point"}
}