{
  "type": "Feature",
  "properties": {
    "iso:country":"US",
    "sg:address":"1416 Memphis Junction Rd",
    "sg:city":"Bowling Green",
    "sg:classifiers":[
        {
            "category":"Home & Garden",
            "subcategory":"Furniture",
            "type":"Retail Goods"
        }
    ],
    "sg:phone":"+1 270 781 2211",
    "sg:postcode":"42101",
    "sg:province":"KY",
    "sg:tags":[
        "cabinet"
    ],
    "wof:name":"Whalen's Cabinets & Remodeling",
    "wof:placetype":"venue"
},
  "geometry": {"coordinates":[-86.489063,36.942093],"type":"Point"}
}