{
  "type": "Feature",
  "properties": {
    "iso:country":"US",
    "sg:address":"2405 Lebanon Rd",
    "sg:city":"Danville",
    "sg:classifiers":[
        {
            "category":"Autos & Motor Vehicles",
            "subcategory":"Automobile Sales",
            "type":"Retail Goods"
        }
    ],
    "sg:phone":"+1 859 236 4558",
    "sg:postcode":"40422",
    "sg:province":"KY",
    "sg:tags":[
        "car",
        "dealer"
    ],
    "wof:name":"G O Chevrolet",
    "wof:placetype":"venue"
},
  "geometry": {"coordinates":[-84.805723,37.627167],"type":"Point"}
}