{
  "type": "Feature",
  "properties": {
    "addr:full":"827 Joe Clifton Dr Paducah KY 42001",
    "addr:housenumber":"827",
    "addr:postcode":"42001",
    "addr:street":"Joe Clifton Dr",
    "iso:country":"US",
    "sg:address":"827 Joe Clifton Dr",
    "sg:city":"Paducah",
    "sg:classifiers":[
        {
            "category":"Organizations",
            "subcategory":"Non-profit Organization",
            "type":"Services"
        }
    ],
    "sg:phone":"+1 270 443 4838",
    "sg:postcode":"42001",
    "sg:province":"KY",
    "wof:name":"Family Service Society",
    "wof:placetype":"venue"
},
  "geometry": {"coordinates":[-88.636788,37.082178],"type":"Point"}
}