{
  "type": "Feature",
  "properties": {
    "iso:country":"US",
    "sg:address":"501 Main St",
    "sg:city":"Greenup",
    "sg:classifiers":[
        {
            "category":"Health Services",
            "subcategory":"Doctor",
            "type":"Services"
        }
    ],
    "sg:phone":"+1 606 473 3932",
    "sg:postcode":"41144",
    "sg:province":"KY",
    "sg:tags":[
        "medical"
    ],
    "wof:name":"Ann Alvarez Margarette MD",
    "wof:placetype":"venue"
},
  "geometry": {"coordinates":[-82.83577,38.577264],"type":"Point"}
}