{
  "type": "Feature",
  "properties": {
    "iso:country":"US",
    "sg:address":"1920 Dawson Springs Rd",
    "sg:city":"Hopkinsville",
    "sg:classifiers":[
        {
            "category":"Manufacturing",
            "subcategory":"Tools & Machinery",
            "type":"Manufacturing & Wholesale Goods"
        }
    ],
    "sg:phone":"+1 270 881 1016",
    "sg:postcode":"42240",
    "sg:province":"KY",
    "sg:tags":[
        "machine",
        "shop"
    ],
    "wof:name":"Welsh Machinery Inc",
    "wof:placetype":"venue"
},
  "geometry": {"coordinates":[-87.510929,36.883721],"type":"Point"}
}