{
  "type": "Feature",
  "properties": {
    "iso:country":"US",
    "sg:address":"515 Salem Dr",
    "sg:city":"Owensboro",
    "sg:classifiers":[
        {
            "category":"Freight",
            "type":"Transportation"
        }
    ],
    "sg:phone":"+1 270 926 1105",
    "sg:postcode":"42303",
    "sg:province":"KY",
    "sg:tags":[
        "commercial",
        "storage"
    ],
    "wof:name":"AAA Rent-A-Space",
    "wof:placetype":"venue"
},
  "geometry": {"coordinates":[-87.118329,37.72687],"type":"Point"}
}