{
  "type": "Feature",
  "properties": {
    "addr:full":"108 E 1st St Smiths Grove KY 42171",
    "addr:housenumber":"108",
    "addr:postcode":"42171",
    "addr:street":"E 1St St",
    "iso:country":"US",
    "sg:address":"108 E 1st St",
    "sg:city":"Smiths Grove",
    "sg:classifiers":[
        {
            "category":"Shopping",
            "subcategory":"Used Merchandise",
            "type":"Retail Goods"
        }
    ],
    "sg:phone":"+1 270 563 9313",
    "sg:postcode":"42171",
    "sg:province":"KY",
    "sg:tags":[
        "antique"
    ],
    "wof:name":"Old Bank Antiques",
    "wof:placetype":"venue"
},
  "geometry": {"coordinates":[-86.207629,37.052647],"type":"Point"}
}