{
  "type": "Feature",
  "properties": {
    "iso:country":"US",
    "sg:address":"2320 Broadway St",
    "sg:city":"Paducah",
    "sg:classifiers":[
        {
            "category":"Health Services",
            "subcategory":"Clinic",
            "type":"Services"
        }
    ],
    "sg:phone":"+1 270 443 0658",
    "sg:postcode":"42001",
    "sg:province":"KY",
    "sg:tags":[
        "banks",
        "tissue",
        "organ"
    ],
    "wof:name":"Ky Organ Donor Affiliates",
    "wof:placetype":"venue"
},
  "geometry": {"coordinates":[-88.624145,37.076085],"type":"Point"}
}