{
  "type": "Feature",
  "properties": {
    "iso:country":"US",
    "sg:address":"501 Crabtree Ave",
    "sg:city":"Owensboro",
    "sg:classifiers":[
        {
            "category":"Shopping",
            "subcategory":"Used Merchandise",
            "type":"Retail Goods"
        }
    ],
    "sg:phone":"+1 270 685 4573",
    "sg:postcode":"42301",
    "sg:province":"KY",
    "sg:tags":[
        "pawnbroker"
    ],
    "wof:name":"Outer Bank Pawn Inc",
    "wof:placetype":"venue"
},
  "geometry": {"coordinates":[-87.13433499999999,37.769361],"type":"Point"}
}