{
  "type": "Feature",
  "properties": {
    "addr:full":"71 Vest Talcum Rd Vest KY 41772",
    "addr:housenumber":"71",
    "addr:postcode":"41772",
    "addr:street":"Vest Talcum Rd",
    "iso:country":"US",
    "sg:address":"71 Vest Talcum Rd",
    "sg:city":"Vest",
    "sg:classifiers":[
        {
            "category":"Shopping",
            "type":"Retail Goods"
        }
    ],
    "sg:phone":"+1 606 785 3848",
    "sg:postcode":"41772",
    "sg:province":"KY",
    "sg:tags":[
        "merchandise"
    ],
    "wof:name":"Art & Framing Shop",
    "wof:placetype":"venue"
},
  "geometry": {"coordinates":[-83.015146,37.400229],"type":"Point"}
}