{
  "type": "Feature",
  "properties": {
    "iso:country":"US",
    "sg:address":"34 N Fort Thomas Ave",
    "sg:city":"Fort Thomas",
    "sg:classifiers":[
        {
            "category":"Banks & Credit Unions",
            "subcategory":"Bank",
            "type":"Services"
        },
        {
            "category":"Banks & Credit Unions",
            "subcategory":"Financial Services",
            "type":"Services"
        }
    ],
    "sg:phone":"+1 859 442 7600",
    "sg:postcode":"41075",
    "sg:province":"KY",
    "sg:tags":[
        "broker",
        "mortgage"
    ],
    "wof:name":"Citizens Bank of Northern Ky",
    "wof:placetype":"venue"
},
  "geometry": {"coordinates":[-84.448402,39.078999],"type":"Point"}
}