{
  "type": "Feature",
  "properties": {
    "addr:full":"1504 S Green St Henderson KY 42420",
    "addr:housenumber":"1504",
    "addr:postcode":"42420",
    "addr:street":"S Green St",
    "iso:country":"US",
    "sg:address":"1504 S Green St",
    "sg:city":"Henderson",
    "sg:classifiers":[
        {
            "category":"Shopping",
            "type":"Retail Goods"
        }
    ],
    "sg:phone":"+1 270 826 4061",
    "sg:postcode":"42420",
    "sg:province":"KY",
    "sg:tags":[
        "pet",
        "shop"
    ],
    "wof:name":"Henderson Pets",
    "wof:placetype":"venue"
},
  "geometry": {"coordinates":[-87.606617,37.821046],"type":"Point"}
}