{
  "type": "Feature",
  "properties": {
    "iso:country":"US",
    "sg:address":"609 Spring St",
    "sg:city":"Elsmere",
    "sg:classifiers":[
        {
            "category":"Manufacturing",
            "subcategory":"Printing",
            "type":"Manufacturing & Wholesale Goods"
        }
    ],
    "sg:phone":"+1 859 342 5300",
    "sg:postcode":"41018",
    "sg:province":"KY",
    "sg:tags":[
        "screen"
    ],
    "wof:name":"Identity Sportswear",
    "wof:placetype":"venue"
},
  "geometry": {"coordinates":[-84.603908,39.006354],"type":"Point"}
}