{
  "type": "Feature",
  "properties": {
    "addr:full":"404 Shadowood Ct Radcliff KY 40160",
    "addr:housenumber":"404",
    "addr:postcode":"40160",
    "addr:street":"Shadowood Ct",
    "iso:country":"US",
    "sg:address":"404 Shadowood Ct",
    "sg:city":"Radcliff",
    "sg:classifiers":[
        {
            "category":"Building & Trades",
            "subcategory":"Landscaping Services",
            "type":"Services"
        }
    ],
    "sg:phone":"+1 270 877 5886",
    "sg:postcode":"40160",
    "sg:province":"KY",
    "sg:tags":[
        "landscape",
        "contractor"
    ],
    "wof:name":"Whispering Hills Landscaping",
    "wof:placetype":"venue"
},
  "geometry": {"coordinates":[-85.947627,37.777986],"type":"Point"}
}