{
  "type": "Feature",
  "properties": {
    "addr:full":"1 S Main St Madisonville KY 42431",
    "addr:housenumber":"1",
    "addr:postcode":"42431",
    "addr:street":"S Main St",
    "iso:country":"US",
    "sg:address":"1 S Main St",
    "sg:city":"Madisonville",
    "sg:classifiers":[
        {
            "category":"Personal",
            "subcategory":"Barber",
            "type":"Services"
        }
    ],
    "sg:phone":"+1 270 821 1017",
    "sg:postcode":"42431",
    "sg:province":"KY",
    "sg:tags":[
        "shop"
    ],
    "wof:name":"Razors Edge Barber Shop",
    "wof:placetype":"venue"
},
  "geometry": {"coordinates":[-87.49896,37.327549],"type":"Point"}
}