{
  "type": "Feature",
  "properties": {
    "iso:country":"US",
    "sg:address":"1351 Catalpa St",
    "sg:city":"Louisville",
    "sg:classifiers":[
        {
            "category":"Organizations",
            "subcategory":"Religious Organization",
            "type":"Services"
        }
    ],
    "sg:phone":"+1 502 774 2734",
    "sg:postcode":"40211",
    "sg:province":"KY",
    "sg:tags":[
        "nursery",
        "center",
        "day",
        "care"
    ],
    "sg:website":"www.bfcenter.org",
    "wof:name":"Baptist Fellowship Center",
    "wof:placetype":"venue"
},
  "geometry": {"coordinates":[-85.80181899999999,38.235498],"type":"Point"}
}