{
  "type": "Feature",
  "properties": {
    "iso:country":"US",
    "sg:address":"617 Edgewood Dr",
    "sg:city":"Nicholasville",
    "sg:classifiers":[
        {
            "category":"Health Services",
            "subcategory":"Doctor",
            "type":"Services"
        }
    ],
    "sg:phone":"+1 859 887 2297",
    "sg:postcode":"40356",
    "sg:province":"KY",
    "sg:tags":[
        "dentist"
    ],
    "wof:name":"Lisa A Kochis DDS",
    "wof:placetype":"venue"
},
  "geometry": {"coordinates":[-84.59633599999999,37.871921],"type":"Point"}
}