{
  "type": "Feature",
  "properties": {
    "iso:country":"US",
    "sg:address":"204 Greensburg St",
    "sg:city":"Columbia",
    "sg:classifiers":[
        {
            "category":"Government",
            "subcategory":"Office",
            "type":"Public Place"
        }
    ],
    "sg:phone":"+1 270 384 6464",
    "sg:postcode":"42728",
    "sg:province":"KY",
    "wof:name":"Adair County Emergency Control",
    "wof:placetype":"venue"
},
  "geometry": {"coordinates":[-85.30725,37.104115],"type":"Point"}
}