{
  "type": "Feature",
  "properties": {
    "addr:full":"114 Bonnie Ln Louisville KY 40218",
    "addr:housenumber":"114",
    "addr:postcode":"40218",
    "addr:street":"Bonnie Ln",
    "iso:country":"US",
    "sg:address":"114 Bonnie Ln",
    "sg:city":"Louisville",
    "sg:classifiers":[
        {
            "category":"Retail",
            "subcategory":"Car Wash",
            "type":"Services"
        }
    ],
    "sg:phone":"+1 502 495 0016",
    "sg:postcode":"40218",
    "sg:province":"KY",
    "sg:tags":[
        "carwash"
    ],
    "wof:name":"Superior Pressure Wash Inc",
    "wof:placetype":"venue"
},
  "geometry": {"coordinates":[-85.63790899999999,38.189714],"type":"Point"}
}