{
  "type": "Feature",
  "properties": {
    "iso:country":"US",
    "sg:address":"3160 State Hwy 54",
    "sg:city":"Owensboro",
    "sg:classifiers":[
        {
            "category":"Banks & Credit Unions",
            "subcategory":"Bank",
            "type":"Services"
        }
    ],
    "sg:phone":"+1 270 926 5830",
    "sg:postcode":"42303",
    "sg:province":"KY",
    "wof:name":"Bank One",
    "wof:placetype":"venue"
},
  "geometry": {"coordinates":[-87.061556,37.754115],"type":"Point"}
}