{
  "type": "Feature",
  "properties": {
    "iso:country":"US",
    "sg:address":"43 Northside Ct",
    "sg:city":"Morganfield",
    "sg:classifiers":[
        {
            "category":"Real Estate",
            "subcategory":"Real Estate Operator",
            "type":"Services"
        }
    ],
    "sg:phone":"+1 270 389 0157",
    "sg:postcode":"42437",
    "sg:province":"KY",
    "sg:tags":[
        "apartment"
    ],
    "wof:name":"Northside Apartments",
    "wof:placetype":"venue"
},
  "geometry": {"coordinates":[-87.917005,37.695943],"type":"Point"}
}