{
  "type": "Feature",
  "properties": {
    "addr:full":"6093 Taylor Mill Rd Latonia KY 41015",
    "addr:housenumber":"6093",
    "addr:postcode":"41015",
    "addr:street":"Taylor Mill Rd",
    "iso:country":"US",
    "sg:address":"6093 Taylor Mill Rd",
    "sg:city":"Latonia",
    "sg:classifiers":[
        {
            "category":"Organizations",
            "subcategory":"Religious Organization",
            "type":"Services"
        }
    ],
    "sg:phone":"+1 859 356 4880",
    "sg:postcode":"41015",
    "sg:province":"KY",
    "wof:name":"Bible Baptist Church",
    "wof:placetype":"venue"
},
  "geometry": {"coordinates":[-84.50159600000001,38.979755],"type":"Point"}
}