{
  "type": "Feature",
  "properties": {
    "addr:full":"2554 Carolina Ave Louisville KY 40205",
    "addr:housenumber":"2554",
    "addr:postcode":"40205",
    "addr:street":"Carolina Ave",
    "iso:country":"US",
    "sg:address":"2554 Carolina Ave",
    "sg:city":"Louisville",
    "sg:classifiers":[
        {
            "category":"Building & Trades",
            "subcategory":"Construction",
            "type":"Services"
        }
    ],
    "sg:phone":"+1 502 459 0410",
    "sg:postcode":"40205",
    "sg:province":"KY",
    "sg:tags":[
        "hanging",
        "contractor"
    ],
    "wof:name":"Thomas P Painting LLC",
    "wof:placetype":"venue"
},
  "geometry": {"coordinates":[-85.679793,38.223928],"type":"Point"}
}