{
  "type": "Feature",
  "properties": {
    "iso:country":"US",
    "sg:address":"130 E Washington St",
    "sg:city":"Hartford",
    "sg:classifiers":[
        {
            "category":"Utilities",
            "subcategory":"Water",
            "type":"Services"
        }
    ],
    "sg:phone":"+1 270 298 7704",
    "sg:postcode":"42347",
    "sg:province":"KY",
    "sg:tags":[
        "company",
        "sewage"
    ],
    "wof:name":"Ohio County Water District",
    "wof:placetype":"venue"
},
  "geometry": {"coordinates":[-86.90693,37.451047],"type":"Point"}
}