{
  "type": "Feature",
  "properties": {
    "iso:country":"US",
    "sg:address":"260 Stockton Dr",
    "sg:city":"Campbellsville",
    "sg:classifiers":[
        {
            "category":"Professional",
            "type":"Services"
        }
    ],
    "sg:phone":"+1 270 469 9600",
    "sg:postcode":"42718",
    "sg:province":"KY",
    "sg:tags":[
        "establishment"
    ],
    "wof:name":"Kidwell Boat",
    "wof:placetype":"venue"
},
  "geometry": {"coordinates":[-85.364876,37.293877],"type":"Point"}
}