{
  "type": "Feature",
  "properties": {
    "iso:country":"US",
    "sg:address":"223 River Dr",
    "sg:city":"Irvine",
    "sg:classifiers":[
        {
            "category":"Health Services",
            "subcategory":"Doctor",
            "type":"Services"
        }
    ],
    "sg:phone":"+1 606 726 9117",
    "sg:postcode":"40336",
    "sg:province":"KY",
    "sg:tags":[
        "clinic"
    ],
    "wof:name":"Children's Clinic Annex",
    "wof:placetype":"venue"
},
  "geometry": {"coordinates":[-83.96785199999999,37.695128],"type":"Point"}
}