{
  "type": "Feature",
  "properties": {
    "addr:full":"144 Airport Rd Campbellsville KY 42718",
    "addr:housenumber":"144",
    "addr:postcode":"42718",
    "addr:street":"Airport Rd",
    "iso:country":"US",
    "sg:address":"144 Airport Rd",
    "sg:city":"Campbellsville",
    "sg:classifiers":[
        {
            "category":"Home & Garden",
            "subcategory":"Garden Supply",
            "type":"Retail Goods"
        }
    ],
    "sg:phone":"+1 270 465 8174",
    "sg:postcode":"42718",
    "sg:province":"KY",
    "sg:tags":[
        "fertilizer"
    ],
    "sg:website":"www.cvilleindustries.com",
    "wof:name":"Campbellsville Crop Svc",
    "wof:placetype":"venue"
},
  "geometry": {"coordinates":[-85.320926,37.356162],"type":"Point"}
}