{
  "type": "Feature",
  "properties": {
    "iso:country":"US",
    "sg:address":"136 Chestnut St",
    "sg:city":"Vanceburg",
    "sg:classifiers":[
        {
            "category":"Professional",
            "subcategory":"Business Services",
            "type":"Services"
        }
    ],
    "sg:phone":"+1 606 796 6557",
    "sg:postcode":"41179",
    "sg:province":"KY",
    "wof:name":"Cassidy Gentry Ltd Co",
    "wof:placetype":"venue"
},
  "geometry": {"coordinates":[-83.325577,38.577048],"type":"Point"}
}