{
  "type": "Feature",
  "properties": {
    "addr:full":"1840 Bryan Station Rd Lexington KY 40505",
    "addr:housenumber":"1840",
    "addr:postcode":"40505",
    "addr:street":"Bryan Station Rd",
    "iso:country":"US",
    "sg:address":"1840 Bryan Station Rd",
    "sg:city":"Lexington",
    "sg:classifiers":[
        {
            "category":"Health Services",
            "subcategory":"Hospital",
            "type":"Services"
        }
    ],
    "sg:phone":"+1 859 299 3161",
    "sg:postcode":"40505",
    "sg:province":"KY",
    "sg:tags":[
        "surgery"
    ],
    "wof:name":"Abu",
    "wof:placetype":"venue"
},
  "geometry": {"coordinates":[-84.452443,38.064093],"type":"Point"}
}