{
  "type": "Feature",
  "properties": {
    "iso:country":"US",
    "sg:address":"203 Snowshoe Dr",
    "sg:city":"Newport",
    "sg:classifiers":[
        {
            "category":"Building & Trades",
            "subcategory":"Construction",
            "type":"Services"
        }
    ],
    "sg:phone":"+1 859 781 0789",
    "sg:postcode":"41071",
    "sg:province":"KY",
    "sg:tags":[
        "drywall",
        "contractor"
    ],
    "wof:name":"T & M Complete Drywall",
    "wof:placetype":"venue"
},
  "geometry": {"coordinates":[-84.480915,39.070502],"type":"Point"}
}