{
  "type": "Feature",
  "properties": {
    "iso:country":"US",
    "sg:address":"1810 Outer Loop",
    "sg:city":"Louisville",
    "sg:classifiers":[
        {
            "category":"Building & Trades",
            "subcategory":"Plumbing",
            "type":"Services"
        },
        {
            "category":"Wholesale",
            "subcategory":"Machinery & Supplies",
            "type":"Manufacturing & Wholesale Goods"
        },
        {
            "category":"Restaurant",
            "type":"Food & Drink"
        },
        {
            "category":"Building & Trades",
            "subcategory":"Construction",
            "type":"Services"
        },
        {
            "category":"Retail",
            "subcategory":"Repair Shop",
            "type":"Services"
        }
    ],
    "sg:phone":"+1 502 368 7678",
    "sg:postcode":"40219",
    "sg:province":"KY",
    "sg:tags":[
        "plumber",
        "equipment-commercial",
        "equipment",
        "contractor",
        "supplies-refrigeration",
        "industrial",
        "refrigeration",
        "boilers-repair",
        "clean",
        "mechanical",
        "freezers-repair",
        "refrigerator",
        "contractors-commercial"
    ],
    "sg:website":"http://www.schardein.com",
    "wof:name":"Schardein Mechanical Contractors, Inc.",
    "wof:placetype":"venue"
},
  "geometry": {"coordinates":[-85.73152,38.13127],"type":"Point"}
}