{
  "type": "Feature",
  "properties": {
    "addr:full":"4101 Tates Creek Centre Dr Lexington KY 40517",
    "addr:housenumber":"4101",
    "addr:postcode":"40517",
    "addr:street":"Tates Creek Centre Dr",
    "iso:country":"US",
    "sg:address":"4101 Tates Creek Centre Dr",
    "sg:city":"Lexington",
    "sg:classifiers":[
        {
            "category":"Health Services",
            "subcategory":"Health Practitioner",
            "type":"Services"
        }
    ],
    "sg:phone":"+1 859 252 8222",
    "sg:postcode":"40517",
    "sg:province":"KY",
    "wof:name":"Any Where Audio",
    "wof:placetype":"venue"
},
  "geometry": {"coordinates":[-84.497559,37.969961],"type":"Point"}
}