{
  "type": "Feature",
  "properties": {
    "iso:country":"US",
    "sg:address":"519 Barret Ave",
    "sg:city":"Louisville",
    "sg:classifiers":[
        {
            "category":"Health Services",
            "subcategory":"Health Practitioner",
            "type":"Services"
        }
    ],
    "sg:phone":"+1 502 581 1725",
    "sg:postcode":"40204",
    "sg:province":"KY",
    "sg:tags":[
        "nurse",
        "registry"
    ],
    "sg:website":"www.amstemporaries.com",
    "wof:name":"AMS Temporaries Inc",
    "wof:placetype":"venue"
},
  "geometry": {"coordinates":[-85.73081000000001,38.247176],"type":"Point"}
}