{
  "type": "Feature",
  "properties": {
    "iso:country":"US",
    "sg:address":"319 W 10th St",
    "sg:city":"Owensboro",
    "sg:classifiers":[
        {
            "category":"Organizations",
            "subcategory":"Non-profit Organization",
            "type":"Services"
        }
    ],
    "sg:phone":"+1 270 926 6110",
    "sg:postcode":"42301",
    "sg:province":"KY",
    "sg:tags":[
        "human"
    ],
    "wof:name":"Habitat For Humanity",
    "wof:placetype":"venue"
},
  "geometry": {"coordinates":[-87.113795,37.766053],"type":"Point"}
}