{
  "type": "Feature",
  "properties": {
    "iso:country":"US",
    "sg:address":"1786 Hickory Corner Rd",
    "sg:city":"Pleasureville",
    "sg:classifiers":[
        {
            "category":"Farming",
            "subcategory":"Farm",
            "type":"Manufacturing & Wholesale Goods"
        }
    ],
    "sg:phone":"+1 502 845 4018",
    "sg:postcode":"40057",
    "sg:province":"KY",
    "sg:tags":[
        "crop",
        "general"
    ],
    "wof:name":"Gayle Douglas",
    "wof:placetype":"venue"
},
  "geometry": {"coordinates":[-85.02993499999999,38.470638],"type":"Point"}
}