{
  "type": "Feature",
  "properties": {
    "addr:full":"7964 Kentucky Dr Florence KY 41042",
    "addr:housenumber":"7964",
    "addr:postcode":"41042",
    "addr:street":"Kentucky Dr",
    "iso:country":"US",
    "sg:address":"7964 Kentucky Dr",
    "sg:city":"Florence",
    "sg:classifiers":[
        {
            "category":"Professional",
            "subcategory":"Advertising",
            "type":"Services"
        }
    ],
    "sg:phone":"+1 859 647 9910",
    "sg:postcode":"41042",
    "sg:province":"KY",
    "sg:tags":[
        "designer",
        "display",
        "producer"
    ],
    "sg:website":"www.consortium-companies.com",
    "wof:name":"Consortium Co Inc",
    "wof:placetype":"venue"
},
  "geometry": {"coordinates":[-84.626311,38.979869],"type":"Point"}
}