{
  "type": "Feature",
  "properties": {
    "addr:full":"4744 Bardstown Rd Louisville KY 40218",
    "addr:housenumber":"4744",
    "addr:postcode":"40218",
    "addr:street":"Bardstown Rd",
    "iso:country":"US",
    "sg:address":"4744 Bardstown Rd",
    "sg:city":"Louisville",
    "sg:classifiers":[
        {
            "category":"Shopping",
            "subcategory":"Department Store",
            "type":"Retail Goods"
        }
    ],
    "sg:phone":"+1 502 499 6008",
    "sg:postcode":"40218",
    "sg:province":"KY",
    "sg:tags":[
        "shop"
    ],
    "wof:name":"Dollar General",
    "wof:placetype":"venue"
},
  "geometry": {"coordinates":[-85.62478900000001,38.179993],"type":"Point"}
}