{
  "type": "Feature",
  "properties": {
    "addr:full":"5215 County Line Rd Kevil KY 42053",
    "addr:housenumber":"5215",
    "addr:postcode":"42053",
    "addr:street":"County Line Rd",
    "iso:country":"US",
    "sg:address":"5215 County Line Rd",
    "sg:city":"Kevil",
    "sg:phone":"+1 270 462 2669",
    "sg:postcode":"42053",
    "sg:province":"KY",
    "sg:tags":[
        "farm",
        "tobacco"
    ],
    "wof:name":"Roy Davis Farms",
    "wof:placetype":"venue"
},
  "geometry": {"coordinates":[-88.868737,37.063522],"type":"Point"}
}