{
  "type": "Feature",
  "properties": {
    "iso:country":"US",
    "sg:address":"5198 Frankfort Rd",
    "sg:city":"Shelbyville",
    "sg:classifiers":[
        {
            "category":"Manufacturing",
            "subcategory":"Glass & Minerals",
            "type":"Manufacturing & Wholesale Goods"
        }
    ],
    "sg:phone":"+1 502 633 7449",
    "sg:postcode":"40065",
    "sg:province":"KY",
    "sg:tags":[
        "concrete",
        "product",
        "mfg"
    ],
    "wof:name":"Barn Market",
    "wof:placetype":"venue"
},
  "geometry": {"coordinates":[-85.12237399999999,38.196136],"type":"Point"}
}