{
  "type": "Feature",
  "properties": {
    "addr:full":"1009 Twilight Trl Frankfort KY 40601",
    "addr:housenumber":"1009",
    "addr:postcode":"40601",
    "addr:street":"Twilight Trl;Ky",
    "iso:country":"US",
    "sg:address":"1009 Twilight Trl",
    "sg:city":"Frankfort",
    "sg:classifiers":[
        {
            "category":"Utilities",
            "subcategory":"Telephone",
            "type":"Services"
        }
    ],
    "sg:phone":"+1 502 226 4737",
    "sg:postcode":"40601",
    "sg:province":"KY",
    "sg:tags":[
        "company"
    ],
    "wof:name":"Qwest Communications",
    "wof:placetype":"venue"
},
  "geometry": {"coordinates":[-84.895118,38.155353],"type":"Point"}
}