{
  "type": "Feature",
  "properties": {
    "iso:country":"US",
    "sg:address":"207 Main St",
    "sg:city":"Corydon",
    "sg:classifiers":[
        {
            "category":"Shopping",
            "subcategory":"Florist",
            "type":"Retail Goods"
        }
    ],
    "sg:phone":"+1 270 533 6788",
    "sg:postcode":"42406",
    "sg:province":"KY",
    "wof:name":"T-P Flower & Gift Shop",
    "wof:placetype":"venue"
},
  "geometry": {"coordinates":[-87.70319499999999,37.744554],"type":"Point"}
}