{
  "type": "Feature",
  "properties": {
    "iso:country":"US",
    "sg:address":"21 Russell Plaza Dr",
    "sg:city":"Ashland",
    "sg:classifiers":[
        {
            "category":"Restaurant",
            "type":"Food & Drink"
        }
    ],
    "sg:phone":"+1 606 324 6441",
    "sg:postcode":"41101",
    "sg:province":"KY",
    "wof:name":"Golden Corral Buffet & Grill",
    "wof:placetype":"venue"
},
  "geometry": {"coordinates":[-82.704452,38.510435],"type":"Point"}
}