{
  "type": "Feature",
  "properties": {
    "addr:full":"6108 Preston Hwy Louisville KY 40219",
    "addr:housenumber":"6108",
    "addr:postcode":"40219",
    "addr:street":"Preston Hwy",
    "iso:country":"US",
    "sg:address":"6108 Preston Hwy",
    "sg:city":"Louisville",
    "sg:classifiers":[
        {
            "category":"Autos & Motor Vehicles",
            "subcategory":"Auto Supplies",
            "type":"Retail Goods"
        }
    ],
    "sg:phone":"+1 502 968 6186",
    "sg:postcode":"40219",
    "sg:province":"KY",
    "sg:tags":[
        "tire"
    ],
    "wof:name":"Michel Tires Plus",
    "wof:placetype":"venue"
},
  "geometry": {"coordinates":[-85.700047,38.162105],"type":"Point"}
}