{
  "type": "Feature",
  "properties": {
    "addr:full":"4514 Briar Hill Rd Lexington KY 40516",
    "addr:housenumber":"4514",
    "addr:postcode":"40516",
    "addr:street":"Briar Hill Rd",
    "iso:country":"US",
    "sg:address":"4514 Briar Hill Rd",
    "sg:city":"Lexington",
    "sg:classifiers":[
        {
            "category":"Organizations",
            "subcategory":"Religious Organization",
            "type":"Services"
        }
    ],
    "sg:phone":"+1 859 299 0664",
    "sg:postcode":"40516",
    "sg:province":"KY",
    "sg:tags":[
        "church"
    ],
    "wof:name":"Grace Fellowship",
    "wof:placetype":"venue"
},
  "geometry": {"coordinates":[-84.367431,38.066066],"type":"Point"}
}