{
  "type": "Feature",
  "properties": {
    "iso:country":"US",
    "sg:address":"10101 Mitchell Hill Rd",
    "sg:city":"Fairdale",
    "sg:classifiers":[
        {
            "category":"Organizations",
            "subcategory":"Community Association",
            "type":"Services"
        }
    ],
    "sg:phone":"+1 502 368 3479",
    "sg:postcode":"40118",
    "sg:province":"KY",
    "sg:tags":[
        "club"
    ],
    "wof:name":"Fairdale Lions Club",
    "wof:placetype":"venue"
},
  "geometry": {"coordinates":[-85.760423,38.104274],"type":"Point"}
}