{
  "type": "Feature",
  "properties": {
    "iso:country":"US",
    "sg:address":"904 N Mulberry St",
    "sg:city":"Elizabethtown",
    "sg:classifiers":[
        {
            "category":"Organizations",
            "subcategory":"Religious Organization",
            "type":"Services"
        }
    ],
    "sg:phone":"+1 270 769 0173",
    "sg:postcode":"42701",
    "sg:province":"KY",
    "sg:tags":[
        "church"
    ],
    "wof:name":"Grace Reformed Church",
    "wof:placetype":"venue"
},
  "geometry": {"coordinates":[-85.84676399999999,37.704578],"type":"Point"}
}