{
  "type": "Feature",
  "properties": {
    "addr:full":"53 Donnermeyer Dr Bellevue KY 41073",
    "addr:housenumber":"53",
    "addr:postcode":"41073",
    "addr:street":"Donnermeyer Dr",
    "iso:country":"US",
    "sg:address":"53 Donnermeyer Dr",
    "sg:city":"Bellevue",
    "sg:classifiers":[
        {
            "category":"Banks & Credit Unions",
            "subcategory":"Bank",
            "type":"Services"
        }
    ],
    "sg:phone":"+1 859 431 2323",
    "sg:postcode":"41073",
    "sg:province":"KY",
    "wof:name":"Fifth Third Bank",
    "wof:placetype":"venue"
},
  "geometry": {"coordinates":[-84.480225,39.099024],"type":"Point"}
}