{
  "type": "Feature",
  "properties": {
    "iso:country":"US",
    "sg:address":"131 W Main St",
    "sg:city":"Louisville",
    "sg:classifiers":[
        {
            "category":"Restaurant",
            "type":"Food & Drink"
        }
    ],
    "sg:menulink":"http://www.allmenus.com/ky/louisville-central/4254-bearnos-by-the-bridge/menu/",
    "sg:phone":"+1 502 584 7437",
    "sg:postcode":"40202",
    "sg:province":"KY",
    "sg:tags":[
        "italian"
    ],
    "wof:name":"Bearno's By The Bridge",
    "wof:placetype":"venue"
},
  "geometry": {"coordinates":[-85.75208499999999,38.256129],"type":"Point"}
}