{
  "type": "Feature",
  "properties": {
    "addr:full":"333 N Main St Smiths Grove KY 42171",
    "addr:housenumber":"333",
    "addr:postcode":"42171",
    "addr:street":"N Main St",
    "iso:country":"US",
    "sg:address":"333 N Main St",
    "sg:city":"Smiths Grove",
    "sg:classifiers":[
        {
            "category":"Organizations",
            "subcategory":"Religious Organization",
            "type":"Services"
        }
    ],
    "sg:phone":"+1 270 563 4338",
    "sg:postcode":"42171",
    "sg:province":"KY",
    "sg:tags":[
        "church"
    ],
    "wof:name":"Smiths Grove United Meth Chr",
    "wof:placetype":"venue"
},
  "geometry": {"coordinates":[-86.207999,37.055734],"type":"Point"}
}