{
  "type": "Feature",
  "properties": {
    "iso:country":"US",
    "sg:address":"610 Flatlick Rd",
    "sg:city":"Mt Washington",
    "sg:classifiers":[
        {
            "category":"Personal",
            "subcategory":"Beauty Salon",
            "type":"Services"
        }
    ],
    "sg:phone":"+1 502 538 6922",
    "sg:postcode":"40047",
    "sg:province":"KY",
    "sg:tags":[
        "shop"
    ],
    "wof:name":"Fran's Beauty Shop",
    "wof:placetype":"venue"
},
  "geometry": {"coordinates":[-85.55686300000001,38.055506],"type":"Point"}
}