{
  "type": "Feature",
  "properties": {
    "iso:country":"US",
    "sg:address":"3902 Brandywine Dr",
    "sg:city":"Catlettsburg",
    "sg:classifiers":[
        {
            "category":"Shopping",
            "subcategory":"Hobbies, Toys, & Games",
            "type":"Retail Goods"
        }
    ],
    "sg:phone":"+1 606 739 6946",
    "sg:postcode":"41129",
    "sg:province":"KY",
    "wof:name":"A&B Hobbies",
    "wof:placetype":"venue"
},
  "geometry": {"coordinates":[-82.678963,38.355079],"type":"Point"}
}