{
  "type": "Feature",
  "properties": {
    "iso:country":"US",
    "sg:address":"148 Keelridge Dr",
    "sg:city":"Georgetown",
    "sg:classifiers":[
        {
            "category":"Communications",
            "type":"Services"
        }
    ],
    "sg:phone":"+1 502 868 9259",
    "sg:postcode":"40324",
    "sg:province":"KY",
    "wof:name":"Details Communication",
    "wof:placetype":"venue"
},
  "geometry": {"coordinates":[-84.57343,38.230987],"type":"Point"}
}