{
  "type": "Feature",
  "properties": {
    "iso:country":"US",
    "sg:address":"7380 Turfway Rd",
    "sg:city":"Florence",
    "sg:classifiers":[
        {
            "category":"Health Services",
            "subcategory":"Doctor",
            "type":"Services"
        },
        {
            "category":"Professional",
            "subcategory":"Lawyer & Legal Services",
            "type":"Services"
        }
    ],
    "sg:phone":"+1 859 212 4889",
    "sg:postcode":"41042",
    "sg:province":"KY",
    "sg:tags":[
        "psychiatrist"
    ],
    "wof:name":"Rodriguez Nelson MD",
    "wof:placetype":"venue"
},
  "geometry": {"coordinates":[-84.632743,39.015368],"type":"Point"}
}