{
  "type": "Feature",
  "properties": {
    "iso:country":"US",
    "sg:address":"150 S 5th St",
    "sg:city":"Louisville",
    "sg:classifiers":[
        {
            "category":"Communications",
            "type":"Services"
        }
    ],
    "sg:phone":"+1 502 582 9326",
    "sg:postcode":"40202",
    "sg:province":"KY",
    "wof:name":"Pro Communication",
    "wof:placetype":"venue"
},
  "geometry": {"coordinates":[-85.75839999999999,38.256127],"type":"Point"}
}