{
  "type": "Feature",
  "properties": {
    "iso:country":"US",
    "sg:address":"4307 Naomi Dr",
    "sg:city":"Louisville",
    "sg:classifiers":[
        {
            "category":"Shopping",
            "subcategory":"Used Merchandise",
            "type":"Retail Goods"
        }
    ],
    "sg:phone":"+1 502 966 9008",
    "sg:postcode":"40219",
    "sg:province":"KY",
    "sg:tags":[
        "flea",
        "market"
    ],
    "wof:name":"Poplar Level Flea Market",
    "wof:placetype":"venue"
},
  "geometry": {"coordinates":[-85.680436,38.165342],"type":"Point"}
}