{
  "type": "Feature",
  "properties": {
    "iso:country":"US",
    "sg:address":"129 Franklin Rd",
    "sg:city":"Scottsville",
    "sg:classifiers":[
        {
            "category":"Building & Trades",
            "subcategory":"Construction",
            "type":"Services"
        }
    ],
    "sg:phone":"+1 502 231 9787",
    "sg:postcode":"42164",
    "sg:province":"KY",
    "sg:tags":[
        "cabling",
        "wiring"
    ],
    "wof:name":"Accurate Networking Cabling",
    "wof:placetype":"venue"
},
  "geometry": {"coordinates":[-86.216534,36.738752],"type":"Point"}
}