{
  "type": "Feature",
  "properties": {
    "iso:country":"US",
    "sg:address":"1903 Eastern Ave",
    "sg:city":"Cincinnati",
    "sg:classifiers":[
        {
            "category":"Autos & Motor Vehicles",
            "subcategory":"Fuel & Gas Station",
            "type":"Retail Goods"
        }
    ],
    "sg:phone":"+1 513 751 2735",
    "sg:postcode":"45202",
    "sg:province":"OH",
    "sg:tags":[
        "oil"
    ],
    "wof:name":"Site Oil Co",
    "wof:placetype":"venue"
},
  "geometry": {"coordinates":[-84.48324,39.117313],"type":"Point"}
}