{
  "type": "Feature",
  "properties": {
    "iso:country":"US",
    "sg:address":"1573 Fort Campbell Blvd",
    "sg:city":"Clarksville",
    "sg:classifiers":[
        {
            "category":"Health Services",
            "subcategory":"Doctor",
            "type":"Services"
        }
    ],
    "sg:phone":"+1 931 552 4806",
    "sg:postcode":"37042",
    "sg:province":"KY",
    "sg:tags":[
        "dentist"
    ],
    "wof:name":"Green Clarksville Family",
    "wof:placetype":"venue"
},
  "geometry": {"coordinates":[-87.407202,36.574075],"type":"Point"}
}