{
  "type": "Feature",
  "properties": {
    "iso:country":"US",
    "sg:address":"2716 Panola St",
    "sg:city":"Catlettsburg",
    "sg:classifiers":[
        {
            "category":"Professional",
            "subcategory":"Lawyer & Legal Services",
            "type":"Services"
        }
    ],
    "sg:phone":"+1 606 739 8434",
    "sg:postcode":"41129",
    "sg:province":"KY",
    "sg:tags":[
        "attorney"
    ],
    "wof:name":"Pruitt & Thorner",
    "wof:placetype":"venue"
},
  "geometry": {"coordinates":[-82.59887999999999,38.416542],"type":"Point"}
}