{
  "type": "Feature",
  "properties": {
    "addr:full":"447 S 3rd St Danville KY 40422",
    "addr:housenumber":"447",
    "addr:postcode":"40422",
    "addr:street":"S 3Rd St",
    "iso:country":"US",
    "sg:address":"447 S 3rd St",
    "sg:city":"Danville",
    "sg:classifiers":[
        {
            "category":"Organizations",
            "subcategory":"Professional Association",
            "type":"Services"
        }
    ],
    "sg:phone":"+1 859 236 3863",
    "sg:postcode":"40422",
    "sg:province":"KY",
    "wof:name":"Family Services Assn",
    "wof:placetype":"venue"
},
  "geometry": {"coordinates":[-84.772974,37.639651],"type":"Point"}
}