{
  "type": "Feature",
  "properties": {
    "iso:country":"US",
    "sg:address":"146 W 12th St",
    "sg:city":"Beaver Dam",
    "sg:classifiers":[
        {
            "category":"Personal",
            "subcategory":"Beauty Salon",
            "type":"Services"
        }
    ],
    "sg:phone":"+1 270 274 4429",
    "sg:postcode":"42320",
    "sg:province":"KY",
    "sg:tags":[
        "shop"
    ],
    "wof:name":"Mildred's Beauty Shop",
    "wof:placetype":"venue"
},
  "geometry": {"coordinates":[-86.879381,37.415305],"type":"Point"}
}