{
  "type": "Feature",
  "properties": {
    "iso:country":"US",
    "sg:address":"207 W Market St",
    "sg:city":"Somerset",
    "sg:classifiers":[
        {
            "category":"Shopping",
            "subcategory":"Used Merchandise",
            "type":"Retail Goods"
        }
    ],
    "sg:phone":"+1 606 679 8041",
    "sg:postcode":"42501",
    "sg:province":"KY",
    "wof:name":"Tyrees Antiques",
    "wof:placetype":"venue"
},
  "geometry": {"coordinates":[-84.605585,37.091028],"type":"Point"}
}