{
  "type": "Feature",
  "properties": {
    "iso:country":"US",
    "sg:address":"1068 Taborlake Dr",
    "sg:city":"Lexington",
    "sg:classifiers":[
        {
            "category":"Professional",
            "subcategory":"Business Services",
            "type":"Services"
        }
    ],
    "sg:phone":"+1 859 269 5457",
    "sg:postcode":"40502",
    "sg:province":"KY",
    "wof:name":"Canup & Wetherby Enterprises",
    "wof:placetype":"venue"
},
  "geometry": {"coordinates":[-84.46853900000001,37.996916],"type":"Point"}
}