{
  "type": "Feature",
  "properties": {
    "iso:country":"US",
    "sg:address":"2413 Richpond Rockfield Rd",
    "sg:city":"Bowling Green",
    "sg:classifiers":[
        {
            "category":"Farming",
            "subcategory":"Livestock Farm",
            "type":"Manufacturing & Wholesale Goods"
        }
    ],
    "sg:phone":"+1 270 781 0738",
    "sg:postcode":"42101",
    "sg:province":"KY",
    "sg:tags":[
        "beef",
        "feedlot",
        "cattle"
    ],
    "wof:name":"Dalton Hardison",
    "wof:placetype":"venue"
},
  "geometry": {"coordinates":[-86.531144,36.900155],"type":"Point"}
}