{
  "type": "Feature",
  "properties": {
    "addr:full":"6616 Dixie Hwy Florence KY 41042",
    "addr:housenumber":"6616",
    "addr:postcode":"41042",
    "addr:street":"Dixie Hwy",
    "iso:country":"US",
    "sg:address":"6616 Dixie Hwy",
    "sg:city":"Florence",
    "sg:classifiers":[
        {
            "category":"Professional",
            "subcategory":"Lawyer & Legal Services",
            "type":"Services"
        }
    ],
    "sg:phone":"+1 859 746 1456",
    "sg:postcode":"41042",
    "sg:province":"KY",
    "sg:tags":[
        "attorney"
    ],
    "wof:name":"Beth Albright Louis Pllc",
    "wof:placetype":"venue"
},
  "geometry": {"coordinates":[-84.61879500000001,39.004982],"type":"Point"}
}