{
  "type": "Feature",
  "properties": {
    "iso:country":"US",
    "sg:address":"606 Bourne Ave",
    "sg:city":"Somerset",
    "sg:classifiers":[
        {
            "category":"Retail",
            "subcategory":"Auto Rental",
            "type":"Services"
        }
    ],
    "sg:phone":"+1 606 679 4946",
    "sg:postcode":"42501",
    "sg:province":"KY",
    "sg:tags":[
        "renting",
        "truck",
        "leasing"
    ],
    "wof:name":"Ryder Truck Rental",
    "wof:placetype":"venue"
},
  "geometry": {"coordinates":[-84.59889099999999,37.086391],"type":"Point"}
}