{
  "type": "Feature",
  "properties": {
    "addr:full":"201 22nd St Ashland KY 41101",
    "addr:housenumber":"201",
    "addr:postcode":"41101",
    "addr:street":"22Nd St",
    "iso:country":"US",
    "sg:address":"201 22nd St",
    "sg:city":"Ashland",
    "sg:classifiers":[
        {
            "category":"Social Services",
            "type":"Services"
        }
    ],
    "sg:phone":"+1 606 324 1141",
    "sg:postcode":"41101",
    "sg:province":"KY",
    "sg:tags":[
        "assault",
        "abuse",
        "sexual",
        "crisis"
    ],
    "wof:name":"Pathways Inc",
    "wof:placetype":"venue"
},
  "geometry": {"coordinates":[-82.63223499999999,38.474971],"type":"Point"}
}