{
  "type": "Feature",
  "properties": {
    "iso:country":"US",
    "sg:address":"501 Saint Ann St",
    "sg:city":"Owensboro",
    "sg:classifiers":[
        {
            "category":"Professional",
            "subcategory":"Lawyer & Legal Services",
            "type":"Services"
        }
    ],
    "sg:phone":"+1 270 685 5002",
    "sg:postcode":"42303",
    "sg:province":"KY",
    "sg:tags":[
        "attorney"
    ],
    "wof:name":"Candy Y Englebert",
    "wof:placetype":"venue"
},
  "geometry": {"coordinates":[-87.111881,37.76947],"type":"Point"}
}