{
  "type": "Feature",
  "properties": {
    "iso:country":"US",
    "sg:address":"8200 Us Highway 60 W",
    "sg:city":"Lewisport",
    "sg:classifiers":[
        {
            "category":"Restaurant",
            "type":"Food & Drink"
        }
    ],
    "sg:menulink":"http://www.allmenus.com/ky/lewisport/120577-subway/menu/",
    "sg:phone":"+1 270 295 6777",
    "sg:postcode":"42351",
    "sg:province":"KY",
    "sg:tags":[
        "american",
        "sandwich"
    ],
    "wof:name":"Subway",
    "wof:placetype":"venue"
},
  "geometry": {"coordinates":[-86.89001,37.925608],"type":"Point"}
}