{
  "type": "Feature",
  "properties": {
    "iso:country":"US",
    "sg:address":"1851 Wilmore Rd",
    "sg:city":"Nicholasville",
    "sg:classifiers":[
        {
            "category":"Building & Trades",
            "subcategory":"Construction",
            "type":"Services"
        }
    ],
    "sg:phone":"+1 859 885 3061",
    "sg:postcode":"40356",
    "sg:province":"KY",
    "sg:tags":[
        "contractor"
    ],
    "wof:name":"Charles K Williams Inc",
    "wof:placetype":"venue"
},
  "geometry": {"coordinates":[-84.613501,37.885771],"type":"Point"}
}