{
  "type": "Feature",
  "properties": {
    "addr:full":"203 Breeze Hill Dr Winchester KY 40391",
    "addr:housenumber":"203",
    "addr:postcode":"40391",
    "addr:street":"Breeze Hill Dr",
    "iso:country":"US",
    "sg:address":"203 Breeze Hill Dr",
    "sg:city":"Winchester",
    "sg:classifiers":[
        {
            "category":"Wholesale",
            "subcategory":"Sporting Goods",
            "type":"Manufacturing & Wholesale Goods"
        }
    ],
    "sg:phone":"+1 859 744 6490",
    "sg:postcode":"40391",
    "sg:province":"KY",
    "sg:tags":[
        "tackle",
        "fishing"
    ],
    "sg:website":"www.cabincreekco.com",
    "wof:name":"Cabin Creek Baits",
    "wof:placetype":"venue"
},
  "geometry": {"coordinates":[-84.206941,38.005175],"type":"Point"}
}