{
  "type": "Feature",
  "properties": {
    "iso:country":"US",
    "sg:address":"1 Levee Way Suite 2122",
    "sg:city":"Newport",
    "sg:classifiers":[
        {
            "category":"Bars & Pubs",
            "type":"Food & Drink"
        },
        {
            "category":"Restaurant",
            "type":"Food & Drink"
        }
    ],
    "sg:phone":"+1 859 581 8888",
    "sg:postcode":"41071",
    "sg:province":"KY",
    "sg:tags":[
        "irish"
    ],
    "sg:website":"www.claddaghirishpubs.com",
    "wof:name":"Claddagh Irish Pub",
    "wof:placetype":"venue"
},
  "geometry": {"coordinates":[-122.184505,47.571865],"type":"Point"}
}