{
  "type": "Feature",
  "properties": {
    "addr:full":"327 Main St Owenton KY 40359",
    "addr:housenumber":"327",
    "addr:postcode":"40359",
    "addr:street":"Main St",
    "iso:country":"US",
    "sg:address":"327 Main St",
    "sg:city":"Owenton",
    "sg:classifiers":[
        {
            "category":"Insurance",
            "subcategory":"Insurance Agent",
            "type":"Services"
        }
    ],
    "sg:phone":"+1 502 484 5190",
    "sg:postcode":"40359",
    "sg:province":"KY",
    "wof:name":"State Farm Insurance",
    "wof:placetype":"venue"
},
  "geometry": {"coordinates":[-84.835843,38.533949],"type":"Point"}
}