{
  "type": "Feature",
  "properties": {
    "iso:country":"US",
    "sg:address":"5 S Main St",
    "sg:city":"Winchester",
    "sg:classifiers":[
        {
            "category":"Shopping",
            "subcategory":"Used Merchandise",
            "type":"Retail Goods"
        }
    ],
    "sg:phone":"+1 859 744 8539",
    "sg:postcode":"40391",
    "sg:province":"KY",
    "sg:tags":[
        "flea",
        "market"
    ],
    "wof:name":"Winchester Flea Market",
    "wof:placetype":"venue"
},
  "geometry": {"coordinates":[-84.176907,37.993351],"type":"Point"}
}