{
  "type": "Feature",
  "properties": {
    "addr:full":"2424 Harrodsburg Rd Lexington KY 40503",
    "addr:housenumber":"2424",
    "addr:postcode":"40503",
    "addr:street":"Harrodsburg Rd",
    "iso:country":"US",
    "sg:address":"2424 Harrodsburg Rd",
    "sg:city":"Lexington",
    "sg:classifiers":[
        {
            "category":"Professional",
            "subcategory":"Computer Services",
            "type":"Services"
        }
    ],
    "sg:phone":"+1 859 296 0600",
    "sg:postcode":"40503",
    "sg:province":"KY",
    "sg:tags":[
        "prepackaged",
        "custom",
        "programing",
        "software"
    ],
    "wof:name":"Exstream Software Inc",
    "wof:placetype":"venue"
},
  "geometry": {"coordinates":[-84.547983,38.017595],"type":"Point"}
}