{
  "type": "Feature",
  "properties": {
    "addr:full":"250 E Liberty St Louisville KY 40202",
    "addr:housenumber":"250",
    "addr:postcode":"40202",
    "addr:street":"E Liberty St",
    "iso:country":"US",
    "sg:address":"250 E Liberty St",
    "sg:city":"Louisville",
    "sg:classifiers":[
        {
            "category":"Health Services",
            "subcategory":"Doctor",
            "type":"Services"
        }
    ],
    "sg:phone":"+1 502 584 0651",
    "sg:postcode":"40202",
    "sg:province":"KY",
    "sg:tags":[
        "physician",
        "surgeon",
        "urology",
        "surgeons"
    ],
    "wof:name":"Smith, Dennis MD",
    "wof:placetype":"venue"
},
  "geometry": {"coordinates":[-85.74954700000001,38.252237],"type":"Point"}
}