{
  "type": "Feature",
  "properties": {
    "iso:country":"US",
    "sg:address":"1550 State Hwy 22",
    "sg:city":"Owenton",
    "sg:classifiers":[
        {
            "category":"Travel",
            "subcategory":"Hotels & Motels",
            "type":"Entertainment"
        }
    ],
    "sg:phone":"+1 502 484 3406",
    "sg:postcode":"40359",
    "sg:province":"KY",
    "wof:name":"Hi Y Inn",
    "wof:placetype":"venue"
},
  "geometry": {"coordinates":[-84.83528800000001,38.533496],"type":"Point"}
}