{
  "type": "Feature",
  "properties": {
    "addr:full":"13001 W Highway 42 Prospect KY 40059",
    "addr:housenumber":"13001",
    "addr:postcode":"40059",
    "addr:street":"W Highway 42",
    "iso:country":"US",
    "sg:address":"13001 W Highway 42",
    "sg:city":"Prospect",
    "sg:classifiers":[
        {
            "category":"Social Services",
            "subcategory":"Child Care",
            "type":"Services"
        },
        {
            "category":"Education",
            "subcategory":"Preschool",
            "type":"Public Place"
        },
        {
            "category":"Education",
            "subcategory":"School",
            "type":"Public Place"
        }
    ],
    "sg:phone":"+1 502 228 4007",
    "sg:postcode":"40059",
    "sg:province":"KY",
    "sg:tags":[
        "elementary",
        "day"
    ],
    "sg:website":"www.prospectpreschool.com",
    "wof:name":"Prospect Centre Preschool",
    "wof:placetype":"venue"
},
  "geometry": {"coordinates":[-85.58719600000001,38.378601],"type":"Point"}
}