{
  "type": "Feature",
  "properties": {
    "iso:country":"US",
    "sg:address":"453 Hambley Blvd",
    "sg:city":"Pikeville",
    "sg:classifiers":[
        {
            "category":"Food & Beverages",
            "subcategory":"Liquor & Beverages",
            "type":"Retail Goods"
        }
    ],
    "sg:phone":"+1 606 437 9219",
    "sg:postcode":"41501",
    "sg:province":"KY",
    "wof:name":"Down Town Liquors",
    "wof:placetype":"venue"
},
  "geometry": {"coordinates":[-82.527812,37.484558],"type":"Point"}
}