{
  "type": "Feature",
  "properties": {
    "iso:country":"US",
    "sg:address":"2333 Alexandria Dr",
    "sg:city":"Lexington",
    "sg:classifiers":[
        {
            "category":"Social Services",
            "type":"Services"
        }
    ],
    "sg:phone":"+1 859 514 6727",
    "sg:postcode":"40504",
    "sg:province":"KY",
    "wof:name":"Nadine Lear Audrey",
    "wof:placetype":"venue"
},
  "geometry": {"coordinates":[-84.550676,38.019327],"type":"Point"}
}