{
  "type": "Feature",
  "properties": {
    "iso:country":"US",
    "sg:address":"229 New Gritton Ave",
    "sg:city":"Oak Grove",
    "sg:classifiers":[
        {
            "category":"Personal",
            "type":"Services"
        }
    ],
    "sg:phone":"+1 270 439 6803",
    "sg:postcode":"42262",
    "sg:province":"KY",
    "wof:name":"First Sprit Flled Wdding Chpel",
    "wof:placetype":"venue"
},
  "geometry": {"coordinates":[-87.39972899999999,36.655807],"type":"Point"}
}