{
  "type": "Feature",
  "properties": {
    "iso:country":"US",
    "sg:address":"710 N Main St",
    "sg:city":"Hopkinsville",
    "sg:classifiers":[
        {
            "category":"Retail",
            "subcategory":"Veterinary Services",
            "type":"Services"
        }
    ],
    "sg:phone":"+1 270 886 9416",
    "sg:postcode":"42240",
    "sg:province":"KY",
    "sg:tags":[
        "hospital",
        "animal"
    ],
    "wof:name":"Mansfield Animal Hospital",
    "wof:placetype":"venue"
},
  "geometry": {"coordinates":[-87.482527,36.878057],"type":"Point"}
}