{
  "type": "Feature",
  "properties": {
    "iso:country":"US",
    "sg:address":"8100 Westport Rd",
    "sg:city":"Louisville",
    "sg:classifiers":[
        {
            "category":"Education",
            "subcategory":"Library",
            "type":"Public Place"
        }
    ],
    "sg:phone":"+1 502 394 0379",
    "sg:postcode":"40222",
    "sg:province":"KY",
    "wof:name":"Westport Library",
    "wof:placetype":"venue"
},
  "geometry": {"coordinates":[-85.605549,38.275557],"type":"Point"}
}