{
  "type": "Feature",
  "properties": {
    "addr:full":"181 Prosperous Pl Lexington KY 40509",
    "addr:housenumber":"181",
    "addr:postcode":"40509",
    "addr:street":"Prosperous Pl",
    "iso:country":"US",
    "sg:address":"181 Prosperous Pl",
    "sg:city":"Lexington",
    "sg:classifiers":[
        {
            "category":"Insurance",
            "subcategory":"Insurance Agent",
            "type":"Services"
        }
    ],
    "sg:phone":"+1 859 263 2771",
    "sg:postcode":"40509",
    "sg:province":"KY",
    "sg:website":"www.vanmeterins.com",
    "wof:name":"Van Meter Insurance",
    "wof:placetype":"venue"
},
  "geometry": {"coordinates":[-84.442497,38.001849],"type":"Point"}
}