{
  "type": "Feature",
  "properties": {
    "iso:country":"US",
    "sg:address":"35 S Bank St",
    "sg:city":"Mt Sterling",
    "sg:classifiers":[
        {
            "category":"Real Estate",
            "subcategory":"Real Estate Agent",
            "type":"Services"
        }
    ],
    "sg:phone":"+1 859 498 7653",
    "sg:postcode":"40353",
    "sg:province":"KY",
    "wof:name":"New Century Realty",
    "wof:placetype":"venue"
},
  "geometry": {"coordinates":[-83.943219,38.055654],"type":"Point"}
}