{
  "type": "Feature",
  "properties": {
    "iso:country":"US",
    "sg:address":"200 E Frazier Ave",
    "sg:city":"Columbia",
    "sg:classifiers":[
        {
            "category":"Health Services",
            "subcategory":"Hospital",
            "type":"Services"
        }
    ],
    "sg:phone":"+1 270 384 4719",
    "sg:postcode":"42728",
    "sg:province":"KY",
    "sg:tags":[
        "mental"
    ],
    "sg:website":"www.adanta.org",
    "wof:name":"Adanta Group Behavioral",
    "wof:placetype":"venue"
},
  "geometry": {"coordinates":[-85.308584,37.099035],"type":"Point"}
}