{
  "type": "Feature",
  "properties": {
    "iso:country":"US",
    "sg:address":"2325 Chrisman Mill Rd",
    "sg:city":"Nicholasville",
    "sg:classifiers":[
        {
            "category":"Personal",
            "type":"Services"
        }
    ],
    "sg:phone":"+1 859 885 2788",
    "sg:postcode":"40356",
    "sg:province":"KY",
    "sg:tags":[
        "control",
        "weight"
    ],
    "wof:name":"Diet Center Of Nicholasville",
    "wof:placetype":"venue"
},
  "geometry": {"coordinates":[-84.504791,37.841032],"type":"Point"}
}