{
  "type": "Feature",
  "properties": {
    "iso:country":"US",
    "sg:address":"896 Kennedy Bridge Rd",
    "sg:city":"Lancaster",
    "sg:phone":"+1 859 548 4561",
    "sg:postcode":"40444",
    "sg:province":"KY",
    "sg:tags":[
        "farm",
        "corn"
    ],
    "wof:name":"Ray Graham",
    "wof:placetype":"venue"
},
  "geometry": {"coordinates":[-84.647347,37.742717],"type":"Point"}
}