{
  "type": "Feature",
  "properties": {
    "addr:full":"1087 Sandlick Rd Princeton KY 42445",
    "addr:housenumber":"1087",
    "addr:postcode":"42445",
    "addr:street":"Sandlick Rd",
    "iso:country":"US",
    "sg:address":"1087 Sandlick Rd",
    "sg:city":"Princeton",
    "sg:classifiers":[
        {
            "category":"Personal",
            "subcategory":"Beauty Salon",
            "type":"Services"
        }
    ],
    "sg:phone":"+1 270 365 5266",
    "sg:postcode":"42445",
    "sg:province":"KY",
    "sg:tags":[
        "shop"
    ],
    "wof:name":"Total E Clips Beauty Salon",
    "wof:placetype":"venue"
},
  "geometry": {"coordinates":[-87.855555,37.102729],"type":"Point"}
}