{
  "type": "Feature",
  "properties": {
    "iso:country":"US",
    "sg:address":"1287 Washington School Rd",
    "sg:city":"Scottsville",
    "sg:classifiers":[
        {
            "category":"Organizations",
            "subcategory":"Religious Organization",
            "type":"Services"
        }
    ],
    "sg:phone":"+1 270 622 3900",
    "sg:postcode":"42164",
    "sg:province":"KY",
    "wof:name":"Church Of God-USA Headquarters",
    "wof:placetype":"venue"
},
  "geometry": {"coordinates":[-86.138682,36.783009],"type":"Point"}
}