{
  "type": "Feature",
  "properties": {
    "addr:full":"4211 Jim Hawkins Dr Louisville KY 40229",
    "addr:housenumber":"4211",
    "addr:postcode":"40229",
    "addr:street":"Jim Hawkins Dr",
    "iso:country":"US",
    "sg:address":"4211 Jim Hawkins Dr",
    "sg:city":"Louisville",
    "sg:classifiers":[
        {
            "category":"Organizations",
            "subcategory":"Religious Organization",
            "type":"Services"
        }
    ],
    "sg:phone":"+1 502 969 6028",
    "sg:postcode":"40229",
    "sg:province":"KY",
    "sg:tags":[
        "church"
    ],
    "wof:name":"St Luke Catholic Church",
    "wof:placetype":"venue"
},
  "geometry": {"coordinates":[-85.68698500000001,38.104809],"type":"Point"}
}