{
  "type": "Feature",
  "properties": {
    "addr:full":"2425 Merchant St Lexington KY 40511",
    "addr:housenumber":"2425",
    "addr:postcode":"40511",
    "addr:street":"Merchant St",
    "iso:country":"US",
    "sg:address":"2425 Merchant St",
    "sg:city":"Lexington",
    "sg:classifiers":[
        {
            "category":"Freight",
            "type":"Transportation"
        }
    ],
    "sg:phone":"+1 859 254 0905",
    "sg:postcode":"40511",
    "sg:province":"KY",
    "sg:tags":[
        "warehouse"
    ],
    "wof:name":"Sumitomo Electric Wiring Syst",
    "wof:placetype":"venue"
},
  "geometry": {"coordinates":[-84.544324,38.077965],"type":"Point"}
}