{
  "type": "Feature",
  "properties": {
    "addr:full":"110 Sterling Ave Mt Sterling KY 40353",
    "addr:housenumber":"110",
    "addr:postcode":"40353",
    "addr:street":"Sterling Ave",
    "iso:country":"US",
    "sg:address":"110 Sterling Ave",
    "sg:city":"Mt Sterling",
    "sg:classifiers":[
        {
            "category":"Restaurant",
            "type":"Food & Drink"
        }
    ],
    "sg:phone":"+1 859 499 0200",
    "sg:postcode":"40353",
    "sg:province":"KY",
    "sg:website":"www.crackerbarrel.com",
    "wof:name":"Cracker Barrel Old Country Str",
    "wof:placetype":"venue"
},
  "geometry": {"coordinates":[-83.947503,38.061593],"type":"Point"}
}