{
  "type": "Feature",
  "properties": {
    "iso:country":"US",
    "sg:address":"2058 Clarence Fox Rd",
    "sg:city":"Obion",
    "sg:classifiers":[
        {
            "category":"Building & Trades",
            "subcategory":"Construction",
            "type":"Services"
        }
    ],
    "sg:phone":"+1 731 536 6220",
    "sg:postcode":"38240",
    "sg:province":"TN",
    "sg:tags":[
        "farm",
        "system",
        "drainage"
    ],
    "wof:name":"Fox Pro Tile",
    "wof:placetype":"venue"
},
  "geometry": {"coordinates":[-89.230432,36.255707],"type":"Point"}
}