{
  "type": "Feature",
  "properties": {
    "iso:country":"US",
    "sg:address":"3701 Frankfort Ave",
    "sg:city":"Louisville",
    "sg:classifiers":[
        {
            "category":"Organizations",
            "subcategory":"Community Association",
            "type":"Services"
        }
    ],
    "sg:phone":"+1 502 897 4933",
    "sg:postcode":"40207",
    "sg:province":"KY",
    "sg:tags":[
        "fraternal"
    ],
    "sg:website":"www.masonichomesky.com",
    "wof:name":"Masonic Homes Of Kentucky Dev",
    "wof:placetype":"venue"
},
  "geometry": {"coordinates":[-85.66021000000001,38.253291],"type":"Point"}
}