{
  "type": "Feature",
  "properties": {
    "addr:full":"988 Locust Grove Rd Hardin KY 42071",
    "addr:housenumber":"988",
    "addr:postcode":"42071",
    "addr:street":"Locust Grove Rd",
    "iso:country":"US",
    "sg:address":"988 Locust Grove Rd",
    "sg:city":"Hardin",
    "sg:classifiers":[
        {
            "category":"Wholesale",
            "subcategory":"Construction Materials",
            "type":"Manufacturing & Wholesale Goods"
        }
    ],
    "sg:phone":"+1 270 769 0705",
    "sg:postcode":"42071",
    "sg:province":"KY",
    "sg:tags":[
        "fence"
    ],
    "wof:name":"Jaggers Fence Co",
    "wof:placetype":"venue"
},
  "geometry": {"coordinates":[-88.28201300000001,36.568124],"type":"Point"}
}