{
  "type": "Feature",
  "properties": {
    "iso:country":"US",
    "sg:address":"2602 Mercer Ln",
    "sg:city":"West Point",
    "sg:classifiers":[
        {
            "category":"Farming",
            "subcategory":"Livestock Farm",
            "type":"Manufacturing & Wholesale Goods"
        }
    ],
    "sg:phone":"+1 502 922 4470",
    "sg:postcode":"40177",
    "sg:province":"KY",
    "sg:tags":[
        "beef",
        "feedlot",
        "cattle"
    ],
    "wof:name":"Riverview Acres",
    "wof:placetype":"venue"
},
  "geometry": {"coordinates":[-85.971391,37.987943],"type":"Point"}
}