{
  "type": "Feature",
  "properties": {
    "iso:country":"US",
    "sg:address":"7605 Empire Dr",
    "sg:city":"Florence",
    "sg:classifiers":[
        {
            "category":"Restaurant",
            "type":"Food & Drink"
        }
    ],
    "sg:phone":"+1 859 371 0500",
    "sg:postcode":"41042",
    "sg:province":"KY",
    "wof:name":"Sabatasso Foods Inc",
    "wof:placetype":"venue"
},
  "geometry": {"coordinates":[-84.632335,38.975065],"type":"Point"}
}