{
  "type": "Feature",
  "properties": {
    "iso:country":"US",
    "sg:address":"904 S Main St",
    "sg:city":"Nicholasville",
    "sg:classifiers":[
        {
            "category":"Social Services",
            "subcategory":"Job Training",
            "type":"Services"
        }
    ],
    "sg:phone":"+1 859 885 1540",
    "sg:postcode":"40356",
    "sg:province":"KY",
    "sg:tags":[
        "rehabilitation"
    ],
    "wof:name":"Alcohol Related Offenders Prgm",
    "wof:placetype":"venue"
},
  "geometry": {"coordinates":[-84.57791,37.86778],"type":"Point"}
}