{
  "type": "Feature",
  "properties": {
    "addr:full":"744 E Broadway Louisville KY 40202",
    "addr:housenumber":"744",
    "addr:postcode":"40202",
    "addr:street":"E Broadway",
    "iso:country":"US",
    "sg:address":"744 E Broadway",
    "sg:city":"Louisville",
    "sg:classifiers":[
        {
            "category":"Health Services",
            "subcategory":"Health Practitioner",
            "type":"Services"
        }
    ],
    "sg:phone":"+1 502 584 7717",
    "sg:postcode":"40202",
    "sg:province":"KY",
    "sg:tags":[
        "therapist",
        "physical"
    ],
    "wof:name":"Bluegrass Physical Rehab",
    "wof:placetype":"venue"
},
  "geometry": {"coordinates":[-85.74023200000001,38.244673],"type":"Point"}
}