{
  "type": "Feature",
  "properties": {
    "iso:country":"US",
    "sg:address":"209 33rd St",
    "sg:city":"Catlettsburg",
    "sg:classifiers":[
        {
            "category":"Freight",
            "type":"Transportation"
        }
    ],
    "sg:phone":"+1 606 739 5792",
    "sg:postcode":"41129",
    "sg:province":"KY",
    "sg:tags":[
        "operator",
        "local",
        "trucking"
    ],
    "wof:name":"Coal Trucking",
    "wof:placetype":"venue"
},
  "geometry": {"coordinates":[-82.597998,38.406781],"type":"Point"}
}