{
  "type": "Feature",
  "properties": {
    "iso:country":"US",
    "sg:address":"1058 Columbia Ave",
    "sg:city":"Monticello",
    "sg:classifiers":[
        {
            "category":"Home & Garden",
            "subcategory":"Carpets & Floor Coverings",
            "type":"Retail Goods"
        }
    ],
    "sg:phone":"+1 606 348 9259",
    "sg:postcode":"42633",
    "sg:province":"KY",
    "sg:tags":[
        "dealer",
        "rug"
    ],
    "wof:name":"Bell's Carpet Ctr",
    "wof:placetype":"venue"
},
  "geometry": {"coordinates":[-84.86114000000001,36.838293],"type":"Point"}
}