{
  "type": "Feature",
  "properties": {
    "iso:country":"US",
    "sg:address":"841 E Washington St",
    "sg:city":"Louisville",
    "sg:classifiers":[
        {
            "category":"Food & Beverages",
            "subcategory":"Groceries & Convenience Stores",
            "type":"Retail Goods"
        }
    ],
    "sg:phone":"+1 502 581 9267",
    "sg:postcode":"40206",
    "sg:province":"KY",
    "sg:tags":[
        "grocer"
    ],
    "wof:name":"Jerry's Market",
    "wof:placetype":"venue"
},
  "geometry": {"coordinates":[-85.736273,38.255276],"type":"Point"}
}