{
  "type": "Feature",
  "properties": {
    "iso:country":"US",
    "sg:address":"430 Hotchkiss St",
    "sg:city":"Campbellsville",
    "sg:classifiers":[
        {
            "category":"Personal",
            "subcategory":"Beauty Salon",
            "type":"Services"
        }
    ],
    "sg:phone":"+1 270 465 5658",
    "sg:postcode":"42718",
    "sg:province":"KY",
    "wof:name":"Barbara's Styling Station",
    "wof:placetype":"venue"
},
  "geometry": {"coordinates":[-85.340298,37.342084],"type":"Point"}
}