{
  "type": "Feature",
  "properties": {
    "iso:country":"US",
    "sg:address":"138 Taylor Rd",
    "sg:city":"Pikeville",
    "sg:classifiers":[
        {
            "category":"Manufacturing",
            "subcategory":"Printing",
            "type":"Manufacturing & Wholesale Goods"
        },
        {
            "category":"Shopping",
            "subcategory":"Clothing, Apparel, & Fashions",
            "type":"Retail Goods"
        }
    ],
    "sg:phone":"+1 606 437 6680",
    "sg:postcode":"41501",
    "sg:province":"KY",
    "sg:tags":[
        "screen",
        "sporting"
    ],
    "wof:name":"Sports Outfitters Supply",
    "wof:placetype":"venue"
},
  "geometry": {"coordinates":[-82.479771,37.523428],"type":"Point"}
}