{
  "type": "Feature",
  "properties": {
    "addr:full":"2152 S Hurstbourne Pkwy Louisville KY 40220",
    "addr:housenumber":"2152",
    "addr:postcode":"40220",
    "addr:street":"S Hurstbourne Pkwy",
    "iso:country":"US",
    "sg:address":"2152 S Hurstbourne Pkwy",
    "sg:city":"Louisville",
    "sg:classifiers":[
        {
            "category":"Health Services",
            "subcategory":"Doctor",
            "type":"Services"
        }
    ],
    "sg:phone":"+1 502 499 0107",
    "sg:postcode":"40220",
    "sg:province":"KY",
    "sg:tags":[
        "physician",
        "surgeons",
        "medicine",
        "surgeon",
        "rehabilitation",
        "physical"
    ],
    "wof:name":"J'town Physical Therapy",
    "wof:placetype":"venue"
},
  "geometry": {"coordinates":[-85.590137,38.216293],"type":"Point"}
}