{
  "type": "Feature",
  "properties": {
    "iso:country":"US",
    "sg:address":"9952 Hodgenville Rd",
    "sg:city":"Campbellsville",
    "sg:classifiers":[
        {
            "category":"Retail",
            "subcategory":"Repair Shop",
            "type":"Services"
        }
    ],
    "sg:phone":"+1 270 789 0270",
    "sg:postcode":"42718",
    "sg:province":"KY",
    "sg:tags":[
        "equipment",
        "medical"
    ],
    "wof:name":"Beams Repair Svc",
    "wof:placetype":"venue"
},
  "geometry": {"coordinates":[-85.48970199999999,37.411977],"type":"Point"}
}