{
  "type": "Feature",
  "properties": {
    "iso:country":"US",
    "sg:address":"505 Lyndon Ln",
    "sg:city":"Louisville",
    "sg:classifiers":[
        {
            "category":"Arts & Performance",
            "subcategory":"Dance",
            "type":"Entertainment"
        }
    ],
    "sg:phone":"+1 502 339 7413",
    "sg:postcode":"40222",
    "sg:province":"KY",
    "sg:tags":[
        "instruction",
        "dancing"
    ],
    "wof:name":"Bobs Dance Sport",
    "wof:placetype":"venue"
},
  "geometry": {"coordinates":[-85.60177899999999,38.256679],"type":"Point"}
}