{
  "type": "Feature",
  "properties": {
    "addr:full":"714 Brown Rd Madisonville KY 42431",
    "addr:housenumber":"714",
    "addr:postcode":"42431",
    "addr:street":"Brown Rd",
    "iso:country":"US",
    "sg:address":"714 Brown Rd",
    "sg:city":"Madisonville",
    "sg:classifiers":[
        {
            "category":"Organizations",
            "subcategory":"Religious Organization",
            "type":"Services"
        }
    ],
    "sg:phone":"+1 270 825 8459",
    "sg:postcode":"42431",
    "sg:province":"KY",
    "sg:tags":[
        "church"
    ],
    "wof:name":"Immanuel Baptist Church",
    "wof:placetype":"venue"
},
  "geometry": {"coordinates":[-87.472866,37.336315],"type":"Point"}
}