{
  "type": "Feature",
  "properties": {
    "iso:country":"US",
    "sg:address":"201 Marion Pike",
    "sg:city":"Ironton",
    "sg:classifiers":[
        {
            "category":"Manufacturing",
            "subcategory":"Retail Goods",
            "type":"Manufacturing & Wholesale Goods"
        }
    ],
    "sg:phone":"+1 740 533 2587",
    "sg:postcode":"45638",
    "sg:province":"OH",
    "sg:tags":[
        "on",
        "garment",
        "screen",
        "printing",
        "embroidery",
        "dealer"
    ],
    "wof:name":"Cjts",
    "wof:placetype":"venue"
},
  "geometry": {"coordinates":[-82.648833,38.501399],"type":"Point"}
}