{
  "type": "Feature",
  "properties": {
    "iso:country":"US",
    "sg:address":"1500 Breckenridge St",
    "sg:city":"Owensboro",
    "sg:classifiers":[
        {
            "category":"Retail",
            "subcategory":"Auto Repair",
            "type":"Services"
        }
    ],
    "sg:phone":"+1 270 685 2062",
    "sg:postcode":"42303",
    "sg:province":"KY",
    "sg:tags":[
        "repairing",
        "automobile"
    ],
    "wof:name":"Larry Roberts Automotive",
    "wof:placetype":"venue"
},
  "geometry": {"coordinates":[-87.098236,37.762003],"type":"Point"}
}