{
  "type": "Feature",
  "properties": {
    "addr:full":"680 Bizzell Dr Lexington KY 40510",
    "addr:housenumber":"680",
    "addr:postcode":"40510",
    "addr:street":"Bizzell Dr",
    "iso:country":"US",
    "sg:address":"680 Bizzell Dr",
    "sg:city":"Lexington",
    "sg:classifiers":[
        {
            "category":"Freight",
            "type":"Transportation"
        }
    ],
    "sg:phone":"+1 859 226 0688",
    "sg:postcode":"40510",
    "sg:province":"KY",
    "sg:tags":[
        "delivery"
    ],
    "wof:name":"Racing Information Delivery",
    "wof:placetype":"venue"
},
  "geometry": {"coordinates":[-84.54150799999999,38.063847],"type":"Point"}
}