{
  "type": "Feature",
  "properties": {
    "iso:country":"US",
    "sg:address":"4100 Lentz Ave",
    "sg:city":"Louisville",
    "sg:classifiers":[
        {
            "category":"Social Services",
            "subcategory":"Child Care",
            "type":"Services"
        }
    ],
    "sg:phone":"+1 502 368 3488",
    "sg:postcode":"40215",
    "sg:province":"KY",
    "wof:name":"Iroquis Child Care Ctr",
    "wof:placetype":"venue"
},
  "geometry": {"coordinates":[-85.78655000000001,38.184735],"type":"Point"}
}