{
  "type": "Feature",
  "properties": {
    "iso:country":"US",
    "sg:address":"404 N 3rd St",
    "sg:city":"Cave City",
    "sg:classifiers":[
        {
            "category":"Retail",
            "subcategory":"Car Wash",
            "type":"Services"
        }
    ],
    "sg:phone":"+1 270 773 2466",
    "sg:postcode":"42127",
    "sg:province":"KY",
    "sg:tags":[
        "carwash"
    ],
    "wof:name":"C&C Car Wash Inc",
    "wof:placetype":"venue"
},
  "geometry": {"coordinates":[-85.950896,37.142099],"type":"Point"}
}