{
  "type": "Feature",
  "properties": {
    "addr:full":"4128 State Hwy 849 E Boaz KY 42027",
    "addr:housenumber":"4128",
    "addr:postcode":"42027",
    "addr:street":"State Hwy 849 E",
    "iso:country":"US",
    "sg:address":"4128 State Hwy 849 E",
    "sg:city":"Boaz",
    "sg:phone":"+1 270 658 3471",
    "sg:postcode":"42027",
    "sg:province":"KY",
    "sg:tags":[
        "farm",
        "field",
        "crop"
    ],
    "wof:name":"Donalee Ford",
    "wof:placetype":"venue"
},
  "geometry": {"coordinates":[-88.618471,36.885056],"type":"Point"}
}