{
  "type": "Feature",
  "properties": {
    "iso:country":"US",
    "sg:address":"1099 Burlington Pike",
    "sg:city":"Florence",
    "sg:classifiers":[
        {
            "category":"Insurance",
            "subcategory":"Insurance Agent",
            "type":"Services"
        }
    ],
    "sg:phone":"+1 859 371 0095",
    "sg:postcode":"41042",
    "sg:province":"KY",
    "wof:name":"State Farm Insurance",
    "wof:placetype":"venue"
},
  "geometry": {"coordinates":[-84.66362700000001,39.008271],"type":"Point"}
}