{
  "type": "Feature",
  "properties": {
    "iso:country":"US",
    "sg:address":"3174 Running Deer Cir",
    "sg:city":"Louisville",
    "sg:classifiers":[
        {
            "category":"Professional",
            "type":"Services"
        }
    ],
    "sg:phone":"+1 502 339 7555",
    "sg:postcode":"40241",
    "sg:province":"KY",
    "sg:tags":[
        "establishment"
    ],
    "wof:name":"Overlook Of St Thomas",
    "wof:placetype":"venue"
},
  "geometry": {"coordinates":[-85.62171499999999,38.296252],"type":"Point"}
}