{
  "type": "Feature",
  "properties": {
    "addr:full":"1508 Edgewood Pl Louisville KY 40205",
    "addr:housenumber":"1508",
    "addr:postcode":"40205",
    "addr:street":"Edgewood Pl",
    "iso:country":"US",
    "sg:address":"1508 Edgewood Pl",
    "sg:city":"Louisville",
    "sg:classifiers":[
        {
            "category":"Real Estate",
            "subcategory":"Real Estate Services",
            "type":"Services"
        }
    ],
    "sg:phone":"+1 502 458 7067",
    "sg:postcode":"40205",
    "sg:province":"KY",
    "sg:tags":[
        "inspection"
    ],
    "wof:name":"Fidelity Property Group",
    "wof:placetype":"venue"
},
  "geometry": {"coordinates":[-85.702792,38.233155],"type":"Point"}
}