{
  "type": "Feature",
  "properties": {
    "iso:country":"US",
    "sg:address":"901 E Liberty St",
    "sg:city":"Louisville",
    "sg:classifiers":[
        {
            "category":"Manufacturing",
            "subcategory":"Signs",
            "type":"Manufacturing & Wholesale Goods"
        }
    ],
    "sg:phone":"+1 502 561 0007",
    "sg:postcode":"40204",
    "sg:province":"KY",
    "sg:website":"www.eaglesign.com",
    "wof:name":"Eagle Sign & Design",
    "wof:placetype":"venue"
},
  "geometry": {"coordinates":[-85.734481,38.250012],"type":"Point"}
}