{
  "type": "Feature",
  "properties": {
    "addr:full":"559 S Forbes Rd Lexington KY 40504",
    "addr:housenumber":"559",
    "addr:postcode":"40504",
    "addr:street":"S Forbes Rd",
    "iso:country":"US",
    "sg:address":"559 S Forbes Rd",
    "sg:city":"Lexington",
    "sg:classifiers":[
        {
            "category":"Manufacturing",
            "subcategory":"Food",
            "type":"Manufacturing & Wholesale Goods"
        }
    ],
    "sg:phone":"+1 859 255 3375",
    "sg:postcode":"40504",
    "sg:province":"KY",
    "sg:tags":[
        "bottler"
    ],
    "wof:name":"Pepsi-Cola Bottling Co",
    "wof:placetype":"venue"
},
  "geometry": {"coordinates":[-84.52342299999999,38.051407],"type":"Point"}
}