{
  "type": "Feature",
  "properties": {
    "iso:country":"US",
    "sg:address":"222 Main St",
    "sg:city":"Falmouth",
    "sg:classifiers":[
        {
            "category":"Personal",
            "subcategory":"Beauty Salon",
            "type":"Services"
        }
    ],
    "sg:phone":"+1 859 654 3845",
    "sg:postcode":"41040",
    "sg:province":"KY",
    "sg:tags":[
        "shop"
    ],
    "wof:name":"Ruby's Beauty Salon",
    "wof:placetype":"venue"
},
  "geometry": {"coordinates":[-84.32947900000001,38.677759],"type":"Point"}
}