{
  "type": "Feature",
  "properties": {
    "iso:country":"US",
    "sg:address":"1630 Lyndon Farm Ct",
    "sg:city":"Louisville",
    "sg:classifiers":[
        {
            "category":"Professional",
            "subcategory":"Management & Consulting",
            "type":"Services"
        }
    ],
    "sg:phone":"+1 502 992 8000",
    "sg:postcode":"40223",
    "sg:province":"KY",
    "sg:tags":[
        "marketing",
        "program"
    ],
    "sg:website":"www.cnet.com",
    "wof:name":"Cnet Networks",
    "wof:placetype":"venue"
},
  "geometry": {"coordinates":[-85.57214999999999,38.269596],"type":"Point"}
}