{
  "type": "Feature",
  "properties": {
    "addr:full":"319 Downing Ave Bowling Green KY 42101",
    "addr:housenumber":"319",
    "addr:postcode":"42101",
    "addr:street":"Downing Ave",
    "iso:country":"US",
    "sg:address":"319 Downing Ave",
    "sg:city":"Bowling Green",
    "sg:classifiers":[
        {
            "category":"Wholesale",
            "subcategory":"Durable Goods & Equipment",
            "type":"Manufacturing & Wholesale Goods"
        }
    ],
    "sg:phone":"+1 270 843 3373",
    "sg:postcode":"42101",
    "sg:province":"KY",
    "sg:tags":[
        "fire",
        "extinguisher"
    ],
    "wof:name":"F & S Fire Safety",
    "wof:placetype":"venue"
},
  "geometry": {"coordinates":[-86.497562,36.949856],"type":"Point"}
}