{
  "type": "Feature",
  "properties": {
    "iso:country":"US",
    "sg:address":"523 Eden Pl",
    "sg:city":"Ashland",
    "sg:classifiers":[
        {
            "category":"Restaurant",
            "type":"Food & Drink"
        }
    ],
    "sg:phone":"+1 606 324 1092",
    "sg:postcode":"41101",
    "sg:province":"KY",
    "sg:tags":[
        "eating"
    ],
    "wof:name":"My Moms Chili Inc",
    "wof:placetype":"venue"
},
  "geometry": {"coordinates":[-82.61664,38.450908],"type":"Point"}
}