{
  "type": "Feature",
  "properties": {
    "iso:country":"US",
    "sg:address":"2468 Grinstead Dr",
    "sg:city":"Louisville",
    "sg:phone":"+1 502 451 4224",
    "sg:postcode":"40204",
    "sg:province":"KY",
    "wof:name":"Maryanita Nursery School",
    "wof:placetype":"venue"
},
  "geometry": {"coordinates":[-85.707245,38.242933],"type":"Point"}
}