{
  "type": "Feature",
  "properties": {
    "iso:country":"US",
    "sg:address":"1885 Dixie Hwy",
    "sg:city":"Fort Wright",
    "sg:classifiers":[
        {
            "category":"Professional",
            "subcategory":"Accounting & Tax Preparation",
            "type":"Services"
        }
    ],
    "sg:phone":"+1 859 331 9400",
    "sg:postcode":"41011",
    "sg:province":"KY",
    "sg:tags":[
        "accountant"
    ],
    "wof:name":"Nancy R Keathley CPA",
    "wof:placetype":"venue"
},
  "geometry": {"coordinates":[-84.54339,39.057653],"type":"Point"}
}