{
  "type": "Feature",
  "properties": {
    "iso:country":"US",
    "sg:address":"2300 Plantside Dr",
    "sg:city":"Jeffersontown",
    "sg:classifiers":[
        {
            "category":"Building & Trades",
            "subcategory":"Construction",
            "type":"Services"
        }
    ],
    "sg:phone":"+1 502 491 9223",
    "sg:postcode":"40299",
    "sg:province":"KY",
    "sg:tags":[
        "fire",
        "restoration",
        "damage"
    ],
    "wof:name":"Bob Wells Co",
    "wof:placetype":"venue"
},
  "geometry": {"coordinates":[-85.56573,38.210229],"type":"Point"}
}