{
  "type": "Feature",
  "properties": {
    "iso:country":"US",
    "sg:address":"6060 Dutchmans Ln",
    "sg:city":"Louisville",
    "sg:classifiers":[
        {
            "category":"Professional",
            "subcategory":"Management & Consulting",
            "type":"Services"
        }
    ],
    "sg:phone":"+1 502 458 0691",
    "sg:postcode":"40205",
    "sg:province":"KY",
    "sg:tags":[
        "investment",
        "closed"
    ],
    "wof:name":"American Express",
    "wof:placetype":"venue"
},
  "geometry": {"coordinates":[-85.64060600000001,38.228251],"type":"Point"}
}