{
  "type": "Feature",
  "properties": {
    "iso:country":"US",
    "sg:address":"2011 Alverson Dr",
    "sg:city":"Paris",
    "sg:classifiers":[
        {
            "category":"Travel",
            "subcategory":"Hotels & Motels",
            "type":"Entertainment"
        }
    ],
    "sg:phone":"+1 877 574 2464",
    "sg:postcode":"40361",
    "sg:province":"KY",
    "sg:website":"http://book.bestwestern.com/bestwestern/priceAvail.do?propertyCode=18091&cm_mmc=IYP-_-YP-_-property-_-18091",
    "wof:name":"Best Western Paris Inn",
    "wof:placetype":"venue"
},
  "geometry": {"coordinates":[-84.275245,38.203281],"type":"Point"}
}