{
  "type": "Feature",
  "properties": {
    "iso:country":"US",
    "sg:address":"7911 Mall Rd",
    "sg:city":"Florence",
    "sg:classifiers":[
        {
            "category":"Shopping",
            "subcategory":"Mobile Phones",
            "type":"Retail Goods"
        }
    ],
    "sg:phone":"+1 859 371 3444",
    "sg:postcode":"41042",
    "sg:province":"KY",
    "sg:website":"www.bellsouth.com",
    "wof:name":"A T & T Mobility",
    "wof:placetype":"venue"
},
  "geometry": {"coordinates":[-84.651763,38.991291],"type":"Point"}
}