{
  "type": "Feature",
  "properties": {
    "iso:country":"US",
    "sg:address":"711 Lyndon Ln",
    "sg:city":"Louisville",
    "sg:classifiers":[
        {
            "category":"Personal",
            "type":"Services"
        }
    ],
    "sg:phone":"+1 502 425 1869",
    "sg:postcode":"40222",
    "sg:province":"KY",
    "sg:tags":[
        "shop",
        "beauty"
    ],
    "wof:name":"Great Lengths",
    "wof:placetype":"venue"
},
  "geometry": {"coordinates":[-85.603837,38.258785],"type":"Point"}
}