{
  "type": "Feature",
  "properties": {
    "iso:country":"US",
    "sg:address":"3913 Buechel Bank Rd",
    "sg:city":"Louisville",
    "sg:classifiers":[
        {
            "category":"Social Services",
            "subcategory":"Child Care",
            "type":"Services"
        }
    ],
    "sg:phone":"+1 502 456 2820",
    "sg:postcode":"40218",
    "sg:province":"KY",
    "wof:name":"Kids At Play Development Ctr",
    "wof:placetype":"venue"
},
  "geometry": {"coordinates":[-85.65779000000001,38.178528],"type":"Point"}
}