{
  "type": "Feature",
  "properties": {
    "iso:country":"US",
    "sg:address":"273 Dover Rd",
    "sg:city":"Clarksville",
    "sg:classifiers":[
        {
            "category":"Health Services",
            "subcategory":"Doctor",
            "type":"Services"
        }
    ],
    "sg:phone":"+1 931 503 9007",
    "sg:postcode":"37042",
    "sg:province":"KY",
    "sg:tags":[
        "physician",
        "surgeon"
    ],
    "wof:name":"Cumberland Surgical",
    "wof:placetype":"venue"
},
  "geometry": {"coordinates":[-87.39946,36.55068],"type":"Point"}
}