{
  "type": "Feature",
  "properties": {
    "iso:country":"US",
    "sg:address":"202 Cardinal Ln",
    "sg:city":"Princeton",
    "sg:classifiers":[
        {
            "category":"Organizations",
            "subcategory":"Religious Organization",
            "type":"Services"
        }
    ],
    "sg:phone":"+1 270 365 6497",
    "sg:postcode":"42445",
    "sg:province":"KY",
    "sg:tags":[
        "church"
    ],
    "wof:name":"Trinity United Methodist Ch",
    "wof:placetype":"venue"
},
  "geometry": {"coordinates":[-87.893457,37.118209],"type":"Point"}
}