{
  "type": "Feature",
  "properties": {
    "iso:country":"US",
    "sg:address":"41 Highland Ave",
    "sg:city":"Fort Thomas",
    "sg:classifiers":[
        {
            "category":"Real Estate",
            "subcategory":"Real Estate Agent",
            "type":"Services"
        }
    ],
    "sg:phone":"+1 859 572 9567",
    "sg:postcode":"41075",
    "sg:province":"KY",
    "wof:name":"Surrett Appraisal Services LLC",
    "wof:placetype":"venue"
},
  "geometry": {"coordinates":[-84.44871500000001,39.078592],"type":"Point"}
}