{
  "type": "Feature",
  "properties": {
    "addr:full":"7519 Preston Hwy Louisville KY 40219",
    "addr:housenumber":"7519",
    "addr:postcode":"40219",
    "addr:street":"Preston Hwy",
    "iso:country":"US",
    "sg:address":"7519 Preston Hwy",
    "sg:city":"Louisville",
    "sg:classifiers":[
        {
            "category":"Autos & Motor Vehicles",
            "subcategory":"Automobile Sales",
            "type":"Retail Goods"
        }
    ],
    "sg:phone":"+1 502 961 0814",
    "sg:postcode":"40219",
    "sg:province":"KY",
    "sg:tags":[
        "car",
        "dealer"
    ],
    "wof:name":"Noel's Auto Sales",
    "wof:placetype":"venue"
},
  "geometry": {"coordinates":[-85.688519,38.141857],"type":"Point"}
}