{
  "type": "Feature",
  "properties": {
    "iso:country":"US",
    "sg:address":"2315 Mayfair Ave",
    "sg:city":"Owensboro",
    "sg:classifiers":[
        {
            "category":"Health Services",
            "subcategory":"Doctor",
            "type":"Services"
        }
    ],
    "sg:phone":"+1 270 684 6255",
    "sg:postcode":"42301",
    "sg:province":"KY",
    "sg:tags":[
        "physician",
        "surgeon"
    ],
    "wof:name":"Ward & Polio",
    "wof:placetype":"venue"
},
  "geometry": {"coordinates":[-87.12290299999999,37.75148],"type":"Point"}
}