{
  "type": "Feature",
  "properties": {
    "addr:full":"116 W Public Sq Scottsville KY 42141",
    "addr:housenumber":"116",
    "addr:postcode":"42141",
    "addr:street":"W Public Sq",
    "iso:country":"US",
    "sg:address":"116 W Public Sq",
    "sg:city":"Scottsville",
    "sg:classifiers":[
        {
            "category":"Education",
            "subcategory":"College",
            "type":"Public Place"
        }
    ],
    "sg:phone":"+1 270 237 9136",
    "sg:postcode":"42141",
    "sg:province":"KY",
    "sg:tags":[
        "academic",
        "school"
    ],
    "wof:name":"Lindsey Wilson College",
    "wof:placetype":"venue"
},
  "geometry": {"coordinates":[-85.912834,36.996232],"type":"Point"}
}