{
  "type": "Feature",
  "properties": {
    "addr:full":"1500 Envoy Circle, Suite 1504 Louisville KY 40299",
    "addr:housenumber":"1500",
    "addr:postcode":"40299",
    "addr:street":"Envoy Circle Suite 1504",
    "iso:country":"US",
    "sg:address":"1500 Envoy Circle, Suite 1504",
    "sg:city":"Louisville",
    "sg:classifiers":[
        {
            "category":"Professional",
            "subcategory":"Lawyer & Legal Services",
            "type":"Services"
        }
    ],
    "sg:phone":"+1 502 413 5246",
    "sg:postcode":"40299",
    "sg:province":"KY",
    "sg:tags":[
        "attorney",
        "law",
        "personal",
        "tax",
        "injury",
        "bankruptcy"
    ],
    "wof:name":"Kain, Taylor--Taylor Kain Law Office",
    "wof:placetype":"venue"
},
  "geometry": {"coordinates":[-85.57755299999999,38.215172],"type":"Point"}
}