{
  "type": "Feature",
  "properties": {
    "iso:country":"US",
    "sg:address":"1108 N Main St",
    "sg:city":"Hopkinsville",
    "sg:classifiers":[
        {
            "category":"Home & Garden",
            "subcategory":"Garden Supply",
            "type":"Retail Goods"
        }
    ],
    "sg:phone":"+1 270 885 4769",
    "sg:postcode":"42240",
    "sg:province":"KY",
    "sg:tags":[
        "center"
    ],
    "wof:name":"Superlawn",
    "wof:placetype":"venue"
},
  "geometry": {"coordinates":[-87.48119699999999,36.888434],"type":"Point"}
}