{
  "type": "Feature",
  "properties": {
    "iso:country":"US",
    "sg:address":"429 S 3rd St",
    "sg:city":"Williamsburg",
    "sg:classifiers":[
        {
            "category":"Organizations",
            "subcategory":"Religious Organization",
            "type":"Services"
        }
    ],
    "sg:phone":"+1 606 549 4424",
    "sg:postcode":"40769",
    "sg:province":"KY",
    "sg:tags":[
        "monastery",
        "convent"
    ],
    "wof:name":"School Sisters Of St Francis",
    "wof:placetype":"venue"
},
  "geometry": {"coordinates":[-84.15639299999999,36.738678],"type":"Point"}
}