{
  "type": "Feature",
  "properties": {
    "iso:country":"US",
    "sg:address":"4416 Hartland Pkwy",
    "sg:city":"Lexington",
    "sg:classifiers":[
        {
            "category":"Home & Garden",
            "subcategory":"Carpets & Floor Coverings",
            "type":"Retail Goods"
        }
    ],
    "sg:phone":"+1 859 245 7718",
    "sg:postcode":"40515",
    "sg:province":"KY",
    "sg:tags":[
        "dealer",
        "rug"
    ],
    "wof:name":"West Distributing Co",
    "wof:placetype":"venue"
},
  "geometry": {"coordinates":[-84.49350200000001,37.963262],"type":"Point"}
}