{
  "type": "Feature",
  "properties": {
    "iso:country":"US",
    "sg:address":"165 S Forrest Rd",
    "sg:city":"Radcliff",
    "sg:classifiers":[
        {
            "category":"Building & Trades",
            "subcategory":"Plumbing",
            "type":"Services"
        }
    ],
    "sg:phone":"+1 270 877 2225",
    "sg:postcode":"40160",
    "sg:province":"KY",
    "sg:tags":[
        "plumbing",
        "contractor"
    ],
    "wof:name":"Fisher Drain Cleaning Svc",
    "wof:placetype":"venue"
},
  "geometry": {"coordinates":[-85.951784,37.834933],"type":"Point"}
}