{
  "type": "Feature",
  "properties": {
    "iso:country":"US",
    "sg:address":"11519 Shelbyville Rd",
    "sg:city":"Louisville",
    "sg:classifiers":[
        {
            "category":"Shopping",
            "subcategory":"Musical Instruments",
            "type":"Retail Goods"
        }
    ],
    "sg:phone":"+1 502 254 1444",
    "sg:postcode":"40243",
    "sg:province":"KY",
    "sg:tags":[
        "piano"
    ],
    "wof:name":"Henderson Music Co",
    "wof:placetype":"venue"
},
  "geometry": {"coordinates":[-85.54271300000001,38.245602],"type":"Point"}
}