{
  "type": "Feature",
  "properties": {
    "addr:full":"1007 Twilight Trl Frankfort KY 40601",
    "addr:housenumber":"1007",
    "addr:postcode":"40601",
    "addr:street":"Twilight Trl;Ky",
    "iso:country":"US",
    "sg:address":"1007 Twilight Trl",
    "sg:city":"Frankfort",
    "sg:classifiers":[
        {
            "category":"Autos & Motor Vehicles",
            "subcategory":"Fuel & Gas Station",
            "type":"Retail Goods"
        }
    ],
    "sg:phone":"+1 502 223 5992",
    "sg:postcode":"40601",
    "sg:province":"KY",
    "sg:tags":[
        "oil"
    ],
    "wof:name":"Speedway",
    "wof:placetype":"venue"
},
  "geometry": {"coordinates":[-84.895055,38.155267],"type":"Point"}
}