{
  "type": "Feature",
  "properties": {
    "addr:full":"404 Bohon Rd Harrodsburg KY 40330",
    "addr:housenumber":"404",
    "addr:postcode":"40330",
    "addr:street":"Bohon Rd",
    "iso:country":"US",
    "sg:address":"404 Bohon Rd",
    "sg:city":"Harrodsburg",
    "sg:classifiers":[
        {
            "category":"Organizations",
            "subcategory":"Religious Organization",
            "type":"Services"
        }
    ],
    "sg:phone":"+1 859 734 4862",
    "sg:postcode":"40330",
    "sg:province":"KY",
    "wof:name":"Kingdom Hall",
    "wof:placetype":"venue"
},
  "geometry": {"coordinates":[-84.850944,37.783927],"type":"Point"}
}