{
  "type": "Feature",
  "properties": {
    "iso:country":"US",
    "sg:address":"5001 Mount Horeb Pike",
    "sg:city":"Lexington",
    "sg:classifiers":[
        {
            "category":"Building & Trades",
            "subcategory":"Plumbing",
            "type":"Services"
        }
    ],
    "sg:phone":"+1 859 255 7951",
    "sg:postcode":"40511",
    "sg:province":"KY",
    "sg:tags":[
        "mechanical",
        "contractor"
    ],
    "wof:name":"Paul S Ogle & Co",
    "wof:placetype":"venue"
},
  "geometry": {"coordinates":[-84.465903,38.172764],"type":"Point"}
}