{
  "type": "Feature",
  "properties": {
    "addr:full":"411 State Hwy 610 W Virgie KY 41572",
    "addr:housenumber":"411",
    "addr:postcode":"41572",
    "addr:street":"State Hwy 610 W Virgie",
    "iso:country":"US",
    "sg:address":"411 State Hwy 610 W",
    "sg:city":"Virgie",
    "sg:classifiers":[
        {
            "category":"Cinema",
            "subcategory":"Movie Rental",
            "type":"Entertainment"
        }
    ],
    "sg:phone":"+1 606 639 0749",
    "sg:postcode":"41572",
    "sg:province":"KY",
    "sg:tags":[
        "video",
        "game",
        "leasing"
    ],
    "wof:name":"Shawne's Update Videos",
    "wof:placetype":"venue"
},
  "geometry": {"coordinates":[-82.592788,37.342404],"type":"Point"}
}