{
  "type": "Feature",
  "properties": {
    "addr:full":"1607 Dixie Hwy Louisville KY 40210",
    "addr:housenumber":"1607",
    "addr:postcode":"40210",
    "addr:street":"Dixie Hwy",
    "iso:country":"US",
    "sg:address":"1607 Dixie Hwy",
    "sg:city":"Louisville",
    "sg:classifiers":[
        {
            "category":"Health Services",
            "subcategory":"Doctor",
            "type":"Services"
        }
    ],
    "sg:phone":"+1 502 772 1822",
    "sg:postcode":"40210",
    "sg:province":"KY",
    "sg:tags":[
        "physician",
        "surgeon"
    ],
    "wof:name":"Chaisak Pengvanich MD",
    "wof:placetype":"venue"
},
  "geometry": {"coordinates":[-85.790993,38.226774],"type":"Point"}
}