{
  "type": "Feature",
  "properties": {
    "iso:country":"US",
    "sg:address":"470 E New Circle Rd",
    "sg:city":"Lexington",
    "sg:classifiers":[
        {
            "category":"Insurance",
            "subcategory":"Insurance Agent",
            "type":"Services"
        }
    ],
    "sg:phone":"+1 859 254 7755",
    "sg:postcode":"40505",
    "sg:province":"KY",
    "wof:name":"Van King",
    "wof:placetype":"venue"
},
  "geometry": {"coordinates":[-84.457195,38.051952],"type":"Point"}
}