{
  "type": "Feature",
  "properties": {
    "iso:country":"US",
    "sg:address":"2120 Frederica St",
    "sg:city":"Owensboro",
    "sg:classifiers":[
        {
            "category":"Insurance",
            "subcategory":"Insurance Agent",
            "type":"Services"
        }
    ],
    "sg:phone":"+1 270 926 2371",
    "sg:postcode":"42301",
    "sg:province":"KY",
    "wof:name":"Kentucky Insurance Co",
    "wof:placetype":"venue"
},
  "geometry": {"coordinates":[-87.111644,37.754576],"type":"Point"}
}