{
  "type": "Feature",
  "properties": {
    "iso:country":"US",
    "sg:address":"1889 US Hwy 641 N",
    "sg:city":"Benton",
    "sg:classifiers":[
        {
            "category":"Building & Trades",
            "subcategory":"Construction",
            "type":"Services"
        }
    ],
    "sg:phone":"+1 270 527 1470",
    "sg:postcode":"42025",
    "sg:province":"KY",
    "sg:tags":[
        "tile",
        "dealer"
    ],
    "wof:name":"Clark Tile Installation",
    "wof:placetype":"venue"
},
  "geometry": {"coordinates":[-88.341341,36.906643],"type":"Point"}
}