{
  "type": "Feature",
  "properties": {
    "addr:full":"504 George McClain Dr Benton KY 42025",
    "addr:housenumber":"504",
    "addr:postcode":"42025",
    "addr:street":"George Mcclain Dr",
    "iso:country":"US",
    "sg:address":"504 George McClain Dr",
    "sg:city":"Benton",
    "sg:classifiers":[
        {
            "category":"Shopping",
            "subcategory":"Pharmacy",
            "type":"Retail Goods"
        }
    ],
    "sg:phone":"+1 270 527 9374",
    "sg:postcode":"42025",
    "sg:province":"KY",
    "wof:name":"J & R Pharmacy",
    "wof:placetype":"venue"
},
  "geometry": {"coordinates":[-88.345322,36.859632],"type":"Point"}
}