{
  "type": "Feature",
  "properties": {
    "addr:full":"480 Marvin Powell Rd Elkton KY 42220",
    "addr:housenumber":"480",
    "addr:postcode":"42220",
    "addr:street":"Marvin Powell Rd",
    "iso:country":"US",
    "sg:address":"480 Marvin Powell Rd",
    "sg:city":"Elkton",
    "sg:classifiers":[
        {
            "category":"Professional",
            "subcategory":"Management & Consulting",
            "type":"Services"
        }
    ],
    "sg:phone":"+1 270 265 2224",
    "sg:postcode":"42220",
    "sg:province":"KY",
    "sg:tags":[
        "retail",
        "direct",
        "sales"
    ],
    "wof:name":"Amandas Avon",
    "wof:placetype":"venue"
},
  "geometry": {"coordinates":[-87.218266,36.964005],"type":"Point"}
}