{
  "type": "Feature",
  "properties": {
    "iso:country":"US",
    "sg:address":"93 Lebanon St",
    "sg:city":"Wingo",
    "sg:classifiers":[
        {
            "category":"Government",
            "subcategory":"Post Office",
            "type":"Public Place"
        }
    ],
    "sg:phone":"+1 270 376 2339",
    "sg:postcode":"42088",
    "sg:province":"KY",
    "wof:name":"US Post Office",
    "wof:placetype":"venue"
},
  "geometry": {"coordinates":[-88.73663999999999,36.641904],"type":"Point"}
}