{
  "type": "Feature",
  "properties": {
    "iso:country":"US",
    "sg:address":"2531 Bank St",
    "sg:city":"Louisville",
    "sg:classifiers":[
        {
            "category":"Shopping",
            "subcategory":"Florist",
            "type":"Retail Goods"
        }
    ],
    "sg:phone":"+1 502 772 3649",
    "sg:postcode":"40212",
    "sg:province":"KY",
    "wof:name":"Mathis Florist LLC",
    "wof:placetype":"venue"
},
  "geometry": {"coordinates":[-85.790446,38.269164],"type":"Point"}
}