{
  "type": "Feature",
  "properties": {
    "iso:country":"US",
    "sg:address":"720 W Broadway",
    "sg:city":"Louisville",
    "sg:classifiers":[
        {
            "category":"Health Services",
            "subcategory":"Hospital",
            "type":"Services"
        }
    ],
    "sg:phone":"+1 502 584 2059",
    "sg:postcode":"40202",
    "sg:province":"KY",
    "sg:tags":[
        "dialysis"
    ],
    "sg:website":"http://www.davita.com",
    "wof:name":"Davita West Broadway",
    "wof:placetype":"venue"
},
  "geometry": {"coordinates":[-85.763724,38.246488],"type":"Point"}
}