{
  "type": "Feature",
  "properties": {
    "iso:country":"US",
    "sg:address":"184 N Martin Luther King Blvd",
    "sg:city":"Lexington",
    "sg:classifiers":[
        {
            "category":"Wholesale",
            "subcategory":"Office Equipment",
            "type":"Manufacturing & Wholesale Goods"
        },
        {
            "category":"Professional",
            "subcategory":"Business Services",
            "type":"Services"
        },
        {
            "category":"Professional",
            "subcategory":"Printing & Photocopies",
            "type":"Services"
        },
        {
            "category":"Shopping",
            "subcategory":"Computers & Home Electronics",
            "type":"Retail Goods"
        }
    ],
    "sg:phone":"+1 859 252 5635",
    "sg:postcode":"40507",
    "sg:province":"KY",
    "sg:tags":[
        "scanning",
        "printer",
        "supply",
        "services-commercial",
        "shipping",
        "mail",
        "plotting"
    ],
    "wof:name":"Feeback Printing & Mailing Service, Inc",
    "wof:placetype":"venue"
},
  "geometry": {"coordinates":[-84.49240899999999,38.046921],"type":"Point"}
}