{
  "type": "Feature",
  "properties": {
    "addr:full":"6088 Gold City Rd Franklin KY 42134",
    "addr:housenumber":"6088",
    "addr:postcode":"42134",
    "addr:street":"Gold City Rd",
    "iso:country":"US",
    "sg:address":"6088 Gold City Rd",
    "sg:city":"Franklin",
    "sg:phone":"+1 270 586 3964",
    "sg:postcode":"42134",
    "sg:province":"KY",
    "sg:tags":[
        "farm",
        "tobacco"
    ],
    "wof:name":"Johnie Cline",
    "wof:placetype":"venue"
},
  "geometry": {"coordinates":[-86.430553,36.754565],"type":"Point"}
}