{
  "type": "Feature",
  "properties": {
    "iso:country":"US",
    "sg:address":"10936 Dixie Hwy",
    "sg:city":"Valley Station",
    "sg:classifiers":[
        {
            "category":"Social Services",
            "subcategory":"Adult Care",
            "type":"Services"
        }
    ],
    "sg:phone":"+1 502 995 4402",
    "sg:postcode":"40272",
    "sg:province":"KY",
    "sg:tags":[
        "foster"
    ],
    "wof:name":"Therapeutic Foster Care Progrm",
    "wof:placetype":"venue"
},
  "geometry": {"coordinates":[-85.87595399999999,38.09207],"type":"Point"}
}