{
  "type": "Feature",
  "properties": {
    "iso:country":"US",
    "sg:address":"8755 Heritage Dr",
    "sg:city":"Florence",
    "sg:classifiers":[
        {
            "category":"Professional",
            "subcategory":"Business Services",
            "type":"Services"
        }
    ],
    "sg:phone":"+1 859 371 3621",
    "sg:postcode":"41042",
    "sg:province":"KY",
    "wof:name":"Ckm Enterprises Inc",
    "wof:placetype":"venue"
},
  "geometry": {"coordinates":[-84.666948,38.980024],"type":"Point"}
}