{
  "type": "Feature",
  "properties": {
    "iso:country":"US",
    "sg:address":"806 Mammoth Cave Rd",
    "sg:city":"Cave City",
    "sg:classifiers":[
        {
            "category":"Recreation",
            "type":"Entertainment"
        }
    ],
    "sg:phone":"+1 270 773 5056",
    "sg:postcode":"42127",
    "sg:province":"KY",
    "sg:tags":[
        "parlor",
        "billiard"
    ],
    "wof:name":"Rack & Cue Pool Room",
    "wof:placetype":"venue"
},
  "geometry": {"coordinates":[-85.98537,37.135708],"type":"Point"}
}