{
  "type": "Feature",
  "properties": {
    "iso:country":"US",
    "sg:address":"1198 National Tpke",
    "sg:city":"Munfordville",
    "sg:classifiers":[
        {
            "category":"Restaurant",
            "type":"Food & Drink"
        }
    ],
    "sg:menulink":"http://www.allmenus.com/ky/munfordville/79660-pizza-hut/menu/",
    "sg:phone":"+1 270 524 4488",
    "sg:postcode":"42765",
    "sg:province":"KY",
    "sg:tags":[
        "american",
        "pizza"
    ],
    "wof:name":"Pizza Hut",
    "wof:placetype":"venue"
},
  "geometry": {"coordinates":[-85.90183399999999,37.287916],"type":"Point"}
}