{
  "type": "Feature",
  "properties": {
    "addr:full":"3251 Nashville Rd Bowling Green KY 42101",
    "addr:housenumber":"3251",
    "addr:postcode":"42101",
    "addr:street":"Nashville Rd",
    "iso:country":"US",
    "sg:address":"3251 Nashville Rd",
    "sg:city":"Bowling Green",
    "sg:classifiers":[
        {
            "category":"Professional",
            "type":"Services"
        }
    ],
    "sg:phone":"+1 270 842 9532",
    "sg:postcode":"42101",
    "sg:province":"KY",
    "sg:tags":[
        "establishment"
    ],
    "wof:name":"NHK Associated",
    "wof:placetype":"venue"
},
  "geometry": {"coordinates":[-86.477442,36.949295],"type":"Point"}
}