{
  "type": "Feature",
  "properties": {
    "addr:full":"4832 Cane Run Rd Shively KY 40216",
    "addr:housenumber":"4832",
    "addr:postcode":"40216",
    "addr:street":"Cane Run Rd",
    "iso:country":"US",
    "sg:address":"4832 Cane Run Rd",
    "sg:city":"Shively",
    "sg:classifiers":[
        {
            "category":"Wholesale",
            "subcategory":"Machinery & Supplies",
            "type":"Manufacturing & Wholesale Goods"
        }
    ],
    "sg:phone":"+1 502 447 7114",
    "sg:postcode":"40216",
    "sg:province":"KY",
    "sg:tags":[
        "casket"
    ],
    "wof:name":"J B Ratterman & Sons",
    "wof:placetype":"venue"
},
  "geometry": {"coordinates":[-85.858396,38.180948],"type":"Point"}
}