{
  "type": "Feature",
  "properties": {
    "iso:country":"US",
    "sg:address":"317 Roland St",
    "sg:city":"Louisville",
    "sg:classifiers":[
        {
            "category":"Building & Trades",
            "subcategory":"Construction",
            "type":"Services"
        }
    ],
    "sg:phone":"+1 502 584 7151",
    "sg:postcode":"40203",
    "sg:province":"KY",
    "sg:tags":[
        "maker",
        "cabinet"
    ],
    "wof:name":"Cornerstone Cabinetry LLC",
    "wof:placetype":"venue"
},
  "geometry": {"coordinates":[-85.749264,38.236923],"type":"Point"}
}