{
  "type": "Feature",
  "properties": {
    "iso:country":"US",
    "sg:address":"1728 Gagel Ave",
    "sg:city":"Louisville",
    "sg:classifiers":[
        {
            "category":"Banks & Credit Unions",
            "subcategory":"Investment Brokerage",
            "type":"Services"
        }
    ],
    "sg:phone":"+1 502 448 7998",
    "sg:postcode":"40216",
    "sg:province":"KY",
    "sg:tags":[
        "stock",
        "bond"
    ],
    "wof:name":"Raymond James Financial Svc",
    "wof:placetype":"venue"
},
  "geometry": {"coordinates":[-85.821197,38.175399],"type":"Point"}
}