{
  "type": "Feature",
  "properties": {
    "iso:country":"US",
    "sg:address":"108 Fairmeade Rd",
    "sg:city":"Louisville",
    "sg:classifiers":[
        {
            "category":"Shopping",
            "subcategory":"Hobbies, Toys, & Games",
            "type":"Retail Goods"
        }
    ],
    "sg:phone":"+1 502 894 0337",
    "sg:postcode":"40207",
    "sg:province":"KY",
    "sg:tags":[
        "craft",
        "supply"
    ],
    "sg:website":"www.rubberwizard.com",
    "wof:name":"Rubber Wizard Inc",
    "wof:placetype":"venue"
},
  "geometry": {"coordinates":[-85.636404,38.250645],"type":"Point"}
}