{
  "type": "Feature",
  "properties": {
    "addr:full":"3517 Cane Run Rd Louisville KY 40211",
    "addr:housenumber":"3517",
    "addr:postcode":"40211",
    "addr:street":"Cane Run Rd",
    "iso:country":"US",
    "sg:address":"3517 Cane Run Rd",
    "sg:city":"Louisville",
    "sg:classifiers":[
        {
            "category":"Shopping",
            "subcategory":"Department Store",
            "type":"Retail Goods"
        }
    ],
    "sg:phone":"+1 502 776 6115",
    "sg:postcode":"40211",
    "sg:province":"KY",
    "sg:tags":[
        "shop",
        "discount"
    ],
    "sg:website":"http://www.dollargeneral.com",
    "wof:name":"Dollar General",
    "wof:placetype":"venue"
},
  "geometry": {"coordinates":[-85.81139400000001,38.222214],"type":"Point"}
}