{
  "type": "Feature",
  "properties": {
    "iso:country":"US",
    "sg:address":"138 E Loudon Ave",
    "sg:city":"Lexington",
    "sg:classifiers":[
        {
            "category":"Home & Garden",
            "subcategory":"Home Furnishings",
            "type":"Retail Goods"
        }
    ],
    "sg:phone":"+1 859 252 0441",
    "sg:postcode":"40505",
    "sg:province":"KY",
    "sg:tags":[
        "fireplace"
    ],
    "wof:name":"Wood Energy Warehouse",
    "wof:placetype":"venue"
},
  "geometry": {"coordinates":[-84.479022,38.054926],"type":"Point"}
}