{
  "type": "Feature",
  "properties": {
    "iso:country":"US",
    "sg:address":"126 Lynwood Dr",
    "sg:city":"Paducah",
    "sg:classifiers":[
        {
            "category":"Local Transit",
            "type":"Transportation"
        }
    ],
    "sg:phone":"+1 270 443 6529",
    "sg:postcode":"42003",
    "sg:province":"KY",
    "sg:tags":[
        "ambulance"
    ],
    "wof:name":"Angels of Mercy Medical Supply",
    "wof:placetype":"venue"
},
  "geometry": {"coordinates":[-88.53312200000001,37.018754],"type":"Point"}
}