{
  "type": "Feature",
  "properties": {
    "iso:country":"US",
    "sg:address":"1901 Williamson Ct",
    "sg:city":"Louisville",
    "sg:classifiers":[
        {
            "category":"Building & Trades",
            "subcategory":"Landscaping Services",
            "type":"Services"
        }
    ],
    "sg:phone":"+1 502 244 8770",
    "sg:postcode":"40223",
    "sg:province":"KY",
    "sg:tags":[
        "tree"
    ],
    "wof:name":"Greenhaven Tree Care Inc",
    "wof:placetype":"venue"
},
  "geometry": {"coordinates":[-85.505083,38.270755],"type":"Point"}
}