{
  "type": "Feature",
  "properties": {
    "iso:country":"US",
    "sg:address":"533 Lone Oak Rd",
    "sg:city":"Paducah",
    "sg:classifiers":[
        {
            "category":"Home & Garden",
            "subcategory":"Furniture",
            "type":"Retail Goods"
        }
    ],
    "sg:phone":"+1 270 443 9108",
    "sg:postcode":"42003",
    "sg:province":"KY",
    "wof:name":"Furniture World Galleries",
    "wof:placetype":"venue"
},
  "geometry": {"coordinates":[-88.638638,37.063545],"type":"Point"}
}