{
  "type": "Feature",
  "properties": {
    "iso:country":"US",
    "sg:address":"2012 Terrace Ct",
    "sg:city":"Florence",
    "sg:classifiers":[
        {
            "category":"Social Services",
            "subcategory":"Child Care",
            "type":"Services"
        }
    ],
    "sg:phone":"+1 859 384 8932",
    "sg:postcode":"41042",
    "sg:province":"KY",
    "sg:tags":[
        "day"
    ],
    "wof:name":"Abby's Child Enrichment Cntr",
    "wof:placetype":"venue"
},
  "geometry": {"coordinates":[-84.678387,38.966777],"type":"Point"}
}