{
  "type": "Feature",
  "properties": {
    "iso:country":"US",
    "sg:address":"50 Osage Trl",
    "sg:city":"Louisville",
    "sg:classifiers":[
        {
            "category":"Professional",
            "subcategory":"Computer Services",
            "type":"Services"
        }
    ],
    "sg:phone":"+1 502 241 2022",
    "sg:postcode":"40245",
    "sg:province":"KY",
    "sg:tags":[
        "consultant",
        "designer"
    ],
    "wof:name":"David & Goliath Computer",
    "wof:placetype":"venue"
},
  "geometry": {"coordinates":[-85.434164,38.294311],"type":"Point"}
}