{
  "type": "Feature",
  "properties": {
    "addr:full":"9921 Ormsby Station Rd Louisville KY 40223",
    "addr:housenumber":"9921",
    "addr:postcode":"40223",
    "addr:street":"Ormsby Station Rd",
    "iso:country":"US",
    "sg:address":"9921 Ormsby Station Rd",
    "sg:city":"Louisville",
    "sg:classifiers":[
        {
            "category":"Restaurant",
            "type":"Food & Drink"
        }
    ],
    "sg:menulink":"http://www.allmenus.com/ky/jefferson-northeast/88647-applebees/menu/",
    "sg:phone":"+1 502 429 8300",
    "sg:postcode":"40223",
    "sg:province":"KY",
    "sg:tags":[
        "burger",
        "american",
        "sandwich",
        "soup"
    ],
    "wof:name":"Applebee's",
    "wof:placetype":"venue"
},
  "geometry": {"coordinates":[-85.57538599999999,38.263731],"type":"Point"}
}