{
  "type": "Feature",
  "properties": {
    "addr:full":"14362 US Hwy 42 Verona KY 41092",
    "addr:housenumber":"14362",
    "addr:postcode":"41092",
    "addr:street":"Us Hwy 42",
    "iso:country":"US",
    "sg:address":"14362 US Hwy 42",
    "sg:city":"Verona",
    "sg:classifiers":[
        {
            "category":"Building & Trades",
            "subcategory":"Plumbing",
            "type":"Services"
        }
    ],
    "sg:phone":"+1 859 485 6500",
    "sg:postcode":"41092",
    "sg:province":"KY",
    "sg:tags":[
        "conditioning",
        "air",
        "system",
        "contractor"
    ],
    "wof:name":"Bogard's Heating & Cooling",
    "wof:placetype":"venue"
},
  "geometry": {"coordinates":[-84.730225,38.842253],"type":"Point"}
}