{
  "type": "Feature",
  "properties": {
    "addr:full":"2228 Lawrence Rd Olmstead KY 42265",
    "addr:housenumber":"2228",
    "addr:postcode":"42265",
    "addr:street":"Lawrence Rd",
    "iso:country":"US",
    "sg:address":"2228 Lawrence Rd",
    "sg:city":"Olmstead",
    "sg:classifiers":[
        {
            "category":"Building & Trades",
            "subcategory":"Construction",
            "type":"Services"
        }
    ],
    "sg:phone":"+1 270 539 3175",
    "sg:postcode":"42265",
    "sg:province":"KY",
    "sg:tags":[
        "home",
        "improvement"
    ],
    "wof:name":"Farmer's Home Improvement",
    "wof:placetype":"venue"
},
  "geometry": {"coordinates":[-86.990336,36.686788],"type":"Point"}
}