{
  "type": "Feature",
  "properties": {
    "iso:country":"US",
    "sg:address":"6500 Maravian Dr",
    "sg:city":"Louisville",
    "sg:classifiers":[
        {
            "category":"Building & Trades",
            "subcategory":"Construction",
            "type":"Services"
        }
    ],
    "sg:phone":"+1 502 447 8910",
    "sg:postcode":"40258",
    "sg:province":"KY",
    "sg:tags":[
        "material",
        "contractor"
    ],
    "wof:name":"Counter Tops By Design",
    "wof:placetype":"venue"
},
  "geometry": {"coordinates":[-85.87777800000001,38.164733],"type":"Point"}
}