{
  "type": "Feature",
  "properties": {
    "addr:full":"3037 Adwalton Rd Lexington KY 40509",
    "addr:housenumber":"3037",
    "addr:postcode":"40509",
    "addr:street":"Adwalton Rd",
    "iso:country":"US",
    "sg:address":"3037 Adwalton Rd",
    "sg:city":"Lexington",
    "sg:classifiers":[
        {
            "category":"Building & Trades",
            "subcategory":"Construction",
            "type":"Services"
        }
    ],
    "sg:phone":"+1 859 294 0221",
    "sg:postcode":"40509",
    "sg:province":"KY",
    "sg:tags":[
        "general",
        "contractor"
    ],
    "wof:name":"Stuart Construction Co Inc",
    "wof:placetype":"venue"
},
  "geometry": {"coordinates":[-84.408006,38.019453],"type":"Point"}
}