{
  "type": "Feature",
  "properties": {
    "addr:full":"1610 Curd Rd Hardin KY 42048",
    "addr:housenumber":"1610",
    "addr:postcode":"42048",
    "addr:street":"Curd Rd",
    "iso:country":"US",
    "sg:address":"1610 Curd Rd",
    "sg:city":"Hardin",
    "sg:classifiers":[
        {
            "category":"Personal",
            "subcategory":"Beauty Salon",
            "type":"Services"
        }
    ],
    "sg:phone":"+1 270 474 8831",
    "sg:postcode":"42048",
    "sg:province":"KY",
    "sg:tags":[
        "shop"
    ],
    "wof:name":"Aurora Beauty Salon",
    "wof:placetype":"venue"
},
  "geometry": {"coordinates":[-88.265157,36.787698],"type":"Point"}
}