{
  "type": "Feature",
  "properties": {
    "iso:country":"US",
    "sg:address":"8114 Limehouse Ln",
    "sg:city":"Louisville",
    "sg:classifiers":[
        {
            "category":"Freight",
            "type":"Transportation"
        }
    ],
    "sg:phone":"+1 502 491 5935",
    "sg:postcode":"40220",
    "sg:province":"KY",
    "sg:tags":[
        "brokerage"
    ],
    "wof:name":"Total Services Inc",
    "wof:placetype":"venue"
},
  "geometry": {"coordinates":[-85.60526400000001,38.225509],"type":"Point"}
}