{
  "type": "Feature",
  "properties": {
    "addr:full":"502 S 1st St La Grange KY 40031",
    "addr:housenumber":"502",
    "addr:postcode":"40031",
    "addr:street":"S 1St St",
    "iso:country":"US",
    "sg:address":"502 S 1st St",
    "sg:city":"La Grange",
    "sg:classifiers":[
        {
            "category":"Autos & Motor Vehicles",
            "subcategory":"Automobile Sales",
            "type":"Retail Goods"
        }
    ],
    "sg:phone":"+1 502 222 9477",
    "sg:postcode":"40031",
    "sg:province":"KY",
    "sg:tags":[
        "car",
        "dealer"
    ],
    "wof:name":"Champion Chevrolet Pontiac",
    "wof:placetype":"venue"
},
  "geometry": {"coordinates":[-85.376006,38.401716],"type":"Point"}
}