{
  "type": "Feature",
  "properties": {
    "addr:full":"806 Eastern Pkwy Louisville KY 40217",
    "addr:housenumber":"806",
    "addr:postcode":"40217",
    "addr:street":"Eastern Pkwy",
    "iso:country":"US",
    "sg:address":"806 Eastern Pkwy",
    "sg:city":"Louisville",
    "sg:classifiers":[
        {
            "category":"Shopping",
            "subcategory":"Gifts & Souvenirs",
            "type":"Retail Goods"
        }
    ],
    "sg:phone":"+1 502 636 5884",
    "sg:postcode":"40217",
    "sg:province":"KY",
    "sg:tags":[
        "shop"
    ],
    "wof:name":"Ginny's Hallmark",
    "wof:placetype":"venue"
},
  "geometry": {"coordinates":[-85.74189699999999,38.215144],"type":"Point"}
}