{
  "type": "Feature",
  "properties": {
    "iso:country":"US",
    "sg:address":"2117 View St",
    "sg:city":"Shelbyville",
    "sg:classifiers":[
        {
            "category":"Manufacturing",
            "subcategory":"Retail Goods",
            "type":"Manufacturing & Wholesale Goods"
        }
    ],
    "sg:phone":"+1 502 633 4699",
    "sg:postcode":"40065",
    "sg:province":"KY",
    "sg:tags":[
        "product",
        "mfg"
    ],
    "wof:name":"Ross Shooters Supply Inc",
    "wof:placetype":"venue"
},
  "geometry": {"coordinates":[-85.166566,38.210738],"type":"Point"}
}