{
  "type": "Feature",
  "properties": {
    "addr:full":"11705 Main St Louisville KY 40243",
    "addr:housenumber":"11705",
    "addr:postcode":"40243",
    "addr:street":"Main St",
    "iso:country":"US",
    "sg:address":"11705 Main St",
    "sg:city":"Louisville",
    "sg:classifiers":[
        {
            "category":"Organizations",
            "subcategory":"Community Association",
            "type":"Services"
        }
    ],
    "sg:phone":"+1 502 244 3004",
    "sg:postcode":"40243",
    "sg:province":"KY",
    "sg:tags":[
        "club"
    ],
    "wof:name":"Middletown Civic Club",
    "wof:placetype":"venue"
},
  "geometry": {"coordinates":[-85.538246,38.245762],"type":"Point"}
}