{
  "type": "Feature",
  "properties": {
    "iso:country":"US",
    "sg:address":"1808 S 4th St",
    "sg:city":"Ironton",
    "sg:classifiers":[
        {
            "category":"Retail",
            "subcategory":"Auto Repair",
            "type":"Services"
        }
    ],
    "sg:phone":"+1 740 533 3962",
    "sg:postcode":"45638",
    "sg:province":"OH",
    "sg:tags":[
        "body",
        "automobile",
        "painting"
    ],
    "wof:name":"Ron's Body Shop & Garage",
    "wof:placetype":"venue"
},
  "geometry": {"coordinates":[-82.672363,38.521016],"type":"Point"}
}