{
  "type": "Feature",
  "properties": {
    "iso:country":"US",
    "sg:address":"109 W Water St",
    "sg:city":"Flemingsburg",
    "sg:classifiers":[
        {
            "category":"Personal",
            "subcategory":"Barber",
            "type":"Services"
        }
    ],
    "sg:phone":"+1 606 845 0921",
    "sg:postcode":"41041",
    "sg:province":"KY",
    "sg:tags":[
        "shop"
    ],
    "wof:name":"Tim's Clip Joint",
    "wof:placetype":"venue"
},
  "geometry": {"coordinates":[-83.734301,38.422354],"type":"Point"}
}