{
  "type": "Feature",
  "properties": {
    "addr:full":"144 Carolyns Dr Somerset KY 42501",
    "addr:housenumber":"144",
    "addr:postcode":"42501",
    "addr:street":"Carolyns Dr",
    "iso:country":"US",
    "sg:address":"144 Carolyns Dr",
    "sg:city":"Somerset",
    "sg:classifiers":[
        {
            "category":"Freight",
            "type":"Transportation"
        }
    ],
    "sg:phone":"+1 606 274 5132",
    "sg:postcode":"42501",
    "sg:province":"KY",
    "sg:tags":[
        "commercial",
        "storage",
        "special"
    ],
    "wof:name":"Wesley's Storage",
    "wof:placetype":"venue"
},
  "geometry": {"coordinates":[-84.54792999999999,37.131117],"type":"Point"}
}