{
  "type": "Feature",
  "properties": {
    "addr:full":"957 Campbellsville Rd Columbia KY 42728",
    "addr:housenumber":"957",
    "addr:postcode":"42728",
    "addr:street":"Campbellsville Rd",
    "iso:country":"US",
    "sg:address":"957 Campbellsville Rd",
    "sg:city":"Columbia",
    "sg:classifiers":[
        {
            "category":"Government",
            "subcategory":"Office",
            "type":"Public Place"
        }
    ],
    "sg:phone":"+1 270 384 4759",
    "sg:postcode":"42728",
    "sg:province":"KY",
    "sg:tags":[
        "federal",
        "planning",
        "dev"
    ],
    "wof:name":"USDA Rural Development",
    "wof:placetype":"venue"
},
  "geometry": {"coordinates":[-85.300484,37.113904],"type":"Point"}
}