{
  "type": "Feature",
  "properties": {
    "iso:country":"US",
    "sg:address":"8986 Laketown Rd",
    "sg:city":"Owensboro",
    "sg:classifiers":[
        {
            "category":"Food & Beverages",
            "subcategory":"Specialty",
            "type":"Retail Goods"
        }
    ],
    "sg:phone":"+1 270 764 5657",
    "sg:postcode":"42301",
    "sg:province":"KY",
    "sg:tags":[
        "poultry"
    ],
    "wof:name":"Settles Farm Poultry",
    "wof:placetype":"venue"
},
  "geometry": {"coordinates":[-87.290752,37.869507],"type":"Point"}
}