{
  "type": "Feature",
  "properties": {
    "addr:full":"1445 Cherry Blossom Way Georgetown KY 40324",
    "addr:housenumber":"1445",
    "addr:postcode":"40324",
    "addr:street":"Cherry Blossom Way",
    "iso:country":"US",
    "sg:address":"1445 Cherry Blossom Way",
    "sg:city":"Georgetown",
    "sg:classifiers":[
        {
            "category":"Restaurant",
            "type":"Food & Drink"
        }
    ],
    "sg:menulink":"http://www.allmenus.com/ky/georgetown/176069-kfc---kentucky-fried-chicken/menu/",
    "sg:phone":"+1 502 863 1867",
    "sg:postcode":"40324",
    "sg:province":"KY",
    "sg:tags":[
        "american",
        "chicken"
    ],
    "wof:name":"KFC - Kentucky Fried Chicken",
    "wof:placetype":"venue"
},
  "geometry": {"coordinates":[-84.541045,38.218083],"type":"Point"}
}