{
  "type": "Feature",
  "properties": {
    "addr:full":"2040 Regency Rd Lexington KY 40503",
    "addr:housenumber":"2040",
    "addr:postcode":"40503",
    "addr:street":"Regency Rd",
    "iso:country":"US",
    "sg:address":"2040 Regency Rd",
    "sg:city":"Lexington",
    "sg:classifiers":[
        {
            "category":"Professional",
            "type":"Services"
        }
    ],
    "sg:phone":"+1 859 276 1946",
    "sg:postcode":"40503",
    "sg:province":"KY",
    "sg:tags":[
        "establishment"
    ],
    "wof:name":"Jinny Vicroy Arnp Pllc",
    "wof:placetype":"venue"
},
  "geometry": {"coordinates":[-84.522747,38.012115],"type":"Point"}
}