{
  "type": "Feature",
  "properties": {
    "addr:full":"4607 Shelbyville Rd Louisville KY 40207",
    "addr:housenumber":"4607",
    "addr:postcode":"40207",
    "addr:street":"Shelbyville Rd",
    "iso:country":"US",
    "sg:address":"4607 Shelbyville Rd",
    "sg:city":"Louisville",
    "sg:classifiers":[
        {
            "category":"Shopping",
            "subcategory":"Clothing, Apparel, & Fashions",
            "type":"Retail Goods"
        }
    ],
    "sg:phone":"+1 502 899 2429",
    "sg:postcode":"40207",
    "sg:province":"KY",
    "sg:tags":[
        "men's",
        "clothing",
        "sportswear"
    ],
    "sg:website":"http://www.casualmale.com",
    "wof:name":"Casual Male Xl",
    "wof:placetype":"venue"
},
  "geometry": {"coordinates":[-85.627818,38.250673],"type":"Point"}
}