{
  "type": "Feature",
  "properties": {
    "addr:full":"217 S Main St Winchester KY 40391",
    "addr:housenumber":"217",
    "addr:postcode":"40391",
    "addr:street":"S Main St",
    "iso:country":"US",
    "sg:address":"217 S Main St",
    "sg:city":"Winchester",
    "sg:classifiers":[
        {
            "category":"Museum",
            "type":"Entertainment"
        }
    ],
    "sg:phone":"+1 859 745 1358",
    "sg:postcode":"40391",
    "sg:province":"KY",
    "wof:name":"Bluegrass Heritage Museum",
    "wof:placetype":"venue"
},
  "geometry": {"coordinates":[-84.178629,37.989972],"type":"Point"}
}