{
  "type": "Feature",
  "properties": {
    "iso:country":"US",
    "sg:address":"321 E 4th St",
    "sg:city":"London",
    "sg:classifiers":[
        {
            "category":"Social Services",
            "subcategory":"Child Care",
            "type":"Services"
        }
    ],
    "sg:phone":"+1 606 878 8199",
    "sg:postcode":"40741",
    "sg:province":"KY",
    "sg:tags":[
        "kindergarten",
        "academic",
        "school"
    ],
    "wof:name":"Wonderland Preschool & Child",
    "wof:placetype":"venue"
},
  "geometry": {"coordinates":[-84.07786299999999,37.130492],"type":"Point"}
}