{
  "type": "Feature",
  "properties": {
    "addr:full":"900 Winchester Rd Lexington KY 40505",
    "addr:housenumber":"900",
    "addr:postcode":"40505",
    "addr:street":"Winchester Rd",
    "iso:country":"US",
    "sg:address":"900 Winchester Rd",
    "sg:city":"Lexington",
    "sg:classifiers":[
        {
            "category":"Food & Beverages",
            "subcategory":"Groceries & Convenience Stores",
            "type":"Retail Goods"
        }
    ],
    "sg:phone":"+1 859 254 4182",
    "sg:postcode":"40505",
    "sg:province":"KY",
    "sg:website":"http://www.speedway.com",
    "wof:name":"Speedway 9658",
    "wof:placetype":"venue"
},
  "geometry": {"coordinates":[-84.47184,38.041592],"type":"Point"}
}