{
  "type": "Feature",
  "properties": {
    "iso:country":"US",
    "sg:address":"2637 Stadium Dr",
    "sg:city":"Henderson",
    "sg:classifiers":[
        {
            "category":"Social Services",
            "subcategory":"Adult Care",
            "type":"Services"
        }
    ],
    "sg:phone":"+1 270 826 2493",
    "sg:postcode":"42420",
    "sg:province":"KY",
    "sg:tags":[
        "home",
        "residential"
    ],
    "wof:name":"Colonial Assisted Living",
    "wof:placetype":"venue"
},
  "geometry": {"coordinates":[-87.55910799999999,37.822555],"type":"Point"}
}