{
  "type": "Feature",
  "properties": {
    "addr:full":"767 Hunts Ln Bowling Green KY 42103",
    "addr:housenumber":"767",
    "addr:postcode":"42103",
    "addr:street":"Hunts Ln",
    "iso:country":"US",
    "sg:address":"767 Hunts Ln",
    "sg:city":"Bowling Green",
    "sg:classifiers":[
        {
            "category":"Sports & Exercise",
            "subcategory":"Gym",
            "type":"Entertainment"
        }
    ],
    "sg:phone":"+1 270 846 4411",
    "sg:postcode":"42103",
    "sg:province":"KY",
    "sg:tags":[
        "fitness",
        "physical",
        "facility"
    ],
    "wof:name":"Bevs Salon of Wellness",
    "wof:placetype":"venue"
},
  "geometry": {"coordinates":[-86.35529,36.94565],"type":"Point"}
}