{
  "type": "Feature",
  "properties": {
    "iso:country":"US",
    "sg:address":"5 N Main St",
    "sg:city":"Henderson",
    "sg:classifiers":[
        {
            "category":"Government",
            "subcategory":"Court House",
            "type":"Public Place"
        }
    ],
    "sg:phone":"+1 270 826 4755",
    "sg:postcode":"42420",
    "sg:province":"KY",
    "sg:tags":[
        "county",
        "state"
    ],
    "wof:name":"Henderson District Court Judge",
    "wof:placetype":"venue"
},
  "geometry": {"coordinates":[-87.592557,37.839443],"type":"Point"}
}