{
  "type": "Feature",
  "properties": {
    "iso:country":"US",
    "sg:address":"4895 Houston Rd",
    "sg:city":"Florence",
    "sg:classifiers":[
        {
            "category":"Real Estate",
            "subcategory":"Real Estate Agent",
            "type":"Services"
        }
    ],
    "sg:phone":"+1 859 344 7303",
    "sg:postcode":"41042",
    "sg:province":"KY",
    "wof:name":"Patmax Inc",
    "wof:placetype":"venue"
},
  "geometry": {"coordinates":[-84.63167799999999,39.018051],"type":"Point"}
}