{
  "type": "Feature",
  "properties": {
    "addr:full":"5751 Briar Hill Rd Lexington KY 40516",
    "addr:housenumber":"5751",
    "addr:postcode":"40516",
    "addr:street":"Briar Hill Rd",
    "iso:country":"US",
    "sg:address":"5751 Briar Hill Rd",
    "sg:city":"Lexington",
    "sg:classifiers":[
        {
            "category":"Government",
            "subcategory":"Office",
            "type":"Public Place"
        }
    ],
    "sg:phone":"+1 859 246 2100",
    "sg:postcode":"40516",
    "sg:province":"KY",
    "wof:name":"Special Invstgtn Drug Infrcmnt",
    "wof:placetype":"venue"
},
  "geometry": {"coordinates":[-84.319091,38.071783],"type":"Point"}
}