{
  "type": "Feature",
  "properties": {
    "addr:full":"1033 Crimson Creek Dr Lexington KY 40509",
    "addr:housenumber":"1033",
    "addr:postcode":"40509",
    "addr:street":"Crimson Creek Dr",
    "iso:country":"US",
    "sg:address":"1033 Crimson Creek Dr",
    "sg:city":"Lexington",
    "sg:classifiers":[
        {
            "category":"Retail",
            "subcategory":"Repair Shop",
            "type":"Services"
        }
    ],
    "sg:phone":"+1 859 263 9256",
    "sg:postcode":"40509",
    "sg:province":"KY",
    "wof:name":"Rs Frames",
    "wof:placetype":"venue"
},
  "geometry": {"coordinates":[-84.401696,38.001463],"type":"Point"}
}