{
  "type": "Feature",
  "properties": {
    "iso:country":"US",
    "sg:address":"2379 Irvine Rd",
    "sg:city":"Richmond",
    "sg:classifiers":[
        {
            "category":"Home & Garden",
            "subcategory":"Carpets & Floor Coverings",
            "type":"Retail Goods"
        }
    ],
    "sg:phone":"+1 859 624 8886",
    "sg:postcode":"40475",
    "sg:province":"KY",
    "sg:tags":[
        "dealer",
        "rug"
    ],
    "wof:name":"WACO Carpet Outlet Inc",
    "wof:placetype":"venue"
},
  "geometry": {"coordinates":[-84.20522800000001,37.738355],"type":"Point"}
}