{
  "type": "Feature",
  "properties": {
    "iso:country":"US",
    "sg:address":"475 Smokey Branch Rd",
    "sg:city":"Campton",
    "sg:classifiers":[
        {
            "category":"Building & Trades",
            "subcategory":"Plumbing",
            "type":"Services"
        }
    ],
    "sg:phone":"+1 606 668 3226",
    "sg:postcode":"41301",
    "sg:province":"KY",
    "sg:tags":[
        "plumbing",
        "contractor"
    ],
    "wof:name":"Bruce's Plumbing",
    "wof:placetype":"venue"
},
  "geometry": {"coordinates":[-83.526901,37.702331],"type":"Point"}
}