{
  "type": "Feature",
  "properties": {
    "addr:full":"720 Main St Ravenna KY 40472",
    "addr:housenumber":"720",
    "addr:postcode":"40472",
    "addr:street":"Main St",
    "iso:country":"US",
    "sg:address":"720 Main St",
    "sg:city":"Ravenna",
    "sg:classifiers":[
        {
            "category":"Home & Garden",
            "subcategory":"Building Materials",
            "type":"Retail Goods"
        }
    ],
    "sg:phone":"+1 606 723 3858",
    "sg:postcode":"40472",
    "sg:province":"KY",
    "sg:tags":[
        "paint"
    ],
    "wof:name":"Bryant's Paint Shop",
    "wof:placetype":"venue"
},
  "geometry": {"coordinates":[-83.95615599999999,37.685666],"type":"Point"}
}