{
  "type": "Feature",
  "properties": {
    "iso:country":"US",
    "sg:address":"427 Meadow Park",
    "sg:city":"Lexington",
    "sg:classifiers":[
        {
            "category":"Building & Trades",
            "subcategory":"Construction",
            "type":"Services"
        }
    ],
    "sg:phone":"+1 859 233 9687",
    "sg:postcode":"40505",
    "sg:province":"KY",
    "sg:tags":[
        "house"
    ],
    "wof:name":"Rileys Repair",
    "wof:placetype":"venue"
},
  "geometry": {"coordinates":[-84.46593799999999,38.05782],"type":"Point"}
}