{
  "type": "Feature",
  "properties": {
    "iso:country":"US",
    "sg:address":"1804 Alexandria Dr",
    "sg:city":"Lexington",
    "sg:classifiers":[
        {
            "category":"Restaurant",
            "type":"Food & Drink"
        }
    ],
    "sg:phone":"+1 859 277 7223",
    "sg:postcode":"40504",
    "sg:province":"KY",
    "wof:name":"Gardenside Cafe",
    "wof:placetype":"venue"
},
  "geometry": {"coordinates":[-84.552184,38.037244],"type":"Point"}
}