{
  "type": "Feature",
  "properties": {
    "iso:country":"US",
    "sg:address":"101 Bullitt Ln Ste 206",
    "sg:city":"Louisville",
    "sg:classifiers":[
        {
            "category":"Professional",
            "subcategory":"Management & Consulting",
            "type":"Services"
        },
        {
            "category":"Professional",
            "subcategory":"Employment Agencies",
            "type":"Services"
        }
    ],
    "sg:phone":"+1 502 339 9007",
    "sg:postcode":"40222",
    "sg:province":"KY",
    "sg:tags":[
        "consultant",
        "search",
        "executive",
        "personnel"
    ],
    "wof:name":"Ajilon Finance",
    "wof:placetype":"venue"
},
  "geometry": {"coordinates":[-85.614639,38.246281],"type":"Point"}
}