{
  "type": "Feature",
  "properties": {
    "iso:country":"US",
    "sg:address":"2701 H C Mathis Dr",
    "sg:city":"Paducah",
    "sg:classifiers":[
        {
            "category":"Travel",
            "subcategory":"Hotels & Motels",
            "type":"Entertainment"
        }
    ],
    "sg:phone":"+1 270 443 5500",
    "sg:postcode":"42001",
    "sg:province":"KY",
    "wof:name":"Red Carpet Inn",
    "wof:placetype":"venue"
},
  "geometry": {"coordinates":[-88.63418799999999,37.082046],"type":"Point"}
}