{
  "type": "Feature",
  "properties": {
    "iso:country":"US",
    "sg:address":"930 Appleblossom Dr",
    "sg:city":"Covington",
    "sg:classifiers":[
        {
            "category":"Manufacturing",
            "subcategory":"Watercraft",
            "type":"Manufacturing & Wholesale Goods"
        }
    ],
    "sg:phone":"+1 859 426 8380",
    "sg:postcode":"41017",
    "sg:province":"KY",
    "wof:name":"Tribal Kayaks LLC",
    "wof:placetype":"venue"
},
  "geometry": {"coordinates":[-84.57238599999999,39.074329],"type":"Point"}
}