{
  "type": "Feature",
  "properties": {
    "iso:country":"US",
    "sg:address":"3902 Archer Ct",
    "sg:city":"Florence",
    "sg:classifiers":[
        {
            "category":"Retail",
            "subcategory":"Laundry & Dry Cleaning",
            "type":"Services"
        },
        {
            "category":"Building & Trades",
            "subcategory":"Cleaning & Sanitation",
            "type":"Services"
        }
    ],
    "sg:phone":"+1 859 282 1292",
    "sg:postcode":"41042",
    "sg:province":"KY",
    "sg:tags":[
        "cleaner",
        "house"
    ],
    "sg:website":"http://www.twoforwomen.com",
    "wof:name":"Two Women & Mop",
    "wof:placetype":"venue"
},
  "geometry": {"coordinates":[-84.599735,38.97393],"type":"Point"}
}