{
  "type": "Feature",
  "properties": {
    "addr:full":"304 E Main St Richmond KY 40475",
    "addr:housenumber":"304",
    "addr:postcode":"40475",
    "addr:street":"E Main St",
    "iso:country":"US",
    "sg:address":"304 E Main St",
    "sg:city":"Richmond",
    "sg:classifiers":[
        {
            "category":"Food & Beverages",
            "subcategory":"Liquor & Beverages",
            "type":"Retail Goods"
        }
    ],
    "sg:phone":"+1 859 623 4840",
    "sg:postcode":"40475",
    "sg:province":"KY",
    "wof:name":"Central Liquor",
    "wof:placetype":"venue"
},
  "geometry": {"coordinates":[-84.291641,37.746183],"type":"Point"}
}