{
  "type": "Feature",
  "properties": {
    "iso:country":"US",
    "sg:address":"10150 Brookridge Village Blvd",
    "sg:city":"Louisville",
    "sg:classifiers":[
        {
            "category":"Manufacturing",
            "subcategory":"Jewelry",
            "type":"Manufacturing & Wholesale Goods"
        },
        {
            "category":"Restaurant",
            "type":"Food & Drink"
        }
    ],
    "sg:phone":"+1 502 231 4663",
    "sg:postcode":"40291",
    "sg:province":"KY",
    "sg:tags":[
        "style",
        "family",
        "novelty",
        "soul",
        "american"
    ],
    "sg:website":"http://www.crackerbarrel.com",
    "wof:name":"Cracker Barrel Old Country Store",
    "wof:placetype":"venue"
},
  "geometry": {"coordinates":[-85.58313800000001,38.145039],"type":"Point"}
}