{
  "type": "Feature",
  "properties": {
    "addr:full":"4195 N Mayo Trl Pikeville KY 41501",
    "addr:housenumber":"4195",
    "addr:postcode":"41501",
    "addr:street":"N Mayo Trl",
    "iso:country":"US",
    "sg:address":"4195 N Mayo Trl",
    "sg:city":"Pikeville",
    "sg:classifiers":[
        {
            "category":"Food & Beverages",
            "subcategory":"Groceries & Convenience Stores",
            "type":"Retail Goods"
        }
    ],
    "sg:phone":"+1 606 433 0827",
    "sg:postcode":"41501",
    "sg:province":"KY",
    "sg:tags":[
        "grocer"
    ],
    "wof:name":"Save-A-Lot",
    "wof:placetype":"venue"
},
  "geometry": {"coordinates":[-82.57292200000001,37.524538],"type":"Point"}
}