{
  "type": "Feature",
  "properties": {
    "iso:country":"US",
    "sg:address":"623 Colby Rd",
    "sg:city":"Winchester",
    "sg:classifiers":[
        {
            "category":"Organizations",
            "subcategory":"Religious Organization",
            "type":"Services"
        }
    ],
    "sg:phone":"+1 859 744 0467",
    "sg:postcode":"40391",
    "sg:province":"KY",
    "sg:tags":[
        "church"
    ],
    "wof:name":"Winchester Church Of Christ",
    "wof:placetype":"venue"
},
  "geometry": {"coordinates":[-84.200408,37.988093],"type":"Point"}
}