{
  "type": "Feature",
  "properties": {
    "iso:country":"US",
    "sg:address":"134 Cody Ln",
    "sg:city":"Hardinsburg",
    "sg:classifiers":[
        {
            "category":"Professional",
            "subcategory":"Lawyer & Legal Services",
            "type":"Services"
        }
    ],
    "sg:phone":"+1 270 756 2184",
    "sg:postcode":"40143",
    "sg:province":"KY",
    "sg:tags":[
        "attorney"
    ],
    "wof:name":"Brite & Butler",
    "wof:placetype":"venue"
},
  "geometry": {"coordinates":[-86.44337,37.770596],"type":"Point"}
}