{
  "type": "Feature",
  "properties": {
    "addr:full":"4502 Samara Dr Louisville KY 40219",
    "addr:housenumber":"4502",
    "addr:postcode":"40219",
    "addr:street":"Samara Dr",
    "iso:country":"US",
    "sg:address":"4502 Samara Dr",
    "sg:city":"Louisville",
    "sg:classifiers":[
        {
            "category":"Wholesale",
            "subcategory":"Non-durable Goods",
            "type":"Manufacturing & Wholesale Goods"
        }
    ],
    "sg:phone":"+1 502 966 8515",
    "sg:postcode":"40219",
    "sg:province":"KY",
    "sg:tags":[
        "merchandise",
        "general"
    ],
    "wof:name":"Blind Faith Sales",
    "wof:placetype":"venue"
},
  "geometry": {"coordinates":[-85.674207,38.16882],"type":"Point"}
}