{
  "type": "Feature",
  "properties": {
    "iso:country":"US",
    "sg:address":"2112 College Farm Rd",
    "sg:city":"Murray",
    "sg:classifiers":[
        {
            "category":"Education",
            "subcategory":"School",
            "type":"Public Place"
        }
    ],
    "sg:phone":"+1 270 762 7355",
    "sg:postcode":"42071",
    "sg:province":"KY",
    "wof:name":"Calloway County Middle School",
    "wof:placetype":"venue"
},
  "geometry": {"coordinates":[-88.340718,36.617433],"type":"Point"}
}