{
  "type": "Feature",
  "properties": {
    "iso:country":"US",
    "sg:address":"1921 Production Dr",
    "sg:city":"Louisville",
    "sg:classifiers":[
        {
            "category":"Manufacturing",
            "subcategory":"Tools & Machinery",
            "type":"Manufacturing & Wholesale Goods"
        }
    ],
    "sg:phone":"+1 502 499 9794",
    "sg:postcode":"40299",
    "sg:province":"KY",
    "sg:tags":[
        "physician",
        "surgical",
        "appliance",
        "surgeon",
        "supply"
    ],
    "sg:website":"http://www.aquaticaccess.com",
    "wof:name":"Aquatic Access, Inc.",
    "wof:placetype":"venue"
},
  "geometry": {"coordinates":[-85.563401,38.219342],"type":"Point"}
}