{
  "type": "Feature",
  "properties": {
    "addr:full":"457 Pointe Blvd Shepherdsville KY 40165",
    "addr:housenumber":"457",
    "addr:postcode":"40165",
    "addr:street":"Pointe Blvd",
    "iso:country":"US",
    "sg:address":"457 Pointe Blvd",
    "sg:city":"Shepherdsville",
    "sg:classifiers":[
        {
            "category":"Wholesale",
            "subcategory":"Machinery & Supplies",
            "type":"Manufacturing & Wholesale Goods"
        }
    ],
    "sg:phone":"+1 502 543 2225",
    "sg:postcode":"40165",
    "sg:province":"KY",
    "sg:tags":[
        "equipment"
    ],
    "wof:name":"Heavy Equipment Data Center",
    "wof:placetype":"venue"
},
  "geometry": {"coordinates":[-85.71034,38.009576],"type":"Point"}
}