{
  "type": "Feature",
  "properties": {
    "iso:country":"US",
    "sg:address":"2510 Mosswood Way",
    "sg:city":"Bowling Green",
    "sg:classifiers":[
        {
            "category":"Real Estate",
            "subcategory":"Real Estate Agent",
            "type":"Services"
        }
    ],
    "sg:phone":"+1 270 781 1625",
    "sg:postcode":"42104",
    "sg:province":"KY",
    "wof:name":"Page Virginia",
    "wof:placetype":"venue"
},
  "geometry": {"coordinates":[-86.443223,36.93489],"type":"Point"}
}