{
  "type": "Feature",
  "properties": {
    "iso:country":"US",
    "sg:address":"3915 Northumberland Dr",
    "sg:city":"Louisville",
    "sg:classifiers":[
        {
            "category":"Social Services",
            "subcategory":"Child Care",
            "type":"Services"
        }
    ],
    "sg:phone":"+1 502 426 5397",
    "sg:postcode":"40245",
    "sg:province":"KY",
    "sg:tags":[
        "day"
    ],
    "wof:name":"Marilyns Day Care Home",
    "wof:placetype":"venue"
},
  "geometry": {"coordinates":[-85.52574,38.312383],"type":"Point"}
}