{
  "type": "Feature",
  "properties": {
    "addr:full":"12615 Taylorsville Rd Louisville KY 40299",
    "addr:housenumber":"12615",
    "addr:postcode":"40299",
    "addr:street":"Taylorsville Rd",
    "iso:country":"US",
    "sg:address":"12615 Taylorsville Rd",
    "sg:city":"Louisville",
    "sg:classifiers":[
        {
            "category":"Health Services",
            "subcategory":"Clinic",
            "type":"Services"
        },
        {
            "category":"Health Services",
            "subcategory":"Hospital",
            "type":"Services"
        }
    ],
    "sg:phone":"+1 502 261 1565",
    "sg:postcode":"40299",
    "sg:province":"KY",
    "sg:tags":[
        "medical"
    ],
    "sg:website":"http://nortonhealthcare.com/NNI",
    "wof:name":"Norton Immediate Care Ctr",
    "wof:placetype":"venue"
},
  "geometry": {"coordinates":[-85.519223,38.187456],"type":"Point"}
}