{
  "type": "Feature",
  "properties": {
    "iso:country":"US",
    "sg:address":"1530 Shopes Creek Rd",
    "sg:city":"Ashland",
    "sg:classifiers":[
        {
            "category":"Food & Beverages",
            "subcategory":"Groceries & Convenience Stores",
            "type":"Retail Goods"
        }
    ],
    "sg:phone":"+1 606 928 4120",
    "sg:postcode":"41102",
    "sg:province":"KY",
    "wof:name":"Wenning's Mini Market",
    "wof:placetype":"venue"
},
  "geometry": {"coordinates":[-82.70003,38.417681],"type":"Point"}
}