{
  "type": "Feature",
  "properties": {
    "iso:country":"US",
    "sg:address":"4109 Petersburg Rd",
    "sg:city":"Burlington",
    "sg:classifiers":[
        {
            "category":"Building & Trades",
            "subcategory":"Construction",
            "type":"Services"
        }
    ],
    "sg:phone":"+1 859 586 8755",
    "sg:postcode":"41005",
    "sg:province":"KY",
    "sg:tags":[
        "concrete",
        "contractor"
    ],
    "wof:name":"Bernard Concrete Cutting Inc",
    "wof:placetype":"venue"
},
  "geometry": {"coordinates":[-84.781516,39.080037],"type":"Point"}
}