{
  "type": "Feature",
  "properties": {
    "addr:full":"8504 Shepherdsville Rd Louisville KY 40219",
    "addr:housenumber":"8504",
    "addr:postcode":"40219",
    "addr:street":"Shepherdsville Rd",
    "iso:country":"US",
    "sg:address":"8504 Shepherdsville Rd",
    "sg:city":"Louisville",
    "sg:classifiers":[
        {
            "category":"Food & Beverages",
            "subcategory":"Groceries & Convenience Stores",
            "type":"Retail Goods"
        }
    ],
    "sg:phone":"+1 502 969 0218",
    "sg:postcode":"40219",
    "sg:province":"KY",
    "sg:tags":[
        "grocer",
        "salvage",
        "surplus",
        "merchandise"
    ],
    "wof:name":"B & E Salvage Co Inc",
    "wof:placetype":"venue"
},
  "geometry": {"coordinates":[-85.665221,38.125911],"type":"Point"}
}