{
  "type": "Feature",
  "properties": {
    "iso:country":"US",
    "sg:address":"107 Young Dr",
    "sg:city":"Madisonville",
    "sg:classifiers":[
        {
            "category":"Building & Trades",
            "subcategory":"Landscaping Services",
            "type":"Services"
        }
    ],
    "sg:phone":"+1 270 825 0106",
    "sg:postcode":"42431",
    "sg:province":"KY",
    "sg:tags":[
        "lawn",
        "maintenance",
        "grounds"
    ],
    "wof:name":"T Nt Lawn Care",
    "wof:placetype":"venue"
},
  "geometry": {"coordinates":[-87.502365,37.31453],"type":"Point"}
}