{
  "type": "Feature",
  "properties": {
    "iso:country":"US",
    "sg:address":"2280 Maggard Dr",
    "sg:city":"Lexington",
    "sg:classifiers":[
        {
            "category":"Freight",
            "type":"Transportation"
        }
    ],
    "sg:phone":"+1 859 389 7054",
    "sg:postcode":"40511",
    "sg:province":"KY",
    "sg:tags":[
        "trucking"
    ],
    "wof:name":"Watkins Motor Lines Lex",
    "wof:placetype":"venue"
},
  "geometry": {"coordinates":[-84.516868,38.087513],"type":"Point"}
}