{
  "type": "Feature",
  "properties": {
    "iso:country":"US",
    "sg:address":"9900 Brownsboro Rd",
    "sg:city":"Louisville",
    "sg:classifiers":[
        {
            "category":"Social Services",
            "type":"Services"
        }
    ],
    "sg:phone":"+1 502 212 0013",
    "sg:postcode":"40241",
    "sg:province":"KY",
    "wof:name":"Evergreen Christian Counseling Inc",
    "wof:placetype":"venue"
},
  "geometry": {"coordinates":[-85.57127800000001,38.310305],"type":"Point"}
}