{
  "type": "Feature",
  "properties": {
    "addr:full":"403 River St Harlan KY 40831",
    "addr:housenumber":"403",
    "addr:postcode":"40831",
    "addr:street":"River St",
    "iso:country":"US",
    "sg:address":"403 River St",
    "sg:city":"Harlan",
    "sg:classifiers":[
        {
            "category":"Social Services",
            "type":"Services"
        }
    ],
    "sg:phone":"+1 606 573 9843",
    "sg:postcode":"40831",
    "sg:province":"KY",
    "sg:tags":[
        "organization",
        "welfare"
    ],
    "wof:name":"Christian Family Svc",
    "wof:placetype":"venue"
},
  "geometry": {"coordinates":[-83.317255,36.844769],"type":"Point"}
}