{
  "type": "Feature",
  "properties": {
    "iso:country":"US",
    "sg:address":"3019 Old Union Springs Dr",
    "sg:city":"London",
    "sg:classifiers":[
        {
            "category":"Insurance",
            "subcategory":"Insurance Agent",
            "type":"Services"
        }
    ],
    "sg:phone":"+1 606 862 1329",
    "sg:postcode":"40744",
    "sg:province":"KY",
    "wof:name":"Comp Risk Management",
    "wof:placetype":"venue"
},
  "geometry": {"coordinates":[-84.083466,37.068205],"type":"Point"}
}