{
  "type": "Feature",
  "properties": {
    "addr:full":"9879 Potomac Ct Independence KY 41051",
    "addr:housenumber":"9879",
    "addr:postcode":"41051",
    "addr:street":"Potomac Ct",
    "iso:country":"US",
    "sg:address":"9879 Potomac Ct",
    "sg:city":"Independence",
    "sg:classifiers":[
        {
            "category":"Home & Garden",
            "subcategory":"Carpets & Floor Coverings",
            "type":"Retail Goods"
        }
    ],
    "sg:phone":"+1 859 371 0389",
    "sg:postcode":"41051",
    "sg:province":"KY",
    "wof:name":"Mc Neese Floor Covering Inc",
    "wof:placetype":"venue"
},
  "geometry": {"coordinates":[-84.58671,38.95839],"type":"Point"}
}