{
  "type": "Feature",
  "properties": {
    "iso:country":"US",
    "sg:address":"120 Wilson Ct",
    "sg:city":"Nicholasville",
    "sg:classifiers":[
        {
            "category":"Wholesale",
            "subcategory":"Electrical",
            "type":"Manufacturing & Wholesale Goods"
        }
    ],
    "sg:phone":"+1 859 885 6168",
    "sg:postcode":"40356",
    "sg:province":"KY",
    "sg:tags":[
        "equipment",
        "electric",
        "supply"
    ],
    "wof:name":"Nicholasville Electrical Supl",
    "wof:placetype":"venue"
},
  "geometry": {"coordinates":[-84.591245,37.887468],"type":"Point"}
}