{
  "type": "Feature",
  "properties": {
    "iso:country":"US",
    "sg:address":"427 S 4th St",
    "sg:city":"Louisville",
    "sg:classifiers":[
        {
            "category":"Restaurant",
            "type":"Food & Drink"
        }
    ],
    "sg:phone":"+1 502 568 1400",
    "sg:postcode":"40202",
    "sg:province":"KY",
    "wof:name":"Downtown Sports",
    "wof:placetype":"venue"
},
  "geometry": {"coordinates":[-85.757211,38.252547],"type":"Point"}
}