{
  "type": "Feature",
  "properties": {
    "iso:country":"US",
    "sg:address":"710 Payne Rd",
    "sg:city":"Ekron",
    "sg:classifiers":[
        {
            "category":"Professional",
            "subcategory":"Business Services",
            "type":"Services"
        }
    ],
    "sg:phone":"+1 270 828 8303",
    "sg:postcode":"40117",
    "sg:province":"KY",
    "wof:name":"Allen Stivers",
    "wof:placetype":"venue"
},
  "geometry": {"coordinates":[-86.130454,37.9096],"type":"Point"}
}