{
  "type": "Feature",
  "properties": {
    "iso:country":"US",
    "sg:address":"212 Bunch Rd",
    "sg:city":"Cave City",
    "sg:classifiers":[
        {
            "category":"Building & Trades",
            "subcategory":"Construction",
            "type":"Services"
        }
    ],
    "sg:phone":"+1 270 453 4938",
    "sg:postcode":"42127",
    "sg:province":"KY",
    "sg:tags":[
        "dry wall",
        "contractor"
    ],
    "wof:name":"Smith Interiors Inc",
    "wof:placetype":"venue"
},
  "geometry": {"coordinates":[-85.86184,37.089571],"type":"Point"}
}