{
  "type": "Feature",
  "properties": {
    "iso:country":"US",
    "sg:address":"23 Marion St",
    "sg:city":"Cadiz",
    "sg:classifiers":[
        {
            "category":"Health Services",
            "subcategory":"Doctor",
            "type":"Services"
        }
    ],
    "sg:phone":"+1 270 522 4060",
    "sg:postcode":"42211",
    "sg:province":"KY",
    "sg:tags":[
        "physician",
        "surgeon"
    ],
    "wof:name":"Trigg County Primary Care",
    "wof:placetype":"venue"
},
  "geometry": {"coordinates":[-87.837611,36.863786],"type":"Point"}
}