{
  "type": "Feature",
  "properties": {
    "addr:full":"5807 Bardstown Rd Fern Creek KY 40291",
    "addr:housenumber":"5807",
    "addr:postcode":"40291",
    "addr:street":"Bardstown Rd",
    "iso:country":"US",
    "sg:address":"5807 Bardstown Rd",
    "sg:city":"Fern Creek",
    "sg:classifiers":[
        {
            "category":"Freight",
            "type":"Transportation"
        }
    ],
    "sg:phone":"+1 502 231 5451",
    "sg:postcode":"40291",
    "sg:province":"KY",
    "sg:tags":[
        "commercial",
        "storage"
    ],
    "wof:name":"Storage USA",
    "wof:placetype":"venue"
},
  "geometry": {"coordinates":[-85.59271699999999,38.160794],"type":"Point"}
}