{
  "type": "Feature",
  "properties": {
    "iso:country":"US",
    "sg:address":"711 Mill St",
    "sg:city":"Leitchfield",
    "sg:classifiers":[
        {
            "category":"Health Services",
            "subcategory":"Doctor",
            "type":"Services"
        }
    ],
    "sg:phone":"+1 270 259 5300",
    "sg:postcode":"42754",
    "sg:province":"KY",
    "sg:tags":[
        "dentist"
    ],
    "wof:name":"Higdon Family Dentistry",
    "wof:placetype":"venue"
},
  "geometry": {"coordinates":[-86.28284600000001,37.483832],"type":"Point"}
}