{
  "type": "Feature",
  "properties": {
    "iso:country":"US",
    "sg:address":"9828 Tiverton Way",
    "sg:city":"Louisville",
    "sg:classifiers":[
        {
            "category":"Wholesale",
            "subcategory":"Medical Equipment & Supplies",
            "type":"Manufacturing & Wholesale Goods"
        }
    ],
    "sg:phone":"+1 502 429 6030",
    "sg:postcode":"40242",
    "sg:province":"KY",
    "sg:tags":[
        "device",
        "orthopedic",
        "appliance",
        "prosthetic"
    ],
    "sg:website":"http://www.medkoinc.com",
    "wof:name":"Medko Inc",
    "wof:placetype":"venue"
},
  "geometry": {"coordinates":[-85.57132799999999,38.284798],"type":"Point"}
}