{
  "type": "Feature",
  "properties": {
    "addr:full":"104 Merchant St Columbia KY 42728",
    "addr:housenumber":"104",
    "addr:postcode":"42728",
    "addr:street":"Merchant St",
    "iso:country":"US",
    "sg:address":"104 Merchant St",
    "sg:city":"Columbia",
    "sg:classifiers":[
        {
            "category":"Shopping",
            "subcategory":"Florist",
            "type":"Retail Goods"
        }
    ],
    "sg:phone":"+1 270 384 2541",
    "sg:postcode":"42728",
    "sg:province":"KY",
    "wof:name":"Adair Florist",
    "wof:placetype":"venue"
},
  "geometry": {"coordinates":[-85.30558499999999,37.104153],"type":"Point"}
}