{
  "type": "Feature",
  "properties": {
    "iso:country":"US",
    "sg:address":"1002 Woodford Dr",
    "sg:city":"Mt Sterling",
    "sg:classifiers":[
        {
            "category":"Retail",
            "subcategory":"Funeral Services",
            "type":"Services"
        }
    ],
    "sg:phone":"+1 859 498 1421",
    "sg:postcode":"40353",
    "sg:province":"KY",
    "sg:tags":[
        "director"
    ],
    "wof:name":"Herald & Stewart Home-Funerals",
    "wof:placetype":"venue"
},
  "geometry": {"coordinates":[-83.937281,38.044189],"type":"Point"}
}