{
  "type": "Feature",
  "properties": {
    "addr:full":"5522 Bloomfield Rd Bardstown KY 40004",
    "addr:housenumber":"5522",
    "addr:postcode":"40004",
    "addr:street":"Bloomfield Rd",
    "iso:country":"US",
    "sg:address":"5522 Bloomfield Rd",
    "sg:city":"Bardstown",
    "sg:classifiers":[
        {
            "category":"Farming",
            "subcategory":"Livestock Farm",
            "type":"Manufacturing & Wholesale Goods"
        }
    ],
    "sg:phone":"+1 502 252 5157",
    "sg:postcode":"40004",
    "sg:province":"KY",
    "sg:tags":[
        "beef",
        "feedlot",
        "cattle"
    ],
    "wof:name":"Andy Snider",
    "wof:placetype":"venue"
},
  "geometry": {"coordinates":[-85.37239099999999,37.844708],"type":"Point"}
}