{
  "type": "Feature",
  "properties": {
    "addr:full":"325 Industrial Rd Morganfield KY 42431",
    "addr:housenumber":"325",
    "addr:postcode":"42431",
    "addr:street":"Industrial Rd",
    "iso:country":"US",
    "sg:address":"325 Industrial Rd",
    "sg:city":"Morganfield",
    "sg:classifiers":[
        {
            "category":"Manufacturing",
            "subcategory":"Tools & Machinery",
            "type":"Manufacturing & Wholesale Goods"
        }
    ],
    "sg:phone":"+1 270 389 4833",
    "sg:postcode":"42431",
    "sg:province":"KY",
    "sg:tags":[
        "equipment",
        "industrial",
        "supply"
    ],
    "wof:name":"Huff Technologies Inc",
    "wof:placetype":"venue"
},
  "geometry": {"coordinates":[-87.55015899999999,37.35779],"type":"Point"}
}