{
  "type": "Feature",
  "properties": {
    "addr:full":"503 Maple St Murray KY 42071",
    "addr:housenumber":"503",
    "addr:postcode":"42071",
    "addr:street":"Maple St",
    "iso:country":"US",
    "sg:address":"503 Maple St",
    "sg:city":"Murray",
    "sg:classifiers":[
        {
            "category":"Organizations",
            "subcategory":"Religious Organization",
            "type":"Services"
        }
    ],
    "sg:phone":"+1 270 753 3812",
    "sg:postcode":"42071",
    "sg:province":"KY",
    "sg:tags":[
        "church"
    ],
    "wof:name":"First United Methodist Church",
    "wof:placetype":"venue"
},
  "geometry": {"coordinates":[-88.30440299999999,36.609798],"type":"Point"}
}