{
  "type": "Feature",
  "properties": {
    "addr:full":"1400 Central Ave Louisville KY 40208",
    "addr:housenumber":"1400",
    "addr:postcode":"40208",
    "addr:street":"Central Ave",
    "iso:country":"US",
    "sg:address":"1400 Central Ave",
    "sg:city":"Louisville",
    "sg:classifiers":[
        {
            "category":"Bars & Pubs",
            "type":"Food & Drink"
        }
    ],
    "sg:phone":"+1 502 635 9239",
    "sg:postcode":"40208",
    "sg:province":"KY",
    "wof:name":"Dan's Bar",
    "wof:placetype":"venue"
},
  "geometry": {"coordinates":[-85.78111199999999,38.212799],"type":"Point"}
}