{
  "type": "Feature",
  "properties": {
    "iso:country":"US",
    "sg:address":"902 N 2nd St",
    "sg:city":"Central City",
    "sg:classifiers":[
        {
            "category":"Retail",
            "subcategory":"Auto Repair",
            "type":"Services"
        }
    ],
    "sg:phone":"+1 270 754 1830",
    "sg:postcode":"42330",
    "sg:province":"KY",
    "sg:tags":[
        "body",
        "automobile",
        "painting"
    ],
    "wof:name":"Oglesby's Body Shop",
    "wof:placetype":"venue"
},
  "geometry": {"coordinates":[-87.131196,37.305549],"type":"Point"}
}