{
  "type": "Feature",
  "properties": {
    "iso:country":"US",
    "sg:address":"1672 Perkins Ridge Rd",
    "sg:city":"Brooksville",
    "sg:classifiers":[
        {
            "category":"Real Estate",
            "subcategory":"Real Estate Operator",
            "type":"Services"
        }
    ],
    "sg:phone":"+1 606 747 5480",
    "sg:postcode":"41004",
    "sg:province":"KY",
    "sg:tags":[
        "property",
        "lessor"
    ],
    "wof:name":"Redden Cleon",
    "wof:placetype":"venue"
},
  "geometry": {"coordinates":[-84.15695700000001,38.716184],"type":"Point"}
}