{
  "type": "Feature",
  "properties": {
    "addr:full":"557 Kinsella Dr Covington KY 41017",
    "addr:housenumber":"557",
    "addr:postcode":"41017",
    "addr:street":"Kinsella Dr",
    "iso:country":"US",
    "sg:address":"557 Kinsella Dr",
    "sg:city":"Covington",
    "sg:classifiers":[
        {
            "category":"Building & Trades",
            "subcategory":"Construction",
            "type":"Services"
        }
    ],
    "sg:phone":"+1 859 341 1701",
    "sg:postcode":"41017",
    "sg:province":"KY",
    "sg:tags":[
        "concrete",
        "contractor"
    ],
    "wof:name":"Jackman Blacktop Inc",
    "wof:placetype":"venue"
},
  "geometry": {"coordinates":[-84.553988,39.004536],"type":"Point"}
}