{
  "type": "Feature",
  "properties": {
    "iso:country":"US",
    "sg:address":"220 Hamilton Ave",
    "sg:city":"Owensboro",
    "sg:classifiers":[
        {
            "category":"Recreation",
            "type":"Entertainment"
        }
    ],
    "sg:phone":"+1 270 684 7707",
    "sg:postcode":"42303",
    "sg:province":"KY",
    "sg:tags":[
        "amusement"
    ],
    "wof:name":"Gridiron Inc",
    "wof:placetype":"venue"
},
  "geometry": {"coordinates":[-87.09777099999999,37.775038],"type":"Point"}
}