{
  "type": "Feature",
  "properties": {
    "addr:full":"100 Fountain Ave Paducah KY 42001",
    "addr:housenumber":"100",
    "addr:postcode":"42001",
    "addr:street":"Fountain Ave",
    "iso:country":"US",
    "sg:address":"100 Fountain Ave",
    "sg:city":"Paducah",
    "sg:classifiers":[
        {
            "category":"Organizations",
            "subcategory":"Labor Organization",
            "type":"Services"
        }
    ],
    "sg:phone":"+1 270 442 2194",
    "sg:postcode":"42001",
    "sg:province":"KY",
    "wof:name":"Asbestos Workers Union",
    "wof:placetype":"venue"
},
  "geometry": {"coordinates":[-88.618003,37.079955],"type":"Point"}
}