{
  "type": "Feature",
  "properties": {
    "addr:full":"1126 Bardstown Rd Louisville KY 40204",
    "addr:housenumber":"1126",
    "addr:postcode":"40204",
    "addr:street":"Bardstown Rd",
    "iso:country":"US",
    "sg:address":"1126 Bardstown Rd",
    "sg:city":"Louisville",
    "sg:classifiers":[
        {
            "category":"Restaurant",
            "type":"Food & Drink"
        }
    ],
    "sg:phone":"+1 502 585 1116",
    "sg:postcode":"40204",
    "sg:province":"KY",
    "wof:name":"Rendezvous Diner",
    "wof:placetype":"venue"
},
  "geometry": {"coordinates":[-85.720726,38.238303],"type":"Point"}
}