{
  "type": "Feature",
  "properties": {
    "iso:country":"US",
    "sg:address":"2327 Manchester Rd",
    "sg:city":"Louisville",
    "sg:classifiers":[
        {
            "category":"Sports & Exercise",
            "subcategory":"Gym",
            "type":"Entertainment"
        }
    ],
    "sg:phone":"+1 502 454 4449",
    "sg:postcode":"40205",
    "sg:province":"KY",
    "sg:tags":[
        "instruction",
        "yoga"
    ],
    "wof:name":"Orbis Yoga Studio",
    "wof:placetype":"venue"
},
  "geometry": {"coordinates":[-85.670097,38.217541],"type":"Point"}
}