{
  "type": "Feature",
  "properties": {
    "addr:full":"6225 Elkhorn Rd Knifley KY 42753",
    "addr:housenumber":"6225",
    "addr:postcode":"42753",
    "addr:street":"Elkhorn Rd",
    "iso:country":"US",
    "sg:address":"6225 Elkhorn Rd",
    "sg:city":"Knifley",
    "sg:classifiers":[
        {
            "category":"Social Services",
            "subcategory":"Child Care",
            "type":"Services"
        }
    ],
    "sg:phone":"+1 270 849 2225",
    "sg:postcode":"42753",
    "sg:province":"KY",
    "wof:name":"Big Blue House Daycare",
    "wof:placetype":"venue"
},
  "geometry": {"coordinates":[-85.191671,37.246182],"type":"Point"}
}