{
  "type": "Feature",
  "properties": {
    "addr:full":"520 17th St Ashland KY 41101",
    "addr:housenumber":"520",
    "addr:postcode":"41101",
    "addr:street":"17Th St",
    "iso:country":"US",
    "sg:address":"520 17th St",
    "sg:city":"Ashland",
    "sg:classifiers":[
        {
            "category":"Education",
            "subcategory":"School",
            "type":"Public Place"
        }
    ],
    "sg:phone":"+1 606 327 2730",
    "sg:postcode":"41101",
    "sg:province":"KY",
    "wof:name":"Crabbe Elementary School",
    "wof:placetype":"venue"
},
  "geometry": {"coordinates":[-82.640486,38.475432],"type":"Point"}
}