{
  "type": "Feature",
  "properties": {
    "addr:full":"1898 Poplar Ridge Rd Melbourne KY 41059",
    "addr:housenumber":"1898",
    "addr:postcode":"41059",
    "addr:street":"Poplar Ridge Rd",
    "iso:country":"US",
    "sg:address":"1898 Poplar Ridge Rd",
    "sg:city":"Melbourne",
    "sg:classifiers":[
        {
            "category":"Animal Shelter",
            "type":"Public Place"
        },
        {
            "category":"Shopping",
            "subcategory":"Pets & Pet Supplies",
            "type":"Retail Goods"
        }
    ],
    "sg:phone":"+1 859 635 2819",
    "sg:postcode":"41059",
    "sg:province":"KY",
    "sg:tags":[
        "store"
    ],
    "wof:name":"Campbell County of Ky",
    "wof:placetype":"venue"
},
  "geometry": {"coordinates":[-84.36877200000001,38.986447],"type":"Point"}
}