{
  "type": "Feature",
  "properties": {
    "iso:country":"US",
    "sg:address":"4515 Taylorsville Rd",
    "sg:city":"Louisville",
    "sg:classifiers":[
        {
            "category":"Education",
            "subcategory":"School",
            "type":"Public Place"
        }
    ],
    "sg:phone":"+1 502 485 6950",
    "sg:postcode":"40220",
    "sg:province":"KY",
    "wof:name":"Kennedy Metro Middle School",
    "wof:placetype":"venue"
},
  "geometry": {"coordinates":[-85.599796,38.218674],"type":"Point"}
}