{
  "type": "Feature",
  "properties": {
    "iso:country":"US",
    "sg:address":"3728 Manslick Rd",
    "sg:city":"Louisville",
    "sg:classifiers":[
        {
            "category":"Wholesale",
            "subcategory":"Machinery & Supplies",
            "type":"Manufacturing & Wholesale Goods"
        }
    ],
    "sg:phone":"+1 800 937 9274",
    "sg:postcode":"40215",
    "sg:province":"KY",
    "sg:tags":[
        "equipment",
        "laundromat"
    ],
    "wof:name":"Commercial Laundry Distributors Inc.",
    "wof:placetype":"venue"
},
  "geometry": {"coordinates":[-85.801034,38.190795],"type":"Point"}
}