{
  "type": "Feature",
  "properties": {
    "iso:country":"US",
    "sg:address":"253 Jackie Way",
    "sg:city":"Rineyville",
    "sg:classifiers":[
        {
            "category":"Home & Garden",
            "subcategory":"Garden Supply",
            "type":"Retail Goods"
        }
    ],
    "sg:phone":"+1 270 234 9055",
    "sg:postcode":"40165",
    "sg:province":"KY",
    "wof:name":"Bonnie Ankarlo",
    "wof:placetype":"venue"
},
  "geometry": {"coordinates":[-85.696412,37.997315],"type":"Point"}
}