{
  "type": "Feature",
  "properties": {
    "addr:full":"1004 Grange Dr La Grange KY 40031",
    "addr:housenumber":"1004",
    "addr:postcode":"40031",
    "addr:street":"Grange Dr",
    "iso:country":"US",
    "sg:address":"1004 Grange Dr",
    "sg:city":"La Grange",
    "sg:classifiers":[
        {
            "category":"Restaurant",
            "type":"Food & Drink"
        }
    ],
    "sg:menulink":"http://www.allmenus.com/ky/la-grange/120569-subway/menu/",
    "sg:phone":"+1 502 225 4691",
    "sg:postcode":"40031",
    "sg:province":"KY",
    "sg:tags":[
        "american",
        "sandwich"
    ],
    "wof:name":"Subway",
    "wof:placetype":"venue"
},
  "geometry": {"coordinates":[-85.364199,38.403718],"type":"Point"}
}