{
  "type": "Feature",
  "properties": {
    "iso:country":"US",
    "sg:address":"4036 Dutchmans Ln",
    "sg:city":"St Matthews",
    "sg:classifiers":[
        {
            "category":"Shopping",
            "subcategory":"Optical Goods",
            "type":"Retail Goods"
        }
    ],
    "sg:phone":"+1 502 895 2020",
    "sg:postcode":"40207",
    "sg:province":"KY",
    "wof:name":"Korrect Optical",
    "wof:placetype":"venue"
},
  "geometry": {"coordinates":[-85.62984899999999,38.236008],"type":"Point"}
}