{
  "type": "Feature",
  "properties": {
    "iso:country":"US",
    "sg:address":"8905 Lakeridge Dr",
    "sg:city":"Louisville",
    "sg:classifiers":[
        {
            "category":"Building & Trades",
            "subcategory":"Construction",
            "type":"Services"
        }
    ],
    "sg:phone":"+1 502 367 7706",
    "sg:postcode":"40272",
    "sg:province":"KY",
    "sg:tags":[
        "concrete",
        "contractor"
    ],
    "wof:name":"Advanced Concrete Lifting Svc",
    "wof:placetype":"venue"
},
  "geometry": {"coordinates":[-85.817402,38.123991],"type":"Point"}
}