{
  "type": "Feature",
  "properties": {
    "addr:full":"813 Hawkins Dr Elizabethtown KY 42701",
    "addr:housenumber":"813",
    "addr:postcode":"42701",
    "addr:street":"Hawkins Dr",
    "iso:country":"US",
    "sg:address":"813 Hawkins Dr",
    "sg:city":"Elizabethtown",
    "sg:classifiers":[
        {
            "category":"Shopping",
            "subcategory":"Clothing, Apparel, & Fashions",
            "type":"Retail Goods"
        }
    ],
    "sg:phone":"+1 270 765 4517",
    "sg:postcode":"42701",
    "sg:province":"KY",
    "sg:tags":[
        "navy",
        "army"
    ],
    "sg:website":"www.conderspaintball.com",
    "wof:name":"Conder's Army Surplus",
    "wof:placetype":"venue"
},
  "geometry": {"coordinates":[-85.84711299999999,37.680834],"type":"Point"}
}