{
  "type": "Feature",
  "properties": {
    "iso:country":"US",
    "sg:address":"104 W Green St",
    "sg:city":"Versailles",
    "sg:classifiers":[
        {
            "category":"Shopping",
            "type":"Retail Goods"
        }
    ],
    "sg:phone":"+1 859 873 2250",
    "sg:postcode":"40383",
    "sg:province":"KY",
    "sg:tags":[
        "pet",
        "food",
        "supply"
    ],
    "wof:name":"Quality Feeds",
    "wof:placetype":"venue"
},
  "geometry": {"coordinates":[-84.730228,38.05413],"type":"Point"}
}