{
  "type": "Feature",
  "properties": {
    "iso:country":"US",
    "sg:address":"1040 Scott Blvd",
    "sg:city":"Covington",
    "sg:classifiers":[
        {
            "category":"Organizations",
            "subcategory":"Religious Organization",
            "type":"Services"
        }
    ],
    "sg:phone":"+1 859 261 8619",
    "sg:postcode":"41011",
    "sg:province":"KY",
    "wof:name":"Church of God",
    "wof:placetype":"venue"
},
  "geometry": {"coordinates":[-84.50761799999999,39.080279],"type":"Point"}
}