{
  "type": "Feature",
  "properties": {
    "iso:country":"US",
    "sg:address":"125 Hickory Pl",
    "sg:city":"Corbin",
    "sg:classifiers":[
        {
            "category":"Building & Trades",
            "subcategory":"Construction",
            "type":"Services"
        }
    ],
    "sg:phone":"+1 606 528 6352",
    "sg:postcode":"40701",
    "sg:province":"KY",
    "sg:tags":[
        "roofing",
        "contractor"
    ],
    "wof:name":"Mel Chandler Contracting Inc",
    "wof:placetype":"venue"
},
  "geometry": {"coordinates":[-84.108689,36.924422],"type":"Point"}
}