{
  "type": "Feature",
  "properties": {
    "iso:country":"US",
    "sg:address":"285 Industrial Pkwy",
    "sg:city":"Dawson Springs",
    "sg:classifiers":[
        {
            "category":"Freight",
            "type":"Transportation"
        }
    ],
    "sg:phone":"+1 270 797 2555",
    "sg:postcode":"42408",
    "sg:province":"KY",
    "sg:tags":[
        "commercial",
        "storage"
    ],
    "wof:name":"Storage Express",
    "wof:placetype":"venue"
},
  "geometry": {"coordinates":[-87.680312,37.175849],"type":"Point"}
}