{
  "type": "Feature",
  "properties": {
    "addr:full":"3733 Pamela Rae Dr Louisville KY 40241",
    "addr:housenumber":"3733",
    "addr:postcode":"40241",
    "addr:street":"Pamela Rae Dr",
    "iso:country":"US",
    "sg:address":"3733 Pamela Rae Dr",
    "sg:city":"Louisville",
    "sg:classifiers":[
        {
            "category":"Retail",
            "subcategory":"Car Wash",
            "type":"Services"
        }
    ],
    "sg:phone":"+1 502 412 5525",
    "sg:postcode":"40241",
    "sg:province":"KY",
    "sg:tags":[
        "polishing",
        "washing"
    ],
    "wof:name":"Aqua Star",
    "wof:placetype":"venue"
},
  "geometry": {"coordinates":[-85.54154699999999,38.30026],"type":"Point"}
}