{
  "type": "Feature",
  "properties": {
    "iso:country":"US",
    "sg:address":"301 Iroquois Dr",
    "sg:city":"Paducah",
    "sg:classifiers":[
        {
            "category":"Real Estate",
            "subcategory":"Real Estate Operator",
            "type":"Services"
        }
    ],
    "sg:phone":"+1 270 554 5760",
    "sg:postcode":"42001",
    "sg:province":"KY",
    "sg:tags":[
        "apartment"
    ],
    "sg:website":"http://www.foxharborapartments.com",
    "wof:name":"Fox Harbor Apartments",
    "wof:placetype":"venue"
},
  "geometry": {"coordinates":[-88.663483,37.04731],"type":"Point"}
}