{
  "type": "Feature",
  "properties": {
    "iso:country":"US",
    "sg:address":"1481 Dixie Hwy",
    "sg:city":"Park Hills",
    "sg:classifiers":[
        {
            "category":"Retail",
            "subcategory":"Repair Shop",
            "type":"Services"
        }
    ],
    "sg:phone":"+1 859 331 5055",
    "sg:postcode":"41011",
    "sg:province":"KY",
    "sg:tags":[
        "upholsterer"
    ],
    "wof:name":"Jim Cline Upholstering",
    "wof:placetype":"venue"
},
  "geometry": {"coordinates":[-84.52879900000001,39.068372],"type":"Point"}
}