{
  "type": "Feature",
  "properties": {
    "iso:country":"US",
    "sg:address":"109 Joe B Hall Ct",
    "sg:city":"Cynthiana",
    "sg:classifiers":[
        {
            "category":"Government",
            "subcategory":"Office",
            "type":"Public Place"
        }
    ],
    "sg:phone":"+1 859 234 7180",
    "sg:postcode":"41031",
    "sg:province":"KY",
    "sg:tags":[
        "county",
        "safety",
        "order"
    ],
    "wof:name":"Harrison County Disaster Svc",
    "wof:placetype":"venue"
},
  "geometry": {"coordinates":[-84.29822799999999,38.390353],"type":"Point"}
}