{
  "type": "Feature",
  "properties": {
    "iso:country":"US",
    "sg:address":"11876 Capital Way",
    "sg:city":"Louisville",
    "sg:classifiers":[
        {
            "category":"Manufacturing",
            "subcategory":"Buildings",
            "type":"Manufacturing & Wholesale Goods"
        },
        {
            "category":"Structure",
            "subcategory":"Warehouse",
            "type":"Public Place"
        },
        {
            "category":"Building & Trades",
            "subcategory":"Construction",
            "type":"Services"
        }
    ],
    "sg:phone":"+1 502 266 0139",
    "sg:postcode":"40299",
    "sg:province":"KY",
    "sg:tags":[
        "warehouses-merchandise",
        "warehouses-public-commercial",
        "builder",
        "contractor",
        "home",
        "estimate"
    ],
    "wof:name":"Shelcon Construction Company",
    "wof:placetype":"venue"
},
  "geometry": {"coordinates":[-85.537712,38.207202],"type":"Point"}
}