{
  "type": "Feature",
  "properties": {
    "addr:full":"4169 Westport Rd St Matthews KY 40207",
    "addr:housenumber":"4169",
    "addr:postcode":"40207",
    "addr:street":"Westport Rd",
    "iso:country":"US",
    "sg:address":"4169 Westport Rd",
    "sg:city":"St Matthews",
    "sg:classifiers":[
        {
            "category":"Real Estate",
            "subcategory":"Real Estate Agent",
            "type":"Services"
        }
    ],
    "sg:phone":"+1 502 895 4297",
    "sg:postcode":"40207",
    "sg:province":"KY",
    "wof:name":"Fielding H Dickey Builders",
    "wof:placetype":"venue"
},
  "geometry": {"coordinates":[-85.64812499999999,38.257282],"type":"Point"}
}