{
  "type": "Feature",
  "properties": {
    "iso:country":"US",
    "sg:address":"4000 Fort Campbell Blvd",
    "sg:city":"Hopkinsville",
    "sg:classifiers":[
        {
            "category":"Shopping",
            "subcategory":"Beauty & Cosmetics",
            "type":"Retail Goods"
        }
    ],
    "sg:phone":"+1 270 886 3731",
    "sg:postcode":"42240",
    "sg:province":"KY",
    "sg:tags":[
        "merchandise"
    ],
    "wof:name":"Merle Norman Cosmetics",
    "wof:placetype":"venue"
},
  "geometry": {"coordinates":[-87.473707,36.833692],"type":"Point"}
}