{
  "type": "Feature",
  "properties": {
    "addr:full":"200 Ohio St Paducah KY 42003",
    "addr:housenumber":"200",
    "addr:postcode":"42003",
    "addr:street":"Ohio St",
    "iso:country":"US",
    "sg:address":"200 Ohio St",
    "sg:city":"Paducah",
    "sg:classifiers":[
        {
            "category":"Marine",
            "type":"Transportation"
        }
    ],
    "sg:phone":"+1 270 443 7223",
    "sg:postcode":"42003",
    "sg:province":"KY",
    "sg:tags":[
        "towing"
    ],
    "wof:name":"Inland Management Inc",
    "wof:placetype":"venue"
},
  "geometry": {"coordinates":[-88.591537,37.081334],"type":"Point"}
}