{
  "type": "Feature",
  "properties": {
    "addr:full":"2828 Lincoln Park Rd Springfield KY 40069",
    "addr:housenumber":"2828",
    "addr:postcode":"40069",
    "addr:street":"Lincoln Park Rd",
    "iso:country":"US",
    "sg:address":"2828 Lincoln Park Rd",
    "sg:city":"Springfield",
    "sg:classifiers":[
        {
            "category":"Retail",
            "subcategory":"Repair Shop",
            "type":"Services"
        }
    ],
    "sg:phone":"+1 859 336 7731",
    "sg:postcode":"40069",
    "sg:province":"KY",
    "sg:tags":[
        "appliance"
    ],
    "wof:name":"Sunshine Center Appliance",
    "wof:placetype":"venue"
},
  "geometry": {"coordinates":[-85.219601,37.721118],"type":"Point"}
}