{
  "type": "Feature",
  "properties": {
    "iso:country":"US",
    "sg:address":"1910 Harrodsburg Rd",
    "sg:city":"Lexington",
    "sg:classifiers":[
        {
            "category":"Building & Trades",
            "subcategory":"Construction",
            "type":"Services"
        }
    ],
    "sg:phone":"+1 859 276 1811",
    "sg:postcode":"40503",
    "sg:province":"KY",
    "sg:tags":[
        "home",
        "improvement"
    ],
    "wof:name":"Handyman Connection",
    "wof:placetype":"venue"
},
  "geometry": {"coordinates":[-84.532028,38.028222],"type":"Point"}
}