{
  "type": "Feature",
  "properties": {
    "addr:full":"1480 Island Fork Rd Morehead KY 40351",
    "addr:housenumber":"1480",
    "addr:postcode":"40351",
    "addr:street":"Island Fork Rd",
    "iso:country":"US",
    "sg:address":"1480 Island Fork Rd",
    "sg:city":"Morehead",
    "sg:classifiers":[
        {
            "category":"Retail",
            "subcategory":"Repair Shop",
            "type":"Services"
        }
    ],
    "sg:phone":"+1 859 498 8859",
    "sg:postcode":"40351",
    "sg:province":"KY",
    "sg:tags":[
        "lock",
        "locksmith"
    ],
    "wof:name":"All Area Locksmith",
    "wof:placetype":"venue"
},
  "geometry": {"coordinates":[-83.445243,38.339441],"type":"Point"}
}