{
  "type": "Feature",
  "properties": {
    "iso:country":"US",
    "sg:address":"2000 Fern Valley Rd",
    "sg:city":"Louisville",
    "sg:classifiers":[
        {
            "category":"Wholesale",
            "subcategory":"Machinery & Supplies",
            "type":"Manufacturing & Wholesale Goods"
        }
    ],
    "sg:phone":"+1 502 368 0021",
    "sg:postcode":"40213",
    "sg:province":"KY",
    "wof:name":"Burns Machinery",
    "wof:placetype":"venue"
},
  "geometry": {"coordinates":[-85.725729,38.157686],"type":"Point"}
}