{
  "type": "Feature",
  "properties": {
    "iso:country":"US",
    "sg:address":"657 Poplar Springs Ln",
    "sg:city":"Lexington",
    "sg:classifiers":[
        {
            "category":"Professional",
            "subcategory":"Art Services",
            "type":"Services"
        }
    ],
    "sg:phone":"+1 859 271 6650",
    "sg:postcode":"40515",
    "sg:province":"KY",
    "sg:tags":[
        "graphic",
        "designer"
    ],
    "wof:name":"Media Vision Graphics",
    "wof:placetype":"venue"
},
  "geometry": {"coordinates":[-84.515069,37.960872],"type":"Point"}
}