{
  "type": "Feature",
  "properties": {
    "iso:country":"US",
    "sg:address":"150 Cherry Hill Rd",
    "sg:city":"Brandenburg",
    "sg:classifiers":[
        {
            "category":"Building & Trades",
            "subcategory":"Construction",
            "type":"Services"
        }
    ],
    "sg:phone":"+1 270 828 5360",
    "sg:postcode":"40108",
    "sg:province":"KY",
    "sg:tags":[
        "resurfacing",
        "laying",
        "refinishing",
        "floor"
    ],
    "wof:name":"Strictly Hardwoods",
    "wof:placetype":"venue"
},
  "geometry": {"coordinates":[-86.140046,37.93892],"type":"Point"}
}