{
  "type": "Feature",
  "properties": {
    "iso:country":"US",
    "sg:address":"161 Summit Rd",
    "sg:city":"Summit",
    "sg:classifiers":[
        {
            "category":"Restaurant",
            "type":"Food & Drink"
        }
    ],
    "sg:phone":"+1 270 862 2363",
    "sg:postcode":"42732",
    "sg:province":"KY",
    "sg:tags":[
        "delicatessen"
    ],
    "wof:name":"Sandra Lynn's General Store",
    "wof:placetype":"venue"
},
  "geometry": {"coordinates":[-86.08031,37.566217],"type":"Point"}
}