{
  "type": "Feature",
  "properties": {
    "iso:country":"US",
    "sg:address":"562 University Dr",
    "sg:city":"Prestonsburg",
    "sg:classifiers":[
        {
            "category":"Organizations",
            "subcategory":"Religious Organization",
            "type":"Services"
        }
    ],
    "sg:phone":"+1 606 886 8046",
    "sg:postcode":"41653",
    "sg:province":"KY",
    "sg:tags":[
        "church"
    ],
    "wof:name":"St James Episcopal Church",
    "wof:placetype":"venue"
},
  "geometry": {"coordinates":[-82.780793,37.681593],"type":"Point"}
}