{
  "type": "Feature",
  "properties": {
    "iso:country":"US",
    "sg:address":"1570 Fairground Rd",
    "sg:city":"Brandenburg",
    "sg:classifiers":[
        {
            "category":"Autos & Motor Vehicles",
            "subcategory":"Auto Supplies",
            "type":"Retail Goods"
        }
    ],
    "sg:phone":"+1 270 422 4100",
    "sg:postcode":"40108",
    "sg:province":"KY",
    "sg:tags":[
        "automobile",
        "parts"
    ],
    "wof:name":"Triangle Auto Parts",
    "wof:placetype":"venue"
},
  "geometry": {"coordinates":[-86.198645,37.997011],"type":"Point"}
}