{
  "type": "Feature",
  "properties": {
    "iso:country":"US",
    "sg:address":"79 Turnip Branch",
    "sg:city":"Phelps",
    "sg:classifiers":[
        {
            "category":"Cinema",
            "subcategory":"Movie Rental",
            "type":"Entertainment"
        }
    ],
    "sg:phone":"+1 606 456 3863",
    "sg:postcode":"41553",
    "sg:province":"KY",
    "sg:tags":[
        "video",
        "tape"
    ],
    "wof:name":"Discount Video",
    "wof:placetype":"venue"
},
  "geometry": {"coordinates":[-82.154861,37.459034],"type":"Point"}
}