{
  "type": "Feature",
  "properties": {
    "addr:full":"3205 7th Street Rd Louisville KY 40216",
    "addr:housenumber":"3205",
    "addr:postcode":"40216",
    "addr:street":"7Th Street Rd",
    "iso:country":"US",
    "sg:address":"3205 7th Street Rd",
    "sg:city":"Louisville",
    "sg:classifiers":[
        {
            "category":"Shopping",
            "subcategory":"Bicycles & Sporting Goods",
            "type":"Retail Goods"
        },
        {
            "category":"Personal",
            "subcategory":"Day Spa",
            "type":"Services"
        },
        {
            "category":"Sports & Exercise",
            "subcategory":"Swimming Pool",
            "type":"Entertainment"
        }
    ],
    "sg:phone":"+1 502 637 5533",
    "sg:postcode":"40216",
    "sg:province":"KY",
    "sg:tags":[
        "repair",
        "consulting",
        "supply",
        "equipment",
        "hot",
        "designing",
        "tub"
    ],
    "sg:website":"http://www.stuartbauerpools.com",
    "wof:name":"Bauer Stuart Pools & Spas Inc",
    "wof:placetype":"venue"
},
  "geometry": {"coordinates":[-85.791223,38.203699],"type":"Point"}
}