{
  "type": "Feature",
  "properties": {
    "iso:country":"US",
    "sg:address":"1940 Campus Pl",
    "sg:city":"Louisville",
    "sg:classifiers":[
        {
            "category":"Building & Trades",
            "subcategory":"Electrical",
            "type":"Services"
        }
    ],
    "sg:phone":"+1 502 261 1939",
    "sg:postcode":"40299",
    "sg:province":"KY",
    "sg:tags":[
        "electric",
        "contractor"
    ],
    "wof:name":"Kentuckiana Maintenance & Elec",
    "wof:placetype":"venue"
},
  "geometry": {"coordinates":[-85.53537799999999,38.214179],"type":"Point"}
}