{
  "type": "Feature",
  "properties": {
    "iso:country":"US",
    "sg:address":"321 N Mulberry St",
    "sg:city":"Elizabethtown",
    "sg:classifiers":[
        {
            "category":"Shopping",
            "subcategory":"Jewelry",
            "type":"Retail Goods"
        }
    ],
    "sg:phone":"+1 270 769 3919",
    "sg:postcode":"42701",
    "sg:province":"KY",
    "wof:name":"Executive Goldsmith",
    "wof:placetype":"venue"
},
  "geometry": {"coordinates":[-85.856245,37.697405],"type":"Point"}
}