{
  "type": "Feature",
  "properties": {
    "iso:country":"US",
    "sg:address":"620 N 3rd St",
    "sg:city":"Bardstown",
    "sg:classifiers":[
        {
            "category":"Mining & Drilling",
            "type":"Manufacturing & Wholesale Goods"
        }
    ],
    "sg:phone":"+1 502 349 3080",
    "sg:postcode":"40004",
    "sg:province":"KY",
    "sg:tags":[
        "oil",
        "gas",
        "producer"
    ],
    "wof:name":"Oil Express Inc",
    "wof:placetype":"venue"
},
  "geometry": {"coordinates":[-85.464035,37.817696],"type":"Point"}
}