{
  "type": "Feature",
  "properties": {
    "iso:country":"US",
    "sg:address":"460 E Main St",
    "sg:city":"Lexington",
    "sg:classifiers":[
        {
            "category":"Organizations",
            "subcategory":"Religious Organization",
            "type":"Services"
        }
    ],
    "sg:phone":"+1 859 254 7768",
    "sg:postcode":"40507",
    "sg:province":"KY",
    "sg:tags":[
        "church"
    ],
    "sg:website":"www.2preslex.org",
    "wof:name":"Second Presbyterian Church",
    "wof:placetype":"venue"
},
  "geometry": {"coordinates":[-84.489279,38.039438],"type":"Point"}
}