{
  "type": "Feature",
  "properties": {
    "iso:country":"US",
    "sg:address":"305 Elm St",
    "sg:city":"Richmond",
    "sg:classifiers":[
        {
            "category":"Organizations",
            "subcategory":"Religious Organization",
            "type":"Services"
        }
    ],
    "sg:phone":"+1 859 623 7407",
    "sg:postcode":"40475",
    "sg:province":"KY",
    "sg:tags":[
        "church"
    ],
    "wof:name":"Elizabeth Predestarian Baptist",
    "wof:placetype":"venue"
},
  "geometry": {"coordinates":[-84.28870499999999,37.749308],"type":"Point"}
}