{
  "type": "Feature",
  "properties": {
    "iso:country":"US",
    "sg:address":"2525 Lake Pointe",
    "sg:city":"Owensboro",
    "sg:classifiers":[
        {
            "category":"Wholesale",
            "subcategory":"Groceries",
            "type":"Manufacturing & Wholesale Goods"
        }
    ],
    "sg:phone":"+1 270 688 8491",
    "sg:postcode":"42301",
    "sg:province":"KY",
    "wof:name":"Bluegrass Distributors",
    "wof:placetype":"venue"
},
  "geometry": {"coordinates":[-87.15468799999999,37.723659],"type":"Point"}
}