{
  "type": "Feature",
  "properties": {
    "iso:country":"US",
    "sg:address":"2307 Greene Way",
    "sg:city":"Louisville",
    "sg:classifiers":[
        {
            "category":"Health Services",
            "subcategory":"Medical Lab",
            "type":"Services"
        }
    ],
    "sg:phone":"+1 502 491 3484",
    "sg:postcode":"40220",
    "sg:province":"KY",
    "sg:tags":[
        "laboratory"
    ],
    "wof:name":"Quest Diagnostics Inc",
    "wof:placetype":"venue"
},
  "geometry": {"coordinates":[-85.597742,38.213881],"type":"Point"}
}