{
  "type": "Feature",
  "properties": {
    "iso:country":"US",
    "sg:address":"1500 Gaither Station Rd",
    "sg:city":"Elizabethtown",
    "sg:classifiers":[
        {
            "category":"Railroad",
            "type":"Transportation"
        }
    ],
    "sg:phone":"+1 270 234 8234",
    "sg:postcode":"42701",
    "sg:province":"KY",
    "wof:name":"CSX",
    "wof:placetype":"venue"
},
  "geometry": {"coordinates":[-85.899885,37.659039],"type":"Point"}
}