{
  "type": "Feature",
  "properties": {
    "iso:country":"US",
    "sg:address":"2042 Kingston Hwy",
    "sg:city":"Richmond",
    "sg:classifiers":[
        {
            "category":"Building & Trades",
            "subcategory":"Construction",
            "type":"Services"
        }
    ],
    "sg:phone":"+1 859 625 1191",
    "sg:postcode":"40475",
    "sg:province":"KY",
    "sg:tags":[
        "woodworker"
    ],
    "wof:name":"Custom Woodwork",
    "wof:placetype":"venue"
},
  "geometry": {"coordinates":[-84.25729800000001,37.680785],"type":"Point"}
}