{
  "type": "Feature",
  "properties": {
    "iso:country":"US",
    "sg:address":"103 Langdon St",
    "sg:city":"Somerset",
    "sg:classifiers":[
        {
            "category":"Organizations",
            "subcategory":"Religious Organization",
            "type":"Services"
        }
    ],
    "sg:phone":"+1 606 678 8874",
    "sg:postcode":"42501",
    "sg:province":"KY",
    "sg:tags":[
        "church"
    ],
    "sg:website":"www.langdonstreetbaptistchurch.com",
    "wof:name":"Langdon Street Baptist Church",
    "wof:placetype":"venue"
},
  "geometry": {"coordinates":[-84.610782,37.081309],"type":"Point"}
}