{
  "type": "Feature",
  "properties": {
    "iso:country":"US",
    "sg:address":"2920 Frankfort Ave",
    "sg:city":"Louisville",
    "sg:classifiers":[
        {
            "category":"Home & Garden",
            "subcategory":"Garden Supply",
            "type":"Retail Goods"
        }
    ],
    "sg:phone":"+1 502 632 1877",
    "sg:postcode":"40206",
    "sg:province":"KY",
    "wof:name":"Bluegrass Organics",
    "wof:placetype":"venue"
},
  "geometry": {"coordinates":[-85.685371,38.25462],"type":"Point"}
}