{
  "type": "Feature",
  "properties": {
    "iso:country":"US",
    "sg:address":"101 N Hurstbourne Pkwy",
    "sg:city":"Louisville",
    "sg:classifiers":[
        {
            "category":"Restaurant",
            "type":"Food & Drink"
        }
    ],
    "sg:phone":"+1 502 412 4545",
    "sg:postcode":"40222",
    "sg:province":"KY",
    "sg:tags":[
        "shop",
        "coffee"
    ],
    "wof:name":"Starbucks",
    "wof:placetype":"venue"
},
  "geometry": {"coordinates":[-85.577651,38.248145],"type":"Point"}
}