{
  "type": "Feature",
  "properties": {
    "iso:country":"US",
    "sg:address":"133 Copperfield Ln",
    "sg:city":"Georgetown",
    "sg:classifiers":[
        {
            "category":"Home & Garden",
            "subcategory":"Home Furnishings",
            "type":"Retail Goods"
        }
    ],
    "sg:phone":"+1 502 863 3590",
    "sg:postcode":"40324",
    "sg:province":"KY",
    "sg:tags":[
        "venetian",
        "blind"
    ],
    "wof:name":"Classic Blinds",
    "wof:placetype":"venue"
},
  "geometry": {"coordinates":[-84.579577,38.200461],"type":"Point"}
}