{
  "type": "Feature",
  "properties": {
    "addr:full":"158 E 2nd St Maysville KY 41056",
    "addr:housenumber":"158",
    "addr:postcode":"41056",
    "addr:street":"E 2Nd St",
    "iso:country":"US",
    "sg:address":"158 E 2nd St",
    "sg:city":"Maysville",
    "sg:classifiers":[
        {
            "category":"Insurance",
            "subcategory":"Insurance Agent",
            "type":"Services"
        }
    ],
    "sg:phone":"+1 606 564 3171",
    "sg:postcode":"41056",
    "sg:province":"KY",
    "wof:name":"Western-Southern Life Ins Co",
    "wof:placetype":"venue"
},
  "geometry": {"coordinates":[-83.760295,38.645952],"type":"Point"}
}