{
  "type": "Feature",
  "properties": {
    "iso:country":"US",
    "sg:address":"203 Cooper Dr",
    "sg:city":"Lexington",
    "sg:classifiers":[
        {
            "category":"Education",
            "subcategory":"College",
            "type":"Public Place"
        }
    ],
    "sg:phone":"+1 859 257 8633",
    "sg:postcode":"40502",
    "sg:province":"KY",
    "sg:tags":[
        "university"
    ],
    "wof:name":"Forestry Department",
    "wof:placetype":"venue"
},
  "geometry": {"coordinates":[-84.51061799999999,38.02809],"type":"Point"}
}