{
  "type": "Feature",
  "properties": {
    "iso:country":"US",
    "sg:address":"1402 Frederica St",
    "sg:city":"Owensboro",
    "sg:classifiers":[
        {
            "category":"Social Services",
            "subcategory":"Job Training",
            "type":"Services"
        }
    ],
    "sg:phone":"+1 270 688 8055",
    "sg:postcode":"42301",
    "sg:province":"KY",
    "sg:tags":[
        "rehabilitation"
    ],
    "wof:name":"Bluegrass Rehab Ctr",
    "wof:placetype":"venue"
},
  "geometry": {"coordinates":[-87.112453,37.762065],"type":"Point"}
}