{
  "type": "Feature",
  "properties": {
    "iso:country":"US",
    "sg:address":"5316 Matterhorn Dr",
    "sg:city":"Louisville",
    "sg:classifiers":[
        {
            "category":"Professional",
            "subcategory":"Business Services",
            "type":"Services"
        }
    ],
    "sg:phone":"+1 502 449 7776",
    "sg:postcode":"40216",
    "sg:province":"KY",
    "wof:name":"Wiley By Design Inc",
    "wof:placetype":"venue"
},
  "geometry": {"coordinates":[-85.85405799999999,38.166468],"type":"Point"}
}