{
  "type": "Feature",
  "properties": {
    "addr:full":"424 N Main St Beaver Dam KY 42320",
    "addr:housenumber":"424",
    "addr:postcode":"42320",
    "addr:street":"N Main St",
    "iso:country":"US",
    "sg:address":"424 N Main St",
    "sg:city":"Beaver Dam",
    "sg:classifiers":[
        {
            "category":"Insurance",
            "subcategory":"Insurance Agent",
            "type":"Services"
        }
    ],
    "sg:phone":"+1 270 274 2322",
    "sg:postcode":"42320",
    "sg:province":"KY",
    "wof:name":"Berryman Insurance",
    "wof:placetype":"venue"
},
  "geometry": {"coordinates":[-86.875733,37.405119],"type":"Point"}
}