{
  "type": "Feature",
  "properties": {
    "iso:country":"US",
    "sg:address":"118 N Vinson Ave",
    "sg:city":"Louisa",
    "sg:classifiers":[
        {
            "category":"Restaurant",
            "type":"Food & Drink"
        }
    ],
    "sg:phone":"+1 606 638 3331",
    "sg:postcode":"41230",
    "sg:province":"KY",
    "sg:tags":[
        "shop",
        "coffee"
    ],
    "wof:name":"Big Sandy Coffee House",
    "wof:placetype":"venue"
},
  "geometry": {"coordinates":[-82.603202,38.117477],"type":"Point"}
}