{
  "type": "Feature",
  "properties": {
    "iso:country":"US",
    "sg:address":"101 Kentucky Ave",
    "sg:city":"Sandy Hook",
    "sg:classifiers":[
        {
            "category":"Autos & Motor Vehicles",
            "subcategory":"Automobile Sales",
            "type":"Retail Goods"
        }
    ],
    "sg:phone":"+1 606 738 6910",
    "sg:postcode":"41144",
    "sg:province":"KY",
    "sg:tags":[
        "car",
        "dealer"
    ],
    "sg:website":"www.tenaska.com",
    "wof:name":"Central Auto Sales",
    "wof:placetype":"venue"
},
  "geometry": {"coordinates":[-82.78424099999999,38.548476],"type":"Point"}
}