{
  "type": "Feature",
  "properties": {
    "iso:country":"US",
    "sg:address":"408 Blankenbaker Pkwy",
    "sg:city":"Louisville",
    "sg:classifiers":[
        {
            "category":"Professional",
            "subcategory":"Accounting & Tax Preparation",
            "type":"Services"
        }
    ],
    "sg:phone":"+1 502 426 0809",
    "sg:postcode":"40243",
    "sg:province":"KY",
    "sg:tags":[
        "accountant"
    ],
    "wof:name":"Sherl L Fetter CPA",
    "wof:placetype":"venue"
},
  "geometry": {"coordinates":[-85.54450799999999,38.237632],"type":"Point"}
}