{
  "type": "Feature",
  "properties": {
    "addr:full":"2001 Russell Dyche Memorial Hwy London KY 40741",
    "addr:housenumber":"2001",
    "addr:postcode":"40741",
    "addr:street":"Russell Dyche Memorial Hwy",
    "iso:country":"US",
    "sg:address":"2001 Russell Dyche Memorial Hwy",
    "sg:city":"London",
    "sg:classifiers":[
        {
            "category":"Home & Garden",
            "subcategory":"Building Materials",
            "type":"Retail Goods"
        }
    ],
    "sg:phone":"+1 606 877 2073",
    "sg:postcode":"40741",
    "sg:province":"KY",
    "sg:tags":[
        "lumber"
    ],
    "wof:name":"Begley Lumber Co",
    "wof:placetype":"venue"
},
  "geometry": {"coordinates":[-84.118453,37.149499],"type":"Point"}
}