{
  "type": "Feature",
  "properties": {
    "iso:country":"US",
    "sg:address":"607 E Saint Catherine St",
    "sg:city":"Louisville",
    "sg:classifiers":[
        {
            "category":"Place Of Worship",
            "subcategory":"Church",
            "type":"Public Place"
        },
        {
            "category":"Place Of Worship",
            "type":"Public Place"
        }
    ],
    "sg:phone":"+1 502 634 9518",
    "sg:postcode":"40203",
    "sg:province":"KY",
    "sg:tags":[
        "christ",
        "churches-community"
    ],
    "wof:name":"Grace United Community Church, Inc.",
    "wof:placetype":"venue"
},
  "geometry": {"coordinates":[-85.745153,38.235114],"type":"Point"}
}