{
  "type": "Feature",
  "properties": {
    "iso:country":"US",
    "sg:address":"314 Dixie Hwy N",
    "sg:city":"Radcliff",
    "sg:classifiers":[
        {
            "category":"Building & Trades",
            "subcategory":"Equipment Rental",
            "type":"Services"
        }
    ],
    "sg:phone":"+1 270 352 3060",
    "sg:postcode":"40160",
    "sg:province":"KY",
    "sg:tags":[
        "yard"
    ],
    "wof:name":"Rent-A-Center",
    "wof:placetype":"venue"
},
  "geometry": {"coordinates":[-85.94270899999999,37.84488],"type":"Point"}
}