{
  "type": "Feature",
  "properties": {
    "addr:full":"4620 Bittersweet Rd Louisville KY 40218",
    "addr:housenumber":"4620",
    "addr:postcode":"40218",
    "addr:street":"Bittersweet Rd",
    "iso:country":"US",
    "sg:address":"4620 Bittersweet Rd",
    "sg:city":"Louisville",
    "sg:classifiers":[
        {
            "category":"Retail",
            "subcategory":"Auto Repair",
            "type":"Services"
        }
    ],
    "sg:phone":"+1 502 969 2617",
    "sg:postcode":"40218",
    "sg:province":"KY",
    "sg:tags":[
        "body",
        "automobile",
        "painting",
        "repairing"
    ],
    "wof:name":"C & O Body Shop And Garage Inc",
    "wof:placetype":"venue"
},
  "geometry": {"coordinates":[-85.69048100000001,38.187877],"type":"Point"}
}