{
  "type": "Feature",
  "properties": {
    "iso:country":"US",
    "sg:address":"914 Paducah Rd",
    "sg:city":"Mayfield",
    "sg:classifiers":[
        {
            "category":"Retail",
            "subcategory":"Auto Repair",
            "type":"Services"
        }
    ],
    "sg:phone":"+1 270 247 8722",
    "sg:postcode":"42066",
    "sg:province":"KY",
    "sg:tags":[
        "truck"
    ],
    "wof:name":"Mauney's Diesel Svc",
    "wof:placetype":"venue"
},
  "geometry": {"coordinates":[-88.638668,36.751792],"type":"Point"}
}