{
  "type": "Feature",
  "properties": {
    "iso:country":"US",
    "sg:address":"801 W Broadway",
    "sg:city":"Louisville",
    "sg:classifiers":[
        {
            "category":"Government",
            "subcategory":"Office",
            "type":"Public Place"
        }
    ],
    "sg:phone":"+1 502 583 2769",
    "sg:postcode":"40202",
    "sg:province":"KY",
    "wof:name":"U S Government",
    "wof:placetype":"venue"
},
  "geometry": {"coordinates":[-85.76503,38.24667],"type":"Point"}
}