{
  "type": "Feature",
  "properties": {
    "iso:country":"US",
    "sg:address":"5904 Taylor Dr",
    "sg:city":"Burlington",
    "sg:classifiers":[
        {
            "category":"Social Services",
            "subcategory":"Child Care",
            "type":"Services"
        },
        {
            "category":"Education",
            "subcategory":"Preschool",
            "type":"Public Place"
        },
        {
            "category":"Education",
            "subcategory":"School",
            "type":"Public Place"
        }
    ],
    "sg:phone":"+1 859 586 6656",
    "sg:postcode":"41005",
    "sg:province":"KY",
    "sg:tags":[
        "elementary",
        "day"
    ],
    "wof:name":"Little Miracles Inc",
    "wof:placetype":"venue"
},
  "geometry": {"coordinates":[-84.69049800000001,39.0205],"type":"Point"}
}