{
  "type": "Feature",
  "properties": {
    "iso:country":"US",
    "sg:address":"230 Court St",
    "sg:city":"Paintsville",
    "sg:classifiers":[
        {
            "category":"Government",
            "subcategory":"Court House",
            "type":"Public Place"
        }
    ],
    "sg:phone":"+1 606 788 7163",
    "sg:postcode":"41240",
    "sg:province":"KY",
    "sg:tags":[
        "state"
    ],
    "wof:name":"Judge's Office",
    "wof:placetype":"venue"
},
  "geometry": {"coordinates":[-82.807067,37.814567],"type":"Point"}
}