{
  "type": "Feature",
  "properties": {
    "iso:country":"US",
    "sg:address":"3288 Kingsburg Ct",
    "sg:city":"Erlanger",
    "sg:classifiers":[
        {
            "category":"Shopping",
            "subcategory":"Computers & Home Electronics",
            "type":"Retail Goods"
        }
    ],
    "sg:phone":"+1 859 578 9376",
    "sg:postcode":"41018",
    "sg:province":"KY",
    "wof:name":"SS&c Technologies Inc",
    "wof:placetype":"venue"
},
  "geometry": {"coordinates":[-84.59053,38.998176],"type":"Point"}
}