{
  "type": "Feature",
  "properties": {
    "addr:full":"2000 Stanley Gault Pkwy Louisville KY 40223",
    "addr:housenumber":"2000",
    "addr:postcode":"40223",
    "addr:street":"Stanley Gault Pkwy",
    "iso:country":"US",
    "sg:address":"2000 Stanley Gault Pkwy",
    "sg:city":"Louisville",
    "sg:classifiers":[
        {
            "category":"Manufacturing",
            "subcategory":"Motor Vehicles & Parts",
            "type":"Manufacturing & Wholesale Goods"
        }
    ],
    "sg:phone":"+1 502 253 4700",
    "sg:postcode":"40223",
    "sg:province":"KY",
    "sg:tags":[
        "automobile",
        "supply"
    ],
    "sg:website":"www.lear.com",
    "wof:name":"Lear Corp",
    "wof:placetype":"venue"
},
  "geometry": {"coordinates":[-85.51289199999999,38.269847],"type":"Point"}
}