{
  "type": "Feature",
  "properties": {
    "iso:country":"US",
    "sg:address":"211 S 2nd St",
    "sg:city":"La Grange",
    "sg:classifiers":[
        {
            "category":"Education",
            "subcategory":"Dance Studio",
            "type":"Public Place"
        }
    ],
    "sg:phone":"+1 502 222 5836",
    "sg:postcode":"40031",
    "sg:province":"KY",
    "wof:name":"Studio 4",
    "wof:placetype":"venue"
},
  "geometry": {"coordinates":[-85.379583,38.406295],"type":"Point"}
}