{
  "type": "Feature",
  "properties": {
    "iso:country":"US",
    "sg:address":"1000 N Laurel Rd",
    "sg:city":"London",
    "sg:classifiers":[
        {
            "category":"Home & Garden",
            "subcategory":"Carpets & Floor Coverings",
            "type":"Retail Goods"
        }
    ],
    "sg:phone":"+1 606 864 2261",
    "sg:postcode":"40741",
    "sg:province":"KY",
    "sg:tags":[
        "dealer",
        "rug"
    ],
    "wof:name":"Laurel Carpet",
    "wof:placetype":"venue"
},
  "geometry": {"coordinates":[-84.109427,37.159541],"type":"Point"}
}