{
  "type": "Feature",
  "properties": {
    "iso:country":"US",
    "sg:address":"6130 Nashville Rd",
    "sg:city":"Bowling Green",
    "sg:classifiers":[
        {
            "category":"Wholesale",
            "subcategory":"Scrap",
            "type":"Manufacturing & Wholesale Goods"
        }
    ],
    "sg:phone":"+1 270 780 0155",
    "sg:postcode":"42101",
    "sg:province":"KY",
    "sg:tags":[
        "recycling",
        "center"
    ],
    "wof:name":"Bowling Green Recycling LLC",
    "wof:placetype":"venue"
},
  "geometry": {"coordinates":[-86.496471,36.9283],"type":"Point"}
}