{
  "type": "Feature",
  "properties": {
    "iso:country":"US",
    "sg:address":"3824 Still Meadow Ln",
    "sg:city":"Lexington",
    "sg:classifiers":[
        {
            "category":"Building & Trades",
            "subcategory":"Construction",
            "type":"Services"
        }
    ],
    "sg:phone":"+1 859 543 4177",
    "sg:postcode":"40509",
    "sg:province":"KY",
    "sg:tags":[
        "home",
        "builder"
    ],
    "wof:name":"James T Nash Builders",
    "wof:placetype":"venue"
},
  "geometry": {"coordinates":[-84.41222999999999,37.991875],"type":"Point"}
}