{
  "type": "Feature",
  "properties": {
    "addr:full":"988 State Hwy 1649 Liberty KY 42539",
    "addr:housenumber":"988;1649",
    "addr:postcode":"42539",
    "addr:street":"State Hwy",
    "iso:country":"US",
    "sg:address":"988 State Hwy 1649",
    "sg:city":"Liberty",
    "sg:classifiers":[
        {
            "category":"Communications",
            "subcategory":"Radio Station",
            "type":"Services"
        }
    ],
    "sg:phone":"+1 606 787 7331",
    "sg:postcode":"42539",
    "sg:province":"KY",
    "sg:tags":[
        "company",
        "broadcasting"
    ],
    "wof:name":"WKDO Radio",
    "wof:placetype":"venue"
},
  "geometry": {"coordinates":[-84.845468,37.290951],"type":"Point"}
}