{
  "type": "Feature",
  "properties": {
    "iso:country":"US",
    "sg:address":"1845 Monmouth St",
    "sg:city":"Newport",
    "sg:classifiers":[
        {
            "category":"Personal",
            "subcategory":"Barber",
            "type":"Services"
        }
    ],
    "sg:phone":"+1 859 261 5535",
    "sg:postcode":"41071",
    "sg:province":"KY",
    "wof:name":"Rick's Center Barbers",
    "wof:placetype":"venue"
},
  "geometry": {"coordinates":[-84.481415,39.080194],"type":"Point"}
}