{
  "type": "Feature",
  "properties": {
    "iso:country":"US",
    "sg:address":"503 George McClain Dr",
    "sg:city":"Benton",
    "sg:classifiers":[
        {
            "category":"Health Services",
            "subcategory":"Doctor",
            "type":"Services"
        }
    ],
    "sg:phone":"+1 270 444 3930",
    "sg:postcode":"42025",
    "sg:province":"KY",
    "sg:tags":[
        "physician",
        "surgeon"
    ],
    "wof:name":"Oncology Associates Of W Ky",
    "wof:placetype":"venue"
},
  "geometry": {"coordinates":[-88.345367,36.859565],"type":"Point"}
}