{
  "type": "Feature",
  "properties": {
    "addr:full":"708 Arbor Dr Henderson KY 42420",
    "addr:housenumber":"708",
    "addr:postcode":"42420",
    "addr:street":"Arbor Dr",
    "iso:country":"US",
    "sg:address":"708 Arbor Dr",
    "sg:city":"Henderson",
    "sg:classifiers":[
        {
            "category":"Real Estate",
            "subcategory":"Real Estate Operator",
            "type":"Services"
        }
    ],
    "sg:phone":"+1 270 827 1300",
    "sg:postcode":"42420",
    "sg:province":"KY",
    "sg:tags":[
        "apartment"
    ],
    "wof:name":"Cottage Of Henderson",
    "wof:placetype":"venue"
},
  "geometry": {"coordinates":[-87.61208600000001,37.812009],"type":"Point"}
}