{
  "type": "Feature",
  "properties": {
    "iso:country":"US",
    "sg:address":"135 Zorro Pl",
    "sg:city":"Shepherdsville",
    "sg:classifiers":[
        {
            "category":"Building & Trades",
            "subcategory":"Plumbing",
            "type":"Services"
        }
    ],
    "sg:phone":"+1 502 955 1414",
    "sg:postcode":"40165",
    "sg:province":"KY",
    "sg:tags":[
        "heating",
        "contractor"
    ],
    "wof:name":"Wheeler Heating & Air",
    "wof:placetype":"venue"
},
  "geometry": {"coordinates":[-85.63981200000001,38.058264],"type":"Point"}
}