{
  "type": "Feature",
  "properties": {
    "addr:full":"1186 Carson Ct Lexington KY 40504",
    "addr:housenumber":"1186",
    "addr:postcode":"40504",
    "addr:street":"Carson Ct",
    "iso:country":"US",
    "sg:address":"1186 Carson Ct",
    "sg:city":"Lexington",
    "sg:classifiers":[
        {
            "category":"Building & Trades",
            "subcategory":"Electrical",
            "type":"Services"
        }
    ],
    "sg:phone":"+1 859 255 3938",
    "sg:postcode":"40504",
    "sg:province":"KY",
    "sg:tags":[
        "electrical",
        "contractor"
    ],
    "wof:name":"Lyons Electric & Hvac Service",
    "wof:placetype":"venue"
},
  "geometry": {"coordinates":[-84.55440299999999,38.054947],"type":"Point"}
}