{
  "type": "Feature",
  "properties": {
    "addr:full":"978 Barret Ave Louisville KY 40204",
    "addr:housenumber":"978",
    "addr:postcode":"40204",
    "addr:street":"Barret Ave",
    "iso:country":"US",
    "sg:address":"978 Barret Ave",
    "sg:city":"Louisville",
    "sg:phone":"+1 502 333 6118",
    "sg:postcode":"40204",
    "sg:province":"KY",
    "wof:name":"The Herb Import Company",
    "wof:placetype":"venue"
},
  "geometry": {"coordinates":[-85.72866,38.237082],"type":"Point"}
}