{
  "type": "Feature",
  "properties": {
    "iso:country":"US",
    "sg:address":"9907 Taylorsville Rd",
    "sg:city":"Jeffersontown",
    "sg:classifiers":[
        {
            "category":"Personal",
            "subcategory":"Beauty Salon",
            "type":"Services"
        }
    ],
    "sg:phone":"+1 502 267 6621",
    "sg:postcode":"40299",
    "sg:province":"KY",
    "wof:name":"Lou's Beauty Salon",
    "wof:placetype":"venue"
},
  "geometry": {"coordinates":[-85.57132799999999,38.199913],"type":"Point"}
}