{
  "type": "Feature",
  "properties": {
    "iso:country":"US",
    "sg:address":"207 E Central St",
    "sg:city":"Harlan",
    "sg:classifiers":[
        {
            "category":"Professional",
            "subcategory":"Lawyer & Legal Services",
            "type":"Services"
        }
    ],
    "sg:phone":"+1 606 573 1234",
    "sg:postcode":"40831",
    "sg:province":"KY",
    "sg:tags":[
        "attorney"
    ],
    "wof:name":"Goss & Goss",
    "wof:placetype":"venue"
},
  "geometry": {"coordinates":[-83.32167800000001,36.847086],"type":"Point"}
}