{
  "type": "Feature",
  "properties": {
    "iso:country":"US",
    "sg:address":"107 E 4th St",
    "sg:city":"Corbin",
    "sg:classifiers":[
        {
            "category":"Health Services",
            "subcategory":"Doctor",
            "type":"Services"
        }
    ],
    "sg:phone":"+1 606 526 1800",
    "sg:postcode":"40701",
    "sg:province":"KY",
    "sg:tags":[
        "physician",
        "surgeon"
    ],
    "wof:name":"Cardiology & Internal Medicine",
    "wof:placetype":"venue"
},
  "geometry": {"coordinates":[-84.095066,36.945345],"type":"Point"}
}