{
  "type": "Feature",
  "properties": {
    "iso:country":"US",
    "sg:address":"491 Louis Waddle Rd",
    "sg:city":"Science Hill",
    "sg:classifiers":[
        {
            "category":"Professional",
            "subcategory":"Secretarial Services",
            "type":"Services"
        }
    ],
    "sg:phone":"+1 606 423 4422",
    "sg:postcode":"42553",
    "sg:province":"KY",
    "sg:tags":[
        "convention",
        "court",
        "reporter"
    ],
    "wof:name":"Grant Reporting Svc",
    "wof:placetype":"venue"
},
  "geometry": {"coordinates":[-84.59776599999999,37.181802],"type":"Point"}
}