{
  "type": "Feature",
  "properties": {
    "addr:full":"3720 Richmond Rd Lexington KY 40509",
    "addr:housenumber":"3720",
    "addr:postcode":"40509",
    "addr:street":"Richmond Rd",
    "iso:country":"US",
    "sg:address":"3720 Richmond Rd",
    "sg:city":"Lexington",
    "sg:classifiers":[
        {
            "category":"Organizations",
            "subcategory":"Community Association",
            "type":"Services"
        }
    ],
    "sg:phone":"+1 859 263 5316",
    "sg:postcode":"40509",
    "sg:province":"KY",
    "sg:tags":[
        "club"
    ],
    "wof:name":"Lake Ellerslie Fishing Club",
    "wof:placetype":"venue"
},
  "geometry": {"coordinates":[-84.43323599999999,37.990035],"type":"Point"}
}