{
  "type": "Feature",
  "properties": {
    "iso:country":"US",
    "sg:address":"10137 Russwill Ln",
    "sg:city":"Union",
    "sg:classifiers":[
        {
            "category":"Professional",
            "subcategory":"Business Services",
            "type":"Services"
        }
    ],
    "sg:phone":"+1 859 384 4456",
    "sg:postcode":"41091",
    "sg:province":"KY",
    "wof:name":"Jerry Lux",
    "wof:placetype":"venue"
},
  "geometry": {"coordinates":[-84.664883,38.946701],"type":"Point"}
}