{
  "type": "Feature",
  "properties": {
    "iso:country":"US",
    "sg:address":"633 Big Hill Ave",
    "sg:city":"Richmond",
    "sg:classifiers":[
        {
            "category":"Real Estate",
            "subcategory":"Real Estate Operator",
            "type":"Services"
        }
    ],
    "sg:phone":"+1 859 623 8860",
    "sg:postcode":"40475",
    "sg:province":"KY",
    "sg:tags":[
        "apartment"
    ],
    "wof:name":"Richmond East Apartments",
    "wof:placetype":"venue"
},
  "geometry": {"coordinates":[-84.278542,37.73688],"type":"Point"}
}