{
  "type": "Feature",
  "properties": {
    "addr:full":"225 Main St Ste 5 Florence KY 41042",
    "addr:housenumber":"225",
    "addr:postcode":"41042",
    "addr:street":"Main St Ste 5",
    "iso:country":"US",
    "sg:address":"225 Main St Ste 5",
    "sg:city":"Florence",
    "sg:classifiers":[
        {
            "category":"Building & Trades",
            "subcategory":"Electrical",
            "type":"Services"
        }
    ],
    "sg:phone":"+1 859 282 6500",
    "sg:postcode":"41042",
    "sg:province":"KY",
    "sg:tags":[
        "electrician"
    ],
    "wof:name":"Nie-Haus Electric",
    "wof:placetype":"venue"
},
  "geometry": {"coordinates":[-84.624397,39.003101],"type":"Point"}
}