{
  "type": "Feature",
  "properties": {
    "addr:full":"425 Reed Dr Frankfort KY 40601",
    "addr:housenumber":"425",
    "addr:postcode":"40601",
    "addr:street":"Reed Dr",
    "iso:country":"US",
    "sg:address":"425 Reed Dr",
    "sg:city":"Frankfort",
    "sg:classifiers":[
        {
            "category":"Organizations",
            "subcategory":"Religious Organization",
            "type":"Services"
        }
    ],
    "sg:phone":"+1 502 696 0620",
    "sg:postcode":"40601",
    "sg:province":"KY",
    "wof:name":"Faith Baptist Church Inc",
    "wof:placetype":"venue"
},
  "geometry": {"coordinates":[-84.881531,38.174445],"type":"Point"}
}