{
  "type": "Feature",
  "properties": {
    "iso:country":"US",
    "sg:address":"110 W Linden St",
    "sg:city":"Wilmore",
    "sg:classifiers":[
        {
            "category":"Retail",
            "subcategory":"Auto Rental",
            "type":"Services"
        }
    ],
    "sg:phone":"+1 859 858 3580",
    "sg:postcode":"40390",
    "sg:province":"KY",
    "sg:tags":[
        "renting",
        "truck",
        "leasing"
    ],
    "wof:name":"U-Haul Co",
    "wof:placetype":"venue"
},
  "geometry": {"coordinates":[-84.66482600000001,37.860876],"type":"Point"}
}