{
  "type": "Feature",
  "properties": {
    "iso:country":"US",
    "sg:address":"15937 State Hwy 92 E",
    "sg:city":"Siler",
    "sg:classifiers":[
        {
            "category":"Building & Trades",
            "subcategory":"Plumbing",
            "type":"Services"
        }
    ],
    "sg:phone":"+1 606 549 1259",
    "sg:postcode":"40763",
    "sg:province":"KY",
    "sg:tags":[
        "conditioning",
        "air",
        "system",
        "contractor"
    ],
    "wof:name":"Lloyd Fulton Heating & AC",
    "wof:placetype":"venue"
},
  "geometry": {"coordinates":[-83.964882,36.70014],"type":"Point"}
}