{
  "type": "Feature",
  "properties": {
    "addr:full":"503 Ryan Ave Franklin KY 42134",
    "addr:housenumber":"503",
    "addr:postcode":"42134",
    "addr:street":"Ryan Ave",
    "iso:country":"US",
    "sg:address":"503 Ryan Ave",
    "sg:city":"Franklin",
    "sg:classifiers":[
        {
            "category":"Organizations",
            "subcategory":"Community Association",
            "type":"Services"
        }
    ],
    "sg:phone":"+1 270 586 9387",
    "sg:postcode":"42134",
    "sg:province":"KY",
    "sg:tags":[
        "military"
    ],
    "wof:name":"American Legion",
    "wof:placetype":"venue"
},
  "geometry": {"coordinates":[-86.586215,36.727934],"type":"Point"}
}