{
  "type": "Feature",
  "properties": {
    "addr:full":"350 1st St Calhoun KY 42327",
    "addr:housenumber":"350",
    "addr:postcode":"42327",
    "addr:street":"1St St",
    "iso:country":"US",
    "sg:address":"350 1st St",
    "sg:city":"Calhoun",
    "sg:classifiers":[
        {
            "category":"Manufacturing",
            "subcategory":"Furniture",
            "type":"Manufacturing & Wholesale Goods"
        }
    ],
    "sg:phone":"+1 270 273 9872",
    "sg:postcode":"42327",
    "sg:province":"KY",
    "wof:name":"Twin Rivers Inc",
    "wof:placetype":"venue"
},
  "geometry": {"coordinates":[-87.259371,37.535838],"type":"Point"}
}