{
  "type": "Feature",
  "properties": {
    "iso:country":"US",
    "sg:address":"2301 Abbott Creek Rd",
    "sg:city":"Prestonsburg",
    "sg:classifiers":[
        {
            "category":"Building & Trades",
            "subcategory":"Construction",
            "type":"Services"
        }
    ],
    "sg:phone":"+1 606 886 2131",
    "sg:postcode":"41653",
    "sg:province":"KY",
    "sg:tags":[
        "residential"
    ],
    "wof:name":"High Tech Construction",
    "wof:placetype":"venue"
},
  "geometry": {"coordinates":[-82.824916,37.683401],"type":"Point"}
}