{
  "type": "Feature",
  "properties": {
    "addr:full":"1248 Taransay Dr Henderson KY 42420",
    "addr:housenumber":"1248",
    "addr:postcode":"42420",
    "addr:street":"Taransay Dr",
    "iso:country":"US",
    "sg:address":"1248 Taransay Dr",
    "sg:city":"Henderson",
    "sg:classifiers":[
        {
            "category":"Professional",
            "type":"Services"
        }
    ],
    "sg:phone":"+1 270 827 2439",
    "sg:postcode":"42420",
    "sg:province":"KY",
    "sg:tags":[
        "establishment"
    ],
    "wof:name":"Wilson Soap Jr",
    "wof:placetype":"venue"
},
  "geometry": {"coordinates":[-87.557633,37.857903],"type":"Point"}
}