{
  "type": "Feature",
  "properties": {
    "iso:country":"US",
    "sg:address":"950 Jamestown St",
    "sg:city":"Columbia",
    "sg:classifiers":[
        {
            "category":"Restaurant",
            "type":"Food & Drink"
        }
    ],
    "sg:menulink":"http://www.allmenus.com/ky/columbia/120477-subway/menu/",
    "sg:phone":"+1 270 384 9422",
    "sg:postcode":"42728",
    "sg:province":"KY",
    "sg:tags":[
        "american",
        "sandwich"
    ],
    "wof:name":"Subway",
    "wof:placetype":"venue"
},
  "geometry": {"coordinates":[-85.30199,37.087025],"type":"Point"}
}