{
  "type": "Feature",
  "properties": {
    "iso:country":"US",
    "sg:address":"220 Big Run Rd",
    "sg:city":"Lexington",
    "sg:classifiers":[
        {
            "category":"Shopping",
            "subcategory":"Bicycles & Sporting Goods",
            "type":"Retail Goods"
        }
    ],
    "sg:phone":"+1 859 278 6387",
    "sg:postcode":"40503",
    "sg:province":"KY",
    "wof:name":"Barnes Sports",
    "wof:placetype":"venue"
},
  "geometry": {"coordinates":[-84.530084,37.999983],"type":"Point"}
}