{
  "type": "Feature",
  "properties": {
    "iso:country":"US",
    "sg:address":"1414 Reed Ave",
    "sg:city":"Paducah",
    "sg:classifiers":[
        {
            "category":"Building & Trades",
            "subcategory":"Cleaning & Sanitation",
            "type":"Services"
        }
    ],
    "sg:phone":"+1 270 442 1882",
    "sg:postcode":"42001",
    "sg:province":"KY",
    "sg:tags":[
        "janitor"
    ],
    "wof:name":"Robinson & Son Janitorial Svc",
    "wof:placetype":"venue"
},
  "geometry": {"coordinates":[-88.635718,37.090393],"type":"Point"}
}