{
  "type": "Feature",
  "properties": {
    "iso:country":"US",
    "sg:address":"1440 Old Mayfield Rd",
    "sg:city":"Paducah",
    "sg:classifiers":[
        {
            "category":"Freight",
            "type":"Transportation"
        }
    ],
    "sg:phone":"+1 270 442 3235",
    "sg:postcode":"42003",
    "sg:province":"KY",
    "sg:tags":[
        "trucking"
    ],
    "wof:name":"Kentucky TOFC Delivery Svc",
    "wof:placetype":"venue"
},
  "geometry": {"coordinates":[-88.613325,37.064272],"type":"Point"}
}