{
  "type": "Feature",
  "properties": {
    "iso:country":"US",
    "sg:address":"1214 Crosstimbers Dr",
    "sg:city":"Louisville",
    "sg:classifiers":[
        {
            "category":"Building & Trades",
            "subcategory":"Construction",
            "type":"Services"
        }
    ],
    "sg:phone":"+1 502 298 2651",
    "sg:postcode":"40245",
    "sg:province":"KY",
    "sg:tags":[
        "contractor"
    ],
    "wof:name":"Dan-Co Specialty Labor Inc",
    "wof:placetype":"venue"
},
  "geometry": {"coordinates":[-85.451807,38.258566],"type":"Point"}
}