{
  "type": "Feature",
  "properties": {
    "iso:country":"US",
    "sg:address":"1101 Laurel River Church Rd",
    "sg:city":"London",
    "sg:classifiers":[
        {
            "category":"Organizations",
            "subcategory":"Religious Organization",
            "type":"Services"
        }
    ],
    "sg:phone":"+1 606 878 0018",
    "sg:postcode":"40744",
    "sg:province":"KY",
    "wof:name":"Laurel Rver Untd Baptst Church",
    "wof:placetype":"venue"
},
  "geometry": {"coordinates":[-83.997615,37.056042],"type":"Point"}
}