{
  "type": "Feature",
  "properties": {
    "iso:country":"US",
    "sg:address":"4006 Dutchmans Ln",
    "sg:city":"St Matthews",
    "sg:classifiers":[
        {
            "category":"Professional",
            "subcategory":"Lawyer & Legal Services",
            "type":"Services"
        }
    ],
    "sg:phone":"+1 502 777 3615",
    "sg:postcode":"40207",
    "sg:province":"KY",
    "sg:tags":[
        "attorney"
    ],
    "wof:name":"W Craig Aulenbach",
    "wof:placetype":"venue"
},
  "geometry": {"coordinates":[-85.631664,38.234545],"type":"Point"}
}