{
  "type": "Feature",
  "properties": {
    "iso:country":"US",
    "sg:address":"601 S Floyd St Ste 700",
    "sg:city":"Louisville",
    "sg:classifiers":[
        {
            "category":"Banks & Credit Unions",
            "subcategory":"Bank",
            "type":"Services"
        },
        {
            "category":"Banks & Credit Unions",
            "subcategory":"Financial Services",
            "type":"Services"
        }
    ],
    "sg:phone":"+1 502 212 6490",
    "sg:postcode":"40202",
    "sg:province":"KY",
    "sg:tags":[
        "commercial",
        "loan",
        "saving"
    ],
    "sg:website":"http://www.pncbank.com",
    "wof:name":"PNC Bank",
    "wof:placetype":"venue"
},
  "geometry": {"coordinates":[-85.749207,38.24799],"type":"Point"}
}