{
  "type": "Feature",
  "properties": {
    "addr:full":"612 Broadway St Paducah KY 42001",
    "addr:housenumber":"612",
    "addr:postcode":"42001",
    "addr:street":"Broadway St",
    "iso:country":"US",
    "sg:address":"612 Broadway St",
    "sg:city":"Paducah",
    "sg:classifiers":[
        {
            "category":"Social Services",
            "type":"Services"
        }
    ],
    "sg:phone":"+1 270 442 1691",
    "sg:postcode":"42001",
    "sg:province":"KY",
    "sg:tags":[
        "organization",
        "welfare"
    ],
    "wof:name":"United Way",
    "wof:placetype":"venue"
},
  "geometry": {"coordinates":[-88.60065299999999,37.085573],"type":"Point"}
}