{
  "type": "Feature",
  "properties": {
    "iso:country":"US",
    "sg:address":"2319 Versailles Rd",
    "sg:city":"Lexington",
    "sg:classifiers":[
        {
            "category":"Organizations",
            "subcategory":"Religious Organization",
            "type":"Services"
        }
    ],
    "sg:phone":"+1 859 255 2349",
    "sg:postcode":"40504",
    "sg:province":"KY",
    "sg:tags":[
        "church"
    ],
    "wof:name":"St Luke Cec",
    "wof:placetype":"venue"
},
  "geometry": {"coordinates":[-84.553078,38.046855],"type":"Point"}
}