{
  "type": "Feature",
  "properties": {
    "iso:country":"US",
    "sg:address":"185 American Legion Rd",
    "sg:city":"Campbellsville",
    "sg:classifiers":[
        {
            "category":"Organizations",
            "subcategory":"Community Association",
            "type":"Services"
        }
    ],
    "sg:phone":"+1 270 465 7131",
    "sg:postcode":"42718",
    "sg:province":"KY",
    "sg:tags":[
        "military"
    ],
    "wof:name":"American Legion",
    "wof:placetype":"venue"
},
  "geometry": {"coordinates":[-85.323555,37.360953],"type":"Point"}
}