{
  "type": "Feature",
  "properties": {
    "addr:full":"1561 Production Dr Burlington KY 41005",
    "addr:housenumber":"1561",
    "addr:postcode":"41005",
    "addr:street":"Production Dr",
    "iso:country":"US",
    "sg:address":"1561 Production Dr",
    "sg:city":"Burlington",
    "sg:classifiers":[
        {
            "category":"Retail",
            "subcategory":"Repair Shop",
            "type":"Services"
        }
    ],
    "sg:phone":"+1 859 371 5702",
    "sg:postcode":"41005",
    "sg:province":"KY",
    "sg:tags":[
        "welding"
    ],
    "wof:name":"Fab N Weld",
    "wof:placetype":"venue"
},
  "geometry": {"coordinates":[-84.68793599999999,39.021981],"type":"Point"}
}