{
  "type": "Feature",
  "properties": {
    "iso:country":"US",
    "sg:address":"3600 Chamberlain Ln # 112",
    "sg:city":"Louisville",
    "sg:classifiers":[
        {
            "category":"Social Services",
            "subcategory":"Adult Care",
            "type":"Services"
        }
    ],
    "sg:phone":"+1 502 412 2378",
    "sg:postcode":"40241",
    "sg:province":"KY",
    "sg:tags":[
        "calibration"
    ],
    "sg:website":"http://www.tangentlabs.com",
    "wof:name":"Tangent Labs",
    "wof:placetype":"venue"
},
  "geometry": {"coordinates":[-85.541254,38.297301],"type":"Point"}
}