{
  "type": "Feature",
  "properties": {
    "iso:country":"US",
    "sg:address":"1208 Old Nazareth Rd",
    "sg:city":"Bardstown",
    "sg:classifiers":[
        {
            "category":"Professional",
            "subcategory":"Business Services",
            "type":"Services"
        }
    ],
    "sg:phone":"+1 502 349 0217",
    "sg:postcode":"40004",
    "sg:province":"KY",
    "wof:name":"Reiter Industries Inc",
    "wof:placetype":"venue"
},
  "geometry": {"coordinates":[-85.479874,37.847499],"type":"Point"}
}