{
  "type": "Feature",
  "properties": {
    "addr:full":"2140 Cave Hill Ln Lexington KY 40513",
    "addr:housenumber":"2140",
    "addr:postcode":"40513",
    "addr:street":"Cave Hill Ln",
    "iso:country":"US",
    "sg:address":"2140 Cave Hill Ln",
    "sg:city":"Lexington",
    "sg:classifiers":[
        {
            "category":"Building & Trades",
            "subcategory":"Landscaping Services",
            "type":"Services"
        }
    ],
    "sg:phone":"+1 859 223 9272",
    "sg:postcode":"40513",
    "sg:province":"KY",
    "sg:tags":[
        "designer",
        "landscape"
    ],
    "sg:website":"www.landesignlex.com",
    "wof:name":"Landesign",
    "wof:placetype":"venue"
},
  "geometry": {"coordinates":[-84.569129,38.009976],"type":"Point"}
}