{
  "type": "Feature",
  "properties": {
    "iso:country":"US",
    "sg:address":"924 Commercial Dr",
    "sg:city":"Richmond",
    "sg:classifiers":[
        {
            "category":"Autos & Motor Vehicles",
            "subcategory":"Auto Supplies",
            "type":"Retail Goods"
        }
    ],
    "sg:phone":"+1 859 624 1044",
    "sg:postcode":"40475",
    "sg:province":"KY",
    "sg:tags":[
        "automobile",
        "parts"
    ],
    "wof:name":"NAPA Auto Parts",
    "wof:placetype":"venue"
},
  "geometry": {"coordinates":[-84.268624,37.737913],"type":"Point"}
}