{
  "type": "Feature",
  "properties": {
    "iso:country":"US",
    "sg:address":"2232 Bardstown Rd",
    "sg:city":"Louisville",
    "sg:classifiers":[
        {
            "category":"Shopping",
            "type":"Retail Goods"
        }
    ],
    "sg:phone":"+1 502 456 4600",
    "sg:postcode":"40205",
    "sg:province":"KY",
    "sg:tags":[
        "monument"
    ],
    "wof:name":"Louisville Monument Co",
    "wof:placetype":"venue"
},
  "geometry": {"coordinates":[-85.69263599999999,38.224204],"type":"Point"}
}