{
  "type": "Feature",
  "properties": {
    "iso:country":"US",
    "sg:address":"317 N Miles St",
    "sg:city":"Elizabethtown",
    "sg:classifiers":[
        {
            "category":"Government",
            "subcategory":"Office",
            "type":"Public Place"
        }
    ],
    "sg:phone":"+1 270 769 5509",
    "sg:postcode":"42701",
    "sg:province":"KY",
    "wof:name":"Natural Resource Conservation",
    "wof:placetype":"venue"
},
  "geometry": {"coordinates":[-85.85917499999999,37.69997],"type":"Point"}
}