{
  "type": "Feature",
  "properties": {
    "iso:country":"US",
    "sg:address":"1945 Scottsville Rd",
    "sg:city":"Bowling Green",
    "sg:classifiers":[
        {
            "category":"Building & Trades",
            "subcategory":"Plumbing",
            "type":"Services"
        }
    ],
    "sg:phone":"+1 270 393 9908",
    "sg:postcode":"42104",
    "sg:province":"KY",
    "sg:tags":[
        "conditioning",
        "air",
        "system",
        "contractor"
    ],
    "wof:name":"Hall Heating & Air",
    "wof:placetype":"venue"
},
  "geometry": {"coordinates":[-86.431231,36.963416],"type":"Point"}
}