{
  "type": "Feature",
  "properties": {
    "iso:country":"US",
    "sg:address":"305 W 2nd St",
    "sg:city":"Morehead",
    "sg:classifiers":[
        {
            "category":"Health Services",
            "subcategory":"Hospital",
            "type":"Services"
        }
    ],
    "sg:phone":"+1 606 780 7296",
    "sg:postcode":"40351",
    "sg:province":"KY",
    "sg:tags":[
        "medical",
        "surgical",
        "emergency"
    ],
    "wof:name":"Kentucky Air Medical Team",
    "wof:placetype":"venue"
},
  "geometry": {"coordinates":[-83.439995,38.180092],"type":"Point"}
}