{
  "type": "Feature",
  "properties": {
    "iso:country":"US",
    "sg:address":"2810 Surfside Dr",
    "sg:city":"Covington",
    "sg:classifiers":[
        {
            "category":"Professional",
            "subcategory":"Engineering",
            "type":"Services"
        }
    ],
    "sg:phone":"+1 859 331 3111",
    "sg:postcode":"41017",
    "sg:province":"KY",
    "wof:name":"Pcr Holding Inc",
    "wof:placetype":"venue"
},
  "geometry": {"coordinates":[-84.60914699999999,39.058221],"type":"Point"}
}