{
  "type": "Feature",
  "properties": {
    "addr:full":"6201 Kenyon Dr Louisville KY 40272",
    "addr:housenumber":"6201",
    "addr:postcode":"40272",
    "addr:street":"Kenyon Dr",
    "iso:country":"US",
    "sg:address":"6201 Kenyon Dr",
    "sg:city":"Louisville",
    "sg:classifiers":[
        {
            "category":"School Buses",
            "type":"Transportation"
        }
    ],
    "sg:phone":"+1 502 937 8057",
    "sg:postcode":"40272",
    "sg:province":"KY",
    "wof:name":"Debra S Walk",
    "wof:placetype":"venue"
},
  "geometry": {"coordinates":[-85.88190400000001,38.095462],"type":"Point"}
}