{
  "type": "Feature",
  "properties": {
    "iso:country":"US",
    "sg:address":"5164 Hinkleville Rd",
    "sg:city":"Paducah",
    "sg:classifiers":[
        {
            "category":"Health Services",
            "subcategory":"Chiropractor",
            "type":"Services"
        }
    ],
    "sg:phone":"+1 270 442 0110",
    "sg:postcode":"42001",
    "sg:province":"KY",
    "wof:name":"Canter Chiropractic & Rehab",
    "wof:placetype":"venue"
},
  "geometry": {"coordinates":[-88.69260199999999,37.074815],"type":"Point"}
}