{
  "type": "Feature",
  "properties": {
    "addr:full":"688 Us Highway 25 W Corbin KY 40701",
    "addr:housenumber":"688",
    "addr:postcode":"40701",
    "addr:street":"Us Highway 25 W",
    "iso:country":"US",
    "sg:address":"688 Us Highway 25 W",
    "sg:city":"Corbin",
    "sg:classifiers":[
        {
            "category":"Restaurant",
            "type":"Food & Drink"
        }
    ],
    "sg:menulink":"http://www.allmenus.com/ky/corbin/176076-kfc---kentucky-fried-chicken/menu/",
    "sg:phone":"+1 606 528 2163",
    "sg:postcode":"40701",
    "sg:province":"KY",
    "sg:tags":[
        "american",
        "chicken"
    ],
    "wof:name":"KFC - Kentucky Fried Chicken",
    "wof:placetype":"venue"
},
  "geometry": {"coordinates":[-84.069722,36.957679],"type":"Point"}
}