{
  "type": "Feature",
  "properties": {
    "addr:full":"2801 Constant Comment Pl Jeffersontown KY 40299",
    "addr:housenumber":"2801",
    "addr:postcode":"40299",
    "addr:street":"Constant Comment Pl",
    "iso:country":"US",
    "sg:address":"2801 Constant Comment Pl",
    "sg:city":"Jeffersontown",
    "sg:classifiers":[
        {
            "category":"Building & Trades",
            "subcategory":"Construction",
            "type":"Services"
        }
    ],
    "sg:phone":"+1 502 266 6157",
    "sg:postcode":"40299",
    "sg:province":"KY",
    "sg:tags":[
        "contractor"
    ],
    "wof:name":"Alter Design Builders",
    "wof:placetype":"venue"
},
  "geometry": {"coordinates":[-85.53471399999999,38.204852],"type":"Point"}
}