{
  "type": "Feature",
  "properties": {
    "iso:country":"US",
    "sg:address":"2600 Stith Valley Rd",
    "sg:city":"Guston",
    "sg:classifiers":[
        {
            "category":"Farming",
            "subcategory":"Livestock Farm",
            "type":"Manufacturing & Wholesale Goods"
        }
    ],
    "sg:phone":"+1 270 828 2117",
    "sg:postcode":"40142",
    "sg:province":"KY",
    "sg:tags":[
        "beef",
        "feedlot",
        "cattle"
    ],
    "wof:name":"Stith Farms",
    "wof:placetype":"venue"
},
  "geometry": {"coordinates":[-86.136729,37.861195],"type":"Point"}
}