{
  "type": "Feature",
  "properties": {
    "iso:country":"US",
    "sg:address":"904 Blackjack Rd",
    "sg:city":"Radcliff",
    "sg:classifiers":[
        {
            "category":"Retail",
            "subcategory":"Repair Shop",
            "type":"Services"
        }
    ],
    "sg:phone":"+1 270 351 0601",
    "sg:postcode":"40160",
    "sg:province":"KY",
    "sg:tags":[
        "lock",
        "locksmith"
    ],
    "wof:name":"Blue Steel Locksmithing",
    "wof:placetype":"venue"
},
  "geometry": {"coordinates":[-85.914511,37.816787],"type":"Point"}
}