{
  "type": "Feature",
  "properties": {
    "iso:country":"US",
    "sg:address":"1251 Georgetown Rd",
    "sg:city":"Lexington",
    "sg:classifiers":[
        {
            "category":"Wholesale",
            "subcategory":"Office Equipment",
            "type":"Manufacturing & Wholesale Goods"
        }
    ],
    "sg:phone":"+1 859 225 9831",
    "sg:postcode":"40511",
    "sg:province":"KY",
    "sg:tags":[
        "machine",
        "duplicating",
        "copying"
    ],
    "wof:name":"KOPY KAT",
    "wof:placetype":"venue"
},
  "geometry": {"coordinates":[-84.50773700000001,38.078889],"type":"Point"}
}