{
  "type": "Feature",
  "properties": {
    "iso:country":"US",
    "sg:address":"1811 Dixie Hwy S",
    "sg:city":"Elizabethtown",
    "sg:classifiers":[
        {
            "category":"Banks & Credit Unions",
            "subcategory":"Bank",
            "type":"Services"
        }
    ],
    "sg:phone":"+1 270 765 4279",
    "sg:postcode":"42701",
    "sg:province":"KY",
    "sg:tags":[
        "loan"
    ],
    "wof:name":"Equity One Inc",
    "wof:placetype":"venue"
},
  "geometry": {"coordinates":[-85.887174,37.734661],"type":"Point"}
}