{
  "type": "Feature",
  "properties": {
    "iso:country":"US",
    "sg:address":"4608 Hanford Ln",
    "sg:city":"Louisville",
    "sg:classifiers":[
        {
            "category":"Professional",
            "subcategory":"Engineering",
            "type":"Services"
        }
    ],
    "sg:phone":"+1 502 627 3868",
    "sg:postcode":"40207",
    "sg:province":"KY",
    "wof:name":"Beverly A Byrum",
    "wof:placetype":"venue"
},
  "geometry": {"coordinates":[-85.64643700000001,38.282939],"type":"Point"}
}