{
  "type": "Feature",
  "properties": {
    "iso:country":"US",
    "sg:address":"1619 W Elizabethtown Rd",
    "sg:city":"Leitchfield",
    "sg:classifiers":[
        {
            "category":"Health Services",
            "subcategory":"Clinic",
            "type":"Services"
        }
    ],
    "sg:phone":"+1 270 259 2994",
    "sg:postcode":"42754",
    "sg:province":"KY",
    "sg:tags":[
        "home"
    ],
    "wof:name":"Intrepid Home Health",
    "wof:placetype":"venue"
},
  "geometry": {"coordinates":[-86.27225,37.48563],"type":"Point"}
}