{
  "type": "Feature",
  "properties": {
    "iso:country":"US",
    "sg:address":"500 Redrier Ln",
    "sg:city":"Danville",
    "sg:classifiers":[
        {
            "category":"Wholesale",
            "subcategory":"Machinery & Supplies",
            "type":"Manufacturing & Wholesale Goods"
        }
    ],
    "sg:phone":"+1 859 239 9353",
    "sg:postcode":"40422",
    "sg:province":"KY",
    "sg:tags":[
        "equipment",
        "welding"
    ],
    "wof:name":"Weldquip",
    "wof:placetype":"venue"
},
  "geometry": {"coordinates":[-84.77732899999999,37.636199],"type":"Point"}
}