{
  "type": "Feature",
  "properties": {
    "iso:country":"US",
    "sg:address":"680 Bizzell Dr",
    "sg:city":"Lexington",
    "sg:classifiers":[
        {
            "category":"Wholesale",
            "subcategory":"Electrical",
            "type":"Manufacturing & Wholesale Goods"
        }
    ],
    "sg:phone":"+1 859 281 9779",
    "sg:postcode":"40510",
    "sg:province":"KY",
    "sg:tags":[
        "fire",
        "alarm",
        "system"
    ],
    "wof:name":"General Sound & Electronics",
    "wof:placetype":"venue"
},
  "geometry": {"coordinates":[-84.54150799999999,38.063847],"type":"Point"}
}