{
  "type": "Feature",
  "properties": {
    "iso:country":"US",
    "sg:address":"715 N Lincoln Blvd",
    "sg:city":"Hodgenville",
    "sg:classifiers":[
        {
            "category":"Restaurant",
            "type":"Food & Drink"
        }
    ],
    "sg:menulink":"http://www.allmenus.com/ky/hodgenville/79652-pizza-hut/menu/",
    "sg:phone":"+1 270 358 9545",
    "sg:postcode":"42748",
    "sg:province":"KY",
    "sg:tags":[
        "american",
        "pizza"
    ],
    "wof:name":"Pizza Hut",
    "wof:placetype":"venue"
},
  "geometry": {"coordinates":[-85.738918,37.585302],"type":"Point"}
}