{
  "type": "Feature",
  "properties": {
    "addr:full":"4512 Church St Latonia KY 41015",
    "addr:housenumber":"4512",
    "addr:postcode":"41015",
    "addr:street":"Church St",
    "iso:country":"US",
    "sg:address":"4512 Church St",
    "sg:city":"Latonia",
    "sg:classifiers":[
        {
            "category":"Education",
            "subcategory":"Vocational School",
            "type":"Public Place"
        }
    ],
    "sg:phone":"+1 859 431 7732",
    "sg:postcode":"41015",
    "sg:province":"KY",
    "sg:tags":[
        "processing",
        "datum"
    ],
    "wof:name":"Career Designers",
    "wof:placetype":"venue"
},
  "geometry": {"coordinates":[-84.502499,39.040297],"type":"Point"}
}