{
  "type": "Feature",
  "properties": {
    "iso:country":"US",
    "sg:address":"14906 State Hwy 121",
    "sg:city":"New Concord",
    "sg:classifiers":[
        {
            "category":"Food & Beverages",
            "subcategory":"Groceries & Convenience Stores",
            "type":"Retail Goods"
        }
    ],
    "sg:phone":"+1 270 436 6300",
    "sg:postcode":"42076",
    "sg:province":"KY",
    "wof:name":"Kentucky Lake Lottery",
    "wof:placetype":"venue"
},
  "geometry": {"coordinates":[-88.10678799999999,36.501427],"type":"Point"}
}