{
  "type": "Feature",
  "properties": {
    "iso:country":"US",
    "sg:address":"807 Paducah Rd",
    "sg:city":"Mayfield",
    "sg:classifiers":[
        {
            "category":"Food & Beverages",
            "subcategory":"Specialty",
            "type":"Retail Goods"
        }
    ],
    "sg:phone":"+1 270 247 4098",
    "sg:postcode":"42066",
    "sg:province":"KY",
    "sg:tags":[
        "vitamin"
    ],
    "wof:name":"Innovative Health Products",
    "wof:placetype":"venue"
},
  "geometry": {"coordinates":[-88.638803,36.750501],"type":"Point"}
}