{
  "type": "Feature",
  "properties": {
    "iso:country":"US",
    "sg:address":"301 Center St",
    "sg:city":"Hazel",
    "sg:classifiers":[
        {
            "category":"Organizations",
            "subcategory":"Religious Organization",
            "type":"Services"
        }
    ],
    "sg:phone":"+1 270 492 8603",
    "sg:postcode":"42049",
    "sg:province":"KY",
    "sg:tags":[
        "church"
    ],
    "wof:name":"Hazel Church Of Christ",
    "wof:placetype":"venue"
},
  "geometry": {"coordinates":[-88.325874,36.502377],"type":"Point"}
}