{
  "type": "Feature",
  "properties": {
    "iso:country":"US",
    "sg:address":"2002 Madison Ave",
    "sg:city":"Covington",
    "sg:classifiers":[
        {
            "category":"Social Services",
            "type":"Services"
        },
        {
            "category":"Health Services",
            "subcategory":"Clinic",
            "type":"Services"
        },
        {
            "category":"Organizations",
            "subcategory":"Community Association",
            "type":"Services"
        },
        {
            "category":"Government",
            "subcategory":"Office",
            "type":"Public Place"
        }
    ],
    "sg:phone":"+1 859 431 3345",
    "sg:postcode":"41014",
    "sg:province":"KY",
    "sg:tags":[
        "planning",
        "information",
        "family",
        "services-information",
        "program",
        "referral"
    ],
    "wof:name":"Health Services Dept",
    "wof:placetype":"venue"
},
  "geometry": {"coordinates":[-84.50582900000001,39.066949],"type":"Point"}
}