{
  "type": "Feature",
  "properties": {
    "iso:country":"US",
    "sg:address":"488 Erlanger Rd",
    "sg:city":"Erlanger",
    "sg:classifiers":[
        {
            "category":"Professional",
            "subcategory":"Lawyer & Legal Services",
            "type":"Services"
        }
    ],
    "sg:phone":"+1 859 727 1000",
    "sg:postcode":"41018",
    "sg:province":"KY",
    "sg:tags":[
        "attorney"
    ],
    "wof:name":"W Ron Adams",
    "wof:placetype":"venue"
},
  "geometry": {"coordinates":[-84.606205,39.024298],"type":"Point"}
}