{
  "type": "Feature",
  "properties": {
    "iso:country":"US",
    "sg:address":"634 E Market St",
    "sg:city":"Louisville",
    "sg:classifiers":[
        {
            "category":"Professional",
            "subcategory":"Business Services",
            "type":"Services"
        }
    ],
    "sg:phone":"+1 502 895 0110",
    "sg:postcode":"40202",
    "sg:province":"KY",
    "sg:tags":[
        "interior",
        "consultant",
        "design",
        "decorator"
    ],
    "wof:name":"Morris Dore Interiors",
    "wof:placetype":"venue"
},
  "geometry": {"coordinates":[-85.740607,38.253406],"type":"Point"}
}