{
  "type": "Feature",
  "properties": {
    "iso:country":"US",
    "sg:address":"324 N Walnut St",
    "sg:city":"Carlisle",
    "sg:classifiers":[
        {
            "category":"Building & Trades",
            "subcategory":"Construction",
            "type":"Services"
        }
    ],
    "sg:phone":"+1 859 289 5392",
    "sg:postcode":"40311",
    "sg:province":"KY",
    "sg:tags":[
        "road",
        "contractor"
    ],
    "wof:name":"State Highway Dept",
    "wof:placetype":"venue"
},
  "geometry": {"coordinates":[-84.026224,38.312822],"type":"Point"}
}