{
  "type": "Feature",
  "properties": {
    "iso:country":"US",
    "sg:address":"6645 Flaherty Rd",
    "sg:city":"Vine Grove",
    "sg:classifiers":[
        {
            "category":"Organizations",
            "subcategory":"Community Association",
            "type":"Services"
        }
    ],
    "sg:phone":"+1 270 828 5483",
    "sg:postcode":"40175",
    "sg:province":"KY",
    "sg:tags":[
        "military"
    ],
    "wof:name":"AMVETS Post 103",
    "wof:placetype":"venue"
},
  "geometry": {"coordinates":[-86.046813,37.829296],"type":"Point"}
}