{
  "type": "Feature",
  "properties": {
    "iso:country":"US",
    "sg:address":"730 E Main St",
    "sg:city":"Frankfort",
    "sg:classifiers":[
        {
            "category":"Building & Trades",
            "subcategory":"Construction",
            "type":"Services"
        }
    ],
    "sg:phone":"+1 502 226 1525",
    "sg:postcode":"40601",
    "sg:province":"KY",
    "sg:tags":[
        "painter"
    ],
    "wof:name":"Kentucky Painting Co",
    "wof:placetype":"venue"
},
  "geometry": {"coordinates":[-84.84439399999999,38.204108],"type":"Point"}
}