{
  "type": "Feature",
  "properties": {
    "iso:country":"US",
    "sg:address":"206 Orchard Dr",
    "sg:city":"Nicholasville",
    "sg:classifiers":[
        {
            "category":"Organizations",
            "subcategory":"Non-profit Organization",
            "type":"Services"
        },
        {
            "category":"Social Services",
            "type":"Services"
        }
    ],
    "sg:phone":"+1 859 885 4391",
    "sg:postcode":"40356",
    "sg:province":"KY",
    "sg:tags":[
        "human"
    ],
    "wof:name":"Red Cross Nicholasville Chptr",
    "wof:placetype":"venue"
},
  "geometry": {"coordinates":[-84.566041,37.893934],"type":"Point"}
}