{
  "type": "Feature",
  "properties": {
    "iso:country":"US",
    "sg:address":"109 W Woodford St",
    "sg:city":"Lawrenceburg",
    "sg:classifiers":[
        {
            "category":"Shopping",
            "subcategory":"Bicycles & Sporting Goods",
            "type":"Retail Goods"
        }
    ],
    "sg:phone":"+1 502 859 5229",
    "sg:postcode":"40342",
    "sg:province":"KY",
    "sg:tags":[
        "horse",
        "furnishing"
    ],
    "wof:name":"Lucky Horseshoe Saddlery & Gft",
    "wof:placetype":"venue"
},
  "geometry": {"coordinates":[-84.896963,38.036878],"type":"Point"}
}