{
  "type": "Feature",
  "properties": {
    "iso:country":"US",
    "sg:address":"4233 Bardstown Rd",
    "sg:city":"Louisville",
    "sg:classifiers":[
        {
            "category":"Professional",
            "subcategory":"Lawyer & Legal Services",
            "type":"Services"
        }
    ],
    "sg:phone":"+1 502 968 1132",
    "sg:postcode":"40218",
    "sg:province":"KY",
    "sg:tags":[
        "attorney"
    ],
    "wof:name":"Keith A Stonecipher",
    "wof:placetype":"venue"
},
  "geometry": {"coordinates":[-85.638239,38.187472],"type":"Point"}
}