{
  "type": "Feature",
  "properties": {
    "iso:country":"US",
    "sg:address":"1250 N Main St",
    "sg:city":"Tompkinsville",
    "sg:classifiers":[
        {
            "category":"Restaurant",
            "type":"Food & Drink"
        }
    ],
    "sg:phone":"+1 270 487 9801",
    "sg:postcode":"42167",
    "sg:province":"KY",
    "wof:name":"Mariachis Mexican Restaurant",
    "wof:placetype":"venue"
},
  "geometry": {"coordinates":[-85.686744,36.717612],"type":"Point"}
}