{
  "type": "Feature",
  "properties": {
    "iso:country":"US",
    "sg:address":"537 Waller Ave",
    "sg:city":"Lexington",
    "sg:classifiers":[
        {
            "category":"Restaurant",
            "type":"Food & Drink"
        }
    ],
    "sg:phone":"+1 859 254 2145",
    "sg:postcode":"40504",
    "sg:province":"KY",
    "wof:name":"Roly Poly Of Lexington",
    "wof:placetype":"venue"
},
  "geometry": {"coordinates":[-84.52205600000001,38.032319],"type":"Point"}
}