{
  "type": "Feature",
  "properties": {
    "addr:full":"1071 Berea Rd Richmond KY 40475",
    "addr:housenumber":"1071",
    "addr:postcode":"40475",
    "addr:street":"Berea Rd",
    "iso:country":"US",
    "sg:address":"1071 Berea Rd",
    "sg:city":"Richmond",
    "sg:classifiers":[
        {
            "category":"Restaurant",
            "type":"Food & Drink"
        }
    ],
    "sg:menulink":"http://www.allmenus.com/ky/richmond/233106-lees-famous-recipe-chicken/menu/",
    "sg:phone":"+1 606 349 3626",
    "sg:postcode":"40475",
    "sg:province":"KY",
    "sg:tags":[
        "american"
    ],
    "wof:name":"Lee's Famous Recipe Chicken",
    "wof:placetype":"venue"
},
  "geometry": {"coordinates":[-84.27296200000001,37.731064],"type":"Point"}
}