{
  "type": "Feature",
  "properties": {
    "iso:country":"US",
    "sg:address":"203 Kentucky Ave",
    "sg:city":"Pineville",
    "sg:classifiers":[
        {
            "category":"Wholesale",
            "subcategory":"Medical Equipment & Supplies",
            "type":"Manufacturing & Wholesale Goods"
        }
    ],
    "sg:phone":"+1 606 337 1890",
    "sg:postcode":"40977",
    "sg:province":"KY",
    "sg:tags":[
        "physician",
        "surgeon"
    ],
    "wof:name":"Apria Healthcare",
    "wof:placetype":"venue"
},
  "geometry": {"coordinates":[-83.69409400000001,36.760617],"type":"Point"}
}