{
  "type": "Feature",
  "properties": {
    "iso:country":"US",
    "sg:address":"30 Oscar Dick Rd",
    "sg:city":"Monticello",
    "sg:classifiers":[
        {
            "category":"Social Services",
            "subcategory":"Child Care",
            "type":"Services"
        }
    ],
    "sg:phone":"+1 606 348 4205",
    "sg:postcode":"42633",
    "sg:province":"KY",
    "sg:tags":[
        "day"
    ],
    "wof:name":"Weymouth Family Childcare",
    "wof:placetype":"venue"
},
  "geometry": {"coordinates":[-84.878956,36.846445],"type":"Point"}
}