{
  "type": "Feature",
  "properties": {
    "iso:country":"US",
    "sg:address":"3510 Grand Ave",
    "sg:city":"Louisville",
    "sg:classifiers":[
        {
            "category":"Social Services",
            "subcategory":"Child Care",
            "type":"Services"
        }
    ],
    "sg:phone":"+1 502 772 3727",
    "sg:postcode":"40211",
    "sg:province":"KY",
    "wof:name":"Alice M Robinson",
    "wof:placetype":"venue"
},
  "geometry": {"coordinates":[-85.811657,38.241787],"type":"Point"}
}