{
  "type": "Feature",
  "properties": {
    "iso:country":"US",
    "sg:address":"3403 Hycliffe Ave",
    "sg:city":"Louisville",
    "sg:classifiers":[
        {
            "category":"Shopping",
            "type":"Retail Goods"
        }
    ],
    "sg:phone":"+1 502 594 0694",
    "sg:postcode":"40207",
    "sg:province":"KY",
    "sg:tags":[
        "mural"
    ],
    "wof:name":"Art Dana",
    "wof:placetype":"venue"
},
  "geometry": {"coordinates":[-85.65832,38.243195],"type":"Point"}
}