{
  "type": "Feature",
  "properties": {
    "addr:full":"7033 Dixie Hwy S Elizabethtown KY 42701",
    "addr:housenumber":"7033",
    "addr:postcode":"42701",
    "addr:street":"Dixie Hwy S",
    "iso:country":"US",
    "sg:address":"7033 Dixie Hwy S",
    "sg:city":"Elizabethtown",
    "sg:classifiers":[
        {
            "category":"Recreation",
            "type":"Entertainment"
        }
    ],
    "sg:phone":"+1 270 234 8352",
    "sg:postcode":"42701",
    "sg:province":"KY",
    "sg:tags":[
        "martial",
        "arts",
        "instruction"
    ],
    "wof:name":"Harris Martial Arts Inc",
    "wof:placetype":"venue"
},
  "geometry": {"coordinates":[-85.912779,37.789358],"type":"Point"}
}