{
  "type": "Feature",
  "properties": {
    "iso:country":"US",
    "sg:address":"1235 Manchester St",
    "sg:city":"Lexington",
    "sg:classifiers":[
        {
            "category":"Home & Garden",
            "subcategory":"Garden Supply",
            "type":"Retail Goods"
        }
    ],
    "sg:phone":"+1 859 255 9663",
    "sg:postcode":"40504",
    "sg:province":"KY",
    "sg:tags":[
        "mulch"
    ],
    "wof:name":"Wholesale Mulch",
    "wof:placetype":"venue"
},
  "geometry": {"coordinates":[-84.519643,38.056785],"type":"Point"}
}