{
  "type": "Feature",
  "properties": {
    "iso:country":"US",
    "sg:address":"414 N Mulberry St",
    "sg:city":"Elizabethtown",
    "sg:classifiers":[
        {
            "category":"Professional",
            "subcategory":"Employment Agencies",
            "type":"Services"
        }
    ],
    "sg:phone":"+1 270 737 6664",
    "sg:postcode":"42701",
    "sg:province":"KY",
    "sg:tags":[
        "help",
        "contractor"
    ],
    "wof:name":"Omni Personnel",
    "wof:placetype":"venue"
},
  "geometry": {"coordinates":[-85.854451,37.699478],"type":"Point"}
}