{
  "type": "Feature",
  "properties": {
    "iso:country":"US",
    "sg:address":"5800 Scottsville Rd",
    "sg:city":"Bowling Green",
    "sg:classifiers":[
        {
            "category":"Recreation",
            "type":"Entertainment"
        }
    ],
    "sg:phone":"+1 270 781 6072",
    "sg:postcode":"42104",
    "sg:province":"KY",
    "sg:tags":[
        "range",
        "practice",
        "golf"
    ],
    "wof:name":"Otte Golf Ctr",
    "wof:placetype":"venue"
},
  "geometry": {"coordinates":[-86.407111,36.916269],"type":"Point"}
}