{
  "type": "Feature",
  "properties": {
    "addr:full":"217 E Walnut St Mayfield KY 42066",
    "addr:housenumber":"217",
    "addr:postcode":"42066",
    "addr:street":"E Walnut St",
    "iso:country":"US",
    "sg:address":"217 E Walnut St",
    "sg:city":"Mayfield",
    "sg:classifiers":[
        {
            "category":"Education",
            "subcategory":"Dance Studio",
            "type":"Public Place"
        }
    ],
    "sg:phone":"+1 270 251 2912",
    "sg:postcode":"42066",
    "sg:province":"KY",
    "sg:tags":[
        "instruction",
        "dancing"
    ],
    "wof:name":"Sue Ann's Dance Factory",
    "wof:placetype":"venue"
},
  "geometry": {"coordinates":[-88.634435,36.738438],"type":"Point"}
}