{
  "type": "Feature",
  "properties": {
    "addr:full":"445 Branch St Madisonville KY 42431",
    "addr:housenumber":"445",
    "addr:postcode":"42431",
    "addr:street":"Branch St",
    "iso:country":"US",
    "sg:address":"445 Branch St",
    "sg:city":"Madisonville",
    "sg:classifiers":[
        {
            "category":"Organizations",
            "subcategory":"Religious Organization",
            "type":"Services"
        }
    ],
    "sg:phone":"+1 270 821 4121",
    "sg:postcode":"42431",
    "sg:province":"KY",
    "wof:name":"Church Of God In Christ",
    "wof:placetype":"venue"
},
  "geometry": {"coordinates":[-87.491075,37.330469],"type":"Point"}
}