{
  "type": "Feature",
  "properties": {
    "iso:country":"US",
    "sg:address":"221 Grant St",
    "sg:city":"Fort Thomas",
    "sg:classifiers":[
        {
            "category":"Building & Trades",
            "subcategory":"Construction",
            "type":"Services"
        }
    ],
    "sg:phone":"+1 859 441 4023",
    "sg:postcode":"41075",
    "sg:province":"KY",
    "sg:tags":[
        "repairing",
        "remodeling",
        "contractor"
    ],
    "wof:name":"Whittle Brothers Remodeling",
    "wof:placetype":"venue"
},
  "geometry": {"coordinates":[-84.45197400000001,39.057773],"type":"Point"}
}