{
  "type": "Feature",
  "properties": {
    "iso:country":"US",
    "sg:address":"1530 State Hwy 121",
    "sg:city":"Murray",
    "sg:classifiers":[
        {
            "category":"Retail",
            "subcategory":"Car Wash",
            "type":"Services"
        }
    ],
    "sg:phone":"+1 270 767 0820",
    "sg:postcode":"42071",
    "sg:province":"KY",
    "sg:tags":[
        "polishing",
        "washing"
    ],
    "wof:name":"Murray Auto Spa",
    "wof:placetype":"venue"
},
  "geometry": {"coordinates":[-88.32323,36.623005],"type":"Point"}
}