{
  "type": "Feature",
  "properties": {
    "iso:country":"US",
    "sg:address":"1523 Gaidry Rd",
    "sg:city":"Lexington",
    "sg:classifiers":[
        {
            "category":"Professional",
            "subcategory":"Business Services",
            "type":"Services"
        }
    ],
    "sg:phone":"+1 859 293 6321",
    "sg:postcode":"40505",
    "sg:province":"KY",
    "wof:name":"Artful Interiors",
    "wof:placetype":"venue"
},
  "geometry": {"coordinates":[-84.447135,38.046171],"type":"Point"}
}