{
  "type": "Feature",
  "properties": {
    "iso:country":"US",
    "sg:address":"1288 S Laurel Rd",
    "sg:city":"London",
    "sg:classifiers":[
        {
            "category":"Retail",
            "subcategory":"Auto Repair",
            "type":"Services"
        }
    ],
    "sg:phone":"+1 606 864 6644",
    "sg:postcode":"40744",
    "sg:province":"KY",
    "sg:tags":[
        "glass",
        "coating",
        "tinting"
    ],
    "wof:name":"Custom Designs",
    "wof:placetype":"venue"
},
  "geometry": {"coordinates":[-84.067842,37.098544],"type":"Point"}
}