{
  "type": "Feature",
  "properties": {
    "addr:full":"202 W Main St Elkton KY 42220",
    "addr:housenumber":"202",
    "addr:postcode":"42220",
    "addr:street":"W Main St",
    "iso:country":"US",
    "sg:address":"202 W Main St",
    "sg:city":"Elkton",
    "sg:classifiers":[
        {
            "category":"Food & Beverages",
            "subcategory":"Groceries & Convenience Stores",
            "type":"Retail Goods"
        }
    ],
    "sg:phone":"+1 270 265 2456",
    "sg:postcode":"42220",
    "sg:province":"KY",
    "sg:tags":[
        "grocer"
    ],
    "wof:name":"Piggly Wiggly",
    "wof:placetype":"venue"
},
  "geometry": {"coordinates":[-87.156662,36.810051],"type":"Point"}
}