{
  "type": "Feature",
  "properties": {
    "iso:country":"US",
    "sg:address":"7000 Houston Rd",
    "sg:city":"Florence",
    "sg:classifiers":[
        {
            "category":"Building & Trades",
            "subcategory":"Construction",
            "type":"Services"
        }
    ],
    "sg:phone":"+1 859 525 6720",
    "sg:postcode":"41042",
    "sg:province":"KY",
    "sg:tags":[
        "builder",
        "patio",
        "deck"
    ],
    "wof:name":"Insul Deck LLC",
    "wof:placetype":"venue"
},
  "geometry": {"coordinates":[-84.645876,39.011019],"type":"Point"}
}