{
  "type": "Feature",
  "properties": {
    "iso:country":"US",
    "sg:address":"14405 US Hwy 27",
    "sg:city":"Waynesburg",
    "sg:classifiers":[
        {
            "category":"Building & Trades",
            "subcategory":"Construction",
            "type":"Services"
        }
    ],
    "sg:phone":"+1 606 379 5174",
    "sg:postcode":"40489",
    "sg:province":"KY",
    "sg:tags":[
        "home",
        "builder"
    ],
    "wof:name":"BTR Construction Co",
    "wof:placetype":"venue"
},
  "geometry": {"coordinates":[-84.65860600000001,37.33201],"type":"Point"}
}