{
  "type": "Feature",
  "properties": {
    "iso:country":"US",
    "sg:address":"1818 Louisville Rd",
    "sg:city":"Bowling Green",
    "sg:classifiers":[
        {
            "category":"Building & Trades",
            "subcategory":"Construction",
            "type":"Services"
        }
    ],
    "sg:phone":"+1 270 842 9800",
    "sg:postcode":"42101",
    "sg:province":"KY",
    "sg:tags":[
        "general",
        "contractor"
    ],
    "wof:name":"Phil Brown Construction",
    "wof:placetype":"venue"
},
  "geometry": {"coordinates":[-86.418646,37.007861],"type":"Point"}
}