{
  "type": "Feature",
  "properties": {
    "addr:full":"616 Main St Shelbyville KY 40065",
    "addr:housenumber":"616",
    "addr:postcode":"40065",
    "addr:street":"Main St",
    "iso:country":"US",
    "sg:address":"616 Main St",
    "sg:city":"Shelbyville",
    "sg:classifiers":[
        {
            "category":"Bars & Pubs",
            "type":"Food & Drink"
        }
    ],
    "sg:phone":"+1 502 633 2127",
    "sg:postcode":"40065",
    "sg:province":"KY",
    "wof:name":"Just Another Bar",
    "wof:placetype":"venue"
},
  "geometry": {"coordinates":[-85.218628,38.211063],"type":"Point"}
}