{
  "type": "Feature",
  "properties": {
    "iso:country":"US",
    "sg:address":"109 S Main St",
    "sg:city":"Elizabethtown",
    "sg:classifiers":[
        {
            "category":"Banks & Credit Unions",
            "subcategory":"Bank",
            "type":"Services"
        }
    ],
    "sg:phone":"+1 270 765 2221",
    "sg:postcode":"42701",
    "sg:province":"KY",
    "sg:tags":[
        "loan",
        "real estate"
    ],
    "wof:name":"CFIC Home Mortgage",
    "wof:placetype":"venue"
},
  "geometry": {"coordinates":[-85.858543,37.692477],"type":"Point"}
}