{
  "type": "Feature",
  "properties": {
    "iso:country":"US",
    "sg:address":"11800 Greenville Rd",
    "sg:city":"Hopkinsville",
    "sg:classifiers":[
        {
            "category":"Shopping",
            "subcategory":"Florist",
            "type":"Retail Goods"
        }
    ],
    "sg:phone":"+1 270 269 2219",
    "sg:postcode":"42240",
    "sg:province":"KY",
    "wof:name":"Mc Kinney's Flowers & Gifts",
    "wof:placetype":"venue"
},
  "geometry": {"coordinates":[-87.36197300000001,36.980166],"type":"Point"}
}