{
  "type": "Feature",
  "properties": {
    "addr:full":"1400 Browns Ln Louisville KY 40207",
    "addr:housenumber":"1400",
    "addr:postcode":"40207",
    "addr:street":"Browns Ln",
    "iso:country":"US",
    "sg:address":"1400 Browns Ln",
    "sg:city":"Louisville",
    "sg:classifiers":[
        {
            "category":"Professional",
            "subcategory":"Research",
            "type":"Services"
        }
    ],
    "sg:phone":"+1 502 479 9250",
    "sg:postcode":"40207",
    "sg:province":"KY",
    "sg:tags":[
        "environmental",
        "ecological"
    ],
    "wof:name":"White Environmental Svc",
    "wof:placetype":"venue"
},
  "geometry": {"coordinates":[-85.62773799999999,38.233621],"type":"Point"}
}