{
  "type": "Feature",
  "properties": {
    "iso:country":"US",
    "sg:address":"109 S Hurstbourne Pkwy",
    "sg:city":"Louisville",
    "sg:classifiers":[
        {
            "category":"Retail",
            "subcategory":"Laundry & Dry Cleaning",
            "type":"Services"
        }
    ],
    "sg:phone":"+1 502 584 0241",
    "sg:postcode":"40222",
    "sg:province":"KY",
    "sg:tags":[
        "cleaners",
        "rug",
        "carpet"
    ],
    "sg:website":"www.carrellrogers.com",
    "wof:name":"Carrell Rogers Flooring",
    "wof:placetype":"venue"
},
  "geometry": {"coordinates":[-85.57687,38.242404],"type":"Point"}
}