{
  "type": "Feature",
  "properties": {
    "addr:full":"6095 Sharon Grove Rd Elkton KY 42220",
    "addr:housenumber":"6095",
    "addr:postcode":"42220",
    "addr:street":"Sharon Grove Rd",
    "iso:country":"US",
    "sg:address":"6095 Sharon Grove Rd",
    "sg:city":"Elkton",
    "sg:classifiers":[
        {
            "category":"Food & Beverages",
            "subcategory":"Groceries & Convenience Stores",
            "type":"Retail Goods"
        }
    ],
    "sg:phone":"+1 270 277 9454",
    "sg:postcode":"42220",
    "sg:province":"KY",
    "sg:tags":[
        "grocer"
    ],
    "wof:name":"Highway 106 Market",
    "wof:placetype":"venue"
},
  "geometry": {"coordinates":[-87.055481,36.936377],"type":"Point"}
}