{
  "type": "Feature",
  "properties": {
    "iso:country":"US",
    "sg:address":"643 Comanche Trl",
    "sg:city":"Frankfort",
    "sg:classifiers":[
        {
            "category":"Government",
            "subcategory":"Office",
            "type":"Public Place"
        }
    ],
    "sg:phone":"+1 502 227 9651",
    "sg:postcode":"40601",
    "sg:province":"KY",
    "sg:website":"www.usda.gov",
    "wof:name":"US Dept Agricultr Veterinary",
    "wof:placetype":"venue"
},
  "geometry": {"coordinates":[-84.83973899999999,38.215865],"type":"Point"}
}