{
  "type": "Feature",
  "properties": {
    "iso:country":"US",
    "sg:address":"2313 Woodhill Dr",
    "sg:city":"Lexington",
    "sg:classifiers":[
        {
            "category":"Food & Beverages",
            "subcategory":"Candy",
            "type":"Retail Goods"
        }
    ],
    "sg:phone":"+1 859 268 1559",
    "sg:postcode":"40509",
    "sg:province":"KY",
    "sg:tags":[
        "confectionery"
    ],
    "wof:name":"Ruth Hunt Candy Co",
    "wof:placetype":"venue"
},
  "geometry": {"coordinates":[-84.455085,38.017527],"type":"Point"}
}