{
  "type": "Feature",
  "properties": {
    "addr:full":"2956 Jackson St Paducah KY 42003",
    "addr:housenumber":"2956",
    "addr:postcode":"42003",
    "addr:street":"Jackson St",
    "iso:country":"US",
    "sg:address":"2956 Jackson St",
    "sg:city":"Paducah",
    "sg:classifiers":[
        {
            "category":"Restaurant",
            "type":"Food & Drink"
        }
    ],
    "sg:menulink":"http://www.allmenus.com/ky/paducah/96204-taco-johns/menu/",
    "sg:phone":"+1 270 442 9399",
    "sg:postcode":"42003",
    "sg:province":"KY",
    "sg:tags":[
        "american",
        "mexican"
    ],
    "wof:name":"Taco John's",
    "wof:placetype":"venue"
},
  "geometry": {"coordinates":[-88.630861,37.066814],"type":"Point"}
}