{
  "type": "Feature",
  "properties": {
    "iso:country":"US",
    "sg:address":"1609 S Main St",
    "sg:city":"Hopkinsville",
    "sg:classifiers":[
        {
            "category":"Health Services",
            "subcategory":"Doctor",
            "type":"Services"
        }
    ],
    "sg:phone":"+1 270 887 0783",
    "sg:postcode":"42240",
    "sg:province":"KY",
    "sg:tags":[
        "physician",
        "surgeon"
    ],
    "wof:name":"West Ky Neurological Medicine",
    "wof:placetype":"venue"
},
  "geometry": {"coordinates":[-87.491415,36.862029],"type":"Point"}
}