{
  "type": "Feature",
  "properties": {
    "addr:full":"3720 Louisa Rd Catlettsburg KY 41129",
    "addr:housenumber":"3720",
    "addr:postcode":"41129",
    "addr:street":"Louisa Rd",
    "iso:country":"US",
    "sg:address":"3720 Louisa Rd",
    "sg:city":"Catlettsburg",
    "sg:classifiers":[
        {
            "category":"Restaurant",
            "type":"Food & Drink"
        }
    ],
    "sg:menulink":"http://www.allmenus.com/ky/catlettsburg/157628-taco-maker/menu/",
    "sg:phone":"+1 606 739 4044",
    "sg:postcode":"41129",
    "sg:province":"KY",
    "sg:tags":[
        "mexican"
    ],
    "wof:name":"Taco Maker",
    "wof:placetype":"venue"
},
  "geometry": {"coordinates":[-82.60096,38.40046],"type":"Point"}
}