{
  "type": "Feature",
  "properties": {
    "iso:country":"US",
    "sg:address":"318 W Washington St",
    "sg:city":"Glasgow",
    "sg:classifiers":[
        {
            "category":"Government",
            "subcategory":"Office",
            "type":"Public Place"
        }
    ],
    "sg:phone":"+1 270 651 5562",
    "sg:postcode":"42141",
    "sg:province":"KY",
    "wof:name":"Barren County Plumbing Inspctr",
    "wof:placetype":"venue"
},
  "geometry": {"coordinates":[-85.91778600000001,36.997157],"type":"Point"}
}