{
  "type": "Feature",
  "properties": {
    "iso:country":"US",
    "sg:address":"145 E Center St",
    "sg:city":"Madisonville",
    "sg:classifiers":[
        {
            "category":"Government",
            "subcategory":"Office",
            "type":"Public Place"
        }
    ],
    "sg:phone":"+1 270 824 7053",
    "sg:postcode":"42431",
    "sg:province":"KY",
    "sg:tags":[
        "program",
        "state",
        "adm"
    ],
    "wof:name":"Economic Development Cabinet",
    "wof:placetype":"venue"
},
  "geometry": {"coordinates":[-87.49639500000001,37.327829],"type":"Point"}
}