{
  "type": "Feature",
  "properties": {
    "addr:full":"3514 Barbour Place Cir Louisville KY 40241",
    "addr:housenumber":"3514",
    "addr:postcode":"40241",
    "addr:street":"Barbour Place Cir",
    "iso:country":"US",
    "sg:address":"3514 Barbour Place Cir",
    "sg:city":"Louisville",
    "sg:classifiers":[
        {
            "category":"Building & Trades",
            "subcategory":"Construction",
            "type":"Services"
        }
    ],
    "sg:phone":"+1 502 412 3310",
    "sg:postcode":"40241",
    "sg:province":"KY",
    "sg:tags":[
        "resurfacing",
        "laying",
        "refinishing",
        "floor"
    ],
    "wof:name":"Artisan Wood Floors",
    "wof:placetype":"venue"
},
  "geometry": {"coordinates":[-85.609115,38.299737],"type":"Point"}
}