{
  "type": "Feature",
  "properties": {
    "iso:country":"US",
    "sg:address":"101 Peggy Flat Rd",
    "sg:city":"Berea",
    "sg:classifiers":[
        {
            "category":"Restaurant",
            "type":"Food & Drink"
        }
    ],
    "sg:menulink":"http://www.allmenus.com/ky/berea/120448-subway/menu/",
    "sg:phone":"+1 859 985 7371",
    "sg:postcode":"40403",
    "sg:province":"KY",
    "sg:tags":[
        "american",
        "sandwich"
    ],
    "wof:name":"Subway",
    "wof:placetype":"venue"
},
  "geometry": {"coordinates":[-84.315575,37.609964],"type":"Point"}
}