{
  "type": "Feature",
  "properties": {
    "addr:full":"10609 Millers Ln Louisville KY 40272",
    "addr:housenumber":"10609",
    "addr:postcode":"40272",
    "addr:street":"Millers Ln",
    "iso:country":"US",
    "sg:address":"10609 Millers Ln",
    "sg:city":"Louisville",
    "sg:classifiers":[
        {
            "category":"Building & Trades",
            "subcategory":"Construction",
            "type":"Services"
        }
    ],
    "sg:phone":"+1 502 933 1912",
    "sg:postcode":"40272",
    "sg:province":"KY",
    "sg:tags":[
        "house"
    ],
    "wof:name":"Steffen A Snodgrass Custom Con",
    "wof:placetype":"venue"
},
  "geometry": {"coordinates":[-85.850397,38.102054],"type":"Point"}
}