{
  "type": "Feature",
  "properties": {
    "iso:country":"US",
    "sg:address":"2827 Hale Ave",
    "sg:city":"Louisville",
    "sg:classifiers":[
        {
            "category":"Banks & Credit Unions",
            "subcategory":"Bank",
            "type":"Services"
        }
    ],
    "sg:phone":"+1 502 772 7283",
    "sg:postcode":"40211",
    "sg:province":"KY",
    "wof:name":"Rale Federal Credit Union",
    "wof:placetype":"venue"
},
  "geometry": {"coordinates":[-85.803011,38.23977],"type":"Point"}
}