{
  "type": "Feature",
  "properties": {
    "iso:country":"US",
    "sg:address":"424 S Mulberry St",
    "sg:city":"Elizabethtown",
    "sg:classifiers":[
        {
            "category":"Wholesale",
            "subcategory":"Machinery & Supplies",
            "type":"Manufacturing & Wholesale Goods"
        }
    ],
    "sg:phone":"+1 270 737 1721",
    "sg:postcode":"42701",
    "sg:province":"KY",
    "sg:tags":[
        "contractor"
    ],
    "sg:website":"www.vermeer.com",
    "wof:name":"Vermeer Sales & Svc",
    "wof:placetype":"venue"
},
  "geometry": {"coordinates":[-85.87209300000001,37.68515],"type":"Point"}
}