{
  "type": "Feature",
  "properties": {
    "iso:country":"US",
    "sg:address":"805 Bluegrass Ave",
    "sg:city":"Louisville",
    "sg:classifiers":[
        {
            "category":"Personal",
            "subcategory":"Beauty Salon",
            "type":"Services"
        }
    ],
    "sg:phone":"+1 502 367 1857",
    "sg:postcode":"40215",
    "sg:province":"KY",
    "wof:name":"Hair Studio 805",
    "wof:placetype":"venue"
},
  "geometry": {"coordinates":[-85.776779,38.179606],"type":"Point"}
}