{
  "type": "Feature",
  "properties": {
    "iso:country":"US",
    "sg:address":"186 Redmar Ln",
    "sg:city":"Radcliff",
    "sg:classifiers":[
        {
            "category":"Insurance",
            "subcategory":"Insurance Agent",
            "type":"Services"
        }
    ],
    "sg:phone":"+1 270 351 2550",
    "sg:postcode":"40160",
    "sg:province":"KY",
    "wof:name":"Johnson & Assoc Inc",
    "wof:placetype":"venue"
},
  "geometry": {"coordinates":[-85.948655,37.856716],"type":"Point"}
}