{
  "type": "Feature",
  "properties": {
    "addr:full":"2760 Frederica St Owensboro KY 42301",
    "addr:housenumber":"2760",
    "addr:postcode":"42301",
    "addr:street":"Frederica St",
    "iso:country":"US",
    "sg:address":"2760 Frederica St",
    "sg:city":"Owensboro",
    "sg:classifiers":[
        {
            "category":"Shopping",
            "subcategory":"Department Store",
            "type":"Retail Goods"
        }
    ],
    "sg:phone":"+1 270 684 0685",
    "sg:postcode":"42301",
    "sg:province":"KY",
    "wof:name":"Kmart",
    "wof:placetype":"venue"
},
  "geometry": {"coordinates":[-87.113687,37.747771],"type":"Point"}
}