{
  "type": "Feature",
  "properties": {
    "iso:country":"US",
    "sg:address":"289 Liberty St",
    "sg:city":"Lynch",
    "sg:classifiers":[
        {
            "category":"Building & Trades",
            "subcategory":"Cleaning & Sanitation",
            "type":"Services"
        }
    ],
    "sg:phone":"+1 606 848 2125",
    "sg:postcode":"40855",
    "sg:province":"KY",
    "sg:tags":[
        "janitor"
    ],
    "wof:name":"Thompson's Professional Jntrl",
    "wof:placetype":"venue"
},
  "geometry": {"coordinates":[-82.908018,36.964756],"type":"Point"}
}