{
  "type": "Feature",
  "properties": {
    "iso:country":"US",
    "sg:address":"302 Dixie Hwy E",
    "sg:city":"Elizabethtown",
    "sg:classifiers":[
        {
            "category":"Manufacturing",
            "subcategory":"Food",
            "type":"Manufacturing & Wholesale Goods"
        }
    ],
    "sg:phone":"+1 270 765 7226",
    "sg:postcode":"42701",
    "sg:province":"KY",
    "sg:tags":[
        "ice"
    ],
    "wof:name":"Bluegrass Ice",
    "wof:placetype":"venue"
},
  "geometry": {"coordinates":[-85.855946,37.691521],"type":"Point"}
}