{
  "type": "Feature",
  "properties": {
    "iso:country":"US",
    "sg:address":"104 S 3rd St",
    "sg:city":"Williamsburg",
    "sg:classifiers":[
        {
            "category":"Personal",
            "subcategory":"Beauty Salon",
            "type":"Services"
        }
    ],
    "sg:phone":"+1 606 549 3001",
    "sg:postcode":"40769",
    "sg:province":"KY",
    "sg:tags":[
        "shop"
    ],
    "wof:name":"Donna's Beauty Shop",
    "wof:placetype":"venue"
},
  "geometry": {"coordinates":[-84.15993400000001,36.742687],"type":"Point"}
}