{
  "type": "Feature",
  "properties": {
    "iso:country":"US",
    "sg:address":"1634 2nd St",
    "sg:city":"Henderson",
    "sg:classifiers":[
        {
            "category":"Shopping",
            "subcategory":"Musical Instruments",
            "type":"Retail Goods"
        }
    ],
    "sg:phone":"+1 270 830 9001",
    "sg:postcode":"42420",
    "sg:province":"KY",
    "sg:tags":[
        "music",
        "dealer"
    ],
    "wof:name":"Book & Music Exchange",
    "wof:placetype":"venue"
},
  "geometry": {"coordinates":[-87.57112100000001,37.832083],"type":"Point"}
}