{
  "type": "Feature",
  "properties": {
    "addr:full":"3707 Bardstown Rd Louisville KY 40218",
    "addr:housenumber":"3707",
    "addr:postcode":"40218",
    "addr:street":"Bardstown Rd",
    "iso:country":"US",
    "sg:address":"3707 Bardstown Rd",
    "sg:city":"Louisville",
    "sg:classifiers":[
        {
            "category":"Personal",
            "subcategory":"Beauty Salon",
            "type":"Services"
        }
    ],
    "sg:phone":"+1 502 458 6775",
    "sg:postcode":"40218",
    "sg:province":"KY",
    "wof:name":"Beauty Personified Hair Salon",
    "wof:placetype":"venue"
},
  "geometry": {"coordinates":[-85.657522,38.197861],"type":"Point"}
}