{
  "type": "Feature",
  "properties": {
    "iso:country":"US",
    "sg:address":"100 Laurel Dr",
    "sg:city":"Secaucus",
    "sg:classifiers":[
        {
            "category":"Shopping",
            "subcategory":"Gifts & Souvenirs",
            "type":"Retail Goods"
        }
    ],
    "sg:phone":"+1 201 420 4845",
    "sg:postcode":"41101",
    "sg:province":"KY",
    "sg:tags":[
        "shop"
    ],
    "sg:website":"www.fabergifts.com",
    "wof:name":"Faber Coe & Gregg Inc",
    "wof:placetype":"venue"
},
  "geometry": {"coordinates":[-82.696275,38.500029],"type":"Point"}
}