{
  "type": "Feature",
  "properties": {
    "addr:full":"200 Hillbrook Dr Owenton KY 40356",
    "addr:housenumber":"200",
    "addr:postcode":"40356",
    "addr:street":"Hillbrook Dr",
    "iso:country":"US",
    "sg:address":"200 Hillbrook Dr",
    "sg:city":"Owenton",
    "sg:classifiers":[
        {
            "category":"Utilities",
            "subcategory":"Cable",
            "type":"Services"
        }
    ],
    "sg:phone":"+1 502 484 5795",
    "sg:postcode":"40356",
    "sg:province":"KY",
    "sg:tags":[
        "television"
    ],
    "wof:name":"Dorothy Neal Cable TV",
    "wof:placetype":"venue"
},
  "geometry": {"coordinates":[-84.584013,37.908932],"type":"Point"}
}