{
  "type": "Feature",
  "properties": {
    "addr:full":"4514 Illinois Ave Louisville KY 40213",
    "addr:housenumber":"4514",
    "addr:postcode":"40213",
    "addr:street":"Illinois Ave",
    "iso:country":"US",
    "sg:address":"4514 Illinois Ave",
    "sg:city":"Louisville",
    "sg:classifiers":[
        {
            "category":"Manufacturing",
            "subcategory":"Building Materials",
            "type":"Manufacturing & Wholesale Goods"
        }
    ],
    "sg:phone":"+1 502 458 3139",
    "sg:postcode":"40213",
    "sg:province":"KY",
    "sg:tags":[
        "cabinet"
    ],
    "wof:name":"Interior Systems Mfg Inc",
    "wof:placetype":"venue"
},
  "geometry": {"coordinates":[-85.70127599999999,38.189448],"type":"Point"}
}