{
  "type": "Feature",
  "properties": {
    "addr:full":"1781 Patrick Dr Burlington KY 41005",
    "addr:housenumber":"1781",
    "addr:postcode":"41005",
    "addr:street":"Patrick Dr",
    "iso:country":"US",
    "sg:address":"1781 Patrick Dr",
    "sg:city":"Burlington",
    "sg:classifiers":[
        {
            "category":"Restaurant",
            "type":"Food & Drink"
        }
    ],
    "sg:phone":"+1 859 689 1888",
    "sg:postcode":"41005",
    "sg:province":"KY",
    "sg:tags":[
        "chinese"
    ],
    "wof:name":"Golden Wok",
    "wof:placetype":"venue"
},
  "geometry": {"coordinates":[-84.69409899999999,39.019199],"type":"Point"}
}