{
  "type": "Feature",
  "properties": {
    "addr:full":"220 Grandview Dr Fort Mitchell KY 41017",
    "addr:housenumber":"220",
    "addr:postcode":"41017",
    "addr:street":"Grandview Dr",
    "iso:country":"US",
    "sg:address":"220 Grandview Dr",
    "sg:city":"Fort Mitchell",
    "sg:classifiers":[
        {
            "category":"Building & Trades",
            "subcategory":"Cleaning & Sanitation",
            "type":"Services"
        }
    ],
    "sg:phone":"+1 859 426 5752",
    "sg:postcode":"41017",
    "sg:province":"KY",
    "sg:tags":[
        "house"
    ],
    "wof:name":"Thomas Management Group",
    "wof:placetype":"venue"
},
  "geometry": {"coordinates":[-84.564483,39.051707],"type":"Point"}
}