{
  "type": "Feature",
  "properties": {
    "addr:full":"191 Frankfort St Versailles KY 40383",
    "addr:housenumber":"191",
    "addr:postcode":"40383",
    "addr:street":"Frankfort St",
    "iso:country":"US",
    "sg:address":"191 Frankfort St",
    "sg:city":"Versailles",
    "sg:classifiers":[
        {
            "category":"Autos & Motor Vehicles",
            "subcategory":"Auto Supplies",
            "type":"Retail Goods"
        }
    ],
    "sg:phone":"+1 859 873 9110",
    "sg:postcode":"40383",
    "sg:province":"KY",
    "sg:tags":[
        "tire"
    ],
    "wof:name":"S & S Tire & Auto Svc Ctr",
    "wof:placetype":"venue"
},
  "geometry": {"coordinates":[-84.733616,38.06164],"type":"Point"}
}