{
  "type": "Feature",
  "properties": {
    "iso:country":"US",
    "sg:address":"138 Vanderbilt Dr",
    "sg:city":"Bowling Green",
    "sg:classifiers":[
        {
            "category":"Retail",
            "subcategory":"Repair Shop",
            "type":"Services"
        }
    ],
    "sg:phone":"+1 270 843 6800",
    "sg:postcode":"42103",
    "sg:province":"KY",
    "sg:tags":[
        "instrument",
        "musical"
    ],
    "wof:name":"Opus Horn Repair",
    "wof:placetype":"venue"
},
  "geometry": {"coordinates":[-86.4105,36.926149],"type":"Point"}
}