{
  "type": "Feature",
  "properties": {
    "iso:country":"US",
    "sg:address":"21 Kenton Lands Rd",
    "sg:city":"Erlanger",
    "sg:classifiers":[
        {
            "category":"Professional",
            "subcategory":"Business Services",
            "type":"Services"
        }
    ],
    "sg:phone":"+1 859 341 0710",
    "sg:postcode":"41018",
    "sg:province":"KY",
    "sg:tags":[
        "water",
        "treatment"
    ],
    "sg:website":"www.aquionics.com",
    "wof:name":"Aquionics Inc",
    "wof:placetype":"venue"
},
  "geometry": {"coordinates":[-84.590881,39.023807],"type":"Point"}
}