{
  "type": "Feature",
  "properties": {
    "addr:full":"2034 Woodford Pl Louisville KY 40205",
    "addr:housenumber":"2034",
    "addr:postcode":"40205",
    "addr:street":"Woodford Pl",
    "iso:country":"US",
    "sg:address":"2034 Woodford Pl",
    "sg:city":"Louisville",
    "sg:classifiers":[
        {
            "category":"Real Estate",
            "subcategory":"Real Estate Agent",
            "type":"Services"
        }
    ],
    "sg:phone":"+1 502 459 1658",
    "sg:postcode":"40205",
    "sg:province":"KY",
    "wof:name":"Alan Adelberg & Assoc",
    "wof:placetype":"venue"
},
  "geometry": {"coordinates":[-85.694106,38.226098],"type":"Point"}
}