{
  "type": "Feature",
  "properties": {
    "addr:full":"23 Pelly Rd Independence KY 41051",
    "addr:housenumber":"23",
    "addr:postcode":"41051",
    "addr:street":"Pelly Rd",
    "iso:country":"US",
    "sg:address":"23 Pelly Rd",
    "sg:city":"Independence",
    "sg:classifiers":[
        {
            "category":"Building & Trades",
            "subcategory":"Cleaning & Sanitation",
            "type":"Services"
        }
    ],
    "sg:phone":"+1 859 356 1455",
    "sg:postcode":"41051",
    "sg:province":"KY",
    "sg:tags":[
        "maintenance"
    ],
    "wof:name":"Bortscheller Enterprises Inc",
    "wof:placetype":"venue"
},
  "geometry": {"coordinates":[-84.539177,38.954914],"type":"Point"}
}