{
  "type": "Feature",
  "properties": {
    "iso:country":"US",
    "sg:address":"305 Frederica St",
    "sg:city":"Owensboro",
    "sg:classifiers":[
        {
            "category":"Professional",
            "subcategory":"Business Services",
            "type":"Services"
        }
    ],
    "sg:phone":"+1 270 926 8553",
    "sg:postcode":"42301",
    "sg:province":"KY",
    "sg:tags":[
        "auctioneer"
    ],
    "sg:website":"www.kurtzauction.com",
    "wof:name":"Kurtz Auction & Realty Co",
    "wof:placetype":"venue"
},
  "geometry": {"coordinates":[-87.11327,37.772607],"type":"Point"}
}