{
  "type": "Feature",
  "properties": {
    "iso:country":"US",
    "sg:address":"101 Warren Ln",
    "sg:city":"Gilbertsville",
    "sg:classifiers":[
        {
            "category":"Shopping",
            "subcategory":"Hobbies, Toys, & Games",
            "type":"Retail Goods"
        }
    ],
    "sg:phone":"+1 270 362 9707",
    "sg:postcode":"42044",
    "sg:province":"KY",
    "sg:tags":[
        "equipment",
        "ceramic",
        "supply"
    ],
    "wof:name":"C Smith Ceramic",
    "wof:placetype":"venue"
},
  "geometry": {"coordinates":[-88.312562,36.950063],"type":"Point"}
}