{
  "type": "Feature",
  "properties": {
    "iso:country":"US",
    "sg:address":"121 Clay St",
    "sg:city":"Erlanger",
    "sg:classifiers":[
        {
            "category":"Building & Trades",
            "subcategory":"Construction",
            "type":"Services"
        }
    ],
    "sg:phone":"+1 859 342 8651",
    "sg:postcode":"41018",
    "sg:province":"KY",
    "sg:tags":[
        "house"
    ],
    "wof:name":"Faris Construction",
    "wof:placetype":"venue"
},
  "geometry": {"coordinates":[-84.600865,39.023095],"type":"Point"}
}