{
  "type": "Feature",
  "properties": {
    "iso:country":"US",
    "sg:address":"1925 W Broadway",
    "sg:city":"Louisville",
    "sg:classifiers":[
        {
            "category":"Health Services",
            "subcategory":"Doctor",
            "type":"Services"
        }
    ],
    "sg:phone":"+1 502 772 3625",
    "sg:postcode":"40203",
    "sg:province":"KY",
    "sg:tags":[
        "physician",
        "surgeon"
    ],
    "wof:name":"William A Kean MD",
    "wof:placetype":"venue"
},
  "geometry": {"coordinates":[-85.78405100000001,38.249151],"type":"Point"}
}