{
  "type": "Feature",
  "properties": {
    "addr:full":"6000 Manslick Rd Louisville KY 40214",
    "addr:housenumber":"6000",
    "addr:postcode":"40214",
    "addr:street":"Manslick Rd",
    "iso:country":"US",
    "sg:address":"6000 Manslick Rd",
    "sg:city":"Louisville",
    "sg:classifiers":[
        {
            "category":"Retail",
            "subcategory":"Laundry & Dry Cleaning",
            "type":"Services"
        }
    ],
    "sg:phone":"+1 502 364 9795",
    "sg:postcode":"40214",
    "sg:province":"KY",
    "sg:tags":[
        "laundries-self"
    ],
    "wof:name":"Manslick Marathon",
    "wof:placetype":"venue"
},
  "geometry": {"coordinates":[-85.797211,38.169552],"type":"Point"}
}