{
  "type": "Feature",
  "properties": {
    "addr:full":"110 N Public Sq Greensburg KY 42743",
    "addr:housenumber":"110",
    "addr:postcode":"42743",
    "addr:street":"N Public Sq",
    "iso:country":"US",
    "sg:address":"110 N Public Sq",
    "sg:city":"Greensburg",
    "sg:classifiers":[
        {
            "category":"Shopping",
            "subcategory":"Jewelry",
            "type":"Retail Goods"
        }
    ],
    "sg:phone":"+1 270 932 2038",
    "sg:postcode":"42743",
    "sg:province":"KY",
    "sg:tags":[
        "jeweler"
    ],
    "wof:name":"Peoples Jewelry & Pawn Shop",
    "wof:placetype":"venue"
},
  "geometry": {"coordinates":[-85.50058300000001,37.260661],"type":"Point"}
}