{
  "type": "Feature",
  "properties": {
    "iso:country":"US",
    "sg:address":"8194 Day Pike",
    "sg:city":"Maysville",
    "sg:classifiers":[
        {
            "category":"Organizations",
            "subcategory":"Religious Organization",
            "type":"Services"
        }
    ],
    "sg:phone":"+1 606 564 6832",
    "sg:postcode":"41056",
    "sg:province":"KY",
    "wof:name":"Corporation of President of Th",
    "wof:placetype":"venue"
},
  "geometry": {"coordinates":[-83.676761,38.598847],"type":"Point"}
}