{
  "type": "Feature",
  "properties": {
    "addr:full":"1500 E John Rowan Blvd Bardstown KY 40004",
    "addr:housenumber":"1500",
    "addr:postcode":"40004",
    "addr:street":"E John Rowan Blvd",
    "iso:country":"US",
    "sg:address":"1500 E John Rowan Blvd",
    "sg:city":"Bardstown",
    "sg:classifiers":[
        {
            "category":"Food & Beverages",
            "subcategory":"Groceries & Convenience Stores",
            "type":"Retail Goods"
        }
    ],
    "sg:phone":"+1 502 348 0845",
    "sg:postcode":"40004",
    "sg:province":"KY",
    "sg:tags":[
        "grocer"
    ],
    "wof:name":"Save-A-Lot",
    "wof:placetype":"venue"
},
  "geometry": {"coordinates":[-85.447931,37.822565],"type":"Point"}
}