{
  "type": "Feature",
  "properties": {
    "iso:country":"US",
    "sg:address":"603 Everly Brothers Blvd",
    "sg:city":"Central City",
    "sg:classifiers":[
        {
            "category":"Real Estate",
            "subcategory":"Developer",
            "type":"Services"
        }
    ],
    "sg:phone":"+1 270 754 9186",
    "sg:postcode":"42330",
    "sg:province":"KY",
    "sg:tags":[
        "cemetery"
    ],
    "wof:name":"Rose Hill Cemetery & Vaults",
    "wof:placetype":"venue"
},
  "geometry": {"coordinates":[-87.126471,37.284665],"type":"Point"}
}