{
  "type": "Feature",
  "properties": {
    "iso:country":"US",
    "sg:address":"1169 Eastern Pkwy",
    "sg:city":"Louisville",
    "sg:classifiers":[
        {
            "category":"Organizations",
            "subcategory":"Non-profit Organization",
            "type":"Services"
        }
    ],
    "sg:phone":"+1 502 454 6350",
    "sg:postcode":"40217",
    "sg:province":"KY",
    "sg:tags":[
        "information",
        "alcoholism",
        "treatment"
    ],
    "wof:name":"Better Alternative Counseling",
    "wof:placetype":"venue"
},
  "geometry": {"coordinates":[-85.724738,38.22524],"type":"Point"}
}