{
  "type": "Feature",
  "properties": {
    "addr:full":"781 State Hwy 1601 Evarts KY 40828",
    "addr:housenumber":"781",
    "addr:postcode":"1601;40828",
    "addr:street":"State Hwy",
    "iso:country":"US",
    "sg:address":"781 State Hwy 1601",
    "sg:city":"Evarts",
    "sg:classifiers":[
        {
            "category":"Food & Beverages",
            "subcategory":"Groceries & Convenience Stores",
            "type":"Retail Goods"
        }
    ],
    "sg:phone":"+1 606 837 3683",
    "sg:postcode":"40828",
    "sg:province":"KY",
    "wof:name":"Grills Store",
    "wof:placetype":"venue"
},
  "geometry": {"coordinates":[-83.21371499999999,36.840591],"type":"Point"}
}