{
  "type": "Feature",
  "properties": {
    "iso:country":"US",
    "sg:address":"3707 Bardstown Rd",
    "sg:city":"Louisville",
    "sg:classifiers":[
        {
            "category":"Personal",
            "subcategory":"Massage",
            "type":"Services"
        }
    ],
    "sg:phone":"+1 502 473 1939",
    "sg:postcode":"40218",
    "sg:province":"KY",
    "wof:name":"Julie's Masseusse",
    "wof:placetype":"venue"
},
  "geometry": {"coordinates":[-85.657522,38.197861],"type":"Point"}
}