{
  "type": "Feature",
  "properties": {
    "iso:country":"US",
    "sg:address":"4727 Poplar Level Rd",
    "sg:city":"Louisville",
    "sg:classifiers":[
        {
            "category":"Manufacturing",
            "subcategory":"Building Materials",
            "type":"Manufacturing & Wholesale Goods"
        },
        {
            "category":"Manufacturing",
            "subcategory":"Glass & Minerals",
            "type":"Manufacturing & Wholesale Goods"
        },
        {
            "category":"Retail",
            "subcategory":"Auto Repair",
            "type":"Services"
        }
    ],
    "sg:phone":"+1 502 969 0125",
    "sg:postcode":"40213",
    "sg:province":"KY",
    "sg:tags":[
        "plate",
        "manufacturer",
        "glazier",
        "shape",
        "glass-wholesale",
        "glass-auto",
        "window",
        "circle",
        "windshield",
        "special",
        "replacement"
    ],
    "sg:website":"http://www.glassdoctor.com",
    "wof:name":"Glass Doctor",
    "wof:placetype":"venue"
},
  "geometry": {"coordinates":[-85.688202,38.175991],"type":"Point"}
}