{
  "type": "Feature",
  "properties": {
    "addr:full":"5040 Frederica St Owensboro KY 42301",
    "addr:housenumber":"5040",
    "addr:postcode":"42301",
    "addr:street":"Frederica St",
    "iso:country":"US",
    "sg:address":"5040 Frederica St",
    "sg:city":"Owensboro",
    "sg:classifiers":[
        {
            "category":"Shopping",
            "subcategory":"Shoes",
            "type":"Retail Goods"
        }
    ],
    "sg:phone":"+1 270 926 8956",
    "sg:postcode":"42301",
    "sg:province":"KY",
    "wof:name":"Fleet Feet Sports",
    "wof:placetype":"venue"
},
  "geometry": {"coordinates":[-87.12549799999999,37.717349],"type":"Point"}
}