{
  "type": "Feature",
  "properties": {
    "iso:country":"US",
    "sg:address":"318 Greenup St",
    "sg:city":"Covington",
    "sg:phone":"+1 859 643 1234",
    "sg:postcode":"41011",
    "sg:province":"KY",
    "sg:website":"http://www.chalkfoodwine.com",
    "wof:name":"Chalk Food + Wine",
    "wof:placetype":"venue"
},
  "geometry": {"coordinates":[-84.507972,39.08821],"type":"Point"}
}