{
  "type": "Feature",
  "properties": {
    "iso:country":"US",
    "sg:address":"8216 State Hwy 268",
    "sg:city":"Corydon",
    "sg:phone":"+1 270 826 0008",
    "sg:postcode":"42406",
    "sg:province":"KY",
    "sg:tags":[
        "farm",
        "corn",
        "soybean"
    ],
    "wof:name":"Barry Green Farms",
    "wof:placetype":"venue"
},
  "geometry": {"coordinates":[-87.711612,37.831505],"type":"Point"}
}