{
  "type": "Feature",
  "properties": {
    "addr:full":"10055 US Hwy 27 Waynesburg KY 40489",
    "addr:housenumber":"10055",
    "addr:postcode":"40489",
    "addr:street":"Us Hwy 27",
    "iso:country":"US",
    "sg:address":"10055 US Hwy 27",
    "sg:city":"Waynesburg",
    "sg:classifiers":[
        {
            "category":"Personal",
            "subcategory":"Beauty Salon",
            "type":"Services"
        }
    ],
    "sg:phone":"+1 606 365 9431",
    "sg:postcode":"40489",
    "sg:province":"KY",
    "sg:tags":[
        "shop"
    ],
    "wof:name":"Cindy Bastin Hairstyling",
    "wof:placetype":"venue"
},
  "geometry": {"coordinates":[-84.653108,37.390935],"type":"Point"}
}