{
  "type": "Feature",
  "properties": {
    "iso:country":"US",
    "sg:address":"1700 Dawson Springs Rd",
    "sg:city":"Hopkinsville",
    "sg:classifiers":[
        {
            "category":"Restaurant",
            "type":"Food & Drink"
        }
    ],
    "sg:phone":"+1 270 887 9989",
    "sg:postcode":"42240",
    "sg:province":"KY",
    "sg:tags":[
        "eating"
    ],
    "wof:name":"Way Cup Station",
    "wof:placetype":"venue"
},
  "geometry": {"coordinates":[-87.50863099999999,36.879868],"type":"Point"}
}