{
  "type": "Feature",
  "properties": {
    "iso:country":"US",
    "sg:address":"2650 Stamper Branch Rd",
    "sg:city":"Hazel Green",
    "sg:phone":"+1 606 662 9241",
    "sg:postcode":"41332",
    "sg:province":"KY",
    "sg:tags":[
        "farm",
        "tobacco"
    ],
    "wof:name":"Oliver Reece",
    "wof:placetype":"venue"
},
  "geometry": {"coordinates":[-83.456884,37.808793],"type":"Point"}
}