{
  "type": "Feature",
  "properties": {
    "addr:full":"1609 Corinthian Dr Florence KY 41042",
    "addr:housenumber":"1609",
    "addr:postcode":"41042",
    "addr:street":"Corinthian Dr",
    "iso:country":"US",
    "sg:address":"1609 Corinthian Dr",
    "sg:city":"Florence",
    "sg:classifiers":[
        {
            "category":"Building & Trades",
            "subcategory":"Landscaping Services",
            "type":"Services"
        }
    ],
    "sg:phone":"+1 859 356 7883",
    "sg:postcode":"41042",
    "sg:province":"KY",
    "wof:name":"Adkins Total Lawn Care LLC",
    "wof:placetype":"venue"
},
  "geometry": {"coordinates":[-84.66663200000001,38.959346],"type":"Point"}
}