{
  "type": "Feature",
  "properties": {
    "addr:full":"815 S Main St Franklin KY 42134",
    "addr:housenumber":"815",
    "addr:postcode":"42134",
    "addr:street":"S Main St",
    "iso:country":"US",
    "sg:address":"815 S Main St",
    "sg:city":"Franklin",
    "sg:classifiers":[
        {
            "category":"Autos & Motor Vehicles",
            "subcategory":"Auto Supplies",
            "type":"Retail Goods"
        }
    ],
    "sg:phone":"+1 270 586 7922",
    "sg:postcode":"42134",
    "sg:province":"KY",
    "sg:tags":[
        "automobile",
        "parts"
    ],
    "wof:name":"Autozone",
    "wof:placetype":"venue"
},
  "geometry": {"coordinates":[-86.576173,36.709037],"type":"Point"}
}