{
  "type": "Feature",
  "properties": {
    "iso:country":"US",
    "sg:address":"2119 Crums Ln",
    "sg:city":"Louisville",
    "sg:classifiers":[
        {
            "category":"Restaurant",
            "type":"Food & Drink"
        }
    ],
    "sg:phone":"+1 502 447 9690",
    "sg:postcode":"40216",
    "sg:province":"KY",
    "wof:name":"Pizza Magia",
    "wof:placetype":"venue"
},
  "geometry": {"coordinates":[-85.811729,38.194458],"type":"Point"}
}