{
  "type": "Feature",
  "properties": {
    "addr:full":"1617 May St Covington KY 41014",
    "addr:housenumber":"1617",
    "addr:postcode":"41014",
    "addr:street":"May St",
    "iso:country":"US",
    "sg:address":"1617 May St",
    "sg:city":"Covington",
    "sg:classifiers":[
        {
            "category":"Wholesale",
            "subcategory":"Construction Materials",
            "type":"Manufacturing & Wholesale Goods"
        }
    ],
    "sg:phone":"+1 859 291 1010",
    "sg:postcode":"41014",
    "sg:province":"KY",
    "sg:tags":[
        "fence"
    ],
    "wof:name":"Lemarbebrothers Fence Co",
    "wof:placetype":"venue"
},
  "geometry": {"coordinates":[-84.51444100000001,39.070231],"type":"Point"}
}