{
  "type": "Feature",
  "properties": {
    "addr:full":"8811 3rd Street Rd Valley Station KY 40272",
    "addr:housenumber":"8811",
    "addr:postcode":"40272",
    "addr:street":"3Rd Street Rd Valley",
    "iso:country":"US",
    "sg:address":"8811 3rd Street Rd",
    "sg:city":"Valley Station",
    "sg:classifiers":[
        {
            "category":"Insurance",
            "subcategory":"Insurance Agent",
            "type":"Services"
        }
    ],
    "sg:phone":"+1 502 937 8833",
    "sg:postcode":"40272",
    "sg:province":"KY",
    "wof:name":"State Farm Insurance",
    "wof:placetype":"venue"
},
  "geometry": {"coordinates":[-85.812884,38.116305],"type":"Point"}
}