{
  "type": "Feature",
  "properties": {
    "iso:country":"US",
    "sg:address":"170 Robert Ln",
    "sg:city":"Madisonville",
    "sg:classifiers":[
        {
            "category":"Personal",
            "subcategory":"Beauty Salon",
            "type":"Services"
        }
    ],
    "sg:phone":"+1 270 824 0154",
    "sg:postcode":"42431",
    "sg:province":"KY",
    "sg:tags":[
        "shop"
    ],
    "wof:name":"Corner Hairplace",
    "wof:placetype":"venue"
},
  "geometry": {"coordinates":[-87.501865,37.383543],"type":"Point"}
}