{
  "type": "Feature",
  "properties": {
    "iso:country":"US",
    "sg:address":"770 Bluff Rd",
    "sg:city":"Hampton",
    "sg:classifiers":[
        {
            "category":"Farming",
            "subcategory":"Farm",
            "type":"Manufacturing & Wholesale Goods"
        }
    ],
    "sg:phone":"+1 270 988 3726",
    "sg:postcode":"42047",
    "sg:province":"KY",
    "sg:tags":[
        "crop",
        "general"
    ],
    "wof:name":"Billy Knoth",
    "wof:placetype":"venue"
},
  "geometry": {"coordinates":[-88.408034,37.265796],"type":"Point"}
}