{
  "type": "Feature",
  "properties": {
    "iso:country":"US",
    "sg:address":"10310 Dixie Hwy",
    "sg:city":"Louisville",
    "sg:classifiers":[
        {
            "category":"Restaurant",
            "type":"Food & Drink"
        }
    ],
    "sg:menulink":"http://www.allmenus.com/ky/jefferson-southwest/163002-rallys/menu/",
    "sg:phone":"+1 502 933 0431",
    "sg:postcode":"40272",
    "sg:province":"KY",
    "sg:tags":[
        "sandwich",
        "dog",
        "burger",
        "hot",
        "wrap",
        "american"
    ],
    "wof:name":"Rally's",
    "wof:placetype":"venue"
},
  "geometry": {"coordinates":[-85.868032,38.105497],"type":"Point"}
}