{
  "type": "Feature",
  "properties": {
    "iso:country":"US",
    "sg:address":"2272 Allensville Rd",
    "sg:city":"Elkton",
    "sg:phone":"+1 270 265 5221",
    "sg:postcode":"42220",
    "sg:province":"KY",
    "sg:tags":[
        "farm",
        "tobacco"
    ],
    "wof:name":"Paul Kirkman",
    "wof:placetype":"venue"
},
  "geometry": {"coordinates":[-87.119832,36.777947],"type":"Point"}
}