{
  "type": "Feature",
  "properties": {
    "addr:full":"208 Twin Shores Ct Lexington KY 40515",
    "addr:housenumber":"208",
    "addr:postcode":"40515",
    "addr:street":"Twin Shores Ct",
    "iso:country":"US",
    "sg:address":"208 Twin Shores Ct",
    "sg:city":"Lexington",
    "sg:classifiers":[
        {
            "category":"Professional",
            "subcategory":"Management & Consulting",
            "type":"Services"
        }
    ],
    "sg:phone":"+1 859 264 1085",
    "sg:postcode":"40515",
    "sg:province":"KY",
    "wof:name":"Sunshine Services LLC",
    "wof:placetype":"venue"
},
  "geometry": {"coordinates":[-84.440455,37.990609],"type":"Point"}
}