{
  "type": "Feature",
  "properties": {
    "iso:country":"US",
    "sg:address":"1304 E Breckinridge St",
    "sg:city":"Louisville",
    "sg:classifiers":[
        {
            "category":"Shopping",
            "subcategory":"Used Merchandise",
            "type":"Retail Goods"
        }
    ],
    "sg:phone":"+1 502 589 0336",
    "sg:postcode":"40204",
    "sg:province":"KY",
    "sg:tags":[
        "clothing"
    ],
    "wof:name":"Queen Of Rags",
    "wof:placetype":"venue"
},
  "geometry": {"coordinates":[-85.729584,38.241025],"type":"Point"}
}