{
  "type": "Feature",
  "properties": {
    "addr:full":"107 W Halstead Ave Bardstown KY 40004",
    "addr:housenumber":"107",
    "addr:postcode":"40004",
    "addr:street":"W Halstead Ave",
    "iso:country":"US",
    "sg:address":"107 W Halstead Ave",
    "sg:city":"Bardstown",
    "sg:classifiers":[
        {
            "category":"Shopping",
            "subcategory":"Used Merchandise",
            "type":"Retail Goods"
        }
    ],
    "sg:phone":"+1 502 348 6106",
    "sg:postcode":"40004",
    "sg:province":"KY",
    "sg:tags":[
        "shop",
        "consignment"
    ],
    "wof:name":"Clothes Corner",
    "wof:placetype":"venue"
},
  "geometry": {"coordinates":[-85.46495,37.821715],"type":"Point"}
}