{
  "type": "Feature",
  "properties": {
    "addr:full":"847 N H C Mathis Dr Paducah KY 42001",
    "addr:housenumber":"847",
    "addr:postcode":"42001",
    "addr:street":"N H C Mathis Dr",
    "iso:country":"US",
    "sg:address":"847 N H C Mathis Dr",
    "sg:city":"Paducah",
    "sg:classifiers":[
        {
            "category":"Wholesale",
            "subcategory":"Hardware",
            "type":"Manufacturing & Wholesale Goods"
        }
    ],
    "sg:phone":"+1 270 441 7230",
    "sg:postcode":"42001",
    "sg:province":"KY",
    "sg:tags":[
        "tool"
    ],
    "sg:website":"www.fastenal.com",
    "wof:name":"Fast Tool",
    "wof:placetype":"venue"
},
  "geometry": {"coordinates":[-88.63083,37.097068],"type":"Point"}
}