{
  "type": "Feature",
  "properties": {
    "iso:country":"US",
    "sg:address":"1035 Washington St",
    "sg:city":"Shelbyville",
    "sg:classifiers":[
        {
            "category":"Restaurant",
            "type":"Food & Drink"
        }
    ],
    "sg:phone":"+1 502 633 7738",
    "sg:postcode":"40065",
    "sg:province":"KY",
    "wof:name":"Bo Bo China Restaurant",
    "wof:placetype":"venue"
},
  "geometry": {"coordinates":[-85.224745,38.212391],"type":"Point"}
}