{
  "type": "Feature",
  "properties": {
    "addr:full":"903 Fairdale Rd Fairdale KY 40118",
    "addr:housenumber":"903",
    "addr:postcode":"40118",
    "addr:street":"Fairdale Rd",
    "iso:country":"US",
    "sg:address":"903 Fairdale Rd",
    "sg:city":"Fairdale",
    "sg:classifiers":[
        {
            "category":"Place Of Worship",
            "subcategory":"Church",
            "type":"Public Place"
        }
    ],
    "sg:phone":"+1 502 363 9929",
    "sg:postcode":"40118",
    "sg:province":"KY",
    "sg:tags":[
        "churches-catholic"
    ],
    "wof:name":"Blessed Teresa Of Calcutta Parish",
    "wof:placetype":"venue"
},
  "geometry": {"coordinates":[-85.750731,38.110666],"type":"Point"}
}