{
  "type": "Feature",
  "properties": {
    "addr:full":"1901 Eastpoint Pkwy Louisville KY 40223",
    "addr:housenumber":"1901",
    "addr:postcode":"40223",
    "addr:street":"Eastpoint Pkwy",
    "iso:country":"US",
    "sg:address":"1901 Eastpoint Pkwy",
    "sg:city":"Louisville",
    "sg:classifiers":[
        {
            "category":"Utilities",
            "subcategory":"Telephone",
            "type":"Services"
        }
    ],
    "sg:phone":"+1 502 244 6666",
    "sg:postcode":"40223",
    "sg:province":"KY",
    "sg:tags":[
        "telecommunication"
    ],
    "wof:name":"Lightyear Network Solutions",
    "wof:placetype":"venue"
},
  "geometry": {"coordinates":[-85.50324500000001,38.279367],"type":"Point"}
}