{
  "type": "Feature",
  "properties": {
    "addr:full":"10314 Watterson Trl Louisville KY 40299",
    "addr:housenumber":"10314",
    "addr:postcode":"40299",
    "addr:street":"Watterson Trl",
    "iso:country":"US",
    "sg:address":"10314 Watterson Trl",
    "sg:city":"Louisville",
    "sg:classifiers":[
        {
            "category":"Restaurant",
            "type":"Food & Drink"
        }
    ],
    "sg:menulink":"http://www.allmenus.com/ky/jefferson-southeast/66157-dominos-pizza/menu/",
    "sg:phone":"+1 502 267 3030",
    "sg:postcode":"40299",
    "sg:province":"KY",
    "sg:tags":[
        "american",
        "wing",
        "pizza"
    ],
    "wof:name":"Domino's Pizza",
    "wof:placetype":"venue"
},
  "geometry": {"coordinates":[-85.56847999999999,38.192292],"type":"Point"}
}