{
  "type": "Feature",
  "properties": {
    "addr:full":"5312 S 3rd St Louisville KY 40214",
    "addr:housenumber":"5312",
    "addr:postcode":"40214",
    "addr:street":"S 3Rd St",
    "iso:country":"US",
    "sg:address":"5312 S 3rd St",
    "sg:city":"Louisville",
    "sg:classifiers":[
        {
            "category":"Restaurant",
            "type":"Food & Drink"
        }
    ],
    "sg:phone":"+1 502 368 5199",
    "sg:postcode":"40214",
    "sg:province":"KY",
    "wof:name":"Djuli",
    "wof:placetype":"venue"
},
  "geometry": {"coordinates":[-85.768199,38.1708],"type":"Point"}
}