{
  "type": "Feature",
  "properties": {
    "addr:full":"1776 Cincinnati Rd Georgetown KY 40324",
    "addr:housenumber":"1776",
    "addr:postcode":"40324",
    "addr:street":"Cincinnati Rd",
    "iso:country":"US",
    "sg:address":"1776 Cincinnati Rd",
    "sg:city":"Georgetown",
    "sg:classifiers":[
        {
            "category":"Organizations",
            "subcategory":"Religious Organization",
            "type":"Services"
        }
    ],
    "sg:phone":"+1 502 863 3008",
    "sg:postcode":"40324",
    "sg:province":"KY",
    "sg:tags":[
        "church"
    ],
    "wof:name":"Scott County Church Of Christ",
    "wof:placetype":"venue"
},
  "geometry": {"coordinates":[-84.565906,38.261007],"type":"Point"}
}