{
  "type": "Feature",
  "properties": {
    "iso:country":"US",
    "sg:address":"4029 S Brook St",
    "sg:city":"Louisville",
    "sg:classifiers":[
        {
            "category":"Building & Trades",
            "subcategory":"Plumbing",
            "type":"Services"
        }
    ],
    "sg:phone":"+1 502 368 3073",
    "sg:postcode":"40214",
    "sg:province":"KY",
    "sg:tags":[
        "metal",
        "work",
        "sheet",
        "contractor"
    ],
    "wof:name":"Buehner Sheet Metal Inc",
    "wof:placetype":"venue"
},
  "geometry": {"coordinates":[-85.760001,38.197831],"type":"Point"}
}