{
  "type": "Feature",
  "properties": {
    "iso:country":"US",
    "sg:address":"1945 Maplewood Pl",
    "sg:city":"Louisville",
    "sg:classifiers":[
        {
            "category":"Arts & Performance",
            "subcategory":"Theater",
            "type":"Entertainment"
        }
    ],
    "sg:phone":"+1 502 452 6767",
    "sg:postcode":"40205",
    "sg:province":"KY",
    "sg:tags":[
        "bureau"
    ],
    "wof:name":"Southern Studs",
    "wof:placetype":"venue"
},
  "geometry": {"coordinates":[-85.706501,38.230502],"type":"Point"}
}