{
  "type": "Feature",
  "properties": {
    "iso:country":"US",
    "sg:address":"128 Production Ct",
    "sg:city":"Louisville",
    "sg:classifiers":[
        {
            "category":"Wholesale",
            "subcategory":"Machinery & Supplies",
            "type":"Manufacturing & Wholesale Goods"
        }
    ],
    "sg:phone":"+1 502 499 0024",
    "sg:postcode":"40299",
    "sg:province":"KY",
    "sg:tags":[
        "equipment",
        "industrial"
    ],
    "wof:name":"Bartholome Associates",
    "wof:placetype":"venue"
},
  "geometry": {"coordinates":[-85.56539600000001,38.221849],"type":"Point"}
}