{
  "type": "Feature",
  "properties": {
    "addr:full":"10055 US Hwy 27 Waynesburg KY 40489",
    "addr:housenumber":"10055",
    "addr:postcode":"40489",
    "addr:street":"Us Hwy 27",
    "iso:country":"US",
    "sg:address":"10055 US Hwy 27",
    "sg:city":"Waynesburg",
    "sg:classifiers":[
        {
            "category":"Autos & Motor Vehicles",
            "subcategory":"Fuel & Gas Station",
            "type":"Retail Goods"
        }
    ],
    "sg:phone":"+1 606 365 3958",
    "sg:postcode":"40489",
    "sg:province":"KY",
    "sg:tags":[
        "oil"
    ],
    "wof:name":"Leaches Shell Mart",
    "wof:placetype":"venue"
},
  "geometry": {"coordinates":[-84.653108,37.390935],"type":"Point"}
}