{
  "type": "Feature",
  "properties": {
    "iso:country":"US",
    "sg:address":"46 Broadway St",
    "sg:city":"Mt Sterling",
    "sg:classifiers":[
        {
            "category":"Insurance",
            "subcategory":"Insurance Agent",
            "type":"Services"
        }
    ],
    "sg:phone":"+1 859 498 3410",
    "sg:postcode":"40353",
    "sg:province":"KY",
    "sg:website":"www.hig-insurance.com",
    "wof:name":"Hoffman Ison & Greene",
    "wof:placetype":"venue"
},
  "geometry": {"coordinates":[-83.94300800000001,38.056831],"type":"Point"}
}