{
  "type": "Feature",
  "properties": {
    "iso:country":"US",
    "sg:address":"4905 Spa Rd",
    "sg:city":"Lewisburg",
    "sg:classifiers":[
        {
            "category":"Autos & Motor Vehicles",
            "subcategory":"Motorcycle Sales",
            "type":"Retail Goods"
        }
    ],
    "sg:phone":"+1 270 755 2170",
    "sg:postcode":"42256",
    "sg:province":"KY",
    "sg:tags":[
        "all",
        "terrain"
    ],
    "wof:name":"Lewisburg Atv Center",
    "wof:placetype":"venue"
},
  "geometry": {"coordinates":[-87.024799,36.953618],"type":"Point"}
}