{
  "type": "Feature",
  "properties": {
    "iso:country":"US",
    "sg:address":"229 Hillview Dr",
    "sg:city":"Shelbyville",
    "sg:classifiers":[
        {
            "category":"Organizations",
            "subcategory":"Professional Association",
            "type":"Services"
        }
    ],
    "sg:phone":"+1 502 633 3239",
    "sg:postcode":"40065",
    "sg:province":"KY",
    "sg:tags":[
        "a",
        "as",
        "nonprofit",
        "operates"
    ],
    "wof:name":"South E Untd Dar Indust Assn",
    "wof:placetype":"venue"
},
  "geometry": {"coordinates":[-85.239795,38.228503],"type":"Point"}
}