{
  "type": "Feature",
  "properties": {
    "iso:country":"US",
    "sg:address":"550 Main St",
    "sg:city":"West Liberty",
    "sg:classifiers":[
        {
            "category":"Real Estate",
            "subcategory":"Real Estate Agent",
            "type":"Services"
        }
    ],
    "sg:phone":"+1 606 743 4009",
    "sg:postcode":"41472",
    "sg:province":"KY",
    "wof:name":"Kee-Hol Realty",
    "wof:placetype":"venue"
},
  "geometry": {"coordinates":[-83.2599,37.921802],"type":"Point"}
}