{
  "type": "Feature",
  "properties": {
    "addr:full":"5007 Fury Way Louisville KY 40258",
    "addr:housenumber":"5007",
    "addr:postcode":"40258",
    "addr:street":"Fury Way",
    "iso:country":"US",
    "sg:address":"5007 Fury Way",
    "sg:city":"Louisville",
    "sg:classifiers":[
        {
            "category":"Building & Trades",
            "subcategory":"Equipment Rental",
            "type":"Services"
        },
        {
            "category":"Shopping",
            "subcategory":"Computers & Home Electronics",
            "type":"Retail Goods"
        }
    ],
    "sg:phone":"+1 502 937 5047",
    "sg:postcode":"40258",
    "sg:province":"KY",
    "sg:tags":[
        "stereo",
        "leasing",
        "video",
        "audio",
        "equipment-renting",
        "audio-visual"
    ],
    "wof:name":"A V Service Co",
    "wof:placetype":"venue"
},
  "geometry": {"coordinates":[-85.847172,38.140993],"type":"Point"}
}