{
  "type": "Feature",
  "properties": {
    "iso:country":"US",
    "sg:address":"11010 Buckeye Trce",
    "sg:city":"Goshen",
    "sg:classifiers":[
        {
            "category":"Professional",
            "subcategory":"Engineering",
            "type":"Services"
        }
    ],
    "sg:phone":"+1 502 228 0715",
    "sg:postcode":"40026",
    "sg:province":"KY",
    "wof:name":"Garcia Engineering",
    "wof:placetype":"venue"
},
  "geometry": {"coordinates":[-85.54853799999999,38.398703],"type":"Point"}
}