{
  "type": "Feature",
  "properties": {
    "iso:country":"US",
    "sg:address":"1386 Bardstown Rd",
    "sg:city":"Louisville",
    "sg:classifiers":[
        {
            "category":"Personal",
            "subcategory":"Beauty Salon",
            "type":"Services"
        }
    ],
    "sg:phone":"+1 502 456 0077",
    "sg:postcode":"40204",
    "sg:province":"KY",
    "sg:tags":[
        "hair",
        "shop",
        "stylist"
    ],
    "sg:website":"http://www.irenessalon.com",
    "wof:name":"Irene's Salon",
    "wof:placetype":"venue"
},
  "geometry": {"coordinates":[-85.712085,38.233519],"type":"Point"}
}