{
  "type": "Feature",
  "properties": {
    "addr:full":"2121 29th St Ashland KY 41101",
    "addr:housenumber":"2121",
    "addr:postcode":"41101",
    "addr:street":"29Th St",
    "iso:country":"US",
    "sg:address":"2121 29th St",
    "sg:city":"Ashland",
    "sg:classifiers":[
        {
            "category":"Organizations",
            "subcategory":"Religious Organization",
            "type":"Services"
        }
    ],
    "sg:phone":"+1 606 324 5447",
    "sg:postcode":"41101",
    "sg:province":"KY",
    "sg:tags":[
        "church"
    ],
    "wof:name":"Second Freewill Baptist Church",
    "wof:placetype":"venue"
},
  "geometry": {"coordinates":[-82.642646,38.459953],"type":"Point"}
}