{
  "type": "Feature",
  "properties": {
    "addr:full":"35 Cedarwood Rd Bedford KY 40006",
    "addr:housenumber":"35",
    "addr:postcode":"40006",
    "addr:street":"Cedarwood Rd",
    "iso:country":"US",
    "sg:address":"35 Cedarwood Rd",
    "sg:city":"Bedford",
    "sg:classifiers":[
        {
            "category":"Manufacturing",
            "subcategory":"Printing",
            "type":"Manufacturing & Wholesale Goods"
        }
    ],
    "sg:phone":"+1 502 255 7560",
    "sg:postcode":"40006",
    "sg:province":"KY",
    "sg:tags":[
        "publishing"
    ],
    "wof:name":"Welsh Enterprises",
    "wof:placetype":"venue"
},
  "geometry": {"coordinates":[-85.319084,38.669173],"type":"Point"}
}