{
  "type": "Feature",
  "properties": {
    "iso:country":"US",
    "sg:address":"1023 US Hwy 60",
    "sg:city":"Morganfield",
    "sg:classifiers":[
        {
            "category":"Personal",
            "subcategory":"Beauty Salon",
            "type":"Services"
        }
    ],
    "sg:phone":"+1 270 389 1118",
    "sg:postcode":"42437",
    "sg:province":"KY",
    "sg:tags":[
        "manicuring"
    ],
    "wof:name":"LA Nails",
    "wof:placetype":"venue"
},
  "geometry": {"coordinates":[-87.896642,37.690669],"type":"Point"}
}