{
  "type": "Feature",
  "properties": {
    "addr:full":"5251 Hodgenville Rd Greensburg KY 42743",
    "addr:housenumber":"5251",
    "addr:postcode":"42743",
    "addr:street":"Hodgenville Rd",
    "iso:country":"US",
    "sg:address":"5251 Hodgenville Rd",
    "sg:city":"Greensburg",
    "sg:classifiers":[
        {
            "category":"Manufacturing",
            "subcategory":"Pet Food",
            "type":"Manufacturing & Wholesale Goods"
        }
    ],
    "sg:phone":"+1 270 932 4347",
    "sg:postcode":"42743",
    "sg:province":"KY",
    "sg:tags":[
        "feed"
    ],
    "wof:name":"Summersville Feed Mill",
    "wof:placetype":"venue"
},
  "geometry": {"coordinates":[-85.62794,37.421189],"type":"Point"}
}