{
  "type": "Feature",
  "properties": {
    "addr:full":"308 Main St Livermore KY 42352",
    "addr:housenumber":"308",
    "addr:postcode":"42352",
    "addr:street":"Main St",
    "iso:country":"US",
    "sg:address":"308 Main St",
    "sg:city":"Livermore",
    "sg:classifiers":[
        {
            "category":"Organizations",
            "subcategory":"Religious Organization",
            "type":"Services"
        }
    ],
    "sg:phone":"+1 270 278 2227",
    "sg:postcode":"42352",
    "sg:province":"KY",
    "sg:tags":[
        "church"
    ],
    "wof:name":"Livermore United Methodist Chr",
    "wof:placetype":"venue"
},
  "geometry": {"coordinates":[-87.13602899999999,37.489145],"type":"Point"}
}