{
  "type": "Feature",
  "properties": {
    "addr:full":"1099 S Broadway Rd Lexington KY 40504",
    "addr:housenumber":"1099",
    "addr:postcode":"40504",
    "addr:street":"S Broadway Rd",
    "iso:country":"US",
    "sg:address":"1099 S Broadway Rd",
    "sg:city":"Lexington",
    "sg:classifiers":[
        {
            "category":"Insurance",
            "subcategory":"Insurance Agent",
            "type":"Services"
        }
    ],
    "sg:phone":"+1 859 231 1099",
    "sg:postcode":"40504",
    "sg:province":"KY",
    "wof:name":"Nationwide Insurance",
    "wof:placetype":"venue"
},
  "geometry": {"coordinates":[-84.51826199999999,38.036912],"type":"Point"}
}