{
  "type": "Feature",
  "properties": {
    "addr:full":"2102 Osage Ave Louisville KY 40210",
    "addr:housenumber":"2102",
    "addr:postcode":"40210",
    "addr:street":"Osage Ave",
    "iso:country":"US",
    "sg:address":"2102 Osage Ave",
    "sg:city":"Louisville",
    "sg:classifiers":[
        {
            "category":"Professional",
            "type":"Services"
        }
    ],
    "sg:phone":"+1 502 939 0455",
    "sg:postcode":"40210",
    "sg:province":"KY",
    "wof:name":"Shenita Diane Gazaway",
    "wof:placetype":"venue"
},
  "geometry": {"coordinates":[-85.789919,38.239248],"type":"Point"}
}