{
  "type": "Feature",
  "properties": {
    "iso:country":"US",
    "sg:address":"428 Valley Rd",
    "sg:city":"Somerset",
    "sg:classifiers":[
        {
            "category":"Building & Trades",
            "subcategory":"Construction",
            "type":"Services"
        }
    ],
    "sg:phone":"+1 606 423 9868",
    "sg:postcode":"42503",
    "sg:province":"KY",
    "sg:tags":[
        "house"
    ],
    "wof:name":"Cumberland Home Improvement",
    "wof:placetype":"venue"
},
  "geometry": {"coordinates":[-84.668126,37.141164],"type":"Point"}
}