{
  "type": "Feature",
  "properties": {
    "iso:country":"US",
    "sg:address":"4911 Depriest Ct",
    "sg:city":"Louisville",
    "sg:classifiers":[
        {
            "category":"Building & Trades",
            "subcategory":"Construction",
            "type":"Services"
        }
    ],
    "sg:phone":"+1 502 459 8690",
    "sg:postcode":"40218",
    "sg:province":"KY",
    "sg:tags":[
        "residential"
    ],
    "wof:name":"A Assurance Builders & Cnstr",
    "wof:placetype":"venue"
},
  "geometry": {"coordinates":[-85.66964,38.177187],"type":"Point"}
}