{
  "type": "Feature",
  "properties": {
    "iso:country":"US",
    "sg:address":"490 Hill-N-Dale Dr",
    "sg:city":"Shelbyville",
    "sg:classifiers":[
        {
            "category":"Retail",
            "subcategory":"Auto Repair",
            "type":"Services"
        }
    ],
    "sg:phone":"+1 502 633 0186",
    "sg:postcode":"40065",
    "sg:province":"KY",
    "sg:tags":[
        "repairing",
        "automobile"
    ],
    "wof:name":"Bailey's Service Ctr",
    "wof:placetype":"venue"
},
  "geometry": {"coordinates":[-85.26210500000001,38.211777],"type":"Point"}
}