{
  "type": "Feature",
  "properties": {
    "iso:country":"US",
    "sg:address":"9822 3rd Street Rd",
    "sg:city":"Louisville",
    "sg:classifiers":[
        {
            "category":"Health Services",
            "subcategory":"Doctor",
            "type":"Services"
        }
    ],
    "sg:phone":"+1 502 935 0670",
    "sg:postcode":"40272",
    "sg:province":"KY",
    "sg:tags":[
        "physician",
        "surgeon"
    ],
    "wof:name":"Louisville Surgical Assoc",
    "wof:placetype":"venue"
},
  "geometry": {"coordinates":[-85.83768499999999,38.112174],"type":"Point"}
}