{
  "type": "Feature",
  "properties": {
    "addr:full":"2215 Blvd Napoleon Louisville KY 40205",
    "addr:housenumber":"2215",
    "addr:postcode":"40205",
    "addr:street":"Blvd Napoleon",
    "iso:country":"US",
    "sg:address":"2215 Blvd Napoleon",
    "sg:city":"Louisville",
    "sg:classifiers":[
        {
            "category":"Professional",
            "subcategory":"Business Services",
            "type":"Services"
        }
    ],
    "sg:phone":"+1 502 456 5330",
    "sg:postcode":"40205",
    "sg:province":"KY",
    "wof:name":"Rogers Technology Services LLC",
    "wof:placetype":"venue"
},
  "geometry": {"coordinates":[-85.695621,38.223119],"type":"Point"}
}