{
  "type": "Feature",
  "properties": {
    "iso:country":"US",
    "sg:address":"376 Cammi Dr",
    "sg:city":"Shepherdsville",
    "sg:classifiers":[
        {
            "category":"Building & Trades",
            "subcategory":"Construction",
            "type":"Services"
        }
    ],
    "sg:phone":"+1 502 543 8285",
    "sg:postcode":"40165",
    "sg:province":"KY",
    "sg:tags":[
        "contractor"
    ],
    "wof:name":"T & C Contracting",
    "wof:placetype":"venue"
},
  "geometry": {"coordinates":[-85.624217,38.02828],"type":"Point"}
}