{
  "type": "Feature",
  "properties": {
    "iso:country":"US",
    "sg:address":"1150 State St",
    "sg:city":"Bowling Green",
    "sg:classifiers":[
        {
            "category":"Manufacturing",
            "subcategory":"Tools & Machinery",
            "type":"Manufacturing & Wholesale Goods"
        }
    ],
    "sg:phone":"+1 270 487 5891",
    "sg:postcode":"42101",
    "sg:province":"KY",
    "sg:tags":[
        "machine",
        "shop"
    ],
    "wof:name":"Froedge Machine & Supl",
    "wof:placetype":"venue"
},
  "geometry": {"coordinates":[-86.443887,36.990427],"type":"Point"}
}