{
  "type": "Feature",
  "properties": {
    "iso:country":"US",
    "sg:address":"115 Cherry St",
    "sg:city":"Marion",
    "sg:classifiers":[
        {
            "category":"Professional",
            "subcategory":"Business Services",
            "type":"Services"
        }
    ],
    "sg:phone":"+1 270 965 9876",
    "sg:postcode":"42064",
    "sg:province":"KY",
    "sg:tags":[
        "auctioneer"
    ],
    "wof:name":"Perryman's Auction Co",
    "wof:placetype":"venue"
},
  "geometry": {"coordinates":[-88.07576299999999,37.333693],"type":"Point"}
}