{
  "type": "Feature",
  "properties": {
    "iso:country":"US",
    "sg:address":"140 Simmons St",
    "sg:city":"Versailles",
    "sg:classifiers":[
        {
            "category":"Retail",
            "subcategory":"Funeral Services",
            "type":"Services"
        }
    ],
    "sg:phone":"+1 859 873 3741",
    "sg:postcode":"40383",
    "sg:province":"KY",
    "sg:tags":[
        "director"
    ],
    "wof:name":"Morgan Funeral Home",
    "wof:placetype":"venue"
},
  "geometry": {"coordinates":[-84.72527700000001,38.050279],"type":"Point"}
}