{
  "type": "Feature",
  "properties": {
    "addr:full":"900 W Market St Louisville KY 40202",
    "addr:housenumber":"900",
    "addr:postcode":"40202",
    "addr:street":"W Market St",
    "iso:country":"US",
    "sg:address":"900 W Market St",
    "sg:city":"Louisville",
    "sg:classifiers":[
        {
            "category":"Education",
            "subcategory":"Preschool",
            "type":"Public Place"
        }
    ],
    "sg:phone":"+1 502 589 3565",
    "sg:postcode":"40202",
    "sg:province":"KY",
    "sg:tags":[
        "kindergarten"
    ],
    "wof:name":"Spradling Mary E Day Nursery",
    "wof:placetype":"venue"
},
  "geometry": {"coordinates":[-85.765511,38.256168],"type":"Point"}
}