{
  "type": "Feature",
  "properties": {
    "iso:country":"US",
    "sg:address":"9793 State Hwy 52",
    "sg:city":"Beattyville",
    "sg:classifiers":[
        {
            "category":"Organizations",
            "subcategory":"Religious Organization",
            "type":"Services"
        }
    ],
    "sg:phone":"+1 606 464 2958",
    "sg:postcode":"41311",
    "sg:province":"KY",
    "sg:tags":[
        "church"
    ],
    "wof:name":"Hopewell First Church Of God",
    "wof:placetype":"venue"
},
  "geometry": {"coordinates":[-83.586975,37.561941],"type":"Point"}
}