{
  "type": "Feature",
  "properties": {
    "addr:full":"212 E 3rd St Grayson KY 41143",
    "addr:housenumber":"212",
    "addr:postcode":"41143",
    "addr:street":"E 3Rd St",
    "iso:country":"US",
    "sg:address":"212 E 3rd St",
    "sg:city":"Grayson",
    "sg:classifiers":[
        {
            "category":"Health Services",
            "subcategory":"Doctor",
            "type":"Services"
        }
    ],
    "sg:phone":"+1 606 474 5193",
    "sg:postcode":"41143",
    "sg:province":"KY",
    "sg:tags":[
        "dentist"
    ],
    "wof:name":"Paula P Caskey DDS",
    "wof:placetype":"venue"
},
  "geometry": {"coordinates":[-82.946535,38.334084],"type":"Point"}
}