{
  "type": "Feature",
  "properties": {
    "addr:full":"3535 Clarks River Rd Paducah KY 42003",
    "addr:housenumber":"3535",
    "addr:postcode":"42003",
    "addr:street":"Clarks River Rd",
    "iso:country":"US",
    "sg:address":"3535 Clarks River Rd",
    "sg:city":"Paducah",
    "sg:classifiers":[
        {
            "category":"Bars & Pubs",
            "type":"Food & Drink"
        }
    ],
    "sg:phone":"+1 270 444 0793",
    "sg:postcode":"42003",
    "sg:province":"KY",
    "sg:tags":[
        "lounge",
        "cocktail"
    ],
    "wof:name":"J J's Lounge",
    "wof:placetype":"venue"
},
  "geometry": {"coordinates":[-88.563056,37.048035],"type":"Point"}
}