{
  "type": "Feature",
  "properties": {
    "iso:country":"US",
    "sg:address":"10009 Robsion Rd",
    "sg:city":"Louisville",
    "sg:classifiers":[
        {
            "category":"Professional",
            "type":"Services"
        }
    ],
    "sg:phone":"+1 502 261 1726",
    "sg:postcode":"40299",
    "sg:province":"KY",
    "wof:name":"C Amy Scott",
    "wof:placetype":"venue"
},
  "geometry": {"coordinates":[-85.57308500000001,38.186422],"type":"Point"}
}