{
  "type": "Feature",
  "properties": {
    "iso:country":"US",
    "sg:address":"2665 State Hwy 121",
    "sg:city":"Murray",
    "sg:classifiers":[
        {
            "category":"Autos & Motor Vehicles",
            "subcategory":"Automobile Sales",
            "type":"Retail Goods"
        }
    ],
    "sg:phone":"+1 270 753 3669",
    "sg:postcode":"42071",
    "sg:province":"KY",
    "sg:tags":[
        "car",
        "dealer"
    ],
    "wof:name":"Underhill Motor Sales",
    "wof:placetype":"venue"
},
  "geometry": {"coordinates":[-88.363967,36.630682],"type":"Point"}
}