{
  "type": "Feature",
  "properties": {
    "addr:full":"375 Thomas More Pkwy Crestview Hills KY 41017",
    "addr:housenumber":"375",
    "addr:postcode":"41017",
    "addr:street":"Thomas More Pkwy",
    "iso:country":"US",
    "sg:address":"375 Thomas More Pkwy",
    "sg:city":"Crestview Hills",
    "sg:classifiers":[
        {
            "category":"Health Services",
            "subcategory":"Medical Lab",
            "type":"Services"
        }
    ],
    "sg:phone":"+1 859 331 1373",
    "sg:postcode":"41017",
    "sg:province":"KY",
    "sg:tags":[
        "laboratory"
    ],
    "wof:name":"Laboratory Corp Of America",
    "wof:placetype":"venue"
},
  "geometry": {"coordinates":[-84.56821600000001,39.024034],"type":"Point"}
}