{
  "type": "Feature",
  "properties": {
    "addr:full":"1308 State Hwy 1046 Calhoun KY 42327",
    "addr:housenumber":"1308",
    "addr:postcode":"1046;42327",
    "addr:street":"State Hwy",
    "iso:country":"US",
    "sg:address":"1308 State Hwy 1046",
    "sg:city":"Calhoun",
    "sg:phone":"+1 270 273 5464",
    "sg:postcode":"42327",
    "sg:province":"KY",
    "sg:tags":[
        "farm",
        "corn",
        "soybean"
    ],
    "wof:name":"Len Bickett",
    "wof:placetype":"venue"
},
  "geometry": {"coordinates":[-87.20683200000001,37.527954],"type":"Point"}
}