{
  "type": "Feature",
  "properties": {
    "addr:full":"103 Shane St Glasgow KY 42141",
    "addr:housenumber":"103",
    "addr:postcode":"42141",
    "addr:street":"Shane St",
    "iso:country":"US",
    "sg:address":"103 Shane St",
    "sg:city":"Glasgow",
    "sg:classifiers":[
        {
            "category":"Autos & Motor Vehicles",
            "subcategory":"Auto Supplies",
            "type":"Retail Goods"
        }
    ],
    "sg:phone":"+1 270 651 7200",
    "sg:postcode":"42141",
    "sg:province":"KY",
    "sg:tags":[
        "automobile",
        "parts"
    ],
    "wof:name":"NAPA Auto Parts",
    "wof:placetype":"venue"
},
  "geometry": {"coordinates":[-85.926636,37.005658],"type":"Point"}
}