{
  "type": "Feature",
  "properties": {
    "addr:full":"209 Kinnaird Ln Louisville KY 40243",
    "addr:housenumber":"209",
    "addr:postcode":"40243",
    "addr:street":"Kinnaird Ln",
    "iso:country":"US",
    "sg:address":"209 Kinnaird Ln",
    "sg:city":"Louisville",
    "sg:classifiers":[
        {
            "category":"Manufacturing",
            "subcategory":"Metals",
            "type":"Manufacturing & Wholesale Goods"
        }
    ],
    "sg:phone":"+1 502 244 0954",
    "sg:postcode":"40243",
    "sg:province":"KY",
    "sg:tags":[
        "plate",
        "work",
        "fabricated",
        "mfg"
    ],
    "wof:name":"H T Technologies Inc",
    "wof:placetype":"venue"
},
  "geometry": {"coordinates":[-85.551439,38.243424],"type":"Point"}
}