{
  "type": "Feature",
  "properties": {
    "iso:country":"US",
    "sg:address":"514 Dover Rd",
    "sg:city":"Louisville",
    "sg:classifiers":[
        {
            "category":"Professional",
            "subcategory":"Art Services",
            "type":"Services"
        }
    ],
    "sg:phone":"+1 502 895 9181",
    "sg:postcode":"40206",
    "sg:province":"KY",
    "sg:tags":[
        "commercial",
        "design"
    ],
    "wof:name":"Hess 2 Design",
    "wof:placetype":"venue"
},
  "geometry": {"coordinates":[-85.67241799999999,38.247743],"type":"Point"}
}