{
  "type": "Feature",
  "properties": {
    "iso:country":"US",
    "sg:address":"649 Independence Dr",
    "sg:city":"Radcliff",
    "sg:classifiers":[
        {
            "category":"Real Estate",
            "subcategory":"Real Estate Agent",
            "type":"Services"
        }
    ],
    "sg:phone":"+1 270 352 1031",
    "sg:postcode":"40160",
    "sg:province":"KY",
    "wof:name":"Harris Independent Realtor",
    "wof:placetype":"venue"
},
  "geometry": {"coordinates":[-85.911564,37.807545],"type":"Point"}
}