{
  "type": "Feature",
  "properties": {
    "iso:country":"US",
    "sg:address":"12800 Castle Rd",
    "sg:city":"Louisville",
    "sg:classifiers":[
        {
            "category":"Organizations",
            "subcategory":"Religious Organization",
            "type":"Services"
        }
    ],
    "sg:phone":"+1 502 935 6682",
    "sg:postcode":"40272",
    "sg:province":"KY",
    "sg:tags":[
        "church"
    ],
    "wof:name":"Providence Baptist Church",
    "wof:placetype":"venue"
},
  "geometry": {"coordinates":[-85.89254699999999,38.069789],"type":"Point"}
}