{
  "type": "Feature",
  "properties": {
    "iso:country":"US",
    "sg:address":"950 Bethel Hill Rd",
    "sg:city":"Salem",
    "sg:classifiers":[
        {
            "category":"Farming",
            "subcategory":"Livestock Farm",
            "type":"Manufacturing & Wholesale Goods"
        }
    ],
    "sg:phone":"+1 270 988 3661",
    "sg:postcode":"42078",
    "sg:province":"KY",
    "sg:tags":[
        "beef",
        "feedlot",
        "cattle"
    ],
    "wof:name":"Lee Nolie",
    "wof:placetype":"venue"
},
  "geometry": {"coordinates":[-88.344116,37.359079],"type":"Point"}
}