{
  "type": "Feature",
  "properties": {
    "addr:full":"4736 Frederica St Owensboro KY 42301",
    "addr:housenumber":"4736",
    "addr:postcode":"42301",
    "addr:street":"Frederica St",
    "iso:country":"US",
    "sg:address":"4736 Frederica St",
    "sg:city":"Owensboro",
    "sg:classifiers":[
        {
            "category":"Restaurant",
            "type":"Food & Drink"
        }
    ],
    "sg:phone":"+1 270 686 7800",
    "sg:postcode":"42301",
    "sg:province":"KY",
    "sg:website":"www.buffalowildwings.com",
    "wof:name":"Buffalo Wild Wings Grill & Bar",
    "wof:placetype":"venue"
},
  "geometry": {"coordinates":[-87.123808,37.724461],"type":"Point"}
}