{
  "type": "Feature",
  "properties": {
    "addr:full":"3928 7th Street Rd Shively KY 40216",
    "addr:housenumber":"3928",
    "addr:postcode":"40216",
    "addr:street":"7Th Street Rd",
    "iso:country":"US",
    "sg:address":"3928 7th Street Rd",
    "sg:city":"Shively",
    "sg:classifiers":[
        {
            "category":"Shopping",
            "subcategory":"Shoes",
            "type":"Retail Goods"
        }
    ],
    "sg:phone":"+1 502 447 9778",
    "sg:postcode":"40216",
    "sg:province":"KY",
    "wof:name":"Payless Shoe Source",
    "wof:placetype":"venue"
},
  "geometry": {"coordinates":[-85.807996,38.192135],"type":"Point"}
}