{
  "type": "Feature",
  "properties": {
    "iso:country":"US",
    "sg:address":"221 Main St",
    "sg:city":"Inez",
    "sg:classifiers":[
        {
            "category":"Government",
            "subcategory":"Court House",
            "type":"Public Place"
        }
    ],
    "sg:phone":"+1 606 298 7731",
    "sg:postcode":"41240",
    "sg:province":"KY",
    "sg:tags":[
        "county",
        "counsel"
    ],
    "wof:name":"County Attorney",
    "wof:placetype":"venue"
},
  "geometry": {"coordinates":[-82.804939,37.814021],"type":"Point"}
}