{
  "type": "Feature",
  "properties": {
    "iso:country":"US",
    "sg:address":"109 Finn St",
    "sg:city":"Franklin",
    "sg:classifiers":[
        {
            "category":"Social Services",
            "subcategory":"Child Care",
            "type":"Services"
        }
    ],
    "sg:phone":"+1 270 598 8899",
    "sg:postcode":"42134",
    "sg:province":"KY",
    "wof:name":"Tot Town Child Care",
    "wof:placetype":"venue"
},
  "geometry": {"coordinates":[-86.577692,36.727141],"type":"Point"}
}