{
  "type": "Feature",
  "properties": {
    "iso:country":"US",
    "sg:address":"706 Cohoon Rd",
    "sg:city":"Murray",
    "sg:classifiers":[
        {
            "category":"Farming",
            "subcategory":"Livestock Farm",
            "type":"Manufacturing & Wholesale Goods"
        }
    ],
    "sg:phone":"+1 270 753 6566",
    "sg:postcode":"42071",
    "sg:province":"KY",
    "sg:tags":[
        "equine"
    ],
    "wof:name":"McCuiston Key",
    "wof:placetype":"venue"
},
  "geometry": {"coordinates":[-88.22842300000001,36.611493],"type":"Point"}
}