{
  "type": "Feature",
  "properties": {
    "iso:country":"US",
    "sg:address":"102 S Walters Ave",
    "sg:city":"Hodgenville",
    "sg:classifiers":[
        {
            "category":"Government",
            "subcategory":"Post Office",
            "type":"Public Place"
        }
    ],
    "sg:phone":"+1 270 000 1111",
    "sg:postcode":"42748",
    "sg:province":"KY",
    "wof:name":"US Post Office",
    "wof:placetype":"venue"
},
  "geometry": {"coordinates":[-85.741384,37.573706],"type":"Point"}
}