{
  "type": "Feature",
  "properties": {
    "iso:country":"US",
    "sg:address":"913 N Mulberry St",
    "sg:city":"Elizabethtown",
    "sg:classifiers":[
        {
            "category":"Food & Beverages",
            "subcategory":"Groceries & Convenience Stores",
            "type":"Retail Goods"
        }
    ],
    "sg:phone":"+1 270 769 1105",
    "sg:postcode":"42701",
    "sg:province":"KY",
    "wof:name":"KWIK Shop Food Mart",
    "wof:placetype":"venue"
},
  "geometry": {"coordinates":[-85.840723,37.707901],"type":"Point"}
}