{
  "type": "Feature",
  "properties": {
    "addr:full":"7602 Old Salem Rd Louisville KY 40242",
    "addr:housenumber":"7602",
    "addr:postcode":"40242",
    "addr:street":"Old Salem Rd",
    "iso:country":"US",
    "sg:address":"7602 Old Salem Rd",
    "sg:city":"Louisville",
    "sg:classifiers":[
        {
            "category":"Building & Trades",
            "subcategory":"Electrical",
            "type":"Services"
        }
    ],
    "sg:phone":"+1 502 423 7333",
    "sg:postcode":"40242",
    "sg:province":"KY",
    "sg:tags":[
        "electric",
        "contractor"
    ],
    "wof:name":"A Professional Installations",
    "wof:placetype":"venue"
},
  "geometry": {"coordinates":[-85.6146,38.284603],"type":"Point"}
}