{
  "type": "Feature",
  "properties": {
    "addr:full":"709 S 1st St Louisville KY 40202",
    "addr:housenumber":"709",
    "addr:postcode":"40202",
    "addr:street":"S 1St St",
    "iso:country":"US",
    "sg:address":"709 S 1st St",
    "sg:city":"Louisville",
    "sg:classifiers":[
        {
            "category":"Shopping",
            "subcategory":"Florist",
            "type":"Retail Goods"
        }
    ],
    "sg:phone":"+1 502 569 2006",
    "sg:postcode":"40202",
    "sg:province":"KY",
    "wof:name":"Dragonfly Floral Events Inc",
    "wof:placetype":"venue"
},
  "geometry": {"coordinates":[-85.75348700000001,38.244753],"type":"Point"}
}