{
  "type": "Feature",
  "properties": {
    "iso:country":"US",
    "sg:address":"5314 Regent Way",
    "sg:city":"Louisville",
    "sg:classifiers":[
        {
            "category":"Building & Trades",
            "subcategory":"Cleaning & Sanitation",
            "type":"Services"
        }
    ],
    "sg:phone":"+1 502 426 7096",
    "sg:postcode":"40218",
    "sg:province":"KY",
    "sg:tags":[
        "janitor"
    ],
    "wof:name":"Renier Cleaning Svc",
    "wof:placetype":"venue"
},
  "geometry": {"coordinates":[-85.66137999999999,38.174539],"type":"Point"}
}