{
  "type": "Feature",
  "properties": {
    "iso:country":"US",
    "sg:address":"1115 S Chesley Dr",
    "sg:city":"Louisville",
    "sg:classifiers":[
        {
            "category":"Building & Trades",
            "subcategory":"Construction",
            "type":"Services"
        }
    ],
    "sg:phone":"+1 502 376 1101",
    "sg:postcode":"40219",
    "sg:province":"KY",
    "sg:tags":[
        "repair",
        "installation",
        "ceilings-supplies"
    ],
    "wof:name":"Shelton's Clean Ceilings Plus",
    "wof:placetype":"venue"
},
  "geometry": {"coordinates":[-85.68088899999999,38.122012],"type":"Point"}
}