{
  "type": "Feature",
  "properties": {
    "addr:full":"1031 Contract St Lexington KY 40505",
    "addr:housenumber":"1031",
    "addr:postcode":"40505",
    "addr:street":"Contract St",
    "iso:country":"US",
    "sg:address":"1031 Contract St",
    "sg:city":"Lexington",
    "sg:classifiers":[
        {
            "category":"Autos & Motor Vehicles",
            "subcategory":"Auto Supplies",
            "type":"Retail Goods"
        },
        {
            "category":"Retail",
            "subcategory":"Auto Repair",
            "type":"Services"
        }
    ],
    "sg:phone":"+1 859 254 8394",
    "sg:postcode":"40505",
    "sg:province":"KY",
    "sg:tags":[
        "electric",
        "transmission",
        "automobile",
        "brake",
        "equipment-service",
        "air conditioning"
    ],
    "wof:name":"Chester Horn's Garage",
    "wof:placetype":"venue"
},
  "geometry": {"coordinates":[-84.46221,38.051108],"type":"Point"}
}