{
  "type": "Feature",
  "properties": {
    "addr:full":"1927 Irvin Cobb Dr Paducah KY 42003",
    "addr:housenumber":"1927",
    "addr:postcode":"42003",
    "addr:street":"Irvin Cobb Dr",
    "iso:country":"US",
    "sg:address":"1927 Irvin Cobb Dr",
    "sg:city":"Paducah",
    "sg:classifiers":[
        {
            "category":"Banks & Credit Unions",
            "subcategory":"Bank",
            "type":"Services"
        }
    ],
    "sg:phone":"+1 270 442 0777",
    "sg:postcode":"42003",
    "sg:province":"KY",
    "sg:tags":[
        "loan"
    ],
    "wof:name":"Heights Finance Corp",
    "wof:placetype":"venue"
},
  "geometry": {"coordinates":[-88.595894,37.06142],"type":"Point"}
}