{
  "type": "Feature",
  "properties": {
    "iso:country":"US",
    "sg:address":"1340 US Hwy 31 W Byp",
    "sg:city":"Bowling Green",
    "sg:classifiers":[
        {
            "category":"Shopping",
            "subcategory":"Computers & Home Electronics",
            "type":"Retail Goods"
        }
    ],
    "sg:phone":"+1 270 783 4900",
    "sg:postcode":"42101",
    "sg:province":"KY",
    "sg:tags":[
        "equipment",
        "electronic",
        "supply"
    ],
    "wof:name":"Total Image Audio Inc",
    "wof:placetype":"venue"
},
  "geometry": {"coordinates":[-86.44258600000001,36.981731],"type":"Point"}
}