{
  "type": "Feature",
  "properties": {
    "addr:full":"1615 US Hwy 431 Browder KY 42326",
    "addr:housenumber":"1615",
    "addr:postcode":"42326",
    "addr:street":"Us Hwy 431",
    "iso:country":"US",
    "sg:address":"1615 US Hwy 431",
    "sg:city":"Browder",
    "sg:classifiers":[
        {
            "category":"Government",
            "subcategory":"Post Office",
            "type":"Public Place"
        }
    ],
    "sg:phone":"+1 270 476 8461",
    "sg:postcode":"42326",
    "sg:province":"KY",
    "wof:name":"US Post Office",
    "wof:placetype":"venue"
},
  "geometry": {"coordinates":[-87.03659399999999,37.196881],"type":"Point"}
}