{
  "type": "Feature",
  "properties": {
    "addr:full":"729 S Preston St Louisville KY 40203",
    "addr:housenumber":"729",
    "addr:postcode":"40203",
    "addr:street":"S Preston St",
    "iso:country":"US",
    "sg:address":"729 S Preston St",
    "sg:city":"Louisville",
    "sg:classifiers":[
        {
            "category":"Building & Trades",
            "subcategory":"Construction",
            "type":"Services"
        }
    ],
    "sg:phone":"+1 502 583 9788",
    "sg:postcode":"40203",
    "sg:province":"KY",
    "sg:tags":[
        "steel",
        "fabrication",
        "welding"
    ],
    "wof:name":"Midwest Steel",
    "wof:placetype":"venue"
},
  "geometry": {"coordinates":[-85.747694,38.243988],"type":"Point"}
}