{
  "type": "Feature",
  "properties": {
    "iso:country":"US",
    "sg:address":"500 Delaney Woods",
    "sg:city":"Nicholasville",
    "sg:classifiers":[
        {
            "category":"Professional",
            "subcategory":"Management & Consulting",
            "type":"Services"
        }
    ],
    "sg:phone":"+1 859 229 2412",
    "sg:postcode":"40356",
    "sg:province":"KY",
    "sg:tags":[
        "business"
    ],
    "wof:name":"Hay & Associates LLC",
    "wof:placetype":"venue"
},
  "geometry": {"coordinates":[-84.633229,37.987839],"type":"Point"}
}