{
  "type": "Feature",
  "properties": {
    "addr:full":"702 S Shore Rd South Shore KY 41175",
    "addr:housenumber":"702",
    "addr:postcode":"41175",
    "addr:street":"S Shore Rd",
    "iso:country":"US",
    "sg:address":"702 S Shore Rd",
    "sg:city":"South Shore",
    "sg:classifiers":[
        {
            "category":"Professional",
            "type":"Services"
        }
    ],
    "sg:phone":"+1 606 932 8000",
    "sg:postcode":"41175",
    "sg:province":"KY",
    "wof:name":"Dept For Community Based Svc",
    "wof:placetype":"venue"
},
  "geometry": {"coordinates":[-82.97515799999999,38.721309],"type":"Point"}
}