{
  "type": "Feature",
  "properties": {
    "addr:full":"10262 Liberty Rd Elk Horn KY 42733",
    "addr:housenumber":"10262",
    "addr:postcode":"42733",
    "addr:street":"Liberty Rd",
    "iso:country":"US",
    "sg:address":"10262 Liberty Rd",
    "sg:city":"Elk Horn",
    "sg:classifiers":[
        {
            "category":"Home & Garden",
            "subcategory":"Building Materials",
            "type":"Retail Goods"
        }
    ],
    "sg:phone":"+1 270 465 8211",
    "sg:postcode":"42733",
    "sg:province":"KY",
    "sg:tags":[
        "center"
    ],
    "wof:name":"Mannsville Sash & Door Co Inc",
    "wof:placetype":"venue"
},
  "geometry": {"coordinates":[-85.189921,37.370296],"type":"Point"}
}