{
  "type": "Feature",
  "properties": {
    "addr:full":"1418 Sasser School Rd London KY 40744",
    "addr:housenumber":"1418",
    "addr:postcode":"40744",
    "addr:street":"Sasser School Rd",
    "iso:country":"US",
    "sg:address":"1418 Sasser School Rd",
    "sg:city":"London",
    "sg:classifiers":[
        {
            "category":"Health Services",
            "subcategory":"Medical Lab",
            "type":"Services"
        }
    ],
    "sg:phone":"+1 606 878 8461",
    "sg:postcode":"40744",
    "sg:province":"KY",
    "sg:tags":[
        "laboratory",
        "dental"
    ],
    "wof:name":"Royal Crown Dental Arts Inc",
    "wof:placetype":"venue"
},
  "geometry": {"coordinates":[-84.051053,37.102925],"type":"Point"}
}