{
  "type": "Feature",
  "properties": {
    "iso:country":"US",
    "sg:address":"1450 Chelsea Dr",
    "sg:city":"Madisonville",
    "sg:classifiers":[
        {
            "category":"Freight",
            "type":"Transportation"
        }
    ],
    "sg:phone":"+1 270 825 8879",
    "sg:postcode":"42431",
    "sg:province":"KY",
    "sg:tags":[
        "commercial",
        "storage"
    ],
    "wof:name":"ABC Mini Storage",
    "wof:placetype":"venue"
},
  "geometry": {"coordinates":[-87.495532,37.349608],"type":"Point"}
}