{
  "type": "Feature",
  "properties": {
    "iso:country":"US",
    "sg:address":"1611 W 7th St",
    "sg:city":"Owensboro",
    "sg:classifiers":[
        {
            "category":"Wholesale",
            "subcategory":"Machinery & Supplies",
            "type":"Manufacturing & Wholesale Goods"
        }
    ],
    "sg:phone":"+1 270 685 4919",
    "sg:postcode":"42301",
    "sg:province":"KY",
    "sg:tags":[
        "equipment",
        "industrial"
    ],
    "sg:website":"http://pvfsupplyco.com",
    "wof:name":"P V F Supply Company Inc-",
    "wof:placetype":"venue"
},
  "geometry": {"coordinates":[-87.12863299999999,37.7683],"type":"Point"}
}