{
  "type": "Feature",
  "properties": {
    "iso:country":"US",
    "sg:address":"742 E Broadway",
    "sg:city":"Louisville",
    "sg:classifiers":[
        {
            "category":"Wholesale",
            "subcategory":"Medical Equipment & Supplies",
            "type":"Manufacturing & Wholesale Goods"
        }
    ],
    "sg:phone":"+1 502 584 2959",
    "sg:postcode":"40202",
    "sg:province":"KY",
    "sg:tags":[
        "device",
        "prosthetic"
    ],
    "sg:website":"http://www.louisvilleprosthetics.com",
    "wof:name":"Louisville Prosthetics",
    "wof:placetype":"venue"
},
  "geometry": {"coordinates":[-85.740638,38.244777],"type":"Point"}
}