{
  "type": "Feature",
  "properties": {
    "addr:full":"817 N Limestone St Lexington KY 40505",
    "addr:housenumber":"817",
    "addr:postcode":"40505",
    "addr:street":"N Limestone St",
    "iso:country":"US",
    "sg:address":"817 N Limestone St",
    "sg:city":"Lexington",
    "sg:classifiers":[
        {
            "category":"Organizations",
            "subcategory":"Religious Organization",
            "type":"Services"
        }
    ],
    "sg:phone":"+1 859 231 1270",
    "sg:postcode":"40505",
    "sg:province":"KY",
    "sg:tags":[
        "church"
    ],
    "wof:name":"West End Baptist Church",
    "wof:placetype":"venue"
},
  "geometry": {"coordinates":[-84.48010600000001,38.0583],"type":"Point"}
}