{
  "type": "Feature",
  "properties": {
    "iso:country":"US",
    "sg:address":"849 Washington Ct",
    "sg:city":"Mt Washington",
    "sg:classifiers":[
        {
            "category":"Professional",
            "subcategory":"Accounting & Tax Preparation",
            "type":"Services"
        }
    ],
    "sg:phone":"+1 502 538 7299",
    "sg:postcode":"40047",
    "sg:province":"KY",
    "sg:tags":[
        "payroll"
    ],
    "wof:name":"Complete Payroll Svc",
    "wof:placetype":"venue"
},
  "geometry": {"coordinates":[-85.558088,38.058967],"type":"Point"}
}