{
  "type": "Feature",
  "properties": {
    "iso:country":"US",
    "sg:address":"1400 Kingsway Dr",
    "sg:city":"Madisonville",
    "sg:classifiers":[
        {
            "category":"Organizations",
            "subcategory":"Religious Organization",
            "type":"Services"
        }
    ],
    "sg:phone":"+1 270 825 8801",
    "sg:postcode":"42431",
    "sg:province":"KY",
    "sg:tags":[
        "church"
    ],
    "wof:name":"Word Of Faith Christian Ctr",
    "wof:placetype":"venue"
},
  "geometry": {"coordinates":[-87.491084,37.372166],"type":"Point"}
}