{
  "type": "Feature",
  "properties": {
    "iso:country":"US",
    "sg:address":"741 Campbell Ln",
    "sg:city":"Bowling Green",
    "sg:classifiers":[
        {
            "category":"Restaurant",
            "type":"Food & Drink"
        }
    ],
    "sg:phone":"+1 270 393 9335",
    "sg:postcode":"42104",
    "sg:province":"KY",
    "sg:tags":[
        "parlor",
        "ice",
        "cream"
    ],
    "wof:name":"Marble Slab Creamery",
    "wof:placetype":"venue"
},
  "geometry": {"coordinates":[-86.47176899999999,36.963941],"type":"Point"}
}