{
  "type": "Feature",
  "properties": {
    "iso:country":"US",
    "sg:address":"10275 US Hwy 27",
    "sg:city":"Eubank",
    "sg:classifiers":[
        {
            "category":"Real Estate",
            "subcategory":"Real Estate Agent",
            "type":"Services"
        }
    ],
    "sg:phone":"+1 606 379 0621",
    "sg:postcode":"42567",
    "sg:province":"KY",
    "sg:website":"www.vlbishop.com",
    "wof:name":"Bishop Whitis Realtors",
    "wof:placetype":"venue"
},
  "geometry": {"coordinates":[-84.63454400000001,37.240169],"type":"Point"}
}