{
  "type": "Feature",
  "properties": {
    "addr:full":"1874 Grundy Rd Somerset KY 42501",
    "addr:housenumber":"1874",
    "addr:postcode":"42501",
    "addr:street":"Grundy Rd",
    "iso:country":"US",
    "sg:address":"1874 Grundy Rd",
    "sg:city":"Somerset",
    "sg:classifiers":[
        {
            "category":"Building & Trades",
            "subcategory":"Electrical",
            "type":"Services"
        }
    ],
    "sg:phone":"+1 606 274 4699",
    "sg:postcode":"42501",
    "sg:province":"KY",
    "sg:tags":[
        "electric",
        "contractor"
    ],
    "wof:name":"P & T Electric",
    "wof:placetype":"venue"
},
  "geometry": {"coordinates":[-84.536281,37.110552],"type":"Point"}
}