{
  "type": "Feature",
  "properties": {
    "addr:full":"555 E Main St Lebanon KY 40033",
    "addr:housenumber":"555",
    "addr:postcode":"40033",
    "addr:street":"E Main St",
    "iso:country":"US",
    "sg:address":"555 E Main St",
    "sg:city":"Lebanon",
    "sg:classifiers":[
        {
            "category":"Personal",
            "subcategory":"Tanning Parlor",
            "type":"Services"
        }
    ],
    "sg:phone":"+1 270 692 6076",
    "sg:postcode":"40033",
    "sg:province":"KY",
    "sg:tags":[
        "salon"
    ],
    "wof:name":"C & C Tan Shack",
    "wof:placetype":"venue"
},
  "geometry": {"coordinates":[-85.24267999999999,37.573726],"type":"Point"}
}