{
  "type": "Feature",
  "properties": {
    "addr:full":"2410 Alexandria Fort Thomas KY 41075",
    "addr:housenumber":"2410",
    "addr:postcode":"41075",
    "addr:street":"Alexandria Fort",
    "iso:country":"US",
    "sg:address":"2410 Alexandria",
    "sg:city":"Fort Thomas",
    "sg:classifiers":[
        {
            "category":"Retail",
            "subcategory":"Laundry & Dry Cleaning",
            "type":"Services"
        }
    ],
    "sg:phone":"+1 859 441 7581",
    "sg:postcode":"41075",
    "sg:province":"KY",
    "sg:website":"sunshinecleanersinc.com/",
    "wof:name":"Sunshine Cleaners",
    "wof:placetype":"venue"
},
  "geometry": {"coordinates":[-84.451401,39.078201],"type":"Point"}
}