{
  "type": "Feature",
  "properties": {
    "iso:country":"US",
    "sg:address":"15045 Herndon Oak Grove Rd",
    "sg:city":"Oak Grove",
    "sg:phone":"+1 270 439 3945",
    "sg:postcode":"42262",
    "sg:province":"KY",
    "sg:tags":[
        "farm",
        "grain",
        "cash"
    ],
    "wof:name":"Sullivan Lilburn",
    "wof:placetype":"venue"
},
  "geometry": {"coordinates":[-87.530435,36.707961],"type":"Point"}
}