{
  "type": "Feature",
  "properties": {
    "iso:country":"US",
    "sg:address":"1905 Brewers Mill Rd",
    "sg:city":"Harrodsburg",
    "sg:classifiers":[
        {
            "category":"Building & Trades",
            "subcategory":"Construction",
            "type":"Services"
        }
    ],
    "sg:phone":"+1 859 366 4409",
    "sg:postcode":"40330",
    "sg:province":"KY",
    "sg:tags":[
        "railroad"
    ],
    "wof:name":"Boswell Construction",
    "wof:placetype":"venue"
},
  "geometry": {"coordinates":[-85.00627,37.75702],"type":"Point"}
}