{
  "type": "Feature",
  "properties": {
    "iso:country":"US",
    "sg:address":"3007 Limaburg Rd",
    "sg:city":"Hebron",
    "sg:classifiers":[
        {
            "category":"Social Services",
            "subcategory":"Child Care",
            "type":"Services"
        }
    ],
    "sg:phone":"+1 859 689 2333",
    "sg:postcode":"41048",
    "sg:province":"KY",
    "sg:tags":[
        "day"
    ],
    "wof:name":"The Safe Place Child Care & Learng Cntr",
    "wof:placetype":"venue"
},
  "geometry": {"coordinates":[-84.700699,39.064899],"type":"Point"}
}