{
  "type": "Feature",
  "properties": {
    "addr:full":"100 W John Rowan Blvd Bardstown KY 40004",
    "addr:housenumber":"100",
    "addr:postcode":"40004",
    "addr:street":"W John Rowan Blvd",
    "iso:country":"US",
    "sg:address":"100 W John Rowan Blvd",
    "sg:city":"Bardstown",
    "sg:classifiers":[
        {
            "category":"Shopping",
            "subcategory":"Department Store",
            "type":"Retail Goods"
        }
    ],
    "sg:phone":"+1 502 349 6007",
    "sg:postcode":"40004",
    "sg:province":"KY",
    "wof:name":"Wal-Mart",
    "wof:placetype":"venue"
},
  "geometry": {"coordinates":[-85.465594,37.826645],"type":"Point"}
}