{
  "type": "Feature",
  "properties": {
    "addr:full":"100 Holt Dr Scottsville KY 42164",
    "addr:housenumber":"100",
    "addr:postcode":"42164",
    "addr:street":"Holt Dr",
    "iso:country":"US",
    "sg:address":"100 Holt Dr",
    "sg:city":"Scottsville",
    "sg:classifiers":[
        {
            "category":"Restaurant",
            "type":"Food & Drink"
        }
    ],
    "sg:phone":"+1 270 237 5629",
    "sg:postcode":"42164",
    "sg:province":"KY",
    "wof:name":"Smoke Shack Bbq",
    "wof:placetype":"venue"
},
  "geometry": {"coordinates":[-86.204666,36.738226],"type":"Point"}
}