{
  "type": "Feature",
  "properties": {
    "addr:full":"145 Smith Ln Louisville KY 40229",
    "addr:housenumber":"145",
    "addr:postcode":"40229",
    "addr:street":"Smith Ln",
    "iso:country":"US",
    "sg:address":"145 Smith Ln",
    "sg:city":"Louisville",
    "sg:classifiers":[
        {
            "category":"Building & Trades",
            "subcategory":"Plumbing",
            "type":"Services"
        }
    ],
    "sg:phone":"+1 502 955 5288",
    "sg:postcode":"40229",
    "sg:province":"KY",
    "sg:tags":[
        "sewer",
        "cleaning",
        "drain"
    ],
    "wof:name":"Pipe Eyes LLC",
    "wof:placetype":"venue"
},
  "geometry": {"coordinates":[-85.687646,38.07819],"type":"Point"}
}