{
  "type": "Feature",
  "properties": {
    "addr:full":"52 S Main St Walton KY 41094",
    "addr:housenumber":"52",
    "addr:postcode":"41094",
    "addr:street":"S Main St",
    "iso:country":"US",
    "sg:address":"52 S Main St",
    "sg:city":"Walton",
    "sg:classifiers":[
        {
            "category":"Government",
            "subcategory":"Post Office",
            "type":"Public Place"
        }
    ],
    "sg:phone":"+1 859 485 4023",
    "sg:postcode":"41094",
    "sg:province":"KY",
    "wof:name":"US Post Office",
    "wof:placetype":"venue"
},
  "geometry": {"coordinates":[-84.610058,38.862471],"type":"Point"}
}