{
  "type": "Feature",
  "properties": {
    "iso:country":"US",
    "sg:address":"1335 S Hurstbourne Pkwy",
    "sg:city":"Louisville",
    "sg:classifiers":[
        {
            "category":"Autos & Motor Vehicles",
            "subcategory":"Fuel & Gas Station",
            "type":"Retail Goods"
        }
    ],
    "sg:phone":"+1 502 412 2652",
    "sg:postcode":"40222",
    "sg:province":"KY",
    "sg:tags":[
        "oil"
    ],
    "wof:name":"Service Plus Chevron",
    "wof:placetype":"venue"
},
  "geometry": {"coordinates":[-85.57799,38.225457],"type":"Point"}
}