{
  "type": "Feature",
  "properties": {
    "addr:full":"4701 Jennings Ln Louisville KY 40218",
    "addr:housenumber":"4701",
    "addr:postcode":"40218",
    "addr:street":"Jennings Ln",
    "iso:country":"US",
    "sg:address":"4701 Jennings Ln",
    "sg:city":"Louisville",
    "sg:classifiers":[
        {
            "category":"Food & Beverages",
            "subcategory":"Farmers Market",
            "type":"Retail Goods"
        },
        {
            "category":"Farming",
            "subcategory":"Farm",
            "type":"Manufacturing & Wholesale Goods"
        },
        {
            "category":"Wholesale",
            "subcategory":"Fruits & Vegetables",
            "type":"Manufacturing & Wholesale Goods"
        }
    ],
    "sg:phone":"+1 502 969 5445",
    "sg:postcode":"40218",
    "sg:province":"KY",
    "sg:tags":[
        "shipper",
        "grower",
        "vegetables-wholesale"
    ],
    "sg:website":"http://www.hortonfruit.com",
    "wof:name":"Grow Farms Inc",
    "wof:placetype":"venue"
},
  "geometry": {"coordinates":[-85.685013,38.187389],"type":"Point"}
}