{
  "type": "Feature",
  "properties": {
    "iso:country":"US",
    "sg:address":"319 Wallace Ave",
    "sg:city":"Frankfort",
    "sg:classifiers":[
        {
            "category":"Shopping",
            "subcategory":"Computers & Home Electronics",
            "type":"Retail Goods"
        }
    ],
    "sg:phone":"+1 502 223 2590",
    "sg:postcode":"40601",
    "sg:province":"KY",
    "sg:tags":[
        "repair"
    ],
    "wof:name":"Zenith",
    "wof:placetype":"venue"
},
  "geometry": {"coordinates":[-84.865883,38.202852],"type":"Point"}
}