{
  "type": "Feature",
  "properties": {
    "addr:full":"374 Crossfield Dr Versailles KY 40383",
    "addr:housenumber":"374",
    "addr:postcode":"40383",
    "addr:street":"Crossfield Dr",
    "iso:country":"US",
    "sg:address":"374 Crossfield Dr",
    "sg:city":"Versailles",
    "sg:classifiers":[
        {
            "category":"Recreation",
            "type":"Entertainment"
        }
    ],
    "sg:phone":"+1 859 879 0313",
    "sg:postcode":"40383",
    "sg:province":"KY",
    "sg:tags":[
        "instruction",
        "gymnastic"
    ],
    "wof:name":"Central Kentucky Gymnastics",
    "wof:placetype":"venue"
},
  "geometry": {"coordinates":[-84.71588199999999,38.059362],"type":"Point"}
}