{
  "type": "Feature",
  "properties": {
    "addr:full":"1714 Perryville Rd Danville KY 40422",
    "addr:housenumber":"1714",
    "addr:postcode":"40422",
    "addr:street":"Perryville Rd",
    "iso:country":"US",
    "sg:address":"1714 Perryville Rd",
    "sg:city":"Danville",
    "sg:classifiers":[
        {
            "category":"Government",
            "subcategory":"Office",
            "type":"Public Place"
        }
    ],
    "sg:phone":"+1 859 239 7105",
    "sg:postcode":"40422",
    "sg:province":"KY",
    "wof:name":"Community Based Svc",
    "wof:placetype":"venue"
},
  "geometry": {"coordinates":[-84.79104100000001,37.64759],"type":"Point"}
}