{
  "type": "Feature",
  "properties": {
    "iso:country":"US",
    "sg:address":"2601 Technology Dr",
    "sg:city":"Louisville",
    "sg:classifiers":[
        {
            "category":"Wholesale",
            "subcategory":"Machinery & Supplies",
            "type":"Manufacturing & Wholesale Goods"
        }
    ],
    "sg:phone":"+1 502 491 6300",
    "sg:postcode":"40299",
    "sg:province":"KY",
    "sg:tags":[
        "instrument",
        "scientific",
        "apparatus"
    ],
    "sg:website":"http://www.chromres.com",
    "wof:name":"Crs",
    "wof:placetype":"venue"
},
  "geometry": {"coordinates":[-85.547043,38.20948],"type":"Point"}
}