{
  "type": "Feature",
  "properties": {
    "iso:country":"US",
    "sg:address":"4401 Produce Rd",
    "sg:city":"Louisville",
    "sg:classifiers":[
        {
            "category":"Wholesale",
            "subcategory":"Beer",
            "type":"Manufacturing & Wholesale Goods"
        }
    ],
    "sg:phone":"+1 502 451 4111",
    "sg:postcode":"40218",
    "sg:province":"KY",
    "sg:tags":[
        "ale"
    ],
    "wof:name":"Mo Moorman Distributing Inc",
    "wof:placetype":"venue"
},
  "geometry": {"coordinates":[-85.676385,38.187734],"type":"Point"}
}