{
  "type": "Feature",
  "properties": {
    "iso:country":"US",
    "sg:address":"117 N 7th St",
    "sg:city":"Mayfield",
    "sg:classifiers":[
        {
            "category":"Professional",
            "subcategory":"Accounting & Tax Preparation",
            "type":"Services"
        }
    ],
    "sg:phone":"+1 270 247 4190",
    "sg:postcode":"42066",
    "sg:province":"KY",
    "sg:tags":[
        "accountant"
    ],
    "wof:name":"Cornman Bryan & Watts",
    "wof:placetype":"venue"
},
  "geometry": {"coordinates":[-88.635865,36.742495],"type":"Point"}
}