{
  "type": "Feature",
  "properties": {
    "iso:country":"US",
    "sg:address":"301 8th St",
    "sg:city":"Carrollton",
    "sg:classifiers":[
        {
            "category":"Professional",
            "subcategory":"Business Services",
            "type":"Services"
        }
    ],
    "sg:phone":"+1 502 732 5157",
    "sg:postcode":"41008",
    "sg:province":"KY",
    "wof:name":"Carrico William O",
    "wof:placetype":"venue"
},
  "geometry": {"coordinates":[-85.17473200000001,38.680133],"type":"Point"}
}