{
  "type": "Feature",
  "properties": {
    "iso:country":"US",
    "sg:address":"107 Main St",
    "sg:city":"Pikeville",
    "sg:classifiers":[
        {
            "category":"Organizations",
            "subcategory":"Religious Organization",
            "type":"Services"
        }
    ],
    "sg:phone":"+1 606 437 7315",
    "sg:postcode":"41501",
    "sg:province":"KY",
    "sg:tags":[
        "church"
    ],
    "sg:website":"www.pikevillemethodistchurch.org",
    "wof:name":"Pikeville United Methodist Chr",
    "wof:placetype":"venue"
},
  "geometry": {"coordinates":[-82.51846,37.477957],"type":"Point"}
}