{
  "type": "Feature",
  "properties": {
    "iso:country":"US",
    "sg:address":"401 W Main St",
    "sg:city":"Danville",
    "sg:classifiers":[
        {
            "category":"Museum",
            "type":"Entertainment"
        }
    ],
    "sg:phone":"+1 859 236 4054",
    "sg:postcode":"40422",
    "sg:province":"KY",
    "sg:tags":[
        "organization",
        "arts",
        "information"
    ],
    "wof:name":"Community Arts Ctr",
    "wof:placetype":"venue"
},
  "geometry": {"coordinates":[-84.775893,37.646049],"type":"Point"}
}