{
  "type": "Feature",
  "properties": {
    "addr:city":"Danville",
    "addr:full":"401 W Main St Danville, Ky 40422-1815",
    "addr:house_number":"401",
    "addr:housenumber":"401",
    "addr:phone":"+1 859-236-4054",
    "addr:postcode":"40422-1815",
    "addr:road":"W Main St",
    "addr:state":"KY",
    "addr:street":"W Main St",
    "iso:country":"US",
    "sg:address":"401 W Main St",
    "sg:city":"Danville",
    "sg:classifiers":[
        {
            "category":"Museum",
            "type":"Entertainment"
        }
    ],
    "sg:phone":"+1 859 236 4054",
    "sg:postcode":"40422",
    "sg:province":"KY",
    "sg:tags":[
        "organization",
        "arts",
        "information"
    ],
    "wof:name":"Community Arts Center",
    "wof:placetype":"venue"
},
  "geometry": {"coordinates":[-84.77548,37.64611],"type":"Point"}
}