{
  "type": "Feature",
  "properties": {
    "addr:city":"Louisville",
    "addr:full":"301 S Peterson Ave Louisville, Ky 40206-2540",
    "addr:house_number":"301",
    "addr:housenumber":"301",
    "addr:phone":"+1 502-895-7975",
    "addr:postcode":"40206-2540",
    "addr:road":"S Peterson Ave",
    "addr:state":"KY",
    "addr:street":"S Peterson Ave",
    "iso:country":"US",
    "sg:address":"301 S Peterson Ave",
    "sg:city":"Louisville",
    "sg:classifiers":[
        {
            "category":"Personal",
            "type":"Services"
        }
    ],
    "sg:phone":"+1 502 895 7975",
    "sg:postcode":"40206",
    "sg:province":"KY",
    "sg:tags":[
        "facility",
        "rental",
        "catering"
    ],
    "wof:airports":[
        102533321,
        102532709
    ],
    "wof:name":"Peterson-Dumesnil House Foundation",
    "wof:placetype":"venue"
},
  "geometry": {"coordinates":[-85.69725,38.25048],"type":"Point"}
}