{
  "type": "Feature",
  "properties": {
    "iso:country":"US",
    "sg:address":"301 S Peterson Ave",
    "sg:city":"Louisville",
    "sg:classifiers":[
        {
            "category":"Personal",
            "type":"Services"
        }
    ],
    "sg:phone":"+1 502 895 7975",
    "sg:postcode":"40206",
    "sg:province":"KY",
    "sg:tags":[
        "facility",
        "rental",
        "catering"
    ],
    "wof:name":"Peterson-Dumesnil House",
    "wof:placetype":"venue"
},
  "geometry": {"coordinates":[-85.69730800000001,38.250712],"type":"Point"}
}