{
  "type": "Feature",
  "properties": {
    "iso:country":"US",
    "sg:address":"3420 W Kentucky St",
    "sg:city":"Louisville",
    "sg:classifiers":[
        {
            "category":"Professional",
            "type":"Services"
        }
    ],
    "sg:phone":"+1 502 774 1269",
    "sg:postcode":"40211",
    "sg:province":"KY",
    "sg:tags":[
        "establishment"
    ],
    "wof:name":"ARP Inc",
    "wof:placetype":"venue"
},
  "geometry": {"coordinates":[-85.81282400000001,38.243441],"type":"Point"}
}