{
  "type": "Feature",
  "properties": {
    "addr:full":"213 W Main St Lebanon KY 40033",
    "addr:housenumber":"213",
    "addr:postcode":"40033",
    "addr:street":"W Main St",
    "iso:country":"US",
    "sg:address":"213 W Main St",
    "sg:city":"Lebanon",
    "sg:classifiers":[
        {
            "category":"Restaurant",
            "type":"Food & Drink"
        }
    ],
    "sg:phone":"+1 270 692 9231",
    "sg:postcode":"40033",
    "sg:province":"KY",
    "wof:name":"Country Kitchen",
    "wof:placetype":"venue"
},
  "geometry": {"coordinates":[-85.25468499999999,37.569129],"type":"Point"}
}