{
  "type": "Feature",
  "properties": {
    "iso:country":"US",
    "sg:address":"11886 Old Lexington Pike",
    "sg:city":"Walton",
    "sg:classifiers":[
        {
            "category":"Building & Trades",
            "subcategory":"Construction",
            "type":"Services"
        }
    ],
    "sg:phone":"+1 859 485 6595",
    "sg:postcode":"41094",
    "sg:province":"KY",
    "sg:tags":[
        "excavating",
        "contractor"
    ],
    "wof:name":"John R Coppage Inc",
    "wof:placetype":"venue"
},
  "geometry": {"coordinates":[-84.606964,38.894923],"type":"Point"}
}