{
  "type": "Feature",
  "properties": {
    "iso:country":"US",
    "sg:address":"1885 Ashes Creek Rd",
    "sg:city":"Bloomfield",
    "sg:classifiers":[
        {
            "category":"Building & Trades",
            "subcategory":"Construction",
            "type":"Services"
        }
    ],
    "sg:phone":"+1 502 348 0752",
    "sg:postcode":"40008",
    "sg:province":"KY",
    "sg:tags":[
        "contractor"
    ],
    "wof:name":"Aj S Roofing",
    "wof:placetype":"venue"
},
  "geometry": {"coordinates":[-85.234014,37.926747],"type":"Point"}
}