{
  "type": "Feature",
  "properties": {
    "iso:country":"US",
    "sg:address":"1596 Fort Campbell Blvd",
    "sg:city":"Clarksville",
    "sg:classifiers":[
        {
            "category":"Recreation",
            "type":"Entertainment"
        }
    ],
    "sg:phone":"+1 931 906 2941",
    "sg:postcode":"37042",
    "sg:province":"KY",
    "wof:name":"Clarksville Mixed Martial Arts",
    "wof:placetype":"venue"
},
  "geometry": {"coordinates":[-87.407763,36.575289],"type":"Point"}
}