{
  "type": "Feature",
  "properties": {
    "addr:full":"3153 Coral Ridge Rd Brooks KY 40109",
    "addr:housenumber":"3153",
    "addr:postcode":"40109",
    "addr:street":"Coral Ridge Rd",
    "iso:country":"US",
    "sg:address":"3153 Coral Ridge Rd",
    "sg:city":"Brooks",
    "sg:classifiers":[
        {
            "category":"Retail",
            "subcategory":"Storage",
            "type":"Services"
        }
    ],
    "sg:phone":"+1 502 955 6499",
    "sg:postcode":"40109",
    "sg:province":"KY",
    "sg:tags":[
        "container"
    ],
    "wof:name":"Derby City Containers",
    "wof:placetype":"venue"
},
  "geometry": {"coordinates":[-85.710341,38.057154],"type":"Point"}
}