{
  "type": "Feature",
  "properties": {
    "iso:country":"US",
    "sg:address":"395 S Limestone St",
    "sg:city":"Lexington",
    "sg:classifiers":[
        {
            "category":"Restaurant",
            "type":"Food & Drink"
        }
    ],
    "sg:phone":"+1 859 253 2007",
    "sg:postcode":"40508",
    "sg:province":"KY",
    "wof:name":"Tolly-Ho Restaurants Inc",
    "wof:placetype":"venue"
},
  "geometry": {"coordinates":[-84.503074,38.04233],"type":"Point"}
}