{
  "type": "Feature",
  "properties": {
    "iso:country":"US",
    "sg:address":"2529 W Broadway",
    "sg:city":"Louisville",
    "sg:classifiers":[
        {
            "category":"Bars & Pubs",
            "type":"Food & Drink"
        }
    ],
    "sg:phone":"+1 502 772 5000",
    "sg:postcode":"40211",
    "sg:province":"KY",
    "wof:name":"Main Event Sports Bar & Lounge",
    "wof:placetype":"venue"
},
  "geometry": {"coordinates":[-85.793182,38.249446],"type":"Point"}
}