{
  "type": "Feature",
  "properties": {
    "addr:full":"800 S Main St Marion KY 42064",
    "addr:housenumber":"800",
    "addr:postcode":"42064",
    "addr:street":"S Main St",
    "iso:country":"US",
    "sg:address":"800 S Main St",
    "sg:city":"Marion",
    "sg:classifiers":[
        {
            "category":"Insurance",
            "subcategory":"Insurance Agent",
            "type":"Services"
        }
    ],
    "sg:phone":"+1 270 965 3333",
    "sg:postcode":"42064",
    "sg:province":"KY",
    "wof:name":"Woodmen Of The World Life Ins",
    "wof:placetype":"venue"
},
  "geometry": {"coordinates":[-88.08308100000001,37.321446],"type":"Point"}
}