{
  "type": "Feature",
  "properties": {
    "addr:full":"401 Park Row Bowling Green KY 42101",
    "addr:housenumber":"401",
    "addr:postcode":"42101",
    "addr:street":"Park Row",
    "iso:country":"US",
    "sg:address":"401 Park Row",
    "sg:city":"Bowling Green",
    "sg:classifiers":[
        {
            "category":"Restaurant",
            "type":"Food & Drink"
        }
    ],
    "sg:menulink":"http://www.allmenus.com/ky/bowling-green/120453-subway/menu/",
    "sg:phone":"+1 270 783 4144",
    "sg:postcode":"42101",
    "sg:province":"KY",
    "sg:tags":[
        "american",
        "sandwich"
    ],
    "wof:name":"Subway",
    "wof:placetype":"venue"
},
  "geometry": {"coordinates":[-86.442178,36.993565],"type":"Point"}
}