{
  "type": "Feature",
  "properties": {
    "iso:country":"US",
    "sg:address":"3532 Ephraim Mcdowell Dr",
    "sg:city":"Louisville",
    "sg:classifiers":[
        {
            "category":"Health Services",
            "subcategory":"Hospice",
            "type":"Services"
        }
    ],
    "sg:phone":"+1 502 719 8922",
    "sg:postcode":"40205",
    "sg:province":"KY",
    "wof:name":"Hospice Foundation Of Louisville",
    "wof:placetype":"venue"
},
  "geometry": {"coordinates":[-85.652182,38.223028],"type":"Point"}
}