{
  "type": "Feature",
  "properties": {
    "iso:country":"US",
    "sg:address":"7613 Shelbyville Rd",
    "sg:city":"Louisville",
    "sg:classifiers":[
        {
            "category":"Utilities",
            "subcategory":"Mobile Phone",
            "type":"Services"
        }
    ],
    "sg:phone":"+1 502 425 7888",
    "sg:postcode":"40222",
    "sg:province":"KY",
    "sg:tags":[
        "telephone",
        "cellular"
    ],
    "sg:website":"www.t-mobile.com",
    "wof:name":"T-Mobile",
    "wof:placetype":"venue"
},
  "geometry": {"coordinates":[-85.610401,38.249242],"type":"Point"}
}