{
  "type": "Feature",
  "properties": {
    "iso:country":"US",
    "sg:address":"1820 Bullock Pen Rd",
    "sg:city":"Covington",
    "sg:classifiers":[
        {
            "category":"Building & Trades",
            "subcategory":"Plumbing",
            "type":"Services"
        }
    ],
    "sg:phone":"+1 859 356 2764",
    "sg:postcode":"41017",
    "sg:province":"KY",
    "sg:tags":[
        "tank",
        "septic"
    ],
    "wof:name":"Neaves Sanitation",
    "wof:placetype":"venue"
},
  "geometry": {"coordinates":[-84.54638199999999,38.992237],"type":"Point"}
}