{
  "type": "Feature",
  "properties": {
    "addr:full":"333 W Vine St Lexington KY 40507",
    "addr:housenumber":"333",
    "addr:postcode":"40507",
    "addr:street":"W Vine St",
    "iso:country":"US",
    "sg:address":"333 W Vine St",
    "sg:city":"Lexington",
    "sg:classifiers":[
        {
            "category":"Professional",
            "subcategory":"Lawyer & Legal Services",
            "type":"Services"
        }
    ],
    "sg:phone":"+1 859 259 4983",
    "sg:postcode":"40507",
    "sg:province":"KY",
    "sg:tags":[
        "attorney"
    ],
    "wof:name":"E Douglas Richards",
    "wof:placetype":"venue"
},
  "geometry": {"coordinates":[-84.500433,38.048117],"type":"Point"}
}