{
  "type": "Feature",
  "properties": {
    "iso:country":"US",
    "sg:address":"1717 Dixie Hwy",
    "sg:city":"Covington",
    "sg:classifiers":[
        {
            "category":"Health Services",
            "subcategory":"Clinic",
            "type":"Services"
        }
    ],
    "sg:phone":"+1 859 331 5200",
    "sg:postcode":"41011",
    "sg:province":"KY",
    "wof:name":"Wellnss Community/Greater Cinn",
    "wof:placetype":"venue"
},
  "geometry": {"coordinates":[-84.53883,39.062683],"type":"Point"}
}