{
  "type": "Feature",
  "properties": {
    "addr:full":"120 US Hwy 27 Somerset KY 42501",
    "addr:housenumber":"120",
    "addr:postcode":"42501",
    "addr:street":"Us Hwy 27",
    "iso:country":"US",
    "sg:address":"120 US Hwy 27",
    "sg:city":"Somerset",
    "sg:classifiers":[
        {
            "category":"Mining & Drilling",
            "type":"Manufacturing & Wholesale Goods"
        }
    ],
    "sg:phone":"+1 606 679 1509",
    "sg:postcode":"42501",
    "sg:province":"KY",
    "sg:tags":[
        "natural",
        "production",
        "gas"
    ],
    "wof:name":"Ron Absher",
    "wof:placetype":"venue"
},
  "geometry": {"coordinates":[-84.62988,37.14344],"type":"Point"}
}