{
  "type": "Feature",
  "properties": {
    "iso:country":"US",
    "sg:address":"125 Chenoweth Ln",
    "sg:city":"Louisville",
    "sg:classifiers":[
        {
            "category":"Wholesale",
            "subcategory":"Medical Equipment & Supplies",
            "type":"Manufacturing & Wholesale Goods"
        }
    ],
    "sg:phone":"+1 502 896 8966",
    "sg:postcode":"40207",
    "sg:province":"KY",
    "sg:tags":[
        "physician",
        "surgeon"
    ],
    "wof:name":"Burke Medical Svc Inc",
    "wof:placetype":"venue"
},
  "geometry": {"coordinates":[-85.655889,38.2535],"type":"Point"}
}