{
  "type": "Feature",
  "properties": {
    "addr:full":"1103 Highland Ave Carrollton KY 41008",
    "addr:housenumber":"1103",
    "addr:postcode":"41008",
    "addr:street":"Highland Ave",
    "iso:country":"US",
    "sg:address":"1103 Highland Ave",
    "sg:city":"Carrollton",
    "sg:classifiers":[
        {
            "category":"Autos & Motor Vehicles",
            "subcategory":"Fuel & Gas Station",
            "type":"Retail Goods"
        }
    ],
    "sg:phone":"+1 502 732 9932",
    "sg:postcode":"41008",
    "sg:province":"KY",
    "sg:tags":[
        "oil"
    ],
    "wof:name":"Swifty Service Station",
    "wof:placetype":"venue"
},
  "geometry": {"coordinates":[-85.169031,38.681916],"type":"Point"}
}