{
  "type": "Feature",
  "properties": {
    "iso:country":"US",
    "sg:address":"617 S 9th St",
    "sg:city":"Murray",
    "sg:classifiers":[
        {
            "category":"Organizations",
            "subcategory":"Religious Organization",
            "type":"Services"
        }
    ],
    "sg:phone":"+1 270 753 7599",
    "sg:postcode":"42071",
    "sg:province":"KY",
    "sg:tags":[
        "church"
    ],
    "wof:name":"Grace Baptist Church",
    "wof:placetype":"venue"
},
  "geometry": {"coordinates":[-88.310531,36.600385],"type":"Point"}
}