{
  "type": "Feature",
  "properties": {
    "iso:country":"US",
    "sg:address":"8025 Action Blvd",
    "sg:city":"Florence",
    "sg:classifiers":[
        {
            "category":"Autos & Motor Vehicles",
            "subcategory":"Automobile Sales",
            "type":"Retail Goods"
        },
        {
            "category":"Retail",
            "subcategory":"Auto Repair",
            "type":"Services"
        }
    ],
    "sg:phone":"+1 859 746 3634",
    "sg:postcode":"41042",
    "sg:province":"KY",
    "sg:tags":[
        "car"
    ],
    "wof:name":"Volkswagen of Florence",
    "wof:placetype":"venue"
},
  "geometry": {"coordinates":[-84.648999,38.999685],"type":"Point"}
}