{
  "type": "Feature",
  "properties": {
    "iso:country":"US",
    "sg:address":"460 W Maple St",
    "sg:city":"Salyersville",
    "sg:classifiers":[
        {
            "category":"Restaurant",
            "type":"Food & Drink"
        }
    ],
    "sg:phone":"+1 606 349 1331",
    "sg:postcode":"41465",
    "sg:province":"KY",
    "sg:tags":[
        "delicatessen"
    ],
    "wof:name":"Super America Deli",
    "wof:placetype":"venue"
},
  "geometry": {"coordinates":[-83.06968000000001,37.752556],"type":"Point"}
}