{
  "type": "Feature",
  "properties": {
    "iso:country":"US",
    "sg:address":"200 Bivins Ln",
    "sg:city":"Beaver Dam",
    "sg:phone":"+1 270 274 5959",
    "sg:postcode":"42320",
    "sg:province":"KY",
    "sg:tags":[
        "farm",
        "corn",
        "soybean"
    ],
    "wof:name":"Mary Lindley",
    "wof:placetype":"venue"
},
  "geometry": {"coordinates":[-86.885689,37.421043],"type":"Point"}
}