{
  "type": "Feature",
  "properties": {
    "iso:country":"US",
    "sg:address":"24 Bingham St",
    "sg:city":"Prestonsburg",
    "sg:classifiers":[
        {
            "category":"Government",
            "subcategory":"Office",
            "type":"Public Place"
        }
    ],
    "sg:phone":"+1 606 886 8912",
    "sg:postcode":"41653",
    "sg:province":"KY",
    "sg:tags":[
        "health"
    ],
    "wof:name":"Health Services KY Cab For",
    "wof:placetype":"venue"
},
  "geometry": {"coordinates":[-82.73497,37.667339],"type":"Point"}
}