{
  "type": "Feature",
  "properties": {
    "iso:country":"US",
    "sg:address":"3207 University Rd",
    "sg:city":"Louisville",
    "sg:classifiers":[
        {
            "category":"Organizations",
            "subcategory":"Religious Organization",
            "type":"Services"
        }
    ],
    "sg:phone":"+1 502 897 2876",
    "sg:postcode":"40206",
    "sg:province":"KY",
    "sg:tags":[
        "church"
    ],
    "wof:name":"Van Buren Baptist Church",
    "wof:placetype":"venue"
},
  "geometry": {"coordinates":[-85.693855,38.266489],"type":"Point"}
}