{
  "type": "Feature",
  "properties": {
    "addr:full":"4151 Shelbyville Rd Louisville KY 40207",
    "addr:housenumber":"4151",
    "addr:postcode":"40207",
    "addr:street":"Shelbyville Rd",
    "iso:country":"US",
    "sg:address":"4151 Shelbyville Rd",
    "sg:city":"Louisville",
    "sg:classifiers":[
        {
            "category":"Shopping",
            "subcategory":"Clothing, Apparel, & Fashions",
            "type":"Retail Goods"
        },
        {
            "category":"Shopping",
            "subcategory":"Shoes",
            "type":"Retail Goods"
        }
    ],
    "sg:phone":"+1 502 897 0096",
    "sg:postcode":"40207",
    "sg:province":"KY",
    "sg:tags":[
        "shoes-orthopedic",
        "store"
    ],
    "sg:website":"http://www.footsolutions.com",
    "wof:name":"Foot Solutions",
    "wof:placetype":"venue"
},
  "geometry": {"coordinates":[-85.64216399999999,38.251823],"type":"Point"}
}