{
  "type": "Feature",
  "properties": {
    "iso:country":"US",
    "sg:address":"812 Wilmore Rd",
    "sg:city":"Nicholasville",
    "sg:classifiers":[
        {
            "category":"Education",
            "subcategory":"Special Training",
            "type":"Public Place"
        }
    ],
    "sg:phone":"+1 859 881 8610",
    "sg:postcode":"40356",
    "sg:province":"KY",
    "sg:tags":[
        "instruction",
        "music"
    ],
    "wof:name":"Center For Education & Art Inc",
    "wof:placetype":"venue"
},
  "geometry": {"coordinates":[-84.587656,37.882585],"type":"Point"}
}