{
  "type": "Feature",
  "properties": {
    "iso:country":"US",
    "sg:address":"706 Main St",
    "sg:city":"Paris",
    "sg:classifiers":[
        {
            "category":"Personal",
            "subcategory":"Beauty Salon",
            "type":"Services"
        }
    ],
    "sg:phone":"+1 859 988 0566",
    "sg:postcode":"40361",
    "sg:province":"KY",
    "wof:name":"Eclips",
    "wof:placetype":"venue"
},
  "geometry": {"coordinates":[-84.25166400000001,38.210121],"type":"Point"}
}