{
  "type": "Feature",
  "properties": {
    "addr:full":"608 Cecil Way Lexington KY 40503",
    "addr:housenumber":"608",
    "addr:postcode":"40503",
    "addr:street":"Cecil Way",
    "iso:country":"US",
    "sg:address":"608 Cecil Way",
    "sg:city":"Lexington",
    "sg:classifiers":[
        {
            "category":"Social Services",
            "subcategory":"Child Care",
            "type":"Services"
        }
    ],
    "sg:phone":"+1 859 277 6859",
    "sg:postcode":"40503",
    "sg:province":"KY",
    "sg:tags":[
        "day"
    ],
    "wof:name":"Grannys House",
    "wof:placetype":"venue"
},
  "geometry": {"coordinates":[-84.544462,38.009663],"type":"Point"}
}