{
  "type": "Feature",
  "properties": {
    "iso:country":"US",
    "sg:address":"8430 Dixie Hwy",
    "sg:city":"Florence",
    "sg:classifiers":[
        {
            "category":"Food & Beverages",
            "subcategory":"Groceries & Convenience Stores",
            "type":"Retail Goods"
        }
    ],
    "sg:phone":"+1 859 824 4376",
    "sg:postcode":"41042",
    "sg:province":"KY",
    "sg:tags":[
        "grocer"
    ],
    "wof:name":"Bruce's Grocery",
    "wof:placetype":"venue"
},
  "geometry": {"coordinates":[-84.615938,38.967769],"type":"Point"}
}