{
  "type": "Feature",
  "properties": {
    "iso:country":"US",
    "sg:address":"1761 Coral Hill Rd",
    "sg:city":"Glasgow",
    "sg:phone":"+1 270 678 1445",
    "sg:postcode":"42141",
    "sg:province":"KY",
    "sg:tags":[
        "farm",
        "tobacco"
    ],
    "wof:name":"Billy Gray",
    "wof:placetype":"venue"
},
  "geometry": {"coordinates":[-85.86448300000001,37.03752],"type":"Point"}
}