{
  "type": "Feature",
  "properties": {
    "iso:country":"US",
    "sg:address":"170 W 5th St",
    "sg:city":"Elkhorn City",
    "sg:classifiers":[
        {
            "category":"Health Services",
            "subcategory":"Doctor",
            "type":"Services"
        }
    ],
    "sg:phone":"+1 606 754 7198",
    "sg:postcode":"41522",
    "sg:province":"KY",
    "sg:tags":[
        "dentist"
    ],
    "wof:name":"Rebecca Anderson Family Dntsry",
    "wof:placetype":"venue"
},
  "geometry": {"coordinates":[-82.348412,37.303009],"type":"Point"}
}