{
  "type": "Feature",
  "properties": {
    "iso:country":"US",
    "sg:address":"6470 N Preston Hwy",
    "sg:city":"Louisville",
    "sg:classifiers":[
        {
            "category":"Professional",
            "subcategory":"Employment Agencies",
            "type":"Services"
        },
        {
            "category":"Professional",
            "subcategory":"Business Services",
            "type":"Services"
        }
    ],
    "sg:phone":"+1 502 955 1485",
    "sg:postcode":"40229",
    "sg:province":"KY",
    "sg:tags":[
        "consultant",
        "coach",
        "opportunity",
        "contractor"
    ],
    "wof:name":"Malone Jc Associates",
    "wof:placetype":"venue"
},
  "geometry": {"coordinates":[-85.670146,38.072096],"type":"Point"}
}