{
  "type": "Feature",
  "properties": {
    "addr:full":"77 Coxes Bend Rd Greensburg KY 42743",
    "addr:housenumber":"77",
    "addr:postcode":"42743",
    "addr:street":"Coxes Bend Rd",
    "iso:country":"US",
    "sg:address":"77 Coxes Bend Rd",
    "sg:city":"Greensburg",
    "sg:classifiers":[
        {
            "category":"Shopping",
            "subcategory":"Gifts & Souvenirs",
            "type":"Retail Goods"
        }
    ],
    "sg:phone":"+1 270 299 2168",
    "sg:postcode":"42743",
    "sg:province":"KY",
    "sg:tags":[
        "shop"
    ],
    "wof:name":"Sugar Plum Cottage",
    "wof:placetype":"venue"
},
  "geometry": {"coordinates":[-85.452979,37.272843],"type":"Point"}
}