{
  "type": "Feature",
  "properties": {
    "iso:country":"US",
    "sg:address":"1647 Duntreath Dr",
    "sg:city":"Lexington",
    "sg:classifiers":[
        {
            "category":"Professional",
            "subcategory":"Accounting & Tax Preparation",
            "type":"Services"
        }
    ],
    "sg:phone":"+1 859 254 0586",
    "sg:postcode":"40504",
    "sg:province":"KY",
    "sg:tags":[
        "accountant"
    ],
    "wof:name":"On-Line Accounting Inc",
    "wof:placetype":"venue"
},
  "geometry": {"coordinates":[-84.537644,38.044216],"type":"Point"}
}