{
  "type": "Feature",
  "properties": {
    "addr:full":"2200 Conner Rd Hebron KY 41048",
    "addr:housenumber":"2200",
    "addr:postcode":"41048",
    "addr:street":"Conner Rd",
    "iso:country":"US",
    "sg:address":"2200 Conner Rd",
    "sg:city":"Hebron",
    "sg:classifiers":[
        {
            "category":"Health Services",
            "subcategory":"Doctor",
            "type":"Services"
        }
    ],
    "sg:phone":"+1 859 814 0010",
    "sg:postcode":"41048",
    "sg:province":"KY",
    "sg:website":"www.kdcmri.com",
    "wof:name":"Kentucky Diagnostic Center",
    "wof:placetype":"venue"
},
  "geometry": {"coordinates":[-84.702951,39.056911],"type":"Point"}
}