{
  "type": "Feature",
  "properties": {
    "iso:country":"US",
    "sg:address":"2160 Lawrenceburg Rd",
    "sg:city":"Bloomfield",
    "sg:classifiers":[
        {
            "category":"Shopping",
            "subcategory":"Computers & Home Electronics",
            "type":"Retail Goods"
        }
    ],
    "sg:phone":"+1 502 252 8822",
    "sg:postcode":"40008",
    "sg:province":"KY",
    "sg:tags":[
        "equipment",
        "dealer"
    ],
    "wof:name":"Holt Computers Inc",
    "wof:placetype":"venue"
},
  "geometry": {"coordinates":[-85.28139299999999,37.902703],"type":"Point"}
}