{
  "type": "Feature",
  "properties": {
    "iso:country":"US",
    "sg:address":"927 E Broadway",
    "sg:city":"Louisville",
    "sg:classifiers":[
        {
            "category":"Wholesale",
            "subcategory":"Sporting Goods",
            "type":"Manufacturing & Wholesale Goods"
        }
    ],
    "sg:phone":"+1 502 585 2396",
    "sg:postcode":"40204",
    "sg:province":"KY",
    "sg:tags":[
        "equipment",
        "billiard",
        "supply"
    ],
    "sg:website":"www.steepleton.com",
    "wof:name":"C C Steepleton Co",
    "wof:placetype":"venue"
},
  "geometry": {"coordinates":[-85.73605000000001,38.244506],"type":"Point"}
}