{
  "type": "Feature",
  "properties": {
    "iso:country":"US",
    "sg:address":"301 Reynolds Rd",
    "sg:city":"Glasgow",
    "sg:classifiers":[
        {
            "category":"Professional",
            "subcategory":"Advertising",
            "type":"Services"
        }
    ],
    "sg:phone":"+1 270 678 6895",
    "sg:postcode":"42141",
    "sg:province":"KY",
    "sg:tags":[
        "distribution"
    ],
    "wof:name":"Barren County Holdings Inc",
    "wof:placetype":"venue"
},
  "geometry": {"coordinates":[-85.931971,37.013347],"type":"Point"}
}