{
  "type": "Feature",
  "properties": {
    "iso:country":"US",
    "sg:address":"3190 Irvine Rd",
    "sg:city":"Richmond",
    "sg:classifiers":[
        {
            "category":"Health Services",
            "subcategory":"Doctor",
            "type":"Services"
        }
    ],
    "sg:phone":"+1 859 369 0070",
    "sg:postcode":"40475",
    "sg:province":"KY",
    "sg:tags":[
        "physician",
        "surgeon"
    ],
    "wof:name":"Family Clinic",
    "wof:placetype":"venue"
},
  "geometry": {"coordinates":[-84.152315,37.741857],"type":"Point"}
}