{
  "type": "Feature",
  "properties": {
    "iso:country":"US",
    "sg:address":"1539 Knight Rd",
    "sg:city":"Wickliffe",
    "sg:classifiers":[
        {
            "category":"Wholesale",
            "subcategory":"Non-durable Goods",
            "type":"Manufacturing & Wholesale Goods"
        },
        {
            "category":"Professional",
            "subcategory":"Advertising",
            "type":"Services"
        }
    ],
    "sg:phone":"+1 270 876 8000",
    "sg:postcode":"42087",
    "sg:province":"KY",
    "wof:name":"Pro-Image Promotions",
    "wof:placetype":"venue"
},
  "geometry": {"coordinates":[-88.957556,37.01271],"type":"Point"}
}