{
  "type": "Feature",
  "properties": {
    "iso:country":"US",
    "sg:address":"1818 Millers Ln",
    "sg:city":"Louisville",
    "sg:classifiers":[
        {
            "category":"Professional",
            "subcategory":"Detective & Security Services",
            "type":"Services"
        }
    ],
    "sg:phone":"+1 502 778 0222",
    "sg:postcode":"40216",
    "sg:province":"KY",
    "sg:tags":[
        "guard",
        "patrol"
    ],
    "wof:name":"Commonwealth Security Inc",
    "wof:placetype":"venue"
},
  "geometry": {"coordinates":[-85.79876299999999,38.214838],"type":"Point"}
}