{
  "type": "Feature",
  "properties": {
    "iso:country":"US",
    "sg:address":"6001 Benton Rd",
    "sg:city":"Paducah",
    "sg:classifiers":[
        {
            "category":"Home & Garden",
            "subcategory":"Home Furnishings",
            "type":"Retail Goods"
        }
    ],
    "sg:phone":"+1 270 898 7888",
    "sg:postcode":"42003",
    "sg:province":"KY",
    "sg:tags":[
        "fireplace"
    ],
    "wof:name":"Hearth & Home Of Kentucky Inc",
    "wof:placetype":"venue"
},
  "geometry": {"coordinates":[-88.53045899999999,37.005292],"type":"Point"}
}