{
  "type": "Feature",
  "properties": {
    "addr:full":"830 S Buntin Rd Hopkinsville KY 42240",
    "addr:housenumber":"830",
    "addr:postcode":"42240",
    "addr:street":"S Buntin Rd",
    "iso:country":"US",
    "sg:address":"830 S Buntin Rd",
    "sg:city":"Hopkinsville",
    "sg:classifiers":[
        {
            "category":"Retail",
            "subcategory":"Repair Shop",
            "type":"Services"
        }
    ],
    "sg:phone":"+1 270 889 0300",
    "sg:postcode":"42240",
    "sg:province":"KY",
    "sg:tags":[
        "equipment",
        "telephone",
        "system"
    ],
    "wof:name":"Pennyrile Custom Electronics",
    "wof:placetype":"venue"
},
  "geometry": {"coordinates":[-87.486439,36.953629],"type":"Point"}
}