{
  "type": "Feature",
  "properties": {
    "addr:full":"751 Comanche Dr Henderson KY 42420",
    "addr:housenumber":"751",
    "addr:postcode":"42420",
    "addr:street":"Comanche Dr",
    "iso:country":"US",
    "sg:address":"751 Comanche Dr",
    "sg:city":"Henderson",
    "sg:classifiers":[
        {
            "category":"Building & Trades",
            "subcategory":"Landscaping Services",
            "type":"Services"
        }
    ],
    "sg:phone":"+1 270 831 2691",
    "sg:postcode":"42420",
    "sg:province":"KY",
    "sg:tags":[
        "landscape",
        "contractor"
    ],
    "wof:name":"H & B Lawncare Landscaping",
    "wof:placetype":"venue"
},
  "geometry": {"coordinates":[-87.570447,37.864186],"type":"Point"}
}