{
  "type": "Feature",
  "properties": {
    "addr:full":"1410 Elmhurst Way Bowling Green KY 42104",
    "addr:housenumber":"1410",
    "addr:postcode":"42104",
    "addr:street":"Elmhurst Way",
    "iso:country":"US",
    "sg:address":"1410 Elmhurst Way",
    "sg:city":"Bowling Green",
    "sg:classifiers":[
        {
            "category":"Retail",
            "subcategory":"Auto Rental",
            "type":"Services"
        }
    ],
    "sg:phone":"+1 270 782 2444",
    "sg:postcode":"42104",
    "sg:province":"KY",
    "sg:tags":[
        "renting",
        "leasing",
        "trailer"
    ],
    "wof:name":"Acorn Storage Trailers & Cntnr",
    "wof:placetype":"venue"
},
  "geometry": {"coordinates":[-86.450076,36.935632],"type":"Point"}
}