{
  "type": "Feature",
  "properties": {
    "iso:country":"US",
    "sg:address":"4843 Dixie Hwy",
    "sg:city":"Louisville",
    "sg:classifiers":[
        {
            "category":"Banks & Credit Unions",
            "subcategory":"Bank",
            "type":"Services"
        }
    ],
    "sg:phone":"+1 502 448 3202",
    "sg:postcode":"40216",
    "sg:province":"KY",
    "sg:tags":[
        "depository",
        "banking"
    ],
    "wof:name":"All Checks Cashed",
    "wof:placetype":"venue"
},
  "geometry": {"coordinates":[-85.82667499999999,38.170746],"type":"Point"}
}