{
  "type": "Feature",
  "properties": {
    "iso:country":"US",
    "sg:address":"5531 Parkers Mill Rd",
    "sg:city":"Lexington",
    "sg:classifiers":[
        {
            "category":"Recreation",
            "type":"Entertainment"
        }
    ],
    "sg:phone":"+1 859 255 3422",
    "sg:postcode":"40513",
    "sg:province":"KY",
    "sg:tags":[
        "riding",
        "academy"
    ],
    "wof:name":"Robert Murphy Stables Inc",
    "wof:placetype":"venue"
},
  "geometry": {"coordinates":[-84.63703099999999,38.034834],"type":"Point"}
}