{
  "type": "Feature",
  "properties": {
    "iso:country":"US",
    "sg:address":"355 Black Rock Rd",
    "sg:city":"Leitchfield",
    "sg:classifiers":[
        {
            "category":"Real Estate",
            "subcategory":"Developer",
            "type":"Services"
        }
    ],
    "sg:phone":"+1 270 259 6531",
    "sg:postcode":"42754",
    "sg:province":"KY",
    "sg:tags":[
        "cemetery"
    ],
    "wof:name":"Kefauver Cemetery Assoc Inc",
    "wof:placetype":"venue"
},
  "geometry": {"coordinates":[-86.355248,37.453844],"type":"Point"}
}