{
  "type": "Feature",
  "properties": {
    "iso:country":"US",
    "sg:address":"6102 State Hwy 923",
    "sg:city":"Sturgis",
    "sg:classifiers":[
        {
            "category":"Organizations",
            "subcategory":"Religious Organization",
            "type":"Services"
        }
    ],
    "sg:phone":"+1 270 333 6907",
    "sg:postcode":"42459",
    "sg:province":"KY",
    "wof:name":"New Hope Genl Baptist Chu",
    "wof:placetype":"venue"
},
  "geometry": {"coordinates":[-88.016115,37.548274],"type":"Point"}
}