{
  "type": "Feature",
  "properties": {
    "iso:country":"US",
    "sg:address":"3580 S Hurstbourne Pkwy",
    "sg:city":"Louisville",
    "sg:classifiers":[
        {
            "category":"Retail",
            "subcategory":"Veterinary Services",
            "type":"Services"
        }
    ],
    "sg:phone":"+1 502 491 0036",
    "sg:postcode":"40299",
    "sg:province":"KY",
    "sg:tags":[
        "clinic",
        "hospital"
    ],
    "sg:website":"http://www.banfield.net",
    "wof:name":"Banfield, The Pet Hospital",
    "wof:placetype":"venue"
},
  "geometry": {"coordinates":[-85.603848,38.195909],"type":"Point"}
}