{
  "type": "Feature",
  "properties": {
    "iso:country":"US",
    "sg:address":"504 Rudd St",
    "sg:city":"Smithland",
    "sg:classifiers":[
        {
            "category":"Real Estate",
            "subcategory":"Real Estate Operator",
            "type":"Services"
        }
    ],
    "sg:phone":"+1 270 928 4278",
    "sg:postcode":"42081",
    "sg:province":"KY",
    "sg:tags":[
        "apartment"
    ],
    "wof:name":"Cumberland Views Apartments",
    "wof:placetype":"venue"
},
  "geometry": {"coordinates":[-88.39760800000001,37.14192],"type":"Point"}
}