{
  "type": "Feature",
  "properties": {
    "addr:full":"132 E Main St Carlisle KY 40311",
    "addr:housenumber":"132",
    "addr:postcode":"40311",
    "addr:street":"E Main St",
    "iso:country":"US",
    "sg:address":"132 E Main St",
    "sg:city":"Carlisle",
    "sg:classifiers":[
        {
            "category":"Shopping",
            "subcategory":"Used Merchandise",
            "type":"Retail Goods"
        }
    ],
    "sg:phone":"+1 859 289 3561",
    "sg:postcode":"40311",
    "sg:province":"KY",
    "sg:tags":[
        "antique"
    ],
    "wof:name":"Carlisle Antique",
    "wof:placetype":"venue"
},
  "geometry": {"coordinates":[-84.028493,38.312232],"type":"Point"}
}