{
  "type": "Feature",
  "properties": {
    "iso:country":"US",
    "sg:address":"345 Monticello St",
    "sg:city":"Somerset",
    "sg:classifiers":[
        {
            "category":"Professional",
            "subcategory":"Lawyer & Legal Services",
            "type":"Services"
        }
    ],
    "sg:phone":"+1 606 679 8488",
    "sg:postcode":"42501",
    "sg:province":"KY",
    "sg:tags":[
        "attorney"
    ],
    "wof:name":"Dean Stewart Law Offices",
    "wof:placetype":"venue"
},
  "geometry": {"coordinates":[-84.61326699999999,37.078043],"type":"Point"}
}