{
  "type": "Feature",
  "properties": {
    "addr:full":"2010 Plantside Dr Louisville KY 40299",
    "addr:housenumber":"2010",
    "addr:postcode":"40299",
    "addr:street":"Plantside Dr",
    "iso:country":"US",
    "sg:address":"2010 Plantside Dr",
    "sg:city":"Louisville",
    "sg:classifiers":[
        {
            "category":"Building & Trades",
            "subcategory":"Construction",
            "type":"Services"
        }
    ],
    "sg:phone":"+1 502 499 4044",
    "sg:postcode":"40299",
    "sg:province":"KY",
    "sg:tags":[
        "equipment",
        "supply",
        "drywall",
        "contractor"
    ],
    "sg:website":"http://www.grayhawk.net",
    "wof:name":"Grayhawk Corp",
    "wof:placetype":"venue"
},
  "geometry": {"coordinates":[-85.571496,38.215364],"type":"Point"}
}