{
  "type": "Feature",
  "properties": {
    "iso:country":"US",
    "sg:address":"415 Dixie Hwy E",
    "sg:city":"Elizabethtown",
    "sg:classifiers":[
        {
            "category":"Shopping",
            "subcategory":"Tobacco",
            "type":"Retail Goods"
        }
    ],
    "sg:phone":"+1 270 737 4183",
    "sg:postcode":"42701",
    "sg:province":"KY",
    "sg:tags":[
        "cigarette",
        "cigar",
        "dealer"
    ],
    "wof:name":"Bo's",
    "wof:placetype":"venue"
},
  "geometry": {"coordinates":[-85.854225,37.689082],"type":"Point"}
}