{
  "type": "Feature",
  "properties": {
    "addr:full":"100 Tiffany Ct Richmond KY 40475",
    "addr:housenumber":"100",
    "addr:postcode":"40475",
    "addr:street":"Tiffany Ct",
    "iso:country":"US",
    "sg:address":"100 Tiffany Ct",
    "sg:city":"Richmond",
    "sg:classifiers":[
        {
            "category":"Building & Trades",
            "subcategory":"Construction",
            "type":"Services"
        }
    ],
    "sg:phone":"+1 859 527 9986",
    "sg:postcode":"40475",
    "sg:province":"KY",
    "sg:tags":[
        "house"
    ],
    "wof:name":"Daff Builders",
    "wof:placetype":"venue"
},
  "geometry": {"coordinates":[-84.29833499999999,37.890547],"type":"Point"}
}