{
  "type": "Feature",
  "properties": {
    "iso:country":"US",
    "sg:address":"1987 S Hurstbourne Pkwy",
    "sg:city":"Louisville",
    "sg:classifiers":[
        {
            "category":"Shopping",
            "subcategory":"Jewelry",
            "type":"Retail Goods"
        }
    ],
    "sg:phone":"+1 502 499 2215",
    "sg:postcode":"40220",
    "sg:province":"KY",
    "sg:tags":[
        "jeweler"
    ],
    "wof:name":"Friedman's",
    "wof:placetype":"venue"
},
  "geometry": {"coordinates":[-85.586687,38.217581],"type":"Point"}
}