{
  "type": "Feature",
  "properties": {
    "iso:country":"US",
    "sg:address":"409 N Miles St",
    "sg:city":"Elizabethtown",
    "sg:classifiers":[
        {
            "category":"Government",
            "subcategory":"Office",
            "type":"Public Place"
        }
    ],
    "sg:phone":"+1 270 766 5121",
    "sg:postcode":"42701",
    "sg:province":"KY",
    "sg:tags":[
        "state",
        "program"
    ],
    "wof:name":"Vocational Rehabilitation Dept",
    "wof:placetype":"venue"
},
  "geometry": {"coordinates":[-85.85834,37.700908],"type":"Point"}
}