{
  "type": "Feature",
  "properties": {
    "addr:full":"2039 Old Nassau Rd Lexington KY 40504",
    "addr:housenumber":"2039",
    "addr:postcode":"40504",
    "addr:street":"Old Nassau Rd",
    "iso:country":"US",
    "sg:address":"2039 Old Nassau Rd",
    "sg:city":"Lexington",
    "sg:classifiers":[
        {
            "category":"Food & Beverages",
            "subcategory":"Specialty",
            "type":"Retail Goods"
        }
    ],
    "sg:phone":"+1 859 277 6705",
    "sg:postcode":"40504",
    "sg:province":"KY",
    "sg:tags":[
        "merchandise"
    ],
    "wof:name":"Shaklee Distributor",
    "wof:placetype":"venue"
},
  "geometry": {"coordinates":[-84.55976699999999,38.03073],"type":"Point"}
}