{
  "type": "Feature",
  "properties": {
    "iso:country":"US",
    "sg:address":"45 Station Rd",
    "sg:city":"Harlan",
    "sg:classifiers":[
        {
            "category":"Real Estate",
            "subcategory":"Real Estate Operator",
            "type":"Services"
        }
    ],
    "sg:phone":"+1 606 837 2089",
    "sg:postcode":"40806",
    "sg:province":"KY",
    "sg:tags":[
        "building",
        "apartment"
    ],
    "wof:name":"Eastbrook Station Apts",
    "wof:placetype":"venue"
},
  "geometry": {"coordinates":[-83.20473699999999,36.912845],"type":"Point"}
}