{
  "type": "Feature",
  "properties": {
    "addr:full":"2222 Alta Ave Louisville KY 40205",
    "addr:housenumber":"2222",
    "addr:postcode":"40205",
    "addr:street":"Alta Ave",
    "iso:country":"US",
    "sg:address":"2222 Alta Ave",
    "sg:city":"Louisville",
    "sg:classifiers":[
        {
            "category":"Manufacturing",
            "subcategory":"Printing",
            "type":"Manufacturing & Wholesale Goods"
        },
        {
            "category":"Professional",
            "subcategory":"Advertising",
            "type":"Services"
        },
        {
            "category":"Professional",
            "type":"Services"
        },
        {
            "category":"Wholesale",
            "subcategory":"Books, Periodicals, & Newspapers",
            "type":"Manufacturing & Wholesale Goods"
        }
    ],
    "sg:phone":"+1 502 456 4568",
    "sg:postcode":"40205",
    "sg:province":"KY",
    "sg:tags":[
        "publisher",
        "publication",
        "publishers-directory",
        "book",
        "editorial",
        "directory",
        "guide"
    ],
    "wof:name":"Stacy Publishing Company, Inc",
    "wof:placetype":"venue"
},
  "geometry": {"coordinates":[-85.70072999999999,38.234682],"type":"Point"}
}