{
  "type": "Feature",
  "properties": {
    "iso:country":"US",
    "sg:address":"4244 Darbrook Rd",
    "sg:city":"Louisville",
    "sg:classifiers":[
        {
            "category":"Professional",
            "subcategory":"Accounting & Tax Preparation",
            "type":"Services"
        }
    ],
    "sg:phone":"+1 502 893 9967",
    "sg:postcode":"40207",
    "sg:province":"KY",
    "sg:tags":[
        "accountant"
    ],
    "wof:name":"David B Hicks Pllc",
    "wof:placetype":"venue"
},
  "geometry": {"coordinates":[-85.634173,38.259294],"type":"Point"}
}