{
  "type": "Feature",
  "properties": {
    "addr:full":"1241 Us Highway 127 S Frankfort KY 40601",
    "addr:housenumber":"1241",
    "addr:postcode":"40601",
    "addr:street":"Us Highway 127 S",
    "iso:country":"US",
    "sg:address":"1241 Us Highway 127 S",
    "sg:city":"Frankfort",
    "sg:classifiers":[
        {
            "category":"Restaurant",
            "type":"Food & Drink"
        }
    ],
    "sg:menulink":"http://www.allmenus.com/ky/frankfort/79671-pizza-hut/menu/",
    "sg:phone":"+1 502 875 5405",
    "sg:postcode":"40601",
    "sg:province":"KY",
    "sg:tags":[
        "american",
        "pizza"
    ],
    "wof:name":"Pizza Hut",
    "wof:placetype":"venue"
},
  "geometry": {"coordinates":[-84.89838,38.172275],"type":"Point"}
}