{
  "type": "Feature",
  "properties": {
    "addr:full":"3348 Hikes Ln Louisville KY 40220",
    "addr:housenumber":"3348",
    "addr:postcode":"40220",
    "addr:street":"Hikes Ln",
    "iso:country":"US",
    "sg:address":"3348 Hikes Ln",
    "sg:city":"Louisville",
    "sg:classifiers":[
        {
            "category":"Restaurant",
            "type":"Food & Drink"
        }
    ],
    "sg:menulink":"http://www.allmenus.com/ky/jefferson-southeast/151653-aw-restaurant/menu/",
    "sg:phone":"+1 502 458 1153",
    "sg:postcode":"40220",
    "sg:province":"KY",
    "sg:tags":[
        "burger",
        "american",
        "dog",
        "pub",
        "hot"
    ],
    "wof:name":"A&W Restaurant",
    "wof:placetype":"venue"
},
  "geometry": {"coordinates":[-85.628181,38.218349],"type":"Point"}
}