{
  "type": "Feature",
  "properties": {
    "iso:country":"US",
    "sg:address":"10004 Cardigan Dr",
    "sg:city":"Louisville",
    "sg:classifiers":[
        {
            "category":"Building & Trades",
            "subcategory":"Cleaning & Sanitation",
            "type":"Services"
        }
    ],
    "sg:phone":"+1 502 267 7165",
    "sg:postcode":"40299",
    "sg:province":"KY",
    "sg:tags":[
        "maintenance"
    ],
    "wof:name":"Beckys Cleaning Service",
    "wof:placetype":"venue"
},
  "geometry": {"coordinates":[-85.570526,38.207033],"type":"Point"}
}