{
  "type": "Feature",
  "properties": {
    "addr:full":"926 N Main St London KY 40741",
    "addr:housenumber":"926",
    "addr:postcode":"40741",
    "addr:street":"N Main St",
    "iso:country":"US",
    "sg:address":"926 N Main St",
    "sg:city":"London",
    "sg:classifiers":[
        {
            "category":"Shopping",
            "subcategory":"Jewelry",
            "type":"Retail Goods"
        }
    ],
    "sg:phone":"+1 606 864 3259",
    "sg:postcode":"40741",
    "sg:province":"KY",
    "sg:tags":[
        "jeweler"
    ],
    "wof:name":"London Jewelry Express",
    "wof:placetype":"venue"
},
  "geometry": {"coordinates":[-84.08964400000001,37.133336],"type":"Point"}
}