{
  "type": "Feature",
  "properties": {
    "iso:country":"US",
    "sg:address":"1919 Emory Ct",
    "sg:city":"Hebron",
    "sg:classifiers":[
        {
            "category":"Manufacturing",
            "subcategory":"Wood Products",
            "type":"Manufacturing & Wholesale Goods"
        }
    ],
    "sg:phone":"+1 859 866 3167",
    "sg:postcode":"41048",
    "sg:province":"KY",
    "sg:tags":[
        "firewood"
    ],
    "wof:name":"Hebron Firewood",
    "wof:placetype":"venue"
},
  "geometry": {"coordinates":[-84.74612999999999,39.114672],"type":"Point"}
}