{
  "type": "Feature",
  "properties": {
    "addr:full":"130 N College St Harrodsburg KY 40330",
    "addr:housenumber":"130",
    "addr:postcode":"40330",
    "addr:street":"N College St",
    "iso:country":"US",
    "sg:address":"130 N College St",
    "sg:city":"Harrodsburg",
    "sg:classifiers":[
        {
            "category":"Social Services",
            "type":"Services"
        }
    ],
    "sg:phone":"+1 859 236 0359",
    "sg:postcode":"40330",
    "sg:province":"KY",
    "sg:tags":[
        "organization",
        "welfare"
    ],
    "wof:name":"YMCA",
    "wof:placetype":"venue"
},
  "geometry": {"coordinates":[-84.84566,37.763091],"type":"Point"}
}