{
  "type": "Feature",
  "properties": {
    "addr:full":"1468 Dixie Hwy N Radcliff KY 40160",
    "addr:housenumber":"1468",
    "addr:postcode":"40160",
    "addr:street":"Dixie Hwy N",
    "iso:country":"US",
    "sg:address":"1468 Dixie Hwy N",
    "sg:city":"Radcliff",
    "sg:classifiers":[
        {
            "category":"Retail",
            "subcategory":"Auto Repair",
            "type":"Services"
        }
    ],
    "sg:phone":"+1 270 351 3637",
    "sg:postcode":"40160",
    "sg:province":"KY",
    "sg:tags":[
        "body",
        "automobile",
        "painting"
    ],
    "sg:website":"www.jackhartbodyshop.com",
    "wof:name":"Jack Hart Body Shop Inc",
    "wof:placetype":"venue"
},
  "geometry": {"coordinates":[-85.953548,37.857063],"type":"Point"}
}