{
  "type": "Feature",
  "properties": {
    "iso:country":"US",
    "sg:address":"4594 Oliver Rd",
    "sg:city":"Independence",
    "sg:classifiers":[
        {
            "category":"Social Services",
            "type":"Services"
        }
    ],
    "sg:phone":"+1 859 363 0100",
    "sg:postcode":"41051",
    "sg:province":"KY",
    "sg:tags":[
        "youth",
        "organization",
        "center"
    ],
    "wof:name":"Community Youth Homes Of N Ky",
    "wof:placetype":"venue"
},
  "geometry": {"coordinates":[-84.530908,38.945068],"type":"Point"}
}