{
  "type": "Feature",
  "properties": {
    "addr:full":"284 Moores Ferry Rd Salt Lick KY 40371",
    "addr:housenumber":"284",
    "addr:postcode":"40371",
    "addr:street":"Moores Ferry Rd",
    "iso:country":"US",
    "sg:address":"284 Moores Ferry Rd",
    "sg:city":"Salt Lick",
    "sg:classifiers":[
        {
            "category":"Building & Trades",
            "subcategory":"Construction",
            "type":"Services"
        }
    ],
    "sg:phone":"+1 606 683 6004",
    "sg:postcode":"40371",
    "sg:province":"KY",
    "sg:tags":[
        "general",
        "contractor"
    ],
    "wof:name":"Staton's Construction Co Inc",
    "wof:placetype":"venue"
},
  "geometry": {"coordinates":[-83.62795199999999,38.131778],"type":"Point"}
}