{
  "type": "Feature",
  "properties": {
    "iso:country":"US",
    "sg:address":"3303 Dixie Hwy",
    "sg:city":"Erlanger",
    "sg:classifiers":[
        {
            "category":"Retail",
            "subcategory":"Auto Repair",
            "type":"Services"
        }
    ],
    "sg:phone":"+1 859 727 8500",
    "sg:postcode":"41018",
    "sg:province":"KY",
    "sg:tags":[
        "muffler",
        "exhaust",
        "system"
    ],
    "wof:name":"Blackjack Auto & Truck Acces",
    "wof:placetype":"venue"
},
  "geometry": {"coordinates":[-84.598056,39.017706],"type":"Point"}
}