{
  "type": "Feature",
  "properties": {
    "addr:full":"3090 Richmond Rd Lexington KY 40509",
    "addr:housenumber":"3090",
    "addr:postcode":"40509",
    "addr:street":"Richmond Rd",
    "iso:country":"US",
    "sg:address":"3090 Richmond Rd",
    "sg:city":"Lexington",
    "sg:classifiers":[
        {
            "category":"Retail",
            "subcategory":"Laundry & Dry Cleaning",
            "type":"Services"
        }
    ],
    "sg:phone":"+1 859 268 9557",
    "sg:postcode":"40509",
    "sg:province":"KY",
    "sg:tags":[
        "cleaners"
    ],
    "wof:name":"Hart's Laundry & Dry Cleaning",
    "wof:placetype":"venue"
},
  "geometry": {"coordinates":[-84.449241,38.004449],"type":"Point"}
}