{
  "type": "Feature",
  "properties": {
    "iso:country":"US",
    "sg:address":"1474 Anniston Dr",
    "sg:city":"Lexington",
    "sg:classifiers":[
        {
            "category":"Personal",
            "type":"Services"
        }
    ],
    "sg:phone":"+1 859 293 6582",
    "sg:postcode":"40505",
    "sg:province":"KY",
    "sg:tags":[
        "wedding",
        "chapel"
    ],
    "wof:name":"Tie The Knot Wedding Chapel",
    "wof:placetype":"venue"
},
  "geometry": {"coordinates":[-84.43795,38.057787],"type":"Point"}
}