{
  "type": "Feature",
  "properties": {
    "iso:country":"US",
    "sg:address":"143 E Main St",
    "sg:city":"Georgetown",
    "sg:classifiers":[
        {
            "category":"Government",
            "subcategory":"Office",
            "type":"Public Place"
        }
    ],
    "sg:phone":"+1 502 863 0565",
    "sg:postcode":"40324",
    "sg:province":"KY",
    "sg:tags":[
        "state",
        "resource"
    ],
    "wof:name":"Social Service Dept",
    "wof:placetype":"venue"
},
  "geometry": {"coordinates":[-84.558628,38.209959],"type":"Point"}
}