{
  "type": "Feature",
  "properties": {
    "addr:full":"608 Richmond Rd N Berea KY 40403",
    "addr:housenumber":"608",
    "addr:postcode":"40403",
    "addr:street":"Richmond Rd N",
    "iso:country":"US",
    "sg:address":"608 Richmond Rd N",
    "sg:city":"Berea",
    "sg:classifiers":[
        {
            "category":"Shopping",
            "subcategory":"Computers & Home Electronics",
            "type":"Retail Goods"
        }
    ],
    "sg:phone":"+1 859 986 0045",
    "sg:postcode":"40403",
    "sg:province":"KY",
    "sg:tags":[
        "equipment",
        "satellite",
        "system"
    ],
    "wof:name":"Full Circle Satellite",
    "wof:placetype":"venue"
},
  "geometry": {"coordinates":[-84.28339200000001,37.594761],"type":"Point"}
}