{
  "type": "Feature",
  "properties": {
    "addr:full":"49 John Ct Elizabethtown KY 42701",
    "addr:housenumber":"49",
    "addr:postcode":"42701",
    "addr:street":"John Ct",
    "iso:country":"US",
    "sg:address":"49 John Ct",
    "sg:city":"Elizabethtown",
    "sg:classifiers":[
        {
            "category":"Food & Beverages",
            "subcategory":"Specialty",
            "type":"Retail Goods"
        }
    ],
    "sg:phone":"+1 270 737 8979",
    "sg:postcode":"42701",
    "sg:province":"KY",
    "sg:tags":[
        "vitamin"
    ],
    "wof:name":"Shaklee Distributor",
    "wof:placetype":"venue"
},
  "geometry": {"coordinates":[-85.819698,37.722452],"type":"Point"}
}