{
  "type": "Feature",
  "properties": {
    "iso:country":"US",
    "sg:address":"3101 Clays Mill Rd",
    "sg:city":"Lexington",
    "sg:classifiers":[
        {
            "category":"Banks & Credit Unions",
            "subcategory":"Investment Brokerage",
            "type":"Services"
        }
    ],
    "sg:phone":"+1 859 219 0228",
    "sg:postcode":"40503",
    "sg:province":"KY",
    "sg:tags":[
        "advisory",
        "financial"
    ],
    "wof:name":"Integra Bank",
    "wof:placetype":"venue"
},
  "geometry": {"coordinates":[-84.54590399999999,38.001186],"type":"Point"}
}