{
  "type": "Feature",
  "properties": {
    "iso:country":"US",
    "sg:address":"3919 Chenoweth Sq",
    "sg:city":"Louisville",
    "sg:classifiers":[
        {
            "category":"Shopping",
            "subcategory":"Gifts & Souvenirs",
            "type":"Retail Goods"
        }
    ],
    "sg:phone":"+1 502 721 9282",
    "sg:postcode":"40207",
    "sg:province":"KY",
    "sg:tags":[
        "shop"
    ],
    "wof:name":"Watermark Gallery",
    "wof:placetype":"venue"
},
  "geometry": {"coordinates":[-85.65313,38.255812],"type":"Point"}
}