{
  "type": "Feature",
  "properties": {
    "addr:full":"6000 US Hwy 27 Somerset KY 42501",
    "addr:housenumber":"6000",
    "addr:postcode":"42501",
    "addr:street":"Us Hwy 27",
    "iso:country":"US",
    "sg:address":"6000 US Hwy 27",
    "sg:city":"Somerset",
    "sg:classifiers":[
        {
            "category":"Banks & Credit Unions",
            "subcategory":"Bank",
            "type":"Services"
        }
    ],
    "sg:phone":"+1 606 561 5352",
    "sg:postcode":"42501",
    "sg:province":"KY",
    "wof:name":"Citizens National Bank",
    "wof:placetype":"venue"
},
  "geometry": {"coordinates":[-84.627689,37.016138],"type":"Point"}
}