{
  "type": "Feature",
  "properties": {
    "iso:country":"US",
    "sg:address":"125 Harp Innis Rd",
    "sg:city":"Lexington",
    "sg:classifiers":[
        {
            "category":"Wholesale",
            "subcategory":"Farm Supplies",
            "type":"Manufacturing & Wholesale Goods"
        }
    ],
    "sg:phone":"+1 859 294 6437",
    "sg:postcode":"40511",
    "sg:province":"KY",
    "sg:tags":[
        "raw",
        "product",
        "material"
    ],
    "wof:name":"Mill Creek Farm",
    "wof:placetype":"venue"
},
  "geometry": {"coordinates":[-84.370565,38.147347],"type":"Point"}
}