{
  "type": "Feature",
  "properties": {
    "addr:full":"101 Keller St Cumberland KY 40823",
    "addr:housenumber":"101",
    "addr:postcode":"40823",
    "addr:street":"Keller St",
    "iso:country":"US",
    "sg:address":"101 Keller St",
    "sg:city":"Cumberland",
    "sg:classifiers":[
        {
            "category":"Communications",
            "subcategory":"Radio Station",
            "type":"Services"
        }
    ],
    "sg:phone":"+1 606 589 4623",
    "sg:postcode":"40823",
    "sg:province":"KY",
    "sg:tags":[
        "company",
        "broadcasting"
    ],
    "wof:name":"WCPM",
    "wof:placetype":"venue"
},
  "geometry": {"coordinates":[-82.98956699999999,36.975229],"type":"Point"}
}