{
  "type": "Feature",
  "properties": {
    "addr:full":"500 Armory Pl Louisville KY 40202",
    "addr:housenumber":"500",
    "addr:postcode":"40202",
    "addr:street":"Armory Pl",
    "iso:country":"US",
    "sg:address":"500 Armory Pl",
    "sg:city":"Louisville",
    "sg:classifiers":[
        {
            "category":"Arena",
            "subcategory":"Sports Club",
            "type":"Entertainment"
        }
    ],
    "sg:phone":"+1 502 333 7328",
    "sg:postcode":"40202",
    "sg:province":"KY",
    "sg:tags":[
        "ticket",
        "sale"
    ],
    "wof:name":"333seat Co",
    "wof:placetype":"venue"
},
  "geometry": {"coordinates":[-85.75988,38.251381],"type":"Point"}
}