{
  "type": "Feature",
  "properties": {
    "addr:full":"151 N Martin Luther King Blvd Lexington KY 40507",
    "addr:housenumber":"151",
    "addr:postcode":"40507",
    "addr:street":"N Martin Luther King Blvd",
    "iso:country":"US",
    "sg:address":"151 N Martin Luther King Blvd",
    "sg:city":"Lexington",
    "sg:classifiers":[
        {
            "category":"Personal",
            "type":"Services"
        }
    ],
    "sg:phone":"+1 859 233 9749",
    "sg:postcode":"40507",
    "sg:province":"KY",
    "sg:tags":[
        "dating"
    ],
    "wof:name":"Private Lines Management",
    "wof:placetype":"venue"
},
  "geometry": {"coordinates":[-84.494508,38.045474],"type":"Point"}
}