{
  "type": "Feature",
  "properties": {
    "iso:country":"US",
    "sg:address":"2601 Nicholasville Rd",
    "sg:city":"Lexington",
    "sg:classifiers":[
        {
            "category":"Professional",
            "subcategory":"Advertising",
            "type":"Services"
        }
    ],
    "sg:phone":"+1 859 280 9898",
    "sg:postcode":"40503",
    "sg:province":"KY",
    "wof:name":"WBUL",
    "wof:placetype":"venue"
},
  "geometry": {"coordinates":[-84.521226,37.998739],"type":"Point"}
}