{
  "type": "Feature",
  "properties": {
    "iso:country":"US",
    "sg:address":"400 Blue Sky Pkwy",
    "sg:city":"Lexington",
    "sg:classifiers":[
        {
            "category":"Building & Trades",
            "subcategory":"Construction",
            "type":"Services"
        }
    ],
    "sg:phone":"+1 859 543 2280",
    "sg:postcode":"40509",
    "sg:province":"KY",
    "sg:tags":[
        "excavating",
        "contractor"
    ],
    "wof:name":"Jessamine Backhoe",
    "wof:placetype":"venue"
},
  "geometry": {"coordinates":[-84.377976,37.963333],"type":"Point"}
}