{
  "type": "Feature",
  "properties": {
    "iso:country":"US",
    "sg:address":"504 Happy Ridge Rd",
    "sg:city":"Brandenburg",
    "sg:classifiers":[
        {
            "category":"Professional",
            "type":"Services"
        }
    ],
    "sg:phone":"+1 270 422 4642",
    "sg:postcode":"40108",
    "sg:province":"KY",
    "sg:tags":[
        "establishment"
    ],
    "wof:name":"Communicare Residence",
    "wof:placetype":"venue"
},
  "geometry": {"coordinates":[-86.16766699999999,37.992303],"type":"Point"}
}