{
  "type": "Feature",
  "properties": {
    "iso:country":"US",
    "sg:address":"115 Grab Rd",
    "sg:city":"Greensburg",
    "sg:classifiers":[
        {
            "category":"Manufacturing",
            "subcategory":"Furniture",
            "type":"Manufacturing & Wholesale Goods"
        }
    ],
    "sg:phone":"+1 270 932 6010",
    "sg:postcode":"42743",
    "sg:province":"KY",
    "wof:name":"Royal Oak Furniture",
    "wof:placetype":"venue"
},
  "geometry": {"coordinates":[-85.59135499999999,37.222427],"type":"Point"}
}