{
  "type": "Feature",
  "properties": {
    "addr:full":"1505 S 7th St Louisville KY 40208",
    "addr:housenumber":"1505",
    "addr:postcode":"40208",
    "addr:street":"S 7Th St",
    "iso:country":"US",
    "sg:address":"1505 S 7th St",
    "sg:city":"Louisville",
    "sg:classifiers":[
        {
            "category":"Health Services",
            "subcategory":"Medical Lab",
            "type":"Services"
        }
    ],
    "sg:phone":"+1 502 636 3665",
    "sg:postcode":"40208",
    "sg:province":"KY",
    "sg:tags":[
        "laboratory"
    ],
    "wof:name":"Quest Diagnostics Inc",
    "wof:placetype":"venue"
},
  "geometry": {"coordinates":[-85.769122,38.2264],"type":"Point"}
}