{
  "type": "Feature",
  "properties": {
    "addr:full":"201 Salem Dr Owensboro KY 42303",
    "addr:housenumber":"201",
    "addr:postcode":"42303",
    "addr:street":"Salem Dr",
    "iso:country":"US",
    "sg:address":"201 Salem Dr",
    "sg:city":"Owensboro",
    "sg:classifiers":[
        {
            "category":"Health Services",
            "subcategory":"Doctor",
            "type":"Services"
        }
    ],
    "sg:phone":"+1 270 684 2433",
    "sg:postcode":"42303",
    "sg:province":"KY",
    "sg:tags":[
        "physician",
        "surgeon"
    ],
    "wof:name":"Dr Snacks",
    "wof:placetype":"venue"
},
  "geometry": {"coordinates":[-87.113682,37.72565],"type":"Point"}
}