{
  "type": "Feature",
  "properties": {
    "iso:country":"US",
    "sg:address":"1010 Jackson Rd",
    "sg:city":"Park Hills",
    "sg:classifiers":[
        {
            "category":"Professional",
            "subcategory":"Advertising",
            "type":"Services"
        }
    ],
    "sg:phone":"+1 859 291 7005",
    "sg:postcode":"41011",
    "sg:province":"KY",
    "sg:tags":[
        "designer",
        "display",
        "producer"
    ],
    "wof:name":"Array",
    "wof:placetype":"venue"
},
  "geometry": {"coordinates":[-84.53290200000001,39.073206],"type":"Point"}
}