{
  "type": "Feature",
  "properties": {
    "iso:country":"US",
    "sg:address":"104 N 5th St",
    "sg:city":"Murray",
    "sg:classifiers":[
        {
            "category":"Banks & Credit Unions",
            "subcategory":"Investment Brokerage",
            "type":"Services"
        }
    ],
    "sg:phone":"+1 270 759 9722",
    "sg:postcode":"42071",
    "sg:province":"KY",
    "sg:tags":[
        "security"
    ],
    "wof:name":"Money Concepts",
    "wof:placetype":"venue"
},
  "geometry": {"coordinates":[-88.302913,36.611878],"type":"Point"}
}