{
  "type": "Feature",
  "properties": {
    "addr:full":"3790 Paris Pike Georgetown KY 40324",
    "addr:housenumber":"3790",
    "addr:postcode":"40324",
    "addr:street":"Paris Pike",
    "iso:country":"US",
    "sg:address":"3790 Paris Pike",
    "sg:city":"Georgetown",
    "sg:classifiers":[
        {
            "category":"Farming",
            "subcategory":"Farm",
            "type":"Manufacturing & Wholesale Goods"
        }
    ],
    "sg:phone":"+1 502 867 1090",
    "sg:postcode":"40324",
    "sg:province":"KY",
    "sg:tags":[
        "crop",
        "general"
    ],
    "wof:name":"Millers Run Farm",
    "wof:placetype":"venue"
},
  "geometry": {"coordinates":[-84.49075499999999,38.219163],"type":"Point"}
}