{
  "type": "Feature",
  "properties": {
    "iso:country":"US",
    "sg:address":"110 E Main St",
    "sg:city":"Providence",
    "sg:classifiers":[
        {
            "category":"Organizations",
            "subcategory":"Religious Organization",
            "type":"Services"
        }
    ],
    "sg:phone":"+1 270 667 6222",
    "sg:postcode":"42450",
    "sg:province":"KY",
    "sg:tags":[
        "church"
    ],
    "wof:name":"New Covenant Christian Center",
    "wof:placetype":"venue"
},
  "geometry": {"coordinates":[-87.762253,37.397527],"type":"Point"}
}