{
  "type": "Feature",
  "properties": {
    "iso:country":"US",
    "sg:address":"7300 Alexandria Pike",
    "sg:city":"Alexandria",
    "sg:classifiers":[
        {
            "category":"Banks & Credit Unions",
            "subcategory":"Bank",
            "type":"Services"
        },
        {
            "category":"Banks & Credit Unions",
            "subcategory":"Financial Services",
            "type":"Services"
        }
    ],
    "sg:phone":"+1 859 635 0777",
    "sg:postcode":"41001",
    "sg:province":"KY",
    "sg:tags":[
        "broker",
        "mortgage"
    ],
    "wof:name":"Citizens Bank of Northern Ky",
    "wof:placetype":"venue"
},
  "geometry": {"coordinates":[-84.399101,38.982601],"type":"Point"}
}