{
  "type": "Feature",
  "properties": {
    "addr:full":"1422 Hopkins Cemetery Rd Lily KY 40740",
    "addr:housenumber":"1422",
    "addr:postcode":"40740",
    "addr:street":"Hopkins Cemetery Rd",
    "iso:country":"US",
    "sg:address":"1422 Hopkins Cemetery Rd",
    "sg:city":"Lily",
    "sg:classifiers":[
        {
            "category":"Building & Trades",
            "subcategory":"Construction",
            "type":"Services"
        }
    ],
    "sg:phone":"+1 606 864 3011",
    "sg:postcode":"40740",
    "sg:province":"KY",
    "sg:tags":[
        "contractor"
    ],
    "wof:name":"J & D Contracting Inc",
    "wof:placetype":"venue"
},
  "geometry": {"coordinates":[-84.017207,37.03407],"type":"Point"}
}