{
  "type": "Feature",
  "properties": {
    "iso:country":"US",
    "sg:address":"409 Happy Valley Rd",
    "sg:city":"Glasgow",
    "sg:classifiers":[
        {
            "category":"Banks & Credit Unions",
            "subcategory":"Bank",
            "type":"Services"
        }
    ],
    "sg:phone":"+1 270 629 4732",
    "sg:postcode":"42141",
    "sg:province":"KY",
    "sg:tags":[
        "loan",
        "real estate"
    ],
    "wof:name":"Personal Finance Co",
    "wof:placetype":"venue"
},
  "geometry": {"coordinates":[-85.910928,37.005182],"type":"Point"}
}