{
  "type": "Feature",
  "properties": {
    "addr:full":"102 Sunset Dr Somerset KY 42518",
    "addr:housenumber":"102",
    "addr:postcode":"42518",
    "addr:street":"Sunset Dr",
    "iso:country":"US",
    "sg:address":"102 Sunset Dr",
    "sg:city":"Somerset",
    "sg:classifiers":[
        {
            "category":"Manufacturing",
            "subcategory":"Watercraft",
            "type":"Manufacturing & Wholesale Goods"
        }
    ],
    "sg:phone":"+1 606 875 5857",
    "sg:postcode":"42518",
    "sg:province":"KY",
    "sg:tags":[
        "manufacture",
        "pontoon"
    ],
    "wof:name":"Bubba Boats",
    "wof:placetype":"venue"
},
  "geometry": {"coordinates":[-84.659256,36.977736],"type":"Point"}
}