{
  "type": "Feature",
  "properties": {
    "addr:full":"2533 Lowell Ct Fort Mitchell KY 41017",
    "addr:housenumber":"2533",
    "addr:postcode":"41017",
    "addr:street":"Lowell Ct",
    "iso:country":"US",
    "sg:address":"2533 Lowell Ct",
    "sg:city":"Fort Mitchell",
    "sg:classifiers":[
        {
            "category":"Real Estate",
            "subcategory":"Real Estate Operator",
            "type":"Services"
        }
    ],
    "sg:phone":"+1 859 426 8365",
    "sg:postcode":"41017",
    "sg:province":"KY",
    "sg:tags":[
        "apartment"
    ],
    "wof:name":"Lakeside Village Apartment",
    "wof:placetype":"venue"
},
  "geometry": {"coordinates":[-84.574186,39.041468],"type":"Point"}
}