{
  "type": "Feature",
  "properties": {
    "iso:country":"US",
    "sg:address":"606 Chestnut St",
    "sg:city":"Georgetown",
    "sg:classifiers":[
        {
            "category":"Building & Trades",
            "subcategory":"Landscaping Services",
            "type":"Services"
        }
    ],
    "sg:phone":"+1 502 570 4876",
    "sg:postcode":"40324",
    "sg:province":"KY",
    "wof:name":"Hastings Mowing",
    "wof:placetype":"venue"
},
  "geometry": {"coordinates":[-84.55838199999999,38.220504],"type":"Point"}
}