{
  "type": "Feature",
  "properties": {
    "iso:country":"US",
    "sg:address":"2035 State Hwy 44 E",
    "sg:city":"Shepherdsville",
    "sg:classifiers":[
        {
            "category":"Retail",
            "subcategory":"Auto Repair",
            "type":"Services"
        }
    ],
    "sg:phone":"+1 502 543 6700",
    "sg:postcode":"40165",
    "sg:province":"KY",
    "sg:tags":[
        "body",
        "automobile",
        "painting"
    ],
    "wof:name":"Fleming's Auto Body Repair Ctr",
    "wof:placetype":"venue"
},
  "geometry": {"coordinates":[-85.69257,37.999767],"type":"Point"}
}