{
  "type": "Feature",
  "properties": {
    "iso:country":"US",
    "sg:address":"1435 State Hwy 11",
    "sg:city":"Campton",
    "sg:classifiers":[
        {
            "category":"Travel",
            "subcategory":"Hotels & Motels",
            "type":"Entertainment"
        }
    ],
    "sg:phone":"+1 606 668 6441",
    "sg:postcode":"41301",
    "sg:province":"KY",
    "sg:tags":[
        "breakfast",
        "accommodation",
        "bed"
    ],
    "sg:website":"www.torrentfalls.com",
    "wof:name":"Torrent Falls Bed & Breakfast",
    "wof:placetype":"venue"
},
  "geometry": {"coordinates":[-83.68075399999999,37.705908],"type":"Point"}
}