{
  "type": "Feature",
  "properties": {
    "addr:full":"452 Barroway Ln Versailles KY 40383",
    "addr:housenumber":"452",
    "addr:postcode":"40383",
    "addr:street":"Barroway Ln",
    "iso:country":"US",
    "sg:address":"452 Barroway Ln",
    "sg:city":"Versailles",
    "sg:classifiers":[
        {
            "category":"Building & Trades",
            "subcategory":"Construction",
            "type":"Services"
        }
    ],
    "sg:phone":"+1 859 873 8472",
    "sg:postcode":"40383",
    "sg:province":"KY",
    "sg:tags":[
        "house"
    ],
    "wof:name":"Lauderdale John",
    "wof:placetype":"venue"
},
  "geometry": {"coordinates":[-84.725092,38.035092],"type":"Point"}
}