{
  "type": "Feature",
  "properties": {
    "addr:full":"8505 Nash Rd Louisville KY 40214",
    "addr:housenumber":"8505",
    "addr:postcode":"40214",
    "addr:street":"Nash Rd",
    "iso:country":"US",
    "sg:address":"8505 Nash Rd",
    "sg:city":"Louisville",
    "sg:classifiers":[
        {
            "category":"Retail",
            "subcategory":"Repair Shop",
            "type":"Services"
        }
    ],
    "sg:phone":"+1 502 366 4300",
    "sg:postcode":"40214",
    "sg:province":"KY",
    "sg:tags":[
        "related"
    ],
    "wof:name":"Bio Medical Corp",
    "wof:placetype":"venue"
},
  "geometry": {"coordinates":[-85.75261,38.126617],"type":"Point"}
}