{
  "type": "Feature",
  "properties": {
    "iso:country":"US",
    "sg:address":"2604 Bardstown Rd",
    "sg:city":"Louisville",
    "sg:classifiers":[
        {
            "category":"Shopping",
            "subcategory":"Computers & Home Electronics",
            "type":"Retail Goods"
        }
    ],
    "sg:phone":"+1 502 485 9600",
    "sg:postcode":"40205",
    "sg:province":"KY",
    "sg:tags":[
        "equipment",
        "dealer"
    ],
    "sg:website":"www.interspacecomputers.com",
    "wof:name":"Access Technologies",
    "wof:placetype":"venue"
},
  "geometry": {"coordinates":[-85.683497,38.222293],"type":"Point"}
}