{
  "type": "Feature",
  "properties": {
    "addr:full":"606 Happy Landing Rd Glasgow KY 42141",
    "addr:housenumber":"606",
    "addr:postcode":"42141",
    "addr:street":"Happy Landing Rd",
    "iso:country":"US",
    "sg:address":"606 Happy Landing Rd",
    "sg:city":"Glasgow",
    "sg:classifiers":[
        {
            "category":"Building & Trades",
            "subcategory":"Construction",
            "type":"Services"
        }
    ],
    "sg:phone":"+1 270 646 4685",
    "sg:postcode":"42141",
    "sg:province":"KY",
    "sg:tags":[
        "house"
    ],
    "wof:name":"Vib Home Repairs",
    "wof:placetype":"venue"
},
  "geometry": {"coordinates":[-86.057254,36.911101],"type":"Point"}
}