{
  "type": "Feature",
  "properties": {
    "addr:full":"445 Knifley Rd Columbia KY 42728",
    "addr:housenumber":"445",
    "addr:postcode":"42728",
    "addr:street":"Knifley Rd",
    "iso:country":"US",
    "sg:address":"445 Knifley Rd",
    "sg:city":"Columbia",
    "sg:phone":"+1 270 384 3088",
    "sg:postcode":"42728",
    "sg:province":"KY",
    "sg:tags":[
        "farm",
        "field",
        "crop"
    ],
    "wof:name":"Chester Taylor",
    "wof:placetype":"venue"
},
  "geometry": {"coordinates":[-85.29225700000001,37.134702],"type":"Point"}
}