{
  "type": "Feature",
  "properties": {
    "addr:full":"4341 Winston Ave Covington KY 41015",
    "addr:housenumber":"4341",
    "addr:postcode":"41015",
    "addr:street":"Winston Ave",
    "iso:country":"US",
    "sg:address":"4341 Winston Ave",
    "sg:city":"Covington",
    "sg:classifiers":[
        {
            "category":"Health Services",
            "subcategory":"Doctor",
            "type":"Services"
        }
    ],
    "sg:phone":"+1 859 431 7660",
    "sg:postcode":"41015",
    "sg:province":"KY",
    "sg:tags":[
        "physician",
        "surgeon"
    ],
    "wof:name":"Summit Medical Group",
    "wof:placetype":"venue"
},
  "geometry": {"coordinates":[-84.50672299999999,39.041297],"type":"Point"}
}