{
  "type": "Feature",
  "properties": {
    "iso:country":"US",
    "sg:address":"9601 Shelbyville Rd",
    "sg:city":"Louisville",
    "sg:classifiers":[
        {
            "category":"Restaurant",
            "type":"Food & Drink"
        }
    ],
    "sg:phone":"+1 502 327 8143",
    "sg:postcode":"40223",
    "sg:province":"KY",
    "wof:name":"Garrett's Restaurant",
    "wof:placetype":"venue"
},
  "geometry": {"coordinates":[-85.574466,38.246213],"type":"Point"}
}