{
  "type": "Feature",
  "properties": {
    "addr:full":"3137 Olivet Church Rd Paducah KY 42001",
    "addr:housenumber":"3137",
    "addr:postcode":"42001",
    "addr:street":"Olivet Church Rd",
    "iso:country":"US",
    "sg:address":"3137 Olivet Church Rd",
    "sg:city":"Paducah",
    "sg:classifiers":[
        {
            "category":"Retail",
            "subcategory":"Veterinary Services",
            "type":"Services"
        }
    ],
    "sg:phone":"+1 270 443 9911",
    "sg:postcode":"42001",
    "sg:province":"KY",
    "sg:tags":[
        "veterinarian"
    ],
    "wof:name":"Heartland Veterinary Hospital",
    "wof:placetype":"venue"
},
  "geometry": {"coordinates":[-88.698477,37.075204],"type":"Point"}
}