{
  "type": "Feature",
  "properties": {
    "iso:country":"US",
    "sg:address":"161 Outer Loop",
    "sg:city":"Louisville",
    "sg:classifiers":[
        {
            "category":"Professional",
            "subcategory":"Employment Agencies",
            "type":"Services"
        }
    ],
    "sg:phone":"+1 502 287 0285",
    "sg:postcode":"40214",
    "sg:province":"KY",
    "sg:tags":[
        "temporary",
        "contractor"
    ],
    "sg:website":"http://louisville.citysearch.com/profile/external/603378202/louisville_ky/manpower.html?publisher=yellowpages&reference_id=1&placement=ypwebsitemip",
    "wof:name":"Manpower",
    "wof:placetype":"venue"
},
  "geometry": {"coordinates":[-85.78127000000001,38.126638],"type":"Point"}
}