{
  "type": "Feature",
  "properties": {
    "iso:country":"US",
    "sg:address":"8009 Terry Rd",
    "sg:city":"Louisville",
    "sg:classifiers":[
        {
            "category":"Social Services",
            "type":"Services"
        }
    ],
    "sg:phone":"+1 502 935 1848",
    "sg:postcode":"40258",
    "sg:province":"KY",
    "sg:tags":[
        "disabled",
        "need",
        "product",
        "special",
        "developmentally"
    ],
    "wof:name":"Southwest Center For The Developmentally Disabled",
    "wof:placetype":"venue"
},
  "geometry": {"coordinates":[-85.873136,38.137504],"type":"Point"}
}