{
  "type": "Feature",
  "properties": {
    "addr:full":"100 Greenway Dr Flemingsburg KY 41041",
    "addr:housenumber":"100",
    "addr:postcode":"41041",
    "addr:street":"Greenway Dr",
    "iso:country":"US",
    "sg:address":"100 Greenway Dr",
    "sg:city":"Flemingsburg",
    "sg:classifiers":[
        {
            "category":"Farming",
            "subcategory":"Farm",
            "type":"Manufacturing & Wholesale Goods"
        }
    ],
    "sg:phone":"+1 606 849 2245",
    "sg:postcode":"41041",
    "sg:province":"KY",
    "wof:name":"Christman Farms",
    "wof:placetype":"venue"
},
  "geometry": {"coordinates":[-83.738607,38.418945],"type":"Point"}
}