{
  "type": "Feature",
  "properties": {
    "iso:country":"US",
    "sg:address":"25 W Main St",
    "sg:city":"Mt Vernon",
    "sg:classifiers":[
        {
            "category":"Professional",
            "subcategory":"Art Services",
            "type":"Services"
        }
    ],
    "sg:phone":"+1 606 256 9011",
    "sg:postcode":"40456",
    "sg:province":"KY",
    "sg:tags":[
        "photographer"
    ],
    "wof:name":"Photo Image",
    "wof:placetype":"venue"
},
  "geometry": {"coordinates":[-84.340655,37.353653],"type":"Point"}
}