{
  "type": "Feature",
  "properties": {
    "iso:country":"US",
    "sg:address":"16999 Lafayette Rd",
    "sg:city":"Herndon",
    "sg:classifiers":[
        {
            "category":"Farming",
            "subcategory":"Livestock Farm",
            "type":"Manufacturing & Wholesale Goods"
        }
    ],
    "sg:phone":"+1 270 271 2227",
    "sg:postcode":"42236",
    "sg:province":"KY",
    "sg:tags":[
        "beef",
        "feedlot",
        "cattle"
    ],
    "wof:name":"L Claxton",
    "wof:placetype":"venue"
},
  "geometry": {"coordinates":[-87.643192,36.67632],"type":"Point"}
}