{
  "type": "Feature",
  "properties": {
    "iso:country":"US",
    "sg:address":"1690 Russell Cave Rd",
    "sg:city":"Lexington",
    "sg:classifiers":[
        {
            "category":"Organizations",
            "subcategory":"Religious Organization",
            "type":"Services"
        }
    ],
    "sg:phone":"+1 859 294 9325",
    "sg:postcode":"40505",
    "sg:province":"KY",
    "sg:tags":[
        "church"
    ],
    "wof:name":"New Birth Church Of Christ",
    "wof:placetype":"venue"
},
  "geometry": {"coordinates":[-84.47164600000001,38.077809],"type":"Point"}
}