{
  "type": "Feature",
  "properties": {
    "addr:full":"428 Dixie Hwy W Elizabethtown KY 42701",
    "addr:housenumber":"428",
    "addr:postcode":"42701",
    "addr:street":"Dixie Hwy W",
    "iso:country":"US",
    "sg:address":"428 Dixie Hwy W",
    "sg:city":"Elizabethtown",
    "sg:classifiers":[
        {
            "category":"Banks & Credit Unions",
            "subcategory":"Bank",
            "type":"Services"
        }
    ],
    "sg:phone":"+1 270 763 0480",
    "sg:postcode":"42701",
    "sg:province":"KY",
    "sg:tags":[
        "cashing",
        "check"
    ],
    "wof:name":"Check Advance",
    "wof:placetype":"venue"
},
  "geometry": {"coordinates":[-85.867092,37.700254],"type":"Point"}
}