{
  "type": "Feature",
  "properties": {
    "iso:country":"US",
    "sg:address":"4416 Wendy Hills Dr",
    "sg:city":"Crestwood",
    "sg:classifiers":[
        {
            "category":"Arts & Performance",
            "subcategory":"Theater",
            "type":"Entertainment"
        }
    ],
    "sg:phone":"+1 502 241 8965",
    "sg:postcode":"40014",
    "sg:province":"KY",
    "sg:tags":[
        "group"
    ],
    "wof:name":"Michael Ray Ballard",
    "wof:placetype":"venue"
},
  "geometry": {"coordinates":[-85.43980999999999,38.32722],"type":"Point"}
}