{
  "type": "Feature",
  "properties": {
    "addr:full":"6414 Payton Ln Crestwood KY 40014",
    "addr:housenumber":"6414",
    "addr:postcode":"40014",
    "addr:street":"Payton Ln",
    "iso:country":"US",
    "sg:address":"6414 Payton Ln",
    "sg:city":"Crestwood",
    "sg:classifiers":[
        {
            "category":"Building & Trades",
            "subcategory":"Plumbing",
            "type":"Services"
        }
    ],
    "sg:phone":"+1 502 241 0467",
    "sg:postcode":"40014",
    "sg:province":"KY",
    "sg:tags":[
        "conditioning",
        "air",
        "system",
        "contractor"
    ],
    "wof:name":"J & T Heating Cooling & Sheet",
    "wof:placetype":"venue"
},
  "geometry": {"coordinates":[-85.383652,38.329924],"type":"Point"}
}