{
  "type": "Feature",
  "properties": {
    "iso:country":"US",
    "sg:address":"425 Marion Fudge Rd",
    "sg:city":"Columbia",
    "sg:classifiers":[
        {
            "category":"Professional",
            "subcategory":"Business Services",
            "type":"Services"
        }
    ],
    "sg:phone":"+1 270 378 6904",
    "sg:postcode":"42728",
    "sg:province":"KY",
    "wof:name":"Babcock Interiors",
    "wof:placetype":"venue"
},
  "geometry": {"coordinates":[-85.44550599999999,36.994134],"type":"Point"}
}