{
  "type": "Feature",
  "properties": {
    "iso:country":"US",
    "sg:address":"3934 Dixie Hwy",
    "sg:city":"Louisville",
    "sg:classifiers":[
        {
            "category":"Health Services",
            "subcategory":"Health Practitioner",
            "type":"Services"
        }
    ],
    "sg:phone":"+1 502 449 1673",
    "sg:postcode":"40216",
    "sg:province":"KY",
    "sg:tags":[
        "therapist",
        "physical"
    ],
    "wof:name":"Healing Hands Physical Therapy",
    "wof:placetype":"venue"
},
  "geometry": {"coordinates":[-85.807472,38.193149],"type":"Point"}
}