{
  "type": "Feature",
  "properties": {
    "iso:country":"US",
    "sg:address":"1404 Russell St",
    "sg:city":"Covington",
    "sg:classifiers":[
        {
            "category":"Organizations",
            "subcategory":"Religious Organization",
            "type":"Services"
        }
    ],
    "sg:phone":"+1 859 581 6167",
    "sg:postcode":"41011",
    "sg:province":"KY",
    "sg:tags":[
        "clergy"
    ],
    "wof:name":"Eugene Perry",
    "wof:placetype":"venue"
},
  "geometry": {"coordinates":[-84.510963,39.074253],"type":"Point"}
}