{
  "type": "Feature",
  "properties": {
    "addr:full":"166 Lynn Acres Rd Corbin KY 40701",
    "addr:housenumber":"166",
    "addr:postcode":"40701",
    "addr:street":"Lynn Acres Rd",
    "iso:country":"US",
    "sg:address":"166 Lynn Acres Rd",
    "sg:city":"Corbin",
    "sg:classifiers":[
        {
            "category":"Real Estate",
            "subcategory":"Architect",
            "type":"Services"
        }
    ],
    "sg:phone":"+1 606 258 8020",
    "sg:postcode":"40701",
    "sg:province":"KY",
    "wof:name":"CGA Architects",
    "wof:placetype":"venue"
},
  "geometry": {"coordinates":[-84.082594,36.973609],"type":"Point"}
}