{
  "type": "Feature",
  "properties": {
    "addr:full":"1944 State Hwy 11 Beattyville KY 41311",
    "addr:housenumber":"1944",
    "addr:postcode":"41311",
    "addr:street":"State Hwy 11",
    "iso:country":"US",
    "sg:address":"1944 State Hwy 11",
    "sg:city":"Beattyville",
    "sg:classifiers":[
        {
            "category":"Banks & Credit Unions",
            "subcategory":"Bank",
            "type":"Services"
        }
    ],
    "sg:phone":"+1 606 464 9912",
    "sg:postcode":"41311",
    "sg:province":"KY",
    "sg:tags":[
        "loan"
    ],
    "wof:name":"World Finance Corp",
    "wof:placetype":"venue"
},
  "geometry": {"coordinates":[-83.69717199999999,37.638898],"type":"Point"}
}