{
  "type": "Feature",
  "properties": {
    "iso:country":"US",
    "sg:address":"1035 Bardstown Rd",
    "sg:city":"Louisville",
    "sg:classifiers":[
        {
            "category":"Personal",
            "type":"Services"
        },
        {
            "category":"Professional",
            "subcategory":"Art Services",
            "type":"Services"
        },
        {
            "category":"Professional",
            "subcategory":"Printing & Photocopies",
            "type":"Services"
        }
    ],
    "sg:phone":"+1 502 456 1922",
    "sg:postcode":"40204",
    "sg:province":"KY",
    "sg:tags":[
        "photography",
        "videography",
        "photographers-commercial",
        "wedding"
    ],
    "sg:website":"http://www.moberlyphotography.com",
    "wof:name":"Moberly Photography Inc",
    "wof:placetype":"venue"
},
  "geometry": {"coordinates":[-85.723489,38.239823],"type":"Point"}
}