{
  "type": "Feature",
  "properties": {
    "iso:country":"US",
    "sg:address":"209 Glades St",
    "sg:city":"Berea",
    "sg:classifiers":[
        {
            "category":"Professional",
            "subcategory":"Accounting & Tax Preparation",
            "type":"Services"
        }
    ],
    "sg:phone":"+1 859 985 2879",
    "sg:postcode":"40403",
    "sg:province":"KY",
    "sg:tags":[
        "bookkeeping",
        "general"
    ],
    "wof:name":"Begley Harrison Business Svc",
    "wof:placetype":"venue"
},
  "geometry": {"coordinates":[-84.27579900000001,37.586823],"type":"Point"}
}