{
  "type": "Feature",
  "properties": {
    "addr:full":"809 Bennett Ave Lexington KY 40508",
    "addr:housenumber":"809",
    "addr:postcode":"40508",
    "addr:street":"Bennett Ave",
    "iso:country":"US",
    "sg:address":"809 Bennett Ave",
    "sg:city":"Lexington",
    "sg:classifiers":[
        {
            "category":"Building & Trades",
            "subcategory":"Equipment Rental",
            "type":"Services"
        }
    ],
    "sg:phone":"+1 859 233 1537",
    "sg:postcode":"40508",
    "sg:province":"KY",
    "sg:tags":[
        "medical"
    ],
    "wof:name":"Pablo Luis Companioni",
    "wof:placetype":"venue"
},
  "geometry": {"coordinates":[-84.518261,38.047774],"type":"Point"}
}