{
  "type": "Feature",
  "properties": {
    "addr:full":"142 Roger Powell Rd Sebree KY 42455",
    "addr:housenumber":"142",
    "addr:postcode":"42455",
    "addr:street":"Roger Powell Rd",
    "iso:country":"US",
    "sg:address":"142 Roger Powell Rd",
    "sg:city":"Sebree",
    "sg:classifiers":[
        {
            "category":"Health Services",
            "subcategory":"Clinic",
            "type":"Services"
        }
    ],
    "sg:phone":"+1 270 835 9448",
    "sg:postcode":"42455",
    "sg:province":"KY",
    "sg:tags":[
        "specialty",
        "outpatient"
    ],
    "wof:name":"Trans Healthcare Inc",
    "wof:placetype":"venue"
},
  "geometry": {"coordinates":[-87.53402,37.601794],"type":"Point"}
}