{
  "type": "Feature",
  "properties": {
    "addr:full":"3717 Taylorsville Rd Louisville KY 40220",
    "addr:housenumber":"3717",
    "addr:postcode":"40220",
    "addr:street":"Taylorsville Rd",
    "iso:country":"US",
    "sg:address":"3717 Taylorsville Rd",
    "sg:city":"Louisville",
    "sg:classifiers":[
        {
            "category":"Organizations",
            "subcategory":"Non-profit Organization",
            "type":"Services"
        }
    ],
    "sg:phone":"+1 502 459 0225",
    "sg:postcode":"40220",
    "sg:province":"KY",
    "sg:website":"www.sevencounties.org",
    "wof:name":"First Steps",
    "wof:placetype":"venue"
},
  "geometry": {"coordinates":[-85.641869,38.220871],"type":"Point"}
}