{
  "type": "Feature",
  "properties": {
    "iso:country":"US",
    "sg:address":"24 Little Oak Dr",
    "sg:city":"Jenkins",
    "sg:classifiers":[
        {
            "category":"Real Estate",
            "subcategory":"Real Estate Operator",
            "type":"Services"
        }
    ],
    "sg:phone":"+1 606 832 4588",
    "sg:postcode":"41537",
    "sg:province":"KY",
    "sg:tags":[
        "apartment"
    ],
    "wof:name":"Goodwater Falls Apartments",
    "wof:placetype":"venue"
},
  "geometry": {"coordinates":[-82.635656,37.163001],"type":"Point"}
}