{
  "type": "Feature",
  "properties": {
    "iso:country":"US",
    "sg:address":"3900 Kresge Way Ste 31",
    "sg:city":"Louisville",
    "sg:classifiers":[
        {
            "category":"Health Services",
            "subcategory":"Doctor",
            "type":"Services"
        }
    ],
    "sg:phone":"+1 502 895 2489",
    "sg:postcode":"40207",
    "sg:province":"KY",
    "sg:tags":[
        "physician",
        "gynecology",
        "surgeons",
        "obstetrics",
        "surgeon"
    ],
    "wof:name":"Schweitzer Robert MD",
    "wof:placetype":"venue"
},
  "geometry": {"coordinates":[-85.642117,38.237833],"type":"Point"}
}