{
  "type": "Feature",
  "properties": {
    "iso:country":"US",
    "sg:address":"1475 State Hwy 121",
    "sg:city":"Murray",
    "sg:classifiers":[
        {
            "category":"Building & Trades",
            "subcategory":"Plumbing",
            "type":"Services"
        }
    ],
    "sg:phone":"+1 270 759 0610",
    "sg:postcode":"42071",
    "sg:province":"KY",
    "sg:tags":[
        "plumbing",
        "contractor"
    ],
    "wof:name":"Sykes Plumbing",
    "wof:placetype":"venue"
},
  "geometry": {"coordinates":[-88.32206499999999,36.623095],"type":"Point"}
}