{
  "type": "Feature",
  "properties": {
    "iso:country":"US",
    "sg:address":"3704 Winding Wood Pl",
    "sg:city":"Lexington",
    "sg:classifiers":[
        {
            "category":"Manufacturing",
            "subcategory":"Tools & Machinery",
            "type":"Manufacturing & Wholesale Goods"
        }
    ],
    "sg:phone":"+1 859 271 0276",
    "sg:postcode":"40515",
    "sg:province":"KY",
    "sg:tags":[
        "equipment",
        "mfg"
    ],
    "wof:name":"Goodknight Medical Devices LLC",
    "wof:placetype":"venue"
},
  "geometry": {"coordinates":[-84.472483,37.958153],"type":"Point"}
}