{
  "type": "Feature",
  "properties": {
    "iso:country":"US",
    "sg:address":"1130 Helvetia Rd",
    "sg:city":"London",
    "sg:classifiers":[
        {
            "category":"Professional",
            "subcategory":"Business Services",
            "type":"Services"
        }
    ],
    "sg:phone":"+1 606 843 2398",
    "sg:postcode":"40741",
    "sg:province":"KY",
    "sg:tags":[
        "repossessing"
    ],
    "wof:name":"Imperial Recovery Agency",
    "wof:placetype":"venue"
},
  "geometry": {"coordinates":[-84.147406,37.16698],"type":"Point"}
}