{
  "type": "Feature",
  "properties": {
    "addr:full":"1185 Buck Knobs Rd Ekron KY 40117",
    "addr:housenumber":"1185",
    "addr:postcode":"40117",
    "addr:street":"Buck Knobs Rd",
    "iso:country":"US",
    "sg:address":"1185 Buck Knobs Rd",
    "sg:city":"Ekron",
    "sg:classifiers":[
        {
            "category":"Building & Trades",
            "subcategory":"Construction",
            "type":"Services"
        }
    ],
    "sg:phone":"+1 270 828 8200",
    "sg:postcode":"40117",
    "sg:province":"KY",
    "sg:tags":[
        "excavating",
        "contractor"
    ],
    "wof:name":"Medley's Excavating",
    "wof:placetype":"venue"
},
  "geometry": {"coordinates":[-86.10301200000001,37.912858],"type":"Point"}
}