{
  "type": "Feature",
  "properties": {
    "addr:full":"10025 Forest Green Blvd Louisville KY 40223",
    "addr:housenumber":"10025",
    "addr:postcode":"40223",
    "addr:street":"Forest Green Blvd",
    "iso:country":"US",
    "sg:address":"10025 Forest Green Blvd",
    "sg:city":"Louisville",
    "sg:classifiers":[
        {
            "category":"Banks & Credit Unions",
            "subcategory":"Investment Brokerage",
            "type":"Services"
        }
    ],
    "sg:phone":"+1 502 327 9052",
    "sg:postcode":"40223",
    "sg:province":"KY",
    "sg:tags":[
        "stock",
        "bond"
    ],
    "wof:name":"Edward Jones Co",
    "wof:placetype":"venue"
},
  "geometry": {"coordinates":[-85.56929599999999,38.263336],"type":"Point"}
}