{
  "type": "Feature",
  "properties": {
    "iso:country":"US",
    "sg:address":"120 Gleneagles Blvd",
    "sg:city":"Richmond",
    "sg:classifiers":[
        {
            "category":"Shopping",
            "subcategory":"Computers & Home Electronics",
            "type":"Retail Goods"
        }
    ],
    "sg:phone":"+1 859 625 9779",
    "sg:postcode":"40475",
    "sg:province":"KY",
    "wof:name":"Nivben Software Inc",
    "wof:placetype":"venue"
},
  "geometry": {"coordinates":[-84.356844,37.886741],"type":"Point"}
}