{
  "type": "Feature",
  "properties": {
    "addr:full":"2876 Middlesex Way Lexington KY 40503",
    "addr:housenumber":"2876",
    "addr:postcode":"40503",
    "addr:street":"Middlesex Way",
    "iso:country":"US",
    "sg:address":"2876 Middlesex Way",
    "sg:city":"Lexington",
    "sg:classifiers":[
        {
            "category":"Professional",
            "subcategory":"Secretarial Services",
            "type":"Services"
        }
    ],
    "sg:phone":"+1 859 277 0340",
    "sg:postcode":"40503",
    "sg:province":"KY",
    "sg:tags":[
        "reporting"
    ],
    "wof:name":"Diane C Hibbard Inc",
    "wof:placetype":"venue"
},
  "geometry": {"coordinates":[-84.53271100000001,38.006324],"type":"Point"}
}