{
  "type": "Feature",
  "properties": {
    "iso:country":"US",
    "sg:address":"1140 Hobbs Rd",
    "sg:city":"Campton",
    "sg:classifiers":[
        {
            "category":"Personal",
            "subcategory":"Beauty Salon",
            "type":"Services"
        }
    ],
    "sg:phone":"+1 606 668 7330",
    "sg:postcode":"41301",
    "sg:province":"KY",
    "sg:tags":[
        "shop"
    ],
    "wof:name":"Hair Works Beauty Salon",
    "wof:placetype":"venue"
},
  "geometry": {"coordinates":[-83.603927,37.742281],"type":"Point"}
}