{
  "type": "Feature",
  "properties": {
    "addr:full":"115 Wiltshire Ave Louisville KY 40207",
    "addr:housenumber":"115",
    "addr:postcode":"40207",
    "addr:street":"Wiltshire Ave",
    "iso:country":"US",
    "sg:address":"115 Wiltshire Ave",
    "sg:city":"Louisville",
    "sg:classifiers":[
        {
            "category":"Shopping",
            "type":"Retail Goods"
        }
    ],
    "sg:phone":"+1 502 893 8936",
    "sg:postcode":"40207",
    "sg:province":"KY",
    "sg:tags":[
        "picture",
        "frame",
        "frames-wholesale",
        "manufacturer"
    ],
    "wof:name":"Davenport's Custom Frames",
    "wof:placetype":"venue"
},
  "geometry": {"coordinates":[-85.65562799999999,38.251578],"type":"Point"}
}