{
  "type": "Feature",
  "properties": {
    "iso:country":"US",
    "sg:address":"143 Bluffside Dr",
    "sg:city":"Covington",
    "sg:classifiers":[
        {
            "category":"Professional",
            "subcategory":"Detective & Security Services",
            "type":"Services"
        }
    ],
    "sg:phone":"+1 859 356 6123",
    "sg:postcode":"41017",
    "sg:province":"KY",
    "sg:tags":[
        "guard",
        "contract"
    ],
    "wof:name":"Kenneth R Honchell",
    "wof:placetype":"venue"
},
  "geometry": {"coordinates":[-84.527067,38.984179],"type":"Point"}
}