{
  "type": "Feature",
  "properties": {
    "iso:country":"US",
    "sg:address":"39 N Madison Ave",
    "sg:city":"Madisonville",
    "sg:classifiers":[
        {
            "category":"Manufacturing",
            "subcategory":"Tools & Machinery",
            "type":"Manufacturing & Wholesale Goods"
        }
    ],
    "sg:phone":"+1 270 821 3538",
    "sg:postcode":"42431",
    "sg:province":"KY",
    "sg:tags":[
        "machine",
        "shop"
    ],
    "wof:name":"Joe Leasure & Sons Inc",
    "wof:placetype":"venue"
},
  "geometry": {"coordinates":[-87.50393,37.329828],"type":"Point"}
}