{
  "type": "Feature",
  "properties": {
    "iso:country":"US",
    "sg:address":"16967 Sonora Hardin Springs Rd",
    "sg:city":"Eastview",
    "sg:classifiers":[
        {
            "category":"Building & Trades",
            "subcategory":"Landscaping Services",
            "type":"Services"
        }
    ],
    "sg:phone":"+1 270 862 9230",
    "sg:postcode":"42732",
    "sg:province":"KY",
    "sg:tags":[
        "landscape",
        "contractor"
    ],
    "wof:name":"Evergreen Lawn Care & Lndscpng",
    "wof:placetype":"venue"
},
  "geometry": {"coordinates":[-86.119945,37.61107],"type":"Point"}
}