{
  "type": "Feature",
  "properties": {
    "iso:country":"US",
    "sg:address":"1070 Brooks Industrial Rd",
    "sg:city":"Shelbyville",
    "sg:classifiers":[
        {
            "category":"Manufacturing",
            "subcategory":"Metals",
            "type":"Manufacturing & Wholesale Goods"
        }
    ],
    "sg:phone":"+1 502 633 4435",
    "sg:postcode":"40065",
    "sg:province":"KY",
    "sg:tags":[
        "forming"
    ],
    "sg:website":"www.rfcorp.com",
    "wof:name":"Roll Forming Corp",
    "wof:placetype":"venue"
},
  "geometry": {"coordinates":[-85.261802,38.209363],"type":"Point"}
}