{
  "type": "Feature",
  "properties": {
    "iso:country":"US",
    "sg:address":"811 Sycamore St",
    "sg:city":"Murray",
    "sg:classifiers":[
        {
            "category":"Food & Beverages",
            "subcategory":"Groceries & Convenience Stores",
            "type":"Retail Goods"
        }
    ],
    "sg:phone":"+1 270 753 7333",
    "sg:postcode":"42071",
    "sg:province":"KY",
    "wof:name":"Deb's Coastal Corner Mart",
    "wof:placetype":"venue"
},
  "geometry": {"coordinates":[-88.310526,36.602674],"type":"Point"}
}