{
  "type": "Feature",
  "properties": {
    "iso:country":"US",
    "sg:address":"4901 Westside Dr",
    "sg:city":"Louisville",
    "sg:classifiers":[
        {
            "category":"Professional",
            "type":"Services"
        }
    ],
    "sg:phone":"+1 502 969 1540",
    "sg:postcode":"40219",
    "sg:province":"KY",
    "sg:tags":[
        "establishment"
    ],
    "wof:name":"Carter Great Lakes",
    "wof:placetype":"venue"
},
  "geometry": {"coordinates":[-85.703064,38.163332],"type":"Point"}
}