{
  "type": "Feature",
  "properties": {
    "iso:country":"US",
    "sg:address":"615 Richmond St",
    "sg:city":"Mt Vernon",
    "sg:classifiers":[
        {
            "category":"Building & Trades",
            "subcategory":"Construction",
            "type":"Services"
        }
    ],
    "sg:phone":"+1 606 256 8441",
    "sg:postcode":"40456",
    "sg:province":"KY",
    "sg:tags":[
        "home",
        "builder"
    ],
    "wof:name":"Clayton Watkins Construction",
    "wof:placetype":"venue"
},
  "geometry": {"coordinates":[-84.337093,37.360181],"type":"Point"}
}