{
  "type": "Feature",
  "properties": {
    "iso:country":"US",
    "sg:address":"700 Kentucky Ave",
    "sg:city":"Paducah",
    "sg:classifiers":[
        {
            "category":"Professional",
            "subcategory":"Lawyer & Legal Services",
            "type":"Services"
        }
    ],
    "sg:phone":"+1 270 444 0374",
    "sg:postcode":"42003",
    "sg:province":"KY",
    "sg:tags":[
        "attorney"
    ],
    "wof:name":"Public Guardian-Administrator",
    "wof:placetype":"venue"
},
  "geometry": {"coordinates":[-88.601164,37.084202],"type":"Point"}
}