{
  "type": "Feature",
  "properties": {
    "iso:country":"US",
    "sg:address":"1205 E Washington St",
    "sg:city":"Louisville",
    "sg:classifiers":[
        {
            "category":"Professional",
            "subcategory":"Advertising",
            "type":"Services"
        },
        {
            "category":"Professional",
            "subcategory":"Computer Services",
            "type":"Services"
        }
    ],
    "sg:phone":"+1 502 568 6090",
    "sg:postcode":"40206",
    "sg:province":"KY",
    "sg:tags":[
        "web",
        "internet",
        "design",
        "site",
        "marketing"
    ],
    "sg:website":"http://www.visualscientists.com",
    "wof:name":"Visual Scientists Inc",
    "wof:placetype":"venue"
},
  "geometry": {"coordinates":[-85.729658,38.256508],"type":"Point"}
}