{
  "type": "Feature",
  "properties": {
    "iso:country":"US",
    "sg:address":"790 Forest Park Rd",
    "sg:city":"Louisville",
    "sg:classifiers":[
        {
            "category":"Manufacturing",
            "subcategory":"Tools & Machinery",
            "type":"Manufacturing & Wholesale Goods"
        },
        {
            "category":"Building & Trades",
            "subcategory":"Construction",
            "type":"Services"
        },
        {
            "category":"Industrial Area",
            "type":"Public Place"
        }
    ],
    "sg:phone":"+1 502 964 7303",
    "sg:postcode":"40223",
    "sg:province":"KY",
    "sg:tags":[
        "repair",
        "specialty",
        "machinery-rebuild",
        "heating",
        "system",
        "air conditioning",
        "contractor",
        "equipment-repairing"
    ],
    "wof:name":"All Hours Heating & Air Conditioning",
    "wof:placetype":"venue"
},
  "geometry": {"coordinates":[-85.562468,38.247908],"type":"Point"}
}