{
  "type": "Feature",
  "properties": {
    "iso:country":"US",
    "sg:address":"28 Thomas St",
    "sg:city":"Fort Thomas",
    "sg:classifiers":[
        {
            "category":"Education",
            "subcategory":"School",
            "type":"Public Place"
        }
    ],
    "sg:phone":"+1 859 781 3333",
    "sg:postcode":"41008",
    "sg:province":"KY",
    "sg:website":"www.ft-thomas.k12.ky.us",
    "wof:name":"Fort Thomas Board Of Education",
    "wof:placetype":"venue"
},
  "geometry": {"coordinates":[-85.126537,38.668784],"type":"Point"}
}