{
  "type": "Feature",
  "properties": {
    "iso:country":"US",
    "sg:address":"1149 Chetford Dr",
    "sg:city":"Lexington",
    "sg:classifiers":[
        {
            "category":"Professional",
            "subcategory":"Management & Consulting",
            "type":"Services"
        }
    ],
    "sg:phone":"+1 859 263 7440",
    "sg:postcode":"40509",
    "sg:province":"KY",
    "sg:tags":[
        "business"
    ],
    "wof:name":"Quinn Consulting Inc",
    "wof:placetype":"venue"
},
  "geometry": {"coordinates":[-84.409813,38.008381],"type":"Point"}
}