{
  "type": "Feature",
  "properties": {
    "addr:full":"11005 Clear Stream Ct Louisville KY 40291",
    "addr:housenumber":"11005",
    "addr:postcode":"40291",
    "addr:street":"Clear Stream Ct",
    "iso:country":"US",
    "sg:address":"11005 Clear Stream Ct",
    "sg:city":"Louisville",
    "sg:classifiers":[
        {
            "category":"Professional",
            "type":"Services"
        }
    ],
    "sg:phone":"+1 502 239 5780",
    "sg:postcode":"40291",
    "sg:province":"KY",
    "wof:name":"Wendy M Oser",
    "wof:placetype":"venue"
},
  "geometry": {"coordinates":[-85.569655,38.143229],"type":"Point"}
}