{
  "type": "Feature",
  "properties": {
    "addr:full":"7525 Industrial Rd Ste E Florence KY 41042",
    "addr:housenumber":"7525",
    "addr:postcode":"41042",
    "addr:street":"Industrial Rd Ste E",
    "iso:country":"US",
    "sg:address":"7525 Industrial Rd Ste E",
    "sg:city":"Florence",
    "sg:classifiers":[
        {
            "category":"Autos & Motor Vehicles",
            "subcategory":"Auto Supplies",
            "type":"Retail Goods"
        }
    ],
    "sg:phone":"+1 859 371 7222",
    "sg:postcode":"41042",
    "sg:province":"KY",
    "sg:tags":[
        "glass"
    ],
    "sg:website":"www.diamondautoglass.com",
    "wof:name":"Triumph Auto Glass",
    "wof:placetype":"venue"
},
  "geometry": {"coordinates":[-84.65389999999999,38.9879],"type":"Point"}
}