{
  "type": "Feature",
  "properties": {
    "addr:full":"979 Villa Dr Covington KY 41017",
    "addr:housenumber":"979",
    "addr:postcode":"41017",
    "addr:street":"Villa Dr",
    "iso:country":"US",
    "sg:address":"979 Villa Dr",
    "sg:city":"Covington",
    "sg:classifiers":[
        {
            "category":"Building & Trades",
            "subcategory":"Cleaning & Sanitation",
            "type":"Services"
        }
    ],
    "sg:phone":"+1 859 578 0225",
    "sg:postcode":"41017",
    "sg:province":"KY",
    "sg:tags":[
        "maintenance"
    ],
    "wof:name":"Absolute Janitorial Service",
    "wof:placetype":"venue"
},
  "geometry": {"coordinates":[-84.591736,39.063501],"type":"Point"}
}