{
  "type": "Feature",
  "properties": {
    "iso:country":"US",
    "sg:address":"2385 Lexington Rd",
    "sg:city":"Danville",
    "sg:classifiers":[
        {
            "category":"Retail",
            "subcategory":"Veterinary Services",
            "type":"Services"
        }
    ],
    "sg:phone":"+1 859 236 4401",
    "sg:postcode":"40422",
    "sg:province":"KY",
    "sg:tags":[
        "veterinarian"
    ],
    "wof:name":"Danville Animal Clinic",
    "wof:placetype":"venue"
},
  "geometry": {"coordinates":[-84.73708499999999,37.666225],"type":"Point"}
}