{
  "type": "Feature",
  "properties": {
    "iso:country":"US",
    "sg:address":"419 Sprite Rd",
    "sg:city":"Louisville",
    "sg:classifiers":[
        {
            "category":"Professional",
            "subcategory":"Management & Consulting",
            "type":"Services"
        }
    ],
    "sg:phone":"+1 502 895 7293",
    "sg:postcode":"40207",
    "sg:province":"KY",
    "sg:tags":[
        "business"
    ],
    "wof:name":"Aseret Congruence LLC",
    "wof:placetype":"venue"
},
  "geometry": {"coordinates":[-85.668021,38.264139],"type":"Point"}
}