{
  "type": "Feature",
  "properties": {
    "addr:full":"389 Waller Ave Lexington KY 40504",
    "addr:housenumber":"389",
    "addr:postcode":"40504",
    "addr:street":"Waller Ave",
    "iso:country":"US",
    "sg:address":"389 Waller Ave",
    "sg:city":"Lexington",
    "sg:classifiers":[
        {
            "category":"Insurance",
            "subcategory":"Insurance Agent",
            "type":"Services"
        }
    ],
    "sg:phone":"+1 859 255 0676",
    "sg:postcode":"40504",
    "sg:province":"KY",
    "wof:name":"Primerica Financial Svc",
    "wof:placetype":"venue"
},
  "geometry": {"coordinates":[-84.520116,38.030918],"type":"Point"}
}