{
  "type": "Feature",
  "properties": {
    "iso:country":"US",
    "sg:address":"156 S Main St",
    "sg:city":"Whitley City",
    "sg:classifiers":[
        {
            "category":"Retail",
            "subcategory":"Funeral Services",
            "type":"Services"
        }
    ],
    "sg:phone":"+1 606 376 5383",
    "sg:postcode":"42633",
    "sg:province":"KY",
    "sg:tags":[
        "director"
    ],
    "sg:website":"www.strunkfuneralhome.net",
    "wof:name":"Hickman-Strunk Funeral Home",
    "wof:placetype":"venue"
},
  "geometry": {"coordinates":[-84.85017999999999,36.82865],"type":"Point"}
}