{
  "type": "Feature",
  "properties": {
    "iso:country":"US",
    "sg:address":"17 Circle Dr",
    "sg:city":"Florence",
    "sg:classifiers":[
        {
            "category":"Shopping",
            "type":"Retail Goods"
        }
    ],
    "sg:phone":"+1 859 746 9968",
    "sg:postcode":"41042",
    "sg:province":"KY",
    "sg:tags":[
        "merchandise"
    ],
    "wof:name":"Max Assocation Inc",
    "wof:placetype":"venue"
},
  "geometry": {"coordinates":[-84.62773300000001,38.992253],"type":"Point"}
}