{
  "type": "Feature",
  "properties": {
    "addr:full":"6415 Bardstown Rd Louisville KY 40291",
    "addr:housenumber":"6415",
    "addr:postcode":"40291",
    "addr:street":"Bardstown Rd",
    "iso:country":"US",
    "sg:address":"6415 Bardstown Rd",
    "sg:city":"Louisville",
    "sg:classifiers":[
        {
            "category":"Health Services",
            "subcategory":"Doctor",
            "type":"Services"
        }
    ],
    "sg:phone":"+1 502 231 0806",
    "sg:postcode":"40291",
    "sg:province":"KY",
    "sg:tags":[
        "dental",
        "dentist",
        "insurance"
    ],
    "wof:name":"Harley Dental Center",
    "wof:placetype":"venue"
},
  "geometry": {"coordinates":[-85.589085,38.153749],"type":"Point"}
}