{
  "type": "Feature",
  "properties": {
    "iso:country":"US",
    "sg:address":"574 N Limestone",
    "sg:city":"Lexington",
    "sg:classifiers":[
        {
            "category":"Restaurant",
            "type":"Food & Drink"
        },
        {
            "category":"Bakery",
            "type":"Food & Drink"
        }
    ],
    "sg:phone":"+1 859 252 3737",
    "sg:postcode":"40508",
    "sg:province":"KY",
    "wof:name":"Spalding B J Bakery",
    "wof:placetype":"venue"
},
  "geometry": {"coordinates":[-84.486873,38.053529],"type":"Point"}
}