{
  "type": "Feature",
  "properties": {
    "iso:country":"US",
    "sg:address":"510 General Dr",
    "sg:city":"Covington",
    "sg:classifiers":[
        {
            "category":"Building & Trades",
            "subcategory":"Construction",
            "type":"Services"
        }
    ],
    "sg:phone":"+1 859 331 3682",
    "sg:postcode":"41011",
    "sg:province":"KY",
    "sg:tags":[
        "contractor"
    ],
    "wof:name":"J J Toebben Construction",
    "wof:placetype":"venue"
},
  "geometry": {"coordinates":[-84.555233,39.070495],"type":"Point"}
}