{
  "type": "Feature",
  "properties": {
    "iso:country":"US",
    "sg:address":"709 Dixie Hwy S",
    "sg:city":"Radcliff",
    "sg:classifiers":[
        {
            "category":"Professional",
            "subcategory":"Accounting & Tax Preparation",
            "type":"Services"
        }
    ],
    "sg:phone":"+1 270 351 2724",
    "sg:postcode":"40160",
    "sg:province":"KY",
    "sg:tags":[
        "accountant"
    ],
    "wof:name":"Young & Hutcherson",
    "wof:placetype":"venue"
},
  "geometry": {"coordinates":[-85.931276,37.831992],"type":"Point"}
}