{
  "type": "Feature",
  "properties": {
    "iso:country":"US",
    "sg:address":"901 Mammoth Cave St",
    "sg:city":"Cave City",
    "sg:classifiers":[
        {
            "category":"Autos & Motor Vehicles",
            "subcategory":"Fuel & Gas Station",
            "type":"Retail Goods"
        }
    ],
    "sg:phone":"+1 270 773 2216",
    "sg:postcode":"42127",
    "sg:province":"KY",
    "sg:tags":[
        "oil"
    ],
    "wof:name":"Cave City Shell Food Mart",
    "wof:placetype":"venue"
},
  "geometry": {"coordinates":[-85.973704,37.137003],"type":"Point"}
}