{
  "type": "Feature",
  "properties": {
    "iso:country":"US",
    "sg:address":"2415 Nashville Rd",
    "sg:city":"Bowling Green",
    "sg:classifiers":[
        {
            "category":"Banks & Credit Unions",
            "subcategory":"Bank",
            "type":"Services"
        }
    ],
    "sg:phone":"+1 270 746 5829",
    "sg:postcode":"42101",
    "sg:province":"KY",
    "wof:name":"Independence Bank",
    "wof:placetype":"venue"
},
  "geometry": {"coordinates":[-86.468307,36.961692],"type":"Point"}
}