{
  "type": "Feature",
  "properties": {
    "addr:full":"65 Payne Rd Ekron KY 40117",
    "addr:housenumber":"65",
    "addr:postcode":"40117",
    "addr:street":"Payne Rd",
    "iso:country":"US",
    "sg:address":"65 Payne Rd",
    "sg:city":"Ekron",
    "sg:classifiers":[
        {
            "category":"Personal",
            "subcategory":"Beauty Salon",
            "type":"Services"
        }
    ],
    "sg:phone":"+1 270 828 2451",
    "sg:postcode":"40117",
    "sg:province":"KY",
    "wof:name":"Image Makers",
    "wof:placetype":"venue"
},
  "geometry": {"coordinates":[-86.12788399999999,37.918608],"type":"Point"}
}