{
  "type": "Feature",
  "properties": {
    "iso:country":"US",
    "sg:address":"2319 Lime Kiln Ln",
    "sg:city":"Louisville",
    "sg:classifiers":[
        {
            "category":"Real Estate",
            "subcategory":"Real Estate Services",
            "type":"Services"
        }
    ],
    "sg:phone":"+1 502 429 6428",
    "sg:postcode":"40222",
    "sg:province":"KY",
    "sg:tags":[
        "company",
        "title"
    ],
    "wof:name":"Title Matters",
    "wof:placetype":"venue"
},
  "geometry": {"coordinates":[-85.62821,38.284313],"type":"Point"}
}