{
  "type": "Feature",
  "properties": {
    "iso:country":"US",
    "sg:address":"3107 Pomeroy Dr",
    "sg:city":"Louisville",
    "sg:classifiers":[
        {
            "category":"Professional",
            "subcategory":"Business Services",
            "type":"Services"
        }
    ],
    "sg:phone":"+1 502 499 5571",
    "sg:postcode":"40220",
    "sg:province":"KY",
    "wof:name":"Pinnacle Business Systems Inc",
    "wof:placetype":"venue"
},
  "geometry": {"coordinates":[-85.62800300000001,38.203732],"type":"Point"}
}