{
  "type": "Feature",
  "properties": {
    "iso:country":"US",
    "sg:address":"1003 Burlew Blvd",
    "sg:city":"Owensboro",
    "sg:classifiers":[
        {
            "category":"Health Services",
            "subcategory":"Doctor",
            "type":"Services"
        }
    ],
    "sg:phone":"+1 270 683 6848",
    "sg:postcode":"42303",
    "sg:province":"KY",
    "sg:tags":[
        "physician",
        "surgeon"
    ],
    "wof:name":"Allergy & Asthma Ctr",
    "wof:placetype":"venue"
},
  "geometry": {"coordinates":[-87.093507,37.741936],"type":"Point"}
}