{
  "type": "Feature",
  "properties": {
    "iso:country":"US",
    "sg:address":"1092 Hands Pike",
    "sg:city":"Covington",
    "sg:classifiers":[
        {
            "category":"Real Estate",
            "subcategory":"Real Estate Operator",
            "type":"Services"
        }
    ],
    "sg:phone":"+1 859 356 9670",
    "sg:postcode":"41017",
    "sg:province":"KY",
    "sg:tags":[
        "building",
        "apartment"
    ],
    "wof:name":"Giro Properties",
    "wof:placetype":"venue"
},
  "geometry": {"coordinates":[-84.525969,38.987571],"type":"Point"}
}