{
  "type": "Feature",
  "properties": {
    "addr:full":"6709 Carolyn Rd Louisville KY 40214",
    "addr:housenumber":"6709",
    "addr:postcode":"40214",
    "addr:street":"Carolyn Rd",
    "iso:country":"US",
    "sg:address":"6709 Carolyn Rd",
    "sg:city":"Louisville",
    "sg:classifiers":[
        {
            "category":"Building & Trades",
            "subcategory":"Construction",
            "type":"Services"
        }
    ],
    "sg:phone":"+1 502 367 2203",
    "sg:postcode":"40214",
    "sg:province":"KY",
    "sg:tags":[
        "steel",
        "erectors"
    ],
    "wof:name":"Trinity Erectors Inc",
    "wof:placetype":"venue"
},
  "geometry": {"coordinates":[-85.765291,38.158557],"type":"Point"}
}