{
  "type": "Feature",
  "properties": {
    "addr:full":"103 S Court St Scottsville KY 42164",
    "addr:housenumber":"103",
    "addr:postcode":"42164",
    "addr:street":"S Court St",
    "iso:country":"US",
    "sg:address":"103 S Court St",
    "sg:city":"Scottsville",
    "sg:classifiers":[
        {
            "category":"Sports & Exercise",
            "subcategory":"Gym",
            "type":"Entertainment"
        }
    ],
    "sg:phone":"+1 270 237 9849",
    "sg:postcode":"42164",
    "sg:province":"KY",
    "sg:tags":[
        "club",
        "health",
        "studio",
        "gymnasium"
    ],
    "wof:name":"Curves For Women",
    "wof:placetype":"venue"
},
  "geometry": {"coordinates":[-86.19021600000001,36.75135],"type":"Point"}
}