{
  "type": "Feature",
  "properties": {
    "addr:full":"3215 Irvin Cobb Dr Paducah KY 42003",
    "addr:housenumber":"3215",
    "addr:postcode":"42003",
    "addr:street":"Irvin Cobb Dr",
    "iso:country":"US",
    "sg:address":"3215 Irvin Cobb Dr",
    "sg:city":"Paducah",
    "sg:classifiers":[
        {
            "category":"Banks & Credit Unions",
            "subcategory":"Bank",
            "type":"Services"
        }
    ],
    "sg:phone":"+1 270 443 9540",
    "sg:postcode":"42003",
    "sg:province":"KY",
    "sg:tags":[
        "cashing",
        "check"
    ],
    "wof:name":"Check 'n Go",
    "wof:placetype":"venue"
},
  "geometry": {"coordinates":[-88.56931,37.053401],"type":"Point"}
}