{
  "type": "Feature",
  "properties": {
    "iso:country":"US",
    "sg:address":"1027 Wetterau Ave",
    "sg:city":"Louisville",
    "sg:classifiers":[
        {
            "category":"Shopping",
            "subcategory":"Musical Instruments",
            "type":"Retail Goods"
        }
    ],
    "sg:phone":"+1 502 635 2735",
    "sg:postcode":"40217",
    "sg:province":"KY",
    "wof:name":"Acoustic Woods Custom Drums",
    "wof:placetype":"venue"
},
  "geometry": {"coordinates":[-85.734296,38.223903],"type":"Point"}
}