{
  "type": "Feature",
  "properties": {
    "iso:country":"US",
    "sg:address":"7500 Sussex Dr",
    "sg:city":"Florence",
    "sg:classifiers":[
        {
            "category":"Sports & Exercise",
            "subcategory":"Bowling",
            "type":"Entertainment"
        }
    ],
    "sg:phone":"+1 859 371 9550",
    "sg:postcode":"41042",
    "sg:province":"KY",
    "sg:tags":[
        "center"
    ],
    "wof:name":"Florence Bowl Inc",
    "wof:placetype":"venue"
},
  "geometry": {"coordinates":[-84.63429499999999,38.985092],"type":"Point"}
}