{
  "type": "Feature",
  "properties": {
    "iso:country":"US",
    "sg:address":"2600 Stephanie Rd",
    "sg:city":"Russellville",
    "sg:classifiers":[
        {
            "category":"Organizations",
            "subcategory":"Religious Organization",
            "type":"Services"
        }
    ],
    "sg:phone":"+1 270 726 8440",
    "sg:postcode":"42276",
    "sg:province":"KY",
    "sg:tags":[
        "church"
    ],
    "wof:name":"New Union Baptist Church",
    "wof:placetype":"venue"
},
  "geometry": {"coordinates":[-86.965693,36.835932],"type":"Point"}
}