{
  "type": "Feature",
  "properties": {
    "iso:country":"US",
    "sg:address":"266 Main St",
    "sg:city":"Vicco",
    "sg:classifiers":[
        {
            "category":"Shopping",
            "subcategory":"Department Store",
            "type":"Retail Goods"
        }
    ],
    "sg:phone":"+1 606 476 2337",
    "sg:postcode":"41773",
    "sg:province":"KY",
    "sg:tags":[
        "shop"
    ],
    "wof:name":"Value Dollar",
    "wof:placetype":"venue"
},
  "geometry": {"coordinates":[-83.064734,37.214459],"type":"Point"}
}