{
  "type": "Feature",
  "properties": {
    "iso:country":"US",
    "sg:address":"4575 Elkhorn Creek",
    "sg:city":"Elkhorn City",
    "sg:classifiers":[
        {
            "category":"Retail",
            "subcategory":"Auto Repair",
            "type":"Services"
        }
    ],
    "sg:phone":"+1 606 754 5860",
    "sg:postcode":"41522",
    "sg:province":"KY",
    "sg:tags":[
        "repairing",
        "automobile"
    ],
    "wof:name":"Gibson's Auto Repair Inc",
    "wof:placetype":"venue"
},
  "geometry": {"coordinates":[-82.40479000000001,37.272333],"type":"Point"}
}