{
  "type": "Feature",
  "properties": {
    "addr:full":"315 Peterson Dr Elizabethtown KY 42701",
    "addr:housenumber":"315",
    "addr:postcode":"42701",
    "addr:street":"Peterson Dr",
    "iso:country":"US",
    "sg:address":"315 Peterson Dr",
    "sg:city":"Elizabethtown",
    "sg:classifiers":[
        {
            "category":"Building & Trades",
            "subcategory":"Plumbing",
            "type":"Services"
        }
    ],
    "sg:phone":"+1 270 737 4852",
    "sg:postcode":"42701",
    "sg:province":"KY",
    "sg:tags":[
        "contractor",
        "conditioning",
        "mechanical"
    ],
    "wof:name":"Schardein Mechanical Contrs",
    "wof:placetype":"venue"
},
  "geometry": {"coordinates":[-85.906749,37.684817],"type":"Point"}
}