{
  "type": "Feature",
  "properties": {
    "addr:full":"204 W Muir Ave Bardstown KY 40004",
    "addr:housenumber":"204",
    "addr:postcode":"40004",
    "addr:street":"W Muir Ave",
    "iso:country":"US",
    "sg:address":"204 W Muir Ave",
    "sg:city":"Bardstown",
    "sg:classifiers":[
        {
            "category":"Manufacturing",
            "subcategory":"Pet Food",
            "type":"Manufacturing & Wholesale Goods"
        }
    ],
    "sg:phone":"+1 502 348 3949",
    "sg:postcode":"40004",
    "sg:province":"KY",
    "sg:tags":[
        "feed"
    ],
    "wof:name":"Bardstown Mills",
    "wof:placetype":"venue"
},
  "geometry": {"coordinates":[-85.471084,37.807139],"type":"Point"}
}