{
  "type": "Feature",
  "properties": {
    "addr:full":"1070 State Hwy 289 Lebanon KY 40033",
    "addr:housenumber":"1070",
    "addr:postcode":"40033",
    "addr:street":"State Hwy 289",
    "iso:country":"US",
    "sg:address":"1070 State Hwy 289",
    "sg:city":"Lebanon",
    "sg:classifiers":[
        {
            "category":"Farming",
            "subcategory":"Farm",
            "type":"Manufacturing & Wholesale Goods"
        }
    ],
    "sg:phone":"+1 270 692 3410",
    "sg:postcode":"40033",
    "sg:province":"KY",
    "sg:tags":[
        "crop",
        "general"
    ],
    "wof:name":"Buckman Farms",
    "wof:placetype":"venue"
},
  "geometry": {"coordinates":[-85.302685,37.512642],"type":"Point"}
}