{
  "type": "Feature",
  "properties": {
    "iso:country":"US",
    "sg:address":"11371 Decimal Dr",
    "sg:city":"Jeffersontown",
    "sg:classifiers":[
        {
            "category":"Professional",
            "subcategory":"Employment Agencies",
            "type":"Services"
        }
    ],
    "sg:phone":"+1 502 261 9398",
    "sg:postcode":"40299",
    "sg:province":"KY",
    "sg:tags":[
        "leasing"
    ],
    "wof:name":"Tradesmen International Inc",
    "wof:placetype":"venue"
},
  "geometry": {"coordinates":[-85.55049099999999,38.21713],"type":"Point"}
}