{
  "type": "Feature",
  "properties": {
    "iso:country":"US",
    "sg:address":"990 Frost Ave",
    "sg:city":"Bardstown",
    "sg:classifiers":[
        {
            "category":"Retail",
            "subcategory":"Auto Repair",
            "type":"Services"
        }
    ],
    "sg:phone":"+1 502 348 4674",
    "sg:postcode":"40004",
    "sg:province":"KY",
    "sg:tags":[
        "glass",
        "coating",
        "tinting"
    ],
    "wof:name":"Dave's Tint Shop",
    "wof:placetype":"venue"
},
  "geometry": {"coordinates":[-85.469669,37.825319],"type":"Point"}
}