{
  "type": "Feature",
  "properties": {
    "iso:country":"US",
    "sg:address":"15 S Main St",
    "sg:city":"Walton",
    "sg:classifiers":[
        {
            "category":"Personal",
            "subcategory":"Beauty Salon",
            "type":"Services"
        }
    ],
    "sg:phone":"+1 859 485 7670",
    "sg:postcode":"41094",
    "sg:province":"KY",
    "wof:name":"Doll House Beauty Salon",
    "wof:placetype":"venue"
},
  "geometry": {"coordinates":[-84.61060000000001,38.864732],"type":"Point"}
}