{
  "type": "Feature",
  "properties": {
    "addr:full":"3868 N Mayo Trl Pikeville KY 41501",
    "addr:housenumber":"3868",
    "addr:postcode":"41501",
    "addr:street":"N Mayo Trl",
    "iso:country":"US",
    "sg:address":"3868 N Mayo Trl",
    "sg:city":"Pikeville",
    "sg:classifiers":[
        {
            "category":"Restaurant",
            "type":"Food & Drink"
        }
    ],
    "sg:menulink":"http://www.allmenus.com/ky/pikeville/173565-wendys/menu/",
    "sg:phone":"+1 606 432 4484",
    "sg:postcode":"41501",
    "sg:province":"KY",
    "sg:tags":[
        "burger",
        "american",
        "soup"
    ],
    "wof:name":"Wendy's",
    "wof:placetype":"venue"
},
  "geometry": {"coordinates":[-82.57491400000001,37.528194],"type":"Point"}
}