{
  "type": "Feature",
  "properties": {
    "iso:country":"US",
    "sg:address":"3520 New Hartford Rd",
    "sg:city":"Owensboro",
    "sg:classifiers":[
        {
            "category":"Professional",
            "subcategory":"Accounting & Tax Preparation",
            "type":"Services"
        }
    ],
    "sg:phone":"+1 270 684 5158",
    "sg:postcode":"42303",
    "sg:province":"KY",
    "sg:tags":[
        "accountant"
    ],
    "wof:name":"Robert F Kuphal CPA",
    "wof:placetype":"venue"
},
  "geometry": {"coordinates":[-87.091758,37.737685],"type":"Point"}
}