{
  "type": "Feature",
  "properties": {
    "iso:country":"US",
    "sg:address":"650 Yates Dr",
    "sg:city":"Radcliff",
    "sg:classifiers":[
        {
            "category":"Professional",
            "subcategory":"Employment Agencies",
            "type":"Services"
        }
    ],
    "sg:phone":"+1 270 351 0928",
    "sg:postcode":"40160",
    "sg:province":"KY",
    "sg:tags":[
        "medical"
    ],
    "wof:name":"Brenda Arnett",
    "wof:placetype":"venue"
},
  "geometry": {"coordinates":[-85.966133,37.842766],"type":"Point"}
}