{
  "type": "Feature",
  "properties": {
    "iso:country":"US",
    "sg:address":"688 Walker Parke Rd",
    "sg:city":"Richmond",
    "sg:classifiers":[
        {
            "category":"Organizations",
            "subcategory":"Membership Organization",
            "type":"Services"
        }
    ],
    "sg:phone":"+1 859 623 6045",
    "sg:postcode":"40475",
    "sg:province":"KY",
    "wof:name":"Homes For Greyhounds",
    "wof:placetype":"venue"
},
  "geometry": {"coordinates":[-84.18947199999999,37.839098],"type":"Point"}
}