{
  "type": "Feature",
  "properties": {
    "iso:country":"US",
    "sg:address":"1047 S 15th St",
    "sg:city":"Louisville",
    "sg:classifiers":[
        {
            "category":"Wholesale",
            "subcategory":"Farm Supplies",
            "type":"Manufacturing & Wholesale Goods"
        }
    ],
    "sg:phone":"+1 502 585 5321",
    "sg:postcode":"40210",
    "sg:province":"KY",
    "sg:tags":[
        "grain"
    ],
    "wof:name":"Consolidated Grain & Barge Co",
    "wof:placetype":"venue"
},
  "geometry": {"coordinates":[-85.77779099999999,38.239811],"type":"Point"}
}