{
  "type": "Feature",
  "properties": {
    "addr:full":"5215 Dixie Hwy Louisville KY 40216",
    "addr:housenumber":"5215",
    "addr:postcode":"40216",
    "addr:street":"Dixie Hwy",
    "iso:country":"US",
    "sg:address":"5215 Dixie Hwy",
    "sg:city":"Louisville",
    "sg:classifiers":[
        {
            "category":"Personal",
            "type":"Services"
        },
        {
            "category":"Retail",
            "subcategory":"Storage",
            "type":"Services"
        }
    ],
    "sg:phone":"+1 866 320 6309",
    "sg:postcode":"40216",
    "sg:province":"KY",
    "sg:tags":[
        "self",
        "full",
        "commercial",
        "mover",
        "household"
    ],
    "sg:website":"http://www.unclebobs.com/stores/UB701/?source=Yellowpages.com&howheard=ISM",
    "wof:name":"Uncle Bob's Self Storage",
    "wof:placetype":"venue"
},
  "geometry": {"coordinates":[-85.83113899999999,38.163189],"type":"Point"}
}