{
  "type": "Feature",
  "properties": {
    "iso:country":"US",
    "sg:address":"301 York St",
    "sg:city":"Louisville",
    "sg:classifiers":[
        {
            "category":"Education",
            "subcategory":"Library",
            "type":"Public Place"
        }
    ],
    "sg:phone":"+1 502 574 1611",
    "sg:postcode":"40203",
    "sg:province":"KY",
    "sg:website":"www.lfpl.org",
    "wof:name":"Louisville Free Public Library",
    "wof:placetype":"venue"
},
  "geometry": {"coordinates":[-85.757882,38.244141],"type":"Point"}
}