{
  "type": "Feature",
  "properties": {
    "iso:country":"US",
    "sg:address":"7690 Burlington Pike",
    "sg:city":"Florence",
    "sg:classifiers":[
        {
            "category":"Autos & Motor Vehicles",
            "subcategory":"Fuel & Gas Station",
            "type":"Retail Goods"
        },
        {
            "category":"Food & Beverages",
            "subcategory":"Groceries & Convenience Stores",
            "type":"Retail Goods"
        }
    ],
    "sg:phone":"+1 859 371 6912",
    "sg:postcode":"41042",
    "sg:province":"KY",
    "sg:website":"www.speedway.com",
    "wof:name":"Speedway Petroleum Corp",
    "wof:placetype":"venue"
},
  "geometry": {"coordinates":[-84.64263099999999,39.000945],"type":"Point"}
}