{
  "type": "Feature",
  "properties": {
    "addr:full":"102 Summertree Dr Nicholasville KY 40356",
    "addr:housenumber":"102",
    "addr:postcode":"40356",
    "addr:street":"Summertree Dr",
    "iso:country":"US",
    "sg:address":"102 Summertree Dr",
    "sg:city":"Nicholasville",
    "sg:classifiers":[
        {
            "category":"Wholesale",
            "subcategory":"Machinery & Supplies",
            "type":"Manufacturing & Wholesale Goods"
        }
    ],
    "sg:phone":"+1 859 223 9179",
    "sg:postcode":"40356",
    "sg:province":"KY",
    "sg:tags":[
        "industrial"
    ],
    "wof:name":"Joseph Cowley LTD Co",
    "wof:placetype":"venue"
},
  "geometry": {"coordinates":[-84.584693,37.970599],"type":"Point"}
}