{
  "type": "Feature",
  "properties": {
    "addr:full":"128 Jamestown Rd Columbia KY 42728",
    "addr:housenumber":"128",
    "addr:postcode":"42728",
    "addr:street":"Jamestown Rd",
    "iso:country":"US",
    "sg:address":"128 Jamestown Rd",
    "sg:city":"Columbia",
    "sg:classifiers":[
        {
            "category":"Shopping",
            "type":"Retail Goods"
        }
    ],
    "sg:phone":"+1 270 384 2555",
    "sg:postcode":"42728",
    "sg:province":"KY",
    "sg:tags":[
        "telephone",
        "cellular"
    ],
    "wof:name":"Cellular One",
    "wof:placetype":"venue"
},
  "geometry": {"coordinates":[-85.305257,37.10187],"type":"Point"}
}