{
  "type": "Feature",
  "properties": {
    "addr:full":"2006 Lynn Way Louisville KY 40222",
    "addr:housenumber":"2006",
    "addr:postcode":"40222",
    "addr:street":"Lynn Way",
    "iso:country":"US",
    "sg:address":"2006 Lynn Way",
    "sg:city":"Louisville",
    "sg:classifiers":[
        {
            "category":"Building & Trades",
            "subcategory":"Construction",
            "type":"Services"
        }
    ],
    "sg:phone":"+1 502 339 7736",
    "sg:postcode":"40222",
    "sg:province":"KY",
    "wof:name":"Maintenance Done Best Co",
    "wof:placetype":"venue"
},
  "geometry": {"coordinates":[-85.619285,38.279446],"type":"Point"}
}