{
  "type": "Feature",
  "properties": {
    "iso:country":"US",
    "sg:address":"330 Bewley Rd",
    "sg:city":"Vine Grove",
    "sg:classifiers":[
        {
            "category":"Building & Trades",
            "subcategory":"Construction",
            "type":"Services"
        }
    ],
    "sg:phone":"+1 270 828 4931",
    "sg:postcode":"40175",
    "sg:province":"KY",
    "sg:tags":[
        "home",
        "improvement"
    ],
    "wof:name":"Marty Smith Construction",
    "wof:placetype":"venue"
},
  "geometry": {"coordinates":[-86.03931,37.811768],"type":"Point"}
}