{
  "type": "Feature",
  "properties": {
    "iso:country":"US",
    "sg:address":"200 Stephens Dr",
    "sg:city":"Nicholasville",
    "sg:classifiers":[
        {
            "category":"Manufacturing",
            "subcategory":"Paper Products",
            "type":"Manufacturing & Wholesale Goods"
        }
    ],
    "sg:phone":"+1 859 296 8606",
    "sg:postcode":"40356",
    "sg:province":"KY",
    "sg:tags":[
        "corrugated",
        "solid",
        "fiber",
        "box"
    ],
    "wof:name":"Gulf States Paper Corp",
    "wof:placetype":"venue"
},
  "geometry": {"coordinates":[-84.581548,37.887724],"type":"Point"}
}