{
  "type": "Feature",
  "properties": {
    "iso:country":"US",
    "sg:address":"5513 Mariemont Rd",
    "sg:city":"Pleasure Rdg Pk",
    "sg:classifiers":[
        {
            "category":"Building & Trades",
            "subcategory":"Plumbing",
            "type":"Services"
        }
    ],
    "sg:phone":"+1 502 447 2291",
    "sg:postcode":"40258",
    "sg:province":"KY",
    "sg:tags":[
        "septic"
    ],
    "wof:name":"Valley Septic Tank",
    "wof:placetype":"venue"
},
  "geometry": {"coordinates":[-85.883836,38.173142],"type":"Point"}
}