{
  "type": "Feature",
  "properties": {
    "iso:country":"US",
    "sg:address":"389 Tollage Creek",
    "sg:city":"Pikeville",
    "sg:classifiers":[
        {
            "category":"Wholesale",
            "subcategory":"Machinery & Supplies",
            "type":"Manufacturing & Wholesale Goods"
        }
    ],
    "sg:phone":"+1 606 432 1044",
    "sg:postcode":"41501",
    "sg:province":"KY",
    "sg:tags":[
        "equipment",
        "oil",
        "well"
    ],
    "wof:name":"Mc Junkin Appalachian",
    "wof:placetype":"venue"
},
  "geometry": {"coordinates":[-82.532124,37.514584],"type":"Point"}
}