{
  "type": "Feature",
  "properties": {
    "addr:full":"101 Tug Branch Rd Clay City KY 40312",
    "addr:housenumber":"101",
    "addr:postcode":"40312",
    "addr:street":"Tug Branch Rd",
    "iso:country":"US",
    "sg:address":"101 Tug Branch Rd",
    "sg:city":"Clay City",
    "sg:classifiers":[
        {
            "category":"Manufacturing",
            "subcategory":"Toys & Sporting Goods",
            "type":"Manufacturing & Wholesale Goods"
        }
    ],
    "sg:phone":"+1 606 663 2734",
    "sg:postcode":"40312",
    "sg:province":"KY",
    "sg:tags":[
        "equipment",
        "archery",
        "supply"
    ],
    "sg:website":"www.scottarchery.com",
    "wof:name":"Scott Archery Mfg Inc",
    "wof:placetype":"venue"
},
  "geometry": {"coordinates":[-83.96091,37.860007],"type":"Point"}
}