{
  "type": "Feature",
  "properties": {
    "iso:country":"US",
    "sg:address":"536 Noel Dr",
    "sg:city":"Hopkinsville",
    "sg:classifiers":[
        {
            "category":"Government",
            "subcategory":"Office",
            "type":"Public Place"
        }
    ],
    "sg:phone":"+1 270 885 5066",
    "sg:postcode":"42240",
    "sg:province":"KY",
    "sg:tags":[
        "federal"
    ],
    "wof:name":"US Consolidated Farm Svc Agcy",
    "wof:placetype":"venue"
},
  "geometry": {"coordinates":[-87.51655100000001,36.856356],"type":"Point"}
}