{
  "type": "Feature",
  "properties": {
    "iso:country":"US",
    "sg:address":"2960 Fairview Dr",
    "sg:city":"Owensboro",
    "sg:classifiers":[
        {
            "category":"Freight",
            "type":"Transportation"
        }
    ],
    "sg:phone":"+1 270 926 9847",
    "sg:postcode":"42303",
    "sg:province":"KY",
    "sg:tags":[
        "commercial",
        "storage"
    ],
    "wof:name":"Store-It-All",
    "wof:placetype":"venue"
},
  "geometry": {"coordinates":[-87.06111799999999,37.746366],"type":"Point"}
}