{
  "type": "Feature",
  "properties": {
    "addr:full":"213 W 10th St Owensboro KY 42303",
    "addr:housenumber":"213",
    "addr:postcode":"42303",
    "addr:street":"W 10Th St",
    "iso:country":"US",
    "sg:address":"213 W 10th St",
    "sg:city":"Owensboro",
    "sg:classifiers":[
        {
            "category":"Food & Beverages",
            "subcategory":"Specialty",
            "type":"Retail Goods"
        }
    ],
    "sg:phone":"+1 270 926 4413",
    "sg:postcode":"42303",
    "sg:province":"KY",
    "sg:tags":[
        "water",
        "bulk",
        "company"
    ],
    "wof:name":"Mountain Valley Water Co",
    "wof:placetype":"venue"
},
  "geometry": {"coordinates":[-87.11215799999999,37.766612],"type":"Point"}
}