{
  "type": "Feature",
  "properties": {
    "addr:full":"1322 S 17th St Louisville KY 40210",
    "addr:housenumber":"1322",
    "addr:postcode":"40210",
    "addr:street":"S 17Th St",
    "iso:country":"US",
    "sg:address":"1322 S 17th St",
    "sg:city":"Louisville",
    "sg:classifiers":[
        {
            "category":"Organizations",
            "subcategory":"Religious Organization",
            "type":"Services"
        }
    ],
    "sg:phone":"+1 502 634 5420",
    "sg:postcode":"40210",
    "sg:province":"KY",
    "sg:tags":[
        "church"
    ],
    "wof:name":"Sanction House Missionary Chrc",
    "wof:placetype":"venue"
},
  "geometry": {"coordinates":[-85.782529,38.233956],"type":"Point"}
}