{
  "type": "Feature",
  "properties": {
    "iso:country":"US",
    "sg:address":"8231 Copper Creek Dr",
    "sg:city":"Louisville",
    "sg:classifiers":[
        {
            "category":"Professional",
            "subcategory":"Computer Services",
            "type":"Services"
        }
    ],
    "sg:phone":"+1 502 339 8704",
    "sg:postcode":"40222",
    "sg:province":"KY",
    "sg:tags":[
        "related"
    ],
    "wof:name":"Catalyst Consulting",
    "wof:placetype":"venue"
},
  "geometry": {"coordinates":[-85.602199,38.251167],"type":"Point"}
}