{
  "type": "Feature",
  "properties": {
    "iso:country":"US",
    "sg:address":"231 E Main St",
    "sg:city":"Frankfort",
    "sg:classifiers":[
        {
            "category":"Health Services",
            "subcategory":"Clinic",
            "type":"Services"
        }
    ],
    "sg:phone":"+1 502 564 7382",
    "sg:postcode":"40601",
    "sg:province":"KY",
    "sg:tags":[
        "specialty",
        "outpatient"
    ],
    "wof:name":"Franklin County Health Depart",
    "wof:placetype":"venue"
},
  "geometry": {"coordinates":[-84.865475,38.197974],"type":"Point"}
}