{
  "type": "Feature",
  "properties": {
    "iso:country":"US",
    "sg:address":"4229 Taylorsville Rd",
    "sg:city":"Louisville",
    "sg:classifiers":[
        {
            "category":"Shopping",
            "subcategory":"Party Supplies",
            "type":"Retail Goods"
        }
    ],
    "sg:phone":"+1 502 429 9922",
    "sg:postcode":"40220",
    "sg:province":"KY",
    "sg:tags":[
        "decorating",
        "convention"
    ],
    "wof:name":"Fern George E Co",
    "wof:placetype":"venue"
},
  "geometry": {"coordinates":[-85.61391399999999,38.219261],"type":"Point"}
}