{
  "type": "Feature",
  "properties": {
    "iso:country":"US",
    "sg:address":"14552 State Hwy 38",
    "sg:city":"Evarts",
    "sg:classifiers":[
        {
            "category":"Organizations",
            "subcategory":"Religious Organization",
            "type":"Services"
        }
    ],
    "sg:phone":"+1 606 837 9628",
    "sg:postcode":"40828",
    "sg:province":"KY",
    "sg:tags":[
        "clergy"
    ],
    "wof:name":"Bill Moore",
    "wof:placetype":"venue"
},
  "geometry": {"coordinates":[-83.11798899999999,36.897627],"type":"Point"}
}