{
  "type": "Feature",
  "properties": {
    "addr:full":"102 Daventry Ln Louisville KY 40223",
    "addr:housenumber":"102",
    "addr:postcode":"40223",
    "addr:street":"Daventry Ln",
    "iso:country":"US",
    "sg:address":"102 Daventry Ln",
    "sg:city":"Louisville",
    "sg:classifiers":[
        {
            "category":"Real Estate",
            "subcategory":"Real Estate Services",
            "type":"Services"
        }
    ],
    "sg:phone":"+1 502 326 2998",
    "sg:postcode":"40223",
    "sg:province":"KY",
    "sg:tags":[
        "company",
        "title"
    ],
    "wof:name":"Derby City Title",
    "wof:placetype":"venue"
},
  "geometry": {"coordinates":[-85.575402,38.247649],"type":"Point"}
}