{
  "type": "Feature",
  "properties": {
    "iso:country":"US",
    "sg:address":"305 Culpepper Rd",
    "sg:city":"Lexington",
    "sg:classifiers":[
        {
            "category":"Retail",
            "subcategory":"Auto Repair",
            "type":"Services"
        }
    ],
    "sg:phone":"+1 859 335 1323",
    "sg:postcode":"40502",
    "sg:province":"KY",
    "wof:name":"All Fleet Maintance Company",
    "wof:placetype":"venue"
},
  "geometry": {"coordinates":[-84.47806199999999,38.022541],"type":"Point"}
}