{
  "type": "Feature",
  "properties": {
    "iso:country":"US",
    "sg:address":"3740 Magruder Rd",
    "sg:city":"Kevil",
    "sg:classifiers":[
        {
            "category":"Recreation",
            "type":"Entertainment"
        }
    ],
    "sg:phone":"+1 270 488 3444",
    "sg:postcode":"42053",
    "sg:province":"KY",
    "wof:name":"Willoway Stables",
    "wof:placetype":"venue"
},
  "geometry": {"coordinates":[-88.82189099999999,37.071191],"type":"Point"}
}