{
  "type": "Feature",
  "properties": {
    "iso:country":"US",
    "sg:address":"342 Old Whitley Rd",
    "sg:city":"London",
    "sg:classifiers":[
        {
            "category":"Government",
            "subcategory":"Office",
            "type":"Public Place"
        }
    ],
    "sg:phone":"+1 606 864 7391",
    "sg:postcode":"40744",
    "sg:province":"KY",
    "sg:website":"www.cvadd.org",
    "wof:name":"Cumberland Valley Area Dev",
    "wof:placetype":"venue"
},
  "geometry": {"coordinates":[-84.097055,37.105578],"type":"Point"}
}