{
  "type": "Feature",
  "properties": {
    "iso:country":"US",
    "sg:address":"2620 Gleeson Ln",
    "sg:city":"Jeffersontown",
    "sg:classifiers":[
        {
            "category":"Health Services",
            "subcategory":"Doctor",
            "type":"Services"
        }
    ],
    "sg:phone":"+1 502 261 0991",
    "sg:postcode":"40299",
    "sg:province":"KY",
    "sg:tags":[
        "dentist"
    ],
    "wof:name":"J-Town Comprehensive Dental",
    "wof:placetype":"venue"
},
  "geometry": {"coordinates":[-85.584064,38.206948],"type":"Point"}
}