{
  "type": "Feature",
  "properties": {
    "iso:country":"US",
    "sg:address":"139 State Hwy 1624",
    "sg:city":"Flatgap",
    "sg:classifiers":[
        {
            "category":"Autos & Motor Vehicles",
            "subcategory":"Automobile Sales",
            "type":"Retail Goods"
        }
    ],
    "sg:phone":"+1 606 265 5415",
    "sg:postcode":"41219",
    "sg:province":"KY",
    "sg:tags":[
        "car",
        "dealer"
    ],
    "wof:name":"Red Barn Auto Sales",
    "wof:placetype":"venue"
},
  "geometry": {"coordinates":[-82.892051,37.963937],"type":"Point"}
}