{
  "type": "Feature",
  "properties": {
    "iso:country":"US",
    "sg:address":"444 E Main St",
    "sg:city":"Lexington",
    "sg:classifiers":[
        {
            "category":"Education",
            "subcategory":"Vocational School",
            "type":"Public Place"
        }
    ],
    "sg:phone":"+1 859 226 9625",
    "sg:postcode":"40507",
    "sg:province":"KY",
    "sg:tags":[
        "training",
        "computer"
    ],
    "sg:website":"www.orcca.com",
    "wof:name":"Orcca Technologies",
    "wof:placetype":"venue"
},
  "geometry": {"coordinates":[-84.490628,38.040708],"type":"Point"}
}