{
  "type": "Feature",
  "properties": {
    "iso:country":"US",
    "sg:address":"8004 Brookglen Ct",
    "sg:city":"Louisville",
    "sg:classifiers":[
        {
            "category":"Building & Trades",
            "subcategory":"Construction",
            "type":"Services"
        }
    ],
    "sg:phone":"+1 502 495 6910",
    "sg:postcode":"40220",
    "sg:province":"KY",
    "sg:tags":[
        "house",
        "builder",
        "operative"
    ],
    "wof:name":"Mike Cothran Builder Inc",
    "wof:placetype":"venue"
},
  "geometry": {"coordinates":[-85.610097,38.194003],"type":"Point"}
}