{
  "type": "Feature",
  "properties": {
    "addr:full":"2000 N Elm St Henderson KY 42420",
    "addr:housenumber":"2000",
    "addr:postcode":"42420",
    "addr:street":"N Elm St",
    "iso:country":"US",
    "sg:address":"2000 N Elm St",
    "sg:city":"Henderson",
    "sg:classifiers":[
        {
            "category":"Health Services",
            "subcategory":"Doctor",
            "type":"Services"
        }
    ],
    "sg:phone":"+1 270 869 9900",
    "sg:postcode":"42420",
    "sg:province":"KY",
    "sg:tags":[
        "physician",
        "surgeon"
    ],
    "wof:name":"Advanced Pain Care Clinics Pcs",
    "wof:placetype":"venue"
},
  "geometry": {"coordinates":[-87.575518,37.864778],"type":"Point"}
}