{
  "type": "Feature",
  "properties": {
    "iso:country":"US",
    "sg:address":"3430 Lone Oak Rd",
    "sg:city":"Paducah",
    "sg:classifiers":[
        {
            "category":"Social Services",
            "subcategory":"Child Care",
            "type":"Services"
        }
    ],
    "sg:phone":"+1 270 554 3313",
    "sg:postcode":"42003",
    "sg:province":"KY",
    "wof:name":"Daytime Mom's Little Blessings",
    "wof:placetype":"venue"
},
  "geometry": {"coordinates":[-88.670489,37.030319],"type":"Point"}
}