{
  "type": "Feature",
  "properties": {
    "iso:country":"US",
    "sg:address":"218 Main St",
    "sg:city":"Falmouth",
    "sg:classifiers":[
        {
            "category":"Shopping",
            "subcategory":"Hobbies, Toys, & Games",
            "type":"Retail Goods"
        }
    ],
    "sg:phone":"+1 859 654 8888",
    "sg:postcode":"41040",
    "sg:province":"KY",
    "sg:tags":[
        "supply"
    ],
    "wof:name":"Jerrys Game Room",
    "wof:placetype":"venue"
},
  "geometry": {"coordinates":[-84.32946699999999,38.677786],"type":"Point"}
}