{
  "type": "Feature",
  "properties": {
    "iso:country":"US",
    "sg:address":"1104 Bob McCullough Dr",
    "sg:city":"Ashland",
    "sg:classifiers":[
        {
            "category":"Education",
            "subcategory":"School",
            "type":"Public Place"
        }
    ],
    "sg:phone":"+1 606 928 4141",
    "sg:postcode":"41102",
    "sg:province":"KY",
    "wof:name":"Boyd County Schools",
    "wof:placetype":"venue"
},
  "geometry": {"coordinates":[-82.684366,38.444633],"type":"Point"}
}