{
  "type": "Feature",
  "properties": {
    "iso:country":"US",
    "sg:address":"108 Main St",
    "sg:city":"Raywick",
    "sg:classifiers":[
        {
            "category":"Organizations",
            "subcategory":"Religious Organization",
            "type":"Services"
        }
    ],
    "sg:phone":"+1 270 692 2245",
    "sg:postcode":"40060",
    "sg:province":"KY",
    "sg:tags":[
        "church"
    ],
    "wof:name":"St Francis Xaviers Catholic Ch",
    "wof:placetype":"venue"
},
  "geometry": {"coordinates":[-85.42961200000001,37.561192],"type":"Point"}
}