{
  "type": "Feature",
  "properties": {
    "addr:full":"1328 S 4th St Louisville KY 40208",
    "addr:housenumber":"1328",
    "addr:postcode":"40208",
    "addr:street":"S 4Th St",
    "iso:country":"US",
    "sg:address":"1328 S 4th St",
    "sg:city":"Louisville",
    "sg:classifiers":[
        {
            "category":"Professional",
            "subcategory":"Art Services",
            "type":"Services"
        }
    ],
    "sg:phone":"+1 502 637 3281",
    "sg:postcode":"40208",
    "sg:province":"KY",
    "sg:tags":[
        "graphic",
        "designer"
    ],
    "wof:name":"Articulations Graphic Design",
    "wof:placetype":"venue"
},
  "geometry": {"coordinates":[-85.760912,38.231566],"type":"Point"}
}