{
  "type": "Feature",
  "properties": {
    "iso:country":"US",
    "sg:address":"235 Johnson & Riley Rd",
    "sg:city":"Calvert City",
    "sg:classifiers":[
        {
            "category":"Building & Trades",
            "subcategory":"Electrical",
            "type":"Services"
        }
    ],
    "sg:phone":"+1 270 395 7145",
    "sg:postcode":"42029",
    "sg:province":"KY",
    "sg:tags":[
        "electric",
        "contractor"
    ],
    "wof:name":"Riley Electric Co",
    "wof:placetype":"venue"
},
  "geometry": {"coordinates":[-88.36842300000001,37.00703],"type":"Point"}
}