{
  "type": "Feature",
  "properties": {
    "addr:full":"102 Restk Ct Nicholasville KY 40356",
    "addr:housenumber":"102",
    "addr:postcode":"40356",
    "addr:street":"Restk Ct",
    "iso:country":"US",
    "sg:address":"102 Restk Ct",
    "sg:city":"Nicholasville",
    "sg:classifiers":[
        {
            "category":"Professional",
            "subcategory":"Management & Consulting",
            "type":"Services"
        }
    ],
    "sg:phone":"+1 859 885 4363",
    "sg:postcode":"40356",
    "sg:province":"KY",
    "sg:tags":[
        "biological",
        "consultant"
    ],
    "wof:name":"Macgregor John",
    "wof:placetype":"venue"
},
  "geometry": {"coordinates":[-84.575615,37.882457],"type":"Point"}
}