{
  "type": "Feature",
  "properties": {
    "iso:country":"US",
    "sg:address":"350 Whitetail Dr",
    "sg:city":"Taylorsville",
    "sg:classifiers":[
        {
            "category":"Building & Trades",
            "subcategory":"Construction",
            "type":"Services"
        }
    ],
    "sg:phone":"+1 502 477 6786",
    "sg:postcode":"40071",
    "sg:province":"KY",
    "sg:tags":[
        "house"
    ],
    "wof:name":"Tapps Home Improvement",
    "wof:placetype":"venue"
},
  "geometry": {"coordinates":[-85.261754,38.058754],"type":"Point"}
}