{
  "type": "Feature",
  "properties": {
    "addr:full":"1276 Anderson City Rd Lawrenceburg KY 40342",
    "addr:housenumber":"1276",
    "addr:postcode":"40342",
    "addr:street":"Anderson City Rd",
    "iso:country":"US",
    "sg:address":"1276 Anderson City Rd",
    "sg:city":"Lawrenceburg",
    "sg:classifiers":[
        {
            "category":"Personal",
            "subcategory":"Beauty Salon",
            "type":"Services"
        }
    ],
    "sg:phone":"+1 502 839 8787",
    "sg:postcode":"40342",
    "sg:province":"KY",
    "sg:tags":[
        "manicuring"
    ],
    "wof:name":"Pretty Nails",
    "wof:placetype":"venue"
},
  "geometry": {"coordinates":[-84.972979,37.987451],"type":"Point"}
}