{
  "type": "Feature",
  "properties": {
    "iso:country":"US",
    "sg:address":"703 S 3rd St",
    "sg:city":"Paducah",
    "sg:classifiers":[
        {
            "category":"Retail",
            "subcategory":"Auto Repair",
            "type":"Services"
        }
    ],
    "sg:phone":"+1 270 443 6434",
    "sg:postcode":"42003",
    "sg:province":"KY",
    "sg:tags":[
        "repairing",
        "automobile"
    ],
    "wof:name":"Denton's Garage",
    "wof:placetype":"venue"
},
  "geometry": {"coordinates":[-88.592812,37.080791],"type":"Point"}
}