{
  "type": "Feature",
  "properties": {
    "iso:country":"US",
    "sg:address":"5835 Raccoon Rd",
    "sg:city":"Raccoon",
    "sg:classifiers":[
        {
            "category":"Utilities",
            "subcategory":"Fuel Oil & Lpg",
            "type":"Services"
        }
    ],
    "sg:phone":"+1 606 433 1962",
    "sg:postcode":"41557",
    "sg:province":"KY",
    "sg:tags":[
        "coal",
        "coke"
    ],
    "wof:name":"Mc Coy Elkhorn Coal Corp",
    "wof:placetype":"venue"
},
  "geometry": {"coordinates":[-82.413281,37.478153],"type":"Point"}
}