{
  "type": "Feature",
  "properties": {
    "iso:country":"US",
    "sg:address":"1455 Campbell Ln",
    "sg:city":"Bowling Green",
    "sg:classifiers":[
        {
            "category":"Food & Beverages",
            "subcategory":"Groceries & Convenience Stores",
            "type":"Retail Goods"
        }
    ],
    "sg:phone":"+1 270 000 1111",
    "sg:postcode":"42104",
    "sg:province":"KY",
    "sg:tags":[
        "grocer"
    ],
    "wof:name":"Aldi",
    "wof:placetype":"venue"
},
  "geometry": {"coordinates":[-86.44302999999999,36.953036],"type":"Point"}
}