{
  "type": "Feature",
  "properties": {
    "iso:country":"US",
    "sg:address":"133 S 3rd St Ste 300",
    "sg:city":"Louisville",
    "sg:classifiers":[
        {
            "category":"Personal",
            "type":"Services"
        }
    ],
    "sg:phone":"+1 502 243 2045",
    "sg:postcode":"40202",
    "sg:province":"KY",
    "sg:tags":[
        "assistant"
    ],
    "wof:name":"Intermedia Partners Of Kentuck",
    "wof:placetype":"venue"
},
  "geometry": {"coordinates":[-85.75496200000001,38.255973],"type":"Point"}
}