{
  "type": "Feature",
  "properties": {
    "iso:country":"US",
    "sg:address":"4615 Wolfcreek Pkwy",
    "sg:city":"Louisville",
    "sg:classifiers":[
        {
            "category":"Professional",
            "subcategory":"Management & Consulting",
            "type":"Services"
        }
    ],
    "sg:phone":"+1 502 292 2277",
    "sg:postcode":"40241",
    "sg:province":"KY",
    "wof:name":"Lask G & Assoc Inc",
    "wof:placetype":"venue"
},
  "geometry": {"coordinates":[-85.603662,38.312951],"type":"Point"}
}