{
  "type": "Feature",
  "properties": {
    "addr:full":"102 W Main St Warsaw KY 41095",
    "addr:housenumber":"102",
    "addr:postcode":"41095",
    "addr:street":"W Main St",
    "iso:country":"US",
    "sg:address":"102 W Main St",
    "sg:city":"Warsaw",
    "sg:classifiers":[
        {
            "category":"Shopping",
            "subcategory":"Pharmacy",
            "type":"Retail Goods"
        }
    ],
    "sg:phone":"+1 859 567 4601",
    "sg:postcode":"41095",
    "sg:province":"KY",
    "wof:name":"Beringer Drug Ctr",
    "wof:placetype":"venue"
},
  "geometry": {"coordinates":[-84.903184,38.783109],"type":"Point"}
}