{
  "type": "Feature",
  "properties": {
    "iso:country":"US",
    "sg:address":"338 W 4th St",
    "sg:city":"Russellville",
    "sg:classifiers":[
        {
            "category":"Professional",
            "subcategory":"Lawyer & Legal Services",
            "type":"Services"
        }
    ],
    "sg:phone":"+1 270 726 3121",
    "sg:postcode":"42276",
    "sg:province":"KY",
    "sg:tags":[
        "attorney"
    ],
    "wof:name":"Wheeler & Wheeler",
    "wof:placetype":"venue"
},
  "geometry": {"coordinates":[-86.89026200000001,36.844798],"type":"Point"}
}