{
  "type": "Feature",
  "properties": {
    "iso:country":"US",
    "sg:address":"9256 US Hwy 62",
    "sg:city":"Calvert City",
    "sg:classifiers":[
        {
            "category":"Food & Beverages",
            "subcategory":"Groceries & Convenience Stores",
            "type":"Retail Goods"
        }
    ],
    "sg:phone":"+1 270 898 7202",
    "sg:postcode":"42029",
    "sg:province":"KY",
    "wof:name":"Possum Trot Quickmart",
    "wof:placetype":"venue"
},
  "geometry": {"coordinates":[-88.38529699999999,37.004847],"type":"Point"}
}