{
  "type": "Feature",
  "properties": {
    "addr:full":"9426 Brownsboro Rd Louisville KY 40241",
    "addr:housenumber":"9426",
    "addr:postcode":"40241",
    "addr:street":"Brownsboro Rd",
    "iso:country":"US",
    "sg:address":"9426 Brownsboro Rd",
    "sg:city":"Louisville",
    "sg:classifiers":[
        {
            "category":"Insurance",
            "subcategory":"Insurance Agent",
            "type":"Services"
        }
    ],
    "sg:phone":"+1 502 339 1517",
    "sg:postcode":"40241",
    "sg:province":"KY",
    "wof:name":"Terrence Bailey Insurance",
    "wof:placetype":"venue"
},
  "geometry": {"coordinates":[-85.57700699999999,38.305124],"type":"Point"}
}