{
  "type": "Feature",
  "properties": {
    "addr:full":"604 N Mulberry St Elizabethtown KY 42701",
    "addr:housenumber":"604",
    "addr:postcode":"42701",
    "addr:street":"N Mulberry St",
    "iso:country":"US",
    "sg:address":"604 N Mulberry St",
    "sg:city":"Elizabethtown",
    "sg:classifiers":[
        {
            "category":"Shopping",
            "type":"Retail Goods"
        }
    ],
    "sg:phone":"+1 270 735 9352",
    "sg:postcode":"42701",
    "sg:province":"KY",
    "sg:tags":[
        "hearing",
        "equipment",
        "supply",
        "impaired"
    ],
    "wof:name":"Heartland Better Hearing Inc",
    "wof:placetype":"venue"
},
  "geometry": {"coordinates":[-85.852321,37.701252],"type":"Point"}
}