{
  "type": "Feature",
  "properties": {
    "addr:full":"5546 Indian Oaks Cir Louisville KY 40219",
    "addr:housenumber":"5546",
    "addr:postcode":"40219",
    "addr:street":"Indian Oaks Cir",
    "iso:country":"US",
    "sg:address":"5546 Indian Oaks Cir",
    "sg:city":"Louisville",
    "sg:classifiers":[
        {
            "category":"Real Estate",
            "subcategory":"Real Estate Operator",
            "type":"Services"
        }
    ],
    "sg:phone":"+1 502 969 3414",
    "sg:postcode":"40219",
    "sg:province":"KY",
    "sg:tags":[
        "apartment"
    ],
    "wof:name":"Eleven Oaks Apartments",
    "wof:placetype":"venue"
},
  "geometry": {"coordinates":[-85.68694000000001,38.169746],"type":"Point"}
}