{
  "type": "Feature",
  "properties": {
    "addr:full":"6825 Green Meadow Cir Louisville KY 40207",
    "addr:housenumber":"6825",
    "addr:postcode":"40207",
    "addr:street":"Green Meadow Cir",
    "iso:country":"US",
    "sg:address":"6825 Green Meadow Cir",
    "sg:city":"Louisville",
    "sg:classifiers":[
        {
            "category":"Professional",
            "subcategory":"Computer Services",
            "type":"Services"
        }
    ],
    "sg:phone":"+1 502 893 0807",
    "sg:postcode":"40207",
    "sg:province":"KY",
    "sg:tags":[
        "related"
    ],
    "wof:name":"Fonzis Place",
    "wof:placetype":"venue"
},
  "geometry": {"coordinates":[-85.628738,38.259837],"type":"Point"}
}