{
  "type": "Feature",
  "properties": {
    "iso:country":"US",
    "sg:address":"301 N 6th St",
    "sg:city":"Paducah",
    "sg:classifiers":[
        {
            "category":"Professional",
            "subcategory":"Lawyer & Legal Services",
            "type":"Services"
        }
    ],
    "sg:phone":"+1 270 442 9229",
    "sg:postcode":"42001",
    "sg:province":"KY",
    "sg:tags":[
        "practice",
        "attorney",
        "criminal",
        "family",
        "law"
    ],
    "wof:name":"Charlotte Scott Law office",
    "wof:placetype":"venue"
},
  "geometry": {"coordinates":[-88.601761,37.087761],"type":"Point"}
}