{
  "type": "Feature",
  "properties": {
    "iso:country":"US",
    "sg:address":"10717 Hickory Cove Ct",
    "sg:city":"Louisville",
    "sg:classifiers":[
        {
            "category":"Building & Trades",
            "subcategory":"Construction",
            "type":"Services"
        }
    ],
    "sg:phone":"+1 502 426 6331",
    "sg:postcode":"40241",
    "sg:province":"KY",
    "sg:tags":[
        "house"
    ],
    "wof:name":"Jurhs Construction",
    "wof:placetype":"venue"
},
  "geometry": {"coordinates":[-85.54843099999999,38.31039],"type":"Point"}
}