{
  "type": "Feature",
  "properties": {
    "addr:full":"3220 Crums Ln Shively KY 40216",
    "addr:housenumber":"3220",
    "addr:postcode":"40216",
    "addr:street":"Crums Ln",
    "iso:country":"US",
    "sg:address":"3220 Crums Ln",
    "sg:city":"Shively",
    "sg:classifiers":[
        {
            "category":"Banks & Credit Unions",
            "subcategory":"Bank",
            "type":"Services"
        }
    ],
    "sg:phone":"+1 502 447 0784",
    "sg:postcode":"40216",
    "sg:province":"KY",
    "wof:name":"US Bank",
    "wof:placetype":"venue"
},
  "geometry": {"coordinates":[-85.83688600000001,38.198938],"type":"Point"}
}