{
  "type": "Feature",
  "properties": {
    "iso:country":"US",
    "sg:address":"2625 Legends Way",
    "sg:city":"Crestview Hills",
    "sg:classifiers":[
        {
            "category":"Social Services",
            "subcategory":"Job Training",
            "type":"Services"
        }
    ],
    "sg:phone":"+1 859 331 3437",
    "sg:postcode":"41017",
    "sg:province":"KY",
    "sg:tags":[
        "rehabilitation"
    ],
    "wof:name":"Westin Group Inc",
    "wof:placetype":"venue"
},
  "geometry": {"coordinates":[-84.566202,39.017368],"type":"Point"}
}