{
  "type": "Feature",
  "properties": {
    "iso:country":"US",
    "sg:address":"2833 Garfield Ave",
    "sg:city":"Louisville",
    "sg:classifiers":[
        {
            "category":"Organizations",
            "subcategory":"Religious Organization",
            "type":"Services"
        }
    ],
    "sg:phone":"+1 502 772 0007",
    "sg:postcode":"40212",
    "sg:province":"KY",
    "sg:tags":[
        "church"
    ],
    "wof:name":"Garfield Avenue Baptist Church",
    "wof:placetype":"venue"
},
  "geometry": {"coordinates":[-85.796869,38.267538],"type":"Point"}
}