{
  "type": "Feature",
  "properties": {
    "addr:full":"511 Ogden St Somerset KY 42501",
    "addr:housenumber":"511",
    "addr:postcode":"42501",
    "addr:street":"Ogden St",
    "iso:country":"US",
    "sg:address":"511 Ogden St",
    "sg:city":"Somerset",
    "sg:classifiers":[
        {
            "category":"Shopping",
            "subcategory":"Musical Instruments",
            "type":"Retail Goods"
        }
    ],
    "sg:phone":"+1 606 679 1088",
    "sg:postcode":"42501",
    "sg:province":"KY",
    "wof:name":"Melody Music Shop",
    "wof:placetype":"venue"
},
  "geometry": {"coordinates":[-84.615461,37.09656],"type":"Point"}
}