{
  "type": "Feature",
  "properties": {
    "iso:country":"US",
    "sg:address":"1235 Beechland Rd",
    "sg:city":"Lewisburg",
    "sg:classifiers":[
        {
            "category":"Shopping",
            "type":"Retail Goods"
        }
    ],
    "sg:phone":"+1 270 755 2489",
    "sg:postcode":"42256",
    "sg:province":"KY",
    "sg:tags":[
        "monument"
    ],
    "wof:name":"Wooldridge & Sons Monuments",
    "wof:placetype":"venue"
},
  "geometry": {"coordinates":[-86.92119,37.01434],"type":"Point"}
}