{
  "type": "Feature",
  "properties": {
    "iso:country":"US",
    "sg:address":"2137 Glen Lily Rd",
    "sg:city":"Bowling Green",
    "sg:classifiers":[
        {
            "category":"Professional",
            "subcategory":"Management & Consulting",
            "type":"Services"
        }
    ],
    "sg:phone":"+1 270 842 6559",
    "sg:postcode":"42101",
    "sg:province":"KY",
    "sg:tags":[
        "business"
    ],
    "wof:name":"Central Plumbing",
    "wof:placetype":"venue"
},
  "geometry": {"coordinates":[-86.49498800000001,37.002744],"type":"Point"}
}