{
  "type": "Feature",
  "properties": {
    "addr:full":"3826 New Bowling Green Rd Glasgow KY 42141",
    "addr:housenumber":"3826",
    "addr:postcode":"42141",
    "addr:street":"New Bowling Green Rd",
    "iso:country":"US",
    "sg:address":"3826 New Bowling Green Rd",
    "sg:city":"Glasgow",
    "sg:classifiers":[
        {
            "category":"Professional",
            "subcategory":"Business Services",
            "type":"Services"
        }
    ],
    "sg:phone":"+1 270 678 7844",
    "sg:postcode":"42141",
    "sg:province":"KY",
    "sg:tags":[
        "disposal",
        "reduction",
        "waste"
    ],
    "wof:name":"Glasgow Industrial Svc",
    "wof:placetype":"venue"
},
  "geometry": {"coordinates":[-85.968356,37.016124],"type":"Point"}
}