{
  "type": "Feature",
  "properties": {
    "iso:country":"US",
    "sg:address":"818 Fairlane Dr",
    "sg:city":"Vanceburg",
    "sg:classifiers":[
        {
            "category":"Food & Beverages",
            "subcategory":"Groceries & Convenience Stores",
            "type":"Retail Goods"
        }
    ],
    "sg:phone":"+1 606 796 2662",
    "sg:postcode":"41179",
    "sg:province":"KY",
    "sg:tags":[
        "grocer"
    ],
    "wof:name":"Steve's Market",
    "wof:placetype":"venue"
},
  "geometry": {"coordinates":[-83.323232,38.589135],"type":"Point"}
}