{
  "type": "Feature",
  "properties": {
    "addr:full":"116 S Main St Nicholasville KY 40356",
    "addr:housenumber":"116",
    "addr:postcode":"40356",
    "addr:street":"S Main St",
    "iso:country":"US",
    "sg:address":"116 S Main St",
    "sg:city":"Nicholasville",
    "sg:classifiers":[
        {
            "category":"Food & Beverages",
            "subcategory":"Liquor & Beverages",
            "type":"Retail Goods"
        }
    ],
    "sg:phone":"+1 859 887 1793",
    "sg:postcode":"40356",
    "sg:province":"KY",
    "wof:name":"Wine Shop Vintages & Spirits",
    "wof:placetype":"venue"
},
  "geometry": {"coordinates":[-84.57329900000001,37.879554],"type":"Point"}
}