{
  "type": "Feature",
  "properties": {
    "addr:full":"10198 State Hwy 7 Kite KY 41828",
    "addr:housenumber":"10198",
    "addr:postcode":"41828",
    "addr:street":"State Hwy 7 Kite",
    "iso:country":"US",
    "sg:address":"10198 State Hwy 7",
    "sg:city":"Kite",
    "sg:classifiers":[
        {
            "category":"Personal",
            "subcategory":"Beauty Salon",
            "type":"Services"
        }
    ],
    "sg:phone":"+1 606 447 2627",
    "sg:postcode":"41828",
    "sg:province":"KY",
    "sg:tags":[
        "shop"
    ],
    "wof:name":"Sams Hair Haven",
    "wof:placetype":"venue"
},
  "geometry": {"coordinates":[-82.803066,37.322888],"type":"Point"}
}