{
  "type": "Feature",
  "properties": {
    "addr:full":"420 Lexington Rd Versailles KY 40383",
    "addr:housenumber":"420",
    "addr:postcode":"40383",
    "addr:street":"Lexington Rd",
    "iso:country":"US",
    "sg:address":"420 Lexington Rd",
    "sg:city":"Versailles",
    "sg:classifiers":[
        {
            "category":"Sports & Exercise",
            "subcategory":"Golf",
            "type":"Entertainment"
        }
    ],
    "sg:phone":"+1 859 873 0299",
    "sg:postcode":"40383",
    "sg:province":"KY",
    "sg:tags":[
        "course"
    ],
    "wof:name":"Lourdes Of Course",
    "wof:placetype":"venue"
},
  "geometry": {"coordinates":[-84.719364,38.051606],"type":"Point"}
}