{
  "type": "Feature",
  "properties": {
    "iso:country":"US",
    "sg:address":"11 Locust Pt",
    "sg:city":"Cold Spring",
    "sg:classifiers":[
        {
            "category":"Professional",
            "subcategory":"Lawyer & Legal Services",
            "type":"Services"
        }
    ],
    "sg:phone":"+1 859 441 8969",
    "sg:postcode":"41076",
    "sg:province":"KY",
    "wof:name":"Twehues Paul H Jr Lwyr",
    "wof:placetype":"venue"
},
  "geometry": {"coordinates":[-84.439903,39.028],"type":"Point"}
}