{
  "type": "Feature",
  "properties": {
    "addr:full":"449 S Ashland Ave Lexington KY 40502",
    "addr:housenumber":"449",
    "addr:postcode":"40502",
    "addr:street":"S Ashland Ave",
    "iso:country":"US",
    "sg:address":"449 S Ashland Ave",
    "sg:city":"Lexington",
    "sg:classifiers":[
        {
            "category":"Professional",
            "subcategory":"Business Services",
            "type":"Services"
        }
    ],
    "sg:phone":"+1 859 266 5330",
    "sg:postcode":"40502",
    "sg:province":"KY",
    "wof:name":"Skm Trust",
    "wof:placetype":"venue"
},
  "geometry": {"coordinates":[-84.491528,38.030317],"type":"Point"}
}