{
  "type": "Feature",
  "properties": {
    "iso:country":"US",
    "sg:address":"6976 Gordon Blvd",
    "sg:city":"Burlington",
    "sg:classifiers":[
        {
            "category":"Building & Trades",
            "subcategory":"Landscaping Services",
            "type":"Services"
        }
    ],
    "sg:phone":"+1 859 384 8716",
    "sg:postcode":"41005",
    "sg:province":"KY",
    "sg:tags":[
        "designer",
        "landscape"
    ],
    "wof:name":"Tri State Land Design Co",
    "wof:placetype":"venue"
},
  "geometry": {"coordinates":[-84.718932,38.988429],"type":"Point"}
}