{
  "type": "Feature",
  "properties": {
    "iso:country":"US",
    "sg:address":"104 Lycan Rd",
    "sg:city":"Ashland",
    "sg:classifiers":[
        {
            "category":"Professional",
            "subcategory":"Business Services",
            "type":"Services"
        }
    ],
    "sg:phone":"+1 606 329 0828",
    "sg:postcode":"41101",
    "sg:province":"KY",
    "sg:tags":[
        "appraiser"
    ],
    "wof:name":"HGH Appraisal Svc Inc",
    "wof:placetype":"venue"
},
  "geometry": {"coordinates":[-82.682457,38.495777],"type":"Point"}
}