{
  "type": "Feature",
  "properties": {
    "iso:country":"US",
    "sg:address":"1865 Hibbs Ln",
    "sg:city":"Coxs Creek",
    "sg:classifiers":[
        {
            "category":"Professional",
            "subcategory":"Detective & Security Services",
            "type":"Services"
        }
    ],
    "sg:phone":"+1 502 349 3117",
    "sg:postcode":"40013",
    "sg:province":"KY",
    "sg:tags":[
        "car"
    ],
    "wof:name":"Ins Investigation Bureu I",
    "wof:placetype":"venue"
},
  "geometry": {"coordinates":[-85.438744,37.938761],"type":"Point"}
}