{
  "type": "Feature",
  "properties": {
    "iso:country":"US",
    "sg:address":"3032 Louisville Rd",
    "sg:city":"Bowling Green",
    "sg:classifiers":[
        {
            "category":"Food & Beverages",
            "subcategory":"Liquor & Beverages",
            "type":"Retail Goods"
        }
    ],
    "sg:phone":"+1 270 782 1900",
    "sg:postcode":"42101",
    "sg:province":"KY",
    "wof:name":"Vette City Liquors",
    "wof:placetype":"venue"
},
  "geometry": {"coordinates":[-86.39170799999999,37.010445],"type":"Point"}
}