{
  "type": "Feature",
  "properties": {
    "iso:country":"US",
    "sg:address":"2113 W Cumberland Ave",
    "sg:city":"Middlesboro",
    "sg:classifiers":[
        {
            "category":"Recreation",
            "type":"Entertainment"
        }
    ],
    "sg:phone":"+1 606 248 0219",
    "sg:postcode":"40965",
    "sg:province":"KY",
    "sg:tags":[
        "skating",
        "rink"
    ],
    "wof:name":"Skate World Inc",
    "wof:placetype":"venue"
},
  "geometry": {"coordinates":[-83.715988,36.607035],"type":"Point"}
}