{
  "type": "Feature",
  "properties": {
    "iso:country":"US",
    "sg:address":"667 Pearman Ave",
    "sg:city":"Radcliff",
    "sg:classifiers":[
        {
            "category":"Home & Garden",
            "subcategory":"Home Furnishings",
            "type":"Retail Goods"
        }
    ],
    "sg:phone":"+1 270 351 1884",
    "sg:postcode":"40160",
    "sg:province":"KY",
    "wof:name":"Cns Asian Bedding",
    "wof:placetype":"venue"
},
  "geometry": {"coordinates":[-85.94115600000001,37.823516],"type":"Point"}
}