{
  "type": "Feature",
  "properties": {
    "iso:country":"US",
    "sg:address":"103 E Dorton Blvd",
    "sg:city":"Staffordsville",
    "sg:classifiers":[
        {
            "category":"Professional",
            "subcategory":"Business Services",
            "type":"Services"
        }
    ],
    "sg:phone":"+1 606 297 1977",
    "sg:postcode":"41256",
    "sg:province":"KY",
    "wof:name":"Reel & Assoc Inc",
    "wof:placetype":"venue"
},
  "geometry": {"coordinates":[-82.845344,37.826243],"type":"Point"}
}