{
  "type": "Feature",
  "properties": {
    "addr:full":"415 N Main St Burkesville KY 42717",
    "addr:housenumber":"415",
    "addr:postcode":"42717",
    "addr:street":"N Main St",
    "iso:country":"US",
    "sg:address":"415 N Main St",
    "sg:city":"Burkesville",
    "sg:classifiers":[
        {
            "category":"Utilities",
            "subcategory":"Electric",
            "type":"Services"
        }
    ],
    "sg:phone":"+1 270 864 3871",
    "sg:postcode":"42717",
    "sg:province":"KY",
    "sg:tags":[
        "company"
    ],
    "wof:name":"Tri County Electric Membership",
    "wof:placetype":"venue"
},
  "geometry": {"coordinates":[-85.367861,36.792869],"type":"Point"}
}