{
  "type": "Feature",
  "properties": {
    "iso:country":"US",
    "sg:address":"400 Mamie Price Rd",
    "sg:city":"Liberty",
    "sg:classifiers":[
        {
            "category":"Wholesale",
            "subcategory":"Construction Materials",
            "type":"Manufacturing & Wholesale Goods"
        }
    ],
    "sg:phone":"+1 606 787 0677",
    "sg:postcode":"42539",
    "sg:province":"KY",
    "sg:tags":[
        "gates"
    ],
    "wof:name":"Rocky Point Mfg",
    "wof:placetype":"venue"
},
  "geometry": {"coordinates":[-84.974396,37.279117],"type":"Point"}
}