{
  "type": "Feature",
  "properties": {
    "iso:country":"US",
    "sg:address":"1633 Rosewood Ave",
    "sg:city":"Louisville",
    "sg:classifiers":[
        {
            "category":"Shopping",
            "subcategory":"Gifts & Souvenirs",
            "type":"Retail Goods"
        },
        {
            "category":"Manufacturing",
            "subcategory":"Retail Goods",
            "type":"Manufacturing & Wholesale Goods"
        }
    ],
    "sg:phone":"+1 502 452 9064",
    "sg:postcode":"40204",
    "sg:province":"KY",
    "sg:tags":[
        "shop",
        "giftware's-wholesale",
        "manufacturer"
    ],
    "wof:name":"Jar Express",
    "wof:placetype":"venue"
},
  "geometry": {"coordinates":[-85.717422,38.233471],"type":"Point"}
}