{
  "type": "Feature",
  "properties": {
    "iso:country":"US",
    "sg:address":"12107 Plantation Blvd",
    "sg:city":"Goshen",
    "sg:classifiers":[
        {
            "category":"Insurance",
            "subcategory":"Life Insurance",
            "type":"Services"
        }
    ],
    "sg:phone":"+1 502 228 1303",
    "sg:postcode":"40026",
    "sg:province":"KY",
    "sg:tags":[
        "carrier"
    ],
    "wof:name":"Pacific Life Insurance Company",
    "wof:placetype":"venue"
},
  "geometry": {"coordinates":[-85.57905,38.422929],"type":"Point"}
}