{
  "type": "Feature",
  "properties": {
    "iso:country":"US",
    "sg:address":"312 Penruth Ave",
    "sg:city":"Louisville",
    "sg:classifiers":[
        {
            "category":"Banks & Credit Unions",
            "subcategory":"Investment Brokerage",
            "type":"Services"
        }
    ],
    "sg:phone":"+1 502 894 9930",
    "sg:postcode":"40207",
    "sg:province":"KY",
    "sg:tags":[
        "advisory",
        "financial"
    ],
    "wof:name":"Conservative Asset Management",
    "wof:placetype":"venue"
},
  "geometry": {"coordinates":[-85.68203699999999,38.264779],"type":"Point"}
}