{
  "type": "Feature",
  "properties": {
    "addr:full":"104 E 25th St Covington KY 41014",
    "addr:housenumber":"104",
    "addr:postcode":"41014",
    "addr:street":"E 25Th St",
    "iso:country":"US",
    "sg:address":"104 E 25th St",
    "sg:city":"Covington",
    "sg:classifiers":[
        {
            "category":"Real Estate",
            "subcategory":"Real Estate Operator",
            "type":"Services"
        }
    ],
    "sg:phone":"+1 859 261 9600",
    "sg:postcode":"41014",
    "sg:province":"KY",
    "sg:tags":[
        "dwelling"
    ],
    "wof:name":"Schrage Properties",
    "wof:placetype":"venue"
},
  "geometry": {"coordinates":[-84.501656,39.062731],"type":"Point"}
}