{
  "type": "Feature",
  "properties": {
    "addr:full":"1413 US Hwy 60 Burna KY 42028",
    "addr:housenumber":"1413",
    "addr:postcode":"42028",
    "addr:street":"Us Hwy 60",
    "iso:country":"US",
    "sg:address":"1413 US Hwy 60",
    "sg:city":"Burna",
    "sg:classifiers":[
        {
            "category":"Farming",
            "subcategory":"Farm",
            "type":"Manufacturing & Wholesale Goods"
        }
    ],
    "sg:phone":"+1 270 988 3765",
    "sg:postcode":"42028",
    "sg:province":"KY",
    "sg:tags":[
        "crop",
        "general"
    ],
    "wof:name":"Joe Robinson",
    "wof:placetype":"venue"
},
  "geometry": {"coordinates":[-88.380574,37.228114],"type":"Point"}
}