{
  "type": "Feature",
  "properties": {
    "iso:country":"US",
    "sg:address":"116 Butler St",
    "sg:city":"Columbia",
    "sg:classifiers":[
        {
            "category":"Utilities",
            "subcategory":"Telephone",
            "type":"Services"
        }
    ],
    "sg:phone":"+1 270 384 4220",
    "sg:postcode":"42728",
    "sg:province":"KY",
    "sg:tags":[
        "communications"
    ],
    "wof:name":"Communication Standards",
    "wof:placetype":"venue"
},
  "geometry": {"coordinates":[-85.317368,37.11336],"type":"Point"}
}