{
  "type": "Feature",
  "properties": {
    "iso:country":"US",
    "sg:address":"4542 Taylorsville Rd",
    "sg:city":"Louisville",
    "sg:classifiers":[
        {
            "category":"Shopping",
            "type":"Retail Goods"
        }
    ],
    "sg:phone":"+1 502 495 0100",
    "sg:postcode":"40220",
    "sg:province":"KY",
    "sg:tags":[
        "picture",
        "frame"
    ],
    "sg:website":"http://www.realpagessites.com/bluegrassframes",
    "wof:name":"Bluegrass Frames",
    "wof:placetype":"venue"
},
  "geometry": {"coordinates":[-85.598938,38.21846],"type":"Point"}
}