{
  "type": "Feature",
  "properties": {
    "iso:country":"US",
    "sg:address":"911 S Lincoln Blvd",
    "sg:city":"Hodgenville",
    "sg:classifiers":[
        {
            "category":"Education",
            "subcategory":"School",
            "type":"Public Place"
        }
    ],
    "sg:phone":"+1 270 358 3196",
    "sg:postcode":"42748",
    "sg:province":"KY",
    "sg:website":"www.larue.k12.ky.us",
    "wof:name":"Larue County Middle School",
    "wof:placetype":"venue"
},
  "geometry": {"coordinates":[-85.734268,37.552215],"type":"Point"}
}