{
  "type": "Feature",
  "properties": {
    "iso:country":"US",
    "sg:address":"445 Richmond St",
    "sg:city":"Mt Vernon",
    "sg:classifiers":[
        {
            "category":"Professional",
            "subcategory":"Business Services",
            "type":"Services"
        }
    ],
    "sg:phone":"+1 606 256 1060",
    "sg:postcode":"40456",
    "sg:province":"KY",
    "sg:tags":[
        "liquidator"
    ],
    "wof:name":"Golden Nickel",
    "wof:placetype":"venue"
},
  "geometry": {"coordinates":[-84.336583,37.36139],"type":"Point"}
}