{
  "type": "Feature",
  "properties": {
    "iso:country":"US",
    "sg:address":"13917 Aiken Rd",
    "sg:city":"Louisville",
    "sg:classifiers":[
        {
            "category":"Building & Trades",
            "subcategory":"Construction",
            "type":"Services"
        }
    ],
    "sg:phone":"+1 502 489 9190",
    "sg:postcode":"40245",
    "sg:province":"KY",
    "sg:tags":[
        "roofing",
        "contractor"
    ],
    "wof:name":"Bob Alberhasky General Contr",
    "wof:placetype":"venue"
},
  "geometry": {"coordinates":[-85.487106,38.266142],"type":"Point"}
}