{
  "type": "Feature",
  "properties": {
    "iso:country":"US",
    "sg:address":"512 W Lexington Ave",
    "sg:city":"Winchester",
    "sg:classifiers":[
        {
            "category":"Building & Trades",
            "subcategory":"Plumbing",
            "type":"Services"
        }
    ],
    "sg:phone":"+1 859 744 3790",
    "sg:postcode":"40391",
    "sg:province":"KY",
    "sg:tags":[
        "conditioning",
        "air",
        "system",
        "contractor"
    ],
    "sg:website":"www.wildcatelectrical.com",
    "wof:name":"Wildcat Electrical Contracting",
    "wof:placetype":"venue"
},
  "geometry": {"coordinates":[-84.188149,37.995341],"type":"Point"}
}