{
  "type": "Feature",
  "properties": {
    "iso:country":"US",
    "sg:address":"111 E Fortune St",
    "sg:city":"Columbia",
    "sg:classifiers":[
        {
            "category":"Wholesale",
            "subcategory":"Durable Goods & Equipment",
            "type":"Manufacturing & Wholesale Goods"
        }
    ],
    "sg:phone":"+1 270 384 4538",
    "sg:postcode":"42728",
    "sg:province":"KY",
    "sg:tags":[
        "importer"
    ],
    "wof:name":"Lopez-Perez Intl Inc",
    "wof:placetype":"venue"
},
  "geometry": {"coordinates":[-85.306473,37.101538],"type":"Point"}
}