{
  "type": "Feature",
  "properties": {
    "iso:country":"US",
    "sg:address":"319 Lowe Ave",
    "sg:city":"Bowling Green",
    "sg:classifiers":[
        {
            "category":"Food & Beverages",
            "subcategory":"Bakery",
            "type":"Retail Goods"
        }
    ],
    "sg:phone":"+1 270 843 4358",
    "sg:postcode":"42101",
    "sg:province":"KY",
    "wof:name":"Interstate Brands Corporation",
    "wof:placetype":"venue"
},
  "geometry": {"coordinates":[-86.426277,37.003889],"type":"Point"}
}