{
  "type": "Feature",
  "properties": {
    "addr:full":"1126 Bardstown Rd Louisville KY 40204",
    "addr:housenumber":"1126",
    "addr:postcode":"40204",
    "addr:street":"Bardstown Rd",
    "iso:country":"US",
    "sg:address":"1126 Bardstown Rd",
    "sg:city":"Louisville",
    "sg:classifiers":[
        {
            "category":"Cafe",
            "type":"Food & Drink"
        }
    ],
    "sg:menulink":"http://www.allmenus.com/ky/louisville-east/39039-karma-cafe/menu/",
    "sg:phone":"+1 502 587 0062",
    "sg:postcode":"40204",
    "sg:province":"KY",
    "sg:tags":[
        "american"
    ],
    "wof:name":"Karma Cafe",
    "wof:placetype":"venue"
},
  "geometry": {"coordinates":[-85.71993999999999,38.237846],"type":"Point"}
}