{
  "type": "Feature",
  "properties": {
    "iso:country":"US",
    "sg:address":"881 Corporate Dr",
    "sg:city":"Lexington",
    "sg:classifiers":[
        {
            "category":"Professional",
            "subcategory":"Employment Agencies",
            "type":"Services"
        }
    ],
    "sg:phone":"+1 859 224 7822",
    "sg:postcode":"40503",
    "sg:province":"KY",
    "sg:tags":[
        "consultant",
        "search",
        "executive"
    ],
    "wof:name":"Us Army Medical Recruiting",
    "wof:placetype":"venue"
},
  "geometry": {"coordinates":[-84.554599,38.013265],"type":"Point"}
}