{
  "type": "Feature",
  "properties": {
    "addr:full":"636 Dixie Hwy S Radcliff KY 40160",
    "addr:housenumber":"636",
    "addr:postcode":"40160",
    "addr:street":"Dixie Hwy S",
    "iso:country":"US",
    "sg:address":"636 Dixie Hwy S",
    "sg:city":"Radcliff",
    "sg:classifiers":[
        {
            "category":"Autos & Motor Vehicles",
            "subcategory":"Fuel & Gas Station",
            "type":"Retail Goods"
        }
    ],
    "sg:phone":"+1 270 351 1227",
    "sg:postcode":"40160",
    "sg:province":"KY",
    "sg:tags":[
        "oil"
    ],
    "wof:name":"Five Star Food Mart",
    "wof:placetype":"venue"
},
  "geometry": {"coordinates":[-85.93203699999999,37.83329],"type":"Point"}
}