{
  "type": "Feature",
  "properties": {
    "iso:country":"US",
    "sg:address":"302 E Breckinridge St",
    "sg:city":"Louisville",
    "sg:classifiers":[
        {
            "category":"Health Services",
            "subcategory":"Doctor",
            "type":"Services"
        },
        {
            "category":"Health Services",
            "subcategory":"Clinic",
            "type":"Services"
        }
    ],
    "sg:phone":"+1 502 561 1112",
    "sg:postcode":"40203",
    "sg:province":"KY",
    "sg:tags":[
        "psychiatry",
        "information",
        "surgeons",
        "mental",
        "physician"
    ],
    "wof:name":"Family & Children's Mental Health Services",
    "wof:placetype":"venue"
},
  "geometry": {"coordinates":[-85.75038499999999,38.240984],"type":"Point"}
}