{
  "type": "Feature",
  "properties": {
    "iso:country":"US",
    "sg:address":"7301 Arnoldtown Rd",
    "sg:city":"Louisville",
    "sg:classifiers":[
        {
            "category":"Organizations",
            "subcategory":"Religious Organization",
            "type":"Services"
        }
    ],
    "sg:phone":"+1 502 933 0085",
    "sg:postcode":"40214",
    "sg:province":"KY",
    "sg:tags":[
        "church"
    ],
    "sg:website":"www.harvestcog.com",
    "wof:name":"Harvest Church Of God",
    "wof:placetype":"venue"
},
  "geometry": {"coordinates":[-85.823234,38.146705],"type":"Point"}
}