{
  "type": "Feature",
  "properties": {
    "iso:country":"US",
    "sg:address":"311 N 3rd St",
    "sg:city":"Scottsville",
    "sg:classifiers":[
        {
            "category":"Organizations",
            "subcategory":"Non-profit Organization",
            "type":"Services"
        }
    ],
    "sg:phone":"+1 270 237 3826",
    "sg:postcode":"42164",
    "sg:province":"KY",
    "wof:name":"Kentucky Home Place",
    "wof:placetype":"venue"
},
  "geometry": {"coordinates":[-86.18698999999999,36.754658],"type":"Point"}
}