{
  "type": "Feature",
  "properties": {
    "iso:country":"US",
    "sg:address":"700 Ceadarmore Rd",
    "sg:city":"Bagdad",
    "sg:classifiers":[
        {
            "category":"Real Estate",
            "subcategory":"Real Estate Agent",
            "type":"Services"
        }
    ],
    "sg:phone":"+1 502 633 2906",
    "sg:postcode":"40003",
    "sg:province":"KY",
    "sg:tags":[
        "inspection"
    ],
    "wof:name":"Jones Services",
    "wof:placetype":"venue"
},
  "geometry": {"coordinates":[-85.012776,38.279955],"type":"Point"}
}