{
  "type": "Feature",
  "properties": {
    "addr:full":"1514 McClure Rd Winchester KY 40391",
    "addr:housenumber":"1514",
    "addr:postcode":"40391",
    "addr:street":"Mcclure Rd",
    "iso:country":"US",
    "sg:address":"1514 McClure Rd",
    "sg:city":"Winchester",
    "sg:classifiers":[
        {
            "category":"Banks & Credit Unions",
            "subcategory":"Financial Services",
            "type":"Services"
        }
    ],
    "sg:phone":"+1 859 744 4220",
    "sg:postcode":"40391",
    "sg:province":"KY",
    "sg:tags":[
        "investor"
    ],
    "sg:website":"www.dfmoore.com",
    "wof:name":"MBP Investors",
    "wof:placetype":"venue"
},
  "geometry": {"coordinates":[-84.223899,37.972554],"type":"Point"}
}