{
  "type": "Feature",
  "properties": {
    "iso:country":"US",
    "sg:address":"9807 Sonrisa Dr",
    "sg:city":"Louisville",
    "sg:classifiers":[
        {
            "category":"Professional",
            "subcategory":"Lawyer & Legal Services",
            "type":"Services"
        }
    ],
    "sg:phone":"+1 502 239 3413",
    "sg:postcode":"40291",
    "sg:province":"KY",
    "sg:tags":[
        "attorney"
    ],
    "wof:name":"Denise Brown",
    "wof:placetype":"venue"
},
  "geometry": {"coordinates":[-85.577837,38.152409],"type":"Point"}
}