{
  "type": "Feature",
  "properties": {
    "iso:country":"US",
    "sg:address":"4955 Leonard Futrell Rd",
    "sg:city":"Paducah",
    "sg:classifiers":[
        {
            "category":"Building & Trades",
            "subcategory":"Plumbing",
            "type":"Services"
        }
    ],
    "sg:phone":"+1 270 442 2682",
    "sg:postcode":"42001",
    "sg:province":"KY",
    "sg:tags":[
        "conditioning",
        "air",
        "system",
        "contractor"
    ],
    "wof:name":"Aircon Inc Heating Air Cond",
    "wof:placetype":"venue"
},
  "geometry": {"coordinates":[-88.73008299999999,37.069122],"type":"Point"}
}