{
  "type": "Feature",
  "properties": {
    "addr:full":"321 Court St Wickliffe KY 42087",
    "addr:housenumber":"321",
    "addr:postcode":"42087",
    "addr:street":"Court St",
    "iso:country":"US",
    "sg:address":"321 Court St",
    "sg:city":"Wickliffe",
    "sg:classifiers":[
        {
            "category":"Government",
            "subcategory":"Office",
            "type":"Public Place"
        }
    ],
    "sg:phone":"+1 270 335 3557",
    "sg:postcode":"42087",
    "sg:province":"KY",
    "sg:tags":[
        "village"
    ],
    "wof:name":"Wickliffe City Sewage Dept",
    "wof:placetype":"venue"
},
  "geometry": {"coordinates":[-89.091561,36.964943],"type":"Point"}
}