{
  "type": "Feature",
  "properties": {
    "iso:country":"US",
    "sg:address":"118 Eastview Dr",
    "sg:city":"Glasgow",
    "sg:classifiers":[
        {
            "category":"Organizations",
            "subcategory":"Religious Organization",
            "type":"Services"
        }
    ],
    "sg:phone":"+1 270 651 8121",
    "sg:postcode":"42141",
    "sg:province":"KY",
    "sg:tags":[
        "church"
    ],
    "wof:name":"Restoration Church",
    "wof:placetype":"venue"
},
  "geometry": {"coordinates":[-85.903165,36.999035],"type":"Point"}
}