{
  "type": "Feature",
  "properties": {
    "iso:country":"US",
    "sg:address":"19006 Beaver Dam Rd",
    "sg:city":"Caneyville",
    "sg:classifiers":[
        {
            "category":"Shopping",
            "subcategory":"Discount & Variety Stores",
            "type":"Retail Goods"
        }
    ],
    "sg:phone":"+1 270 879 0400",
    "sg:postcode":"42721",
    "sg:province":"KY",
    "wof:name":"Strings & Things",
    "wof:placetype":"venue"
},
  "geometry": {"coordinates":[-86.609354,37.430499],"type":"Point"}
}