{
  "type": "Feature",
  "properties": {
    "iso:country":"US",
    "sg:address":"1617 Dixie Hwy S",
    "sg:city":"Elizabethtown",
    "sg:classifiers":[
        {
            "category":"Cinema",
            "subcategory":"Movie Rental",
            "type":"Entertainment"
        }
    ],
    "sg:phone":"+1 270 737 1148",
    "sg:postcode":"42701",
    "sg:province":"KY",
    "sg:tags":[
        "leasing",
        "video",
        "disc",
        "tape"
    ],
    "sg:website":"www.hollywoodvideo.com",
    "wof:name":"Hollywood Video",
    "wof:placetype":"venue"
},
  "geometry": {"coordinates":[-85.88399699999999,37.728296],"type":"Point"}
}