{
  "type": "Feature",
  "properties": {
    "iso:country":"US",
    "sg:address":"9600 Old Six Mile Ln",
    "sg:city":"Louisville",
    "sg:classifiers":[
        {
            "category":"Education",
            "subcategory":"School",
            "type":"Public Place"
        }
    ],
    "sg:phone":"+1 502 485 8275",
    "sg:postcode":"40299",
    "sg:province":"KY",
    "sg:website":"www.jefferson.k12.ky.us",
    "wof:name":"Jeffersontown High School",
    "wof:placetype":"venue"
},
  "geometry": {"coordinates":[-85.579616,38.201475],"type":"Point"}
}