{
  "type": "Feature",
  "properties": {
    "iso:country":"US",
    "sg:address":"570 Judy Ln",
    "sg:city":"Lexington",
    "sg:classifiers":[
        {
            "category":"Wholesale",
            "subcategory":"Hardware",
            "type":"Manufacturing & Wholesale Goods"
        }
    ],
    "sg:phone":"+1 859 299 5724",
    "sg:postcode":"40505",
    "sg:province":"KY",
    "sg:tags":[
        "refrigerating"
    ],
    "wof:name":"Marty's Refrigeration Heating",
    "wof:placetype":"venue"
},
  "geometry": {"coordinates":[-84.457589,38.082291],"type":"Point"}
}