{
  "type": "Feature",
  "properties": {
    "addr:full":"211 Midland Trl Mt Sterling KY 40353",
    "addr:housenumber":"211",
    "addr:postcode":"40353",
    "addr:street":"Midland Trl",
    "iso:country":"US",
    "sg:address":"211 Midland Trl",
    "sg:city":"Mt Sterling",
    "sg:classifiers":[
        {
            "category":"Manufacturing",
            "subcategory":"Tools & Machinery",
            "type":"Manufacturing & Wholesale Goods"
        }
    ],
    "sg:phone":"+1 859 498 5113",
    "sg:postcode":"40353",
    "sg:province":"KY",
    "sg:tags":[
        "machine",
        "shop"
    ],
    "wof:name":"Chandler Machining Co",
    "wof:placetype":"venue"
},
  "geometry": {"coordinates":[-83.91916999999999,38.07561],"type":"Point"}
}