{
  "type": "Feature",
  "properties": {
    "iso:country":"US",
    "sg:address":"509 Broadway",
    "sg:city":"Barlow",
    "sg:classifiers":[
        {
            "category":"Museum",
            "type":"Entertainment"
        }
    ],
    "sg:phone":"+1 270 334 3010",
    "sg:postcode":"42024",
    "sg:province":"KY",
    "wof:name":"Barlow House Museum",
    "wof:placetype":"venue"
},
  "geometry": {"coordinates":[-89.045643,37.051629],"type":"Point"}
}