{
  "type": "Feature",
  "properties": {
    "addr:city":"Barlow",
    "addr:full":"509 Broadway St Barlow, Ky 42024",
    "addr:house_number":"509",
    "addr:housenumber":"509",
    "addr:phone":"+1 270-334-3010",
    "addr:postcode":"42024",
    "addr:road":"Broadway St",
    "addr:state":"KY",
    "addr:street":"Broadway",
    "iso:country":"US",
    "sg:address":"509 Broadway",
    "sg:city":"Barlow",
    "sg:classifiers":[
        {
            "category":"Museum",
            "type":"Entertainment"
        }
    ],
    "sg:phone":"+1 270 334 3010",
    "sg:postcode":"42024",
    "sg:province":"KY",
    "wof:name":"Barlow House Museum",
    "wof:placetype":"venue"
},
  "geometry": {"coordinates":[-89.045,37.05158],"type":"Point"}
}