{
  "type": "Feature",
  "properties": {
    "addr:full":"12305 Westport Rd Louisville KY 40245",
    "addr:housenumber":"12305",
    "addr:postcode":"40245",
    "addr:street":"Westport Rd",
    "iso:country":"US",
    "sg:address":"12305 Westport Rd",
    "sg:city":"Louisville",
    "sg:classifiers":[
        {
            "category":"Real Estate",
            "subcategory":"Real Estate Agent",
            "type":"Services"
        }
    ],
    "sg:phone":"+1 502 774 9464",
    "sg:postcode":"40245",
    "sg:province":"KY",
    "wof:name":"First Realty Group",
    "wof:placetype":"venue"
},
  "geometry": {"coordinates":[-85.520691,38.305175],"type":"Point"}
}