{
  "type": "Feature",
  "properties": {
    "iso:country":"US",
    "sg:address":"600 Dr Martin Luther King Pl",
    "sg:city":"Louisville",
    "sg:classifiers":[
        {
            "category":"Government",
            "subcategory":"Office",
            "type":"Public Place"
        }
    ],
    "sg:phone":"+1 502 582 5237",
    "sg:postcode":"40202",
    "sg:province":"KY",
    "sg:tags":[
        "federal",
        "program"
    ],
    "wof:name":"US Food & Drug Adm",
    "wof:placetype":"venue"
},
  "geometry": {"coordinates":[-85.76291999999999,38.249032],"type":"Point"}
}