{
  "type": "Feature",
  "properties": {
    "addr:full":"143 Raisor Ave Bardstown KY 40004",
    "addr:housenumber":"143",
    "addr:postcode":"40004",
    "addr:street":"Raisor Ave",
    "iso:country":"US",
    "sg:address":"143 Raisor Ave",
    "sg:city":"Bardstown",
    "sg:classifiers":[
        {
            "category":"Shopping",
            "subcategory":"Hobbies, Toys, & Games",
            "type":"Retail Goods"
        }
    ],
    "sg:phone":"+1 502 349 1168",
    "sg:postcode":"40004",
    "sg:province":"KY",
    "sg:tags":[
        "doll",
        "barbie"
    ],
    "wof:name":"Chers Vntage Collectible Dolls",
    "wof:placetype":"venue"
},
  "geometry": {"coordinates":[-85.507936,37.85904],"type":"Point"}
}