{
  "type": "Feature",
  "properties": {
    "addr:full":"1624 Fort Campbell Blvd Clarksville KY 37042",
    "addr:housenumber":"1624",
    "addr:postcode":"37042",
    "addr:street":"Fort Campbell Blvd",
    "iso:country":"US",
    "sg:address":"1624 Fort Campbell Blvd",
    "sg:city":"Clarksville",
    "sg:classifiers":[
        {
            "category":"Shopping",
            "subcategory":"Bicycles & Sporting Goods",
            "type":"Retail Goods"
        }
    ],
    "sg:phone":"+1 931 503 2459",
    "sg:postcode":"37042",
    "sg:province":"KY",
    "sg:website":"www.hibbett.com",
    "wof:name":"Hibbett Sporting Goods Inc",
    "wof:placetype":"venue"
},
  "geometry": {"coordinates":[-87.408354,36.576401],"type":"Point"}
}