{
  "type": "Feature",
  "properties": {
    "iso:country":"US",
    "sg:address":"123 N Lincoln Blvd",
    "sg:city":"Hodgenville",
    "sg:classifiers":[
        {
            "category":"Retail",
            "subcategory":"Car Wash",
            "type":"Services"
        }
    ],
    "sg:phone":"+1 270 358 5897",
    "sg:postcode":"42748",
    "sg:province":"KY",
    "sg:tags":[
        "automobile",
        "detail",
        "clean"
    ],
    "wof:name":"Bumper To Bumper",
    "wof:placetype":"venue"
},
  "geometry": {"coordinates":[-85.740278,37.574719],"type":"Point"}
}