{
  "type": "Feature",
  "properties": {
    "addr:full":"176 12th St Clay City KY 40312",
    "addr:housenumber":"176",
    "addr:postcode":"40312",
    "addr:street":"12Th St",
    "iso:country":"US",
    "sg:address":"176 12th St",
    "sg:city":"Clay City",
    "sg:classifiers":[
        {
            "category":"Social Services",
            "type":"Services"
        }
    ],
    "sg:phone":"+1 606 663 0794",
    "sg:postcode":"40312",
    "sg:province":"KY",
    "sg:tags":[
        "organization",
        "welfare"
    ],
    "wof:name":"Powell Adult Day Care",
    "wof:placetype":"venue"
},
  "geometry": {"coordinates":[-83.916186,37.853246],"type":"Point"}
}