{
  "type": "Feature",
  "properties": {
    "addr:full":"73 Elblaine Dr Highland Heights KY 41076",
    "addr:housenumber":"73",
    "addr:postcode":"41076",
    "addr:street":"Elblaine Dr",
    "iso:country":"US",
    "sg:address":"73 Elblaine Dr",
    "sg:city":"Highland Heights",
    "sg:classifiers":[
        {
            "category":"Professional",
            "type":"Services"
        },
        {
            "category":"Health Services",
            "subcategory":"Health Practitioner",
            "type":"Services"
        }
    ],
    "sg:phone":"+1 859 572 0430",
    "sg:postcode":"41076",
    "sg:province":"KY",
    "sg:tags":[
        "speech",
        "therapy",
        "hearing"
    ],
    "wof:name":"Speech Language Therapy Svcs",
    "wof:placetype":"venue"
},
  "geometry": {"coordinates":[-84.452395,39.034629],"type":"Point"}
}