{
  "type": "Feature",
  "properties": {
    "iso:country":"US",
    "sg:address":"3021 Mason Way",
    "sg:city":"Shelbyville",
    "sg:classifiers":[
        {
            "category":"Shopping",
            "subcategory":"Clothing, Apparel, & Fashions",
            "type":"Retail Goods"
        }
    ],
    "sg:phone":"+1 502 633 0467",
    "sg:postcode":"40065",
    "sg:province":"KY",
    "wof:name":"Eunique Designer Fashions",
    "wof:placetype":"venue"
},
  "geometry": {"coordinates":[-85.20252499999999,38.185512],"type":"Point"}
}