{
  "type": "Feature",
  "properties": {
    "iso:country":"US",
    "sg:address":"1609 Dixie Hwy S",
    "sg:city":"Elizabethtown",
    "sg:classifiers":[
        {
            "category":"Home & Garden",
            "subcategory":"Building Materials",
            "type":"Retail Goods"
        }
    ],
    "sg:phone":"+1 270 769 5437",
    "sg:postcode":"42701",
    "sg:province":"KY",
    "sg:tags":[
        "paint"
    ],
    "wof:name":"Morgan Carpet One",
    "wof:placetype":"venue"
},
  "geometry": {"coordinates":[-85.88481400000001,37.729797],"type":"Point"}
}