{
  "type": "Feature",
  "properties": {
    "iso:country":"US",
    "sg:address":"71 Dogwood Ln",
    "sg:city":"Mayfield",
    "sg:classifiers":[
        {
            "category":"Building & Trades",
            "subcategory":"Construction",
            "type":"Services"
        }
    ],
    "sg:phone":"+1 270 251 9580",
    "sg:postcode":"42066",
    "sg:province":"KY",
    "sg:tags":[
        "insulation",
        "heat",
        "contractor"
    ],
    "wof:name":"Thermo Spray Of West Ky",
    "wof:placetype":"venue"
},
  "geometry": {"coordinates":[-88.628212,36.684813],"type":"Point"}
}