{
  "type": "Feature",
  "properties": {
    "addr:full":"109 E 9th St Newport KY 41071",
    "addr:housenumber":"109",
    "addr:postcode":"41071",
    "addr:street":"E 9Th St",
    "iso:country":"US",
    "sg:address":"109 E 9th St",
    "sg:city":"Newport",
    "sg:classifiers":[
        {
            "category":"Arts & Performance",
            "subcategory":"Theater",
            "type":"Entertainment"
        }
    ],
    "sg:phone":"+1 859 491 3086",
    "sg:postcode":"41071",
    "sg:province":"KY",
    "sg:tags":[
        "bureau"
    ],
    "wof:name":"Entertainment Galaxy",
    "wof:placetype":"venue"
},
  "geometry": {"coordinates":[-84.48957799999999,39.088659],"type":"Point"}
}