{
  "type": "Feature",
  "properties": {
    "iso:country":"US",
    "sg:address":"115 N Main Cross St",
    "sg:city":"Louisa",
    "sg:classifiers":[
        {
            "category":"Shopping",
            "subcategory":"Discount & Variety Stores",
            "type":"Retail Goods"
        }
    ],
    "sg:phone":"+1 304 638 1303",
    "sg:postcode":"41230",
    "sg:province":"KY",
    "wof:name":"Variety Store",
    "wof:placetype":"venue"
},
  "geometry": {"coordinates":[-82.602977,38.115717],"type":"Point"}
}