{
  "type": "Feature",
  "properties": {
    "iso:country":"US",
    "sg:address":"6712 Dixie Hwy",
    "sg:city":"Florence",
    "sg:classifiers":[
        {
            "category":"Food & Beverages",
            "subcategory":"Groceries & Convenience Stores",
            "type":"Retail Goods"
        }
    ],
    "sg:phone":"+1 859 371 7216",
    "sg:postcode":"41042",
    "sg:province":"KY",
    "wof:name":"United Dairy Farmers",
    "wof:placetype":"venue"
},
  "geometry": {"coordinates":[-84.619732,39.004712],"type":"Point"}
}