{
  "type": "Feature",
  "properties": {
    "addr:full":"253 Main St Paintsville KY 41240",
    "addr:housenumber":"253",
    "addr:postcode":"41240",
    "addr:street":"Main St",
    "iso:country":"US",
    "sg:address":"253 Main St",
    "sg:city":"Paintsville",
    "sg:classifiers":[
        {
            "category":"Professional",
            "subcategory":"Lawyer & Legal Services",
            "type":"Services"
        }
    ],
    "sg:phone":"+1 606 789 1286",
    "sg:postcode":"41240",
    "sg:province":"KY",
    "sg:tags":[
        "attorney"
    ],
    "wof:name":"Johnson County Attorneys Off",
    "wof:placetype":"venue"
},
  "geometry": {"coordinates":[-82.80525299999999,37.813968],"type":"Point"}
}