{
  "type": "Feature",
  "properties": {
    "iso:country":"US",
    "sg:address":"1205 E New Circle Rd",
    "sg:city":"Lexington",
    "sg:classifiers":[
        {
            "category":"Shopping Center",
            "type":"Public Place"
        }
    ],
    "sg:phone":"+1 859 246 0028",
    "sg:postcode":"40505",
    "sg:province":"KY",
    "sg:tags":[
        "mall"
    ],
    "wof:name":"Lexington Peddlers Mall",
    "wof:placetype":"venue"
},
  "geometry": {"coordinates":[-84.452754,38.031562],"type":"Point"}
}