{
  "type": "Feature",
  "properties": {
    "iso:country":"US",
    "sg:address":"623 N Wilson Rd Ste A",
    "sg:city":"Radcliff",
    "sg:classifiers":[
        {
            "category":"Coffee & Tea",
            "type":"Food & Drink"
        },
        {
            "category":"Restaurant",
            "type":"Food & Drink"
        }
    ],
    "sg:phone":"+1 270 351 9443",
    "sg:postcode":"40160",
    "sg:province":"KY",
    "sg:tags":[
        "shop",
        "cafeteria",
        "espresso"
    ],
    "sg:website":"http://www.radcafe.com",
    "wof:name":"Internet Cafe",
    "wof:placetype":"venue"
},
  "geometry": {"coordinates":[-85.94439300000001,37.845294],"type":"Point"}
}