{
  "type": "Feature",
  "properties": {
    "iso:country":"US",
    "sg:address":"110 Carley Dr",
    "sg:city":"Georgetown",
    "sg:classifiers":[
        {
            "category":"Food & Beverages",
            "subcategory":"Bakery",
            "type":"Retail Goods"
        },
        {
            "category":"Bakery",
            "type":"Food & Drink"
        }
    ],
    "sg:phone":"+1 502 868 9388",
    "sg:postcode":"40324",
    "sg:province":"KY",
    "sg:tags":[
        "bakers-wholesale"
    ],
    "wof:name":"Interstate Brands Corp",
    "wof:placetype":"venue"
},
  "geometry": {"coordinates":[-84.543182,38.198372],"type":"Point"}
}