{
  "type": "Feature",
  "properties": {
    "iso:country":"US",
    "sg:address":"1201 River Rd",
    "sg:city":"Louisville",
    "sg:classifiers":[
        {
            "category":"Building & Trades",
            "subcategory":"Construction",
            "type":"Services"
        }
    ],
    "sg:phone":"+1 502 561 6066",
    "sg:postcode":"40206",
    "sg:province":"KY",
    "sg:tags":[
        "general",
        "contractor"
    ],
    "wof:name":"Sinclair Construction",
    "wof:placetype":"venue"
},
  "geometry": {"coordinates":[-85.73580800000001,38.262],"type":"Point"}
}