{
  "type": "Feature",
  "properties": {
    "iso:country":"US",
    "sg:address":"1301 Portland Ave Ste 1",
    "sg:city":"Louisville",
    "sg:classifiers":[
        {
            "category":"Manufacturing",
            "subcategory":"Buildings",
            "type":"Manufacturing & Wholesale Goods"
        },
        {
            "category":"Building & Trades",
            "subcategory":"Construction",
            "type":"Services"
        }
    ],
    "sg:phone":"+1 502 589 6526",
    "sg:postcode":"40203",
    "sg:province":"KY",
    "sg:tags":[
        "home",
        "builder",
        "contractor"
    ],
    "wof:name":"Hanka Builders",
    "wof:placetype":"venue"
},
  "geometry": {"coordinates":[-85.77422300000001,38.262218],"type":"Point"}
}