{
  "type": "Feature",
  "properties": {
    "addr:full":"1743 Belmar Dr Louisville KY 40213",
    "addr:housenumber":"1743",
    "addr:postcode":"40213",
    "addr:street":"Belmar Dr",
    "iso:country":"US",
    "sg:address":"1743 Belmar Dr",
    "sg:city":"Louisville",
    "sg:classifiers":[
        {
            "category":"Building & Trades",
            "subcategory":"Cleaning & Sanitation",
            "type":"Services"
        }
    ],
    "sg:phone":"+1 502 454 0234",
    "sg:postcode":"40213",
    "sg:province":"KY",
    "sg:tags":[
        "janitor"
    ],
    "wof:name":"Fresh Air Svc Inc",
    "wof:placetype":"venue"
},
  "geometry": {"coordinates":[-85.714136,38.203483],"type":"Point"}
}