{
  "type": "Feature",
  "properties": {
    "iso:country":"US",
    "sg:address":"123 Highview Dr",
    "sg:city":"Fort Thomas",
    "sg:classifiers":[
        {
            "category":"Professional",
            "subcategory":"Lawyer & Legal Services",
            "type":"Services"
        }
    ],
    "sg:phone":"+1 859 781 2257",
    "sg:postcode":"41075",
    "sg:province":"KY",
    "wof:name":"Ogden Jas F Lwyr",
    "wof:placetype":"venue"
},
  "geometry": {"coordinates":[-84.45909899999999,39.080799],"type":"Point"}
}