{
  "type": "Feature",
  "properties": {
    "addr:full":"10 Eagle Ln Hyden KY 41749",
    "addr:housenumber":"10",
    "addr:postcode":"41749",
    "addr:street":"Eagle Ln",
    "iso:country":"US",
    "sg:address":"10 Eagle Ln",
    "sg:city":"Hyden",
    "sg:classifiers":[
        {
            "category":"Retail",
            "subcategory":"Portrait Studio",
            "type":"Services"
        },
        {
            "category":"Professional",
            "subcategory":"Art Services",
            "type":"Services"
        }
    ],
    "sg:phone":"+1 606 672 3950",
    "sg:postcode":"41749",
    "sg:province":"KY",
    "sg:tags":[
        "rental",
        "photographers-portrait",
        "photographic",
        "darkroom"
    ],
    "wof:name":"Lane Memory Studio",
    "wof:placetype":"venue"
},
  "geometry": {"coordinates":[-83.38204,37.146169],"type":"Point"}
}