{
  "type": "Feature",
  "properties": {
    "iso:country":"US",
    "sg:address":"630 Emory Dr",
    "sg:city":"Owensboro",
    "sg:classifiers":[
        {
            "category":"Restaurant",
            "type":"Food & Drink"
        }
    ],
    "sg:phone":"+1 270 691 6133",
    "sg:postcode":"42301",
    "sg:province":"KY",
    "wof:name":"Los Cuatro Amigos",
    "wof:placetype":"venue"
},
  "geometry": {"coordinates":[-87.115934,37.748277],"type":"Point"}
}