{
  "type": "Feature",
  "properties": {
    "iso:country":"US",
    "sg:address":"4772 Allmond Ave",
    "sg:city":"Louisville",
    "sg:classifiers":[
        {
            "category":"Government",
            "subcategory":"Post Office",
            "type":"Public Place"
        }
    ],
    "sg:phone":"+1 502 368 8911",
    "sg:postcode":"40209",
    "sg:province":"KY",
    "wof:name":"US Post Office",
    "wof:placetype":"venue"
},
  "geometry": {"coordinates":[-85.757229,38.17637],"type":"Point"}
}