{
  "type": "Feature",
  "properties": {
    "iso:country":"US",
    "sg:address":"1443 County Rd",
    "sg:city":"Morgantown",
    "sg:classifiers":[
        {
            "category":"Home & Garden",
            "subcategory":"Building Materials",
            "type":"Retail Goods"
        }
    ],
    "sg:phone":"+1 270 526 2888",
    "sg:postcode":"42261",
    "sg:province":"KY",
    "sg:tags":[
        "lumber"
    ],
    "wof:name":"Church Hardwoods",
    "wof:placetype":"venue"
},
  "geometry": {"coordinates":[-86.629058,37.304031],"type":"Point"}
}