{
  "type": "Feature",
  "properties": {
    "iso:country":"US",
    "sg:address":"1 Big Red Way",
    "sg:city":"Bowling Green",
    "sg:classifiers":[
        {
            "category":"Restaurant",
            "type":"Food & Drink"
        }
    ],
    "sg:menulink":"http://www.allmenus.com/ky/bowling-green/120451-subway/menu/",
    "sg:phone":"+1 270 745 5099",
    "sg:postcode":"42101",
    "sg:province":"KY",
    "sg:tags":[
        "american",
        "sandwich"
    ],
    "wof:name":"Subway",
    "wof:placetype":"venue"
},
  "geometry": {"coordinates":[-86.452096,36.98905],"type":"Point"}
}