{
  "type": "Feature",
  "properties": {
    "addr:full":"103 Southview Sq Louisville KY 40214",
    "addr:housenumber":"103",
    "addr:postcode":"40214",
    "addr:street":"Southview Sq",
    "iso:country":"US",
    "sg:address":"103 Southview Sq",
    "sg:city":"Louisville",
    "sg:classifiers":[
        {
            "category":"Shopping",
            "type":"Retail Goods"
        }
    ],
    "sg:phone":"+1 502 368 6980",
    "sg:postcode":"40214",
    "sg:province":"KY",
    "sg:tags":[
        "religious"
    ],
    "wof:name":"Gabriel Publications",
    "wof:placetype":"venue"
},
  "geometry": {"coordinates":[-85.781961,38.147996],"type":"Point"}
}