{
  "type": "Feature",
  "properties": {
    "iso:country":"US",
    "sg:address":"602 S Fort Thomas Ave Ste 2",
    "sg:city":"Fort Thomas",
    "sg:classifiers":[
        {
            "category":"Banks & Credit Unions",
            "subcategory":"Bank",
            "type":"Services"
        }
    ],
    "sg:phone":"+1 859 442 9888",
    "sg:postcode":"41075",
    "sg:province":"KY",
    "wof:name":"Victory Community Bank",
    "wof:placetype":"venue"
},
  "geometry": {"coordinates":[-84.445638,39.071078],"type":"Point"}
}