{
  "type": "Feature",
  "properties": {
    "iso:country":"US",
    "sg:address":"231 S Clay Ave",
    "sg:city":"West Van Lear",
    "sg:classifiers":[
        {
            "category":"Organizations",
            "subcategory":"Religious Organization",
            "type":"Services"
        }
    ],
    "sg:phone":"+1 606 789 1123",
    "sg:postcode":"41268",
    "sg:province":"KY",
    "sg:tags":[
        "church"
    ],
    "wof:name":"West Vanlear Bapt Freewill Chr",
    "wof:placetype":"venue"
},
  "geometry": {"coordinates":[-82.77927,37.781713],"type":"Point"}
}