{
  "type": "Feature",
  "properties": {
    "iso:country":"US",
    "sg:address":"713 Berry St",
    "sg:city":"Independence",
    "sg:classifiers":[
        {
            "category":"Shopping",
            "subcategory":"Bicycles & Sporting Goods",
            "type":"Retail Goods"
        }
    ],
    "sg:phone":"+1 859 363 8300",
    "sg:postcode":"41074",
    "sg:province":"KY",
    "wof:name":"Soul Ride Bike Shop",
    "wof:placetype":"venue"
},
  "geometry": {"coordinates":[-84.470169,39.112874],"type":"Point"}
}