{
  "type": "Feature",
  "properties": {
    "iso:country":"US",
    "sg:address":"1150 S 3rd St",
    "sg:city":"Louisville",
    "sg:classifiers":[
        {
            "category":"Professional",
            "subcategory":"Lawyer & Legal Services",
            "type":"Services"
        }
    ],
    "sg:phone":"+1 502 357 6900",
    "sg:postcode":"40203",
    "sg:province":"KY",
    "sg:tags":[
        "practice",
        "attorney",
        "criminal",
        "law"
    ],
    "wof:name":"Moses W Christopher",
    "wof:placetype":"venue"
},
  "geometry": {"coordinates":[-85.758458,38.236047],"type":"Point"}
}