{
  "type": "Feature",
  "properties": {
    "addr:full":"350 Thomas More Pkwy Crestview Hills KY 41017",
    "addr:housenumber":"350",
    "addr:postcode":"41017",
    "addr:street":"Thomas More Pkwy",
    "iso:country":"US",
    "sg:address":"350 Thomas More Pkwy",
    "sg:city":"Crestview Hills",
    "sg:classifiers":[
        {
            "category":"Health Services",
            "subcategory":"Doctor",
            "type":"Services"
        }
    ],
    "sg:phone":"+1 859 426 0800",
    "sg:postcode":"41017",
    "sg:province":"KY",
    "sg:tags":[
        "physician",
        "surgeon"
    ],
    "wof:name":"Comprehensive Cardiology Cnslt",
    "wof:placetype":"venue"
},
  "geometry": {"coordinates":[-84.569428,39.023445],"type":"Point"}
}