{
  "type": "Feature",
  "properties": {
    "iso:country":"US",
    "sg:address":"1455 Catalpa St",
    "sg:city":"Louisville",
    "sg:classifiers":[
        {
            "category":"Organizations",
            "subcategory":"Religious Organization",
            "type":"Services"
        }
    ],
    "sg:phone":"+1 502 778 1050",
    "sg:postcode":"40211",
    "sg:province":"KY",
    "sg:tags":[
        "church"
    ],
    "wof:name":"Cane Run Missionary Baptist",
    "wof:placetype":"venue"
},
  "geometry": {"coordinates":[-85.802212,38.232186],"type":"Point"}
}