{
  "type": "Feature",
  "properties": {
    "iso:country":"US",
    "sg:address":"9701 Shady Acres Ln",
    "sg:city":"Louisville",
    "sg:classifiers":[
        {
            "category":"Building & Trades",
            "subcategory":"Construction",
            "type":"Services"
        }
    ],
    "sg:phone":"+1 502 266 9256",
    "sg:postcode":"40299",
    "sg:province":"KY",
    "sg:tags":[
        "house"
    ],
    "wof:name":"Chris Leigh Custom Built Homes",
    "wof:placetype":"venue"
},
  "geometry": {"coordinates":[-85.580369,38.175204],"type":"Point"}
}