{
  "type": "Feature",
  "properties": {
    "addr:full":"100 Canewood Blvd Georgetown KY 40324",
    "addr:housenumber":"100",
    "addr:postcode":"40324",
    "addr:street":"Canewood Blvd",
    "iso:country":"US",
    "sg:address":"100 Canewood Blvd",
    "sg:city":"Georgetown",
    "sg:classifiers":[
        {
            "category":"Autos & Motor Vehicles",
            "subcategory":"Fuel & Gas Station",
            "type":"Retail Goods"
        }
    ],
    "sg:phone":"+1 502 863 4621",
    "sg:postcode":"40324",
    "sg:province":"KY",
    "sg:tags":[
        "oil"
    ],
    "wof:name":"Clark Pump N Shop",
    "wof:placetype":"venue"
},
  "geometry": {"coordinates":[-84.590558,38.208802],"type":"Point"}
}