{
  "type": "Feature",
  "properties": {
    "iso:country":"US",
    "sg:address":"201 N Court St",
    "sg:city":"Scottsville",
    "sg:classifiers":[
        {
            "category":"Retail",
            "subcategory":"Funeral Services",
            "type":"Services"
        }
    ],
    "sg:phone":"+1 270 237 3114",
    "sg:postcode":"42164",
    "sg:province":"KY",
    "sg:tags":[
        "director"
    ],
    "wof:name":"T W Crow & Son Funeral Home",
    "wof:placetype":"venue"
},
  "geometry": {"coordinates":[-86.190191,36.755055],"type":"Point"}
}