{
  "type": "Feature",
  "properties": {
    "iso:country":"US",
    "sg:address":"590 Airport Rd",
    "sg:city":"London",
    "sg:classifiers":[
        {
            "category":"Autos & Motor Vehicles",
            "subcategory":"Automobile Sales",
            "type":"Retail Goods"
        }
    ],
    "sg:phone":"+1 606 864 3918",
    "sg:postcode":"40744",
    "sg:province":"KY",
    "wof:name":"Eurotrade International Inc",
    "wof:placetype":"venue"
},
  "geometry": {"coordinates":[-84.07445,37.090728],"type":"Point"}
}