{
  "type": "Feature",
  "properties": {
    "iso:country":"US",
    "sg:address":"4001 W Broadway",
    "sg:city":"Louisville",
    "sg:classifiers":[
        {
            "category":"Shopping",
            "type":"Retail Goods"
        }
    ],
    "sg:phone":"+1 502 778 6772",
    "sg:postcode":"40211",
    "sg:province":"KY",
    "sg:tags":[
        "cosmetic",
        "perfume"
    ],
    "wof:name":"Golden Beauty Supply",
    "wof:placetype":"venue"
},
  "geometry": {"coordinates":[-85.819209,38.250268],"type":"Point"}
}