{
  "type": "Feature",
  "properties": {
    "addr:full":"4700 Allmond Ave Louisville KY 40209",
    "addr:housenumber":"4700",
    "addr:postcode":"40209",
    "addr:street":"Allmond Ave",
    "iso:country":"US",
    "sg:address":"4700 Allmond Ave",
    "sg:city":"Louisville",
    "sg:classifiers":[
        {
            "category":"Professional",
            "subcategory":"Advertising",
            "type":"Services"
        }
    ],
    "sg:phone":"+1 502 499 5802",
    "sg:postcode":"40209",
    "sg:province":"KY",
    "sg:tags":[
        "distributing",
        "sample"
    ],
    "wof:name":"Dri View Distribution",
    "wof:placetype":"venue"
},
  "geometry": {"coordinates":[-85.754357,38.175869],"type":"Point"}
}