{
  "type": "Feature",
  "properties": {
    "iso:country":"US",
    "sg:address":"1011 Hampton Rd",
    "sg:city":"Salem",
    "sg:classifiers":[
        {
            "category":"Restaurant",
            "type":"Food & Drink"
        }
    ],
    "sg:phone":"+1 270 988 3737",
    "sg:postcode":"42078",
    "sg:province":"KY",
    "sg:tags":[
        "style",
        "family"
    ],
    "wof:name":"Denny Workman",
    "wof:placetype":"venue"
},
  "geometry": {"coordinates":[-88.30953599999999,37.317005],"type":"Point"}
}