{
  "type": "Feature",
  "properties": {
    "iso:country":"US",
    "sg:address":"197 Computrex Dr",
    "sg:city":"Nicholasville",
    "sg:classifiers":[
        {
            "category":"Professional",
            "type":"Services"
        }
    ],
    "sg:phone":"+1 859 881 1445",
    "sg:postcode":"40356",
    "sg:province":"KY",
    "sg:tags":[
        "establishment"
    ],
    "wof:name":"Tracom Ns LLC",
    "wof:placetype":"venue"
},
  "geometry": {"coordinates":[-84.55439699999999,37.935915],"type":"Point"}
}