{
  "type": "Feature",
  "properties": {
    "addr:full":"4917 Dixie Hwy Shively KY 40216",
    "addr:housenumber":"4917",
    "addr:postcode":"40216",
    "addr:street":"Dixie Hwy",
    "iso:country":"US",
    "sg:address":"4917 Dixie Hwy",
    "sg:city":"Shively",
    "sg:classifiers":[
        {
            "category":"Personal",
            "subcategory":"Beauty Salon",
            "type":"Services"
        }
    ],
    "sg:phone":"+1 502 448 1015",
    "sg:postcode":"40216",
    "sg:province":"KY",
    "wof:name":"Fantastic Sam's",
    "wof:placetype":"venue"
},
  "geometry": {"coordinates":[-85.828367,38.168597],"type":"Point"}
}