{
  "type": "Feature",
  "properties": {
    "iso:country":"US",
    "sg:address":"361 Veterans Hwy",
    "sg:city":"Morgantown",
    "sg:classifiers":[
        {
            "category":"Organizations",
            "subcategory":"Community Association",
            "type":"Services"
        }
    ],
    "sg:phone":"+1 270 526 9275",
    "sg:postcode":"42261",
    "sg:province":"KY",
    "sg:tags":[
        "club"
    ],
    "wof:name":"Veterans Of Foreign Wars",
    "wof:placetype":"venue"
},
  "geometry": {"coordinates":[-86.70086499999999,37.224101],"type":"Point"}
}