{
  "type": "Feature",
  "properties": {
    "iso:country":"US",
    "sg:address":"200 Lebanon Ave",
    "sg:city":"Campbellsville",
    "sg:classifiers":[
        {
            "category":"Autos & Motor Vehicles",
            "subcategory":"Automobile Sales",
            "type":"Retail Goods"
        }
    ],
    "sg:phone":"+1 270 789 1677",
    "sg:postcode":"42718",
    "sg:province":"KY",
    "sg:tags":[
        "car",
        "dealer"
    ],
    "wof:name":"Discount Used Cars",
    "wof:placetype":"venue"
},
  "geometry": {"coordinates":[-85.342141,37.343252],"type":"Point"}
}