{
  "type": "Feature",
  "properties": {
    "addr:full":"1714 Perryville Rd Danville KY 40422",
    "addr:housenumber":"1714",
    "addr:postcode":"40422",
    "addr:street":"Perryville Rd",
    "iso:country":"US",
    "sg:address":"1714 Perryville Rd",
    "sg:city":"Danville",
    "sg:classifiers":[
        {
            "category":"Professional",
            "subcategory":"Employment Agencies",
            "type":"Services"
        }
    ],
    "sg:phone":"+1 859 236 3432",
    "sg:postcode":"40422",
    "sg:province":"KY",
    "sg:tags":[
        "help",
        "contractor"
    ],
    "sg:website":"www.kellyservices.com",
    "wof:name":"Kelly Services Inc",
    "wof:placetype":"venue"
},
  "geometry": {"coordinates":[-84.79104100000001,37.64759],"type":"Point"}
}