{
  "type": "Feature",
  "properties": {
    "iso:country":"US",
    "sg:address":"834 Fountain Ave",
    "sg:city":"Louisville",
    "sg:classifiers":[
        {
            "category":"Professional",
            "subcategory":"Employment Agencies",
            "type":"Services"
        }
    ],
    "sg:phone":"+1 502 931 4834",
    "sg:postcode":"40222",
    "sg:province":"KY",
    "sg:tags":[
        "contractor"
    ],
    "wof:name":"C Wherthey Enterprises",
    "wof:placetype":"venue"
},
  "geometry": {"coordinates":[-85.61821399999999,38.263725],"type":"Point"}
}