{
  "type": "Feature",
  "properties": {
    "iso:country":"US",
    "sg:address":"102 Success Dr",
    "sg:city":"Georgetown",
    "sg:classifiers":[
        {
            "category":"Autos & Motor Vehicles",
            "subcategory":"Fuel & Gas Station",
            "type":"Retail Goods"
        }
    ],
    "sg:phone":"+1 502 570 9909",
    "sg:postcode":"40324",
    "sg:province":"KY",
    "sg:tags":[
        "oil"
    ],
    "wof:name":"Pro Travel Marathon",
    "wof:placetype":"venue"
},
  "geometry": {"coordinates":[-84.541528,38.218922],"type":"Point"}
}