{
  "type": "Feature",
  "properties": {
    "addr:full":"130 Depot St Springfield KY 40069",
    "addr:housenumber":"130",
    "addr:postcode":"40069",
    "addr:street":"Depot St",
    "iso:country":"US",
    "sg:address":"130 Depot St",
    "sg:city":"Springfield",
    "sg:classifiers":[
        {
            "category":"Insurance",
            "subcategory":"Insurance Agent",
            "type":"Services"
        }
    ],
    "sg:phone":"+1 859 336 0886",
    "sg:postcode":"40069",
    "sg:province":"KY",
    "wof:name":"American General Life Ins Co",
    "wof:placetype":"venue"
},
  "geometry": {"coordinates":[-85.22246699999999,37.683585],"type":"Point"}
}