{
  "type": "Feature",
  "properties": {
    "iso:country":"US",
    "sg:address":"201 Kentucky Ave",
    "sg:city":"Lexington",
    "sg:classifiers":[
        {
            "category":"Real Estate",
            "subcategory":"Architect",
            "type":"Services"
        }
    ],
    "sg:phone":"+1 859 233 1213",
    "sg:postcode":"40502",
    "sg:province":"KY",
    "wof:name":"Pearson/Bender Assoc Archs",
    "wof:placetype":"venue"
},
  "geometry": {"coordinates":[-84.495175,38.033713],"type":"Point"}
}