{
  "type": "Feature",
  "properties": {
    "addr:full":"511 Pierce Ln Frankfort KY 40601",
    "addr:housenumber":"511",
    "addr:postcode":"40601",
    "addr:street":"Pierce Ln",
    "iso:country":"US",
    "sg:address":"511 Pierce Ln",
    "sg:city":"Frankfort",
    "sg:classifiers":[
        {
            "category":"Shopping",
            "subcategory":"Bicycles & Sporting Goods",
            "type":"Retail Goods"
        }
    ],
    "sg:phone":"+1 502 223 8120",
    "sg:postcode":"40601",
    "sg:province":"KY",
    "sg:tags":[
        "gun",
        "gunsmith"
    ],
    "wof:name":"Mike's Guns Archery & Pawn",
    "wof:placetype":"venue"
},
  "geometry": {"coordinates":[-84.896112,38.192016],"type":"Point"}
}