{
  "type": "Feature",
  "properties": {
    "iso:country":"US",
    "sg:address":"1103 King Arthur Ln",
    "sg:city":"Louisville",
    "sg:classifiers":[
        {
            "category":"Wholesale",
            "subcategory":"Stationery",
            "type":"Manufacturing & Wholesale Goods"
        }
    ],
    "sg:phone":"+1 502 425 9009",
    "sg:postcode":"40222",
    "sg:province":"KY",
    "sg:tags":[
        "cup"
    ],
    "wof:name":"Irwin Sales Delivery Svc",
    "wof:placetype":"venue"
},
  "geometry": {"coordinates":[-85.612736,38.266617],"type":"Point"}
}