{
  "type": "Feature",
  "properties": {
    "addr:full":"3788 US Hwy 431 Calhoun KY 42327",
    "addr:housenumber":"3788",
    "addr:postcode":"42327",
    "addr:street":"Us Hwy 431",
    "iso:country":"US",
    "sg:address":"3788 US Hwy 431",
    "sg:city":"Calhoun",
    "sg:classifiers":[
        {
            "category":"Organizations",
            "subcategory":"Religious Organization",
            "type":"Services"
        }
    ],
    "sg:phone":"+1 270 733 4056",
    "sg:postcode":"42327",
    "sg:province":"KY",
    "sg:tags":[
        "church"
    ],
    "wof:name":"Buck Creek Baptist Church",
    "wof:placetype":"venue"
},
  "geometry": {"coordinates":[-87.109354,37.546073],"type":"Point"}
}