{
  "type": "Feature",
  "properties": {
    "iso:country":"US",
    "sg:address":"2424 Eagles Eyrie Ct",
    "sg:city":"Louisville",
    "sg:classifiers":[
        {
            "category":"Real Estate",
            "subcategory":"Real Estate Operator",
            "type":"Services"
        }
    ],
    "sg:phone":"+1 502 897 2112",
    "sg:postcode":"40206",
    "sg:province":"KY",
    "sg:tags":[
        "apartment"
    ],
    "wof:name":"Eagles Eyrie Apartments",
    "wof:placetype":"venue"
},
  "geometry": {"coordinates":[-85.69894600000001,38.25823],"type":"Point"}
}