{
  "type": "Feature",
  "properties": {
    "iso:country":"US",
    "sg:address":"634 Cherry Wood Dr",
    "sg:city":"Elizabethtown",
    "sg:classifiers":[
        {
            "category":"Real Estate",
            "subcategory":"Developer",
            "type":"Services"
        }
    ],
    "sg:phone":"+1 270 765 5227",
    "sg:postcode":"42701",
    "sg:province":"KY",
    "sg:tags":[
        "cemetery"
    ],
    "wof:name":"Hardin Memorial Cemetery",
    "wof:placetype":"venue"
},
  "geometry": {"coordinates":[-85.875638,37.706723],"type":"Point"}
}