{
  "type": "Feature",
  "properties": {
    "addr:full":"505 E 18th St Owensboro KY 42303",
    "addr:housenumber":"505",
    "addr:postcode":"42303",
    "addr:street":"E 18Th St",
    "iso:country":"US",
    "sg:address":"505 E 18th St",
    "sg:city":"Owensboro",
    "sg:classifiers":[
        {
            "category":"Retail",
            "subcategory":"Animal Services",
            "type":"Services"
        }
    ],
    "sg:phone":"+1 270 926 3075",
    "sg:postcode":"42303",
    "sg:province":"KY",
    "sg:tags":[
        "pet",
        "grooming",
        "washing"
    ],
    "wof:name":"D & L's Palace Of Pets",
    "wof:placetype":"venue"
},
  "geometry": {"coordinates":[-87.10284,37.758987],"type":"Point"}
}