{
  "type": "Feature",
  "properties": {
    "iso:country":"US",
    "sg:address":"850 Pine Valley Dr",
    "sg:city":"Elizabethtown",
    "sg:classifiers":[
        {
            "category":"Sports & Exercise",
            "subcategory":"Golf",
            "type":"Entertainment"
        }
    ],
    "sg:phone":"+1 270 737 8300",
    "sg:postcode":"42701",
    "sg:province":"KY",
    "sg:tags":[
        "course"
    ],
    "sg:website":"www.pinevalleygolfresort.com",
    "wof:name":"Pine Valley Golf Club",
    "wof:placetype":"venue"
},
  "geometry": {"coordinates":[-85.883815,37.756504],"type":"Point"}
}