{
  "type": "Feature",
  "properties": {
    "iso:country":"US",
    "sg:address":"800 E 18th St",
    "sg:city":"Owensboro",
    "sg:classifiers":[
        {
            "category":"Autos & Motor Vehicles",
            "subcategory":"Automobile Sales",
            "type":"Retail Goods"
        }
    ],
    "sg:phone":"+1 270 685 5690",
    "sg:postcode":"42303",
    "sg:province":"KY",
    "sg:tags":[
        "car",
        "dealer"
    ],
    "wof:name":"Heritage Motor Sales",
    "wof:placetype":"venue"
},
  "geometry": {"coordinates":[-87.10038900000001,37.758946],"type":"Point"}
}