{
  "type": "Feature",
  "properties": {
    "iso:country":"US",
    "sg:address":"5512 State Hwy 81",
    "sg:city":"Owensboro",
    "sg:phone":"+1 270 683 4255",
    "sg:postcode":"42301",
    "sg:province":"KY",
    "sg:tags":[
        "farm",
        "grain",
        "cash"
    ],
    "wof:name":"Raphael Ebelhar",
    "wof:placetype":"venue"
},
  "geometry": {"coordinates":[-87.19061000000001,37.697042],"type":"Point"}
}