{
  "type": "Feature",
  "properties": {
    "iso:country":"US",
    "sg:address":"3521 Park Plaza Rd",
    "sg:city":"Paducah",
    "sg:classifiers":[
        {
            "category":"Building & Trades",
            "subcategory":"Construction",
            "type":"Services"
        }
    ],
    "sg:phone":"+1 270 443 0220",
    "sg:postcode":"42001",
    "sg:province":"KY",
    "sg:tags":[
        "designer",
        "dealer",
        "pool",
        "swimming"
    ],
    "wof:name":"Aloha Pools & Spas",
    "wof:placetype":"venue"
},
  "geometry": {"coordinates":[-88.663472,37.081397],"type":"Point"}
}