{
  "type": "Feature",
  "properties": {
    "iso:country":"US",
    "sg:address":"333 Scott Blvd",
    "sg:city":"Covington",
    "sg:classifiers":[
        {
            "category":"Wholesale",
            "subcategory":"Vending Machines",
            "type":"Manufacturing & Wholesale Goods"
        }
    ],
    "sg:phone":"+1 859 431 8046",
    "sg:postcode":"41011",
    "sg:province":"KY",
    "wof:name":"Gateway Vending",
    "wof:placetype":"venue"
},
  "geometry": {"coordinates":[-84.509745,39.088287],"type":"Point"}
}