{
  "type": "Feature",
  "properties": {
    "iso:country":"US",
    "sg:address":"1847 Berry Blvd",
    "sg:city":"Louisville",
    "sg:classifiers":[
        {
            "category":"Building & Trades",
            "subcategory":"Construction",
            "type":"Services"
        }
    ],
    "sg:phone":"+1 502 361 7777",
    "sg:postcode":"40215",
    "sg:province":"KY",
    "sg:tags":[
        "consulting",
        "gutter",
        "business",
        "cover",
        "contractor",
        "r"
    ],
    "sg:website":"http://www.abramsroofing.com",
    "wof:name":"Abrams Roofing & Sheet Metal Inc",
    "wof:placetype":"venue"
},
  "geometry": {"coordinates":[-85.79741,38.196742],"type":"Point"}
}