{
  "type": "Feature",
  "properties": {
    "iso:country":"US",
    "sg:address":"55 Co Rd 7f",
    "sg:city":"Ironton",
    "sg:classifiers":[
        {
            "category":"Manufacturing",
            "subcategory":"Retail Goods",
            "type":"Manufacturing & Wholesale Goods"
        }
    ],
    "sg:phone":"+1 740 533 2657",
    "sg:postcode":"45638",
    "sg:province":"OH",
    "sg:tags":[
        "product",
        "mfg"
    ],
    "wof:name":"Kelly Jessi",
    "wof:placetype":"venue"
},
  "geometry": {"coordinates":[-82.638858,38.560745],"type":"Point"}
}