{
  "type": "Feature",
  "properties": {
    "iso:country":"US",
    "sg:address":"1010 Clarks Ln",
    "sg:city":"Louisville",
    "sg:classifiers":[
        {
            "category":"Shopping",
            "type":"Retail Goods"
        }
    ],
    "sg:phone":"+1 502 634 6349",
    "sg:postcode":"40217",
    "sg:province":"KY",
    "sg:tags":[
        "orthopedic",
        "appliance"
    ],
    "wof:name":"Center-Orthotic & Prosthetic",
    "wof:placetype":"venue"
},
  "geometry": {"coordinates":[-85.72886,38.219821],"type":"Point"}
}