{
  "type": "Feature",
  "properties": {
    "iso:country":"US",
    "sg:address":"226 Copper Ln",
    "sg:city":"Burkesville",
    "sg:classifiers":[
        {
            "category":"Health Services",
            "subcategory":"Optometrist",
            "type":"Services"
        }
    ],
    "sg:phone":"+1 270 864 3894",
    "sg:postcode":"42717",
    "sg:province":"KY",
    "wof:name":"Wagner Eye Ctr",
    "wof:placetype":"venue"
},
  "geometry": {"coordinates":[-85.376803,36.786523],"type":"Point"}
}