{
  "type": "Feature",
  "properties": {
    "addr:full":"1600 Scottsville Rd Bowling Green KY 42104",
    "addr:housenumber":"1600",
    "addr:postcode":"42104",
    "addr:street":"Scottsville Rd",
    "iso:country":"US",
    "sg:address":"1600 Scottsville Rd",
    "sg:city":"Bowling Green",
    "sg:classifiers":[
        {
            "category":"Health Services",
            "subcategory":"Clinic",
            "type":"Services"
        }
    ],
    "sg:phone":"+1 270 781 0028",
    "sg:postcode":"42104",
    "sg:province":"KY",
    "sg:tags":[
        "home"
    ],
    "wof:name":"Phoenix Rehab Group",
    "wof:placetype":"venue"
},
  "geometry": {"coordinates":[-86.434675,36.971329],"type":"Point"}
}