{
  "type": "Feature",
  "properties": {
    "iso:country":"US",
    "sg:address":"201 N Main St",
    "sg:city":"Beaver Dam",
    "sg:classifiers":[
        {
            "category":"Retail",
            "subcategory":"Portrait Studio",
            "type":"Services"
        }
    ],
    "sg:phone":"+1 270 274 3227",
    "sg:postcode":"42320",
    "sg:province":"KY",
    "sg:tags":[
        "photographer"
    ],
    "wof:name":"Studio II",
    "wof:placetype":"venue"
},
  "geometry": {"coordinates":[-86.87586400000001,37.403918],"type":"Point"}
}