{
  "type": "Feature",
  "properties": {
    "iso:country":"US",
    "sg:address":"9420 Bunsen Pkwy",
    "sg:city":"Louisville",
    "sg:classifiers":[
        {
            "category":"Health Services",
            "subcategory":"Clinic",
            "type":"Services"
        }
    ],
    "sg:phone":"+1 502 753 0160",
    "sg:postcode":"40220",
    "sg:province":"KY",
    "sg:tags":[
        "organization",
        "maintenance"
    ],
    "wof:name":"Community Health Solutions",
    "wof:placetype":"venue"
},
  "geometry": {"coordinates":[-85.58641799999999,38.221565],"type":"Point"}
}