{
  "type": "Feature",
  "properties": {
    "iso:country":"US",
    "sg:address":"1439 Pigeon Fork Rd",
    "sg:city":"Lawrenceburg",
    "sg:classifiers":[
        {
            "category":"Building & Trades",
            "subcategory":"Construction",
            "type":"Services"
        }
    ],
    "sg:phone":"+1 502 839 3025",
    "sg:postcode":"40342",
    "sg:province":"KY",
    "sg:tags":[
        "carpenter"
    ],
    "wof:name":"Jon Butler Inc",
    "wof:placetype":"venue"
},
  "geometry": {"coordinates":[-85.041555,38.099438],"type":"Point"}
}