{
  "type": "Feature",
  "properties": {
    "iso:country":"US",
    "sg:address":"1152 Dixie Hwy",
    "sg:city":"Louisville",
    "sg:classifiers":[
        {
            "category":"Social Services",
            "subcategory":"Child Care",
            "type":"Services"
        }
    ],
    "sg:phone":"+1 502 774 2376",
    "sg:postcode":"40210",
    "sg:province":"KY",
    "wof:name":"Kiddieland Day Care Ctr",
    "wof:placetype":"venue"
},
  "geometry": {"coordinates":[-85.786807,38.237494],"type":"Point"}
}