{
  "type": "Feature",
  "properties": {
    "iso:country":"US",
    "sg:address":"4450 S 3rd St",
    "sg:city":"Louisville",
    "sg:classifiers":[
        {
            "category":"Food & Beverages",
            "subcategory":"Liquor & Beverages",
            "type":"Retail Goods"
        }
    ],
    "sg:phone":"+1 502 363 4110",
    "sg:postcode":"40214",
    "sg:province":"KY",
    "wof:name":"Express Liquors",
    "wof:placetype":"venue"
},
  "geometry": {"coordinates":[-85.764859,38.189859],"type":"Point"}
}