{
  "type": "Feature",
  "properties": {
    "iso:country":"US",
    "sg:address":"9900 Corporate Campus Dr Ste 3000",
    "sg:city":"Louisville",
    "sg:classifiers":[
        {
            "category":"Autos & Motor Vehicles",
            "subcategory":"Auto Supplies",
            "type":"Retail Goods"
        },
        {
            "category":"Manufacturing",
            "subcategory":"Glass & Minerals",
            "type":"Manufacturing & Wholesale Goods"
        }
    ],
    "sg:phone":"+1 502 240 5550",
    "sg:postcode":"40223",
    "sg:province":"KY",
    "sg:tags":[
        "plate",
        "glass-auto",
        "window",
        "tinting"
    ],
    "wof:name":"Sun Shield",
    "wof:placetype":"venue"
},
  "geometry": {"coordinates":[-85.575508,38.265049],"type":"Point"}
}