{
  "type": "Feature",
  "properties": {
    "iso:country":"US",
    "sg:address":"901 S 6th St",
    "sg:city":"Louisville",
    "sg:classifiers":[
        {
            "category":"Autos & Motor Vehicles",
            "subcategory":"Auto Supplies",
            "type":"Retail Goods"
        }
    ],
    "sg:phone":"+1 502 585 1010",
    "sg:postcode":"40203",
    "sg:province":"KY",
    "sg:tags":[
        "tire"
    ],
    "wof:name":"Carrie Ferrel",
    "wof:placetype":"venue"
},
  "geometry": {"coordinates":[-85.762413,38.24231],"type":"Point"}
}