{
  "type": "Feature",
  "properties": {
    "iso:country":"US",
    "sg:address":"325 Triplett St",
    "sg:city":"Morehead",
    "sg:classifiers":[
        {
            "category":"Wholesale",
            "subcategory":"Scrap",
            "type":"Manufacturing & Wholesale Goods"
        }
    ],
    "sg:phone":"+1 606 784 1250",
    "sg:postcode":"40351",
    "sg:province":"KY",
    "sg:tags":[
        "recycling",
        "center"
    ],
    "wof:name":"Community Recycling Ctr",
    "wof:placetype":"venue"
},
  "geometry": {"coordinates":[-83.42952099999999,38.181589],"type":"Point"}
}