{
  "type": "Feature",
  "properties": {
    "iso:country":"US",
    "sg:address":"103 Drake Ln",
    "sg:city":"Georgetown",
    "sg:classifiers":[
        {
            "category":"Banks & Credit Unions",
            "subcategory":"Investment Brokerage",
            "type":"Services"
        }
    ],
    "sg:phone":"+1 502 863 2864",
    "sg:postcode":"40324",
    "sg:province":"KY",
    "sg:tags":[
        "advisory",
        "financial"
    ],
    "wof:name":"S & L Financial Svc Inc",
    "wof:placetype":"venue"
},
  "geometry": {"coordinates":[-84.578366,38.308426],"type":"Point"}
}