{
  "type": "Feature",
  "properties": {
    "iso:country":"US",
    "sg:address":"7702 Preston Hwy",
    "sg:city":"Okolona",
    "sg:classifiers":[
        {
            "category":"Retail",
            "subcategory":"Laundry & Dry Cleaning",
            "type":"Services"
        }
    ],
    "sg:phone":"+1 502 964 3217",
    "sg:postcode":"40219",
    "sg:province":"KY",
    "sg:tags":[
        "cleaners"
    ],
    "wof:name":"Vogt The Cleaners",
    "wof:placetype":"venue"
},
  "geometry": {"coordinates":[-85.687738,38.140105],"type":"Point"}
}