{
  "type": "Feature",
  "properties": {
    "addr:full":"1231 Durrett Ln Louisville KY 40213",
    "addr:housenumber":"1231",
    "addr:postcode":"40213",
    "addr:street":"Durrett Ln",
    "iso:country":"US",
    "sg:address":"1231 Durrett Ln",
    "sg:city":"Louisville",
    "sg:classifiers":[
        {
            "category":"Professional",
            "subcategory":"Employment Agencies",
            "type":"Services"
        }
    ],
    "sg:phone":"+1 502 315 2352",
    "sg:postcode":"40213",
    "sg:province":"KY",
    "sg:tags":[
        "temporary",
        "help"
    ],
    "wof:name":"Randstad North America LP",
    "wof:placetype":"venue"
},
  "geometry": {"coordinates":[-85.720949,38.188284],"type":"Point"}
}