{
  "type": "Feature",
  "properties": {
    "iso:country":"US",
    "sg:address":"783 Chittenden Rd",
    "sg:city":"Salem",
    "sg:classifiers":[
        {
            "category":"Farming",
            "subcategory":"Livestock Farm",
            "type":"Manufacturing & Wholesale Goods"
        }
    ],
    "sg:phone":"+1 270 988 3531",
    "sg:postcode":"42078",
    "sg:province":"KY",
    "sg:tags":[
        "beef",
        "feedlot",
        "cattle"
    ],
    "wof:name":"Chittenden Lucian",
    "wof:placetype":"venue"
},
  "geometry": {"coordinates":[-88.35679500000001,37.349335],"type":"Point"}
}