{
  "type": "Feature",
  "properties": {
    "addr:full":"104 Washington Ct Mt Washington KY 40047",
    "addr:housenumber":"104",
    "addr:postcode":"40047",
    "addr:street":"Washington Ct",
    "iso:country":"US",
    "sg:address":"104 Washington Ct",
    "sg:city":"Mt Washington",
    "sg:classifiers":[
        {
            "category":"Shopping",
            "subcategory":"Computers & Home Electronics",
            "type":"Retail Goods"
        }
    ],
    "sg:phone":"+1 502 538 2277",
    "sg:postcode":"40047",
    "sg:province":"KY",
    "sg:tags":[
        "high",
        "fidelity",
        "stereophonic"
    ],
    "wof:name":"Mountain City Audio",
    "wof:placetype":"venue"
},
  "geometry": {"coordinates":[-85.55814100000001,38.059162],"type":"Point"}
}