{
  "type": "Feature",
  "properties": {
    "iso:country":"US",
    "sg:address":"4837 Madison Pike",
    "sg:city":"Independence",
    "sg:classifiers":[
        {
            "category":"Retail",
            "subcategory":"Repair Shop",
            "type":"Services"
        }
    ],
    "sg:phone":"+1 859 363 8621",
    "sg:postcode":"41051",
    "sg:province":"KY",
    "sg:tags":[
        "taxidermist"
    ],
    "wof:name":"A-1 Hamrick's Wildlife Studio",
    "wof:placetype":"venue"
},
  "geometry": {"coordinates":[-84.542351,38.975604],"type":"Point"}
}