{
  "type": "Feature",
  "properties": {
    "addr:full":"6150 State Hwy 70 Bremen KY 42325",
    "addr:housenumber":"6150",
    "addr:postcode":"42325",
    "addr:street":"State Hwy 70",
    "iso:country":"US",
    "sg:address":"6150 State Hwy 70",
    "sg:city":"Bremen",
    "sg:classifiers":[
        {
            "category":"Retail",
            "subcategory":"Portrait Studio",
            "type":"Services"
        }
    ],
    "sg:phone":"+1 270 757 0060",
    "sg:postcode":"42325",
    "sg:province":"KY",
    "sg:tags":[
        "photo"
    ],
    "wof:name":"Jennifer Hoeft Photography",
    "wof:placetype":"venue"
},
  "geometry": {"coordinates":[-87.24181,37.309253],"type":"Point"}
}