{
  "type": "Feature",
  "properties": {
    "iso:country":"US",
    "sg:address":"101 W 10th Ave",
    "sg:city":"Bowling Green",
    "sg:classifiers":[
        {
            "category":"Retail",
            "subcategory":"Auto Repair",
            "type":"Services"
        }
    ],
    "sg:phone":"+1 270 842 6650",
    "sg:postcode":"42101",
    "sg:province":"KY",
    "sg:tags":[
        "wrecker"
    ],
    "wof:name":"Moe's Towing & Automotive",
    "wof:placetype":"venue"
},
  "geometry": {"coordinates":[-86.44799399999999,36.99807],"type":"Point"}
}