{
  "type": "Feature",
  "properties": {
    "addr:full":"1490 Belmar Dr Louisville KY 40213",
    "addr:housenumber":"1490",
    "addr:postcode":"40213",
    "addr:street":"Belmar Dr",
    "iso:country":"US",
    "sg:address":"1490 Belmar Dr",
    "sg:city":"Louisville",
    "sg:classifiers":[
        {
            "category":"Organizations",
            "subcategory":"Religious Organization",
            "type":"Services"
        }
    ],
    "sg:phone":"+1 502 458 4329",
    "sg:postcode":"40213",
    "sg:province":"KY",
    "sg:tags":[
        "church"
    ],
    "wof:name":"St Lukes United Methodist Chr",
    "wof:placetype":"venue"
},
  "geometry": {"coordinates":[-85.719212,38.197399],"type":"Point"}
}