{
  "type": "Feature",
  "properties": {
    "iso:country":"US",
    "sg:address":"3004 Clark St",
    "sg:city":"Paducah",
    "sg:classifiers":[
        {
            "category":"Professional",
            "type":"Services"
        }
    ],
    "sg:phone":"+1 270 444 4595",
    "sg:postcode":"42001",
    "sg:province":"KY",
    "sg:tags":[
        "establishment"
    ],
    "wof:name":"Millennium Tech",
    "wof:placetype":"venue"
},
  "geometry": {"coordinates":[-88.632811,37.068773],"type":"Point"}
}