{
  "type": "Feature",
  "properties": {
    "iso:country":"US",
    "sg:address":"2408 Merchant St",
    "sg:city":"Lexington",
    "sg:classifiers":[
        {
            "category":"Professional",
            "subcategory":"Business Services",
            "type":"Services"
        }
    ],
    "sg:phone":"+1 859 231 6424",
    "sg:postcode":"40511",
    "sg:province":"KY",
    "sg:tags":[
        "paper",
        "lamination"
    ],
    "wof:name":"Tri-State Laminators Inc",
    "wof:placetype":"venue"
},
  "geometry": {"coordinates":[-84.54462599999999,38.078024],"type":"Point"}
}