{
  "type": "Feature",
  "properties": {
    "iso:country":"US",
    "sg:address":"521 Henry Clay Blvd",
    "sg:city":"Lexington",
    "sg:classifiers":[
        {
            "category":"Shopping",
            "subcategory":"Discount & Variety Stores",
            "type":"Retail Goods"
        }
    ],
    "sg:phone":"+1 859 252 0142",
    "sg:postcode":"40505",
    "sg:province":"KY",
    "sg:tags":[
        "merchandise",
        "general"
    ],
    "wof:name":"City Salvage Co",
    "wof:placetype":"venue"
},
  "geometry": {"coordinates":[-84.465664,38.036336],"type":"Point"}
}