{
  "type": "Feature",
  "properties": {
    "addr:full":"217 W Belleville St Marion KY 42064",
    "addr:housenumber":"217",
    "addr:postcode":"42064",
    "addr:street":"W Belleville St",
    "iso:country":"US",
    "sg:address":"217 W Belleville St",
    "sg:city":"Marion",
    "sg:classifiers":[
        {
            "category":"Professional",
            "subcategory":"Lawyer & Legal Services",
            "type":"Services"
        }
    ],
    "sg:phone":"+1 270 965 2222",
    "sg:postcode":"42064",
    "sg:province":"KY",
    "sg:tags":[
        "attorney"
    ],
    "wof:name":"Rebecca J Johnson Law Offices",
    "wof:placetype":"venue"
},
  "geometry": {"coordinates":[-88.084683,37.333371],"type":"Point"}
}