{
  "type": "Feature",
  "properties": {
    "iso:country":"US",
    "sg:address":"6616 Zebulon Hwy",
    "sg:city":"Pikeville",
    "sg:classifiers":[
        {
            "category":"Wholesale",
            "subcategory":"Farm Supplies",
            "type":"Manufacturing & Wholesale Goods"
        }
    ],
    "sg:phone":"+1 606 631 4993",
    "sg:postcode":"41501",
    "sg:province":"KY",
    "wof:name":"Taylor's Farm",
    "wof:placetype":"venue"
},
  "geometry": {"coordinates":[-82.454593,37.553197],"type":"Point"}
}