{
  "type": "Feature",
  "properties": {
    "iso:country":"US",
    "sg:address":"65 Beech Dr",
    "sg:city":"Edgewood",
    "sg:classifiers":[
        {
            "category":"Recreation",
            "subcategory":"Fishing",
            "type":"Entertainment"
        }
    ],
    "sg:phone":"+1 859 341 6711",
    "sg:postcode":"41017",
    "sg:province":"KY",
    "sg:tags":[
        "tackle",
        "bait"
    ],
    "wof:name":"Sorrell Tackle",
    "wof:placetype":"venue"
},
  "geometry": {"coordinates":[-84.582176,39.02026],"type":"Point"}
}