{
  "type": "Feature",
  "properties": {
    "iso:country":"US",
    "sg:address":"2021 Frederica St",
    "sg:city":"Owensboro",
    "sg:classifiers":[
        {
            "category":"Professional",
            "subcategory":"Business Services",
            "type":"Services"
        }
    ],
    "sg:phone":"+1 270 684 7679",
    "sg:postcode":"42301",
    "sg:province":"KY",
    "sg:tags":[
        "interior",
        "consultant",
        "design",
        "decorator"
    ],
    "wof:name":"Ted Bowne",
    "wof:placetype":"venue"
},
  "geometry": {"coordinates":[-87.11168000000001,37.755483],"type":"Point"}
}