{
  "type": "Feature",
  "properties": {
    "iso:country":"US",
    "sg:address":"6900 Hopeful Rd",
    "sg:city":"Florence",
    "sg:classifiers":[
        {
            "category":"Personal",
            "subcategory":"Beauty Salon",
            "type":"Services"
        }
    ],
    "sg:phone":"+1 859 283 2939",
    "sg:postcode":"41042",
    "sg:province":"KY",
    "sg:tags":[
        "shop"
    ],
    "wof:name":"T R's Haircare",
    "wof:placetype":"venue"
},
  "geometry": {"coordinates":[-84.661717,38.993876],"type":"Point"}
}