{
  "type": "Feature",
  "properties": {
    "iso:country":"US",
    "sg:address":"817 S 8th St",
    "sg:city":"Ironton",
    "sg:classifiers":[
        {
            "category":"Organizations",
            "subcategory":"Religious Organization",
            "type":"Services"
        }
    ],
    "sg:phone":"+1 740 533 3304",
    "sg:postcode":"45638",
    "sg:province":"OH",
    "sg:tags":[
        "church"
    ],
    "wof:name":"New Jerusalem Christian Ctr",
    "wof:placetype":"venue"
},
  "geometry": {"coordinates":[-82.67574,38.532707],"type":"Point"}
}