{
  "type": "Feature",
  "properties": {
    "iso:country":"US",
    "sg:address":"520 Tyree Rd",
    "sg:city":"Paducah",
    "sg:classifiers":[
        {
            "category":"Building & Trades",
            "subcategory":"Construction",
            "type":"Services"
        }
    ],
    "sg:phone":"+1 270 898 7145",
    "sg:postcode":"42003",
    "sg:province":"KY",
    "sg:tags":[
        "dry wall",
        "contractor"
    ],
    "wof:name":"A & M Drywall",
    "wof:placetype":"venue"
},
  "geometry": {"coordinates":[-88.512826,37.002061],"type":"Point"}
}