{
  "type": "Feature",
  "properties": {
    "addr:full":"1745 Linstead Ct Lexington KY 40504",
    "addr:housenumber":"1745",
    "addr:postcode":"40504",
    "addr:street":"Linstead Ct",
    "iso:country":"US",
    "sg:address":"1745 Linstead Ct",
    "sg:city":"Lexington",
    "sg:classifiers":[
        {
            "category":"Real Estate",
            "subcategory":"Architect",
            "type":"Services"
        }
    ],
    "sg:phone":"+1 859 277 1879",
    "sg:postcode":"40504",
    "sg:province":"KY",
    "sg:tags":[
        "architectural"
    ],
    "wof:name":"Holton Buckley Architect",
    "wof:placetype":"venue"
},
  "geometry": {"coordinates":[-84.558939,38.039196],"type":"Point"}
}