{
  "type": "Feature",
  "properties": {
    "addr:full":"511 Thurman Dr Lexington KY 40505",
    "addr:housenumber":"511",
    "addr:postcode":"40505",
    "addr:street":"Thurman Dr",
    "iso:country":"US",
    "sg:address":"511 Thurman Dr",
    "sg:city":"Lexington",
    "sg:classifiers":[
        {
            "category":"Organizations",
            "subcategory":"Religious Organization",
            "type":"Services"
        }
    ],
    "sg:phone":"+1 859 294 5646",
    "sg:postcode":"40505",
    "sg:province":"KY",
    "wof:name":"St John Baptist Church",
    "wof:placetype":"venue"
},
  "geometry": {"coordinates":[-84.468447,38.076843],"type":"Point"}
}