{
  "type": "Feature",
  "properties": {
    "addr:full":"7500 Old Franklin Rd Scottsville KY 42164",
    "addr:housenumber":"7500",
    "addr:postcode":"42164",
    "addr:street":"Old Franklin Rd",
    "iso:country":"US",
    "sg:address":"7500 Old Franklin Rd",
    "sg:city":"Scottsville",
    "sg:classifiers":[
        {
            "category":"Building & Trades",
            "subcategory":"Construction",
            "type":"Services"
        }
    ],
    "sg:phone":"+1 270 622 2539",
    "sg:postcode":"42164",
    "sg:province":"KY",
    "sg:tags":[
        "general",
        "contractor"
    ],
    "wof:name":"Saw Dust Shop & Construction",
    "wof:placetype":"venue"
},
  "geometry": {"coordinates":[-86.38351299999999,36.753217],"type":"Point"}
}