{
  "type": "Feature",
  "properties": {
    "iso:country":"US",
    "sg:address":"7862 Brandenburg Rd",
    "sg:city":"Leitchfield",
    "sg:classifiers":[
        {
            "category":"Professional",
            "subcategory":"Business Services",
            "type":"Services"
        }
    ],
    "sg:phone":"+1 270 259 9774",
    "sg:postcode":"42754",
    "sg:province":"KY",
    "wof:name":"Specialty Cakes",
    "wof:placetype":"venue"
},
  "geometry": {"coordinates":[-86.32590500000001,37.580637],"type":"Point"}
}