{
  "type": "Feature",
  "properties": {
    "iso:country":"US",
    "sg:address":"256 Hemlock Dr",
    "sg:city":"Russell Springs",
    "sg:classifiers":[
        {
            "category":"Retail",
            "subcategory":"Auto Repair",
            "type":"Services"
        }
    ],
    "sg:phone":"+1 270 866 8666",
    "sg:postcode":"42642",
    "sg:province":"KY",
    "sg:tags":[
        "body",
        "automobile",
        "painting"
    ],
    "wof:name":"Auto Make-Up",
    "wof:placetype":"venue"
},
  "geometry": {"coordinates":[-85.05941,37.094427],"type":"Point"}
}