{
  "type": "Feature",
  "properties": {
    "iso:country":"US",
    "sg:address":"3657 Yates Rd",
    "sg:city":"Hornbeak",
    "sg:classifiers":[
        {
            "category":"Professional",
            "type":"Services"
        }
    ],
    "sg:phone":"+1 731 538 2078",
    "sg:postcode":"38232",
    "sg:province":"TN",
    "wof:name":"Larry H Mitchell",
    "wof:placetype":"venue"
},
  "geometry": {"coordinates":[-89.277957,36.348216],"type":"Point"}
}