{
  "type": "Feature",
  "properties": {
    "addr:full":"709 Phillips Ln Louisville KY 40209",
    "addr:housenumber":"709",
    "addr:postcode":"40209",
    "addr:street":"Phillips Ln",
    "iso:country":"US",
    "sg:address":"709 Phillips Ln",
    "sg:city":"Louisville",
    "sg:classifiers":[
        {
            "category":"Travel",
            "subcategory":"Hotels & Motels",
            "type":"Entertainment"
        }
    ],
    "sg:phone":"+1 502 363 9952",
    "sg:postcode":"40209",
    "sg:province":"KY",
    "sg:website":"www.hojo.com",
    "wof:name":"Howard Johnson",
    "wof:placetype":"venue"
},
  "geometry": {"coordinates":[-85.742075,38.192065],"type":"Point"}
}