{
  "type": "Feature",
  "properties": {
    "addr:full":"5932 Timber Ridge Dr Prospect KY 40059",
    "addr:housenumber":"5932",
    "addr:postcode":"40059",
    "addr:street":"Timber Ridge Dr",
    "iso:country":"US",
    "sg:address":"5932 Timber Ridge Dr",
    "sg:city":"Prospect",
    "sg:classifiers":[
        {
            "category":"Banks & Credit Unions",
            "subcategory":"Bank",
            "type":"Services"
        }
    ],
    "sg:phone":"+1 502 292 2806",
    "sg:postcode":"40059",
    "sg:province":"KY",
    "sg:tags":[
        "loan",
        "real estate"
    ],
    "wof:name":"Wells Fargo Home Mortgage Inc",
    "wof:placetype":"venue"
},
  "geometry": {"coordinates":[-85.622861,38.338908],"type":"Point"}
}