{
  "type": "Feature",
  "properties": {
    "addr:full":"108 Lakeview Dr Elizabethtown KY 42701",
    "addr:housenumber":"108",
    "addr:postcode":"42701",
    "addr:street":"Lakeview Dr",
    "iso:country":"US",
    "sg:address":"108 Lakeview Dr",
    "sg:city":"Elizabethtown",
    "sg:classifiers":[
        {
            "category":"Professional",
            "subcategory":"Management & Consulting",
            "type":"Services"
        }
    ],
    "sg:phone":"+1 270 360 9288",
    "sg:postcode":"42701",
    "sg:province":"KY",
    "sg:tags":[
        "consultant",
        "chain",
        "supply"
    ],
    "wof:name":"Coulter Consulting",
    "wof:placetype":"venue"
},
  "geometry": {"coordinates":[-85.86354900000001,37.721909],"type":"Point"}
}