{
  "type": "Feature",
  "properties": {
    "addr:full":"526 Hopewell St Madisonville KY 42431",
    "addr:housenumber":"526",
    "addr:postcode":"42431",
    "addr:street":"Hopewell St",
    "iso:country":"US",
    "sg:address":"526 Hopewell St",
    "sg:city":"Madisonville",
    "sg:classifiers":[
        {
            "category":"Organizations",
            "subcategory":"Religious Organization",
            "type":"Services"
        }
    ],
    "sg:phone":"+1 270 821 8078",
    "sg:postcode":"42431",
    "sg:province":"KY",
    "sg:tags":[
        "church"
    ],
    "wof:name":"Christ Church Holiness",
    "wof:placetype":"venue"
},
  "geometry": {"coordinates":[-87.502189,37.336233],"type":"Point"}
}