{
  "type": "Feature",
  "properties": {
    "addr:full":"1301 US Hwy 62 Princeton KY 42445",
    "addr:housenumber":"1301",
    "addr:postcode":"42445",
    "addr:street":"Us Hwy 62",
    "iso:country":"US",
    "sg:address":"1301 US Hwy 62",
    "sg:city":"Princeton",
    "sg:classifiers":[
        {
            "category":"Wholesale",
            "subcategory":"Farm Supplies",
            "type":"Manufacturing & Wholesale Goods"
        }
    ],
    "sg:phone":"+1 270 365 7232",
    "sg:postcode":"42445",
    "sg:province":"KY",
    "sg:tags":[
        "fertilizer"
    ],
    "wof:name":"Agri-Chem Inc",
    "wof:placetype":"venue"
},
  "geometry": {"coordinates":[-87.860754,37.119293],"type":"Point"}
}