{
  "type": "Feature",
  "properties": {
    "iso:country":"US",
    "sg:address":"106 E Washington St",
    "sg:city":"Princeton",
    "sg:classifiers":[
        {
            "category":"Restaurant",
            "type":"Food & Drink"
        }
    ],
    "sg:phone":"+1 270 365 9033",
    "sg:postcode":"42445",
    "sg:province":"KY",
    "wof:name":"Peggy's Cafe",
    "wof:placetype":"venue"
},
  "geometry": {"coordinates":[-87.88267,37.107906],"type":"Point"}
}