{
  "type": "Feature",
  "properties": {
    "iso:country":"US",
    "sg:address":"96 Cross Creek Farms Rd",
    "sg:city":"Benton",
    "sg:classifiers":[
        {
            "category":"Professional",
            "subcategory":"Computer Services",
            "type":"Services"
        }
    ],
    "sg:phone":"+1 270 527 9412",
    "sg:postcode":"42025",
    "sg:province":"KY",
    "sg:tags":[
        "consultant",
        "designer"
    ],
    "wof:name":"Computer Consulting & Network",
    "wof:placetype":"venue"
},
  "geometry": {"coordinates":[-88.30823599999999,36.909488],"type":"Point"}
}