{
  "type": "Feature",
  "properties": {
    "iso:country":"US",
    "sg:address":"410 E Mount Vernon St",
    "sg:city":"Somerset",
    "sg:classifiers":[
        {
            "category":"Government",
            "subcategory":"Office",
            "type":"Public Place"
        }
    ],
    "sg:phone":"+1 606 676 0759",
    "sg:postcode":"42501",
    "sg:province":"KY",
    "wof:name":"Cumberlands WIA",
    "wof:placetype":"venue"
},
  "geometry": {"coordinates":[-84.598715,37.094377],"type":"Point"}
}