{
  "type": "Feature",
  "properties": {
    "iso:country":"US",
    "sg:address":"3347 Tates Creek Rd",
    "sg:city":"Lexington",
    "sg:classifiers":[
        {
            "category":"Education",
            "subcategory":"Dance Studio",
            "type":"Public Place"
        }
    ],
    "sg:phone":"+1 859 268 3382",
    "sg:postcode":"40502",
    "sg:province":"KY",
    "sg:tags":[
        "instruction",
        "dancing"
    ],
    "wof:name":"Gotta Dance Studio Inc",
    "wof:placetype":"venue"
},
  "geometry": {"coordinates":[-84.495576,37.994988],"type":"Point"}
}