{
  "type": "Feature",
  "properties": {
    "addr:full":"88 Darlas Dr Cold Spring KY 41076",
    "addr:housenumber":"88",
    "addr:postcode":"41076",
    "addr:street":"Darlas Dr",
    "iso:country":"US",
    "sg:address":"88 Darlas Dr",
    "sg:city":"Cold Spring",
    "sg:classifiers":[
        {
            "category":"Organizations",
            "subcategory":"Membership Organization",
            "type":"Services"
        }
    ],
    "sg:phone":"+1 859 572 0003",
    "sg:postcode":"41076",
    "sg:province":"KY",
    "sg:tags":[
        "athletic"
    ],
    "sg:website":"www.nksl-soccer.org",
    "wof:name":"Northern Kentucky Soccer",
    "wof:placetype":"venue"
},
  "geometry": {"coordinates":[-84.45287,39.015113],"type":"Point"}
}