{
  "type": "Feature",
  "properties": {
    "iso:country":"US",
    "sg:address":"2353 Paris Pike",
    "sg:city":"Lexington",
    "sg:classifiers":[
        {
            "category":"Food & Beverages",
            "subcategory":"Groceries & Convenience Stores",
            "type":"Retail Goods"
        }
    ],
    "sg:phone":"+1 859 294 0459",
    "sg:postcode":"40505",
    "sg:province":"KY",
    "wof:name":"Paris Pike Food Mart",
    "wof:placetype":"venue"
},
  "geometry": {"coordinates":[-84.446915,38.081099],"type":"Point"}
}