{
  "type": "Feature",
  "properties": {
    "addr:full":"1750 Alexandria Dr Lexington KY 40504",
    "addr:housenumber":"1750",
    "addr:postcode":"40504",
    "addr:street":"Alexandria Dr",
    "iso:country":"US",
    "sg:address":"1750 Alexandria Dr",
    "sg:city":"Lexington",
    "sg:classifiers":[
        {
            "category":"Health Services",
            "subcategory":"Doctor",
            "type":"Services"
        }
    ],
    "sg:phone":"+1 859 278 8471",
    "sg:postcode":"40504",
    "sg:province":"KY",
    "sg:tags":[
        "physician",
        "surgeon"
    ],
    "wof:name":"Marina T Yarbro MD",
    "wof:placetype":"venue"
},
  "geometry": {"coordinates":[-84.552426,38.038157],"type":"Point"}
}