{
  "type": "Feature",
  "properties": {
    "addr:full":"7300 Turfway Rd Florence KY 41042",
    "addr:housenumber":"7300",
    "addr:postcode":"41042",
    "addr:street":"Turfway Rd",
    "iso:country":"US",
    "sg:address":"7300 Turfway Rd",
    "sg:city":"Florence",
    "sg:classifiers":[
        {
            "category":"Wholesale",
            "subcategory":"Drugs",
            "type":"Manufacturing & Wholesale Goods"
        }
    ],
    "sg:phone":"+1 859 371 7581",
    "sg:postcode":"41042",
    "sg:province":"KY",
    "sg:tags":[
        "pharmaceutical",
        "product"
    ],
    "wof:name":"Union Springs II",
    "wof:placetype":"venue"
},
  "geometry": {"coordinates":[-84.62939799999999,39.011922],"type":"Point"}
}