{
  "type": "Feature",
  "properties": {
    "iso:country":"US",
    "sg:address":"202 Merchant St",
    "sg:city":"Cadiz",
    "sg:classifiers":[
        {
            "category":"Insurance",
            "subcategory":"Hazard Insurance",
            "type":"Services"
        },
        {
            "category":"Insurance",
            "subcategory":"Insurance Agent",
            "type":"Services"
        },
        {
            "category":"Insurance",
            "subcategory":"Life Insurance",
            "type":"Services"
        },
        {
            "category":"Insurance",
            "subcategory":"Title Insurance",
            "type":"Services"
        }
    ],
    "sg:phone":"+1 270 522 5700",
    "sg:postcode":"42211",
    "sg:province":"KY",
    "sg:tags":[
        "auto",
        "commercial",
        "business",
        "homeowner"
    ],
    "wof:name":"Goodwin Insurance Agency Of Cadiz",
    "wof:placetype":"venue"
},
  "geometry": {"coordinates":[-87.792509,36.868028],"type":"Point"}
}