{
  "type": "Feature",
  "properties": {
    "iso:country":"US",
    "sg:address":"2701 Veach Rd",
    "sg:city":"Owensboro",
    "sg:classifiers":[
        {
            "category":"Shopping",
            "subcategory":"Florist",
            "type":"Retail Goods"
        }
    ],
    "sg:phone":"+1 270 685 8322",
    "sg:postcode":"42303",
    "sg:province":"KY",
    "wof:name":"Granny Smith Florist",
    "wof:placetype":"venue"
},
  "geometry": {"coordinates":[-87.101849,37.749012],"type":"Point"}
}