{
  "type": "Feature",
  "properties": {
    "iso:country":"US",
    "sg:address":"90 Alexandria Pike",
    "sg:city":"Fort Thomas",
    "sg:classifiers":[
        {
            "category":"Shopping",
            "subcategory":"Jewelry",
            "type":"Retail Goods"
        }
    ],
    "sg:phone":"+1 859 442 0506",
    "sg:postcode":"41075",
    "sg:province":"KY",
    "sg:tags":[
        "jeweler"
    ],
    "wof:name":"Fort Thomas Jewelers",
    "wof:placetype":"venue"
},
  "geometry": {"coordinates":[-84.466893,39.068811],"type":"Point"}
}