{
  "type": "Feature",
  "properties": {
    "iso:country":"US",
    "sg:address":"3920 US Hwy 25",
    "sg:city":"Carrollton",
    "sg:classifiers":[
        {
            "category":"Building & Trades",
            "subcategory":"Plumbing",
            "type":"Services"
        }
    ],
    "sg:phone":"+1 502 732 8863",
    "sg:postcode":"41018",
    "sg:province":"KY",
    "sg:tags":[
        "contractor"
    ],
    "wof:name":"Potts Tim Heating & Cooling",
    "wof:placetype":"venue"
},
  "geometry": {"coordinates":[-84.605306,39.013792],"type":"Point"}
}