{
  "type": "Feature",
  "properties": {
    "iso:country":"US",
    "sg:address":"934 Louisville Rd",
    "sg:city":"Frankfort",
    "sg:classifiers":[
        {
            "category":"Banks & Credit Unions",
            "subcategory":"Bank",
            "type":"Services"
        }
    ],
    "sg:phone":"+1 502 696 9280",
    "sg:postcode":"40601",
    "sg:province":"KY",
    "sg:tags":[
        "cashing",
        "check"
    ],
    "wof:name":"Quik Cash Of Kentucky",
    "wof:placetype":"venue"
},
  "geometry": {"coordinates":[-84.891904,38.181853],"type":"Point"}
}