{
  "type": "Feature",
  "properties": {
    "addr:full":"1312 Russell Cave Rd Lexington KY 40505",
    "addr:housenumber":"1312",
    "addr:postcode":"40505",
    "addr:street":"Russell Cave Rd",
    "iso:country":"US",
    "sg:address":"1312 Russell Cave Rd",
    "sg:city":"Lexington",
    "sg:classifiers":[
        {
            "category":"Home & Garden",
            "subcategory":"Building Materials",
            "type":"Retail Goods"
        }
    ],
    "sg:phone":"+1 859 233 0312",
    "sg:postcode":"40505",
    "sg:province":"KY",
    "sg:tags":[
        "windows"
    ],
    "wof:name":"Ni Autowindow Systems Inc",
    "wof:placetype":"venue"
},
  "geometry": {"coordinates":[-84.480619,38.068389],"type":"Point"}
}