{
  "type": "Feature",
  "properties": {
    "addr:full":"2460 Beech Grove Rd Shepherdsville KY 40165",
    "addr:housenumber":"2460",
    "addr:postcode":"40165",
    "addr:street":"Beech Grove Rd",
    "iso:country":"US",
    "sg:address":"2460 Beech Grove Rd",
    "sg:city":"Shepherdsville",
    "sg:classifiers":[
        {
            "category":"Recreation",
            "type":"Entertainment"
        },
        {
            "category":"Farming",
            "subcategory":"Aquatic Farm",
            "type":"Manufacturing & Wholesale Goods"
        }
    ],
    "sg:phone":"+1 502 921 0277",
    "sg:postcode":"40165",
    "sg:province":"KY",
    "sg:tags":[
        "pond",
        "fishing",
        "lake"
    ],
    "wof:name":"Al's Pay Lake",
    "wof:placetype":"venue"
},
  "geometry": {"coordinates":[-85.74878099999999,37.96082],"type":"Point"}
}