{
  "type": "Feature",
  "properties": {
    "addr:full":"1639 Greenland Park Cir Shelbyville KY 40065",
    "addr:housenumber":"1639",
    "addr:postcode":"40065",
    "addr:street":"Greenland Park Cir",
    "iso:country":"US",
    "sg:address":"1639 Greenland Park Cir",
    "sg:city":"Shelbyville",
    "sg:classifiers":[
        {
            "category":"Retail",
            "subcategory":"Repair Shop",
            "type":"Services"
        }
    ],
    "sg:phone":"+1 502 633 2748",
    "sg:postcode":"40065",
    "sg:province":"KY",
    "sg:tags":[
        "locksmith"
    ],
    "wof:name":"Dans Lock & Key",
    "wof:placetype":"venue"
},
  "geometry": {"coordinates":[-85.206857,38.190834],"type":"Point"}
}