{
  "type": "Feature",
  "properties": {
    "iso:country":"US",
    "sg:address":"2021 Alexandria Pike",
    "sg:city":"Newport",
    "sg:classifiers":[
        {
            "category":"Professional",
            "subcategory":"Business Services",
            "type":"Services"
        }
    ],
    "sg:phone":"+1 859 781 0800",
    "sg:postcode":"41076",
    "sg:province":"KY",
    "wof:name":"All State Financial Services",
    "wof:placetype":"venue"
},
  "geometry": {"coordinates":[-84.44553999999999,39.04566],"type":"Point"}
}