{
  "type": "Feature",
  "properties": {
    "iso:country":"US",
    "sg:address":"1128 Winchester Rd",
    "sg:city":"Lexington",
    "sg:classifiers":[
        {
            "category":"Bars & Pubs",
            "type":"Food & Drink"
        }
    ],
    "sg:phone":"+1 859 388 2604",
    "sg:postcode":"40505",
    "sg:province":"KY",
    "sg:tags":[
        "lounge",
        "cocktail"
    ],
    "wof:name":"Suede Ultra Lounge",
    "wof:placetype":"venue"
},
  "geometry": {"coordinates":[-84.461377,38.04244],"type":"Point"}
}