{
  "type": "Feature",
  "properties": {
    "addr:full":"108 Magnolia St Barbourville KY 40906",
    "addr:housenumber":"108",
    "addr:postcode":"40906",
    "addr:street":"Magnolia St",
    "iso:country":"US",
    "sg:address":"108 Magnolia St",
    "sg:city":"Barbourville",
    "sg:classifiers":[
        {
            "category":"Shopping",
            "subcategory":"Used Merchandise",
            "type":"Retail Goods"
        }
    ],
    "sg:phone":"+1 606 546 9500",
    "sg:postcode":"40906",
    "sg:province":"KY",
    "sg:tags":[
        "shop",
        "consignment"
    ],
    "wof:name":"Teens Tots & More",
    "wof:placetype":"venue"
},
  "geometry": {"coordinates":[-83.87951200000001,36.859964],"type":"Point"}
}