{
  "type": "Feature",
  "properties": {
    "addr:full":"600 Meriwether Ave Louisville KY 40217",
    "addr:housenumber":"600",
    "addr:postcode":"40217",
    "addr:street":"Meriwether Ave",
    "iso:country":"US",
    "sg:address":"600 Meriwether Ave",
    "sg:city":"Louisville",
    "sg:classifiers":[
        {
            "category":"Utilities",
            "subcategory":"Refuse",
            "type":"Services"
        }
    ],
    "sg:phone":"+1 502 574 3571",
    "sg:postcode":"40217",
    "sg:province":"KY",
    "sg:tags":[
        "system"
    ],
    "wof:name":"Solid Waste Management Service",
    "wof:placetype":"venue"
},
  "geometry": {"coordinates":[-85.74450400000001,38.227649],"type":"Point"}
}