{
  "type": "Feature",
  "properties": {
    "iso:country":"US",
    "sg:address":"500 Clark St",
    "sg:city":"Paducah",
    "sg:classifiers":[
        {
            "category":"Government",
            "subcategory":"Office",
            "type":"Public Place"
        }
    ],
    "sg:phone":"+1 270 442 6381",
    "sg:postcode":"42003",
    "sg:province":"KY",
    "sg:tags":[
        "county",
        "safety",
        "order"
    ],
    "wof:name":"Mc Cracken County Disaster",
    "wof:placetype":"venue"
},
  "geometry": {"coordinates":[-88.59741,37.083154],"type":"Point"}
}