{
  "type": "Feature",
  "properties": {
    "iso:country":"US",
    "sg:address":"4320 S Wilson Rd",
    "sg:city":"Elizabethtown",
    "sg:classifiers":[
        {
            "category":"Organizations",
            "subcategory":"Religious Organization",
            "type":"Services"
        }
    ],
    "sg:phone":"+1 270 737 7558",
    "sg:postcode":"42701",
    "sg:province":"KY",
    "sg:tags":[
        "church"
    ],
    "wof:name":"Longview United Methodist",
    "wof:placetype":"venue"
},
  "geometry": {"coordinates":[-85.91124499999999,37.783927],"type":"Point"}
}