{
  "type": "Feature",
  "properties": {
    "addr:full":"8075 Steilen Dr Florence KY 41042",
    "addr:postcode":"8075;41042",
    "addr:street":"Steilen Dr",
    "iso:country":"US",
    "sg:address":"8075 Steilen Dr",
    "sg:city":"Florence",
    "sg:classifiers":[
        {
            "category":"Travel",
            "subcategory":"Hotels & Motels",
            "type":"Entertainment"
        }
    ],
    "sg:phone":"+1 859 371 0277",
    "sg:postcode":"41042",
    "sg:province":"KY",
    "sg:tags":[
        "operation"
    ],
    "wof:name":"Cli Investments Inc",
    "wof:placetype":"venue"
},
  "geometry": {"coordinates":[-84.643592,38.983225],"type":"Point"}
}