{
  "type": "Feature",
  "properties": {
    "addr:full":"12109 Madison Pike Independence KY 41051",
    "addr:housenumber":"12109",
    "addr:postcode":"41051",
    "addr:street":"Madison Pike",
    "iso:country":"US",
    "sg:address":"12109 Madison Pike",
    "sg:city":"Independence",
    "sg:classifiers":[
        {
            "category":"Retail",
            "subcategory":"Veterinary Services",
            "type":"Services"
        }
    ],
    "sg:phone":"+1 859 356 8883",
    "sg:postcode":"41051",
    "sg:province":"KY",
    "sg:tags":[
        "veterinarian"
    ],
    "wof:name":"Bach Veterinary Clinic",
    "wof:placetype":"venue"
},
  "geometry": {"coordinates":[-84.541409,38.89964],"type":"Point"}
}