{
  "type": "Feature",
  "properties": {
    "iso:country":"US",
    "sg:address":"1108 N College St",
    "sg:city":"Harrodsburg",
    "sg:classifiers":[
        {
            "category":"Home & Garden",
            "subcategory":"Home Furnishings",
            "type":"Retail Goods"
        }
    ],
    "sg:phone":"+1 859 734 4763",
    "sg:postcode":"40330",
    "sg:province":"KY",
    "wof:name":"Harrodsburg Dish Barn",
    "wof:placetype":"venue"
},
  "geometry": {"coordinates":[-84.846294,37.783714],"type":"Point"}
}