{
  "type": "Feature",
  "properties": {
    "iso:country":"US",
    "sg:address":"2300 W Broadway",
    "sg:city":"Louisville",
    "sg:classifiers":[
        {
            "category":"Personal",
            "subcategory":"Barber",
            "type":"Services"
        }
    ],
    "sg:phone":"+1 502 778 2539",
    "sg:postcode":"40211",
    "sg:province":"KY",
    "wof:name":"Geometric Shapes By Alex",
    "wof:placetype":"venue"
},
  "geometry": {"coordinates":[-85.79156399999999,38.249333],"type":"Point"}
}