{
  "type": "Feature",
  "properties": {
    "addr:full":"5960 Dunbar Rd New Concord KY 42076",
    "addr:housenumber":"5960",
    "addr:postcode":"42076",
    "addr:street":"Dunbar Rd",
    "iso:country":"US",
    "sg:address":"5960 Dunbar Rd",
    "sg:city":"New Concord",
    "sg:classifiers":[
        {
            "category":"Food & Beverages",
            "subcategory":"Groceries & Convenience Stores",
            "type":"Retail Goods"
        }
    ],
    "sg:phone":"+1 270 436 5175",
    "sg:postcode":"42076",
    "sg:province":"KY",
    "sg:tags":[
        "grocer"
    ],
    "wof:name":"Hamlin One Stop",
    "wof:placetype":"venue"
},
  "geometry": {"coordinates":[-88.081813,36.596247],"type":"Point"}
}