{
  "type": "Feature",
  "properties": {
    "iso:country":"US",
    "sg:address":"1521 Park Ave",
    "sg:city":"Paducah",
    "sg:classifiers":[
        {
            "category":"Banks & Credit Unions",
            "subcategory":"Bank",
            "type":"Services"
        },
        {
            "category":"Banks & Credit Unions",
            "subcategory":"Financial Services",
            "type":"Services"
        }
    ],
    "sg:phone":"+1 270 898 6266",
    "sg:postcode":"42001",
    "sg:province":"KY",
    "sg:tags":[
        "commercial",
        "financing",
        "saving",
        "loan"
    ],
    "sg:website":"http://www.bbt.com",
    "wof:name":"BB & T",
    "wof:placetype":"venue"
},
  "geometry": {"coordinates":[-88.618492,37.086089],"type":"Point"}
}