{
  "type": "Feature",
  "properties": {
    "addr:full":"9216 Westport Rd Louisville KY 40242",
    "addr:housenumber":"9216",
    "addr:postcode":"40242",
    "addr:street":"Westport Rd",
    "iso:country":"US",
    "sg:address":"9216 Westport Rd",
    "sg:city":"Louisville",
    "sg:classifiers":[
        {
            "category":"Personal",
            "subcategory":"Beauty Salon",
            "type":"Services"
        }
    ],
    "sg:phone":"+1 502 425 5212",
    "sg:postcode":"40242",
    "sg:province":"KY",
    "wof:name":"Hairport",
    "wof:placetype":"venue"
},
  "geometry": {"coordinates":[-85.580023,38.285075],"type":"Point"}
}