{
  "type": "Feature",
  "properties": {
    "iso:country":"US",
    "sg:address":"321 Simmerman St",
    "sg:city":"Hartford",
    "sg:classifiers":[
        {
            "category":"Social Services",
            "subcategory":"Child Care",
            "type":"Services"
        }
    ],
    "sg:phone":"+1 270 298 3489",
    "sg:postcode":"42347",
    "sg:province":"KY",
    "wof:name":"Little Friends Playhouse",
    "wof:placetype":"venue"
},
  "geometry": {"coordinates":[-86.89426899999999,37.451987],"type":"Point"}
}