{
  "type": "Feature",
  "properties": {
    "iso:country":"US",
    "sg:address":"33 Catfish Cir",
    "sg:city":"Hazard",
    "sg:classifiers":[
        {
            "category":"Manufacturing",
            "subcategory":"Buildings",
            "type":"Manufacturing & Wholesale Goods"
        },
        {
            "category":"Building & Trades",
            "subcategory":"Construction",
            "type":"Services"
        }
    ],
    "sg:phone":"+1 606 436 6342",
    "sg:postcode":"41701",
    "sg:province":"KY",
    "sg:tags":[
        "excavation",
        "home",
        "builder",
        "contractor"
    ],
    "wof:name":"Clinton Construction, Inc",
    "wof:placetype":"venue"
},
  "geometry": {"coordinates":[-83.193388,37.276539],"type":"Point"}
}