{
  "type": "Feature",
  "properties": {
    "iso:country":"US",
    "sg:address":"1497 Taylor Bridge Rd",
    "sg:city":"London",
    "sg:classifiers":[
        {
            "category":"Real Estate",
            "subcategory":"Surveying",
            "type":"Services"
        }
    ],
    "sg:phone":"+1 606 878 6834",
    "sg:postcode":"40744",
    "sg:province":"KY",
    "sg:tags":[
        "surveyor"
    ],
    "wof:name":"Peters Land Surveying",
    "wof:placetype":"venue"
},
  "geometry": {"coordinates":[-84.10816699999999,37.040731],"type":"Point"}
}