{
  "type": "Feature",
  "properties": {
    "addr:full":"219 Ballard St Barbourville KY 40906",
    "addr:housenumber":"219",
    "addr:postcode":"40906",
    "addr:street":"Ballard St",
    "iso:country":"US",
    "sg:address":"219 Ballard St",
    "sg:city":"Barbourville",
    "sg:classifiers":[
        {
            "category":"Utilities",
            "subcategory":"Fuel Oil & Lpg",
            "type":"Services"
        }
    ],
    "sg:phone":"+1 606 546 4647",
    "sg:postcode":"40906",
    "sg:province":"KY",
    "sg:tags":[
        "wood"
    ],
    "wof:name":"City-Barbourville Street Dept",
    "wof:placetype":"venue"
},
  "geometry": {"coordinates":[-83.886065,36.866174],"type":"Point"}
}