{
  "type": "Feature",
  "properties": {
    "iso:country":"US",
    "sg:address":"505 Barton Dr",
    "sg:city":"Mayfield",
    "sg:classifiers":[
        {
            "category":"Personal",
            "subcategory":"Beauty Salon",
            "type":"Services"
        }
    ],
    "sg:phone":"+1 270 247 6822",
    "sg:postcode":"42066",
    "sg:province":"KY",
    "wof:name":"Jayne's",
    "wof:placetype":"venue"
},
  "geometry": {"coordinates":[-88.624982,36.724084],"type":"Point"}
}