{
  "type": "Feature",
  "properties": {
    "iso:country":"US",
    "sg:address":"1500 Leestown Rd",
    "sg:city":"Lexington",
    "sg:classifiers":[
        {
            "category":"Health Services",
            "subcategory":"Doctor",
            "type":"Services"
        }
    ],
    "sg:phone":"+1 859 243 0332",
    "sg:postcode":"40511",
    "sg:province":"KY",
    "sg:tags":[
        "dentist"
    ],
    "wof:name":"Masterson Dentistry",
    "wof:placetype":"venue"
},
  "geometry": {"coordinates":[-84.52560699999999,38.067147],"type":"Point"}
}