{
  "type": "Feature",
  "properties": {
    "addr:full":"1815 Mayfield Dr Crestwood KY 40014",
    "addr:housenumber":"1815",
    "addr:postcode":"40014",
    "addr:street":"Mayfield Dr",
    "iso:country":"US",
    "sg:address":"1815 Mayfield Dr",
    "sg:city":"Crestwood",
    "sg:classifiers":[
        {
            "category":"Building & Trades",
            "subcategory":"Construction",
            "type":"Services"
        }
    ],
    "sg:phone":"+1 502 225 9393",
    "sg:postcode":"40014",
    "sg:province":"KY",
    "sg:tags":[
        "designer"
    ],
    "wof:name":"Frank Luecke Design",
    "wof:placetype":"venue"
},
  "geometry": {"coordinates":[-85.35189099999999,38.330279],"type":"Point"}
}