{
  "type": "Feature",
  "properties": {
    "iso:country":"US",
    "sg:address":"875 N Bend Rd",
    "sg:city":"Hebron",
    "sg:classifiers":[
        {
            "category":"Education",
            "subcategory":"School",
            "type":"Public Place"
        }
    ],
    "sg:phone":"+1 859 334 7000",
    "sg:postcode":"41048",
    "sg:province":"KY",
    "sg:website":"www.boone.k12.ky.us",
    "wof:name":"North Pointe Elementary School",
    "wof:placetype":"venue"
},
  "geometry": {"coordinates":[-84.73264399999999,39.112501],"type":"Point"}
}