{
  "type": "Feature",
  "properties": {
    "addr:full":"519 Morrison Dr Clarksville KY 37042",
    "addr:housenumber":"519",
    "addr:postcode":"37042",
    "addr:street":"Morrison Dr",
    "iso:country":"US",
    "sg:address":"519 Morrison Dr",
    "sg:city":"Clarksville",
    "sg:classifiers":[
        {
            "category":"Retail",
            "subcategory":"Animal Services",
            "type":"Services"
        }
    ],
    "sg:phone":"+1 931 503 1877",
    "sg:postcode":"37042",
    "sg:province":"KY",
    "sg:tags":[
        "pet",
        "grooming",
        "washing"
    ],
    "wof:name":"Two Paws Up Grooming",
    "wof:placetype":"venue"
},
  "geometry": {"coordinates":[-87.412015,36.55236],"type":"Point"}
}