{
  "type": "Feature",
  "properties": {
    "iso:country":"US",
    "sg:address":"523 Old Hwy 90",
    "sg:city":"Monticello",
    "sg:classifiers":[
        {
            "category":"Building & Trades",
            "subcategory":"Construction",
            "type":"Services"
        }
    ],
    "sg:phone":"+1 606 348 8877",
    "sg:postcode":"42633",
    "sg:province":"KY",
    "sg:tags":[
        "excavating",
        "contractor"
    ],
    "wof:name":"Upchurch Truck & Equipment",
    "wof:placetype":"venue"
},
  "geometry": {"coordinates":[-84.832814,36.856737],"type":"Point"}
}