{
  "type": "Feature",
  "properties": {
    "iso:country":"US",
    "sg:address":"2515 Ransdell Ave",
    "sg:city":"Louisville",
    "sg:classifiers":[
        {
            "category":"Sports & Exercise",
            "subcategory":"Race Track",
            "type":"Entertainment"
        }
    ],
    "sg:phone":"+1 502 473 1036",
    "sg:postcode":"40204",
    "sg:province":"KY",
    "sg:tags":[
        "operation",
        "racing",
        "or"
    ],
    "wof:name":"Commemorative Derby Promotions",
    "wof:placetype":"venue"
},
  "geometry": {"coordinates":[-85.707222,38.242545],"type":"Point"}
}