{
  "type": "Feature",
  "properties": {
    "addr:full":"2237 Hikes Ln Louisville KY 40218",
    "addr:housenumber":"2237",
    "addr:postcode":"40218",
    "addr:street":"Hikes Ln",
    "iso:country":"US",
    "sg:address":"2237 Hikes Ln",
    "sg:city":"Louisville",
    "sg:classifiers":[
        {
            "category":"Health Services",
            "subcategory":"Doctor",
            "type":"Services"
        },
        {
            "category":"Health Services",
            "subcategory":"Clinic",
            "type":"Services"
        }
    ],
    "sg:phone":"+1 502 479 8930",
    "sg:postcode":"40218",
    "sg:province":"KY",
    "sg:tags":[
        "physician",
        "surgeon",
        "outpatient"
    ],
    "wof:name":"Newburg Primary Care Center",
    "wof:placetype":"venue"
},
  "geometry": {"coordinates":[-85.65879099999999,38.199841],"type":"Point"}
}