{
  "type": "Feature",
  "properties": {
    "iso:country":"US",
    "sg:address":"78 Spruce St",
    "sg:city":"Murray",
    "sg:classifiers":[
        {
            "category":"Wholesale",
            "subcategory":"Drugs",
            "type":"Manufacturing & Wholesale Goods"
        }
    ],
    "sg:phone":"+1 270 753 6033",
    "sg:postcode":"42071",
    "sg:province":"KY",
    "sg:tags":[
        "pharmaceutical",
        "product"
    ],
    "wof:name":"Nephron Pharmaceutical Corp",
    "wof:placetype":"venue"
},
  "geometry": {"coordinates":[-88.296753,36.614391],"type":"Point"}
}