{
  "type": "Feature",
  "properties": {
    "iso:country":"US",
    "sg:address":"325 Richmond St",
    "sg:city":"Mt Vernon",
    "sg:classifiers":[
        {
            "category":"Health Services",
            "subcategory":"Doctor",
            "type":"Services"
        }
    ],
    "sg:phone":"+1 606 256 5812",
    "sg:postcode":"40456",
    "sg:province":"KY",
    "sg:tags":[
        "dentist"
    ],
    "wof:name":"Family Dentistry",
    "wof:placetype":"venue"
},
  "geometry": {"coordinates":[-84.339907,37.356457],"type":"Point"}
}