{
  "type": "Feature",
  "properties": {
    "addr:full":"7015 S Jackson Hwy Horse Cave KY 42749",
    "addr:housenumber":"7015",
    "addr:postcode":"42749",
    "addr:street":"S Jackson Hwy",
    "iso:country":"US",
    "sg:address":"7015 S Jackson Hwy",
    "sg:city":"Horse Cave",
    "sg:classifiers":[
        {
            "category":"Food & Beverages",
            "subcategory":"Groceries & Convenience Stores",
            "type":"Retail Goods"
        }
    ],
    "sg:phone":"+1 270 786 1949",
    "sg:postcode":"42749",
    "sg:province":"KY",
    "sg:tags":[
        "grocer"
    ],
    "wof:name":"Wigwam General Store",
    "wof:placetype":"venue"
},
  "geometry": {"coordinates":[-85.840773,37.163113],"type":"Point"}
}