{
  "type": "Feature",
  "properties": {
    "addr:full":"101 N Columbia Ave Campbellsville KY 42718",
    "addr:housenumber":"101",
    "addr:postcode":"42718",
    "addr:street":"N Columbia Ave",
    "iso:country":"US",
    "sg:address":"101 N Columbia Ave",
    "sg:city":"Campbellsville",
    "sg:classifiers":[
        {
            "category":"Restaurant",
            "type":"Food & Drink"
        }
    ],
    "sg:phone":"+1 270 465 3870",
    "sg:postcode":"42718",
    "sg:province":"KY",
    "wof:name":"Druther's Restaurant",
    "wof:placetype":"venue"
},
  "geometry": {"coordinates":[-85.34545300000001,37.341014],"type":"Point"}
}