{
  "type": "Feature",
  "properties": {
    "iso:country":"US",
    "sg:address":"301 N Broadway St",
    "sg:city":"Providence",
    "sg:classifiers":[
        {
            "category":"Retail",
            "subcategory":"Funeral Services",
            "type":"Services"
        }
    ],
    "sg:phone":"+1 270 667 5655",
    "sg:postcode":"42450",
    "sg:province":"KY",
    "sg:tags":[
        "director"
    ],
    "wof:name":"Townsend-Jones Funeral Home",
    "wof:placetype":"venue"
},
  "geometry": {"coordinates":[-87.76391599999999,37.400411],"type":"Point"}
}