{
  "type": "Feature",
  "properties": {
    "iso:country":"US",
    "sg:address":"401 E Main St",
    "sg:city":"Wilmore",
    "sg:classifiers":[
        {
            "category":"Retail",
            "subcategory":"Auto Repair",
            "type":"Services"
        }
    ],
    "sg:phone":"+1 859 858 4917",
    "sg:postcode":"40390",
    "sg:province":"KY",
    "sg:tags":[
        "repairing",
        "automobile"
    ],
    "wof:name":"Fox Automotive & Equipment",
    "wof:placetype":"venue"
},
  "geometry": {"coordinates":[-84.658047,37.857876],"type":"Point"}
}