{
  "type": "Feature",
  "properties": {
    "iso:country":"US",
    "sg:address":"190 State Hwy 72",
    "sg:city":"Baxter",
    "sg:classifiers":[
        {
            "category":"Retail",
            "subcategory":"Auto Repair",
            "type":"Services"
        }
    ],
    "sg:phone":"+1 606 573 7766",
    "sg:postcode":"40831",
    "sg:province":"KY",
    "sg:tags":[
        "recreational",
        "vehicle"
    ],
    "wof:name":"Trail Riders Atv Parts",
    "wof:placetype":"venue"
},
  "geometry": {"coordinates":[-83.322762,36.847115],"type":"Point"}
}