{
  "type": "Feature",
  "properties": {
    "iso:country":"US",
    "sg:address":"502 Hanover Ct",
    "sg:city":"Elizabethtown",
    "sg:classifiers":[
        {
            "category":"Freight",
            "type":"Transportation"
        }
    ],
    "sg:phone":"+1 270 234 9919",
    "sg:postcode":"42701",
    "sg:province":"KY",
    "sg:tags":[
        "trucking"
    ],
    "wof:name":"Cruz Carriers Inc",
    "wof:placetype":"venue"
},
  "geometry": {"coordinates":[-85.90825100000001,37.681578],"type":"Point"}
}