{
  "type": "Feature",
  "properties": {
    "addr:full":"567 Bagdad Rd Shelbyville KY 40065",
    "addr:housenumber":"567",
    "addr:postcode":"40065",
    "addr:street":"Bagdad Rd",
    "iso:country":"US",
    "sg:address":"567 Bagdad Rd",
    "sg:city":"Shelbyville",
    "sg:phone":"+1 502 747 5106",
    "sg:postcode":"40065",
    "sg:province":"KY",
    "sg:tags":[
        "farm",
        "tobacco"
    ],
    "wof:name":"Glenn Floyd",
    "wof:placetype":"venue"
},
  "geometry": {"coordinates":[-85.134227,38.265188],"type":"Point"}
}