{
  "type": "Feature",
  "properties": {
    "addr:full":"1120 Wyanoke St Ironton OH 45638",
    "addr:housenumber":"1120",
    "addr:postcode":"45638",
    "addr:street":"Wyanoke St",
    "iso:country":"US",
    "sg:address":"1120 Wyanoke St",
    "sg:city":"Ironton",
    "sg:classifiers":[
        {
            "category":"Professional",
            "type":"Services"
        }
    ],
    "sg:phone":"+1 740 533 1445",
    "sg:postcode":"45638",
    "sg:province":"OH",
    "wof:name":"Feecorp Inc",
    "wof:placetype":"venue"
},
  "geometry": {"coordinates":[-82.656559,38.515581],"type":"Point"}
}