{
  "type": "Feature",
  "properties": {
    "iso:country":"US",
    "sg:address":"133 Highland Trce",
    "sg:city":"Highland Heights",
    "sg:classifiers":[
        {
            "category":"Real Estate",
            "subcategory":"Real Estate Operator",
            "type":"Services"
        }
    ],
    "sg:phone":"+1 859 781 4200",
    "sg:postcode":"41076",
    "sg:province":"KY",
    "sg:tags":[
        "apartment"
    ],
    "wof:name":"Hidden Valley Apartments",
    "wof:placetype":"venue"
},
  "geometry": {"coordinates":[-84.447881,39.043418],"type":"Point"}
}