{
  "type": "Feature",
  "properties": {
    "iso:country":"US",
    "sg:address":"88 Michael Blvd",
    "sg:city":"Frankfort",
    "sg:classifiers":[
        {
            "category":"Freight",
            "type":"Transportation"
        }
    ],
    "sg:phone":"+1 502 875 5625",
    "sg:postcode":"40601",
    "sg:province":"KY",
    "sg:tags":[
        "delivery"
    ],
    "wof:name":"K C Courier Svc",
    "wof:placetype":"venue"
},
  "geometry": {"coordinates":[-84.930863,38.131936],"type":"Point"}
}