{
  "type": "Feature",
  "properties": {
    "addr:full":"2805 US Hwy 60 Morehead KY 40351",
    "addr:housenumber":"2805",
    "addr:postcode":"40351",
    "addr:street":"Us Hwy 60",
    "iso:country":"US",
    "sg:address":"2805 US Hwy 60",
    "sg:city":"Morehead",
    "sg:classifiers":[
        {
            "category":"Organizations",
            "subcategory":"Religious Organization",
            "type":"Services"
        }
    ],
    "sg:phone":"+1 606 784 9982",
    "sg:postcode":"40351",
    "sg:province":"KY",
    "sg:tags":[
        "clergy"
    ],
    "wof:name":"H Michael Anderson",
    "wof:placetype":"venue"
},
  "geometry": {"coordinates":[-83.468568,38.155888],"type":"Point"}
}