{
  "type": "Feature",
  "properties": {
    "addr:full":"1079 Court St Wickliffe KY 42087",
    "addr:housenumber":"1079",
    "addr:postcode":"42087",
    "addr:street":"Court St",
    "iso:country":"US",
    "sg:address":"1079 Court St",
    "sg:city":"Wickliffe",
    "sg:classifiers":[
        {
            "category":"Retail",
            "subcategory":"Funeral Services",
            "type":"Services"
        }
    ],
    "sg:phone":"+1 270 335 3377",
    "sg:postcode":"42087",
    "sg:province":"KY",
    "sg:tags":[
        "director"
    ],
    "wof:name":"Milner & Orr Funeral Home",
    "wof:placetype":"venue"
},
  "geometry": {"coordinates":[-89.079171,36.96295],"type":"Point"}
}