{
  "type": "Feature",
  "properties": {
    "iso:country":"US",
    "sg:address":"204 Old Ford Rd",
    "sg:city":"Shepherdsville",
    "sg:classifiers":[
        {
            "category":"Building & Trades",
            "subcategory":"Plumbing",
            "type":"Services"
        }
    ],
    "sg:phone":"+1 502 543 7743",
    "sg:postcode":"40165",
    "sg:province":"KY",
    "sg:tags":[
        "septic"
    ],
    "wof:name":"Bullitt County Septic Svc",
    "wof:placetype":"venue"
},
  "geometry": {"coordinates":[-85.724433,37.980875],"type":"Point"}
}