{
  "type": "Feature",
  "properties": {
    "iso:country":"US",
    "sg:address":"4190 McCowans Ferry Rd",
    "sg:city":"Versailles",
    "sg:classifiers":[
        {
            "category":"Shopping",
            "subcategory":"Gifts & Souvenirs",
            "type":"Retail Goods"
        }
    ],
    "sg:phone":"+1 859 873 6605",
    "sg:postcode":"40383",
    "sg:province":"KY",
    "wof:name":"Squires James & Mary Anne",
    "wof:placetype":"venue"
},
  "geometry": {"coordinates":[-84.76551000000001,38.002324],"type":"Point"}
}