{
  "type": "Feature",
  "properties": {
    "iso:country":"US",
    "sg:address":"1314 Sycamore St",
    "sg:city":"Murray",
    "sg:classifiers":[
        {
            "category":"Autos & Motor Vehicles",
            "subcategory":"Automobile Sales",
            "type":"Retail Goods"
        }
    ],
    "sg:phone":"+1 270 753 4904",
    "sg:postcode":"42071",
    "sg:province":"KY",
    "sg:tags":[
        "car",
        "dealer"
    ],
    "wof:name":"Billy D Crouse Auto Brokers",
    "wof:placetype":"venue"
},
  "geometry": {"coordinates":[-88.31767000000001,36.602897],"type":"Point"}
}