{
  "type": "Feature",
  "properties": {
    "addr:full":"377 College Hill Rd Waco KY 40385",
    "addr:housenumber":"377",
    "addr:postcode":"40385",
    "addr:street":"College Hill Rd",
    "iso:country":"US",
    "sg:address":"377 College Hill Rd",
    "sg:city":"Waco",
    "sg:classifiers":[
        {
            "category":"Organizations",
            "subcategory":"Religious Organization",
            "type":"Services"
        }
    ],
    "sg:phone":"+1 859 369 5219",
    "sg:postcode":"40385",
    "sg:province":"KY",
    "sg:tags":[
        "church"
    ],
    "wof:name":"Pleasant Green Predestinarian",
    "wof:placetype":"venue"
},
  "geometry": {"coordinates":[-84.144018,37.748709],"type":"Point"}
}