{
  "type": "Feature",
  "properties": {
    "iso:country":"US",
    "sg:address":"218 Union Cir",
    "sg:city":"Mayfield",
    "sg:classifiers":[
        {
            "category":"Organizations",
            "subcategory":"Religious Organization",
            "type":"Services"
        }
    ],
    "sg:phone":"+1 270 247 7337",
    "sg:postcode":"42066",
    "sg:province":"KY",
    "wof:name":"Hickory Baptist",
    "wof:placetype":"venue"
},
  "geometry": {"coordinates":[-88.646394,36.793165],"type":"Point"}
}