{
  "type": "Feature",
  "properties": {
    "addr:full":"390 Lillies Ferry Rd Winchester KY 40391",
    "addr:housenumber":"390",
    "addr:postcode":"40391",
    "addr:street":"Lillies Ferry Rd",
    "iso:country":"US",
    "sg:address":"390 Lillies Ferry Rd",
    "sg:city":"Winchester",
    "sg:classifiers":[
        {
            "category":"Professional",
            "type":"Services"
        }
    ],
    "sg:phone":"+1 859 737 1576",
    "sg:postcode":"40391",
    "sg:province":"KY",
    "wof:name":"Lois J Hannah",
    "wof:placetype":"venue"
},
  "geometry": {"coordinates":[-84.020521,37.850868],"type":"Point"}
}