{
  "type": "Feature",
  "properties": {
    "iso:country":"US",
    "sg:address":"466 Linden Ave",
    "sg:city":"Harrodsburg",
    "sg:classifiers":[
        {
            "category":"Health Services",
            "subcategory":"Doctor",
            "type":"Services"
        }
    ],
    "sg:phone":"+1 859 734 5173",
    "sg:postcode":"40330",
    "sg:province":"KY",
    "sg:tags":[
        "physician",
        "surgeon"
    ],
    "wof:name":"Dedman Angel & Hall",
    "wof:placetype":"venue"
},
  "geometry": {"coordinates":[-84.848085,37.75711],"type":"Point"}
}