{
  "type": "Feature",
  "properties": {
    "iso:country":"US",
    "sg:address":"130 W Tiverton Way Ste 15",
    "sg:city":"Lexington",
    "sg:classifiers":[
        {
            "category":"Restaurant",
            "type":"Food & Drink"
        }
    ],
    "sg:phone":"+1 859 272 1093",
    "sg:postcode":"40503",
    "sg:province":"KY",
    "sg:tags":[
        "house",
        "steak"
    ],
    "wof:name":"Lees Garden",
    "wof:placetype":"venue"
},
  "geometry": {"coordinates":[-84.529811,37.980687],"type":"Point"}
}