{
  "type": "Feature",
  "properties": {
    "iso:country":"US",
    "sg:address":"700 W Blue Lick Rd",
    "sg:city":"Shepherdsville",
    "sg:classifiers":[
        {
            "category":"Real Estate",
            "subcategory":"Real Estate Operator",
            "type":"Services"
        }
    ],
    "sg:phone":"+1 502 955 8918",
    "sg:postcode":"40165",
    "sg:province":"KY",
    "sg:tags":[
        "mobile",
        "home",
        "community"
    ],
    "wof:name":"Shepherdsville Mobile Home Pk",
    "wof:placetype":"venue"
},
  "geometry": {"coordinates":[-85.72381799999999,38.004238],"type":"Point"}
}