{
  "type": "Feature",
  "properties": {
    "addr:full":"15000 Taylorsville Rd Fisherville KY 40023",
    "addr:housenumber":"15000",
    "addr:postcode":"40023",
    "addr:street":"Taylorsville Rd",
    "iso:country":"US",
    "sg:address":"15000 Taylorsville Rd",
    "sg:city":"Fisherville",
    "sg:classifiers":[
        {
            "category":"Government",
            "subcategory":"Fire Station",
            "type":"Public Place"
        }
    ],
    "sg:phone":"+1 502 266 6700",
    "sg:postcode":"40023",
    "sg:province":"KY",
    "sg:tags":[
        "department"
    ],
    "wof:name":"Eastwood Fire Dept",
    "wof:placetype":"venue"
},
  "geometry": {"coordinates":[-85.455421,38.18897],"type":"Point"}
}