{
  "type": "Feature",
  "properties": {
    "iso:country":"US",
    "sg:address":"3128 Ashgrove Ln",
    "sg:city":"Nicholasville",
    "sg:classifiers":[
        {
            "category":"Freight",
            "type":"Transportation"
        }
    ],
    "sg:phone":"+1 859 273 4588",
    "sg:postcode":"40356",
    "sg:province":"KY",
    "sg:tags":[
        "mobile",
        "home"
    ],
    "wof:name":"Bartlet Mobile Home Transit",
    "wof:placetype":"venue"
},
  "geometry": {"coordinates":[-84.518289,37.940947],"type":"Point"}
}