{
  "type": "Feature",
  "properties": {
    "iso:country":"US",
    "sg:address":"970 Wells Landing Rd",
    "sg:city":"Danville",
    "sg:classifiers":[
        {
            "category":"Building & Trades",
            "subcategory":"Electrical",
            "type":"Services"
        }
    ],
    "sg:phone":"+1 859 236 9427",
    "sg:postcode":"40422",
    "sg:province":"KY",
    "sg:tags":[
        "electrical",
        "contractor"
    ],
    "wof:name":"Leffew Electric",
    "wof:placetype":"venue"
},
  "geometry": {"coordinates":[-84.710697,37.676232],"type":"Point"}
}