{
  "type": "Feature",
  "properties": {
    "iso:country":"US",
    "sg:address":"4259 State Hwy 1426",
    "sg:city":"Dana",
    "sg:classifiers":[
        {
            "category":"Shopping",
            "subcategory":"Florist",
            "type":"Retail Goods"
        }
    ],
    "sg:phone":"+1 606 478 8008",
    "sg:postcode":"41603",
    "sg:province":"KY",
    "wof:name":"Maggies",
    "wof:placetype":"venue"
},
  "geometry": {"coordinates":[-82.691112,37.557177],"type":"Point"}
}