{
  "type": "Feature",
  "properties": {
    "addr:full":"445 Farmington Ave Louisville KY 40209",
    "addr:housenumber":"445",
    "addr:postcode":"40209",
    "addr:street":"Farmington Ave",
    "iso:country":"US",
    "sg:address":"445 Farmington Ave",
    "sg:city":"Louisville",
    "sg:classifiers":[
        {
            "category":"Retail",
            "subcategory":"Auto Repair",
            "type":"Services"
        }
    ],
    "sg:phone":"+1 502 962 1020",
    "sg:postcode":"40209",
    "sg:province":"KY",
    "sg:tags":[
        "wrecker"
    ],
    "wof:name":"Dave's Towing",
    "wof:placetype":"venue"
},
  "geometry": {"coordinates":[-85.754498,38.199949],"type":"Point"}
}