{
  "type": "Feature",
  "properties": {
    "iso:country":"US",
    "sg:address":"132 E Main St",
    "sg:city":"Grayson",
    "sg:classifiers":[
        {
            "category":"Shopping",
            "subcategory":"Department Store",
            "type":"Retail Goods"
        }
    ],
    "sg:phone":"+1 606 474 5341",
    "sg:postcode":"41143",
    "sg:province":"KY",
    "wof:name":"Rupert's Department Store Inc",
    "wof:placetype":"venue"
},
  "geometry": {"coordinates":[-82.947924,38.332331],"type":"Point"}
}