{
  "type": "Feature",
  "properties": {
    "addr:full":"827 Old Hartford Rd Owensboro KY 42303",
    "addr:housenumber":"827",
    "addr:postcode":"42303",
    "addr:street":"Old Hartford Rd",
    "iso:country":"US",
    "sg:address":"827 Old Hartford Rd",
    "sg:city":"Owensboro",
    "sg:classifiers":[
        {
            "category":"Organizations",
            "subcategory":"Labor Organization",
            "type":"Services"
        }
    ],
    "sg:phone":"+1 270 683 6353",
    "sg:postcode":"42303",
    "sg:province":"KY",
    "wof:name":"Laborers International Union",
    "wof:placetype":"venue"
},
  "geometry": {"coordinates":[-87.10026499999999,37.754831],"type":"Point"}
}