{
  "type": "Feature",
  "properties": {
    "iso:country":"US",
    "sg:address":"914 State St",
    "sg:city":"Bowling Green",
    "sg:classifiers":[
        {
            "category":"Real Estate",
            "subcategory":"Real Estate Agent",
            "type":"Services"
        }
    ],
    "sg:phone":"+1 270 843 4303",
    "sg:postcode":"42101",
    "sg:province":"KY",
    "wof:name":"Perkins Realty",
    "wof:placetype":"venue"
},
  "geometry": {"coordinates":[-86.440629,36.99268],"type":"Point"}
}