{
  "type": "Feature",
  "properties": {
    "iso:country":"US",
    "sg:address":"140 Old Bronston School Rd",
    "sg:city":"Bronston",
    "sg:classifiers":[
        {
            "category":"Recreation",
            "type":"Entertainment"
        }
    ],
    "sg:phone":"+1 606 561 7449",
    "sg:postcode":"42518",
    "sg:province":"KY",
    "sg:tags":[
        "center"
    ],
    "wof:name":"Cole's Shooting Sports",
    "wof:placetype":"venue"
},
  "geometry": {"coordinates":[-84.63943999999999,36.977294],"type":"Point"}
}