{
  "type": "Feature",
  "properties": {
    "addr:full":"901 Crossgate Dr Florence KY 41042",
    "addr:housenumber":"901",
    "addr:postcode":"41042",
    "addr:street":"Crossgate Dr",
    "iso:country":"US",
    "sg:address":"901 Crossgate Dr",
    "sg:city":"Florence",
    "sg:classifiers":[
        {
            "category":"Professional",
            "type":"Services"
        }
    ],
    "sg:phone":"+1 859 384 3989",
    "sg:postcode":"41042",
    "sg:province":"KY",
    "sg:tags":[
        "establishment"
    ],
    "wof:name":"Crossgate At Farmview",
    "wof:placetype":"venue"
},
  "geometry": {"coordinates":[-84.67648,38.969929],"type":"Point"}
}