{
  "type": "Feature",
  "properties": {
    "iso:country":"US",
    "sg:address":"1025 Euclid Ave",
    "sg:city":"Paintsville",
    "sg:classifiers":[
        {
            "category":"Health Services",
            "subcategory":"Nursing And Care Facility",
            "type":"Services"
        }
    ],
    "sg:phone":"+1 606 789 5808",
    "sg:postcode":"41240",
    "sg:province":"KY",
    "sg:tags":[
        "home",
        "convalescent"
    ],
    "wof:name":"Mountain Manor Of Paintsville",
    "wof:placetype":"venue"
},
  "geometry": {"coordinates":[-82.78633000000001,37.817105],"type":"Point"}
}