{
  "type": "Feature",
  "properties": {
    "iso:country":"US",
    "sg:address":"1601 S Campbell St",
    "sg:city":"Hopkinsville",
    "sg:classifiers":[
        {
            "category":"Freight",
            "type":"Transportation"
        }
    ],
    "sg:phone":"+1 270 886 8744",
    "sg:postcode":"42240",
    "sg:province":"KY",
    "sg:tags":[
        "grain",
        "elevator"
    ],
    "wof:name":"ACME Grain Elevator",
    "wof:placetype":"venue"
},
  "geometry": {"coordinates":[-87.48675900000001,36.859507],"type":"Point"}
}