{
  "type": "Feature",
  "properties": {
    "iso:country":"US",
    "sg:address":"7209 Sherbrook Ct",
    "sg:city":"Florence",
    "sg:classifiers":[
        {
            "category":"Manufacturing",
            "subcategory":"Printing",
            "type":"Manufacturing & Wholesale Goods"
        }
    ],
    "sg:phone":"+1 859 356 6588",
    "sg:postcode":"41042",
    "sg:province":"KY",
    "sg:tags":[
        "commercial"
    ],
    "wof:name":"Victory Promotions",
    "wof:placetype":"venue"
},
  "geometry": {"coordinates":[-84.681286,38.994963],"type":"Point"}
}