{
  "type": "Feature",
  "properties": {
    "iso:country":"US",
    "sg:address":"4127 Lexington Rd",
    "sg:city":"Paris",
    "sg:classifiers":[
        {
            "category":"Restaurant",
            "type":"Food & Drink"
        }
    ],
    "sg:phone":"+1 859 987 3465",
    "sg:postcode":"40361",
    "sg:province":"KY",
    "wof:name":"Jerry's Restaurant",
    "wof:placetype":"venue"
},
  "geometry": {"coordinates":[-84.285461,38.187999],"type":"Point"}
}