{
  "type": "Feature",
  "properties": {
    "iso:country":"US",
    "sg:address":"3508 Hurstborne Ridge Blvd",
    "sg:city":"Louisville",
    "sg:classifiers":[
        {
            "category":"Health Services",
            "subcategory":"Doctor",
            "type":"Services"
        }
    ],
    "sg:phone":"+1 502 499 2957",
    "sg:postcode":"40299",
    "sg:province":"KY",
    "wof:name":"Clarence George Jung",
    "wof:placetype":"venue"
},
  "geometry": {"coordinates":[-85.606194,38.195796],"type":"Point"}
}