{
  "type": "Feature",
  "properties": {
    "addr:full":"539 Summitt Rd Ashland KY 41102",
    "addr:housenumber":"539",
    "addr:postcode":"41102",
    "addr:street":"Summitt Rd",
    "iso:country":"US",
    "sg:address":"539 Summitt Rd",
    "sg:city":"Ashland",
    "sg:classifiers":[
        {
            "category":"Travel",
            "subcategory":"Hotels & Motels",
            "type":"Entertainment"
        }
    ],
    "sg:phone":"+1 606 929 9005",
    "sg:postcode":"41102",
    "sg:province":"KY",
    "wof:name":"Dean's Inn",
    "wof:placetype":"venue"
},
  "geometry": {"coordinates":[-82.703317,38.438452],"type":"Point"}
}