{
  "type": "Feature",
  "properties": {
    "iso:country":"US",
    "sg:address":"9311 Preston Hwy",
    "sg:city":"Okolona",
    "sg:classifiers":[
        {
            "category":"Professional",
            "subcategory":"Lawyer & Legal Services",
            "type":"Services"
        }
    ],
    "sg:phone":"+1 502 962 7575",
    "sg:postcode":"40229",
    "sg:province":"KY",
    "sg:tags":[
        "attorney"
    ],
    "sg:website":"www.obryanlawoffices.com",
    "wof:name":"O'Bryan Law Offices",
    "wof:placetype":"venue"
},
  "geometry": {"coordinates":[-85.676605,38.116299],"type":"Point"}
}