{
  "type": "Feature",
  "properties": {
    "addr:full":"10939 Calvary Rd Campbellsville KY 42718",
    "addr:housenumber":"10939",
    "addr:postcode":"42718",
    "addr:street":"Calvary Rd",
    "iso:country":"US",
    "sg:address":"10939 Calvary Rd",
    "sg:city":"Campbellsville",
    "sg:classifiers":[
        {
            "category":"Food & Beverages",
            "subcategory":"Liquor & Beverages",
            "type":"Retail Goods"
        }
    ],
    "sg:phone":"+1 270 692 3311",
    "sg:postcode":"42718",
    "sg:province":"KY",
    "wof:name":"Big John's Liquor",
    "wof:placetype":"venue"
},
  "geometry": {"coordinates":[-85.273939,37.435583],"type":"Point"}
}