{
  "type": "Feature",
  "properties": {
    "iso:country":"US",
    "sg:address":"11509 Commonwealth Dr",
    "sg:city":"Louisville",
    "sg:classifiers":[
        {
            "category":"Utilities",
            "subcategory":"Mobile Phone",
            "type":"Services"
        }
    ],
    "sg:phone":"+1 502 297 6200",
    "sg:postcode":"40299",
    "sg:province":"KY",
    "sg:tags":[
        "telephone",
        "cellular"
    ],
    "wof:name":"T-Mobile",
    "wof:placetype":"venue"
},
  "geometry": {"coordinates":[-85.541048,38.214372],"type":"Point"}
}