{
  "type": "Feature",
  "properties": {
    "addr:full":"905 Baxter Ave Louisville KY 40204",
    "addr:housenumber":"905",
    "addr:postcode":"40204",
    "addr:street":"Baxter Ave",
    "iso:country":"US",
    "sg:address":"905 Baxter Ave",
    "sg:city":"Louisville",
    "sg:classifiers":[
        {
            "category":"Real Estate",
            "subcategory":"Real Estate Agent",
            "type":"Services"
        }
    ],
    "sg:phone":"+1 502 479 8887",
    "sg:postcode":"40204",
    "sg:province":"KY",
    "sg:tags":[
        "management"
    ],
    "wof:name":"Romato Inc",
    "wof:placetype":"venue"
},
  "geometry": {"coordinates":[-85.72662200000001,38.243457],"type":"Point"}
}