{
  "type": "Feature",
  "properties": {
    "iso:country":"US",
    "sg:address":"1571 Frogtown Rd",
    "sg:city":"Union",
    "sg:classifiers":[
        {
            "category":"Retail",
            "subcategory":"Car Wash",
            "type":"Services"
        }
    ],
    "sg:phone":"+1 859 384 2100",
    "sg:postcode":"41091",
    "sg:province":"KY",
    "sg:tags":[
        "truck",
        "cleaning"
    ],
    "wof:name":"Kem Klean",
    "wof:placetype":"venue"
},
  "geometry": {"coordinates":[-84.664067,38.93472],"type":"Point"}
}