{
  "type": "Feature",
  "properties": {
    "iso:country":"US",
    "sg:address":"3608 Hycliffe Ave",
    "sg:city":"Louisville",
    "sg:classifiers":[
        {
            "category":"Building & Trades",
            "subcategory":"Landscaping Services",
            "type":"Services"
        }
    ],
    "sg:phone":"+1 502 895 9504",
    "sg:postcode":"40207",
    "sg:province":"KY",
    "sg:tags":[
        "landscape",
        "contractor"
    ],
    "wof:name":"Douglas Landscaping & Gdn Pnds",
    "wof:placetype":"venue"
},
  "geometry": {"coordinates":[-85.65396,38.245125],"type":"Point"}
}