{
  "type": "Feature",
  "properties": {
    "iso:country":"US",
    "sg:address":"248 Jason Dr",
    "sg:city":"Nicholasville",
    "sg:classifiers":[
        {
            "category":"Recreation",
            "subcategory":"Campground",
            "type":"Entertainment"
        }
    ],
    "sg:phone":"+1 859 885 5267",
    "sg:postcode":"40356",
    "sg:province":"KY",
    "sg:tags":[
        "recreational",
        "park",
        "vehicle"
    ],
    "wof:name":"Vernon & Debra Hutton",
    "wof:placetype":"venue"
},
  "geometry": {"coordinates":[-84.55963199999999,37.890172],"type":"Point"}
}