{
  "type": "Feature",
  "properties": {
    "iso:country":"US",
    "sg:address":"5454 New Cut Rd",
    "sg:city":"Louisville",
    "sg:classifiers":[
        {
            "category":"Professional",
            "subcategory":"Accounting & Tax Preparation",
            "type":"Services"
        }
    ],
    "sg:phone":"+1 502 367 1120",
    "sg:postcode":"40214",
    "sg:province":"KY",
    "sg:tags":[
        "accountant"
    ],
    "wof:name":"William E Armistead CPA",
    "wof:placetype":"venue"
},
  "geometry": {"coordinates":[-85.775915,38.148339],"type":"Point"}
}