{
  "type": "Feature",
  "properties": {
    "iso:country":"US",
    "sg:address":"4600 Shelbyville Rd",
    "sg:city":"Louisville",
    "sg:classifiers":[
        {
            "category":"Food & Beverages",
            "subcategory":"Groceries & Convenience Stores",
            "type":"Retail Goods"
        }
    ],
    "sg:phone":"+1 502 891 0066",
    "sg:postcode":"40207",
    "sg:province":"KY",
    "sg:tags":[
        "market"
    ],
    "wof:name":"World Market Stores",
    "wof:placetype":"venue"
},
  "geometry": {"coordinates":[-85.628187,38.250686],"type":"Point"}
}