{
  "type": "Feature",
  "properties": {
    "addr:full":"592 Emma Rd Prestonsburg KY 41653",
    "addr:housenumber":"592",
    "addr:postcode":"41653",
    "addr:street":"Emma Rd",
    "iso:country":"US",
    "sg:address":"592 Emma Rd",
    "sg:city":"Prestonsburg",
    "sg:classifiers":[
        {
            "category":"Building & Trades",
            "subcategory":"Construction",
            "type":"Services"
        }
    ],
    "sg:phone":"+1 606 874 4307",
    "sg:postcode":"41653",
    "sg:province":"KY",
    "wof:name":"Allen Tire Muffler & Portable",
    "wof:placetype":"venue"
},
  "geometry": {"coordinates":[-82.699983,37.641302],"type":"Point"}
}