{
  "type": "Feature",
  "properties": {
    "iso:country":"US",
    "sg:address":"600 Jefferies Ln",
    "sg:city":"Hustonville",
    "sg:classifiers":[
        {
            "category":"Wholesale",
            "subcategory":"Auto Parts",
            "type":"Manufacturing & Wholesale Goods"
        }
    ],
    "sg:phone":"+1 606 346 2898",
    "sg:postcode":"40437",
    "sg:province":"KY",
    "sg:tags":[
        "automobile",
        "rebuilt"
    ],
    "wof:name":"Witte Auto Crushing",
    "wof:placetype":"venue"
},
  "geometry": {"coordinates":[-84.803963,37.50242],"type":"Point"}
}