{
  "type": "Feature",
  "properties": {
    "addr:full":"530 S Jackson St Louisville KY 40202",
    "addr:housenumber":"530",
    "addr:postcode":"40202",
    "addr:street":"S Jackson St",
    "iso:country":"US",
    "sg:address":"530 S Jackson St",
    "sg:city":"Louisville",
    "sg:classifiers":[
        {
            "category":"Health Services",
            "subcategory":"Hospital",
            "type":"Services"
        },
        {
            "category":"Health Services",
            "subcategory":"Doctor",
            "type":"Services"
        }
    ],
    "sg:phone":"+1 502 562 3000",
    "sg:postcode":"40202",
    "sg:province":"KY",
    "sg:tags":[
        "physician",
        "surgeon"
    ],
    "wof:name":"University Of Louisville Hosp",
    "wof:placetype":"venue"
},
  "geometry": {"coordinates":[-85.745231,38.247712],"type":"Point"}
}