{
  "type": "Feature",
  "properties": {
    "iso:country":"US",
    "sg:address":"444 Sparrow Ln",
    "sg:city":"Eminence",
    "sg:classifiers":[
        {
            "category":"Retail",
            "subcategory":"Auto Repair",
            "type":"Services"
        }
    ],
    "sg:phone":"+1 502 845 5467",
    "sg:postcode":"40019",
    "sg:province":"KY",
    "sg:tags":[
        "wrecker"
    ],
    "wof:name":"Godbey's Wrecker Svc",
    "wof:placetype":"venue"
},
  "geometry": {"coordinates":[-85.17284600000001,38.380012],"type":"Point"}
}