{
  "type": "Feature",
  "properties": {
    "addr:full":"801 Tennessee Rd Albany KY 42602",
    "addr:housenumber":"801",
    "addr:postcode":"42602",
    "addr:street":"Tennessee Rd",
    "iso:country":"US",
    "sg:address":"801 Tennessee Rd",
    "sg:city":"Albany",
    "sg:classifiers":[
        {
            "category":"Government",
            "subcategory":"Office",
            "type":"Public Place"
        }
    ],
    "sg:phone":"+1 606 387 6655",
    "sg:postcode":"42602",
    "sg:province":"KY",
    "wof:name":"Community Based Services",
    "wof:placetype":"venue"
},
  "geometry": {"coordinates":[-85.127315,36.682897],"type":"Point"}
}