{
  "type": "Feature",
  "properties": {
    "iso:country":"US",
    "sg:address":"5521 Halstead Ave",
    "sg:city":"Louisville",
    "sg:classifiers":[
        {
            "category":"Building & Trades",
            "subcategory":"Pest Control",
            "type":"Services"
        }
    ],
    "sg:phone":"+1 502 968 3947",
    "sg:postcode":"40213",
    "sg:province":"KY",
    "sg:tags":[
        "repellent",
        "bird",
        "barrier"
    ],
    "wof:name":"River City Termite & Pest",
    "wof:placetype":"venue"
},
  "geometry": {"coordinates":[-85.71109,38.167085],"type":"Point"}
}