{
  "type": "Feature",
  "properties": {
    "iso:country":"US",
    "sg:address":"904 Fleming Rd",
    "sg:city":"Maysville",
    "sg:classifiers":[
        {
            "category":"Manufacturing",
            "subcategory":"Metals",
            "type":"Manufacturing & Wholesale Goods"
        }
    ],
    "sg:phone":"+1 606 564 3746",
    "sg:postcode":"41056",
    "sg:province":"KY",
    "sg:tags":[
        "plating"
    ],
    "wof:name":"Custom Chrome & Plating",
    "wof:placetype":"venue"
},
  "geometry": {"coordinates":[-83.751903,38.632861],"type":"Point"}
}