{
  "type": "Feature",
  "properties": {
    "addr:full":"701 N Columbia Ave Campbellsville KY 42718",
    "addr:housenumber":"701",
    "addr:postcode":"42718",
    "addr:street":"N Columbia Ave",
    "iso:country":"US",
    "sg:address":"701 N Columbia Ave",
    "sg:city":"Campbellsville",
    "sg:classifiers":[
        {
            "category":"Shopping",
            "type":"Retail Goods"
        }
    ],
    "sg:phone":"+1 270 465 2072",
    "sg:postcode":"42718",
    "sg:province":"KY",
    "sg:tags":[
        "merchandise"
    ],
    "wof:name":"Hh Enterprises",
    "wof:placetype":"venue"
},
  "geometry": {"coordinates":[-85.35103599999999,37.348305],"type":"Point"}
}