{
  "type": "Feature",
  "properties": {
    "iso:country":"US",
    "sg:address":"651 S 4th St",
    "sg:city":"Louisville",
    "sg:classifiers":[
        {
            "category":"Professional",
            "subcategory":"Lawyer & Legal Services",
            "type":"Services"
        }
    ],
    "sg:phone":"+1 502 562 0020",
    "sg:postcode":"40202",
    "sg:province":"KY",
    "sg:tags":[
        "information",
        "attorney",
        "accident",
        "referral",
        "practice",
        "damage",
        "plan",
        "property"
    ],
    "wof:name":"Haner Law Office",
    "wof:placetype":"venue"
},
  "geometry": {"coordinates":[-85.75814800000001,38.24712],"type":"Point"}
}