{
  "type": "Feature",
  "properties": {
    "addr:full":"9560 US Hwy 62 Horse Branch KY 42349",
    "addr:housenumber":"9560",
    "addr:postcode":"42349",
    "addr:street":"Us Hwy 62 Horse Branch",
    "iso:country":"US",
    "sg:address":"9560 US Hwy 62",
    "sg:city":"Horse Branch",
    "sg:classifiers":[
        {
            "category":"Professional",
            "type":"Services"
        }
    ],
    "sg:phone":"+1 270 274 7357",
    "sg:postcode":"42349",
    "sg:province":"KY",
    "wof:name":"Final Touch",
    "wof:placetype":"venue"
},
  "geometry": {"coordinates":[-86.72,37.457712],"type":"Point"}
}