{
  "type": "Feature",
  "properties": {
    "addr:full":"1170 E Broadway Louisville KY 40204",
    "addr:housenumber":"1170",
    "addr:postcode":"40204",
    "addr:street":"E Broadway",
    "iso:country":"US",
    "sg:address":"1170 E Broadway",
    "sg:city":"Louisville",
    "sg:classifiers":[
        {
            "category":"Shopping",
            "subcategory":"Pharmacy",
            "type":"Retail Goods"
        }
    ],
    "sg:phone":"+1 502 589 1828",
    "sg:postcode":"40204",
    "sg:province":"KY",
    "wof:name":"East Broadway Pharmacy",
    "wof:placetype":"venue"
},
  "geometry": {"coordinates":[-85.732124,38.244099],"type":"Point"}
}