{
  "type": "Feature",
  "properties": {
    "iso:country":"US",
    "sg:address":"130 Courchelle Dr",
    "sg:city":"Nicholasville",
    "sg:classifiers":[
        {
            "category":"Organizations",
            "subcategory":"Religious Organization",
            "type":"Services"
        }
    ],
    "sg:phone":"+1 859 887 8757",
    "sg:postcode":"40356",
    "sg:province":"KY",
    "sg:tags":[
        "church"
    ],
    "wof:name":"Jessamine Christian Church",
    "wof:placetype":"venue"
},
  "geometry": {"coordinates":[-84.59603199999999,37.884964],"type":"Point"}
}