{
  "type": "Feature",
  "properties": {
    "addr:full":"561 Rockfield Browning Rd Rockfield KY 42274",
    "addr:housenumber":"561",
    "addr:postcode":"42274",
    "addr:street":"Rockfield Browning Rd",
    "iso:country":"US",
    "sg:address":"561 Rockfield Browning Rd",
    "sg:city":"Rockfield",
    "sg:classifiers":[
        {
            "category":"Building & Trades",
            "subcategory":"Landscaping Services",
            "type":"Services"
        }
    ],
    "sg:phone":"+1 270 781 8932",
    "sg:postcode":"42274",
    "sg:province":"KY",
    "sg:tags":[
        "lawn",
        "maintenance"
    ],
    "wof:name":"Linhardt Lawn Care",
    "wof:placetype":"venue"
},
  "geometry": {"coordinates":[-86.57240400000001,36.922846],"type":"Point"}
}