{
  "type": "Feature",
  "properties": {
    "addr:full":"1612 Greenup Ave Ashland KY 41101",
    "addr:housenumber":"1612",
    "addr:postcode":"41101",
    "addr:street":"Greenup Ave",
    "iso:country":"US",
    "sg:address":"1612 Greenup Ave",
    "sg:city":"Ashland",
    "sg:classifiers":[
        {
            "category":"Coffee & Tea",
            "type":"Food & Drink"
        }
    ],
    "sg:menulink":"http://www.allmenus.com/ky/ashland/222768-boston-beanery/menu/",
    "sg:phone":"+1 606 329 1870",
    "sg:postcode":"41101",
    "sg:province":"KY",
    "sg:tags":[
        "american"
    ],
    "wof:name":"Boston Beanery",
    "wof:placetype":"venue"
},
  "geometry": {"coordinates":[-82.638589,38.479516],"type":"Point"}
}