{
  "type": "Feature",
  "properties": {
    "addr:full":"1150 Hughes Ln Lexington KY 40511",
    "addr:housenumber":"1150",
    "addr:postcode":"40511",
    "addr:street":"Hughes Ln",
    "iso:country":"US",
    "sg:address":"1150 Hughes Ln",
    "sg:city":"Lexington",
    "sg:classifiers":[
        {
            "category":"Farming",
            "subcategory":"Farm",
            "type":"Manufacturing & Wholesale Goods"
        }
    ],
    "sg:phone":"+1 859 299 7500",
    "sg:postcode":"40511",
    "sg:province":"KY",
    "wof:name":"Tomoka Hills Farms-Kentucky",
    "wof:placetype":"venue"
},
  "geometry": {"coordinates":[-84.40398,38.135743],"type":"Point"}
}