{
  "type": "Feature",
  "properties": {
    "iso:country":"US",
    "sg:address":"68 S Main St",
    "sg:city":"Walton",
    "sg:classifiers":[
        {
            "category":"Organizations",
            "subcategory":"Religious Organization",
            "type":"Services"
        }
    ],
    "sg:phone":"+1 859 485 4200",
    "sg:postcode":"41094",
    "sg:province":"KY",
    "sg:tags":[
        "church"
    ],
    "wof:name":"Walton United Methodist Church",
    "wof:placetype":"venue"
},
  "geometry": {"coordinates":[-84.61027199999999,38.861363],"type":"Point"}
}