{
  "type": "Feature",
  "properties": {
    "iso:country":"US",
    "sg:address":"233 Woodland St",
    "sg:city":"Burkesville",
    "sg:classifiers":[
        {
            "category":"Building & Trades",
            "subcategory":"Construction",
            "type":"Services"
        }
    ],
    "sg:phone":"+1 270 433 5552",
    "sg:postcode":"42717",
    "sg:province":"KY",
    "sg:tags":[
        "excavating",
        "contractor"
    ],
    "wof:name":"Ernest Anderson Bulldozer Svc",
    "wof:placetype":"venue"
},
  "geometry": {"coordinates":[-85.36554,36.799158],"type":"Point"}
}