{
  "type": "Feature",
  "properties": {
    "iso:country":"US",
    "sg:address":"1224 Stringtown Rd",
    "sg:city":"Bloomfield",
    "sg:classifiers":[
        {
            "category":"Freight",
            "type":"Transportation"
        }
    ],
    "sg:phone":"+1 502 249 1088",
    "sg:postcode":"40008",
    "sg:province":"KY",
    "sg:tags":[
        "hauling",
        "trucking"
    ],
    "wof:name":"Rountree Services",
    "wof:placetype":"venue"
},
  "geometry": {"coordinates":[-85.355676,37.836782],"type":"Point"}
}