{
  "type": "Feature",
  "properties": {
    "iso:country":"US",
    "sg:address":"835 Blair Rd",
    "sg:city":"Brandenburg",
    "sg:classifiers":[
        {
            "category":"Building & Trades",
            "subcategory":"Construction",
            "type":"Services"
        }
    ],
    "sg:phone":"+1 270 422 3001",
    "sg:postcode":"40108",
    "sg:province":"KY",
    "sg:tags":[
        "general",
        "contractor"
    ],
    "wof:name":"M B Construction",
    "wof:placetype":"venue"
},
  "geometry": {"coordinates":[-86.226907,37.982883],"type":"Point"}
}