{
  "type": "Feature",
  "properties": {
    "addr:full":"214 S Broadway St Providence KY 42450",
    "addr:housenumber":"214",
    "addr:postcode":"42450",
    "addr:street":"S Broadway St",
    "iso:country":"US",
    "sg:address":"214 S Broadway St",
    "sg:city":"Providence",
    "sg:classifiers":[
        {
            "category":"Organizations",
            "subcategory":"Religious Organization",
            "type":"Services"
        }
    ],
    "sg:phone":"+1 270 667 2212",
    "sg:postcode":"42450",
    "sg:province":"KY",
    "sg:tags":[
        "church"
    ],
    "wof:name":"First Baptist Church",
    "wof:placetype":"venue"
},
  "geometry": {"coordinates":[-87.762021,37.395869],"type":"Point"}
}