{
  "type": "Feature",
  "properties": {
    "iso:country":"US",
    "sg:address":"2309 Nicholasville Rd",
    "sg:city":"Lexington",
    "sg:classifiers":[
        {
            "category":"Shopping",
            "subcategory":"Hobbies, Toys, & Games",
            "type":"Retail Goods"
        }
    ],
    "sg:phone":"+1 859 277 1022",
    "sg:postcode":"40503",
    "sg:province":"KY",
    "sg:tags":[
        "craft",
        "supply"
    ],
    "wof:name":"Michaels Arts & Crafts Store",
    "wof:placetype":"venue"
},
  "geometry": {"coordinates":[-84.519492,38.003668],"type":"Point"}
}