{
  "type": "Feature",
  "properties": {
    "iso:country":"US",
    "sg:address":"W Jefferson St",
    "sg:city":"Louisville",
    "sg:classifiers":[
        {
            "category":"Shopping",
            "subcategory":"Clothing, Apparel, & Fashions",
            "type":"Retail Goods"
        },
        {
            "category":"Shopping",
            "subcategory":"Baby Store",
            "type":"Retail Goods"
        }
    ],
    "sg:phone":"+1 502 964 5889",
    "sg:postcode":"40202",
    "sg:province":"KY",
    "sg:tags":[
        "infant",
        "men's",
        "women's",
        "children's",
        "maternity",
        "wear",
        "apparel",
        "girls'",
        "clothing",
        "boys'",
        "clothes"
    ],
    "sg:website":"http://www.oldnavy.com",
    "wof:name":"Old Navy",
    "wof:placetype":"venue"
},
  "geometry": {"coordinates":[-85.76512099999999,38.254696],"type":"Point"}
}