{
  "type": "Feature",
  "properties": {
    "addr:full":"12663 Fruithill Red Bridge Rd Crofton KY 42240",
    "addr:housenumber":"12663",
    "addr:postcode":"42240",
    "addr:street":"Fruithill Red Bridge Rd",
    "iso:country":"US",
    "sg:address":"12663 Fruithill Red Bridge Rd",
    "sg:city":"Crofton",
    "sg:phone":"+1 270 269 0629",
    "sg:postcode":"42240",
    "sg:province":"KY",
    "sg:tags":[
        "oil"
    ],
    "wof:name":"Durbin Petroleum Maintenance",
    "wof:placetype":"venue"
},
  "geometry": {"coordinates":[-87.357659,37.01393],"type":"Point"}
}