{
  "type": "Feature",
  "properties": {
    "iso:country":"US",
    "sg:address":"511 S 5th St",
    "sg:city":"Louisville",
    "sg:classifiers":[
        {
            "category":"Social Services",
            "type":"Services"
        }
    ],
    "sg:phone":"+1 502 459 5004",
    "sg:postcode":"40202",
    "sg:province":"KY",
    "sg:tags":[
        "organization",
        "welfare"
    ],
    "wof:name":"Kay's Family Resources",
    "wof:placetype":"venue"
},
  "geometry": {"coordinates":[-85.759413,38.249341],"type":"Point"}
}