{
  "type": "Feature",
  "properties": {
    "iso:country":"US",
    "sg:address":"65 Barbara Lynn Dr",
    "sg:city":"Owingsville",
    "sg:classifiers":[
        {
            "category":"Organizations",
            "subcategory":"Religious Organization",
            "type":"Services"
        }
    ],
    "sg:phone":"+1 606 674 9370",
    "sg:postcode":"40360",
    "sg:province":"KY",
    "sg:tags":[
        "clergy"
    ],
    "wof:name":"Raymond A Manley",
    "wof:placetype":"venue"
},
  "geometry": {"coordinates":[-83.761645,38.145213],"type":"Point"}
}