{
  "type": "Feature",
  "properties": {
    "iso:country":"US",
    "sg:address":"760 Interstate Dr",
    "sg:city":"Bowling Green",
    "sg:classifiers":[
        {
            "category":"Travel",
            "subcategory":"Hotels & Motels",
            "type":"Entertainment"
        }
    ],
    "sg:phone":"+1 270 781 6181",
    "sg:postcode":"42101",
    "sg:province":"KY",
    "sg:tags":[
        "operation"
    ],
    "wof:name":"Value Lodge",
    "wof:placetype":"venue"
},
  "geometry": {"coordinates":[-86.37287000000001,37.007931],"type":"Point"}
}