{
  "type": "Feature",
  "properties": {
    "iso:country":"US",
    "sg:address":"104 W Court St",
    "sg:city":"Greensburg",
    "sg:classifiers":[
        {
            "category":"Real Estate",
            "subcategory":"Real Estate Agent",
            "type":"Services"
        }
    ],
    "sg:phone":"+1 270 932 4249",
    "sg:postcode":"42743",
    "sg:province":"KY",
    "sg:tags":[
        "management"
    ],
    "wof:name":"Jim Durham",
    "wof:placetype":"venue"
},
  "geometry": {"coordinates":[-85.50308099999999,37.261179],"type":"Point"}
}