{
  "type": "Feature",
  "properties": {
    "iso:country":"US",
    "sg:address":"222 S Mayo Trl",
    "sg:city":"Pikeville",
    "sg:classifiers":[
        {
            "category":"Insurance",
            "subcategory":"Hazard Insurance",
            "type":"Services"
        }
    ],
    "sg:phone":"+1 606 432 2114",
    "sg:postcode":"41501",
    "sg:province":"KY",
    "sg:website":"http://www.orinsco.com",
    "wof:name":"Old Republic Insurance Co",
    "wof:placetype":"venue"
},
  "geometry": {"coordinates":[-82.53389300000001,37.470466],"type":"Point"}
}