{
  "type": "Feature",
  "properties": {
    "iso:country":"US",
    "sg:address":"1300 Park Ave",
    "sg:city":"Paducah",
    "sg:classifiers":[
        {
            "category":"Shopping",
            "subcategory":"Gifts & Souvenirs",
            "type":"Retail Goods"
        }
    ],
    "sg:phone":"+1 270 442 2221",
    "sg:postcode":"42001",
    "sg:province":"KY",
    "sg:tags":[
        "shop"
    ],
    "wof:name":"Alkebu Lan Gifts",
    "wof:placetype":"venue"
},
  "geometry": {"coordinates":[-88.615133,37.087447],"type":"Point"}
}