{
  "type": "Feature",
  "properties": {
    "iso:country":"US",
    "sg:address":"804 N Dixie Ave",
    "sg:city":"Elizabethtown",
    "sg:classifiers":[
        {
            "category":"Shopping",
            "subcategory":"Pets & Pet Supplies",
            "type":"Retail Goods"
        },
        {
            "category":"Retail",
            "subcategory":"Veterinary Services",
            "type":"Services"
        },
        {
            "category":"Retail",
            "subcategory":"Animal Services",
            "type":"Services"
        }
    ],
    "sg:phone":"+1 270 737 1818",
    "sg:postcode":"42701",
    "sg:province":"KY",
    "sg:tags":[
        "grooming",
        "cat",
        "veterinarian",
        "specialty",
        "dog"
    ],
    "sg:website":"http://www.helmwoodvet.com",
    "wof:name":"Northharden Vet Clinic",
    "wof:placetype":"venue"
},
  "geometry": {"coordinates":[-85.873428,37.707812],"type":"Point"}
}