{
  "type": "Feature",
  "properties": {
    "iso:country":"US",
    "sg:address":"508 Frames Branch Rd",
    "sg:city":"Clay City",
    "sg:classifiers":[
        {
            "category":"Retail",
            "subcategory":"Auto Repair",
            "type":"Services"
        }
    ],
    "sg:phone":"+1 606 663 2547",
    "sg:postcode":"40312",
    "sg:province":"KY",
    "sg:tags":[
        "body",
        "automobile",
        "painting"
    ],
    "wof:name":"Patrick's Collision",
    "wof:placetype":"venue"
},
  "geometry": {"coordinates":[-83.925619,37.810825],"type":"Point"}
}