{
  "type": "Feature",
  "properties": {
    "iso:country":"US",
    "sg:address":"353 Kona Dr",
    "sg:city":"Whitesburg",
    "sg:classifiers":[
        {
            "category":"Shopping",
            "type":"Retail Goods"
        }
    ],
    "sg:phone":"+1 606 855 4384",
    "sg:postcode":"41858",
    "sg:province":"KY",
    "sg:tags":[
        "monument"
    ],
    "wof:name":"Potter Monument",
    "wof:placetype":"venue"
},
  "geometry": {"coordinates":[-82.735564,37.16049],"type":"Point"}
}