{
  "type": "Feature",
  "properties": {
    "addr:full":"361 Taylor Ave Bellevue KY 41073",
    "addr:housenumber":"361",
    "addr:postcode":"41073",
    "addr:street":"Taylor Ave",
    "iso:country":"US",
    "sg:address":"361 Taylor Ave",
    "sg:city":"Bellevue",
    "sg:classifiers":[
        {
            "category":"Government",
            "subcategory":"Post Office",
            "type":"Public Place"
        }
    ],
    "sg:phone":"+1 859 261 2358",
    "sg:postcode":"41073",
    "sg:province":"KY",
    "sg:tags":[
        "postal",
        "us"
    ],
    "wof:name":"US Post Office",
    "wof:placetype":"venue"
},
  "geometry": {"coordinates":[-84.48074800000001,39.102906],"type":"Point"}
}