{
  "type": "Feature",
  "properties": {
    "iso:country":"US",
    "sg:address":"516 Ogden St",
    "sg:city":"Somerset",
    "sg:classifiers":[
        {
            "category":"Autos & Motor Vehicles",
            "subcategory":"Auto Supplies",
            "type":"Retail Goods"
        }
    ],
    "sg:phone":"+1 606 678 8106",
    "sg:postcode":"42501",
    "sg:province":"KY",
    "sg:tags":[
        "automobile",
        "parts"
    ],
    "wof:name":"Somerset Automotive Inc",
    "wof:placetype":"venue"
},
  "geometry": {"coordinates":[-84.615565,37.096604],"type":"Point"}
}