{
  "type": "Feature",
  "properties": {
    "iso:country":"US",
    "sg:address":"110 Gettysburg Square Rd",
    "sg:city":"Fort Thomas",
    "sg:classifiers":[
        {
            "category":"Real Estate",
            "subcategory":"Real Estate Operator",
            "type":"Services"
        }
    ],
    "sg:phone":"+1 859 442 0131",
    "sg:postcode":"41075",
    "sg:province":"KY",
    "sg:tags":[
        "apartment"
    ],
    "wof:name":"Gettysburg Square Apts",
    "wof:placetype":"venue"
},
  "geometry": {"coordinates":[-84.46643,39.082717],"type":"Point"}
}