{
  "type": "Feature",
  "properties": {
    "iso:country":"US",
    "sg:address":"108 Hayden Dr",
    "sg:city":"Eddyville",
    "sg:classifiers":[
        {
            "category":"Real Estate",
            "subcategory":"Real Estate Agent",
            "type":"Services"
        }
    ],
    "sg:phone":"+1 270 388 0166",
    "sg:postcode":"42038",
    "sg:province":"KY",
    "wof:name":"Advantage Real Estate Co",
    "wof:placetype":"venue"
},
  "geometry": {"coordinates":[-88.06850900000001,37.098789],"type":"Point"}
}