{
  "type": "Feature",
  "properties": {
    "iso:country":"US",
    "sg:address":"2255 Beargrass Ave",
    "sg:city":"Louisville",
    "sg:classifiers":[
        {
            "category":"Personal",
            "subcategory":"Massage",
            "type":"Services"
        }
    ],
    "sg:phone":"+1 502 499 0360",
    "sg:postcode":"40218",
    "sg:province":"KY",
    "wof:name":"Julies Masseusse",
    "wof:placetype":"venue"
},
  "geometry": {"coordinates":[-85.639652,38.191414],"type":"Point"}
}