{
  "type": "Feature",
  "properties": {
    "iso:country":"US",
    "sg:address":"626 Greene Dr",
    "sg:city":"Greenville",
    "sg:classifiers":[
        {
            "category":"Home & Garden",
            "subcategory":"Garden Supply",
            "type":"Retail Goods"
        }
    ],
    "sg:phone":"+1 270 338 4326",
    "sg:postcode":"42345",
    "sg:province":"KY",
    "sg:tags":[
        "lawn"
    ],
    "wof:name":"Four Seasons Outdoor Power",
    "wof:placetype":"venue"
},
  "geometry": {"coordinates":[-87.17920100000001,37.216696],"type":"Point"}
}