{
  "type": "Feature",
  "properties": {
    "addr:full":"7292 Manslick Rd Louisville KY 40214",
    "addr:housenumber":"7292",
    "addr:postcode":"40214",
    "addr:street":"Manslick Rd",
    "iso:country":"US",
    "sg:address":"7292 Manslick Rd",
    "sg:city":"Louisville",
    "sg:classifiers":[
        {
            "category":"Shopping",
            "type":"Retail Goods"
        }
    ],
    "sg:phone":"+1 502 367 2333",
    "sg:postcode":"40214",
    "sg:province":"KY",
    "sg:tags":[
        "picture",
        "frame"
    ],
    "wof:name":"Frames N More",
    "wof:placetype":"venue"
},
  "geometry": {"coordinates":[-85.80194299999999,38.155398],"type":"Point"}
}