{
  "type": "Feature",
  "properties": {
    "iso:country":"US",
    "sg:address":"11728 US Hwy 68 E",
    "sg:city":"Benton",
    "sg:classifiers":[
        {
            "category":"Restaurant",
            "type":"Food & Drink"
        }
    ],
    "sg:phone":"+1 270 354 8116",
    "sg:postcode":"42025",
    "sg:province":"KY",
    "wof:name":"Marquita's Place",
    "wof:placetype":"venue"
},
  "geometry": {"coordinates":[-88.20039199999999,36.813602],"type":"Point"}
}