{
  "type": "Feature",
  "properties": {
    "iso:country":"US",
    "sg:address":"6510 Glenridge Park Pl",
    "sg:city":"Louisville",
    "sg:classifiers":[
        {
            "category":"Health Services",
            "subcategory":"Doctor",
            "type":"Services"
        }
    ],
    "sg:phone":"+1 502 425 8866",
    "sg:postcode":"40222",
    "sg:province":"KY",
    "sg:tags":[
        "physician",
        "surgeon"
    ],
    "wof:name":"Elaine Stauble MD",
    "wof:placetype":"venue"
},
  "geometry": {"coordinates":[-85.63055799999999,38.285093],"type":"Point"}
}