{
  "type": "Feature",
  "properties": {
    "addr:full":"7505 Sussex Dr Florence KY 41042",
    "addr:housenumber":"7505",
    "addr:postcode":"41042",
    "addr:street":"Sussex Dr",
    "iso:country":"US",
    "sg:address":"7505 Sussex Dr",
    "sg:city":"Florence",
    "sg:classifiers":[
        {
            "category":"Professional",
            "subcategory":"Management & Consulting",
            "type":"Services"
        }
    ],
    "sg:phone":"+1 859 371 4999",
    "sg:postcode":"41042",
    "sg:province":"KY",
    "sg:tags":[
        "personnel",
        "consultant"
    ],
    "sg:website":"www.jmsnursingpool.com",
    "wof:name":"JMS",
    "wof:placetype":"venue"
},
  "geometry": {"coordinates":[-84.63414899999999,38.984971],"type":"Point"}
}