{
  "type": "Feature",
  "properties": {
    "iso:country":"US",
    "sg:address":"908 W Broadway",
    "sg:city":"Louisville",
    "sg:classifiers":[
        {
            "category":"Government",
            "subcategory":"Office",
            "type":"Public Place"
        }
    ],
    "sg:phone":"+1 502 595 4803",
    "sg:postcode":"40203",
    "sg:province":"KY",
    "sg:tags":[
        "state",
        "resource"
    ],
    "wof:name":"Social Service Dept Adult",
    "wof:placetype":"venue"
},
  "geometry": {"coordinates":[-85.76818799999999,38.247015],"type":"Point"}
}