{
  "type": "Feature",
  "properties": {
    "iso:country":"US",
    "sg:address":"10 Harris Ridge Rd",
    "sg:city":"Owenton",
    "sg:classifiers":[
        {
            "category":"Government",
            "subcategory":"Office",
            "type":"Public Place"
        }
    ],
    "sg:phone":"+1 502 484 2227",
    "sg:postcode":"40359",
    "sg:province":"KY",
    "sg:website":"www.kentucky.com",
    "wof:name":"Maintenance Barn",
    "wof:placetype":"venue"
},
  "geometry": {"coordinates":[-84.80674399999999,38.559845],"type":"Point"}
}