{
  "type": "Feature",
  "properties": {
    "addr:full":"104 S Main St Edmonton KY 42129",
    "addr:housenumber":"104",
    "addr:postcode":"42129",
    "addr:street":"S Main St",
    "iso:country":"US",
    "sg:address":"104 S Main St",
    "sg:city":"Edmonton",
    "sg:classifiers":[
        {
            "category":"Shopping",
            "subcategory":"Computers & Home Electronics",
            "type":"Retail Goods"
        }
    ],
    "sg:phone":"+1 270 432 5860",
    "sg:postcode":"42129",
    "sg:province":"KY",
    "sg:tags":[
        "television",
        "radio"
    ],
    "wof:name":"Hammer's TV Svc",
    "wof:placetype":"venue"
},
  "geometry": {"coordinates":[-85.61186600000001,36.978436],"type":"Point"}
}