{
  "type": "Feature",
  "properties": {
    "iso:country":"US",
    "sg:address":"3337 Brighton Place Dr",
    "sg:city":"Lexington",
    "sg:classifiers":[
        {
            "category":"Real Estate",
            "subcategory":"Architect",
            "type":"Services"
        }
    ],
    "sg:phone":"+1 859 263 9901",
    "sg:postcode":"40509",
    "sg:province":"KY",
    "sg:tags":[
        "architectural"
    ],
    "wof:name":"Golf Greens Fore U KY LLC",
    "wof:placetype":"venue"
},
  "geometry": {"coordinates":[-84.40994600000001,38.010365],"type":"Point"}
}