{
  "type": "Feature",
  "properties": {
    "addr:full":"1530 Mc Johnson Ave Owensboro KY 42303",
    "addr:housenumber":"1530",
    "addr:postcode":"42303",
    "addr:street":"Mc Johnson Ave",
    "iso:country":"US",
    "sg:address":"1530 Mc Johnson Ave",
    "sg:city":"Owensboro",
    "sg:classifiers":[
        {
            "category":"Recreation",
            "type":"Entertainment"
        }
    ],
    "sg:phone":"+1 270 687 8700",
    "sg:postcode":"42303",
    "sg:province":"KY",
    "sg:tags":[
        "parks"
    ],
    "sg:website":"www.owensboroparks.org",
    "wof:name":"Owensboro Parks & Recreation",
    "wof:placetype":"venue"
},
  "geometry": {"coordinates":[-87.093915,37.765972],"type":"Point"}
}