{
  "type": "Feature",
  "properties": {
    "iso:country":"US",
    "sg:address":"5555 Louisville Rd",
    "sg:city":"Bardstown",
    "sg:classifiers":[
        {
            "category":"Utilities",
            "subcategory":"Water",
            "type":"Services"
        }
    ],
    "sg:phone":"+1 502 348 8342",
    "sg:postcode":"40013",
    "sg:province":"KY",
    "sg:tags":[
        "company",
        "sewage"
    ],
    "wof:name":"North Nelson Water District",
    "wof:placetype":"venue"
},
  "geometry": {"coordinates":[-85.46805999999999,37.876318],"type":"Point"}
}