{
  "type": "Feature",
  "properties": {
    "addr:full":"309 W Mount Vernon St Somerset KY 42501",
    "addr:housenumber":"309",
    "addr:postcode":"42501",
    "addr:street":"W Mount Vernon St",
    "iso:country":"US",
    "sg:address":"309 W Mount Vernon St",
    "sg:city":"Somerset",
    "sg:classifiers":[
        {
            "category":"Cinema",
            "subcategory":"Movie Rental",
            "type":"Entertainment"
        }
    ],
    "sg:phone":"+1 606 679 3323",
    "sg:postcode":"42501",
    "sg:province":"KY",
    "sg:tags":[
        "leasing",
        "video",
        "disc",
        "tape"
    ],
    "wof:name":"Video Palace",
    "wof:placetype":"venue"
},
  "geometry": {"coordinates":[-84.607974,37.091673],"type":"Point"}
}