{
  "type": "Feature",
  "properties": {
    "iso:country":"US",
    "sg:address":"39 Erlanger St",
    "sg:city":"Elsmere",
    "sg:classifiers":[
        {
            "category":"Retail",
            "subcategory":"Auto Repair",
            "type":"Services"
        }
    ],
    "sg:phone":"+1 859 727 1711",
    "sg:postcode":"41018",
    "sg:province":"KY",
    "sg:tags":[
        "repairing",
        "automobile"
    ],
    "wof:name":"Don's Garage",
    "wof:placetype":"venue"
},
  "geometry": {"coordinates":[-84.601798,39.015724],"type":"Point"}
}