{
  "type": "Feature",
  "properties": {
    "addr:full":"1809 N Main St London KY 40741",
    "addr:housenumber":"1809",
    "addr:postcode":"40741",
    "addr:street":"N Main St",
    "iso:country":"US",
    "sg:address":"1809 N Main St",
    "sg:city":"London",
    "sg:classifiers":[
        {
            "category":"Social Services",
            "type":"Services"
        }
    ],
    "sg:phone":"+1 606 877 1138",
    "sg:postcode":"40741",
    "sg:province":"KY",
    "sg:tags":[
        "organization",
        "welfare"
    ],
    "wof:name":"Goodwill Industries",
    "wof:placetype":"venue"
},
  "geometry": {"coordinates":[-84.09913,37.139756],"type":"Point"}
}