{
  "type": "Feature",
  "properties": {
    "iso:country":"US",
    "sg:address":"515 Hospital Dr",
    "sg:city":"Shelbyville",
    "sg:classifiers":[
        {
            "category":"Health Services",
            "subcategory":"Doctor",
            "type":"Services"
        }
    ],
    "sg:phone":"+1 502 633 3525",
    "sg:postcode":"40065",
    "sg:province":"KY",
    "sg:tags":[
        "clinic"
    ],
    "wof:name":"Family Physician Assoc",
    "wof:placetype":"venue"
},
  "geometry": {"coordinates":[-85.23598699999999,38.211071],"type":"Point"}
}