{
  "type": "Feature",
  "properties": {
    "iso:country":"US",
    "sg:address":"8712 Bayberry Pl",
    "sg:city":"Louisville",
    "sg:classifiers":[
        {
            "category":"Real Estate",
            "subcategory":"Real Estate Operator",
            "type":"Services"
        }
    ],
    "sg:phone":"+1 502 339 1524",
    "sg:postcode":"40242",
    "sg:province":"KY",
    "sg:tags":[
        "reside",
        "commercial",
        "builder",
        "leasing"
    ],
    "wof:name":"Lan-Del Construction Co Inc",
    "wof:placetype":"venue"
},
  "geometry": {"coordinates":[-85.590079,38.28253],"type":"Point"}
}