{
  "type": "Feature",
  "properties": {
    "iso:country":"US",
    "sg:address":"721 Iroquois Ave",
    "sg:city":"Louisville",
    "sg:classifiers":[
        {
            "category":"Freight",
            "type":"Transportation"
        }
    ],
    "sg:phone":"+1 502 361 7482",
    "sg:postcode":"40214",
    "sg:province":"KY",
    "sg:tags":[
        "operator",
        "local",
        "trucking"
    ],
    "wof:name":"Kays Cartage Inc",
    "wof:placetype":"venue"
},
  "geometry": {"coordinates":[-85.77778600000001,38.168036],"type":"Point"}
}