{
  "type": "Feature",
  "properties": {
    "iso:country":"US",
    "sg:address":"203 N Kennett Ave",
    "sg:city":"Bardstown",
    "sg:classifiers":[
        {
            "category":"Social Services",
            "type":"Services"
        }
    ],
    "sg:phone":"+1 502 350 0551",
    "sg:postcode":"40004",
    "sg:province":"KY",
    "sg:tags":[
        "organization",
        "welfare"
    ],
    "wof:name":"Big Brothers & Big Sisters",
    "wof:placetype":"venue"
},
  "geometry": {"coordinates":[-85.476355,37.812933],"type":"Point"}
}