{
  "type": "Feature",
  "properties": {
    "iso:country":"US",
    "sg:address":"46 Eastern Ave",
    "sg:city":"Elsmere",
    "sg:classifiers":[
        {
            "category":"Shopping",
            "subcategory":"Florist",
            "type":"Retail Goods"
        }
    ],
    "sg:phone":"+1 859 581 3740",
    "sg:postcode":"41018",
    "sg:province":"KY",
    "wof:name":"Flowers By Flora Inc",
    "wof:placetype":"venue"
},
  "geometry": {"coordinates":[-84.611844,39.003258],"type":"Point"}
}