{
  "type": "Feature",
  "properties": {
    "addr:full":"101 N Big Run Rd Ashland KY 41102",
    "addr:housenumber":"101",
    "addr:postcode":"41102",
    "addr:street":"N Big Run Rd",
    "iso:country":"US",
    "sg:address":"101 N Big Run Rd",
    "sg:city":"Ashland",
    "sg:classifiers":[
        {
            "category":"Utilities",
            "subcategory":"Refuse",
            "type":"Services"
        }
    ],
    "sg:phone":"+1 606 928 9633",
    "sg:postcode":"41102",
    "sg:province":"KY",
    "sg:tags":[
        "landfill"
    ],
    "wof:name":"Cooksey Brothers Disposal",
    "wof:placetype":"venue"
},
  "geometry": {"coordinates":[-82.739637,38.363823],"type":"Point"}
}