{
  "type": "Feature",
  "properties": {
    "iso:country":"US",
    "sg:address":"2312 Waller Rd",
    "sg:city":"Verona",
    "sg:classifiers":[
        {
            "category":"Freight",
            "type":"Transportation"
        }
    ],
    "sg:phone":"+1 859 485 1829",
    "sg:postcode":"41092",
    "sg:province":"KY",
    "sg:tags":[
        "operator",
        "local",
        "trucking"
    ],
    "wof:name":"Richie Smeal Trucking Inc",
    "wof:placetype":"venue"
},
  "geometry": {"coordinates":[-84.66318200000001,38.789867],"type":"Point"}
}