{
  "type": "Feature",
  "properties": {
    "iso:country":"US",
    "sg:address":"1170 Penny Hwy",
    "sg:city":"Pikeville",
    "sg:classifiers":[
        {
            "category":"Retail",
            "subcategory":"Auto Repair",
            "type":"Services"
        }
    ],
    "sg:phone":"+1 606 639 2001",
    "sg:postcode":"41501",
    "sg:province":"KY",
    "sg:tags":[
        "repairing",
        "automobile"
    ],
    "wof:name":"D & D Garage & Car Wash",
    "wof:placetype":"venue"
},
  "geometry": {"coordinates":[-82.573707,37.356651],"type":"Point"}
}