{
  "type": "Feature",
  "properties": {
    "addr:full":"3792 Lake Park Dr Covington KY 41017",
    "addr:housenumber":"3792",
    "addr:postcode":"41017",
    "addr:street":"Lake Park Dr",
    "iso:country":"US",
    "sg:address":"3792 Lake Park Dr",
    "sg:city":"Covington",
    "sg:classifiers":[
        {
            "category":"Manufacturing",
            "subcategory":"Tools & Machinery",
            "type":"Manufacturing & Wholesale Goods"
        }
    ],
    "sg:phone":"+1 859 344 0415",
    "sg:postcode":"41017",
    "sg:province":"KY",
    "sg:tags":[
        "equipment",
        "construction"
    ],
    "wof:name":"ESCO Corp",
    "wof:placetype":"venue"
},
  "geometry": {"coordinates":[-84.527006,39.014737],"type":"Point"}
}