{
  "type": "Feature",
  "properties": {
    "iso:country":"US",
    "sg:address":"170 Durbin Ln",
    "sg:city":"Richmond",
    "sg:classifiers":[
        {
            "category":"Building & Trades",
            "subcategory":"Construction",
            "type":"Services"
        }
    ],
    "sg:phone":"+1 859 624 0059",
    "sg:postcode":"40475",
    "sg:province":"KY",
    "sg:tags":[
        "contractor"
    ],
    "wof:name":"Epps Roofing",
    "wof:placetype":"venue"
},
  "geometry": {"coordinates":[-84.20948300000001,37.788558],"type":"Point"}
}