{
  "type": "Feature",
  "properties": {
    "addr:full":"7216 US Hwy 60 Ashland KY 41102",
    "addr:housenumber":"7216",
    "addr:postcode":"41102",
    "addr:street":"Us Hwy 60",
    "iso:country":"US",
    "sg:address":"7216 US Hwy 60",
    "sg:city":"Ashland",
    "sg:classifiers":[
        {
            "category":"Travel",
            "subcategory":"Hotels & Motels",
            "type":"Entertainment"
        }
    ],
    "sg:phone":"+1 606 928 9501",
    "sg:postcode":"41102",
    "sg:province":"KY",
    "wof:name":"Knights Inn",
    "wof:placetype":"venue"
},
  "geometry": {"coordinates":[-82.69802,38.426457],"type":"Point"}
}