{
  "type": "Feature",
  "properties": {
    "addr:full":"1091 Scaffold Cane Rd Berea KY 40403",
    "addr:housenumber":"1091",
    "addr:postcode":"40403",
    "addr:street":"Scaffold Cane Rd",
    "iso:country":"US",
    "sg:address":"1091 Scaffold Cane Rd",
    "sg:city":"Berea",
    "sg:classifiers":[
        {
            "category":"Building & Trades",
            "subcategory":"Construction",
            "type":"Services"
        }
    ],
    "sg:phone":"+1 859 986 3469",
    "sg:postcode":"40403",
    "sg:province":"KY",
    "sg:tags":[
        "hanging",
        "contractor"
    ],
    "wof:name":"Vanwinkle Painting",
    "wof:placetype":"venue"
},
  "geometry": {"coordinates":[-84.280725,37.555548],"type":"Point"}
}