{
  "type": "Feature",
  "properties": {
    "iso:country":"US",
    "sg:address":"2129 Shelton Rd",
    "sg:city":"Lexington",
    "sg:classifiers":[
        {
            "category":"Health Services",
            "subcategory":"Doctor",
            "type":"Services"
        }
    ],
    "sg:phone":"+1 859 272 9576",
    "sg:postcode":"40515",
    "sg:province":"KY",
    "sg:tags":[
        "physician",
        "surgeon"
    ],
    "wof:name":"John E Plumlee Md",
    "wof:placetype":"venue"
},
  "geometry": {"coordinates":[-84.480566,37.957248],"type":"Point"}
}