{
  "type": "Feature",
  "properties": {
    "iso:country":"US",
    "sg:address":"1449 Bethlehem Rd",
    "sg:city":"Paris",
    "sg:classifiers":[
        {
            "category":"Farming",
            "subcategory":"Farm",
            "type":"Manufacturing & Wholesale Goods"
        }
    ],
    "sg:phone":"+1 859 987 5321",
    "sg:postcode":"40361",
    "sg:province":"KY",
    "sg:tags":[
        "crop",
        "general"
    ],
    "wof:name":"Ariparis Farm",
    "wof:placetype":"venue"
},
  "geometry": {"coordinates":[-84.296267,38.140418],"type":"Point"}
}