{
  "type": "Feature",
  "properties": {
    "iso:country":"US",
    "sg:address":"210 E Gray St",
    "sg:city":"Louisville",
    "sg:classifiers":[
        {
            "category":"Health Services",
            "subcategory":"Doctor",
            "type":"Services"
        }
    ],
    "sg:phone":"+1 502 629 3972",
    "sg:postcode":"40202",
    "sg:province":"KY",
    "sg:tags":[
        "physician",
        "surgeon"
    ],
    "wof:name":"University Children's Kidney",
    "wof:placetype":"venue"
},
  "geometry": {"coordinates":[-85.74963200000001,38.246652],"type":"Point"}
}