{
  "type": "Feature",
  "properties": {
    "iso:country":"US",
    "sg:address":"2130 Edenderry Dr",
    "sg:city":"Covington",
    "sg:classifiers":[
        {
            "category":"Health Services",
            "subcategory":"Doctor",
            "type":"Services"
        }
    ],
    "sg:phone":"+1 859 578 9104",
    "sg:postcode":"41017",
    "sg:province":"KY",
    "sg:tags":[
        "medical"
    ],
    "wof:name":"Rjw Architects PSC",
    "wof:placetype":"venue"
},
  "geometry": {"coordinates":[-84.56456300000001,39.059296],"type":"Point"}
}