{
  "type": "Feature",
  "properties": {
    "addr:full":"650 Boone Ave Winchester KY 40391",
    "addr:housenumber":"650",
    "addr:postcode":"40391",
    "addr:street":"Boone Ave",
    "iso:country":"US",
    "sg:address":"650 Boone Ave",
    "sg:city":"Winchester",
    "sg:classifiers":[
        {
            "category":"Education",
            "subcategory":"School",
            "type":"Public Place"
        }
    ],
    "sg:phone":"+1 859 744 1250",
    "sg:postcode":"40391",
    "sg:province":"KY",
    "wof:name":"Clark County Vocational School",
    "wof:placetype":"venue"
},
  "geometry": {"coordinates":[-84.193299,37.980135],"type":"Point"}
}