{
  "type": "Feature",
  "properties": {
    "iso:country":"US",
    "sg:address":"33 N Fort Thomas Ave",
    "sg:city":"Fort Thomas",
    "sg:classifiers":[
        {
            "category":"Professional",
            "subcategory":"Lawyer & Legal Services",
            "type":"Services"
        }
    ],
    "sg:phone":"+1 859 781 5700",
    "sg:postcode":"41075",
    "sg:province":"KY",
    "wof:name":"Tranter & Meier",
    "wof:placetype":"venue"
},
  "geometry": {"coordinates":[-84.4487,39.079601],"type":"Point"}
}