{
  "type": "Feature",
  "properties": {
    "addr:full":"2201 High St Ashland KY 41101",
    "addr:housenumber":"2201",
    "addr:postcode":"41101",
    "addr:street":"High St",
    "iso:country":"US",
    "sg:address":"2201 High St",
    "sg:city":"Ashland",
    "sg:classifiers":[
        {
            "category":"Retail",
            "subcategory":"Laundry & Dry Cleaning",
            "type":"Services"
        }
    ],
    "sg:phone":"+1 606 324 6733",
    "sg:postcode":"41101",
    "sg:province":"KY",
    "sg:tags":[
        "cleaners",
        "rug",
        "carpet"
    ],
    "wof:name":"A 1 Carpet Care",
    "wof:placetype":"venue"
},
  "geometry": {"coordinates":[-82.643683,38.455921],"type":"Point"}
}