{
  "type": "Feature",
  "properties": {
    "iso:country":"US",
    "sg:address":"800 Pennebaker Ave",
    "sg:city":"Bardstown",
    "sg:classifiers":[
        {
            "category":"Retail",
            "subcategory":"Car Wash",
            "type":"Services"
        }
    ],
    "sg:phone":"+1 502 331 0086",
    "sg:postcode":"40004",
    "sg:province":"KY",
    "sg:tags":[
        "carwash",
        "automobile",
        "detail",
        "clean"
    ],
    "wof:name":"Hands On Auto Detailing Inc",
    "wof:placetype":"venue"
},
  "geometry": {"coordinates":[-85.439701,37.826753],"type":"Point"}
}