{
  "type": "Feature",
  "properties": {
    "iso:country":"US",
    "sg:address":"3934 Dixie Hwy",
    "sg:city":"Louisville",
    "sg:classifiers":[
        {
            "category":"Health Services",
            "subcategory":"Doctor",
            "type":"Services"
        }
    ],
    "sg:phone":"+1 502 447 3016",
    "sg:postcode":"40216",
    "sg:province":"KY",
    "sg:tags":[
        "physician",
        "pediatrics-orthopedic",
        "surgeons",
        "orthopedics",
        "surgery",
        "surgeon"
    ],
    "wof:name":"Ellis And Badenhaus",
    "wof:placetype":"venue"
},
  "geometry": {"coordinates":[-85.807196,38.193442],"type":"Point"}
}