{
  "type": "Feature",
  "properties": {
    "iso:country":"US",
    "sg:address":"3343 Lexington Rd",
    "sg:city":"Paris",
    "sg:classifiers":[
        {
            "category":"Education",
            "subcategory":"School",
            "type":"Public Place"
        }
    ],
    "sg:phone":"+1 859 987 5855",
    "sg:postcode":"40361",
    "sg:province":"KY",
    "wof:name":"Bourbon County Learning Ctr",
    "wof:placetype":"venue"
},
  "geometry": {"coordinates":[-84.275301,38.194116],"type":"Point"}
}