{
  "type": "Feature",
  "properties": {
    "iso:country":"US",
    "sg:address":"116 Arterburn Dr",
    "sg:city":"Louisville",
    "sg:classifiers":[
        {
            "category":"Personal",
            "type":"Services"
        }
    ],
    "sg:phone":"+1 502 314 3254",
    "sg:postcode":"40222",
    "sg:province":"KY",
    "sg:tags":[
        "therapist",
        "massage"
    ],
    "wof:name":"Pami-Licensed Massage",
    "wof:placetype":"venue"
},
  "geometry": {"coordinates":[-85.61028,38.251629],"type":"Point"}
}