{
  "type": "Feature",
  "properties": {
    "addr:full":"3576 Pitchford Ridge Rd Scottsville KY 42164",
    "addr:housenumber":"3576",
    "addr:postcode":"42164",
    "addr:street":"Pitchford Ridge Rd",
    "iso:country":"US",
    "sg:address":"3576 Pitchford Ridge Rd",
    "sg:city":"Scottsville",
    "sg:classifiers":[
        {
            "category":"Travel",
            "subcategory":"Hotels & Motels",
            "type":"Entertainment"
        }
    ],
    "sg:phone":"+1 270 237 5775",
    "sg:postcode":"42164",
    "sg:province":"KY",
    "sg:tags":[
        "operation"
    ],
    "wof:name":"Magnolia Bed & Breakfast",
    "wof:placetype":"venue"
},
  "geometry": {"coordinates":[-86.048129,36.750539],"type":"Point"}
}