{
  "type": "Feature",
  "properties": {
    "iso:country":"US",
    "sg:address":"1801 Research Dr",
    "sg:city":"Louisville",
    "sg:classifiers":[
        {
            "category":"Retail",
            "subcategory":"Laundry & Dry Cleaning",
            "type":"Services"
        }
    ],
    "sg:phone":"+1 502 491 5202",
    "sg:postcode":"40299",
    "sg:province":"KY",
    "sg:tags":[
        "hospital"
    ],
    "wof:name":"Regional Hospital Services",
    "wof:placetype":"venue"
},
  "geometry": {"coordinates":[-85.556614,38.220237],"type":"Point"}
}