{
  "type": "Feature",
  "properties": {
    "iso:country":"US",
    "sg:address":"319 High St",
    "sg:city":"Campbellsville",
    "sg:classifiers":[
        {
            "category":"Professional",
            "subcategory":"Lawyer & Legal Services",
            "type":"Services"
        }
    ],
    "sg:phone":"+1 270 465 2022",
    "sg:postcode":"42718",
    "sg:province":"KY",
    "sg:tags":[
        "hearing",
        "contract",
        "reporter"
    ],
    "wof:name":"Linda McMahan",
    "wof:placetype":"venue"
},
  "geometry": {"coordinates":[-85.34412500000001,37.347004],"type":"Point"}
}