{
  "type": "Feature",
  "properties": {
    "iso:country":"US",
    "sg:address":"128 Wilmer Ave",
    "sg:city":"Cincinnati",
    "sg:classifiers":[
        {
            "category":"Recreation",
            "subcategory":"Marina",
            "type":"Entertainment"
        }
    ],
    "sg:phone":"+1 513 321 8809",
    "sg:postcode":"45226",
    "sg:province":"OH",
    "sg:tags":[
        "repairing",
        "boat"
    ],
    "wof:name":"Fiberglass Custom Repair Ctr",
    "wof:placetype":"venue"
},
  "geometry": {"coordinates":[-84.43307900000001,39.101813],"type":"Point"}
}