{
  "type": "Feature",
  "properties": {
    "iso:country":"US",
    "sg:address":"88 E Main St",
    "sg:city":"Taylorsville",
    "sg:classifiers":[
        {
            "category":"Government",
            "subcategory":"Office",
            "type":"Public Place"
        }
    ],
    "sg:phone":"+1 502 477 3246",
    "sg:postcode":"40071",
    "sg:province":"KY",
    "sg:tags":[
        "county",
        "program",
        "adm"
    ],
    "wof:name":"Spencer County Economic Ofc",
    "wof:placetype":"venue"
},
  "geometry": {"coordinates":[-85.34296399999999,38.031438],"type":"Point"}
}