{
  "type": "Feature",
  "properties": {
    "iso:country":"US",
    "sg:address":"515 S Main St",
    "sg:city":"Greenville",
    "sg:classifiers":[
        {
            "category":"Autos & Motor Vehicles",
            "subcategory":"Automobile Sales",
            "type":"Retail Goods"
        }
    ],
    "sg:phone":"+1 270 338 2700",
    "sg:postcode":"42345",
    "sg:province":"KY",
    "sg:tags":[
        "car",
        "dealer"
    ],
    "wof:name":"Larry Sparks Wholesale Motors",
    "wof:placetype":"venue"
},
  "geometry": {"coordinates":[-87.173041,37.193762],"type":"Point"}
}