{
  "type": "Feature",
  "properties": {
    "addr:full":"112 Bellview Ave Versailles KY 40383",
    "addr:housenumber":"112",
    "addr:postcode":"40383",
    "addr:street":"Bellview Ave",
    "iso:country":"US",
    "sg:address":"112 Bellview Ave",
    "sg:city":"Versailles",
    "sg:classifiers":[
        {
            "category":"Retail",
            "subcategory":"Repair Shop",
            "type":"Services"
        }
    ],
    "sg:phone":"+1 859 873 4453",
    "sg:postcode":"40383",
    "sg:province":"KY",
    "sg:tags":[
        "picture",
        "framing"
    ],
    "wof:name":"Hide Your Hearts Creations",
    "wof:placetype":"venue"
},
  "geometry": {"coordinates":[-84.71892800000001,38.052246],"type":"Point"}
}