{
  "type": "Feature",
  "properties": {
    "addr:full":"5338 S 3rd St Louisville KY 40214",
    "addr:housenumber":"5338",
    "addr:postcode":"40214",
    "addr:street":"S 3Rd St",
    "iso:country":"US",
    "sg:address":"5338 S 3rd St",
    "sg:city":"Louisville",
    "sg:classifiers":[
        {
            "category":"Restaurant",
            "type":"Food & Drink"
        }
    ],
    "sg:menulink":"http://www.allmenus.com/ky/louisville-south/81936-subway/menu/",
    "sg:phone":"+1 502 361 3626",
    "sg:postcode":"40214",
    "sg:province":"KY",
    "sg:tags":[
        "american",
        "sandwich"
    ],
    "wof:name":"Subway",
    "wof:placetype":"venue"
},
  "geometry": {"coordinates":[-85.768079,38.171154],"type":"Point"}
}