{
  "type": "Feature",
  "properties": {
    "iso:country":"US",
    "sg:address":"321 Outer Loop",
    "sg:city":"Louisville",
    "sg:classifiers":[
        {
            "category":"Retail",
            "subcategory":"Auto Rental",
            "type":"Services"
        },
        {
            "category":"Bus Charters",
            "type":"Transportation"
        },
        {
            "category":"Airport",
            "type":"Transportation"
        },
        {
            "category":"Autos & Motor Vehicles",
            "subcategory":"Recreational Vehicle Sales",
            "type":"Retail Goods"
        }
    ],
    "sg:phone":"+1 502 561 4022",
    "sg:postcode":"40214",
    "sg:province":"KY",
    "sg:tags":[
        "home",
        "limousine",
        "buses-charter"
    ],
    "wof:name":"Sandollar Limousine Service",
    "wof:placetype":"venue"
},
  "geometry": {"coordinates":[-85.77176900000001,38.126136],"type":"Point"}
}