{
  "type": "Feature",
  "properties": {
    "addr:full":"7803 National Tpke Louisville KY 40214",
    "addr:housenumber":"7803",
    "addr:postcode":"40214",
    "addr:street":"National Tpke",
    "iso:country":"US",
    "sg:address":"7803 National Tpke",
    "sg:city":"Louisville",
    "sg:classifiers":[
        {
            "category":"Shopping",
            "type":"Retail Goods"
        }
    ],
    "sg:phone":"+1 502 363 7088",
    "sg:postcode":"40214",
    "sg:province":"KY",
    "sg:tags":[
        "chemical"
    ],
    "wof:name":"Freebird Chemical Inc",
    "wof:placetype":"venue"
},
  "geometry": {"coordinates":[-85.75411800000001,38.140524],"type":"Point"}
}