{
  "type": "Feature",
  "properties": {
    "iso:country":"US",
    "sg:address":"4079 Dogwood Ln",
    "sg:city":"Paducah",
    "sg:classifiers":[
        {
            "category":"Building & Trades",
            "subcategory":"Electrical",
            "type":"Services"
        }
    ],
    "sg:phone":"+1 270 443 6847",
    "sg:postcode":"42003",
    "sg:province":"KY",
    "sg:tags":[
        "industrial",
        "electrician",
        "contractors-commercial",
        "electric"
    ],
    "wof:name":"Middleton Electric Service",
    "wof:placetype":"venue"
},
  "geometry": {"coordinates":[-88.627009,37.050203],"type":"Point"}
}