{
  "type": "Feature",
  "properties": {
    "addr:full":"3228 Latonia Ave Covington KY 41015",
    "addr:housenumber":"3228",
    "addr:postcode":"41015",
    "addr:street":"Latonia Ave",
    "iso:country":"US",
    "sg:address":"3228 Latonia Ave",
    "sg:city":"Covington",
    "sg:classifiers":[
        {
            "category":"Food & Beverages",
            "subcategory":"Groceries & Convenience Stores",
            "type":"Retail Goods"
        }
    ],
    "sg:phone":"+1 859 261 5878",
    "sg:postcode":"41015",
    "sg:province":"KY",
    "sg:tags":[
        "grocer"
    ],
    "wof:name":"Sarah's Stop & Shop",
    "wof:placetype":"venue"
},
  "geometry": {"coordinates":[-84.51325,39.047126],"type":"Point"}
}