{
  "type": "Feature",
  "properties": {
    "iso:country":"US",
    "sg:address":"3137 Dixie Hwy",
    "sg:city":"Erlanger",
    "sg:classifiers":[
        {
            "category":"Health Services",
            "subcategory":"Chiropractor",
            "type":"Services"
        }
    ],
    "sg:phone":"+1 859 426 5870",
    "sg:postcode":"41018",
    "sg:province":"KY",
    "wof:name":"Midwest Chiropractic",
    "wof:placetype":"venue"
},
  "geometry": {"coordinates":[-84.589945,39.020717],"type":"Point"}
}