{
  "type": "Feature",
  "properties": {
    "iso:country":"US",
    "sg:address":"5401 Southside Dr",
    "sg:city":"Louisville",
    "sg:classifiers":[
        {
            "category":"Government",
            "subcategory":"Office",
            "type":"Public Place"
        }
    ],
    "sg:phone":"+1 502 375 3329",
    "sg:postcode":"40214",
    "sg:province":"KY",
    "sg:tags":[
        "federal",
        "security"
    ],
    "wof:name":"US Naval Reserve Ctr",
    "wof:placetype":"venue"
},
  "geometry": {"coordinates":[-85.76463200000001,38.169717],"type":"Point"}
}