{
  "type": "Feature",
  "properties": {
    "iso:country":"US",
    "sg:address":"210 6th St",
    "sg:city":"Carrollton",
    "sg:classifiers":[
        {
            "category":"Professional",
            "subcategory":"Accounting & Tax Preparation",
            "type":"Services"
        }
    ],
    "sg:phone":"+1 502 732 5085",
    "sg:postcode":"41008",
    "sg:province":"KY",
    "sg:tags":[
        "return"
    ],
    "wof:name":"Daileys Tax Service",
    "wof:placetype":"venue"
},
  "geometry": {"coordinates":[-85.17821000000001,38.681067],"type":"Point"}
}