{
  "type": "Feature",
  "properties": {
    "iso:country":"US",
    "sg:address":"3703 Taylorsville Rd",
    "sg:city":"Louisville",
    "sg:classifiers":[
        {
            "category":"Professional",
            "subcategory":"Research",
            "type":"Services"
        }
    ],
    "sg:phone":"+1 502 452 2937",
    "sg:postcode":"40220",
    "sg:province":"KY",
    "sg:tags":[
        "development",
        "laboratory"
    ],
    "wof:name":"Research Department",
    "wof:placetype":"venue"
},
  "geometry": {"coordinates":[-85.64526499999999,38.221025],"type":"Point"}
}