{
  "type": "Feature",
  "properties": {
    "addr:full":"2520 Cumberland Trace Rd Bowling Green KY 42103",
    "addr:housenumber":"2520",
    "addr:postcode":"42103",
    "addr:street":"Cumberland Trace Rd",
    "iso:country":"US",
    "sg:address":"2520 Cumberland Trace Rd",
    "sg:city":"Bowling Green",
    "sg:classifiers":[
        {
            "category":"Farming",
            "subcategory":"Livestock Farm",
            "type":"Manufacturing & Wholesale Goods"
        }
    ],
    "sg:phone":"+1 270 842 1826",
    "sg:postcode":"42103",
    "sg:province":"KY",
    "sg:tags":[
        "beef",
        "feedlot",
        "cattle"
    ],
    "wof:name":"Dewey Dickerson",
    "wof:placetype":"venue"
},
  "geometry": {"coordinates":[-86.39732600000001,36.964334],"type":"Point"}
}