{
  "type": "Feature",
  "properties": {
    "iso:country":"US",
    "sg:address":"152 E Reynolds Rd",
    "sg:city":"Lexington",
    "sg:classifiers":[
        {
            "category":"Restaurant",
            "type":"Food & Drink"
        }
    ],
    "sg:phone":"+1 859 272 3486",
    "sg:postcode":"40517",
    "sg:province":"KY",
    "sg:tags":[
        "style",
        "family"
    ],
    "wof:name":"Corbin Restaurants Inc",
    "wof:placetype":"venue"
},
  "geometry": {"coordinates":[-84.521449,37.990449],"type":"Point"}
}