{
  "type": "Feature",
  "properties": {
    "iso:country":"US",
    "sg:address":"7280 Antioch Rd",
    "sg:city":"Hopkinsville",
    "sg:classifiers":[
        {
            "category":"Farming",
            "subcategory":"Nursery",
            "type":"Manufacturing & Wholesale Goods"
        },
        {
            "category":"Home & Garden",
            "subcategory":"Garden Supply",
            "type":"Retail Goods"
        }
    ],
    "sg:phone":"+1 270 886 8535",
    "sg:postcode":"42240",
    "sg:province":"KY",
    "sg:tags":[
        "florist",
        "ornamental",
        "greenhouse"
    ],
    "wof:name":"Ma & Pa's Country Greenhouses",
    "wof:placetype":"venue"
},
  "geometry": {"coordinates":[-87.40414,36.91843],"type":"Point"}
}