{
  "type": "Feature",
  "properties": {
    "addr:full":"200 E Washington St Glasgow KY 42141",
    "addr:housenumber":"200",
    "addr:postcode":"42141",
    "addr:street":"E Washington St",
    "iso:country":"US",
    "sg:address":"200 E Washington St",
    "sg:city":"Glasgow",
    "sg:classifiers":[
        {
            "category":"Organizations",
            "subcategory":"Religious Organization",
            "type":"Services"
        }
    ],
    "sg:phone":"+1 270 651 2818",
    "sg:postcode":"42141",
    "sg:province":"KY",
    "sg:tags":[
        "church"
    ],
    "wof:name":"First Presbyterian Church",
    "wof:placetype":"venue"
},
  "geometry": {"coordinates":[-85.911338,36.99458],"type":"Point"}
}