{
  "type": "Feature",
  "properties": {
    "iso:country":"US",
    "sg:address":"1600 Midland Trl",
    "sg:city":"Shelbyville",
    "sg:classifiers":[
        {
            "category":"Professional",
            "type":"Services"
        }
    ],
    "sg:phone":"+1 502 633 9472",
    "sg:postcode":"40065",
    "sg:province":"KY",
    "sg:tags":[
        "establishment"
    ],
    "wof:name":"CPM",
    "wof:placetype":"venue"
},
  "geometry": {"coordinates":[-85.24147499999999,38.21272],"type":"Point"}
}