{
  "type": "Feature",
  "properties": {
    "iso:country":"US",
    "sg:address":"606 W Main St",
    "sg:city":"Morehead",
    "sg:classifiers":[
        {
            "category":"Manufacturing",
            "subcategory":"Apparel",
            "type":"Manufacturing & Wholesale Goods"
        }
    ],
    "sg:phone":"+1 606 784 4101",
    "sg:postcode":"40351",
    "sg:province":"KY",
    "sg:tags":[
        "outerwear"
    ],
    "wof:name":"Cowden-Morehead Co",
    "wof:placetype":"venue"
},
  "geometry": {"coordinates":[-83.439373,38.175292],"type":"Point"}
}