{
  "type": "Feature",
  "properties": {
    "iso:country":"US",
    "sg:address":"115 Rice Ct",
    "sg:city":"Richmond",
    "sg:classifiers":[
        {
            "category":"Retail",
            "subcategory":"Auto Repair",
            "type":"Services"
        }
    ],
    "sg:phone":"+1 859 623 1549",
    "sg:postcode":"40475",
    "sg:province":"KY",
    "sg:tags":[
        "general"
    ],
    "wof:name":"Independent Service Garage",
    "wof:placetype":"venue"
},
  "geometry": {"coordinates":[-84.281693,37.736286],"type":"Point"}
}