{
  "type": "Feature",
  "properties": {
    "iso:country":"US",
    "sg:address":"12820 US Hwy 60",
    "sg:city":"Guston",
    "sg:classifiers":[
        {
            "category":"Farming",
            "subcategory":"Nursery",
            "type":"Manufacturing & Wholesale Goods"
        }
    ],
    "sg:phone":"+1 270 547 3843",
    "sg:postcode":"40142",
    "sg:province":"KY",
    "sg:tags":[
        "greenhouse"
    ],
    "wof:name":"Janice's Greenhouse",
    "wof:placetype":"venue"
},
  "geometry": {"coordinates":[-86.204157,37.883093],"type":"Point"}
}