{
  "type": "Feature",
  "properties": {
    "iso:country":"US",
    "sg:address":"230 2nd St",
    "sg:city":"Henderson",
    "sg:classifiers":[
        {
            "category":"Insurance",
            "subcategory":"Insurance Agent",
            "type":"Services"
        }
    ],
    "sg:phone":"+1 270 831 1038",
    "sg:postcode":"42420",
    "sg:province":"KY",
    "wof:name":"Pat Morgan & Assoc",
    "wof:placetype":"venue"
},
  "geometry": {"coordinates":[-87.59124199999999,37.840497],"type":"Point"}
}