{
  "type": "Feature",
  "properties": {
    "addr:full":"605 Pike St Sadieville KY 40370",
    "addr:housenumber":"605",
    "addr:postcode":"40370",
    "addr:street":"Pike St",
    "iso:country":"US",
    "sg:address":"605 Pike St",
    "sg:city":"Sadieville",
    "sg:classifiers":[
        {
            "category":"Government",
            "subcategory":"Office",
            "type":"Public Place"
        }
    ],
    "sg:phone":"+1 502 857 4576",
    "sg:postcode":"40370",
    "sg:province":"KY",
    "sg:tags":[
        "city"
    ],
    "wof:name":"Sadieville City Hall",
    "wof:placetype":"venue"
},
  "geometry": {"coordinates":[-84.534178,38.390791],"type":"Point"}
}