{
  "type": "Feature",
  "properties": {
    "iso:country":"US",
    "sg:address":"1209 Moseley St",
    "sg:city":"Owensboro",
    "sg:classifiers":[
        {
            "category":"Social Services",
            "type":"Services"
        }
    ],
    "sg:phone":"+1 270 684 8783",
    "sg:postcode":"42303",
    "sg:province":"KY",
    "sg:tags":[
        "organization",
        "religious"
    ],
    "wof:name":"Gods Outreach Inc",
    "wof:placetype":"venue"
},
  "geometry": {"coordinates":[-87.10622499999999,37.763298],"type":"Point"}
}