{
  "type": "Feature",
  "properties": {
    "iso:country":"US",
    "sg:address":"301 John J Johnson Ave",
    "sg:city":"Franklin",
    "sg:classifiers":[
        {
            "category":"Organizations",
            "subcategory":"Religious Organization",
            "type":"Services"
        }
    ],
    "sg:phone":"+1 270 586 6044",
    "sg:postcode":"42134",
    "sg:province":"KY",
    "sg:tags":[
        "church"
    ],
    "wof:name":"Alpha Baptist Church",
    "wof:placetype":"venue"
},
  "geometry": {"coordinates":[-86.58386299999999,36.725573],"type":"Point"}
}