{
  "type": "Feature",
  "properties": {
    "iso:country":"US",
    "sg:address":"3464 Warwick Ct",
    "sg:city":"Lexington",
    "sg:classifiers":[
        {
            "category":"Professional",
            "type":"Services"
        }
    ],
    "sg:phone":"+1 859 273 3788",
    "sg:postcode":"40517",
    "sg:province":"KY",
    "sg:tags":[
        "establishment"
    ],
    "wof:name":"N R Cron",
    "wof:placetype":"venue"
},
  "geometry": {"coordinates":[-84.508444,37.990572],"type":"Point"}
}