{
  "type": "Feature",
  "properties": {
    "iso:country":"US",
    "sg:address":"4225 Nashville Rd",
    "sg:city":"Franklin",
    "sg:phone":"+1 270 586 8283",
    "sg:postcode":"42134",
    "sg:province":"KY",
    "sg:tags":[
        "oil"
    ],
    "wof:name":"Keystops LLC",
    "wof:placetype":"venue"
},
  "geometry": {"coordinates":[-86.555069,36.663278],"type":"Point"}
}