{
  "type": "Feature",
  "properties": {
    "addr:full":"616 E Main St Frankfort KY 40601",
    "addr:housenumber":"616",
    "addr:postcode":"40601",
    "addr:street":"E Main St",
    "iso:country":"US",
    "sg:address":"616 E Main St",
    "sg:city":"Frankfort",
    "sg:classifiers":[
        {
            "category":"Shopping",
            "subcategory":"Tobacco",
            "type":"Retail Goods"
        }
    ],
    "sg:phone":"+1 502 223 5116",
    "sg:postcode":"40601",
    "sg:province":"KY",
    "sg:tags":[
        "cigarette",
        "cigar",
        "dealer"
    ],
    "wof:name":"Margaret's Tobacco Warehouse",
    "wof:placetype":"venue"
},
  "geometry": {"coordinates":[-84.847824,38.203068],"type":"Point"}
}