{
  "type": "Feature",
  "properties": {
    "iso:country":"US",
    "sg:address":"3407 W Broadway",
    "sg:city":"Louisville",
    "sg:classifiers":[
        {
            "category":"Restaurant",
            "type":"Food & Drink"
        }
    ],
    "sg:menulink":"http://www.allmenus.com/ky/louisville-west/200447-long-john-silvers/menu/",
    "sg:phone":"+1 502 774 1285",
    "sg:postcode":"40211",
    "sg:province":"KY",
    "sg:tags":[
        "seafood",
        "american"
    ],
    "wof:name":"Long John Silver's",
    "wof:placetype":"venue"
},
  "geometry": {"coordinates":[-85.808283,38.2499],"type":"Point"}
}