{
  "type": "Feature",
  "properties": {
    "addr:full":"583 Silver Star School Rd Princeton KY 42445",
    "addr:housenumber":"583",
    "addr:postcode":"42445",
    "addr:street":"Silver Star School Rd",
    "iso:country":"US",
    "sg:address":"583 Silver Star School Rd",
    "sg:city":"Princeton",
    "sg:classifiers":[
        {
            "category":"Organizations",
            "subcategory":"Religious Organization",
            "type":"Services"
        }
    ],
    "sg:phone":"+1 270 365 2878",
    "sg:postcode":"42445",
    "sg:province":"KY",
    "sg:tags":[
        "church"
    ],
    "wof:name":"Rock Spring United Methodist",
    "wof:placetype":"venue"
},
  "geometry": {"coordinates":[-87.901248,37.048824],"type":"Point"}
}