{
  "type": "Feature",
  "properties": {
    "iso:country":"US",
    "sg:address":"517 Ash St",
    "sg:city":"Elsmere",
    "sg:classifiers":[
        {
            "category":"Retail",
            "subcategory":"Auto Repair",
            "type":"Services"
        }
    ],
    "sg:phone":"+1 859 727 9005",
    "sg:postcode":"41018",
    "sg:province":"KY",
    "sg:tags":[
        "repairing",
        "automobile"
    ],
    "wof:name":"A4A Auto Electric",
    "wof:placetype":"venue"
},
  "geometry": {"coordinates":[-84.60209500000001,39.009692],"type":"Point"}
}