{
  "type": "Feature",
  "properties": {
    "iso:country":"US",
    "sg:address":"9477 Westport Rd",
    "sg:city":"Louisville",
    "sg:classifiers":[
        {
            "category":"Shopping",
            "type":"Retail Goods"
        }
    ],
    "sg:phone":"+1 502 425 1692",
    "sg:postcode":"40241",
    "sg:province":"KY",
    "sg:tags":[
        "equipment",
        "wine",
        "supply"
    ],
    "wof:name":"Winemakers Supply",
    "wof:placetype":"venue"
},
  "geometry": {"coordinates":[-85.57822899999999,38.286041],"type":"Point"}
}