{
  "type": "Feature",
  "properties": {
    "iso:country":"US",
    "sg:address":"699 Washington School Rd",
    "sg:city":"Scottsville",
    "sg:classifiers":[
        {
            "category":"Professional",
            "type":"Services"
        }
    ],
    "sg:phone":"+1 270 622 2589",
    "sg:postcode":"42164",
    "sg:province":"KY",
    "sg:tags":[
        "establishment"
    ],
    "wof:name":"Purdy Pure Producers Inc",
    "wof:placetype":"venue"
},
  "geometry": {"coordinates":[-86.138682,36.783009],"type":"Point"}
}