{
  "type": "Feature",
  "properties": {
    "iso:country":"US",
    "sg:address":"7337 State Hwy 698",
    "sg:city":"Hustonville",
    "sg:classifiers":[
        {
            "category":"Organizations",
            "subcategory":"Religious Organization",
            "type":"Services"
        }
    ],
    "sg:phone":"+1 606 365 2315",
    "sg:postcode":"40437",
    "sg:province":"KY",
    "sg:tags":[
        "church"
    ],
    "wof:name":"Green River Pentecostal Church",
    "wof:placetype":"venue"
},
  "geometry": {"coordinates":[-84.736064,37.438028],"type":"Point"}
}