{
  "type": "Feature",
  "properties": {
    "addr:full":"1324 Frederica St Owensboro KY 42301",
    "addr:housenumber":"1324",
    "addr:postcode":"42301",
    "addr:street":"Frederica St",
    "iso:country":"US",
    "sg:address":"1324 Frederica St",
    "sg:city":"Owensboro",
    "sg:classifiers":[
        {
            "category":"Professional",
            "subcategory":"Lawyer & Legal Services",
            "type":"Services"
        }
    ],
    "sg:phone":"+1 270 685 0033",
    "sg:postcode":"42301",
    "sg:province":"KY",
    "sg:tags":[
        "attorney"
    ],
    "wof:name":"Alvey & Duty",
    "wof:placetype":"venue"
},
  "geometry": {"coordinates":[-87.112528,37.762913],"type":"Point"}
}