{
  "type": "Feature",
  "properties": {
    "iso:country":"US",
    "sg:address":"191 Cumberland Trace Rd",
    "sg:city":"Bowling Green",
    "sg:classifiers":[
        {
            "category":"Restaurant",
            "type":"Food & Drink"
        }
    ],
    "sg:phone":"+1 270 846 1125",
    "sg:postcode":"42103",
    "sg:province":"KY",
    "wof:name":"Motor City Bar & Grill",
    "wof:placetype":"venue"
},
  "geometry": {"coordinates":[-86.41493699999999,36.938255],"type":"Point"}
}