{
  "type": "Feature",
  "properties": {
    "iso:country":"US",
    "sg:address":"305 W Main St",
    "sg:city":"Cumberland",
    "sg:classifiers":[
        {
            "category":"Home & Garden",
            "subcategory":"Furniture",
            "type":"Retail Goods"
        }
    ],
    "sg:phone":"+1 606 589 4162",
    "sg:postcode":"40823",
    "sg:province":"KY",
    "wof:name":"Rowletts Furniture",
    "wof:placetype":"venue"
},
  "geometry": {"coordinates":[-82.992262,36.975275],"type":"Point"}
}