{
  "type": "Feature",
  "properties": {
    "iso:country":"US",
    "sg:address":"1217 Blackwater Rd",
    "sg:city":"London",
    "sg:phone":"+1 606 878 9568",
    "sg:postcode":"40744",
    "sg:province":"KY",
    "sg:tags":[
        "farm",
        "tobacco"
    ],
    "wof:name":"Carol Asher",
    "wof:placetype":"venue"
},
  "geometry": {"coordinates":[-83.9228,37.06996],"type":"Point"}
}