{
  "type": "Feature",
  "properties": {
    "addr:full":"1000 Celina Rd Burkesville KY 42717",
    "addr:housenumber":"1000",
    "addr:postcode":"42717",
    "addr:street":"Celina Rd",
    "iso:country":"US",
    "sg:address":"1000 Celina Rd",
    "sg:city":"Burkesville",
    "sg:classifiers":[
        {
            "category":"Shopping",
            "subcategory":"Bicycles & Sporting Goods",
            "type":"Retail Goods"
        }
    ],
    "sg:phone":"+1 270 433 6500",
    "sg:postcode":"42717",
    "sg:province":"KY",
    "wof:name":"Cumberland Sportsman Supply",
    "wof:placetype":"venue"
},
  "geometry": {"coordinates":[-85.377757,36.773902],"type":"Point"}
}