{
  "type": "Feature",
  "properties": {
    "addr:full":"10 US Hwy 41A N Dixon KY 42409",
    "addr:housenumber":"10",
    "addr:postcode":"42409",
    "addr:street":"Us Hwy 41A N",
    "iso:country":"US",
    "sg:address":"10 US Hwy 41A N",
    "sg:city":"Dixon",
    "sg:classifiers":[
        {
            "category":"Utilities",
            "subcategory":"Water",
            "type":"Services"
        }
    ],
    "sg:phone":"+1 270 639 5088",
    "sg:postcode":"42409",
    "sg:province":"KY",
    "sg:tags":[
        "company",
        "sewage"
    ],
    "wof:name":"Dixon City Water Works",
    "wof:placetype":"venue"
},
  "geometry": {"coordinates":[-87.68998000000001,37.518982],"type":"Point"}
}