{
  "type": "Feature",
  "properties": {
    "addr:full":"184 State Hwy 810 N Kuttawa KY 42055",
    "addr:housenumber":"184",
    "addr:postcode":"42055",
    "addr:street":"State Hwy 810 N",
    "iso:country":"US",
    "sg:address":"184 State Hwy 810 N",
    "sg:city":"Kuttawa",
    "sg:classifiers":[
        {
            "category":"Organizations",
            "subcategory":"Religious Organization",
            "type":"Services"
        }
    ],
    "sg:phone":"+1 270 388 9579",
    "sg:postcode":"42055",
    "sg:province":"KY",
    "sg:tags":[
        "church"
    ],
    "wof:name":"Suwanee Furnace Baptist Church",
    "wof:placetype":"venue"
},
  "geometry": {"coordinates":[-88.17477599999999,37.063438],"type":"Point"}
}