{
  "type": "Feature",
  "properties": {
    "addr:full":"6126 State Hwy 315 Booneville KY 41314",
    "addr:housenumber":"6126",
    "addr:postcode":"41314",
    "addr:street":"State Hwy 315",
    "iso:country":"US",
    "sg:address":"6126 State Hwy 315",
    "sg:city":"Booneville",
    "sg:classifiers":[
        {
            "category":"Organizations",
            "subcategory":"Religious Organization",
            "type":"Services"
        }
    ],
    "sg:phone":"+1 606 295 5673",
    "sg:postcode":"41314",
    "sg:province":"KY",
    "sg:tags":[
        "church"
    ],
    "wof:name":"Old Macedonia Regular Bapt Chr",
    "wof:placetype":"venue"
},
  "geometry": {"coordinates":[-83.468963,37.439166],"type":"Point"}
}