{
  "type": "Feature",
  "properties": {
    "iso:country":"US",
    "sg:address":"1200 N Middletown Rd",
    "sg:city":"Paris",
    "sg:classifiers":[
        {
            "category":"Retail",
            "subcategory":"Animal Services",
            "type":"Services"
        }
    ],
    "sg:phone":"+1 859 987 8282",
    "sg:postcode":"40361",
    "sg:province":"KY",
    "sg:tags":[
        "breeder",
        "horse"
    ],
    "sg:website":"www.stonerside.com",
    "wof:name":"Stoneside Stable",
    "wof:placetype":"venue"
},
  "geometry": {"coordinates":[-84.196288,38.19875],"type":"Point"}
}