{
  "type": "Feature",
  "properties": {
    "iso:country":"US",
    "sg:address":"3201 State Hwy 825",
    "sg:city":"Hagerhill",
    "sg:classifiers":[
        {
            "category":"Professional",
            "subcategory":"Accounting & Tax Preparation",
            "type":"Services"
        }
    ],
    "sg:phone":"+1 606 265 3535",
    "sg:postcode":"41222",
    "sg:province":"KY",
    "sg:tags":[
        "accountant"
    ],
    "wof:name":"Connie Workman CPA",
    "wof:placetype":"venue"
},
  "geometry": {"coordinates":[-82.85132900000001,37.777128],"type":"Point"}
}