{
  "type": "Feature",
  "properties": {
    "iso:country":"US",
    "sg:address":"1625 Lowes Rd",
    "sg:city":"Cunningham",
    "sg:phone":"+1 270 674 5748",
    "sg:postcode":"42035",
    "sg:province":"KY",
    "sg:tags":[
        "farm",
        "soybean"
    ],
    "wof:name":"Dorothy Sue Sanderson",
    "wof:placetype":"venue"
},
  "geometry": {"coordinates":[-88.790584,36.902985],"type":"Point"}
}