{
  "type": "Feature",
  "properties": {
    "addr:full":"2745 Nashville Rd Bowling Green KY 42101",
    "addr:housenumber":"2745",
    "addr:postcode":"42101",
    "addr:street":"Nashville Rd",
    "iso:country":"US",
    "sg:address":"2745 Nashville Rd",
    "sg:city":"Bowling Green",
    "sg:classifiers":[
        {
            "category":"Professional",
            "type":"Services"
        }
    ],
    "sg:phone":"+1 270 745 0936",
    "sg:postcode":"42101",
    "sg:province":"KY",
    "wof:name":"Bd Home Services",
    "wof:placetype":"venue"
},
  "geometry": {"coordinates":[-86.473339,36.955044],"type":"Point"}
}