{
  "type": "Feature",
  "properties": {
    "iso:country":"US",
    "sg:address":"3004 Freys Hill Rd",
    "sg:city":"Louisville",
    "sg:classifiers":[
        {
            "category":"Building & Trades",
            "subcategory":"Construction",
            "type":"Services"
        }
    ],
    "sg:phone":"+1 502 425 7574",
    "sg:postcode":"40241",
    "sg:province":"KY",
    "sg:tags":[
        "contractor"
    ],
    "wof:name":"Crossroads Contracting LLC",
    "wof:placetype":"venue"
},
  "geometry": {"coordinates":[-85.54785,38.278971],"type":"Point"}
}