{
  "type": "Feature",
  "properties": {
    "addr:full":"1021 N Main St Nicholasville KY 40356",
    "addr:housenumber":"1021",
    "addr:postcode":"40356",
    "addr:street":"N Main St",
    "iso:country":"US",
    "sg:address":"1021 N Main St",
    "sg:city":"Nicholasville",
    "sg:classifiers":[
        {
            "category":"Shopping",
            "subcategory":"Used Merchandise",
            "type":"Retail Goods"
        }
    ],
    "sg:phone":"+1 859 885 9097",
    "sg:postcode":"40356",
    "sg:province":"KY",
    "sg:tags":[
        "flea",
        "market"
    ],
    "wof:name":"Nicholsville Peddlers Mall",
    "wof:placetype":"venue"
},
  "geometry": {"coordinates":[-84.565135,37.89906],"type":"Point"}
}