{
  "type": "Feature",
  "properties": {
    "iso:country":"US",
    "sg:address":"4075 Richmond Rd",
    "sg:city":"Irvine",
    "sg:classifiers":[
        {
            "category":"Home & Garden",
            "subcategory":"Building Materials",
            "type":"Retail Goods"
        }
    ],
    "sg:phone":"+1 606 723 8733",
    "sg:postcode":"40336",
    "sg:province":"KY",
    "sg:tags":[
        "lumber"
    ],
    "wof:name":"Rogers Quality Wood Products",
    "wof:placetype":"venue"
},
  "geometry": {"coordinates":[-84.036959,37.702041],"type":"Point"}
}