{
  "type": "Feature",
  "properties": {
    "iso:country":"US",
    "sg:address":"10370 Bluegrass Pkwy",
    "sg:city":"Louisville",
    "sg:classifiers":[
        {
            "category":"Retail",
            "subcategory":"Auto Repair",
            "type":"Services"
        }
    ],
    "sg:phone":"+1 502 491 5100",
    "sg:postcode":"40299",
    "sg:province":"KY",
    "sg:tags":[
        "repairing",
        "automobile"
    ],
    "wof:name":"Pioneer Industrial",
    "wof:placetype":"venue"
},
  "geometry": {"coordinates":[-85.562372,38.222426],"type":"Point"}
}