{
  "type": "Feature",
  "properties": {
    "iso:country":"US",
    "sg:address":"1808 S 7th St",
    "sg:city":"Louisville",
    "sg:classifiers":[
        {
            "category":"Health Services",
            "subcategory":"Doctor",
            "type":"Services"
        },
        {
            "category":"Health Services",
            "subcategory":"Health Practitioner",
            "type":"Services"
        }
    ],
    "sg:phone":"+1 502 634 4424",
    "sg:postcode":"40208",
    "sg:province":"KY",
    "sg:tags":[
        "physician",
        "surgeons",
        "drug",
        "abuse",
        "medicine",
        "addiction"
    ],
    "wof:name":"Women Of Worth",
    "wof:placetype":"venue"
},
  "geometry": {"coordinates":[-85.77375000000001,38.222488],"type":"Point"}
}