{
  "type": "Feature",
  "properties": {
    "addr:full":"1613 Farmer Ave Murray KY 42071",
    "addr:housenumber":"1613",
    "addr:postcode":"42071",
    "addr:street":"Farmer Ave",
    "iso:country":"US",
    "sg:address":"1613 Farmer Ave",
    "sg:city":"Murray",
    "sg:classifiers":[
        {
            "category":"Shopping",
            "subcategory":"Catalog Store",
            "type":"Retail Goods"
        }
    ],
    "sg:phone":"+1 270 761 0268",
    "sg:postcode":"42071",
    "sg:province":"KY",
    "sg:tags":[
        "mail",
        "house"
    ],
    "wof:name":"Time 4 Change Central",
    "wof:placetype":"venue"
},
  "geometry": {"coordinates":[-88.3263,36.610196],"type":"Point"}
}