{
  "type": "Feature",
  "properties": {
    "iso:country":"US",
    "sg:address":"719 Garvey Ave",
    "sg:city":"Elsmere",
    "sg:classifiers":[
        {
            "category":"Food & Beverages",
            "subcategory":"Groceries & Convenience Stores",
            "type":"Retail Goods"
        }
    ],
    "sg:phone":"+1 859 342 0111",
    "sg:postcode":"41018",
    "sg:province":"KY",
    "sg:tags":[
        "grocer"
    ],
    "wof:name":"Elsmere Market",
    "wof:placetype":"venue"
},
  "geometry": {"coordinates":[-84.599065,39.007424],"type":"Point"}
}