{
  "type": "Feature",
  "properties": {
    "addr:full":"6801 Dixie Hwy Louisville KY 40272",
    "addr:housenumber":"6801",
    "addr:postcode":"40272",
    "addr:street":"Dixie Hwy",
    "iso:country":"US",
    "sg:address":"6801 Dixie Hwy",
    "sg:city":"Louisville",
    "sg:classifiers":[
        {
            "category":"Professional",
            "subcategory":"Accounting & Tax Preparation",
            "type":"Services"
        },
        {
            "category":"Banks & Credit Unions",
            "subcategory":"Financial Services",
            "type":"Services"
        }
    ],
    "sg:phone":"+1 502 933 3151",
    "sg:postcode":"40272",
    "sg:province":"KY",
    "sg:tags":[
        "return",
        "preparation-business",
        "taxes-consultants",
        "loan",
        "reporting",
        "representative",
        "alternative",
        "bookkeeping"
    ],
    "sg:website":"http://www.hrblock.com",
    "wof:name":"H&R Block",
    "wof:placetype":"venue"
},
  "geometry": {"coordinates":[-85.94190999999999,38.00161],"type":"Point"}
}