{
  "type": "Feature",
  "properties": {
    "iso:country":"US",
    "sg:address":"140 Midland Blvd",
    "sg:city":"Shelbyville",
    "sg:classifiers":[
        {
            "category":"Food & Beverages",
            "subcategory":"Bakery",
            "type":"Retail Goods"
        }
    ],
    "sg:phone":"+1 502 633 0333",
    "sg:postcode":"40065",
    "sg:province":"KY",
    "sg:tags":[
        "baker"
    ],
    "wof:name":"Laespiga Bakery",
    "wof:placetype":"venue"
},
  "geometry": {"coordinates":[-85.252111,38.21523],"type":"Point"}
}