{
  "type": "Feature",
  "properties": {
    "iso:country":"US",
    "sg:address":"104 Columbia Ave",
    "sg:city":"Monticello",
    "sg:classifiers":[
        {
            "category":"Professional",
            "subcategory":"Lawyer & Legal Services",
            "type":"Services"
        }
    ],
    "sg:phone":"+1 606 348 7369",
    "sg:postcode":"42633",
    "sg:province":"KY",
    "sg:tags":[
        "attorney"
    ],
    "wof:name":"Simmons & Pharis",
    "wof:placetype":"venue"
},
  "geometry": {"coordinates":[-84.849142,36.829439],"type":"Point"}
}