{
  "type": "Feature",
  "properties": {
    "iso:country":"US",
    "sg:address":"125 Towne Center Dr",
    "sg:city":"Lexington",
    "sg:classifiers":[
        {
            "category":"Restaurant",
            "type":"Food & Drink"
        },
        {
            "category":"Food & Beverages",
            "subcategory":"Groceries & Convenience Stores",
            "type":"Retail Goods"
        }
    ],
    "sg:phone":"+1 859 255 0250",
    "sg:postcode":"40511",
    "sg:province":"KY",
    "sg:tags":[
        "grill",
        "latin",
        "bar",
        "american",
        "mexican"
    ],
    "sg:website":"http://www.elmariachilex.com",
    "wof:name":"El Mariachi Mexican Restaurante & Cantina",
    "wof:placetype":"venue"
},
  "geometry": {"coordinates":[-84.530299,38.067323],"type":"Point"}
}