{
  "type": "Feature",
  "properties": {
    "addr:full":"8000 3rd Street Rd Louisville KY 40214",
    "addr:housenumber":"8000",
    "addr:postcode":"40214",
    "addr:street":"3Rd Street Rd",
    "iso:country":"US",
    "sg:address":"8000 3rd Street Rd",
    "sg:city":"Louisville",
    "sg:classifiers":[
        {
            "category":"Retail",
            "subcategory":"Auto Repair",
            "type":"Services"
        }
    ],
    "sg:phone":"+1 502 366 0388",
    "sg:postcode":"40214",
    "sg:province":"KY",
    "sg:tags":[
        "machine",
        "automobile",
        "shop"
    ],
    "wof:name":"Joe's Auto Parts & Machine Shp",
    "wof:placetype":"venue"
},
  "geometry": {"coordinates":[-85.796342,38.125617],"type":"Point"}
}