{
  "type": "Feature",
  "properties": {
    "iso:country":"US",
    "sg:address":"5560 Bethlehem Church Rd",
    "sg:city":"Wickliffe",
    "sg:classifiers":[
        {
            "category":"Organizations",
            "subcategory":"Religious Organization",
            "type":"Services"
        }
    ],
    "sg:phone":"+1 270 876 7585",
    "sg:postcode":"42087",
    "sg:province":"KY",
    "sg:tags":[
        "church"
    ],
    "wof:name":"Blandville Baptist Church",
    "wof:placetype":"venue"
},
  "geometry": {"coordinates":[-88.965732,36.943249],"type":"Point"}
}