{
  "type": "Feature",
  "properties": {
    "iso:country":"US",
    "sg:address":"3614 Toler Creek Rd",
    "sg:city":"Harold",
    "sg:classifiers":[
        {
            "category":"Organizations",
            "subcategory":"Religious Organization",
            "type":"Services"
        }
    ],
    "sg:phone":"+1 606 478 1191",
    "sg:postcode":"41635",
    "sg:province":"KY",
    "sg:tags":[
        "church"
    ],
    "wof:name":"Upper Tolar Church Of Christ",
    "wof:placetype":"venue"
},
  "geometry": {"coordinates":[-82.63699099999999,37.514337],"type":"Point"}
}