{
  "type": "Feature",
  "properties": {
    "addr:full":"226 2nd St Pikeville KY 41501",
    "addr:housenumber":"226",
    "addr:postcode":"41501",
    "addr:street":"2Nd St",
    "iso:country":"US",
    "sg:address":"226 2nd St",
    "sg:city":"Pikeville",
    "sg:classifiers":[
        {
            "category":"Professional",
            "subcategory":"Lawyer & Legal Services",
            "type":"Services"
        }
    ],
    "sg:phone":"+1 606 437 7366",
    "sg:postcode":"41501",
    "sg:province":"KY",
    "sg:tags":[
        "attorney"
    ],
    "wof:name":"Pruitt De Bourbon Law Firm",
    "wof:placetype":"venue"
},
  "geometry": {"coordinates":[-82.518625,37.479677],"type":"Point"}
}