{
  "type": "Feature",
  "properties": {
    "iso:country":"US",
    "sg:address":"117 N Main St",
    "sg:city":"Somerset",
    "sg:classifiers":[
        {
            "category":"Professional",
            "subcategory":"Lawyer & Legal Services",
            "type":"Services"
        }
    ],
    "sg:phone":"+1 606 679 9222",
    "sg:postcode":"42501",
    "sg:province":"KY",
    "sg:tags":[
        "attorney"
    ],
    "wof:name":"Gillum & Gillum",
    "wof:placetype":"venue"
},
  "geometry": {"coordinates":[-84.605388,37.094358],"type":"Point"}
}