{
  "type": "Feature",
  "properties": {
    "addr:full":"106 Arbor Ridge Dr Mayfield KY 42066",
    "addr:housenumber":"106",
    "addr:postcode":"42066",
    "addr:street":"Arbor Ridge Dr",
    "iso:country":"US",
    "sg:address":"106 Arbor Ridge Dr",
    "sg:city":"Mayfield",
    "sg:classifiers":[
        {
            "category":"Real Estate",
            "subcategory":"Developer",
            "type":"Services"
        }
    ],
    "sg:phone":"+1 270 247 9019",
    "sg:postcode":"42066",
    "sg:province":"KY",
    "sg:tags":[
        "cemetery"
    ],
    "wof:name":"Cemetary Hicks Assoc",
    "wof:placetype":"venue"
},
  "geometry": {"coordinates":[-88.660466,36.743183],"type":"Point"}
}