{
  "type": "Feature",
  "properties": {
    "iso:country":"US",
    "sg:address":"411 River Ave",
    "sg:city":"Louisa",
    "sg:phone":"+1 606 638 4197",
    "sg:postcode":"41230",
    "sg:province":"KY",
    "sg:tags":[
        "farm",
        "field",
        "crop"
    ],
    "wof:name":"Edd Preston",
    "wof:placetype":"venue"
},
  "geometry": {"coordinates":[-82.604254,38.118906],"type":"Point"}
}