{
  "type": "Feature",
  "properties": {
    "addr:full":"1405 State Hwy 518 Hustonville KY 40437",
    "addr:housenumber":"1405",
    "addr:postcode":"40437",
    "addr:street":"State Hwy 518",
    "iso:country":"US",
    "sg:address":"1405 State Hwy 518",
    "sg:city":"Hustonville",
    "sg:classifiers":[
        {
            "category":"Farming",
            "subcategory":"Livestock Farm",
            "type":"Manufacturing & Wholesale Goods"
        }
    ],
    "sg:phone":"+1 606 346 2859",
    "sg:postcode":"40437",
    "sg:province":"KY",
    "sg:tags":[
        "beef",
        "feedlot",
        "cattle"
    ],
    "wof:name":"Clark Long",
    "wof:placetype":"venue"
},
  "geometry": {"coordinates":[-84.80800000000001,37.455786],"type":"Point"}
}