{
  "type": "Feature",
  "properties": {
    "iso:country":"US",
    "sg:address":"14750 Ovil Rd",
    "sg:city":"Hopkinsville",
    "sg:classifiers":[
        {
            "category":"Recreation",
            "type":"Entertainment"
        }
    ],
    "sg:phone":"+1 270 269 2416",
    "sg:postcode":"42240",
    "sg:province":"KY",
    "sg:tags":[
        "riding",
        "academy"
    ],
    "wof:name":"Copper Canyon Ranch LLC",
    "wof:placetype":"venue"
},
  "geometry": {"coordinates":[-87.31715199999999,36.969184],"type":"Point"}
}