{
  "type": "Feature",
  "properties": {
    "iso:country":"US",
    "sg:address":"3603 W Cumberland Ave",
    "sg:city":"Middlesboro",
    "sg:classifiers":[
        {
            "category":"Health Services",
            "subcategory":"Doctor",
            "type":"Services"
        }
    ],
    "sg:phone":"+1 606 248 2213",
    "sg:postcode":"40965",
    "sg:province":"KY",
    "sg:tags":[
        "physician",
        "surgeon"
    ],
    "wof:name":"Hilton Brooks MD",
    "wof:placetype":"venue"
},
  "geometry": {"coordinates":[-83.739823,36.605187],"type":"Point"}
}