{
  "type": "Feature",
  "properties": {
    "addr:full":"704 Elm St Eminence KY 40019",
    "addr:housenumber":"704",
    "addr:postcode":"40019",
    "addr:street":"Elm St",
    "iso:country":"US",
    "sg:address":"704 Elm St",
    "sg:city":"Eminence",
    "sg:classifiers":[
        {
            "category":"Food & Beverages",
            "subcategory":"Groceries & Convenience Stores",
            "type":"Retail Goods"
        }
    ],
    "sg:phone":"+1 502 845 4457",
    "sg:postcode":"40019",
    "sg:province":"KY",
    "sg:tags":[
        "grocer"
    ],
    "wof:name":"Norm's",
    "wof:placetype":"venue"
},
  "geometry": {"coordinates":[-85.17074599999999,38.36969],"type":"Point"}
}