{
  "type": "Feature",
  "properties": {
    "iso:country":"US",
    "sg:address":"3520 Algonquin Pkwy",
    "sg:city":"Louisville",
    "sg:classifiers":[
        {
            "category":"Professional",
            "subcategory":"Business Services",
            "type":"Services"
        }
    ],
    "sg:phone":"+1 502 776 1118",
    "sg:postcode":"40211",
    "sg:province":"KY",
    "wof:name":"Heymans House of Hugs",
    "wof:placetype":"venue"
},
  "geometry": {"coordinates":[-85.816253,38.225003],"type":"Point"}
}