{
  "type": "Feature",
  "properties": {
    "iso:country":"US",
    "sg:address":"95 E Main St",
    "sg:city":"Fordsville",
    "sg:classifiers":[
        {
            "category":"Personal",
            "subcategory":"Beauty Salon",
            "type":"Services"
        }
    ],
    "sg:phone":"+1 270 276 3319",
    "sg:postcode":"42343",
    "sg:province":"KY",
    "sg:tags":[
        "shop"
    ],
    "wof:name":"Hair Studio",
    "wof:placetype":"venue"
},
  "geometry": {"coordinates":[-86.715981,37.635242],"type":"Point"}
}