{
  "type": "Feature",
  "properties": {
    "iso:country":"US",
    "sg:address":"1076 Armstrong Mill Rd",
    "sg:city":"Lexington",
    "sg:classifiers":[
        {
            "category":"Communications",
            "subcategory":"Film & Video Production",
            "type":"Services"
        }
    ],
    "sg:phone":"+1 859 233 9399",
    "sg:postcode":"40517",
    "sg:province":"KY",
    "sg:tags":[
        "motion",
        "picture"
    ],
    "wof:name":"Third I Productions",
    "wof:placetype":"venue"
},
  "geometry": {"coordinates":[-84.493582,37.982308],"type":"Point"}
}