{
  "type": "Feature",
  "properties": {
    "iso:country":"US",
    "sg:address":"443 S 4th St",
    "sg:city":"Danville",
    "sg:classifiers":[
        {
            "category":"Real Estate",
            "subcategory":"Real Estate Agent",
            "type":"Services"
        }
    ],
    "sg:phone":"+1 859 236 0021",
    "sg:postcode":"40422",
    "sg:province":"KY",
    "wof:name":"Wilson Realty & Auction Co",
    "wof:placetype":"venue"
},
  "geometry": {"coordinates":[-84.774607,37.640654],"type":"Point"}
}