{
  "type": "Feature",
  "properties": {
    "iso:country":"US",
    "sg:address":"248 N Broadway Rd",
    "sg:city":"Lexington",
    "sg:classifiers":[
        {
            "category":"Real Estate",
            "subcategory":"Real Estate Agent",
            "type":"Services"
        }
    ],
    "sg:phone":"+1 859 252 7970",
    "sg:postcode":"40507",
    "sg:province":"KY",
    "wof:name":"Kingswood Properties",
    "wof:placetype":"venue"
},
  "geometry": {"coordinates":[-84.495445,38.051954],"type":"Point"}
}