{
  "type": "Feature",
  "properties": {
    "iso:country":"US",
    "sg:address":"505 York St",
    "sg:city":"Newport",
    "sg:classifiers":[
        {
            "category":"Freight",
            "type":"Transportation"
        }
    ],
    "sg:phone":"+1 859 431 6585",
    "sg:postcode":"41071",
    "sg:province":"KY",
    "sg:tags":[
        "mover"
    ],
    "wof:name":"A-1 Approved Veteran's Moving",
    "wof:placetype":"venue"
},
  "geometry": {"coordinates":[-84.495226,39.091302],"type":"Point"}
}