{
  "type": "Feature",
  "properties": {
    "addr:full":"404 S Mayo Trl Pikeville KY 41501",
    "addr:housenumber":"404",
    "addr:postcode":"41501",
    "addr:street":"S Mayo Trl",
    "iso:country":"US",
    "sg:address":"404 S Mayo Trl",
    "sg:city":"Pikeville",
    "sg:classifiers":[
        {
            "category":"Building & Trades",
            "subcategory":"Equipment Rental",
            "type":"Services"
        }
    ],
    "sg:phone":"+1 606 432 7368",
    "sg:postcode":"41501",
    "sg:province":"KY",
    "sg:tags":[
        "leasing",
        "furniture"
    ],
    "wof:name":"A Plus Rentals",
    "wof:placetype":"venue"
},
  "geometry": {"coordinates":[-82.530469,37.466153],"type":"Point"}
}