{
  "type": "Feature",
  "properties": {
    "addr:full":"507 Frederica St Owensboro KY 42301",
    "addr:housenumber":"507",
    "addr:postcode":"42301",
    "addr:street":"Frederica St",
    "iso:country":"US",
    "sg:address":"507 Frederica St",
    "sg:city":"Owensboro",
    "sg:classifiers":[
        {
            "category":"Shopping",
            "subcategory":"Gifts & Souvenirs",
            "type":"Retail Goods"
        }
    ],
    "sg:phone":"+1 270 683 2309",
    "sg:postcode":"42301",
    "sg:province":"KY",
    "sg:tags":[
        "shop"
    ],
    "wof:name":"Trisons",
    "wof:placetype":"venue"
},
  "geometry": {"coordinates":[-87.113028,37.769904],"type":"Point"}
}