{
  "type": "Feature",
  "properties": {
    "iso:country":"US",
    "sg:address":"1069 Summerlake Dr",
    "sg:city":"Alexandria",
    "sg:classifiers":[
        {
            "category":"Building & Trades",
            "subcategory":"Construction",
            "type":"Services"
        }
    ],
    "sg:phone":"+1 859 635 4808",
    "sg:postcode":"41001",
    "sg:province":"KY",
    "sg:tags":[
        "contractor"
    ],
    "wof:name":"Maple Street Homes",
    "wof:placetype":"venue"
},
  "geometry": {"coordinates":[-84.38977,38.926727],"type":"Point"}
}