{
  "type": "Feature",
  "properties": {
    "iso:country":"US",
    "sg:address":"1150 Thornberry Dr",
    "sg:city":"Madisonville",
    "sg:classifiers":[
        {
            "category":"Insurance",
            "subcategory":"Insurance Agent",
            "type":"Services"
        }
    ],
    "sg:phone":"+1 270 821 1744",
    "sg:postcode":"42431",
    "sg:province":"KY",
    "wof:name":"State Farm Insurance",
    "wof:placetype":"venue"
},
  "geometry": {"coordinates":[-87.497434,37.346516],"type":"Point"}
}