{
  "type": "Feature",
  "properties": {
    "iso:country":"US",
    "sg:address":"237 Red Haven Ct",
    "sg:city":"Bowling Green",
    "sg:classifiers":[
        {
            "category":"Professional",
            "subcategory":"Art Services",
            "type":"Services"
        }
    ],
    "sg:phone":"+1 270 781 4070",
    "sg:postcode":"42103",
    "sg:province":"KY",
    "sg:tags":[
        "photographer"
    ],
    "sg:website":"www.roshan.com",
    "wof:name":"Roshan Foto",
    "wof:placetype":"venue"
},
  "geometry": {"coordinates":[-86.394204,36.925893],"type":"Point"}
}