{
  "type": "Feature",
  "properties": {
    "addr:full":"6618 Sun Ray Dr Louisville KY 40272",
    "addr:housenumber":"6618",
    "addr:postcode":"40272",
    "addr:street":"Sun Ray Dr",
    "iso:country":"US",
    "sg:address":"6618 Sun Ray Dr",
    "sg:city":"Louisville",
    "sg:classifiers":[
        {
            "category":"Social Services",
            "subcategory":"Child Care",
            "type":"Services"
        }
    ],
    "sg:phone":"+1 502 933 4333",
    "sg:postcode":"40272",
    "sg:province":"KY",
    "wof:name":"Na Na's Child Care",
    "wof:placetype":"venue"
},
  "geometry": {"coordinates":[-85.88388399999999,38.110011],"type":"Point"}
}