{
  "type": "Feature",
  "properties": {
    "addr:full":"1940 Harvard Dr Louisville KY 40205",
    "addr:housenumber":"1940",
    "addr:postcode":"40205",
    "addr:street":"Harvard Dr",
    "iso:country":"US",
    "sg:address":"1940 Harvard Dr",
    "sg:city":"Louisville",
    "sg:classifiers":[
        {
            "category":"Shopping",
            "subcategory":"Used Merchandise",
            "type":"Retail Goods"
        }
    ],
    "sg:phone":"+1 502 479 8362",
    "sg:postcode":"40205",
    "sg:province":"KY",
    "sg:tags":[
        "antique"
    ],
    "wof:name":"Antiques At Douglas Loop",
    "wof:placetype":"venue"
},
  "geometry": {"coordinates":[-85.69323300000001,38.224334],"type":"Point"}
}