{
  "type": "Feature",
  "properties": {
    "iso:country":"US",
    "sg:address":"501 Doran Rd",
    "sg:city":"Murray",
    "sg:classifiers":[
        {
            "category":"Education",
            "subcategory":"School",
            "type":"Public Place"
        }
    ],
    "sg:phone":"+1 270 753 5202",
    "sg:postcode":"42071",
    "sg:province":"KY",
    "wof:name":"Murray High School",
    "wof:placetype":"venue"
},
  "geometry": {"coordinates":[-88.333625,36.602971],"type":"Point"}
}