{
  "type": "Feature",
  "properties": {
    "iso:country":"US",
    "sg:address":"172 Bright Leaf Dr",
    "sg:city":"Lancaster",
    "sg:classifiers":[
        {
            "category":"Professional",
            "subcategory":"Business Services",
            "type":"Services"
        }
    ],
    "sg:phone":"+1 859 548 4326",
    "sg:postcode":"40444",
    "sg:province":"KY",
    "wof:name":"G&G Banta Enterprises Inc",
    "wof:placetype":"venue"
},
  "geometry": {"coordinates":[-84.667036,37.712697],"type":"Point"}
}