{
  "type": "Feature",
  "properties": {
    "iso:country":"US",
    "sg:address":"1958 Reed Rd",
    "sg:city":"Benton",
    "sg:classifiers":[
        {
            "category":"Travel",
            "subcategory":"Hotels & Motels",
            "type":"Entertainment"
        }
    ],
    "sg:phone":"+1 270 354 8168",
    "sg:postcode":"42025",
    "sg:province":"KY",
    "sg:tags":[
        "resort"
    ],
    "wof:name":"Cozy Cove Waterfront Resort",
    "wof:placetype":"venue"
},
  "geometry": {"coordinates":[-88.190355,36.855117],"type":"Point"}
}