{
  "type": "Feature",
  "properties": {
    "iso:country":"US",
    "sg:address":"11220 US Hwy 60",
    "sg:city":"Guston",
    "sg:classifiers":[
        {
            "category":"Freight",
            "type":"Transportation"
        }
    ],
    "sg:phone":"+1 270 547 3437",
    "sg:postcode":"40142",
    "sg:province":"KY",
    "sg:tags":[
        "local",
        "without",
        "storage",
        "trucking"
    ],
    "wof:name":"Fields Trucking",
    "wof:placetype":"venue"
},
  "geometry": {"coordinates":[-86.196721,37.882714],"type":"Point"}
}