{
  "type": "Feature",
  "properties": {
    "iso:country":"US",
    "sg:address":"1355 Pond Creek Rd",
    "sg:city":"Stone",
    "sg:classifiers":[
        {
            "category":"Shopping",
            "subcategory":"Discount & Variety Stores",
            "type":"Retail Goods"
        }
    ],
    "sg:phone":"+1 606 353 4007",
    "sg:postcode":"41567",
    "sg:province":"KY",
    "wof:name":"Carla's Red Robin Variety Shop",
    "wof:placetype":"venue"
},
  "geometry": {"coordinates":[-82.27077800000001,37.584707],"type":"Point"}
}