{
  "type": "Feature",
  "properties": {
    "iso:country":"US",
    "sg:address":"30 Big John Dr",
    "sg:city":"Greenville",
    "sg:classifiers":[
        {
            "category":"Shopping",
            "type":"Retail Goods"
        }
    ],
    "sg:phone":"+1 270 338 2710",
    "sg:postcode":"42345",
    "sg:province":"KY",
    "sg:tags":[
        "hearing",
        "equipment",
        "supply",
        "impaired"
    ],
    "wof:name":"Hearing Aid Ctr",
    "wof:placetype":"venue"
},
  "geometry": {"coordinates":[-87.178918,37.212695],"type":"Point"}
}