{
  "type": "Feature",
  "properties": {
    "addr:full":"2335 Pollard Rd Ashland KY 41101",
    "addr:housenumber":"2335",
    "addr:postcode":"41101",
    "addr:street":"Pollard Rd",
    "iso:country":"US",
    "sg:address":"2335 Pollard Rd",
    "sg:city":"Ashland",
    "sg:classifiers":[
        {
            "category":"Organizations",
            "subcategory":"Religious Organization",
            "type":"Services"
        }
    ],
    "sg:phone":"+1 606 329 8787",
    "sg:postcode":"41101",
    "sg:province":"KY",
    "sg:tags":[
        "church"
    ],
    "wof:name":"Christ United Methodist Church",
    "wof:placetype":"venue"
},
  "geometry": {"coordinates":[-82.661855,38.47357],"type":"Point"}
}