{
  "type": "Feature",
  "properties": {
    "addr:full":"891 Maple St Russell Springs KY 42642",
    "addr:housenumber":"891",
    "addr:postcode":"42642",
    "addr:street":"Maple St",
    "iso:country":"US",
    "sg:address":"891 Maple St",
    "sg:city":"Russell Springs",
    "sg:classifiers":[
        {
            "category":"Autos & Motor Vehicles",
            "subcategory":"Fuel & Gas Station",
            "type":"Retail Goods"
        }
    ],
    "sg:phone":"+1 270 866 9555",
    "sg:postcode":"42642",
    "sg:province":"KY",
    "sg:tags":[
        "oil"
    ],
    "wof:name":"Parkway Chevron",
    "wof:placetype":"venue"
},
  "geometry": {"coordinates":[-85.080349,37.055536],"type":"Point"}
}