{
  "type": "Feature",
  "properties": {
    "addr:full":"2207 Macon-Kessinger Rd Munfordville KY 42765",
    "addr:housenumber":"2207",
    "addr:postcode":"42765",
    "addr:street":"Macon-Kessinger Rd",
    "iso:country":"US",
    "sg:address":"2207 Macon-Kessinger Rd",
    "sg:city":"Munfordville",
    "sg:classifiers":[
        {
            "category":"Health Services",
            "subcategory":"Health Practitioner",
            "type":"Services"
        }
    ],
    "sg:phone":"+1 270 524 0305",
    "sg:postcode":"42765",
    "sg:province":"KY",
    "sg:tags":[
        "nutrition",
        "consultant"
    ],
    "wof:name":"Whispering Hills Herbs",
    "wof:placetype":"venue"
},
  "geometry": {"coordinates":[-85.98562,37.330919],"type":"Point"}
}