{
  "type": "Feature",
  "properties": {
    "iso:country":"US",
    "sg:address":"51 Sagebrush Ln",
    "sg:city":"Erlanger",
    "sg:classifiers":[
        {
            "category":"Professional",
            "type":"Services"
        }
    ],
    "sg:phone":"+1 859 426 0123",
    "sg:postcode":"41018",
    "sg:province":"KY",
    "sg:tags":[
        "establishment"
    ],
    "wof:name":"Dixie Area Knothole",
    "wof:placetype":"venue"
},
  "geometry": {"coordinates":[-84.576286,38.99413],"type":"Point"}
}