{
  "type": "Feature",
  "properties": {
    "addr:full":"206 Robinson Ln Georgetown KY 40324",
    "addr:housenumber":"206",
    "addr:postcode":"40324",
    "addr:street":"Robinson Ln",
    "iso:country":"US",
    "sg:address":"206 Robinson Ln",
    "sg:city":"Georgetown",
    "sg:classifiers":[
        {
            "category":"Recreation",
            "type":"Entertainment"
        }
    ],
    "sg:phone":"+1 502 863 0584",
    "sg:postcode":"40324",
    "sg:province":"KY",
    "wof:name":"Rosies Ponies",
    "wof:placetype":"venue"
},
  "geometry": {"coordinates":[-84.624106,38.209527],"type":"Point"}
}