{
  "type": "Feature",
  "properties": {
    "iso:country":"US",
    "sg:address":"747 McBrayer Dr",
    "sg:city":"Harrodsburg",
    "sg:classifiers":[
        {
            "category":"Professional",
            "type":"Services"
        }
    ],
    "sg:phone":"+1 859 733 9988",
    "sg:postcode":"40330",
    "sg:province":"KY",
    "wof:name":"Kentucky Carton Corner LLC",
    "wof:placetype":"venue"
},
  "geometry": {"coordinates":[-84.8413,37.749934],"type":"Point"}
}