{
  "type": "Feature",
  "properties": {
    "iso:country":"US",
    "sg:address":"301 Eversole Dr",
    "sg:city":"Bowling Green",
    "sg:classifiers":[
        {
            "category":"Shopping",
            "subcategory":"Computers & Home Electronics",
            "type":"Retail Goods"
        }
    ],
    "sg:phone":"+1 270 842 1155",
    "sg:postcode":"42101",
    "sg:province":"KY",
    "sg:tags":[
        "equipment",
        "electronic",
        "supply"
    ],
    "wof:name":"Davis Electronics",
    "wof:placetype":"venue"
},
  "geometry": {"coordinates":[-86.441954,37.039106],"type":"Point"}
}