{
  "type": "Feature",
  "properties": {
    "addr:full":"231 Elm St Ludlow KY 41016",
    "addr:housenumber":"231",
    "addr:postcode":"41016",
    "addr:street":"Elm St",
    "iso:country":"US",
    "sg:address":"231 Elm St",
    "sg:city":"Ludlow",
    "sg:classifiers":[
        {
            "category":"Government",
            "subcategory":"Police Station",
            "type":"Public Place"
        }
    ],
    "sg:phone":"+1 859 261 8186",
    "sg:postcode":"41016",
    "sg:province":"KY",
    "sg:tags":[
        "department"
    ],
    "wof:name":"Ludlow Police Dept",
    "wof:placetype":"venue"
},
  "geometry": {"coordinates":[-84.54762100000001,39.093868],"type":"Point"}
}