{
  "type": "Feature",
  "properties": {
    "iso:country":"US",
    "sg:address":"10316 Dixie Hwy",
    "sg:city":"Louisville",
    "sg:classifiers":[
        {
            "category":"Restaurant",
            "type":"Food & Drink"
        }
    ],
    "sg:phone":"+1 502 933 7707",
    "sg:postcode":"40272",
    "sg:province":"KY",
    "wof:name":"Mark's Feed Store Bar-B-Q & Catering",
    "wof:placetype":"venue"
},
  "geometry": {"coordinates":[-85.86827,38.105162],"type":"Point"}
}