{
  "type": "Feature",
  "properties": {
    "iso:country":"US",
    "sg:address":"6592 US Hwy 231",
    "sg:city":"Cromwell",
    "sg:classifiers":[
        {
            "category":"Building & Trades",
            "subcategory":"Plumbing",
            "type":"Services"
        }
    ],
    "sg:phone":"+1 270 274 4636",
    "sg:postcode":"42333",
    "sg:province":"KY",
    "sg:tags":[
        "septic"
    ],
    "wof:name":"Jones Septic Svc",
    "wof:placetype":"venue"
},
  "geometry": {"coordinates":[-86.777169,37.33401],"type":"Point"}
}