{
  "type": "Feature",
  "properties": {
    "iso:country":"US",
    "sg:address":"301 Happy Valley Rd",
    "sg:city":"Glasgow",
    "sg:classifiers":[
        {
            "category":"Real Estate",
            "subcategory":"Real Estate Agent",
            "type":"Services"
        }
    ],
    "sg:phone":"+1 270 651 7580",
    "sg:postcode":"42141",
    "sg:province":"KY",
    "sg:tags":[
        "business"
    ],
    "wof:name":"Armstrong Appraisal Service",
    "wof:placetype":"venue"
},
  "geometry": {"coordinates":[-85.90984899999999,37.004829],"type":"Point"}
}