{
  "type": "Feature",
  "properties": {
    "addr:full":"2103 Grimes Ave Owensboro KY 42303",
    "addr:housenumber":"2103",
    "addr:postcode":"42303",
    "addr:street":"Grimes Ave",
    "iso:country":"US",
    "sg:address":"2103 Grimes Ave",
    "sg:city":"Owensboro",
    "sg:classifiers":[
        {
            "category":"Utilities",
            "subcategory":"Refuse",
            "type":"Services"
        }
    ],
    "sg:phone":"+1 270 926 3255",
    "sg:postcode":"42303",
    "sg:province":"KY",
    "sg:tags":[
        "garbage",
        "collection"
    ],
    "sg:website":"www.bfi.com",
    "wof:name":"BFI Recycling Systems",
    "wof:placetype":"venue"
},
  "geometry": {"coordinates":[-87.081937,37.770058],"type":"Point"}
}