{
  "type": "Feature",
  "properties": {
    "iso:country":"US",
    "sg:address":"2828 McKnipp Dr",
    "sg:city":"Ashland",
    "sg:classifiers":[
        {
            "category":"Recreation",
            "type":"Entertainment"
        }
    ],
    "sg:phone":"+1 606 329 9944",
    "sg:postcode":"41102",
    "sg:province":"KY",
    "wof:name":"Willies Used Cars & Trucks",
    "wof:placetype":"venue"
},
  "geometry": {"coordinates":[-82.67363899999999,38.442632],"type":"Point"}
}