{
  "type": "Feature",
  "properties": {
    "addr:full":"8311 US Hwy 42 Florence KY 41042",
    "addr:housenumber":"8311",
    "addr:postcode":"41042",
    "addr:street":"Us Hwy 42",
    "iso:country":"US",
    "sg:address":"8311 US Hwy 42",
    "sg:city":"Florence",
    "sg:classifiers":[
        {
            "category":"Professional",
            "type":"Services"
        }
    ],
    "sg:phone":"+1 859 647 7913",
    "sg:postcode":"41042",
    "sg:province":"KY",
    "sg:tags":[
        "establishment"
    ],
    "wof:name":"Cableview Comunicatns",
    "wof:placetype":"venue"
},
  "geometry": {"coordinates":[-84.65422599999999,38.979122],"type":"Point"}
}