{
  "type": "Feature",
  "properties": {
    "addr:full":"6128 State Hwy 339 W Wingo KY 42088",
    "addr:housenumber":"6128",
    "addr:postcode":"42088",
    "addr:street":"State Hwy 339 W Wingo",
    "iso:country":"US",
    "sg:address":"6128 State Hwy 339 W",
    "sg:city":"Wingo",
    "sg:classifiers":[
        {
            "category":"Professional",
            "subcategory":"Business Services",
            "type":"Services"
        }
    ],
    "sg:phone":"+1 270 376 2992",
    "sg:postcode":"42088",
    "sg:province":"KY",
    "sg:tags":[
        "appraiser"
    ],
    "wof:name":"Bunch Brothers Auction & Rlty",
    "wof:placetype":"venue"
},
  "geometry": {"coordinates":[-88.73436599999999,36.6425],"type":"Point"}
}