{
  "type": "Feature",
  "properties": {
    "iso:country":"US",
    "sg:address":"408 Center St",
    "sg:city":"Henderson",
    "sg:classifiers":[
        {
            "category":"Health Services",
            "subcategory":"Doctor",
            "type":"Services"
        }
    ],
    "sg:phone":"+1 270 827 1263",
    "sg:postcode":"42420",
    "sg:province":"KY",
    "sg:tags":[
        "dentist"
    ],
    "wof:name":"Jay P Beard DDS",
    "wof:placetype":"venue"
},
  "geometry": {"coordinates":[-87.589883,37.837104],"type":"Point"}
}