{
  "type": "Feature",
  "properties": {
    "addr:full":"3401 Nicholasville Rd Lexington KY 40503",
    "addr:housenumber":"3401",
    "addr:postcode":"40503",
    "addr:street":"Nicholasville Rd",
    "iso:country":"US",
    "sg:address":"3401 Nicholasville Rd",
    "sg:city":"Lexington",
    "sg:classifiers":[
        {
            "category":"Shopping",
            "subcategory":"Department Store",
            "type":"Retail Goods"
        }
    ],
    "sg:phone":"+1 859 273 2525",
    "sg:postcode":"40503",
    "sg:province":"KY",
    "wof:name":"J C Penney Co",
    "wof:placetype":"venue"
},
  "geometry": {"coordinates":[-84.52438600000001,37.989923],"type":"Point"}
}