{
  "type": "Feature",
  "properties": {
    "iso:country":"US",
    "sg:address":"8179 Dixie Hwy",
    "sg:city":"Florence",
    "sg:classifiers":[
        {
            "category":"Building & Trades",
            "subcategory":"Electrical",
            "type":"Services"
        }
    ],
    "sg:phone":"+1 859 283 2350",
    "sg:postcode":"41042",
    "sg:province":"KY",
    "sg:tags":[
        "electric",
        "contractor"
    ],
    "wof:name":"Port Of Cinti",
    "wof:placetype":"venue"
},
  "geometry": {"coordinates":[-84.61559,38.969939],"type":"Point"}
}