{
  "type": "Feature",
  "properties": {
    "iso:country":"US",
    "sg:address":"4560 13th St",
    "sg:city":"Ashland",
    "sg:classifiers":[
        {
            "category":"Autos & Motor Vehicles",
            "subcategory":"Auto Supplies",
            "type":"Retail Goods"
        }
    ],
    "sg:phone":"+1 606 329 2886",
    "sg:postcode":"41102",
    "sg:province":"KY",
    "sg:tags":[
        "tire"
    ],
    "wof:name":"Summit Wholesale Tire",
    "wof:placetype":"venue"
},
  "geometry": {"coordinates":[-82.68058600000001,38.44563],"type":"Point"}
}