{
  "type": "Feature",
  "properties": {
    "iso:country":"US",
    "sg:address":"4200 Outer Loop",
    "sg:city":"Louisville",
    "sg:classifiers":[
        {
            "category":"Restaurant",
            "type":"Food & Drink"
        }
    ],
    "sg:phone":"+1 502 964 0920",
    "sg:postcode":"40219",
    "sg:province":"KY",
    "wof:name":"Mr Gatti's Pizza",
    "wof:placetype":"venue"
},
  "geometry": {"coordinates":[-85.68162100000001,38.138189],"type":"Point"}
}