{
  "type": "Feature",
  "properties": {
    "iso:country":"US",
    "sg:address":"324 Eastern Ave",
    "sg:city":"Elsmere",
    "sg:classifiers":[
        {
            "category":"Building & Trades",
            "subcategory":"Landscaping Services",
            "type":"Services"
        }
    ],
    "sg:phone":"+1 859 760 5281",
    "sg:postcode":"41018",
    "sg:province":"KY",
    "sg:tags":[
        "landscape",
        "contractor"
    ],
    "wof:name":"Ike's Lawncare Svc",
    "wof:placetype":"venue"
},
  "geometry": {"coordinates":[-84.607607,38.997579],"type":"Point"}
}