{
  "type": "Feature",
  "properties": {
    "iso:country":"US",
    "sg:address":"320 Robin Rd",
    "sg:city":"Henderson",
    "sg:classifiers":[
        {
            "category":"Shopping",
            "type":"Retail Goods"
        }
    ],
    "sg:phone":"+1 270 827 1799",
    "sg:postcode":"42420",
    "sg:province":"KY",
    "sg:tags":[
        "hearing",
        "equipment",
        "supply",
        "impaired"
    ],
    "wof:name":"Beltone Hearing Aid Ctr",
    "wof:placetype":"venue"
},
  "geometry": {"coordinates":[-87.572935,37.86916],"type":"Point"}
}