{
  "type": "Feature",
  "properties": {
    "addr:full":"2024 S 9th St Ironton OH 45638",
    "addr:housenumber":"2024",
    "addr:postcode":"45638",
    "addr:street":"S 9Th St",
    "iso:country":"US",
    "sg:address":"2024 S 9th St",
    "sg:city":"Ironton",
    "sg:classifiers":[
        {
            "category":"Shopping",
            "subcategory":"Pharmacy",
            "type":"Retail Goods"
        }
    ],
    "sg:phone":"+1 740 532 2546",
    "sg:postcode":"45638",
    "sg:province":"OH",
    "wof:name":"Staley's Pharmacy",
    "wof:placetype":"venue"
},
  "geometry": {"coordinates":[-82.66596800000001,38.522124],"type":"Point"}
}