{
  "type": "Feature",
  "properties": {
    "addr:full":"132 Jackson Trl Glasgow KY 42141",
    "addr:housenumber":"132",
    "addr:postcode":"42141",
    "addr:street":"Jackson Trl",
    "iso:country":"US",
    "sg:address":"132 Jackson Trl",
    "sg:city":"Glasgow",
    "sg:classifiers":[
        {
            "category":"Bars & Pubs",
            "type":"Food & Drink"
        }
    ],
    "sg:phone":"+1 270 646 2287",
    "sg:postcode":"42141",
    "sg:province":"KY",
    "sg:tags":[
        "drinking"
    ],
    "wof:name":"Up Up and Away Balloons",
    "wof:placetype":"venue"
},
  "geometry": {"coordinates":[-86.003274,36.920259],"type":"Point"}
}