{
  "type": "Feature",
  "properties": {
    "addr:full":"2287 State Hwy 519 Morehead KY 40351",
    "addr:housenumber":"2287",
    "addr:postcode":"40351",
    "addr:street":"State Hwy 519",
    "iso:country":"US",
    "sg:address":"2287 State Hwy 519",
    "sg:city":"Morehead",
    "sg:classifiers":[
        {
            "category":"Manufacturing",
            "subcategory":"Petroleum Products",
            "type":"Manufacturing & Wholesale Goods"
        }
    ],
    "sg:phone":"+1 606 784 4097",
    "sg:postcode":"40351",
    "sg:province":"KY",
    "sg:tags":[
        "asphalt"
    ],
    "wof:name":"Hinkle Contracting Corp",
    "wof:placetype":"venue"
},
  "geometry": {"coordinates":[-83.419856,38.143356],"type":"Point"}
}