{
  "type": "Feature",
  "properties": {
    "iso:country":"US",
    "sg:address":"301 N Columbia Ave",
    "sg:city":"Campbellsville",
    "sg:classifiers":[
        {
            "category":"Health Services",
            "subcategory":"Doctor",
            "type":"Services"
        }
    ],
    "sg:phone":"+1 270 789 2471",
    "sg:postcode":"42718",
    "sg:province":"KY",
    "sg:tags":[
        "physician",
        "surgeon"
    ],
    "wof:name":"James R Angel MD",
    "wof:placetype":"venue"
},
  "geometry": {"coordinates":[-85.34617799999999,37.341968],"type":"Point"}
}