{
  "type": "Feature",
  "properties": {
    "iso:country":"US",
    "sg:address":"9011 Pine Lake Dr",
    "sg:city":"Louisville",
    "sg:classifiers":[
        {
            "category":"Real Estate",
            "subcategory":"Real Estate Services",
            "type":"Services"
        }
    ],
    "sg:phone":"+1 502 499 1281",
    "sg:postcode":"40220",
    "sg:province":"KY",
    "sg:tags":[
        "abstract",
        "title"
    ],
    "wof:name":"John M Shcroering",
    "wof:placetype":"venue"
},
  "geometry": {"coordinates":[-85.59153499999999,38.209043],"type":"Point"}
}