{
  "type": "Feature",
  "properties": {
    "addr:full":"194 N Hurstbourne Pkwy Louisville KY 40222",
    "addr:housenumber":"194",
    "addr:postcode":"40222",
    "addr:street":"N Hurstbourne Pkwy",
    "iso:country":"US",
    "sg:address":"194 N Hurstbourne Pkwy",
    "sg:city":"Louisville",
    "sg:classifiers":[
        {
            "category":"Shopping",
            "subcategory":"Clothing, Apparel, & Fashions",
            "type":"Retail Goods"
        }
    ],
    "sg:phone":"+1 502 423 9445",
    "sg:postcode":"40222",
    "sg:province":"KY",
    "sg:website":"www.talbots.com",
    "wof:name":"Talbots",
    "wof:placetype":"venue"
},
  "geometry": {"coordinates":[-85.578872,38.250822],"type":"Point"}
}