{
  "type": "Feature",
  "properties": {
    "addr:full":"237 Industry Pkwy Nicholasville KY 40356",
    "addr:housenumber":"237",
    "addr:postcode":"40356",
    "addr:street":"Industry Pkwy",
    "iso:country":"US",
    "sg:address":"237 Industry Pkwy",
    "sg:city":"Nicholasville",
    "sg:classifiers":[
        {
            "category":"Retail",
            "subcategory":"Auto Repair",
            "type":"Services"
        }
    ],
    "sg:phone":"+1 859 881 1899",
    "sg:postcode":"40356",
    "sg:province":"KY",
    "sg:tags":[
        "automobile",
        "top",
        "upholstery"
    ],
    "wof:name":"G T Customs",
    "wof:placetype":"venue"
},
  "geometry": {"coordinates":[-84.53966699999999,37.935424],"type":"Point"}
}