{
  "type": "Feature",
  "properties": {
    "iso:country":"US",
    "sg:address":"1101 Center St",
    "sg:city":"Catlettsburg",
    "sg:classifiers":[
        {
            "category":"Home & Garden",
            "subcategory":"Home Furnishings",
            "type":"Retail Goods"
        }
    ],
    "sg:phone":"+1 606 739 8871",
    "sg:postcode":"41129",
    "sg:province":"KY",
    "sg:tags":[
        "repair",
        "sporting",
        "g"
    ],
    "wof:name":"Tackle Shak",
    "wof:placetype":"venue"
},
  "geometry": {"coordinates":[-82.607395,38.436268],"type":"Point"}
}