{
  "type": "Feature",
  "properties": {
    "iso:country":"US",
    "sg:address":"4951 Jennie Kate Ln",
    "sg:city":"Lexington",
    "sg:classifiers":[
        {
            "category":"Travel",
            "subcategory":"Hotels & Motels",
            "type":"Entertainment"
        },
        {
            "category":"Travel",
            "subcategory":"Bed & Breakfast",
            "type":"Entertainment"
        }
    ],
    "sg:phone":"+1 859 226 9520",
    "sg:postcode":"40510",
    "sg:province":"KY",
    "sg:tags":[
        "inn",
        "lodging"
    ],
    "wof:name":"Swanns Nest",
    "wof:placetype":"venue"
},
  "geometry": {"coordinates":[-84.628317,38.052335],"type":"Point"}
}