{
  "type": "Feature",
  "properties": {
    "addr:full":"613 Clifford Dr Elizabethtown KY 42701",
    "addr:housenumber":"613",
    "addr:postcode":"42701",
    "addr:street":"Clifford Dr",
    "iso:country":"US",
    "sg:address":"613 Clifford Dr",
    "sg:city":"Elizabethtown",
    "sg:classifiers":[
        {
            "category":"Shopping",
            "subcategory":"Catalog Store",
            "type":"Retail Goods"
        }
    ],
    "sg:phone":"+1 270 765 6711",
    "sg:postcode":"42701",
    "sg:province":"KY",
    "sg:tags":[
        "mail",
        "house"
    ],
    "wof:name":"Orville Underwood",
    "wof:placetype":"venue"
},
  "geometry": {"coordinates":[-85.878517,37.704805],"type":"Point"}
}