{
  "type": "Feature",
  "properties": {
    "iso:country":"US",
    "sg:address":"118 N Fort Thomas Ave",
    "sg:city":"Fort Thomas",
    "sg:classifiers":[
        {
            "category":"Building & Trades",
            "subcategory":"Construction",
            "type":"Services"
        },
        {
            "category":"Home & Garden",
            "subcategory":"Furniture",
            "type":"Retail Goods"
        }
    ],
    "sg:phone":"+1 859 781 9600",
    "sg:postcode":"41075",
    "sg:province":"KY",
    "sg:tags":[
        "interior",
        "design",
        "store"
    ],
    "wof:name":"Three French Hens",
    "wof:placetype":"venue"
},
  "geometry": {"coordinates":[-84.44879899999999,39.0807],"type":"Point"}
}