{
  "type": "Feature",
  "properties": {
    "addr:full":"5022 State Hwy 93 Eddyville KY 42038",
    "addr:housenumber":"5022",
    "addr:postcode":"42038",
    "addr:street":"State Hwy 93",
    "iso:country":"US",
    "sg:address":"5022 State Hwy 93",
    "sg:city":"Eddyville",
    "sg:classifiers":[
        {
            "category":"Organizations",
            "subcategory":"Religious Organization",
            "type":"Services"
        }
    ],
    "sg:phone":"+1 270 388 9425",
    "sg:postcode":"42038",
    "sg:province":"KY",
    "sg:tags":[
        "church"
    ],
    "wof:name":"Pleasant Hill Baptist Church",
    "wof:placetype":"venue"
},
  "geometry": {"coordinates":[-88.032242,37.047347],"type":"Point"}
}