{
  "type": "Feature",
  "properties": {
    "addr:full":"636 Sayre Ave Lexington KY 40508",
    "addr:housenumber":"636",
    "addr:postcode":"40508",
    "addr:street":"Sayre Ave",
    "iso:country":"US",
    "sg:address":"636 Sayre Ave",
    "sg:city":"Lexington",
    "sg:classifiers":[
        {
            "category":"Health Services",
            "subcategory":"Health Practitioner",
            "type":"Services"
        }
    ],
    "sg:phone":"+1 859 225 1476",
    "sg:postcode":"40508",
    "sg:province":"KY",
    "sg:tags":[
        "psychologist"
    ],
    "wof:name":"Marilyn B Robie PHD",
    "wof:placetype":"venue"
},
  "geometry": {"coordinates":[-84.48609999999999,38.038326],"type":"Point"}
}