{
  "type": "Feature",
  "properties": {
    "iso:country":"US",
    "sg:address":"185 Moriah Rd",
    "sg:city":"London",
    "sg:classifiers":[
        {
            "category":"Retail",
            "subcategory":"Repair Shop",
            "type":"Services"
        }
    ],
    "sg:phone":"+1 606 877 5477",
    "sg:postcode":"40741",
    "sg:province":"KY",
    "sg:tags":[
        "equipment"
    ],
    "wof:name":"Laurel Restaurant Equipment",
    "wof:placetype":"venue"
},
  "geometry": {"coordinates":[-84.190533,37.168595],"type":"Point"}
}