{
  "type": "Feature",
  "properties": {
    "iso:country":"US",
    "sg:address":"122 Robinson Dr",
    "sg:city":"Paintsville",
    "sg:classifiers":[
        {
            "category":"Retail",
            "subcategory":"Auto Repair",
            "type":"Services"
        }
    ],
    "sg:phone":"+1 606 297 1234",
    "sg:postcode":"41240",
    "sg:province":"KY",
    "sg:tags":[
        "repairing",
        "automobile"
    ],
    "wof:name":"S & S Auto Body Shop",
    "wof:placetype":"venue"
},
  "geometry": {"coordinates":[-82.82701,37.841902],"type":"Point"}
}