{
  "type": "Feature",
  "properties": {
    "addr:full":"202 E Stephen Foster Ave Bardstown KY 40004",
    "addr:housenumber":"202",
    "addr:postcode":"40004",
    "addr:street":"E Stephen Foster Ave",
    "iso:country":"US",
    "sg:address":"202 E Stephen Foster Ave",
    "sg:city":"Bardstown",
    "sg:classifiers":[
        {
            "category":"Professional",
            "subcategory":"Lawyer & Legal Services",
            "type":"Services"
        }
    ],
    "sg:phone":"+1 502 348 4466",
    "sg:postcode":"40004",
    "sg:province":"KY",
    "sg:tags":[
        "attorney"
    ],
    "wof:name":"Kelley Hite & Pottinger",
    "wof:placetype":"venue"
},
  "geometry": {"coordinates":[-85.46510000000001,37.808832],"type":"Point"}
}