{
  "type": "Feature",
  "properties": {
    "iso:country":"US",
    "sg:address":"10 Golden Pond Loop",
    "sg:city":"Campbellsville",
    "sg:classifiers":[
        {
            "category":"Home & Garden",
            "subcategory":"Carpets & Floor Coverings",
            "type":"Retail Goods"
        }
    ],
    "sg:phone":"+1 270 465 8372",
    "sg:postcode":"42718",
    "sg:province":"KY",
    "sg:tags":[
        "laying",
        "contractor"
    ],
    "wof:name":"Riggs Tile Inc",
    "wof:placetype":"venue"
},
  "geometry": {"coordinates":[-85.39232199999999,37.323961],"type":"Point"}
}