{
  "type": "Feature",
  "properties": {
    "iso:country":"US",
    "sg:address":"732 Southwestern Pkwy",
    "sg:city":"Louisville",
    "sg:classifiers":[
        {
            "category":"Professional",
            "subcategory":"Business Services",
            "type":"Services"
        }
    ],
    "sg:phone":"+1 502 778 5817",
    "sg:postcode":"40211",
    "sg:province":"KY",
    "wof:name":"A Better Home Inspection",
    "wof:placetype":"venue"
},
  "geometry": {"coordinates":[-85.82957399999999,38.248741],"type":"Point"}
}