{
  "type": "Feature",
  "properties": {
    "iso:country":"US",
    "sg:address":"307 Carr St",
    "sg:city":"Fulton",
    "sg:classifiers":[
        {
            "category":"Shopping",
            "subcategory":"Gifts & Souvenirs",
            "type":"Retail Goods"
        }
    ],
    "sg:phone":"+1 270 472 1059",
    "sg:postcode":"42041",
    "sg:province":"KY",
    "sg:tags":[
        "shop"
    ],
    "wof:name":"Ivy Depot",
    "wof:placetype":"venue"
},
  "geometry": {"coordinates":[-88.87682599999999,36.507081],"type":"Point"}
}