{
  "type": "Feature",
  "properties": {
    "iso:country":"US",
    "sg:address":"1104 Dixie Hwy S",
    "sg:city":"Elizabethtown",
    "sg:classifiers":[
        {
            "category":"Autos & Motor Vehicles",
            "subcategory":"Automobile Sales",
            "type":"Retail Goods"
        }
    ],
    "sg:phone":"+1 270 737 2181",
    "sg:postcode":"42701",
    "sg:province":"KY",
    "sg:tags":[
        "car",
        "dealer"
    ],
    "wof:name":"Swope Toyota",
    "wof:placetype":"venue"
},
  "geometry": {"coordinates":[-85.877713,37.715304],"type":"Point"}
}