{
  "type": "Feature",
  "properties": {
    "iso:country":"US",
    "sg:address":"301 E Main St",
    "sg:city":"Morehead",
    "sg:classifiers":[
        {
            "category":"Health Services",
            "subcategory":"Doctor",
            "type":"Services"
        }
    ],
    "sg:phone":"+1 606 784 8124",
    "sg:postcode":"40351",
    "sg:province":"KY",
    "sg:tags":[
        "physician",
        "surgeon"
    ],
    "wof:name":"Donald E Blair MD",
    "wof:placetype":"venue"
},
  "geometry": {"coordinates":[-83.432486,38.185133],"type":"Point"}
}