{
  "type": "Feature",
  "properties": {
    "addr:full":"10127 State Hwy 405 Maceo KY 42355",
    "addr:housenumber":"10127",
    "addr:postcode":"42355",
    "addr:street":"State Hwy 405 Maceo",
    "iso:country":"US",
    "sg:address":"10127 State Hwy 405",
    "sg:city":"Maceo",
    "sg:classifiers":[
        {
            "category":"Restaurant",
            "type":"Food & Drink"
        }
    ],
    "sg:phone":"+1 270 264 5029",
    "sg:postcode":"42355",
    "sg:province":"KY",
    "wof:name":"Maceo Market",
    "wof:placetype":"venue"
},
  "geometry": {"coordinates":[-86.99493200000001,37.864261],"type":"Point"}
}