{
  "type": "Feature",
  "properties": {
    "addr:full":"805 S Main St Edmonton KY 42129",
    "addr:housenumber":"805",
    "addr:postcode":"42129",
    "addr:street":"S Main St",
    "iso:country":"US",
    "sg:address":"805 S Main St",
    "sg:city":"Edmonton",
    "sg:classifiers":[
        {
            "category":"Shopping",
            "subcategory":"Used Merchandise",
            "type":"Retail Goods"
        }
    ],
    "sg:phone":"+1 270 432 2354",
    "sg:postcode":"42129",
    "sg:province":"KY",
    "sg:tags":[
        "shop",
        "thrift"
    ],
    "wof:name":"Fantastic Finds",
    "wof:placetype":"venue"
},
  "geometry": {"coordinates":[-85.609004,36.969128],"type":"Point"}
}