{
  "type": "Feature",
  "properties": {
    "iso:country":"US",
    "sg:address":"667 E New Circle Rd",
    "sg:city":"Lexington",
    "sg:classifiers":[
        {
            "category":"Autos & Motor Vehicles",
            "subcategory":"Auto Supplies",
            "type":"Retail Goods"
        }
    ],
    "sg:phone":"+1 859 294 9509",
    "sg:postcode":"40505",
    "sg:province":"KY",
    "sg:tags":[
        "automobile",
        "parts"
    ],
    "wof:name":"NAPA Auto & Truck Parts",
    "wof:placetype":"venue"
},
  "geometry": {"coordinates":[-84.454014,38.048133],"type":"Point"}
}