{
  "type": "Feature",
  "properties": {
    "addr:full":"226 Main St Florence KY 41042",
    "addr:housenumber":"226",
    "addr:postcode":"41042",
    "addr:street":"Main St",
    "iso:country":"US",
    "sg:address":"226 Main St",
    "sg:city":"Florence",
    "sg:classifiers":[
        {
            "category":"Professional",
            "subcategory":"Lawyer & Legal Services",
            "type":"Services"
        }
    ],
    "sg:phone":"+1 859 371 3600",
    "sg:postcode":"41042",
    "sg:province":"KY",
    "sg:tags":[
        "personal",
        "injury"
    ],
    "wof:name":"Langendorf Gail M Atty",
    "wof:placetype":"venue"
},
  "geometry": {"coordinates":[-84.62460299999999,39.003201],"type":"Point"}
}