{
  "type": "Feature",
  "properties": {
    "iso:country":"US",
    "sg:address":"779 Hamlin Chapel Rd",
    "sg:city":"Hartford",
    "sg:classifiers":[
        {
            "category":"Farming",
            "subcategory":"Farm",
            "type":"Manufacturing & Wholesale Goods"
        }
    ],
    "sg:phone":"+1 270 298 9524",
    "sg:postcode":"42347",
    "sg:province":"KY",
    "wof:name":"S & A Hayse Farm",
    "wof:placetype":"venue"
},
  "geometry": {"coordinates":[-86.85690200000001,37.472944],"type":"Point"}
}