{
  "type": "Feature",
  "properties": {
    "iso:country":"US",
    "sg:address":"118 Taylorsville Rd",
    "sg:city":"Taylorsville",
    "sg:classifiers":[
        {
            "category":"Professional",
            "subcategory":"Lawyer & Legal Services",
            "type":"Services"
        }
    ],
    "sg:phone":"+1 502 477 2400",
    "sg:postcode":"40071",
    "sg:province":"KY",
    "sg:tags":[
        "attorney"
    ],
    "wof:name":"Kenneth S Jones Law Office",
    "wof:placetype":"venue"
},
  "geometry": {"coordinates":[-85.341067,38.033648],"type":"Point"}
}