{
  "type": "Feature",
  "properties": {
    "iso:country":"US",
    "sg:address":"5366 New Cut Rd",
    "sg:city":"Louisville",
    "sg:classifiers":[
        {
            "category":"Restaurant",
            "type":"Food & Drink"
        }
    ],
    "sg:menulink":"http://www.allmenus.com/ky/louisville-south/79678-pizza-hut/menu/",
    "sg:phone":"+1 502 363 2608",
    "sg:postcode":"40214",
    "sg:province":"KY",
    "sg:tags":[
        "american",
        "pizza"
    ],
    "wof:name":"Pizza Hut",
    "wof:placetype":"venue"
},
  "geometry": {"coordinates":[-85.777038,38.153434],"type":"Point"}
}