{
  "type": "Feature",
  "properties": {
    "addr:full":"4508 Shepherdsville Rd Louisville KY 40218",
    "addr:housenumber":"4508",
    "addr:postcode":"40218",
    "addr:street":"Shepherdsville Rd",
    "iso:country":"US",
    "sg:address":"4508 Shepherdsville Rd",
    "sg:city":"Louisville",
    "sg:classifiers":[
        {
            "category":"Manufacturing",
            "subcategory":"Printing",
            "type":"Manufacturing & Wholesale Goods"
        }
    ],
    "sg:phone":"+1 502 635 7061",
    "sg:postcode":"40218",
    "sg:province":"KY",
    "sg:tags":[
        "printer"
    ],
    "wof:name":"Fetter Printing Co",
    "wof:placetype":"venue"
},
  "geometry": {"coordinates":[-85.659499,38.180047],"type":"Point"}
}