{
  "type": "Feature",
  "properties": {
    "iso:country":"US",
    "sg:address":"241 Hickory Ridge Rd",
    "sg:city":"Carlisle",
    "sg:classifiers":[
        {
            "category":"Retail",
            "subcategory":"Auto Repair",
            "type":"Services"
        }
    ],
    "sg:phone":"+1 859 289 3113",
    "sg:postcode":"40311",
    "sg:province":"KY",
    "sg:tags":[
        "repairing",
        "automobile"
    ],
    "wof:name":"Hickory Ridge Auto Repair",
    "wof:placetype":"venue"
},
  "geometry": {"coordinates":[-84.014681,38.345459],"type":"Point"}
}