{
  "type": "Feature",
  "properties": {
    "iso:country":"US",
    "sg:address":"2704 S Pope Lick Rd",
    "sg:city":"Louisville",
    "sg:classifiers":[
        {
            "category":"Wholesale",
            "subcategory":"Books, Periodicals, & Newspapers",
            "type":"Manufacturing & Wholesale Goods"
        }
    ],
    "sg:phone":"+1 502 245 8983",
    "sg:postcode":"40299",
    "sg:province":"KY",
    "sg:tags":[
        "news",
        "dealers-wholesale"
    ],
    "wof:name":"I Am Publications Inc",
    "wof:placetype":"venue"
},
  "geometry": {"coordinates":[-85.48942,38.200355],"type":"Point"}
}