{
  "type": "Feature",
  "properties": {
    "iso:country":"US",
    "sg:address":"421 Etter Dr",
    "sg:city":"Nicholasville",
    "sg:classifiers":[
        {
            "category":"Autos & Motor Vehicles",
            "subcategory":"Automobile Sales",
            "type":"Retail Goods"
        }
    ],
    "sg:phone":"+1 859 887 0333",
    "sg:postcode":"40356",
    "sg:province":"KY",
    "sg:tags":[
        "car",
        "dealer"
    ],
    "wof:name":"Auto Credit Of Kentucky",
    "wof:placetype":"venue"
},
  "geometry": {"coordinates":[-84.589077,37.888618],"type":"Point"}
}