{
  "type": "Feature",
  "properties": {
    "addr:full":"1360 Stewarts Creek Rd Lebanon KY 40033",
    "addr:housenumber":"1360",
    "addr:postcode":"40033",
    "addr:street":"Stewarts Creek Rd",
    "iso:country":"US",
    "sg:address":"1360 Stewarts Creek Rd",
    "sg:city":"Lebanon",
    "sg:classifiers":[
        {
            "category":"Building & Trades",
            "subcategory":"Construction",
            "type":"Services"
        }
    ],
    "sg:phone":"+1 270 692 2134",
    "sg:postcode":"40033",
    "sg:province":"KY",
    "sg:tags":[
        "house"
    ],
    "wof:name":"Burdette Construction",
    "wof:placetype":"venue"
},
  "geometry": {"coordinates":[-85.35552,37.538458],"type":"Point"}
}