{
  "type": "Feature",
  "properties": {
    "iso:country":"US",
    "sg:address":"1506 Oxford Dr",
    "sg:city":"Murray",
    "sg:classifiers":[
        {
            "category":"Professional",
            "subcategory":"Management & Consulting",
            "type":"Services"
        }
    ],
    "sg:phone":"+1 270 753 7716",
    "sg:postcode":"42071",
    "sg:province":"KY",
    "sg:tags":[
        "business"
    ],
    "wof:name":"Stepto Enterprises",
    "wof:placetype":"venue"
},
  "geometry": {"coordinates":[-88.323058,36.587981],"type":"Point"}
}