{
  "type": "Feature",
  "properties": {
    "iso:country":"US",
    "sg:address":"2332 W Broadway",
    "sg:city":"Louisville",
    "sg:classifiers":[
        {
            "category":"Personal",
            "subcategory":"Beauty Salon",
            "type":"Services"
        }
    ],
    "sg:phone":"+1 502 772 1004",
    "sg:postcode":"40211",
    "sg:province":"KY",
    "wof:name":"Hair Way",
    "wof:placetype":"venue"
},
  "geometry": {"coordinates":[-85.791135,38.249239],"type":"Point"}
}