{
  "type": "Feature",
  "properties": {
    "iso:country":"US",
    "sg:address":"6000 Brownsboro Park Blvd",
    "sg:city":"St Matthews",
    "sg:classifiers":[
        {
            "category":"Health Services",
            "subcategory":"Doctor",
            "type":"Services"
        }
    ],
    "sg:phone":"+1 502 899 7716",
    "sg:postcode":"40207",
    "sg:province":"KY",
    "sg:tags":[
        "physician",
        "surgeon"
    ],
    "wof:name":"Louisville Emergency Medicine",
    "wof:placetype":"venue"
},
  "geometry": {"coordinates":[-85.639786,38.281887],"type":"Point"}
}