{
  "type": "Feature",
  "properties": {
    "iso:country":"US",
    "sg:address":"199 E Lincoln Trail Blvd",
    "sg:city":"Radcliff",
    "sg:classifiers":[
        {
            "category":"Sports & Exercise",
            "subcategory":"Gym",
            "type":"Entertainment"
        }
    ],
    "sg:phone":"+1 270 351 2296",
    "sg:postcode":"40160",
    "sg:province":"KY",
    "sg:tags":[
        "club",
        "health",
        "studio",
        "gymnasium"
    ],
    "wof:name":"Curves For Women",
    "wof:placetype":"venue"
},
  "geometry": {"coordinates":[-85.936083,37.84076],"type":"Point"}
}