{
  "type": "Feature",
  "properties": {
    "iso:country":"US",
    "sg:address":"3809 Schneidman Rd",
    "sg:city":"Paducah",
    "sg:classifiers":[
        {
            "category":"Wholesale",
            "subcategory":"Toys & Hobbies",
            "type":"Manufacturing & Wholesale Goods"
        }
    ],
    "sg:phone":"+1 270 442 0000",
    "sg:postcode":"42003",
    "sg:province":"KY",
    "wof:name":"CND Inc",
    "wof:placetype":"venue"
},
  "geometry": {"coordinates":[-88.61921100000001,37.052156],"type":"Point"}
}