{
  "type": "Feature",
  "properties": {
    "addr:full":"6540 Outer Loop Louisville KY 40228",
    "addr:housenumber":"6540",
    "addr:postcode":"40228",
    "addr:street":"Outer Loop",
    "iso:country":"US",
    "sg:address":"6540 Outer Loop",
    "sg:city":"Louisville",
    "sg:classifiers":[
        {
            "category":"Personal",
            "subcategory":"Beauty Salon",
            "type":"Services"
        }
    ],
    "sg:phone":"+1 502 968 9411",
    "sg:postcode":"40228",
    "sg:province":"KY",
    "sg:tags":[
        "treatment",
        "skin"
    ],
    "wof:name":"Susan Skin Care & Day Spa",
    "wof:placetype":"venue"
},
  "geometry": {"coordinates":[-85.635153,38.137562],"type":"Point"}
}