{
  "type": "Feature",
  "properties": {
    "addr:full":"2853 Fort Campbell Blvd Clarksville KY 37042",
    "addr:housenumber":"2853",
    "addr:postcode":"37042",
    "addr:street":"Fort Campbell Blvd",
    "iso:country":"US",
    "sg:address":"2853 Fort Campbell Blvd",
    "sg:city":"Clarksville",
    "sg:classifiers":[
        {
            "category":"Retail",
            "subcategory":"Self-service Laundry",
            "type":"Services"
        }
    ],
    "sg:phone":"+1 931 431 4264",
    "sg:postcode":"37042",
    "sg:province":"KY",
    "wof:name":"Wash House Laundry",
    "wof:placetype":"venue"
},
  "geometry": {"coordinates":[-87.43344399999999,36.627223],"type":"Point"}
}