{
  "type": "Feature",
  "properties": {
    "iso:country":"US",
    "sg:address":"792 State Hwy 160",
    "sg:city":"Hindman",
    "sg:classifiers":[
        {
            "category":"Insurance",
            "subcategory":"Insurance Agent",
            "type":"Services"
        }
    ],
    "sg:phone":"+1 606 785 3794",
    "sg:postcode":"41822",
    "sg:province":"KY",
    "wof:name":"Kentucky Farm Bureau Insurance",
    "wof:placetype":"venue"
},
  "geometry": {"coordinates":[-82.968895,37.331511],"type":"Point"}
}