{
  "type": "Feature",
  "properties": {
    "iso:country":"US",
    "sg:address":"1014 Marshall St",
    "sg:city":"Louisville",
    "sg:classifiers":[
        {
            "category":"Professional",
            "type":"Services"
        }
    ],
    "sg:phone":"+1 502 540 5767",
    "sg:postcode":"40204",
    "sg:province":"KY",
    "wof:name":"Jpdurbinnet",
    "wof:placetype":"venue"
},
  "geometry": {"coordinates":[-85.73353400000001,38.249145],"type":"Point"}
}