{
  "type": "Feature",
  "properties": {
    "addr:full":"613 W Main St Lebanon KY 40033",
    "addr:housenumber":"613",
    "addr:postcode":"40033",
    "addr:street":"W Main St",
    "iso:country":"US",
    "sg:address":"613 W Main St",
    "sg:city":"Lebanon",
    "sg:classifiers":[
        {
            "category":"Restaurant",
            "type":"Food & Drink"
        }
    ],
    "sg:menulink":"http://www.allmenus.com/ky/lebanon/101770-huddle-house/menu/",
    "sg:phone":"+1 270 699 2449",
    "sg:postcode":"40033",
    "sg:province":"KY",
    "sg:tags":[
        "american",
        "diner"
    ],
    "wof:name":"Huddle House",
    "wof:placetype":"venue"
},
  "geometry": {"coordinates":[-85.26504199999999,37.564191],"type":"Point"}
}