{
  "type": "Feature",
  "properties": {
    "iso:country":"US",
    "sg:address":"4646 Illinois Ave",
    "sg:city":"Louisville",
    "sg:classifiers":[
        {
            "category":"Manufacturing",
            "subcategory":"Building Materials",
            "type":"Manufacturing & Wholesale Goods"
        }
    ],
    "sg:phone":"+1 502 452 6233",
    "sg:postcode":"40213",
    "sg:province":"KY",
    "sg:tags":[
        "cabinet"
    ],
    "wof:name":"Dial One Custom Workshop",
    "wof:placetype":"venue"
},
  "geometry": {"coordinates":[-85.699534,38.187284],"type":"Point"}
}