{
  "type": "Feature",
  "properties": {
    "iso:country":"US",
    "sg:address":"1449 Bardstown Rd",
    "sg:city":"Louisville",
    "sg:classifiers":[
        {
            "category":"Restaurant",
            "type":"Food & Drink"
        }
    ],
    "sg:phone":"+1 502 454 5212",
    "sg:postcode":"40204",
    "sg:province":"KY",
    "sg:tags":[
        "shop",
        "coffee"
    ],
    "wof:name":"Heine Brothers Coffee",
    "wof:placetype":"venue"
},
  "geometry": {"coordinates":[-85.70961800000001,38.232276],"type":"Point"}
}