{
  "type": "Feature",
  "properties": {
    "iso:country":"US",
    "sg:address":"3612 Decoursey Ave",
    "sg:city":"Covington",
    "sg:classifiers":[
        {
            "category":"Food & Beverages",
            "subcategory":"Bakery",
            "type":"Retail Goods"
        }
    ],
    "sg:phone":"+1 859 491 8855",
    "sg:postcode":"41015",
    "sg:province":"KY",
    "sg:tags":[
        "baker",
        "bakers-wholesale"
    ],
    "wof:name":"Bernhard's Bakery",
    "wof:placetype":"venue"
},
  "geometry": {"coordinates":[-84.503202,39.048237],"type":"Point"}
}