{
  "type": "Feature",
  "properties": {
    "iso:country":"US",
    "sg:address":"1210 Main St",
    "sg:city":"Murray",
    "sg:classifiers":[
        {
            "category":"Shopping",
            "subcategory":"Hobbies, Toys, & Games",
            "type":"Retail Goods"
        }
    ],
    "sg:phone":"+1 270 753 8197",
    "sg:postcode":"42071",
    "sg:province":"KY",
    "sg:tags":[
        "model",
        "supply"
    ],
    "wof:name":"Strick's RC Hobbies",
    "wof:placetype":"venue"
},
  "geometry": {"coordinates":[-88.31533399999999,36.610639],"type":"Point"}
}