{
  "type": "Feature",
  "properties": {
    "iso:country":"US",
    "sg:address":"1648 Barbourville St",
    "sg:city":"London",
    "sg:classifiers":[
        {
            "category":"Real Estate",
            "subcategory":"Real Estate Agent",
            "type":"Services"
        }
    ],
    "sg:phone":"+1 606 862 9658",
    "sg:postcode":"40741",
    "sg:province":"KY",
    "wof:name":"Daoud Realty Co",
    "wof:placetype":"venue"
},
  "geometry": {"coordinates":[-84.069925,37.113643],"type":"Point"}
}