{
  "type": "Feature",
  "properties": {
    "addr:full":"8304 Midland Trail Rd Ashland KY 41102",
    "addr:housenumber":"8304",
    "addr:postcode":"41102",
    "addr:street":"Midland Trail Rd",
    "iso:country":"US",
    "sg:address":"8304 Midland Trail Rd",
    "sg:city":"Ashland",
    "sg:classifiers":[
        {
            "category":"Autos & Motor Vehicles",
            "subcategory":"Automobile Sales",
            "type":"Retail Goods"
        }
    ],
    "sg:phone":"+1 606 928 7753",
    "sg:postcode":"41102",
    "sg:province":"KY",
    "sg:tags":[
        "car",
        "dealer"
    ],
    "wof:name":"K B Auto Mart",
    "wof:placetype":"venue"
},
  "geometry": {"coordinates":[-82.70530100000001,38.416407],"type":"Point"}
}