{
  "type": "Feature",
  "properties": {
    "addr:full":"2608 N Main St Madisonville KY 42431",
    "addr:housenumber":"2608",
    "addr:postcode":"42431",
    "addr:street":"N Main St",
    "iso:country":"US",
    "sg:address":"2608 N Main St",
    "sg:city":"Madisonville",
    "sg:classifiers":[
        {
            "category":"Retail",
            "subcategory":"Laundry & Dry Cleaning",
            "type":"Services"
        }
    ],
    "sg:phone":"+1 270 821 5265",
    "sg:postcode":"42431",
    "sg:province":"KY",
    "wof:name":"Western Kentucky Hospital Svc",
    "wof:placetype":"venue"
},
  "geometry": {"coordinates":[-87.496591,37.362513],"type":"Point"}
}