{
  "type": "Feature",
  "properties": {
    "addr:full":"834 Walter Jetton Blvd Paducah KY 42003",
    "addr:housenumber":"834",
    "addr:postcode":"42003",
    "addr:street":"Walter Jetton Blvd",
    "iso:country":"US",
    "sg:address":"834 Walter Jetton Blvd",
    "sg:city":"Paducah",
    "sg:classifiers":[
        {
            "category":"Real Estate",
            "subcategory":"Real Estate Agent",
            "type":"Services"
        }
    ],
    "sg:phone":"+1 270 442 9730",
    "sg:postcode":"42003",
    "sg:province":"KY",
    "wof:name":"Alston & Assoc Realty",
    "wof:placetype":"venue"
},
  "geometry": {"coordinates":[-88.600622,37.075956],"type":"Point"}
}