{
  "type": "Feature",
  "properties": {
    "addr:full":"907 Martinsville Rd Oakland KY 42159",
    "addr:housenumber":"907",
    "addr:postcode":"42159",
    "addr:street":"Martinsville Rd",
    "iso:country":"US",
    "sg:address":"907 Martinsville Rd",
    "sg:city":"Oakland",
    "sg:classifiers":[
        {
            "category":"Building & Trades",
            "subcategory":"Plumbing",
            "type":"Services"
        }
    ],
    "sg:phone":"+1 270 563 9994",
    "sg:postcode":"42159",
    "sg:province":"KY",
    "sg:tags":[
        "contractor"
    ],
    "wof:name":"Keith Plumbing",
    "wof:placetype":"venue"
},
  "geometry": {"coordinates":[-86.213047,36.935762],"type":"Point"}
}