{
  "type": "Feature",
  "properties": {
    "addr:full":"4113 Palomar Blvd Lexington KY 40513",
    "addr:housenumber":"4113",
    "addr:postcode":"40513",
    "addr:street":"Palomar Blvd",
    "iso:country":"US",
    "sg:address":"4113 Palomar Blvd",
    "sg:city":"Lexington",
    "sg:classifiers":[
        {
            "category":"Freight",
            "type":"Transportation"
        }
    ],
    "sg:phone":"+1 859 223 5245",
    "sg:postcode":"40513",
    "sg:province":"KY",
    "sg:tags":[
        "arrangement"
    ],
    "wof:name":"Dealer Referral Services",
    "wof:placetype":"venue"
},
  "geometry": {"coordinates":[-84.58231600000001,38.004765],"type":"Point"}
}