{
  "type": "Feature",
  "properties": {
    "addr:full":"541 Ashley Way Lexington KY 40503",
    "addr:housenumber":"541",
    "addr:postcode":"40503",
    "addr:street":"Ashley Way",
    "iso:country":"US",
    "sg:address":"541 Ashley Way",
    "sg:city":"Lexington",
    "sg:classifiers":[
        {
            "category":"Professional",
            "subcategory":"Art Services",
            "type":"Services"
        }
    ],
    "sg:phone":"+1 859 278 3578",
    "sg:postcode":"40503",
    "sg:province":"KY",
    "sg:tags":[
        "photography",
        "commercial"
    ],
    "wof:name":"Twenty Twelve Inc",
    "wof:placetype":"venue"
},
  "geometry": {"coordinates":[-84.53767999999999,38.007643],"type":"Point"}
}