{
  "type": "Feature",
  "properties": {
    "iso:country":"US",
    "sg:address":"88 Joyce Hts",
    "sg:city":"Danville",
    "sg:classifiers":[
        {
            "category":"Building & Trades",
            "subcategory":"Construction",
            "type":"Services"
        }
    ],
    "sg:phone":"+1 859 854 0339",
    "sg:postcode":"40422",
    "sg:province":"KY",
    "sg:tags":[
        "house"
    ],
    "wof:name":"Donald R Keck Remodeling",
    "wof:placetype":"venue"
},
  "geometry": {"coordinates":[-84.78254099999999,37.577687],"type":"Point"}
}