{
  "type": "Feature",
  "properties": {
    "addr:full":"1300 Bramlage Rd Walton KY 41094",
    "addr:housenumber":"1300",
    "addr:postcode":"41094",
    "addr:street":"Bramlage Rd",
    "iso:country":"US",
    "sg:address":"1300 Bramlage Rd",
    "sg:city":"Walton",
    "sg:classifiers":[
        {
            "category":"Building & Trades",
            "subcategory":"Construction",
            "type":"Services"
        }
    ],
    "sg:phone":"+1 859 363 9505",
    "sg:postcode":"41094",
    "sg:province":"KY",
    "sg:tags":[
        "home",
        "builder"
    ],
    "wof:name":"T W Construction Co",
    "wof:placetype":"venue"
},
  "geometry": {"coordinates":[-84.578029,38.910448],"type":"Point"}
}