{
  "type": "Feature",
  "properties": {
    "addr:full":"119 N Maple St Somerset KY 42501",
    "addr:housenumber":"119",
    "addr:postcode":"42501",
    "addr:street":"N Maple St",
    "iso:country":"US",
    "sg:address":"119 N Maple St",
    "sg:city":"Somerset",
    "sg:classifiers":[
        {
            "category":"Government",
            "subcategory":"Post Office",
            "type":"Public Place"
        }
    ],
    "sg:phone":"+1 606 678 5712",
    "sg:postcode":"42501",
    "sg:province":"KY",
    "wof:name":"US Post Office",
    "wof:placetype":"venue"
},
  "geometry": {"coordinates":[-84.603824,37.093278],"type":"Point"}
}