{
  "type": "Feature",
  "properties": {
    "iso:country":"US",
    "sg:address":"1044 S 36th St",
    "sg:city":"Louisville",
    "sg:classifiers":[
        {
            "category":"Personal",
            "subcategory":"Barber",
            "type":"Services"
        }
    ],
    "sg:phone":"+1 502 772 1706",
    "sg:postcode":"40211",
    "sg:province":"KY",
    "wof:name":"Rob's Barbershop",
    "wof:placetype":"venue"
},
  "geometry": {"coordinates":[-85.81313299999999,38.242325],"type":"Point"}
}