{
  "type": "Feature",
  "properties": {
    "addr:full":"107 Brookside Dr Nicholasville KY 40356",
    "addr:housenumber":"107",
    "addr:postcode":"40356",
    "addr:street":"Brookside Dr",
    "iso:country":"US",
    "sg:address":"107 Brookside Dr",
    "sg:city":"Nicholasville",
    "sg:classifiers":[
        {
            "category":"Social Services",
            "subcategory":"Child Care",
            "type":"Services"
        }
    ],
    "sg:phone":"+1 859 885 9241",
    "sg:postcode":"40356",
    "sg:province":"KY",
    "sg:tags":[
        "kindergarten",
        "academic",
        "school"
    ],
    "wof:name":"A Child's Place",
    "wof:placetype":"venue"
},
  "geometry": {"coordinates":[-84.58902399999999,37.887358],"type":"Point"}
}