{
  "type": "Feature",
  "properties": {
    "iso:country":"US",
    "sg:address":"416 S Main St",
    "sg:city":"Hartford",
    "sg:classifiers":[
        {
            "category":"Professional",
            "subcategory":"Accounting & Tax Preparation",
            "type":"Services"
        }
    ],
    "sg:phone":"+1 270 298 7647",
    "sg:postcode":"42347",
    "sg:province":"KY",
    "sg:tags":[
        "accountant"
    ],
    "wof:name":"Clemens Guthrie & Robinson",
    "wof:placetype":"venue"
},
  "geometry": {"coordinates":[-86.908039,37.44998],"type":"Point"}
}