{
  "type": "Feature",
  "properties": {
    "iso:country":"US",
    "sg:address":"612 Triplett St",
    "sg:city":"Owensboro",
    "sg:classifiers":[
        {
            "category":"Professional",
            "subcategory":"Credit Reporting & Collection",
            "type":"Services"
        }
    ],
    "sg:phone":"+1 270 685 4065",
    "sg:postcode":"42303",
    "sg:province":"KY",
    "sg:tags":[
        "agency"
    ],
    "wof:name":"Cornerstone Enterprises",
    "wof:placetype":"venue"
},
  "geometry": {"coordinates":[-87.103905,37.770003],"type":"Point"}
}