{
  "type": "Feature",
  "properties": {
    "addr:full":"6714 Outer Loop Louisville KY 40228",
    "addr:housenumber":"6714",
    "addr:postcode":"40228",
    "addr:street":"Outer Loop",
    "iso:country":"US",
    "sg:address":"6714 Outer Loop",
    "sg:city":"Louisville",
    "sg:classifiers":[
        {
            "category":"Restaurant",
            "type":"Food & Drink"
        }
    ],
    "sg:menulink":"http://www.allmenus.com/ky/jefferson-central/87484-little-caesars-pizza/menu/",
    "sg:phone":"+1 502 966 3111",
    "sg:postcode":"40228",
    "sg:province":"KY",
    "sg:tags":[
        "american",
        "pizza"
    ],
    "wof:name":"Little Caesar's Pizza",
    "wof:placetype":"venue"
},
  "geometry": {"coordinates":[-85.63247200000001,38.137508],"type":"Point"}
}