{
  "type": "Feature",
  "properties": {
    "addr:full":"106 Cedar St Providence KY 42450",
    "addr:housenumber":"106",
    "addr:postcode":"42450",
    "addr:street":"Cedar St",
    "iso:country":"US",
    "sg:address":"106 Cedar St",
    "sg:city":"Providence",
    "sg:classifiers":[
        {
            "category":"Shopping",
            "subcategory":"Clothing, Apparel, & Fashions",
            "type":"Retail Goods"
        }
    ],
    "sg:phone":"+1 270 667 5969",
    "sg:postcode":"42450",
    "sg:province":"KY",
    "wof:name":"Ruby's Four Seasons Clothing",
    "wof:placetype":"venue"
},
  "geometry": {"coordinates":[-87.76261599999999,37.396876],"type":"Point"}
}