{
  "type": "Feature",
  "properties": {
    "iso:country":"US",
    "sg:address":"734 Knox Blvd",
    "sg:city":"Radcliff",
    "sg:classifiers":[
        {
            "category":"Banks & Credit Unions",
            "subcategory":"Bank",
            "type":"Services"
        }
    ],
    "sg:phone":"+1 270 351 2101",
    "sg:postcode":"40160",
    "sg:province":"KY",
    "sg:tags":[
        "cashing",
        "check"
    ],
    "wof:name":"Quick Cash Kentucky",
    "wof:placetype":"venue"
},
  "geometry": {"coordinates":[-85.955175,37.861046],"type":"Point"}
}