{
  "type": "Feature",
  "properties": {
    "iso:country":"US",
    "sg:address":"111 E Main St",
    "sg:city":"Wilmore",
    "sg:classifiers":[
        {
            "category":"Restaurant",
            "type":"Food & Drink"
        }
    ],
    "sg:phone":"+1 859 858 9060",
    "sg:postcode":"40390",
    "sg:province":"KY",
    "wof:name":"Solomon's Porch Inc",
    "wof:placetype":"venue"
},
  "geometry": {"coordinates":[-84.662367,37.860967],"type":"Point"}
}