{
  "type": "Feature",
  "properties": {
    "iso:country":"US",
    "sg:address":"3615 Burkesville Rd",
    "sg:city":"Columbia",
    "sg:classifiers":[
        {
            "category":"Building & Trades",
            "subcategory":"Construction",
            "type":"Services"
        }
    ],
    "sg:phone":"+1 270 384 2677",
    "sg:postcode":"42728",
    "sg:province":"KY",
    "sg:tags":[
        "general",
        "contractor"
    ],
    "wof:name":"Stotts Construction Shop",
    "wof:placetype":"venue"
},
  "geometry": {"coordinates":[-85.34384,37.063988],"type":"Point"}
}