{
  "type": "Feature",
  "properties": {
    "iso:country":"US",
    "sg:address":"810 Taylorsville Rd",
    "sg:city":"Shelbyville",
    "sg:classifiers":[
        {
            "category":"Restaurant",
            "type":"Food & Drink"
        }
    ],
    "sg:menulink":"http://www.allmenus.com/ky/shelbyville/159381-arbys/menu/",
    "sg:phone":"+1 502 633 4240",
    "sg:postcode":"40065",
    "sg:province":"KY",
    "sg:tags":[
        "burger",
        "american"
    ],
    "wof:name":"Arby's",
    "wof:placetype":"venue"
},
  "geometry": {"coordinates":[-85.26546500000001,38.204821],"type":"Point"}
}