{
  "type": "Feature",
  "properties": {
    "addr:full":"1050 Jackson Rd Park Hills KY 41011",
    "addr:housenumber":"1050",
    "addr:postcode":"41011",
    "addr:street":"Jackson",
    "iso:country":"US",
    "sg:address":"1050 Jackson Rd",
    "sg:city":"Park Hills",
    "sg:classifiers":[
        {
            "category":"Retail",
            "subcategory":"Repair Shop",
            "type":"Services"
        }
    ],
    "sg:phone":"+1 859 261 1459",
    "sg:postcode":"41011",
    "sg:province":"KY",
    "sg:tags":[
        "vinyl"
    ],
    "wof:name":"Vinyl Additives & Equipment",
    "wof:placetype":"venue"
},
  "geometry": {"coordinates":[-84.532268,39.073548],"type":"Point"}
}