{
  "type": "Feature",
  "properties": {
    "iso:country":"US",
    "sg:address":"35 W 5th St",
    "sg:city":"Covington",
    "sg:classifiers":[
        {
            "category":"Government",
            "subcategory":"Court House",
            "type":"Public Place"
        }
    ],
    "sg:phone":"+1 859 392 7925",
    "sg:postcode":"41011",
    "sg:province":"KY",
    "sg:tags":[
        "federal"
    ],
    "wof:name":"US District Court Clerk",
    "wof:placetype":"venue"
},
  "geometry": {"coordinates":[-84.51249799999999,39.085491],"type":"Point"}
}