{
  "type": "Feature",
  "properties": {
    "addr:full":"701 Capitol Ave Frankfort KY 40601",
    "addr:housenumber":"701",
    "addr:postcode":"40601",
    "addr:street":"Capitol Ave",
    "iso:country":"US",
    "sg:address":"701 Capitol Ave",
    "sg:city":"Frankfort",
    "sg:classifiers":[
        {
            "category":"Government",
            "subcategory":"Court House",
            "type":"Public Place"
        }
    ],
    "sg:phone":"+1 502 564 6753",
    "sg:postcode":"40601",
    "sg:province":"KY",
    "sg:tags":[
        "state"
    ],
    "wof:name":"Supreme Court Chief Jusitce",
    "wof:placetype":"venue"
},
  "geometry": {"coordinates":[-84.87517699999999,38.189654],"type":"Point"}
}