{
  "type": "Feature",
  "properties": {
    "addr:full":"1604 N Dixie Hwy Elizabethtown KY 42701",
    "addr:housenumber":"1604",
    "addr:postcode":"42701",
    "addr:street":"N Dixie Hwy",
    "iso:country":"US",
    "sg:address":"1604 N Dixie Hwy",
    "sg:city":"Elizabethtown",
    "sg:classifiers":[
        {
            "category":"Restaurant",
            "type":"Food & Drink"
        }
    ],
    "sg:menulink":"http://www.allmenus.com/ky/elizabethtown/208226-taco-bell/menu/",
    "sg:phone":"+1 270 765 2499",
    "sg:postcode":"42701",
    "sg:province":"KY",
    "sg:tags":[
        "mexican"
    ],
    "wof:name":"Taco Bell",
    "wof:placetype":"venue"
},
  "geometry": {"coordinates":[-85.88531999999999,37.730433],"type":"Point"}
}