{
  "type": "Feature",
  "properties": {
    "iso:country":"US",
    "sg:address":"137 Hillcrest Rd",
    "sg:city":"Bowling Green",
    "sg:classifiers":[
        {
            "category":"Professional",
            "subcategory":"Business Services",
            "type":"Services"
        }
    ],
    "sg:phone":"+1 270 726 2558",
    "sg:postcode":"42103",
    "sg:province":"KY",
    "sg:tags":[
        "interior",
        "consultant",
        "design",
        "decorator"
    ],
    "wof:name":"Home Interiors & Gifts",
    "wof:placetype":"venue"
},
  "geometry": {"coordinates":[-86.358565,36.96317],"type":"Point"}
}