{
  "type": "Feature",
  "properties": {
    "iso:country":"US",
    "sg:address":"1115 Broadway St",
    "sg:city":"Paducah",
    "sg:classifiers":[
        {
            "category":"Retail",
            "subcategory":"Auto Rental",
            "type":"Services"
        }
    ],
    "sg:phone":"+1 270 444 2000",
    "sg:postcode":"42001",
    "sg:province":"KY",
    "sg:tags":[
        "renting",
        "automobile"
    ],
    "wof:name":"U-Save Auto Rental",
    "wof:placetype":"venue"
},
  "geometry": {"coordinates":[-88.60773399999999,37.082871],"type":"Point"}
}