{
  "type": "Feature",
  "properties": {
    "addr:full":"4780 Hanson Rd Madisonville KY 42431",
    "addr:housenumber":"4780",
    "addr:postcode":"42431",
    "addr:street":"Hanson Rd",
    "iso:country":"US",
    "sg:address":"4780 Hanson Rd",
    "sg:city":"Madisonville",
    "sg:classifiers":[
        {
            "category":"Organizations",
            "subcategory":"Religious Organization",
            "type":"Services"
        }
    ],
    "sg:phone":"+1 270 824 9007",
    "sg:postcode":"42431",
    "sg:province":"KY",
    "wof:name":"Meals From Heaven Ministry",
    "wof:placetype":"venue"
},
  "geometry": {"coordinates":[-87.488328,37.381884],"type":"Point"}
}