{
  "type": "Feature",
  "properties": {
    "iso:country":"US",
    "sg:address":"954 Hill",
    "sg:city":"Cincinnati",
    "sg:classifiers":[
        {
            "category":"Shopping",
            "subcategory":"Tobacco",
            "type":"Retail Goods"
        }
    ],
    "sg:phone":"+1 513 784 9099",
    "sg:postcode":"45202",
    "sg:province":"OH",
    "sg:tags":[
        "cigarette",
        "cigar",
        "dealer"
    ],
    "wof:name":"Thoroughbred Cigar Co LTD",
    "wof:placetype":"venue"
},
  "geometry": {"coordinates":[-84.49576,39.10671],"type":"Point"}
}