{
  "type": "Feature",
  "properties": {
    "iso:country":"US",
    "sg:address":"6501 Bardstown Rd",
    "sg:city":"Louisville",
    "sg:classifiers":[
        {
            "category":"Bars & Pubs",
            "subcategory":"Sports Bar",
            "type":"Food & Drink"
        },
        {
            "category":"Restaurant",
            "type":"Food & Drink"
        }
    ],
    "sg:phone":"+1 502 231 6501",
    "sg:postcode":"40291",
    "sg:province":"KY",
    "sg:tags":[
        "barbecue"
    ],
    "wof:name":"Buffalo Wings & Ring",
    "wof:placetype":"venue"
},
  "geometry": {"coordinates":[-85.58857,38.15263],"type":"Point"}
}