{
  "type": "Feature",
  "properties": {
    "addr:full":"1704 E 9th St Hopkinsville KY 42240",
    "addr:housenumber":"1704",
    "addr:postcode":"42240",
    "addr:street":"E 9Th St",
    "iso:country":"US",
    "sg:address":"1704 E 9th St",
    "sg:city":"Hopkinsville",
    "sg:classifiers":[
        {
            "category":"Manufacturing",
            "subcategory":"Printing",
            "type":"Manufacturing & Wholesale Goods"
        }
    ],
    "sg:phone":"+1 270 886 5847",
    "sg:postcode":"42240",
    "sg:province":"KY",
    "sg:tags":[
        "commercial"
    ],
    "wof:name":"Sprint Print",
    "wof:placetype":"venue"
},
  "geometry": {"coordinates":[-87.47224199999999,36.851783],"type":"Point"}
}