{
  "type": "Feature",
  "properties": {
    "iso:country":"US",
    "sg:address":"1599 State Hwy 122",
    "sg:city":"Printer",
    "sg:classifiers":[
        {
            "category":"Home & Garden",
            "subcategory":"Furniture",
            "type":"Retail Goods"
        }
    ],
    "sg:phone":"+1 606 285 0271",
    "sg:postcode":"41655",
    "sg:province":"KY",
    "wof:name":"Billy J's Furniture Etc",
    "wof:placetype":"venue"
},
  "geometry": {"coordinates":[-82.74610300000001,37.531132],"type":"Point"}
}