{
  "type": "Feature",
  "properties": {
    "addr:full":"1033 Paris Rd Mayfield KY 42066",
    "addr:housenumber":"1033",
    "addr:postcode":"42066",
    "addr:street":"Paris Rd",
    "iso:country":"US",
    "sg:address":"1033 Paris Rd",
    "sg:city":"Mayfield",
    "sg:classifiers":[
        {
            "category":"Restaurant",
            "type":"Food & Drink"
        }
    ],
    "sg:menulink":"http://www.allmenus.com/ky/mayfield/155911-hardees/menu/",
    "sg:phone":"+1 270 247 5968",
    "sg:postcode":"42066",
    "sg:province":"KY",
    "sg:tags":[
        "burger",
        "american"
    ],
    "wof:name":"Hardee's",
    "wof:placetype":"venue"
},
  "geometry": {"coordinates":[-88.63143700000001,36.72946],"type":"Point"}
}