{
  "type": "Feature",
  "properties": {
    "iso:country":"US",
    "sg:address":"822 Ash St",
    "sg:city":"Louisville",
    "sg:classifiers":[
        {
            "category":"Personal",
            "subcategory":"Beauty Salon",
            "type":"Services"
        }
    ],
    "sg:phone":"+1 502 637 2383",
    "sg:postcode":"40217",
    "sg:province":"KY",
    "wof:name":"Braiding Unlimited",
    "wof:placetype":"venue"
},
  "geometry": {"coordinates":[-85.739896,38.228244],"type":"Point"}
}