{
  "type": "Feature",
  "properties": {
    "iso:country":"US",
    "sg:address":"5918 Bybee Rd",
    "sg:city":"Ashland",
    "sg:classifiers":[
        {
            "category":"Building & Trades",
            "subcategory":"Construction",
            "type":"Services"
        }
    ],
    "sg:phone":"+1 606 928 2242",
    "sg:postcode":"41102",
    "sg:province":"KY",
    "sg:tags":[
        "acoustical",
        "contractor"
    ],
    "wof:name":"Ashland Acoustical",
    "wof:placetype":"venue"
},
  "geometry": {"coordinates":[-82.69587300000001,38.437321],"type":"Point"}
}