{
  "type": "Feature",
  "properties": {
    "iso:country":"US",
    "sg:address":"3191 Beaumont Centre Cir",
    "sg:city":"Lexington",
    "sg:classifiers":[
        {
            "category":"Restaurant",
            "type":"Food & Drink"
        }
    ],
    "sg:phone":"+1 859 296 9330",
    "sg:postcode":"40513",
    "sg:province":"KY",
    "wof:name":"Pasta Plus LLC",
    "wof:placetype":"venue"
},
  "geometry": {"coordinates":[-84.55668300000001,38.020655],"type":"Point"}
}