{
  "type": "Feature",
  "properties": {
    "addr:full":"3001 Irvine Rd Richmond KY 40475",
    "addr:housenumber":"3001",
    "addr:postcode":"40475",
    "addr:street":"Irvine Rd",
    "iso:country":"US",
    "sg:address":"3001 Irvine Rd",
    "sg:city":"Richmond",
    "sg:classifiers":[
        {
            "category":"Retail",
            "subcategory":"Veterinary Services",
            "type":"Services"
        }
    ],
    "sg:phone":"+1 859 369 3699",
    "sg:postcode":"40475",
    "sg:province":"KY",
    "sg:tags":[
        "veterinarian"
    ],
    "wof:name":"Central Madison Veterinary",
    "wof:placetype":"venue"
},
  "geometry": {"coordinates":[-84.161304,37.74009],"type":"Point"}
}