{
  "type": "Feature",
  "properties": {
    "iso:country":"US",
    "sg:address":"49 Fairfield Dr",
    "sg:city":"Somerset",
    "sg:classifiers":[
        {
            "category":"Building & Trades",
            "subcategory":"Construction",
            "type":"Services"
        }
    ],
    "sg:phone":"+1 606 679 2702",
    "sg:postcode":"42501",
    "sg:province":"KY",
    "sg:tags":[
        "house"
    ],
    "wof:name":"New Homes LLC",
    "wof:placetype":"venue"
},
  "geometry": {"coordinates":[-84.622276,37.043337],"type":"Point"}
}