{
  "type": "Feature",
  "properties": {
    "addr:full":"11 Price Ave Erlanger KY 41018",
    "addr:housenumber":"11",
    "addr:postcode":"41018",
    "addr:street":"Price Ave",
    "iso:country":"US",
    "sg:address":"11 Price Ave",
    "sg:city":"Erlanger",
    "sg:classifiers":[
        {
            "category":"Home & Garden",
            "subcategory":"Household Appliances",
            "type":"Retail Goods"
        },
        {
            "category":"Retail",
            "subcategory":"Repair Shop",
            "type":"Services"
        }
    ],
    "sg:phone":"+1 859 342 9900",
    "sg:postcode":"41018",
    "sg:province":"KY",
    "sg:tags":[
        "major",
        "refinishing"
    ],
    "sg:website":"http://www.niceleys.com",
    "wof:name":"Niceley's Appliance Repair Inc",
    "wof:placetype":"venue"
},
  "geometry": {"coordinates":[-84.603909,39.015029],"type":"Point"}
}