{
  "type": "Feature",
  "properties": {
    "addr:full":"100 Bauer Ave Louisville KY 40207",
    "addr:housenumber":"100",
    "addr:postcode":"40207",
    "addr:street":"Bauer Ave",
    "iso:country":"US",
    "sg:address":"100 Bauer Ave",
    "sg:city":"Louisville",
    "sg:classifiers":[
        {
            "category":"Retail",
            "subcategory":"Animal Services",
            "type":"Services"
        }
    ],
    "sg:phone":"+1 502 899 9300",
    "sg:postcode":"40207",
    "sg:province":"KY",
    "sg:tags":[
        "pet",
        "grooming"
    ],
    "wof:name":"Abra Cadabra Pet Grooming",
    "wof:placetype":"venue"
},
  "geometry": {"coordinates":[-85.662308,38.253448],"type":"Point"}
}