{
  "type": "Feature",
  "properties": {
    "iso:country":"US",
    "sg:address":"625 Elrod Rd",
    "sg:city":"Bowling Green",
    "sg:classifiers":[
        {
            "category":"Manufacturing",
            "subcategory":"Printing",
            "type":"Manufacturing & Wholesale Goods"
        }
    ],
    "sg:phone":"+1 270 780 9334",
    "sg:postcode":"42104",
    "sg:province":"KY",
    "sg:tags":[
        "periodical"
    ],
    "wof:name":"Golden Anchor Press",
    "wof:placetype":"venue"
},
  "geometry": {"coordinates":[-86.48112399999999,36.928552],"type":"Point"}
}