{
  "type": "Feature",
  "properties": {
    "addr:full":"1640 Harristown Rd Russell Springs KY 42642",
    "addr:housenumber":"1640",
    "addr:postcode":"42642",
    "addr:street":"Harristown Rd",
    "iso:country":"US",
    "sg:address":"1640 Harristown Rd",
    "sg:city":"Russell Springs",
    "sg:phone":"+1 270 866 6708",
    "sg:postcode":"42642",
    "sg:province":"KY",
    "sg:tags":[
        "farm",
        "tobacco"
    ],
    "wof:name":"Roy Arlie",
    "wof:placetype":"venue"
},
  "geometry": {"coordinates":[-84.93830800000001,37.056596],"type":"Point"}
}