{
  "type": "Feature",
  "properties": {
    "iso:country":"US",
    "sg:address":"8300 Hudson Ln",
    "sg:city":"Louisville",
    "sg:classifiers":[
        {
            "category":"Building & Trades",
            "subcategory":"Landscaping Services",
            "type":"Services"
        }
    ],
    "sg:phone":"+1 502 239 3955",
    "sg:postcode":"40291",
    "sg:province":"KY",
    "sg:tags":[
        "sod",
        "sodding"
    ],
    "wof:name":"Bush Sod Farms",
    "wof:placetype":"venue"
},
  "geometry": {"coordinates":[-85.60015300000001,38.164459],"type":"Point"}
}