{
  "type": "Feature",
  "properties": {
    "iso:country":"US",
    "sg:address":"210 E 7th Ave",
    "sg:city":"Bowling Green",
    "sg:classifiers":[
        {
            "category":"Organizations",
            "subcategory":"Religious Organization",
            "type":"Services"
        }
    ],
    "sg:phone":"+1 270 782 7717",
    "sg:postcode":"42101",
    "sg:province":"KY",
    "sg:tags":[
        "church"
    ],
    "wof:name":"Iglesia LA Hermosa SN Blas De",
    "wof:placetype":"venue"
},
  "geometry": {"coordinates":[-86.441346,36.997611],"type":"Point"}
}