{
  "type": "Feature",
  "properties": {
    "iso:country":"US",
    "sg:address":"127 E 2nd St",
    "sg:city":"Covington",
    "sg:classifiers":[
        {
            "category":"Wholesale",
            "subcategory":"Photographic Equipment",
            "type":"Manufacturing & Wholesale Goods"
        }
    ],
    "sg:phone":"+1 859 655 8100",
    "sg:postcode":"41011",
    "sg:province":"KY",
    "sg:tags":[
        "audio"
    ],
    "sg:website":"www.prestigeav.net",
    "wof:name":"Prestige Audio Visual",
    "wof:placetype":"venue"
},
  "geometry": {"coordinates":[-84.508427,39.089877],"type":"Point"}
}