{
  "type": "Feature",
  "properties": {
    "iso:country":"US",
    "sg:address":"4665 Scottsville Rd",
    "sg:city":"Bowling Green",
    "sg:classifiers":[
        {
            "category":"Restaurant",
            "type":"Food & Drink"
        }
    ],
    "sg:phone":"+1 270 782 9400",
    "sg:postcode":"42104",
    "sg:province":"KY",
    "wof:name":"Mancino's Grinders & Pizza",
    "wof:placetype":"venue"
},
  "geometry": {"coordinates":[-86.415297,36.931726],"type":"Point"}
}