{
  "type": "Feature",
  "properties": {
    "addr:full":"3054 Lyndale Ct Edgewood KY 41017",
    "addr:housenumber":"3054",
    "addr:postcode":"41017",
    "addr:street":"Lyndale Ct",
    "iso:country":"US",
    "sg:address":"3054 Lyndale Ct",
    "sg:city":"Edgewood",
    "sg:classifiers":[
        {
            "category":"Building & Trades",
            "subcategory":"Construction",
            "type":"Services"
        }
    ],
    "sg:phone":"+1 859 344 1888",
    "sg:postcode":"41017",
    "sg:province":"KY",
    "sg:tags":[
        "home",
        "builder"
    ],
    "wof:name":"Ashley Homes",
    "wof:placetype":"venue"
},
  "geometry": {"coordinates":[-84.586404,39.019001],"type":"Point"}
}