{
  "type": "Feature",
  "properties": {
    "iso:country":"US",
    "sg:address":"157 Towne Dr",
    "sg:city":"Elizabethtown",
    "sg:classifiers":[
        {
            "category":"Shopping",
            "subcategory":"Clothing, Apparel, & Fashions",
            "type":"Retail Goods"
        }
    ],
    "sg:phone":"+1 270 765 0908",
    "sg:postcode":"42701",
    "sg:province":"KY",
    "sg:tags":[
        "handbag"
    ],
    "wof:name":"Jewelry & Handbag Warehouse",
    "wof:placetype":"venue"
},
  "geometry": {"coordinates":[-85.887671,37.733962],"type":"Point"}
}