{
  "type": "Feature",
  "properties": {
    "iso:country":"US",
    "sg:address":"1477 S 2nd St",
    "sg:city":"Louisville",
    "sg:classifiers":[
        {
            "category":"Restaurant",
            "type":"Food & Drink"
        }
    ],
    "sg:phone":"+1 502 635 0240",
    "sg:postcode":"40208",
    "sg:province":"KY",
    "sg:tags":[
        "caterer"
    ],
    "wof:name":"Gumby's Speciality Catering",
    "wof:placetype":"venue"
},
  "geometry": {"coordinates":[-85.758403,38.226337],"type":"Point"}
}