{
  "type": "Feature",
  "properties": {
    "addr:full":"4214 Shelbyville Rd Louisville KY 40207",
    "addr:housenumber":"4214",
    "addr:postcode":"40207",
    "addr:street":"Shelbyville Rd",
    "iso:country":"US",
    "sg:address":"4214 Shelbyville Rd",
    "sg:city":"Louisville",
    "sg:classifiers":[
        {
            "category":"Restaurant",
            "type":"Food & Drink"
        }
    ],
    "sg:menulink":"http://www.allmenus.com/ky/louisville-east/200456-long-john-silvers/menu/",
    "sg:phone":"+1 502 893 3318",
    "sg:postcode":"40207",
    "sg:province":"KY",
    "sg:tags":[
        "seafood",
        "american"
    ],
    "wof:name":"Long John Silver's",
    "wof:placetype":"venue"
},
  "geometry": {"coordinates":[-85.640306,38.251637],"type":"Point"}
}