{
  "type": "Feature",
  "properties": {
    "iso:country":"US",
    "sg:address":"12221 Somerset Dr",
    "sg:city":"Louisville",
    "sg:classifiers":[
        {
            "category":"Building & Trades",
            "subcategory":"Construction",
            "type":"Services"
        }
    ],
    "sg:phone":"+1 502 957 2852",
    "sg:postcode":"40229",
    "sg:province":"KY",
    "sg:tags":[
        "field",
        "oil",
        "hauling"
    ],
    "wof:name":"Petrolink",
    "wof:placetype":"venue"
},
  "geometry": {"coordinates":[-85.681799,38.068489],"type":"Point"}
}