{
  "type": "Feature",
  "properties": {
    "iso:country":"US",
    "sg:address":"64 First Union Church Rd",
    "sg:city":"Glendale",
    "sg:classifiers":[
        {
            "category":"Personal",
            "type":"Services"
        }
    ],
    "sg:phone":"+1 270 369 8368",
    "sg:postcode":"42740",
    "sg:province":"KY",
    "wof:name":"Bennett Slaughter Bennett",
    "wof:placetype":"venue"
},
  "geometry": {"coordinates":[-85.858363,37.614656],"type":"Point"}
}