{
  "type": "Feature",
  "properties": {
    "iso:country":"US",
    "sg:address":"6000 Manslick Rd",
    "sg:city":"Louisville",
    "sg:classifiers":[
        {
            "category":"Autos & Motor Vehicles",
            "subcategory":"Fuel & Gas Station",
            "type":"Retail Goods"
        }
    ],
    "sg:phone":"+1 502 367 9887",
    "sg:postcode":"40214",
    "sg:province":"KY",
    "sg:tags":[
        "oil"
    ],
    "wof:name":"Speedway",
    "wof:placetype":"venue"
},
  "geometry": {"coordinates":[-85.797175,38.169404],"type":"Point"}
}