{
  "type": "Feature",
  "properties": {
    "iso:country":"US",
    "sg:address":"3409 Burkland Blvd",
    "sg:city":"Shepherdsville",
    "sg:classifiers":[
        {
            "category":"Building & Trades",
            "subcategory":"Plumbing",
            "type":"Services"
        }
    ],
    "sg:phone":"+1 502 957 6789",
    "sg:postcode":"40165",
    "sg:province":"KY",
    "sg:tags":[
        "conditioning",
        "air",
        "system",
        "contractor"
    ],
    "wof:name":"Four Seasons HVAC-Heating",
    "wof:placetype":"venue"
},
  "geometry": {"coordinates":[-85.67278,38.052284],"type":"Point"}
}