{
  "type": "Feature",
  "properties": {
    "addr:full":"9190 Camp Ernst Rd Union KY 41091",
    "addr:housenumber":"9190",
    "addr:postcode":"41091",
    "addr:street":"Camp Ernst Rd",
    "iso:country":"US",
    "sg:address":"9190 Camp Ernst Rd",
    "sg:city":"Union",
    "sg:classifiers":[
        {
            "category":"Park",
            "type":"Public Place"
        },
        {
            "category":"Recreation",
            "type":"Entertainment"
        }
    ],
    "sg:phone":"+1 859 384 4999",
    "sg:postcode":"41091",
    "sg:province":"KY",
    "sg:tags":[
        "hiking"
    ],
    "sg:website":"www.bcarboretum.org",
    "wof:name":"Boone County Arboretum",
    "wof:placetype":"venue"
},
  "geometry": {"coordinates":[-84.722703,38.964896],"type":"Point"}
}