{
  "type": "Feature",
  "properties": {
    "iso:country":"US",
    "sg:address":"270 Tewmey Ln",
    "sg:city":"Harrodsburg",
    "sg:classifiers":[
        {
            "category":"Building & Trades",
            "subcategory":"Construction",
            "type":"Services"
        }
    ],
    "sg:phone":"+1 859 734 7964",
    "sg:postcode":"40330",
    "sg:province":"KY",
    "sg:tags":[
        "excavating",
        "contractor"
    ],
    "wof:name":"Ronnie Claunch Construction Co",
    "wof:placetype":"venue"
},
  "geometry": {"coordinates":[-84.87593200000001,37.765875],"type":"Point"}
}