{
  "type": "Feature",
  "properties": {
    "iso:country":"US",
    "sg:address":"1708 Highland Ave",
    "sg:city":"Carrollton",
    "sg:classifiers":[
        {
            "category":"Government",
            "subcategory":"Office",
            "type":"Public Place"
        }
    ],
    "sg:phone":"+1 502 732 7008",
    "sg:postcode":"41008",
    "sg:province":"KY",
    "wof:name":"Carroll County Family Resource",
    "wof:placetype":"venue"
},
  "geometry": {"coordinates":[-85.14876599999999,38.688562],"type":"Point"}
}