{
  "type": "Feature",
  "properties": {
    "iso:country":"US",
    "sg:address":"201 Breckenridge Ln",
    "sg:city":"Louisville",
    "sg:classifiers":[
        {
            "category":"Shopping",
            "subcategory":"Jewelry",
            "type":"Retail Goods"
        }
    ],
    "sg:phone":"+1 502 893 0900",
    "sg:postcode":"40207",
    "sg:province":"KY",
    "sg:tags":[
        "jeweler"
    ],
    "wof:name":"From The Vault",
    "wof:placetype":"venue"
},
  "geometry": {"coordinates":[-85.65271199999999,38.24959],"type":"Point"}
}