{
  "type": "Feature",
  "properties": {
    "addr:full":"3818 Shelbyville Rd Louisville KY 40207",
    "addr:housenumber":"3818",
    "addr:postcode":"40207",
    "addr:street":"Shelbyville Rd",
    "iso:country":"US",
    "sg:address":"3818 Shelbyville Rd",
    "sg:city":"Louisville",
    "sg:classifiers":[
        {
            "category":"Manufacturing",
            "subcategory":"Printing",
            "type":"Manufacturing & Wholesale Goods"
        }
    ],
    "sg:phone":"+1 502 897 8900",
    "sg:postcode":"40207",
    "sg:province":"KY",
    "sg:tags":[
        "newspaper"
    ],
    "sg:website":"www.voice-tribune.com",
    "wof:name":"Southern Publishing Inc",
    "wof:placetype":"venue"
},
  "geometry": {"coordinates":[-85.655599,38.252894],"type":"Point"}
}