{
  "type": "Feature",
  "properties": {
    "iso:country":"US",
    "sg:address":"221 Sterling Ave",
    "sg:city":"Mt Sterling",
    "sg:classifiers":[
        {
            "category":"Shopping",
            "subcategory":"Gifts & Souvenirs",
            "type":"Retail Goods"
        }
    ],
    "sg:phone":"+1 859 498 8141",
    "sg:postcode":"40353",
    "sg:province":"KY",
    "sg:tags":[
        "party",
        "supply"
    ],
    "wof:name":"Party Paradise",
    "wof:placetype":"venue"
},
  "geometry": {"coordinates":[-83.952292,38.061233],"type":"Point"}
}