{
  "type": "Feature",
  "properties": {
    "iso:country":"US",
    "sg:address":"6856 Russell Cave Rd",
    "sg:city":"Lexington",
    "sg:classifiers":[
        {
            "category":"Organizations",
            "subcategory":"Religious Organization",
            "type":"Services"
        }
    ],
    "sg:phone":"+1 859 293 6192",
    "sg:postcode":"40511",
    "sg:province":"KY",
    "sg:tags":[
        "church"
    ],
    "wof:name":"Old Union Christian Church",
    "wof:placetype":"venue"
},
  "geometry": {"coordinates":[-84.397587,38.19539],"type":"Point"}
}