{
  "type": "Feature",
  "properties": {
    "addr:full":"1625 Kirksville Rd Lancaster KY 40444",
    "addr:housenumber":"1625",
    "addr:postcode":"40444",
    "addr:street":"Kirksville Rd",
    "iso:country":"US",
    "sg:address":"1625 Kirksville Rd",
    "sg:city":"Lancaster",
    "sg:classifiers":[
        {
            "category":"Personal",
            "subcategory":"Beauty Salon",
            "type":"Services"
        }
    ],
    "sg:phone":"+1 859 792 4480",
    "sg:postcode":"40444",
    "sg:province":"KY",
    "sg:tags":[
        "shop"
    ],
    "wof:name":"Cut Above",
    "wof:placetype":"venue"
},
  "geometry": {"coordinates":[-84.469026,37.638699],"type":"Point"}
}