{
  "type": "Feature",
  "properties": {
    "iso:country":"US",
    "sg:address":"430 Blue Sky Pkwy",
    "sg:city":"Lexington",
    "sg:classifiers":[
        {
            "category":"Manufacturing",
            "subcategory":"Motor Vehicles & Parts",
            "type":"Manufacturing & Wholesale Goods"
        }
    ],
    "sg:phone":"+1 859 263 5064",
    "sg:postcode":"40509",
    "sg:province":"KY",
    "sg:tags":[
        "body",
        "truck"
    ],
    "wof:name":"Metro Equipment",
    "wof:placetype":"venue"
},
  "geometry": {"coordinates":[-84.373597,37.96428],"type":"Point"}
}