{
  "type": "Feature",
  "properties": {
    "addr:full":"194 Johns Creek Rd Pikeville KY 41501",
    "addr:housenumber":"194",
    "addr:postcode":"41501",
    "addr:street":"Johns Creek Rd",
    "iso:country":"US",
    "sg:address":"194 Johns Creek Rd",
    "sg:city":"Pikeville",
    "sg:classifiers":[
        {
            "category":"Food & Beverages",
            "subcategory":"Groceries & Convenience Stores",
            "type":"Retail Goods"
        }
    ],
    "sg:phone":"+1 606 432 1192",
    "sg:postcode":"41501",
    "sg:province":"KY",
    "sg:tags":[
        "grocer"
    ],
    "wof:name":"Clevinger's Grocery",
    "wof:placetype":"venue"
},
  "geometry": {"coordinates":[-82.437431,37.568248],"type":"Point"}
}