{
  "type": "Feature",
  "properties": {
    "addr:full":"902 N Main St Barbourville KY 40906",
    "addr:housenumber":"902",
    "addr:postcode":"40906",
    "addr:street":"N Main St",
    "iso:country":"US",
    "sg:address":"902 N Main St",
    "sg:city":"Barbourville",
    "sg:classifiers":[
        {
            "category":"Food & Beverages",
            "subcategory":"Groceries & Convenience Stores",
            "type":"Retail Goods"
        }
    ],
    "sg:phone":"+1 606 546 3217",
    "sg:postcode":"40906",
    "sg:province":"KY",
    "wof:name":"Handy Mart",
    "wof:placetype":"venue"
},
  "geometry": {"coordinates":[-83.896002,36.875265],"type":"Point"}
}