{
  "type": "Feature",
  "properties": {
    "addr:full":"202 Parrot Dr Clarksville KY 37042",
    "addr:housenumber":"202",
    "addr:postcode":"37042",
    "addr:street":"Parrot Dr",
    "iso:country":"US",
    "sg:address":"202 Parrot Dr",
    "sg:city":"Clarksville",
    "sg:classifiers":[
        {
            "category":"Shopping",
            "subcategory":"Computers & Home Electronics",
            "type":"Retail Goods"
        }
    ],
    "sg:phone":"+1 931 920 3650",
    "sg:postcode":"37042",
    "sg:province":"KY",
    "sg:tags":[
        "consumer"
    ],
    "wof:name":"Audiovisions",
    "wof:placetype":"venue"
},
  "geometry": {"coordinates":[-87.404983,36.594482],"type":"Point"}
}