{
  "type": "Feature",
  "properties": {
    "addr:full":"6293 Beaver Rd Union KY 41091",
    "addr:housenumber":"6293",
    "addr:postcode":"41091",
    "addr:street":"Beaver Rd",
    "iso:country":"US",
    "sg:address":"6293 Beaver Rd",
    "sg:city":"Union",
    "sg:classifiers":[
        {
            "category":"Building & Trades",
            "subcategory":"Equipment Rental",
            "type":"Services"
        }
    ],
    "sg:phone":"+1 859 689 1666",
    "sg:postcode":"41091",
    "sg:province":"KY",
    "sg:tags":[
        "scaffolding"
    ],
    "wof:name":"Safeway",
    "wof:placetype":"venue"
},
  "geometry": {"coordinates":[-84.84343800000001,38.914774],"type":"Point"}
}