{
  "type": "Feature",
  "properties": {
    "iso:country":"US",
    "sg:address":"602 Pollard Rd",
    "sg:city":"Ashland",
    "sg:classifiers":[
        {
            "category":"Building & Trades",
            "subcategory":"Construction",
            "type":"Services"
        }
    ],
    "sg:phone":"+1 606 324 9731",
    "sg:postcode":"41101",
    "sg:province":"KY",
    "sg:tags":[
        "painter"
    ],
    "wof:name":"Duley's Painting & Decorating",
    "wof:placetype":"venue"
},
  "geometry": {"coordinates":[-82.6544,38.47347],"type":"Point"}
}