{
  "type": "Feature",
  "properties": {
    "iso:country":"US",
    "sg:address":"1401 Scottsville Rd",
    "sg:city":"Bowling Green",
    "sg:classifiers":[
        {
            "category":"Professional",
            "subcategory":"Business Services",
            "type":"Services"
        }
    ],
    "sg:phone":"+1 270 781 4942",
    "sg:postcode":"42104",
    "sg:province":"KY",
    "sg:tags":[
        "interior",
        "consultant",
        "design",
        "decorator"
    ],
    "wof:name":"Betty Thomas Interiors",
    "wof:placetype":"venue"
},
  "geometry": {"coordinates":[-86.437011,36.976009],"type":"Point"}
}