{
  "type": "Feature",
  "properties": {
    "iso:country":"US",
    "sg:address":"3419 Cedar Tree Ln",
    "sg:city":"Erlanger",
    "sg:classifiers":[
        {
            "category":"Shopping",
            "subcategory":"Books",
            "type":"Retail Goods"
        }
    ],
    "sg:phone":"+1 859 283 5178",
    "sg:postcode":"41018",
    "sg:province":"KY",
    "wof:name":"Legend Comics",
    "wof:placetype":"venue"
},
  "geometry": {"coordinates":[-84.61882199999999,39.035925],"type":"Point"}
}