{
  "type": "Feature",
  "properties": {
    "iso:country":"US",
    "sg:address":"2221 Douglass Blvd",
    "sg:city":"Louisville",
    "sg:classifiers":[
        {
            "category":"Communications",
            "type":"Services"
        }
    ],
    "sg:phone":"+1 502 451 7016",
    "sg:postcode":"40205",
    "sg:province":"KY",
    "sg:tags":[
        "paging",
        "signaling"
    ],
    "sg:website":"http://www.pagesandpcs.com",
    "wof:name":"Cane Run Save",
    "wof:placetype":"venue"
},
  "geometry": {"coordinates":[-85.68752600000001,38.227832],"type":"Point"}
}