{
  "type": "Feature",
  "properties": {
    "addr:full":"2200 Old Higbee Mill Rd Lexington KY 40514",
    "addr:housenumber":"2200",
    "addr:postcode":"40514",
    "addr:street":"Old Higbee Mill Rd",
    "iso:country":"US",
    "sg:address":"2200 Old Higbee Mill Rd",
    "sg:city":"Lexington",
    "sg:classifiers":[
        {
            "category":"Autos & Motor Vehicles",
            "subcategory":"Auto Supplies",
            "type":"Retail Goods"
        },
        {
            "category":"Wholesale",
            "subcategory":"Auto Parts",
            "type":"Manufacturing & Wholesale Goods"
        }
    ],
    "sg:phone":"+1 859 223 4559",
    "sg:postcode":"40514",
    "sg:province":"KY",
    "sg:tags":[
        "wheel",
        "vehicles-supplies",
        "drive",
        "four",
        "equipment",
        "truck"
    ],
    "wof:name":"Waits A Sales & Service",
    "wof:placetype":"venue"
},
  "geometry": {"coordinates":[-84.579671,37.99494],"type":"Point"}
}