{
  "type": "Feature",
  "properties": {
    "iso:country":"US",
    "sg:address":"2046 Hancock Valley Dr",
    "sg:city":"Winchester",
    "sg:classifiers":[
        {
            "category":"Wholesale",
            "subcategory":"Groceries",
            "type":"Manufacturing & Wholesale Goods"
        }
    ],
    "sg:phone":"+1 859 744 6931",
    "sg:postcode":"40391",
    "sg:province":"KY",
    "sg:tags":[
        "food",
        "product"
    ],
    "wof:name":"Pro-Nutech Inc",
    "wof:placetype":"venue"
},
  "geometry": {"coordinates":[-84.262602,38.035114],"type":"Point"}
}