{
  "type": "Feature",
  "properties": {
    "iso:country":"US",
    "sg:address":"1700 Fortune Dr",
    "sg:city":"Winchester",
    "sg:classifiers":[
        {
            "category":"Retail",
            "subcategory":"Repair Shop",
            "type":"Services"
        }
    ],
    "sg:phone":"+1 859 745 0016",
    "sg:postcode":"40391",
    "sg:province":"KY",
    "sg:tags":[
        "tractor"
    ],
    "wof:name":"S & W Truck & Trailer Svc",
    "wof:placetype":"venue"
},
  "geometry": {"coordinates":[-84.184246,38.023047],"type":"Point"}
}