{
  "type": "Feature",
  "properties": {
    "iso:country":"US",
    "sg:address":"1004 Brookhaven Rd",
    "sg:city":"Franklin",
    "sg:classifiers":[
        {
            "category":"Health Services",
            "subcategory":"Health Practitioner",
            "type":"Services"
        }
    ],
    "sg:phone":"+1 270 586 4479",
    "sg:postcode":"42134",
    "sg:province":"KY",
    "sg:tags":[
        "therapist",
        "physical"
    ],
    "wof:name":"Advanced Physical Therapy",
    "wof:placetype":"venue"
},
  "geometry": {"coordinates":[-86.57623100000001,36.703997],"type":"Point"}
}