{
  "type": "Feature",
  "properties": {
    "addr:full":"2222 Hikes Ln Louisville KY 40218",
    "addr:housenumber":"2222",
    "addr:postcode":"40218",
    "addr:street":"Hikes Ln",
    "iso:country":"US",
    "sg:address":"2222 Hikes Ln",
    "sg:city":"Louisville",
    "sg:classifiers":[
        {
            "category":"Health Services",
            "subcategory":"Chiropractor",
            "type":"Services"
        }
    ],
    "sg:phone":"+1 502 458 0000",
    "sg:postcode":"40218",
    "sg:province":"KY",
    "wof:name":"Back Pain Ctr",
    "wof:placetype":"venue"
},
  "geometry": {"coordinates":[-85.657444,38.200485],"type":"Point"}
}