{
  "type": "Feature",
  "properties": {
    "iso:country":"US",
    "sg:address":"625 Denver Ave",
    "sg:city":"Paducah",
    "sg:classifiers":[
        {
            "category":"Wholesale",
            "subcategory":"Hardware",
            "type":"Manufacturing & Wholesale Goods"
        }
    ],
    "sg:phone":"+1 270 554 5924",
    "sg:postcode":"42001",
    "sg:province":"KY",
    "wof:name":"Burcham Terence Elec Coolg Htg",
    "wof:placetype":"venue"
},
  "geometry": {"coordinates":[-88.67515899999999,37.037574],"type":"Point"}
}