{
  "type": "Feature",
  "properties": {
    "iso:country":"US",
    "sg:address":"1065 Ashley St",
    "sg:city":"Bowling Green",
    "sg:classifiers":[
        {
            "category":"Banks & Credit Unions",
            "subcategory":"Investment Brokerage",
            "type":"Services"
        }
    ],
    "sg:phone":"+1 270 846 7822",
    "sg:postcode":"42103",
    "sg:province":"KY",
    "sg:tags":[
        "security"
    ],
    "wof:name":"Morgan Stanley",
    "wof:placetype":"venue"
},
  "geometry": {"coordinates":[-86.430128,36.966954],"type":"Point"}
}