{
  "type": "Feature",
  "properties": {
    "iso:country":"US",
    "sg:address":"933 Goss Ave",
    "sg:city":"Louisville",
    "sg:classifiers":[
        {
            "category":"Social Services",
            "type":"Services"
        }
    ],
    "sg:phone":"+1 502 636 4646",
    "sg:postcode":"40217",
    "sg:province":"KY",
    "sg:website":"http://www.voaky.org",
    "wof:name":"Nashville Volunteers Of America Living Center, Inc",
    "wof:placetype":"venue"
},
  "geometry": {"coordinates":[-85.73898699999999,38.229459],"type":"Point"}
}