{
  "type": "Feature",
  "properties": {
    "iso:country":"US",
    "sg:address":"118 Marion Pike",
    "sg:city":"Ironton",
    "sg:classifiers":[
        {
            "category":"Restaurant",
            "type":"Food & Drink"
        }
    ],
    "sg:phone":"+1 740 532 8878",
    "sg:postcode":"45638",
    "sg:province":"OH",
    "sg:tags":[
        "operates"
    ],
    "wof:name":"L & J Tops Okreem Inc",
    "wof:placetype":"venue"
},
  "geometry": {"coordinates":[-82.64774,38.501539],"type":"Point"}
}