{
  "type": "Feature",
  "properties": {
    "addr:full":"640 S 4th St Ste 210 Louisville KY 40202",
    "addr:housenumber":"640",
    "addr:postcode":"40202",
    "addr:street":"S 4Th St Ste 210",
    "iso:country":"US",
    "sg:address":"640 S 4th St Ste 210",
    "sg:city":"Louisville",
    "sg:classifiers":[
        {
            "category":"Real Estate",
            "subcategory":"Architect",
            "type":"Services"
        }
    ],
    "sg:phone":"+1 502 587 3420",
    "sg:postcode":"40202",
    "sg:province":"KY",
    "sg:tags":[
        "architects'",
        "specification",
        "builders'",
        "construction",
        "architectural",
        "engineer"
    ],
    "sg:website":"http://www.coxallen.com",
    "wof:name":"Allen Cox And Associates Architects Inc",
    "wof:placetype":"venue"
},
  "geometry": {"coordinates":[-85.758104,38.247423],"type":"Point"}
}