{
  "type": "Feature",
  "properties": {
    "addr:full":"137 Old Post Rd Paris KY 40361",
    "addr:housenumber":"137",
    "addr:postcode":"40361",
    "addr:street":"Old Post Rd",
    "iso:country":"US",
    "sg:address":"137 Old Post Rd",
    "sg:city":"Paris",
    "sg:classifiers":[
        {
            "category":"Retail",
            "subcategory":"Repair Shop",
            "type":"Services"
        }
    ],
    "sg:phone":"+1 859 987 4474",
    "sg:postcode":"40361",
    "sg:province":"KY",
    "sg:tags":[
        "appliance"
    ],
    "wof:name":"Downing Repair Svc",
    "wof:placetype":"venue"
},
  "geometry": {"coordinates":[-84.277608,38.180801],"type":"Point"}
}