{
  "type": "Feature",
  "properties": {
    "addr:full":"429 Walker Parke Rd Richmond KY 40475",
    "addr:housenumber":"429",
    "addr:postcode":"40475",
    "addr:street":"Walker Parke Rd",
    "iso:country":"US",
    "sg:address":"429 Walker Parke Rd",
    "sg:city":"Richmond",
    "sg:classifiers":[
        {
            "category":"Farming",
            "subcategory":"Livestock Farm",
            "type":"Manufacturing & Wholesale Goods"
        }
    ],
    "sg:phone":"+1 859 624 2346",
    "sg:postcode":"40475",
    "sg:province":"KY",
    "sg:tags":[
        "beef",
        "feedlot",
        "cattle"
    ],
    "wof:name":"Carl Hoover",
    "wof:placetype":"venue"
},
  "geometry": {"coordinates":[-84.193607,37.824246],"type":"Point"}
}