{
  "type": "Feature",
  "properties": {
    "iso:country":"US",
    "sg:address":"1718 Bryan Station Rd",
    "sg:city":"Lexington",
    "sg:classifiers":[
        {
            "category":"Organizations",
            "subcategory":"Religious Organization",
            "type":"Services"
        }
    ],
    "sg:phone":"+1 859 299 2780",
    "sg:postcode":"40505",
    "sg:province":"KY",
    "sg:tags":[
        "church"
    ],
    "wof:name":"Lexington Korean Presbyterian",
    "wof:placetype":"venue"
},
  "geometry": {"coordinates":[-84.459119,38.061715],"type":"Point"}
}