{
  "type": "Feature",
  "properties": {
    "addr:full":"198 Computrex Dr Nicholasville KY 40356",
    "addr:housenumber":"198",
    "addr:postcode":"40356",
    "addr:street":"Computrex Dr",
    "iso:country":"US",
    "sg:address":"198 Computrex Dr",
    "sg:city":"Nicholasville",
    "sg:classifiers":[
        {
            "category":"Professional",
            "type":"Services"
        }
    ],
    "sg:phone":"+1 859 881 3996",
    "sg:postcode":"40356",
    "sg:province":"KY",
    "sg:tags":[
        "establishment"
    ],
    "wof:name":"Collins Dental",
    "wof:placetype":"venue"
},
  "geometry": {"coordinates":[-84.554323,37.935678],"type":"Point"}
}