{
  "type": "Feature",
  "properties": {
    "addr:full":"501 Forest Ave Maysville KY 41056",
    "addr:housenumber":"501",
    "addr:postcode":"41056",
    "addr:street":"Forest Ave",
    "iso:country":"US",
    "sg:address":"501 Forest Ave",
    "sg:city":"Maysville",
    "sg:classifiers":[
        {
            "category":"Organizations",
            "subcategory":"Religious Organization",
            "type":"Services"
        }
    ],
    "sg:phone":"+1 606 564 5862",
    "sg:postcode":"41056",
    "sg:province":"KY",
    "sg:tags":[
        "church"
    ],
    "wof:name":"Bethel Baptist Church",
    "wof:placetype":"venue"
},
  "geometry": {"coordinates":[-83.753249,38.642461],"type":"Point"}
}