{
  "type": "Feature",
  "properties": {
    "iso:country":"US",
    "sg:address":"11165 Frontage Rd",
    "sg:city":"Burlington",
    "sg:classifiers":[
        {
            "category":"Travel",
            "subcategory":"Hotels & Motels",
            "type":"Entertainment"
        }
    ],
    "sg:phone":"+1 859 485 4123",
    "sg:postcode":"41005",
    "sg:province":"KY",
    "wof:name":"Econo Lodge",
    "wof:placetype":"venue"
},
  "geometry": {"coordinates":[-84.716103,39.0238],"type":"Point"}
}