{
  "type": "Feature",
  "properties": {
    "addr:full":"6020 Highgrade Dr Louisville KY 40291",
    "addr:housenumber":"6020",
    "addr:postcode":"40291",
    "addr:street":"Highgrade Dr",
    "iso:country":"US",
    "sg:address":"6020 Highgrade Dr",
    "sg:city":"Louisville",
    "sg:classifiers":[
        {
            "category":"Professional",
            "subcategory":"Business Services",
            "type":"Services"
        }
    ],
    "sg:phone":"+1 502 969 0766",
    "sg:postcode":"40291",
    "sg:province":"KY",
    "wof:name":"Doug Bibelhauser",
    "wof:placetype":"venue"
},
  "geometry": {"coordinates":[-85.61023299999999,38.161069],"type":"Point"}
}