{
  "type": "Feature",
  "properties": {
    "iso:country":"US",
    "sg:address":"275 Conover Ln",
    "sg:city":"Columbia",
    "sg:classifiers":[
        {
            "category":"Professional",
            "subcategory":"Business Services",
            "type":"Services"
        }
    ],
    "sg:phone":"+1 270 384 2772",
    "sg:postcode":"42728",
    "sg:province":"KY",
    "wof:name":"David D Upchurch",
    "wof:placetype":"venue"
},
  "geometry": {"coordinates":[-85.278308,37.088398],"type":"Point"}
}