{
  "type": "Feature",
  "properties": {
    "addr:full":"107 S 4th St Paducah KY 42001",
    "addr:housenumber":"107",
    "addr:postcode":"42001",
    "addr:street":"S 4Th St",
    "iso:country":"US",
    "sg:address":"107 S 4th St",
    "sg:city":"Paducah",
    "sg:classifiers":[
        {
            "category":"Personal",
            "subcategory":"Shoe Repair & Shine",
            "type":"Services"
        }
    ],
    "sg:phone":"+1 270 444 6454",
    "sg:postcode":"42001",
    "sg:province":"KY",
    "sg:tags":[
        "repairing",
        "boot"
    ],
    "wof:name":"Boaz Fourth Street Shoe Shop",
    "wof:placetype":"venue"
},
  "geometry": {"coordinates":[-88.598094,37.086622],"type":"Point"}
}