{
  "type": "Feature",
  "properties": {
    "addr:full":"2671 King's Church Rd Taylorsville KY 40071",
    "addr:housenumber":"2671",
    "addr:postcode":"40071",
    "addr:street":"King'S Church Rd",
    "iso:country":"US",
    "sg:address":"2671 King's Church Rd",
    "sg:city":"Taylorsville",
    "sg:classifiers":[
        {
            "category":"Professional",
            "type":"Services"
        }
    ],
    "sg:phone":"+1 502 817 3373",
    "sg:postcode":"40071",
    "sg:province":"KY",
    "wof:name":"At Your Convenience Mobile Svc",
    "wof:placetype":"venue"
},
  "geometry": {"coordinates":[-85.483903,38.088893],"type":"Point"}
}