{
  "type": "Feature",
  "properties": {
    "addr:full":"1405 Rufer Ave Louisville KY 40204",
    "addr:housenumber":"1405",
    "addr:postcode":"40204",
    "addr:street":"Rufer Ave",
    "iso:country":"US",
    "sg:address":"1405 Rufer Ave",
    "sg:city":"Louisville",
    "sg:classifiers":[
        {
            "category":"Building & Trades",
            "subcategory":"Landscaping Services",
            "type":"Services"
        }
    ],
    "sg:phone":"+1 502 794 3449",
    "sg:postcode":"40204",
    "sg:province":"KY",
    "sg:tags":[
        "consultant",
        "lawn",
        "designer",
        "landscape",
        "contractor"
    ],
    "wof:name":"Invision Gardens Landscaping Co-",
    "wof:placetype":"venue"
},
  "geometry": {"coordinates":[-85.725114,38.235652],"type":"Point"}
}