{
  "type": "Feature",
  "properties": {
    "iso:country":"US",
    "sg:address":"439 Dudley Pike",
    "sg:city":"Edgewood",
    "sg:classifiers":[
        {
            "category":"Wholesale",
            "subcategory":"Medical Equipment & Supplies",
            "type":"Manufacturing & Wholesale Goods"
        }
    ],
    "sg:phone":"+1 859 331 0300",
    "sg:postcode":"41017",
    "sg:province":"KY",
    "sg:tags":[
        "dental"
    ],
    "wof:name":"Americana Distributing Co",
    "wof:placetype":"venue"
},
  "geometry": {"coordinates":[-84.562423,39.006669],"type":"Point"}
}