{
  "type": "Feature",
  "properties": {
    "iso:country":"US",
    "sg:address":"3519 Ramona Ave",
    "sg:city":"Louisville",
    "sg:classifiers":[
        {
            "category":"Professional",
            "subcategory":"Computer Services",
            "type":"Services"
        }
    ],
    "sg:phone":"+1 502 238 3555",
    "sg:postcode":"40220",
    "sg:province":"KY",
    "sg:tags":[
        "datum"
    ],
    "wof:name":"Blazing Web Pages",
    "wof:placetype":"venue"
},
  "geometry": {"coordinates":[-85.654679,38.212612],"type":"Point"}
}