{
  "type": "Feature",
  "properties": {
    "addr:full":"104 Woodhill Rd Bardstown KY 40004",
    "addr:housenumber":"104",
    "addr:postcode":"40004",
    "addr:street":"Woodhill Rd",
    "iso:country":"US",
    "sg:address":"104 Woodhill Rd",
    "sg:city":"Bardstown",
    "sg:classifiers":[
        {
            "category":"Building & Trades",
            "subcategory":"Construction",
            "type":"Services"
        }
    ],
    "sg:phone":"+1 502 348 8723",
    "sg:postcode":"40004",
    "sg:province":"KY",
    "sg:tags":[
        "house"
    ],
    "wof:name":"Bright Builders LLC",
    "wof:placetype":"venue"
},
  "geometry": {"coordinates":[-85.40655599999999,37.822753],"type":"Point"}
}