{
  "type": "Feature",
  "properties": {
    "iso:country":"US",
    "sg:address":"2245 Winchester Ave",
    "sg:city":"Ashland",
    "sg:classifiers":[
        {
            "category":"Health Services",
            "subcategory":"Doctor",
            "type":"Services"
        }
    ],
    "sg:phone":"+1 606 324 1996",
    "sg:postcode":"41101",
    "sg:province":"KY",
    "sg:tags":[
        "physician",
        "surgeon"
    ],
    "wof:name":"Tri-State Family Practice",
    "wof:placetype":"venue"
},
  "geometry": {"coordinates":[-82.631106,38.47451],"type":"Point"}
}