{
  "type": "Feature",
  "properties": {
    "iso:country":"US",
    "sg:address":"108 Division St",
    "sg:city":"Pikeville",
    "sg:classifiers":[
        {
            "category":"Professional",
            "subcategory":"Lawyer & Legal Services",
            "type":"Services"
        }
    ],
    "sg:phone":"+1 606 437 7777",
    "sg:postcode":"41501",
    "sg:province":"KY",
    "sg:tags":[
        "attorney"
    ],
    "wof:name":"Glen Martin Hammond Law Office",
    "wof:placetype":"venue"
},
  "geometry": {"coordinates":[-82.518882,37.48053],"type":"Point"}
}