{
  "type": "Feature",
  "properties": {
    "addr:full":"307 Comer Ave Horse Cave KY 42749",
    "addr:housenumber":"307",
    "addr:postcode":"42749",
    "addr:street":"Comer Ave",
    "iso:country":"US",
    "sg:address":"307 Comer Ave",
    "sg:city":"Horse Cave",
    "sg:classifiers":[
        {
            "category":"Professional",
            "subcategory":"Computer Services",
            "type":"Services"
        }
    ],
    "sg:phone":"+1 270 786 1521",
    "sg:postcode":"42749",
    "sg:province":"KY",
    "sg:tags":[
        "programming"
    ],
    "sg:website":"www.smcomputerservices.com",
    "wof:name":"S & M Computer Svc",
    "wof:placetype":"venue"
},
  "geometry": {"coordinates":[-85.901161,37.17461],"type":"Point"}
}