{
  "type": "Feature",
  "properties": {
    "iso:country":"US",
    "sg:address":"3822 N Mayo Trl",
    "sg:city":"Pikeville",
    "sg:classifiers":[
        {
            "category":"Banks & Credit Unions",
            "subcategory":"Bank",
            "type":"Services"
        }
    ],
    "sg:phone":"+1 606 437 6231",
    "sg:postcode":"41501",
    "sg:province":"KY",
    "wof:name":"Family Bank",
    "wof:placetype":"venue"
},
  "geometry": {"coordinates":[-82.567161,37.519737],"type":"Point"}
}