{
  "type": "Feature",
  "properties": {
    "addr:full":"104 Oxmoor Ct Louisville KY 40222",
    "addr:housenumber":"104",
    "addr:postcode":"40222",
    "addr:street":"Oxmoor Ct",
    "iso:country":"US",
    "sg:address":"104 Oxmoor Ct",
    "sg:city":"Louisville",
    "sg:classifiers":[
        {
            "category":"Restaurant",
            "type":"Food & Drink"
        }
    ],
    "sg:phone":"+1 502 423 9040",
    "sg:postcode":"40222",
    "sg:province":"KY",
    "sg:website":"www.bahamabreeze.com",
    "wof:name":"Bahama Breeze",
    "wof:placetype":"venue"
},
  "geometry": {"coordinates":[-85.616603,38.248381],"type":"Point"}
}