{
  "type": "Feature",
  "properties": {
    "iso:country":"US",
    "sg:address":"1100 US Hwy 127 S",
    "sg:city":"Frankfort",
    "sg:classifiers":[
        {
            "category":"Banks & Credit Unions",
            "subcategory":"Bank",
            "type":"Services"
        }
    ],
    "sg:phone":"+1 502 875 9044",
    "sg:postcode":"40601",
    "sg:province":"KY",
    "sg:tags":[
        "personal",
        "institution"
    ],
    "wof:name":"Beneficial",
    "wof:placetype":"venue"
},
  "geometry": {"coordinates":[-84.89655399999999,38.175664],"type":"Point"}
}