{
  "type": "Feature",
  "properties": {
    "iso:country":"US",
    "sg:address":"1289 Boonesborough Rd",
    "sg:city":"Richmond",
    "sg:classifiers":[
        {
            "category":"Government",
            "subcategory":"Fire Station",
            "type":"Public Place"
        }
    ],
    "sg:phone":"+1 859 626 5144",
    "sg:postcode":"40475",
    "sg:province":"KY",
    "sg:tags":[
        "department"
    ],
    "wof:name":"Whitehall Volunteer Fire Dept",
    "wof:placetype":"venue"
},
  "geometry": {"coordinates":[-84.32241,37.844843],"type":"Point"}
}