{
  "type": "Feature",
  "properties": {
    "iso:country":"US",
    "sg:address":"2247 Fedders Ct",
    "sg:city":"Fort Wright",
    "sg:classifiers":[
        {
            "category":"Organizations",
            "subcategory":"Religious Organization",
            "type":"Services"
        }
    ],
    "sg:phone":"+1 859 363 7710",
    "sg:postcode":"41017",
    "sg:province":"KY",
    "sg:tags":[
        "clergy"
    ],
    "wof:name":"Keith Blair",
    "wof:placetype":"venue"
},
  "geometry": {"coordinates":[-84.534514,38.977586],"type":"Point"}
}