{
  "type": "Feature",
  "properties": {
    "iso:country":"US",
    "sg:address":"101 Dale Dr",
    "sg:city":"Georgetown",
    "sg:classifiers":[
        {
            "category":"Real Estate",
            "subcategory":"Real Estate Operator",
            "type":"Services"
        }
    ],
    "sg:phone":"+1 502 863 5656",
    "sg:postcode":"40324",
    "sg:province":"KY",
    "sg:tags":[
        "management"
    ],
    "wof:name":"Spindle Mobile Home Park",
    "wof:placetype":"venue"
},
  "geometry": {"coordinates":[-84.54375,38.159625],"type":"Point"}
}