{
  "type": "Feature",
  "properties": {
    "iso:country":"US",
    "sg:address":"3330 Cougar Path",
    "sg:city":"Hebron",
    "sg:classifiers":[
        {
            "category":"Education",
            "subcategory":"School",
            "type":"Public Place"
        },
        {
            "category":"Organizations",
            "subcategory":"Religious Organization",
            "type":"Services"
        }
    ],
    "sg:phone":"+1 859 334 4420",
    "sg:postcode":"41048",
    "sg:province":"KY",
    "sg:tags":[
        "high",
        "middle",
        "elementary"
    ],
    "wof:name":"Schools-Public & Parochial",
    "wof:placetype":"venue"
},
  "geometry": {"coordinates":[-84.694153,39.060834],"type":"Point"}
}