{
  "type": "Feature",
  "properties": {
    "iso:country":"US",
    "sg:address":"4906 Bardstown Rd",
    "sg:city":"Fern Creek",
    "sg:classifiers":[
        {
            "category":"Health Services",
            "subcategory":"Doctor",
            "type":"Services"
        }
    ],
    "sg:phone":"+1 502 671 8443",
    "sg:postcode":"40291",
    "sg:province":"KY",
    "sg:tags":[
        "dentist"
    ],
    "wof:name":"Implant Group",
    "wof:placetype":"venue"
},
  "geometry": {"coordinates":[-85.61972299999999,38.177241],"type":"Point"}
}