{
  "type": "Feature",
  "properties": {
    "iso:country":"US",
    "sg:address":"4047 Mount Union Rd",
    "sg:city":"Scottsville",
    "sg:classifiers":[
        {
            "category":"Building & Trades",
            "subcategory":"Plumbing",
            "type":"Services"
        }
    ],
    "sg:phone":"+1 270 622 4412",
    "sg:postcode":"42164",
    "sg:province":"KY",
    "sg:tags":[
        "conditioning",
        "air",
        "system",
        "contractor"
    ],
    "sg:website":"www.youngselectrichvac.com",
    "wof:name":"Young's Electric Heating & Air",
    "wof:placetype":"venue"
},
  "geometry": {"coordinates":[-86.139011,36.681309],"type":"Point"}
}