{
  "type": "Feature",
  "properties": {
    "iso:country":"US",
    "sg:address":"301 E High St",
    "sg:city":"Lexington",
    "sg:classifiers":[
        {
            "category":"Communications",
            "subcategory":"Newspaper",
            "type":"Services"
        }
    ],
    "sg:phone":"+1 859 253 0455",
    "sg:postcode":"40507",
    "sg:province":"KY",
    "wof:name":"Bank Travel Management",
    "wof:placetype":"venue"
},
  "geometry": {"coordinates":[-84.494556,38.041333],"type":"Point"}
}