{
  "type": "Feature",
  "properties": {
    "addr:full":"4780 Bristow Rd Bowling Green KY 42103",
    "addr:housenumber":"4780",
    "addr:postcode":"42103",
    "addr:street":"Bristow Rd",
    "iso:country":"US",
    "sg:address":"4780 Bristow Rd",
    "sg:city":"Bowling Green",
    "sg:classifiers":[
        {
            "category":"Building & Trades",
            "subcategory":"Construction",
            "type":"Services"
        }
    ],
    "sg:phone":"+1 270 781 7700",
    "sg:postcode":"42103",
    "sg:province":"KY",
    "sg:tags":[
        "contractor"
    ],
    "wof:name":"South State Contractors Inc",
    "wof:placetype":"venue"
},
  "geometry": {"coordinates":[-86.290926,37.006331],"type":"Point"}
}