{
  "type": "Feature",
  "properties": {
    "addr:full":"770 Bates Rd Elizabethtown KY 42701",
    "addr:housenumber":"770",
    "addr:postcode":"42701",
    "addr:street":"Bates Rd",
    "iso:country":"US",
    "sg:address":"770 Bates Rd",
    "sg:city":"Elizabethtown",
    "sg:classifiers":[
        {
            "category":"Health Services",
            "subcategory":"Health Practitioner",
            "type":"Services"
        }
    ],
    "sg:phone":"+1 270 737 8404",
    "sg:postcode":"42701",
    "sg:province":"KY",
    "sg:tags":[
        "mammography"
    ],
    "wof:name":"Pamela Casper",
    "wof:placetype":"venue"
},
  "geometry": {"coordinates":[-85.848901,37.736978],"type":"Point"}
}