{
  "type": "Feature",
  "properties": {
    "addr:full":"4444 Dixie Hwy Louisville KY 40216",
    "addr:housenumber":"4444",
    "addr:postcode":"40216",
    "addr:street":"Dixie Hwy",
    "iso:country":"US",
    "sg:address":"4444 Dixie Hwy",
    "sg:city":"Louisville",
    "sg:classifiers":[
        {
            "category":"Travel",
            "subcategory":"Hotels & Motels",
            "type":"Entertainment"
        }
    ],
    "sg:phone":"+1 502 447 2096",
    "sg:postcode":"40216",
    "sg:province":"KY",
    "sg:tags":[
        "lodging"
    ],
    "sg:website":"http://www.comfortinn.com/hotel-louisville-kentucky-KY148",
    "wof:name":"Comfort Inn Louisville",
    "wof:placetype":"venue"
},
  "geometry": {"coordinates":[-85.816742,38.180229],"type":"Point"}
}