{
  "type": "Feature",
  "properties": {
    "iso:country":"US",
    "sg:address":"100 Payne Ave",
    "sg:city":"Georgetown",
    "sg:classifiers":[
        {
            "category":"Shopping",
            "subcategory":"Musical Instruments",
            "type":"Retail Goods"
        }
    ],
    "sg:phone":"+1 502 867 7890",
    "sg:postcode":"40324",
    "sg:province":"KY",
    "wof:name":"Backwoods Music Co",
    "wof:placetype":"venue"
},
  "geometry": {"coordinates":[-84.56014999999999,38.219237],"type":"Point"}
}