{
  "type": "Feature",
  "properties": {
    "iso:country":"US",
    "sg:address":"120 Hiawatha Trl",
    "sg:city":"Georgetown",
    "sg:classifiers":[
        {
            "category":"Real Estate",
            "subcategory":"Real Estate Operator",
            "type":"Services"
        }
    ],
    "sg:phone":"+1 502 863 4673",
    "sg:postcode":"40324",
    "sg:province":"KY",
    "sg:tags":[
        "apartment"
    ],
    "wof:name":"Indian Trace Apartments LTD",
    "wof:placetype":"venue"
},
  "geometry": {"coordinates":[-84.563637,38.199457],"type":"Point"}
}