{
  "type": "Feature",
  "properties": {
    "iso:country":"US",
    "sg:address":"233 Williamsburg Sq",
    "sg:city":"Owensboro",
    "sg:classifiers":[
        {
            "category":"Health Services",
            "subcategory":"Optometrist",
            "type":"Services"
        }
    ],
    "sg:phone":"+1 270 684 3234",
    "sg:postcode":"42303",
    "sg:province":"KY",
    "wof:name":"Jon A Skillman & Assoc",
    "wof:placetype":"venue"
},
  "geometry": {"coordinates":[-87.101364,37.746693],"type":"Point"}
}