{
  "type": "Feature",
  "properties": {
    "iso:country":"US",
    "sg:address":"235 Madison Square Dr",
    "sg:city":"Madisonville",
    "sg:classifiers":[
        {
            "category":"Shopping",
            "subcategory":"Department Store",
            "type":"Retail Goods"
        }
    ],
    "sg:phone":"+1 270 821 8861",
    "sg:postcode":"42431",
    "sg:province":"KY",
    "wof:name":"Young's",
    "wof:placetype":"venue"
},
  "geometry": {"coordinates":[-87.479983,37.324849],"type":"Point"}
}