{
  "type": "Feature",
  "properties": {
    "iso:country":"US",
    "sg:address":"9725 US Hwy 60 W",
    "sg:city":"Kevil",
    "sg:classifiers":[
        {
            "category":"Retail",
            "subcategory":"Auto Repair",
            "type":"Services"
        }
    ],
    "sg:phone":"+1 270 488 3656",
    "sg:postcode":"42053",
    "sg:province":"KY",
    "sg:tags":[
        "body",
        "automobile",
        "painting"
    ],
    "wof:name":"G & R Body Shop",
    "wof:placetype":"venue"
},
  "geometry": {"coordinates":[-88.811308,37.063044],"type":"Point"}
}