{
  "type": "Feature",
  "properties": {
    "iso:country":"US",
    "sg:address":"932 N Main St",
    "sg:city":"Hopkinsville",
    "sg:classifiers":[
        {
            "category":"Food & Beverages",
            "subcategory":"Groceries & Convenience Stores",
            "type":"Retail Goods"
        }
    ],
    "sg:phone":"+1 270 885 5231",
    "sg:postcode":"42240",
    "sg:province":"KY",
    "wof:name":"Pantry",
    "wof:placetype":"venue"
},
  "geometry": {"coordinates":[-87.481747,36.88227],"type":"Point"}
}