{
  "type": "Feature",
  "properties": {
    "iso:country":"US",
    "sg:address":"7813 Old Tree Run",
    "sg:city":"Louisville",
    "sg:classifiers":[
        {
            "category":"Professional",
            "subcategory":"Business Services",
            "type":"Services"
        }
    ],
    "sg:phone":"+1 502 429 6670",
    "sg:postcode":"40222",
    "sg:province":"KY",
    "sg:tags":[
        "commercial",
        "designers-industrial"
    ],
    "wof:name":"Design Factory",
    "wof:placetype":"venue"
},
  "geometry": {"coordinates":[-85.611603,38.259849],"type":"Point"}
}