{
  "type": "Feature",
  "properties": {
    "iso:country":"US",
    "sg:address":"309 S 6th St",
    "sg:city":"Bardstown",
    "sg:classifiers":[
        {
            "category":"Professional",
            "subcategory":"Art Services",
            "type":"Services"
        }
    ],
    "sg:phone":"+1 502 331 1803",
    "sg:postcode":"40004",
    "sg:province":"KY",
    "sg:tags":[
        "artist"
    ],
    "wof:name":"Black Pearl",
    "wof:placetype":"venue"
},
  "geometry": {"coordinates":[-85.472915,37.806436],"type":"Point"}
}