{
  "type": "Feature",
  "properties": {
    "iso:country":"US",
    "sg:address":"4617 Athens Boonesboro Rd",
    "sg:city":"Lexington",
    "sg:phone":"+1 859 263 3608",
    "sg:postcode":"40509",
    "sg:province":"KY",
    "sg:tags":[
        "farm",
        "tobacco"
    ],
    "wof:name":"L L Hanks Jr and Sons LLC",
    "wof:placetype":"venue"
},
  "geometry": {"coordinates":[-84.41132,37.975303],"type":"Point"}
}