{
  "type": "Feature",
  "properties": {
    "addr:full":"35 US Hwy 68 E Benton KY 42025",
    "addr:housenumber":"35",
    "addr:postcode":"42025",
    "addr:street":"Us Hwy 68 E",
    "iso:country":"US",
    "sg:address":"35 US Hwy 68 E",
    "sg:city":"Benton",
    "sg:classifiers":[
        {
            "category":"Autos & Motor Vehicles",
            "subcategory":"Fuel & Gas Station",
            "type":"Retail Goods"
        }
    ],
    "sg:phone":"+1 270 527 7262",
    "sg:postcode":"42025",
    "sg:province":"KY",
    "sg:tags":[
        "oil"
    ],
    "wof:name":"Leo's Lotto Gas",
    "wof:placetype":"venue"
},
  "geometry": {"coordinates":[-88.34324100000001,36.925429],"type":"Point"}
}