{
  "type": "Feature",
  "properties": {
    "addr:full":"403 S Green St Henderson KY 42420",
    "addr:housenumber":"403",
    "addr:postcode":"42420",
    "addr:street":"S Green St",
    "iso:country":"US",
    "sg:address":"403 S Green St",
    "sg:city":"Henderson",
    "sg:classifiers":[
        {
            "category":"Building & Trades",
            "subcategory":"Cleaning & Sanitation",
            "type":"Services"
        }
    ],
    "sg:phone":"+1 270 830 7505",
    "sg:postcode":"42420",
    "sg:province":"KY",
    "sg:tags":[
        "janitor"
    ],
    "wof:name":"Diversco",
    "wof:placetype":"venue"
},
  "geometry": {"coordinates":[-87.594206,37.832915],"type":"Point"}
}