{
  "type": "Feature",
  "properties": {
    "iso:country":"US",
    "sg:address":"12902 Shelbyville Rd",
    "sg:city":"Louisville",
    "sg:classifiers":[
        {
            "category":"Home & Garden",
            "subcategory":"Garden Supply",
            "type":"Retail Goods"
        },
        {
            "category":"Manufacturing",
            "subcategory":"Paper Products",
            "type":"Manufacturing & Wholesale Goods"
        }
    ],
    "sg:phone":"+1 502 245 5920",
    "sg:postcode":"40243",
    "sg:province":"KY",
    "sg:tags":[
        "equipment",
        "bamboo",
        "landscaping"
    ],
    "wof:name":"Otte Frank Nursery & Garden Centers",
    "wof:placetype":"venue"
},
  "geometry": {"coordinates":[-85.51562699999999,38.243224],"type":"Point"}
}