{
  "type": "Feature",
  "properties": {
    "addr:full":"4537 Clarks River Rd Paducah KY 42003",
    "addr:housenumber":"4537",
    "addr:postcode":"42003",
    "addr:street":"Clarks River Rd",
    "iso:country":"US",
    "sg:address":"4537 Clarks River Rd",
    "sg:city":"Paducah",
    "sg:classifiers":[
        {
            "category":"Shopping Center",
            "type":"Public Place"
        }
    ],
    "sg:phone":"+1 270 898 8919",
    "sg:postcode":"42003",
    "sg:province":"KY",
    "sg:tags":[
        "mall"
    ],
    "wof:name":"James Enterprises Inc",
    "wof:placetype":"venue"
},
  "geometry": {"coordinates":[-88.563053,37.048296],"type":"Point"}
}