{
  "type": "Feature",
  "properties": {
    "addr:full":"10609 Dixie Hwy Valley Station KY 40272",
    "addr:housenumber":"10609",
    "addr:postcode":"40272",
    "addr:street":"Dixie Hwy Valley",
    "iso:country":"US",
    "sg:address":"10609 Dixie Hwy",
    "sg:city":"Valley Station",
    "sg:classifiers":[
        {
            "category":"Shopping",
            "subcategory":"Gifts & Souvenirs",
            "type":"Retail Goods"
        }
    ],
    "sg:phone":"+1 502 933 3838",
    "sg:postcode":"40272",
    "sg:province":"KY",
    "sg:tags":[
        "shop"
    ],
    "wof:name":"Car-Mo Gifts",
    "wof:placetype":"venue"
},
  "geometry": {"coordinates":[-85.871801,38.099127],"type":"Point"}
}