{
  "type": "Feature",
  "properties": {
    "iso:country":"US",
    "sg:address":"640 Reynolds Rd",
    "sg:city":"Glasgow",
    "sg:classifiers":[
        {
            "category":"Retail",
            "subcategory":"Repair Shop",
            "type":"Services"
        }
    ],
    "sg:phone":"+1 270 651 3890",
    "sg:postcode":"42141",
    "sg:province":"KY",
    "sg:tags":[
        "welding"
    ],
    "wof:name":"Young & Furlong Welding Shop",
    "wof:placetype":"venue"
},
  "geometry": {"coordinates":[-85.93621,37.009516],"type":"Point"}
}