{
  "type": "Feature",
  "properties": {
    "iso:country":"US",
    "sg:address":"800 Floyd Dr",
    "sg:city":"Lexington",
    "sg:classifiers":[
        {
            "category":"Autos & Motor Vehicles",
            "subcategory":"Auto Supplies",
            "type":"Retail Goods"
        }
    ],
    "sg:phone":"+1 859 255 3142",
    "sg:postcode":"40505",
    "sg:province":"KY",
    "sg:tags":[
        "equipment",
        "racing",
        "car",
        "automobile"
    ],
    "wof:name":"Horsepower House",
    "wof:placetype":"venue"
},
  "geometry": {"coordinates":[-84.46084500000001,38.04996],"type":"Point"}
}