{
  "type": "Feature",
  "properties": {
    "iso:country":"US",
    "sg:address":"2747 Mercedes Dr",
    "sg:city":"Owensboro",
    "sg:classifiers":[
        {
            "category":"Building & Trades",
            "subcategory":"Landscaping Services",
            "type":"Services"
        }
    ],
    "sg:phone":"+1 270 683 8050",
    "sg:postcode":"42301",
    "sg:province":"KY",
    "wof:name":"A1 Discount Lawn & Land",
    "wof:placetype":"venue"
},
  "geometry": {"coordinates":[-87.14489,37.767255],"type":"Point"}
}