{
  "type": "Feature",
  "properties": {
    "addr:full":"281 Big Run Rd Lexington KY 40503",
    "addr:housenumber":"281",
    "addr:postcode":"40503",
    "addr:street":"Big Run Rd",
    "iso:country":"US",
    "sg:address":"281 Big Run Rd",
    "sg:city":"Lexington",
    "sg:classifiers":[
        {
            "category":"Manufacturing",
            "subcategory":"Electronics",
            "type":"Manufacturing & Wholesale Goods"
        }
    ],
    "sg:phone":"+1 859 276 3705",
    "sg:postcode":"40503",
    "sg:province":"KY",
    "sg:tags":[
        "equipment",
        "electronic",
        "supply"
    ],
    "wof:name":"Lex-Pro",
    "wof:placetype":"venue"
},
  "geometry": {"coordinates":[-84.527035,37.999031],"type":"Point"}
}