{
  "type": "Feature",
  "properties": {
    "addr:full":"1111 State Hwy 122 Martin KY 41649",
    "addr:housenumber":"1111",
    "addr:postcode":"41649",
    "addr:street":"State Hwy 122",
    "iso:country":"US",
    "sg:address":"1111 State Hwy 122",
    "sg:city":"Martin",
    "sg:classifiers":[
        {
            "category":"Banks & Credit Unions",
            "subcategory":"Bank",
            "type":"Services"
        }
    ],
    "sg:phone":"+1 606 285 0054",
    "sg:postcode":"41649",
    "sg:province":"KY",
    "sg:tags":[
        "loan",
        "real estate"
    ],
    "wof:name":"A Plus Mortgage",
    "wof:placetype":"venue"
},
  "geometry": {"coordinates":[-82.77774100000001,37.576131],"type":"Point"}
}