{
  "type": "Feature",
  "properties": {
    "iso:country":"US",
    "sg:address":"711 Martin Luther King Jr Blvd",
    "sg:city":"Ashland",
    "sg:classifiers":[
        {
            "category":"Home & Garden",
            "subcategory":"Furniture",
            "type":"Retail Goods"
        }
    ],
    "sg:phone":"+1 606 920 7660",
    "sg:postcode":"41101",
    "sg:province":"KY",
    "wof:name":"DFW Furniture Warehouse",
    "wof:placetype":"venue"
},
  "geometry": {"coordinates":[-82.646196,38.478575],"type":"Point"}
}