{
  "type": "Feature",
  "properties": {
    "iso:country":"US",
    "sg:address":"2624 Old Lebanon Rd",
    "sg:city":"Campbellsville",
    "sg:classifiers":[
        {
            "category":"Shopping",
            "type":"Retail Goods"
        }
    ],
    "sg:phone":"+1 270 465 8104",
    "sg:postcode":"42718",
    "sg:province":"KY",
    "sg:tags":[
        "monument"
    ],
    "wof:name":"Mc Kinley Monument Co",
    "wof:placetype":"venue"
},
  "geometry": {"coordinates":[-85.345375,37.376857],"type":"Point"}
}