{
  "type": "Feature",
  "properties": {
    "addr:full":"770 State Hwy 2022 Buckhorn KY 41721",
    "addr:housenumber":"770",
    "addr:postcode":"2022;41721",
    "addr:street":"State Hwy",
    "iso:country":"US",
    "sg:address":"770 State Hwy 2022",
    "sg:city":"Buckhorn",
    "sg:classifiers":[
        {
            "category":"Building & Trades",
            "subcategory":"Construction",
            "type":"Services"
        }
    ],
    "sg:phone":"+1 606 398 7270",
    "sg:postcode":"41721",
    "sg:province":"KY",
    "sg:tags":[
        "house"
    ],
    "wof:name":"Elisha Abner Inc",
    "wof:placetype":"venue"
},
  "geometry": {"coordinates":[-83.498661,37.331894],"type":"Point"}
}