{
  "type": "Feature",
  "properties": {
    "addr:full":"128 Macarthur Ct Nicholasville KY 40356",
    "addr:housenumber":"128",
    "addr:postcode":"40356",
    "addr:street":"Macarthur Ct",
    "iso:country":"US",
    "sg:address":"128 Macarthur Ct",
    "sg:city":"Nicholasville",
    "sg:classifiers":[
        {
            "category":"Manufacturing",
            "subcategory":"Metals",
            "type":"Manufacturing & Wholesale Goods"
        }
    ],
    "sg:phone":"+1 859 881 0205",
    "sg:postcode":"40356",
    "sg:province":"KY",
    "wof:name":"Pass Industries Inc",
    "wof:placetype":"venue"
},
  "geometry": {"coordinates":[-84.538631,37.93747],"type":"Point"}
}