{
  "type": "Feature",
  "properties": {
    "addr:full":"3610 Camp Ground Rd Louisville KY 40211",
    "addr:housenumber":"3610",
    "addr:postcode":"40211",
    "addr:street":"Camp Ground Rd",
    "iso:country":"US",
    "sg:address":"3610 Camp Ground Rd",
    "sg:city":"Louisville",
    "sg:classifiers":[
        {
            "category":"Utilities",
            "subcategory":"Refuse",
            "type":"Services"
        }
    ],
    "sg:phone":"+1 502 772 1942",
    "sg:postcode":"40211",
    "sg:province":"KY",
    "sg:tags":[
        "truck",
        "dump"
    ],
    "wof:name":"Pjax, Inc.",
    "wof:placetype":"venue"
},
  "geometry": {"coordinates":[-85.82746299999999,38.213863],"type":"Point"}
}