{
  "type": "Feature",
  "properties": {
    "addr:full":"115 Brooks St Elizabethtown KY 42701",
    "addr:housenumber":"115",
    "addr:postcode":"42701",
    "addr:street":"Brooks St",
    "iso:country":"US",
    "sg:address":"115 Brooks St",
    "sg:city":"Elizabethtown",
    "sg:classifiers":[
        {
            "category":"Professional",
            "subcategory":"Business Services",
            "type":"Services"
        }
    ],
    "sg:phone":"+1 270 765 4234",
    "sg:postcode":"42701",
    "sg:province":"KY",
    "wof:name":"Watts Shafter",
    "wof:placetype":"venue"
},
  "geometry": {"coordinates":[-85.848839,37.703134],"type":"Point"}
}