{
  "type": "Feature",
  "properties": {
    "iso:country":"US",
    "sg:address":"814 Euclid Ave",
    "sg:city":"Lexington",
    "sg:classifiers":[
        {
            "category":"Shopping",
            "type":"Retail Goods"
        }
    ],
    "sg:phone":"+1 859 885 0282",
    "sg:postcode":"40502",
    "sg:province":"KY",
    "sg:tags":[
        "merchandise"
    ],
    "wof:name":"Josephines Post Mastectomy Sp",
    "wof:placetype":"venue"
},
  "geometry": {"coordinates":[-84.490667,38.029649],"type":"Point"}
}