{
  "type": "Feature",
  "properties": {
    "addr:full":"1700 Old Lebanon Rd Campbellsville KY 42718",
    "addr:housenumber":"1700",
    "addr:postcode":"42718",
    "addr:street":"Old Lebanon Rd",
    "iso:country":"US",
    "sg:address":"1700 Old Lebanon Rd",
    "sg:city":"Campbellsville",
    "sg:classifiers":[
        {
            "category":"Building & Trades",
            "subcategory":"Construction",
            "type":"Services"
        }
    ],
    "sg:phone":"+1 270 469 2036",
    "sg:postcode":"42718",
    "sg:province":"KY",
    "sg:tags":[
        "contractor"
    ],
    "wof:name":"Wehr Construction",
    "wof:placetype":"venue"
},
  "geometry": {"coordinates":[-85.339156,37.365308],"type":"Point"}
}