{
  "type": "Feature",
  "properties": {
    "iso:country":"US",
    "sg:address":"1051 Bryant Way",
    "sg:city":"Bowling Green",
    "sg:classifiers":[
        {
            "category":"Personal",
            "subcategory":"Beauty Salon",
            "type":"Services"
        }
    ],
    "sg:phone":"+1 270 843 8737",
    "sg:postcode":"42103",
    "sg:province":"KY",
    "wof:name":"Studio 1 Hair Designers",
    "wof:placetype":"venue"
},
  "geometry": {"coordinates":[-86.42252999999999,36.949189],"type":"Point"}
}