{
  "type": "Feature",
  "properties": {
    "iso:country":"US",
    "sg:address":"104 S Vine St",
    "sg:city":"Somerset",
    "sg:classifiers":[
        {
            "category":"Shopping",
            "subcategory":"Stationery & Office Supplies",
            "type":"Retail Goods"
        }
    ],
    "sg:phone":"+1 606 677 1763",
    "sg:postcode":"42501",
    "sg:province":"KY",
    "wof:name":"Danville Office Equipment",
    "wof:placetype":"venue"
},
  "geometry": {"coordinates":[-84.605693,37.091831],"type":"Point"}
}