{
  "type": "Feature",
  "properties": {
    "iso:country":"US",
    "sg:address":"1430 Bosley Rd",
    "sg:city":"Owensboro",
    "sg:classifiers":[
        {
            "category":"Professional",
            "type":"Services"
        }
    ],
    "sg:phone":"+1 270 683 2442",
    "sg:postcode":"42301",
    "sg:province":"KY",
    "sg:tags":[
        "establishment"
    ],
    "wof:name":"Zoddies",
    "wof:placetype":"venue"
},
  "geometry": {"coordinates":[-87.134969,37.760139],"type":"Point"}
}