{
  "type": "Feature",
  "properties": {
    "iso:country":"US",
    "sg:address":"2211 Meadow Dr",
    "sg:city":"Louisville",
    "sg:classifiers":[
        {
            "category":"Banks & Credit Unions",
            "subcategory":"Investment Brokerage",
            "type":"Services"
        }
    ],
    "sg:phone":"+1 502 451 7183",
    "sg:postcode":"40218",
    "sg:province":"KY",
    "sg:tags":[
        "security"
    ],
    "wof:name":"WMA Securities Inc",
    "wof:placetype":"venue"
},
  "geometry": {"coordinates":[-85.663664,38.20487],"type":"Point"}
}