{
  "type": "Feature",
  "properties": {
    "iso:country":"US",
    "sg:address":"647 Chyleen Ct",
    "sg:city":"Lexington",
    "sg:classifiers":[
        {
            "category":"Building & Trades",
            "subcategory":"Construction",
            "type":"Services"
        }
    ],
    "sg:phone":"+1 859 293 2386",
    "sg:postcode":"40505",
    "sg:province":"KY",
    "sg:tags":[
        "carpentry",
        "contractor"
    ],
    "wof:name":"Witts Carpentry",
    "wof:placetype":"venue"
},
  "geometry": {"coordinates":[-84.461072,38.086174],"type":"Point"}
}