{
  "type": "Feature",
  "properties": {
    "iso:country":"US",
    "sg:address":"1826 Madison Ave",
    "sg:city":"Covington",
    "sg:classifiers":[
        {
            "category":"Real Estate",
            "subcategory":"Real Estate Operator",
            "type":"Services"
        }
    ],
    "sg:phone":"+1 859 291 5751",
    "sg:postcode":"41014",
    "sg:province":"KY",
    "sg:tags":[
        "building",
        "apartment"
    ],
    "wof:name":"Tri-State Properties I O K",
    "wof:placetype":"venue"
},
  "geometry": {"coordinates":[-84.506462,39.069331],"type":"Point"}
}