{
  "type": "Feature",
  "properties": {
    "iso:country":"US",
    "sg:address":"731 Madison Ave",
    "sg:city":"Covington",
    "sg:classifiers":[
        {
            "category":"Shopping",
            "subcategory":"Computers & Home Electronics",
            "type":"Retail Goods"
        }
    ],
    "sg:phone":"+1 859 431 4480",
    "sg:postcode":"41011",
    "sg:province":"KY",
    "sg:tags":[
        "equipment",
        "dealer"
    ],
    "wof:name":"Charity Cars & Computers",
    "wof:placetype":"venue"
},
  "geometry": {"coordinates":[-84.50994300000001,39.082574],"type":"Point"}
}