{
  "type": "Feature",
  "properties": {
    "addr:full":"3204 Cumminsville-Berlin Rd Brooksville KY 41004",
    "addr:housenumber":"3204",
    "addr:postcode":"41004",
    "addr:street":"Cumminsville-Berlin Rd",
    "iso:country":"US",
    "sg:address":"3204 Cumminsville-Berlin Rd",
    "sg:city":"Brooksville",
    "sg:phone":"+1 606 747 5678",
    "sg:postcode":"41004",
    "sg:province":"KY",
    "sg:tags":[
        "farm",
        "tobacco"
    ],
    "wof:name":"Kenneth Buser",
    "wof:placetype":"venue"
},
  "geometry": {"coordinates":[-84.151048,38.691207],"type":"Point"}
}