{
  "type": "Feature",
  "properties": {
    "addr:full":"1309 US Hwy 127 S Frankfort KY 40601",
    "addr:housenumber":"1309",
    "addr:postcode":"40601",
    "addr:street":"Us Hwy 127 S",
    "iso:country":"US",
    "sg:address":"1309 US Hwy 127 S",
    "sg:city":"Frankfort",
    "sg:classifiers":[
        {
            "category":"Shopping",
            "subcategory":"Computers & Home Electronics",
            "type":"Retail Goods"
        }
    ],
    "sg:phone":"+1 502 223 3936",
    "sg:postcode":"40601",
    "sg:province":"KY",
    "sg:tags":[
        "equipment",
        "electronic",
        "supply"
    ],
    "wof:name":"Radio Shack",
    "wof:placetype":"venue"
},
  "geometry": {"coordinates":[-84.893693,38.160399],"type":"Point"}
}