{
  "type": "Feature",
  "properties": {
    "iso:country":"US",
    "sg:address":"1319 Bonnie Blue Loop",
    "sg:city":"Lawrenceburg",
    "sg:classifiers":[
        {
            "category":"Utilities",
            "subcategory":"Mobile Phone",
            "type":"Services"
        }
    ],
    "sg:phone":"+1 502 859 5330",
    "sg:postcode":"40342",
    "sg:province":"KY",
    "sg:tags":[
        "telephone",
        "cellular"
    ],
    "wof:name":"ACO",
    "wof:placetype":"venue"
},
  "geometry": {"coordinates":[-84.891076,38.016593],"type":"Point"}
}