{
  "type": "Feature",
  "properties": {
    "addr:full":"1015 Crossroad Dr Lawrenceburg KY 40342",
    "addr:housenumber":"1015",
    "addr:postcode":"40342",
    "addr:street":"Crossroad Dr",
    "iso:country":"US",
    "sg:address":"1015 Crossroad Dr",
    "sg:city":"Lawrenceburg",
    "sg:classifiers":[
        {
            "category":"Banks & Credit Unions",
            "subcategory":"Bank",
            "type":"Services"
        }
    ],
    "sg:phone":"+1 502 839 7776",
    "sg:postcode":"40342",
    "sg:province":"KY",
    "wof:name":"1st Independence Bank",
    "wof:placetype":"venue"
},
  "geometry": {"coordinates":[-84.92103899999999,38.027602],"type":"Point"}
}