{
  "type": "Feature",
  "properties": {
    "iso:country":"US",
    "sg:address":"3913 Oaklawn Dr",
    "sg:city":"Louisville",
    "sg:classifiers":[
        {
            "category":"Wholesale",
            "subcategory":"Machinery & Supplies",
            "type":"Manufacturing & Wholesale Goods"
        }
    ],
    "sg:phone":"+1 502 968 0505",
    "sg:postcode":"40219",
    "sg:province":"KY",
    "sg:tags":[
        "industrial",
        "equipment",
        "used",
        "machinery-new",
        "supplies-wholesale"
    ],
    "wof:name":"Louisville Industrial Supply Company Inc",
    "wof:placetype":"venue"
},
  "geometry": {"coordinates":[-85.688692,38.148467],"type":"Point"}
}