{
  "type": "Feature",
  "properties": {
    "iso:country":"US",
    "sg:address":"5226 Bardstown Rd",
    "sg:city":"Louisville",
    "sg:classifiers":[
        {
            "category":"Professional",
            "subcategory":"Art Services",
            "type":"Services"
        }
    ],
    "sg:phone":"+1 502 495 1500",
    "sg:postcode":"40291",
    "sg:province":"KY",
    "sg:tags":[
        "photographer"
    ],
    "wof:name":"Morgan's Photography",
    "wof:placetype":"venue"
},
  "geometry": {"coordinates":[-85.608647,38.171322],"type":"Point"}
}