{
  "type": "Feature",
  "properties": {
    "iso:country":"US",
    "sg:address":"3896 State Hwy 3298",
    "sg:city":"Olive Hill",
    "sg:classifiers":[
        {
            "category":"Farming",
            "subcategory":"Livestock Farm",
            "type":"Manufacturing & Wholesale Goods"
        }
    ],
    "sg:phone":"+1 606 286 6372",
    "sg:postcode":"41164",
    "sg:province":"KY",
    "sg:tags":[
        "beef",
        "feedlot",
        "cattle"
    ],
    "wof:name":"Benjamin Harmon",
    "wof:placetype":"venue"
},
  "geometry": {"coordinates":[-83.125122,38.287686],"type":"Point"}
}