{
  "type": "Feature",
  "properties": {
    "addr:full":"127 N 2nd St Louisville KY 40202",
    "addr:housenumber":"127",
    "addr:postcode":"40202",
    "addr:street":"N 2Nd St",
    "iso:country":"US",
    "sg:address":"127 N 2nd St",
    "sg:city":"Louisville",
    "sg:classifiers":[
        {
            "category":"Building & Trades",
            "subcategory":"Cleaning & Sanitation",
            "type":"Services"
        }
    ],
    "sg:phone":"+1 502 775 4070",
    "sg:postcode":"40202",
    "sg:province":"KY",
    "sg:tags":[
        "maintenance"
    ],
    "wof:name":"Custom Cleaning Services",
    "wof:placetype":"venue"
},
  "geometry": {"coordinates":[-85.75288,38.257699],"type":"Point"}
}