{
  "type": "Feature",
  "properties": {
    "iso:country":"US",
    "sg:address":"3800 Bryan Station Rd",
    "sg:city":"Lexington",
    "sg:classifiers":[
        {
            "category":"Recreation",
            "type":"Entertainment"
        }
    ],
    "sg:phone":"+1 859 294 4162",
    "sg:postcode":"40516",
    "sg:province":"KY",
    "sg:tags":[
        "stable"
    ],
    "wof:name":"Summit Racing Stables",
    "wof:placetype":"venue"
},
  "geometry": {"coordinates":[-84.396007,38.088728],"type":"Point"}
}