{
  "type": "Feature",
  "properties": {
    "addr:full":"1620 E Main St Cumberland KY 40823",
    "addr:housenumber":"1620",
    "addr:postcode":"40823",
    "addr:street":"E Main St",
    "iso:country":"US",
    "sg:address":"1620 E Main St",
    "sg:city":"Cumberland",
    "sg:classifiers":[
        {
            "category":"Health Services",
            "subcategory":"Doctor",
            "type":"Services"
        }
    ],
    "sg:phone":"+1 606 589 6113",
    "sg:postcode":"40823",
    "sg:province":"KY",
    "sg:tags":[
        "dentist"
    ],
    "wof:name":"Clyde E Blair DDS",
    "wof:placetype":"venue"
},
  "geometry": {"coordinates":[-82.980694,36.974831],"type":"Point"}
}