{
  "type": "Feature",
  "properties": {
    "iso:country":"US",
    "sg:address":"800 Campbellsville Byp",
    "sg:city":"Campbellsville",
    "sg:classifiers":[
        {
            "category":"Food & Beverages",
            "subcategory":"Groceries & Convenience Stores",
            "type":"Retail Goods"
        }
    ],
    "sg:phone":"+1 270 465 0952",
    "sg:postcode":"42718",
    "sg:province":"KY",
    "sg:tags":[
        "grocer"
    ],
    "wof:name":"Fastrack Food Store",
    "wof:placetype":"venue"
},
  "geometry": {"coordinates":[-85.372652,37.347059],"type":"Point"}
}