{
  "type": "Feature",
  "properties": {
    "addr:full":"650 US Hwy 127 Russell Springs KY 42642",
    "addr:housenumber":"650",
    "addr:postcode":"42642",
    "addr:street":"Us Hwy 127",
    "iso:country":"US",
    "sg:address":"650 US Hwy 127",
    "sg:city":"Russell Springs",
    "sg:classifiers":[
        {
            "category":"Organizations",
            "subcategory":"Professional Association",
            "type":"Services"
        }
    ],
    "sg:phone":"+1 270 866 4333",
    "sg:postcode":"42642",
    "sg:province":"KY",
    "sg:tags":[
        "chambers",
        "commerce"
    ],
    "wof:name":"Chamber Of Commerce",
    "wof:placetype":"venue"
},
  "geometry": {"coordinates":[-85.071445,37.073098],"type":"Point"}
}