{
  "type": "Feature",
  "properties": {
    "iso:country":"US",
    "sg:address":"1032 Arden Dr",
    "sg:city":"Covington",
    "sg:classifiers":[
        {
            "category":"Professional",
            "subcategory":"Management & Consulting",
            "type":"Services"
        }
    ],
    "sg:phone":"+1 859 341 3984",
    "sg:postcode":"41017",
    "sg:province":"KY",
    "wof:name":"Kerr Marketing Consulting",
    "wof:placetype":"venue"
},
  "geometry": {"coordinates":[-84.584476,39.070226],"type":"Point"}
}