{
  "type": "Feature",
  "properties": {
    "addr:full":"25 Lombardy Dr Cecilia KY 42724",
    "addr:housenumber":"25",
    "addr:postcode":"42724",
    "addr:street":"Lombardy Dr Cecilia",
    "iso:country":"US",
    "sg:address":"25 Lombardy Dr",
    "sg:city":"Cecilia",
    "sg:classifiers":[
        {
            "category":"Utilities",
            "type":"Services"
        }
    ],
    "sg:phone":"+1 270 862 9091",
    "sg:postcode":"42724",
    "sg:province":"KY",
    "sg:tags":[
        "sweeping"
    ],
    "wof:name":"Heartland Commercial Sweeping",
    "wof:placetype":"venue"
},
  "geometry": {"coordinates":[-85.94911999999999,37.666227],"type":"Point"}
}