{
  "type": "Feature",
  "properties": {
    "iso:country":"US",
    "sg:address":"1281 Keene Rd",
    "sg:city":"Nicholasville",
    "sg:classifiers":[
        {
            "category":"Professional",
            "subcategory":"Business Services",
            "type":"Services"
        }
    ],
    "sg:phone":"+1 859 885 5276",
    "sg:postcode":"40356",
    "sg:province":"KY",
    "sg:tags":[
        "water",
        "hauling"
    ],
    "wof:name":"Teater's Trucking Svc",
    "wof:placetype":"venue"
},
  "geometry": {"coordinates":[-84.579989,37.897531],"type":"Point"}
}