{
  "type": "Feature",
  "properties": {
    "addr:full":"505 E 1st St Hopkinsville KY 42240",
    "addr:housenumber":"505",
    "addr:postcode":"42240",
    "addr:street":"E 1St St",
    "iso:country":"US",
    "sg:address":"505 E 1st St",
    "sg:city":"Hopkinsville",
    "sg:classifiers":[
        {
            "category":"Home & Garden",
            "subcategory":"Household Appliances",
            "type":"Retail Goods"
        },
        {
            "category":"Building & Trades",
            "subcategory":"Cleaning & Sanitation",
            "type":"Services"
        },
        {
            "category":"Building & Trades",
            "subcategory":"Construction",
            "type":"Services"
        }
    ],
    "sg:phone":"+1 270 885 4010",
    "sg:postcode":"42240",
    "sg:province":"KY",
    "sg:tags":[
        "log",
        "specialty",
        "duct",
        "gas",
        "heating",
        "system",
        "contractor",
        "air conditioning"
    ],
    "sg:website":"http://www.realpagessites.com/qualityheatingcooling",
    "wof:name":"Quality Heating & Cooling",
    "wof:placetype":"venue"
},
  "geometry": {"coordinates":[-87.481255,36.869354],"type":"Point"}
}