{
  "type": "Feature",
  "properties": {
    "iso:country":"US",
    "sg:address":"1985 H Murray Rd",
    "sg:city":"Bowling Green",
    "sg:classifiers":[
        {
            "category":"Building & Trades",
            "subcategory":"Plumbing",
            "type":"Services"
        }
    ],
    "sg:phone":"+1 270 842 8855",
    "sg:postcode":"42104",
    "sg:province":"KY",
    "sg:tags":[
        "conditioning",
        "air",
        "system",
        "contractor"
    ],
    "wof:name":"Creek Heating & Cooling LLC",
    "wof:placetype":"venue"
},
  "geometry": {"coordinates":[-86.496053,36.84963],"type":"Point"}
}