{
  "type": "Feature",
  "properties": {
    "addr:full":"527 Madison Ave Covington KY 41011",
    "addr:housenumber":"527",
    "addr:postcode":"41011",
    "addr:street":"Madison Ave",
    "iso:country":"US",
    "sg:address":"527 Madison Ave",
    "sg:city":"Covington",
    "sg:classifiers":[
        {
            "category":"Shopping",
            "subcategory":"Used Merchandise",
            "type":"Retail Goods"
        }
    ],
    "sg:phone":"+1 859 491 0023",
    "sg:postcode":"41011",
    "sg:province":"KY",
    "sg:tags":[
        "pawnbroker"
    ],
    "wof:name":"Cash-N-A-Flash",
    "wof:placetype":"venue"
},
  "geometry": {"coordinates":[-84.51049399999999,39.084655],"type":"Point"}
}