{
  "type": "Feature",
  "properties": {
    "addr:full":"500 Blue Sky Pkwy Lexington KY 40509",
    "addr:housenumber":"500",
    "addr:postcode":"40509",
    "addr:street":"Blue Sky Pkwy",
    "iso:country":"US",
    "sg:address":"500 Blue Sky Pkwy",
    "sg:city":"Lexington",
    "sg:classifiers":[
        {
            "category":"Wholesale",
            "subcategory":"Auto Parts",
            "type":"Manufacturing & Wholesale Goods"
        }
    ],
    "sg:phone":"+1 859 263 5092",
    "sg:postcode":"40509",
    "sg:province":"KY",
    "sg:tags":[
        "lining",
        "brake"
    ],
    "wof:name":"Scan Pac Mfg Co",
    "wof:placetype":"venue"
},
  "geometry": {"coordinates":[-84.373192,37.963967],"type":"Point"}
}