{
  "type": "Feature",
  "properties": {
    "iso:country":"US",
    "sg:address":"2743 Keller Rd",
    "sg:city":"Owensboro",
    "sg:classifiers":[
        {
            "category":"Home & Garden",
            "subcategory":"Furniture",
            "type":"Retail Goods"
        }
    ],
    "sg:phone":"+1 270 683 0361",
    "sg:postcode":"42301",
    "sg:province":"KY",
    "wof:name":"Keller Amish Furniture",
    "wof:placetype":"venue"
},
  "geometry": {"coordinates":[-87.148228,37.709701],"type":"Point"}
}