{
  "type": "Feature",
  "properties": {
    "iso:country":"US",
    "sg:address":"1928 Grassy Branch",
    "sg:city":"Raccoon",
    "sg:classifiers":[
        {
            "category":"Wholesale",
            "subcategory":"Auto Parts",
            "type":"Manufacturing & Wholesale Goods"
        }
    ],
    "sg:phone":"+1 606 437 4418",
    "sg:postcode":"41557",
    "sg:province":"KY",
    "sg:tags":[
        "automobile",
        "rebuilt"
    ],
    "wof:name":"Tom's Truck Parts",
    "wof:placetype":"venue"
},
  "geometry": {"coordinates":[-82.419414,37.518459],"type":"Point"}
}