{
  "type": "Feature",
  "properties": {
    "addr:full":"340 E Main Ave Bowling Green KY 42101",
    "addr:housenumber":"340",
    "addr:postcode":"42101",
    "addr:street":"E Main Ave",
    "iso:country":"US",
    "sg:address":"340 E Main Ave",
    "sg:city":"Bowling Green",
    "sg:classifiers":[
        {
            "category":"Banks & Credit Unions",
            "subcategory":"Investment Brokerage",
            "type":"Services"
        }
    ],
    "sg:phone":"+1 270 782 7051",
    "sg:postcode":"42101",
    "sg:province":"KY",
    "sg:tags":[
        "stock",
        "bond"
    ],
    "wof:name":"Merrill Lynch",
    "wof:placetype":"venue"
},
  "geometry": {"coordinates":[-86.442161,36.994534],"type":"Point"}
}