{
  "type": "Feature",
  "properties": {
    "iso:country":"US",
    "sg:address":"118 N 3rd St",
    "sg:city":"Bardstown",
    "sg:classifiers":[
        {
            "category":"Real Estate",
            "subcategory":"Real Estate Operator",
            "type":"Services"
        }
    ],
    "sg:phone":"+1 502 331 0005",
    "sg:postcode":"40004",
    "sg:province":"KY",
    "sg:tags":[
        "building",
        "nonresidential"
    ],
    "wof:name":"Antiques On Third",
    "wof:placetype":"venue"
},
  "geometry": {"coordinates":[-85.46651199999999,37.810329],"type":"Point"}
}