{
  "type": "Feature",
  "properties": {
    "iso:country":"US",
    "sg:address":"2730 W Parrish Ave",
    "sg:city":"Owensboro",
    "sg:classifiers":[
        {
            "category":"Restaurant",
            "type":"Food & Drink"
        }
    ],
    "sg:menulink":"http://www.allmenus.com/ky/owensboro/186934-mcdonalds/menu/",
    "sg:phone":"+1 270 683 3545",
    "sg:postcode":"42301",
    "sg:province":"KY",
    "sg:tags":[
        "burger",
        "american"
    ],
    "wof:name":"McDonald's",
    "wof:placetype":"venue"
},
  "geometry": {"coordinates":[-87.146153,37.757579],"type":"Point"}
}