{
  "type": "Feature",
  "properties": {
    "iso:country":"US",
    "sg:address":"4418 Dyer Ave",
    "sg:city":"Louisville",
    "sg:classifiers":[
        {
            "category":"Manufacturing",
            "subcategory":"Tools & Machinery",
            "type":"Manufacturing & Wholesale Goods"
        },
        {
            "category":"Freight",
            "type":"Transportation"
        },
        {
            "category":"Building & Trades",
            "subcategory":"Construction",
            "type":"Services"
        }
    ],
    "sg:phone":"+1 502 964 1967",
    "sg:postcode":"40213",
    "sg:province":"KY",
    "sg:tags":[
        "conveying",
        "conveyor",
        "equipment-wholesale",
        "system",
        "equipment",
        "monorail",
        "manufacturer"
    ],
    "wof:name":"Aim Conveyor & Cargo Systems",
    "wof:placetype":"venue"
},
  "geometry": {"coordinates":[-85.70454700000001,38.182796],"type":"Point"}
}