{
  "type": "Feature",
  "properties": {
    "addr:full":"1885 Bunnell Crossing Rd Munfordville KY 42765",
    "addr:housenumber":"1885",
    "addr:postcode":"42765",
    "addr:street":"Bunnell Crossing Rd",
    "iso:country":"US",
    "sg:address":"1885 Bunnell Crossing Rd",
    "sg:city":"Munfordville",
    "sg:classifiers":[
        {
            "category":"Freight",
            "type":"Transportation"
        }
    ],
    "sg:phone":"+1 270 537 5109",
    "sg:postcode":"42765",
    "sg:province":"KY",
    "sg:tags":[
        "commercial",
        "storage"
    ],
    "wof:name":"Wilson Storage",
    "wof:placetype":"venue"
},
  "geometry": {"coordinates":[-85.86243399999999,37.241622],"type":"Point"}
}