{
  "type": "Feature",
  "properties": {
    "iso:country":"US",
    "sg:address":"7613 Shepherdsville Rd",
    "sg:city":"Louisville",
    "sg:classifiers":[
        {
            "category":"Food & Beverages",
            "subcategory":"Liquor & Beverages",
            "type":"Retail Goods"
        }
    ],
    "sg:phone":"+1 502 969 8068",
    "sg:postcode":"40219",
    "sg:province":"KY",
    "wof:name":"Discount Cigeratte & Liquor",
    "wof:placetype":"venue"
},
  "geometry": {"coordinates":[-85.657573,38.139145],"type":"Point"}
}