{
  "type": "Feature",
  "properties": {
    "iso:country":"US",
    "sg:address":"4362 Aurora Hwy",
    "sg:city":"Hardin",
    "sg:classifiers":[
        {
            "category":"Wholesale",
            "subcategory":"Sporting Goods",
            "type":"Manufacturing & Wholesale Goods"
        }
    ],
    "sg:phone":"+1 270 354 9197",
    "sg:postcode":"42048",
    "sg:province":"KY",
    "sg:tags":[
        "tackle",
        "fishing"
    ],
    "wof:name":"Fast Eddie's Bait & Tackle",
    "wof:placetype":"venue"
},
  "geometry": {"coordinates":[-88.227603,36.764508],"type":"Point"}
}