{
  "type": "Feature",
  "properties": {
    "iso:country":"US",
    "sg:address":"100 Buttercup Ln",
    "sg:city":"Greensburg",
    "sg:classifiers":[
        {
            "category":"Restaurant",
            "type":"Food & Drink"
        }
    ],
    "sg:phone":"+1 270 465 3097",
    "sg:postcode":"42718",
    "sg:province":"KY",
    "wof:name":"Larry & Margaret Gadberry Inc",
    "wof:placetype":"venue"
},
  "geometry": {"coordinates":[-85.335263,37.365608],"type":"Point"}
}