{
  "type": "Feature",
  "properties": {
    "iso:country":"US",
    "sg:address":"229 Churchill Dr",
    "sg:city":"Richmond",
    "sg:classifiers":[
        {
            "category":"Wholesale",
            "subcategory":"Electrical",
            "type":"Manufacturing & Wholesale Goods"
        }
    ],
    "sg:phone":"+1 859 623 0085",
    "sg:postcode":"40475",
    "sg:province":"KY",
    "sg:tags":[
        "control",
        "security",
        "system"
    ],
    "wof:name":"Commonwealth Communications",
    "wof:placetype":"venue"
},
  "geometry": {"coordinates":[-84.319891,37.773347],"type":"Point"}
}