{
  "type": "Feature",
  "properties": {
    "addr:full":"100 Sycamore Industrial Rd Murray KY 42071",
    "addr:housenumber":"100",
    "addr:postcode":"42071",
    "addr:street":"Sycamore Industrial Rd",
    "iso:country":"US",
    "sg:address":"100 Sycamore Industrial Rd",
    "sg:city":"Murray",
    "sg:classifiers":[
        {
            "category":"Wholesale",
            "subcategory":"Farm Supplies",
            "type":"Manufacturing & Wholesale Goods"
        }
    ],
    "sg:phone":"+1 270 753 1423",
    "sg:postcode":"42071",
    "sg:province":"KY",
    "sg:website":"www.southernstates.com",
    "wof:name":"Southern States Cooperative",
    "wof:placetype":"venue"
},
  "geometry": {"coordinates":[-88.297884,36.602029],"type":"Point"}
}