{
  "type": "Feature",
  "properties": {
    "iso:country":"US",
    "sg:address":"123 N Nicholas St",
    "sg:city":"Elizabethtown",
    "sg:classifiers":[
        {
            "category":"Real Estate",
            "subcategory":"Real Estate Agent",
            "type":"Services"
        }
    ],
    "sg:phone":"+1 270 737 4005",
    "sg:postcode":"42701",
    "sg:province":"KY",
    "wof:name":"Mre Inc",
    "wof:placetype":"venue"
},
  "geometry": {"coordinates":[-85.851887,37.69035],"type":"Point"}
}