{
  "type": "Feature",
  "properties": {
    "iso:country":"US",
    "sg:address":"803 Scott Blvd",
    "sg:city":"Covington",
    "sg:classifiers":[
        {
            "category":"Utilities",
            "subcategory":"Telephone",
            "type":"Services"
        }
    ],
    "sg:phone":"+1 859 292 8999",
    "sg:postcode":"41011",
    "sg:province":"KY",
    "sg:tags":[
        "communications"
    ],
    "wof:name":"Long Distance Entertainment",
    "wof:placetype":"venue"
},
  "geometry": {"coordinates":[-84.508151,39.082058],"type":"Point"}
}