{
  "type": "Feature",
  "properties": {
    "addr:full":"316 E Main St Morehead KY 40351",
    "addr:housenumber":"316",
    "addr:postcode":"40351",
    "addr:street":"E Main St",
    "iso:country":"US",
    "sg:address":"316 E Main St",
    "sg:city":"Morehead",
    "sg:classifiers":[
        {
            "category":"Social Services",
            "subcategory":"Child Care",
            "type":"Services"
        }
    ],
    "sg:phone":"+1 606 780 4365",
    "sg:postcode":"40351",
    "sg:province":"KY",
    "sg:tags":[
        "kindergarten",
        "academic",
        "school"
    ],
    "wof:name":"A B C's Of Preschool",
    "wof:placetype":"venue"
},
  "geometry": {"coordinates":[-83.43182400000001,38.185755],"type":"Point"}
}