{
  "type": "Feature",
  "properties": {
    "addr:full":"878 E High St Lexington KY 40502",
    "addr:housenumber":"878",
    "addr:postcode":"40502",
    "addr:street":"E High St",
    "iso:country":"US",
    "sg:address":"878 E High St",
    "sg:city":"Lexington",
    "sg:classifiers":[
        {
            "category":"Shopping",
            "subcategory":"Pharmacy",
            "type":"Retail Goods"
        }
    ],
    "sg:phone":"+1 859 266 1171",
    "sg:postcode":"40502",
    "sg:province":"KY",
    "wof:name":"Rite Aid Pharmacy",
    "wof:placetype":"venue"
},
  "geometry": {"coordinates":[-84.490273,38.028806],"type":"Point"}
}