{
  "type": "Feature",
  "properties": {
    "iso:country":"US",
    "sg:address":"1801 Lantaff Blvd",
    "sg:city":"Madisonville",
    "sg:classifiers":[
        {
            "category":"Autos & Motor Vehicles",
            "subcategory":"Automobile Sales",
            "type":"Retail Goods"
        }
    ],
    "sg:phone":"+1 270 821 4100",
    "sg:postcode":"42431",
    "sg:province":"KY",
    "sg:tags":[
        "car",
        "dealer"
    ],
    "sg:website":"www.hudsonauto.com",
    "wof:name":"Hudson Ford-Nissan Inc",
    "wof:placetype":"venue"
},
  "geometry": {"coordinates":[-87.490206,37.353761],"type":"Point"}
}