{
  "type": "Feature",
  "properties": {
    "iso:country":"US",
    "sg:address":"324 E 5th St",
    "sg:city":"Beaver Dam",
    "sg:classifiers":[
        {
            "category":"Retail",
            "subcategory":"Auto Repair",
            "type":"Services"
        }
    ],
    "sg:phone":"+1 270 274 3288",
    "sg:postcode":"42320",
    "sg:province":"KY",
    "sg:tags":[
        "body",
        "automobile",
        "painting"
    ],
    "wof:name":"Bradley's Body Shop Inc",
    "wof:placetype":"venue"
},
  "geometry": {"coordinates":[-86.87497999999999,37.406698],"type":"Point"}
}