{
  "type": "Feature",
  "properties": {
    "iso:country":"US",
    "sg:address":"6761 Oscar Rd",
    "sg:city":"La Center",
    "sg:classifiers":[
        {
            "category":"Travel",
            "subcategory":"Hotels & Motels",
            "type":"Entertainment"
        }
    ],
    "sg:phone":"+1 270 224 2222",
    "sg:postcode":"42056",
    "sg:province":"KY",
    "sg:tags":[
        "breakfast",
        "accommodation",
        "bed"
    ],
    "wof:name":"Goose Lodge",
    "wof:placetype":"venue"
},
  "geometry": {"coordinates":[-89.021697,37.140664],"type":"Point"}
}