{
  "type": "Feature",
  "properties": {
    "iso:country":"US",
    "sg:address":"109 Carolina Ave",
    "sg:city":"Fort Thomas",
    "sg:classifiers":[
        {
            "category":"Building & Trades",
            "subcategory":"Locksmith",
            "type":"Services"
        }
    ],
    "sg:phone":"+1 859 394 0420",
    "sg:postcode":"41075",
    "sg:province":"KY",
    "sg:tags":[
        "key"
    ],
    "wof:name":"Aarant Emergency Locksmith",
    "wof:placetype":"venue"
},
  "geometry": {"coordinates":[-84.450351,39.074118],"type":"Point"}
}