{
  "type": "Feature",
  "properties": {
    "iso:country":"US",
    "sg:address":"851 Corporate Dr",
    "sg:city":"Lexington",
    "sg:classifiers":[
        {
            "category":"Shopping",
            "subcategory":"Gifts & Souvenirs",
            "type":"Retail Goods"
        }
    ],
    "sg:phone":"+1 859 254 3532",
    "sg:postcode":"40503",
    "sg:province":"KY",
    "sg:tags":[
        "party",
        "supply"
    ],
    "wof:name":"Republican Party-Fayette",
    "wof:placetype":"venue"
},
  "geometry": {"coordinates":[-84.554599,38.013265],"type":"Point"}
}