{
  "type": "Feature",
  "properties": {
    "iso:country":"US",
    "sg:address":"194 N Main St",
    "sg:city":"Mt Olivet",
    "sg:classifiers":[
        {
            "category":"Health Services",
            "subcategory":"Doctor",
            "type":"Services"
        }
    ],
    "sg:phone":"+1 606 724 2124",
    "sg:postcode":"41064",
    "sg:province":"KY",
    "sg:tags":[
        "physician",
        "surgeon"
    ],
    "wof:name":"Healthpoint Family Care",
    "wof:placetype":"venue"
},
  "geometry": {"coordinates":[-84.031775,38.534637],"type":"Point"}
}