{
  "type": "Feature",
  "properties": {
    "iso:country":"US",
    "sg:address":"157 Greenbriar Dr",
    "sg:city":"Campbellsville",
    "sg:classifiers":[
        {
            "category":"Shopping",
            "subcategory":"Jewelry",
            "type":"Retail Goods"
        }
    ],
    "sg:phone":"+1 270 465 4726",
    "sg:postcode":"42718",
    "sg:province":"KY",
    "sg:tags":[
        "jeweler"
    ],
    "wof:name":"Friedman's",
    "wof:placetype":"venue"
},
  "geometry": {"coordinates":[-85.33615,37.36803],"type":"Point"}
}