{
  "type": "Feature",
  "properties": {
    "iso:country":"US",
    "sg:address":"440 S Mayo Trl",
    "sg:city":"Pikeville",
    "sg:classifiers":[
        {
            "category":"Restaurant",
            "type":"Food & Drink"
        }
    ],
    "sg:phone":"+1 606 218 6007",
    "sg:postcode":"41501",
    "sg:province":"KY",
    "wof:name":"El Poncho",
    "wof:placetype":"venue"
},
  "geometry": {"coordinates":[-82.52915,37.465624],"type":"Point"}
}