{
  "type": "Feature",
  "properties": {
    "addr:full":"9166 Burkesville Rd Glasgow KY 42141",
    "addr:housenumber":"9166",
    "addr:postcode":"42141",
    "addr:street":"Burkesville Rd",
    "iso:country":"US",
    "sg:address":"9166 Burkesville Rd",
    "sg:city":"Glasgow",
    "sg:classifiers":[
        {
            "category":"Government",
            "subcategory":"Post Office",
            "type":"Public Place"
        }
    ],
    "sg:phone":"+1 270 678 1520",
    "sg:postcode":"42141",
    "sg:province":"KY",
    "wof:name":"US Post Office",
    "wof:placetype":"venue"
},
  "geometry": {"coordinates":[-85.79581399999999,36.921497],"type":"Point"}
}