{
  "type": "Feature",
  "properties": {
    "addr:full":"825 Barret Ave Louisville KY 40204",
    "addr:housenumber":"825",
    "addr:postcode":"40204",
    "addr:street":"Barret Ave",
    "iso:country":"US",
    "sg:address":"825 Barret Ave",
    "sg:city":"Louisville",
    "sg:classifiers":[
        {
            "category":"Health Services",
            "subcategory":"Doctor",
            "type":"Services"
        }
    ],
    "sg:phone":"+1 502 540 7200",
    "sg:postcode":"40204",
    "sg:province":"KY",
    "sg:tags":[
        "physician",
        "surgeons",
        "internal",
        "medicine",
        "surgeon"
    ],
    "wof:name":"Community Medical Associates",
    "wof:placetype":"venue"
},
  "geometry": {"coordinates":[-85.73184999999999,38.241192],"type":"Point"}
}