{
  "type": "Feature",
  "properties": {
    "iso:country":"US",
    "sg:address":"919 Palatka Rd",
    "sg:city":"Louisville",
    "sg:classifiers":[
        {
            "category":"Organizations",
            "subcategory":"Religious Organization",
            "type":"Services"
        }
    ],
    "sg:phone":"+1 502 366 3030",
    "sg:postcode":"40214",
    "sg:province":"KY",
    "wof:name":"Family Life Ctr",
    "wof:placetype":"venue"
},
  "geometry": {"coordinates":[-85.777343,38.150944],"type":"Point"}
}