{
  "type": "Feature",
  "properties": {
    "addr:full":"13604 Sample Ct Louisville KY 40245",
    "addr:housenumber":"13604",
    "addr:postcode":"40245",
    "addr:street":"Sample Ct",
    "iso:country":"US",
    "sg:address":"13604 Sample Ct",
    "sg:city":"Louisville",
    "sg:classifiers":[
        {
            "category":"Shopping",
            "subcategory":"Stationery & Office Supplies",
            "type":"Retail Goods"
        }
    ],
    "sg:phone":"+1 502 241 0384",
    "sg:postcode":"40245",
    "sg:province":"KY",
    "sg:tags":[
        "store"
    ],
    "wof:name":"Creative Options",
    "wof:placetype":"venue"
},
  "geometry": {"coordinates":[-85.505151,38.287936],"type":"Point"}
}