{
  "type": "Feature",
  "properties": {
    "iso:country":"US",
    "sg:address":"1293 Bardstown Rd",
    "sg:city":"Louisville",
    "sg:classifiers":[
        {
            "category":"Professional",
            "type":"Services"
        },
        {
            "category":"Restaurant",
            "type":"Food & Drink"
        }
    ],
    "sg:phone":"+1 502 451 0700",
    "sg:postcode":"40204",
    "sg:province":"KY",
    "sg:tags":[
        "caterer"
    ],
    "sg:website":"http://www.ramsiscafe.com",
    "wof:name":"Ramsi's Cafe On The World",
    "wof:placetype":"venue"
},
  "geometry": {"coordinates":[-85.715687,38.23551],"type":"Point"}
}