{
  "type": "Feature",
  "properties": {
    "addr:full":"240 Dixie Hwy W Elizabethtown KY 42701",
    "addr:housenumber":"240",
    "addr:postcode":"42701",
    "addr:street":"Dixie Hwy W",
    "iso:country":"US",
    "sg:address":"240 Dixie Hwy W",
    "sg:city":"Elizabethtown",
    "sg:classifiers":[
        {
            "category":"Social Services",
            "type":"Services"
        }
    ],
    "sg:phone":"+1 270 737 6252",
    "sg:postcode":"42701",
    "sg:province":"KY",
    "sg:tags":[
        "counselor",
        "marriage",
        "family"
    ],
    "wof:name":"Mayfield & Assoc",
    "wof:placetype":"venue"
},
  "geometry": {"coordinates":[-85.86145999999999,37.694994],"type":"Point"}
}