{
  "type": "Feature",
  "properties": {
    "addr:full":"102 Front St Butler KY 41006",
    "addr:housenumber":"102",
    "addr:postcode":"41006",
    "addr:street":"Front St",
    "iso:country":"US",
    "sg:address":"102 Front St",
    "sg:city":"Butler",
    "sg:classifiers":[
        {
            "category":"Government",
            "subcategory":"Office",
            "type":"Public Place"
        }
    ],
    "sg:phone":"+1 859 472 5015",
    "sg:postcode":"41006",
    "sg:province":"KY",
    "sg:tags":[
        "city"
    ],
    "wof:name":"Butler City Clerk",
    "wof:placetype":"venue"
},
  "geometry": {"coordinates":[-84.36864199999999,38.786851],"type":"Point"}
}