{
  "type": "Feature",
  "properties": {
    "addr:full":"206 S Main St Edmonton KY 42129",
    "addr:housenumber":"206",
    "addr:postcode":"42129",
    "addr:street":"S Main St",
    "iso:country":"US",
    "sg:address":"206 S Main St",
    "sg:city":"Edmonton",
    "sg:classifiers":[
        {
            "category":"Restaurant",
            "type":"Food & Drink"
        }
    ],
    "sg:phone":"+1 270 432 3830",
    "sg:postcode":"42129",
    "sg:province":"KY",
    "wof:name":"City Grill",
    "wof:placetype":"venue"
},
  "geometry": {"coordinates":[-85.61174699999999,36.977993],"type":"Point"}
}