{
  "type": "Feature",
  "properties": {
    "iso:country":"US",
    "sg:address":"46 Grafenburg Rd",
    "sg:city":"Frankfort",
    "sg:classifiers":[
        {
            "category":"Organizations",
            "subcategory":"Religious Organization",
            "type":"Services"
        }
    ],
    "sg:phone":"+1 502 829 5535",
    "sg:postcode":"40601",
    "sg:province":"KY",
    "wof:name":"Graefnburg Untd Methdst Church",
    "wof:placetype":"venue"
},
  "geometry": {"coordinates":[-85.00694900000001,38.158048],"type":"Point"}
}