{
  "type": "Feature",
  "properties": {
    "addr:full":"3765 Mount Zion Elliston Rd Dry Ridge KY 41035",
    "addr:housenumber":"3765",
    "addr:postcode":"41035",
    "addr:street":"Mount Zion Elliston Rd",
    "iso:country":"US",
    "sg:address":"3765 Mount Zion Elliston Rd",
    "sg:city":"Dry Ridge",
    "sg:classifiers":[
        {
            "category":"Personal",
            "subcategory":"Beauty Salon",
            "type":"Services"
        }
    ],
    "sg:phone":"+1 859 428 0833",
    "sg:postcode":"41035",
    "sg:province":"KY",
    "wof:name":"House Of Hair",
    "wof:placetype":"venue"
},
  "geometry": {"coordinates":[-84.659212,38.738198],"type":"Point"}
}