{
  "type": "Feature",
  "properties": {
    "addr:full":"115 E Main St Earlington KY 42410",
    "addr:housenumber":"115",
    "addr:postcode":"42410",
    "addr:street":"E Main St",
    "iso:country":"US",
    "sg:address":"115 E Main St",
    "sg:city":"Earlington",
    "sg:classifiers":[
        {
            "category":"Health Services",
            "subcategory":"Doctor",
            "type":"Services"
        }
    ],
    "sg:phone":"+1 270 383 2521",
    "sg:postcode":"42410",
    "sg:province":"KY",
    "sg:tags":[
        "physician",
        "surgeon"
    ],
    "wof:name":"Trover Clinic",
    "wof:placetype":"venue"
},
  "geometry": {"coordinates":[-87.51111299999999,37.274856],"type":"Point"}
}