{
  "type": "Feature",
  "properties": {
    "addr:full":"10350 Ormsby Park Pl Louisville KY 40223",
    "addr:housenumber":"10350",
    "addr:postcode":"40223",
    "addr:street":"Ormsby Park Pl",
    "iso:country":"US",
    "sg:address":"10350 Ormsby Park Pl",
    "sg:city":"Louisville",
    "sg:classifiers":[
        {
            "category":"Banks & Credit Unions",
            "subcategory":"Bank",
            "type":"Services"
        }
    ],
    "sg:phone":"+1 502 339 1604",
    "sg:postcode":"40223",
    "sg:province":"KY",
    "wof:name":"Integra Bank",
    "wof:placetype":"venue"
},
  "geometry": {"coordinates":[-85.567273,38.263904],"type":"Point"}
}