{
  "type": "Feature",
  "properties": {
    "addr:full":"4801 Sherburn Ln Louisville KY 40207",
    "addr:housenumber":"4801",
    "addr:postcode":"40207",
    "addr:street":"Sherburn Ln",
    "iso:country":"US",
    "sg:address":"4801 Sherburn Ln",
    "sg:city":"Louisville",
    "sg:classifiers":[
        {
            "category":"Utilities",
            "type":"Services"
        }
    ],
    "sg:phone":"+1 502 896 9141",
    "sg:postcode":"40207",
    "sg:province":"KY",
    "sg:tags":[
        "sweeping"
    ],
    "wof:name":"Tru-Service CO LLC",
    "wof:placetype":"venue"
},
  "geometry": {"coordinates":[-85.623926,38.240817],"type":"Point"}
}