{
  "type": "Feature",
  "properties": {
    "iso:country":"US",
    "sg:address":"2625 Lexington Rd",
    "sg:city":"Louisville",
    "sg:classifiers":[
        {
            "category":"Professional",
            "subcategory":"Employment Agencies",
            "type":"Services"
        }
    ],
    "sg:phone":"+1 502 897 1077",
    "sg:postcode":"40206",
    "sg:province":"KY",
    "sg:tags":[
        "employer"
    ],
    "wof:name":"American Massage Therapy",
    "wof:placetype":"venue"
},
  "geometry": {"coordinates":[-85.693005,38.245121],"type":"Point"}
}