{
  "type": "Feature",
  "properties": {
    "iso:country":"US",
    "sg:address":"100 S 4th St",
    "sg:city":"Louisville",
    "sg:classifiers":[
        {
            "category":"Banks & Credit Unions",
            "subcategory":"Investment Brokerage",
            "type":"Services"
        }
    ],
    "sg:phone":"+1 502 562 7759",
    "sg:postcode":"40202",
    "sg:province":"KY",
    "wof:name":"Joan Baldwin",
    "wof:placetype":"venue"
},
  "geometry": {"coordinates":[-85.75678499999999,38.25523],"type":"Point"}
}