{
  "type": "Feature",
  "properties": {
    "iso:country":"US",
    "sg:address":"429 Westwood Dr",
    "sg:city":"Frankfort",
    "sg:classifiers":[
        {
            "category":"Shopping",
            "subcategory":"Beauty & Cosmetics",
            "type":"Retail Goods"
        }
    ],
    "sg:phone":"+1 502 875 2350",
    "sg:postcode":"40601",
    "sg:province":"KY",
    "sg:tags":[
        "merchandise"
    ],
    "wof:name":"Mary Kay Cosmetics",
    "wof:placetype":"venue"
},
  "geometry": {"coordinates":[-84.90552599999999,38.169052],"type":"Point"}
}