{
  "type": "Feature",
  "properties": {
    "addr:full":"497 Industrial Dr Glasgow KY 42141",
    "addr:housenumber":"497",
    "addr:postcode":"42141",
    "addr:street":"Industrial Dr",
    "iso:country":"US",
    "sg:address":"497 Industrial Dr",
    "sg:city":"Glasgow",
    "sg:classifiers":[
        {
            "category":"Wholesale",
            "subcategory":"Hardware",
            "type":"Manufacturing & Wholesale Goods"
        }
    ],
    "sg:phone":"+1 270 678 4377",
    "sg:postcode":"42141",
    "sg:province":"KY",
    "sg:tags":[
        "fastener"
    ],
    "wof:name":"Fastenal Co",
    "wof:placetype":"venue"
},
  "geometry": {"coordinates":[-85.944427,36.998539],"type":"Point"}
}