{
  "type": "Feature",
  "properties": {
    "iso:country":"US",
    "sg:address":"1147 Kentucky Ave",
    "sg:city":"Paducah",
    "sg:classifiers":[
        {
            "category":"Autos & Motor Vehicles",
            "subcategory":"Auto Supplies",
            "type":"Retail Goods"
        }
    ],
    "sg:phone":"+1 270 442 0737",
    "sg:postcode":"42003",
    "sg:province":"KY",
    "sg:tags":[
        "tire"
    ],
    "wof:name":"Paducah Tire Svc",
    "wof:placetype":"venue"
},
  "geometry": {"coordinates":[-88.608656,37.081254],"type":"Point"}
}