{
  "type": "Feature",
  "properties": {
    "iso:country":"US",
    "sg:address":"1729 Blevins Valley Rd",
    "sg:city":"Owingsville",
    "sg:phone":"+1 606 674 2194",
    "sg:postcode":"40360",
    "sg:province":"KY",
    "sg:tags":[
        "farm",
        "tobacco"
    ],
    "wof:name":"Rexal Short",
    "wof:placetype":"venue"
},
  "geometry": {"coordinates":[-83.735435,38.066994],"type":"Point"}
}