{
  "type": "Feature",
  "properties": {
    "iso:country":"US",
    "sg:address":"3378 Greentree Cir",
    "sg:city":"Lexington",
    "sg:classifiers":[
        {
            "category":"Social Services",
            "subcategory":"Child Care",
            "type":"Services"
        }
    ],
    "sg:phone":"+1 859 245 1476",
    "sg:postcode":"40517",
    "sg:province":"KY",
    "sg:tags":[
        "day"
    ],
    "wof:name":"Nanas Haven Day Care",
    "wof:placetype":"venue"
},
  "geometry": {"coordinates":[-84.481588,37.99132],"type":"Point"}
}