{
  "type": "Feature",
  "properties": {
    "iso:country":"US",
    "sg:address":"50 Halls Gap Ests",
    "sg:city":"Stanford",
    "sg:classifiers":[
        {
            "category":"Organizations",
            "subcategory":"Religious Organization",
            "type":"Services"
        }
    ],
    "sg:phone":"+1 606 365 2241",
    "sg:postcode":"40484",
    "sg:province":"KY",
    "wof:name":"Tabernacle",
    "wof:placetype":"venue"
},
  "geometry": {"coordinates":[-84.633898,37.448201],"type":"Point"}
}