{
  "type": "Feature",
  "properties": {
    "iso:country":"US",
    "sg:address":"5360 Zebulon Hwy",
    "sg:city":"Pikeville",
    "sg:classifiers":[
        {
            "category":"Autos & Motor Vehicles",
            "subcategory":"Auto Supplies",
            "type":"Retail Goods"
        }
    ],
    "sg:phone":"+1 606 631 7020",
    "sg:postcode":"41501",
    "sg:province":"KY",
    "sg:tags":[
        "automotive",
        "general",
        "tire",
        "repair"
    ],
    "wof:name":"Mullens Auto Service",
    "wof:placetype":"venue"
},
  "geometry": {"coordinates":[-82.46808900000001,37.542067],"type":"Point"}
}