{
  "type": "Feature",
  "properties": {
    "iso:country":"US",
    "sg:address":"5655 State Hwy 22",
    "sg:city":"Owenton",
    "sg:classifiers":[
        {
            "category":"Professional",
            "type":"Services"
        }
    ],
    "sg:phone":"+1 502 484 2360",
    "sg:postcode":"40359",
    "sg:province":"KY",
    "wof:name":"Schroder Urban",
    "wof:placetype":"venue"
},
  "geometry": {"coordinates":[-84.91517899999999,38.500817],"type":"Point"}
}