{
  "type": "Feature",
  "properties": {
    "addr:full":"6614 Dixie Hwy Florence KY 41042",
    "addr:housenumber":"6614",
    "addr:postcode":"41042",
    "addr:street":"Dixie Hwy",
    "iso:country":"US",
    "sg:address":"6614 Dixie Hwy",
    "sg:city":"Florence",
    "sg:classifiers":[
        {
            "category":"Personal",
            "subcategory":"Beauty Salon",
            "type":"Services"
        }
    ],
    "sg:phone":"+1 859 282 1554",
    "sg:postcode":"41042",
    "sg:province":"KY",
    "sg:tags":[
        "shop"
    ],
    "wof:name":"Unique Hair Design",
    "wof:placetype":"venue"
},
  "geometry": {"coordinates":[-84.618821,39.004971],"type":"Point"}
}