{
  "type": "Feature",
  "properties": {
    "addr:full":"837 Meridian Rd Hickory KY 42051",
    "addr:housenumber":"837",
    "addr:postcode":"42051",
    "addr:street":"Meridian Rd",
    "iso:country":"US",
    "sg:address":"837 Meridian Rd",
    "sg:city":"Hickory",
    "sg:classifiers":[
        {
            "category":"Farming",
            "subcategory":"Poultry Farm",
            "type":"Manufacturing & Wholesale Goods"
        }
    ],
    "sg:phone":"+1 270 856 3834",
    "sg:postcode":"42051",
    "sg:province":"KY",
    "wof:name":"Suiters Poultry",
    "wof:placetype":"venue"
},
  "geometry": {"coordinates":[-88.70213,36.848977],"type":"Point"}
}