{
  "type": "Feature",
  "properties": {
    "iso:country":"US",
    "sg:address":"488 Old Preston Hwy S",
    "sg:city":"Shepherdsville",
    "sg:classifiers":[
        {
            "category":"Wholesale",
            "subcategory":"Groceries",
            "type":"Manufacturing & Wholesale Goods"
        }
    ],
    "sg:phone":"+1 502 921 2151",
    "sg:postcode":"40165",
    "sg:province":"KY",
    "sg:tags":[
        "beverage"
    ],
    "wof:name":"Ken's Beverage Inc",
    "wof:placetype":"venue"
},
  "geometry": {"coordinates":[-85.712424,37.978649],"type":"Point"}
}