{
  "type": "Feature",
  "properties": {
    "iso:country":"US",
    "sg:address":"1322 Lebanon Rd",
    "sg:city":"Danville",
    "sg:classifiers":[
        {
            "category":"Travel",
            "subcategory":"Travel Agent",
            "type":"Entertainment"
        }
    ],
    "sg:phone":"+1 859 236 0000",
    "sg:postcode":"40422",
    "sg:province":"KY",
    "sg:tags":[
        "agency",
        "bureau"
    ],
    "wof:name":"Thomas Travel",
    "wof:placetype":"venue"
},
  "geometry": {"coordinates":[-84.791545,37.640023],"type":"Point"}
}