{
  "type": "Feature",
  "properties": {
    "addr:full":"617 Patterson St Lexington KY 40508",
    "addr:housenumber":"617",
    "addr:postcode":"40508",
    "addr:street":"Patterson St",
    "iso:country":"US",
    "sg:address":"617 Patterson St",
    "sg:city":"Lexington",
    "sg:classifiers":[
        {
            "category":"Freight",
            "type":"Transportation"
        }
    ],
    "sg:phone":"+1 859 255 0257",
    "sg:postcode":"40508",
    "sg:province":"KY",
    "sg:tags":[
        "trucking"
    ],
    "wof:name":"Maupin Trucking",
    "wof:placetype":"venue"
},
  "geometry": {"coordinates":[-84.509587,38.045393],"type":"Point"}
}