{
  "type": "Feature",
  "properties": {
    "addr:full":"2988 Washington St Burlington KY 41005",
    "addr:housenumber":"2988",
    "addr:postcode":"41005",
    "addr:street":"Washington St",
    "iso:country":"US",
    "sg:address":"2988 Washington St",
    "sg:city":"Burlington",
    "sg:classifiers":[
        {
            "category":"Social Services",
            "type":"Services"
        }
    ],
    "sg:phone":"+1 859 586 9100",
    "sg:postcode":"41005",
    "sg:province":"KY",
    "sg:tags":[
        "organization",
        "welfare"
    ],
    "wof:name":"Boone County Child Support",
    "wof:placetype":"venue"
},
  "geometry": {"coordinates":[-84.723874,39.027822],"type":"Point"}
}