{
  "type": "Feature",
  "properties": {
    "addr:full":"3098 Taylor Ford Rd Columbia KY 42728",
    "addr:housenumber":"3098",
    "addr:postcode":"42728",
    "addr:street":"Taylor Ford Rd",
    "iso:country":"US",
    "sg:address":"3098 Taylor Ford Rd",
    "sg:city":"Columbia",
    "sg:phone":"+1 270 384 3117",
    "sg:postcode":"42728",
    "sg:province":"KY",
    "sg:tags":[
        "farm",
        "tobacco"
    ],
    "wof:name":"Frank Radford",
    "wof:placetype":"venue"
},
  "geometry": {"coordinates":[-85.199828,37.106949],"type":"Point"}
}