{
  "type": "Feature",
  "properties": {
    "addr:full":"464 Lakeshore Dr Lexington KY 40502",
    "addr:housenumber":"464",
    "addr:postcode":"40502",
    "addr:street":"Lakeshore Dr",
    "iso:country":"US",
    "sg:address":"464 Lakeshore Dr",
    "sg:city":"Lexington",
    "sg:classifiers":[
        {
            "category":"Professional",
            "subcategory":"Business Services",
            "type":"Services"
        }
    ],
    "sg:phone":"+1 859 254 1234",
    "sg:postcode":"40502",
    "sg:province":"KY",
    "sg:tags":[
        "embroidery"
    ],
    "sg:website":"www.brownsportswear.com",
    "wof:name":"Kentucky Hot Brown",
    "wof:placetype":"venue"
},
  "geometry": {"coordinates":[-84.472544,38.011089],"type":"Point"}
}