{
  "type": "Feature",
  "properties": {
    "iso:country":"US",
    "sg:address":"8515 US Highway 42",
    "sg:city":"Florence",
    "sg:classifiers":[
        {
            "category":"Home & Garden",
            "subcategory":"Hardware",
            "type":"Retail Goods"
        }
    ],
    "sg:phone":"+1 859 525 2038",
    "sg:postcode":"41042",
    "sg:province":"KY",
    "sg:tags":[
        "store"
    ],
    "sg:website":"www.acehardware.com",
    "wof:name":"Ace Hardware Florence",
    "wof:placetype":"venue"
},
  "geometry": {"coordinates":[-84.65958500000001,38.975211],"type":"Point"}
}