{
  "type": "Feature",
  "properties": {
    "iso:country":"US",
    "sg:address":"279 Mountain Pkwy",
    "sg:city":"Salyersville",
    "sg:classifiers":[
        {
            "category":"Autos & Motor Vehicles",
            "subcategory":"Fuel & Gas Station",
            "type":"Retail Goods"
        }
    ],
    "sg:phone":"+1 606 349 3334",
    "sg:postcode":"41465",
    "sg:province":"KY",
    "sg:tags":[
        "oil"
    ],
    "wof:name":"Parkway Sunoco",
    "wof:placetype":"venue"
},
  "geometry": {"coordinates":[-83.043111,37.739115],"type":"Point"}
}