{
  "type": "Feature",
  "properties": {
    "iso:country":"US",
    "sg:address":"7910 Shepherdsville Rd",
    "sg:city":"Louisville",
    "sg:classifiers":[
        {
            "category":"Retail",
            "subcategory":"Auto Repair",
            "type":"Services"
        }
    ],
    "sg:phone":"+1 502 962 8555",
    "sg:postcode":"40219",
    "sg:province":"KY",
    "sg:tags":[
        "repairing",
        "automobile"
    ],
    "wof:name":"Tom's Service Ctr",
    "wof:placetype":"venue"
},
  "geometry": {"coordinates":[-85.659009,38.13482],"type":"Point"}
}