{
  "type": "Feature",
  "properties": {
    "addr:full":"7920 Bardstown Rd Louisville KY 40291",
    "addr:housenumber":"7920",
    "addr:postcode":"40291",
    "addr:street":"Bardstown Rd",
    "iso:country":"US",
    "sg:address":"7920 Bardstown Rd",
    "sg:city":"Louisville",
    "sg:classifiers":[
        {
            "category":"Bakery",
            "type":"Food & Drink"
        },
        {
            "category":"Coffee & Tea",
            "type":"Food & Drink"
        },
        {
            "category":"Bagels",
            "type":"Food & Drink"
        },
        {
            "category":"Donuts",
            "type":"Food & Drink"
        }
    ],
    "sg:menulink":"http://www.allmenus.com/ky/jefferson-southeast/133154-dunkin-donuts/menu/",
    "sg:phone":"+1 502 231 6319",
    "sg:postcode":"40291",
    "sg:province":"KY",
    "sg:tags":[
        "american",
        "pastry"
    ],
    "wof:name":"Dunkin' Donuts",
    "wof:placetype":"venue"
},
  "geometry": {"coordinates":[-85.577164,38.130227],"type":"Point"}
}