{
  "type": "Feature",
  "properties": {
    "iso:country":"US",
    "sg:address":"1075 Collins Ln",
    "sg:city":"Frankfort",
    "sg:classifiers":[
        {
            "category":"Social Services",
            "type":"Services"
        }
    ],
    "sg:phone":"+1 502 875 7502",
    "sg:postcode":"40601",
    "sg:province":"KY",
    "wof:name":"Cornerstone Counseling Inc",
    "wof:placetype":"venue"
},
  "geometry": {"coordinates":[-84.89107300000001,38.177434],"type":"Point"}
}