{
  "type": "Feature",
  "properties": {
    "iso:country":"US",
    "sg:address":"13145 Ironworks Rd",
    "sg:city":"Winchester",
    "sg:phone":"+1 859 842 6022",
    "sg:postcode":"40391",
    "sg:province":"KY",
    "sg:tags":[
        "farm",
        "tobacco"
    ],
    "wof:name":"Wilbur Osborne",
    "wof:placetype":"venue"
},
  "geometry": {"coordinates":[-84.00667799999999,37.929291],"type":"Point"}
}