{
  "type": "Feature",
  "properties": {
    "iso:country":"US",
    "sg:address":"104 N Bradford Ln",
    "sg:city":"Georgetown",
    "sg:classifiers":[
        {
            "category":"Ice Cream",
            "type":"Food & Drink"
        }
    ],
    "sg:menulink":"http://www.allmenus.com/ky/georgetown/220748-braums-ice-cream--dairy-stores/menu/",
    "sg:phone":"+1 502 570 8688",
    "sg:postcode":"40324",
    "sg:province":"KY",
    "sg:tags":[
        "american"
    ],
    "wof:name":"Braum's Ice Cream & Dairy Stores",
    "wof:placetype":"venue"
},
  "geometry": {"coordinates":[-84.562905,38.193873],"type":"Point"}
}