{
  "type": "Feature",
  "properties": {
    "iso:country":"US",
    "sg:address":"117 Highland Dr",
    "sg:city":"Bardstown",
    "sg:classifiers":[
        {
            "category":"Social Services",
            "type":"Services"
        }
    ],
    "sg:phone":"+1 502 349 0866",
    "sg:postcode":"40004",
    "sg:province":"KY",
    "sg:tags":[
        "counselor",
        "marriage",
        "family"
    ],
    "wof:name":"Jay A Hall Lcsw Lmft",
    "wof:placetype":"venue"
},
  "geometry": {"coordinates":[-85.521821,37.863806],"type":"Point"}
}