{
  "type": "Feature",
  "properties": {
    "iso:country":"US",
    "sg:address":"917 Georgetown Rd",
    "sg:city":"Lexington",
    "sg:classifiers":[
        {
            "category":"Travel",
            "subcategory":"Hotels & Motels",
            "type":"Entertainment"
        }
    ],
    "sg:phone":"+1 859 225 4842",
    "sg:postcode":"40508",
    "sg:province":"KY",
    "wof:name":"Horseshoe Motel",
    "wof:placetype":"venue"
},
  "geometry": {"coordinates":[-84.50541200000001,38.073008],"type":"Point"}
}