{
  "type": "Feature",
  "properties": {
    "iso:country":"US",
    "sg:address":"1658 Production Dr",
    "sg:city":"Burlington",
    "sg:classifiers":[
        {
            "category":"Manufacturing",
            "subcategory":"Glass & Minerals",
            "type":"Manufacturing & Wholesale Goods"
        }
    ],
    "sg:phone":"+1 859 371 5542",
    "sg:postcode":"41005",
    "sg:province":"KY",
    "sg:tags":[
        "ready"
    ],
    "wof:name":"Boone Ready Mix Inc",
    "wof:placetype":"venue"
},
  "geometry": {"coordinates":[-84.68696799999999,39.022574],"type":"Point"}
}