{
  "type": "Feature",
  "properties": {
    "iso:country":"US",
    "sg:address":"630 Main St",
    "sg:city":"Shelbyville",
    "sg:classifiers":[
        {
            "category":"Social Services",
            "type":"Services"
        }
    ],
    "sg:phone":"+1 502 633 7800",
    "sg:postcode":"40065",
    "sg:province":"KY",
    "sg:tags":[
        "organization",
        "welfare"
    ],
    "wof:name":"Center For Women & Families",
    "wof:placetype":"venue"
},
  "geometry": {"coordinates":[-85.218456,38.211048],"type":"Point"}
}