{
  "type": "Feature",
  "properties": {
    "addr:full":"675 Vance Dr Mt Sterling KY 40353",
    "addr:housenumber":"675",
    "addr:postcode":"40353",
    "addr:street":"Vance Dr",
    "iso:country":"US",
    "sg:address":"675 Vance Dr",
    "sg:city":"Mt Sterling",
    "sg:classifiers":[
        {
            "category":"Home & Garden",
            "subcategory":"Household Appliances",
            "type":"Retail Goods"
        }
    ],
    "sg:phone":"+1 859 498 3500",
    "sg:postcode":"40353",
    "sg:province":"KY",
    "wof:name":"J & J Direct Maytag",
    "wof:placetype":"venue"
},
  "geometry": {"coordinates":[-83.95140499999999,38.074045],"type":"Point"}
}