{
  "type": "Feature",
  "properties": {
    "iso:country":"US",
    "sg:address":"407 South St",
    "sg:city":"West Point",
    "sg:classifiers":[
        {
            "category":"Arts & Performance",
            "subcategory":"Theater",
            "type":"Entertainment"
        }
    ],
    "sg:phone":"+1 502 922 9393",
    "sg:postcode":"40177",
    "sg:province":"KY",
    "sg:tags":[
        "live",
        "music"
    ],
    "wof:name":"Music Ranch USA",
    "wof:placetype":"venue"
},
  "geometry": {"coordinates":[-85.946089,37.998554],"type":"Point"}
}