{
  "type": "Feature",
  "properties": {
    "addr:full":"205 S Main St Lawrenceburg KY 40342",
    "addr:housenumber":"205",
    "addr:postcode":"40342",
    "addr:street":"S Main St",
    "iso:country":"US",
    "sg:address":"205 S Main St",
    "sg:city":"Lawrenceburg",
    "sg:classifiers":[
        {
            "category":"Retail",
            "subcategory":"Car Wash",
            "type":"Services"
        },
        {
            "category":"Retail",
            "subcategory":"Auto Repair",
            "type":"Services"
        }
    ],
    "sg:phone":"+1 502 839 1672",
    "sg:postcode":"40342",
    "sg:province":"KY",
    "sg:tags":[
        "stereo",
        "installation",
        "automobile",
        "alarm",
        "detail",
        "equipment",
        "clean"
    ],
    "wof:name":"Auto Techtronics",
    "wof:placetype":"venue"
},
  "geometry": {"coordinates":[-84.895618,38.035227],"type":"Point"}
}