{
  "type": "Feature",
  "properties": {
    "iso:country":"US",
    "sg:address":"3230 Buckner Ln",
    "sg:city":"Paducah",
    "sg:classifiers":[
        {
            "category":"Education",
            "subcategory":"School",
            "type":"Public Place"
        }
    ],
    "sg:phone":"+1 270 575 0025",
    "sg:postcode":"42001",
    "sg:province":"KY",
    "sg:website":"www.ccapaducah.org",
    "wof:name":"Community Christian Academy",
    "wof:placetype":"venue"
},
  "geometry": {"coordinates":[-88.638783,37.069981],"type":"Point"}
}