{
  "type": "Feature",
  "properties": {
    "addr:full":"12080 Virginia Blvd Ashland KY 41102",
    "addr:housenumber":"12080",
    "addr:postcode":"41102",
    "addr:street":"Virginia Blvd",
    "iso:country":"US",
    "sg:address":"12080 Virginia Blvd",
    "sg:city":"Ashland",
    "sg:classifiers":[
        {
            "category":"Freight",
            "type":"Transportation"
        }
    ],
    "sg:phone":"+1 606 928 3131",
    "sg:postcode":"41102",
    "sg:province":"KY",
    "sg:tags":[
        "hauling",
        "trucking"
    ],
    "wof:name":"Buck's Trucks",
    "wof:placetype":"venue"
},
  "geometry": {"coordinates":[-82.745074,38.391473],"type":"Point"}
}