{
  "type": "Feature",
  "properties": {
    "addr:full":"102 E Main St Morganfield KY 42437",
    "addr:housenumber":"102",
    "addr:postcode":"42437",
    "addr:street":"E Main St",
    "iso:country":"US",
    "sg:address":"102 E Main St",
    "sg:city":"Morganfield",
    "sg:classifiers":[
        {
            "category":"Social Services",
            "type":"Services"
        }
    ],
    "sg:phone":"+1 270 389 2408",
    "sg:postcode":"42437",
    "sg:province":"KY",
    "sg:tags":[
        "organization",
        "welfare"
    ],
    "wof:name":"Salvation Army Thrift Store",
    "wof:placetype":"venue"
},
  "geometry": {"coordinates":[-87.91685099999999,37.683721],"type":"Point"}
}