{
  "type": "Feature",
  "properties": {
    "iso:country":"US",
    "sg:address":"2236 By-Pass Rd",
    "sg:city":"Paris",
    "sg:classifiers":[
        {
            "category":"Food & Beverages",
            "subcategory":"Groceries & Convenience Stores",
            "type":"Retail Goods"
        }
    ],
    "sg:phone":"+1 859 987 5551",
    "sg:postcode":"40361",
    "sg:province":"KY",
    "sg:tags":[
        "grocer"
    ],
    "wof:name":"Food Lion",
    "wof:placetype":"venue"
},
  "geometry": {"coordinates":[-84.27674500000001,38.213844],"type":"Point"}
}