{
  "type": "Feature",
  "properties": {
    "addr:full":"15300 State Hwy 180 Catlettsburg KY 41129",
    "addr:housenumber":"15300",
    "addr:postcode":"41129",
    "addr:street":"State Hwy 180",
    "iso:country":"US",
    "sg:address":"15300 State Hwy 180",
    "sg:city":"Catlettsburg",
    "sg:classifiers":[
        {
            "category":"Autos & Motor Vehicles",
            "subcategory":"Fuel & Gas Station",
            "type":"Retail Goods"
        }
    ],
    "sg:phone":"+1 606 928 8383",
    "sg:postcode":"41129",
    "sg:province":"KY",
    "sg:tags":[
        "plaza",
        "truck",
        "stops"
    ],
    "wof:name":"Flying J Travel Plaza",
    "wof:placetype":"venue"
},
  "geometry": {"coordinates":[-82.69889499999999,38.365553],"type":"Point"}
}