{
  "type": "Feature",
  "properties": {
    "iso:country":"US",
    "sg:address":"423 S 28th St",
    "sg:city":"Paducah",
    "sg:classifiers":[
        {
            "category":"Building & Trades",
            "subcategory":"Construction",
            "type":"Services"
        }
    ],
    "sg:phone":"+1 270 415 9972",
    "sg:postcode":"42003",
    "sg:province":"KY",
    "sg:tags":[
        "general",
        "contractor"
    ],
    "wof:name":"Williams Contracting",
    "wof:placetype":"venue"
},
  "geometry": {"coordinates":[-88.629126,37.070092],"type":"Point"}
}