{
  "type": "Feature",
  "properties": {
    "addr:full":"1555 E New Circle Rd Lexington KY 40509",
    "addr:housenumber":"1555",
    "addr:postcode":"40509",
    "addr:street":"E New Circle Rd",
    "iso:country":"US",
    "sg:address":"1555 E New Circle Rd",
    "sg:city":"Lexington",
    "sg:classifiers":[
        {
            "category":"Shopping",
            "subcategory":"Department Store",
            "type":"Retail Goods"
        }
    ],
    "sg:phone":"+1 859 269 0075",
    "sg:postcode":"40509",
    "sg:province":"KY",
    "sg:tags":[
        "shop"
    ],
    "wof:name":"Home Goods",
    "wof:placetype":"venue"
},
  "geometry": {"coordinates":[-84.456394,38.018697],"type":"Point"}
}