{
  "type": "Feature",
  "properties": {
    "iso:country":"US",
    "sg:address":"820 S Main St",
    "sg:city":"Greenville",
    "sg:classifiers":[
        {
            "category":"Professional",
            "subcategory":"Computer Services",
            "type":"Services"
        }
    ],
    "sg:phone":"+1 270 338 0005",
    "sg:postcode":"42345",
    "sg:province":"KY",
    "sg:tags":[
        "internet"
    ],
    "wof:name":"Diamond Cure Technologies",
    "wof:placetype":"venue"
},
  "geometry": {"coordinates":[-87.17286799999999,37.193525],"type":"Point"}
}