{
  "type": "Feature",
  "properties": {
    "addr:full":"2300 Bardstown Rd Louisville KY 40205",
    "addr:housenumber":"2300",
    "addr:postcode":"40205",
    "addr:street":"Bardstown Rd",
    "iso:country":"US",
    "sg:address":"2300 Bardstown Rd",
    "sg:city":"Louisville",
    "sg:classifiers":[
        {
            "category":"Personal",
            "subcategory":"Tanning Parlor",
            "type":"Services"
        }
    ],
    "sg:phone":"+1 502 456 4390",
    "sg:postcode":"40205",
    "sg:province":"KY",
    "sg:tags":[
        "salon"
    ],
    "wof:name":"Suntan City",
    "wof:placetype":"venue"
},
  "geometry": {"coordinates":[-85.68918600000001,38.223856],"type":"Point"}
}