{
  "type": "Feature",
  "properties": {
    "iso:country":"US",
    "sg:address":"139 N Sherrin Ave Ste 202",
    "sg:city":"Louisville",
    "sg:classifiers":[
        {
            "category":"Wholesale",
            "subcategory":"Home Furnishings",
            "type":"Manufacturing & Wholesale Goods"
        }
    ],
    "sg:phone":"+1 502 895 0307",
    "sg:postcode":"40207",
    "sg:province":"KY",
    "sg:tags":[
        "fixture",
        "part",
        "plumbing",
        "supplies-wholesale",
        "manufacturer"
    ],
    "wof:name":"Broady Co Inc",
    "wof:placetype":"venue"
},
  "geometry": {"coordinates":[-85.650243,38.253857],"type":"Point"}
}