{
  "type": "Feature",
  "properties": {
    "addr:full":"1024 N Main St Nicholasville KY 40356",
    "addr:housenumber":"1024",
    "addr:postcode":"40356",
    "addr:street":"N Main St",
    "iso:country":"US",
    "sg:address":"1024 N Main St",
    "sg:city":"Nicholasville",
    "sg:classifiers":[
        {
            "category":"Restaurant",
            "type":"Food & Drink"
        }
    ],
    "sg:menulink":"http://www.allmenus.com/ky/nicholasville/120669-subway/menu/",
    "sg:phone":"+1 859 887 3964",
    "sg:postcode":"40356",
    "sg:province":"KY",
    "sg:tags":[
        "american",
        "sandwich"
    ],
    "wof:name":"Subway",
    "wof:placetype":"venue"
},
  "geometry": {"coordinates":[-84.56488400000001,37.899462],"type":"Point"}
}