{
  "type": "Feature",
  "properties": {
    "iso:country":"US",
    "sg:address":"563 Hambley Blvd",
    "sg:city":"Pikeville",
    "sg:classifiers":[
        {
            "category":"Building & Trades",
            "subcategory":"Equipment Rental",
            "type":"Services"
        }
    ],
    "sg:phone":"+1 606 432 0102",
    "sg:postcode":"41501",
    "sg:province":"KY",
    "sg:tags":[
        "hospital",
        "supply"
    ],
    "wof:name":"Lincare",
    "wof:placetype":"venue"
},
  "geometry": {"coordinates":[-82.52307999999999,37.484895],"type":"Point"}
}