{
  "type": "Feature",
  "properties": {
    "iso:country":"US",
    "sg:address":"414 E 7th St",
    "sg:city":"Newport",
    "sg:classifiers":[
        {
            "category":"Food & Beverages",
            "subcategory":"Liquor & Beverages",
            "type":"Retail Goods"
        }
    ],
    "sg:phone":"+1 859 261 5696",
    "sg:postcode":"41071",
    "sg:province":"KY",
    "wof:name":"Jerry's Jug House Package Str",
    "wof:placetype":"venue"
},
  "geometry": {"coordinates":[-84.48766500000001,39.092867],"type":"Point"}
}