{
  "type": "Feature",
  "properties": {
    "addr:full":"628 N Main St Jamestown KY 42629",
    "addr:housenumber":"628",
    "addr:postcode":"42629",
    "addr:street":"N Main St",
    "iso:country":"US",
    "sg:address":"628 N Main St",
    "sg:city":"Jamestown",
    "sg:classifiers":[
        {
            "category":"Arts & Performance",
            "subcategory":"Theater",
            "type":"Entertainment"
        }
    ],
    "sg:phone":"+1 270 343 3939",
    "sg:postcode":"42629",
    "sg:province":"KY",
    "sg:tags":[
        "bureau"
    ],
    "wof:name":"Kentucky Off Track Betting",
    "wof:placetype":"venue"
},
  "geometry": {"coordinates":[-85.072109,36.996271],"type":"Point"}
}