{
  "type": "Feature",
  "properties": {
    "iso:country":"US",
    "sg:address":"114 W Shelby St",
    "sg:city":"Falmouth",
    "sg:classifiers":[
        {
            "category":"Personal",
            "subcategory":"Beauty Salon",
            "type":"Services"
        }
    ],
    "sg:phone":"+1 859 654 2887",
    "sg:postcode":"41040",
    "sg:province":"KY",
    "wof:name":"More Than Hair",
    "wof:placetype":"venue"
},
  "geometry": {"coordinates":[-84.33069,38.676914],"type":"Point"}
}