{
  "type": "Feature",
  "properties": {
    "iso:country":"US",
    "sg:address":"1485 E New Circle Rd",
    "sg:city":"Lexington",
    "sg:classifiers":[
        {
            "category":"Autos & Motor Vehicles",
            "subcategory":"Automobile Sales",
            "type":"Retail Goods"
        }
    ],
    "sg:phone":"+1 859 255 3101",
    "sg:postcode":"40509",
    "sg:province":"KY",
    "sg:tags":[
        "dealers-used",
        "car",
        "used",
        "cars-wholesale"
    ],
    "sg:website":"http://www.karsmart.com",
    "wof:name":"Kar Smart",
    "wof:placetype":"venue"
},
  "geometry": {"coordinates":[-84.45452299999999,38.022931],"type":"Point"}
}