{
  "type": "Feature",
  "properties": {
    "iso:country":"US",
    "sg:address":"9514 Taylorsville Rd",
    "sg:city":"Jeffersontown",
    "sg:classifiers":[
        {
            "category":"Autos & Motor Vehicles",
            "subcategory":"Auto Supplies",
            "type":"Retail Goods"
        }
    ],
    "sg:phone":"+1 502 267 4400",
    "sg:postcode":"40299",
    "sg:province":"KY",
    "sg:tags":[
        "tire"
    ],
    "wof:name":"Michel Tires Plus",
    "wof:placetype":"venue"
},
  "geometry": {"coordinates":[-85.580709,38.20585],"type":"Point"}
}