{
  "type": "Feature",
  "properties": {
    "iso:country":"US",
    "sg:address":"5920 Lexington Rd",
    "sg:city":"Winchester",
    "sg:classifiers":[
        {
            "category":"Food & Beverages",
            "subcategory":"Groceries & Convenience Stores",
            "type":"Retail Goods"
        }
    ],
    "sg:phone":"+1 859 744 9413",
    "sg:postcode":"40391",
    "sg:province":"KY",
    "sg:tags":[
        "grocer"
    ],
    "wof:name":"Shopper's Market",
    "wof:placetype":"venue"
},
  "geometry": {"coordinates":[-84.272768,38.02652],"type":"Point"}
}