{
  "type": "Feature",
  "properties": {
    "iso:country":"US",
    "sg:address":"4816 Preston Hwy",
    "sg:city":"Louisville",
    "sg:classifiers":[
        {
            "category":"Personal",
            "subcategory":"Massage",
            "type":"Services"
        }
    ],
    "sg:phone":"+1 502 964 7771",
    "sg:postcode":"40213",
    "sg:province":"KY",
    "wof:name":"Blue Spa",
    "wof:placetype":"venue"
},
  "geometry": {"coordinates":[-85.717167,38.178752],"type":"Point"}
}