{
  "type": "Feature",
  "properties": {
    "iso:country":"US",
    "sg:address":"400 S 31st St",
    "sg:city":"Paducah",
    "sg:classifiers":[
        {
            "category":"Freight",
            "type":"Transportation"
        }
    ],
    "sg:phone":"+1 270 442 9147",
    "sg:postcode":"42001",
    "sg:province":"KY",
    "sg:tags":[
        "trucking"
    ],
    "wof:name":"Sturdi-Craft",
    "wof:placetype":"venue"
},
  "geometry": {"coordinates":[-88.63502200000001,37.067918],"type":"Point"}
}