{
  "type": "Feature",
  "properties": {
    "addr:full":"509 E 18th St Owensboro KY 42303",
    "addr:housenumber":"509",
    "addr:postcode":"42303",
    "addr:street":"E 18Th St",
    "iso:country":"US",
    "sg:address":"509 E 18th St",
    "sg:city":"Owensboro",
    "sg:classifiers":[
        {
            "category":"Health Services",
            "subcategory":"Podiatrist",
            "type":"Services"
        }
    ],
    "sg:phone":"+1 270 684 1660",
    "sg:postcode":"42303",
    "sg:province":"KY",
    "wof:name":"Lee H Goldstein DPM",
    "wof:placetype":"venue"
},
  "geometry": {"coordinates":[-87.102864,37.758988],"type":"Point"}
}