{
  "type": "Feature",
  "properties": {
    "addr:full":"215 Shoreline Cir Austin KY 42123",
    "addr:housenumber":"215",
    "addr:postcode":"42123",
    "addr:street":"Shoreline Cir",
    "iso:country":"US",
    "sg:address":"215 Shoreline Cir",
    "sg:city":"Austin",
    "sg:classifiers":[
        {
            "category":"Professional",
            "subcategory":"Management & Consulting",
            "type":"Services"
        }
    ],
    "sg:phone":"+1 270 434 3216",
    "sg:postcode":"42123",
    "sg:province":"KY",
    "wof:name":"Ecolab Inc",
    "wof:placetype":"venue"
},
  "geometry": {"coordinates":[-86.033402,36.783094],"type":"Point"}
}