{
  "type": "Feature",
  "properties": {
    "iso:country":"US",
    "sg:address":"1028 S Mayo Trl",
    "sg:city":"Pikeville",
    "sg:classifiers":[
        {
            "category":"Travel",
            "subcategory":"Hotels & Motels",
            "type":"Entertainment"
        }
    ],
    "sg:phone":"+1 606 432 0314",
    "sg:postcode":"41501",
    "sg:province":"KY",
    "sg:website":"www.daysinn.com",
    "wof:name":"Days Inn",
    "wof:placetype":"venue"
},
  "geometry": {"coordinates":[-82.52097999999999,37.454318],"type":"Point"}
}