{
  "type": "Feature",
  "properties": {
    "addr:full":"320 W Woodlawn Ave Louisville KY 40214",
    "addr:housenumber":"320",
    "addr:postcode":"40214",
    "addr:street":"W Woodlawn Ave",
    "iso:country":"US",
    "sg:address":"320 W Woodlawn Ave",
    "sg:city":"Louisville",
    "sg:classifiers":[
        {
            "category":"Home & Garden",
            "subcategory":"Building Materials",
            "type":"Retail Goods"
        }
    ],
    "sg:phone":"+1 502 364 9034",
    "sg:postcode":"40214",
    "sg:province":"KY",
    "sg:tags":[
        "paint"
    ],
    "wof:name":"Mr Mike's Professional Paint",
    "wof:placetype":"venue"
},
  "geometry": {"coordinates":[-85.768091,38.181691],"type":"Point"}
}