{
  "type": "Feature",
  "properties": {
    "addr:full":"2231 Shelbyville Rd Shelbyville KY 40065",
    "addr:housenumber":"2231",
    "addr:postcode":"40065",
    "addr:street":"Shelbyville Rd",
    "iso:country":"US",
    "sg:address":"2231 Shelbyville Rd",
    "sg:city":"Shelbyville",
    "sg:classifiers":[
        {
            "category":"Home & Garden",
            "subcategory":"Building Materials",
            "type":"Retail Goods"
        }
    ],
    "sg:phone":"+1 502 647 3204",
    "sg:postcode":"40065",
    "sg:province":"KY",
    "sg:tags":[
        "glass",
        "window",
        "plate"
    ],
    "wof:name":"Harmon Auto Glass",
    "wof:placetype":"venue"
},
  "geometry": {"coordinates":[-85.265136,38.215469],"type":"Point"}
}