{
  "type": "Feature",
  "properties": {
    "iso:country":"US",
    "sg:address":"914 Dixie Hwy S",
    "sg:city":"Elizabethtown",
    "sg:classifiers":[
        {
            "category":"Health Services",
            "subcategory":"Doctor",
            "type":"Services"
        }
    ],
    "sg:phone":"+1 270 763 1711",
    "sg:postcode":"42701",
    "sg:province":"KY",
    "sg:tags":[
        "physician",
        "surgeon"
    ],
    "wof:name":"Urogynecology Specialists",
    "wof:placetype":"venue"
},
  "geometry": {"coordinates":[-85.874009,37.708825],"type":"Point"}
}