{
  "type": "Feature",
  "properties": {
    "iso:country":"US",
    "sg:address":"2200 W Broadway",
    "sg:city":"Louisville",
    "sg:classifiers":[
        {
            "category":"Retail",
            "subcategory":"Funeral Services",
            "type":"Services"
        }
    ],
    "sg:phone":"+1 502 772 9276",
    "sg:postcode":"40211",
    "sg:province":"KY",
    "sg:tags":[
        "director"
    ],
    "wof:name":"Anderson Funeral Svc LTD",
    "wof:placetype":"venue"
},
  "geometry": {"coordinates":[-85.78988,38.249275],"type":"Point"}
}