{
  "type": "Feature",
  "properties": {
    "addr:full":"974 State Hwy 1409 Oil Springs KY 41238",
    "addr:housenumber":"974",
    "addr:postcode":"1409;41238",
    "addr:street":"State Hwy",
    "iso:country":"US",
    "sg:address":"974 State Hwy 1409",
    "sg:city":"Oil Springs",
    "sg:classifiers":[
        {
            "category":"Retail",
            "subcategory":"Auto Repair",
            "type":"Services"
        }
    ],
    "sg:phone":"+1 606 297 2817",
    "sg:postcode":"41238",
    "sg:province":"KY",
    "sg:tags":[
        "repairing",
        "automobile",
        "radiator"
    ],
    "wof:name":"Kelly's Radiator Svc",
    "wof:placetype":"venue"
},
  "geometry": {"coordinates":[-82.96747499999999,37.850902],"type":"Point"}
}