{
  "type": "Feature",
  "properties": {
    "iso:country":"US",
    "sg:address":"3600 Alexandria Pike",
    "sg:city":"Fort Thomas",
    "sg:classifiers":[
        {
            "category":"Banks & Credit Unions",
            "subcategory":"Bank",
            "type":"Services"
        }
    ],
    "sg:phone":"+1 859 442 2000",
    "sg:postcode":"41076",
    "sg:province":"KY",
    "wof:name":"U S Bank",
    "wof:placetype":"venue"
},
  "geometry": {"coordinates":[-84.451324,39.030088],"type":"Point"}
}