{
  "type": "Feature",
  "properties": {
    "iso:country":"US",
    "sg:address":"7606 Dixie Hwy",
    "sg:city":"Florence",
    "sg:classifiers":[
        {
            "category":"Food & Beverages",
            "subcategory":"Bakery",
            "type":"Retail Goods"
        }
    ],
    "sg:phone":"+1 859 371 9228",
    "sg:postcode":"41042",
    "sg:province":"KY",
    "sg:tags":[
        "bakers-wholesale"
    ],
    "wof:name":"Emerson's Bakery Inc",
    "wof:placetype":"venue"
},
  "geometry": {"coordinates":[-84.624281,38.992669],"type":"Point"}
}