{
  "type": "Feature",
  "properties": {
    "iso:country":"US",
    "sg:address":"3555 New Shepherdsville Rd",
    "sg:city":"Bardstown",
    "sg:classifiers":[
        {
            "category":"Retail",
            "subcategory":"Laundry & Dry Cleaning",
            "type":"Services"
        }
    ],
    "sg:phone":"+1 502 348 1198",
    "sg:postcode":"40004",
    "sg:province":"KY",
    "sg:tags":[
        "cleaners",
        "rug",
        "carpet"
    ],
    "wof:name":"Steamatic Of Heartland Ky",
    "wof:placetype":"venue"
},
  "geometry": {"coordinates":[-85.512524,37.854593],"type":"Point"}
}