{
  "type": "Feature",
  "properties": {
    "addr:full":"2301 Argillite Rd Flatwoods KY 41139",
    "addr:housenumber":"2301",
    "addr:postcode":"41139",
    "addr:street":"Argillite Rd",
    "iso:country":"US",
    "sg:address":"2301 Argillite Rd",
    "sg:city":"Flatwoods",
    "sg:classifiers":[
        {
            "category":"Retail",
            "subcategory":"Funeral Services",
            "type":"Services"
        }
    ],
    "sg:phone":"+1 606 836 5833",
    "sg:postcode":"41139",
    "sg:province":"KY",
    "sg:tags":[
        "director"
    ],
    "wof:name":"Carman Funeral Home",
    "wof:placetype":"venue"
},
  "geometry": {"coordinates":[-82.721891,38.51822],"type":"Point"}
}