{
  "type": "Feature",
  "properties": {
    "iso:country":"US",
    "sg:address":"8101 Blue Lick Rd",
    "sg:city":"Louisville",
    "sg:classifiers":[
        {
            "category":"Social Services",
            "subcategory":"Child Care",
            "type":"Services"
        }
    ],
    "sg:phone":"+1 502 969 2500",
    "sg:postcode":"40219",
    "sg:province":"KY",
    "sg:tags":[
        "kindergarten",
        "preschool"
    ],
    "wof:name":"Southside Chirstian Child Care",
    "wof:placetype":"venue"
},
  "geometry": {"coordinates":[-85.685188,38.133202],"type":"Point"}
}