{
  "type": "Feature",
  "properties": {
    "iso:country":"US",
    "sg:address":"116 N Front St",
    "sg:city":"Prestonsburg",
    "sg:classifiers":[
        {
            "category":"Organizations",
            "subcategory":"Non-profit Organization",
            "type":"Services"
        }
    ],
    "sg:phone":"+1 606 886 0152",
    "sg:postcode":"41653",
    "sg:province":"KY",
    "wof:name":"Links Inc",
    "wof:placetype":"venue"
},
  "geometry": {"coordinates":[-82.77560200000001,37.667487],"type":"Point"}
}