{
  "type": "Feature",
  "properties": {
    "addr:full":"444 E Main St Lexington KY 40507",
    "addr:housenumber":"444",
    "addr:postcode":"40507",
    "addr:street":"E Main St",
    "iso:country":"US",
    "sg:address":"444 E Main St",
    "sg:city":"Lexington",
    "sg:classifiers":[
        {
            "category":"Professional",
            "subcategory":"Accounting & Tax Preparation",
            "type":"Services"
        }
    ],
    "sg:phone":"+1 859 231 0541",
    "sg:postcode":"40507",
    "sg:province":"KY",
    "sg:tags":[
        "accountant"
    ],
    "wof:name":"Kring Ray Farley & Riddle",
    "wof:placetype":"venue"
},
  "geometry": {"coordinates":[-84.490628,38.040708],"type":"Point"}
}