{
  "type": "Feature",
  "properties": {
    "iso:country":"US",
    "sg:address":"642 South 2nd St",
    "sg:city":"Louisville",
    "sg:classifiers":[
        {
            "category":"Shopping",
            "subcategory":"Party Supplies",
            "type":"Retail Goods"
        },
        {
            "category":"Retail",
            "subcategory":"Event Space",
            "type":"Services"
        },
        {
            "category":"Personal",
            "type":"Services"
        },
        {
            "category":"Communications",
            "subcategory":"Television Station",
            "type":"Services"
        }
    ],
    "sg:phone":"+1 502 472 8444",
    "sg:postcode":"40202",
    "sg:province":"KY",
    "sg:tags":[
        "commercials-radio",
        "sale",
        "planning",
        "convention",
        "ticket",
        "decorating"
    ],
    "wof:name":"Bliss*LLc",
    "wof:placetype":"venue"
},
  "geometry": {"coordinates":[-85.754745,38.24744],"type":"Point"}
}