{
  "type": "Feature",
  "properties": {
    "addr:full":"4001 Nicholasville Rd Lexington KY 40503",
    "addr:housenumber":"4001",
    "addr:postcode":"40503",
    "addr:street":"Nicholasville Rd",
    "iso:country":"US",
    "sg:address":"4001 Nicholasville Rd",
    "sg:city":"Lexington",
    "sg:classifiers":[
        {
            "category":"Fast Food",
            "type":"Food & Drink"
        },
        {
            "category":"Restaurant",
            "type":"Food & Drink"
        }
    ],
    "sg:phone":"+1 859 272 6283",
    "sg:postcode":"40503",
    "sg:province":"KY",
    "sg:tags":[
        "style",
        "hamburger",
        "family",
        "house",
        "dog",
        "hot",
        "barbecue",
        "steak"
    ],
    "sg:website":"http://www.outbacksteakhouse.com",
    "wof:name":"Outback Steakhouse",
    "wof:placetype":"venue"
},
  "geometry": {"coordinates":[-84.528412,37.980358],"type":"Point"}
}