{
  "type": "Feature",
  "properties": {
    "addr:full":"1060 Searcy Way Bowling Green KY 42103",
    "addr:housenumber":"1060",
    "addr:postcode":"42103",
    "addr:street":"Searcy Way",
    "iso:country":"US",
    "sg:address":"1060 Searcy Way",
    "sg:city":"Bowling Green",
    "sg:classifiers":[
        {
            "category":"Professional",
            "type":"Services"
        }
    ],
    "sg:phone":"+1 270 843 4290",
    "sg:postcode":"42103",
    "sg:province":"KY",
    "sg:tags":[
        "establishment"
    ],
    "wof:name":"Bluegrass Network",
    "wof:placetype":"venue"
},
  "geometry": {"coordinates":[-86.42229500000001,36.956159],"type":"Point"}
}