{
  "type": "Feature",
  "properties": {
    "iso:country":"US",
    "sg:address":"301 Slim Hall Rd",
    "sg:city":"Franklin",
    "sg:classifiers":[
        {
            "category":"Professional",
            "subcategory":"Management & Consulting",
            "type":"Services"
        }
    ],
    "sg:phone":"+1 270 586 3519",
    "sg:postcode":"42134",
    "sg:province":"KY",
    "sg:tags":[
        "marketing",
        "program"
    ],
    "wof:name":"Overton Marketing",
    "wof:placetype":"venue"
},
  "geometry": {"coordinates":[-86.591071,36.679324],"type":"Point"}
}