{
  "type": "Feature",
  "properties": {
    "iso:country":"US",
    "sg:address":"161 Lincoln Ave",
    "sg:city":"Lexington",
    "sg:classifiers":[
        {
            "category":"Professional",
            "subcategory":"Art Services",
            "type":"Services"
        }
    ],
    "sg:phone":"+1 859 268 0337",
    "sg:postcode":"40502",
    "sg:province":"KY",
    "sg:tags":[
        "photography",
        "commercial"
    ],
    "wof:name":"AZ Communications",
    "wof:placetype":"venue"
},
  "geometry": {"coordinates":[-84.478177,38.031996],"type":"Point"}
}