{
  "type": "Feature",
  "properties": {
    "addr:full":"9407 Westport Rd Louisville KY 40241",
    "addr:housenumber":"9407",
    "addr:postcode":"40241",
    "addr:street":"Westport Rd",
    "iso:country":"US",
    "sg:address":"9407 Westport Rd",
    "sg:city":"Louisville",
    "sg:classifiers":[
        {
            "category":"Banks & Credit Unions",
            "subcategory":"Investment Brokerage",
            "type":"Services"
        }
    ],
    "sg:phone":"+1 502 412 5802",
    "sg:postcode":"40241",
    "sg:province":"KY",
    "sg:tags":[
        "stock",
        "bond"
    ],
    "wof:name":"Edward Jones Co",
    "wof:placetype":"venue"
},
  "geometry": {"coordinates":[-85.58123500000001,38.284509],"type":"Point"}
}