{
  "type": "Feature",
  "properties": {
    "iso:country":"US",
    "sg:address":"106 E Main St",
    "sg:city":"Midway",
    "sg:classifiers":[
        {
            "category":"Shopping",
            "subcategory":"Used Merchandise",
            "type":"Retail Goods"
        }
    ],
    "sg:phone":"+1 859 846 4652",
    "sg:postcode":"40347",
    "sg:province":"KY",
    "sg:tags":[
        "antique"
    ],
    "wof:name":"Eagle's Nest Gallery",
    "wof:placetype":"venue"
},
  "geometry": {"coordinates":[-84.682818,38.150482],"type":"Point"}
}