{
  "type": "Feature",
  "properties": {
    "addr:full":"2900 State Hwy 176 Greenville KY 42345",
    "addr:housenumber":"2900",
    "addr:postcode":"42345",
    "addr:street":"State Hwy 176;Ky",
    "iso:country":"US",
    "sg:address":"2900 State Hwy 176",
    "sg:city":"Greenville",
    "sg:classifiers":[
        {
            "category":"Education",
            "subcategory":"School",
            "type":"Public Place"
        }
    ],
    "sg:phone":"+1 270 338 9409",
    "sg:postcode":"42345",
    "sg:province":"KY",
    "wof:name":"Muhlenberg South High School",
    "wof:placetype":"venue"
},
  "geometry": {"coordinates":[-87.129892,37.197887],"type":"Point"}
}