{
  "type": "Feature",
  "properties": {
    "addr:full":"5745 Russellville Rd Hopkinsville KY 42240",
    "addr:postcode":"5745;42240",
    "addr:street":"Russellville Rd",
    "iso:country":"US",
    "sg:address":"5745 Russellville Rd",
    "sg:city":"Hopkinsville",
    "sg:classifiers":[
        {
            "category":"Farming",
            "subcategory":"Farm",
            "type":"Manufacturing & Wholesale Goods"
        }
    ],
    "sg:phone":"+1 270 885 9761",
    "sg:postcode":"42240",
    "sg:province":"KY",
    "wof:name":"Five T's Farms LLC",
    "wof:placetype":"venue"
},
  "geometry": {"coordinates":[-87.396916,36.853245],"type":"Point"}
}