{
  "type": "Feature",
  "properties": {
    "addr:full":"928 Sombrero Dr Richmond KY 40475",
    "addr:housenumber":"928",
    "addr:postcode":"40475",
    "addr:street":"Sombrero Dr",
    "iso:country":"US",
    "sg:address":"928 Sombrero Dr",
    "sg:city":"Richmond",
    "sg:phone":"+1 859 527 3467",
    "sg:postcode":"40475",
    "sg:province":"KY",
    "sg:tags":[
        "farm",
        "tobacco"
    ],
    "wof:name":"Pigg Inalee",
    "wof:placetype":"venue"
},
  "geometry": {"coordinates":[-84.26829600000001,37.734364],"type":"Point"}
}