{
  "type": "Feature",
  "properties": {
    "iso:country":"US",
    "sg:address":"200 Broadway St",
    "sg:city":"Paducah",
    "sg:classifiers":[
        {
            "category":"Shopping",
            "type":"Retail Goods"
        }
    ],
    "sg:phone":"+1 270 442 2453",
    "sg:postcode":"42001",
    "sg:province":"KY",
    "sg:tags":[
        "art",
        "gallery",
        "dealer"
    ],
    "wof:name":"Yeiser Art Ctr Inc",
    "wof:placetype":"venue"
},
  "geometry": {"coordinates":[-88.595868,37.087607],"type":"Point"}
}