{
  "type": "Feature",
  "properties": {
    "addr:city":"Paducah",
    "addr:full":"200 Broadway St Paducah, Ky 42001",
    "addr:house_number":"200",
    "addr:housenumber":"200",
    "addr:phone":"+1 270-442-2453",
    "addr:postcode":"42001",
    "addr:road":"Broadway St",
    "addr:state":"KY",
    "addr:street":"Broadway St",
    "iso:country":"US",
    "sg:address":"200 Broadway St",
    "sg:city":"Paducah",
    "sg:classifiers":[
        {
            "category":"Shopping",
            "type":"Retail Goods"
        }
    ],
    "sg:phone":"+1 270 442 2453",
    "sg:postcode":"42001",
    "sg:province":"KY",
    "sg:tags":[
        "art",
        "gallery",
        "dealer"
    ],
    "wof:airports":[
        102529565
    ],
    "wof:name":"Yeiser Art Center",
    "wof:placetype":"venue"
},
  "geometry": {"coordinates":[-88.5966,37.0872],"type":"Point"}
}