{
  "type": "Feature",
  "properties": {
    "addr:full":"826 N Elm St Hopkinsville KY 42240",
    "addr:housenumber":"826",
    "addr:postcode":"42240",
    "addr:street":"N Elm St",
    "iso:country":"US",
    "sg:address":"826 N Elm St",
    "sg:city":"Hopkinsville",
    "sg:classifiers":[
        {
            "category":"Real Estate",
            "subcategory":"Real Estate Operator",
            "type":"Services"
        }
    ],
    "sg:phone":"+1 270 885 4333",
    "sg:postcode":"42240",
    "sg:province":"KY",
    "sg:tags":[
        "apartment"
    ],
    "wof:name":"Greenway Place Apartments",
    "wof:placetype":"venue"
},
  "geometry": {"coordinates":[-87.48396099999999,36.883283],"type":"Point"}
}