{
  "type": "Feature",
  "properties": {
    "addr:full":"8664 Kingfisher Lake Rd Maceo KY 42355",
    "addr:housenumber":"8664",
    "addr:postcode":"42355",
    "addr:street":"Kingfisher Lake Rd",
    "iso:country":"US",
    "sg:address":"8664 Kingfisher Lake Rd",
    "sg:city":"Maceo",
    "sg:classifiers":[
        {
            "category":"Real Estate",
            "subcategory":"Real Estate Operator",
            "type":"Services"
        }
    ],
    "sg:phone":"+1 270 264 1276",
    "sg:postcode":"42355",
    "sg:province":"KY",
    "sg:tags":[
        "mobile",
        "home",
        "site"
    ],
    "wof:name":"Trail A Way Mobile Home Park",
    "wof:placetype":"venue"
},
  "geometry": {"coordinates":[-86.97418399999999,37.844441],"type":"Point"}
}