{
  "type": "Feature",
  "properties": {
    "iso:country":"US",
    "sg:address":"2920 Brownsboro Rd",
    "sg:city":"Louisville",
    "sg:classifiers":[
        {
            "category":"Personal",
            "subcategory":"Barber",
            "type":"Services"
        }
    ],
    "sg:phone":"+1 502 897 1209",
    "sg:postcode":"40206",
    "sg:province":"KY",
    "wof:name":"Visible Changes Hair Studio",
    "wof:placetype":"venue"
},
  "geometry": {"coordinates":[-85.68678300000001,38.260288],"type":"Point"}
}