{
  "type": "Feature",
  "properties": {
    "iso:country":"US",
    "sg:address":"1630 Hampton Rd",
    "sg:city":"London",
    "sg:classifiers":[
        {
            "category":"Building & Trades",
            "subcategory":"Equipment Rental",
            "type":"Services"
        }
    ],
    "sg:phone":"+1 606 878 8425",
    "sg:postcode":"40741",
    "sg:province":"KY",
    "sg:tags":[
        "toilet"
    ],
    "wof:name":"A Plus Portable Restrooms",
    "wof:placetype":"venue"
},
  "geometry": {"coordinates":[-84.07569100000001,37.108878],"type":"Point"}
}