{
  "type": "Feature",
  "properties": {
    "iso:country":"US",
    "sg:address":"5084 Murray-Paris Rd",
    "sg:city":"Hazel",
    "sg:classifiers":[
        {
            "category":"Organizations",
            "subcategory":"Religious Organization",
            "type":"Services"
        }
    ],
    "sg:phone":"+1 270 492 6154",
    "sg:postcode":"42049",
    "sg:province":"KY",
    "sg:tags":[
        "church"
    ],
    "wof:name":"Mason's Chapel Methodist Chr",
    "wof:placetype":"venue"
},
  "geometry": {"coordinates":[-88.301558,36.514373],"type":"Point"}
}