{
  "type": "Feature",
  "properties": {
    "addr:full":"1118 Chaffee Ave Fort Knox KY 40121",
    "addr:housenumber":"1118",
    "addr:postcode":"40121",
    "addr:street":"Chaffee Ave",
    "iso:country":"US",
    "sg:address":"1118 Chaffee Ave",
    "sg:city":"Fort Knox",
    "sg:classifiers":[
        {
            "category":"Organizations",
            "subcategory":"Community Association",
            "type":"Services"
        }
    ],
    "sg:phone":"+1 502 942 8383",
    "sg:postcode":"40121",
    "sg:province":"KY",
    "sg:tags":[
        "club"
    ],
    "wof:name":"Fort KNOX Officers Club",
    "wof:placetype":"venue"
},
  "geometry": {"coordinates":[-85.952716,37.8949],"type":"Point"}
}