{
  "type": "Feature",
  "properties": {
    "iso:country":"US",
    "sg:address":"31 S Laurel Rd",
    "sg:city":"London",
    "sg:classifiers":[
        {
            "category":"Government",
            "subcategory":"Office",
            "type":"Public Place"
        }
    ],
    "sg:phone":"+1 606 864 6811",
    "sg:postcode":"40744",
    "sg:province":"KY",
    "sg:tags":[
        "state",
        "resource"
    ],
    "sg:website":"www.kentucky.gov",
    "wof:name":"Food Stamp Ofc",
    "wof:placetype":"venue"
},
  "geometry": {"coordinates":[-84.071985,37.106431],"type":"Point"}
}