{
  "type": "Feature",
  "properties": {
    "iso:country":"US",
    "sg:address":"636 Cherry St",
    "sg:city":"Calvert City",
    "sg:classifiers":[
        {
            "category":"Professional",
            "subcategory":"Art Services",
            "type":"Services"
        }
    ],
    "sg:phone":"+1 270 395 1782",
    "sg:postcode":"42029",
    "sg:province":"KY",
    "sg:tags":[
        "photography",
        "commercial"
    ],
    "wof:name":"Pma",
    "wof:placetype":"venue"
},
  "geometry": {"coordinates":[-88.346284,37.023203],"type":"Point"}
}