{
  "type": "Feature",
  "properties": {
    "addr:full":"9300 Shelbyville Rd Louisville KY 40222",
    "addr:housenumber":"9300",
    "addr:postcode":"40222",
    "addr:street":"Shelbyville Rd",
    "iso:country":"US",
    "sg:address":"9300 Shelbyville Rd",
    "sg:city":"Louisville",
    "sg:classifiers":[
        {
            "category":"Health Services",
            "subcategory":"Medical Lab",
            "type":"Services"
        }
    ],
    "sg:phone":"+1 502 412 0650",
    "sg:postcode":"40222",
    "sg:province":"KY",
    "sg:tags":[
        "resonance",
        "magnetic",
        "imaging"
    ],
    "sg:website":"www.reeng.com",
    "wof:name":"Results Engineering",
    "wof:placetype":"venue"
},
  "geometry": {"coordinates":[-85.579438,38.24661],"type":"Point"}
}