{
  "type": "Feature",
  "properties": {
    "iso:country":"US",
    "sg:address":"204 Prince Royal Dr",
    "sg:city":"Berea",
    "sg:classifiers":[
        {
            "category":"Sports & Exercise",
            "subcategory":"Gym",
            "type":"Entertainment"
        }
    ],
    "sg:phone":"+1 859 985 5000",
    "sg:postcode":"40403",
    "sg:province":"KY",
    "sg:tags":[
        "club",
        "health",
        "studio",
        "gymnasium"
    ],
    "wof:name":"Contours Express-Berea",
    "wof:placetype":"venue"
},
  "geometry": {"coordinates":[-84.31088,37.568861],"type":"Point"}
}