{
  "type": "Feature",
  "properties": {
    "iso:country":"US",
    "sg:address":"405 McGuire St",
    "sg:city":"Somerset",
    "sg:classifiers":[
        {
            "category":"Building & Trades",
            "subcategory":"Plumbing",
            "type":"Services"
        }
    ],
    "sg:phone":"+1 606 678 0441",
    "sg:postcode":"42501",
    "sg:province":"KY",
    "sg:tags":[
        "heating",
        "contractor"
    ],
    "wof:name":"Trig Heating & Air",
    "wof:placetype":"venue"
},
  "geometry": {"coordinates":[-84.602687,37.074052],"type":"Point"}
}