{
  "type": "Feature",
  "properties": {
    "addr:full":"3306 N Henderson Way Clarksville KY 37042",
    "addr:housenumber":"3306",
    "addr:postcode":"37042",
    "addr:street":"N Henderson Way",
    "iso:country":"US",
    "sg:address":"3306 N Henderson Way",
    "sg:city":"Clarksville",
    "sg:classifiers":[
        {
            "category":"Real Estate",
            "subcategory":"Real Estate Operator",
            "type":"Services"
        }
    ],
    "sg:phone":"+1 931 647 7964",
    "sg:postcode":"37042",
    "sg:province":"KY",
    "sg:tags":[
        "building",
        "nonresidential"
    ],
    "wof:name":"Saint Jude Properties LLC",
    "wof:placetype":"venue"
},
  "geometry": {"coordinates":[-87.35867500000001,36.628802],"type":"Point"}
}