{
  "type": "Feature",
  "properties": {
    "iso:country":"US",
    "sg:address":"1085 Bloomfield Rd",
    "sg:city":"Bardstown",
    "sg:classifiers":[
        {
            "category":"Food & Beverages",
            "subcategory":"Groceries & Convenience Stores",
            "type":"Retail Goods"
        }
    ],
    "sg:phone":"+1 502 349 0707",
    "sg:postcode":"40004",
    "sg:province":"KY",
    "sg:tags":[
        "grocer"
    ],
    "wof:name":"Rosie's Food Market",
    "wof:placetype":"venue"
},
  "geometry": {"coordinates":[-85.425397,37.827482],"type":"Point"}
}