{
  "type": "Feature",
  "properties": {
    "addr:full":"100 Marketplace Dr Lexington KY 40503",
    "addr:housenumber":"100",
    "addr:postcode":"40503",
    "addr:street":"Marketplace Dr",
    "iso:country":"US",
    "sg:address":"100 Marketplace Dr",
    "sg:city":"Lexington",
    "sg:classifiers":[
        {
            "category":"Restaurant",
            "type":"Food & Drink"
        }
    ],
    "sg:phone":"+1 859 245 9791",
    "sg:postcode":"40503",
    "sg:province":"KY",
    "wof:name":"Mc Donald's",
    "wof:placetype":"venue"
},
  "geometry": {"coordinates":[-84.52930499999999,37.978283],"type":"Point"}
}