{
  "type": "Feature",
  "properties": {
    "iso:country":"US",
    "sg:address":"11 Hunter Rd",
    "sg:city":"Taylorsville",
    "sg:classifiers":[
        {
            "category":"Travel",
            "subcategory":"Campground",
            "type":"Entertainment"
        }
    ],
    "sg:phone":"+1 502 477 1291",
    "sg:postcode":"40071",
    "sg:province":"KY",
    "sg:tags":[
        "camp"
    ],
    "wof:name":"Village By The Lake",
    "wof:placetype":"venue"
},
  "geometry": {"coordinates":[-85.29062500000001,38.04066],"type":"Point"}
}