{
  "type": "Feature",
  "properties": {
    "iso:country":"US",
    "sg:address":"208 S Broadway St",
    "sg:city":"Georgetown",
    "sg:classifiers":[
        {
            "category":"Autos & Motor Vehicles",
            "subcategory":"Fuel & Gas Station",
            "type":"Retail Goods"
        }
    ],
    "sg:phone":"+1 502 863 6395",
    "sg:postcode":"40324",
    "sg:province":"KY",
    "sg:tags":[
        "oil"
    ],
    "wof:name":"Fast Max Sunoco",
    "wof:placetype":"venue"
},
  "geometry": {"coordinates":[-84.559879,38.208224],"type":"Point"}
}