{
  "type": "Feature",
  "properties": {
    "iso:country":"US",
    "sg:address":"1026 N Dividing Ridge Rd",
    "sg:city":"Sadieville",
    "sg:classifiers":[
        {
            "category":"Retail",
            "subcategory":"Auto Repair",
            "type":"Services"
        }
    ],
    "sg:phone":"+1 502 857 2722",
    "sg:postcode":"40370",
    "sg:province":"KY",
    "sg:tags":[
        "body"
    ],
    "wof:name":"Dans Autobody",
    "wof:placetype":"venue"
},
  "geometry": {"coordinates":[-84.46969900000001,38.374118],"type":"Point"}
}