{
  "type": "Feature",
  "properties": {
    "iso:country":"US",
    "sg:address":"201 E Main St",
    "sg:city":"Richmond",
    "sg:classifiers":[
        {
            "category":"Organizations",
            "subcategory":"Professional Association",
            "type":"Services"
        }
    ],
    "sg:phone":"+1 859 623 1720",
    "sg:postcode":"40475",
    "sg:province":"KY",
    "sg:tags":[
        "chambers",
        "commerce"
    ],
    "sg:website":"www.richmondchamber.com",
    "wof:name":"Richmond Chamber Of Commerce",
    "wof:placetype":"venue"
},
  "geometry": {"coordinates":[-84.29304399999999,37.74693],"type":"Point"}
}