{
  "type": "Feature",
  "properties": {
    "addr:full":"213 W Stephen Foster Ave Bardstown KY 40004",
    "addr:housenumber":"213",
    "addr:postcode":"40004",
    "addr:street":"W Stephen Foster Ave",
    "iso:country":"US",
    "sg:address":"213 W Stephen Foster Ave",
    "sg:city":"Bardstown",
    "sg:classifiers":[
        {
            "category":"Shopping",
            "subcategory":"Used Merchandise",
            "type":"Retail Goods"
        }
    ],
    "sg:phone":"+1 502 348 2779",
    "sg:postcode":"40004",
    "sg:province":"KY",
    "sg:tags":[
        "flea",
        "market"
    ],
    "wof:name":"Fergie's Now & Then",
    "wof:placetype":"venue"
},
  "geometry": {"coordinates":[-85.47012100000001,37.809686],"type":"Point"}
}