{
  "type": "Feature",
  "properties": {
    "iso:country":"US",
    "sg:address":"3932 Dutchmans Ln",
    "sg:city":"St Matthews",
    "sg:classifiers":[
        {
            "category":"Health Services",
            "subcategory":"Doctor",
            "type":"Services"
        }
    ],
    "sg:phone":"+1 502 895 0797",
    "sg:postcode":"40207",
    "sg:province":"KY",
    "sg:tags":[
        "dentist"
    ],
    "sg:website":"www.dupontdentalgroup.com",
    "wof:name":"Dupont Dental Office",
    "wof:placetype":"venue"
},
  "geometry": {"coordinates":[-85.63754900000001,38.23244],"type":"Point"}
}