{
  "type": "Feature",
  "properties": {
    "iso:country":"US",
    "sg:address":"7526 N Dixie Hwy",
    "sg:city":"Bonnieville",
    "sg:classifiers":[
        {
            "category":"Restaurant",
            "type":"Food & Drink"
        }
    ],
    "sg:phone":"+1 270 531 3663",
    "sg:postcode":"42713",
    "sg:province":"KY",
    "wof:name":"Jameson House Family Rstrnt",
    "wof:placetype":"venue"
},
  "geometry": {"coordinates":[-85.90263299999999,37.375126],"type":"Point"}
}