{
  "type": "Feature",
  "properties": {
    "iso:country":"US",
    "sg:address":"1527 Duncan Creek Rd",
    "sg:city":"Kirksey",
    "sg:classifiers":[
        {
            "category":"Real Estate",
            "subcategory":"Real Estate Operator",
            "type":"Services"
        }
    ],
    "sg:phone":"+1 270 489 2601",
    "sg:postcode":"42054",
    "sg:province":"KY",
    "sg:tags":[
        "property",
        "lessor"
    ],
    "wof:name":"Michael Palmer",
    "wof:placetype":"venue"
},
  "geometry": {"coordinates":[-88.45160199999999,36.752377],"type":"Point"}
}