{
  "type": "Feature",
  "properties": {
    "iso:country":"US",
    "sg:address":"215 S Hurstbourne Pkwy",
    "sg:city":"Louisville",
    "sg:classifiers":[
        {
            "category":"Shopping",
            "subcategory":"Books",
            "type":"Retail Goods"
        }
    ],
    "sg:phone":"+1 502 426 2424",
    "sg:postcode":"40222",
    "sg:province":"KY",
    "sg:tags":[
        "dealer"
    ],
    "sg:website":"www.iloveaudiobooks.com",
    "wof:name":"I Love Audiobooks",
    "wof:placetype":"venue"
},
  "geometry": {"coordinates":[-85.576814,38.246327],"type":"Point"}
}