{
  "type": "Feature",
  "properties": {
    "iso:country":"US",
    "sg:address":"3 Cleveland Ave",
    "sg:city":"Winchester",
    "sg:classifiers":[
        {
            "category":"Real Estate",
            "subcategory":"Architect",
            "type":"Services"
        }
    ],
    "sg:phone":"+1 859 745 5783",
    "sg:postcode":"40391",
    "sg:province":"KY",
    "sg:tags":[
        "architectural"
    ],
    "wof:name":"Gary Spry Architect",
    "wof:placetype":"venue"
},
  "geometry": {"coordinates":[-84.177869,37.993337],"type":"Point"}
}