{
  "type": "Feature",
  "properties": {
    "iso:country":"US",
    "sg:address":"97 Kentucky St",
    "sg:city":"Fordsville",
    "sg:classifiers":[
        {
            "category":"Building & Trades",
            "subcategory":"Equipment Rental",
            "type":"Services"
        }
    ],
    "sg:phone":"+1 270 276 5304",
    "sg:postcode":"42343",
    "sg:province":"KY",
    "wof:name":"Lakeland Home Rentals Inc",
    "wof:placetype":"venue"
},
  "geometry": {"coordinates":[-86.72031699999999,37.635696],"type":"Point"}
}