{
  "type": "Feature",
  "properties": {
    "addr:full":"2858 Frankfort Ave Louisville KY 40206",
    "addr:housenumber":"2858",
    "addr:postcode":"40206",
    "addr:street":"Frankfort",
    "iso:country":"US",
    "sg:address":"2858 Frankfort Ave",
    "sg:city":"Louisville",
    "sg:classifiers":[
        {
            "category":"Professional",
            "subcategory":"Management & Consulting",
            "type":"Services"
        }
    ],
    "sg:phone":"+1 502 895 2821",
    "sg:postcode":"40206",
    "sg:province":"KY",
    "sg:tags":[
        "consultant",
        "business"
    ],
    "wof:name":"Ewing Niels & Assoc",
    "wof:placetype":"venue"
},
  "geometry": {"coordinates":[-85.687516,38.254603],"type":"Point"}
}