{
  "type": "Feature",
  "properties": {
    "iso:country":"US",
    "sg:address":"5025 Shelbyville Rd",
    "sg:city":"St Matthews",
    "sg:classifiers":[
        {
            "category":"Home & Garden",
            "subcategory":"Garden Supply",
            "type":"Retail Goods"
        }
    ],
    "sg:phone":"+1 502 896 2226",
    "sg:postcode":"40207",
    "sg:province":"KY",
    "sg:tags":[
        "nurseryman"
    ],
    "wof:name":"Frank Otte Nursery & Garden",
    "wof:placetype":"venue"
},
  "geometry": {"coordinates":[-85.623563,38.250336],"type":"Point"}
}