{
  "type": "Feature",
  "properties": {
    "addr:full":"4079 Old Salem Rd London KY 40741",
    "addr:housenumber":"4079",
    "addr:postcode":"40741",
    "addr:street":"Old Salem Rd",
    "iso:country":"US",
    "sg:address":"4079 Old Salem Rd",
    "sg:city":"London",
    "sg:classifiers":[
        {
            "category":"Farming",
            "subcategory":"Farm",
            "type":"Manufacturing & Wholesale Goods"
        }
    ],
    "sg:phone":"+1 606 864 5981",
    "sg:postcode":"40741",
    "sg:province":"KY",
    "sg:tags":[
        "crop",
        "general"
    ],
    "wof:name":"Calvin Rush",
    "wof:placetype":"venue"
},
  "geometry": {"coordinates":[-84.044552,37.170935],"type":"Point"}
}