{
  "type": "Feature",
  "properties": {
    "iso:country":"US",
    "sg:address":"626 Sunnyside Dr",
    "sg:city":"Franklin",
    "sg:classifiers":[
        {
            "category":"Professional",
            "subcategory":"Management & Consulting",
            "type":"Services"
        }
    ],
    "sg:phone":"+1 270 586 8459",
    "sg:postcode":"42134",
    "sg:province":"KY",
    "wof:name":"Sunnyside Marketing",
    "wof:placetype":"venue"
},
  "geometry": {"coordinates":[-86.561393,36.735213],"type":"Point"}
}