{
  "type": "Feature",
  "properties": {
    "iso:country":"US",
    "sg:address":"190 W 1st St",
    "sg:city":"Campbellsville",
    "sg:classifiers":[
        {
            "category":"Government",
            "subcategory":"Office",
            "type":"Public Place"
        }
    ],
    "sg:phone":"+1 270 789 2359",
    "sg:postcode":"42718",
    "sg:province":"KY",
    "sg:tags":[
        "state",
        "resource"
    ],
    "wof:name":"Vocational Rehabilitation",
    "wof:placetype":"venue"
},
  "geometry": {"coordinates":[-85.346411,37.3405],"type":"Point"}
}