{
  "type": "Feature",
  "properties": {
    "addr:full":"1407 Old Gallatin Rd Scottsville KY 42164",
    "addr:housenumber":"1407",
    "addr:postcode":"42164",
    "addr:street":"Old Gallatin Rd",
    "iso:country":"US",
    "sg:address":"1407 Old Gallatin Rd",
    "sg:city":"Scottsville",
    "sg:classifiers":[
        {
            "category":"Shopping",
            "subcategory":"Pharmacy",
            "type":"Retail Goods"
        }
    ],
    "sg:phone":"+1 270 237 4024",
    "sg:postcode":"42164",
    "sg:province":"KY",
    "sg:tags":[
        "drug",
        "store"
    ],
    "wof:name":"Rite Aid",
    "wof:placetype":"venue"
},
  "geometry": {"coordinates":[-86.208838,36.741703],"type":"Point"}
}