{
  "type": "Feature",
  "properties": {
    "iso:country":"US",
    "sg:address":"4112 Brentler Rd",
    "sg:city":"Louisville",
    "sg:classifiers":[
        {
            "category":"Professional",
            "subcategory":"Computer Services",
            "type":"Services"
        }
    ],
    "sg:phone":"+1 502 821 6794",
    "sg:postcode":"40241",
    "sg:province":"KY",
    "sg:tags":[
        "publisher",
        "developer",
        "software"
    ],
    "wof:name":"Van Horn, Amos",
    "wof:placetype":"venue"
},
  "geometry": {"coordinates":[-85.60180699999999,38.306954],"type":"Point"}
}