{
  "type": "Feature",
  "properties": {
    "iso:country":"US",
    "sg:address":"103 Cherry Ln",
    "sg:city":"Frankfort",
    "sg:classifiers":[
        {
            "category":"Building & Trades",
            "subcategory":"Construction",
            "type":"Services"
        }
    ],
    "sg:phone":"+1 502 226 2511",
    "sg:postcode":"40601",
    "sg:province":"KY",
    "sg:tags":[
        "house"
    ],
    "wof:name":"Suter Construction",
    "wof:placetype":"venue"
},
  "geometry": {"coordinates":[-84.93146299999999,38.111496],"type":"Point"}
}