{
  "type": "Feature",
  "properties": {
    "addr:full":"2516 Frankfort Ave Louisville KY 40206",
    "addr:housenumber":"2516",
    "addr:postcode":"40206",
    "addr:street":"Frankfort",
    "iso:country":"US",
    "sg:address":"2516 Frankfort Ave",
    "sg:city":"Louisville",
    "sg:classifiers":[
        {
            "category":"Professional",
            "subcategory":"Business Services",
            "type":"Services"
        }
    ],
    "sg:phone":"+1 502 897 2098",
    "sg:postcode":"40206",
    "sg:province":"KY",
    "sg:tags":[
        "interior",
        "consultant",
        "design",
        "decorator"
    ],
    "wof:name":"Beverley Beaver Interior Dsgn",
    "wof:placetype":"venue"
},
  "geometry": {"coordinates":[-85.696798,38.254066],"type":"Point"}
}