{
  "type": "Feature",
  "properties": {
    "iso:country":"US",
    "sg:address":"7 Main St",
    "sg:city":"Cadiz",
    "sg:classifiers":[
        {
            "category":"Personal",
            "type":"Services"
        }
    ],
    "sg:phone":"+1 270 522 1030",
    "sg:postcode":"42211",
    "sg:province":"KY",
    "sg:tags":[
        "therapist",
        "massage"
    ],
    "wof:name":"Therapeutic Touch",
    "wof:placetype":"venue"
},
  "geometry": {"coordinates":[-87.83833,36.861177],"type":"Point"}
}