{
  "type": "Feature",
  "properties": {
    "iso:country":"US",
    "sg:address":"2340 Ampere Dr",
    "sg:city":"Louisville",
    "sg:classifiers":[
        {
            "category":"Wholesale",
            "subcategory":"Farm Supplies",
            "type":"Manufacturing & Wholesale Goods"
        },
        {
            "category":"Recreation",
            "subcategory":"Picnic Area",
            "type":"Entertainment"
        }
    ],
    "sg:phone":"+1 502 266 7177",
    "sg:postcode":"40299",
    "sg:province":"KY",
    "sg:tags":[
        "equipment",
        "equipment-parts",
        "repair"
    ],
    "sg:website":"http://www.wajohnson.com",
    "wof:name":"Johnson W A Inc",
    "wof:placetype":"venue"
},
  "geometry": {"coordinates":[-85.551905,38.208182],"type":"Point"}
}