{
  "type": "Feature",
  "properties": {
    "iso:country":"US",
    "sg:address":"5245 Stewartsville Rd",
    "sg:city":"Williamstown",
    "sg:classifiers":[
        {
            "category":"Home & Garden",
            "subcategory":"Garden Supply",
            "type":"Retail Goods"
        }
    ],
    "sg:phone":"+1 859 824 4266",
    "sg:postcode":"41097",
    "sg:province":"KY",
    "sg:tags":[
        "bulb",
        "seed"
    ],
    "wof:name":"Henry Northcutt",
    "wof:placetype":"venue"
},
  "geometry": {"coordinates":[-84.666241,38.63811],"type":"Point"}
}