{
  "type": "Feature",
  "properties": {
    "iso:country":"US",
    "sg:address":"4632 Old Lagrange Rd",
    "sg:city":"Buckner",
    "sg:classifiers":[
        {
            "category":"Professional",
            "subcategory":"Testing Lab",
            "type":"Services"
        }
    ],
    "sg:phone":"+1 502 222 5720",
    "sg:postcode":"40010",
    "sg:province":"KY",
    "sg:tags":[
        "laboratory"
    ],
    "wof:name":"Air Filter Testing Labs Inc",
    "wof:placetype":"venue"
},
  "geometry": {"coordinates":[-85.44271999999999,38.377217],"type":"Point"}
}