{
  "type": "Feature",
  "properties": {
    "addr:full":"2010 S Walnut St Hopkinsville KY 42240",
    "addr:housenumber":"2010",
    "addr:postcode":"42240",
    "addr:street":"S Walnut St",
    "iso:country":"US",
    "sg:address":"2010 S Walnut St",
    "sg:city":"Hopkinsville",
    "sg:classifiers":[
        {
            "category":"Autos & Motor Vehicles",
            "subcategory":"Automobile Sales",
            "type":"Retail Goods"
        }
    ],
    "sg:phone":"+1 270 889 9050",
    "sg:postcode":"42240",
    "sg:province":"KY",
    "sg:tags":[
        "car",
        "dealer"
    ],
    "wof:name":"Car-Mart Of Hopkinsville",
    "wof:placetype":"venue"
},
  "geometry": {"coordinates":[-87.48807499999999,36.85501],"type":"Point"}
}