{
  "type": "Feature",
  "properties": {
    "iso:country":"US",
    "sg:address":"6809 Norway Dr",
    "sg:city":"Louisville",
    "sg:classifiers":[
        {
            "category":"Shopping",
            "type":"Retail Goods"
        }
    ],
    "sg:phone":"+1 502 367 0630",
    "sg:postcode":"40214",
    "sg:province":"KY",
    "sg:tags":[
        "church",
        "supply"
    ],
    "wof:name":"Train Depot",
    "wof:placetype":"venue"
},
  "geometry": {"coordinates":[-85.79526,38.162028],"type":"Point"}
}