{
  "type": "Feature",
  "properties": {
    "addr:full":"5 E 8th St Covington KY 41011",
    "addr:housenumber":"5",
    "addr:postcode":"41011",
    "addr:street":"E 8Th St",
    "iso:country":"US",
    "sg:address":"5 E 8th St",
    "sg:city":"Covington",
    "sg:classifiers":[
        {
            "category":"Retail",
            "subcategory":"Portrait Studio",
            "type":"Services"
        }
    ],
    "sg:phone":"+1 859 261 9500",
    "sg:postcode":"41011",
    "sg:province":"KY",
    "sg:tags":[
        "photography"
    ],
    "wof:name":"Beach Photography & DJ",
    "wof:placetype":"venue"
},
  "geometry": {"coordinates":[-84.50821999999999,39.082397],"type":"Point"}
}