{
  "type": "Feature",
  "properties": {
    "addr:full":"1700 Ups Dr Louisville KY 40223",
    "addr:housenumber":"1700",
    "addr:postcode":"40223",
    "addr:street":"Ups Dr",
    "iso:country":"US",
    "sg:address":"1700 Ups Dr",
    "sg:city":"Louisville",
    "sg:classifiers":[
        {
            "category":"Banks & Credit Unions",
            "subcategory":"Investment Brokerage",
            "type":"Services"
        }
    ],
    "sg:phone":"+1 502 426 7918",
    "sg:postcode":"40223",
    "sg:province":"KY",
    "sg:tags":[
        "consultant",
        "financing"
    ],
    "wof:name":"AIG Royal Alliance",
    "wof:placetype":"venue"
},
  "geometry": {"coordinates":[-85.569091,38.269114],"type":"Point"}
}