{
  "type": "Feature",
  "properties": {
    "iso:country":"US",
    "sg:address":"10076 Jackson Rd N",
    "sg:city":"Utica",
    "sg:classifiers":[
        {
            "category":"Professional",
            "type":"Services"
        }
    ],
    "sg:phone":"+1 270 733 4794",
    "sg:postcode":"42376",
    "sg:province":"KY",
    "wof:name":"Morrison Sheet Metal",
    "wof:placetype":"venue"
},
  "geometry": {"coordinates":[-87.146584,37.621213],"type":"Point"}
}