{
  "type": "Feature",
  "properties": {
    "iso:country":"US",
    "sg:address":"408 Lebanon Ave",
    "sg:city":"Campbellsville",
    "sg:classifiers":[
        {
            "category":"Travel",
            "subcategory":"Travel Agent",
            "type":"Entertainment"
        }
    ],
    "sg:phone":"+1 270 465 3387",
    "sg:postcode":"42718",
    "sg:province":"KY",
    "sg:tags":[
        "operator",
        "tour"
    ],
    "wof:name":"Faulkner Tours",
    "wof:placetype":"venue"
},
  "geometry": {"coordinates":[-85.343097,37.34492],"type":"Point"}
}