{
  "type": "Feature",
  "properties": {
    "iso:country":"US",
    "sg:address":"304 Ash Run Rd",
    "sg:city":"Louisville",
    "sg:classifiers":[
        {
            "category":"Retail",
            "subcategory":"Animal Services",
            "type":"Services"
        }
    ],
    "sg:phone":"+1 502 253 1763",
    "sg:postcode":"40245",
    "sg:province":"KY",
    "sg:tags":[
        "horse",
        "training"
    ],
    "wof:name":"Wallace A. Dollase Thoroughbred Training, Inc.",
    "wof:placetype":"venue"
},
  "geometry": {"coordinates":[-85.43951199999999,38.234431],"type":"Point"}
}