{
  "type": "Feature",
  "properties": {
    "iso:country":"US",
    "sg:address":"10350 Ormsby Park Pl",
    "sg:city":"Louisville",
    "sg:classifiers":[
        {
            "category":"Banks & Credit Unions",
            "subcategory":"Bank",
            "type":"Services"
        }
    ],
    "sg:phone":"+1 502 412 4260",
    "sg:postcode":"40223",
    "sg:province":"KY",
    "sg:tags":[
        "loan",
        "real estate"
    ],
    "wof:name":"Waterfield Financial Corp",
    "wof:placetype":"venue"
},
  "geometry": {"coordinates":[-85.567273,38.263904],"type":"Point"}
}