{
  "type": "Feature",
  "properties": {
    "iso:country":"US",
    "sg:address":"334 E 10th Ave",
    "sg:city":"Bowling Green",
    "sg:classifiers":[
        {
            "category":"Professional",
            "subcategory":"Accounting & Tax Preparation",
            "type":"Services"
        }
    ],
    "sg:phone":"+1 270 783 9035",
    "sg:postcode":"42101",
    "sg:province":"KY",
    "sg:tags":[
        "accountant"
    ],
    "wof:name":"Dale Rose CPA",
    "wof:placetype":"venue"
},
  "geometry": {"coordinates":[-86.44356000000001,36.993739],"type":"Point"}
}