{
  "type": "Feature",
  "properties": {
    "iso:country":"US",
    "sg:address":"401 Asbury Point Dr",
    "sg:city":"Warsaw",
    "sg:classifiers":[
        {
            "category":"Personal",
            "type":"Services"
        }
    ],
    "sg:phone":"+1 859 567 2700",
    "sg:postcode":"41095",
    "sg:province":"KY",
    "wof:name":"Asbury Pointe",
    "wof:placetype":"venue"
},
  "geometry": {"coordinates":[-84.885955,38.782143],"type":"Point"}
}