{
  "type": "Feature",
  "properties": {
    "addr:full":"4500 Bowling Blvd Louisville KY 40207",
    "addr:housenumber":"4500",
    "addr:postcode":"40207",
    "addr:street":"Bowling Blvd",
    "iso:country":"US",
    "sg:address":"4500 Bowling Blvd",
    "sg:city":"Louisville",
    "sg:classifiers":[
        {
            "category":"Professional",
            "subcategory":"Lawyer & Legal Services",
            "type":"Services"
        }
    ],
    "sg:phone":"+1 502 895 8787",
    "sg:postcode":"40207",
    "sg:province":"KY",
    "sg:tags":[
        "attorney",
        "injury",
        "family",
        "personal",
        "collection",
        "real estate",
        "law"
    ],
    "sg:website":"http://www.bornopp.com",
    "wof:name":"Bornstein & Oppenheimer PLLC",
    "wof:placetype":"venue"
},
  "geometry": {"coordinates":[-85.63131,38.240528],"type":"Point"}
}