{
  "type": "Feature",
  "properties": {
    "iso:country":"US",
    "sg:address":"177 Graham Dr",
    "sg:city":"Bowling Green",
    "sg:classifiers":[
        {
            "category":"Social Services",
            "type":"Services"
        }
    ],
    "sg:phone":"+1 270 781 7923",
    "sg:postcode":"42101",
    "sg:province":"KY",
    "sg:tags":[
        "info",
        "program",
        "referral"
    ],
    "wof:name":"Kentucky Homeplace Program",
    "wof:placetype":"venue"
},
  "geometry": {"coordinates":[-86.441225,37.002299],"type":"Point"}
}