{
  "type": "Feature",
  "properties": {
    "iso:country":"US",
    "sg:address":"203 Bradshaw Pike",
    "sg:city":"Hopkinsville",
    "sg:classifiers":[
        {
            "category":"Freight",
            "type":"Transportation"
        }
    ],
    "sg:phone":"+1 270 886 0156",
    "sg:postcode":"42240",
    "sg:province":"KY",
    "sg:tags":[
        "commercial",
        "storage"
    ],
    "wof:name":"Leek Van & Storage Co",
    "wof:placetype":"venue"
},
  "geometry": {"coordinates":[-87.457461,36.841129],"type":"Point"}
}