{
  "type": "Feature",
  "properties": {
    "addr:full":"101 W Ramsey St Dawson Springs KY 42408",
    "addr:housenumber":"101",
    "addr:postcode":"42408",
    "addr:street":"W Ramsey St",
    "iso:country":"US",
    "sg:address":"101 W Ramsey St",
    "sg:city":"Dawson Springs",
    "sg:classifiers":[
        {
            "category":"Government",
            "subcategory":"Post Office",
            "type":"Public Place"
        }
    ],
    "sg:phone":"+1 270 797 5598",
    "sg:postcode":"42408",
    "sg:province":"KY",
    "wof:name":"US Post Office",
    "wof:placetype":"venue"
},
  "geometry": {"coordinates":[-87.69133600000001,37.166365],"type":"Point"}
}