{
  "type": "Feature",
  "properties": {
    "iso:country":"US",
    "sg:address":"423 Woodbine St",
    "sg:city":"Louisville",
    "sg:classifiers":[
        {
            "category":"Wholesale",
            "subcategory":"Metals & Minerals",
            "type":"Manufacturing & Wholesale Goods"
        }
    ],
    "sg:phone":"+1 502 637 1247",
    "sg:postcode":"40208",
    "sg:province":"KY",
    "sg:tags":[
        "pipe"
    ],
    "wof:name":"Corrosion Products Inc",
    "wof:placetype":"venue"
},
  "geometry": {"coordinates":[-85.748802,38.228884],"type":"Point"}
}