{
  "type": "Feature",
  "properties": {
    "addr:full":"1999 Roundtop Rd Elizabethtown KY 42701",
    "addr:housenumber":"1999",
    "addr:postcode":"42701",
    "addr:street":"Roundtop Rd",
    "iso:country":"US",
    "sg:address":"1999 Roundtop Rd",
    "sg:city":"Elizabethtown",
    "sg:classifiers":[
        {
            "category":"Wholesale",
            "subcategory":"Auto Parts",
            "type":"Manufacturing & Wholesale Goods"
        }
    ],
    "sg:phone":"+1 270 234 1552",
    "sg:postcode":"42701",
    "sg:province":"KY",
    "sg:tags":[
        "automobile",
        "wrecking"
    ],
    "wof:name":"Groovy's 1135 Auto Recycle",
    "wof:placetype":"venue"
},
  "geometry": {"coordinates":[-85.820961,37.616237],"type":"Point"}
}