{
  "type": "Feature",
  "properties": {
    "iso:country":"US",
    "sg:address":"221 S Porter Dr",
    "sg:city":"Richmond",
    "sg:classifiers":[
        {
            "category":"Health Services",
            "subcategory":"Clinic",
            "type":"Services"
        }
    ],
    "sg:phone":"+1 859 623 6527",
    "sg:postcode":"40475",
    "sg:province":"KY",
    "sg:tags":[
        "home"
    ],
    "wof:name":"Comfort Keepers",
    "wof:placetype":"venue"
},
  "geometry": {"coordinates":[-84.316925,37.736073],"type":"Point"}
}