{
  "type": "Feature",
  "properties": {
    "addr:full":"2909 Richmond Rd Lexington KY 40509",
    "addr:housenumber":"2909",
    "addr:postcode":"40509",
    "addr:street":"Richmond Rd",
    "iso:country":"US",
    "sg:address":"2909 Richmond Rd",
    "sg:city":"Lexington",
    "sg:classifiers":[
        {
            "category":"Shopping",
            "subcategory":"Clothing, Apparel, & Fashions",
            "type":"Retail Goods"
        }
    ],
    "sg:phone":"+1 859 335 0015",
    "sg:postcode":"40509",
    "sg:province":"KY",
    "sg:tags":[
        "shop",
        "bridal"
    ],
    "wof:name":"Karen's Bridal Boutique",
    "wof:placetype":"venue"
},
  "geometry": {"coordinates":[-84.45458600000001,38.009173],"type":"Point"}
}