{
  "type": "Feature",
  "properties": {
    "iso:country":"US",
    "sg:address":"1028 Peaceful Way",
    "sg:city":"Shepherdsville",
    "sg:classifiers":[
        {
            "category":"Real Estate",
            "subcategory":"Developer",
            "type":"Services"
        },
        {
            "category":"Retail",
            "subcategory":"Animal Services",
            "type":"Services"
        }
    ],
    "sg:phone":"+1 502 897 9556",
    "sg:postcode":"40165",
    "sg:province":"KY",
    "sg:tags":[
        "pet",
        "funeral",
        "crematory",
        "cemetery",
        "s"
    ],
    "wof:name":"Pet Haven Cemetery Inc",
    "wof:placetype":"venue"
},
  "geometry": {"coordinates":[-85.670079,37.960302],"type":"Point"}
}