{
  "type": "Feature",
  "properties": {
    "iso:country":"US",
    "sg:address":"211 W Mount Vernon St",
    "sg:city":"Somerset",
    "sg:classifiers":[
        {
            "category":"Personal",
            "subcategory":"Beauty Salon",
            "type":"Services"
        }
    ],
    "sg:phone":"+1 606 451 0400",
    "sg:postcode":"42501",
    "sg:province":"KY",
    "wof:name":"Weir World Hair Design",
    "wof:placetype":"venue"
},
  "geometry": {"coordinates":[-84.605853,37.091733],"type":"Point"}
}