{
  "type": "Feature",
  "properties": {
    "addr:full":"2595 Faxon Rd Murray KY 42071",
    "addr:housenumber":"2595",
    "addr:postcode":"42071",
    "addr:street":"Faxon Rd",
    "iso:country":"US",
    "sg:address":"2595 Faxon Rd",
    "sg:city":"Murray",
    "sg:classifiers":[
        {
            "category":"Restaurant",
            "type":"Food & Drink"
        }
    ],
    "sg:phone":"+1 270 436 6122",
    "sg:postcode":"42071",
    "sg:province":"KY",
    "sg:tags":[
        "eating"
    ],
    "wof:name":"Campus Coffee Shop",
    "wof:placetype":"venue"
},
  "geometry": {"coordinates":[-88.166437,36.671341],"type":"Point"}
}