{
  "type": "Feature",
  "properties": {
    "addr:full":"1000 E Lexington Ave Danville KY 40422",
    "addr:housenumber":"1000",
    "addr:postcode":"40422",
    "addr:street":"E Lexington Ave",
    "iso:country":"US",
    "sg:address":"1000 E Lexington Ave",
    "sg:city":"Danville",
    "sg:classifiers":[
        {
            "category":"Health Services",
            "subcategory":"Doctor",
            "type":"Services"
        }
    ],
    "sg:phone":"+1 859 236 7756",
    "sg:postcode":"40422",
    "sg:province":"KY",
    "sg:tags":[
        "physician",
        "surgeon"
    ],
    "wof:name":"Yahya Allahham MD",
    "wof:placetype":"venue"
},
  "geometry": {"coordinates":[-84.75546799999999,37.653693],"type":"Point"}
}