{
  "type": "Feature",
  "properties": {
    "addr:full":"100 W Broadway Louisville KY 40202",
    "addr:housenumber":"100",
    "addr:postcode":"40202",
    "addr:street":"W Broadway",
    "iso:country":"US",
    "sg:address":"100 W Broadway",
    "sg:city":"Louisville",
    "sg:classifiers":[
        {
            "category":"Bakery",
            "type":"Food & Drink"
        },
        {
            "category":"Coffee & Tea",
            "type":"Food & Drink"
        },
        {
            "category":"Bagels",
            "type":"Food & Drink"
        },
        {
            "category":"Donuts",
            "type":"Food & Drink"
        }
    ],
    "sg:menulink":"http://www.allmenus.com/ky/louisville-central/133135-dunkin-donuts/menu/",
    "sg:phone":"+1 502 584 5355",
    "sg:postcode":"40202",
    "sg:province":"KY",
    "sg:tags":[
        "american",
        "pastry"
    ],
    "wof:name":"Dunkin' Donuts",
    "wof:placetype":"venue"
},
  "geometry": {"coordinates":[-85.753382,38.245715],"type":"Point"}
}