{
  "type": "Feature",
  "properties": {
    "iso:country":"US",
    "sg:address":"180 Dug Hill Rd",
    "sg:city":"Irvine",
    "sg:classifiers":[
        {
            "category":"Organizations",
            "subcategory":"Religious Organization",
            "type":"Services"
        }
    ],
    "sg:phone":"+1 606 723 2282",
    "sg:postcode":"40336",
    "sg:province":"KY",
    "sg:tags":[
        "church"
    ],
    "wof:name":"Jehovah's Witnesses",
    "wof:placetype":"venue"
},
  "geometry": {"coordinates":[-84.022583,37.673364],"type":"Point"}
}