{
  "type": "Feature",
  "properties": {
    "addr:full":"Cincinnati N KY International Airport Terminal 2 Hebron KY 41048",
    "addr:housenumber":"2",
    "addr:postcode":"41048",
    "addr:street":"N;International",
    "iso:country":"US",
    "sg:address":"Cincinnati N KY International Airport Terminal 2",
    "sg:city":"Hebron",
    "sg:classifiers":[
        {
            "category":"Bagels",
            "subcategory":"None",
            "type":"Food & Drink"
        }
    ],
    "sg:phone":"+1 859 767 5812",
    "sg:postcode":"41048",
    "sg:province":"KY",
    "sg:website":"www.brueggers.com",
    "wof:name":"Bruegger's",
    "wof:placetype":"venue"
},
  "geometry": {"coordinates":[-84.66862399999999,39.048183],"type":"Point"}
}