{
  "type": "Feature",
  "properties": {
    "iso:country":"US",
    "sg:address":"17 Comer Dr",
    "sg:city":"Madisonville",
    "sg:classifiers":[
        {
            "category":"Building & Trades",
            "subcategory":"Construction",
            "type":"Services"
        }
    ],
    "sg:phone":"+1 270 825 0510",
    "sg:postcode":"42431",
    "sg:province":"KY",
    "sg:tags":[
        "house"
    ],
    "wof:name":"Reuben Morris Construction",
    "wof:placetype":"venue"
},
  "geometry": {"coordinates":[-87.50026,37.355675],"type":"Point"}
}