{
  "type": "Feature",
  "properties": {
    "addr:full":"549 E 4th St Newport KY 41071",
    "addr:housenumber":"549",
    "addr:postcode":"41071",
    "addr:street":"E 4Th St",
    "iso:country":"US",
    "sg:address":"549 E 4th St",
    "sg:city":"Newport",
    "sg:classifiers":[
        {
            "category":"Professional",
            "subcategory":"Management & Consulting",
            "type":"Services"
        }
    ],
    "sg:phone":"+1 859 581 0601",
    "sg:postcode":"41071",
    "sg:province":"KY",
    "sg:tags":[
        "business"
    ],
    "wof:name":"Peter Lloyd Inc",
    "wof:placetype":"venue"
},
  "geometry": {"coordinates":[-84.489014,39.096492],"type":"Point"}
}