{
  "type": "Feature",
  "properties": {
    "addr:full":"380 Waitsboro Dr Somerset KY 42503",
    "addr:housenumber":"380",
    "addr:postcode":"42503",
    "addr:street":"Waitsboro Dr",
    "iso:country":"US",
    "sg:address":"380 Waitsboro Dr",
    "sg:city":"Somerset",
    "sg:classifiers":[
        {
            "category":"Building & Trades",
            "subcategory":"Construction",
            "type":"Services"
        }
    ],
    "sg:phone":"+1 606 679 2701",
    "sg:postcode":"42503",
    "sg:province":"KY",
    "sg:tags":[
        "contractor"
    ],
    "wof:name":"Rok Construction",
    "wof:placetype":"venue"
},
  "geometry": {"coordinates":[-84.63489300000001,37.017062],"type":"Point"}
}