{
  "type": "Feature",
  "properties": {
    "iso:country":"US",
    "sg:address":"641 Vonda View Blvd",
    "sg:city":"Franklin",
    "sg:classifiers":[
        {
            "category":"Health Services",
            "subcategory":"Chiropractor",
            "type":"Services"
        }
    ],
    "sg:phone":"+1 270 586 6568",
    "sg:postcode":"42134",
    "sg:province":"KY",
    "sg:tags":[
        "chiropractic"
    ],
    "wof:name":"Howard L Taylor Dc",
    "wof:placetype":"venue"
},
  "geometry": {"coordinates":[-86.564939,36.762637],"type":"Point"}
}