{
  "type": "Feature",
  "properties": {
    "iso:country":"US",
    "sg:address":"1522 Dixie Hwy",
    "sg:city":"Park Hills",
    "sg:classifiers":[
        {
            "category":"Organizations",
            "subcategory":"Religious Organization",
            "type":"Services"
        }
    ],
    "sg:phone":"+1 859 261 8888",
    "sg:postcode":"41011",
    "sg:province":"KY",
    "sg:tags":[
        "church"
    ],
    "sg:website":"www.newbeginningscc.org",
    "wof:name":"New Beginnings Community Chr",
    "wof:placetype":"venue"
},
  "geometry": {"coordinates":[-84.52981699999999,39.067192],"type":"Point"}
}