{
  "type": "Feature",
  "properties": {
    "iso:country":"US",
    "sg:address":"2840 Alexandria Pike",
    "sg:city":"Highland Heights",
    "sg:classifiers":[
        {
            "category":"Retail",
            "subcategory":"Portrait Studio",
            "type":"Services"
        },
        {
            "category":"Shopping",
            "subcategory":"Pharmacy",
            "type":"Retail Goods"
        }
    ],
    "sg:phone":"+1 859 781 0631",
    "sg:postcode":"41076",
    "sg:province":"KY",
    "sg:tags":[
        "photography",
        "drugstore",
        "store"
    ],
    "sg:website":"www.walgreens.com",
    "wof:name":"Walgreens",
    "wof:placetype":"venue"
},
  "geometry": {"coordinates":[-84.451685,39.031912],"type":"Point"}
}