{
  "type": "Feature",
  "properties": {
    "addr:full":"1136 US Hwy 27 Somerset KY 42503",
    "addr:housenumber":"1136",
    "addr:postcode":"42503",
    "addr:street":"Us Hwy 27",
    "iso:country":"US",
    "sg:address":"1136 US Hwy 27",
    "sg:city":"Somerset",
    "sg:classifiers":[
        {
            "category":"Insurance",
            "subcategory":"Insurance Agent",
            "type":"Services"
        }
    ],
    "sg:phone":"+1 606 679 6904",
    "sg:postcode":"42503",
    "sg:province":"KY",
    "wof:name":"Crawford Insurance",
    "wof:placetype":"venue"
},
  "geometry": {"coordinates":[-84.62771499999999,37.124707],"type":"Point"}
}