{
  "type": "Feature",
  "properties": {
    "addr:full":"2160 Phillips Dr Hazel KY 42049",
    "addr:housenumber":"2160",
    "addr:postcode":"42049",
    "addr:street":"Phillips Dr",
    "iso:country":"US",
    "sg:address":"2160 Phillips Dr",
    "sg:city":"Hazel",
    "sg:classifiers":[
        {
            "category":"Shopping",
            "subcategory":"Gifts & Souvenirs",
            "type":"Retail Goods"
        }
    ],
    "sg:phone":"+1 270 492 6115",
    "sg:postcode":"42049",
    "sg:province":"KY",
    "wof:name":"Creations",
    "wof:placetype":"venue"
},
  "geometry": {"coordinates":[-88.35843300000001,36.544981],"type":"Point"}
}