{
  "type": "Feature",
  "properties": {
    "iso:country":"US",
    "sg:address":"131 Lexington St",
    "sg:city":"Versailles",
    "sg:classifiers":[
        {
            "category":"Restaurant",
            "type":"Food & Drink"
        }
    ],
    "sg:phone":"+1 859 879 0277",
    "sg:postcode":"40383",
    "sg:province":"KY",
    "wof:name":"Wilson's Pool Room",
    "wof:placetype":"venue"
},
  "geometry": {"coordinates":[-84.72994,38.052922],"type":"Point"}
}