{
  "type": "Feature",
  "properties": {
    "iso:country":"US",
    "sg:address":"149 Village Ln",
    "sg:city":"Hazard",
    "sg:classifiers":[
        {
            "category":"Restaurant",
            "type":"Food & Drink"
        }
    ],
    "sg:menulink":"http://www.allmenus.com/ky/hazard/100754-captain-ds-seafood/menu/",
    "sg:phone":"+1 606 439 3510",
    "sg:postcode":"41701",
    "sg:province":"KY",
    "sg:tags":[
        "seafood",
        "american"
    ],
    "wof:name":"Captain D's Seafood",
    "wof:placetype":"venue"
},
  "geometry": {"coordinates":[-83.226247,37.282915],"type":"Point"}
}