{
  "type": "Feature",
  "properties": {
    "iso:country":"US",
    "sg:address":"405 Executive Park",
    "sg:city":"Louisville",
    "sg:classifiers":[
        {
            "category":"Real Estate",
            "subcategory":"Real Estate Agent",
            "type":"Services"
        }
    ],
    "sg:phone":"+1 502 896 2222",
    "sg:postcode":"40207",
    "sg:province":"KY",
    "sg:tags":[
        "appraiser"
    ],
    "sg:website":"www.brangersappraisal.com",
    "wof:name":"Brangers Co",
    "wof:placetype":"venue"
},
  "geometry": {"coordinates":[-85.622449,38.242711],"type":"Point"}
}