{
  "type": "Feature",
  "properties": {
    "addr:full":"11152 Ballardsville Rd Louisville KY 40241",
    "addr:housenumber":"11152",
    "addr:postcode":"40241",
    "addr:street":"Ballardsville Rd",
    "iso:country":"US",
    "sg:address":"11152 Ballardsville Rd",
    "sg:city":"Louisville",
    "sg:classifiers":[
        {
            "category":"Home & Garden",
            "subcategory":"Household Appliances",
            "type":"Retail Goods"
        },
        {
            "category":"Building & Trades",
            "subcategory":"Construction",
            "type":"Services"
        }
    ],
    "sg:phone":"+1 502 243 9040",
    "sg:postcode":"40241",
    "sg:province":"KY",
    "sg:tags":[
        "dishwashing",
        "specialty",
        "system",
        "machine",
        "heating",
        "contractor",
        "air conditioning"
    ],
    "wof:name":"D & M Service Company Incorporated Heating & Air Conditioning",
    "wof:placetype":"venue"
},
  "geometry": {"coordinates":[-85.543508,38.317392],"type":"Point"}
}