{
  "type": "Feature",
  "properties": {
    "iso:country":"US",
    "sg:address":"2493 Dixie Hwy",
    "sg:city":"Fort Mitchell",
    "sg:classifiers":[
        {
            "category":"Professional",
            "type":"Services"
        }
    ],
    "sg:phone":"+1 859 344 0878",
    "sg:postcode":"41017",
    "sg:province":"KY",
    "sg:tags":[
        "establishment"
    ],
    "wof:name":"Ferdinand J Kibler Plc",
    "wof:placetype":"venue"
},
  "geometry": {"coordinates":[-84.559816,39.037079],"type":"Point"}
}