{
  "type": "Feature",
  "properties": {
    "addr:full":"1171 Jackson Pike Harrodsburg KY 40330",
    "addr:housenumber":"1171",
    "addr:postcode":"40330",
    "addr:street":"Jackson Pike",
    "iso:country":"US",
    "sg:address":"1171 Jackson Pike",
    "sg:city":"Harrodsburg",
    "sg:classifiers":[
        {
            "category":"Farming",
            "subcategory":"Dairy Farm",
            "type":"Manufacturing & Wholesale Goods"
        }
    ],
    "sg:phone":"+1 859 734 5915",
    "sg:postcode":"40330",
    "sg:province":"KY",
    "wof:name":"Brent Hazelwood",
    "wof:placetype":"venue"
},
  "geometry": {"coordinates":[-84.890136,37.825841],"type":"Point"}
}