{
  "type": "Feature",
  "properties": {
    "addr:full":"5135 Dixie Hwy Louisville KY 40216",
    "addr:housenumber":"5135",
    "addr:postcode":"40216",
    "addr:street":"Dixie Hwy",
    "iso:country":"US",
    "sg:address":"5135 Dixie Hwy",
    "sg:city":"Louisville",
    "sg:classifiers":[
        {
            "category":"Health Services",
            "subcategory":"Doctor",
            "type":"Services"
        }
    ],
    "sg:phone":"+1 502 447 7315",
    "sg:postcode":"40216",
    "sg:province":"KY",
    "sg:tags":[
        "physician",
        "surgeon"
    ],
    "wof:name":"Frank R Burns MD",
    "wof:placetype":"venue"
},
  "geometry": {"coordinates":[-85.829364,38.16677],"type":"Point"}
}