{
  "type": "Feature",
  "properties": {
    "iso:country":"US",
    "sg:address":"5445 Hollyridge Ct",
    "sg:city":"Latonia",
    "sg:classifiers":[
        {
            "category":"Shopping",
            "subcategory":"Gifts & Souvenirs",
            "type":"Retail Goods"
        }
    ],
    "sg:phone":"+1 859 363 0702",
    "sg:postcode":"41015",
    "sg:province":"KY",
    "wof:name":"Rymarquis Woodworking",
    "wof:placetype":"venue"
},
  "geometry": {"coordinates":[-84.512192,38.990836],"type":"Point"}
}