{
  "type": "Feature",
  "properties": {
    "addr:full":"2975 State Hwy 44 E Shepherdsville KY 40165",
    "addr:housenumber":"2975",
    "addr:postcode":"40165",
    "addr:street":"State Hwy 44 E",
    "iso:country":"US",
    "sg:address":"2975 State Hwy 44 E",
    "sg:city":"Shepherdsville",
    "sg:classifiers":[
        {
            "category":"Organizations",
            "subcategory":"Religious Organization",
            "type":"Services"
        }
    ],
    "sg:phone":"+1 502 543 2483",
    "sg:postcode":"40165",
    "sg:province":"KY",
    "sg:tags":[
        "church"
    ],
    "sg:website":"www.bullittlickbaptist.org",
    "wof:name":"Bullitt Lick Baptist Church",
    "wof:placetype":"venue"
},
  "geometry": {"coordinates":[-85.669549,38.008009],"type":"Point"}
}