{
  "type": "Feature",
  "properties": {
    "addr:full":"3915 Elmwood Ave Louisville KY 40207",
    "addr:housenumber":"3915",
    "addr:postcode":"40207",
    "addr:street":"Elmwood Ave",
    "iso:country":"US",
    "sg:address":"3915 Elmwood Ave",
    "sg:city":"Louisville",
    "sg:classifiers":[
        {
            "category":"Banks & Credit Unions",
            "subcategory":"Financial Services",
            "type":"Services"
        }
    ],
    "sg:phone":"+1 502 899 1840",
    "sg:postcode":"40207",
    "sg:province":"KY",
    "sg:tags":[
        "trust",
        "investment",
        "real estate"
    ],
    "wof:name":"Cayman Investments LLC",
    "wof:placetype":"venue"
},
  "geometry": {"coordinates":[-85.656704,38.259942],"type":"Point"}
}