{
  "type": "Feature",
  "properties": {
    "iso:country":"US",
    "sg:address":"158 N 3rd St",
    "sg:city":"Danville",
    "sg:classifiers":[
        {
            "category":"Shopping",
            "subcategory":"Used Merchandise",
            "type":"Retail Goods"
        }
    ],
    "sg:phone":"+1 859 236 3026",
    "sg:postcode":"40422",
    "sg:province":"KY",
    "sg:tags":[
        "antique"
    ],
    "wof:name":"Antique Mall Historic Danville",
    "wof:placetype":"venue"
},
  "geometry": {"coordinates":[-84.77231,37.646434],"type":"Point"}
}