{
  "type": "Feature",
  "properties": {
    "addr:full":"1881 Dixie Hwy Fort Wright KY 41011",
    "addr:housenumber":"1881",
    "addr:postcode":"41011",
    "addr:street":"Dixie Hwy",
    "iso:country":"US",
    "sg:address":"1881 Dixie Hwy",
    "sg:city":"Fort Wright",
    "sg:classifiers":[
        {
            "category":"Professional",
            "subcategory":"Accounting & Tax Preparation",
            "type":"Services"
        }
    ],
    "sg:phone":"+1 859 331 7755",
    "sg:postcode":"41011",
    "sg:province":"KY",
    "sg:tags":[
        "accountant"
    ],
    "wof:name":"Advisory Team",
    "wof:placetype":"venue"
},
  "geometry": {"coordinates":[-84.54172699999999,39.058775],"type":"Point"}
}