{
  "type": "Feature",
  "properties": {
    "iso:country":"US",
    "sg:address":"4051 Nicholasville Rd",
    "sg:city":"Lexington",
    "sg:classifiers":[
        {
            "category":"Manufacturing",
            "subcategory":"Apparel",
            "type":"Manufacturing & Wholesale Goods"
        }
    ],
    "sg:phone":"+1 859 245 6452",
    "sg:postcode":"40503",
    "sg:province":"KY",
    "wof:name":"Hometown Threads",
    "wof:placetype":"venue"
},
  "geometry": {"coordinates":[-84.530036,37.976688],"type":"Point"}
}