{
  "type": "Feature",
  "properties": {
    "addr:full":"2963 State Hwy 83 Mayfield KY 42066",
    "addr:housenumber":"2963",
    "addr:postcode":"42066",
    "addr:street":"State Hwy 83",
    "iso:country":"US",
    "sg:address":"2963 State Hwy 83",
    "sg:city":"Mayfield",
    "sg:phone":"+1 270 382 2510",
    "sg:postcode":"42066",
    "sg:province":"KY",
    "sg:tags":[
        "farm",
        "tobacco"
    ],
    "wof:name":"Adams Fray Alan",
    "wof:placetype":"venue"
},
  "geometry": {"coordinates":[-88.595055,36.575182],"type":"Point"}
}