{
  "type": "Feature",
  "properties": {
    "addr:full":"11440 Watterson Ct Louisville KY 40299",
    "addr:housenumber":"11440",
    "addr:postcode":"40299",
    "addr:street":"Watterson Ct",
    "iso:country":"US",
    "sg:address":"11440 Watterson Ct",
    "sg:city":"Louisville",
    "sg:classifiers":[
        {
            "category":"Manufacturing",
            "subcategory":"Chemicals & Compounds",
            "type":"Manufacturing & Wholesale Goods"
        }
    ],
    "sg:phone":"+1 502 267 5700",
    "sg:postcode":"40299",
    "sg:province":"KY",
    "sg:tags":[
        "organic",
        "cyclic"
    ],
    "wof:name":"Vogt Supply Co",
    "wof:placetype":"venue"
},
  "geometry": {"coordinates":[-85.55627800000001,38.214651],"type":"Point"}
}