{
  "type": "Feature",
  "properties": {
    "iso:country":"US",
    "sg:address":"603 US Hwy 31 W Byp",
    "sg:city":"Bowling Green",
    "sg:classifiers":[
        {
            "category":"Retail",
            "subcategory":"Auto Repair",
            "type":"Services"
        }
    ],
    "sg:phone":"+1 270 842 6561",
    "sg:postcode":"42101",
    "sg:province":"KY",
    "sg:tags":[
        "muffler",
        "exhaust",
        "system"
    ],
    "sg:website":"www.midas.com",
    "wof:name":"Midas Muffler Shops",
    "wof:placetype":"venue"
},
  "geometry": {"coordinates":[-86.428346,36.990658],"type":"Point"}
}