{
  "type": "Feature",
  "properties": {
    "addr:full":"503 E 12th St Benton KY 42025",
    "addr:housenumber":"503",
    "addr:postcode":"42025",
    "addr:street":"E 12Th St",
    "iso:country":"US",
    "sg:address":"503 E 12th St",
    "sg:city":"Benton",
    "sg:classifiers":[
        {
            "category":"Restaurant",
            "type":"Food & Drink"
        }
    ],
    "sg:phone":"+1 270 527 4377",
    "sg:postcode":"42025",
    "sg:province":"KY",
    "wof:name":"Shade Tree",
    "wof:placetype":"venue"
},
  "geometry": {"coordinates":[-88.341522,36.857334],"type":"Point"}
}