{
  "type": "Feature",
  "properties": {
    "iso:country":"US",
    "sg:address":"402 N Main St",
    "sg:city":"Leitchfield",
    "sg:classifiers":[
        {
            "category":"Social Services",
            "subcategory":"Job Training",
            "type":"Services"
        }
    ],
    "sg:phone":"+1 270 259 4469",
    "sg:postcode":"42754",
    "sg:province":"KY",
    "sg:tags":[
        "retardation",
        "disabled",
        "mental",
        "dev"
    ],
    "wof:name":"Grayson County Industries",
    "wof:placetype":"venue"
},
  "geometry": {"coordinates":[-86.292951,37.486053],"type":"Point"}
}