{
  "type": "Feature",
  "properties": {
    "addr:full":"400 Atkinson Hill Ave Bardstown KY 40004",
    "addr:housenumber":"400",
    "addr:postcode":"40004",
    "addr:street":"Atkinson Hill Ave",
    "iso:country":"US",
    "sg:address":"400 Atkinson Hill Ave",
    "sg:city":"Bardstown",
    "sg:classifiers":[
        {
            "category":"Wholesale",
            "subcategory":"Hardware",
            "type":"Manufacturing & Wholesale Goods"
        }
    ],
    "sg:phone":"+1 502 348 0461",
    "sg:postcode":"40004",
    "sg:province":"KY",
    "sg:tags":[
        "equipment",
        "heating",
        "system"
    ],
    "wof:name":"S & R Supply Co",
    "wof:placetype":"venue"
},
  "geometry": {"coordinates":[-85.437349,37.826962],"type":"Point"}
}