{
  "type": "Feature",
  "properties": {
    "addr:full":"1413 Story Ave Louisville KY 40206",
    "addr:housenumber":"1413",
    "addr:postcode":"40206",
    "addr:street":"Story Ave",
    "iso:country":"US",
    "sg:address":"1413 Story Ave",
    "sg:city":"Louisville",
    "sg:classifiers":[
        {
            "category":"Shopping",
            "subcategory":"Discount & Variety Stores",
            "type":"Retail Goods"
        }
    ],
    "sg:phone":"+1 502 582 1736",
    "sg:postcode":"40206",
    "sg:province":"KY",
    "sg:tags":[
        "merchandise",
        "general"
    ],
    "wof:name":"Quartermaster Costume Rentals",
    "wof:placetype":"venue"
},
  "geometry": {"coordinates":[-85.72515199999999,38.257294],"type":"Point"}
}