{
  "type": "Feature",
  "properties": {
    "addr:full":"3923 River Park Dr Louisville KY 40211",
    "addr:housenumber":"3923",
    "addr:postcode":"40211",
    "addr:street":"River Park Dr",
    "iso:country":"US",
    "sg:address":"3923 River Park Dr",
    "sg:city":"Louisville",
    "sg:classifiers":[
        {
            "category":"Retail",
            "subcategory":"Laundry & Dry Cleaning",
            "type":"Services"
        }
    ],
    "sg:phone":"+1 502 775 9204",
    "sg:postcode":"40211",
    "sg:province":"KY",
    "sg:tags":[
        "cleaners"
    ],
    "wof:name":"Five Star Cleaners",
    "wof:placetype":"venue"
},
  "geometry": {"coordinates":[-85.816731,38.255552],"type":"Point"}
}