{
  "type": "Feature",
  "properties": {
    "addr:full":"23355 Louisville Nashville Tpke West Point KY 40177",
    "addr:housenumber":"23355",
    "addr:postcode":"40177",
    "addr:street":"Louisville Nashville Tpke",
    "iso:country":"US",
    "sg:address":"23355 Louisville Nashville Tpke",
    "sg:city":"West Point",
    "sg:classifiers":[
        {
            "category":"Home & Garden",
            "subcategory":"Furniture",
            "type":"Retail Goods"
        }
    ],
    "sg:phone":"+1 502 922 1600",
    "sg:postcode":"40177",
    "sg:province":"KY",
    "sg:tags":[
        "cabinet"
    ],
    "wof:name":"Midwest Cabinet Supplier Inc",
    "wof:placetype":"venue"
},
  "geometry": {"coordinates":[-85.961229,37.971255],"type":"Point"}
}