{
  "type": "Feature",
  "properties": {
    "addr:full":"508 Auburndale Ave Louisville KY 40214",
    "addr:housenumber":"508",
    "addr:postcode":"40214",
    "addr:street":"Auburndale Ave",
    "iso:country":"US",
    "sg:address":"508 Auburndale Ave",
    "sg:city":"Louisville",
    "sg:classifiers":[
        {
            "category":"Personal",
            "subcategory":"Nail Salon",
            "type":"Services"
        }
    ],
    "sg:phone":"+1 502 368 5612",
    "sg:postcode":"40214",
    "sg:province":"KY",
    "wof:name":"Yorktown Nails",
    "wof:placetype":"venue"
},
  "geometry": {"coordinates":[-85.773893,38.171457],"type":"Point"}
}