{
  "type": "Feature",
  "properties": {
    "addr:full":"4406 US Hwy 431 Belton KY 42324",
    "addr:housenumber":"4406",
    "addr:postcode":"42324",
    "addr:street":"Us Hwy 431",
    "iso:country":"US",
    "sg:address":"4406 US Hwy 431",
    "sg:city":"Belton",
    "sg:classifiers":[
        {
            "category":"Autos & Motor Vehicles",
            "subcategory":"Automobile Sales",
            "type":"Retail Goods"
        }
    ],
    "sg:phone":"+1 270 476 2308",
    "sg:postcode":"42324",
    "sg:province":"KY",
    "sg:tags":[
        "car",
        "dealer"
    ],
    "wof:name":"B & B Auto Sales",
    "wof:placetype":"venue"
},
  "geometry": {"coordinates":[-87.030778,37.157348],"type":"Point"}
}