{
  "type": "Feature",
  "properties": {
    "iso:country":"US",
    "sg:address":"7620 Dixie Hwy",
    "sg:city":"Florence",
    "sg:classifiers":[
        {
            "category":"Professional",
            "subcategory":"Lawyer & Legal Services",
            "type":"Services"
        }
    ],
    "sg:phone":"+1 859 371 3040",
    "sg:postcode":"41042",
    "sg:province":"KY",
    "sg:tags":[
        "attorney"
    ],
    "wof:name":"Gary Holland & Co Psc",
    "wof:placetype":"venue"
},
  "geometry": {"coordinates":[-84.62377499999999,38.991528],"type":"Point"}
}