{
  "type": "Feature",
  "properties": {
    "addr:full":"7170 Turfway Rd Florence KY 41042",
    "addr:postcode":"7170;41042",
    "addr:street":"Turfway Rd",
    "iso:country":"US",
    "sg:address":"7170 Turfway Rd",
    "sg:city":"Florence",
    "sg:classifiers":[
        {
            "category":"Banks & Credit Unions",
            "subcategory":"Bank",
            "type":"Services"
        }
    ],
    "sg:phone":"+1 859 525 2265",
    "sg:postcode":"41042",
    "sg:province":"KY",
    "wof:name":"Huntington National Bank",
    "wof:placetype":"venue"
},
  "geometry": {"coordinates":[-84.623242,39.008064],"type":"Point"}
}