{
  "type": "Feature",
  "properties": {
    "addr:full":"1632 E Cumberland Ave Middlesboro KY 40965",
    "addr:housenumber":"1632",
    "addr:postcode":"40965",
    "addr:street":"E Cumberland Ave",
    "iso:country":"US",
    "sg:address":"1632 E Cumberland Ave",
    "sg:city":"Middlesboro",
    "sg:classifiers":[
        {
            "category":"Health Services",
            "subcategory":"Doctor",
            "type":"Services"
        }
    ],
    "sg:phone":"+1 606 248 7550",
    "sg:postcode":"40965",
    "sg:province":"KY",
    "sg:tags":[
        "clinic"
    ],
    "wof:name":"Southeast Free Medical Clinic",
    "wof:placetype":"venue"
},
  "geometry": {"coordinates":[-83.709109,36.607547],"type":"Point"}
}