{
  "type": "Feature",
  "properties": {
    "iso:country":"US",
    "sg:address":"4326 Dixie Hwy S",
    "sg:city":"Elizabethtown",
    "sg:classifiers":[
        {
            "category":"Building & Trades",
            "subcategory":"Construction",
            "type":"Services"
        }
    ],
    "sg:phone":"+1 270 737 1688",
    "sg:postcode":"42701",
    "sg:province":"KY",
    "sg:tags":[
        "general",
        "contractor"
    ],
    "wof:name":"Stone Works Inc",
    "wof:placetype":"venue"
},
  "geometry": {"coordinates":[-85.893894,37.749025],"type":"Point"}
}