{
  "type": "Feature",
  "properties": {
    "iso:country":"US",
    "sg:address":"410 E 14th St",
    "sg:city":"Owensboro",
    "sg:classifiers":[
        {
            "category":"Wholesale",
            "subcategory":"Hardware",
            "type":"Manufacturing & Wholesale Goods"
        }
    ],
    "sg:phone":"+1 270 688 8117",
    "sg:postcode":"42303",
    "sg:province":"KY",
    "sg:tags":[
        "equipment",
        "heating",
        "system"
    ],
    "wof:name":"Benoist Brothers Supply Co",
    "wof:placetype":"venue"
},
  "geometry": {"coordinates":[-87.10559600000001,37.763191],"type":"Point"}
}