{
  "type": "Feature",
  "properties": {
    "addr:full":"421 Ogden St Somerset KY 42501",
    "addr:housenumber":"421",
    "addr:postcode":"42501",
    "addr:street":"Ogden St",
    "iso:country":"US",
    "sg:address":"421 Ogden St",
    "sg:city":"Somerset",
    "sg:classifiers":[
        {
            "category":"Social Services",
            "subcategory":"Child Care",
            "type":"Services"
        }
    ],
    "sg:phone":"+1 606 678 8669",
    "sg:postcode":"42501",
    "sg:province":"KY",
    "wof:name":"Tiny Tots Day Care Ctr",
    "wof:placetype":"venue"
},
  "geometry": {"coordinates":[-84.61265299999999,37.096372],"type":"Point"}
}