{
  "type": "Feature",
  "properties": {
    "iso:country":"US",
    "sg:address":"5287 Madison Pike",
    "sg:city":"Independence",
    "sg:classifiers":[
        {
            "category":"Personal",
            "subcategory":"Beauty Salon",
            "type":"Services"
        }
    ],
    "sg:phone":"+1 859 356 8410",
    "sg:postcode":"41051",
    "sg:province":"KY",
    "wof:name":"Carol's Hairstyling",
    "wof:placetype":"venue"
},
  "geometry": {"coordinates":[-84.544511,38.942121],"type":"Point"}
}