{
  "type": "Feature",
  "properties": {
    "addr:full":"6913 Enterprise Dr Louisville KY 40214",
    "addr:housenumber":"6913",
    "addr:postcode":"40214",
    "addr:street":"Enterprise Dr",
    "iso:country":"US",
    "sg:address":"6913 Enterprise Dr",
    "sg:city":"Louisville",
    "sg:classifiers":[
        {
            "category":"Building & Trades",
            "subcategory":"Plumbing",
            "type":"Services"
        }
    ],
    "sg:phone":"+1 502 375 3500",
    "sg:postcode":"40214",
    "sg:province":"KY",
    "sg:tags":[
        "mechanical",
        "contractor"
    ],
    "sg:website":"www.hmcservice.com",
    "wof:name":"Hussung Mechanical Contractors",
    "wof:placetype":"venue"
},
  "geometry": {"coordinates":[-85.752014,38.153409],"type":"Point"}
}