{
  "type": "Feature",
  "properties": {
    "iso:country":"US",
    "sg:address":"10417 Taylorsville Rd",
    "sg:city":"Louisville",
    "sg:classifiers":[
        {
            "category":"Retail",
            "subcategory":"Auto Repair",
            "type":"Services"
        }
    ],
    "sg:phone":"+1 502 297 8100",
    "sg:postcode":"40299",
    "sg:province":"KY",
    "sg:tags":[
        "repairing",
        "automobile"
    ],
    "wof:name":"Singletary Automotive Svc",
    "wof:placetype":"venue"
},
  "geometry": {"coordinates":[-85.56385899999999,38.192619],"type":"Point"}
}