{
  "type": "Feature",
  "properties": {
    "iso:country":"US",
    "sg:address":"1150 Brooks Industrial Rd",
    "sg:city":"Shelbyville",
    "sg:classifiers":[
        {
            "category":"Home & Garden",
            "subcategory":"Building Materials",
            "type":"Retail Goods"
        }
    ],
    "sg:phone":"+1 502 633 1756",
    "sg:postcode":"40065",
    "sg:province":"KY",
    "sg:tags":[
        "mixed",
        "concrete"
    ],
    "wof:name":"Rodgers Concrete Co Inc",
    "wof:placetype":"venue"
},
  "geometry": {"coordinates":[-85.261016,38.209199],"type":"Point"}
}