{
  "type": "Feature",
  "properties": {
    "addr:full":"65 Compton Dr Pikeville KY 41501",
    "addr:housenumber":"65",
    "addr:postcode":"41501",
    "addr:street":"Compton Dr",
    "iso:country":"US",
    "sg:address":"65 Compton Dr",
    "sg:city":"Pikeville",
    "sg:classifiers":[
        {
            "category":"Retail",
            "subcategory":"Repair Shop",
            "type":"Services"
        }
    ],
    "sg:phone":"+1 606 639 0017",
    "sg:postcode":"41501",
    "sg:province":"KY",
    "sg:tags":[
        "machine"
    ],
    "wof:name":"Coal Ridge Machine",
    "wof:placetype":"venue"
},
  "geometry": {"coordinates":[-82.534459,37.391243],"type":"Point"}
}