{
  "type": "Feature",
  "properties": {
    "addr:full":"2908 Winchester Ave Ashland KY 41101",
    "addr:housenumber":"2908",
    "addr:postcode":"41101",
    "addr:street":"Winchester Ave",
    "iso:country":"US",
    "sg:address":"2908 Winchester Ave",
    "sg:city":"Ashland",
    "sg:classifiers":[
        {
            "category":"Health Services",
            "subcategory":"Doctor",
            "type":"Services"
        }
    ],
    "sg:phone":"+1 606 920 9988",
    "sg:postcode":"41101",
    "sg:province":"KY",
    "sg:tags":[
        "medical",
        "imaging"
    ],
    "wof:name":"Advanced Medical Imaging PC",
    "wof:placetype":"venue"
},
  "geometry": {"coordinates":[-82.62259,38.469289],"type":"Point"}
}