{
  "type": "Feature",
  "properties": {
    "addr:full":"117 Brighton Park Blvd Frankfort KY 40601",
    "addr:housenumber":"117",
    "addr:postcode":"40601",
    "addr:street":"Brighton Park Blvd",
    "iso:country":"US",
    "sg:address":"117 Brighton Park Blvd",
    "sg:city":"Frankfort",
    "sg:classifiers":[
        {
            "category":"Shopping",
            "subcategory":"Clothing, Apparel, & Fashions",
            "type":"Retail Goods"
        }
    ],
    "sg:phone":"+1 502 695 0373",
    "sg:postcode":"40601",
    "sg:province":"KY",
    "sg:tags":[
        "alteration"
    ],
    "wof:name":"Sew What Corp",
    "wof:placetype":"venue"
},
  "geometry": {"coordinates":[-84.82802599999999,38.196187],"type":"Point"}
}