{
  "type": "Feature",
  "properties": {
    "iso:country":"US",
    "sg:address":"2433 Scottsville Rd",
    "sg:city":"Glasgow",
    "sg:classifiers":[
        {
            "category":"Restaurant",
            "type":"Food & Drink"
        }
    ],
    "sg:phone":"+1 270 651 8008",
    "sg:postcode":"42141",
    "sg:province":"KY",
    "wof:name":"Bolton's Landing",
    "wof:placetype":"venue"
},
  "geometry": {"coordinates":[-85.93989500000001,36.972625],"type":"Point"}
}