{
  "type": "Feature",
  "properties": {
    "iso:country":"US",
    "sg:address":"630 Lexington St",
    "sg:city":"Maysville",
    "sg:classifiers":[
        {
            "category":"Manufacturing",
            "subcategory":"Petroleum Products",
            "type":"Manufacturing & Wholesale Goods"
        }
    ],
    "sg:phone":"+1 606 564 5452",
    "sg:postcode":"41056",
    "sg:province":"KY",
    "sg:tags":[
        "oil"
    ],
    "wof:name":"M C Russell Co Inc",
    "wof:placetype":"venue"
},
  "geometry": {"coordinates":[-83.753596,38.638672],"type":"Point"}
}