{
  "type": "Feature",
  "properties": {
    "addr:full":"193 Versailles Rd Frankfort KY 40601",
    "addr:housenumber":"193",
    "addr:postcode":"40601",
    "addr:street":"Versailles Rd",
    "iso:country":"US",
    "sg:address":"193 Versailles Rd",
    "sg:city":"Frankfort",
    "sg:classifiers":[
        {
            "category":"Shopping",
            "subcategory":"Stationery & Office Supplies",
            "type":"Retail Goods"
        }
    ],
    "sg:phone":"+1 502 695 3477",
    "sg:postcode":"40601",
    "sg:province":"KY",
    "sg:tags":[
        "album",
        "scrapbook"
    ],
    "wof:name":"Memories A LA Mode",
    "wof:placetype":"venue"
},
  "geometry": {"coordinates":[-84.833586,38.202699],"type":"Point"}
}