{
  "type": "Feature",
  "properties": {
    "iso:country":"US",
    "sg:address":"9208 Blue Lick Rd",
    "sg:city":"Okolona",
    "sg:classifiers":[
        {
            "category":"Shopping",
            "subcategory":"Bicycles & Sporting Goods",
            "type":"Retail Goods"
        }
    ],
    "sg:phone":"+1 502 968 5094",
    "sg:postcode":"40229",
    "sg:province":"KY",
    "sg:tags":[
        "bait",
        "fishing"
    ],
    "wof:name":"Catfish Jeff's Bait & Tackle",
    "wof:placetype":"venue"
},
  "geometry": {"coordinates":[-85.689578,38.113468],"type":"Point"}
}