{
  "type": "Feature",
  "properties": {
    "iso:country":"US",
    "sg:address":"4004 Glenarm Rd",
    "sg:city":"Crestwood",
    "sg:classifiers":[
        {
            "category":"Home & Garden",
            "subcategory":"Garden Supply",
            "type":"Retail Goods"
        }
    ],
    "sg:phone":"+1 502 241 1332",
    "sg:postcode":"40014",
    "sg:province":"KY",
    "wof:name":"Jules Klein Nursery",
    "wof:placetype":"venue"
},
  "geometry": {"coordinates":[-85.49320299999999,38.363831],"type":"Point"}
}