{
  "type": "Feature",
  "properties": {
    "iso:country":"US",
    "sg:address":"4036 Frederica St",
    "sg:city":"Owensboro",
    "sg:classifiers":[
        {
            "category":"Shopping",
            "type":"Retail Goods"
        }
    ],
    "sg:phone":"+1 270 684 5248",
    "sg:postcode":"42301",
    "sg:province":"KY",
    "sg:tags":[
        "pet",
        "shop"
    ],
    "wof:name":"E & L Pets",
    "wof:placetype":"venue"
},
  "geometry": {"coordinates":[-87.12188999999999,37.730815],"type":"Point"}
}