{
  "type": "Feature",
  "properties": {
    "iso:country":"US",
    "sg:address":"2225 Lexington Rd",
    "sg:city":"Louisville",
    "sg:classifiers":[
        {
            "category":"Professional",
            "subcategory":"Lawyer & Legal Services",
            "type":"Services"
        }
    ],
    "sg:phone":"+1 502 992 3590",
    "sg:postcode":"40206",
    "sg:province":"KY",
    "sg:tags":[
        "attorney"
    ],
    "wof:name":"David Deep Law Office",
    "wof:placetype":"venue"
},
  "geometry": {"coordinates":[-85.70735000000001,38.246652],"type":"Point"}
}