{
  "type": "Feature",
  "properties": {
    "addr:full":"275 Klutey Park Dr Henderson KY 42420",
    "addr:housenumber":"275",
    "addr:postcode":"42420",
    "addr:street":"Klutey Park Dr",
    "iso:country":"US",
    "sg:address":"275 Klutey Park Dr",
    "sg:city":"Henderson",
    "sg:classifiers":[
        {
            "category":"Manufacturing",
            "subcategory":"Apparel",
            "type":"Manufacturing & Wholesale Goods"
        }
    ],
    "sg:phone":"+1 270 826 5474",
    "sg:postcode":"42420",
    "sg:province":"KY",
    "sg:tags":[
        "clothing"
    ],
    "wof:name":"Student Union Apparel Inc",
    "wof:placetype":"venue"
},
  "geometry": {"coordinates":[-87.571091,37.832821],"type":"Point"}
}