{
  "type": "Feature",
  "properties": {
    "addr:full":"4725 Camelback Rd Paducah KY 42003",
    "addr:housenumber":"4725",
    "addr:postcode":"42003",
    "addr:street":"Camelback Rd",
    "iso:country":"US",
    "sg:address":"4725 Camelback Rd",
    "sg:city":"Paducah",
    "sg:classifiers":[
        {
            "category":"Manufacturing",
            "subcategory":"Building Materials",
            "type":"Manufacturing & Wholesale Goods"
        }
    ],
    "sg:phone":"+1 270 898 8779",
    "sg:postcode":"42003",
    "sg:province":"KY",
    "sg:tags":[
        "mfg"
    ],
    "wof:name":"Allen Abram III",
    "wof:placetype":"venue"
},
  "geometry": {"coordinates":[-88.531834,37.032623],"type":"Point"}
}