{
  "type": "Feature",
  "properties": {
    "addr:full":"5320 Valley Station Rd # 100 Louisville KY 40272",
    "addr:housenumber":"5320",
    "addr:postcode":"40272",
    "addr:street":"Valley Station Rd # 100",
    "iso:country":"US",
    "sg:address":"5320 Valley Station Rd # 100",
    "sg:city":"Louisville",
    "sg:classifiers":[
        {
            "category":"Professional",
            "subcategory":"Business Services",
            "type":"Services"
        },
        {
            "category":"Government",
            "subcategory":"Post Office",
            "type":"Public Place"
        }
    ],
    "sg:phone":"+1 502 935 4231",
    "sg:postcode":"40272",
    "sg:province":"KY",
    "sg:tags":[
        "delivery",
        "messenger",
        "courier"
    ],
    "wof:name":"Regional Express Courier",
    "wof:placetype":"venue"
},
  "geometry": {"coordinates":[-85.86264,38.10622],"type":"Point"}
}