{
  "type": "Feature",
  "properties": {
    "iso:country":"US",
    "sg:address":"1400 Lincoln Ave",
    "sg:city":"Louisville",
    "sg:classifiers":[
        {
            "category":"Manufacturing",
            "subcategory":"Wood Products",
            "type":"Manufacturing & Wholesale Goods"
        },
        {
            "category":"Manufacturing",
            "subcategory":"Building Materials",
            "type":"Manufacturing & Wholesale Goods"
        }
    ],
    "sg:phone":"+1 502 459 8710",
    "sg:postcode":"40213",
    "sg:province":"KY",
    "sg:tags":[
        "accessory",
        "frames",
        "doors",
        "millwork-wholesale",
        "millwork",
        "manufacturer"
    ],
    "wof:name":"Louisville Lumber & Millwork Company",
    "wof:placetype":"venue"
},
  "geometry": {"coordinates":[-85.714737,38.193039],"type":"Point"}
}