{
  "type": "Feature",
  "properties": {
    "iso:country":"US",
    "sg:address":"921 Belmere Dr",
    "sg:city":"Lexington",
    "sg:classifiers":[
        {
            "category":"Organizations",
            "subcategory":"Religious Organization",
            "type":"Services"
        }
    ],
    "sg:phone":"+1 859 263 0049",
    "sg:postcode":"40509",
    "sg:province":"KY",
    "sg:tags":[
        "clergy"
    ],
    "wof:name":"G M Smith",
    "wof:placetype":"venue"
},
  "geometry": {"coordinates":[-84.430588,38.022042],"type":"Point"}
}