{
  "type": "Feature",
  "properties": {
    "iso:country":"US",
    "sg:address":"1045 Krebs Station Rd",
    "sg:city":"Paducah",
    "sg:classifiers":[
        {
            "category":"Autos & Motor Vehicles",
            "subcategory":"Auto Supplies",
            "type":"Retail Goods"
        }
    ],
    "sg:phone":"+1 270 554 4479",
    "sg:postcode":"42003",
    "sg:province":"KY",
    "sg:tags":[
        "alternator",
        "generator"
    ],
    "wof:name":"Wurth Auto Electric Rebuilder",
    "wof:placetype":"venue"
},
  "geometry": {"coordinates":[-88.656128,36.99458],"type":"Point"}
}