{
  "type": "Feature",
  "properties": {
    "iso:country":"US",
    "sg:address":"1205 S Green St",
    "sg:city":"Henderson",
    "sg:classifiers":[
        {
            "category":"Banks & Credit Unions",
            "subcategory":"Bank",
            "type":"Services"
        }
    ],
    "sg:phone":"+1 270 869 9939",
    "sg:postcode":"42420",
    "sg:province":"KY",
    "sg:tags":[
        "cashing",
        "check"
    ],
    "wof:name":"Pay Day USA",
    "wof:placetype":"venue"
},
  "geometry": {"coordinates":[-87.60193599999999,37.824944],"type":"Point"}
}