{
  "type": "Feature",
  "properties": {
    "iso:country":"US",
    "sg:address":"925 Bypass Rd",
    "sg:city":"Winchester",
    "sg:classifiers":[
        {
            "category":"Shopping",
            "subcategory":"Musical Instruments",
            "type":"Retail Goods"
        }
    ],
    "sg:phone":"+1 859 737 5267",
    "sg:postcode":"40391",
    "sg:province":"KY",
    "wof:name":"Jams Music Exchange",
    "wof:placetype":"venue"
},
  "geometry": {"coordinates":[-84.21362000000001,38.000551],"type":"Point"}
}