{
  "type": "Feature",
  "properties": {
    "iso:country":"US",
    "sg:address":"1505 Grange Dr",
    "sg:city":"La Grange",
    "sg:classifiers":[
        {
            "category":"Building & Trades",
            "subcategory":"Construction",
            "type":"Services"
        }
    ],
    "sg:phone":"+1 502 592 2241",
    "sg:postcode":"40031",
    "sg:province":"KY",
    "sg:tags":[
        "house"
    ],
    "wof:name":"Victorian Homebuilders Im",
    "wof:placetype":"venue"
},
  "geometry": {"coordinates":[-85.366961,38.400552],"type":"Point"}
}