{
  "type": "Feature",
  "properties": {
    "addr:full":"1533 Shiloh Rd Campbellsville KY 42718",
    "addr:housenumber":"1533",
    "addr:postcode":"42718",
    "addr:street":"Shiloh Rd",
    "iso:country":"US",
    "sg:address":"1533 Shiloh Rd",
    "sg:city":"Campbellsville",
    "sg:classifiers":[
        {
            "category":"Real Estate",
            "subcategory":"Real Estate Agent",
            "type":"Services"
        }
    ],
    "sg:phone":"+1 270 789 0438",
    "sg:postcode":"42718",
    "sg:province":"KY",
    "wof:name":"United Country Caldwell Realty",
    "wof:placetype":"venue"
},
  "geometry": {"coordinates":[-85.41998100000001,37.321765],"type":"Point"}
}