{
  "type": "Feature",
  "properties": {
    "addr:full":"1450 Bardstown Rd Louisville KY 40204",
    "addr:housenumber":"1450",
    "addr:postcode":"40204",
    "addr:street":"Bardstown Rd",
    "iso:country":"US",
    "sg:address":"1450 Bardstown Rd",
    "sg:city":"Louisville",
    "sg:classifiers":[
        {
            "category":"Retail",
            "subcategory":"Auto Repair",
            "type":"Services"
        }
    ],
    "sg:phone":"+1 502 458 3315",
    "sg:postcode":"40204",
    "sg:province":"KY",
    "sg:tags":[
        "automobile",
        "lubrication"
    ],
    "wof:name":"Valvoline Instant Oil Change",
    "wof:placetype":"venue"
},
  "geometry": {"coordinates":[-85.70971400000001,38.23216],"type":"Point"}
}