{
  "type": "Feature",
  "properties": {
    "iso:country":"US",
    "sg:address":"3668 Deckard School Rd",
    "sg:city":"Radcliff",
    "sg:classifiers":[
        {
            "category":"Professional",
            "subcategory":"Accounting & Tax Preparation",
            "type":"Services"
        }
    ],
    "sg:phone":"+1 270 877 2938",
    "sg:postcode":"40160",
    "sg:province":"KY",
    "sg:tags":[
        "return",
        "filing"
    ],
    "wof:name":"Johnsons Bookkeeping & Tax Svc",
    "wof:placetype":"venue"
},
  "geometry": {"coordinates":[-85.947714,37.792665],"type":"Point"}
}