{
  "type": "Feature",
  "properties": {
    "addr:full":"1804 Farnsley Rd Louisville KY 40216",
    "addr:housenumber":"1804",
    "addr:postcode":"40216",
    "addr:street":"Farnsley Rd",
    "iso:country":"US",
    "sg:address":"1804 Farnsley Rd",
    "sg:city":"Louisville",
    "sg:classifiers":[
        {
            "category":"Social Services",
            "type":"Services"
        }
    ],
    "sg:phone":"+1 502 449 0005",
    "sg:postcode":"40216",
    "sg:province":"KY",
    "wof:name":"Circle Care Family Services",
    "wof:placetype":"venue"
},
  "geometry": {"coordinates":[-85.81300299999999,38.201722],"type":"Point"}
}