{
  "type": "Feature",
  "properties": {
    "addr:full":"426 Madison Ave Covington KY 41011",
    "addr:housenumber":"426",
    "addr:postcode":"41011",
    "addr:street":"Madison Ave",
    "iso:country":"US",
    "sg:address":"426 Madison Ave",
    "sg:city":"Covington",
    "sg:classifiers":[
        {
            "category":"Banks & Credit Unions",
            "subcategory":"Bank",
            "type":"Services"
        }
    ],
    "sg:phone":"+1 859 431 6228",
    "sg:postcode":"41011",
    "sg:province":"KY",
    "sg:tags":[
        "loan",
        "real estate"
    ],
    "wof:name":"MBB Mortge LLC",
    "wof:placetype":"venue"
},
  "geometry": {"coordinates":[-84.51065199999999,39.085882],"type":"Point"}
}