{
  "type": "Feature",
  "properties": {
    "addr:full":"1940 Midland Trl Shelbyville KY 40065",
    "addr:housenumber":"1940",
    "addr:postcode":"40065",
    "addr:street":"Midland Trl",
    "iso:country":"US",
    "sg:address":"1940 Midland Trl",
    "sg:city":"Shelbyville",
    "sg:classifiers":[
        {
            "category":"Organizations",
            "subcategory":"Religious Organization",
            "type":"Services"
        }
    ],
    "sg:phone":"+1 502 633 5922",
    "sg:postcode":"40065",
    "sg:province":"KY",
    "sg:tags":[
        "church"
    ],
    "wof:name":"Clay Street Baptist Church",
    "wof:placetype":"venue"
},
  "geometry": {"coordinates":[-85.25963400000001,38.213645],"type":"Point"}
}