{
  "type": "Feature",
  "properties": {
    "iso:country":"US",
    "sg:address":"34 High School Ct",
    "sg:city":"Walton",
    "sg:classifiers":[
        {
            "category":"Real Estate",
            "subcategory":"Real Estate Agent",
            "type":"Services"
        }
    ],
    "sg:phone":"+1 859 356 1914",
    "sg:postcode":"41094",
    "sg:province":"KY",
    "sg:tags":[
        "inspection"
    ],
    "wof:name":"Northern Kentucky Inspctn Inc",
    "wof:placetype":"venue"
},
  "geometry": {"coordinates":[-84.614051,38.867443],"type":"Point"}
}