{
  "type": "Feature",
  "properties": {
    "iso:country":"US",
    "sg:address":"1495 Corinth Rd",
    "sg:city":"Lawrenceburg",
    "sg:classifiers":[
        {
            "category":"Retail",
            "subcategory":"Auto Repair",
            "type":"Services"
        }
    ],
    "sg:phone":"+1 502 839 6789",
    "sg:postcode":"40342",
    "sg:province":"KY",
    "sg:tags":[
        "repairing",
        "automobile",
        "radiator"
    ],
    "wof:name":"Young's Radiator Shop",
    "wof:placetype":"venue"
},
  "geometry": {"coordinates":[-84.98553699999999,38.054973],"type":"Point"}
}