{
  "type": "Feature",
  "properties": {
    "iso:country":"US",
    "sg:address":"2443 Alexandria Pike",
    "sg:city":"Highland Heights",
    "sg:classifiers":[
        {
            "category":"Sports & Exercise",
            "subcategory":"Bowling",
            "type":"Entertainment"
        }
    ],
    "sg:phone":"+1 859 781 2111",
    "sg:postcode":"41076",
    "sg:province":"KY",
    "wof:name":"Laru Bowling Lanes",
    "wof:placetype":"venue"
},
  "geometry": {"coordinates":[-84.45059999999999,39.0387],"type":"Point"}
}