{
  "type": "Feature",
  "properties": {
    "iso:country":"US",
    "sg:address":"10213 Eve Adam Dr",
    "sg:city":"Louisville",
    "sg:classifiers":[
        {
            "category":"Real Estate",
            "subcategory":"Real Estate Agent",
            "type":"Services"
        }
    ],
    "sg:phone":"+1 502 935 7260",
    "sg:postcode":"40272",
    "sg:province":"KY",
    "wof:name":"Sarah A Bailey",
    "wof:placetype":"venue"
},
  "geometry": {"coordinates":[-85.843469,38.103546],"type":"Point"}
}