{
  "type": "Feature",
  "properties": {
    "addr:full":"3966 Flaherty Rd Vine Grove KY 40175",
    "addr:housenumber":"3966",
    "addr:postcode":"40175",
    "addr:street":"Flaherty Rd",
    "iso:country":"US",
    "sg:address":"3966 Flaherty Rd",
    "sg:city":"Vine Grove",
    "sg:classifiers":[
        {
            "category":"Social Services",
            "subcategory":"Child Care",
            "type":"Services"
        }
    ],
    "sg:phone":"+1 270 828 8383",
    "sg:postcode":"40175",
    "sg:province":"KY",
    "wof:name":"Wee Care Day Care Ctr",
    "wof:placetype":"venue"
},
  "geometry": {"coordinates":[-86.051543,37.830359],"type":"Point"}
}