{
  "type": "Feature",
  "properties": {
    "iso:country":"US",
    "sg:address":"3425 Taylor Blvd",
    "sg:city":"Louisville",
    "sg:classifiers":[
        {
            "category":"Bars & Pubs",
            "type":"Food & Drink"
        }
    ],
    "sg:phone":"+1 502 363 4236",
    "sg:postcode":"40215",
    "sg:province":"KY",
    "wof:name":"Win Place & Show Bar",
    "wof:placetype":"venue"
},
  "geometry": {"coordinates":[-85.782596,38.199665],"type":"Point"}
}