{
  "type": "Feature",
  "properties": {
    "iso:country":"US",
    "sg:address":"115 Hamilton Rd",
    "sg:city":"Morehead",
    "sg:classifiers":[
        {
            "category":"Wholesale",
            "subcategory":"Construction Materials",
            "type":"Manufacturing & Wholesale Goods"
        }
    ],
    "sg:phone":"+1 606 784 6699",
    "sg:postcode":"40351",
    "sg:province":"KY",
    "sg:tags":[
        "concrete",
        "product"
    ],
    "wof:name":"Quality Concrete Products",
    "wof:placetype":"venue"
},
  "geometry": {"coordinates":[-83.363254,38.236762],"type":"Point"}
}