{
  "type": "Feature",
  "properties": {
    "iso:country":"US",
    "sg:address":"106 Springfield Rd",
    "sg:city":"Bloomfield",
    "sg:classifiers":[
        {
            "category":"Organizations",
            "subcategory":"Religious Organization",
            "type":"Services"
        }
    ],
    "sg:phone":"+1 502 252 8435",
    "sg:postcode":"40008",
    "sg:province":"KY",
    "sg:tags":[
        "church"
    ],
    "sg:website":"www.bloomfieldbaptist.org",
    "wof:name":"Bloomfield Baptist Church",
    "wof:placetype":"venue"
},
  "geometry": {"coordinates":[-85.31768099999999,37.911825],"type":"Point"}
}