{
  "type": "Feature",
  "properties": {
    "iso:country":"US",
    "sg:address":"1120 E New Circle Rd",
    "sg:city":"Lexington",
    "sg:classifiers":[
        {
            "category":"Freight",
            "type":"Transportation"
        }
    ],
    "sg:phone":"+1 859 254 4455",
    "sg:postcode":"40505",
    "sg:province":"KY",
    "sg:tags":[
        "commercial",
        "storage"
    ],
    "wof:name":"Space Center Storage",
    "wof:placetype":"venue"
},
  "geometry": {"coordinates":[-84.452799,38.030913],"type":"Point"}
}