{
  "type": "Feature",
  "properties": {
    "addr:full":"215 E 8th St Newport KY 41071",
    "addr:housenumber":"215",
    "addr:postcode":"41071",
    "addr:street":"E 8Th St",
    "iso:country":"US",
    "sg:address":"215 E 8th St",
    "sg:city":"Newport",
    "sg:classifiers":[
        {
            "category":"Professional",
            "subcategory":"Lawyer & Legal Services",
            "type":"Services"
        }
    ],
    "sg:phone":"+1 859 578 8544",
    "sg:postcode":"41071",
    "sg:province":"KY",
    "sg:tags":[
        "attorney"
    ],
    "wof:name":"Joseph K Wehby Law Offices",
    "wof:placetype":"venue"
},
  "geometry": {"coordinates":[-84.490031,39.090221],"type":"Point"}
}