{
  "type": "Feature",
  "properties": {
    "iso:country":"US",
    "sg:address":"2709 State Hwy 11",
    "sg:city":"Sharpsburg",
    "sg:classifiers":[
        {
            "category":"Autos & Motor Vehicles",
            "subcategory":"Automobile Sales",
            "type":"Retail Goods"
        }
    ],
    "sg:phone":"+1 606 247 5024",
    "sg:postcode":"40374",
    "sg:province":"KY",
    "sg:tags":[
        "used"
    ],
    "wof:name":"Gw Auto Sales",
    "wof:placetype":"venue"
},
  "geometry": {"coordinates":[-83.892802,38.236043],"type":"Point"}
}