{
  "type": "Feature",
  "properties": {
    "iso:country":"US",
    "sg:address":"105 S Maysville Rd",
    "sg:city":"Mount Sterling",
    "sg:classifiers":[
        {
            "category":"Organizations",
            "subcategory":"Religious Organization",
            "type":"Services"
        }
    ],
    "sg:phone":"+1 859 497 9498",
    "sg:postcode":"40353",
    "sg:province":"KY",
    "wof:name":"Cathedral of Praise Church",
    "wof:placetype":"venue"
},
  "geometry": {"coordinates":[-83.941552,38.055195],"type":"Point"}
}