{
  "type": "Feature",
  "properties": {
    "addr:full":"408 S 1st St La Grange KY 40031",
    "addr:housenumber":"408",
    "addr:postcode":"40031",
    "addr:street":"S 1St St",
    "iso:country":"US",
    "sg:address":"408 S 1st St",
    "sg:city":"La Grange",
    "sg:classifiers":[
        {
            "category":"Shopping",
            "subcategory":"Pharmacy",
            "type":"Retail Goods"
        }
    ],
    "sg:phone":"+1 502 222 0322",
    "sg:postcode":"40031",
    "sg:province":"KY",
    "wof:name":"Rite Aid Pharmacy",
    "wof:placetype":"venue"
},
  "geometry": {"coordinates":[-85.377126,38.403229],"type":"Point"}
}