{
  "type": "Feature",
  "properties": {
    "iso:country":"US",
    "sg:address":"109 W Hickman St",
    "sg:city":"Winchester",
    "sg:classifiers":[
        {
            "category":"Freight",
            "type":"Transportation"
        }
    ],
    "sg:phone":"+1 859 737 4423",
    "sg:postcode":"40391",
    "sg:province":"KY",
    "sg:tags":[
        "mover"
    ],
    "wof:name":"Monsieus Moving",
    "wof:placetype":"venue"
},
  "geometry": {"coordinates":[-84.180103,37.991116],"type":"Point"}
}