{
  "type": "Feature",
  "properties": {
    "addr:full":"2331 W Broadway Louisville KY 40211",
    "addr:housenumber":"2331",
    "addr:postcode":"40211",
    "addr:street":"W Broadway",
    "iso:country":"US",
    "sg:address":"2331 W Broadway",
    "sg:city":"Louisville",
    "sg:classifiers":[
        {
            "category":"Organizations",
            "subcategory":"Political Organization",
            "type":"Services"
        }
    ],
    "sg:phone":"+1 502 618 4063",
    "sg:postcode":"40211",
    "sg:province":"KY",
    "wof:name":"Fischer For Mayor",
    "wof:placetype":"venue"
},
  "geometry": {"coordinates":[-85.79038,38.249309],"type":"Point"}
}