{
  "type": "Feature",
  "properties": {
    "iso:country":"US",
    "sg:address":"250 N Main St",
    "sg:city":"Russellville",
    "sg:classifiers":[
        {
            "category":"Banks & Credit Unions",
            "subcategory":"Bank",
            "type":"Services"
        }
    ],
    "sg:phone":"+1 270 725 8698",
    "sg:postcode":"42276",
    "sg:province":"KY",
    "sg:tags":[
        "cashing",
        "check"
    ],
    "wof:name":"Cash Express LLC",
    "wof:placetype":"venue"
},
  "geometry": {"coordinates":[-86.888341,36.847494],"type":"Point"}
}