{
  "type": "Feature",
  "properties": {
    "iso:country":"US",
    "sg:address":"462 W 4th St",
    "sg:city":"Russellville",
    "sg:classifiers":[
        {
            "category":"Insurance",
            "subcategory":"Insurance Agent",
            "type":"Services"
        }
    ],
    "sg:phone":"+1 270 726 8182",
    "sg:postcode":"42276",
    "sg:province":"KY",
    "wof:name":"Primerica Financial Svc",
    "wof:placetype":"venue"
},
  "geometry": {"coordinates":[-86.89202,36.844206],"type":"Point"}
}