{
  "type": "Feature",
  "properties": {
    "addr:full":"1234 Paris Pike Georgetown KY 40324",
    "addr:housenumber":"1234",
    "addr:postcode":"40324",
    "addr:street":"Paris Pike",
    "iso:country":"US",
    "sg:address":"1234 Paris Pike",
    "sg:city":"Georgetown",
    "sg:classifiers":[
        {
            "category":"Banks & Credit Unions",
            "subcategory":"Bank",
            "type":"Services"
        }
    ],
    "sg:phone":"+1 502 863 2600",
    "sg:postcode":"40324",
    "sg:province":"KY",
    "sg:tags":[
        "cashing",
        "check"
    ],
    "wof:name":"Check 'n Go",
    "wof:placetype":"venue"
},
  "geometry": {"coordinates":[-84.54491,38.213195],"type":"Point"}
}