{
  "type": "Feature",
  "properties": {
    "iso:country":"US",
    "sg:address":"6 Locust Ln",
    "sg:city":"Florence",
    "sg:classifiers":[
        {
            "category":"Professional",
            "subcategory":"Advertising",
            "type":"Services"
        }
    ],
    "sg:phone":"+1 859 371 4897",
    "sg:postcode":"41042",
    "sg:province":"KY",
    "sg:tags":[
        "counselor"
    ],
    "wof:name":"Greetings Of Northern Kentucky",
    "wof:placetype":"venue"
},
  "geometry": {"coordinates":[-84.62354999999999,38.994469],"type":"Point"}
}