{
  "type": "Feature",
  "properties": {
    "iso:country":"US",
    "sg:address":"7521 US Hwy 641 N",
    "sg:city":"Gilbertsville",
    "sg:classifiers":[
        {
            "category":"Autos & Motor Vehicles",
            "subcategory":"Fuel & Gas Station",
            "type":"Retail Goods"
        }
    ],
    "sg:phone":"+1 270 362 8449",
    "sg:postcode":"42044",
    "sg:province":"KY",
    "sg:tags":[
        "oil"
    ],
    "wof:name":"Kentucky Lake Citgo",
    "wof:placetype":"venue"
},
  "geometry": {"coordinates":[-88.29604999999999,36.971782],"type":"Point"}
}