{
  "type": "Feature",
  "properties": {
    "iso:country":"US",
    "sg:address":"2325 Barnes Mill Rd",
    "sg:city":"Richmond",
    "sg:classifiers":[
        {
            "category":"Farming",
            "subcategory":"Nursery",
            "type":"Manufacturing & Wholesale Goods"
        }
    ],
    "sg:phone":"+1 859 328 7005",
    "sg:postcode":"40475",
    "sg:province":"KY",
    "sg:tags":[
        "greenhouse"
    ],
    "wof:name":"Warren Farm Greenhouse",
    "wof:placetype":"venue"
},
  "geometry": {"coordinates":[-84.41771,37.709056],"type":"Point"}
}