{
  "type": "Feature",
  "properties": {
    "iso:country":"US",
    "sg:address":"413 Knob View Dr",
    "sg:city":"Shelbyville",
    "sg:classifiers":[
        {
            "category":"Building & Trades",
            "subcategory":"Electrical",
            "type":"Services"
        }
    ],
    "sg:phone":"+1 502 647 9960",
    "sg:postcode":"40065",
    "sg:province":"KY",
    "sg:tags":[
        "electric",
        "contractor"
    ],
    "wof:name":"A Lite Electric",
    "wof:placetype":"venue"
},
  "geometry": {"coordinates":[-85.204866,38.177103],"type":"Point"}
}