{
  "type": "Feature",
  "properties": {
    "iso:country":"US",
    "sg:address":"708 N 12th St",
    "sg:city":"Murray",
    "sg:classifiers":[
        {
            "category":"Banks & Credit Unions",
            "subcategory":"Bank",
            "type":"Services"
        }
    ],
    "sg:phone":"+1 270 753 1284",
    "sg:postcode":"42071",
    "sg:province":"KY",
    "sg:tags":[
        "cashing",
        "check"
    ],
    "wof:name":"Check Into Cash",
    "wof:placetype":"venue"
},
  "geometry": {"coordinates":[-88.31488400000001,36.621351],"type":"Point"}
}