{
  "type": "Feature",
  "properties": {
    "iso:country":"US",
    "sg:address":"14362 Aulick Rd",
    "sg:city":"Butler",
    "sg:classifiers":[
        {
            "category":"Building & Trades",
            "subcategory":"Cleaning & Sanitation",
            "type":"Services"
        }
    ],
    "sg:phone":"+1 859 448 0778",
    "sg:postcode":"41006",
    "sg:province":"KY",
    "sg:tags":[
        "fireplace",
        "chimney"
    ],
    "wof:name":"Freezes Chimney Sweep Svc",
    "wof:placetype":"venue"
},
  "geometry": {"coordinates":[-84.404481,38.824592],"type":"Point"}
}