{
  "type": "Feature",
  "properties": {
    "addr:full":"2856 Lone Oak Rd Paducah KY 42003",
    "addr:housenumber":"2856",
    "addr:postcode":"42003",
    "addr:street":"Lone Oak Rd",
    "iso:country":"US",
    "sg:address":"2856 Lone Oak Rd",
    "sg:city":"Paducah",
    "sg:classifiers":[
        {
            "category":"Education",
            "subcategory":"Special Training",
            "type":"Public Place"
        }
    ],
    "sg:phone":"+1 270 554 4111",
    "sg:postcode":"42003",
    "sg:province":"KY",
    "sg:tags":[
        "tutoring"
    ],
    "wof:name":"Sylvan Learning Ctr",
    "wof:placetype":"venue"
},
  "geometry": {"coordinates":[-88.661142,37.039394],"type":"Point"}
}