{
  "type": "Feature",
  "properties": {
    "iso:country":"US",
    "sg:address":"5101 Commerce Crossings Dr",
    "sg:city":"Louisville",
    "sg:classifiers":[
        {
            "category":"Communications",
            "subcategory":"Television Station",
            "type":"Services"
        }
    ],
    "sg:phone":"+1 502 291 6009",
    "sg:postcode":"40229",
    "sg:province":"KY",
    "sg:tags":[
        "network"
    ],
    "wof:name":"On Site Solutions Inc",
    "wof:placetype":"venue"
},
  "geometry": {"coordinates":[-85.676203,38.103484],"type":"Point"}
}