{
  "type": "Feature",
  "properties": {
    "iso:country":"US",
    "sg:address":"100 1st St",
    "sg:city":"Elizabethtown",
    "sg:classifiers":[
        {
            "category":"Real Estate",
            "subcategory":"Real Estate Agent",
            "type":"Services"
        }
    ],
    "sg:phone":"+1 270 982 9299",
    "sg:postcode":"42701",
    "sg:province":"KY",
    "wof:name":"Miller & Zaring",
    "wof:placetype":"venue"
},
  "geometry": {"coordinates":[-85.89722999999999,37.763754],"type":"Point"}
}