{
  "type": "Feature",
  "properties": {
    "iso:country":"US",
    "sg:address":"1575 Ogburn Chapel Rd",
    "sg:city":"Clarksville",
    "sg:classifiers":[
        {
            "category":"Building & Trades",
            "subcategory":"Construction",
            "type":"Services"
        }
    ],
    "sg:phone":"+1 931 645 9228",
    "sg:postcode":"37042",
    "sg:province":"KY",
    "sg:tags":[
        "paint",
        "paper",
        "contractor"
    ],
    "wof:name":"Bassett Painting",
    "wof:placetype":"venue"
},
  "geometry": {"coordinates":[-87.458681,36.509967],"type":"Point"}
}