{
  "type": "Feature",
  "properties": {
    "addr:full":"1645 Elder Ct Fort Wright KY 41011",
    "addr:housenumber":"1645",
    "addr:postcode":"41011",
    "addr:street":"Elder Ct",
    "iso:country":"US",
    "sg:address":"1645 Elder Ct",
    "sg:city":"Fort Wright",
    "sg:classifiers":[
        {
            "category":"Real Estate",
            "subcategory":"Real Estate Agent",
            "type":"Services"
        }
    ],
    "sg:phone":"+1 859 331 8744",
    "sg:postcode":"41011",
    "sg:province":"KY",
    "sg:tags":[
        "appraiser"
    ],
    "wof:name":"R Bryan Meade Inc",
    "wof:placetype":"venue"
},
  "geometry": {"coordinates":[-84.545081,39.06453],"type":"Point"}
}