{
  "type": "Feature",
  "properties": {
    "addr:full":"132 Ryan Rd Cadiz KY 42211",
    "addr:housenumber":"132",
    "addr:postcode":"42211",
    "addr:street":"Ryan Rd",
    "iso:country":"US",
    "sg:address":"132 Ryan Rd",
    "sg:city":"Cadiz",
    "sg:classifiers":[
        {
            "category":"Home & Garden",
            "subcategory":"Building Materials",
            "type":"Retail Goods"
        }
    ],
    "sg:phone":"+1 606 876 2213",
    "sg:postcode":"42211",
    "sg:province":"KY",
    "sg:tags":[
        "lumber"
    ],
    "wof:name":"Muses Mills Lumber",
    "wof:placetype":"venue"
},
  "geometry": {"coordinates":[-87.832559,36.901301],"type":"Point"}
}