{
  "type": "Feature",
  "properties": {
    "addr:full":"204 Franklin St Warsaw KY 41095",
    "addr:housenumber":"204",
    "addr:postcode":"41095",
    "addr:street":"Franklin St",
    "iso:country":"US",
    "sg:address":"204 Franklin St",
    "sg:city":"Warsaw",
    "sg:classifiers":[
        {
            "category":"Government",
            "subcategory":"Office",
            "type":"Public Place"
        }
    ],
    "sg:phone":"+1 859 567 2844",
    "sg:postcode":"41095",
    "sg:province":"KY",
    "sg:tags":[
        "county",
        "program",
        "health"
    ],
    "wof:name":"Gallatin County Health Dept",
    "wof:placetype":"venue"
},
  "geometry": {"coordinates":[-84.902444,38.783673],"type":"Point"}
}