{
  "type": "Feature",
  "properties": {
    "iso:country":"US",
    "sg:address":"1141 Red Mile Rd",
    "sg:city":"Lexington",
    "sg:classifiers":[
        {
            "category":"Social Services",
            "subcategory":"Child Care",
            "type":"Services"
        }
    ],
    "sg:phone":"+1 859 255 0501",
    "sg:postcode":"40504",
    "sg:province":"KY",
    "wof:name":"Step By Step Childcare Ctr",
    "wof:placetype":"venue"
},
  "geometry": {"coordinates":[-84.523139,38.040271],"type":"Point"}
}