{
  "type": "Feature",
  "properties": {
    "addr:full":"7509 Preston Hwy Louisville KY 40219",
    "addr:housenumber":"7509",
    "addr:postcode":"40219",
    "addr:street":"Preston Hwy",
    "iso:country":"US",
    "sg:address":"7509 Preston Hwy",
    "sg:city":"Louisville",
    "sg:classifiers":[
        {
            "category":"Restaurant",
            "type":"Food & Drink"
        }
    ],
    "sg:menulink":"http://www.allmenus.com/ky/jefferson-central/79670-pizza-hut/menu/",
    "sg:phone":"+1 502 964 5986",
    "sg:postcode":"40219",
    "sg:province":"KY",
    "sg:tags":[
        "american",
        "pizza"
    ],
    "wof:name":"Pizza Hut",
    "wof:placetype":"venue"
},
  "geometry": {"coordinates":[-85.689046,38.142818],"type":"Point"}
}