{
  "type": "Feature",
  "properties": {
    "addr:full":"201 Morgan Mill Rd Georgetown KY 40324",
    "addr:housenumber":"201",
    "addr:postcode":"40324",
    "addr:street":"Morgan Mill Rd",
    "iso:country":"US",
    "sg:address":"201 Morgan Mill Rd",
    "sg:city":"Georgetown",
    "sg:classifiers":[
        {
            "category":"Retail",
            "subcategory":"Portrait Studio",
            "type":"Services"
        }
    ],
    "sg:phone":"+1 502 863 0366",
    "sg:postcode":"40324",
    "sg:province":"KY",
    "sg:tags":[
        "photographer"
    ],
    "wof:name":"Timeless Creations Family",
    "wof:placetype":"venue"
},
  "geometry": {"coordinates":[-84.543166,38.221225],"type":"Point"}
}