{
  "type": "Feature",
  "properties": {
    "addr:full":"526 Philadelphia St Covington KY 41011",
    "addr:housenumber":"526",
    "addr:postcode":"41011",
    "addr:street":"Philadelphia St",
    "iso:country":"US",
    "sg:address":"526 Philadelphia St",
    "sg:city":"Covington",
    "sg:classifiers":[
        {
            "category":"Shopping",
            "subcategory":"Hobbies, Toys, & Games",
            "type":"Retail Goods"
        }
    ],
    "sg:phone":"+1 859 491 1313",
    "sg:postcode":"41011",
    "sg:province":"KY",
    "wof:name":"The Magic Shop",
    "wof:placetype":"venue"
},
  "geometry": {"coordinates":[-84.519943,39.084963],"type":"Point"}
}