{
  "type": "Feature",
  "properties": {
    "iso:country":"US",
    "sg:address":"8005 Vinecrest Ave",
    "sg:city":"Louisville",
    "sg:classifiers":[
        {
            "category":"Building & Trades",
            "subcategory":"Construction",
            "type":"Services"
        }
    ],
    "sg:phone":"+1 502 425 3802",
    "sg:postcode":"40222",
    "sg:province":"KY",
    "sg:tags":[
        "general",
        "contractor"
    ],
    "wof:name":"ABN Restoration Inc",
    "wof:placetype":"venue"
},
  "geometry": {"coordinates":[-85.60655,38.261487],"type":"Point"}
}