{
  "type": "Feature",
  "properties": {
    "iso:country":"US",
    "sg:address":"308 N Ashland Ave",
    "sg:city":"Lexington",
    "sg:classifiers":[
        {
            "category":"Personal",
            "type":"Services"
        },
        {
            "category":"Shopping",
            "subcategory":"Florist",
            "type":"Retail Goods"
        }
    ],
    "sg:phone":"+1 859 252 6833",
    "sg:postcode":"40502",
    "sg:province":"KY",
    "sg:tags":[
        "party",
        "planning"
    ],
    "wof:name":"Crist N Creona Designs",
    "wof:placetype":"venue"
},
  "geometry": {"coordinates":[-84.479141,38.038803],"type":"Point"}
}