{
  "type": "Feature",
  "properties": {
    "iso:country":"US",
    "sg:address":"102 Courchelle Dr",
    "sg:city":"Nicholasville",
    "sg:classifiers":[
        {
            "category":"Wholesale",
            "subcategory":"Machinery & Supplies",
            "type":"Manufacturing & Wholesale Goods"
        }
    ],
    "sg:phone":"+1 859 887 8836",
    "sg:postcode":"40356",
    "sg:province":"KY",
    "sg:tags":[
        "truck"
    ],
    "wof:name":"All-Lift Equipment Co",
    "wof:placetype":"venue"
},
  "geometry": {"coordinates":[-84.59654999999999,37.884469],"type":"Point"}
}