{
  "type": "Feature",
  "properties": {
    "iso:country":"US",
    "sg:address":"829 S Floyd St",
    "sg:city":"Louisville",
    "sg:classifiers":[
        {
            "category":"Manufacturing",
            "subcategory":"Paper Products",
            "type":"Manufacturing & Wholesale Goods"
        }
    ],
    "sg:phone":"+1 502 584 8287",
    "sg:postcode":"40203",
    "sg:province":"KY",
    "sg:tags":[
        "envelope",
        "envelopes-manufacturers"
    ],
    "wof:name":"Louisville Envelope Inc",
    "wof:placetype":"venue"
},
  "geometry": {"coordinates":[-85.750332,38.241495],"type":"Point"}
}