{
  "type": "Feature",
  "properties": {
    "iso:country":"US",
    "sg:address":"1625 W Market St",
    "sg:city":"Louisville",
    "sg:classifiers":[
        {
            "category":"Professional",
            "subcategory":"Employment Agencies",
            "type":"Services"
        }
    ],
    "sg:phone":"+1 502 561 9346",
    "sg:postcode":"40203",
    "sg:province":"KY",
    "sg:tags":[
        "help",
        "contractor"
    ],
    "wof:name":"Labor Express",
    "wof:placetype":"venue"
},
  "geometry": {"coordinates":[-85.777871,38.257632],"type":"Point"}
}