{
  "type": "Feature",
  "properties": {
    "addr:full":"18 Clark Dr Hindman KY 41826",
    "addr:housenumber":"18",
    "addr:postcode":"41826",
    "addr:street":"Clark Dr",
    "iso:country":"US",
    "sg:address":"18 Clark Dr",
    "sg:city":"Hindman",
    "sg:classifiers":[
        {
            "category":"Personal",
            "subcategory":"Barber",
            "type":"Services"
        }
    ],
    "sg:phone":"+1 606 785 3033",
    "sg:postcode":"41826",
    "sg:province":"KY",
    "wof:name":"Clyde's Barber & Hair Styling",
    "wof:placetype":"venue"
},
  "geometry": {"coordinates":[-82.943022,37.153554],"type":"Point"}
}