{
  "type": "Feature",
  "properties": {
    "addr:full":"375 Sunview Dr Shepherdsville KY 40165",
    "addr:housenumber":"375",
    "addr:postcode":"40165",
    "addr:street":"Sunview Dr",
    "iso:country":"US",
    "sg:address":"375 Sunview Dr",
    "sg:city":"Shepherdsville",
    "sg:classifiers":[
        {
            "category":"Organizations",
            "subcategory":"Community Association",
            "type":"Services"
        }
    ],
    "sg:phone":"+1 502 543 4333",
    "sg:postcode":"40165",
    "sg:province":"KY",
    "sg:tags":[
        "fraternal"
    ],
    "wof:name":"Bullitt County Shrine Club",
    "wof:placetype":"venue"
},
  "geometry": {"coordinates":[-85.647531,38.012957],"type":"Point"}
}