{
  "type": "Feature",
  "properties": {
    "iso:country":"US",
    "sg:address":"2100 Watterson Trl",
    "sg:city":"Jeffersontown",
    "sg:classifiers":[
        {
            "category":"Home & Garden",
            "subcategory":"Furniture",
            "type":"Retail Goods"
        }
    ],
    "sg:phone":"+1 502 499 1517",
    "sg:postcode":"40299",
    "sg:province":"KY",
    "sg:tags":[
        "mattress"
    ],
    "sg:website":"www.havertys.com",
    "wof:name":"Havertys Furniture",
    "wof:placetype":"venue"
},
  "geometry": {"coordinates":[-85.55901,38.208696],"type":"Point"}
}