{
  "type": "Feature",
  "properties": {
    "iso:country":"US",
    "sg:address":"412 Green St",
    "sg:city":"Williamsburg",
    "sg:classifiers":[
        {
            "category":"Building & Trades",
            "subcategory":"Construction",
            "type":"Services"
        }
    ],
    "sg:phone":"+1 606 549 4806",
    "sg:postcode":"40769",
    "sg:province":"KY",
    "sg:tags":[
        "contractor"
    ],
    "wof:name":"Kenneth M Baird Jr",
    "wof:placetype":"venue"
},
  "geometry": {"coordinates":[-84.157315,36.737566],"type":"Point"}
}