{
  "type": "Feature",
  "properties": {
    "iso:country":"US",
    "sg:address":"360 Spring St",
    "sg:city":"London",
    "sg:classifiers":[
        {
            "category":"Professional",
            "subcategory":"Engineering",
            "type":"Services"
        }
    ],
    "sg:phone":"+1 606 878 1735",
    "sg:postcode":"40741",
    "sg:province":"KY",
    "sg:tags":[
        "engineer"
    ],
    "wof:name":"Capital Consulting Inc",
    "wof:placetype":"venue"
},
  "geometry": {"coordinates":[-84.074789,37.128406],"type":"Point"}
}