{
  "type": "Feature",
  "properties": {
    "iso:country":"US",
    "sg:address":"288 Griffis Ln",
    "sg:city":"Brooks",
    "sg:classifiers":[
        {
            "category":"Building & Trades",
            "subcategory":"Construction",
            "type":"Services"
        }
    ],
    "sg:phone":"+1 502 955 6240",
    "sg:postcode":"40109",
    "sg:province":"KY",
    "sg:tags":[
        "masonry",
        "contractor"
    ],
    "wof:name":"Rennirt Masonry",
    "wof:placetype":"venue"
},
  "geometry": {"coordinates":[-85.721924,38.059179],"type":"Point"}
}