{
  "type": "Feature",
  "properties": {
    "addr:full":"851 Liberty Rd West Liberty KY 41472",
    "addr:housenumber":"851",
    "addr:postcode":"41472",
    "addr:street":"Liberty Rd",
    "iso:country":"US",
    "sg:address":"851 Liberty Rd",
    "sg:city":"West Liberty",
    "sg:classifiers":[
        {
            "category":"Professional",
            "type":"Services"
        }
    ],
    "sg:phone":"+1 606 743 4099",
    "sg:postcode":"41472",
    "sg:province":"KY",
    "sg:tags":[
        "establishment"
    ],
    "wof:name":"AMERI.COM",
    "wof:placetype":"venue"
},
  "geometry": {"coordinates":[-83.275335,37.924435],"type":"Point"}
}