{
  "type": "Feature",
  "properties": {
    "iso:country":"US",
    "sg:address":"9440 Brownsboro Rd",
    "sg:city":"Louisville",
    "sg:classifiers":[
        {
            "category":"Food & Beverages",
            "subcategory":"Groceries & Convenience Stores",
            "type":"Retail Goods"
        }
    ],
    "sg:phone":"+1 502 425 8542",
    "sg:postcode":"40241",
    "sg:province":"KY",
    "sg:tags":[
        "grocer"
    ],
    "wof:name":"Kroger",
    "wof:placetype":"venue"
},
  "geometry": {"coordinates":[-85.57428299999999,38.307735],"type":"Point"}
}