{
  "type": "Feature",
  "properties": {
    "iso:country":"US",
    "sg:address":"432 Mill Rd",
    "sg:city":"Magnolia",
    "sg:classifiers":[
        {
            "category":"Health Services",
            "subcategory":"Nursing And Care Facility",
            "type":"Services"
        }
    ],
    "sg:phone":"+1 270 324 3241",
    "sg:postcode":"42757",
    "sg:province":"KY",
    "wof:name":"HMH Family Care Ctr",
    "wof:placetype":"venue"
},
  "geometry": {"coordinates":[-85.742485,37.448605],"type":"Point"}
}