{
  "type": "Feature",
  "properties": {
    "iso:country":"US",
    "sg:address":"524 Whitney Rd",
    "sg:city":"Columbia",
    "sg:classifiers":[
        {
            "category":"Manufacturing",
            "subcategory":"Lumber",
            "type":"Manufacturing & Wholesale Goods"
        }
    ],
    "sg:phone":"+1 270 789 3495",
    "sg:postcode":"42728",
    "sg:province":"KY",
    "sg:tags":[
        "sawmill"
    ],
    "wof:name":"Whitney Lumber",
    "wof:placetype":"venue"
},
  "geometry": {"coordinates":[-85.329061,37.12283],"type":"Point"}
}