{
  "type": "Feature",
  "properties": {
    "iso:country":"US",
    "sg:address":"902 Gardenia Dr",
    "sg:city":"Campbellsville",
    "sg:classifiers":[
        {
            "category":"Organizations",
            "subcategory":"Religious Organization",
            "type":"Services"
        }
    ],
    "sg:phone":"+1 270 465 4808",
    "sg:postcode":"42718",
    "sg:province":"KY",
    "wof:name":"Mt Gilboa Baptist Church",
    "wof:placetype":"venue"
},
  "geometry": {"coordinates":[-85.349677,37.35451],"type":"Point"}
}