{
  "type": "Feature",
  "properties": {
    "iso:country":"US",
    "sg:address":"3311 Preston Hwy",
    "sg:city":"Louisville",
    "sg:phone":"+1 502 375 8766",
    "sg:postcode":"40213",
    "sg:province":"KY",
    "wof:name":"Oasis Sushi Bar",
    "wof:placetype":"venue"
},
  "geometry": {"coordinates":[-85.733431,38.200523],"type":"Point"}
}