{
  "type": "Feature",
  "properties": {
    "iso:country":"US",
    "sg:address":"771 Chloe Rd",
    "sg:city":"Pikeville",
    "sg:classifiers":[
        {
            "category":"Professional",
            "subcategory":"Engineering",
            "type":"Services"
        }
    ],
    "sg:phone":"+1 606 437 7517",
    "sg:postcode":"41501",
    "sg:province":"KY",
    "sg:tags":[
        "engineer"
    ],
    "wof:name":"Johnson Engineering Inc",
    "wof:placetype":"venue"
},
  "geometry": {"coordinates":[-82.48867300000001,37.475994],"type":"Point"}
}