{
  "type": "Feature",
  "properties": {
    "iso:country":"US",
    "sg:address":"1134 Main St",
    "sg:city":"Shelbyville",
    "sg:classifiers":[
        {
            "category":"Real Estate",
            "subcategory":"Real Estate Agent",
            "type":"Services"
        }
    ],
    "sg:phone":"+1 502 633 9209",
    "sg:postcode":"40065",
    "sg:province":"KY",
    "wof:name":"Shelby Realty Company",
    "wof:placetype":"venue"
},
  "geometry": {"coordinates":[-85.22699299999999,38.211644],"type":"Point"}
}