{
  "type": "Feature",
  "properties": {
    "iso:country":"US",
    "sg:address":"3135 Custer Dr",
    "sg:city":"Lexington",
    "sg:classifiers":[
        {
            "category":"Health Services",
            "subcategory":"Doctor",
            "type":"Services"
        }
    ],
    "sg:phone":"+1 859 272 0991",
    "sg:postcode":"40517",
    "sg:province":"KY",
    "sg:tags":[
        "physician",
        "surgeon"
    ],
    "wof:name":"Stephen Cox MD",
    "wof:placetype":"venue"
},
  "geometry": {"coordinates":[-84.45926300000001,37.988857],"type":"Point"}
}