{
  "type": "Feature",
  "properties": {
    "iso:country":"US",
    "sg:address":"3718 Dixie Hwy E",
    "sg:city":"Elizabethtown",
    "sg:classifiers":[
        {
            "category":"Organizations",
            "subcategory":"Religious Organization",
            "type":"Services"
        }
    ],
    "sg:phone":"+1 270 769 5399",
    "sg:postcode":"42701",
    "sg:province":"KY",
    "sg:tags":[
        "church"
    ],
    "wof:name":"Heartland Freewill Baptist Chr",
    "wof:placetype":"venue"
},
  "geometry": {"coordinates":[-85.85283800000001,37.642222],"type":"Point"}
}