{
  "type": "Feature",
  "properties": {
    "iso:country":"US",
    "sg:address":"303 E Main St",
    "sg:city":"Bradfordsville",
    "sg:classifiers":[
        {
            "category":"Autos & Motor Vehicles",
            "subcategory":"Automobile Sales",
            "type":"Retail Goods"
        }
    ],
    "sg:phone":"+1 270 337 3404",
    "sg:postcode":"40009",
    "sg:province":"KY",
    "sg:tags":[
        "car",
        "dealer"
    ],
    "wof:name":"Wrights Used Cars",
    "wof:placetype":"venue"
},
  "geometry": {"coordinates":[-85.14546799999999,37.49602],"type":"Point"}
}