{
  "type": "Feature",
  "properties": {
    "iso:country":"US",
    "sg:address":"1710 Anton Rd",
    "sg:city":"Madisonville",
    "sg:classifiers":[
        {
            "category":"Education",
            "subcategory":"School",
            "type":"Public Place"
        }
    ],
    "sg:phone":"+1 270 825 6033",
    "sg:postcode":"42431",
    "sg:province":"KY",
    "wof:name":"Jesse Stuart Elementary School",
    "wof:placetype":"venue"
},
  "geometry": {"coordinates":[-87.468644,37.327385],"type":"Point"}
}