{
  "type": "Feature",
  "properties": {
    "iso:country":"US",
    "sg:address":"260 N Hurstbourne Pkwy",
    "sg:city":"Louisville",
    "sg:classifiers":[
        {
            "category":"Shopping",
            "subcategory":"Bicycles & Sporting Goods",
            "type":"Retail Goods"
        }
    ],
    "sg:phone":"+1 502 425 6666",
    "sg:postcode":"40223",
    "sg:province":"KY",
    "sg:tags":[
        "equipment",
        "exercise"
    ],
    "wof:name":"Fitness Systems",
    "wof:placetype":"venue"
},
  "geometry": {"coordinates":[-85.579178,38.251436],"type":"Point"}
}