{
  "type": "Feature",
  "properties": {
    "addr:full":"761 S Laurel Rd London KY 40744",
    "addr:housenumber":"761",
    "addr:postcode":"40744",
    "addr:street":"S Laurel Rd",
    "iso:country":"US",
    "sg:address":"761 S Laurel Rd",
    "sg:city":"London",
    "sg:classifiers":[
        {
            "category":"Government",
            "subcategory":"Police Station",
            "type":"Public Place"
        }
    ],
    "sg:phone":"+1 606 864 8522",
    "sg:postcode":"40744",
    "sg:province":"KY",
    "sg:tags":[
        "department"
    ],
    "wof:name":"Us Forest Svc Law Inforcement",
    "wof:placetype":"venue"
},
  "geometry": {"coordinates":[-84.06974099999999,37.101971],"type":"Point"}
}