{
  "type": "Feature",
  "properties": {
    "iso:country":"US",
    "sg:address":"6043 Scottsville Rd",
    "sg:city":"Bowling Green",
    "sg:classifiers":[
        {
            "category":"Professional",
            "subcategory":"Research",
            "type":"Services"
        }
    ],
    "sg:phone":"+1 270 781 5126",
    "sg:postcode":"42122",
    "sg:province":"KY",
    "sg:tags":[
        "environmental",
        "ecological"
    ],
    "wof:name":"Enviro-Tec Svc Inc",
    "wof:placetype":"venue"
},
  "geometry": {"coordinates":[-86.40287600000001,36.909736],"type":"Point"}
}