{
  "type": "Feature",
  "properties": {
    "addr:full":"608 Greenwood Dr Harrodsburg KY 40330",
    "addr:housenumber":"608",
    "addr:postcode":"40330",
    "addr:street":"Greenwood Dr",
    "iso:country":"US",
    "sg:address":"608 Greenwood Dr",
    "sg:city":"Harrodsburg",
    "sg:classifiers":[
        {
            "category":"Real Estate",
            "subcategory":"Real Estate Operator",
            "type":"Services"
        }
    ],
    "sg:phone":"+1 859 734 4948",
    "sg:postcode":"40330",
    "sg:province":"KY",
    "sg:tags":[
        "property",
        "lessor"
    ],
    "wof:name":"Randall Sanders",
    "wof:placetype":"venue"
},
  "geometry": {"coordinates":[-84.82684,37.763424],"type":"Point"}
}