{
  "type": "Feature",
  "properties": {
    "iso:country":"US",
    "sg:address":"113 S 4th St",
    "sg:city":"Paducah",
    "sg:classifiers":[
        {
            "category":"Professional",
            "subcategory":"Lawyer & Legal Services",
            "type":"Services"
        }
    ],
    "sg:phone":"+1 270 575 9100",
    "sg:postcode":"42001",
    "sg:province":"KY",
    "sg:tags":[
        "attorney"
    ],
    "wof:name":"Michael D Moore",
    "wof:placetype":"venue"
},
  "geometry": {"coordinates":[-88.59806399999999,37.08656],"type":"Point"}
}