{
  "type": "Feature",
  "properties": {
    "addr:full":"1141 S 2nd St Louisville KY 40203",
    "addr:housenumber":"1141",
    "addr:postcode":"40203",
    "addr:street":"S 2Nd St",
    "iso:country":"US",
    "sg:address":"1141 S 2nd St",
    "sg:city":"Louisville",
    "sg:classifiers":[
        {
            "category":"Organizations",
            "subcategory":"Religious Organization",
            "type":"Services"
        }
    ],
    "sg:phone":"+1 502 581 0690",
    "sg:postcode":"40203",
    "sg:province":"KY",
    "sg:tags":[
        "church"
    ],
    "wof:name":"Peniel Revival Ctr",
    "wof:placetype":"venue"
},
  "geometry": {"coordinates":[-85.756602,38.236949],"type":"Point"}
}