{
  "type": "Feature",
  "properties": {
    "addr:full":"286 Sawmill Hollow Rd Williamsburg KY 40769",
    "addr:housenumber":"286",
    "addr:postcode":"40769",
    "addr:street":"Sawmill Hollow Rd",
    "iso:country":"US",
    "sg:address":"286 Sawmill Hollow Rd",
    "sg:city":"Williamsburg",
    "sg:classifiers":[
        {
            "category":"Manufacturing",
            "subcategory":"Lumber",
            "type":"Manufacturing & Wholesale Goods"
        }
    ],
    "sg:phone":"+1 606 786 7838",
    "sg:postcode":"40769",
    "sg:province":"KY",
    "sg:tags":[
        "logging"
    ],
    "wof:name":"Roy Rowe Logging",
    "wof:placetype":"venue"
},
  "geometry": {"coordinates":[-84.135424,36.616962],"type":"Point"}
}