{
  "type": "Feature",
  "properties": {
    "addr:full":"709 W Main St Morehead KY 40351",
    "addr:housenumber":"709",
    "addr:postcode":"40351",
    "addr:street":"W Main St",
    "iso:country":"US",
    "sg:address":"709 W Main St",
    "sg:city":"Morehead",
    "sg:classifiers":[
        {
            "category":"Health Services",
            "subcategory":"Doctor",
            "type":"Services"
        }
    ],
    "sg:phone":"+1 606 784 8983",
    "sg:postcode":"40351",
    "sg:province":"KY",
    "sg:tags":[
        "dentist"
    ],
    "wof:name":"Smith Gray & Morris",
    "wof:placetype":"venue"
},
  "geometry": {"coordinates":[-83.440038,38.174124],"type":"Point"}
}