{
  "type": "Feature",
  "properties": {
    "iso:country":"US",
    "sg:address":"111 Vanderbilt Dr",
    "sg:city":"Bowling Green",
    "sg:classifiers":[
        {
            "category":"Manufacturing",
            "subcategory":"Printing",
            "type":"Manufacturing & Wholesale Goods"
        }
    ],
    "sg:phone":"+1 270 842 1635",
    "sg:postcode":"42103",
    "sg:province":"KY",
    "sg:tags":[
        "printer"
    ],
    "sg:website":"www.pip.com",
    "wof:name":"PIP Printing",
    "wof:placetype":"venue"
},
  "geometry": {"coordinates":[-86.40694999999999,36.926665],"type":"Point"}
}