{
  "type": "Feature",
  "properties": {
    "addr:full":"325 W Main St Lexington KY 40507",
    "addr:housenumber":"325",
    "addr:postcode":"40507",
    "addr:street":"W Main St",
    "iso:country":"US",
    "sg:address":"325 W Main St",
    "sg:city":"Lexington",
    "sg:classifiers":[
        {
            "category":"Professional",
            "subcategory":"Advertising",
            "type":"Services"
        }
    ],
    "sg:phone":"+1 859 252 3350",
    "sg:postcode":"40507",
    "sg:province":"KY",
    "sg:tags":[
        "counselor"
    ],
    "sg:website":"www.meridiancomm.com",
    "wof:name":"Meridian Communication",
    "wof:placetype":"venue"
},
  "geometry": {"coordinates":[-84.49963099999999,38.048778],"type":"Point"}
}