{
  "type": "Feature",
  "properties": {
    "addr:full":"2425 Ralph Ave Louisville KY 40216",
    "addr:housenumber":"2425",
    "addr:postcode":"40216",
    "addr:street":"Ralph Ave",
    "iso:country":"US",
    "sg:address":"2425 Ralph Ave",
    "sg:city":"Louisville",
    "sg:classifiers":[
        {
            "category":"Freight",
            "type":"Transportation"
        }
    ],
    "sg:phone":"+1 502 449 9870",
    "sg:postcode":"40216",
    "sg:province":"KY",
    "sg:tags":[
        "trucking"
    ],
    "wof:name":"Midwest Transportation Svc",
    "wof:placetype":"venue"
},
  "geometry": {"coordinates":[-85.809337,38.206707],"type":"Point"}
}