{
  "type": "Feature",
  "properties": {
    "iso:country":"US",
    "sg:address":"3420 Rocky Hill Rd",
    "sg:city":"Glasgow",
    "sg:classifiers":[
        {
            "category":"Farming",
            "subcategory":"Farm",
            "type":"Manufacturing & Wholesale Goods"
        }
    ],
    "sg:phone":"+1 270 678 2475",
    "sg:postcode":"42141",
    "sg:province":"KY",
    "sg:tags":[
        "crop",
        "general"
    ],
    "wof:name":"Bailey Farm Brad Bailey",
    "wof:placetype":"venue"
},
  "geometry": {"coordinates":[-86.069374,36.977372],"type":"Point"}
}