{
  "type": "Feature",
  "properties": {
    "iso:country":"US",
    "sg:address":"5135 State Hwy 79",
    "sg:city":"Brandenburg",
    "sg:classifiers":[
        {
            "category":"Manufacturing",
            "subcategory":"Printing",
            "type":"Manufacturing & Wholesale Goods"
        }
    ],
    "sg:phone":"+1 270 422 2385",
    "sg:postcode":"40108",
    "sg:province":"KY",
    "sg:tags":[
        "commercial"
    ],
    "wof:name":"K Bebbie",
    "wof:placetype":"venue"
},
  "geometry": {"coordinates":[-86.239181,37.95092],"type":"Point"}
}