{
  "type": "Feature",
  "properties": {
    "addr:full":"320 5th St Pineville KY 40977",
    "addr:housenumber":"320",
    "addr:postcode":"40977",
    "addr:street":"5Th St",
    "iso:country":"US",
    "sg:address":"320 5th St",
    "sg:city":"Pineville",
    "sg:classifiers":[
        {
            "category":"Organizations",
            "subcategory":"Religious Organization",
            "type":"Services"
        }
    ],
    "sg:phone":"+1 606 337 1154",
    "sg:postcode":"40977",
    "sg:province":"KY",
    "sg:tags":[
        "church"
    ],
    "wof:name":"West Pineville Baptist Church",
    "wof:placetype":"venue"
},
  "geometry": {"coordinates":[-83.710911,36.766594],"type":"Point"}
}