{
  "type": "Feature",
  "properties": {
    "addr:full":"41 Altamont Ct Fort Thomas KY 41075",
    "addr:housenumber":"41",
    "addr:postcode":"41075",
    "addr:street":"Altamont Ct",
    "iso:country":"US",
    "sg:address":"41 Altamont Ct",
    "sg:city":"Fort Thomas",
    "sg:classifiers":[
        {
            "category":"Professional",
            "subcategory":"Business Services",
            "type":"Services"
        }
    ],
    "sg:phone":"+1 859 441 1121",
    "sg:postcode":"41075",
    "sg:province":"KY",
    "wof:name":"Matthew Ziegler",
    "wof:placetype":"venue"
},
  "geometry": {"coordinates":[-84.44447700000001,39.070258],"type":"Point"}
}