{
  "type": "Feature",
  "properties": {
    "addr:full":"6615 Foxcroft Rd Prospect KY 40059",
    "addr:housenumber":"6615",
    "addr:postcode":"40059",
    "addr:street":"Foxcroft Rd",
    "iso:country":"US",
    "sg:address":"6615 Foxcroft Rd",
    "sg:city":"Prospect",
    "sg:classifiers":[
        {
            "category":"Personal",
            "type":"Services"
        }
    ],
    "sg:phone":"+1 502 228 0615",
    "sg:postcode":"40059",
    "sg:province":"KY",
    "sg:tags":[
        "locker"
    ],
    "wof:name":"Vanderbur Industrial Products",
    "wof:placetype":"venue"
},
  "geometry": {"coordinates":[-85.60193099999999,38.340752],"type":"Point"}
}