{
  "type": "Feature",
  "properties": {
    "addr:full":"1841 White City Rd Hodgenville KY 42748",
    "addr:housenumber":"1841",
    "addr:postcode":"42748",
    "addr:street":"White City Rd",
    "iso:country":"US",
    "sg:address":"1841 White City Rd",
    "sg:city":"Hodgenville",
    "sg:classifiers":[
        {
            "category":"Freight",
            "type":"Transportation"
        }
    ],
    "sg:phone":"+1 270 258 9844",
    "sg:postcode":"42748",
    "sg:province":"KY",
    "sg:tags":[
        "trucking"
    ],
    "wof:name":"Tristate Express",
    "wof:placetype":"venue"
},
  "geometry": {"coordinates":[-85.674542,37.619345],"type":"Point"}
}