{
  "type": "Feature",
  "properties": {
    "iso:country":"US",
    "sg:address":"121 Prosperous Pl",
    "sg:city":"Lexington",
    "sg:classifiers":[
        {
            "category":"Professional",
            "subcategory":"Management & Consulting",
            "type":"Services"
        }
    ],
    "sg:phone":"+1 859 263 9425",
    "sg:postcode":"40509",
    "sg:province":"KY",
    "sg:tags":[
        "communications",
        "consultant"
    ],
    "wof:name":"Intelcom Inc",
    "wof:placetype":"venue"
},
  "geometry": {"coordinates":[-84.44449400000001,38.000547],"type":"Point"}
}