{
  "type": "Feature",
  "properties": {
    "iso:country":"US",
    "sg:address":"101 S Main St",
    "sg:city":"Somerset",
    "sg:classifiers":[
        {
            "category":"Shopping",
            "subcategory":"Pharmacy",
            "type":"Retail Goods"
        }
    ],
    "sg:phone":"+1 606 679 1571",
    "sg:postcode":"42501",
    "sg:province":"KY",
    "wof:name":"Somerset Pharmacy",
    "wof:placetype":"venue"
},
  "geometry": {"coordinates":[-84.604219,37.09067],"type":"Point"}
}