{
  "type": "Feature",
  "properties": {
    "iso:country":"US",
    "sg:address":"4522 Unseld Blvd",
    "sg:city":"Louisville",
    "sg:classifiers":[
        {
            "category":"Building & Trades",
            "subcategory":"Cleaning & Sanitation",
            "type":"Services"
        }
    ],
    "sg:phone":"+1 502 458 8261",
    "sg:postcode":"40218",
    "sg:province":"KY",
    "sg:tags":[
        "janitor"
    ],
    "wof:name":"MDB Enterprise Inc",
    "wof:placetype":"venue"
},
  "geometry": {"coordinates":[-85.67106200000001,38.18613],"type":"Point"}
}