{
  "type": "Feature",
  "properties": {
    "iso:country":"US",
    "sg:address":"116 S Main St",
    "sg:city":"Edmonton",
    "sg:classifiers":[
        {
            "category":"Manufacturing",
            "subcategory":"Printing",
            "type":"Manufacturing & Wholesale Goods"
        }
    ],
    "sg:phone":"+1 270 432 3291",
    "sg:postcode":"42129",
    "sg:province":"KY",
    "sg:tags":[
        "newspaper"
    ],
    "wof:name":"Edmonton Herald News",
    "wof:placetype":"venue"
},
  "geometry": {"coordinates":[-85.61185500000001,36.978381],"type":"Point"}
}