{
  "type": "Feature",
  "properties": {
    "iso:country":"US",
    "sg:address":"1712 E Broadway St",
    "sg:city":"Campbellsville",
    "sg:classifiers":[
        {
            "category":"Health Services",
            "subcategory":"Medical Lab",
            "type":"Services"
        }
    ],
    "sg:phone":"+1 270 469 9977",
    "sg:postcode":"42718",
    "sg:province":"KY",
    "sg:tags":[
        "detection",
        "equipment",
        "drug"
    ],
    "wof:name":"Control Substance Management",
    "wof:placetype":"venue"
},
  "geometry": {"coordinates":[-85.32306,37.357487],"type":"Point"}
}