{
  "type": "Feature",
  "properties": {
    "iso:country":"US",
    "sg:address":"300 Huff Ln",
    "sg:city":"Scottsville",
    "sg:classifiers":[
        {
            "category":"Manufacturing",
            "subcategory":"Lumber",
            "type":"Manufacturing & Wholesale Goods"
        }
    ],
    "sg:phone":"+1 270 622 6359",
    "sg:postcode":"42164",
    "sg:province":"KY",
    "sg:tags":[
        "operation",
        "timber",
        "tract"
    ],
    "wof:name":"RDS Tree Farm Inc",
    "wof:placetype":"venue"
},
  "geometry": {"coordinates":[-86.28522599999999,36.72875],"type":"Point"}
}