{
  "type": "Feature",
  "properties": {
    "iso:country":"US",
    "sg:address":"102 South St",
    "sg:city":"Butler",
    "sg:classifiers":[
        {
            "category":"Manufacturing",
            "subcategory":"Tools & Machinery",
            "type":"Manufacturing & Wholesale Goods"
        }
    ],
    "sg:phone":"+1 859 472 2386",
    "sg:postcode":"41006",
    "sg:province":"KY",
    "sg:tags":[
        "ind",
        "general"
    ],
    "wof:name":"Pittsfield Of Kentucky",
    "wof:placetype":"venue"
},
  "geometry": {"coordinates":[-84.36612599999999,38.785363],"type":"Point"}
}