{
  "type": "Feature",
  "properties": {
    "iso:country":"US",
    "sg:address":"605 W Main St",
    "sg:city":"Louisville",
    "sg:classifiers":[
        {
            "category":"Professional",
            "subcategory":"Lawyer & Legal Services",
            "type":"Services"
        }
    ],
    "sg:phone":"+1 502 587 0900",
    "sg:postcode":"40202",
    "sg:province":"KY",
    "sg:tags":[
        "attorney"
    ],
    "wof:name":"J Bruce Miller Law Group",
    "wof:placetype":"venue"
},
  "geometry": {"coordinates":[-85.761426,38.257226],"type":"Point"}
}