{
  "type": "Feature",
  "properties": {
    "iso:country":"US",
    "sg:address":"3706 Locklee Rd",
    "sg:city":"Louisville",
    "sg:classifiers":[
        {
            "category":"Building & Trades",
            "subcategory":"Plumbing",
            "type":"Services"
        }
    ],
    "sg:phone":"+1 502 937 2165",
    "sg:postcode":"40214",
    "sg:province":"KY",
    "sg:tags":[
        "plumbing",
        "contractor"
    ],
    "wof:name":"Charlie's Plumbing & Piping",
    "wof:placetype":"venue"
},
  "geometry": {"coordinates":[-85.826229,38.144523],"type":"Point"}
}