{
  "type": "Feature",
  "properties": {
    "addr:full":"1086 Thornberry Dr Madisonville KY 42431",
    "addr:housenumber":"1086",
    "addr:postcode":"42431",
    "addr:street":"Thornberry Dr",
    "iso:country":"US",
    "sg:address":"1086 Thornberry Dr",
    "sg:city":"Madisonville",
    "sg:classifiers":[
        {
            "category":"Social Services",
            "type":"Services"
        }
    ],
    "sg:phone":"+1 270 824 7555",
    "sg:postcode":"42431",
    "sg:province":"KY",
    "sg:tags":[
        "government"
    ],
    "wof:name":"Dept Of Families & Children",
    "wof:placetype":"venue"
},
  "geometry": {"coordinates":[-87.49747499999999,37.345923],"type":"Point"}
}