{
  "type": "Feature",
  "properties": {
    "iso:country":"US",
    "sg:address":"2502 S Us Highway 421",
    "sg:city":"Harlan",
    "sg:classifiers":[
        {
            "category":"Restaurant",
            "type":"Food & Drink"
        }
    ],
    "sg:menulink":"http://www.allmenus.com/ky/harlan/237747-rax/menu/",
    "sg:phone":"+1 606 573 7922",
    "sg:postcode":"40831",
    "sg:province":"KY",
    "sg:tags":[
        "wrap",
        "american",
        "sandwich"
    ],
    "wof:name":"Rax",
    "wof:placetype":"venue"
},
  "geometry": {"coordinates":[-83.311077,36.808345],"type":"Point"}
}