{
  "type": "Feature",
  "properties": {
    "iso:country":"US",
    "sg:address":"732 National Ave",
    "sg:city":"Lexington",
    "sg:classifiers":[
        {
            "category":"Shopping",
            "subcategory":"Used Merchandise",
            "type":"Retail Goods"
        }
    ],
    "sg:phone":"+1 859 253 0137",
    "sg:postcode":"40502",
    "sg:province":"KY",
    "sg:tags":[
        "antique"
    ],
    "wof:name":"Lenabelles Antiques & Interors",
    "wof:placetype":"venue"
},
  "geometry": {"coordinates":[-84.47783800000001,38.039706],"type":"Point"}
}