{
  "type": "Feature",
  "properties": {
    "iso:country":"US",
    "sg:address":"1850 Production Ct",
    "sg:city":"Louisville",
    "sg:classifiers":[
        {
            "category":"Home & Garden",
            "subcategory":"Building Materials",
            "type":"Retail Goods"
        },
        {
            "category":"Manufacturing",
            "subcategory":"Glass & Minerals",
            "type":"Manufacturing & Wholesale Goods"
        }
    ],
    "sg:phone":"+1 502 671 7777",
    "sg:postcode":"40299",
    "sg:province":"KY",
    "sg:tags":[
        "plate",
        "window",
        "glass-auto"
    ],
    "wof:name":"Window World Incorporated",
    "wof:placetype":"venue"
},
  "geometry": {"coordinates":[-85.565308,38.220501],"type":"Point"}
}