{
  "type": "Feature",
  "properties": {
    "addr:full":"1705 Mount Zion Rd Union KY 41091",
    "addr:housenumber":"1705",
    "addr:postcode":"41091",
    "addr:street":"Mount Zion Rd",
    "iso:country":"US",
    "sg:address":"1705 Mount Zion Rd",
    "sg:city":"Union",
    "sg:classifiers":[
        {
            "category":"Social Services",
            "subcategory":"Child Care",
            "type":"Services"
        }
    ],
    "sg:phone":"+1 859 384 1313",
    "sg:postcode":"41091",
    "sg:province":"KY",
    "sg:tags":[
        "day"
    ],
    "wof:name":"Littlest Angels'learning Cntr",
    "wof:placetype":"venue"
},
  "geometry": {"coordinates":[-84.67040299999999,38.9482],"type":"Point"}
}