{
  "type": "Feature",
  "properties": {
    "addr:full":"105 Imperial Way Nicholasville KY 40356",
    "addr:housenumber":"105",
    "addr:postcode":"40356",
    "addr:street":"Imperial Way",
    "iso:country":"US",
    "sg:address":"105 Imperial Way",
    "sg:city":"Nicholasville",
    "sg:classifiers":[
        {
            "category":"Retail",
            "subcategory":"Auto Repair",
            "type":"Services"
        }
    ],
    "sg:phone":"+1 859 885 0202",
    "sg:postcode":"40356",
    "sg:province":"KY",
    "sg:website":"http://www.autoproky.com",
    "wof:name":"Allen Wrench Enterprices",
    "wof:placetype":"venue"
},
  "geometry": {"coordinates":[-84.566948,37.89864],"type":"Point"}
}