{
  "type": "Feature",
  "properties": {
    "iso:country":"US",
    "sg:address":"1347 S 3rd St",
    "sg:city":"Louisville",
    "sg:classifiers":[
        {
            "category":"Professional",
            "subcategory":"Detective & Security Services",
            "type":"Services"
        }
    ],
    "sg:phone":"+1 502 637 5074",
    "sg:postcode":"40208",
    "sg:province":"KY",
    "sg:tags":[
        "investigator"
    ],
    "wof:name":"Global Investigations Inc",
    "wof:placetype":"venue"
},
  "geometry": {"coordinates":[-85.759028,38.232632],"type":"Point"}
}