{
  "type": "Feature",
  "properties": {
    "iso:country":"US",
    "sg:address":"1514 Brush Creek Rd",
    "sg:city":"Liberty",
    "sg:classifiers":[
        {
            "category":"Building & Trades",
            "subcategory":"Landscaping Services",
            "type":"Services"
        }
    ],
    "sg:phone":"+1 606 787 5560",
    "sg:postcode":"42539",
    "sg:province":"KY",
    "wof:name":"Clems Mowing Inc",
    "wof:placetype":"venue"
},
  "geometry": {"coordinates":[-84.93628099999999,37.367953],"type":"Point"}
}