{
  "type": "Feature",
  "properties": {
    "addr:full":"2403 Langdon Dr Louisville KY 40242",
    "addr:housenumber":"2403",
    "addr:postcode":"40242",
    "addr:street":"Langdon Dr",
    "iso:country":"US",
    "sg:address":"2403 Langdon Dr",
    "sg:city":"Louisville",
    "sg:classifiers":[
        {
            "category":"Retail",
            "subcategory":"Repair Shop",
            "type":"Services"
        }
    ],
    "sg:phone":"+1 502 327 7410",
    "sg:postcode":"40242",
    "sg:province":"KY",
    "wof:name":"Mandzo Cleaning LLC",
    "wof:placetype":"venue"
},
  "geometry": {"coordinates":[-85.57977,38.281893],"type":"Point"}
}