{
  "type": "Feature",
  "properties": {
    "iso:country":"US",
    "sg:address":"616 S 5th St",
    "sg:city":"Louisville",
    "sg:classifiers":[
        {
            "category":"Professional",
            "subcategory":"Lawyer & Legal Services",
            "type":"Services"
        }
    ],
    "sg:phone":"+1 502 583 3898",
    "sg:postcode":"40202",
    "sg:province":"KY",
    "sg:tags":[
        "attorney"
    ],
    "wof:name":"Samuel B Carl",
    "wof:placetype":"venue"
},
  "geometry": {"coordinates":[-85.75985,38.247883],"type":"Point"}
}