{
  "type": "Feature",
  "properties": {
    "iso:country":"US",
    "sg:address":"5046 Poplar Level Rd",
    "sg:city":"Louisville",
    "sg:classifiers":[
        {
            "category":"Food & Beverages",
            "subcategory":"Liquor & Beverages",
            "type":"Retail Goods"
        }
    ],
    "sg:phone":"+1 502 968 7720",
    "sg:postcode":"40219",
    "sg:province":"KY",
    "wof:name":"Freddy's Liquor Store",
    "wof:placetype":"venue"
},
  "geometry": {"coordinates":[-85.678686,38.163145],"type":"Point"}
}