{
  "type": "Feature",
  "properties": {
    "addr:full":"510 W Broadway Louisville KY 40202",
    "addr:housenumber":"510",
    "addr:postcode":"40202",
    "addr:street":"W Broadway",
    "iso:country":"US",
    "sg:address":"510 W Broadway",
    "sg:city":"Louisville",
    "sg:classifiers":[
        {
            "category":"Government",
            "subcategory":"Court House",
            "type":"Public Place"
        }
    ],
    "sg:phone":"+1 502 582 5911",
    "sg:postcode":"40202",
    "sg:province":"KY",
    "sg:tags":[
        "federal",
        "counsel"
    ],
    "wof:name":"US Attorney",
    "wof:placetype":"venue"
},
  "geometry": {"coordinates":[-85.760683,38.246169],"type":"Point"}
}