{
  "type": "Feature",
  "properties": {
    "addr:full":"320 Pugh Rd Paducah KY 42003",
    "addr:housenumber":"320",
    "addr:postcode":"42003",
    "addr:street":"Pugh Rd",
    "iso:country":"US",
    "sg:address":"320 Pugh Rd",
    "sg:city":"Paducah",
    "sg:classifiers":[
        {
            "category":"Professional",
            "subcategory":"Business Services",
            "type":"Services"
        }
    ],
    "sg:phone":"+1 270 898 6478",
    "sg:postcode":"42003",
    "sg:province":"KY",
    "wof:name":"Edward R Robertson",
    "wof:placetype":"venue"
},
  "geometry": {"coordinates":[-88.543835,37.030666],"type":"Point"}
}