{
  "type": "Feature",
  "properties": {
    "iso:country":"US",
    "sg:address":"208 Butler St",
    "sg:city":"Columbia",
    "sg:classifiers":[
        {
            "category":"Farming",
            "subcategory":"Farm",
            "type":"Manufacturing & Wholesale Goods"
        }
    ],
    "sg:phone":"+1 270 384 5682",
    "sg:postcode":"42728",
    "sg:province":"KY",
    "sg:tags":[
        "crop",
        "general"
    ],
    "wof:name":"Nelson Farms",
    "wof:placetype":"venue"
},
  "geometry": {"coordinates":[-85.315048,37.114983],"type":"Point"}
}