{
  "type": "Feature",
  "properties": {
    "iso:country":"US",
    "sg:address":"8908 Ash Ave",
    "sg:city":"Pewee Valley",
    "sg:classifiers":[
        {
            "category":"Building & Trades",
            "subcategory":"Construction",
            "type":"Services"
        }
    ],
    "sg:phone":"+1 502 243 8697",
    "sg:postcode":"40056",
    "sg:province":"KY",
    "sg:tags":[
        "contractor"
    ],
    "wof:name":"Garry Drexler Drywall & Remode",
    "wof:placetype":"venue"
},
  "geometry": {"coordinates":[-85.47861399999999,38.297501],"type":"Point"}
}