{
  "type": "Feature",
  "properties": {
    "iso:country":"US",
    "sg:address":"310 S Lake Dr",
    "sg:city":"Prestonsburg",
    "sg:classifiers":[
        {
            "category":"Professional",
            "subcategory":"Lawyer & Legal Services",
            "type":"Services"
        }
    ],
    "sg:phone":"+1 606 886 1428",
    "sg:postcode":"41653",
    "sg:province":"KY",
    "sg:tags":[
        "attorney"
    ],
    "wof:name":"Vanover Hall & Bartley",
    "wof:placetype":"venue"
},
  "geometry": {"coordinates":[-82.769381,37.66578],"type":"Point"}
}