{
  "type": "Feature",
  "properties": {
    "iso:country":"US",
    "sg:address":"8047 Connector Dr",
    "sg:city":"Florence",
    "sg:classifiers":[
        {
            "category":"Personal",
            "type":"Services"
        }
    ],
    "sg:phone":"+1 859 371 1719",
    "sg:postcode":"41042",
    "sg:province":"KY",
    "sg:tags":[
        "control",
        "weight"
    ],
    "wof:name":"Inches A Weigh",
    "wof:placetype":"venue"
},
  "geometry": {"coordinates":[-84.652244,38.989118],"type":"Point"}
}