{
  "type": "Feature",
  "properties": {
    "iso:country":"US",
    "sg:address":"1620 Burlington Pike Suite A",
    "sg:city":"Florence",
    "sg:classifiers":[
        {
            "category":"Building & Trades",
            "subcategory":"Construction",
            "type":"Services"
        }
    ],
    "sg:phone":"+1 513 753 8463",
    "sg:postcode":"41042",
    "sg:province":"KY",
    "sg:tags":[
        "contractor"
    ],
    "sg:website":"newrooftime.com",
    "wof:name":"A New Roof Time / \u00a0Rooftime",
    "wof:placetype":"venue"
},
  "geometry": {"coordinates":[-84.656885,39.006047],"type":"Point"}
}