{
  "type": "Feature",
  "properties": {
    "iso:country":"US",
    "sg:address":"6703 Scenic Trl",
    "sg:city":"Louisville",
    "sg:classifiers":[
        {
            "category":"Personal",
            "type":"Services"
        }
    ],
    "sg:phone":"+1 502 935 8918",
    "sg:postcode":"40272",
    "sg:province":"KY",
    "wof:name":"Mattingly W I Association LLC",
    "wof:placetype":"venue"
},
  "geometry": {"coordinates":[-85.888544,38.072749],"type":"Point"}
}