{
  "type": "Feature",
  "properties": {
    "addr:full":"100 Howards Grove Rd Calvert City KY 42029",
    "addr:housenumber":"100",
    "addr:postcode":"42029",
    "addr:street":"Howards Grove Rd",
    "iso:country":"US",
    "sg:address":"100 Howards Grove Rd",
    "sg:city":"Calvert City",
    "sg:classifiers":[
        {
            "category":"Freight",
            "type":"Transportation"
        }
    ],
    "sg:phone":"+1 270 395 7652",
    "sg:postcode":"42029",
    "sg:province":"KY",
    "sg:tags":[
        "local",
        "trucking"
    ],
    "wof:name":"Collins Bulk",
    "wof:placetype":"venue"
},
  "geometry": {"coordinates":[-88.38512900000001,37.007464],"type":"Point"}
}