{
  "type": "Feature",
  "properties": {
    "iso:country":"US",
    "sg:address":"515 S 3rd St",
    "sg:city":"Paducah",
    "sg:classifiers":[
        {
            "category":"Autos & Motor Vehicles",
            "subcategory":"Boat Sales",
            "type":"Retail Goods"
        }
    ],
    "sg:phone":"+1 270 443 5626",
    "sg:postcode":"42003",
    "sg:province":"KY",
    "sg:tags":[
        "dealer",
        "sales"
    ],
    "wof:name":"Southside Outboard Inc",
    "wof:placetype":"venue"
},
  "geometry": {"coordinates":[-88.594103,37.082802],"type":"Point"}
}