{
  "type": "Feature",
  "properties": {
    "addr:full":"1990 N Bend Rd Hebron KY 41048",
    "addr:housenumber":"1990",
    "addr:postcode":"41048",
    "addr:street":"N Bend Rd",
    "iso:country":"US",
    "sg:address":"1990 N Bend Rd",
    "sg:city":"Hebron",
    "sg:classifiers":[
        {
            "category":"Shopping",
            "subcategory":"Tobacco",
            "type":"Retail Goods"
        },
        {
            "category":"Food & Beverages",
            "subcategory":"Liquor & Beverages",
            "type":"Retail Goods"
        }
    ],
    "sg:phone":"+1 859 586 9270",
    "sg:postcode":"41048",
    "sg:province":"KY",
    "sg:tags":[
        "shop",
        "beer",
        "spirit",
        "wine"
    ],
    "wof:name":"Liquor Cabinet",
    "wof:placetype":"venue"
},
  "geometry": {"coordinates":[-84.712833,39.090408],"type":"Point"}
}