{
  "type": "Feature",
  "properties": {
    "iso:country":"US",
    "sg:address":"1853 E 9th St",
    "sg:city":"Hopkinsville",
    "sg:classifiers":[
        {
            "category":"Retail",
            "subcategory":"Auto Repair",
            "type":"Services"
        }
    ],
    "sg:phone":"+1 270 885 6008",
    "sg:postcode":"42240",
    "sg:province":"KY",
    "sg:tags":[
        "automobile",
        "electric"
    ],
    "wof:name":"Five Star Rebuilders",
    "wof:placetype":"venue"
},
  "geometry": {"coordinates":[-87.46785800000001,36.848707],"type":"Point"}
}