{
  "type": "Feature",
  "properties": {
    "iso:country":"US",
    "sg:address":"754 Dove Ct",
    "sg:city":"Owensboro",
    "sg:classifiers":[
        {
            "category":"Building & Trades",
            "subcategory":"Landscaping Services",
            "type":"Services"
        }
    ],
    "sg:phone":"+1 270 684 2182",
    "sg:postcode":"42301",
    "sg:province":"KY",
    "sg:tags":[
        "lawn",
        "maintenance",
        "grounds"
    ],
    "wof:name":"Perfection Lawn Care Inc",
    "wof:placetype":"venue"
},
  "geometry": {"coordinates":[-87.17883500000001,37.764964],"type":"Point"}
}