{
  "type": "Feature",
  "properties": {
    "iso:country":"US",
    "sg:address":"4449 Chloe Rd",
    "sg:city":"Pikeville",
    "sg:classifiers":[
        {
            "category":"Wholesale",
            "subcategory":"Construction Materials",
            "type":"Manufacturing & Wholesale Goods"
        }
    ],
    "sg:phone":"+1 606 437 6002",
    "sg:postcode":"41501",
    "sg:province":"KY",
    "sg:tags":[
        "top",
        "counter"
    ],
    "wof:name":"Custom Countertops",
    "wof:placetype":"venue"
},
  "geometry": {"coordinates":[-82.478837,37.439986],"type":"Point"}
}