{
  "type": "Feature",
  "properties": {
    "iso:country":"US",
    "sg:address":"1930 Oxford Cir",
    "sg:city":"Lexington",
    "sg:classifiers":[
        {
            "category":"Food & Beverages",
            "subcategory":"Bakery",
            "type":"Retail Goods"
        }
    ],
    "sg:phone":"+1 859 225 5744",
    "sg:postcode":"40504",
    "sg:province":"KY",
    "sg:tags":[
        "baker"
    ],
    "wof:name":"Sanpanchos Bakery",
    "wof:placetype":"venue"
},
  "geometry": {"coordinates":[-84.540627,38.050145],"type":"Point"}
}