{
  "type": "Feature",
  "properties": {
    "addr:full":"3333 Industrial Dr Bowling Green KY 42101",
    "addr:housenumber":"3333",
    "addr:postcode":"42101",
    "addr:street":"Industrial Dr",
    "iso:country":"US",
    "sg:address":"3333 Industrial Dr",
    "sg:city":"Bowling Green",
    "sg:classifiers":[
        {
            "category":"Manufacturing",
            "subcategory":"Building Materials",
            "type":"Manufacturing & Wholesale Goods"
        }
    ],
    "sg:phone":"+1 270 782 1970",
    "sg:postcode":"42101",
    "sg:province":"KY",
    "sg:tags":[
        "member",
        "wood",
        "structural"
    ],
    "wof:name":"Truss Supply Inc",
    "wof:placetype":"venue"
},
  "geometry": {"coordinates":[-86.48205299999999,36.95325],"type":"Point"}
}