{
  "type": "Feature",
  "properties": {
    "iso:country":"US",
    "sg:address":"1182 Catnip Hill Rd",
    "sg:city":"Nicholasville",
    "sg:classifiers":[
        {
            "category":"Food & Beverages",
            "subcategory":"Groceries & Convenience Stores",
            "type":"Retail Goods"
        }
    ],
    "sg:phone":"+1 859 223 5818",
    "sg:postcode":"40356",
    "sg:province":"KY",
    "wof:name":"Salleys Food Stores",
    "wof:placetype":"venue"
},
  "geometry": {"coordinates":[-84.594362,37.945454],"type":"Point"}
}