{
  "type": "Feature",
  "properties": {
    "iso:country":"US",
    "sg:address":"3390 Allen Rd",
    "sg:city":"Clarksville",
    "sg:classifiers":[
        {
            "category":"Building & Trades",
            "subcategory":"Cleaning & Sanitation",
            "type":"Services"
        }
    ],
    "sg:phone":"+1 931 648 3114",
    "sg:postcode":"37042",
    "sg:province":"KY",
    "sg:tags":[
        "maintenance"
    ],
    "wof:name":"Miller Maintenance Co",
    "wof:placetype":"venue"
},
  "geometry": {"coordinates":[-87.38695800000001,36.63714],"type":"Point"}
}