{
  "type": "Feature",
  "properties": {
    "iso:country":"US",
    "sg:address":"2044 Baltimore Church Rd",
    "sg:city":"Mayfield",
    "sg:classifiers":[
        {
            "category":"Organizations",
            "subcategory":"Religious Organization",
            "type":"Services"
        }
    ],
    "sg:phone":"+1 270 376 2191",
    "sg:postcode":"42066",
    "sg:province":"KY",
    "sg:tags":[
        "church"
    ],
    "wof:name":"Baltimore Baptist Church",
    "wof:placetype":"venue"
},
  "geometry": {"coordinates":[-88.808391,36.67351],"type":"Point"}
}