{
  "type": "Feature",
  "properties": {
    "addr:full":"404 College St Elizabethtown KY 42701",
    "addr:housenumber":"404",
    "addr:postcode":"42701",
    "addr:street":"College St",
    "iso:country":"US",
    "sg:address":"404 College St",
    "sg:city":"Elizabethtown",
    "sg:classifiers":[
        {
            "category":"Local Transit",
            "type":"Transportation"
        }
    ],
    "sg:phone":"+1 270 234 0191",
    "sg:postcode":"42701",
    "sg:province":"KY",
    "wof:name":"Truck Transport",
    "wof:placetype":"venue"
},
  "geometry": {"coordinates":[-85.867278,37.692924],"type":"Point"}
}