{
  "type": "Feature",
  "properties": {
    "addr:full":"7642 Mall Rd Florence KY 41042",
    "addr:housenumber":"7642",
    "addr:postcode":"41042",
    "addr:street":"Mall Rd",
    "iso:country":"US",
    "sg:address":"7642 Mall Rd",
    "sg:city":"Florence",
    "sg:classifiers":[
        {
            "category":"Restaurant",
            "type":"Food & Drink"
        }
    ],
    "sg:menulink":"http://www.allmenus.com/ky/florence/152350-honeybaked-ham/menu/",
    "sg:phone":"+1 859 371 7171",
    "sg:postcode":"41042",
    "sg:province":"KY",
    "sg:tags":[
        "american"
    ],
    "wof:name":"The HoneyBaked Ham Company",
    "wof:placetype":"venue"
},
  "geometry": {"coordinates":[-84.651903,38.999551],"type":"Point"}
}