{
  "type": "Feature",
  "properties": {
    "addr:full":"200 Breckenridge Ln Louisville KY 40207",
    "addr:housenumber":"200",
    "addr:postcode":"40207",
    "addr:street":"Breckenridge Ln",
    "iso:country":"US",
    "sg:address":"200 Breckenridge Ln",
    "sg:city":"Louisville",
    "sg:classifiers":[
        {
            "category":"Banks & Credit Unions",
            "subcategory":"Bank",
            "type":"Services"
        }
    ],
    "sg:phone":"+1 502 895 4663",
    "sg:postcode":"40207",
    "sg:province":"KY",
    "sg:tags":[
        "mortgage"
    ],
    "wof:name":"Allied Home Mrtg Capitl Corp",
    "wof:placetype":"venue"
},
  "geometry": {"coordinates":[-85.65271199999999,38.24959],"type":"Point"}
}