{
  "type": "Feature",
  "properties": {
    "iso:country":"US",
    "sg:address":"6201 Preston Hwy",
    "sg:city":"Louisville",
    "sg:classifiers":[
        {
            "category":"Shopping",
            "type":"Retail Goods"
        },
        {
            "category":"Home & Garden",
            "subcategory":"Furniture",
            "type":"Retail Goods"
        }
    ],
    "sg:phone":"+1 502 968 9590",
    "sg:postcode":"40219",
    "sg:province":"KY",
    "sg:tags":[
        "rent-to-own",
        "leasing",
        "store",
        "renting"
    ],
    "sg:website":"http://www.seiaarons.com",
    "wof:name":"Aaron's Rental Purchase",
    "wof:placetype":"venue"
},
  "geometry": {"coordinates":[-85.69967699999999,38.161671],"type":"Point"}
}