{
  "type": "Feature",
  "properties": {
    "iso:country":"US",
    "sg:address":"1300 S 26th St",
    "sg:city":"Louisville",
    "sg:classifiers":[
        {
            "category":"Organizations",
            "subcategory":"Community Association",
            "type":"Services"
        }
    ],
    "sg:phone":"+1 502 778 1007",
    "sg:postcode":"40210",
    "sg:province":"KY",
    "sg:tags":[
        "club"
    ],
    "wof:name":"Retired Service Men Club",
    "wof:placetype":"venue"
},
  "geometry": {"coordinates":[-85.796623,38.234089],"type":"Point"}
}