{
  "type": "Feature",
  "properties": {
    "addr:full":"1400 Dixie Hwy S Elizabethtown KY 42701",
    "addr:housenumber":"1400",
    "addr:postcode":"42701",
    "addr:street":"Dixie Hwy S",
    "iso:country":"US",
    "sg:address":"1400 Dixie Hwy S",
    "sg:city":"Elizabethtown",
    "sg:classifiers":[
        {
            "category":"Autos & Motor Vehicles",
            "subcategory":"Auto Supplies",
            "type":"Retail Goods"
        }
    ],
    "sg:phone":"+1 270 737 1160",
    "sg:postcode":"42701",
    "sg:province":"KY",
    "sg:tags":[
        "tire"
    ],
    "wof:name":"Tci Tire Centers Inc",
    "wof:placetype":"venue"
},
  "geometry": {"coordinates":[-85.882549,37.724768],"type":"Point"}
}