{
  "type": "Feature",
  "properties": {
    "addr:full":"940 Taylor Rd Frankfort KY 40601",
    "addr:housenumber":"940",
    "addr:postcode":"40601",
    "addr:street":"Taylor Rd",
    "iso:country":"US",
    "sg:address":"940 Taylor Rd",
    "sg:city":"Frankfort",
    "sg:classifiers":[
        {
            "category":"Home & Garden",
            "subcategory":"Building Materials",
            "type":"Retail Goods"
        }
    ],
    "sg:phone":"+1 502 695 4008",
    "sg:postcode":"40601",
    "sg:province":"KY",
    "sg:tags":[
        "glass"
    ],
    "wof:name":"Strategic Materials Inc",
    "wof:placetype":"venue"
},
  "geometry": {"coordinates":[-84.81106200000001,38.187641],"type":"Point"}
}