{
  "type": "Feature",
  "properties": {
    "iso:country":"US",
    "sg:address":"569 el Paseo Pl",
    "sg:city":"Lexington",
    "sg:classifiers":[
        {
            "category":"Professional",
            "subcategory":"Computer Services",
            "type":"Services"
        }
    ],
    "sg:phone":"+1 859 335 8640",
    "sg:postcode":"40517",
    "sg:province":"KY",
    "sg:tags":[
        "related"
    ],
    "wof:name":"Intelledev Inc",
    "wof:placetype":"venue"
},
  "geometry": {"coordinates":[-84.455957,37.995987],"type":"Point"}
}