{
  "type": "Feature",
  "properties": {
    "iso:country":"US",
    "sg:address":"6806 John Paul Ln",
    "sg:city":"Louisville",
    "sg:classifiers":[
        {
            "category":"Building & Trades",
            "subcategory":"Construction",
            "type":"Services"
        }
    ],
    "sg:phone":"+1 502 439 9918",
    "sg:postcode":"40229",
    "sg:province":"KY",
    "sg:tags":[
        "resurfacing",
        "laying",
        "refinishing",
        "floor"
    ],
    "wof:name":"Quality Hardwood Flooring Inc",
    "wof:placetype":"venue"
},
  "geometry": {"coordinates":[-85.637317,38.117052],"type":"Point"}
}