{
  "type": "Feature",
  "properties": {
    "iso:country":"US",
    "sg:address":"1671 Park Rd Ste 8",
    "sg:city":"Covington",
    "sg:classifiers":[
        {
            "category":"Health Services",
            "subcategory":"Hospital",
            "type":"Services"
        },
        {
            "category":"Health Services",
            "subcategory":"Health Practitioner",
            "type":"Services"
        }
    ],
    "sg:phone":"+1 859 578 0099",
    "sg:postcode":"41011",
    "sg:province":"KY",
    "sg:tags":[
        "medicine",
        "alternative",
        "sleep",
        "treatment",
        "disorders-information"
    ],
    "wof:name":"Spice Of Life Health Choices",
    "wof:placetype":"venue"
},
  "geometry": {"coordinates":[-84.542191,39.061981],"type":"Point"}
}