{
  "type": "Feature",
  "properties": {
    "iso:country":"US",
    "sg:address":"4247 Lexington Rd",
    "sg:city":"Paris",
    "sg:classifiers":[
        {
            "category":"Real Estate",
            "subcategory":"Real Estate Agent",
            "type":"Services"
        }
    ],
    "sg:phone":"+1 859 987 8800",
    "sg:postcode":"40361",
    "sg:province":"KY",
    "wof:name":"Rector-Hayden Realtors",
    "wof:placetype":"venue"
},
  "geometry": {"coordinates":[-84.28875600000001,38.185614],"type":"Point"}
}