{
  "type": "Feature",
  "properties": {
    "iso:country":"US",
    "sg:address":"565 E New Circle Rd",
    "sg:city":"Lexington",
    "sg:classifiers":[
        {
            "category":"Shopping",
            "subcategory":"News",
            "type":"Retail Goods"
        }
    ],
    "sg:phone":"+1 859 293 1966",
    "sg:postcode":"40505",
    "sg:province":"KY",
    "sg:tags":[
        "magazine"
    ],
    "wof:name":"News Stand",
    "wof:placetype":"venue"
},
  "geometry": {"coordinates":[-84.459136,38.054204],"type":"Point"}
}