{
  "type": "Feature",
  "properties": {
    "iso:country":"US",
    "sg:address":"805 Euclid Ave",
    "sg:city":"Paintsville",
    "sg:classifiers":[
        {
            "category":"Education",
            "subcategory":"Special Training",
            "type":"Public Place"
        }
    ],
    "sg:phone":"+1 606 789 2499",
    "sg:postcode":"41240",
    "sg:province":"KY",
    "sg:tags":[
        "instruction",
        "music"
    ],
    "wof:name":"Mel-O-Dee Music",
    "wof:placetype":"venue"
},
  "geometry": {"coordinates":[-82.78642000000001,37.817085],"type":"Point"}
}