{
  "type": "Feature",
  "properties": {
    "iso:country":"US",
    "sg:address":"1141 Dixie Hwy N",
    "sg:city":"Radcliff",
    "sg:classifiers":[
        {
            "category":"Personal",
            "subcategory":"Beauty Salon",
            "type":"Services"
        }
    ],
    "sg:phone":"+1 270 351 5555",
    "sg:postcode":"40160",
    "sg:province":"KY",
    "wof:name":"A Tressa Rice Co",
    "wof:placetype":"venue"
},
  "geometry": {"coordinates":[-85.949844,37.852177],"type":"Point"}
}