{
  "type": "Feature",
  "properties": {
    "iso:country":"US",
    "sg:address":"1371 Bardstown Rd",
    "sg:city":"Louisville",
    "sg:classifiers":[
        {
            "category":"Shopping",
            "subcategory":"Used Merchandise",
            "type":"Retail Goods"
        }
    ],
    "sg:phone":"+1 502 456 6123",
    "sg:postcode":"40204",
    "sg:province":"KY",
    "sg:tags":[
        "clothing"
    ],
    "wof:name":"Cherry Bomb",
    "wof:placetype":"venue"
},
  "geometry": {"coordinates":[-85.712597,38.233936],"type":"Point"}
}