{
  "type": "Feature",
  "properties": {
    "iso:country":"US",
    "sg:address":"4500 Abbott Grove Pl",
    "sg:city":"Crestwood",
    "sg:classifiers":[
        {
            "category":"Professional",
            "subcategory":"Business Services",
            "type":"Services"
        }
    ],
    "sg:phone":"+1 502 243 0357",
    "sg:postcode":"40014",
    "sg:province":"KY",
    "wof:name":"Check Express Inc",
    "wof:placetype":"venue"
},
  "geometry": {"coordinates":[-85.434623,38.311952],"type":"Point"}
}