{
  "type": "Feature",
  "properties": {
    "iso:country":"US",
    "sg:address":"2107 Sandersville Rd",
    "sg:city":"Lexington",
    "sg:classifiers":[
        {
            "category":"Manufacturing",
            "subcategory":"Retail Goods",
            "type":"Manufacturing & Wholesale Goods"
        }
    ],
    "sg:phone":"+1 859 252 0613",
    "sg:postcode":"40511",
    "sg:province":"KY",
    "sg:tags":[
        "manufacturer"
    ],
    "wof:name":"Tema Isenmann Inc",
    "wof:placetype":"venue"
},
  "geometry": {"coordinates":[-84.514988,38.086209],"type":"Point"}
}