{
  "type": "Feature",
  "properties": {
    "iso:country":"US",
    "sg:address":"7 Main St",
    "sg:city":"Cadiz",
    "sg:classifiers":[
        {
            "category":"Personal",
            "subcategory":"Beauty Salon",
            "type":"Services"
        }
    ],
    "sg:phone":"+1 270 522 4247",
    "sg:postcode":"42211",
    "sg:province":"KY",
    "wof:name":"Lynn's Hair Studio",
    "wof:placetype":"venue"
},
  "geometry": {"coordinates":[-87.83833,36.861177],"type":"Point"}
}