{
  "type": "Feature",
  "properties": {
    "iso:country":"US",
    "sg:address":"306 Clifty Ave",
    "sg:city":"Clarkson",
    "sg:classifiers":[
        {
            "category":"Organizations",
            "subcategory":"Religious Organization",
            "type":"Services"
        }
    ],
    "sg:phone":"+1 270 242 4414",
    "sg:postcode":"42726",
    "sg:province":"KY",
    "wof:name":"Saint Elizabeth Church",
    "wof:placetype":"venue"
},
  "geometry": {"coordinates":[-86.21885399999999,37.498975],"type":"Point"}
}