{
  "type": "Feature",
  "properties": {
    "iso:country":"US",
    "sg:address":"406 Garden Ct",
    "sg:city":"Simpsonville",
    "sg:classifiers":[
        {
            "category":"Professional",
            "subcategory":"Engineering",
            "type":"Services"
        }
    ],
    "sg:phone":"+1 502 722 0647",
    "sg:postcode":"40067",
    "sg:province":"KY",
    "sg:tags":[
        "engineer"
    ],
    "wof:name":"Rockaway Consulting Inc",
    "wof:placetype":"venue"
},
  "geometry": {"coordinates":[-85.35623,38.219124],"type":"Point"}
}