{
  "type": "Feature",
  "properties": {
    "iso:country":"US",
    "sg:address":"108 N Main St",
    "sg:city":"Somerset",
    "sg:classifiers":[
        {
            "category":"Professional",
            "subcategory":"Lawyer & Legal Services",
            "type":"Services"
        }
    ],
    "sg:phone":"+1 606 679 1198",
    "sg:postcode":"42501",
    "sg:province":"KY",
    "sg:tags":[
        "attorney"
    ],
    "wof:name":"Jeffrey S Lawless",
    "wof:placetype":"venue"
},
  "geometry": {"coordinates":[-84.60487999999999,37.092426],"type":"Point"}
}