{
  "type": "Feature",
  "properties": {
    "iso:country":"US",
    "sg:address":"3794 Lexington Rd",
    "sg:city":"Louisville",
    "sg:classifiers":[
        {
            "category":"Banks & Credit Unions",
            "subcategory":"Bank",
            "type":"Services"
        }
    ],
    "sg:phone":"+1 502 625 2280",
    "sg:postcode":"40207",
    "sg:province":"KY",
    "wof:name":"Stock Yards Bank & Trust Co",
    "wof:placetype":"venue"
},
  "geometry": {"coordinates":[-85.658546,38.252361],"type":"Point"}
}