{
  "type": "Feature",
  "properties": {
    "addr:full":"3361 US Hwy 60 Morganfield KY 42437",
    "addr:housenumber":"3361",
    "addr:postcode":"42437",
    "addr:street":"Us Hwy 60",
    "iso:country":"US",
    "sg:address":"3361 US Hwy 60",
    "sg:city":"Morganfield",
    "sg:classifiers":[
        {
            "category":"Manufacturing",
            "subcategory":"Glass & Minerals",
            "type":"Manufacturing & Wholesale Goods"
        }
    ],
    "sg:phone":"+1 270 389 2686",
    "sg:postcode":"42437",
    "sg:province":"KY",
    "sg:tags":[
        "ready"
    ],
    "wof:name":"Irving Materials Inc",
    "wof:placetype":"venue"
},
  "geometry": {"coordinates":[-87.94581700000001,37.64429],"type":"Point"}
}