{
  "type": "Feature",
  "properties": {
    "addr:full":"526 Frederica St Owensboro KY 42301",
    "addr:housenumber":"526",
    "addr:postcode":"42301",
    "addr:street":"Frederica St",
    "iso:country":"US",
    "sg:address":"526 Frederica St",
    "sg:city":"Owensboro",
    "sg:classifiers":[
        {
            "category":"Retail",
            "subcategory":"Portrait Studio",
            "type":"Services"
        }
    ],
    "sg:phone":"+1 270 926 6312",
    "sg:postcode":"42301",
    "sg:province":"KY",
    "sg:tags":[
        "photographer"
    ],
    "wof:name":"Image Photography",
    "wof:placetype":"venue"
},
  "geometry": {"coordinates":[-87.11318799999999,37.77003],"type":"Point"}
}