{
  "type": "Feature",
  "properties": {
    "addr:full":"8025 Dream St Florence KY 41042",
    "addr:housenumber":"8025",
    "addr:postcode":"41042",
    "addr:street":"Dream St",
    "iso:country":"US",
    "sg:address":"8025 Dream St",
    "sg:city":"Florence",
    "sg:classifiers":[
        {
            "category":"Social Services",
            "subcategory":"Child Care",
            "type":"Services"
        }
    ],
    "sg:phone":"+1 859 371 9078",
    "sg:postcode":"41042",
    "sg:province":"KY",
    "sg:tags":[
        "day"
    ],
    "sg:website":"www.biedermaneducationalcenters.com",
    "wof:name":"Biederman Educational Centers",
    "wof:placetype":"venue"
},
  "geometry": {"coordinates":[-84.64250199999999,38.990799],"type":"Point"}
}