{
  "type": "Feature",
  "properties": {
    "iso:country":"US",
    "sg:address":"500 Cumberland Way",
    "sg:city":"Campbellsville",
    "sg:classifiers":[
        {
            "category":"Organizations",
            "subcategory":"Religious Organization",
            "type":"Services"
        }
    ],
    "sg:phone":"+1 270 465 4091",
    "sg:postcode":"42718",
    "sg:province":"KY",
    "sg:tags":[
        "church"
    ],
    "wof:name":"First Cumberland Presbyterian",
    "wof:placetype":"venue"
},
  "geometry": {"coordinates":[-85.328897,37.356913],"type":"Point"}
}