{
  "type": "Feature",
  "properties": {
    "iso:country":"US",
    "sg:address":"2201 Regency Rd",
    "sg:city":"Lexington",
    "sg:classifiers":[
        {
            "category":"Professional",
            "type":"Services"
        }
    ],
    "sg:phone":"+1 859 277 9223",
    "sg:postcode":"40503",
    "sg:province":"KY",
    "sg:tags":[
        "establishment"
    ],
    "wof:name":"Labcorp",
    "wof:placetype":"venue"
},
  "geometry": {"coordinates":[-84.524694,38.008041],"type":"Point"}
}