{
  "type": "Feature",
  "properties": {
    "iso:country":"US",
    "sg:address":"1125 N Adams St",
    "sg:city":"Sturgis",
    "sg:classifiers":[
        {
            "category":"Personal",
            "subcategory":"Beauty Salon",
            "type":"Services"
        }
    ],
    "sg:phone":"+1 270 333 2398",
    "sg:postcode":"42459",
    "sg:province":"KY",
    "sg:tags":[
        "shop"
    ],
    "wof:name":"Gillie's Town Shop",
    "wof:placetype":"venue"
},
  "geometry": {"coordinates":[-87.983797,37.55212],"type":"Point"}
}