{
  "type": "Feature",
  "properties": {
    "iso:country":"US",
    "sg:address":"209 N 12th St",
    "sg:city":"Murray",
    "sg:classifiers":[
        {
            "category":"Shopping",
            "subcategory":"Clothing, Apparel, & Fashions",
            "type":"Retail Goods"
        }
    ],
    "sg:phone":"+1 270 753 7534",
    "sg:postcode":"42071",
    "sg:province":"KY",
    "sg:tags":[
        "baby",
        "accessory"
    ],
    "wof:name":"Babies In Bloom",
    "wof:placetype":"venue"
},
  "geometry": {"coordinates":[-88.315241,36.613851],"type":"Point"}
}