{
  "type": "Feature",
  "properties": {
    "addr:full":"1315 Larchmont Ave Louisville KY 40215",
    "addr:housenumber":"1315",
    "addr:postcode":"40215",
    "addr:street":"Larchmont Ave",
    "iso:country":"US",
    "sg:address":"1315 Larchmont Ave",
    "sg:city":"Louisville",
    "sg:classifiers":[
        {
            "category":"Professional",
            "subcategory":"Printing & Photocopies",
            "type":"Services"
        }
    ],
    "sg:phone":"+1 502 634 5852",
    "sg:postcode":"40215",
    "sg:province":"KY",
    "sg:tags":[
        "lithographer"
    ],
    "wof:name":"Cyber Print Text",
    "wof:placetype":"venue"
},
  "geometry": {"coordinates":[-85.780033,38.209363],"type":"Point"}
}