{
  "type": "Feature",
  "properties": {
    "iso:country":"US",
    "sg:address":"1595 Highway 1157",
    "sg:city":"Lebanon",
    "sg:classifiers":[
        {
            "category":"Government",
            "subcategory":"Office",
            "type":"Public Place"
        }
    ],
    "sg:phone":"+1 270 692 4320",
    "sg:postcode":"40033",
    "sg:province":"KY",
    "wof:name":"Joseph Sherman Lee",
    "wof:placetype":"venue"
},
  "geometry": {"coordinates":[-85.231841,37.494352],"type":"Point"}
}