{
  "type": "Feature",
  "properties": {
    "iso:country":"US",
    "sg:address":"114 Loy St",
    "sg:city":"Versailles",
    "sg:classifiers":[
        {
            "category":"Building & Trades",
            "subcategory":"Construction",
            "type":"Services"
        }
    ],
    "sg:phone":"+1 859 873 1684",
    "sg:postcode":"40383",
    "sg:province":"KY",
    "sg:tags":[
        "painter"
    ],
    "wof:name":"Dave Edwards Painting",
    "wof:placetype":"venue"
},
  "geometry": {"coordinates":[-84.731516,38.064854],"type":"Point"}
}