{
  "type": "Feature",
  "properties": {
    "addr:full":"149 Newman Ave Fort Thomas KY 41075",
    "addr:housenumber":"149",
    "addr:postcode":"41075",
    "addr:street":"Newman Ave",
    "iso:country":"US",
    "sg:address":"149 Newman Ave",
    "sg:city":"Fort Thomas",
    "sg:classifiers":[
        {
            "category":"Building & Trades",
            "subcategory":"Plumbing",
            "type":"Services"
        }
    ],
    "sg:phone":"+1 859 441 5700",
    "sg:postcode":"41075",
    "sg:province":"KY",
    "wof:name":"Kuhnhein Dave Sewer Clng & Plumbg Repr",
    "wof:placetype":"venue"
},
  "geometry": {"coordinates":[-84.462997,39.0798],"type":"Point"}
}