{
  "type": "Feature",
  "properties": {
    "addr:full":"375 Beech Grove Rd Shepherdsville KY 40165",
    "addr:housenumber":"375",
    "addr:postcode":"40165",
    "addr:street":"Beech Grove Rd",
    "iso:country":"US",
    "sg:address":"375 Beech Grove Rd",
    "sg:city":"Shepherdsville",
    "sg:classifiers":[
        {
            "category":"Home & Garden",
            "subcategory":"Building Materials",
            "type":"Retail Goods"
        }
    ],
    "sg:phone":"+1 502 955 7725",
    "sg:postcode":"40165",
    "sg:province":"KY",
    "sg:tags":[
        "door"
    ],
    "sg:website":"www.actionoverheaddoor.com",
    "wof:name":"Action Overhead Door",
    "wof:placetype":"venue"
},
  "geometry": {"coordinates":[-85.72581099999999,37.979033],"type":"Point"}
}