{
  "type": "Feature",
  "properties": {
    "iso:country":"US",
    "sg:address":"5222 Dixie Hwy",
    "sg:city":"Shively",
    "sg:classifiers":[
        {
            "category":"Shopping",
            "subcategory":"Florist",
            "type":"Retail Goods"
        }
    ],
    "sg:phone":"+1 502 447 3641",
    "sg:postcode":"40216",
    "sg:province":"KY",
    "wof:name":"Nanz & Kraft Florists",
    "wof:placetype":"venue"
},
  "geometry": {"coordinates":[-85.83110000000001,38.163577],"type":"Point"}
}