{
  "type": "Feature",
  "properties": {
    "iso:country":"US",
    "sg:address":"4525 Countryside Dr",
    "sg:city":"Owensboro",
    "sg:classifiers":[
        {
            "category":"Manufacturing",
            "subcategory":"Tools & Machinery",
            "type":"Manufacturing & Wholesale Goods"
        }
    ],
    "sg:phone":"+1 270 686 7705",
    "sg:postcode":"42303",
    "sg:province":"KY",
    "sg:tags":[
        "surgical",
        "appliance",
        "supply"
    ],
    "wof:name":"Pall Corporation",
    "wof:placetype":"venue"
},
  "geometry": {"coordinates":[-87.02361000000001,37.740895],"type":"Point"}
}