{
  "type": "Feature",
  "properties": {
    "iso:country":"US",
    "sg:address":"6615 North Dr",
    "sg:city":"Louisville",
    "sg:classifiers":[
        {
            "category":"Organizations",
            "subcategory":"Religious Organization",
            "type":"Services"
        }
    ],
    "sg:phone":"+1 502 935 6057",
    "sg:postcode":"40272",
    "sg:province":"KY",
    "wof:name":"Soaring Eagles Fellowship",
    "wof:placetype":"venue"
},
  "geometry": {"coordinates":[-85.88648499999999,38.090303],"type":"Point"}
}