{
  "type": "Feature",
  "properties": {
    "addr:full":"521 N Mantle Ave Elizabethtown KY 42701",
    "addr:housenumber":"521",
    "addr:postcode":"42701",
    "addr:street":"N Mantle Ave",
    "iso:country":"US",
    "sg:address":"521 N Mantle Ave",
    "sg:city":"Elizabethtown",
    "sg:classifiers":[
        {
            "category":"Health Services",
            "subcategory":"Health Practitioner",
            "type":"Services"
        }
    ],
    "sg:phone":"+1 270 737 6624",
    "sg:postcode":"42701",
    "sg:province":"KY",
    "sg:tags":[
        "nurse",
        "for",
        "government"
    ],
    "wof:name":"Jerry Effner Owner",
    "wof:placetype":"venue"
},
  "geometry": {"coordinates":[-85.858217,37.708552],"type":"Point"}
}