{
  "type": "Feature",
  "properties": {
    "addr:full":"225 Al-Fan Ct Winchester KY 40391",
    "addr:housenumber":"225",
    "addr:postcode":"40391",
    "addr:street":"Al-Fan Ct",
    "iso:country":"US",
    "sg:address":"225 Al-Fan Ct",
    "sg:city":"Winchester",
    "sg:classifiers":[
        {
            "category":"Professional",
            "subcategory":"Management & Consulting",
            "type":"Services"
        }
    ],
    "sg:phone":"+1 859 744 1018",
    "sg:postcode":"40391",
    "sg:province":"KY",
    "sg:tags":[
        "business"
    ],
    "wof:name":"Studebaker Group Inc",
    "wof:placetype":"venue"
},
  "geometry": {"coordinates":[-84.196544,37.981416],"type":"Point"}
}