{
  "type": "Feature",
  "properties": {
    "iso:country":"US",
    "sg:address":"3244 Alabama St",
    "sg:city":"Paducah",
    "sg:classifiers":[
        {
            "category":"Manufacturing",
            "subcategory":"Buildings",
            "type":"Manufacturing & Wholesale Goods"
        },
        {
            "category":"Building & Trades",
            "subcategory":"Construction",
            "type":"Services"
        }
    ],
    "sg:phone":"+1 270 443 2107",
    "sg:postcode":"42003",
    "sg:province":"KY",
    "sg:tags":[
        "home",
        "builder",
        "contractor"
    ],
    "wof:name":"Skaggs Home Improvements",
    "wof:placetype":"venue"
},
  "geometry": {"coordinates":[-88.618369,37.056776],"type":"Point"}
}