{
  "type": "Feature",
  "properties": {
    "iso:country":"US",
    "sg:address":"8 Timberview Ct",
    "sg:city":"Newport",
    "sg:classifiers":[
        {
            "category":"Building & Trades",
            "subcategory":"Construction",
            "type":"Services"
        }
    ],
    "sg:phone":"+1 859 441 6080",
    "sg:postcode":"41076",
    "sg:province":"KY",
    "sg:tags":[
        "installs",
        "floor",
        "covering"
    ],
    "wof:name":"Rizzo Floor and Wallcovering",
    "wof:placetype":"venue"
},
  "geometry": {"coordinates":[-84.45827300000001,39.023013],"type":"Point"}
}