{
  "type": "Feature",
  "properties": {
    "iso:country":"US",
    "sg:address":"404 Chenoweth Ln",
    "sg:city":"Louisville",
    "sg:classifiers":[
        {
            "category":"Professional",
            "subcategory":"Management & Consulting",
            "type":"Services"
        }
    ],
    "sg:phone":"+1 502 897 9489",
    "sg:postcode":"40207",
    "sg:province":"KY",
    "sg:tags":[
        "public",
        "relations"
    ],
    "wof:name":"Salty Gardens Inc",
    "wof:placetype":"venue"
},
  "geometry": {"coordinates":[-85.66457699999999,38.263921],"type":"Point"}
}