{
  "type": "Feature",
  "properties": {
    "iso:country":"US",
    "sg:address":"10513 Mountain Ash Ln",
    "sg:city":"Prospect",
    "sg:classifiers":[
        {
            "category":"Professional",
            "subcategory":"Management & Consulting",
            "type":"Services"
        }
    ],
    "sg:phone":"+1 502 339 0426",
    "sg:postcode":"40059",
    "sg:province":"KY",
    "sg:tags":[
        "business"
    ],
    "wof:name":"Tadasana Consulting LLC",
    "wof:placetype":"venue"
},
  "geometry": {"coordinates":[-85.54920799999999,38.331346],"type":"Point"}
}