{
  "type": "Feature",
  "properties": {
    "iso:country":"US",
    "sg:address":"727 Keavy Rd",
    "sg:city":"London",
    "sg:classifiers":[
        {
            "category":"Building & Trades",
            "subcategory":"Landscaping Services",
            "type":"Services"
        }
    ],
    "sg:phone":"+1 606 864 4510",
    "sg:postcode":"40744",
    "sg:province":"KY",
    "sg:tags":[
        "landscape",
        "contractor"
    ],
    "wof:name":"James Duttlinger & Assoc",
    "wof:placetype":"venue"
},
  "geometry": {"coordinates":[-84.09054399999999,37.096992],"type":"Point"}
}