{
  "type": "Feature",
  "properties": {
    "addr:full":"1580 Neelie Webb Rd Madisonville KY 42431",
    "addr:housenumber":"1580",
    "addr:postcode":"42431",
    "addr:street":"Neelie Webb Rd",
    "iso:country":"US",
    "sg:address":"1580 Neelie Webb Rd",
    "sg:city":"Madisonville",
    "sg:classifiers":[
        {
            "category":"Utilities",
            "subcategory":"Water",
            "type":"Services"
        }
    ],
    "sg:phone":"+1 270 825 1623",
    "sg:postcode":"42431",
    "sg:province":"KY",
    "sg:tags":[
        "company",
        "sewage"
    ],
    "wof:name":"North Hopkins Water",
    "wof:placetype":"venue"
},
  "geometry": {"coordinates":[-87.39525399999999,37.352042],"type":"Point"}
}