{
  "type": "Feature",
  "properties": {
    "addr:full":"1409 Victory-Greenmont Rd London KY 40741",
    "addr:housenumber":"1409",
    "addr:postcode":"40741",
    "addr:street":"Victory-Greenmont Rd",
    "iso:country":"US",
    "sg:address":"1409 Victory-Greenmont Rd",
    "sg:city":"London",
    "sg:classifiers":[
        {
            "category":"Farming",
            "subcategory":"Livestock Farm",
            "type":"Manufacturing & Wholesale Goods"
        }
    ],
    "sg:phone":"+1 606 843 6298",
    "sg:postcode":"40741",
    "sg:province":"KY",
    "sg:tags":[
        "beef",
        "feedlot",
        "cattle"
    ],
    "wof:name":"Roy Lincks",
    "wof:placetype":"venue"
},
  "geometry": {"coordinates":[-84.05577700000001,37.251126],"type":"Point"}
}