{
  "type": "Feature",
  "properties": {
    "addr:full":"724 Time Dr Owensboro KY 42303",
    "addr:housenumber":"724",
    "addr:postcode":"42303",
    "addr:street":"Time Dr",
    "iso:country":"US",
    "sg:address":"724 Time Dr",
    "sg:city":"Owensboro",
    "sg:classifiers":[
        {
            "category":"Professional",
            "subcategory":"Accounting & Tax Preparation",
            "type":"Services"
        }
    ],
    "sg:phone":"+1 270 688 9070",
    "sg:postcode":"42303",
    "sg:province":"KY",
    "sg:tags":[
        "return",
        "filing"
    ],
    "wof:name":"Jackson Hewitt Tax Svc",
    "wof:placetype":"venue"
},
  "geometry": {"coordinates":[-87.118939,37.73047],"type":"Point"}
}