{
  "type": "Feature",
  "properties": {
    "addr:full":"547 Main St Shelbyville KY 40065",
    "addr:housenumber":"547",
    "addr:postcode":"40065",
    "addr:street":"Main St",
    "iso:country":"US",
    "sg:address":"547 Main St",
    "sg:city":"Shelbyville",
    "sg:classifiers":[
        {
            "category":"Restaurant",
            "type":"Food & Drink"
        }
    ],
    "sg:phone":"+1 502 647 7751",
    "sg:postcode":"40065",
    "sg:province":"KY",
    "sg:tags":[
        "shop",
        "coffee"
    ],
    "wof:name":"Sixth And Main Coffeehouse Inc",
    "wof:placetype":"venue"
},
  "geometry": {"coordinates":[-85.21648399999999,38.211034],"type":"Point"}
}