{
  "type": "Feature",
  "properties": {
    "iso:country":"US",
    "sg:address":"4903 Poplar Level Rd",
    "sg:city":"Okolona",
    "sg:classifiers":[
        {
            "category":"Food & Beverages",
            "subcategory":"Groceries & Convenience Stores",
            "type":"Retail Goods"
        }
    ],
    "sg:phone":"+1 502 964 5417",
    "sg:postcode":"40219",
    "sg:province":"KY",
    "wof:name":"First Stop",
    "wof:placetype":"venue"
},
  "geometry": {"coordinates":[-85.681719,38.167388],"type":"Point"}
}