{
  "type": "Feature",
  "properties": {
    "iso:country":"US",
    "sg:address":"3445 Dangerfield Rd",
    "sg:city":"Hodgenville",
    "sg:classifiers":[
        {
            "category":"Manufacturing",
            "subcategory":"Furniture",
            "type":"Manufacturing & Wholesale Goods"
        }
    ],
    "sg:phone":"+1 270 325 2863",
    "sg:postcode":"42748",
    "sg:province":"KY",
    "sg:tags":[
        "custom",
        "cabinet"
    ],
    "wof:name":"A Ky Cabinet and Furniture",
    "wof:placetype":"venue"
},
  "geometry": {"coordinates":[-85.62826,37.52482],"type":"Point"}
}