{
  "type": "Feature",
  "properties": {
    "iso:country":"US",
    "sg:address":"8710 Albany Rd",
    "sg:city":"Burkesville",
    "sg:classifiers":[
        {
            "category":"Shopping",
            "subcategory":"Computers & Home Electronics",
            "type":"Retail Goods"
        }
    ],
    "sg:phone":"+1 270 433 6110",
    "sg:postcode":"42717",
    "sg:province":"KY",
    "sg:tags":[
        "equipment",
        "electronic",
        "supply"
    ],
    "sg:website":"www.page-electronics.com",
    "wof:name":"Page Electronics",
    "wof:placetype":"venue"
},
  "geometry": {"coordinates":[-85.241111,36.769545],"type":"Point"}
}