{
  "type": "Feature",
  "properties": {
    "addr:full":"1579 Hustonville Rd Danville KY 40422",
    "addr:housenumber":"1579",
    "addr:postcode":"40422",
    "addr:street":"Hustonville Rd",
    "iso:country":"US",
    "sg:address":"1579 Hustonville Rd",
    "sg:city":"Danville",
    "sg:classifiers":[
        {
            "category":"Banks & Credit Unions",
            "subcategory":"Bank",
            "type":"Services"
        }
    ],
    "sg:phone":"+1 859 236 5676",
    "sg:postcode":"40422",
    "sg:province":"KY",
    "sg:tags":[
        "loan",
        "real estate"
    ],
    "wof:name":"Citi Financial",
    "wof:placetype":"venue"
},
  "geometry": {"coordinates":[-84.77467900000001,37.621618],"type":"Point"}
}