{
  "type": "Feature",
  "properties": {
    "iso:country":"US",
    "sg:address":"2135 Boyce Fairview Rd",
    "sg:city":"Alvaton",
    "sg:classifiers":[
        {
            "category":"Building & Trades",
            "subcategory":"Construction",
            "type":"Services"
        },
        {
            "category":"Home & Garden",
            "subcategory":"Furniture",
            "type":"Retail Goods"
        }
    ],
    "sg:phone":"+1 270 842 4093",
    "sg:postcode":"42122",
    "sg:province":"KY",
    "sg:tags":[
        "carpentry",
        "cabinet",
        "material",
        "contractor"
    ],
    "wof:name":"Ball-Old Cabinets Made New",
    "wof:placetype":"venue"
},
  "geometry": {"coordinates":[-86.35142999999999,36.844501],"type":"Point"}
}