{
  "type": "Feature",
  "properties": {
    "addr:full":"10400 Linn Station Rd Louisville KY 40223",
    "addr:housenumber":"10400",
    "addr:postcode":"40223",
    "addr:street":"Linn Station Rd",
    "iso:country":"US",
    "sg:address":"10400 Linn Station Rd",
    "sg:city":"Louisville",
    "sg:classifiers":[
        {
            "category":"Professional",
            "type":"Services"
        }
    ],
    "sg:phone":"+1 502 423 1666",
    "sg:postcode":"40223",
    "sg:province":"KY",
    "sg:tags":[
        "establishment"
    ],
    "wof:name":"World Wide Vacations",
    "wof:placetype":"venue"
},
  "geometry": {"coordinates":[-85.563766,38.224448],"type":"Point"}
}