{
  "type": "Feature",
  "properties": {
    "addr:full":"120 Hidden Woods Ct Lexington KY 40515",
    "addr:housenumber":"120",
    "addr:postcode":"40515",
    "addr:street":"Hidden Woods Ct",
    "iso:country":"US",
    "sg:address":"120 Hidden Woods Ct",
    "sg:city":"Lexington",
    "sg:classifiers":[
        {
            "category":"Shopping",
            "subcategory":"Clothing, Apparel, & Fashions",
            "type":"Retail Goods"
        }
    ],
    "sg:phone":"+1 859 227 4942",
    "sg:postcode":"40515",
    "sg:province":"KY",
    "wof:name":"Brides Assistant",
    "wof:placetype":"venue"
},
  "geometry": {"coordinates":[-84.530908,37.967163],"type":"Point"}
}