{
  "type": "Feature",
  "properties": {
    "iso:country":"US",
    "sg:address":"3235 Vermont Ave",
    "sg:city":"Louisville",
    "sg:classifiers":[
        {
            "category":"Retail",
            "subcategory":"Auto Repair",
            "type":"Services"
        }
    ],
    "sg:phone":"+1 502 774 1229",
    "sg:postcode":"40211",
    "sg:province":"KY",
    "sg:tags":[
        "repairing",
        "automobile"
    ],
    "wof:name":"Harris Auto Repair Shop",
    "wof:placetype":"venue"
},
  "geometry": {"coordinates":[-85.807018,38.255581],"type":"Point"}
}