{
  "type": "Feature",
  "properties": {
    "iso:country":"US",
    "sg:address":"201 E Main St",
    "sg:city":"Georgetown",
    "sg:classifiers":[
        {
            "category":"Restaurant",
            "type":"Food & Drink"
        }
    ],
    "sg:phone":"+1 502 867 1972",
    "sg:postcode":"40324",
    "sg:province":"KY",
    "sg:tags":[
        "eating"
    ],
    "wof:name":"Lock & Key",
    "wof:placetype":"venue"
},
  "geometry": {"coordinates":[-84.55807299999999,38.209855],"type":"Point"}
}