{
  "type": "Feature",
  "properties": {
    "iso:country":"US",
    "sg:address":"3801 Bardstown Rd",
    "sg:city":"Louisville",
    "sg:classifiers":[
        {
            "category":"Health Services",
            "subcategory":"Doctor",
            "type":"Services"
        }
    ],
    "sg:phone":"+1 502 458 5292",
    "sg:postcode":"40218",
    "sg:province":"KY",
    "sg:tags":[
        "dentist"
    ],
    "wof:name":"Timothy J Wahl DDS",
    "wof:placetype":"venue"
},
  "geometry": {"coordinates":[-85.65389999999999,38.195721],"type":"Point"}
}