{
  "type": "Feature",
  "properties": {
    "iso:country":"US",
    "sg:address":"209 Northbrook Rd",
    "sg:city":"Nicholasville",
    "sg:classifiers":[
        {
            "category":"Building & Trades",
            "subcategory":"Cleaning & Sanitation",
            "type":"Services"
        }
    ],
    "sg:phone":"+1 859 885 9776",
    "sg:postcode":"40356",
    "sg:province":"KY",
    "sg:tags":[
        "maintenance"
    ],
    "wof:name":"Carl Carson",
    "wof:placetype":"venue"
},
  "geometry": {"coordinates":[-84.58114500000001,37.854457],"type":"Point"}
}