{
  "type": "Feature",
  "properties": {
    "iso:country":"US",
    "sg:address":"2915 Warehouse Rd",
    "sg:city":"Owensboro",
    "sg:classifiers":[
        {
            "category":"Freight",
            "type":"Transportation"
        }
    ],
    "sg:phone":"+1 270 685 9988",
    "sg:postcode":"42301",
    "sg:province":"KY",
    "sg:tags":[
        "trucking"
    ],
    "wof:name":"Alco Transportation",
    "wof:placetype":"venue"
},
  "geometry": {"coordinates":[-87.144825,37.782976],"type":"Point"}
}