{
  "type": "Feature",
  "properties": {
    "iso:country":"US",
    "sg:address":"616 Mount Zion Rd",
    "sg:city":"Fountain Run",
    "sg:classifiers":[
        {
            "category":"Farming",
            "subcategory":"Farm",
            "type":"Manufacturing & Wholesale Goods"
        }
    ],
    "sg:phone":"+1 270 434 4464",
    "sg:postcode":"42101",
    "sg:province":"KY",
    "wof:name":"Dixieland Farm",
    "wof:placetype":"venue"
},
  "geometry": {"coordinates":[-86.49165600000001,37.093624],"type":"Point"}
}