{
  "type": "Feature",
  "properties": {
    "iso:country":"US",
    "sg:address":"1561 Versailles Rd",
    "sg:city":"Frankfort",
    "sg:classifiers":[
        {
            "category":"Wholesale",
            "subcategory":"Motor Vehicles",
            "type":"Manufacturing & Wholesale Goods"
        }
    ],
    "sg:phone":"+1 502 695 4546",
    "sg:postcode":"40601",
    "sg:province":"KY",
    "sg:tags":[
        "automobile",
        "used"
    ],
    "wof:name":"Day B E & Sons Auto Sales",
    "wof:placetype":"venue"
},
  "geometry": {"coordinates":[-84.814611,38.178986],"type":"Point"}
}