{
  "type": "Feature",
  "properties": {
    "iso:country":"US",
    "sg:address":"1725 Larkmoor Ln",
    "sg:city":"Louisville",
    "sg:classifiers":[
        {
            "category":"Communications",
            "subcategory":"Film & Video Production",
            "type":"Services"
        }
    ],
    "sg:phone":"+1 502 459 2935",
    "sg:postcode":"40218",
    "sg:province":"KY",
    "sg:tags":[
        "motion"
    ],
    "wof:name":"Kyle Thatch Studios",
    "wof:placetype":"venue"
},
  "geometry": {"coordinates":[-85.68176800000001,38.196477],"type":"Point"}
}