{
  "type": "Feature",
  "properties": {
    "addr:full":"4100 US Hwy 60 Morganfield KY 42437",
    "addr:housenumber":"4100",
    "addr:postcode":"42437",
    "addr:street":"Us Hwy 60",
    "iso:country":"US",
    "sg:address":"4100 US Hwy 60",
    "sg:city":"Morganfield",
    "sg:classifiers":[
        {
            "category":"Retail",
            "subcategory":"Repair Shop",
            "type":"Services"
        }
    ],
    "sg:phone":"+1 270 389 3535",
    "sg:postcode":"42437",
    "sg:province":"KY",
    "sg:tags":[
        "welding"
    ],
    "wof:name":"Free Form Fabrication",
    "wof:placetype":"venue"
},
  "geometry": {"coordinates":[-87.941749,37.633557],"type":"Point"}
}