{
  "type": "Feature",
  "properties": {
    "addr:full":"210 S Main St Elizabethtown KY 42701",
    "addr:housenumber":"210",
    "addr:postcode":"42701",
    "addr:street":"S Main St",
    "iso:country":"US",
    "sg:address":"210 S Main St",
    "sg:city":"Elizabethtown",
    "sg:classifiers":[
        {
            "category":"Building & Trades",
            "subcategory":"Electrical",
            "type":"Services"
        }
    ],
    "sg:phone":"+1 270 765 7886",
    "sg:postcode":"42701",
    "sg:province":"KY",
    "sg:tags":[
        "electric",
        "contractor"
    ],
    "wof:name":"Peters Electric Inc",
    "wof:placetype":"venue"
},
  "geometry": {"coordinates":[-85.85950099999999,37.691526],"type":"Point"}
}