{
  "type": "Feature",
  "properties": {
    "addr:full":"2125 W 2nd St Owensboro KY 42301",
    "addr:housenumber":"2125",
    "addr:postcode":"42301",
    "addr:street":"W 2Nd St",
    "iso:country":"US",
    "sg:address":"2125 W 2nd St",
    "sg:city":"Owensboro",
    "sg:classifiers":[
        {
            "category":"Autos & Motor Vehicles",
            "subcategory":"Fuel & Gas Station",
            "type":"Retail Goods"
        }
    ],
    "sg:phone":"+1 270 685 3967",
    "sg:postcode":"42301",
    "sg:province":"KY",
    "sg:tags":[
        "oil"
    ],
    "wof:name":"West End Shell",
    "wof:placetype":"venue"
},
  "geometry": {"coordinates":[-87.137135,37.773531],"type":"Point"}
}