{
  "type": "Feature",
  "properties": {
    "iso:country":"US",
    "sg:address":"2230 Thurman Dr",
    "sg:city":"Louisville",
    "sg:classifiers":[
        {
            "category":"Home & Garden",
            "subcategory":"Building Materials",
            "type":"Retail Goods"
        }
    ],
    "sg:phone":"+1 502 448 8244",
    "sg:postcode":"40216",
    "sg:province":"KY",
    "sg:tags":[
        "windows"
    ],
    "wof:name":"A T Remodeling",
    "wof:placetype":"venue"
},
  "geometry": {"coordinates":[-85.82158699999999,38.198576],"type":"Point"}
}