{
  "type": "Feature",
  "properties": {
    "iso:country":"US",
    "sg:address":"5554 State Hwy 764",
    "sg:city":"Whitesville",
    "sg:classifiers":[
        {
            "category":"Personal",
            "subcategory":"Beauty Salon",
            "type":"Services"
        }
    ],
    "sg:phone":"+1 270 275 4718",
    "sg:postcode":"42378",
    "sg:province":"KY",
    "wof:name":"Kuntry KURL",
    "wof:placetype":"venue"
},
  "geometry": {"coordinates":[-86.953034,37.592304],"type":"Point"}
}