{
  "type": "Feature",
  "properties": {
    "iso:country":"US",
    "sg:address":"RR 18",
    "sg:city":"Florence",
    "sg:classifiers":[
        {
            "category":"Autos & Motor Vehicles",
            "subcategory":"Automobile Sales",
            "type":"Retail Goods"
        }
    ],
    "sg:phone":"+1 859 371 1818",
    "sg:postcode":"41042",
    "sg:province":"KY",
    "sg:tags":[
        "car"
    ],
    "wof:name":"Jake Sweeney Automotive",
    "wof:placetype":"venue"
},
  "geometry": {"coordinates":[-84.65389999999999,38.9879],"type":"Point"}
}