{
  "type": "Feature",
  "properties": {
    "addr:full":"193 Kentucky Ave Lexington KY 40502",
    "addr:housenumber":"193",
    "addr:postcode":"40502",
    "addr:street":"Kentucky Ave",
    "iso:country":"US",
    "sg:address":"193 Kentucky Ave",
    "sg:city":"Lexington",
    "sg:classifiers":[
        {
            "category":"Professional",
            "subcategory":"Business Services",
            "type":"Services"
        }
    ],
    "sg:phone":"+1 859 252 5210",
    "sg:postcode":"40502",
    "sg:province":"KY",
    "sg:tags":[
        "interior",
        "consultant",
        "design",
        "decorator"
    ],
    "wof:name":"Mary Jane Nuckols Interiors",
    "wof:placetype":"venue"
},
  "geometry": {"coordinates":[-84.49136799999999,38.036647],"type":"Point"}
}