{
  "type": "Feature",
  "properties": {
    "iso:country":"US",
    "sg:address":"2505 Highland Ave",
    "sg:city":"Carrollton",
    "sg:classifiers":[
        {
            "category":"Organizations",
            "subcategory":"Religious Organization",
            "type":"Services"
        }
    ],
    "sg:phone":"+1 502 732 4132",
    "sg:postcode":"41008",
    "sg:province":"KY",
    "sg:tags":[
        "church"
    ],
    "wof:name":"United Pentecostal Church",
    "wof:placetype":"venue"
},
  "geometry": {"coordinates":[-85.139518,38.692484],"type":"Point"}
}