{
  "type": "Feature",
  "properties": {
    "iso:country":"US",
    "sg:address":"3418 Frankfort Ave",
    "sg:city":"Louisville",
    "sg:classifiers":[
        {
            "category":"Banks & Credit Unions",
            "subcategory":"Bank",
            "type":"Services"
        }
    ],
    "sg:phone":"+1 502 899 9242",
    "sg:postcode":"40207",
    "sg:province":"KY",
    "sg:tags":[
        "loan",
        "real estate"
    ],
    "wof:name":"CFIC Home Mortgage",
    "wof:placetype":"venue"
},
  "geometry": {"coordinates":[-85.667046,38.253731],"type":"Point"}
}