{
  "type": "Feature",
  "properties": {
    "addr:full":"1298 Rogersville Rd Radcliff KY 40160",
    "addr:housenumber":"1298",
    "addr:postcode":"40160",
    "addr:street":"Rogersville Rd",
    "iso:country":"US",
    "sg:address":"1298 Rogersville Rd",
    "sg:city":"Radcliff",
    "sg:classifiers":[
        {
            "category":"Education",
            "subcategory":"School",
            "type":"Public Place"
        }
    ],
    "sg:phone":"+1 270 351 7707",
    "sg:postcode":"40160",
    "sg:province":"KY",
    "wof:name":"North Hardin Christian School",
    "wof:placetype":"venue"
},
  "geometry": {"coordinates":[-85.95197400000001,37.807893],"type":"Point"}
}