{
  "type": "Feature",
  "properties": {
    "iso:country":"US",
    "sg:address":"211 Pike St Ste 3",
    "sg:city":"Covington",
    "sg:classifiers":[
        {
            "category":"Professional",
            "subcategory":"Accounting & Tax Preparation",
            "type":"Services"
        }
    ],
    "sg:phone":"+1 859 261 2795",
    "sg:postcode":"41011",
    "sg:province":"KY",
    "sg:tags":[
        "bookkeeping",
        "return",
        "billing",
        "preparation-business"
    ],
    "wof:name":"Weyer's Tax & Bookpg",
    "wof:placetype":"venue"
},
  "geometry": {"coordinates":[-84.513437,39.082254],"type":"Point"}
}