{
  "type": "Feature",
  "properties": {
    "iso:country":"US",
    "sg:address":"102 Fieldview Dr",
    "sg:city":"Versailles",
    "sg:classifiers":[
        {
            "category":"Shopping",
            "subcategory":"Bicycles & Sporting Goods",
            "type":"Retail Goods"
        }
    ],
    "sg:phone":"+1 859 873 2352",
    "sg:postcode":"40383",
    "sg:province":"KY",
    "sg:tags":[
        "gun",
        "gunsmith"
    ],
    "sg:website":"www.centerfiresystems.com",
    "wof:name":"Centerfire Systems",
    "wof:placetype":"venue"
},
  "geometry": {"coordinates":[-84.717353,38.06295],"type":"Point"}
}