{
  "type": "Feature",
  "properties": {
    "addr:full":"111 Montgomery Ave Providence KY 42450",
    "addr:housenumber":"111",
    "addr:postcode":"42450",
    "addr:street":"Montgomery Ave",
    "iso:country":"US",
    "sg:address":"111 Montgomery Ave",
    "sg:city":"Providence",
    "sg:classifiers":[
        {
            "category":"Food & Beverages",
            "subcategory":"Groceries & Convenience Stores",
            "type":"Retail Goods"
        }
    ],
    "sg:phone":"+1 270 667 7836",
    "sg:postcode":"42450",
    "sg:province":"KY",
    "sg:tags":[
        "grocer"
    ],
    "wof:name":"Save-A-Lot",
    "wof:placetype":"venue"
},
  "geometry": {"coordinates":[-87.757048,37.39951],"type":"Point"}
}