{
  "type": "Feature",
  "properties": {
    "addr:full":"209 Sutton Ln Owensboro KY 42301",
    "addr:housenumber":"209",
    "addr:postcode":"42301",
    "addr:street":"Sutton Ln",
    "iso:country":"US",
    "sg:address":"209 Sutton Ln",
    "sg:city":"Owensboro",
    "sg:classifiers":[
        {
            "category":"Wholesale",
            "subcategory":"Hardware",
            "type":"Manufacturing & Wholesale Goods"
        }
    ],
    "sg:phone":"+1 270 685 5900",
    "sg:postcode":"42301",
    "sg:province":"KY",
    "sg:tags":[
        "plumbing",
        "fixture",
        "supply"
    ],
    "wof:name":"Frank's Plumbing & Heating",
    "wof:placetype":"venue"
},
  "geometry": {"coordinates":[-87.139842,37.772222],"type":"Point"}
}