{
  "type": "Feature",
  "properties": {
    "addr:full":"574 Buckingham Ln Lexington KY 40503",
    "addr:housenumber":"574",
    "addr:postcode":"40503",
    "addr:street":"Buckingham Ln",
    "iso:country":"US",
    "sg:address":"574 Buckingham Ln",
    "sg:city":"Lexington",
    "sg:classifiers":[
        {
            "category":"Insurance",
            "subcategory":"Insurance Agent",
            "type":"Services"
        }
    ],
    "sg:phone":"+1 859 223 7050",
    "sg:postcode":"40503",
    "sg:province":"KY",
    "sg:tags":[
        "consulting",
        "management"
    ],
    "wof:name":"Group Benefit Services",
    "wof:placetype":"venue"
},
  "geometry": {"coordinates":[-84.546852,38.003304],"type":"Point"}
}