{
  "type": "Feature",
  "properties": {
    "addr:full":"104 N 15th St Murray KY 42071",
    "addr:housenumber":"104",
    "addr:postcode":"42071",
    "addr:street":"N 15Th St",
    "iso:country":"US",
    "sg:address":"104 N 15th St",
    "sg:city":"Murray",
    "sg:classifiers":[
        {
            "category":"Manufacturing",
            "subcategory":"Printing",
            "type":"Manufacturing & Wholesale Goods"
        }
    ],
    "sg:phone":"+1 270 759 4180",
    "sg:postcode":"42071",
    "sg:province":"KY",
    "sg:tags":[
        "screen"
    ],
    "wof:name":"Zax Imprinted Sportswear",
    "wof:placetype":"venue"
},
  "geometry": {"coordinates":[-88.32174500000001,36.610194],"type":"Point"}
}