{
  "type": "Feature",
  "properties": {
    "iso:country":"US",
    "sg:address":"221 W John Rowan Blvd",
    "sg:city":"Bardstown",
    "sg:classifiers":[
        {
            "category":"Retail",
            "subcategory":"Laundry & Dry Cleaning",
            "type":"Services"
        }
    ],
    "sg:phone":"+1 502 348 8138",
    "sg:postcode":"40004",
    "sg:province":"KY",
    "wof:name":"Bluegrass Alterations Inc",
    "wof:placetype":"venue"
},
  "geometry": {"coordinates":[-85.471789,37.828154],"type":"Point"}
}