{
  "type": "Feature",
  "properties": {
    "iso:country":"US",
    "sg:address":"427 E Broadway St",
    "sg:city":"Mayfield",
    "sg:classifiers":[
        {
            "category":"Social Services",
            "type":"Services"
        }
    ],
    "sg:phone":"+1 270 251 2060",
    "sg:postcode":"42066",
    "sg:province":"KY",
    "sg:tags":[
        "organization",
        "welfare"
    ],
    "wof:name":"Mayfield Graves County Child",
    "wof:placetype":"venue"
},
  "geometry": {"coordinates":[-88.632289,36.741697],"type":"Point"}
}