{
  "type": "Feature",
  "properties": {
    "addr:full":"852 S 5th St Louisville KY 40203",
    "addr:housenumber":"852",
    "addr:postcode":"40203",
    "addr:street":"S 5Th St",
    "iso:country":"US",
    "sg:address":"852 S 5th St",
    "sg:city":"Louisville",
    "sg:classifiers":[
        {
            "category":"Professional",
            "subcategory":"Detective & Security Services",
            "type":"Services"
        }
    ],
    "sg:phone":"+1 502 595 6010",
    "sg:postcode":"40203",
    "sg:province":"KY",
    "sg:tags":[
        "guard",
        "patrol"
    ],
    "wof:name":"Special Peace Officers & Assoc",
    "wof:placetype":"venue"
},
  "geometry": {"coordinates":[-85.760633,38.243296],"type":"Point"}
}