{
  "type": "Feature",
  "properties": {
    "iso:country":"US",
    "sg:address":"1931 Caldwell Chapel Rd",
    "sg:city":"Princeton",
    "sg:classifiers":[
        {
            "category":"Real Estate",
            "subcategory":"Real Estate Agent",
            "type":"Services"
        }
    ],
    "sg:phone":"+1 270 365 3041",
    "sg:postcode":"42445",
    "sg:province":"KY",
    "wof:name":"Steven L Tays",
    "wof:placetype":"venue"
},
  "geometry": {"coordinates":[-87.964669,37.057046],"type":"Point"}
}