{
  "type": "Feature",
  "properties": {
    "addr:full":"903 Cross St Albany KY 42602",
    "addr:housenumber":"903",
    "addr:postcode":"42602",
    "addr:street":"Cross St",
    "iso:country":"US",
    "sg:address":"903 Cross St",
    "sg:city":"Albany",
    "sg:classifiers":[
        {
            "category":"Shopping",
            "subcategory":"Clothing, Apparel, & Fashions",
            "type":"Retail Goods"
        }
    ],
    "sg:phone":"+1 606 387 0457",
    "sg:postcode":"42602",
    "sg:province":"KY",
    "wof:name":"Maynord Thrifty Clothing II",
    "wof:placetype":"venue"
},
  "geometry": {"coordinates":[-85.135408,36.698899],"type":"Point"}
}