{
  "type": "Feature",
  "properties": {
    "addr:full":"807 Taylorsville Rd Shelbyville KY 40065",
    "addr:housenumber":"807",
    "addr:postcode":"40065",
    "addr:street":"Taylorsville Rd",
    "iso:country":"US",
    "sg:address":"807 Taylorsville Rd",
    "sg:city":"Shelbyville",
    "sg:classifiers":[
        {
            "category":"Professional",
            "subcategory":"Computer Services",
            "type":"Services"
        }
    ],
    "sg:phone":"+1 502 633 7484",
    "sg:postcode":"40065",
    "sg:province":"KY",
    "sg:tags":[
        "repair"
    ],
    "sg:website":"www.faubush.com",
    "wof:name":"On-Site Kentucky Inc",
    "wof:placetype":"venue"
},
  "geometry": {"coordinates":[-85.277372,38.18813],"type":"Point"}
}