{
  "type": "Feature",
  "properties": {
    "iso:country":"US",
    "sg:address":"1509 Beaver Dam Church Rd",
    "sg:city":"Brownsville",
    "sg:classifiers":[
        {
            "category":"Personal",
            "subcategory":"Barber",
            "type":"Services"
        }
    ],
    "sg:phone":"+1 270 597 3348",
    "sg:postcode":"42210",
    "sg:province":"KY",
    "sg:tags":[
        "shop"
    ],
    "wof:name":"Judys Barber Shop",
    "wof:placetype":"venue"
},
  "geometry": {"coordinates":[-86.217017,37.141122],"type":"Point"}
}