{
  "type": "Feature",
  "properties": {
    "addr:full":"473 E Main St Lexington KY 40507",
    "addr:housenumber":"473",
    "addr:postcode":"40507",
    "addr:street":"E Main St",
    "iso:country":"US",
    "sg:address":"473 E Main St",
    "sg:city":"Lexington",
    "sg:classifiers":[
        {
            "category":"Restaurant",
            "type":"Food & Drink"
        }
    ],
    "sg:phone":"+1 859 253 4993",
    "sg:postcode":"40507",
    "sg:province":"KY",
    "wof:name":"Juan Gomez Restaurant",
    "wof:placetype":"venue"
},
  "geometry": {"coordinates":[-84.489411,38.039812],"type":"Point"}
}