{
  "type": "Feature",
  "properties": {
    "iso:country":"US",
    "sg:address":"112 Cane Run Rd",
    "sg:city":"Stanford",
    "sg:classifiers":[
        {
            "category":"Shopping",
            "subcategory":"Department Store",
            "type":"Retail Goods"
        }
    ],
    "sg:phone":"+1 606 365 7279",
    "sg:postcode":"40484",
    "sg:province":"KY",
    "sg:tags":[
        "shop"
    ],
    "wof:name":"Dollar General",
    "wof:placetype":"venue"
},
  "geometry": {"coordinates":[-84.672572,37.547044],"type":"Point"}
}