{
  "type": "Feature",
  "properties": {
    "addr:full":"307 Beaver Junction-Dwale Rd Dwale KY 41621",
    "addr:housenumber":"307",
    "addr:postcode":"41621",
    "addr:street":"Beaver Junction-Dwale Rd",
    "iso:country":"US",
    "sg:address":"307 Beaver Junction-Dwale Rd",
    "sg:city":"Dwale",
    "sg:classifiers":[
        {
            "category":"Government",
            "subcategory":"Post Office",
            "type":"Public Place"
        }
    ],
    "sg:phone":"+1 606 874 2982",
    "sg:postcode":"41621",
    "sg:province":"KY",
    "wof:name":"US Post Office",
    "wof:placetype":"venue"
},
  "geometry": {"coordinates":[-82.725223,37.623482],"type":"Point"}
}