{
  "type": "Feature",
  "properties": {
    "iso:country":"US",
    "sg:address":"3315 Park Ave",
    "sg:city":"Paducah",
    "sg:classifiers":[
        {
            "category":"Retail",
            "subcategory":"Auto Repair",
            "type":"Services"
        }
    ],
    "sg:phone":"+1 270 444 0151",
    "sg:postcode":"42001",
    "sg:province":"KY",
    "sg:tags":[
        "transmission"
    ],
    "wof:name":"Precision Transmission",
    "wof:placetype":"venue"
},
  "geometry": {"coordinates":[-88.65357400000001,37.083836],"type":"Point"}
}