{
  "type": "Feature",
  "properties": {
    "iso:country":"US",
    "sg:address":"816 Phillips Ln",
    "sg:city":"Louisville",
    "sg:classifiers":[
        {
            "category":"Manufacturing",
            "subcategory":"Signs",
            "type":"Manufacturing & Wholesale Goods"
        }
    ],
    "sg:phone":"+1 502 366 2311",
    "sg:postcode":"40209",
    "sg:province":"KY",
    "wof:name":"Dan-D Signs",
    "wof:placetype":"venue"
},
  "geometry": {"coordinates":[-85.742131,38.191851],"type":"Point"}
}