{
  "type": "Feature",
  "properties": {
    "iso:country":"US",
    "sg:address":"382 Diederich Blvd",
    "sg:city":"Ashland",
    "sg:classifiers":[
        {
            "category":"Banks & Credit Unions",
            "subcategory":"Bank",
            "type":"Services"
        }
    ],
    "sg:phone":"+1 606 324 8874",
    "sg:postcode":"41169",
    "sg:province":"KY",
    "sg:tags":[
        "cashing",
        "check"
    ],
    "wof:name":"First American Cash Advance",
    "wof:placetype":"venue"
},
  "geometry": {"coordinates":[-82.677989,38.502171],"type":"Point"}
}