{
  "type": "Feature",
  "properties": {
    "addr:full":"3808 Shepherdsville Rd Louisville KY 40218",
    "addr:housenumber":"3808",
    "addr:postcode":"40218",
    "addr:street":"Shepherdsville Rd",
    "iso:country":"US",
    "sg:address":"3808 Shepherdsville Rd",
    "sg:city":"Louisville",
    "sg:classifiers":[
        {
            "category":"Shopping",
            "type":"Retail Goods"
        }
    ],
    "sg:phone":"+1 502 266 6571",
    "sg:postcode":"40218",
    "sg:province":"KY",
    "sg:tags":[
        "cosmetic",
        "perfume"
    ],
    "wof:name":"Salon Service Group",
    "wof:placetype":"venue"
},
  "geometry": {"coordinates":[-85.65958999999999,38.188465],"type":"Point"}
}