{
  "type": "Feature",
  "properties": {
    "addr:full":"10003 Whipps Mill Rd Louisville KY 40223",
    "addr:housenumber":"10003",
    "addr:postcode":"40223",
    "addr:street":"Whipps Mill Rd",
    "iso:country":"US",
    "sg:address":"10003 Whipps Mill Rd",
    "sg:city":"Louisville",
    "sg:classifiers":[
        {
            "category":"Restaurant",
            "type":"Food & Drink"
        }
    ],
    "sg:phone":"+1 502 329 8283",
    "sg:postcode":"40223",
    "sg:province":"KY",
    "sg:tags":[
        "eating"
    ],
    "wof:name":"Coulston Creations",
    "wof:placetype":"venue"
},
  "geometry": {"coordinates":[-85.56748899999999,38.272909],"type":"Point"}
}