{
  "type": "Feature",
  "properties": {
    "addr:full":"10474 Shelbyville Rd Louisville KY 40223",
    "addr:housenumber":"10474",
    "addr:postcode":"40223",
    "addr:street":"Shelbyville Rd",
    "iso:country":"US",
    "sg:address":"10474 Shelbyville Rd",
    "sg:city":"Louisville",
    "sg:classifiers":[
        {
            "category":"Personal",
            "subcategory":"Beauty Salon",
            "type":"Services"
        }
    ],
    "sg:phone":"+1 502 244 1454",
    "sg:postcode":"40223",
    "sg:province":"KY",
    "wof:name":"Great Clips",
    "wof:placetype":"venue"
},
  "geometry": {"coordinates":[-85.56294800000001,38.245297],"type":"Point"}
}