{
  "type": "Feature",
  "properties": {
    "addr:full":"58 Us Highway 68 W Benton KY 42025",
    "addr:housenumber":"58",
    "addr:postcode":"42025",
    "addr:street":"Us Highway 68 W",
    "iso:country":"US",
    "sg:address":"58 Us Highway 68 W",
    "sg:city":"Benton",
    "sg:classifiers":[
        {
            "category":"Restaurant",
            "type":"Food & Drink"
        }
    ],
    "sg:menulink":"http://www.allmenus.com/ky/calvert-city/159291-arbys/menu/",
    "sg:phone":"+1 270 527 5290",
    "sg:postcode":"42025",
    "sg:province":"KY",
    "sg:tags":[
        "burger",
        "american"
    ],
    "wof:name":"Arby's",
    "wof:placetype":"venue"
},
  "geometry": {"coordinates":[-88.34421,36.925846],"type":"Point"}
}