{
  "type": "Feature",
  "properties": {
    "addr:full":"401 Maclean Ave Louisville KY 40209",
    "addr:housenumber":"401",
    "addr:postcode":"40209",
    "addr:street":"Maclean Ave",
    "iso:country":"US",
    "sg:address":"401 Maclean Ave",
    "sg:city":"Louisville",
    "sg:classifiers":[
        {
            "category":"Wholesale",
            "subcategory":"Non-durable Goods",
            "type":"Manufacturing & Wholesale Goods"
        }
    ],
    "sg:phone":"+1 502 368 3047",
    "sg:postcode":"40209",
    "sg:province":"KY",
    "sg:tags":[
        "pet",
        "supply"
    ],
    "wof:name":"Kentuckiana Pets Supply",
    "wof:placetype":"venue"
},
  "geometry": {"coordinates":[-85.75284600000001,38.175184],"type":"Point"}
}