{
  "type": "Feature",
  "properties": {
    "addr:full":"11 Gray Rd Hodgenville KY 42748",
    "addr:housenumber":"11",
    "addr:postcode":"42748",
    "addr:street":"Gray Rd",
    "iso:country":"US",
    "sg:address":"11 Gray Rd",
    "sg:city":"Hodgenville",
    "sg:classifiers":[
        {
            "category":"Organizations",
            "subcategory":"Religious Organization",
            "type":"Services"
        }
    ],
    "sg:phone":"+1 270 358 8565",
    "sg:postcode":"42748",
    "sg:province":"KY",
    "sg:tags":[
        "church"
    ],
    "wof:name":"Roanoke House Of Prayer",
    "wof:placetype":"venue"
},
  "geometry": {"coordinates":[-85.716916,37.681407],"type":"Point"}
}