{
  "type": "Feature",
  "properties": {
    "iso:country":"US",
    "sg:address":"1713 Ivy Lynn Ct",
    "sg:city":"Hopkinsville",
    "sg:classifiers":[
        {
            "category":"Professional",
            "subcategory":"Business Services",
            "type":"Services"
        }
    ],
    "sg:phone":"+1 270 886 2358",
    "sg:postcode":"42240",
    "sg:province":"KY",
    "wof:name":"Quality Solutions Inc",
    "wof:placetype":"venue"
},
  "geometry": {"coordinates":[-87.54906200000001,36.846121],"type":"Point"}
}