{
  "type": "Feature",
  "properties": {
    "addr:full":"725 Campbellsville Byp Campbellsville KY 42718",
    "addr:housenumber":"725",
    "addr:postcode":"42718",
    "addr:street":"Campbellsville Byp",
    "iso:country":"US",
    "sg:address":"725 Campbellsville Byp",
    "sg:city":"Campbellsville",
    "sg:classifiers":[
        {
            "category":"Professional",
            "subcategory":"Accounting & Tax Preparation",
            "type":"Services"
        }
    ],
    "sg:phone":"+1 270 789 0399",
    "sg:postcode":"42718",
    "sg:province":"KY",
    "sg:tags":[
        "return",
        "filing"
    ],
    "wof:name":"Jackson Hewitt Tax Svc",
    "wof:placetype":"venue"
},
  "geometry": {"coordinates":[-85.367222,37.343919],"type":"Point"}
}