{
  "type": "Feature",
  "properties": {
    "addr:full":"281 Main St Cadiz KY 42211",
    "addr:housenumber":"281",
    "addr:postcode":"42211",
    "addr:street":"Main St",
    "iso:country":"US",
    "sg:address":"281 Main St",
    "sg:city":"Cadiz",
    "sg:classifiers":[
        {
            "category":"Retail",
            "subcategory":"Auto Repair",
            "type":"Services"
        }
    ],
    "sg:phone":"+1 270 522 8934",
    "sg:postcode":"42211",
    "sg:province":"KY",
    "sg:tags":[
        "repairing",
        "automobile"
    ],
    "wof:name":"Auto Doctor",
    "wof:placetype":"venue"
},
  "geometry": {"coordinates":[-87.818701,36.867378],"type":"Point"}
}