{
  "type": "Feature",
  "properties": {
    "addr:full":"32 State Hwy 1820 Cunningham KY 42069",
    "addr:housenumber":"32",
    "addr:postcode":"1820;42069",
    "addr:street":"State Hwy",
    "iso:country":"US",
    "sg:address":"32 State Hwy 1820",
    "sg:city":"Cunningham",
    "sg:classifiers":[
        {
            "category":"Freight",
            "type":"Transportation"
        }
    ],
    "sg:phone":"+1 270 642 2255",
    "sg:postcode":"42069",
    "sg:province":"KY",
    "sg:tags":[
        "hauling",
        "trucking"
    ],
    "wof:name":"Presson Trucking",
    "wof:placetype":"venue"
},
  "geometry": {"coordinates":[-88.686933,36.938913],"type":"Point"}
}