{
  "type": "Feature",
  "properties": {
    "addr:full":"103 Wind Haven Dr Nicholasville KY 40356",
    "addr:housenumber":"103",
    "addr:postcode":"40356",
    "addr:street":"Wind Haven Dr",
    "iso:country":"US",
    "sg:address":"103 Wind Haven Dr",
    "sg:city":"Nicholasville",
    "sg:classifiers":[
        {
            "category":"Professional",
            "subcategory":"Employment Agencies",
            "type":"Services"
        }
    ],
    "sg:phone":"+1 859 296 1605",
    "sg:postcode":"40356",
    "sg:province":"KY",
    "sg:tags":[
        "help",
        "contractor"
    ],
    "wof:name":"Management Recruiters",
    "wof:placetype":"venue"
},
  "geometry": {"coordinates":[-84.59404600000001,37.9854],"type":"Point"}
}