{
  "type": "Feature",
  "properties": {
    "iso:country":"US",
    "sg:address":"1307 W Lexington Ave",
    "sg:city":"Winchester",
    "sg:classifiers":[
        {
            "category":"Travel",
            "subcategory":"Hotels & Motels",
            "type":"Entertainment"
        }
    ],
    "sg:phone":"+1 877 574 2464",
    "sg:postcode":"40391",
    "sg:province":"KY",
    "sg:website":"http://book.bestwestern.com/bestwestern/priceAvail.do?propertyCode=18018&cm_mmc=IYP-_-YP-_-property-_-18018",
    "wof:name":"Best Western Country Squire",
    "wof:placetype":"venue"
},
  "geometry": {"coordinates":[-84.20143899999999,38.002285],"type":"Point"}
}