{
  "type": "Feature",
  "properties": {
    "addr:full":"5723 Bardstown Rd Fern Creek KY 40291",
    "addr:housenumber":"5723",
    "addr:postcode":"40291",
    "addr:street":"Bardstown Rd",
    "iso:country":"US",
    "sg:address":"5723 Bardstown Rd",
    "sg:city":"Fern Creek",
    "sg:classifiers":[
        {
            "category":"Manufacturing",
            "subcategory":"Metals",
            "type":"Manufacturing & Wholesale Goods"
        }
    ],
    "sg:phone":"+1 502 239 2187",
    "sg:postcode":"40291",
    "sg:province":"KY",
    "sg:tags":[
        "coating"
    ],
    "wof:name":"PPG Porter Paints",
    "wof:placetype":"venue"
},
  "geometry": {"coordinates":[-85.59526099999999,38.162573],"type":"Point"}
}