{
  "type": "Feature",
  "properties": {
    "addr:full":"1701 Ashley Cir Bowling Green KY 42104",
    "addr:housenumber":"1701",
    "addr:postcode":"42104",
    "addr:street":"Ashley Cir",
    "iso:country":"US",
    "sg:address":"1701 Ashley Cir",
    "sg:city":"Bowling Green",
    "sg:classifiers":[
        {
            "category":"Health Services",
            "subcategory":"Doctor",
            "type":"Services"
        }
    ],
    "sg:phone":"+1 270 796 6000",
    "sg:postcode":"42104",
    "sg:province":"KY",
    "sg:tags":[
        "physician",
        "surgeon"
    ],
    "wof:name":"Nagy Morsi MD",
    "wof:placetype":"venue"
},
  "geometry": {"coordinates":[-86.437096,36.967623],"type":"Point"}
}