{
  "type": "Feature",
  "properties": {
    "iso:country":"US",
    "sg:address":"5298 Cane Valley Mill Rd",
    "sg:city":"Columbia",
    "sg:classifiers":[
        {
            "category":"Professional",
            "subcategory":"Management & Consulting",
            "type":"Services"
        }
    ],
    "sg:phone":"+1 270 932 5572",
    "sg:postcode":"42728",
    "sg:province":"KY",
    "sg:tags":[
        "business"
    ],
    "wof:name":"AMS Consulting Inc",
    "wof:placetype":"venue"
},
  "geometry": {"coordinates":[-85.337755,37.156246],"type":"Point"}
}