{
  "type": "Feature",
  "properties": {
    "addr:full":"1141 High St Brandenburg KY 40108",
    "addr:housenumber":"1141",
    "addr:postcode":"40108",
    "addr:street":"High St",
    "iso:country":"US",
    "sg:address":"1141 High St",
    "sg:city":"Brandenburg",
    "sg:classifiers":[
        {
            "category":"Real Estate",
            "subcategory":"Real Estate Agent",
            "type":"Services"
        }
    ],
    "sg:phone":"+1 270 422 1535",
    "sg:postcode":"40108",
    "sg:province":"KY",
    "wof:name":"Land Realty Inc",
    "wof:placetype":"venue"
},
  "geometry": {"coordinates":[-86.184623,37.993131],"type":"Point"}
}