{
  "type": "Feature",
  "properties": {
    "iso:country":"US",
    "sg:address":"420 W 8th St",
    "sg:city":"Benton",
    "sg:classifiers":[
        {
            "category":"Building & Trades",
            "subcategory":"Landscaping Services",
            "type":"Services"
        }
    ],
    "sg:phone":"+1 270 527 0425",
    "sg:postcode":"42025",
    "sg:province":"KY",
    "wof:name":"Basic Lawn Care",
    "wof:placetype":"venue"
},
  "geometry": {"coordinates":[-88.354579,36.86101],"type":"Point"}
}