{
  "type": "Feature",
  "properties": {
    "iso:country":"US",
    "sg:address":"356 Co Rd 7 E",
    "sg:city":"Ironton",
    "sg:classifiers":[
        {
            "category":"Retail",
            "subcategory":"Auto Repair",
            "type":"Services"
        }
    ],
    "sg:phone":"+1 740 532 8394",
    "sg:postcode":"45638",
    "sg:province":"OH",
    "sg:tags":[
        "wrecker"
    ],
    "wof:name":"Mart's Body Shop",
    "wof:placetype":"venue"
},
  "geometry": {"coordinates":[-82.645285,38.549895],"type":"Point"}
}