{
  "type": "Feature",
  "properties": {
    "iso:country":"US",
    "sg:address":"6600 Outer Loop",
    "sg:city":"Louisville",
    "sg:classifiers":[
        {
            "category":"Real Estate",
            "subcategory":"Real Estate Operator",
            "type":"Services"
        }
    ],
    "sg:phone":"+1 502 968 0101",
    "sg:postcode":"40228",
    "sg:province":"KY",
    "sg:tags":[
        "apartment"
    ],
    "wof:name":"Derby Run Apartments",
    "wof:placetype":"venue"
},
  "geometry": {"coordinates":[-85.635653,38.137591],"type":"Point"}
}