{
  "type": "Feature",
  "properties": {
    "iso:country":"US",
    "sg:address":"201 Harpers Ferry Rd",
    "sg:city":"Louisville",
    "sg:classifiers":[
        {
            "category":"Food & Beverages",
            "subcategory":"Groceries & Convenience Stores",
            "type":"Retail Goods"
        }
    ],
    "sg:phone":"+1 502 562 6500",
    "sg:postcode":"40214",
    "sg:province":"KY",
    "wof:name":"Chevron Food Mart",
    "wof:placetype":"venue"
},
  "geometry": {"coordinates":[-85.769724,38.131426],"type":"Point"}
}