{
  "type": "Feature",
  "properties": {
    "addr:full":"324 Browns Ln Louisville KY 40207",
    "addr:housenumber":"324",
    "addr:postcode":"40207",
    "addr:street":"Browns Ln",
    "iso:country":"US",
    "sg:address":"324 Browns Ln",
    "sg:city":"Louisville",
    "sg:classifiers":[
        {
            "category":"Education",
            "subcategory":"Special Training",
            "type":"Public Place"
        }
    ],
    "sg:phone":"+1 502 895 2821",
    "sg:postcode":"40207",
    "sg:province":"KY",
    "sg:tags":[
        "management"
    ],
    "wof:name":"Priority Management",
    "wof:placetype":"venue"
},
  "geometry": {"coordinates":[-85.644576,38.248736],"type":"Point"}
}