{
  "type": "Feature",
  "properties": {
    "addr:full":"170 Old Cuba Rd Eubank KY 42567",
    "addr:housenumber":"170",
    "addr:postcode":"42567",
    "addr:street":"Old Cuba Rd",
    "iso:country":"US",
    "sg:address":"170 Old Cuba Rd",
    "sg:city":"Eubank",
    "sg:classifiers":[
        {
            "category":"Wholesale",
            "subcategory":"Construction Materials",
            "type":"Manufacturing & Wholesale Goods"
        }
    ],
    "sg:phone":"+1 606 379 6401",
    "sg:postcode":"42567",
    "sg:province":"KY",
    "sg:tags":[
        "pallet",
        "skid"
    ],
    "wof:name":"Barron Pallet Inc",
    "wof:placetype":"venue"
},
  "geometry": {"coordinates":[-84.63161599999999,37.267],"type":"Point"}
}