{
  "type": "Feature",
  "properties": {
    "iso:country":"US",
    "sg:address":"826 N Main St",
    "sg:city":"London",
    "sg:classifiers":[
        {
            "category":"Wholesale",
            "subcategory":"Machinery & Supplies",
            "type":"Manufacturing & Wholesale Goods"
        }
    ],
    "sg:phone":"+1 606 864 3324",
    "sg:postcode":"40741",
    "sg:province":"KY",
    "sg:tags":[
        "equipment",
        "industrial"
    ],
    "sg:website":"www.southernsupply.net",
    "wof:name":"Southern Supply & Equipment",
    "wof:placetype":"venue"
},
  "geometry": {"coordinates":[-84.089114,37.133001],"type":"Point"}
}