{
  "type": "Feature",
  "properties": {
    "addr:full":"127 N Main St Mt Olivet KY 41064",
    "addr:housenumber":"127",
    "addr:postcode":"41064",
    "addr:street":"N Main St",
    "iso:country":"US",
    "sg:address":"127 N Main St",
    "sg:city":"Mt Olivet",
    "sg:classifiers":[
        {
            "category":"Social Services",
            "subcategory":"Child Care",
            "type":"Services"
        }
    ],
    "sg:phone":"+1 606 724 5614",
    "sg:postcode":"41064",
    "sg:province":"KY",
    "sg:tags":[
        "kindergarten",
        "academic",
        "school"
    ],
    "wof:name":"Mt Olivet Headstart",
    "wof:placetype":"venue"
},
  "geometry": {"coordinates":[-84.03434900000001,38.534633],"type":"Point"}
}