{
  "type": "Feature",
  "properties": {
    "iso:country":"US",
    "sg:address":"2250 S Green St",
    "sg:city":"Henderson",
    "sg:classifiers":[
        {
            "category":"Wholesale",
            "subcategory":"Machinery & Supplies",
            "type":"Manufacturing & Wholesale Goods"
        }
    ],
    "sg:phone":"+1 270 830 9627",
    "sg:postcode":"42420",
    "sg:province":"KY",
    "sg:tags":[
        "engine"
    ],
    "wof:name":"Ag-Con Diesel Svc",
    "wof:placetype":"venue"
},
  "geometry": {"coordinates":[-87.63404800000001,37.805169],"type":"Point"}
}