{
  "type": "Feature",
  "properties": {
    "addr:full":"3604 W Cumberland Ave Middlesboro KY 40965",
    "addr:housenumber":"3604",
    "addr:postcode":"40965",
    "addr:street":"W Cumberland Ave",
    "iso:country":"US",
    "sg:address":"3604 W Cumberland Ave",
    "sg:city":"Middlesboro",
    "sg:classifiers":[
        {
            "category":"Health Services",
            "subcategory":"Doctor",
            "type":"Services"
        }
    ],
    "sg:phone":"+1 606 248 8282",
    "sg:postcode":"40965",
    "sg:province":"KY",
    "sg:tags":[
        "physician",
        "surgeon"
    ],
    "wof:name":"Pediatric Clinic",
    "wof:placetype":"venue"
},
  "geometry": {"coordinates":[-83.739834,36.605186],"type":"Point"}
}