{
  "type": "Feature",
  "properties": {
    "iso:country":"US",
    "sg:address":"13400 Kinross Blvd",
    "sg:city":"Louisville",
    "sg:classifiers":[
        {
            "category":"Shopping",
            "subcategory":"Catalog Store",
            "type":"Retail Goods"
        }
    ],
    "sg:phone":"+1 502 933 9560",
    "sg:postcode":"40272",
    "sg:province":"KY",
    "sg:tags":[
        "mail",
        "house"
    ],
    "wof:name":"House of Lyods Demonstration",
    "wof:placetype":"venue"
},
  "geometry": {"coordinates":[-85.891041,38.06155],"type":"Point"}
}