{
  "type": "Feature",
  "properties": {
    "addr:full":"982 Breckenridge Ln St Matthews KY 40207",
    "addr:housenumber":"982",
    "addr:postcode":"40207",
    "addr:street":"Breckenridge Ln",
    "iso:country":"US",
    "sg:address":"982 Breckenridge Ln",
    "sg:city":"St Matthews",
    "sg:classifiers":[
        {
            "category":"Cinema",
            "subcategory":"Movie Rental",
            "type":"Entertainment"
        }
    ],
    "sg:phone":"+1 502 899 9455",
    "sg:postcode":"40207",
    "sg:province":"KY",
    "sg:tags":[
        "leasing",
        "video",
        "disc",
        "tape"
    ],
    "sg:website":"www.blockbuster.com",
    "wof:name":"Blockbuster Video",
    "wof:placetype":"venue"
},
  "geometry": {"coordinates":[-85.639098,38.232845],"type":"Point"}
}