{
  "type": "Feature",
  "properties": {
    "iso:country":"US",
    "sg:address":"811 Oak St",
    "sg:city":"Covington",
    "sg:classifiers":[
        {
            "category":"Home & Garden",
            "subcategory":"Hardware",
            "type":"Retail Goods"
        }
    ],
    "sg:phone":"+1 859 431 1991",
    "sg:postcode":"41016",
    "sg:province":"KY",
    "wof:name":"Rolfsen Hardware Company",
    "wof:placetype":"venue"
},
  "geometry": {"coordinates":[-84.556313,39.087273],"type":"Point"}
}