{
  "type": "Feature",
  "properties": {
    "iso:country":"US",
    "sg:address":"11855 Commonwealth Dr",
    "sg:city":"Louisville",
    "sg:classifiers":[
        {
            "category":"Professional",
            "subcategory":"Accounting & Tax Preparation",
            "type":"Services"
        }
    ],
    "sg:phone":"+1 502 266 0000",
    "sg:postcode":"40299",
    "sg:province":"KY",
    "sg:tags":[
        "payroll"
    ],
    "sg:website":"www.advancedpayroll.com",
    "wof:name":"Advanced Payroll Systems",
    "wof:placetype":"venue"
},
  "geometry": {"coordinates":[-85.537435,38.214576],"type":"Point"}
}