{
  "type": "Feature",
  "properties": {
    "iso:country":"US",
    "sg:address":"645 Goshen Church Rd N",
    "sg:city":"Bowling Green",
    "sg:classifiers":[
        {
            "category":"Freight",
            "type":"Transportation"
        }
    ],
    "sg:phone":"+1 270 563 4942",
    "sg:postcode":"42101",
    "sg:province":"KY",
    "sg:tags":[
        "interstate",
        "trucking"
    ],
    "wof:name":"Harriford Brothers",
    "wof:placetype":"venue"
},
  "geometry": {"coordinates":[-86.283556,37.024817],"type":"Point"}
}