{
  "type": "Feature",
  "properties": {
    "iso:country":"US",
    "sg:address":"2919 Pine Grove Rd",
    "sg:city":"Crab Orchard",
    "sg:classifiers":[
        {
            "category":"Mining & Drilling",
            "type":"Manufacturing & Wholesale Goods"
        }
    ],
    "sg:phone":"+1 606 355 2176",
    "sg:postcode":"40419",
    "sg:province":"KY",
    "sg:tags":[
        "stone"
    ],
    "wof:name":"Dix River Manufactured Stone",
    "wof:placetype":"venue"
},
  "geometry": {"coordinates":[-84.544641,37.427896],"type":"Point"}
}