{
  "type": "Feature",
  "properties": {
    "addr:full":"12121 Shelbyville Rd Louisville KY 40243",
    "addr:housenumber":"12121",
    "addr:postcode":"40243",
    "addr:street":"Shelbyville Rd",
    "iso:country":"US",
    "sg:address":"12121 Shelbyville Rd",
    "sg:city":"Louisville",
    "sg:classifiers":[
        {
            "category":"Shopping",
            "subcategory":"Gifts & Souvenirs",
            "type":"Retail Goods"
        }
    ],
    "sg:phone":"+1 502 244 4440",
    "sg:postcode":"40243",
    "sg:province":"KY",
    "sg:tags":[
        "shop"
    ],
    "wof:name":"Simply Cottage",
    "wof:placetype":"venue"
},
  "geometry": {"coordinates":[-85.5292,38.247863],"type":"Point"}
}