{
  "type": "Feature",
  "properties": {
    "iso:country":"US",
    "sg:address":"2321 Donna Rd",
    "sg:city":"Louisville",
    "sg:classifiers":[
        {
            "category":"Shopping",
            "type":"Retail Goods"
        }
    ],
    "sg:phone":"+1 502 448 8935",
    "sg:postcode":"40216",
    "sg:province":"KY",
    "sg:tags":[
        "cosmetic",
        "perfume"
    ],
    "wof:name":"Hicks",
    "wof:placetype":"venue"
},
  "geometry": {"coordinates":[-85.833213,38.183059],"type":"Point"}
}