{
  "type": "Feature",
  "properties": {
    "addr:full":"190 Holsclaw Hill Ct Brooks KY 40109",
    "addr:housenumber":"190",
    "addr:postcode":"40109",
    "addr:street":"Holsclaw Hill Ct",
    "iso:country":"US",
    "sg:address":"190 Holsclaw Hill Ct",
    "sg:city":"Brooks",
    "sg:classifiers":[
        {
            "category":"Manufacturing",
            "subcategory":"Pottery",
            "type":"Manufacturing & Wholesale Goods"
        }
    ],
    "sg:phone":"+1 502 957 6821",
    "sg:postcode":"40109",
    "sg:province":"KY",
    "sg:tags":[
        "pottery-wholesale",
        "manufacturer"
    ],
    "wof:name":"S Leksrisawat",
    "wof:placetype":"venue"
},
  "geometry": {"coordinates":[-85.736721,38.06447],"type":"Point"}
}