{
  "type": "Feature",
  "properties": {
    "iso:country":"US",
    "sg:address":"1148 College St",
    "sg:city":"Bowling Green",
    "sg:classifiers":[
        {
            "category":"Utilities",
            "subcategory":"Telephone",
            "type":"Services"
        }
    ],
    "sg:phone":"+1 270 842 8227",
    "sg:postcode":"42101",
    "sg:province":"KY",
    "sg:tags":[
        "telecommunication"
    ],
    "wof:name":"Cinergy Communications",
    "wof:placetype":"venue"
},
  "geometry": {"coordinates":[-86.444962,36.991546],"type":"Point"}
}