{
  "type": "Feature",
  "properties": {
    "iso:country":"US",
    "sg:address":"6908 Dixie Hwy",
    "sg:city":"Louisville",
    "sg:classifiers":[
        {
            "category":"Restaurant",
            "type":"Food & Drink"
        }
    ],
    "sg:menulink":"http://www.allmenus.com/ky/jefferson-southwest/176047-kfc---kentucky-fried-chicken/menu/",
    "sg:phone":"+1 502 933 3255",
    "sg:postcode":"40258",
    "sg:province":"KY",
    "sg:tags":[
        "american",
        "chicken"
    ],
    "wof:name":"KFC - Kentucky Fried Chicken",
    "wof:placetype":"venue"
},
  "geometry": {"coordinates":[-85.837118,38.149959],"type":"Point"}
}