{
  "type": "Feature",
  "properties": {
    "addr:full":"695 W Blue Lick Rd Shepherdsville KY 40165",
    "addr:housenumber":"695",
    "addr:postcode":"40165",
    "addr:street":"W Blue Lick Rd",
    "iso:country":"US",
    "sg:address":"695 W Blue Lick Rd",
    "sg:city":"Shepherdsville",
    "sg:classifiers":[
        {
            "category":"Retail",
            "subcategory":"Laundry & Dry Cleaning",
            "type":"Services"
        }
    ],
    "sg:phone":"+1 502 543 8506",
    "sg:postcode":"40165",
    "sg:province":"KY",
    "sg:tags":[
        "cleaners",
        "rug",
        "carpet"
    ],
    "wof:name":"Cook's Carpet & Upholstery",
    "wof:placetype":"venue"
},
  "geometry": {"coordinates":[-85.72387999999999,38.004342],"type":"Point"}
}