{
  "type": "Feature",
  "properties": {
    "addr:full":"6023 Cooper Chapel Rd Louisville KY 40229",
    "addr:housenumber":"6023",
    "addr:postcode":"40229",
    "addr:street":"Cooper Chapel Rd",
    "iso:country":"US",
    "sg:address":"6023 Cooper Chapel Rd",
    "sg:city":"Louisville",
    "sg:classifiers":[
        {
            "category":"Building & Trades",
            "subcategory":"Construction",
            "type":"Services"
        }
    ],
    "sg:phone":"+1 502 968 9885",
    "sg:postcode":"40229",
    "sg:province":"KY",
    "sg:tags":[
        "siding",
        "contractor"
    ],
    "wof:name":"Don Johnson Contractors",
    "wof:placetype":"venue"
},
  "geometry": {"coordinates":[-85.64928500000001,38.105595],"type":"Point"}
}