{
  "type": "Feature",
  "properties": {
    "addr:full":"600 US Hwy 31 W Byp Bowling Green KY 42101",
    "addr:housenumber":"600",
    "addr:postcode":"42101",
    "addr:street":"Us Hwy 31 W Byp",
    "iso:country":"US",
    "sg:address":"600 US Hwy 31 W Byp",
    "sg:city":"Bowling Green",
    "sg:classifiers":[
        {
            "category":"Home & Garden",
            "subcategory":"Hardware",
            "type":"Retail Goods"
        }
    ],
    "sg:phone":"+1 270 843 0126",
    "sg:postcode":"42101",
    "sg:province":"KY",
    "wof:name":"Ace Hardware",
    "wof:placetype":"venue"
},
  "geometry": {"coordinates":[-86.428241,36.990707],"type":"Point"}
}