{
  "type": "Feature",
  "properties": {
    "iso:country":"US",
    "sg:address":"3328 New Providence Rd",
    "sg:city":"Murray",
    "sg:classifiers":[
        {
            "category":"Farming",
            "subcategory":"Farm",
            "type":"Manufacturing & Wholesale Goods"
        }
    ],
    "sg:phone":"+1 270 436 2602",
    "sg:postcode":"42071",
    "sg:province":"KY",
    "sg:tags":[
        "crop",
        "general"
    ],
    "wof:name":"Barry Grogan",
    "wof:placetype":"venue"
},
  "geometry": {"coordinates":[-88.237382,36.538673],"type":"Point"}
}