{
  "type": "Feature",
  "properties": {
    "addr:full":"9163 US Hwy 62 Calvert City KY 42029",
    "addr:housenumber":"9163",
    "addr:postcode":"42029",
    "addr:street":"Us Hwy 62",
    "iso:country":"US",
    "sg:address":"9163 US Hwy 62",
    "sg:city":"Calvert City",
    "sg:classifiers":[
        {
            "category":"Shopping",
            "type":"Retail Goods"
        }
    ],
    "sg:phone":"+1 270 898 9040",
    "sg:postcode":"42029",
    "sg:province":"KY",
    "sg:tags":[
        "cosmetic",
        "perfume"
    ],
    "wof:name":"Exceptional Gifts",
    "wof:placetype":"venue"
},
  "geometry": {"coordinates":[-88.384541,37.004903],"type":"Point"}
}