{
  "type": "Feature",
  "properties": {
    "iso:country":"US",
    "sg:address":"3033 Melbourne Ave",
    "sg:city":"Louisville",
    "sg:classifiers":[
        {
            "category":"Building & Trades",
            "subcategory":"Cleaning & Sanitation",
            "type":"Services"
        }
    ],
    "sg:phone":"+1 502 231 9369",
    "sg:postcode":"40220",
    "sg:province":"KY",
    "sg:tags":[
        "window"
    ],
    "wof:name":"Simple Solutions Window Clning",
    "wof:placetype":"venue"
},
  "geometry": {"coordinates":[-85.63091900000001,38.217011],"type":"Point"}
}