{
  "type": "Feature",
  "properties": {
    "addr:full":"1312 S Main St Hopkinsville KY 42240",
    "addr:housenumber":"1312",
    "addr:postcode":"42240",
    "addr:street":"S Main St",
    "iso:country":"US",
    "sg:address":"1312 S Main St",
    "sg:city":"Hopkinsville",
    "sg:classifiers":[
        {
            "category":"Banks & Credit Unions",
            "subcategory":"Bank",
            "type":"Services"
        }
    ],
    "sg:phone":"+1 270 886 9030",
    "sg:postcode":"42240",
    "sg:province":"KY",
    "sg:website":"http://www.plantersbankonline.com",
    "wof:name":"Planters Bank",
    "wof:placetype":"venue"
},
  "geometry": {"coordinates":[-87.490273,36.863533],"type":"Point"}
}