{
  "type": "Feature",
  "properties": {
    "iso:country":"US",
    "sg:address":"1713 Scottsville Rd",
    "sg:city":"Bowling Green",
    "sg:classifiers":[
        {
            "category":"Personal",
            "type":"Services"
        }
    ],
    "sg:phone":"+1 270 781 5533",
    "sg:postcode":"42104",
    "sg:province":"KY",
    "sg:tags":[
        "control",
        "weight"
    ],
    "wof:name":"Tenkan LA Weight Loss Ctr",
    "wof:placetype":"venue"
},
  "geometry": {"coordinates":[-86.43390599999999,36.969388],"type":"Point"}
}