{
  "type": "Feature",
  "properties": {
    "iso:country":"US",
    "sg:address":"1119 S Main St",
    "sg:city":"Corbin",
    "sg:classifiers":[
        {
            "category":"Shopping",
            "subcategory":"Used Merchandise",
            "type":"Retail Goods"
        }
    ],
    "sg:phone":"+1 606 528 5572",
    "sg:postcode":"40701",
    "sg:province":"KY",
    "wof:name":"Sharaes Consignment Shop",
    "wof:placetype":"venue"
},
  "geometry": {"coordinates":[-84.093632,36.938712],"type":"Point"}
}