{
  "type": "Feature",
  "properties": {
    "addr:full":"3415 Bardstown Rd Louisville KY 40218",
    "addr:housenumber":"3415",
    "addr:postcode":"40218",
    "addr:street":"Bardstown Rd",
    "iso:country":"US",
    "sg:address":"3415 Bardstown Rd",
    "sg:city":"Louisville",
    "sg:classifiers":[
        {
            "category":"Building & Trades",
            "subcategory":"Construction",
            "type":"Services"
        }
    ],
    "sg:phone":"+1 502 451 3500",
    "sg:postcode":"40218",
    "sg:province":"KY",
    "sg:tags":[
        "masonry",
        "contractor"
    ],
    "wof:name":"BSM Construction Co Inc",
    "wof:placetype":"venue"
},
  "geometry": {"coordinates":[-85.66533099999999,38.204166],"type":"Point"}
}