{
  "type": "Feature",
  "properties": {
    "iso:country":"US",
    "sg:address":"3205 Dunlova Ct",
    "sg:city":"Louisville",
    "sg:classifiers":[
        {
            "category":"Professional",
            "subcategory":"Lawyer & Legal Services",
            "type":"Services"
        }
    ],
    "sg:phone":"+1 502 326 4172",
    "sg:postcode":"40241",
    "sg:province":"KY",
    "sg:tags":[
        "attorney"
    ],
    "wof:name":"R Mark Beal",
    "wof:placetype":"venue"
},
  "geometry": {"coordinates":[-85.571333,38.292876],"type":"Point"}
}