{
  "type": "Feature",
  "properties": {
    "iso:country":"US",
    "sg:address":"812 Boone Pl",
    "sg:city":"Morehead",
    "sg:classifiers":[
        {
            "category":"Social Services",
            "subcategory":"Child Care",
            "type":"Services"
        }
    ],
    "sg:phone":"+1 606 784 5090",
    "sg:postcode":"40351",
    "sg:province":"KY",
    "wof:name":"Bright Beginnings Child Care",
    "wof:placetype":"venue"
},
  "geometry": {"coordinates":[-83.435468,38.173111],"type":"Point"}
}