{
  "type": "Feature",
  "properties": {
    "iso:country":"US",
    "sg:address":"191 2nd St",
    "sg:city":"Pikeville",
    "sg:classifiers":[
        {
            "category":"Shopping",
            "subcategory":"Bicycles & Sporting Goods",
            "type":"Retail Goods"
        }
    ],
    "sg:phone":"+1 606 437 0413",
    "sg:postcode":"41501",
    "sg:province":"KY",
    "sg:tags":[
        "gun",
        "gunsmith"
    ],
    "wof:name":"Roger's Gun & Pawn",
    "wof:placetype":"venue"
},
  "geometry": {"coordinates":[-82.51767,37.480705],"type":"Point"}
}