{
  "type": "Feature",
  "properties": {
    "iso:country":"US",
    "sg:address":"405 Babb Dr",
    "sg:city":"Mayfield",
    "sg:classifiers":[
        {
            "category":"Real Estate",
            "subcategory":"Real Estate Operator",
            "type":"Services"
        }
    ],
    "sg:phone":"+1 270 247 7723",
    "sg:postcode":"42066",
    "sg:province":"KY",
    "sg:tags":[
        "apartment"
    ],
    "wof:name":"Mayfield Plaza Apartments",
    "wof:placetype":"venue"
},
  "geometry": {"coordinates":[-88.62409599999999,36.724272],"type":"Point"}
}