{
  "type": "Feature",
  "properties": {
    "addr:full":"2288 Wagoner Rd Alexandria KY 41007",
    "addr:housenumber":"2288",
    "addr:postcode":"41007",
    "addr:street":"Wagoner Rd",
    "iso:country":"US",
    "sg:address":"2288 Wagoner Rd",
    "sg:city":"Alexandria",
    "sg:classifiers":[
        {
            "category":"Building & Trades",
            "subcategory":"Electrical",
            "type":"Services"
        }
    ],
    "sg:phone":"+1 859 694 1241",
    "sg:postcode":"41007",
    "sg:province":"KY",
    "sg:tags":[
        "electric",
        "contractor"
    ],
    "wof:name":"Mister Electric Inc",
    "wof:placetype":"venue"
},
  "geometry": {"coordinates":[-84.337733,38.9049],"type":"Point"}
}