{
  "type": "Feature",
  "properties": {
    "addr:full":"9010 Taylorsville Rd Louisville KY 40299",
    "addr:housenumber":"9010",
    "addr:postcode":"40299",
    "addr:street":"Taylorsville Rd",
    "iso:country":"US",
    "sg:address":"9010 Taylorsville Rd",
    "sg:city":"Louisville",
    "sg:classifiers":[
        {
            "category":"Restaurant",
            "type":"Food & Drink"
        }
    ],
    "sg:phone":"+1 502 499 9804",
    "sg:postcode":"40299",
    "sg:province":"KY",
    "wof:name":"Mr Gatti's Pizza",
    "wof:placetype":"venue"
},
  "geometry": {"coordinates":[-85.589399,38.21427],"type":"Point"}
}