{
  "type": "Feature",
  "properties": {
    "iso:country":"US",
    "sg:address":"5003 Old Federal Rd",
    "sg:city":"Louisville",
    "sg:classifiers":[
        {
            "category":"Shopping",
            "subcategory":"Clothing, Apparel, & Fashions",
            "type":"Retail Goods"
        }
    ],
    "sg:phone":"+1 502 893 0945",
    "sg:postcode":"40207",
    "sg:province":"KY",
    "wof:name":"MCS Accessories LLC",
    "wof:placetype":"venue"
},
  "geometry": {"coordinates":[-85.652181,38.286005],"type":"Point"}
}