{
  "type": "Feature",
  "properties": {
    "iso:country":"US",
    "sg:address":"6219 Ancient Oak Dr",
    "sg:city":"Florence",
    "sg:classifiers":[
        {
            "category":"Shopping",
            "type":"Retail Goods"
        }
    ],
    "sg:phone":"+1 859 282 1964",
    "sg:postcode":"41042",
    "sg:province":"KY",
    "sg:tags":[
        "cosmetic",
        "perfume"
    ],
    "wof:name":"Beauti Control Independent",
    "wof:placetype":"venue"
},
  "geometry": {"coordinates":[-84.687906,39.013313],"type":"Point"}
}