{
  "type": "Feature",
  "properties": {
    "addr:full":"1759 S Green St Henderson KY 42420",
    "addr:housenumber":"1759",
    "addr:postcode":"42420",
    "addr:street":"S Green St",
    "iso:country":"US",
    "sg:address":"1759 S Green St",
    "sg:city":"Henderson",
    "sg:classifiers":[
        {
            "category":"Restaurant",
            "type":"Food & Drink"
        }
    ],
    "sg:phone":"+1 270 826 2380",
    "sg:postcode":"42420",
    "sg:province":"KY",
    "wof:name":"Holiday House Family Rstrnt",
    "wof:placetype":"venue"
},
  "geometry": {"coordinates":[-87.615077,37.815929],"type":"Point"}
}