{
  "type": "Feature",
  "properties": {
    "addr:full":"6934 Ambridge Cir Louisville KY 40207",
    "addr:housenumber":"6934",
    "addr:postcode":"40207",
    "addr:street":"Ambridge Cir",
    "iso:country":"US",
    "sg:address":"6934 Ambridge Cir",
    "sg:city":"Louisville",
    "sg:classifiers":[
        {
            "category":"Communications",
            "subcategory":"Film & Video Production",
            "type":"Services"
        }
    ],
    "sg:phone":"+1 502 897 3328",
    "sg:postcode":"40207",
    "sg:province":"KY",
    "sg:tags":[
        "motion"
    ],
    "wof:name":"Graphic Attack Productions",
    "wof:placetype":"venue"
},
  "geometry": {"coordinates":[-85.625347,38.263979],"type":"Point"}
}