{
  "type": "Feature",
  "properties": {
    "iso:country":"US",
    "sg:address":"121 Hollyhill Dr",
    "sg:city":"Berea",
    "sg:classifiers":[
        {
            "category":"Real Estate",
            "subcategory":"Real Estate Agent",
            "type":"Services"
        }
    ],
    "sg:phone":"+1 859 986 8663",
    "sg:postcode":"40403",
    "sg:province":"KY",
    "wof:name":"Hays Real Estate Inc",
    "wof:placetype":"venue"
},
  "geometry": {"coordinates":[-84.30049200000001,37.565308],"type":"Point"}
}