{
  "type": "Feature",
  "properties": {
    "iso:country":"US",
    "sg:address":"1169 Eastern Pkwy",
    "sg:city":"Louisville",
    "sg:classifiers":[
        {
            "category":"Social Services",
            "type":"Services"
        }
    ],
    "sg:phone":"+1 502 473 7028",
    "sg:postcode":"40217",
    "sg:province":"KY",
    "sg:tags":[
        "counselor",
        "marriage",
        "family"
    ],
    "wof:name":"Parkway Psychotherapy Group",
    "wof:placetype":"venue"
},
  "geometry": {"coordinates":[-85.724738,38.22524],"type":"Point"}
}