{
  "type": "Feature",
  "properties": {
    "iso:country":"US",
    "sg:address":"504 S Broadway",
    "sg:city":"Glasgow",
    "sg:phone":"+1 270 678 2444",
    "sg:postcode":"42141",
    "sg:province":"KY",
    "sg:tags":[
        "gas"
    ],
    "wof:name":"Farmer's Energy Propane Plus",
    "wof:placetype":"venue"
},
  "geometry": {"coordinates":[-85.912975,36.991924],"type":"Point"}
}