{
  "type": "Feature",
  "properties": {
    "iso:country":"US",
    "sg:address":"2204 Burrus Dr",
    "sg:city":"Lexington",
    "sg:classifiers":[
        {
            "category":"Real Estate",
            "subcategory":"Real Estate Agent",
            "type":"Services"
        }
    ],
    "sg:phone":"+1 859 264 1811",
    "sg:postcode":"40513",
    "sg:province":"KY",
    "wof:name":"Goins Realty",
    "wof:placetype":"venue"
},
  "geometry": {"coordinates":[-84.57131800000001,38.010294],"type":"Point"}
}