{
  "type": "Feature",
  "properties": {
    "iso:country":"US",
    "sg:address":"115 Baptist Church Ln",
    "sg:city":"Brandenburg",
    "sg:classifiers":[
        {
            "category":"Organizations",
            "subcategory":"Religious Organization",
            "type":"Services"
        }
    ],
    "sg:phone":"+1 270 422 3389",
    "sg:postcode":"40108",
    "sg:province":"KY",
    "sg:tags":[
        "church"
    ],
    "wof:name":"New Brandenburg Baptist Church",
    "wof:placetype":"venue"
},
  "geometry": {"coordinates":[-86.137692,37.967409],"type":"Point"}
}