{
  "type": "Feature",
  "properties": {
    "iso:country":"US",
    "sg:address":"5705 New Cut Rd",
    "sg:city":"Louisville",
    "sg:classifiers":[
        {
            "category":"Wholesale",
            "subcategory":"Construction Materials",
            "type":"Manufacturing & Wholesale Goods"
        }
    ],
    "sg:phone":"+1 502 968 1724",
    "sg:postcode":"40214",
    "sg:province":"KY",
    "sg:tags":[
        "coatings-protective"
    ],
    "wof:name":"A Liner Inc.",
    "wof:placetype":"venue"
},
  "geometry": {"coordinates":[-85.773439,38.137052],"type":"Point"}
}