{
  "type": "Feature",
  "properties": {
    "addr:full":"2460 Orchid Ln Villa Hills KY 41017",
    "addr:housenumber":"2460",
    "addr:postcode":"41017",
    "addr:street":"Orchid Ln",
    "iso:country":"US",
    "sg:address":"2460 Orchid Ln",
    "sg:city":"Villa Hills",
    "sg:classifiers":[
        {
            "category":"Banks & Credit Unions",
            "subcategory":"Investment Brokerage",
            "type":"Services"
        }
    ],
    "sg:phone":"+1 859 426 5493",
    "sg:postcode":"41017",
    "sg:province":"KY",
    "sg:tags":[
        "security"
    ],
    "wof:name":"Patrick Financial Corp",
    "wof:placetype":"venue"
},
  "geometry": {"coordinates":[-84.58806300000001,39.058767],"type":"Point"}
}