{
  "type": "Feature",
  "properties": {
    "iso:country":"US",
    "sg:address":"104 Independence Ave",
    "sg:city":"Bardstown",
    "sg:classifiers":[
        {
            "category":"Professional",
            "subcategory":"Business Services",
            "type":"Services"
        }
    ],
    "sg:phone":"+1 502 331 0822",
    "sg:postcode":"40004",
    "sg:province":"KY",
    "wof:name":"Homepro Inspections LLC",
    "wof:placetype":"venue"
},
  "geometry": {"coordinates":[-85.383493,37.816615],"type":"Point"}
}