{
  "type": "Feature",
  "properties": {
    "iso:country":"US",
    "sg:address":"122 Campbell St",
    "sg:city":"Hazard",
    "sg:classifiers":[
        {
            "category":"Real Estate",
            "subcategory":"Real Estate Operator",
            "type":"Services"
        }
    ],
    "sg:phone":"+1 606 436 8829",
    "sg:postcode":"41701",
    "sg:province":"KY",
    "sg:tags":[
        "apartment"
    ],
    "wof:name":"Oakbrook Apartments",
    "wof:placetype":"venue"
},
  "geometry": {"coordinates":[-83.195796,37.250521],"type":"Point"}
}