{
  "type": "Feature",
  "properties": {
    "iso:country":"US",
    "sg:address":"2053 River Rd",
    "sg:city":"Hyden",
    "sg:classifiers":[
        {
            "category":"Building & Trades",
            "subcategory":"Construction",
            "type":"Services"
        }
    ],
    "sg:phone":"+1 606 672 4474",
    "sg:postcode":"41749",
    "sg:province":"KY",
    "sg:tags":[
        "carpenter"
    ],
    "wof:name":"Leaf Guard Of Eastern Ky",
    "wof:placetype":"venue"
},
  "geometry": {"coordinates":[-83.35974,37.25203],"type":"Point"}
}