{
  "type": "Feature",
  "properties": {
    "iso:country":"US",
    "sg:address":"8235 McCowans Ferry Rd",
    "sg:city":"Versailles",
    "sg:classifiers":[
        {
            "category":"Wholesale",
            "subcategory":"Non-durable Goods",
            "type":"Manufacturing & Wholesale Goods"
        }
    ],
    "sg:phone":"+1 859 873 2537",
    "sg:postcode":"40383",
    "sg:province":"KY",
    "sg:tags":[
        "blacksmith",
        "shop",
        "supply"
    ],
    "sg:website":"www.nanric.com",
    "wof:name":"Nanric Inc",
    "wof:placetype":"venue"
},
  "geometry": {"coordinates":[-84.794338,37.949823],"type":"Point"}
}