{
  "type": "Feature",
  "properties": {
    "iso:country":"US",
    "sg:address":"111 S Walnut St",
    "sg:city":"Carlisle",
    "sg:classifiers":[
        {
            "category":"Restaurant",
            "type":"Food & Drink"
        }
    ],
    "sg:phone":"+1 859 289 7508",
    "sg:postcode":"40311",
    "sg:province":"KY",
    "sg:tags":[
        "caterer"
    ],
    "wof:name":"Talk Of The Town",
    "wof:placetype":"venue"
},
  "geometry": {"coordinates":[-84.02672099999999,38.310954],"type":"Point"}
}