{
  "type": "Feature",
  "properties": {
    "addr:full":"2124 Old Hwy 90 Monticello KY 42633",
    "addr:housenumber":"2124",
    "addr:postcode":"42633",
    "addr:street":"Old Hwy 90",
    "iso:country":"US",
    "sg:address":"2124 Old Hwy 90",
    "sg:city":"Monticello",
    "sg:classifiers":[
        {
            "category":"Organizations",
            "subcategory":"Religious Organization",
            "type":"Services"
        }
    ],
    "sg:phone":"+1 606 348 8225",
    "sg:postcode":"42633",
    "sg:province":"KY",
    "sg:tags":[
        "church"
    ],
    "sg:website":"www.monticellofbc.com",
    "wof:name":"First Baptist Church",
    "wof:placetype":"venue"
},
  "geometry": {"coordinates":[-84.82188499999999,36.868327],"type":"Point"}
}