{
  "type": "Feature",
  "properties": {
    "iso:country":"US",
    "sg:address":"100 State Hwy 15",
    "sg:city":"Jackson",
    "sg:classifiers":[
        {
            "category":"Shopping",
            "subcategory":"Department Store",
            "type":"Retail Goods"
        }
    ],
    "sg:phone":"+1 606 666 8299",
    "sg:postcode":"41339",
    "sg:province":"KY",
    "sg:tags":[
        "shop"
    ],
    "wof:name":"Family Dollar Store",
    "wof:placetype":"venue"
},
  "geometry": {"coordinates":[-83.397424,37.561035],"type":"Point"}
}