{
  "type": "Feature",
  "properties": {
    "iso:country":"US",
    "sg:address":"106 Sears Ave",
    "sg:city":"Louisville",
    "sg:classifiers":[
        {
            "category":"Shopping",
            "subcategory":"Bicycles & Sporting Goods",
            "type":"Retail Goods"
        }
    ],
    "sg:phone":"+1 502 895 0553",
    "sg:postcode":"40207",
    "sg:province":"KY",
    "wof:name":"St Mathews Schwinn Cyclery",
    "wof:placetype":"venue"
},
  "geometry": {"coordinates":[-85.646334,38.254126],"type":"Point"}
}