{
  "type": "Feature",
  "properties": {
    "addr:full":"2010 Fleet St Smithland KY 42081",
    "addr:housenumber":"2010",
    "addr:postcode":"42081",
    "addr:street":"Fleet St",
    "iso:country":"US",
    "sg:address":"2010 Fleet St",
    "sg:city":"Smithland",
    "sg:classifiers":[
        {
            "category":"Personal",
            "subcategory":"Beauty Salon",
            "type":"Services"
        }
    ],
    "sg:phone":"+1 270 988 3997",
    "sg:postcode":"42081",
    "sg:province":"KY",
    "sg:tags":[
        "hair",
        "stylist"
    ],
    "wof:name":"Hair Artist The",
    "wof:placetype":"venue"
},
  "geometry": {"coordinates":[-88.375698,37.397937],"type":"Point"}
}