{
  "type": "Feature",
  "properties": {
    "addr:full":"1047 Franklin St Louisville KY 40206",
    "addr:housenumber":"1047",
    "addr:postcode":"40206",
    "addr:street":"Franklin St",
    "iso:country":"US",
    "sg:address":"1047 Franklin St",
    "sg:city":"Louisville",
    "sg:classifiers":[
        {
            "category":"Manufacturing",
            "subcategory":"Tools & Machinery",
            "type":"Manufacturing & Wholesale Goods"
        },
        {
            "category":"Professional",
            "subcategory":"Engineering",
            "type":"Services"
        },
        {
            "category":"Freight",
            "type":"Transportation"
        },
        {
            "category":"Building & Trades",
            "subcategory":"Construction",
            "type":"Services"
        }
    ],
    "sg:phone":"+1 502 587 8578",
    "sg:postcode":"40206",
    "sg:province":"KY",
    "sg:tags":[
        "conveying",
        "consulting",
        "conveyor",
        "equipment-wholesale",
        "system",
        "equipment",
        "engineer",
        "monorail",
        "manufacturer"
    ],
    "wof:name":"Thomas E Anderson Company",
    "wof:placetype":"venue"
},
  "geometry": {"coordinates":[-85.73143,38.256901],"type":"Point"}
}