{
  "type": "Feature",
  "properties": {
    "iso:country":"US",
    "sg:address":"2319 Frankfort Ave",
    "sg:city":"Louisville",
    "sg:classifiers":[
        {
            "category":"Restaurant",
            "type":"Food & Drink"
        }
    ],
    "sg:menulink":"http://www.allmenus.com/ky/louisville-east/4440-the-irish-rover/menu/",
    "sg:phone":"+1 502 899 3544",
    "sg:postcode":"40206",
    "sg:province":"KY",
    "sg:tags":[
        "irish"
    ],
    "wof:name":"The Irish Rover",
    "wof:placetype":"venue"
},
  "geometry": {"coordinates":[-85.702207,38.253468],"type":"Point"}
}