{
  "type": "Feature",
  "properties": {
    "iso:country":"US",
    "sg:address":"528 W Main St",
    "sg:city":"Richmond",
    "sg:classifiers":[
        {
            "category":"Building & Trades",
            "subcategory":"Construction",
            "type":"Services"
        }
    ],
    "sg:phone":"+1 859 625 0780",
    "sg:postcode":"40475",
    "sg:province":"KY",
    "sg:tags":[
        "general",
        "contractor"
    ],
    "wof:name":"J W Jones Inc",
    "wof:placetype":"venue"
},
  "geometry": {"coordinates":[-84.29997400000001,37.749703],"type":"Point"}
}