{
  "type": "Feature",
  "properties": {
    "iso:country":"US",
    "sg:address":"1001 S Columbia Ave",
    "sg:city":"Campbellsville",
    "sg:classifiers":[
        {
            "category":"Manufacturing",
            "subcategory":"Tools & Machinery",
            "type":"Manufacturing & Wholesale Goods"
        }
    ],
    "sg:phone":"+1 270 789 3594",
    "sg:postcode":"42718",
    "sg:province":"KY",
    "sg:tags":[
        "equipment",
        "energy",
        "system",
        "supply"
    ],
    "wof:name":"Cox Waste To Energy",
    "wof:placetype":"venue"
},
  "geometry": {"coordinates":[-85.35120999999999,37.328472],"type":"Point"}
}