{
  "type": "Feature",
  "properties": {
    "addr:full":"111 Charro Ct Frankfort KY 40601",
    "addr:housenumber":"111",
    "addr:postcode":"40601",
    "addr:street":"Charro Ct",
    "iso:country":"US",
    "sg:address":"111 Charro Ct",
    "sg:city":"Frankfort",
    "sg:classifiers":[
        {
            "category":"Organizations",
            "subcategory":"Non-profit Organization",
            "type":"Services"
        }
    ],
    "sg:phone":"+1 502 209 5382",
    "sg:postcode":"40601",
    "sg:province":"KY",
    "sg:website":"www.kdva.org",
    "wof:name":"Kentucky Domestic Violence",
    "wof:placetype":"venue"
},
  "geometry": {"coordinates":[-84.833174,38.184571],"type":"Point"}
}