{
  "type": "Feature",
  "properties": {
    "addr:full":"1640 Kentucky Mills Dr Louisville KY 40299",
    "addr:housenumber":"1640",
    "addr:postcode":"40299",
    "addr:street":"Kentucky Mills Dr",
    "iso:country":"US",
    "sg:address":"1640 Kentucky Mills Dr",
    "sg:city":"Louisville",
    "sg:classifiers":[
        {
            "category":"Restaurant",
            "type":"Food & Drink"
        }
    ],
    "sg:phone":"+1 502 267 8130",
    "sg:postcode":"40299",
    "sg:province":"KY",
    "wof:name":"Arby's",
    "wof:placetype":"venue"
},
  "geometry": {"coordinates":[-85.541021,38.222405],"type":"Point"}
}