{
  "type": "Feature",
  "properties": {
    "addr:full":"7710 Bardstown Rd Louisville KY 40291",
    "addr:housenumber":"7710",
    "addr:postcode":"40291",
    "addr:street":"Bardstown Rd",
    "iso:country":"US",
    "sg:address":"7710 Bardstown Rd",
    "sg:city":"Louisville",
    "sg:classifiers":[
        {
            "category":"Place Of Worship",
            "subcategory":"Church",
            "type":"Public Place"
        },
        {
            "category":"Place Of Worship",
            "type":"Public Place"
        }
    ],
    "sg:phone":"+1 502 290 0392",
    "sg:postcode":"40291",
    "sg:province":"KY",
    "sg:tags":[
        "christ",
        "churches-community"
    ],
    "wof:name":"Promised Land Community Church",
    "wof:placetype":"venue"
},
  "geometry": {"coordinates":[-85.580344,38.135572],"type":"Point"}
}