{
  "type": "Feature",
  "properties": {
    "iso:country":"US",
    "sg:address":"180 Frankfort St",
    "sg:city":"Versailles",
    "sg:classifiers":[
        {
            "category":"Education",
            "subcategory":"School",
            "type":"Public Place"
        }
    ],
    "sg:phone":"+1 859 873 5434",
    "sg:postcode":"40383",
    "sg:province":"KY",
    "wof:name":"Woodford County High School",
    "wof:placetype":"venue"
},
  "geometry": {"coordinates":[-84.732992,38.060764],"type":"Point"}
}