{
  "type": "Feature",
  "properties": {
    "addr:full":"10359 Dixie Hwy Louisville KY 40272",
    "addr:housenumber":"10359",
    "addr:postcode":"40272",
    "addr:street":"Dixie Hwy",
    "iso:country":"US",
    "sg:address":"10359 Dixie Hwy",
    "sg:city":"Louisville",
    "sg:classifiers":[
        {
            "category":"Personal",
            "subcategory":"Beauty Salon",
            "type":"Services"
        }
    ],
    "sg:phone":"+1 502 933 9420",
    "sg:postcode":"40272",
    "sg:province":"KY",
    "sg:tags":[
        "manicuring"
    ],
    "wof:name":"Nail Tech",
    "wof:placetype":"venue"
},
  "geometry": {"coordinates":[-85.869176,38.103797],"type":"Point"}
}