{
  "type": "Feature",
  "properties": {
    "iso:country":"US",
    "sg:address":"79 Southside Mall Rd",
    "sg:city":"South Williamson",
    "sg:classifiers":[
        {
            "category":"Health Services",
            "subcategory":"Doctor",
            "type":"Services"
        }
    ],
    "sg:phone":"+1 606 237 0073",
    "sg:postcode":"41503",
    "sg:province":"KY",
    "sg:tags":[
        "dentist"
    ],
    "wof:name":"Gary L Hopkins DDS",
    "wof:placetype":"venue"
},
  "geometry": {"coordinates":[-82.27072699999999,37.652844],"type":"Point"}
}