{
  "type": "Feature",
  "properties": {
    "iso:country":"US",
    "sg:address":"217 S 3rd St",
    "sg:city":"Ironton",
    "sg:classifiers":[
        {
            "category":"Shopping",
            "subcategory":"Pharmacy",
            "type":"Retail Goods"
        }
    ],
    "sg:phone":"+1 740 532 7943",
    "sg:postcode":"45638",
    "sg:province":"OH",
    "wof:name":"Staley's Pharmacy",
    "wof:placetype":"venue"
},
  "geometry": {"coordinates":[-82.68446,38.533988],"type":"Point"}
}