{
  "type": "Feature",
  "properties": {
    "addr:full":"9804 Pictor Way Louisville KY 40241",
    "addr:housenumber":"9804",
    "addr:postcode":"40241",
    "addr:street":"Pictor Way",
    "iso:country":"US",
    "sg:address":"9804 Pictor Way",
    "sg:city":"Louisville",
    "sg:classifiers":[
        {
            "category":"Professional",
            "subcategory":"Management & Consulting",
            "type":"Services"
        }
    ],
    "sg:phone":"+1 502 931 2131",
    "sg:postcode":"40241",
    "sg:province":"KY",
    "sg:tags":[
        "marketing",
        "consultant"
    ],
    "wof:name":"Bevarly Communications",
    "wof:placetype":"venue"
},
  "geometry": {"coordinates":[-85.567048,38.305755],"type":"Point"}
}