{
  "type": "Feature",
  "properties": {
    "iso:country":"US",
    "sg:address":"1125 Island Ford Rd",
    "sg:city":"Madisonville",
    "sg:classifiers":[
        {
            "category":"Building & Trades",
            "subcategory":"Plumbing",
            "type":"Services"
        }
    ],
    "sg:phone":"+1 270 821 3400",
    "sg:postcode":"42431",
    "sg:province":"KY",
    "sg:tags":[
        "plumbing",
        "contractor"
    ],
    "wof:name":"Prow Brothers Plumbing & Htg",
    "wof:placetype":"venue"
},
  "geometry": {"coordinates":[-87.479851,37.35453],"type":"Point"}
}