{
  "type": "Feature",
  "properties": {
    "iso:country":"US",
    "sg:address":"820 Logan St",
    "sg:city":"Louisville",
    "sg:classifiers":[
        {
            "category":"Restaurant",
            "type":"Food & Drink"
        }
    ],
    "sg:phone":"+1 502 454 4383",
    "sg:postcode":"40204",
    "sg:province":"KY",
    "sg:website":"www.jicamagrill.com",
    "wof:name":"Jicama Grill",
    "wof:placetype":"venue"
},
  "geometry": {"coordinates":[-85.739059,38.24006],"type":"Point"}
}