{
  "type": "Feature",
  "properties": {
    "addr:full":"2126 State Hwy 384 Mayfield KY 42066",
    "addr:housenumber":"2126",
    "addr:postcode":"42066",
    "addr:street":"State Hwy 384",
    "iso:country":"US",
    "sg:address":"2126 State Hwy 384",
    "sg:city":"Mayfield",
    "sg:classifiers":[
        {
            "category":"Organizations",
            "subcategory":"Religious Organization",
            "type":"Services"
        }
    ],
    "sg:phone":"+1 270 623 8230",
    "sg:postcode":"42066",
    "sg:province":"KY",
    "wof:name":"Macedonia Church of Christ",
    "wof:placetype":"venue"
},
  "geometry": {"coordinates":[-88.743155,36.741467],"type":"Point"}
}