{
  "type": "Feature",
  "properties": {
    "iso:country":"US",
    "sg:address":"6733 State Hwy 849 W",
    "sg:city":"Cunningham",
    "sg:classifiers":[
        {
            "category":"Retail",
            "subcategory":"Repair Shop",
            "type":"Services"
        }
    ],
    "sg:phone":"+1 270 674 5525",
    "sg:postcode":"42035",
    "sg:province":"KY",
    "sg:tags":[
        "scooter",
        "motorcycle",
        "motor"
    ],
    "wof:name":"West Kentucky Motorcross",
    "wof:placetype":"venue"
},
  "geometry": {"coordinates":[-88.789372,36.885967],"type":"Point"}
}