{
  "type": "Feature",
  "properties": {
    "addr:full":"5508 Hidden Rd Louisville KY 40291",
    "addr:housenumber":"5508",
    "addr:postcode":"40291",
    "addr:street":"Hidden Rd",
    "iso:country":"US",
    "sg:address":"5508 Hidden Rd",
    "sg:city":"Louisville",
    "sg:classifiers":[
        {
            "category":"Professional",
            "subcategory":"Management & Consulting",
            "type":"Services"
        }
    ],
    "sg:phone":"+1 502 499 6108",
    "sg:postcode":"40291",
    "sg:province":"KY",
    "wof:name":"J&J Management Group Inc",
    "wof:placetype":"venue"
},
  "geometry": {"coordinates":[-85.616916,38.167666],"type":"Point"}
}