{
  "type": "Feature",
  "properties": {
    "iso:country":"US",
    "sg:address":"135 Fairground Rd",
    "sg:city":"Bedford",
    "sg:classifiers":[
        {
            "category":"Real Estate",
            "subcategory":"Real Estate Operator",
            "type":"Services"
        }
    ],
    "sg:phone":"+1 502 255 4909",
    "sg:postcode":"40006",
    "sg:province":"KY",
    "sg:tags":[
        "apartment"
    ],
    "wof:name":"Fairground Place Apartments",
    "wof:placetype":"venue"
},
  "geometry": {"coordinates":[-85.31948199999999,38.598952],"type":"Point"}
}