{
  "type": "Feature",
  "properties": {
    "iso:country":"US",
    "sg:address":"675 Monticello St",
    "sg:city":"Somerset",
    "sg:classifiers":[
        {
            "category":"Banks & Credit Unions",
            "subcategory":"Bank",
            "type":"Services"
        }
    ],
    "sg:phone":"+1 606 676 9600",
    "sg:postcode":"42501",
    "sg:province":"KY",
    "sg:tags":[
        "financing"
    ],
    "wof:name":"First Financial Credits",
    "wof:placetype":"venue"
},
  "geometry": {"coordinates":[-84.61702,37.069405],"type":"Point"}
}