{
  "type": "Feature",
  "properties": {
    "addr:full":"617 Clay St Bowling Green KY 42101",
    "addr:housenumber":"617",
    "addr:postcode":"42101",
    "addr:street":"Clay St",
    "iso:country":"US",
    "sg:address":"617 Clay St",
    "sg:city":"Bowling Green",
    "sg:classifiers":[
        {
            "category":"Manufacturing",
            "subcategory":"Pet Food",
            "type":"Manufacturing & Wholesale Goods"
        }
    ],
    "sg:phone":"+1 270 843 1191",
    "sg:postcode":"42101",
    "sg:province":"KY",
    "sg:tags":[
        "feed"
    ],
    "wof:name":"Lowe's Feed & Grain Inc",
    "wof:placetype":"venue"
},
  "geometry": {"coordinates":[-86.441919,37.000408],"type":"Point"}
}