{
  "type": "Feature",
  "properties": {
    "iso:country":"US",
    "sg:address":"3397 Coral Ridge Rd",
    "sg:city":"Brooks",
    "sg:classifiers":[
        {
            "category":"Personal",
            "subcategory":"Beauty Salon",
            "type":"Services"
        }
    ],
    "sg:phone":"+1 502 957 0320",
    "sg:postcode":"40109",
    "sg:province":"KY",
    "wof:name":"Totally You",
    "wof:placetype":"venue"
},
  "geometry": {"coordinates":[-85.710453,38.059483],"type":"Point"}
}