{
  "type": "Feature",
  "properties": {
    "iso:country":"US",
    "sg:address":"1700 Eastpoint Pkwy",
    "sg:city":"Louisville",
    "sg:classifiers":[
        {
            "category":"Shopping",
            "subcategory":"Department Store",
            "type":"Retail Goods"
        },
        {
            "category":"Home & Garden",
            "subcategory":"Building Materials",
            "type":"Retail Goods"
        },
        {
            "category":"Manufacturing",
            "subcategory":"Building Materials",
            "type":"Manufacturing & Wholesale Goods"
        }
    ],
    "sg:phone":"+1 502 589 8100",
    "sg:postcode":"40223",
    "sg:province":"KY",
    "sg:tags":[
        "product",
        "aluminum"
    ],
    "wof:name":"Aleris",
    "wof:placetype":"venue"
},
  "geometry": {"coordinates":[-85.50456699999999,38.271757],"type":"Point"}
}