{
  "type": "Feature",
  "properties": {
    "iso:country":"US",
    "sg:address":"5710 State Hwy 144",
    "sg:city":"Owensboro",
    "sg:classifiers":[
        {
            "category":"Recreation",
            "type":"Entertainment"
        }
    ],
    "sg:phone":"+1 270 281 5346",
    "sg:postcode":"42303",
    "sg:province":"KY",
    "sg:tags":[
        "parks"
    ],
    "wof:name":"Daviess County Parks & Rec",
    "wof:placetype":"venue"
},
  "geometry": {"coordinates":[-87.027913,37.801211],"type":"Point"}
}