{
  "type": "Feature",
  "properties": {
    "iso:country":"US",
    "sg:address":"2783 Hade Bell Rd",
    "sg:city":"Scottsville",
    "sg:classifiers":[
        {
            "category":"Building & Trades",
            "subcategory":"Construction",
            "type":"Services"
        }
    ],
    "sg:phone":"+1 270 622 7393",
    "sg:postcode":"42164",
    "sg:province":"KY",
    "sg:tags":[
        "roofing",
        "contractor"
    ],
    "wof:name":"Shrum Roofing",
    "wof:placetype":"venue"
},
  "geometry": {"coordinates":[-86.163473,36.705258],"type":"Point"}
}