{
  "type": "Feature",
  "properties": {
    "addr:full":"711 W Saint Catherine St Louisville KY 40203",
    "addr:housenumber":"711",
    "addr:postcode":"40203",
    "addr:street":"W Saint Catherine St",
    "iso:country":"US",
    "sg:address":"711 W Saint Catherine St",
    "sg:city":"Louisville",
    "sg:classifiers":[
        {
            "category":"Organizations",
            "subcategory":"Religious Organization",
            "type":"Services"
        }
    ],
    "sg:phone":"+1 502 584 5978",
    "sg:postcode":"40203",
    "sg:province":"KY",
    "sg:tags":[
        "church"
    ],
    "wof:name":"Mt Moriah Baptist Church",
    "wof:placetype":"venue"
},
  "geometry": {"coordinates":[-85.76640500000001,38.237962],"type":"Point"}
}