{
  "type": "Feature",
  "properties": {
    "iso:country":"US",
    "sg:address":"5313 Madison Pike",
    "sg:city":"Independence",
    "sg:classifiers":[
        {
            "category":"Recreation",
            "type":"Entertainment"
        }
    ],
    "sg:phone":"+1 859 363 4313",
    "sg:postcode":"41051",
    "sg:province":"KY",
    "sg:tags":[
        "hall",
        "auditorium"
    ],
    "wof:name":"St Cecilia Social Hall",
    "wof:placetype":"venue"
},
  "geometry": {"coordinates":[-84.544338,38.938401],"type":"Point"}
}