{
  "type": "Feature",
  "properties": {
    "addr:full":"1405 S 3rd St Paducah KY 42001",
    "addr:housenumber":"1405",
    "addr:postcode":"42001",
    "addr:street":"S 3Rd St",
    "iso:country":"US",
    "sg:address":"1405 S 3rd St",
    "sg:city":"Paducah",
    "sg:classifiers":[
        {
            "category":"Organizations",
            "subcategory":"Non-profit Organization",
            "type":"Services"
        }
    ],
    "sg:phone":"+1 270 442 9131",
    "sg:postcode":"42001",
    "sg:province":"KY",
    "sg:tags":[
        "info",
        "addiction",
        "abuse",
        "treatment",
        "drug"
    ],
    "wof:name":"Four Rivers Behavioral Health",
    "wof:placetype":"venue"
},
  "geometry": {"coordinates":[-88.587648,37.0725],"type":"Point"}
}