{
  "type": "Feature",
  "properties": {
    "addr:full":"6 McKee Ln Burdine KY 41501",
    "addr:housenumber":"6",
    "addr:postcode":"41501",
    "addr:street":"Mckee Ln",
    "iso:country":"US",
    "sg:address":"6 McKee Ln",
    "sg:city":"Burdine",
    "sg:classifiers":[
        {
            "category":"Organizations",
            "subcategory":"Religious Organization",
            "type":"Services"
        }
    ],
    "sg:phone":"+1 606 639 8939",
    "sg:postcode":"41501",
    "sg:province":"KY",
    "sg:tags":[
        "church"
    ],
    "wof:name":"Peeks Branch Alliance Church",
    "wof:placetype":"venue"
},
  "geometry": {"coordinates":[-82.503354,37.430684],"type":"Point"}
}