{
  "type": "Feature",
  "properties": {
    "iso:country":"US",
    "sg:address":"310 Highland Ave",
    "sg:city":"Carrollton",
    "sg:classifiers":[
        {
            "category":"Organizations",
            "subcategory":"Religious Organization",
            "type":"Services"
        }
    ],
    "sg:phone":"+1 502 732 8886",
    "sg:postcode":"41008",
    "sg:province":"KY",
    "sg:tags":[
        "church"
    ],
    "wof:name":"United Methodist Church",
    "wof:placetype":"venue"
},
  "geometry": {"coordinates":[-85.18312899999999,38.680771],"type":"Point"}
}