{
  "type": "Feature",
  "properties": {
    "iso:country":"US",
    "sg:address":"13 W Broadway St",
    "sg:city":"Winchester",
    "sg:classifiers":[
        {
            "category":"Organizations",
            "subcategory":"Religious Organization",
            "type":"Services"
        }
    ],
    "sg:phone":"+1 859 745 0700",
    "sg:postcode":"40391",
    "sg:province":"KY",
    "sg:tags":[
        "church"
    ],
    "wof:name":"Ark Of Mercy Mission",
    "wof:placetype":"venue"
},
  "geometry": {"coordinates":[-84.177331,37.993679],"type":"Point"}
}