{
  "type": "Feature",
  "properties": {
    "addr:full":"11003 Raider Hollow Rd Upton KY 42784",
    "addr:housenumber":"11003",
    "addr:postcode":"42784",
    "addr:street":"Raider Hollow Rd",
    "iso:country":"US",
    "sg:address":"11003 Raider Hollow Rd",
    "sg:city":"Upton",
    "sg:classifiers":[
        {
            "category":"Building & Trades",
            "subcategory":"Construction",
            "type":"Services"
        }
    ],
    "sg:phone":"+1 270 369 9641",
    "sg:postcode":"42784",
    "sg:province":"KY",
    "sg:tags":[
        "concrete",
        "contractor"
    ],
    "wof:name":"Priddy's Concrete Construction",
    "wof:placetype":"venue"
},
  "geometry": {"coordinates":[-86.011625,37.420544],"type":"Point"}
}