{
  "type": "Feature",
  "properties": {
    "iso:country":"US",
    "sg:address":"10300 Deering Rd",
    "sg:city":"Valley Station",
    "sg:classifiers":[
        {
            "category":"Restaurant",
            "type":"Food & Drink"
        }
    ],
    "sg:phone":"+1 502 933 3429",
    "sg:postcode":"40272",
    "sg:province":"KY",
    "sg:tags":[
        "parlor",
        "ice",
        "cream"
    ],
    "wof:name":"Valley Dairy Freeze",
    "wof:placetype":"venue"
},
  "geometry": {"coordinates":[-85.861093,38.102615],"type":"Point"}
}