{
  "type": "Feature",
  "properties": {
    "iso:country":"US",
    "sg:address":"3457 Birkenhead Dr",
    "sg:city":"Lexington",
    "sg:classifiers":[
        {
            "category":"Wholesale",
            "subcategory":"Farm Supplies",
            "type":"Manufacturing & Wholesale Goods"
        }
    ],
    "sg:phone":"+1 859 245 5304",
    "sg:postcode":"40503",
    "sg:province":"KY",
    "wof:name":"Yard Aquatics LLC",
    "wof:placetype":"venue"
},
  "geometry": {"coordinates":[-84.55327699999999,37.990136],"type":"Point"}
}