{
  "type": "Feature",
  "properties": {
    "iso:country":"US",
    "sg:address":"425 Highway 406",
    "sg:city":"Stinnett",
    "sg:classifiers":[
        {
            "category":"Wholesale",
            "subcategory":"Hardware",
            "type":"Manufacturing & Wholesale Goods"
        },
        {
            "category":"Home & Garden",
            "subcategory":"Garden Supply",
            "type":"Retail Goods"
        },
        {
            "category":"Retail",
            "subcategory":"Repair Shop",
            "type":"Services"
        }
    ],
    "sg:phone":"+1 606 374 3718",
    "sg:postcode":"40868",
    "sg:province":"KY",
    "sg:tags":[
        "renting",
        "lawn",
        "outdoor",
        "power",
        "landscaping",
        "equipment-sales",
        "equipment",
        "saw"
    ],
    "sg:website":"http://www.stihlusa.com/",
    "wof:name":"Al's Discount Store",
    "wof:placetype":"venue"
},
  "geometry": {"coordinates":[-83.397746,37.092613],"type":"Point"}
}