{
  "type": "Feature",
  "properties": {
    "addr:full":"2140 Bonnycastle Ave Louisville KY 40205",
    "addr:housenumber":"2140",
    "addr:postcode":"40205",
    "addr:street":"Bonnycastle Ave",
    "iso:country":"US",
    "sg:address":"2140 Bonnycastle Ave",
    "sg:city":"Louisville",
    "sg:classifiers":[
        {
            "category":"Professional",
            "subcategory":"Art Services",
            "type":"Services"
        }
    ],
    "sg:phone":"+1 502 451 8578",
    "sg:postcode":"40205",
    "sg:province":"KY",
    "sg:tags":[
        "commercial",
        "design"
    ],
    "wof:name":"Lark Studio Inc",
    "wof:placetype":"venue"
},
  "geometry": {"coordinates":[-85.702287,38.231906],"type":"Point"}
}