{
  "type": "Feature",
  "properties": {
    "iso:country":"US",
    "sg:address":"8400 Preston Hwy",
    "sg:city":"Louisville",
    "sg:classifiers":[
        {
            "category":"Retail",
            "subcategory":"Auto Repair",
            "type":"Services"
        }
    ],
    "sg:phone":"+1 502 964 9446",
    "sg:postcode":"40219",
    "sg:province":"KY",
    "sg:tags":[
        "transmission"
    ],
    "wof:name":"Performance Transmissions",
    "wof:placetype":"venue"
},
  "geometry": {"coordinates":[-85.68416499999999,38.133767],"type":"Point"}
}