{
  "type": "Feature",
  "properties": {
    "iso:country":"US",
    "sg:address":"49 Bonnie Blvd",
    "sg:city":"Springfield",
    "sg:classifiers":[
        {
            "category":"Insurance",
            "subcategory":"Insurance Agent",
            "type":"Services"
        }
    ],
    "sg:phone":"+1 859 336 7944",
    "sg:postcode":"40069",
    "sg:province":"KY",
    "wof:name":"Shelter Insurance",
    "wof:placetype":"venue"
},
  "geometry": {"coordinates":[-85.222303,37.697609],"type":"Point"}
}