{
  "type": "Feature",
  "properties": {
    "addr:full":"2224 Main St W Ashland KY 41102",
    "addr:housenumber":"2224",
    "addr:postcode":"41102",
    "addr:street":"Main St W",
    "iso:country":"US",
    "sg:address":"2224 Main St W",
    "sg:city":"Ashland",
    "sg:classifiers":[
        {
            "category":"Organizations",
            "subcategory":"Professional Association",
            "type":"Services"
        }
    ],
    "sg:phone":"+1 606 325 2624",
    "sg:postcode":"41102",
    "sg:province":"KY",
    "sg:tags":[
        "business"
    ],
    "wof:name":"Westwood Boy's Club",
    "wof:placetype":"venue"
},
  "geometry": {"coordinates":[-82.675566,38.479896],"type":"Point"}
}