{
  "type": "Feature",
  "properties": {
    "iso:country":"US",
    "sg:address":"4007 River Rd",
    "sg:city":"St Matthews",
    "sg:classifiers":[
        {
            "category":"Organizations",
            "subcategory":"Religious Organization",
            "type":"Services"
        }
    ],
    "sg:phone":"+1 502 893 9466",
    "sg:postcode":"40207",
    "sg:province":"KY",
    "sg:tags":[
        "church"
    ],
    "wof:name":"Islamic Cultural Ctr",
    "wof:placetype":"venue"
},
  "geometry": {"coordinates":[-85.677702,38.292183],"type":"Point"}
}