{
  "type": "Feature",
  "properties": {
    "iso:country":"US",
    "sg:address":"254 Moody Rd",
    "sg:city":"Franklin",
    "sg:classifiers":[
        {
            "category":"Retail",
            "subcategory":"Repair Shop",
            "type":"Services"
        }
    ],
    "sg:phone":"+1 270 586 3926",
    "sg:postcode":"42134",
    "sg:province":"KY",
    "sg:tags":[
        "welding"
    ],
    "wof:name":"K B Welding",
    "wof:placetype":"venue"
},
  "geometry": {"coordinates":[-86.625513,36.783257],"type":"Point"}
}