{
  "type": "Feature",
  "properties": {
    "addr:full":"5383 US Hwy 27 Somerset KY 42501",
    "addr:housenumber":"5383",
    "addr:postcode":"42501",
    "addr:street":"Us Hwy 27",
    "iso:country":"US",
    "sg:address":"5383 US Hwy 27",
    "sg:city":"Somerset",
    "sg:classifiers":[
        {
            "category":"Real Estate",
            "subcategory":"Real Estate Agent",
            "type":"Services"
        }
    ],
    "sg:phone":"+1 606 561 5691",
    "sg:postcode":"42501",
    "sg:province":"KY",
    "sg:website":"www.coldwellbanker.com",
    "wof:name":"Coldwell Banker Foster Rl Est",
    "wof:placetype":"venue"
},
  "geometry": {"coordinates":[-84.62708000000001,37.029533],"type":"Point"}
}