{
  "type": "Feature",
  "properties": {
    "addr:full":"110 Hillcrest Dr Madisonville KY 42431",
    "addr:housenumber":"110",
    "addr:postcode":"42431",
    "addr:street":"Hillcrest Dr",
    "iso:country":"US",
    "sg:address":"110 Hillcrest Dr",
    "sg:city":"Madisonville",
    "sg:classifiers":[
        {
            "category":"Building & Trades",
            "subcategory":"Plumbing",
            "type":"Services"
        }
    ],
    "sg:phone":"+1 270 825 0303",
    "sg:postcode":"42431",
    "sg:province":"KY",
    "sg:tags":[
        "plumbing",
        "contractor"
    ],
    "wof:name":"Thompson Plumbing",
    "wof:placetype":"venue"
},
  "geometry": {"coordinates":[-87.481369,37.392545],"type":"Point"}
}