{
  "type": "Feature",
  "properties": {
    "iso:country":"US",
    "sg:address":"6454 US Hwy 41A",
    "sg:city":"Henderson",
    "sg:classifiers":[
        {
            "category":"Utilities",
            "subcategory":"Mobile Phone",
            "type":"Services"
        }
    ],
    "sg:phone":"+1 270 830 8854",
    "sg:postcode":"42420",
    "sg:province":"KY",
    "sg:tags":[
        "telephone",
        "cellular"
    ],
    "wof:name":"Verizon Wireless Cell Tower",
    "wof:placetype":"venue"
},
  "geometry": {"coordinates":[-87.621005,37.774095],"type":"Point"}
}