{
  "type": "Feature",
  "properties": {
    "iso:country":"US",
    "sg:address":"227 Fairfield Ave",
    "sg:city":"Bellevue",
    "sg:classifiers":[
        {
            "category":"Manufacturing",
            "subcategory":"Apparel",
            "type":"Manufacturing & Wholesale Goods"
        }
    ],
    "sg:phone":"+1 859 581 3312",
    "sg:postcode":"41073",
    "sg:province":"KY",
    "wof:name":"Kennedys Specialty & EMB",
    "wof:placetype":"venue"
},
  "geometry": {"coordinates":[-84.484205,39.105559],"type":"Point"}
}