{
  "type": "Feature",
  "properties": {
    "iso:country":"US",
    "sg:address":"1486 Buffalo Rd",
    "sg:city":"Annville",
    "sg:phone":"+1 606 364 5665",
    "sg:postcode":"40402",
    "sg:province":"KY",
    "sg:tags":[
        "farm",
        "tobacco"
    ],
    "wof:name":"Ronnie Bowling",
    "wof:placetype":"venue"
},
  "geometry": {"coordinates":[-83.978646,37.257447],"type":"Point"}
}