{
  "type": "Feature",
  "properties": {
    "iso:country":"US",
    "sg:address":"7456 Burlington Pike",
    "sg:city":"Florence",
    "sg:classifiers":[
        {
            "category":"Autos & Motor Vehicles",
            "subcategory":"Automobile Sales",
            "type":"Retail Goods"
        }
    ],
    "sg:phone":"+1 859 746 3673",
    "sg:postcode":"41042",
    "sg:province":"KY",
    "sg:tags":[
        "car",
        "dealer"
    ],
    "wof:name":"John Nolan Superstore",
    "wof:placetype":"venue"
},
  "geometry": {"coordinates":[-84.641813,39.000853],"type":"Point"}
}