{
  "type": "Feature",
  "properties": {
    "addr:full":"4325 Gateway Dr Owensboro KY 42303",
    "addr:housenumber":"4325",
    "addr:postcode":"42303",
    "addr:street":"Gateway Dr",
    "iso:country":"US",
    "sg:address":"4325 Gateway Dr",
    "sg:city":"Owensboro",
    "sg:classifiers":[
        {
            "category":"Professional",
            "subcategory":"Accounting & Tax Preparation",
            "type":"Services"
        }
    ],
    "sg:phone":"+1 270 684 0300",
    "sg:postcode":"42303",
    "sg:province":"KY",
    "sg:tags":[
        "return",
        "filing"
    ],
    "wof:name":"American Tax Svc Inc",
    "wof:placetype":"venue"
},
  "geometry": {"coordinates":[-87.04161000000001,37.74543],"type":"Point"}
}