{
  "type": "Feature",
  "properties": {
    "iso:country":"US",
    "sg:address":"170 Main St",
    "sg:city":"Campton",
    "sg:classifiers":[
        {
            "category":"Shopping",
            "subcategory":"Florist",
            "type":"Retail Goods"
        }
    ],
    "sg:phone":"+1 606 668 3927",
    "sg:postcode":"41301",
    "sg:province":"KY",
    "wof:name":"Accent On Flowers",
    "wof:placetype":"venue"
},
  "geometry": {"coordinates":[-83.549031,37.734102],"type":"Point"}
}