{
  "type": "Feature",
  "properties": {
    "addr:full":"205 Matthew Dr Mt Washington KY 40047",
    "addr:housenumber":"205",
    "addr:postcode":"40047",
    "addr:street":"Matthew Dr",
    "iso:country":"US",
    "sg:address":"205 Matthew Dr",
    "sg:city":"Mt Washington",
    "sg:classifiers":[
        {
            "category":"Banks & Credit Unions",
            "subcategory":"Bank",
            "type":"Services"
        }
    ],
    "sg:phone":"+1 502 957 6610",
    "sg:postcode":"40047",
    "sg:province":"KY",
    "wof:name":"US Bank",
    "wof:placetype":"venue"
},
  "geometry": {"coordinates":[-85.61129200000001,38.023615],"type":"Point"}
}