{
  "type": "Feature",
  "properties": {
    "iso:country":"US",
    "sg:address":"10 Hud Rd",
    "sg:city":"Winchester",
    "sg:classifiers":[
        {
            "category":"Retail",
            "subcategory":"Auto Repair",
            "type":"Services"
        }
    ],
    "sg:phone":"+1 859 744 7561",
    "sg:postcode":"40391",
    "sg:province":"KY",
    "sg:tags":[
        "truck"
    ],
    "wof:name":"Bob Rayburn Truck Repair",
    "wof:placetype":"venue"
},
  "geometry": {"coordinates":[-84.224164,38.015322],"type":"Point"}
}