{
  "type": "Feature",
  "properties": {
    "addr:full":"100 Executive Park Louisville KY 40207",
    "addr:housenumber":"100",
    "addr:postcode":"40207",
    "addr:street":"Executive Park",
    "iso:country":"US",
    "sg:address":"100 Executive Park",
    "sg:city":"Louisville",
    "sg:classifiers":[
        {
            "category":"Shopping",
            "type":"Retail Goods"
        }
    ],
    "sg:phone":"+1 502 899 3770",
    "sg:postcode":"40207",
    "sg:province":"KY",
    "sg:tags":[
        "limb",
        "artificial"
    ],
    "wof:name":"Hanger Prosthetics & Orthotics",
    "wof:placetype":"venue"
},
  "geometry": {"coordinates":[-85.624118,38.242945],"type":"Point"}
}