{
  "type": "Feature",
  "properties": {
    "iso:country":"US",
    "sg:address":"9510 Aylesbury Dr",
    "sg:city":"Louisville",
    "sg:classifiers":[
        {
            "category":"Professional",
            "subcategory":"Management & Consulting",
            "type":"Services"
        }
    ],
    "sg:phone":"+1 502 425 6746",
    "sg:postcode":"40242",
    "sg:province":"KY",
    "sg:tags":[
        "construction"
    ],
    "wof:name":"Ridgeway Construction Svc",
    "wof:placetype":"venue"
},
  "geometry": {"coordinates":[-85.574263,38.283932],"type":"Point"}
}