{
  "type": "Feature",
  "properties": {
    "iso:country":"US",
    "sg:address":"270 Shiloh Rd",
    "sg:city":"Corinth",
    "sg:classifiers":[
        {
            "category":"Professional",
            "subcategory":"Business Services",
            "type":"Services"
        }
    ],
    "sg:phone":"+1 859 823 9000",
    "sg:postcode":"41010",
    "sg:province":"KY",
    "sg:tags":[
        "process",
        "server"
    ],
    "wof:name":"Dedietrich Process Systems",
    "wof:placetype":"venue"
},
  "geometry": {"coordinates":[-84.624246,38.521273],"type":"Point"}
}