{
  "type": "Feature",
  "properties": {
    "iso:country":"US",
    "sg:address":"350 Utterback Rd",
    "sg:city":"Murray",
    "sg:classifiers":[
        {
            "category":"Social Services",
            "subcategory":"Child Care",
            "type":"Services"
        }
    ],
    "sg:phone":"+1 270 753 5050",
    "sg:postcode":"42071",
    "sg:province":"KY",
    "wof:name":"Busy Bee's Child Care",
    "wof:placetype":"venue"
},
  "geometry": {"coordinates":[-88.315585,36.638828],"type":"Point"}
}