{
  "type": "Feature",
  "properties": {
    "addr:full":"745 W Main St Louisville KY 40202",
    "addr:housenumber":"745",
    "addr:postcode":"40202",
    "addr:street":"W Main St",
    "iso:country":"US",
    "sg:address":"745 W Main St",
    "sg:city":"Louisville",
    "sg:classifiers":[
        {
            "category":"Professional",
            "subcategory":"Engineering",
            "type":"Services"
        }
    ],
    "sg:phone":"+1 502 589 6615",
    "sg:postcode":"40202",
    "sg:province":"KY",
    "wof:name":"Stanley D Lindsey & Associates",
    "wof:placetype":"venue"
},
  "geometry": {"coordinates":[-85.76255399999999,38.257333],"type":"Point"}
}