{
  "type": "Feature",
  "properties": {
    "addr:full":"8900 Greeneway Commons Pl Louisville KY 40220",
    "addr:housenumber":"8900",
    "addr:postcode":"40220",
    "addr:street":"Greeneway Commons Pl",
    "iso:country":"US",
    "sg:address":"8900 Greeneway Commons Pl",
    "sg:city":"Louisville",
    "sg:classifiers":[
        {
            "category":"Organizations",
            "subcategory":"Community Association",
            "type":"Services"
        }
    ],
    "sg:phone":"+1 502 491 1056",
    "sg:postcode":"40220",
    "sg:province":"KY",
    "sg:tags":[
        "club"
    ],
    "sg:website":"www.kytennis.com",
    "wof:name":"Kentucky Tennis Assoc Inc",
    "wof:placetype":"venue"
},
  "geometry": {"coordinates":[-85.59795099999999,38.213865],"type":"Point"}
}