{
  "type": "Feature",
  "properties": {
    "iso:country":"US",
    "sg:address":"2456 Palumbo Dr",
    "sg:city":"Lexington",
    "sg:classifiers":[
        {
            "category":"Wholesale",
            "subcategory":"Farm Supplies",
            "type":"Manufacturing & Wholesale Goods"
        }
    ],
    "sg:phone":"+1 859 269 8803",
    "sg:postcode":"40509",
    "sg:province":"KY",
    "sg:tags":[
        "fertilizer"
    ],
    "wof:name":"Lesco Service Ctr",
    "wof:placetype":"venue"
},
  "geometry": {"coordinates":[-84.440608,38.014459],"type":"Point"}
}