{
  "type": "Feature",
  "properties": {
    "iso:country":"US",
    "sg:address":"519 S 3rd St",
    "sg:city":"Louisville",
    "sg:classifiers":[
        {
            "category":"Personal",
            "subcategory":"Beauty Salon",
            "type":"Services"
        }
    ],
    "sg:phone":"+1 502 584 8800",
    "sg:postcode":"40202",
    "sg:province":"KY",
    "sg:tags":[
        "shop"
    ],
    "wof:name":"Simply Gorgeous",
    "wof:placetype":"venue"
},
  "geometry": {"coordinates":[-85.755837,38.250637],"type":"Point"}
}