{
  "type": "Feature",
  "properties": {
    "iso:country":"US",
    "sg:address":"4345 Kellogg Ave",
    "sg:city":"Cincinnati",
    "sg:classifiers":[
        {
            "category":"Professional",
            "type":"Services"
        }
    ],
    "sg:phone":"+1 513 871 8961",
    "sg:postcode":"45226",
    "sg:province":"OH",
    "sg:tags":[
        "establishment"
    ],
    "wof:name":"Spurlino Materials",
    "wof:placetype":"venue"
},
  "geometry": {"coordinates":[-84.431848,39.100443],"type":"Point"}
}