{
  "type": "Feature",
  "properties": {
    "iso:country":"US",
    "sg:address":"3204 Industrial Pkwy",
    "sg:city":"Calvert City",
    "sg:classifiers":[
        {
            "category":"Manufacturing",
            "subcategory":"Tools & Machinery",
            "type":"Manufacturing & Wholesale Goods"
        }
    ],
    "sg:phone":"+1 270 395 4143",
    "sg:postcode":"42029",
    "sg:province":"KY",
    "sg:tags":[
        "carbon",
        "product",
        "graphite"
    ],
    "wof:name":"Carbide Industries",
    "wof:placetype":"venue"
},
  "geometry": {"coordinates":[-88.34342599999999,37.049583],"type":"Point"}
}