{
  "type": "Feature",
  "properties": {
    "iso:country":"US",
    "sg:address":"638 Monmouth St",
    "sg:city":"Newport",
    "sg:classifiers":[
        {
            "category":"Shopping",
            "subcategory":"Clothing, Apparel, & Fashions",
            "type":"Retail Goods"
        }
    ],
    "sg:phone":"+1 859 655 9419",
    "sg:postcode":"41071",
    "sg:province":"KY",
    "sg:tags":[
        "theatrical",
        "costume"
    ],
    "wof:name":"Costume Gallery",
    "wof:placetype":"venue"
},
  "geometry": {"coordinates":[-84.492794,39.090749],"type":"Point"}
}