{
  "type": "Feature",
  "properties": {
    "addr:full":"3358 Nevius Dr Lexington KY 40513",
    "addr:housenumber":"3358",
    "addr:postcode":"40513",
    "addr:street":"Nevius Dr",
    "iso:country":"US",
    "sg:address":"3358 Nevius Dr",
    "sg:city":"Lexington",
    "sg:classifiers":[
        {
            "category":"Mining & Drilling",
            "type":"Manufacturing & Wholesale Goods"
        }
    ],
    "sg:phone":"+1 859 223 7232",
    "sg:postcode":"40513",
    "sg:province":"KY",
    "sg:tags":[
        "oil",
        "gas",
        "producer"
    ],
    "wof:name":"Ohio Kentucky Oil Corp",
    "wof:placetype":"venue"
},
  "geometry": {"coordinates":[-84.561168,38.010244],"type":"Point"}
}