{
  "type": "Feature",
  "properties": {
    "addr:full":"3089 Dixie Hwy Erlanger KY 41018",
    "addr:housenumber":"3089",
    "addr:postcode":"41018",
    "addr:street":"Dixie Hwy",
    "iso:country":"US",
    "sg:address":"3089 Dixie Hwy",
    "sg:city":"Erlanger",
    "sg:classifiers":[
        {
            "category":"Shopping",
            "subcategory":"Gifts & Souvenirs",
            "type":"Retail Goods"
        }
    ],
    "sg:phone":"+1 859 341 7460",
    "sg:postcode":"41018",
    "sg:province":"KY",
    "sg:tags":[
        "stationery"
    ],
    "wof:name":"Paperphanalia",
    "wof:placetype":"venue"
},
  "geometry": {"coordinates":[-84.58651,39.021919],"type":"Point"}
}