{
  "type": "Feature",
  "properties": {
    "addr:full":"93 Shawnee Dr Hodgenville KY 42748",
    "addr:housenumber":"93",
    "addr:postcode":"42748",
    "addr:street":"Shawnee Dr",
    "iso:country":"US",
    "sg:address":"93 Shawnee Dr",
    "sg:city":"Hodgenville",
    "sg:classifiers":[
        {
            "category":"Banks & Credit Unions",
            "subcategory":"Bank",
            "type":"Services"
        }
    ],
    "sg:phone":"+1 270 358 4314",
    "sg:postcode":"42748",
    "sg:province":"KY",
    "wof:name":"Citizens Union Bank",
    "wof:placetype":"venue"
},
  "geometry": {"coordinates":[-85.733548,37.579014],"type":"Point"}
}