{
  "type": "Feature",
  "properties": {
    "iso:country":"US",
    "sg:address":"1835 Campbellsville Rd",
    "sg:city":"Lebanon",
    "sg:classifiers":[
        {
            "category":"Government",
            "subcategory":"Office",
            "type":"Public Place"
        }
    ],
    "sg:phone":"+1 270 692 2004",
    "sg:postcode":"40033",
    "sg:province":"KY",
    "sg:tags":[
        "county"
    ],
    "wof:name":"Marion County Water District",
    "wof:placetype":"venue"
},
  "geometry": {"coordinates":[-85.28074700000001,37.556911],"type":"Point"}
}