{
  "type": "Feature",
  "properties": {
    "iso:country":"US",
    "sg:address":"5041 Boswell Rd",
    "sg:city":"Owensboro",
    "sg:classifiers":[
        {
            "category":"Autos & Motor Vehicles",
            "subcategory":"Motorcycle Sales",
            "type":"Retail Goods"
        }
    ],
    "sg:phone":"+1 270 684 5867",
    "sg:postcode":"42301",
    "sg:province":"KY",
    "sg:tags":[
        "scooter"
    ],
    "wof:name":"Moto Works",
    "wof:placetype":"venue"
},
  "geometry": {"coordinates":[-87.29233499999999,37.743588],"type":"Point"}
}