{
  "type": "Feature",
  "properties": {
    "iso:country":"US",
    "sg:address":"925 Red Mile Ct",
    "sg:city":"Lexington",
    "sg:classifiers":[
        {
            "category":"Wholesale",
            "subcategory":"Computers",
            "type":"Manufacturing & Wholesale Goods"
        }
    ],
    "sg:phone":"+1 502 314 3997",
    "sg:postcode":"40504",
    "sg:province":"KY",
    "sg:tags":[
        "product",
        "seller"
    ],
    "wof:name":"Johnny Blaze Inc",
    "wof:placetype":"venue"
},
  "geometry": {"coordinates":[-84.52481,38.041017],"type":"Point"}
}