{
  "type": "Feature",
  "properties": {
    "addr:full":"10 Legion Rd Paris KY 40361",
    "addr:housenumber":"10",
    "addr:postcode":"40361",
    "addr:street":"Legion Rd",
    "iso:country":"US",
    "sg:address":"10 Legion Rd",
    "sg:city":"Paris",
    "sg:classifiers":[
        {
            "category":"Freight",
            "type":"Transportation"
        }
    ],
    "sg:phone":"+1 859 987 2754",
    "sg:postcode":"40361",
    "sg:province":"KY",
    "sg:tags":[
        "hauling",
        "trucking"
    ],
    "wof:name":"Roeder Cartage Co",
    "wof:placetype":"venue"
},
  "geometry": {"coordinates":[-84.240161,38.21832],"type":"Point"}
}