{
  "type": "Feature",
  "properties": {
    "iso:country":"US",
    "sg:address":"9 Highland Ave",
    "sg:city":"Fort Thomas",
    "sg:classifiers":[
        {
            "category":"Personal",
            "subcategory":"Barber",
            "type":"Services"
        }
    ],
    "sg:phone":"+1 859 781 3331",
    "sg:postcode":"41075",
    "sg:province":"KY",
    "wof:name":"Shari's On the Av",
    "wof:placetype":"venue"
},
  "geometry": {"coordinates":[-84.4487,39.0784],"type":"Point"}
}