{
  "type": "Feature",
  "properties": {
    "iso:country":"US",
    "sg:address":"973 Hatch St",
    "sg:city":"Cincinnati",
    "sg:classifiers":[
        {
            "category":"Banks & Credit Unions",
            "subcategory":"Financial Services",
            "type":"Services"
        }
    ],
    "sg:phone":"+1 513 304 4200",
    "sg:postcode":"45202",
    "sg:province":"OH",
    "sg:tags":[
        "company",
        "holding"
    ],
    "wof:name":"Deckreal LLC",
    "wof:placetype":"venue"
},
  "geometry": {"coordinates":[-84.496472,39.109153],"type":"Point"}
}