{
  "type": "Feature",
  "properties": {
    "iso:country":"US",
    "sg:address":"493 Blue Sky Pkwy",
    "sg:city":"Lexington",
    "sg:classifiers":[
        {
            "category":"Building & Trades",
            "subcategory":"Construction",
            "type":"Services"
        }
    ],
    "sg:phone":"+1 859 264 7676",
    "sg:postcode":"40509",
    "sg:province":"KY",
    "sg:tags":[
        "home",
        "improvement"
    ],
    "wof:name":"Pro Craft",
    "wof:placetype":"venue"
},
  "geometry": {"coordinates":[-84.373088,37.964082],"type":"Point"}
}