{
  "type": "Feature",
  "properties": {
    "addr:full":"531 Estill Ct Georgetown KY 40324",
    "addr:housenumber":"531",
    "addr:postcode":"40324",
    "addr:street":"Estill Ct",
    "iso:country":"US",
    "sg:address":"531 Estill Ct",
    "sg:city":"Georgetown",
    "sg:classifiers":[
        {
            "category":"Home & Garden",
            "subcategory":"Hardware",
            "type":"Retail Goods"
        }
    ],
    "sg:phone":"+1 502 863 2951",
    "sg:postcode":"40324",
    "sg:province":"KY",
    "wof:name":"Lush Inc",
    "wof:placetype":"venue"
},
  "geometry": {"coordinates":[-84.557596,38.205549],"type":"Point"}
}