{
  "type": "Feature",
  "properties": {
    "addr:full":"6301 Midland Industrial Dr Shelbyville KY 40065",
    "addr:housenumber":"6301",
    "addr:postcode":"40065",
    "addr:street":"Midland Industrial Dr",
    "iso:country":"US",
    "sg:address":"6301 Midland Industrial Dr",
    "sg:city":"Shelbyville",
    "sg:classifiers":[
        {
            "category":"Professional",
            "type":"Services"
        },
        {
            "category":"Manufacturing",
            "subcategory":"Tools & Machinery",
            "type":"Manufacturing & Wholesale Goods"
        }
    ],
    "sg:phone":"+1 502 633 7330",
    "sg:postcode":"40065",
    "sg:province":"KY",
    "sg:tags":[
        "establishment",
        "stampings",
        "metal",
        "mfg"
    ],
    "wof:name":"Noble Metal Processing Midwest",
    "wof:placetype":"venue"
},
  "geometry": {"coordinates":[-85.25283399999999,38.221188],"type":"Point"}
}