{
  "type": "Feature",
  "properties": {
    "addr:full":"5462 New Cut Rd Louisville KY 40214",
    "addr:housenumber":"5462",
    "addr:postcode":"40214",
    "addr:street":"New Cut Rd",
    "iso:country":"US",
    "sg:address":"5462 New Cut Rd",
    "sg:city":"Louisville",
    "sg:classifiers":[
        {
            "category":"Restaurant",
            "type":"Food & Drink"
        }
    ],
    "sg:menulink":"http://www.allmenus.com/ky/jefferson-southwest/176038-kfc---kentucky-fried-chicken/menu/",
    "sg:phone":"+1 502 361 1671",
    "sg:postcode":"40214",
    "sg:province":"KY",
    "sg:tags":[
        "american",
        "chicken"
    ],
    "wof:name":"KFC - Kentucky Fried Chicken",
    "wof:placetype":"venue"
},
  "geometry": {"coordinates":[-85.77565800000001,38.147283],"type":"Point"}
}