{
  "type": "Feature",
  "properties": {
    "iso:country":"US",
    "sg:address":"2612 S English Station Rd",
    "sg:city":"Louisville",
    "sg:classifiers":[
        {
            "category":"Sports & Exercise",
            "subcategory":"Stables",
            "type":"Entertainment"
        }
    ],
    "sg:phone":"+1 502 267 0833",
    "sg:postcode":"40299",
    "sg:province":"KY",
    "sg:tags":[
        "riding",
        "academy"
    ],
    "wof:name":"Louisville Equestrian Center",
    "wof:placetype":"venue"
},
  "geometry": {"coordinates":[-85.478579,38.199261],"type":"Point"}
}