{
  "type": "Feature",
  "properties": {
    "addr:full":"119 Creekside Dr Georgetown KY 40324",
    "addr:housenumber":"119",
    "addr:postcode":"40324",
    "addr:street":"Creekside Dr",
    "iso:country":"US",
    "sg:address":"119 Creekside Dr",
    "sg:city":"Georgetown",
    "sg:classifiers":[
        {
            "category":"Professional",
            "subcategory":"Management & Consulting",
            "type":"Services"
        },
        {
            "category":"Farming",
            "subcategory":"Farm & Veterinary Services",
            "type":"Manufacturing & Wholesale Goods"
        }
    ],
    "sg:phone":"+1 502 863 0513",
    "sg:postcode":"40324",
    "sg:province":"KY",
    "sg:tags":[
        "nutritionist",
        "consultant",
        "dairy",
        "for",
        "cattle"
    ],
    "wof:name":"Southeast Dairy Consulting",
    "wof:placetype":"venue"
},
  "geometry": {"coordinates":[-84.65992,38.180791],"type":"Point"}
}