{
  "type": "Feature",
  "properties": {
    "iso:country":"US",
    "sg:address":"525 W Main St",
    "sg:city":"Glasgow",
    "sg:classifiers":[
        {
            "category":"Restaurant",
            "type":"Food & Drink"
        }
    ],
    "sg:phone":"+1 270 651 1913",
    "sg:postcode":"42141",
    "sg:province":"KY",
    "sg:tags":[
        "eating"
    ],
    "wof:name":"Big Moose's BBQ & Smokehouse",
    "wof:placetype":"venue"
},
  "geometry": {"coordinates":[-85.918485,36.998448],"type":"Point"}
}