{
  "type": "Feature",
  "properties": {
    "iso:country":"US",
    "sg:address":"132 Flat Lick Rd",
    "sg:city":"Somerset",
    "sg:classifiers":[
        {
            "category":"Organizations",
            "subcategory":"Religious Organization",
            "type":"Services"
        }
    ],
    "sg:phone":"+1 606 274 8008",
    "sg:postcode":"42503",
    "sg:province":"KY",
    "sg:tags":[
        "clergy"
    ],
    "wof:name":"Gerald Ashley",
    "wof:placetype":"venue"
},
  "geometry": {"coordinates":[-84.470817,37.175703],"type":"Point"}
}