{
  "type": "Feature",
  "properties": {
    "addr:full":"7308 Dixie Hwy Florence KY 41042",
    "addr:housenumber":"7308",
    "addr:postcode":"41042",
    "addr:street":"Dixie Hwy",
    "iso:country":"US",
    "sg:address":"7308 Dixie Hwy",
    "sg:city":"Florence",
    "sg:classifiers":[
        {
            "category":"Retail",
            "subcategory":"Repair Shop",
            "type":"Services"
        }
    ],
    "sg:phone":"+1 859 525 6077",
    "sg:postcode":"41042",
    "sg:province":"KY",
    "wof:name":"Current Circuits Inc",
    "wof:placetype":"venue"
},
  "geometry": {"coordinates":[-84.625731,38.9962],"type":"Point"}
}