{
  "type": "Feature",
  "properties": {
    "addr:full":"318 Cycle Dr Richmond KY 40475",
    "addr:housenumber":"318",
    "addr:postcode":"40475",
    "addr:street":"Cycle Dr",
    "iso:country":"US",
    "sg:address":"318 Cycle Dr",
    "sg:city":"Richmond",
    "sg:classifiers":[
        {
            "category":"Wholesale",
            "subcategory":"Construction Materials",
            "type":"Manufacturing & Wholesale Goods"
        }
    ],
    "sg:phone":"+1 859 625 0002",
    "sg:postcode":"40475",
    "sg:province":"KY",
    "sg:tags":[
        "concrete",
        "shape",
        "block"
    ],
    "wof:name":"Hinkle Block & Masonry Product",
    "wof:placetype":"venue"
},
  "geometry": {"coordinates":[-84.287859,37.726473],"type":"Point"}
}