{
  "type": "Feature",
  "properties": {
    "iso:country":"US",
    "sg:address":"417 Ellen St",
    "sg:city":"London",
    "sg:classifiers":[
        {
            "category":"Home & Garden",
            "subcategory":"Building Materials",
            "type":"Retail Goods"
        }
    ],
    "sg:phone":"+1 606 864 5733",
    "sg:postcode":"40741",
    "sg:province":"KY",
    "sg:tags":[
        "center"
    ],
    "wof:name":"Bullock Lumber Co",
    "wof:placetype":"venue"
},
  "geometry": {"coordinates":[-84.07499900000001,37.129533],"type":"Point"}
}