{
  "type": "Feature",
  "properties": {
    "iso:country":"US",
    "sg:address":"384 Lakeview Dr",
    "sg:city":"Shepherdsville",
    "sg:classifiers":[
        {
            "category":"Freight",
            "type":"Transportation"
        }
    ],
    "sg:phone":"+1 502 543 5220",
    "sg:postcode":"40165",
    "sg:province":"KY",
    "sg:tags":[
        "general"
    ],
    "wof:name":"Ramey Mini Storage",
    "wof:placetype":"venue"
},
  "geometry": {"coordinates":[-85.65093299999999,38.066324],"type":"Point"}
}