{
  "type": "Feature",
  "properties": {
    "addr:full":"291 N Hubbards Ln Louisville KY 40207",
    "addr:housenumber":"291",
    "addr:postcode":"40207",
    "addr:street":"N Hubbards Ln",
    "iso:country":"US",
    "sg:address":"291 N Hubbards Ln",
    "sg:city":"Louisville",
    "sg:classifiers":[
        {
            "category":"Banks & Credit Unions",
            "subcategory":"Bank",
            "type":"Services"
        }
    ],
    "sg:phone":"+1 502 894 0111",
    "sg:postcode":"40207",
    "sg:province":"KY",
    "sg:tags":[
        "commercial",
        "saving"
    ],
    "sg:website":"https://www.53.com/",
    "wof:name":"Fifth Third Bank",
    "wof:placetype":"venue"
},
  "geometry": {"coordinates":[-85.639875,38.258297],"type":"Point"}
}