{
  "type": "Feature",
  "properties": {
    "iso:country":"US",
    "sg:address":"3433 State Hwy 52",
    "sg:city":"Beattyville",
    "sg:classifiers":[
        {
            "category":"Personal",
            "subcategory":"Beauty Salon",
            "type":"Services"
        }
    ],
    "sg:phone":"+1 606 464 9458",
    "sg:postcode":"41311",
    "sg:province":"KY",
    "wof:name":"Reflections Styling Salon",
    "wof:placetype":"venue"
},
  "geometry": {"coordinates":[-83.73132,37.622649],"type":"Point"}
}