{
  "type": "Feature",
  "properties": {
    "addr:full":"4129 Palmetto Dr Lexington KY 40513",
    "addr:housenumber":"4129",
    "addr:postcode":"40513",
    "addr:street":"Palmetto Dr",
    "iso:country":"US",
    "sg:address":"4129 Palmetto Dr",
    "sg:city":"Lexington",
    "sg:classifiers":[
        {
            "category":"Food & Beverages",
            "subcategory":"Groceries & Convenience Stores",
            "type":"Retail Goods"
        }
    ],
    "sg:phone":"+1 859 224 3539",
    "sg:postcode":"40513",
    "sg:province":"KY",
    "wof:name":"Market Investments",
    "wof:placetype":"venue"
},
  "geometry": {"coordinates":[-84.583744,38.002211],"type":"Point"}
}