{
  "type": "Feature",
  "properties": {
    "iso:country":"US",
    "sg:address":"1536 Winchester Ave",
    "sg:city":"Ashland",
    "sg:classifiers":[
        {
            "category":"Banks & Credit Unions",
            "subcategory":"Bank",
            "type":"Services"
        }
    ],
    "sg:phone":"+1 606 325 4500",
    "sg:postcode":"41101",
    "sg:province":"KY",
    "sg:tags":[
        "loan",
        "real estate"
    ],
    "wof:name":"EZ Mortgage Loans Inc",
    "wof:placetype":"venue"
},
  "geometry": {"coordinates":[-82.63997999999999,38.478814],"type":"Point"}
}