{
  "type": "Feature",
  "properties": {
    "iso:country":"US",
    "sg:address":"300 Acorn Ln",
    "sg:city":"Paducah",
    "sg:classifiers":[
        {
            "category":"Professional",
            "subcategory":"Lawyer & Legal Services",
            "type":"Services"
        }
    ],
    "sg:phone":"+1 270 554 8709",
    "sg:postcode":"42003",
    "sg:province":"KY",
    "sg:tags":[
        "program",
        "analyst"
    ],
    "wof:name":"Kathy J Hogancamp",
    "wof:placetype":"venue"
},
  "geometry": {"coordinates":[-88.659655,37.00964],"type":"Point"}
}