{
  "type": "Feature",
  "properties": {
    "addr:full":"505 W Ormsby Ave Louisville KY 40203",
    "addr:housenumber":"505",
    "addr:postcode":"40203",
    "addr:street":"W Ormsby Ave",
    "iso:country":"US",
    "sg:address":"505 W Ormsby Ave",
    "sg:city":"Louisville",
    "sg:classifiers":[
        {
            "category":"Professional",
            "subcategory":"Lawyer & Legal Services",
            "type":"Services"
        }
    ],
    "sg:phone":"+1 502 637 6000",
    "sg:postcode":"40203",
    "sg:province":"KY",
    "sg:tags":[
        "information",
        "attorney",
        "referral",
        "negligence",
        "practice",
        "liability",
        "plan",
        "malpractice",
        "law"
    ],
    "sg:website":"http://www.franklingrayandwhite.com/",
    "wof:name":"Franklin Gray And White",
    "wof:placetype":"venue"
},
  "geometry": {"coordinates":[-85.76245,38.233015],"type":"Point"}
}