{
  "type": "Feature",
  "properties": {
    "iso:country":"US",
    "sg:address":"3384 Main St",
    "sg:city":"Stamping Ground",
    "sg:classifiers":[
        {
            "category":"Government",
            "subcategory":"Office",
            "type":"Public Place"
        }
    ],
    "sg:phone":"+1 502 535 6223",
    "sg:postcode":"40379",
    "sg:province":"KY",
    "sg:tags":[
        "management"
    ],
    "wof:name":"Stamping Ground City of",
    "wof:placetype":"venue"
},
  "geometry": {"coordinates":[-84.687894,38.272256],"type":"Point"}
}