{
  "type": "Feature",
  "properties": {
    "iso:country":"US",
    "sg:address":"717 W Lexington Ave",
    "sg:city":"Danville",
    "sg:classifiers":[
        {
            "category":"Taxi",
            "type":"Transportation"
        }
    ],
    "sg:phone":"+1 859 236 4443",
    "sg:postcode":"40422",
    "sg:province":"KY",
    "sg:tags":[
        "taxicab"
    ],
    "wof:name":"Danville Boyle County Taxi Svc",
    "wof:placetype":"venue"
},
  "geometry": {"coordinates":[-84.780216,37.649588],"type":"Point"}
}