{
  "type": "Feature",
  "properties": {
    "iso:country":"US",
    "sg:address":"187 Old Dover Rd",
    "sg:city":"Cadiz",
    "sg:classifiers":[
        {
            "category":"Organizations",
            "subcategory":"Religious Organization",
            "type":"Services"
        }
    ],
    "sg:phone":"+1 270 522 3958",
    "sg:postcode":"42211",
    "sg:province":"KY",
    "sg:tags":[
        "church"
    ],
    "wof:name":"Liberty Point Baptist Church",
    "wof:placetype":"venue"
},
  "geometry": {"coordinates":[-87.849885,36.846249],"type":"Point"}
}