{
  "type": "Feature",
  "properties": {
    "addr:full":"4803 Southside Dr Louisville KY 40214",
    "addr:housenumber":"4803",
    "addr:postcode":"40214",
    "addr:street":"Southside Dr",
    "iso:country":"US",
    "sg:address":"4803 Southside Dr",
    "sg:city":"Louisville",
    "sg:classifiers":[
        {
            "category":"Social Services",
            "type":"Services"
        }
    ],
    "sg:phone":"+1 502 375 0705",
    "sg:postcode":"40214",
    "sg:province":"KY",
    "sg:tags":[
        "organization",
        "welfare"
    ],
    "wof:name":"Louisville Urban Corps",
    "wof:placetype":"venue"
},
  "geometry": {"coordinates":[-85.76463,38.176689],"type":"Point"}
}