{
  "type": "Feature",
  "properties": {
    "addr:full":"807 W White Oak St Leitchfield KY 42754",
    "addr:housenumber":"807",
    "addr:postcode":"42754",
    "addr:street":"W White Oak St",
    "iso:country":"US",
    "sg:address":"807 W White Oak St",
    "sg:city":"Leitchfield",
    "sg:classifiers":[
        {
            "category":"Restaurant",
            "type":"Food & Drink"
        }
    ],
    "sg:phone":"+1 270 259 6413",
    "sg:postcode":"42754",
    "sg:province":"KY",
    "wof:name":"Kerns Sunbeam Bread",
    "wof:placetype":"venue"
},
  "geometry": {"coordinates":[-86.30887,37.473095],"type":"Point"}
}