{
  "type": "Feature",
  "properties": {
    "addr:full":"102 Crescent Ct Louisville KY 40206",
    "addr:housenumber":"102",
    "addr:postcode":"40206",
    "addr:street":"Crescent Ct",
    "iso:country":"US",
    "sg:address":"102 Crescent Ct",
    "sg:city":"Louisville",
    "sg:classifiers":[
        {
            "category":"Building & Trades",
            "subcategory":"Cleaning & Sanitation",
            "type":"Services"
        }
    ],
    "sg:phone":"+1 502 893 7272",
    "sg:postcode":"40206",
    "sg:province":"KY",
    "sg:tags":[
        "maintenance"
    ],
    "wof:name":"Mighty Mouse Cleaning Service",
    "wof:placetype":"venue"
},
  "geometry": {"coordinates":[-85.686601,38.253694],"type":"Point"}
}