{
  "type": "Feature",
  "properties": {
    "iso:country":"US",
    "sg:address":"407 Tennessee Rd",
    "sg:city":"Albany",
    "sg:classifiers":[
        {
            "category":"Restaurant",
            "type":"Food & Drink"
        }
    ],
    "sg:menulink":"http://www.allmenus.com/ky/albany/157627-taco-maker/menu/",
    "sg:phone":"+1 606 387 8685",
    "sg:postcode":"42602",
    "sg:province":"KY",
    "sg:tags":[
        "mexican"
    ],
    "wof:name":"Taco Maker",
    "wof:placetype":"venue"
},
  "geometry": {"coordinates":[-85.13396299999999,36.687653],"type":"Point"}
}