{
  "type": "Feature",
  "properties": {
    "iso:country":"US",
    "sg:address":"901 E 11th Ave",
    "sg:city":"Bowling Green",
    "sg:classifiers":[
        {
            "category":"Manufacturing",
            "subcategory":"Printing",
            "type":"Manufacturing & Wholesale Goods"
        }
    ],
    "sg:phone":"+1 270 783 4233",
    "sg:postcode":"42101",
    "sg:province":"KY",
    "sg:tags":[
        "printer"
    ],
    "wof:name":"Express Printing",
    "wof:placetype":"venue"
},
  "geometry": {"coordinates":[-86.437866,36.985046],"type":"Point"}
}