{
  "type": "Feature",
  "properties": {
    "iso:country":"US",
    "sg:address":"3705 Flemingsburg Rd",
    "sg:city":"Morehead",
    "sg:classifiers":[
        {
            "category":"Wholesale",
            "subcategory":"Machinery & Supplies",
            "type":"Manufacturing & Wholesale Goods"
        }
    ],
    "sg:phone":"+1 606 784 5555",
    "sg:postcode":"40351",
    "sg:province":"KY",
    "sg:tags":[
        "equipment",
        "sawmill"
    ],
    "wof:name":"Reckart Equipment Co",
    "wof:placetype":"venue"
},
  "geometry": {"coordinates":[-83.479546,38.214042],"type":"Point"}
}