{
  "type": "Feature",
  "properties": {
    "iso:country":"US",
    "sg:address":"4167 Westport Rd",
    "sg:city":"St Matthews",
    "sg:classifiers":[
        {
            "category":"Shopping",
            "type":"Retail Goods"
        }
    ],
    "sg:phone":"+1 502 895 4080",
    "sg:postcode":"40207",
    "sg:province":"KY",
    "sg:tags":[
        "pet",
        "shop"
    ],
    "wof:name":"Haller's Pet Shop",
    "wof:placetype":"venue"
},
  "geometry": {"coordinates":[-85.64798500000001,38.257365],"type":"Point"}
}