{
  "type": "Feature",
  "properties": {
    "iso:country":"US",
    "sg:address":"3814 Frankfort Ave",
    "sg:city":"Louisville",
    "sg:classifiers":[
        {
            "category":"Bars & Pubs",
            "type":"Food & Drink"
        }
    ],
    "sg:phone":"+1 502 895 7351",
    "sg:postcode":"40207",
    "sg:province":"KY",
    "wof:name":"Diamond Pub & Billiards",
    "wof:placetype":"venue"
},
  "geometry": {"coordinates":[-85.656296,38.252887],"type":"Point"}
}