{
  "type": "Feature",
  "properties": {
    "addr:full":"3527 Sample Way Louisville KY 40245",
    "addr:housenumber":"3527",
    "addr:postcode":"40245",
    "addr:street":"Sample Way",
    "iso:country":"US",
    "sg:address":"3527 Sample Way",
    "sg:city":"Louisville",
    "sg:classifiers":[
        {
            "category":"Shopping",
            "subcategory":"Jewelry",
            "type":"Retail Goods"
        }
    ],
    "sg:phone":"+1 502 243 1099",
    "sg:postcode":"40245",
    "sg:province":"KY",
    "sg:tags":[
        "precious",
        "semi-precious",
        "stone"
    ],
    "wof:name":"Idu Jewelry",
    "wof:placetype":"venue"
},
  "geometry": {"coordinates":[-85.50711800000001,38.289829],"type":"Point"}
}