{
  "type": "Feature",
  "properties": {
    "addr:full":"301 Main St Cadiz KY 42211",
    "addr:housenumber":"301",
    "addr:postcode":"42211",
    "addr:street":"Main St",
    "iso:country":"US",
    "sg:address":"301 Main St",
    "sg:city":"Cadiz",
    "sg:classifiers":[
        {
            "category":"Shopping",
            "subcategory":"Computers & Home Electronics",
            "type":"Retail Goods"
        }
    ],
    "sg:phone":"+1 270 522 9442",
    "sg:postcode":"42211",
    "sg:province":"KY",
    "wof:name":"Eddies Computer Sales and Svc",
    "wof:placetype":"venue"
},
  "geometry": {"coordinates":[-87.818417,36.867306],"type":"Point"}
}