{
  "type": "Feature",
  "properties": {
    "iso:country":"US",
    "sg:address":"839 S Park Rd",
    "sg:city":"Elizabethtown",
    "sg:classifiers":[
        {
            "category":"Shopping",
            "subcategory":"Musical Instruments",
            "type":"Retail Goods"
        }
    ],
    "sg:phone":"+1 270 234 1336",
    "sg:postcode":"42701",
    "sg:province":"KY",
    "sg:tags":[
        "piano"
    ],
    "wof:name":"Keyboard Technical Svc",
    "wof:placetype":"venue"
},
  "geometry": {"coordinates":[-85.840282,37.677502],"type":"Point"}
}