{
  "type": "Feature",
  "properties": {
    "iso:country":"US",
    "sg:address":"8413 Calm Ln",
    "sg:city":"Louisville",
    "sg:classifiers":[
        {
            "category":"Building & Trades",
            "subcategory":"Construction",
            "type":"Services"
        }
    ],
    "sg:phone":"+1 502 364 8822",
    "sg:postcode":"40219",
    "sg:province":"KY",
    "sg:tags":[
        "house"
    ],
    "wof:name":"Remodeling By Reid LLC",
    "wof:placetype":"venue"
},
  "geometry": {"coordinates":[-85.693438,38.127727],"type":"Point"}
}