{
  "type": "Feature",
  "properties": {
    "addr:full":"213 Kratz Ln Louisville KY 40243",
    "addr:housenumber":"213",
    "addr:postcode":"40243",
    "addr:street":"Kratz Ln",
    "iso:country":"US",
    "sg:address":"213 Kratz Ln",
    "sg:city":"Louisville",
    "sg:classifiers":[
        {
            "category":"Shopping",
            "subcategory":"Gifts & Souvenirs",
            "type":"Retail Goods"
        }
    ],
    "sg:phone":"+1 502 245 1999",
    "sg:postcode":"40243",
    "sg:province":"KY",
    "sg:tags":[
        "shop"
    ],
    "wof:name":"Ritchiebrt Gifts",
    "wof:placetype":"venue"
},
  "geometry": {"coordinates":[-85.53455,38.248591],"type":"Point"}
}