{
  "type": "Feature",
  "properties": {
    "iso:country":"US",
    "sg:address":"1734 Old Calvert City Rd",
    "sg:city":"Calvert City",
    "sg:classifiers":[
        {
            "category":"Building & Trades",
            "subcategory":"Landscaping Services",
            "type":"Services"
        }
    ],
    "sg:phone":"+1 270 898 8176",
    "sg:postcode":"42029",
    "sg:province":"KY",
    "sg:tags":[
        "landscape"
    ],
    "wof:name":"Moore Landscaping",
    "wof:placetype":"venue"
},
  "geometry": {"coordinates":[-88.470533,37.001345],"type":"Point"}
}