{
  "type": "Feature",
  "properties": {
    "iso:country":"US",
    "sg:address":"717 Bullock Pl",
    "sg:city":"Lexington",
    "sg:classifiers":[
        {
            "category":"Professional",
            "type":"Services"
        }
    ],
    "sg:phone":"+1 859 255 1594",
    "sg:postcode":"40508",
    "sg:province":"KY",
    "wof:name":"Pete Slagel Drilling Services",
    "wof:placetype":"venue"
},
  "geometry": {"coordinates":[-84.483141,38.036459],"type":"Point"}
}