{
  "type": "Feature",
  "properties": {
    "addr:full":"470 Hays Rd N Smiths Grove KY 42171",
    "addr:housenumber":"470",
    "addr:postcode":"42171",
    "addr:street":"Hays Rd N Smiths Grove",
    "iso:country":"US",
    "sg:address":"470 Hays Rd N",
    "sg:city":"Smiths Grove",
    "sg:classifiers":[
        {
            "category":"Farming",
            "subcategory":"Livestock Farm",
            "type":"Manufacturing & Wholesale Goods"
        }
    ],
    "sg:phone":"+1 270 563 4782",
    "sg:postcode":"42171",
    "sg:province":"KY",
    "sg:tags":[
        "co",
        "beef",
        "tobacco",
        "soybean",
        "cattle",
        "feedlot"
    ],
    "wof:name":"David Mc Kinney",
    "wof:placetype":"venue"
},
  "geometry": {"coordinates":[-86.172887,37.044244],"type":"Point"}
}