{
  "type": "Feature",
  "properties": {
    "addr:full":"325 Park Plaza Dr Owensboro KY 42301",
    "addr:housenumber":"325",
    "addr:postcode":"42301",
    "addr:street":"Park Plaza Dr",
    "iso:country":"US",
    "sg:address":"325 Park Plaza Dr",
    "sg:city":"Owensboro",
    "sg:classifiers":[
        {
            "category":"Shopping",
            "subcategory":"Gifts & Souvenirs",
            "type":"Retail Goods"
        }
    ],
    "sg:phone":"+1 270 683 0137",
    "sg:postcode":"42301",
    "sg:province":"KY",
    "sg:tags":[
        "shop"
    ],
    "wof:name":"Patio Gifts & Collectibles",
    "wof:placetype":"venue"
},
  "geometry": {"coordinates":[-87.11369999999999,37.750824],"type":"Point"}
}