{
  "type": "Feature",
  "properties": {
    "iso:country":"US",
    "sg:address":"325 Ann St",
    "sg:city":"Frankfort",
    "sg:classifiers":[
        {
            "category":"Wholesale",
            "subcategory":"Groceries",
            "type":"Manufacturing & Wholesale Goods"
        }
    ],
    "sg:phone":"+1 502 352 2740",
    "sg:postcode":"40601",
    "sg:province":"KY",
    "sg:tags":[
        "beverage"
    ],
    "wof:name":"Kentucky Malt & Beverage Cncl",
    "wof:placetype":"venue"
},
  "geometry": {"coordinates":[-84.876391,38.197882],"type":"Point"}
}