{
  "type": "Feature",
  "properties": {
    "iso:country":"US",
    "sg:address":"2200 Level Green Rd",
    "sg:city":"Corbin",
    "sg:classifiers":[
        {
            "category":"Home & Garden",
            "subcategory":"Garden Supply",
            "type":"Retail Goods"
        }
    ],
    "sg:phone":"+1 606 528 3186",
    "sg:postcode":"40701",
    "sg:province":"KY",
    "sg:tags":[
        "center"
    ],
    "wof:name":"Laurel Landscaping Co",
    "wof:placetype":"venue"
},
  "geometry": {"coordinates":[-84.17224299999999,36.976944],"type":"Point"}
}