{
  "type": "Feature",
  "properties": {
    "addr:full":"690 Indian Creek Rd Virgie KY 41572",
    "addr:housenumber":"690",
    "addr:postcode":"41572",
    "addr:street":"Indian Creek Rd",
    "iso:country":"US",
    "sg:address":"690 Indian Creek Rd",
    "sg:city":"Virgie",
    "sg:classifiers":[
        {
            "category":"Organizations",
            "subcategory":"Religious Organization",
            "type":"Services"
        }
    ],
    "sg:phone":"+1 606 639 8118",
    "sg:postcode":"41572",
    "sg:province":"KY",
    "sg:tags":[
        "church"
    ],
    "wof:name":"Caney Creek Freewill Baptist",
    "wof:placetype":"venue"
},
  "geometry": {"coordinates":[-82.602152,37.34537],"type":"Point"}
}