{
  "type": "Feature",
  "properties": {
    "iso:country":"US",
    "sg:address":"311 Valley View Dr",
    "sg:city":"Radcliff",
    "sg:classifiers":[
        {
            "category":"Restaurant",
            "type":"Food & Drink"
        }
    ],
    "sg:phone":"+1 270 877 7220",
    "sg:postcode":"40160",
    "sg:province":"KY",
    "sg:tags":[
        "caterer"
    ],
    "wof:name":"Cobblestone Cafe & Catering",
    "wof:placetype":"venue"
},
  "geometry": {"coordinates":[-85.952684,37.808556],"type":"Point"}
}