{
  "type": "Feature",
  "properties": {
    "addr:full":"205 W G L Smith St Morgantown KY 42261",
    "addr:housenumber":"205",
    "addr:postcode":"42261",
    "addr:street":"W G L Smith St",
    "iso:country":"US",
    "sg:address":"205 W G L Smith St",
    "sg:city":"Morgantown",
    "sg:classifiers":[
        {
            "category":"Shopping",
            "subcategory":"Pharmacy",
            "type":"Retail Goods"
        }
    ],
    "sg:phone":"+1 270 526 5615",
    "sg:postcode":"42261",
    "sg:province":"KY",
    "wof:name":"Rite Aid Pharmacy",
    "wof:placetype":"venue"
},
  "geometry": {"coordinates":[-86.68625400000001,37.226886],"type":"Point"}
}