{
  "type": "Feature",
  "properties": {
    "iso:country":"US",
    "sg:address":"102 N Main St",
    "sg:city":"Greensburg",
    "sg:classifiers":[
        {
            "category":"Insurance",
            "subcategory":"Insurance Agent",
            "type":"Services"
        }
    ],
    "sg:phone":"+1 270 932 4421",
    "sg:postcode":"42743",
    "sg:province":"KY",
    "wof:name":"Calhoon & Cooke Insurance",
    "wof:placetype":"venue"
},
  "geometry": {"coordinates":[-85.501565,37.261103],"type":"Point"}
}