{
  "type": "Feature",
  "properties": {
    "iso:country":"US",
    "sg:address":"101 Prosperous Pl",
    "sg:city":"Lexington",
    "sg:classifiers":[
        {
            "category":"Health Services",
            "subcategory":"Doctor",
            "type":"Services"
        }
    ],
    "sg:phone":"+1 859 263 1900",
    "sg:postcode":"40509",
    "sg:province":"KY",
    "sg:tags":[
        "physician",
        "surgeon"
    ],
    "sg:website":"www.thoroughbredallergy.salu.net",
    "wof:name":"Thoroughbred Allergy & Asthma",
    "wof:placetype":"venue"
},
  "geometry": {"coordinates":[-84.443946,38.000914],"type":"Point"}
}