{
  "type": "Feature",
  "properties": {
    "addr:full":"118 W Washington St Franklin KY 42134",
    "addr:housenumber":"118",
    "addr:postcode":"42134",
    "addr:street":"W Washington St",
    "iso:country":"US",
    "sg:address":"118 W Washington St",
    "sg:city":"Franklin",
    "sg:classifiers":[
        {
            "category":"Government",
            "subcategory":"Fire Station",
            "type":"Public Place"
        }
    ],
    "sg:phone":"+1 270 651 3339",
    "sg:postcode":"42134",
    "sg:province":"KY",
    "sg:tags":[
        "department"
    ],
    "wof:name":"Park City Fire Dept",
    "wof:placetype":"venue"
},
  "geometry": {"coordinates":[-86.578722,36.724122],"type":"Point"}
}