{
  "type": "Feature",
  "properties": {
    "iso:country":"US",
    "sg:address":"4102 Rivulet Ct",
    "sg:city":"Louisville",
    "sg:classifiers":[
        {
            "category":"Freight",
            "type":"Transportation"
        }
    ],
    "sg:phone":"+1 502 267 0130",
    "sg:postcode":"40299",
    "sg:province":"KY",
    "sg:tags":[
        "delivery"
    ],
    "wof:name":"U S Express Inc",
    "wof:placetype":"venue"
},
  "geometry": {"coordinates":[-85.547015,38.187904],"type":"Point"}
}