{
  "type": "Feature",
  "properties": {
    "iso:country":"US",
    "sg:address":"1564 Diederich Blvd",
    "sg:city":"Russell",
    "sg:classifiers":[
        {
            "category":"Shopping",
            "subcategory":"Clothing, Apparel, & Fashions",
            "type":"Retail Goods"
        }
    ],
    "sg:phone":"+1 606 833 8875",
    "sg:postcode":"41169",
    "sg:province":"KY",
    "sg:tags":[
        "uniform"
    ],
    "wof:name":"Got Scrubs",
    "wof:placetype":"venue"
},
  "geometry": {"coordinates":[-82.708022,38.508765],"type":"Point"}
}