{
  "type": "Feature",
  "properties": {
    "iso:country":"US",
    "sg:address":"811 Monmouth St",
    "sg:city":"Newport",
    "sg:classifiers":[
        {
            "category":"Shopping",
            "subcategory":"Books",
            "type":"Retail Goods"
        }
    ],
    "sg:phone":"+1 859 431 4469",
    "sg:postcode":"41071",
    "sg:province":"KY",
    "sg:tags":[
        "dealer"
    ],
    "wof:name":"Dragon Treasure Books",
    "wof:placetype":"venue"
},
  "geometry": {"coordinates":[-84.490888,39.088968],"type":"Point"}
}