{
  "type": "Feature",
  "properties": {
    "iso:country":"US",
    "sg:address":"417 W Hill St",
    "sg:city":"Louisville",
    "sg:classifiers":[
        {
            "category":"Manufacturing",
            "subcategory":"Electronics",
            "type":"Manufacturing & Wholesale Goods"
        }
    ],
    "sg:phone":"+1 502 634 8001",
    "sg:postcode":"40208",
    "sg:province":"KY",
    "sg:tags":[
        "prerecorded",
        "durable",
        "mfg"
    ],
    "wof:name":"Desperate Attempt Records",
    "wof:placetype":"venue"
},
  "geometry": {"coordinates":[-85.76334199999999,38.22622],"type":"Point"}
}