{
  "type": "Feature",
  "properties": {
    "addr:full":"930 Winchester Rd Lexington KY 40505",
    "addr:housenumber":"930",
    "addr:postcode":"40505",
    "addr:street":"Winchester Rd",
    "iso:country":"US",
    "sg:address":"930 Winchester Rd",
    "sg:city":"Lexington",
    "sg:classifiers":[
        {
            "category":"Wholesale",
            "subcategory":"Machinery & Supplies",
            "type":"Manufacturing & Wholesale Goods"
        }
    ],
    "sg:phone":"+1 859 225 1228",
    "sg:postcode":"40505",
    "sg:province":"KY",
    "sg:tags":[
        "equipment",
        "ride",
        "park",
        "amusement"
    ],
    "wof:name":"Kentucky Game Exchange",
    "wof:placetype":"venue"
},
  "geometry": {"coordinates":[-84.46763900000001,38.041879],"type":"Point"}
}