{
  "type": "Feature",
  "properties": {
    "iso:country":"US",
    "sg:address":"2801 Dixie Hwy",
    "sg:city":"Fort Mitchell",
    "sg:classifiers":[
        {
            "category":"Building & Trades",
            "subcategory":"Construction",
            "type":"Services"
        }
    ],
    "sg:phone":"+1 859 426 5999",
    "sg:postcode":"41017",
    "sg:province":"KY",
    "sg:tags":[
        "general",
        "contractor"
    ],
    "wof:name":"CDI Contractors",
    "wof:placetype":"venue"
},
  "geometry": {"coordinates":[-84.576583,39.028951],"type":"Point"}
}