{
  "type": "Feature",
  "properties": {
    "iso:country":"US",
    "sg:address":"152 Cheyenne Dr",
    "sg:city":"Shelbyville",
    "sg:classifiers":[
        {
            "category":"Freight",
            "type":"Transportation"
        }
    ],
    "sg:phone":"+1 502 633 6341",
    "sg:postcode":"40065",
    "sg:province":"KY",
    "sg:tags":[
        "operator",
        "local",
        "trucking"
    ],
    "wof:name":"Db Trucking Co",
    "wof:placetype":"venue"
},
  "geometry": {"coordinates":[-85.24151500000001,38.226721],"type":"Point"}
}