{
  "type": "Feature",
  "properties": {
    "iso:country":"US",
    "sg:address":"145 College St",
    "sg:city":"Lawrenceburg",
    "sg:classifiers":[
        {
            "category":"Professional",
            "subcategory":"Accounting & Tax Preparation",
            "type":"Services"
        }
    ],
    "sg:phone":"+1 502 839 8112",
    "sg:postcode":"40342",
    "sg:province":"KY",
    "sg:tags":[
        "accountant"
    ],
    "wof:name":"W Dudley Shryock CPA",
    "wof:placetype":"venue"
},
  "geometry": {"coordinates":[-84.894884,38.03572],"type":"Point"}
}