{
  "type": "Feature",
  "properties": {
    "iso:country":"US",
    "sg:address":"105 Lawrence St",
    "sg:city":"Franklin",
    "sg:classifiers":[
        {
            "category":"Retail",
            "subcategory":"Veterinary Services",
            "type":"Services"
        }
    ],
    "sg:phone":"+1 270 586 4438",
    "sg:postcode":"42134",
    "sg:province":"KY",
    "sg:tags":[
        "clinic",
        "hospital",
        "veterinarian",
        "specialty",
        "emergency"
    ],
    "wof:name":"Simpson County Animal Hospital",
    "wof:placetype":"venue"
},
  "geometry": {"coordinates":[-86.577629,36.72795],"type":"Point"}
}