{
  "type": "Feature",
  "properties": {
    "iso:country":"US",
    "sg:address":"294 Lexington Rd",
    "sg:city":"Lancaster",
    "sg:classifiers":[
        {
            "category":"Autos & Motor Vehicles",
            "subcategory":"Fuel & Gas Station",
            "type":"Retail Goods"
        }
    ],
    "sg:phone":"+1 859 792 4344",
    "sg:postcode":"40444",
    "sg:province":"KY",
    "sg:tags":[
        "oil"
    ],
    "wof:name":"Somerset Oil Inc",
    "wof:placetype":"venue"
},
  "geometry": {"coordinates":[-84.57803699999999,37.623376],"type":"Point"}
}