{
  "type": "Feature",
  "properties": {
    "iso:country":"US",
    "sg:address":"2192 Commercial Dr",
    "sg:city":"Frankfort",
    "sg:classifiers":[
        {
            "category":"Manufacturing",
            "subcategory":"Printing",
            "type":"Manufacturing & Wholesale Goods"
        }
    ],
    "sg:phone":"+1 502 875 2745",
    "sg:postcode":"40601",
    "sg:province":"KY",
    "sg:tags":[
        "marking",
        "mfg",
        "commercial",
        "bo",
        "lithographic",
        "devices"
    ],
    "wof:name":"Triangle Printing",
    "wof:placetype":"venue"
},
  "geometry": {"coordinates":[-84.90225,38.156277],"type":"Point"}
}