{
  "type": "Feature",
  "properties": {
    "iso:country":"US",
    "sg:address":"209 S Preston St",
    "sg:city":"Louisville",
    "sg:classifiers":[
        {
            "category":"Bars & Pubs",
            "type":"Food & Drink"
        }
    ],
    "sg:phone":"+1 502 583 6395",
    "sg:postcode":"40202",
    "sg:province":"KY",
    "sg:tags":[
        "lounge",
        "cocktail"
    ],
    "wof:name":"Tryangles Inc",
    "wof:placetype":"venue"
},
  "geometry": {"coordinates":[-85.746095,38.253715],"type":"Point"}
}