{
  "type": "Feature",
  "properties": {
    "iso:country":"US",
    "sg:address":"185 Short Line Pike",
    "sg:city":"Berea",
    "sg:classifiers":[
        {
            "category":"Building & Trades",
            "subcategory":"Construction",
            "type":"Services"
        }
    ],
    "sg:phone":"+1 859 986 3380",
    "sg:postcode":"40403",
    "sg:province":"KY",
    "sg:tags":[
        "heavy"
    ],
    "wof:name":"Alcorns Backhoe Service",
    "wof:placetype":"venue"
},
  "geometry": {"coordinates":[-84.25719700000001,37.565505],"type":"Point"}
}