{
  "type": "Feature",
  "properties": {
    "iso:country":"US",
    "sg:address":"2710 Mobley Mill Rd",
    "sg:city":"Coxs Creek",
    "sg:classifiers":[
        {
            "category":"Food & Beverages",
            "subcategory":"Fruits & Vegetables",
            "type":"Retail Goods"
        }
    ],
    "sg:phone":"+1 502 331 0316",
    "sg:postcode":"40013",
    "sg:province":"KY",
    "wof:name":"Vegetable Market",
    "wof:placetype":"venue"
},
  "geometry": {"coordinates":[-85.52360299999999,37.897646],"type":"Point"}
}