{
  "type": "Feature",
  "properties": {
    "addr:full":"1761 Sharkey Way Lexington KY 40511",
    "addr:housenumber":"1761",
    "addr:postcode":"40511",
    "addr:street":"Sharkey Way",
    "iso:country":"US",
    "sg:address":"1761 Sharkey Way",
    "sg:city":"Lexington",
    "sg:classifiers":[
        {
            "category":"Restaurant",
            "type":"Food & Drink"
        }
    ],
    "sg:menulink":"http://www.allmenus.com/ky/fayette/88637-applebees/menu/",
    "sg:phone":"+1 859 226 6970",
    "sg:postcode":"40511",
    "sg:province":"KY",
    "sg:tags":[
        "burger",
        "american",
        "sandwich",
        "soup"
    ],
    "wof:name":"Applebee's",
    "wof:placetype":"venue"
},
  "geometry": {"coordinates":[-84.530305,38.068169],"type":"Point"}
}