{
  "type": "Feature",
  "properties": {
    "iso:country":"US",
    "sg:address":"7236 S Woodland Dr",
    "sg:city":"Radcliff",
    "sg:classifiers":[
        {
            "category":"Bars & Pubs",
            "type":"Food & Drink"
        }
    ],
    "sg:phone":"+1 270 351 0808",
    "sg:postcode":"40160",
    "sg:province":"KY",
    "sg:tags":[
        "brew"
    ],
    "wof:name":"J Cs Sports Bar And Grill",
    "wof:placetype":"venue"
},
  "geometry": {"coordinates":[-85.92663,37.795812],"type":"Point"}
}