{
  "type": "Feature",
  "properties": {
    "iso:country":"US",
    "sg:address":"3601 Parker Ave",
    "sg:city":"Louisville",
    "sg:classifiers":[
        {
            "category":"Professional",
            "subcategory":"Research",
            "type":"Services"
        },
        {
            "category":"Utilities",
            "subcategory":"Refuse",
            "type":"Services"
        }
    ],
    "sg:phone":"+1 502 776 5502",
    "sg:postcode":"40212",
    "sg:province":"KY",
    "sg:tags":[
        "disposal",
        "waste",
        "commercial",
        "physical"
    ],
    "wof:name":"Midwest Environmental Services",
    "wof:placetype":"venue"
},
  "geometry": {"coordinates":[-85.810942,38.269327],"type":"Point"}
}