{
  "type": "Feature",
  "properties": {
    "iso:country":"US",
    "sg:address":"1225 Greasy Creek Rd",
    "sg:city":"Shelbiana",
    "sg:classifiers":[
        {
            "category":"Food & Beverages",
            "subcategory":"Groceries & Convenience Stores",
            "type":"Retail Goods"
        }
    ],
    "sg:phone":"+1 606 437 7095",
    "sg:postcode":"41562",
    "sg:province":"KY",
    "sg:tags":[
        "grocer"
    ],
    "wof:name":"Thacker's Grocery",
    "wof:placetype":"venue"
},
  "geometry": {"coordinates":[-82.468256,37.405859],"type":"Point"}
}