{
  "type": "Feature",
  "properties": {
    "addr:full":"501 Amy Ave Louisville KY 40211",
    "addr:housenumber":"501",
    "addr:postcode":"40211",
    "addr:street":"Amy Ave",
    "iso:country":"US",
    "sg:address":"501 Amy Ave",
    "sg:city":"Louisville",
    "sg:classifiers":[
        {
            "category":"Organizations",
            "subcategory":"Religious Organization",
            "type":"Services"
        }
    ],
    "sg:phone":"+1 502 774 1425",
    "sg:postcode":"40211",
    "sg:province":"KY",
    "sg:tags":[
        "church"
    ],
    "wof:name":"Greater Christ's Refuge Church",
    "wof:placetype":"venue"
},
  "geometry": {"coordinates":[-85.813789,38.25627],"type":"Point"}
}