{
  "type": "Feature",
  "properties": {
    "addr:full":"1209 E New Circle Rd Lexington KY 40505",
    "addr:housenumber":"1209",
    "addr:postcode":"40505",
    "addr:street":"E New Circle Rd",
    "iso:country":"US",
    "sg:address":"1209 E New Circle Rd",
    "sg:city":"Lexington",
    "sg:classifiers":[
        {
            "category":"Autos & Motor Vehicles",
            "subcategory":"Automobile Sales",
            "type":"Retail Goods"
        }
    ],
    "sg:phone":"+1 859 255 1900",
    "sg:postcode":"40505",
    "sg:province":"KY",
    "sg:tags":[
        "car",
        "dealer"
    ],
    "wof:name":"Motorvation Motor Cars",
    "wof:placetype":"venue"
},
  "geometry": {"coordinates":[-84.452719,38.031862],"type":"Point"}
}