{
  "type": "Feature",
  "properties": {
    "iso:country":"US",
    "sg:address":"4106 Dellridge Dr",
    "sg:city":"Louisville",
    "sg:classifiers":[
        {
            "category":"Health Services",
            "subcategory":"Health Practitioner",
            "type":"Services"
        }
    ],
    "sg:phone":"+1 502 412 8711",
    "sg:postcode":"40207",
    "sg:province":"KY",
    "sg:tags":[
        "pathologist",
        "speech"
    ],
    "wof:name":"Pediatric Rehab Solution",
    "wof:placetype":"venue"
},
  "geometry": {"coordinates":[-85.64596299999999,38.260498],"type":"Point"}
}