{
  "type": "Feature",
  "properties": {
    "addr:full":"30 S Main St Dry Ridge KY 41035",
    "addr:housenumber":"30",
    "addr:postcode":"41035",
    "addr:street":"S Main St",
    "iso:country":"US",
    "sg:address":"30 S Main St",
    "sg:city":"Dry Ridge",
    "sg:classifiers":[
        {
            "category":"Retail",
            "subcategory":"Funeral Services",
            "type":"Services"
        }
    ],
    "sg:phone":"+1 859 823 5641",
    "sg:postcode":"41035",
    "sg:province":"KY",
    "sg:tags":[
        "director"
    ],
    "wof:name":"Eckler-Hudson Funeral Home",
    "wof:placetype":"venue"
},
  "geometry": {"coordinates":[-84.588032,38.681538],"type":"Point"}
}