{
  "type": "Feature",
  "properties": {
    "iso:country":"US",
    "sg:address":"10203 Eve Adam Dr",
    "sg:city":"Louisville",
    "sg:classifiers":[
        {
            "category":"Shopping",
            "subcategory":"Hobbies, Toys, & Games",
            "type":"Retail Goods"
        }
    ],
    "sg:phone":"+1 502 933 5659",
    "sg:postcode":"40272",
    "sg:province":"KY",
    "wof:name":"We Make It Easy LLC",
    "wof:placetype":"venue"
},
  "geometry": {"coordinates":[-85.843138,38.105704],"type":"Point"}
}