{
  "type": "Feature",
  "properties": {
    "iso:country":"US",
    "sg:address":"192 State Hwy 70",
    "sg:city":"Eubank",
    "sg:classifiers":[
        {
            "category":"Restaurant",
            "type":"Food & Drink"
        }
    ],
    "sg:phone":"+1 606 379 6400",
    "sg:postcode":"42567",
    "sg:province":"KY",
    "wof:name":"Ruckel's Restaurant",
    "wof:placetype":"venue"
},
  "geometry": {"coordinates":[-84.64213100000001,37.275665],"type":"Point"}
}