{
  "type": "Feature",
  "properties": {
    "iso:country":"US",
    "sg:address":"426 Lexington Rd",
    "sg:city":"Versailles",
    "sg:classifiers":[
        {
            "category":"Restaurant",
            "type":"Food & Drink"
        }
    ],
    "sg:phone":"+1 859 873 1559",
    "sg:postcode":"40383",
    "sg:province":"KY",
    "wof:name":"Wok N Go",
    "wof:placetype":"venue"
},
  "geometry": {"coordinates":[-84.716678,38.05115],"type":"Point"}
}