{
  "type": "Feature",
  "properties": {
    "iso:country":"US",
    "sg:address":"236 16th St",
    "sg:city":"Ashland",
    "sg:classifiers":[
        {
            "category":"Shopping",
            "subcategory":"Clothing, Apparel, & Fashions",
            "type":"Retail Goods"
        }
    ],
    "sg:phone":"+1 606 324 0250",
    "sg:postcode":"41101",
    "sg:province":"KY",
    "sg:tags":[
        "navy",
        "army"
    ],
    "wof:name":"Army & Navy Store Original Inc",
    "wof:placetype":"venue"
},
  "geometry": {"coordinates":[-82.639286,38.478946],"type":"Point"}
}