{
  "type": "Feature",
  "properties": {
    "iso:country":"US",
    "sg:address":"8906 Cottingham Way",
    "sg:city":"Louisville",
    "sg:classifiers":[
        {
            "category":"Real Estate",
            "subcategory":"Architect",
            "type":"Services"
        }
    ],
    "sg:phone":"+1 502 933 2454",
    "sg:postcode":"40258",
    "sg:province":"KY",
    "sg:tags":[
        "architects'",
        "builders'"
    ],
    "wof:name":"Shannon Taylor",
    "wof:placetype":"venue"
},
  "geometry": {"coordinates":[-85.871802,38.124512],"type":"Point"}
}