{
  "type": "Feature",
  "properties": {
    "iso:country":"US",
    "sg:address":"84 Warren Rd",
    "sg:city":"Cumberland",
    "sg:classifiers":[
        {
            "category":"Organizations",
            "subcategory":"Religious Organization",
            "type":"Services"
        }
    ],
    "sg:phone":"+1 606 589 2336",
    "sg:postcode":"40823",
    "sg:province":"KY",
    "sg:tags":[
        "church"
    ],
    "wof:name":"Dione Baptist Church",
    "wof:placetype":"venue"
},
  "geometry": {"coordinates":[-83.083292,36.949878],"type":"Point"}
}