{
  "type": "Feature",
  "properties": {
    "addr:full":"756 Cottage Grove Ln Lexington KY 40502",
    "addr:housenumber":"756",
    "addr:postcode":"40502",
    "addr:street":"Cottage Grove Ln",
    "iso:country":"US",
    "sg:address":"756 Cottage Grove Ln",
    "sg:city":"Lexington",
    "sg:classifiers":[
        {
            "category":"Farming",
            "subcategory":"Farm",
            "type":"Manufacturing & Wholesale Goods"
        }
    ],
    "sg:phone":"+1 859 269 2258",
    "sg:postcode":"40502",
    "sg:province":"KY",
    "sg:tags":[
        "crop",
        "general"
    ],
    "wof:name":"CP Lebus Farms LLC",
    "wof:placetype":"venue"
},
  "geometry": {"coordinates":[-84.495215,38.014873],"type":"Point"}
}