{
  "type": "Feature",
  "properties": {
    "iso:country":"US",
    "sg:address":"1716 Portland Ave",
    "sg:city":"Louisville",
    "sg:classifiers":[
        {
            "category":"Retail",
            "subcategory":"Auto Repair",
            "type":"Services"
        }
    ],
    "sg:phone":"+1 502 587 6369",
    "sg:postcode":"40203",
    "sg:province":"KY",
    "sg:tags":[
        "repairing",
        "automobile"
    ],
    "wof:name":"Lanning Auto Svc",
    "wof:placetype":"venue"
},
  "geometry": {"coordinates":[-85.77662599999999,38.263866],"type":"Point"}
}