{
  "type": "Feature",
  "properties": {
    "iso:country":"US",
    "sg:address":"210 Paraquet Springs Dr",
    "sg:city":"Shepherdsville",
    "sg:classifiers":[
        {
            "category":"Restaurant",
            "type":"Food & Drink"
        }
    ],
    "sg:menulink":"http://www.allmenus.com/ky/shepherdsville-northwest/121627-fazolis/menu/",
    "sg:phone":"+1 502 543 4058",
    "sg:postcode":"40165",
    "sg:province":"KY",
    "sg:tags":[
        "italian"
    ],
    "wof:name":"Fazoli's",
    "wof:placetype":"venue"
},
  "geometry": {"coordinates":[-85.70638099999999,37.989188],"type":"Point"}
}