{
  "type": "Feature",
  "properties": {
    "iso:country":"US",
    "sg:address":"3200 Greenwood Ave",
    "sg:city":"Louisville",
    "sg:classifiers":[
        {
            "category":"Social Services",
            "type":"Services"
        }
    ],
    "sg:phone":"+1 502 774 2305",
    "sg:postcode":"40211",
    "sg:province":"KY",
    "sg:tags":[
        "youth",
        "organization",
        "center"
    ],
    "wof:name":"Parkland Boys' & Girls' Club",
    "wof:placetype":"venue"
},
  "geometry": {"coordinates":[-85.809524,38.243147],"type":"Point"}
}