{
  "type": "Feature",
  "properties": {
    "iso:country":"US",
    "sg:address":"1002 Goose Creek Rd",
    "sg:city":"Neon",
    "sg:classifiers":[
        {
            "category":"Wholesale",
            "subcategory":"Durable Goods & Equipment",
            "type":"Manufacturing & Wholesale Goods"
        }
    ],
    "sg:phone":"+1 606 855 7753",
    "sg:postcode":"41840",
    "sg:province":"KY",
    "sg:tags":[
        "representative",
        "manufacturer"
    ],
    "wof:name":"Jlh Inc",
    "wof:placetype":"venue"
},
  "geometry": {"coordinates":[-82.720851,37.211393],"type":"Point"}
}