{
  "type": "Feature",
  "properties": {
    "iso:country":"US",
    "sg:address":"3931 Central Ave",
    "sg:city":"Louisville",
    "sg:classifiers":[
        {
            "category":"Shopping",
            "subcategory":"Bicycles & Sporting Goods",
            "type":"Retail Goods"
        },
        {
            "category":"Sports & Exercise",
            "subcategory":"Swimming Pool",
            "type":"Entertainment"
        },
        {
            "category":"Building & Trades",
            "subcategory":"Construction",
            "type":"Services"
        },
        {
            "category":"Personal",
            "subcategory":"Sauna",
            "type":"Services"
        }
    ],
    "sg:phone":"+1 502 964 1996",
    "sg:postcode":"40218",
    "sg:province":"KY",
    "sg:tags":[
        "equipment",
        "supply"
    ],
    "wof:name":"Boyd's Pools",
    "wof:placetype":"venue"
},
  "geometry": {"coordinates":[-85.64975699999999,38.19099],"type":"Point"}
}