{
  "type": "Feature",
  "properties": {
    "addr:full":"232 Main St Paintsville KY 41240",
    "addr:housenumber":"232",
    "addr:postcode":"41240",
    "addr:street":"Main St",
    "iso:country":"US",
    "sg:address":"232 Main St",
    "sg:city":"Paintsville",
    "sg:classifiers":[
        {
            "category":"Professional",
            "subcategory":"Lawyer & Legal Services",
            "type":"Services"
        }
    ],
    "sg:phone":"+1 606 789 3059",
    "sg:postcode":"41240",
    "sg:province":"KY",
    "sg:tags":[
        "attorney"
    ],
    "wof:name":"Will Mullins Law Office",
    "wof:placetype":"venue"
},
  "geometry": {"coordinates":[-82.805031,37.813853],"type":"Point"}
}