{
  "type": "Feature",
  "properties": {
    "addr:full":"624 Westport Rd Elizabethtown KY 42701",
    "addr:housenumber":"624",
    "addr:postcode":"42701",
    "addr:street":"Westport Rd",
    "iso:country":"US",
    "sg:address":"624 Westport Rd",
    "sg:city":"Elizabethtown",
    "sg:classifiers":[
        {
            "category":"Shopping",
            "subcategory":"Florist",
            "type":"Retail Goods"
        }
    ],
    "sg:phone":"+1 270 765 4134",
    "sg:postcode":"42701",
    "sg:province":"KY",
    "wof:name":"E-Town Florist",
    "wof:placetype":"venue"
},
  "geometry": {"coordinates":[-85.88412099999999,37.706239],"type":"Point"}
}