{
  "type": "Feature",
  "properties": {
    "iso:country":"US",
    "sg:address":"2239 State Hwy 121 N",
    "sg:city":"Mayfield",
    "sg:classifiers":[
        {
            "category":"Home & Garden",
            "subcategory":"Furniture",
            "type":"Retail Goods"
        }
    ],
    "sg:phone":"+1 270 247 6620",
    "sg:postcode":"42066",
    "sg:province":"KY",
    "wof:name":"Gilliam Thompson Furniture Co",
    "wof:placetype":"venue"
},
  "geometry": {"coordinates":[-88.658637,36.758887],"type":"Point"}
}