{
  "type": "Feature",
  "properties": {
    "iso:country":"US",
    "sg:address":"535 Walnut St",
    "sg:city":"Georgetown",
    "sg:classifiers":[
        {
            "category":"Building & Trades",
            "subcategory":"Plumbing",
            "type":"Services"
        }
    ],
    "sg:phone":"+1 502 863 9686",
    "sg:postcode":"40324",
    "sg:province":"KY",
    "sg:tags":[
        "conditioning",
        "air",
        "system",
        "contractor"
    ],
    "wof:name":"Performance Products HVAC",
    "wof:placetype":"venue"
},
  "geometry": {"coordinates":[-84.55671100000001,38.219667],"type":"Point"}
}