{
  "type": "Feature",
  "properties": {
    "iso:country":"US",
    "sg:address":"2305 Arnold Palmer Blvd",
    "sg:city":"Louisville",
    "sg:classifiers":[
        {
            "category":"Wholesale",
            "subcategory":"Non-durable Goods",
            "type":"Manufacturing & Wholesale Goods"
        }
    ],
    "sg:phone":"+1 502 253 4671",
    "sg:postcode":"40245",
    "sg:province":"KY",
    "wof:name":"Preferred Solutions",
    "wof:placetype":"venue"
},
  "geometry": {"coordinates":[-85.482224,38.273452],"type":"Point"}
}