{
  "type": "Feature",
  "properties": {
    "addr:full":"597 US Hwy 421 Waneta KY 40475",
    "addr:housenumber":"597",
    "addr:postcode":"40475",
    "addr:street":"Us Hwy 421",
    "iso:country":"US",
    "sg:address":"597 US Hwy 421",
    "sg:city":"Waneta",
    "sg:classifiers":[
        {
            "category":"Government",
            "subcategory":"Post Office",
            "type":"Public Place"
        }
    ],
    "sg:phone":"+1 606 287 4441",
    "sg:postcode":"40475",
    "sg:province":"KY",
    "wof:name":"US Post Office",
    "wof:placetype":"venue"
},
  "geometry": {"coordinates":[-84.30047999999999,37.750067],"type":"Point"}
}