{
  "type": "Feature",
  "properties": {
    "iso:country":"US",
    "sg:address":"2017 Main St",
    "sg:city":"Paris",
    "sg:classifiers":[
        {
            "category":"Health Services",
            "subcategory":"Medical Lab",
            "type":"Services"
        }
    ],
    "sg:phone":"+1 859 987 1665",
    "sg:postcode":"40361",
    "sg:province":"KY",
    "sg:tags":[
        "laboratory"
    ],
    "wof:name":"Bourbon Medical Ctr Inc Lab",
    "wof:placetype":"venue"
},
  "geometry": {"coordinates":[-84.27106000000001,38.196898],"type":"Point"}
}