{
  "type": "Feature",
  "properties": {
    "addr:full":"22 Cindy Ann Ave Campbellsville KY 42718",
    "addr:housenumber":"22",
    "addr:postcode":"42718",
    "addr:street":"Cindy Ann Ave",
    "iso:country":"US",
    "sg:address":"22 Cindy Ann Ave",
    "sg:city":"Campbellsville",
    "sg:classifiers":[
        {
            "category":"Building & Trades",
            "subcategory":"Electrical",
            "type":"Services"
        }
    ],
    "sg:phone":"+1 270 465 5378",
    "sg:postcode":"42718",
    "sg:province":"KY",
    "sg:tags":[
        "electrical",
        "contractor"
    ],
    "wof:name":"Beard Electric",
    "wof:placetype":"venue"
},
  "geometry": {"coordinates":[-85.386016,37.332685],"type":"Point"}
}