{
  "type": "Feature",
  "properties": {
    "addr:full":"3135 Commerce Center Pl Louisville KY 40211",
    "addr:housenumber":"3135",
    "addr:postcode":"40211",
    "addr:street":"Commerce Center Pl",
    "iso:country":"US",
    "sg:address":"3135 Commerce Center Pl",
    "sg:city":"Louisville",
    "sg:classifiers":[
        {
            "category":"Building & Trades",
            "subcategory":"Cleaning & Sanitation",
            "type":"Services"
        }
    ],
    "sg:phone":"+1 502 772 0740",
    "sg:postcode":"40211",
    "sg:province":"KY",
    "sg:tags":[
        "janitor"
    ],
    "wof:name":"Alpha Building Maintenance Svc",
    "wof:placetype":"venue"
},
  "geometry": {"coordinates":[-85.81052099999999,38.220531],"type":"Point"}
}