{
  "type": "Feature",
  "properties": {
    "iso:country":"US",
    "sg:address":"3805 W Cumberland Ave",
    "sg:city":"Middlesboro",
    "sg:classifiers":[
        {
            "category":"Banks & Credit Unions",
            "subcategory":"Bank",
            "type":"Services"
        }
    ],
    "sg:phone":"+1 606 248 8566",
    "sg:postcode":"40965",
    "sg:province":"KY",
    "sg:website":"www.arhfcu.org",
    "wof:name":"Arh Employee's Federal Cu",
    "wof:placetype":"venue"
},
  "geometry": {"coordinates":[-83.741749,36.605251],"type":"Point"}
}