{
  "type": "Feature",
  "properties": {
    "iso:country":"US",
    "sg:address":"107 S Arnold Ave",
    "sg:city":"Prestonsburg",
    "sg:classifiers":[
        {
            "category":"Professional",
            "subcategory":"Lawyer & Legal Services",
            "type":"Services"
        }
    ],
    "sg:phone":"+1 606 886 7997",
    "sg:postcode":"41653",
    "sg:province":"KY",
    "sg:tags":[
        "attorney"
    ],
    "wof:name":"Johnny Harris",
    "wof:placetype":"venue"
},
  "geometry": {"coordinates":[-82.772745,37.665681],"type":"Point"}
}