{
  "type": "Feature",
  "properties": {
    "iso:country":"US",
    "sg:address":"161 Woods Point Dr",
    "sg:city":"Berea",
    "sg:classifiers":[
        {
            "category":"Retail",
            "subcategory":"Animal Services",
            "type":"Services"
        }
    ],
    "sg:phone":"+1 859 986 3137",
    "sg:postcode":"40403",
    "sg:province":"KY",
    "wof:name":"Kritter Kare",
    "wof:placetype":"venue"
},
  "geometry": {"coordinates":[-84.22617,37.61464],"type":"Point"}
}