{
  "type": "Feature",
  "properties": {
    "iso:country":"US",
    "sg:address":"2542 W Laurel Rd",
    "sg:city":"London",
    "sg:classifiers":[
        {
            "category":"Food & Beverages",
            "subcategory":"Groceries & Convenience Stores",
            "type":"Retail Goods"
        }
    ],
    "sg:phone":"+1 606 862 6881",
    "sg:postcode":"40741",
    "sg:province":"KY",
    "wof:name":"Tonys Bait & Tackle",
    "wof:placetype":"venue"
},
  "geometry": {"coordinates":[-84.137563,37.075927],"type":"Point"}
}