{
  "type": "Feature",
  "properties": {
    "iso:country":"US",
    "sg:address":"325 Elm St",
    "sg:city":"Bardwell",
    "sg:classifiers":[
        {
            "category":"Shopping",
            "subcategory":"Pharmacy",
            "type":"Retail Goods"
        }
    ],
    "sg:phone":"+1 270 628 5445",
    "sg:postcode":"42025",
    "sg:province":"KY",
    "wof:name":"Bardwell Pharmacy",
    "wof:placetype":"venue"
},
  "geometry": {"coordinates":[-88.34775399999999,36.865806],"type":"Point"}
}