{
  "type": "Feature",
  "properties": {
    "iso:country":"US",
    "sg:address":"5808 Brittany Valley Rd",
    "sg:city":"Louisville",
    "sg:classifiers":[
        {
            "category":"Communications",
            "type":"Services"
        }
    ],
    "sg:phone":"+1 502 412 0747",
    "sg:postcode":"40222",
    "sg:province":"KY",
    "sg:tags":[
        "data"
    ],
    "sg:website":"http://www.1st-telcomgroup.com",
    "wof:name":"1st Telcom Group Inc",
    "wof:placetype":"venue"
},
  "geometry": {"coordinates":[-85.64342499999999,38.296397],"type":"Point"}
}