{
  "type": "Feature",
  "properties": {
    "addr:full":"653 Stevenson Rd Erlanger KY 41018",
    "addr:housenumber":"653",
    "addr:postcode":"41018",
    "addr:street":"Stevenson Rd",
    "iso:country":"US",
    "sg:address":"653 Stevenson Rd",
    "sg:city":"Erlanger",
    "sg:classifiers":[
        {
            "category":"Professional",
            "subcategory":"Accounting & Tax Preparation",
            "type":"Services"
        }
    ],
    "sg:phone":"+1 859 342 0333",
    "sg:postcode":"41018",
    "sg:province":"KY",
    "sg:tags":[
        "accountant"
    ],
    "wof:name":"Martina Hopson CPA",
    "wof:placetype":"venue"
},
  "geometry": {"coordinates":[-84.58853000000001,39.006181],"type":"Point"}
}