{
  "type": "Feature",
  "properties": {
    "iso:country":"US",
    "sg:address":"165 Cranborne Grange",
    "sg:city":"Shelbyville",
    "sg:classifiers":[
        {
            "category":"Professional",
            "type":"Services"
        },
        {
            "category":"Retail",
            "subcategory":"Animal Services",
            "type":"Services"
        }
    ],
    "sg:phone":"+1 502 633 6863",
    "sg:postcode":"40065",
    "sg:province":"KY",
    "sg:tags":[
        "breeder",
        "horse"
    ],
    "wof:name":"Escalade Stables",
    "wof:placetype":"venue"
},
  "geometry": {"coordinates":[-85.174948,38.21918],"type":"Point"}
}