{
  "type": "Feature",
  "properties": {
    "addr:full":"107 N Public Sq Greensburg KY 42743",
    "addr:housenumber":"107",
    "addr:postcode":"42743",
    "addr:street":"N Public Sq",
    "iso:country":"US",
    "sg:address":"107 N Public Sq",
    "sg:city":"Greensburg",
    "sg:classifiers":[
        {
            "category":"Shopping",
            "subcategory":"Florist",
            "type":"Retail Goods"
        }
    ],
    "sg:phone":"+1 270 932 4559",
    "sg:postcode":"42743",
    "sg:province":"KY",
    "wof:name":"Brenda's Flowers & Crafts",
    "wof:placetype":"venue"
},
  "geometry": {"coordinates":[-85.500721,37.26072],"type":"Point"}
}