{
  "type": "Feature",
  "properties": {
    "iso:country":"US",
    "sg:address":"1857 Calvin Dr",
    "sg:city":"Hopkinsville",
    "sg:classifiers":[
        {
            "category":"Wholesale",
            "subcategory":"Metals & Minerals",
            "type":"Manufacturing & Wholesale Goods"
        }
    ],
    "sg:phone":"+1 270 885 4094",
    "sg:postcode":"42240",
    "sg:province":"KY",
    "sg:tags":[
        "steel",
        "warehouse"
    ],
    "wof:name":"Powell's Metal Sales Inc",
    "wof:placetype":"venue"
},
  "geometry": {"coordinates":[-87.471064,36.846221],"type":"Point"}
}