{
  "type": "Feature",
  "properties": {
    "iso:country":"US",
    "sg:address":"1110 S 2nd St",
    "sg:city":"Ironton",
    "sg:classifiers":[
        {
            "category":"Organizations",
            "subcategory":"Membership Organization",
            "type":"Services"
        }
    ],
    "sg:phone":"+1 740 533 1106",
    "sg:postcode":"45638",
    "sg:province":"OH",
    "wof:name":"Women Of The Moose",
    "wof:placetype":"venue"
},
  "geometry": {"coordinates":[-82.679219,38.526278],"type":"Point"}
}