{
  "type": "Feature",
  "properties": {
    "iso:country":"US",
    "sg:address":"110 Mark Trl",
    "sg:city":"Bowling Green",
    "sg:classifiers":[
        {
            "category":"Organizations",
            "subcategory":"Religious Organization",
            "type":"Services"
        }
    ],
    "sg:phone":"+1 270 781 5355",
    "sg:postcode":"42101",
    "sg:province":"KY",
    "sg:tags":[
        "church"
    ],
    "sg:website":"www.gbcky.com",
    "wof:name":"Grace Baptist Church",
    "wof:placetype":"venue"
},
  "geometry": {"coordinates":[-86.508894,36.994799],"type":"Point"}
}