{
  "type": "Feature",
  "properties": {
    "iso:country":"US",
    "sg:address":"216 Lindsey St",
    "sg:city":"Dayton",
    "sg:classifiers":[
        {
            "category":"Retail",
            "subcategory":"Laundry & Dry Cleaning",
            "type":"Services"
        }
    ],
    "sg:phone":"+1 859 491 9477",
    "sg:postcode":"41074",
    "sg:province":"KY",
    "wof:name":"Point Laundry",
    "wof:placetype":"venue"
},
  "geometry": {"coordinates":[-84.476737,39.108698],"type":"Point"}
}