{
  "type": "Feature",
  "properties": {
    "addr:full":"530 S Jackson St Louisville KY 40202",
    "addr:housenumber":"530",
    "addr:postcode":"40202",
    "addr:street":"S Jackson St",
    "iso:country":"US",
    "sg:address":"530 S Jackson St",
    "sg:city":"Louisville",
    "sg:classifiers":[
        {
            "category":"Banks & Credit Unions",
            "subcategory":"Bank",
            "type":"Services"
        },
        {
            "category":"Banks & Credit Unions",
            "subcategory":"Financial Services",
            "type":"Services"
        }
    ],
    "sg:phone":"+1 502 562 6660",
    "sg:postcode":"40202",
    "sg:province":"KY",
    "sg:tags":[
        "saving",
        "loan",
        "commercial"
    ],
    "sg:website":"http://www.firstar.com",
    "wof:name":"Us Bank",
    "wof:placetype":"venue"
},
  "geometry": {"coordinates":[-85.745003,38.248589],"type":"Point"}
}