{
  "type": "Feature",
  "properties": {
    "iso:country":"US",
    "sg:address":"9125 Galene Dr",
    "sg:city":"Louisville",
    "sg:classifiers":[
        {
            "category":"Shopping",
            "subcategory":"Used Merchandise",
            "type":"Retail Goods"
        }
    ],
    "sg:phone":"+1 502 297 8784",
    "sg:postcode":"40299",
    "sg:province":"KY",
    "sg:tags":[
        "shop",
        "thrift"
    ],
    "wof:name":"Wayside Christian Mission",
    "wof:placetype":"venue"
},
  "geometry": {"coordinates":[-85.59262099999999,38.198575],"type":"Point"}
}