{
  "type": "Feature",
  "properties": {
    "iso:country":"US",
    "sg:address":"116 S Dixie Hwy",
    "sg:city":"Muldraugh",
    "sg:classifiers":[
        {
            "category":"Travel",
            "subcategory":"Hotels & Motels",
            "type":"Entertainment"
        },
        {
            "category":"Restaurant",
            "type":"Food & Drink"
        }
    ],
    "sg:phone":"+1 502 942 2800",
    "sg:postcode":"40155",
    "sg:province":"KY",
    "sg:tags":[
        "lodging"
    ],
    "sg:website":"http://www.goldenmanormotel.com",
    "wof:name":"Golden Manor Motel",
    "wof:placetype":"venue"
},
  "geometry": {"coordinates":[-85.99561799999999,37.939078],"type":"Point"}
}