{
  "type": "Feature",
  "properties": {
    "addr:full":"10200 Bunsen Way Jeffersontown KY 40299",
    "addr:housenumber":"10200",
    "addr:postcode":"40299",
    "addr:street":"Bunsen Way",
    "iso:country":"US",
    "sg:address":"10200 Bunsen Way",
    "sg:city":"Jeffersontown",
    "sg:classifiers":[
        {
            "category":"Building & Trades",
            "subcategory":"Plumbing",
            "type":"Services"
        }
    ],
    "sg:phone":"+1 502 499 5480",
    "sg:postcode":"40299",
    "sg:province":"KY",
    "sg:tags":[
        "sheet",
        "work",
        "metal",
        "contractor"
    ],
    "wof:name":"Thybar Corp",
    "wof:placetype":"venue"
},
  "geometry": {"coordinates":[-85.567735,38.215078],"type":"Point"}
}