{
  "type": "Feature",
  "properties": {
    "iso:country":"US",
    "sg:address":"4800 Strawberry Ln",
    "sg:city":"Louisville",
    "sg:classifiers":[
        {
            "category":"Freight",
            "type":"Transportation"
        }
    ],
    "sg:phone":"+1 502 375 9661",
    "sg:postcode":"40209",
    "sg:province":"KY",
    "sg:tags":[
        "commercial",
        "storage"
    ],
    "wof:name":"Document Storage & Retrieval",
    "wof:placetype":"venue"
},
  "geometry": {"coordinates":[-85.754169,38.178938],"type":"Point"}
}