{
  "type": "Feature",
  "properties": {
    "iso:country":"US",
    "sg:address":"4950 Flemingsburg Rd",
    "sg:city":"Morehead",
    "sg:classifiers":[
        {
            "category":"Recreation",
            "type":"Entertainment"
        }
    ],
    "sg:phone":"+1 606 784 3989",
    "sg:postcode":"40351",
    "sg:province":"KY",
    "sg:tags":[
        "instruction",
        "gymnastic"
    ],
    "wof:name":"Don Hardin's Gym Dandy's Ctr",
    "wof:placetype":"venue"
},
  "geometry": {"coordinates":[-83.498932,38.23191],"type":"Point"}
}