{
  "type": "Feature",
  "properties": {
    "addr:full":"805 N Main St London KY 40741",
    "addr:housenumber":"805",
    "addr:postcode":"40741",
    "addr:street":"N Main St",
    "iso:country":"US",
    "sg:address":"805 N Main St",
    "sg:city":"London",
    "sg:classifiers":[
        {
            "category":"Professional",
            "subcategory":"Accounting & Tax Preparation",
            "type":"Services"
        }
    ],
    "sg:phone":"+1 606 862 9920",
    "sg:postcode":"40741",
    "sg:province":"KY",
    "wof:name":"Butch Grubb CPA",
    "wof:placetype":"venue"
},
  "geometry": {"coordinates":[-84.08938999999999,37.133029],"type":"Point"}
}