{
  "type": "Feature",
  "properties": {
    "addr:full":"3901 Dutchmans Ln Louisville KY 40207",
    "addr:housenumber":"3901",
    "addr:postcode":"40207",
    "addr:street":"Dutchmans Ln",
    "iso:country":"US",
    "sg:address":"3901 Dutchmans Ln",
    "sg:city":"Louisville",
    "sg:classifiers":[
        {
            "category":"Wholesale",
            "subcategory":"Medical Equipment & Supplies",
            "type":"Manufacturing & Wholesale Goods"
        },
        {
            "category":"Shopping",
            "subcategory":"Clothing, Apparel, & Fashions",
            "type":"Retail Goods"
        },
        {
            "category":"Building & Trades",
            "subcategory":"Construction",
            "type":"Services"
        },
        {
            "category":"Health Services",
            "subcategory":"Clinic",
            "type":"Services"
        },
        {
            "category":"Autos & Motor Vehicles",
            "subcategory":"Fuel & Gas Station",
            "type":"Retail Goods"
        },
        {
            "category":"Health Services",
            "subcategory":"Hospital",
            "type":"Services"
        },
        {
            "category":"Wholesale",
            "subcategory":"Construction Materials",
            "type":"Manufacturing & Wholesale Goods"
        },
        {
            "category":"Shopping",
            "subcategory":"Pharmacy",
            "type":"Retail Goods"
        },
        {
            "category":"Building & Trades",
            "subcategory":"Equipment Rental",
            "type":"Services"
        }
    ],
    "sg:phone":"+1 502 491 2000",
    "sg:postcode":"40207",
    "sg:province":"KY",
    "sg:tags":[
        "oxygen",
        "form",
        "mastectomy",
        "wheelchair",
        "diabetic",
        "ramp",
        "elevator",
        "uniform",
        "lift",
        "sleep",
        "treatment",
        "apparel",
        "home",
        "care",
        "wheelchairs-rental",
        "disorders-information"
    ],
    "sg:website":"http://www.gouldsdiscountmedical.com",
    "wof:name":"Goulds Discount Medical",
    "wof:placetype":"venue"
},
  "geometry": {"coordinates":[-85.637466,38.23246],"type":"Point"}
}