{
  "type": "Feature",
  "properties": {
    "iso:country":"US",
    "sg:address":"7 S Calumet Ct",
    "sg:city":"Louisville",
    "sg:classifiers":[
        {
            "category":"Building & Trades",
            "subcategory":"Electrical",
            "type":"Services"
        }
    ],
    "sg:phone":"+1 502 361 7990",
    "sg:postcode":"40214",
    "sg:province":"KY",
    "sg:tags":[
        "electrician"
    ],
    "wof:name":"Bennett, Jacky x",
    "wof:placetype":"venue"
},
  "geometry": {"coordinates":[-85.76024099999999,38.127132],"type":"Point"}
}