{
  "type": "Feature",
  "properties": {
    "iso:country":"US",
    "sg:address":"4814 Outer Loop",
    "sg:city":"Louisville",
    "sg:classifiers":[
        {
            "category":"Health Services",
            "subcategory":"Doctor",
            "type":"Services"
        }
    ],
    "sg:phone":"+1 502 969 6229",
    "sg:postcode":"40219",
    "sg:province":"KY",
    "sg:tags":[
        "dentist"
    ],
    "wof:name":"Zeh Orthodontics",
    "wof:placetype":"venue"
},
  "geometry": {"coordinates":[-85.671592,38.137783],"type":"Point"}
}