{
  "type": "Feature",
  "properties": {
    "iso:country":"US",
    "sg:address":"114 Woodside Way",
    "sg:city":"Nicholasville",
    "sg:classifiers":[
        {
            "category":"Professional",
            "subcategory":"Management & Consulting",
            "type":"Services"
        }
    ],
    "sg:phone":"+1 859 223 5113",
    "sg:postcode":"40356",
    "sg:province":"KY",
    "wof:name":"Big C Consulting",
    "wof:placetype":"venue"
},
  "geometry": {"coordinates":[-84.59869,37.977224],"type":"Point"}
}