{
  "type": "Feature",
  "properties": {
    "iso:country":"US",
    "sg:address":"433 Southland Dr",
    "sg:city":"Lexington",
    "sg:classifiers":[
        {
            "category":"Professional",
            "subcategory":"Business Services",
            "type":"Services"
        },
        {
            "category":"Government",
            "subcategory":"Post Office",
            "type":"Public Place"
        }
    ],
    "sg:phone":"+1 800 275 8777",
    "sg:postcode":"40503",
    "sg:province":"KY",
    "sg:tags":[
        "mail",
        "shipping"
    ],
    "sg:website":"http://www.usps.com",
    "wof:name":"USPS - United States Post Office - CPU Pip",
    "wof:placetype":"venue"
},
  "geometry": {"coordinates":[-84.52737500000001,38.018937],"type":"Point"}
}