{
  "type": "Feature",
  "properties": {
    "addr:full":"2452 Harrodsburg Rd Lexington KY 40503",
    "addr:housenumber":"2452",
    "addr:postcode":"40503",
    "addr:street":"Harrodsburg Rd",
    "iso:country":"US",
    "sg:address":"2452 Harrodsburg Rd",
    "sg:city":"Lexington",
    "sg:classifiers":[
        {
            "category":"Banks & Credit Unions",
            "subcategory":"Bank",
            "type":"Services"
        }
    ],
    "sg:phone":"+1 859 281 5460",
    "sg:postcode":"40503",
    "sg:province":"KY",
    "wof:name":"National City Bank",
    "wof:placetype":"venue"
},
  "geometry": {"coordinates":[-84.54706400000001,38.018225],"type":"Point"}
}