{
  "type": "Feature",
  "properties": {
    "iso:country":"US",
    "sg:address":"1972 Pavilion Way",
    "sg:city":"Lexington",
    "sg:classifiers":[
        {
            "category":"Shopping",
            "subcategory":"Shoes",
            "type":"Retail Goods"
        }
    ],
    "sg:phone":"+1 859 543 8060",
    "sg:postcode":"40509",
    "sg:province":"KY",
    "sg:website":"www.rackroomshoes.com",
    "wof:name":"Rack Room Shoes",
    "wof:placetype":"venue"
},
  "geometry": {"coordinates":[-84.418252,38.020707],"type":"Point"}
}