{
  "type": "Feature",
  "properties": {
    "iso:country":"US",
    "sg:address":"223 Saint Ann St",
    "sg:city":"Owensboro",
    "sg:classifiers":[
        {
            "category":"Wholesale",
            "subcategory":"Jewelry",
            "type":"Manufacturing & Wholesale Goods"
        }
    ],
    "sg:phone":"+1 270 685 0047",
    "sg:postcode":"42303",
    "sg:province":"KY",
    "sg:tags":[
        "manufacture",
        "retail"
    ],
    "wof:name":"Dewitts Repair",
    "wof:placetype":"venue"
},
  "geometry": {"coordinates":[-87.1122,37.773969],"type":"Point"}
}