{
  "type": "Feature",
  "properties": {
    "iso:country":"US",
    "sg:address":"1513 Main St",
    "sg:city":"Benton",
    "sg:classifiers":[
        {
            "category":"Restaurant",
            "type":"Food & Drink"
        }
    ],
    "sg:phone":"+1 270 252 0089",
    "sg:postcode":"42025",
    "sg:province":"KY",
    "wof:name":"Number 1 China Buffet",
    "wof:placetype":"venue"
},
  "geometry": {"coordinates":[-88.350368,36.851653],"type":"Point"}
}