{
  "type": "Feature",
  "properties": {
    "addr:full":"432 Little Rock - Jackstown Rd Carlisle KY 40311",
    "addr:housenumber":"432",
    "addr:postcode":"40311",
    "addr:street":"Little;Jackstown Rd",
    "iso:country":"US",
    "sg:address":"432 Little Rock - Jackstown Rd",
    "sg:city":"Carlisle",
    "sg:phone":"+1 859 383 4334",
    "sg:postcode":"40311",
    "sg:province":"KY",
    "sg:tags":[
        "farm",
        "field",
        "dairy",
        "crop"
    ],
    "wof:name":"Tommy Gillispie",
    "wof:placetype":"venue"
},
  "geometry": {"coordinates":[-84.06899300000001,38.240646],"type":"Point"}
}