{
  "type": "Feature",
  "properties": {
    "addr:full":"16350 Fort Campbell Blvd Oak Grove KY 42262",
    "addr:housenumber":"16350",
    "addr:postcode":"42262",
    "addr:street":"Fort Campbell Blvd",
    "iso:country":"US",
    "sg:address":"16350 Fort Campbell Blvd",
    "sg:city":"Oak Grove",
    "sg:classifiers":[
        {
            "category":"Personal",
            "subcategory":"Shoe Repair & Shine",
            "type":"Services"
        }
    ],
    "sg:phone":"+1 270 439 6334",
    "sg:postcode":"42262",
    "sg:province":"KY",
    "sg:tags":[
        "repairing",
        "boot"
    ],
    "wof:name":"Eagle Shoe Repair",
    "wof:placetype":"venue"
},
  "geometry": {"coordinates":[-87.437388,36.646356],"type":"Point"}
}