{
  "type": "Feature",
  "properties": {
    "addr:full":"135 Main St Paducah KY 42003",
    "addr:housenumber":"135",
    "addr:postcode":"42003",
    "addr:street":"Main St",
    "iso:country":"US",
    "sg:address":"135 Main St",
    "sg:city":"Paducah",
    "sg:classifiers":[
        {
            "category":"Building & Trades",
            "subcategory":"Pest Control",
            "type":"Services"
        }
    ],
    "sg:phone":"+1 270 442 8998",
    "sg:postcode":"42003",
    "sg:province":"KY",
    "wof:name":"Alert Pest Control Co",
    "wof:placetype":"venue"
},
  "geometry": {"coordinates":[-88.57438399999999,37.056427],"type":"Point"}
}