{
  "type": "Feature",
  "properties": {
    "addr:full":"501 York St Newport KY 41071",
    "addr:housenumber":"501",
    "addr:postcode":"41071",
    "addr:street":"York St",
    "iso:country":"US",
    "sg:address":"501 York St",
    "sg:city":"Newport",
    "sg:classifiers":[
        {
            "category":"Shopping",
            "subcategory":"Tobacco",
            "type":"Retail Goods"
        },
        {
            "category":"Food & Beverages",
            "subcategory":"Liquor & Beverages",
            "type":"Retail Goods"
        }
    ],
    "sg:phone":"+1 859 581 8650",
    "sg:postcode":"41071",
    "sg:province":"KY",
    "sg:tags":[
        "cigarette",
        "cigar",
        "store"
    ],
    "wof:name":"Famous Liquor Cigar-Cigarette",
    "wof:placetype":"venue"
},
  "geometry": {"coordinates":[-84.495644,39.09166],"type":"Point"}
}