{
  "type": "Feature",
  "properties": {
    "iso:country":"US",
    "sg:address":"421 Scott Blvd",
    "sg:city":"Covington",
    "sg:classifiers":[
        {
            "category":"Professional",
            "subcategory":"Management & Consulting",
            "type":"Services"
        }
    ],
    "sg:phone":"+1 859 581 4815",
    "sg:postcode":"41011",
    "sg:province":"KY",
    "sg:tags":[
        "fuel"
    ],
    "wof:name":"Rentz Management",
    "wof:placetype":"venue"
},
  "geometry": {"coordinates":[-84.509244,39.086313],"type":"Point"}
}