{
  "type": "Feature",
  "properties": {
    "iso:country":"US",
    "sg:address":"330 Douglas Ave",
    "sg:city":"Versailles",
    "sg:classifiers":[
        {
            "category":"Home & Garden",
            "subcategory":"Home Furnishings",
            "type":"Retail Goods"
        }
    ],
    "sg:phone":"+1 859 873 7236",
    "sg:postcode":"40383",
    "sg:province":"KY",
    "sg:tags":[
        "curtain",
        "made",
        "drapery"
    ],
    "wof:name":"Goins Sewing Ctr",
    "wof:placetype":"venue"
},
  "geometry": {"coordinates":[-84.723657,38.056888],"type":"Point"}
}