{
  "type": "Feature",
  "properties": {
    "addr:full":"969 Baxter Ave Louisville KY 40204",
    "addr:housenumber":"969",
    "addr:postcode":"40204",
    "addr:street":"Baxter Ave",
    "iso:country":"US",
    "sg:address":"969 Baxter Ave",
    "sg:city":"Louisville",
    "sg:classifiers":[
        {
            "category":"Restaurant",
            "type":"Food & Drink"
        }
    ],
    "sg:menulink":"http://www.allmenus.com/ky/louisville-east/4375-omars-gyro/menu/",
    "sg:phone":"+1 502 454 4888",
    "sg:postcode":"40204",
    "sg:province":"KY",
    "sg:tags":[
        "mediterranean"
    ],
    "wof:name":"Omar's Gyro",
    "wof:placetype":"venue"
},
  "geometry": {"coordinates":[-85.724547,38.240938],"type":"Point"}
}