{
  "type": "Feature",
  "properties": {
    "iso:country":"US",
    "sg:address":"1300 Oak Hill Rd",
    "sg:city":"Louisville",
    "sg:classifiers":[
        {
            "category":"Manufacturing",
            "subcategory":"Petroleum Products",
            "type":"Manufacturing & Wholesale Goods"
        },
        {
            "category":"Wholesale",
            "subcategory":"Petroleum",
            "type":"Manufacturing & Wholesale Goods"
        }
    ],
    "sg:phone":"+1 502 458 5999",
    "sg:postcode":"40213",
    "sg:province":"KY",
    "sg:tags":[
        "manufacturer",
        "products-wholesale",
        "oils-petroleum"
    ],
    "wof:name":"Red Leonard Associates Inc",
    "wof:placetype":"venue"
},
  "geometry": {"coordinates":[-85.705353,38.208359],"type":"Point"}
}