{
  "type": "Feature",
  "properties": {
    "addr:full":"1501 S Jefferson St Princeton KY 42445",
    "addr:housenumber":"1501",
    "addr:postcode":"42445",
    "addr:street":"S Jefferson St",
    "iso:country":"US",
    "sg:address":"1501 S Jefferson St",
    "sg:city":"Princeton",
    "sg:classifiers":[
        {
            "category":"Organizations",
            "subcategory":"Community Association",
            "type":"Services"
        }
    ],
    "sg:phone":"+1 270 365 6378",
    "sg:postcode":"42445",
    "sg:province":"KY",
    "wof:name":"Daughters of American Rev",
    "wof:placetype":"venue"
},
  "geometry": {"coordinates":[-87.910054,37.077022],"type":"Point"}
}