{
  "type": "Feature",
  "properties": {
    "iso:country":"US",
    "sg:address":"12015 Hunting Crest Dr",
    "sg:city":"Prospect",
    "sg:classifiers":[
        {
            "category":"Restaurant",
            "type":"Food & Drink"
        }
    ],
    "sg:phone":"+1 502 228 8434",
    "sg:postcode":"40059",
    "sg:province":"KY",
    "sg:tags":[
        "eating"
    ],
    "wof:name":"Tanexa Enterprises LLC",
    "wof:placetype":"venue"
},
  "geometry": {"coordinates":[-85.59080400000001,38.35955],"type":"Point"}
}