{
  "type": "Feature",
  "properties": {
    "iso:country":"US",
    "sg:address":"1312 Anneta Rd",
    "sg:city":"Leitchfield",
    "sg:classifiers":[
        {
            "category":"Shopping",
            "type":"Retail Goods"
        }
    ],
    "sg:phone":"+1 270 230 9553",
    "sg:postcode":"42754",
    "sg:province":"KY",
    "sg:tags":[
        "pet",
        "shop"
    ],
    "wof:name":"Pet Emporium",
    "wof:placetype":"venue"
},
  "geometry": {"coordinates":[-86.291517,37.463705],"type":"Point"}
}