{
  "type": "Feature",
  "properties": {
    "iso:country":"US",
    "sg:address":"810 Lain Ave",
    "sg:city":"Bowling Green",
    "sg:classifiers":[
        {
            "category":"Banks & Credit Unions",
            "subcategory":"Bank",
            "type":"Services"
        }
    ],
    "sg:phone":"+1 270 783 7240",
    "sg:postcode":"42101",
    "sg:province":"KY",
    "wof:name":"US Bank",
    "wof:placetype":"venue"
},
  "geometry": {"coordinates":[-86.43252099999999,36.987269],"type":"Point"}
}