{
  "type": "Feature",
  "properties": {
    "iso:country":"US",
    "sg:address":"450 E New Circle Rd",
    "sg:city":"Lexington",
    "sg:classifiers":[
        {
            "category":"Health Services",
            "subcategory":"Doctor",
            "type":"Services"
        }
    ],
    "sg:phone":"+1 859 255 2532",
    "sg:postcode":"40505",
    "sg:province":"KY",
    "sg:tags":[
        "physician",
        "surgeon"
    ],
    "wof:name":"Lexington Clinic Northeast",
    "wof:placetype":"venue"
},
  "geometry": {"coordinates":[-84.46493700000001,38.060051],"type":"Point"}
}