{
  "type": "Feature",
  "properties": {
    "iso:country":"US",
    "sg:address":"718 S Main St",
    "sg:city":"London",
    "sg:classifiers":[
        {
            "category":"Retail",
            "subcategory":"Portrait Studio",
            "type":"Services"
        }
    ],
    "sg:phone":"+1 606 864 6506",
    "sg:postcode":"40741",
    "sg:province":"KY",
    "sg:tags":[
        "photographer"
    ],
    "wof:name":"Photo Joy Photography",
    "wof:placetype":"venue"
},
  "geometry": {"coordinates":[-84.08017599999999,37.124744],"type":"Point"}
}