{
  "type": "Feature",
  "properties": {
    "iso:country":"US",
    "sg:address":"4017 Altawood Ct",
    "sg:city":"Louisville",
    "sg:classifiers":[
        {
            "category":"Home & Garden",
            "subcategory":"Building Materials",
            "type":"Retail Goods"
        }
    ],
    "sg:phone":"+1 502 225 6338",
    "sg:postcode":"40245",
    "sg:province":"KY",
    "sg:tags":[
        "top",
        "counter"
    ],
    "sg:website":"http://www.caibeco.com",
    "wof:name":"Caibe & Co",
    "wof:placetype":"venue"
},
  "geometry": {"coordinates":[-85.505408,38.303474],"type":"Point"}
}