{
  "type": "Feature",
  "properties": {
    "addr:full":"4215 N Dixie Hwy Bonnieville KY 42713",
    "addr:housenumber":"4215",
    "addr:postcode":"42713",
    "addr:street":"N Dixie Hwy",
    "iso:country":"US",
    "sg:address":"4215 N Dixie Hwy",
    "sg:city":"Bonnieville",
    "sg:classifiers":[
        {
            "category":"Wholesale",
            "subcategory":"Scrap",
            "type":"Manufacturing & Wholesale Goods"
        }
    ],
    "sg:phone":"+1 270 524 7071",
    "sg:postcode":"42713",
    "sg:province":"KY",
    "sg:tags":[
        "automotive",
        "material",
        "used"
    ],
    "wof:name":"Lou Ken Auto & Wrecker Service",
    "wof:placetype":"venue"
},
  "geometry": {"coordinates":[-85.90973700000001,37.317849],"type":"Point"}
}