{
  "type": "Feature",
  "properties": {
    "iso:country":"US",
    "sg:address":"1800 Alexandria Dr",
    "sg:city":"Lexington",
    "sg:classifiers":[
        {
            "category":"Retail",
            "subcategory":"Auto Repair",
            "type":"Services"
        }
    ],
    "sg:phone":"+1 859 276 1809",
    "sg:postcode":"40504",
    "sg:province":"KY",
    "sg:tags":[
        "brake"
    ],
    "wof:name":"Lexington Brake",
    "wof:placetype":"venue"
},
  "geometry": {"coordinates":[-84.552211,38.037307],"type":"Point"}
}