{
  "type": "Feature",
  "properties": {
    "iso:country":"US",
    "sg:address":"350 Park St",
    "sg:city":"Bowling Green",
    "sg:classifiers":[
        {
            "category":"Health Services",
            "subcategory":"Doctor",
            "type":"Services"
        }
    ],
    "sg:phone":"+1 270 796 3330",
    "sg:postcode":"42101",
    "sg:province":"KY",
    "sg:tags":[
        "physician",
        "surgeon"
    ],
    "wof:name":"Heart Institute",
    "wof:placetype":"venue"
},
  "geometry": {"coordinates":[-86.431437,36.995446],"type":"Point"}
}