{
  "type": "Feature",
  "properties": {
    "iso:country":"US",
    "sg:address":"115 W Main St",
    "sg:city":"Flemingsburg",
    "sg:classifiers":[
        {
            "category":"Government",
            "subcategory":"Police Station",
            "type":"Public Place"
        }
    ],
    "sg:phone":"+1 606 845 4701",
    "sg:postcode":"41041",
    "sg:province":"KY",
    "sg:tags":[
        "sheriff"
    ],
    "wof:name":"Fleming County Sheriff",
    "wof:placetype":"venue"
},
  "geometry": {"coordinates":[-83.73331399999999,38.423272],"type":"Point"}
}