{
  "type": "Feature",
  "properties": {
    "addr:full":"65 Main St Cadiz KY 42211",
    "addr:housenumber":"65",
    "addr:postcode":"42211",
    "addr:street":"Main St",
    "iso:country":"US",
    "sg:address":"65 Main St",
    "sg:city":"Cadiz",
    "sg:classifiers":[
        {
            "category":"Government",
            "subcategory":"Office",
            "type":"Public Place"
        }
    ],
    "sg:phone":"+1 270 522 7695",
    "sg:postcode":"42211",
    "sg:province":"KY",
    "wof:name":"Court Designated Worker",
    "wof:placetype":"venue"
},
  "geometry": {"coordinates":[-87.838776,36.860726],"type":"Point"}
}