{
  "type": "Feature",
  "properties": {
    "iso:country":"US",
    "sg:address":"2817 del Rio Pl",
    "sg:city":"Louisville",
    "sg:classifiers":[
        {
            "category":"Shopping",
            "subcategory":"Musical Instruments",
            "type":"Retail Goods"
        }
    ],
    "sg:phone":"+1 502 479 3772",
    "sg:postcode":"40220",
    "sg:province":"KY",
    "wof:name":"Miles Ahead Instrument Sales",
    "wof:placetype":"venue"
},
  "geometry": {"coordinates":[-85.65502600000001,38.214882],"type":"Point"}
}