{
  "type": "Feature",
  "properties": {
    "addr:full":"195 American Ave Glasgow KY 42141",
    "addr:housenumber":"195",
    "addr:postcode":"42141",
    "addr:street":"American Ave",
    "iso:country":"US",
    "sg:address":"195 American Ave",
    "sg:city":"Glasgow",
    "sg:classifiers":[
        {
            "category":"Professional",
            "subcategory":"Business Services",
            "type":"Services"
        }
    ],
    "sg:phone":"+1 270 651 1662",
    "sg:postcode":"42141",
    "sg:province":"KY",
    "sg:website":"www.expresslogisticsinc.com",
    "wof:name":"LMR Express Logistics Inc",
    "wof:placetype":"venue"
},
  "geometry": {"coordinates":[-85.944891,37.004926],"type":"Point"}
}