{
  "type": "Feature",
  "properties": {
    "addr:full":"4301 Holly Tree Dr Louisville KY 40241",
    "addr:housenumber":"4301",
    "addr:postcode":"40241",
    "addr:street":"Holly Tree Dr",
    "iso:country":"US",
    "sg:address":"4301 Holly Tree Dr",
    "sg:city":"Louisville",
    "sg:classifiers":[
        {
            "category":"Building & Trades",
            "subcategory":"Electrical",
            "type":"Services"
        }
    ],
    "sg:phone":"+1 502 339 8213",
    "sg:postcode":"40241",
    "sg:province":"KY",
    "sg:tags":[
        "electrical",
        "contractor"
    ],
    "wof:name":"Electrical Specialties LLC",
    "wof:placetype":"venue"
},
  "geometry": {"coordinates":[-85.56295799999999,38.306211],"type":"Point"}
}