{
  "type": "Feature",
  "properties": {
    "iso:country":"US",
    "sg:address":"1015 N Main St",
    "sg:city":"Nicholasville",
    "sg:classifiers":[
        {
            "category":"Wholesale",
            "subcategory":"Farm Supplies",
            "type":"Manufacturing & Wholesale Goods"
        }
    ],
    "sg:phone":"+1 859 887 9192",
    "sg:postcode":"40356",
    "sg:province":"KY",
    "wof:name":"Tractor Supply Co",
    "wof:placetype":"venue"
},
  "geometry": {"coordinates":[-84.565258,37.898575],"type":"Point"}
}