{
  "type": "Feature",
  "properties": {
    "addr:full":"124 W Main St Springfield KY 40069",
    "addr:housenumber":"124",
    "addr:postcode":"40069",
    "addr:street":"W Main St",
    "iso:country":"US",
    "sg:address":"124 W Main St",
    "sg:city":"Springfield",
    "sg:classifiers":[
        {
            "category":"Government",
            "subcategory":"Office",
            "type":"Public Place"
        }
    ],
    "sg:phone":"+1 859 336 0052",
    "sg:postcode":"40069",
    "sg:province":"KY",
    "sg:tags":[
        "county"
    ],
    "wof:name":"Springfield Washington County",
    "wof:placetype":"venue"
},
  "geometry": {"coordinates":[-85.223133,37.685571],"type":"Point"}
}