{
  "type": "Feature",
  "properties": {
    "iso:country":"US",
    "sg:address":"273 Washington Ct",
    "sg:city":"Mt Washington",
    "sg:classifiers":[
        {
            "category":"Shopping",
            "subcategory":"Department Store",
            "type":"Retail Goods"
        }
    ],
    "sg:phone":"+1 502 538 4384",
    "sg:postcode":"40047",
    "sg:province":"KY",
    "sg:tags":[
        "shop"
    ],
    "wof:name":"Dollar General",
    "wof:placetype":"venue"
},
  "geometry": {"coordinates":[-85.558194,38.059019],"type":"Point"}
}