{
  "type": "Feature",
  "properties": {
    "addr:full":"6135 Winchester Rd Irvine KY 40336",
    "addr:housenumber":"6135",
    "addr:postcode":"40336",
    "addr:street":"Winchester Rd",
    "iso:country":"US",
    "sg:address":"6135 Winchester Rd",
    "sg:city":"Irvine",
    "sg:classifiers":[
        {
            "category":"Manufacturing",
            "subcategory":"Printing",
            "type":"Manufacturing & Wholesale Goods"
        }
    ],
    "sg:phone":"+1 606 723 5012",
    "sg:postcode":"40336",
    "sg:province":"KY",
    "sg:tags":[
        "newspaper"
    ],
    "wof:name":"Estill County Tribune",
    "wof:placetype":"venue"
},
  "geometry": {"coordinates":[-84.00891799999999,37.781546],"type":"Point"}
}