{
  "type": "Feature",
  "properties": {
    "iso:country":"US",
    "sg:address":"1101 Grade Ln",
    "sg:city":"Louisville",
    "sg:classifiers":[
        {
            "category":"Banks & Credit Unions",
            "subcategory":"Bank",
            "type":"Services"
        }
    ],
    "sg:phone":"+1 502 364 9410",
    "sg:postcode":"40213",
    "sg:province":"KY",
    "wof:name":"Kyang Fcu",
    "wof:placetype":"venue"
},
  "geometry": {"coordinates":[-85.72116699999999,38.169737],"type":"Point"}
}