{
  "type": "Feature",
  "properties": {
    "iso:country":"US",
    "sg:address":"785 Stone Ln",
    "sg:city":"Sadieville",
    "sg:classifiers":[
        {
            "category":"Shopping",
            "subcategory":"Shoes",
            "type":"Retail Goods"
        }
    ],
    "sg:phone":"+1 502 857 2886",
    "sg:postcode":"40370",
    "sg:province":"KY",
    "wof:name":"KS Blacksmith Ltd",
    "wof:placetype":"venue"
},
  "geometry": {"coordinates":[-84.56495,38.4336],"type":"Point"}
}