{
  "type": "Feature",
  "properties": {
    "addr:full":"508 Sandy Dr Shepherdsville KY 40165",
    "addr:housenumber":"508",
    "addr:postcode":"40165",
    "addr:street":"Sandy Dr",
    "iso:country":"US",
    "sg:address":"508 Sandy Dr",
    "sg:city":"Shepherdsville",
    "sg:classifiers":[
        {
            "category":"Home & Garden",
            "subcategory":"Carpets & Floor Coverings",
            "type":"Retail Goods"
        }
    ],
    "sg:phone":"+1 502 543 2566",
    "sg:postcode":"40165",
    "sg:province":"KY",
    "wof:name":"Rick S Carpet Service Co",
    "wof:placetype":"venue"
},
  "geometry": {"coordinates":[-85.64925599999999,38.018201],"type":"Point"}
}