{
  "type": "Feature",
  "properties": {
    "addr:full":"8300 Adams Run Rd Louisville KY 40228",
    "addr:housenumber":"8300",
    "addr:postcode":"40228",
    "addr:street":"Adams Run Rd",
    "iso:country":"US",
    "sg:address":"8300 Adams Run Rd",
    "sg:city":"Louisville",
    "sg:classifiers":[
        {
            "category":"Building & Trades",
            "subcategory":"Construction",
            "type":"Services"
        }
    ],
    "sg:phone":"+1 502 231 3831",
    "sg:postcode":"40228",
    "sg:province":"KY",
    "sg:tags":[
        "home",
        "builder"
    ],
    "wof:name":"Ball Homes Inc",
    "wof:placetype":"venue"
},
  "geometry": {"coordinates":[-85.61024500000001,38.116876],"type":"Point"}
}