{
  "type": "Feature",
  "properties": {
    "iso:country":"US",
    "sg:address":"1180 Four Wynds Trl",
    "sg:city":"Lexington",
    "sg:classifiers":[
        {
            "category":"Professional",
            "subcategory":"Art Services",
            "type":"Services"
        }
    ],
    "sg:phone":"+1 859 245 8189",
    "sg:postcode":"40515",
    "sg:province":"KY",
    "sg:tags":[
        "commercial",
        "design"
    ],
    "wof:name":"Thoroughbred Digitizing",
    "wof:placetype":"venue"
},
  "geometry": {"coordinates":[-84.48863799999999,37.962005],"type":"Point"}
}