{
  "type": "Feature",
  "properties": {
    "addr:full":"10000 Brownsboro Rd Louisville KY 40241",
    "addr:housenumber":"10000",
    "addr:postcode":"40241",
    "addr:street":"Brownsboro Rd",
    "iso:country":"US",
    "sg:address":"10000 Brownsboro Rd",
    "sg:city":"Louisville",
    "sg:classifiers":[
        {
            "category":"Retail",
            "subcategory":"Laundry & Dry Cleaning",
            "type":"Services"
        }
    ],
    "sg:phone":"+1 502 339 0604",
    "sg:postcode":"40241",
    "sg:province":"KY",
    "sg:tags":[
        "cleaners"
    ],
    "wof:name":"Thoroughbred Dry Cleaners",
    "wof:placetype":"venue"
},
  "geometry": {"coordinates":[-85.56147799999999,38.318608],"type":"Point"}
}