{
  "type": "Feature",
  "properties": {
    "iso:country":"US",
    "sg:address":"916 Dixie Hwy N",
    "sg:city":"Radcliff",
    "sg:classifiers":[
        {
            "category":"Retail",
            "subcategory":"Car Wash",
            "type":"Services"
        }
    ],
    "sg:phone":"+1 270 351 7848",
    "sg:postcode":"40160",
    "sg:province":"KY",
    "sg:tags":[
        "polishing",
        "washing"
    ],
    "wof:name":"All Star Car Wash",
    "wof:placetype":"venue"
},
  "geometry": {"coordinates":[-85.946484,37.848996],"type":"Point"}
}