{
  "type": "Feature",
  "properties": {
    "iso:country":"US",
    "sg:address":"117 Laurel Ln",
    "sg:city":"Paintsville",
    "sg:classifiers":[
        {
            "category":"Professional",
            "subcategory":"Management & Consulting",
            "type":"Services"
        }
    ],
    "sg:phone":"+1 606 789 5775",
    "sg:postcode":"41240",
    "sg:province":"KY",
    "sg:tags":[
        "retail",
        "direct",
        "sales"
    ],
    "wof:name":"Common Sense Publications",
    "wof:placetype":"venue"
},
  "geometry": {"coordinates":[-82.779752,37.816273],"type":"Point"}
}