{
  "type": "Feature",
  "properties": {
    "iso:country":"US",
    "sg:address":"5500 N Preston Hwy",
    "sg:city":"Shepherdsville",
    "sg:classifiers":[
        {
            "category":"Organizations",
            "subcategory":"Religious Organization",
            "type":"Services"
        }
    ],
    "sg:phone":"+1 502 957 7686",
    "sg:postcode":"40165",
    "sg:province":"KY",
    "sg:tags":[
        "church"
    ],
    "wof:name":"Little Flock Christian Academy",
    "wof:placetype":"venue"
},
  "geometry": {"coordinates":[-85.671249,38.061523],"type":"Point"}
}