{
  "type": "Feature",
  "properties": {
    "iso:country":"US",
    "sg:address":"2130 Crittenden Dr",
    "sg:city":"Louisville",
    "sg:classifiers":[
        {
            "category":"Retail",
            "subcategory":"Car Wash",
            "type":"Services"
        }
    ],
    "sg:phone":"+1 502 962 9991",
    "sg:postcode":"40217",
    "sg:province":"KY",
    "sg:tags":[
        "automobile",
        "detail",
        "clean"
    ],
    "wof:name":"Detailing Solutions Inc",
    "wof:placetype":"venue"
},
  "geometry": {"coordinates":[-85.750739,38.21589],"type":"Point"}
}