{
  "type": "Feature",
  "properties": {
    "iso:country":"US",
    "sg:address":"110 S Broadway St",
    "sg:city":"Carlisle",
    "sg:classifiers":[
        {
            "category":"Travel",
            "subcategory":"Hotels & Motels",
            "type":"Entertainment"
        }
    ],
    "sg:phone":"+1 859 289 2577",
    "sg:postcode":"40311",
    "sg:province":"KY",
    "sg:tags":[
        "resort"
    ],
    "wof:name":"Nicholas County Development",
    "wof:placetype":"venue"
},
  "geometry": {"coordinates":[-84.027902,38.311637],"type":"Point"}
}