{
  "type": "Feature",
  "properties": {
    "iso:country":"US",
    "sg:address":"600 W Main St",
    "sg:city":"Louisville",
    "sg:classifiers":[
        {
            "category":"Professional",
            "subcategory":"Lawyer & Legal Services",
            "type":"Services"
        }
    ],
    "sg:phone":"+1 502 583 5500",
    "sg:postcode":"40202",
    "sg:province":"KY",
    "sg:tags":[
        "attorney"
    ],
    "wof:name":"Bradley R Hume",
    "wof:placetype":"venue"
},
  "geometry": {"coordinates":[-85.761488,38.257158],"type":"Point"}
}