{
  "type": "Feature",
  "properties": {
    "iso:country":"US",
    "sg:address":"1021 N Yarnallton Pike",
    "sg:city":"Lexington",
    "sg:classifiers":[
        {
            "category":"Real Estate",
            "subcategory":"Real Estate Agent",
            "type":"Services"
        }
    ],
    "sg:phone":"+1 859 233 0700",
    "sg:postcode":"40511",
    "sg:province":"KY",
    "wof:name":"White Horse Properties",
    "wof:placetype":"venue"
},
  "geometry": {"coordinates":[-84.572639,38.130282],"type":"Point"}
}