{
  "type": "Feature",
  "properties": {
    "iso:country":"US",
    "sg:address":"146 Consumer Ln",
    "sg:city":"Frankfort",
    "sg:classifiers":[
        {
            "category":"Social Services",
            "subcategory":"Child Care",
            "type":"Services"
        }
    ],
    "sg:phone":"+1 502 223 5002",
    "sg:postcode":"40601",
    "sg:province":"KY",
    "wof:name":"Kentucky Assn-Childcare Rsrc",
    "wof:placetype":"venue"
},
  "geometry": {"coordinates":[-84.892839,38.150206],"type":"Point"}
}