{
  "type": "Feature",
  "properties": {
    "iso:country":"US",
    "sg:address":"4895 Beaver Rd",
    "sg:city":"Union",
    "sg:classifiers":[
        {
            "category":"Recreation",
            "subcategory":"Marina",
            "type":"Entertainment"
        }
    ],
    "sg:phone":"+1 859 384 0282",
    "sg:postcode":"41091",
    "sg:province":"KY",
    "wof:name":"Trixies Marina",
    "wof:placetype":"venue"
},
  "geometry": {"coordinates":[-84.796656,38.90195],"type":"Point"}
}