{
  "type": "Feature",
  "properties": {
    "iso:country":"US",
    "sg:address":"5000 Long Knife Run",
    "sg:city":"Louisville",
    "sg:classifiers":[
        {
            "category":"Wholesale",
            "subcategory":"Medical Equipment & Supplies",
            "type":"Manufacturing & Wholesale Goods"
        }
    ],
    "sg:phone":"+1 502 893 8892",
    "sg:postcode":"40207",
    "sg:province":"KY",
    "sg:tags":[
        "pharmaceutical",
        "prep",
        "mfg"
    ],
    "wof:name":"James Michael Berryman",
    "wof:placetype":"venue"
},
  "geometry": {"coordinates":[-85.65886500000001,38.282246],"type":"Point"}
}