{
  "type": "Feature",
  "properties": {
    "iso:country":"US",
    "sg:address":"2517 Dixie Hwy",
    "sg:city":"Fort Mitchell",
    "sg:classifiers":[
        {
            "category":"Shopping",
            "subcategory":"Clothing, Apparel, & Fashions",
            "type":"Retail Goods"
        }
    ],
    "sg:phone":"+1 859 331 6111",
    "sg:postcode":"41017",
    "sg:province":"KY",
    "sg:tags":[
        "alteration"
    ],
    "wof:name":"Top Quality Cleaners Inc",
    "wof:placetype":"venue"
},
  "geometry": {"coordinates":[-84.56049,39.036611],"type":"Point"}
}