{
  "type": "Feature",
  "properties": {
    "iso:country":"US",
    "sg:address":"269 Old Porter Pike",
    "sg:city":"Bowling Green",
    "sg:classifiers":[
        {
            "category":"Building & Trades",
            "subcategory":"Construction",
            "type":"Services"
        }
    ],
    "sg:phone":"+1 270 842 2989",
    "sg:postcode":"42103",
    "sg:province":"KY",
    "sg:tags":[
        "roofing",
        "contractor"
    ],
    "wof:name":"Hale Roofing Inc",
    "wof:placetype":"venue"
},
  "geometry": {"coordinates":[-86.397817,37.007946],"type":"Point"}
}