{
  "type": "Feature",
  "properties": {
    "addr:full":"235 Longview Dr Paducah KY 42001",
    "addr:housenumber":"235",
    "addr:postcode":"42001",
    "addr:street":"Longview Dr",
    "iso:country":"US",
    "sg:address":"235 Longview Dr",
    "sg:city":"Paducah",
    "sg:classifiers":[
        {
            "category":"Shopping",
            "subcategory":"Department Store",
            "type":"Retail Goods"
        }
    ],
    "sg:phone":"+1 270 744 8064",
    "sg:postcode":"42001",
    "sg:province":"KY",
    "wof:name":"Surplus USA Liquidations",
    "wof:placetype":"venue"
},
  "geometry": {"coordinates":[-88.680633,37.038405],"type":"Point"}
}