{
  "type": "Feature",
  "properties": {
    "iso:country":"US",
    "sg:address":"300 Brinegar Ln",
    "sg:city":"Winchester",
    "sg:classifiers":[
        {
            "category":"Mining & Drilling",
            "type":"Manufacturing & Wholesale Goods"
        }
    ],
    "sg:phone":"+1 859 744 7663",
    "sg:postcode":"40391",
    "sg:province":"KY",
    "sg:tags":[
        "limestone"
    ],
    "wof:name":"Brinegar Limestone Spreading",
    "wof:placetype":"venue"
},
  "geometry": {"coordinates":[-84.12706300000001,37.920423],"type":"Point"}
}