{
  "type": "Feature",
  "properties": {
    "iso:country":"US",
    "sg:address":"8009 New Lagrange Rd",
    "sg:city":"Louisville",
    "sg:classifiers":[
        {
            "category":"Wholesale",
            "subcategory":"Electrical",
            "type":"Manufacturing & Wholesale Goods"
        }
    ],
    "sg:phone":"+1 502 423 5398",
    "sg:postcode":"40222",
    "sg:province":"KY",
    "sg:tags":[
        "fire",
        "alarm",
        "system"
    ],
    "wof:name":"Fire Alarm Pros LLC",
    "wof:placetype":"venue"
},
  "geometry": {"coordinates":[-85.605082,38.258016],"type":"Point"}
}