{
  "type": "Feature",
  "properties": {
    "addr:full":"699 Shaker Mill Rd Bowling Green KY 42103",
    "addr:housenumber":"699",
    "addr:postcode":"42103",
    "addr:street":"Shaker Mill Rd",
    "iso:country":"US",
    "sg:address":"699 Shaker Mill Rd",
    "sg:city":"Bowling Green",
    "sg:classifiers":[
        {
            "category":"Freight",
            "type":"Transportation"
        }
    ],
    "sg:phone":"+1 270 746 0816",
    "sg:postcode":"42103",
    "sg:province":"KY",
    "sg:tags":[
        "commercial",
        "storage"
    ],
    "wof:name":"Riverwood Mini Storage",
    "wof:placetype":"venue"
},
  "geometry": {"coordinates":[-86.38959199999999,36.968047],"type":"Point"}
}