{
  "type": "Feature",
  "properties": {
    "iso:country":"US",
    "sg:address":"989 Logan St",
    "sg:city":"Louisville",
    "sg:classifiers":[
        {
            "category":"Home & Garden",
            "subcategory":"Building Materials",
            "type":"Retail Goods"
        }
    ],
    "sg:phone":"+1 502 315 5110",
    "sg:postcode":"40204",
    "sg:province":"KY",
    "sg:tags":[
        "granite",
        "top",
        "counter"
    ],
    "sg:website":"http://www.stonemarkgranite.com",
    "wof:name":"Stonemark Granite",
    "wof:placetype":"venue"
},
  "geometry": {"coordinates":[-85.739487,38.23682],"type":"Point"}
}