{
  "type": "Feature",
  "properties": {
    "addr:full":"703 Danville Ave Stanford KY 40484",
    "addr:housenumber":"703",
    "addr:postcode":"40484",
    "addr:street":"Danville Ave",
    "iso:country":"US",
    "sg:address":"703 Danville Ave",
    "sg:city":"Stanford",
    "sg:classifiers":[
        {
            "category":"Banks & Credit Unions",
            "subcategory":"Bank",
            "type":"Services"
        }
    ],
    "sg:phone":"+1 606 365 9338",
    "sg:postcode":"40484",
    "sg:province":"KY",
    "sg:tags":[
        "loan"
    ],
    "wof:name":"Kentucky Fidelity Mtg & Ins",
    "wof:placetype":"venue"
},
  "geometry": {"coordinates":[-84.670636,37.542162],"type":"Point"}
}