{
  "type": "Feature",
  "properties": {
    "addr:full":"107 N Killarney Ln Richmond KY 40475",
    "addr:housenumber":"107",
    "addr:postcode":"40475",
    "addr:street":"N Killarney Ln",
    "iso:country":"US",
    "sg:address":"107 N Killarney Ln",
    "sg:city":"Richmond",
    "sg:classifiers":[
        {
            "category":"Real Estate",
            "subcategory":"Real Estate Agent",
            "type":"Services"
        }
    ],
    "sg:phone":"+1 859 623 8777",
    "sg:postcode":"40475",
    "sg:province":"KY",
    "wof:name":"Coldwell Banker",
    "wof:placetype":"venue"
},
  "geometry": {"coordinates":[-84.31974200000001,37.737653],"type":"Point"}
}