{
  "type": "Feature",
  "properties": {
    "addr:full":"10911 Bearcamp Rd Louisville KY 40272",
    "addr:housenumber":"10911",
    "addr:postcode":"40272",
    "addr:street":"Bearcamp Rd",
    "iso:country":"US",
    "sg:address":"10911 Bearcamp Rd",
    "sg:city":"Louisville",
    "sg:classifiers":[
        {
            "category":"Home & Garden",
            "subcategory":"Garden Supply",
            "type":"Retail Goods"
        },
        {
            "category":"Wholesale",
            "subcategory":"Plants",
            "type":"Manufacturing & Wholesale Goods"
        },
        {
            "category":"Home & Garden",
            "subcategory":"Building Materials",
            "type":"Retail Goods"
        },
        {
            "category":"Manufacturing",
            "subcategory":"Paper Products",
            "type":"Manufacturing & Wholesale Goods"
        },
        {
            "category":"Farming",
            "subcategory":"Nursery",
            "type":"Manufacturing & Wholesale Goods"
        }
    ],
    "sg:phone":"+1 502 937 6132",
    "sg:postcode":"40272",
    "sg:province":"KY",
    "sg:tags":[
        "nurseries-plants",
        "builder",
        "tree",
        "nursery-wholesale",
        "equipment",
        "greenhouse",
        "bamboo",
        "grower",
        "growers'"
    ],
    "wof:name":"Creek Ridge Greenhouses Inc",
    "wof:placetype":"venue"
},
  "geometry": {"coordinates":[-85.81293100000001,38.094833],"type":"Point"}
}