{
  "type": "Feature",
  "properties": {
    "iso:country":"US",
    "sg:address":"1762 Big Hill Rd",
    "sg:city":"Berea",
    "sg:classifiers":[
        {
            "category":"Home & Garden",
            "subcategory":"Garden Supply",
            "type":"Retail Goods"
        }
    ],
    "sg:phone":"+1 859 986 9587",
    "sg:postcode":"40403",
    "sg:province":"KY",
    "sg:tags":[
        "fertilizer"
    ],
    "wof:name":"Johnson Farm Supply Inc",
    "wof:placetype":"venue"
},
  "geometry": {"coordinates":[-84.258894,37.563772],"type":"Point"}
}