{
  "type": "Feature",
  "properties": {
    "iso:country":"US",
    "sg:address":"3793 Poplar Level Rd",
    "sg:city":"Louisville",
    "sg:classifiers":[
        {
            "category":"Professional",
            "subcategory":"Management & Consulting",
            "type":"Services"
        }
    ],
    "sg:phone":"+1 502 452 6423",
    "sg:postcode":"40213",
    "sg:province":"KY",
    "sg:tags":[
        "medical",
        "administration",
        "business"
    ],
    "wof:name":"Kentuckiana Medical Billing Service",
    "wof:placetype":"venue"
},
  "geometry": {"coordinates":[-85.71347799999999,38.206089],"type":"Point"}
}