{
  "type": "Feature",
  "properties": {
    "iso:country":"US",
    "sg:address":"50 Cooper Ave",
    "sg:city":"Beaver Dam",
    "sg:classifiers":[
        {
            "category":"Real Estate",
            "subcategory":"Real Estate Operator",
            "type":"Services"
        }
    ],
    "sg:phone":"+1 270 274 7579",
    "sg:postcode":"42320",
    "sg:province":"KY",
    "sg:tags":[
        "building",
        "apartment"
    ],
    "wof:name":"Blanchard Manor Apartments",
    "wof:placetype":"venue"
},
  "geometry": {"coordinates":[-86.87120299999999,37.391027],"type":"Point"}
}