{
  "type": "Feature",
  "properties": {
    "iso:country":"US",
    "sg:address":"481 Poor Farm Rd",
    "sg:city":"Murray",
    "sg:classifiers":[
        {
            "category":"Building & Trades",
            "subcategory":"Construction",
            "type":"Services"
        }
    ],
    "sg:phone":"+1 270 767 9160",
    "sg:postcode":"42071",
    "sg:province":"KY",
    "sg:tags":[
        "general",
        "contractor"
    ],
    "wof:name":"Jim Smith Contracting Co",
    "wof:placetype":"venue"
},
  "geometry": {"coordinates":[-88.323949,36.645727],"type":"Point"}
}