{
  "type": "Feature",
  "properties": {
    "iso:country":"US",
    "sg:address":"1860 S Danville Byp",
    "sg:city":"Danville",
    "sg:classifiers":[
        {
            "category":"Government",
            "subcategory":"Jail",
            "type":"Public Place"
        }
    ],
    "sg:phone":"+1 859 238 1127",
    "sg:postcode":"40422",
    "sg:province":"KY",
    "sg:tags":[
        "county",
        "govt",
        "institution"
    ],
    "wof:name":"Boyle County Jail",
    "wof:placetype":"venue"
},
  "geometry": {"coordinates":[-84.777793,37.617061],"type":"Point"}
}