{
  "type": "Feature",
  "properties": {
    "addr:full":"104 Secretariat St Georgetown KY 40324",
    "addr:housenumber":"104",
    "addr:postcode":"40324",
    "addr:street":"Secretariat St",
    "iso:country":"US",
    "sg:address":"104 Secretariat St",
    "sg:city":"Georgetown",
    "sg:classifiers":[
        {
            "category":"Retail",
            "subcategory":"Repair Shop",
            "type":"Services"
        }
    ],
    "sg:phone":"+1 502 535 5598",
    "sg:postcode":"40324",
    "sg:province":"KY",
    "sg:tags":[
        "upholsterer"
    ],
    "wof:name":"Touch O Class Upholstery",
    "wof:placetype":"venue"
},
  "geometry": {"coordinates":[-84.577935,38.24041],"type":"Point"}
}