{
  "type": "Feature",
  "properties": {
    "addr:full":"8243 State Hwy 141 Morganfield KY 42437",
    "addr:housenumber":"8243",
    "addr:postcode":"42437",
    "addr:street":"State Hwy 141",
    "iso:country":"US",
    "sg:address":"8243 State Hwy 141",
    "sg:city":"Morganfield",
    "sg:classifiers":[
        {
            "category":"Farming",
            "subcategory":"Livestock Farm",
            "type":"Manufacturing & Wholesale Goods"
        }
    ],
    "sg:phone":"+1 270 389 0257",
    "sg:postcode":"42437",
    "sg:province":"KY",
    "sg:tags":[
        "corn",
        "beef",
        "feedlot",
        "cattle"
    ],
    "wof:name":"Jack Freer",
    "wof:placetype":"venue"
},
  "geometry": {"coordinates":[-87.828943,37.626049],"type":"Point"}
}