{
  "type": "Feature",
  "properties": {
    "addr:full":"2011 US Hwy 60 Henderson KY 42420",
    "addr:housenumber":"2011",
    "addr:postcode":"42420",
    "addr:street":"Us Hwy 60",
    "iso:country":"US",
    "sg:address":"2011 US Hwy 60",
    "sg:city":"Henderson",
    "sg:classifiers":[
        {
            "category":"Banks & Credit Unions",
            "subcategory":"Bank",
            "type":"Services"
        }
    ],
    "sg:phone":"+1 270 831 6860",
    "sg:postcode":"42420",
    "sg:province":"KY",
    "wof:name":"Old National Bank",
    "wof:placetype":"venue"
},
  "geometry": {"coordinates":[-87.566327,37.860462],"type":"Point"}
}