{
  "type": "Feature",
  "properties": {
    "iso:country":"US",
    "sg:address":"8119 Elkhorn Creek",
    "sg:city":"Ashcamp",
    "sg:classifiers":[
        {
            "category":"Utilities",
            "subcategory":"Natural Gas",
            "type":"Services"
        }
    ],
    "sg:phone":"+1 606 754 4331",
    "sg:postcode":"41512",
    "sg:province":"KY",
    "wof:name":"Elkhorn Gas & Home Center",
    "wof:placetype":"venue"
},
  "geometry": {"coordinates":[-82.448876,37.264245],"type":"Point"}
}