{
  "type": "Feature",
  "properties": {
    "iso:country":"US",
    "sg:address":"111 Obrien St",
    "sg:city":"Greenville",
    "sg:classifiers":[
        {
            "category":"Real Estate",
            "subcategory":"Surveying",
            "type":"Services"
        }
    ],
    "sg:phone":"+1 270 338 3187",
    "sg:postcode":"42345",
    "sg:province":"KY",
    "sg:tags":[
        "surveyor"
    ],
    "wof:name":"Larry Hill",
    "wof:placetype":"venue"
},
  "geometry": {"coordinates":[-87.177897,37.202336],"type":"Point"}
}