{
  "type": "Feature",
  "properties": {
    "iso:country":"US",
    "sg:address":"640 E Center St",
    "sg:city":"Madisonville",
    "sg:classifiers":[
        {
            "category":"Professional",
            "type":"Services"
        }
    ],
    "sg:phone":"+1 270 824 8276",
    "sg:postcode":"42431",
    "sg:province":"KY",
    "sg:tags":[
        "establishment"
    ],
    "wof:name":"Waffen Arms",
    "wof:placetype":"venue"
},
  "geometry": {"coordinates":[-87.48616,37.327584],"type":"Point"}
}