{
  "type": "Feature",
  "properties": {
    "addr:full":"1031 W Lexington Ave Winchester KY 40391",
    "addr:housenumber":"1031",
    "addr:postcode":"40391",
    "addr:street":"W Lexington Ave",
    "iso:country":"US",
    "sg:address":"1031 W Lexington Ave",
    "sg:city":"Winchester",
    "sg:classifiers":[
        {
            "category":"Autos & Motor Vehicles",
            "subcategory":"Automobile Sales",
            "type":"Retail Goods"
        }
    ],
    "sg:phone":"+1 859 744 7800",
    "sg:postcode":"40391",
    "sg:province":"KY",
    "sg:tags":[
        "car",
        "dealer"
    ],
    "wof:name":"Fitzpatrick Motors Inc",
    "wof:placetype":"venue"
},
  "geometry": {"coordinates":[-84.194446,37.998696],"type":"Point"}
}