{
  "type": "Feature",
  "properties": {
    "iso:country":"US",
    "sg:address":"5005 Cadiz Rd",
    "sg:city":"Hopkinsville",
    "sg:phone":"+1 270 885 8488",
    "sg:postcode":"42240",
    "sg:province":"KY",
    "sg:tags":[
        "farm",
        "grain",
        "cash",
        "tobacco"
    ],
    "wof:name":"Arnold Farms Inc",
    "wof:placetype":"venue"
},
  "geometry": {"coordinates":[-87.56482699999999,36.878246],"type":"Point"}
}