{
  "type": "Feature",
  "properties": {
    "iso:country":"US",
    "sg:address":"8911 Greeneway Commons Pl",
    "sg:city":"Louisville",
    "sg:classifiers":[
        {
            "category":"Organizations",
            "subcategory":"Religious Organization",
            "type":"Services"
        }
    ],
    "sg:phone":"+1 502 491 7091",
    "sg:postcode":"40220",
    "sg:province":"KY",
    "sg:tags":[
        "church"
    ],
    "wof:name":"District Office Of The Umc",
    "wof:placetype":"venue"
},
  "geometry": {"coordinates":[-85.598056,38.21386],"type":"Point"}
}