{
  "type": "Feature",
  "properties": {
    "iso:country":"US",
    "sg:address":"2280 Winchester Ave",
    "sg:city":"Ashland",
    "sg:classifiers":[
        {
            "category":"Travel",
            "subcategory":"Hotels & Motels",
            "type":"Entertainment"
        }
    ],
    "sg:phone":"+1 606 329 2868",
    "sg:postcode":"41101",
    "sg:province":"KY",
    "wof:name":"Winchester Inn Motel",
    "wof:placetype":"venue"
},
  "geometry": {"coordinates":[-82.63176,38.474751],"type":"Point"}
}