{
  "type": "Feature",
  "properties": {
    "addr:full":"10326 Amberwell Park Rd Louisville KY 40241",
    "addr:housenumber":"10326",
    "addr:postcode":"40241",
    "addr:street":"Amberwell Park Rd",
    "iso:country":"US",
    "sg:address":"10326 Amberwell Park Rd",
    "sg:city":"Louisville",
    "sg:classifiers":[
        {
            "category":"Wholesale",
            "subcategory":"Farm Supplies",
            "type":"Manufacturing & Wholesale Goods"
        }
    ],
    "sg:phone":"+1 502 394 9395",
    "sg:postcode":"40241",
    "sg:province":"KY",
    "sg:tags":[
        "feed",
        "merchandise"
    ],
    "wof:name":"Speed Feeds Inc",
    "wof:placetype":"venue"
},
  "geometry": {"coordinates":[-85.559534,38.288721],"type":"Point"}
}