{
  "type": "Feature",
  "properties": {
    "iso:country":"US",
    "sg:address":"2200 Erwin Rd",
    "sg:city":"Murray",
    "sg:classifiers":[
        {
            "category":"Wholesale",
            "subcategory":"Electrical",
            "type":"Manufacturing & Wholesale Goods"
        }
    ],
    "sg:phone":"+1 270 759 4476",
    "sg:postcode":"42071",
    "sg:province":"KY",
    "sg:tags":[
        "alarm",
        "burglar",
        "system"
    ],
    "wof:name":"Advanced Security & Electronic",
    "wof:placetype":"venue"
},
  "geometry": {"coordinates":[-88.397212,36.567386],"type":"Point"}
}