{
  "type": "Feature",
  "properties": {
    "iso:country":"US",
    "sg:address":"1060 Glensboro Rd",
    "sg:city":"Lawrenceburg",
    "sg:classifiers":[
        {
            "category":"Health Services",
            "subcategory":"Hospital",
            "type":"Services"
        }
    ],
    "sg:phone":"+1 502 839 5361",
    "sg:postcode":"40342",
    "sg:province":"KY",
    "sg:tags":[
        "mental"
    ],
    "wof:name":"Rainbow House",
    "wof:placetype":"venue"
},
  "geometry": {"coordinates":[-84.913726,38.032081],"type":"Point"}
}