{
  "type": "Feature",
  "properties": {
    "iso:country":"US",
    "sg:address":"1828 South Rd",
    "sg:city":"Cadiz",
    "sg:classifiers":[
        {
            "category":"Organizations",
            "subcategory":"Religious Organization",
            "type":"Services"
        }
    ],
    "sg:phone":"+1 270 522 3929",
    "sg:postcode":"42211",
    "sg:province":"KY",
    "sg:tags":[
        "church"
    ],
    "wof:name":"S Cadiz United Meth Circuit",
    "wof:placetype":"venue"
},
  "geometry": {"coordinates":[-87.82246000000001,36.838448],"type":"Point"}
}