{
  "type": "Feature",
  "properties": {
    "addr:full":"4138 Taylor Blvd Louisville KY 40215",
    "addr:housenumber":"4138",
    "addr:postcode":"40215",
    "addr:street":"Taylor Blvd",
    "iso:country":"US",
    "sg:address":"4138 Taylor Blvd",
    "sg:city":"Louisville",
    "sg:classifiers":[
        {
            "category":"Utilities",
            "subcategory":"Mobile Phone",
            "type":"Services"
        },
        {
            "category":"Utilities",
            "subcategory":"Telephone",
            "type":"Services"
        },
        {
            "category":"Shopping",
            "subcategory":"Mobile Phones",
            "type":"Retail Goods"
        },
        {
            "category":"Manufacturing",
            "subcategory":"Electronics",
            "type":"Manufacturing & Wholesale Goods"
        }
    ],
    "sg:phone":"+1 502 361 5498",
    "sg:postcode":"40215",
    "sg:province":"KY",
    "sg:tags":[
        "equipment",
        "telecommunications-equipment",
        "system",
        "cellular",
        "supply"
    ],
    "wof:name":"Hello Enterprise",
    "wof:placetype":"venue"
},
  "geometry": {"coordinates":[-85.783552,38.181727],"type":"Point"}
}