{
  "type": "Feature",
  "properties": {
    "iso:country":"US",
    "sg:address":"1234 W Broadway",
    "sg:city":"Louisville",
    "sg:classifiers":[
        {
            "category":"Freight",
            "type":"Transportation"
        }
    ],
    "sg:phone":"+1 502 587 3487",
    "sg:postcode":"40203",
    "sg:province":"KY",
    "sg:tags":[
        "delivery"
    ],
    "sg:website":"www.zipexpress.com",
    "wof:name":"Zip Express Courier Svc",
    "wof:placetype":"venue"
},
  "geometry": {"coordinates":[-85.77282099999999,38.247632],"type":"Point"}
}