{
  "type": "Feature",
  "properties": {
    "addr:full":"1726 Mellwood Ave Louisville KY 40206",
    "addr:housenumber":"1726",
    "addr:postcode":"40206",
    "addr:street":"Mellwood Ave",
    "iso:country":"US",
    "sg:address":"1726 Mellwood Ave",
    "sg:city":"Louisville",
    "sg:classifiers":[
        {
            "category":"Real Estate",
            "subcategory":"Real Estate Agent",
            "type":"Services"
        }
    ],
    "sg:phone":"+1 502 897 5528",
    "sg:postcode":"40206",
    "sg:province":"KY",
    "wof:name":"Frankfort Properties",
    "wof:placetype":"venue"
},
  "geometry": {"coordinates":[-85.71781300000001,38.258904],"type":"Point"}
}