{
  "type": "Feature",
  "properties": {
    "addr:full":"10000 Watsonville Rd Louisville KY 40272",
    "addr:housenumber":"10000",
    "addr:postcode":"40272",
    "addr:street":"Watsonville Rd",
    "iso:country":"US",
    "sg:address":"10000 Watsonville Rd",
    "sg:city":"Louisville",
    "sg:classifiers":[
        {
            "category":"Manufacturing",
            "subcategory":"Chemicals & Compounds",
            "type":"Manufacturing & Wholesale Goods"
        }
    ],
    "sg:phone":"+1 502 935 8835",
    "sg:postcode":"40272",
    "sg:province":"KY",
    "sg:tags":[
        "compounds",
        "powders",
        "materials-colorants",
        "plastics-raw",
        "resins",
        "liquids"
    ],
    "wof:name":"J R Machine & Tool, Inc.",
    "wof:placetype":"venue"
},
  "geometry": {"coordinates":[-85.818451,38.107342],"type":"Point"}
}