{
  "type": "Feature",
  "properties": {
    "addr:full":"309 Lyttle Blvd Hazard KY 41701",
    "addr:housenumber":"309",
    "addr:postcode":"41701",
    "addr:street":"Lyttle Blvd",
    "iso:country":"US",
    "sg:address":"309 Lyttle Blvd",
    "sg:city":"Hazard",
    "sg:classifiers":[
        {
            "category":"Manufacturing",
            "subcategory":"Printing",
            "type":"Manufacturing & Wholesale Goods"
        }
    ],
    "sg:phone":"+1 606 439 1569",
    "sg:postcode":"41701",
    "sg:province":"KY",
    "sg:tags":[
        "consulting",
        "document",
        "computer",
        "publishing"
    ],
    "wof:name":"Sphere Publishing House",
    "wof:placetype":"venue"
},
  "geometry": {"coordinates":[-83.192064,37.250516],"type":"Point"}
}