{
  "type": "Feature",
  "properties": {
    "addr:full":"232 E Jacob St Louisville KY 40203",
    "addr:housenumber":"232",
    "addr:postcode":"40203",
    "addr:street":"E Jacob St",
    "iso:country":"US",
    "sg:address":"232 E Jacob St",
    "sg:city":"Louisville",
    "sg:classifiers":[
        {
            "category":"Organizations",
            "subcategory":"Religious Organization",
            "type":"Services"
        }
    ],
    "sg:phone":"+1 502 561 1690",
    "sg:postcode":"40203",
    "sg:province":"KY",
    "sg:tags":[
        "church"
    ],
    "wof:name":"Greater New Hope Community Chr",
    "wof:placetype":"venue"
},
  "geometry": {"coordinates":[-85.750409,38.243973],"type":"Point"}
}