{
  "type": "Feature",
  "properties": {
    "iso:country":"US",
    "sg:address":"655 Cottonwood Dr",
    "sg:city":"Radcliff",
    "sg:classifiers":[
        {
            "category":"Freight",
            "type":"Transportation"
        }
    ],
    "sg:phone":"+1 270 351 7737",
    "sg:postcode":"40160",
    "sg:province":"KY",
    "sg:tags":[
        "trucking"
    ],
    "wof:name":"Brangers Trucking",
    "wof:placetype":"venue"
},
  "geometry": {"coordinates":[-85.963376,37.841652],"type":"Point"}
}