{
  "type": "Feature",
  "properties": {
    "addr:full":"7309 Preston Hwy Okolona KY 40219",
    "addr:housenumber":"7309",
    "addr:postcode":"40219",
    "addr:street":"Preston Hwy",
    "iso:country":"US",
    "sg:address":"7309 Preston Hwy",
    "sg:city":"Okolona",
    "sg:classifiers":[
        {
            "category":"Building & Trades",
            "subcategory":"Plumbing",
            "type":"Services"
        }
    ],
    "sg:phone":"+1 502 968 4821",
    "sg:postcode":"40219",
    "sg:province":"KY",
    "sg:tags":[
        "conditioning",
        "air",
        "system",
        "contractor"
    ],
    "wof:name":"Hood's Heating & Air Cond Inc",
    "wof:placetype":"venue"
},
  "geometry": {"coordinates":[-85.690495,38.145442],"type":"Point"}
}