{
  "type": "Feature",
  "properties": {
    "iso:country":"US",
    "sg:address":"226 Peterson Dr",
    "sg:city":"Elizabethtown",
    "sg:classifiers":[
        {
            "category":"Building & Trades",
            "subcategory":"Construction",
            "type":"Services"
        }
    ],
    "sg:phone":"+1 270 234 0058",
    "sg:postcode":"42701",
    "sg:province":"KY",
    "sg:tags":[
        "erectors",
        "machinery"
    ],
    "wof:name":"Fighter Group LLC",
    "wof:placetype":"venue"
},
  "geometry": {"coordinates":[-85.899806,37.682357],"type":"Point"}
}