{
  "type": "Feature",
  "properties": {
    "addr:full":"23 Grandview Dr Frankfort KY 40601",
    "addr:housenumber":"23",
    "addr:postcode":"40601",
    "addr:street":"Grandview Dr",
    "iso:country":"US",
    "sg:address":"23 Grandview Dr",
    "sg:city":"Frankfort",
    "sg:classifiers":[
        {
            "category":"Home & Garden",
            "subcategory":"Home Furnishings",
            "type":"Retail Goods"
        }
    ],
    "sg:phone":"+1 502 848 1140",
    "sg:postcode":"40601",
    "sg:province":"KY",
    "sg:tags":[
        "upholstery",
        "fabric"
    ],
    "wof:name":"Howard's Upholstery",
    "wof:placetype":"venue"
},
  "geometry": {"coordinates":[-84.830872,38.202548],"type":"Point"}
}