{
  "type": "Feature",
  "properties": {
    "addr:full":"1216 Wing Ave Owensboro KY 42303",
    "addr:housenumber":"1216",
    "addr:postcode":"42303",
    "addr:street":"Wing Ave",
    "iso:country":"US",
    "sg:address":"1216 Wing Ave",
    "sg:city":"Owensboro",
    "sg:classifiers":[
        {
            "category":"Manufacturing",
            "subcategory":"Tools & Machinery",
            "type":"Manufacturing & Wholesale Goods"
        }
    ],
    "sg:phone":"+1 270 684 3668",
    "sg:postcode":"42303",
    "sg:province":"KY",
    "sg:tags":[
        "machine",
        "shop"
    ],
    "sg:website":"www.immci.com",
    "wof:name":"Industrial Mold & Machine Co",
    "wof:placetype":"venue"
},
  "geometry": {"coordinates":[-87.089304,37.767689],"type":"Point"}
}