{
  "type": "Feature",
  "properties": {
    "addr:full":"2777 Pioneer Dr Bowling Green KY 42101",
    "addr:housenumber":"2777",
    "addr:postcode":"42101",
    "addr:street":"Pioneer Dr",
    "iso:country":"US",
    "sg:address":"2777 Pioneer Dr",
    "sg:city":"Bowling Green",
    "sg:classifiers":[
        {
            "category":"Building & Trades",
            "subcategory":"Plumbing",
            "type":"Services"
        }
    ],
    "sg:phone":"+1 270 843 2135",
    "sg:postcode":"42101",
    "sg:province":"KY",
    "sg:tags":[
        "plumbing",
        "contractor"
    ],
    "wof:name":"C & C Plumbing",
    "wof:placetype":"venue"
},
  "geometry": {"coordinates":[-86.48854900000001,36.95386],"type":"Point"}
}