{
  "type": "Feature",
  "properties": {
    "iso:country":"US",
    "sg:address":"9500 Williamsburg Plz",
    "sg:city":"Louisville",
    "sg:classifiers":[
        {
            "category":"Personal",
            "type":"Services"
        }
    ],
    "sg:phone":"+1 502 339 3095",
    "sg:postcode":"40222",
    "sg:province":"KY",
    "sg:tags":[
        "advisory",
        "consumer",
        "counseling"
    ],
    "wof:name":"G E Co",
    "wof:placetype":"venue"
},
  "geometry": {"coordinates":[-85.578402,38.24006],"type":"Point"}
}