{
  "type": "Feature",
  "properties": {
    "iso:country":"US",
    "sg:address":"121 Clay Dr",
    "sg:city":"Berea",
    "sg:classifiers":[
        {
            "category":"Sports & Exercise",
            "subcategory":"Gym",
            "type":"Entertainment"
        }
    ],
    "sg:phone":"+1 859 985 5151",
    "sg:postcode":"40403",
    "sg:province":"KY",
    "sg:tags":[
        "club",
        "health",
        "studio",
        "gymnasium"
    ],
    "wof:name":"Total Fitness",
    "wof:placetype":"venue"
},
  "geometry": {"coordinates":[-84.284284,37.584218],"type":"Point"}
}