{
  "type": "Feature",
  "properties": {
    "addr:full":"6601 Mount Washington Rd Louisville KY 40229",
    "addr:housenumber":"6601",
    "addr:postcode":"40229",
    "addr:street":"Mount Washington Rd",
    "iso:country":"US",
    "sg:address":"6601 Mount Washington Rd",
    "sg:city":"Louisville",
    "sg:classifiers":[
        {
            "category":"Building & Trades",
            "subcategory":"Plumbing",
            "type":"Services"
        }
    ],
    "sg:phone":"+1 502 231 1834",
    "sg:postcode":"40229",
    "sg:province":"KY",
    "sg:tags":[
        "plumbing",
        "contractor"
    ],
    "wof:name":"Quire Plumbing Co",
    "wof:placetype":"venue"
},
  "geometry": {"coordinates":[-85.63623200000001,38.083695],"type":"Point"}
}