{
  "type": "Feature",
  "properties": {
    "addr:full":"157 3rd St Pikeville KY 41501",
    "addr:housenumber":"157",
    "addr:postcode":"41501",
    "addr:street":"3Rd St",
    "iso:country":"US",
    "sg:address":"157 3rd St",
    "sg:city":"Pikeville",
    "sg:classifiers":[
        {
            "category":"Shopping",
            "subcategory":"Clothing, Apparel, & Fashions",
            "type":"Retail Goods"
        }
    ],
    "sg:phone":"+1 606 432 5689",
    "sg:postcode":"41501",
    "sg:province":"KY",
    "sg:tags":[
        "swimwear",
        "accessory"
    ],
    "wof:name":"Ghostbusters Tanning & More",
    "wof:placetype":"venue"
},
  "geometry": {"coordinates":[-82.51748499999999,37.483036],"type":"Point"}
}