{
  "type": "Feature",
  "properties": {
    "addr:full":"326 S Jefferson St Princeton KY 42445",
    "addr:housenumber":"326",
    "addr:postcode":"42445",
    "addr:street":"S Jefferson St",
    "iso:country":"US",
    "sg:address":"326 S Jefferson St",
    "sg:city":"Princeton",
    "sg:classifiers":[
        {
            "category":"Retail",
            "subcategory":"Car Wash",
            "type":"Services"
        }
    ],
    "sg:phone":"+1 270 365 0807",
    "sg:postcode":"42445",
    "sg:province":"KY",
    "sg:tags":[
        "carwash"
    ],
    "wof:name":"Handshakes",
    "wof:placetype":"venue"
},
  "geometry": {"coordinates":[-87.884473,37.105132],"type":"Point"}
}