{
  "type": "Feature",
  "properties": {
    "addr:full":"302 Big Hill Ave Richmond KY 40475",
    "addr:housenumber":"302",
    "addr:postcode":"40475",
    "addr:street":"Big Hill Ave",
    "iso:country":"US",
    "sg:address":"302 Big Hill Ave",
    "sg:city":"Richmond",
    "sg:classifiers":[
        {
            "category":"Food & Beverages",
            "subcategory":"Liquor & Beverages",
            "type":"Retail Goods"
        }
    ],
    "sg:phone":"+1 859 623 5932",
    "sg:postcode":"40475",
    "sg:province":"KY",
    "wof:name":"Mikes' Warehouse Liquors",
    "wof:placetype":"venue"
},
  "geometry": {"coordinates":[-84.285213,37.739679],"type":"Point"}
}