{
  "type": "Feature",
  "properties": {
    "iso:country":"US",
    "sg:address":"6527 State Hwy 581",
    "sg:city":"River",
    "sg:classifiers":[
        {
            "category":"Government",
            "subcategory":"Fire Station",
            "type":"Public Place"
        }
    ],
    "sg:phone":"+1 606 789 7942",
    "sg:postcode":"41254",
    "sg:province":"KY",
    "sg:tags":[
        "department"
    ],
    "wof:name":"River Volunteer Fire Dept",
    "wof:placetype":"venue"
},
  "geometry": {"coordinates":[-82.72852399999999,37.858436],"type":"Point"}
}