{
  "type": "Feature",
  "properties": {
    "addr:full":"10230 Shelbyville Rd Louisville KY 40223",
    "addr:housenumber":"10230",
    "addr:postcode":"40223",
    "addr:street":"Shelbyville Rd",
    "iso:country":"US",
    "sg:address":"10230 Shelbyville Rd",
    "sg:city":"Louisville",
    "sg:classifiers":[
        {
            "category":"Professional",
            "subcategory":"Accounting & Tax Preparation",
            "type":"Services"
        }
    ],
    "sg:phone":"+1 502 254 9400",
    "sg:postcode":"40223",
    "sg:province":"KY",
    "sg:tags":[
        "accountant"
    ],
    "wof:name":"Wilcox & Co",
    "wof:placetype":"venue"
},
  "geometry": {"coordinates":[-85.56476600000001,38.245407],"type":"Point"}
}