{
  "type": "Feature",
  "properties": {
    "addr:full":"401 N 12th St Murray KY 42071",
    "addr:housenumber":"401",
    "addr:postcode":"42071",
    "addr:street":"N 12Th St",
    "iso:country":"US",
    "sg:address":"401 N 12th St",
    "sg:city":"Murray",
    "sg:classifiers":[
        {
            "category":"Organizations",
            "subcategory":"Religious Organization",
            "type":"Services"
        }
    ],
    "sg:phone":"+1 270 753 3876",
    "sg:postcode":"42071",
    "sg:province":"KY",
    "sg:tags":[
        "church"
    ],
    "wof:name":"St Leo Church",
    "wof:placetype":"venue"
},
  "geometry": {"coordinates":[-88.315084,36.617045],"type":"Point"}
}