{
  "type": "Feature",
  "properties": {
    "iso:country":"US",
    "sg:address":"385 Woodburn Allen Springs Rd",
    "sg:city":"Woodburn",
    "sg:classifiers":[
        {
            "category":"Wholesale",
            "subcategory":"Computers",
            "type":"Manufacturing & Wholesale Goods"
        }
    ],
    "sg:phone":"+1 270 529 0090",
    "sg:postcode":"42170",
    "sg:province":"KY",
    "sg:tags":[
        "communications",
        "datum"
    ],
    "wof:name":"Aztec Computer Systems Inc",
    "wof:placetype":"venue"
},
  "geometry": {"coordinates":[-86.533642,36.844634],"type":"Point"}
}