{
  "type": "Feature",
  "properties": {
    "iso:country":"US",
    "sg:address":"1144 Alton Rd",
    "sg:city":"Lawrenceburg",
    "sg:classifiers":[
        {
            "category":"Autos & Motor Vehicles",
            "subcategory":"Auto Supplies",
            "type":"Retail Goods"
        }
    ],
    "sg:phone":"+1 502 839 4190",
    "sg:postcode":"40342",
    "sg:province":"KY",
    "sg:tags":[
        "tire"
    ],
    "wof:name":"Robinson's Tire & Svc Ctr",
    "wof:placetype":"venue"
},
  "geometry": {"coordinates":[-84.923457,38.072187],"type":"Point"}
}