{
  "type": "Feature",
  "properties": {
    "addr:full":"703 Toms Creek Ivel KY 41642",
    "addr:housenumber":"703",
    "addr:postcode":"41642",
    "addr:street":"Toms Creek",
    "iso:country":"US",
    "sg:address":"703 Toms Creek",
    "sg:city":"Ivel",
    "sg:classifiers":[
        {
            "category":"Professional",
            "type":"Services"
        }
    ],
    "sg:phone":"+1 606 478 5722",
    "sg:postcode":"41642",
    "sg:province":"KY",
    "wof:name":"Rayconn Services Inc",
    "wof:placetype":"venue"
},
  "geometry": {"coordinates":[-82.63868600000001,37.584773],"type":"Point"}
}