{
  "type": "Feature",
  "properties": {
    "iso:country":"US",
    "sg:address":"1440 Lower Colesburg Rd",
    "sg:city":"Elizabethtown",
    "sg:classifiers":[
        {
            "category":"Building & Trades",
            "subcategory":"Construction",
            "type":"Services"
        }
    ],
    "sg:phone":"+1 270 737 4983",
    "sg:postcode":"42701",
    "sg:province":"KY",
    "sg:tags":[
        "painter"
    ],
    "wof:name":"Goodman Enterprises & Tank",
    "wof:placetype":"venue"
},
  "geometry": {"coordinates":[-85.733126,37.769764],"type":"Point"}
}