{
  "type": "Feature",
  "properties": {
    "iso:country":"US",
    "sg:address":"1013 Greenup St",
    "sg:city":"Covington",
    "sg:classifiers":[
        {
            "category":"Food & Beverages",
            "subcategory":"Groceries & Convenience Stores",
            "type":"Retail Goods"
        }
    ],
    "sg:phone":"+1 859 491 4567",
    "sg:postcode":"41011",
    "sg:province":"KY",
    "sg:tags":[
        "grocer"
    ],
    "wof:name":"Greenup Market",
    "wof:placetype":"venue"
},
  "geometry": {"coordinates":[-84.506174,39.08089],"type":"Point"}
}