{
  "type": "Feature",
  "properties": {
    "iso:country":"US",
    "sg:address":"1198 Betty Dr",
    "sg:city":"Paris",
    "sg:classifiers":[
        {
            "category":"Building & Trades",
            "subcategory":"Plumbing",
            "type":"Services"
        }
    ],
    "sg:phone":"+1 859 987 3800",
    "sg:postcode":"40361",
    "sg:province":"KY",
    "sg:tags":[
        "septic"
    ],
    "wof:name":"Stanley Sanitation Svc",
    "wof:placetype":"venue"
},
  "geometry": {"coordinates":[-84.249726,38.235712],"type":"Point"}
}