{
  "type": "Feature",
  "properties": {
    "iso:country":"US",
    "sg:address":"591 Commerce St",
    "sg:city":"Bowling Green",
    "sg:classifiers":[
        {
            "category":"Home & Garden",
            "subcategory":"Building Materials",
            "type":"Retail Goods"
        }
    ],
    "sg:phone":"+1 270 842 2861",
    "sg:postcode":"42101",
    "sg:province":"KY",
    "sg:tags":[
        "mixed",
        "concrete"
    ],
    "wof:name":"Bowling Green Concrete LLC",
    "wof:placetype":"venue"
},
  "geometry": {"coordinates":[-86.38812299999999,37.018497],"type":"Point"}
}