{
  "type": "Feature",
  "properties": {
    "iso:country":"US",
    "sg:address":"1001 S Jefferson St",
    "sg:city":"Princeton",
    "sg:classifiers":[
        {
            "category":"Organizations",
            "subcategory":"Community Association",
            "type":"Services"
        }
    ],
    "sg:phone":"+1 270 365 6110",
    "sg:postcode":"42445",
    "sg:province":"KY",
    "sg:tags":[
        "club"
    ],
    "wof:name":"Princeton Golf & Country Club",
    "wof:placetype":"venue"
},
  "geometry": {"coordinates":[-87.90048899999999,37.083597],"type":"Point"}
}