{
  "type": "Feature",
  "properties": {
    "addr:full":"6515 New Shepherdsville Rd Coxs Creek KY 40013",
    "addr:housenumber":"6515",
    "addr:postcode":"40013",
    "addr:street":"New Shepherdsville Rd",
    "iso:country":"US",
    "sg:address":"6515 New Shepherdsville Rd",
    "sg:city":"Coxs Creek",
    "sg:classifiers":[
        {
            "category":"Food & Beverages",
            "subcategory":"Groceries & Convenience Stores",
            "type":"Retail Goods"
        }
    ],
    "sg:phone":"+1 502 348 8753",
    "sg:postcode":"40013",
    "sg:province":"KY",
    "sg:tags":[
        "grocer"
    ],
    "wof:name":"Rooster Run General Store",
    "wof:placetype":"venue"
},
  "geometry": {"coordinates":[-85.545851,37.883444],"type":"Point"}
}