{
  "type": "Feature",
  "properties": {
    "iso:country":"US",
    "sg:address":"1001 Joe Clifton Dr",
    "sg:city":"Paducah",
    "sg:classifiers":[
        {
            "category":"Restaurant",
            "type":"Food & Drink"
        }
    ],
    "sg:menulink":"http://www.allmenus.com/ky/paducah/66338-pizza-inn/menu/",
    "sg:phone":"+1 270 442 7105",
    "sg:postcode":"42001",
    "sg:province":"KY",
    "sg:tags":[
        "american",
        "pizza"
    ],
    "wof:name":"Pizza Inn",
    "wof:placetype":"venue"
},
  "geometry": {"coordinates":[-88.636983,37.082706],"type":"Point"}
}