{
  "type": "Feature",
  "properties": {
    "iso:country":"US",
    "sg:address":"315 W Maple St",
    "sg:city":"Salyersville",
    "sg:classifiers":[
        {
            "category":"Government",
            "subcategory":"Office",
            "type":"Public Place"
        }
    ],
    "sg:phone":"+1 606 349 3933",
    "sg:postcode":"41465",
    "sg:province":"KY",
    "sg:tags":[
        "county",
        "safety",
        "order"
    ],
    "wof:name":"Magoffin County Disaster Svc",
    "wof:placetype":"venue"
},
  "geometry": {"coordinates":[-83.074108,37.752225],"type":"Point"}
}