{
  "type": "Feature",
  "properties": {
    "iso:country":"US",
    "sg:address":"4216 Lynnbrook Dr",
    "sg:city":"Louisville",
    "sg:classifiers":[
        {
            "category":"Professional",
            "subcategory":"Advertising",
            "type":"Services"
        }
    ],
    "sg:phone":"+1 502 459 2034",
    "sg:postcode":"40220",
    "sg:province":"KY",
    "sg:tags":[
        "agency"
    ],
    "wof:name":"Mid South Sales Inc",
    "wof:placetype":"venue"
},
  "geometry": {"coordinates":[-85.628568,38.230478],"type":"Point"}
}