{
  "type": "Feature",
  "properties": {
    "addr:full":"13003 Rehl Rd Jeffersontown KY 40299",
    "addr:housenumber":"13003",
    "addr:postcode":"40299",
    "addr:street":"Rehl Rd",
    "iso:country":"US",
    "sg:address":"13003 Rehl Rd",
    "sg:city":"Jeffersontown",
    "sg:classifiers":[
        {
            "category":"Building & Trades",
            "subcategory":"Landscaping Services",
            "type":"Services"
        }
    ],
    "sg:phone":"+1 502 267 8724",
    "sg:postcode":"40299",
    "sg:province":"KY",
    "sg:tags":[
        "landscape",
        "contractor"
    ],
    "wof:name":"Paradise Lawnscape Inc",
    "wof:placetype":"venue"
},
  "geometry": {"coordinates":[-85.520055,38.203116],"type":"Point"}
}