{
  "type": "Feature",
  "properties": {
    "iso:country":"US",
    "sg:address":"7619 Dixie Hwy",
    "sg:city":"Pleasure Rdg Pk",
    "sg:classifiers":[
        {
            "category":"Insurance",
            "subcategory":"Insurance Agent",
            "type":"Services"
        }
    ],
    "sg:phone":"+1 502 937 5256",
    "sg:postcode":"40258",
    "sg:province":"KY",
    "wof:name":"Rudy Scheynost Insurance Inc",
    "wof:placetype":"venue"
},
  "geometry": {"coordinates":[-85.840649,38.141315],"type":"Point"}
}