{
  "type": "Feature",
  "properties": {
    "iso:country":"US",
    "sg:address":"712 Plum Springs Loop",
    "sg:city":"Bowling Green",
    "sg:classifiers":[
        {
            "category":"Organizations",
            "subcategory":"Labor Organization",
            "type":"Services"
        }
    ],
    "sg:phone":"+1 270 782 2164",
    "sg:postcode":"42101",
    "sg:province":"KY",
    "wof:name":"UAW",
    "wof:placetype":"venue"
},
  "geometry": {"coordinates":[-86.380684,37.014612],"type":"Point"}
}