{
  "type": "Feature",
  "properties": {
    "iso:country":"US",
    "sg:address":"12474 la Grange Rd",
    "sg:city":"Louisville",
    "sg:classifiers":[
        {
            "category":"Personal",
            "subcategory":"Beauty Salon",
            "type":"Services"
        }
    ],
    "sg:phone":"+1 502 243 6911",
    "sg:postcode":"40245",
    "sg:province":"KY",
    "wof:name":"Supercuts",
    "wof:placetype":"venue"
},
  "geometry": {"coordinates":[-85.475021,38.258384],"type":"Point"}
}