{
  "type": "Feature",
  "properties": {
    "iso:country":"US",
    "sg:address":"1011 W Main St",
    "sg:city":"Louisville",
    "sg:classifiers":[
        {
            "category":"Government",
            "subcategory":"Office",
            "type":"Public Place"
        }
    ],
    "sg:phone":"+1 502 560 1500",
    "sg:postcode":"40202",
    "sg:province":"KY",
    "sg:tags":[
        "state",
        "taxation"
    ],
    "wof:name":"Lottery Corp",
    "wof:placetype":"venue"
},
  "geometry": {"coordinates":[-85.766858,38.257813],"type":"Point"}
}