{
  "type": "Feature",
  "properties": {
    "iso:country":"US",
    "sg:address":"614 Amherst Dr",
    "sg:city":"Owensboro",
    "sg:classifiers":[
        {
            "category":"Shopping",
            "subcategory":"Gifts & Souvenirs",
            "type":"Retail Goods"
        }
    ],
    "sg:phone":"+1 270 926 3160",
    "sg:postcode":"42303",
    "sg:province":"KY",
    "sg:tags":[
        "shop"
    ],
    "wof:name":"Clock Man's Gift Shop",
    "wof:placetype":"venue"
},
  "geometry": {"coordinates":[-87.119471,37.732823],"type":"Point"}
}