{
  "type": "Feature",
  "properties": {
    "addr:full":"3130 Pimlico Pkwy Lexington KY 40517",
    "addr:housenumber":"3130",
    "addr:postcode":"40517",
    "addr:street":"Pimlico Pkwy",
    "iso:country":"US",
    "sg:address":"3130 Pimlico Pkwy",
    "sg:city":"Lexington",
    "sg:classifiers":[
        {
            "category":"Restaurant",
            "type":"Food & Drink"
        }
    ],
    "sg:phone":"+1 859 273 8885",
    "sg:postcode":"40517",
    "sg:province":"KY",
    "sg:website":"www.spudsgrill.com",
    "wof:name":"Spuds Grill & Tavern",
    "wof:placetype":"venue"
},
  "geometry": {"coordinates":[-84.46007,37.985808],"type":"Point"}
}