{
  "type": "Feature",
  "properties": {
    "iso:country":"US",
    "sg:address":"3701 Chamberlain Ln",
    "sg:city":"Louisville",
    "sg:classifiers":[
        {
            "category":"Health Services",
            "subcategory":"Doctor",
            "type":"Services"
        },
        {
            "category":"Health Services",
            "subcategory":"Clinic",
            "type":"Services"
        },
        {
            "category":"Health Services",
            "subcategory":"Hospital",
            "type":"Services"
        }
    ],
    "sg:phone":"+1 502 327 1144",
    "sg:postcode":"40241",
    "sg:province":"KY",
    "sg:tags":[
        "physician",
        "dialysis",
        "medical",
        "surgeons",
        "nephrology",
        "kidneys"
    ],
    "wof:name":"Fresenius Medical Care",
    "wof:placetype":"venue"
},
  "geometry": {"coordinates":[-85.54467,38.301159],"type":"Point"}
}