{
  "type": "Feature",
  "properties": {
    "iso:country":"US",
    "sg:address":"4500 S Hurstbourne Pkwy",
    "sg:city":"Louisville",
    "sg:classifiers":[
        {
            "category":"Personal",
            "type":"Services"
        },
        {
            "category":"Retail",
            "subcategory":"Portrait Studio",
            "type":"Services"
        },
        {
            "category":"Professional",
            "subcategory":"Art Services",
            "type":"Services"
        }
    ],
    "sg:phone":"+1 502 491 1312",
    "sg:postcode":"40299",
    "sg:province":"KY",
    "sg:tags":[
        "photographers-portrait",
        "videography",
        "darkroom",
        "rental",
        "photography",
        "wedding",
        "photographic"
    ],
    "sg:website":"http://www.olanmills.com",
    "wof:name":"Olan Mills",
    "wof:placetype":"venue"
},
  "geometry": {"coordinates":[-85.605423,38.18795],"type":"Point"}
}