{
  "type": "Feature",
  "properties": {
    "addr:full":"100 Woodsway Dr Elizabethtown KY 42701",
    "addr:housenumber":"100",
    "addr:postcode":"42701",
    "addr:street":"Woodsway Dr",
    "iso:country":"US",
    "sg:address":"100 Woodsway Dr",
    "sg:city":"Elizabethtown",
    "sg:classifiers":[
        {
            "category":"Professional",
            "subcategory":"Employment Agencies",
            "type":"Services"
        }
    ],
    "sg:phone":"+1 270 268 0655",
    "sg:postcode":"42701",
    "sg:province":"KY",
    "sg:tags":[
        "medical"
    ],
    "wof:name":"Scott J Hopkins",
    "wof:placetype":"venue"
},
  "geometry": {"coordinates":[-85.854094,37.770372],"type":"Point"}
}