{
  "type": "Feature",
  "properties": {
    "iso:country":"US",
    "sg:address":"3429 Buckhorn Dr Ste 2",
    "sg:city":"Lexington",
    "sg:classifiers":[
        {
            "category":"Bars & Pubs",
            "type":"Food & Drink"
        }
    ],
    "sg:phone":"+1 859 272 7672",
    "sg:postcode":"40515",
    "sg:province":"KY",
    "sg:tags":[
        "tavern"
    ],
    "wof:name":"Squires Tavern",
    "wof:placetype":"venue"
},
  "geometry": {"coordinates":[-84.456942,37.976201],"type":"Point"}
}