{
  "type": "Feature",
  "properties": {
    "iso:country":"US",
    "sg:address":"512 Wilson St",
    "sg:city":"Falmouth",
    "sg:classifiers":[
        {
            "category":"Professional",
            "subcategory":"Lawyer & Legal Services",
            "type":"Services"
        }
    ],
    "sg:phone":"+1 859 654 1500",
    "sg:postcode":"41040",
    "sg:province":"KY",
    "sg:tags":[
        "attorney"
    ],
    "wof:name":"Gwen A Pollard",
    "wof:placetype":"venue"
},
  "geometry": {"coordinates":[-84.342626,38.677541],"type":"Point"}
}