{
  "type": "Feature",
  "properties": {
    "addr:full":"32 Kenton Lands Rd Erlanger KY 41018",
    "addr:housenumber":"32",
    "addr:postcode":"41018",
    "addr:street":"Kenton Lands Rd",
    "iso:country":"US",
    "sg:address":"32 Kenton Lands Rd",
    "sg:city":"Erlanger",
    "sg:classifiers":[
        {
            "category":"Building & Trades",
            "subcategory":"Equipment Rental",
            "type":"Services"
        }
    ],
    "sg:phone":"+1 859 342 8100",
    "sg:postcode":"41018",
    "sg:province":"KY",
    "sg:tags":[
        "yard"
    ],
    "sg:website":"www.snappytents.com",
    "wof:name":"Snappy Tent & Party Rentals",
    "wof:placetype":"venue"
},
  "geometry": {"coordinates":[-84.590059,39.022881],"type":"Point"}
}