{
  "type": "Feature",
  "properties": {
    "iso:country":"US",
    "sg:address":"2301 S 7th St",
    "sg:city":"Ironton",
    "sg:classifiers":[
        {
            "category":"Health Services",
            "subcategory":"Doctor",
            "type":"Services"
        }
    ],
    "sg:phone":"+1 740 532 4613",
    "sg:postcode":"45638",
    "sg:province":"OH",
    "sg:tags":[
        "dentist"
    ],
    "wof:name":"Jerry A Mayer DDS",
    "wof:placetype":"venue"
},
  "geometry": {"coordinates":[-82.666028,38.518795],"type":"Point"}
}