{
  "type": "Feature",
  "properties": {
    "iso:country":"US",
    "sg:address":"321 S College St",
    "sg:city":"Harrodsburg",
    "sg:classifiers":[
        {
            "category":"Autos & Motor Vehicles",
            "subcategory":"Automobile Sales",
            "type":"Retail Goods"
        }
    ],
    "sg:phone":"+1 859 734 8388",
    "sg:postcode":"40330",
    "sg:province":"KY",
    "sg:tags":[
        "car",
        "used",
        "dealer"
    ],
    "wof:name":"Don Alford's Cruisin Classics",
    "wof:placetype":"venue"
},
  "geometry": {"coordinates":[-84.845963,37.758254],"type":"Point"}
}