{
  "type": "Feature",
  "properties": {
    "addr:full":"1121 Winchester Rd Lexington KY 40505",
    "addr:housenumber":"1121",
    "addr:postcode":"40505",
    "addr:street":"Winchester Rd",
    "iso:country":"US",
    "sg:address":"1121 Winchester Rd",
    "sg:city":"Lexington",
    "sg:classifiers":[
        {
            "category":"Autos & Motor Vehicles",
            "subcategory":"Auto Supplies",
            "type":"Retail Goods"
        },
        {
            "category":"Wholesale",
            "subcategory":"Electrical",
            "type":"Manufacturing & Wholesale Goods"
        },
        {
            "category":"Wholesale",
            "subcategory":"Auto Parts",
            "type":"Manufacturing & Wholesale Goods"
        }
    ],
    "sg:phone":"+1 859 389 9490",
    "sg:postcode":"40505",
    "sg:province":"KY",
    "sg:tags":[
        "body",
        "battery",
        "automobile",
        "accessory",
        "equipment",
        "truck"
    ],
    "sg:website":"http://www.oreillyauto.com?utm_source=yellowpages&utm_medium=iyp&utm_campaign=1138",
    "wof:name":"O'Reilly Auto Parts",
    "wof:placetype":"venue"
},
  "geometry": {"coordinates":[-84.463975,38.042279],"type":"Point"}
}