{
  "type": "Feature",
  "properties": {
    "iso:country":"US",
    "sg:address":"2004 Hikes Ln",
    "sg:city":"Louisville",
    "sg:classifiers":[
        {
            "category":"Shopping",
            "subcategory":"Pets & Pet Supplies",
            "type":"Retail Goods"
        }
    ],
    "sg:phone":"+1 502 419 4853",
    "sg:postcode":"40218",
    "sg:province":"KY",
    "sg:tags":[
        "furnishing",
        "dog",
        "store",
        "cat"
    ],
    "wof:name":"Just Fish",
    "wof:placetype":"venue"
},
  "geometry": {"coordinates":[-85.66327200000001,38.196918],"type":"Point"}
}