{
  "type": "Feature",
  "properties": {
    "iso:country":"US",
    "sg:address":"409 E W Miller St",
    "sg:city":"Hazel",
    "sg:phone":"+1 270 492 8156",
    "sg:postcode":"42049",
    "sg:province":"KY",
    "sg:tags":[
        "farm",
        "tobacco"
    ],
    "wof:name":"Craig Fox",
    "wof:placetype":"venue"
},
  "geometry": {"coordinates":[-88.327224,36.507535],"type":"Point"}
}