{
  "type": "Feature",
  "properties": {
    "addr:full":"12920 Fenwick Center Dr B Louisville KY 40223",
    "addr:housenumber":"12920",
    "addr:postcode":"40223",
    "addr:street":"Fenwick Center Dr B",
    "iso:country":"US",
    "sg:address":"12920 Fenwick Center Dr B",
    "sg:city":"Louisville",
    "sg:classifiers":[
        {
            "category":"Shopping",
            "subcategory":"Gifts & Souvenirs",
            "type":"Retail Goods"
        },
        {
            "category":"Manufacturing",
            "subcategory":"Retail Goods",
            "type":"Manufacturing & Wholesale Goods"
        }
    ],
    "sg:phone":"+1 502 244 6299",
    "sg:postcode":"40223",
    "sg:province":"KY",
    "sg:tags":[
        "shop",
        "giftware's-wholesale",
        "manufacturer"
    ],
    "wof:name":"J & S Distributors",
    "wof:placetype":"venue"
},
  "geometry": {"coordinates":[-85.513701,38.251251],"type":"Point"}
}