{
  "type": "Feature",
  "properties": {
    "addr:full":"152 Cates Byp Russellville KY 42276",
    "addr:housenumber":"152",
    "addr:postcode":"42276",
    "addr:street":"Cates Byp",
    "iso:country":"US",
    "sg:address":"152 Cates Byp",
    "sg:city":"Russellville",
    "sg:classifiers":[
        {
            "category":"Freight",
            "type":"Transportation"
        }
    ],
    "sg:phone":"+1 270 726 7729",
    "sg:postcode":"42276",
    "sg:province":"KY",
    "sg:tags":[
        "commercial",
        "storage"
    ],
    "wof:name":"Russellville Self-Storage",
    "wof:placetype":"venue"
},
  "geometry": {"coordinates":[-86.904669,36.868775],"type":"Point"}
}