{
  "type": "Feature",
  "properties": {
    "iso:country":"US",
    "sg:address":"399 French Valley Rd",
    "sg:city":"Russell Springs",
    "sg:classifiers":[
        {
            "category":"Real Estate",
            "subcategory":"Real Estate Operator",
            "type":"Services"
        }
    ],
    "sg:phone":"+1 270 866 3976",
    "sg:postcode":"42642",
    "sg:province":"KY",
    "sg:tags":[
        "property",
        "lessor"
    ],
    "wof:name":"Lester Bernard",
    "wof:placetype":"venue"
},
  "geometry": {"coordinates":[-85.086324,37.031928],"type":"Point"}
}