{
  "type": "Feature",
  "properties": {
    "iso:country":"US",
    "sg:address":"201 E 5th St",
    "sg:city":"Millersburg",
    "sg:classifiers":[
        {
            "category":"Wholesale",
            "subcategory":"Chemicals & Plastics",
            "type":"Manufacturing & Wholesale Goods"
        }
    ],
    "sg:phone":"+1 859 484 3340",
    "sg:postcode":"40311",
    "sg:province":"KY",
    "wof:name":"Millersburg Fertilizer Co",
    "wof:placetype":"venue"
},
  "geometry": {"coordinates":[-84.148257,38.299934],"type":"Point"}
}