{
  "type": "Feature",
  "properties": {
    "iso:country":"US",
    "sg:address":"1500 N Main St",
    "sg:city":"Monticello",
    "sg:classifiers":[
        {
            "category":"Banks & Credit Unions",
            "subcategory":"Bank",
            "type":"Services"
        }
    ],
    "sg:phone":"+1 606 348 0300",
    "sg:postcode":"42633",
    "sg:province":"KY",
    "sg:tags":[
        "loan"
    ],
    "wof:name":"Lendmark Financial Svc",
    "wof:placetype":"venue"
},
  "geometry": {"coordinates":[-84.836761,36.847913],"type":"Point"}
}