{
  "type": "Feature",
  "properties": {
    "addr:full":"112 E 30th St Covington KY 41015",
    "addr:housenumber":"112",
    "addr:postcode":"41015",
    "addr:street":"E 30Th St",
    "iso:country":"US",
    "sg:address":"112 E 30th St",
    "sg:city":"Covington",
    "sg:classifiers":[
        {
            "category":"Restaurant",
            "type":"Food & Drink"
        }
    ],
    "sg:phone":"+1 859 291 8017",
    "sg:postcode":"41015",
    "sg:province":"KY",
    "wof:name":"Breakfast At Ashley's",
    "wof:placetype":"venue"
},
  "geometry": {"coordinates":[-84.501132,39.054827],"type":"Point"}
}