{
  "type": "Feature",
  "properties": {
    "iso:country":"US",
    "sg:address":"958 Commercial Dr",
    "sg:city":"Richmond",
    "sg:classifiers":[
        {
            "category":"Personal",
            "subcategory":"Barber",
            "type":"Services"
        }
    ],
    "sg:phone":"+1 859 626 7661",
    "sg:postcode":"40475",
    "sg:province":"KY",
    "wof:name":"Dixons Barber Shop",
    "wof:placetype":"venue"
},
  "geometry": {"coordinates":[-84.26925199999999,37.737131],"type":"Point"}
}