{
  "type": "Feature",
  "properties": {
    "addr:full":"458 N Main St Madisonville KY 42431",
    "addr:housenumber":"458",
    "addr:postcode":"42431",
    "addr:street":"N Main St",
    "iso:country":"US",
    "sg:address":"458 N Main St",
    "sg:city":"Madisonville",
    "sg:classifiers":[
        {
            "category":"Real Estate",
            "subcategory":"Real Estate Agent",
            "type":"Services"
        }
    ],
    "sg:phone":"+1 270 821 2426",
    "sg:postcode":"42431",
    "sg:province":"KY",
    "sg:website":"www.ruddrealestate.com",
    "wof:name":"Rudd Real Estate & Assoc Inc",
    "wof:placetype":"venue"
},
  "geometry": {"coordinates":[-87.497685,37.334725],"type":"Point"}
}