{
  "type": "Feature",
  "properties": {
    "iso:country":"US",
    "sg:address":"890 Fairview Ave",
    "sg:city":"Bowling Green",
    "sg:classifiers":[
        {
            "category":"Building & Trades",
            "subcategory":"Plumbing",
            "type":"Services"
        }
    ],
    "sg:phone":"+1 270 843 1981",
    "sg:postcode":"42101",
    "sg:province":"KY",
    "sg:tags":[
        "plumbing",
        "contractor"
    ],
    "wof:name":"Millard Martin Svc",
    "wof:placetype":"venue"
},
  "geometry": {"coordinates":[-86.42964000000001,36.990804],"type":"Point"}
}