{
  "type": "Feature",
  "properties": {
    "addr:full":"22 Fountain Cir Richmond KY 40475",
    "addr:housenumber":"22",
    "addr:postcode":"40475",
    "addr:street":"Fountain Cir",
    "iso:country":"US",
    "sg:address":"22 Fountain Cir",
    "sg:city":"Richmond",
    "sg:classifiers":[
        {
            "category":"Freight",
            "type":"Transportation"
        }
    ],
    "sg:phone":"+1 859 624 0398",
    "sg:postcode":"40475",
    "sg:province":"KY",
    "sg:tags":[
        "operator",
        "local",
        "trucking"
    ],
    "wof:name":"Home Meals Delivery Inc",
    "wof:placetype":"venue"
},
  "geometry": {"coordinates":[-84.333423,37.778629],"type":"Point"}
}