{
  "type": "Feature",
  "properties": {
    "iso:country":"US",
    "sg:address":"644 Beaumont Ave",
    "sg:city":"Harrodsburg",
    "sg:classifiers":[
        {
            "category":"Personal",
            "subcategory":"Beauty Salon",
            "type":"Services"
        }
    ],
    "sg:phone":"+1 859 734 7833",
    "sg:postcode":"40330",
    "sg:province":"KY",
    "wof:name":"Hair Capers",
    "wof:placetype":"venue"
},
  "geometry": {"coordinates":[-84.837733,37.750612],"type":"Point"}
}