{
  "type": "Feature",
  "properties": {
    "addr:full":"1701 US Hwy 60 Grayson KY 41143",
    "addr:housenumber":"1701",
    "addr:postcode":"41143",
    "addr:street":"Us Hwy 60",
    "iso:country":"US",
    "sg:address":"1701 US Hwy 60",
    "sg:city":"Grayson",
    "sg:classifiers":[
        {
            "category":"Professional",
            "type":"Services"
        }
    ],
    "sg:phone":"+1 606 475 1555",
    "sg:postcode":"41143",
    "sg:province":"KY",
    "sg:tags":[
        "establishment"
    ],
    "wof:name":"LA Costenita",
    "wof:placetype":"venue"
},
  "geometry": {"coordinates":[-82.90317400000001,38.330954],"type":"Point"}
}