{
  "type": "Feature",
  "properties": {
    "addr:full":"217 Martin Trl Stanford KY 40484",
    "addr:housenumber":"217",
    "addr:postcode":"40484",
    "addr:street":"Martin Trl",
    "iso:country":"US",
    "sg:address":"217 Martin Trl",
    "sg:city":"Stanford",
    "sg:classifiers":[
        {
            "category":"Home & Garden",
            "subcategory":"Furniture",
            "type":"Retail Goods"
        }
    ],
    "sg:phone":"+1 606 365 1283",
    "sg:postcode":"40484",
    "sg:province":"KY",
    "sg:tags":[
        "cabinet"
    ],
    "wof:name":"Ellen Mc Clure",
    "wof:placetype":"venue"
},
  "geometry": {"coordinates":[-84.714112,37.470858],"type":"Point"}
}