{
  "type": "Feature",
  "properties": {
    "iso:country":"US",
    "sg:address":"213 E Western Ave",
    "sg:city":"Sonora",
    "sg:classifiers":[
        {
            "category":"Home & Garden",
            "subcategory":"Household Appliances",
            "type":"Retail Goods"
        }
    ],
    "sg:phone":"+1 270 369 7661",
    "sg:postcode":"42776",
    "sg:province":"KY",
    "wof:name":"Stewarts Appliances",
    "wof:placetype":"venue"
},
  "geometry": {"coordinates":[-85.88922599999999,37.523123],"type":"Point"}
}