{
  "type": "Feature",
  "properties": {
    "addr:full":"1315 Peacock Rd Paris KY 40361",
    "addr:housenumber":"1315",
    "addr:postcode":"40361",
    "addr:street":"Peacock Rd",
    "iso:country":"US",
    "sg:address":"1315 Peacock Rd",
    "sg:city":"Paris",
    "sg:classifiers":[
        {
            "category":"Building & Trades",
            "subcategory":"Electrical",
            "type":"Services"
        }
    ],
    "sg:phone":"+1 859 987 2927",
    "sg:postcode":"40361",
    "sg:province":"KY",
    "sg:tags":[
        "electrical",
        "contractor"
    ],
    "wof:name":"Henney Electric Inc",
    "wof:placetype":"venue"
},
  "geometry": {"coordinates":[-84.25309300000001,38.238641],"type":"Point"}
}