{
  "type": "Feature",
  "properties": {
    "iso:country":"US",
    "sg:address":"17519 Middle Delaware Rd",
    "sg:city":"Henderson",
    "sg:classifiers":[
        {
            "category":"Retail",
            "subcategory":"Auto Repair",
            "type":"Services"
        }
    ],
    "sg:phone":"+1 270 316 0285",
    "sg:postcode":"42420",
    "sg:province":"KY",
    "sg:tags":[
        "automotive",
        "wrecker"
    ],
    "wof:name":"Emerson's Towing & Hauling",
    "wof:placetype":"venue"
},
  "geometry": {"coordinates":[-87.442126,37.730162],"type":"Point"}
}