{
  "type": "Feature",
  "properties": {
    "iso:country":"US",
    "sg:address":"2537 Garland Ave",
    "sg:city":"Louisville",
    "sg:classifiers":[
        {
            "category":"Bars & Pubs",
            "type":"Food & Drink"
        }
    ],
    "sg:phone":"+1 502 772 2345",
    "sg:postcode":"40211",
    "sg:province":"KY",
    "wof:name":"26th Street Blues Tavern",
    "wof:placetype":"venue"
},
  "geometry": {"coordinates":[-85.79524600000001,38.244695],"type":"Point"}
}