{
  "type": "Feature",
  "properties": {
    "iso:country":"US",
    "sg:address":"806 S Main St",
    "sg:city":"Hopkinsville",
    "sg:classifiers":[
        {
            "category":"Recreation",
            "type":"Entertainment"
        }
    ],
    "sg:phone":"+1 270 885 4573",
    "sg:postcode":"42240",
    "sg:province":"KY",
    "sg:tags":[
        "parlor",
        "billiard"
    ],
    "wof:name":"Lee's Game Room",
    "wof:placetype":"venue"
},
  "geometry": {"coordinates":[-87.488929,36.865604],"type":"Point"}
}