{
  "type": "Feature",
  "properties": {
    "iso:country":"US",
    "sg:address":"2604 Burlington Pike",
    "sg:city":"Burlington",
    "sg:classifiers":[
        {
            "category":"Health Services",
            "subcategory":"Chiropractor",
            "type":"Services"
        }
    ],
    "sg:phone":"+1 859 689 4373",
    "sg:postcode":"41005",
    "sg:province":"KY",
    "sg:tags":[
        "clinic",
        "chiropractic"
    ],
    "wof:name":"Jeremy Storms DC",
    "wof:placetype":"venue"
},
  "geometry": {"coordinates":[-84.715594,39.026611],"type":"Point"}
}