{
  "type": "Feature",
  "properties": {
    "iso:country":"US",
    "sg:address":"902 Highland Ave",
    "sg:city":"Jackson",
    "sg:classifiers":[
        {
            "category":"Personal",
            "subcategory":"Beauty Salon",
            "type":"Services"
        }
    ],
    "sg:phone":"+1 606 666 7161",
    "sg:postcode":"41339",
    "sg:province":"KY",
    "sg:tags":[
        "shop"
    ],
    "wof:name":"Caricos Wavelengths",
    "wof:placetype":"venue"
},
  "geometry": {"coordinates":[-83.37990000000001,37.553357],"type":"Point"}
}