{
  "type": "Feature",
  "properties": {
    "iso:country":"US",
    "sg:address":"620 Blue Lick Rd",
    "sg:city":"Berea",
    "sg:classifiers":[
        {
            "category":"Professional",
            "subcategory":"Management & Consulting",
            "type":"Services"
        }
    ],
    "sg:phone":"+1 859 985 3858",
    "sg:postcode":"40403",
    "sg:province":"KY",
    "sg:tags":[
        "training",
        "leadership"
    ],
    "wof:name":"Peter Hille",
    "wof:placetype":"venue"
},
  "geometry": {"coordinates":[-84.24285,37.588372],"type":"Point"}
}