{
  "type": "Feature",
  "properties": {
    "iso:country":"US",
    "sg:address":"6282 Zebulon Hwy",
    "sg:city":"Pikeville",
    "sg:classifiers":[
        {
            "category":"Shopping",
            "subcategory":"Bicycles & Sporting Goods",
            "type":"Retail Goods"
        }
    ],
    "sg:phone":"+1 606 631 9143",
    "sg:postcode":"41501",
    "sg:province":"KY",
    "sg:tags":[
        "equipment",
        "archery",
        "supply"
    ],
    "wof:name":"Robinette's Gun & Archery",
    "wof:placetype":"venue"
},
  "geometry": {"coordinates":[-82.457746,37.550164],"type":"Point"}
}