{
  "type": "Feature",
  "properties": {
    "addr:full":"72 Hershell Stacey Rd Hazard KY 41701",
    "addr:housenumber":"72",
    "addr:postcode":"41701",
    "addr:street":"Hershell Stacey Rd",
    "iso:country":"US",
    "sg:address":"72 Hershell Stacey Rd",
    "sg:city":"Hazard",
    "sg:classifiers":[
        {
            "category":"Building & Trades",
            "subcategory":"Construction",
            "type":"Services"
        }
    ],
    "sg:phone":"+1 606 439 3999",
    "sg:postcode":"41701",
    "sg:province":"KY",
    "sg:tags":[
        "downspouts",
        "gutter"
    ],
    "wof:name":"J & J Construction",
    "wof:placetype":"venue"
},
  "geometry": {"coordinates":[-83.16055299999999,37.273105],"type":"Point"}
}