{
  "type": "Feature",
  "properties": {
    "iso:country":"US",
    "sg:address":"808 N 12th St",
    "sg:city":"Murray",
    "sg:classifiers":[
        {
            "category":"Banks & Credit Unions",
            "subcategory":"Bank",
            "type":"Services"
        }
    ],
    "sg:phone":"+1 270 767 2235",
    "sg:postcode":"42071",
    "sg:province":"KY",
    "sg:tags":[
        "state",
        "commercial"
    ],
    "wof:name":"BB&T",
    "wof:placetype":"venue"
},
  "geometry": {"coordinates":[-88.314837,36.62409],"type":"Point"}
}