{
  "type": "Feature",
  "properties": {
    "addr:full":"254 Columbia Ln Shepherdsville KY 40165",
    "addr:housenumber":"254",
    "addr:postcode":"40165",
    "addr:street":"Columbia Ln",
    "iso:country":"US",
    "sg:address":"254 Columbia Ln",
    "sg:city":"Shepherdsville",
    "sg:classifiers":[
        {
            "category":"Building & Trades",
            "subcategory":"Plumbing",
            "type":"Services"
        }
    ],
    "sg:phone":"+1 502 643 8126",
    "sg:postcode":"40165",
    "sg:province":"KY",
    "sg:tags":[
        "conditioning",
        "air",
        "system",
        "contractor"
    ],
    "wof:name":"Savage Mechanical Inc",
    "wof:placetype":"venue"
},
  "geometry": {"coordinates":[-85.628345,38.057705],"type":"Point"}
}