{
  "type": "Feature",
  "properties": {
    "iso:country":"US",
    "sg:address":"101 Canewood Blvd",
    "sg:city":"Georgetown",
    "sg:classifiers":[
        {
            "category":"Banks & Credit Unions",
            "subcategory":"Bank",
            "type":"Services"
        }
    ],
    "sg:phone":"+1 502 863 7276",
    "sg:postcode":"40324",
    "sg:province":"KY",
    "wof:name":"Town & Country Bank & Trust Co",
    "wof:placetype":"venue"
},
  "geometry": {"coordinates":[-84.590558,38.208802],"type":"Point"}
}