{
  "type": "Feature",
  "properties": {
    "iso:country":"US",
    "sg:address":"1345 N Broadway Rd",
    "sg:city":"Lexington",
    "sg:classifiers":[
        {
            "category":"Social Services",
            "subcategory":"Child Care",
            "type":"Services"
        }
    ],
    "sg:phone":"+1 859 254 5439",
    "sg:postcode":"40505",
    "sg:province":"KY",
    "sg:tags":[
        "center"
    ],
    "wof:name":"Kidz Konnection",
    "wof:placetype":"venue"
},
  "geometry": {"coordinates":[-84.478689,38.063698],"type":"Point"}
}