{
  "type": "Feature",
  "properties": {
    "addr:full":"6835 Preston Hwy Lebanon Junction KY 40150",
    "addr:housenumber":"6835",
    "addr:postcode":"40150",
    "addr:street":"Preston Hwy",
    "iso:country":"US",
    "sg:address":"6835 Preston Hwy",
    "sg:city":"Lebanon Junction",
    "sg:classifiers":[
        {
            "category":"Food & Beverages",
            "subcategory":"Groceries & Convenience Stores",
            "type":"Retail Goods"
        }
    ],
    "sg:phone":"+1 502 543 3896",
    "sg:postcode":"40150",
    "sg:province":"KY",
    "sg:tags":[
        "grocer"
    ],
    "wof:name":"Mini Mart",
    "wof:placetype":"venue"
},
  "geometry": {"coordinates":[-85.69834400000001,37.922212],"type":"Point"}
}