{
  "type": "Feature",
  "properties": {
    "iso:country":"US",
    "sg:address":"150 W Main St",
    "sg:city":"Georgetown",
    "sg:classifiers":[
        {
            "category":"Professional",
            "subcategory":"Art Services",
            "type":"Services"
        }
    ],
    "sg:phone":"+1 502 867 7447",
    "sg:postcode":"40324",
    "sg:province":"KY",
    "sg:tags":[
        "graphic",
        "designer"
    ],
    "wof:name":"Original Signs & Graphics",
    "wof:placetype":"venue"
},
  "geometry": {"coordinates":[-84.561364,38.209946],"type":"Point"}
}