{
  "type": "Feature",
  "properties": {
    "addr:full":"500 Scott Ave Paris KY 40361",
    "addr:housenumber":"500",
    "addr:postcode":"40361",
    "addr:street":"Scott Ave",
    "iso:country":"US",
    "sg:address":"500 Scott Ave",
    "sg:city":"Paris",
    "sg:classifiers":[
        {
            "category":"Building & Trades",
            "subcategory":"Construction",
            "type":"Services"
        }
    ],
    "sg:phone":"+1 859 987 5756",
    "sg:postcode":"40361",
    "sg:province":"KY",
    "sg:tags":[
        "hanging",
        "contractor"
    ],
    "wof:name":"Cartmill Painting",
    "wof:placetype":"venue"
},
  "geometry": {"coordinates":[-84.24109199999999,38.206325],"type":"Point"}
}