{
  "type": "Feature",
  "properties": {
    "addr:full":"8131 Bardstown Rd Louisville KY 40291",
    "addr:housenumber":"8131",
    "addr:postcode":"40291",
    "addr:street":"Bardstown Rd",
    "iso:country":"US",
    "sg:address":"8131 Bardstown Rd",
    "sg:city":"Louisville",
    "sg:classifiers":[
        {
            "category":"Restaurant",
            "type":"Food & Drink"
        }
    ],
    "sg:menulink":"http://www.allmenus.com/ky/jefferson-southeast/79663-pizza-hut/menu/",
    "sg:phone":"+1 502 231 1200",
    "sg:postcode":"40291",
    "sg:province":"KY",
    "sg:tags":[
        "american",
        "pizza"
    ],
    "wof:name":"Pizza Hut",
    "wof:placetype":"venue"
},
  "geometry": {"coordinates":[-85.575839,38.1282],"type":"Point"}
}