{
  "type": "Feature",
  "properties": {
    "iso:country":"US",
    "sg:address":"120 N Main St",
    "sg:city":"Nicholasville",
    "sg:classifiers":[
        {
            "category":"Personal",
            "subcategory":"Beauty Salon",
            "type":"Services"
        }
    ],
    "sg:phone":"+1 859 885 7265",
    "sg:postcode":"40356",
    "sg:province":"KY",
    "wof:name":"Bastin Hair Co",
    "wof:placetype":"venue"
},
  "geometry": {"coordinates":[-84.57266300000001,37.881045],"type":"Point"}
}