{
  "type": "Feature",
  "properties": {
    "iso:country":"US",
    "sg:address":"1101 Armory Dr",
    "sg:city":"Jackson",
    "sg:classifiers":[
        {
            "category":"Manufacturing",
            "subcategory":"Lumber",
            "type":"Manufacturing & Wholesale Goods"
        }
    ],
    "sg:phone":"+1 606 666 5529",
    "sg:postcode":"41339",
    "sg:province":"KY",
    "sg:tags":[
        "company",
        "logging"
    ],
    "wof:name":"Begley Lumber Co",
    "wof:placetype":"venue"
},
  "geometry": {"coordinates":[-83.38816799999999,37.532336],"type":"Point"}
}