{
  "type": "Feature",
  "properties": {
    "addr:full":"4100 Dutchmans Ln Louisville KY 40207",
    "addr:housenumber":"4100",
    "addr:postcode":"40207",
    "addr:street":"Dutchmans Ln",
    "iso:country":"US",
    "sg:address":"4100 Dutchmans Ln",
    "sg:city":"Louisville",
    "sg:classifiers":[
        {
            "category":"Restaurant",
            "type":"Food & Drink"
        }
    ],
    "sg:phone":"+1 502 899 6159",
    "sg:postcode":"40207",
    "sg:province":"KY",
    "sg:tags":[
        "eating"
    ],
    "wof:name":"Morrians Management Specialist",
    "wof:placetype":"venue"
},
  "geometry": {"coordinates":[-85.631664,38.234545],"type":"Point"}
}