{
  "type": "Feature",
  "properties": {
    "iso:country":"US",
    "sg:address":"845 Isabella St",
    "sg:city":"Newport",
    "sg:classifiers":[
        {
            "category":"Wholesale",
            "subcategory":"Stationery",
            "type":"Manufacturing & Wholesale Goods"
        }
    ],
    "sg:phone":"+1 859 491 8100",
    "sg:postcode":"41071",
    "sg:province":"KY",
    "sg:tags":[
        "school",
        "supply"
    ],
    "sg:website":"www.corpuscentral.com",
    "wof:name":"Corpus Central Purchasing",
    "wof:placetype":"venue"
},
  "geometry": {"coordinates":[-84.49588,39.085173],"type":"Point"}
}