{
  "type": "Feature",
  "properties": {
    "iso:country":"US",
    "sg:address":"836 Pope Rd",
    "sg:city":"Scottsville",
    "sg:classifiers":[
        {
            "category":"Utilities",
            "subcategory":"Electric",
            "type":"Services"
        }
    ],
    "sg:phone":"+1 270 618 5202",
    "sg:postcode":"42164",
    "sg:province":"KY",
    "sg:tags":[
        "company"
    ],
    "wof:name":"RPM Power Troll",
    "wof:placetype":"venue"
},
  "geometry": {"coordinates":[-86.30524800000001,36.777776],"type":"Point"}
}