{
  "type": "Feature",
  "properties": {
    "iso:country":"US",
    "sg:address":"18 Bellaire Pl",
    "sg:city":"Fort Thomas",
    "sg:classifiers":[
        {
            "category":"Organizations",
            "subcategory":"Religious Organization",
            "type":"Services"
        }
    ],
    "sg:phone":"+1 859 442 5666",
    "sg:postcode":"41075",
    "sg:province":"KY",
    "wof:name":"Look of Living LLC",
    "wof:placetype":"venue"
},
  "geometry": {"coordinates":[-84.446969,39.094448],"type":"Point"}
}