{
  "type": "Feature",
  "properties": {
    "iso:country":"US",
    "sg:address":"925 US Hwy 150",
    "sg:city":"Stanford",
    "sg:classifiers":[
        {
            "category":"Professional",
            "type":"Services"
        }
    ],
    "sg:phone":"+1 606 365 2143",
    "sg:postcode":"40484",
    "sg:province":"KY",
    "wof:name":"Southern States Stanford Svc",
    "wof:placetype":"venue"
},
  "geometry": {"coordinates":[-84.706293,37.578609],"type":"Point"}
}