{
  "type": "Feature",
  "properties": {
    "iso:country":"US",
    "sg:address":"5030 Poplar Level Rd",
    "sg:city":"Louisville",
    "sg:classifiers":[
        {
            "category":"Shopping",
            "subcategory":"Music",
            "type":"Retail Goods"
        }
    ],
    "sg:phone":"+1 502 964 4959",
    "sg:postcode":"40219",
    "sg:province":"KY",
    "wof:name":"Joes Music Vault",
    "wof:placetype":"venue"
},
  "geometry": {"coordinates":[-85.680307,38.165326],"type":"Point"}
}