{
  "type": "Feature",
  "properties": {
    "iso:country":"US",
    "sg:address":"727 1/2 Hospital Dr 100",
    "sg:city":"Shelbyville",
    "sg:classifiers":[
        {
            "category":"Health Services",
            "subcategory":"Doctor",
            "type":"Services"
        }
    ],
    "sg:phone":"+1 502 647 4341",
    "sg:postcode":"40065",
    "sg:province":"KY",
    "sg:tags":[
        "physician",
        "pediatrics-otorhinolaryngology",
        "surgeons",
        "nose",
        "throat",
        "ear"
    ],
    "wof:name":"Commonwealth Ear Nose & Throat",
    "wof:placetype":"venue"
},
  "geometry": {"coordinates":[-85.23612799999999,38.210184],"type":"Point"}
}