{
  "type": "Feature",
  "properties": {
    "iso:country":"US",
    "sg:address":"630 S Broadway St",
    "sg:city":"Georgetown",
    "sg:classifiers":[
        {
            "category":"Manufacturing",
            "subcategory":"Tools & Machinery",
            "type":"Manufacturing & Wholesale Goods"
        }
    ],
    "sg:phone":"+1 502 868 5106",
    "sg:postcode":"40324",
    "sg:province":"KY",
    "sg:tags":[
        "machine",
        "shop"
    ],
    "wof:name":"Polycraft Tool",
    "wof:placetype":"venue"
},
  "geometry": {"coordinates":[-84.56047100000001,38.201527],"type":"Point"}
}