{
  "type": "Feature",
  "properties": {
    "addr:full":"3038 Lone Oak Rd Paducah KY 42003",
    "addr:housenumber":"3038",
    "addr:postcode":"42003",
    "addr:street":"Lone Oak Rd",
    "iso:country":"US",
    "sg:address":"3038 Lone Oak Rd",
    "sg:city":"Paducah",
    "sg:classifiers":[
        {
            "category":"Professional",
            "subcategory":"Accounting & Tax Preparation",
            "type":"Services"
        }
    ],
    "sg:phone":"+1 270 554 1487",
    "sg:postcode":"42003",
    "sg:province":"KY",
    "sg:tags":[
        "accountant"
    ],
    "wof:name":"David K Sanders CPA",
    "wof:placetype":"venue"
},
  "geometry": {"coordinates":[-88.66458299999999,37.036306],"type":"Point"}
}