{
  "type": "Feature",
  "properties": {
    "iso:country":"US",
    "sg:address":"220 Dunn Store Rd",
    "sg:city":"Morgantown",
    "sg:classifiers":[
        {
            "category":"Retail",
            "subcategory":"Auto Repair",
            "type":"Services"
        }
    ],
    "sg:phone":"+1 270 526 6723",
    "sg:postcode":"42261",
    "sg:province":"KY",
    "sg:tags":[
        "repairing",
        "automobile"
    ],
    "wof:name":"Premier Welding & Fabrication",
    "wof:placetype":"venue"
},
  "geometry": {"coordinates":[-86.68235900000001,37.160035],"type":"Point"}
}