{
  "type": "Feature",
  "properties": {
    "iso:country":"US",
    "sg:address":"4800 Poplar Place Dr",
    "sg:city":"Louisville",
    "sg:classifiers":[
        {
            "category":"Wholesale",
            "subcategory":"Office Equipment",
            "type":"Manufacturing & Wholesale Goods"
        },
        {
            "category":"Shopping",
            "subcategory":"Stationery & Office Supplies",
            "type":"Retail Goods"
        },
        {
            "category":"Manufacturing",
            "subcategory":"Motor Vehicles & Parts",
            "type":"Manufacturing & Wholesale Goods"
        },
        {
            "category":"Retail",
            "subcategory":"Repair Shop",
            "type":"Services"
        },
        {
            "category":"Manufacturing",
            "subcategory":"Electronics",
            "type":"Manufacturing & Wholesale Goods"
        }
    ],
    "sg:phone":"+1 502 968 0990",
    "sg:postcode":"40213",
    "sg:province":"KY",
    "sg:tags":[
        "machine",
        "fax",
        "printers-equipment",
        "copy",
        "supplies-repair"
    ],
    "sg:website":"http://www.printmanageinc.com",
    "wof:name":"Print Manage Inc",
    "wof:placetype":"venue"
},
  "geometry": {"coordinates":[-85.694283,38.180462],"type":"Point"}
}