{
  "type": "Feature",
  "properties": {
    "addr:full":"402 Samson St Glasgow KY 42141",
    "addr:housenumber":"402",
    "addr:postcode":"42141",
    "addr:street":"Samson St",
    "iso:country":"US",
    "sg:address":"402 Samson St",
    "sg:city":"Glasgow",
    "sg:classifiers":[
        {
            "category":"Real Estate",
            "subcategory":"Surveying",
            "type":"Services"
        }
    ],
    "sg:phone":"+1 270 651 8311",
    "sg:postcode":"42141",
    "sg:province":"KY",
    "sg:tags":[
        "surveyor"
    ],
    "wof:name":"Pride Engineering & Land Srvyg",
    "wof:placetype":"venue"
},
  "geometry": {"coordinates":[-85.91601,37.004093],"type":"Point"}
}