{
  "type": "Feature",
  "properties": {
    "addr:full":"6983 Shelbyville Rd Simpsonville KY 40067",
    "addr:housenumber":"6983",
    "addr:postcode":"40067",
    "addr:street":"Shelbyville Rd",
    "iso:country":"US",
    "sg:address":"6983 Shelbyville Rd",
    "sg:city":"Simpsonville",
    "sg:classifiers":[
        {
            "category":"Real Estate",
            "subcategory":"Real Estate Agent",
            "type":"Services"
        }
    ],
    "sg:phone":"+1 502 722 5213",
    "sg:postcode":"40067",
    "sg:province":"KY",
    "sg:tags":[
        "appraiser"
    ],
    "wof:name":"Frazier-Mc Mullan & Shouse",
    "wof:placetype":"venue"
},
  "geometry": {"coordinates":[-85.336277,38.221257],"type":"Point"}
}