{
  "type": "Feature",
  "properties": {
    "iso:country":"US",
    "sg:address":"135 Quarry Rd",
    "sg:city":"Leitchfield",
    "sg:classifiers":[
        {
            "category":"Professional",
            "type":"Services"
        }
    ],
    "sg:phone":"+1 270 259 5124",
    "sg:postcode":"42754",
    "sg:province":"KY",
    "sg:tags":[
        "establishment"
    ],
    "wof:name":"S & S Stave Co Inc",
    "wof:placetype":"venue"
},
  "geometry": {"coordinates":[-86.326313,37.473699],"type":"Point"}
}