{
  "type": "Feature",
  "properties": {
    "addr:full":"3973 Scenic Trl Shepherdsville KY 40165",
    "addr:housenumber":"3973",
    "addr:postcode":"40165",
    "addr:street":"Scenic Trl",
    "iso:country":"US",
    "sg:address":"3973 Scenic Trl",
    "sg:city":"Shepherdsville",
    "sg:classifiers":[
        {
            "category":"Building & Trades",
            "subcategory":"Construction",
            "type":"Services"
        }
    ],
    "sg:phone":"+1 502 957 3627",
    "sg:postcode":"40165",
    "sg:province":"KY",
    "sg:tags":[
        "house"
    ],
    "wof:name":"Byers Layman Builder",
    "wof:placetype":"venue"
},
  "geometry": {"coordinates":[-85.67064999999999,38.05271],"type":"Point"}
}