{
  "type": "Feature",
  "properties": {
    "addr:full":"10490 Bluegrass Pkwy Louisville KY 40299",
    "addr:housenumber":"10490",
    "addr:postcode":"40299",
    "addr:street":"Bluegrass Pkwy",
    "iso:country":"US",
    "sg:address":"10490 Bluegrass Pkwy",
    "sg:city":"Louisville",
    "sg:classifiers":[
        {
            "category":"Building & Trades",
            "subcategory":"Equipment Rental",
            "type":"Services"
        }
    ],
    "sg:phone":"+1 502 499 5800",
    "sg:postcode":"40299",
    "sg:province":"KY",
    "sg:tags":[
        "audio",
        "leasing"
    ],
    "wof:name":"TEMPORARY Technology Inc",
    "wof:placetype":"venue"
},
  "geometry": {"coordinates":[-85.563106,38.222417],"type":"Point"}
}