{
  "type": "Feature",
  "properties": {
    "addr:full":"9300 National Tpke Fairdale KY 40118",
    "addr:housenumber":"9300",
    "addr:postcode":"40118",
    "addr:street":"National Tpke",
    "iso:country":"US",
    "sg:address":"9300 National Tpke",
    "sg:city":"Fairdale",
    "sg:classifiers":[
        {
            "category":"Building & Trades",
            "subcategory":"Construction",
            "type":"Services"
        }
    ],
    "sg:phone":"+1 502 364 0089",
    "sg:postcode":"40118",
    "sg:province":"KY",
    "sg:tags":[
        "siding",
        "contractor"
    ],
    "wof:name":"Bluegrass Siding & Trim Inc",
    "wof:placetype":"venue"
},
  "geometry": {"coordinates":[-85.747889,38.11379],"type":"Point"}
}