{
  "type": "Feature",
  "properties": {
    "addr:full":"1117 E Center St Madisonville KY 42431",
    "addr:housenumber":"1117",
    "addr:postcode":"42431",
    "addr:street":"E Center St",
    "iso:country":"US",
    "sg:address":"1117 E Center St",
    "sg:city":"Madisonville",
    "sg:classifiers":[
        {
            "category":"Wholesale",
            "subcategory":"Non-durable Goods",
            "type":"Manufacturing & Wholesale Goods"
        }
    ],
    "sg:phone":"+1 270 821 7100",
    "sg:postcode":"42431",
    "sg:province":"KY",
    "sg:tags":[
        "merchandise",
        "general"
    ],
    "sg:website":"www.price-busters.net",
    "wof:name":"Pricebusters Gift Outlet",
    "wof:placetype":"venue"
},
  "geometry": {"coordinates":[-87.481093,37.327054],"type":"Point"}
}