{
  "type": "Feature",
  "properties": {
    "iso:country":"US",
    "sg:address":"610 S Main St",
    "sg:city":"Franklin",
    "sg:classifiers":[
        {
            "category":"Retail",
            "subcategory":"Repair Shop",
            "type":"Services"
        }
    ],
    "sg:phone":"+1 270 586 2818",
    "sg:postcode":"42134",
    "sg:province":"KY",
    "sg:tags":[
        "upholsterer"
    ],
    "wof:name":"Custom Auto Trim",
    "wof:placetype":"venue"
},
  "geometry": {"coordinates":[-86.576385,36.712409],"type":"Point"}
}