{
  "type": "Feature",
  "properties": {
    "addr:full":"207 E Kentucky St Franklin KY 42134",
    "addr:housenumber":"207",
    "addr:postcode":"42134",
    "addr:street":"E Kentucky St",
    "iso:country":"US",
    "sg:address":"207 E Kentucky St",
    "sg:city":"Franklin",
    "sg:classifiers":[
        {
            "category":"Real Estate",
            "subcategory":"Real Estate Agent",
            "type":"Services"
        }
    ],
    "sg:phone":"+1 270 586 9656",
    "sg:postcode":"42134",
    "sg:province":"KY",
    "wof:name":"Kerry Bullington Properties",
    "wof:placetype":"venue"
},
  "geometry": {"coordinates":[-86.576016,36.723005],"type":"Point"}
}