{
  "type": "Feature",
  "properties": {
    "addr:full":"2594 Anton Rd Madisonville KY 42431",
    "addr:housenumber":"2594",
    "addr:postcode":"42431",
    "addr:street":"Anton Rd",
    "iso:country":"US",
    "sg:address":"2594 Anton Rd",
    "sg:city":"Madisonville",
    "sg:classifiers":[
        {
            "category":"Home & Garden",
            "subcategory":"Garden Supply",
            "type":"Retail Goods"
        }
    ],
    "sg:phone":"+1 270 821 2658",
    "sg:postcode":"42431",
    "sg:province":"KY",
    "sg:tags":[
        "lawn",
        "mower"
    ],
    "wof:name":"Lawn Mower Ctr",
    "wof:placetype":"venue"
},
  "geometry": {"coordinates":[-87.451037,37.326727],"type":"Point"}
}