{
  "type": "Feature",
  "properties": {
    "iso:country":"US",
    "sg:address":"2501 Madison Ave",
    "sg:city":"Covington",
    "sg:classifiers":[
        {
            "category":"Autos & Motor Vehicles",
            "subcategory":"Automobile Sales",
            "type":"Retail Goods"
        }
    ],
    "sg:phone":"+1 859 291 3475",
    "sg:postcode":"41014",
    "sg:province":"KY",
    "sg:tags":[
        "car",
        "dealer"
    ],
    "wof:name":"Fast Auto & Payday Loans",
    "wof:placetype":"venue"
},
  "geometry": {"coordinates":[-84.503619,39.060476],"type":"Point"}
}