{
  "type": "Feature",
  "properties": {
    "iso:country":"US",
    "sg:address":"1011 Crossroad Dr",
    "sg:city":"Lawrenceburg",
    "sg:classifiers":[
        {
            "category":"Restaurant",
            "type":"Food & Drink"
        }
    ],
    "sg:menulink":"http://www.allmenus.com/ky/lawrenceburg/96200-taco-johns/menu/",
    "sg:phone":"+1 502 859 5577",
    "sg:postcode":"40342",
    "sg:province":"KY",
    "sg:tags":[
        "american",
        "mexican"
    ],
    "wof:name":"Taco John's",
    "wof:placetype":"venue"
},
  "geometry": {"coordinates":[-84.92058400000001,38.027473],"type":"Point"}
}