{
  "type": "Feature",
  "properties": {
    "iso:country":"US",
    "sg:address":"11301 Decimal Dr",
    "sg:city":"Louisville",
    "sg:classifiers":[
        {
            "category":"Manufacturing",
            "subcategory":"Buildings",
            "type":"Manufacturing & Wholesale Goods"
        },
        {
            "category":"Building & Trades",
            "subcategory":"Construction",
            "type":"Services"
        }
    ],
    "sg:phone":"+1 502 266 5060",
    "sg:postcode":"40299",
    "sg:province":"KY",
    "sg:tags":[
        "industrial",
        "system",
        "specialty",
        "builder",
        "heating",
        "contractor",
        "contractors-commercial",
        "home",
        "air conditioning"
    ],
    "wof:name":"Al Post Inc",
    "wof:placetype":"venue"
},
  "geometry": {"coordinates":[-85.54512800000001,38.21777],"type":"Point"}
}