{
  "type": "Feature",
  "properties": {
    "iso:country":"US",
    "sg:address":"201 N Kentucky Ave",
    "sg:city":"Corbin",
    "sg:classifiers":[
        {
            "category":"Manufacturing",
            "subcategory":"Printing",
            "type":"Manufacturing & Wholesale Goods"
        }
    ],
    "sg:phone":"+1 606 528 2464",
    "sg:postcode":"40701",
    "sg:province":"KY",
    "sg:tags":[
        "newspaper"
    ],
    "sg:website":"www.timestribune.com",
    "wof:name":"Times Tribune",
    "wof:placetype":"venue"
},
  "geometry": {"coordinates":[-84.097697,36.948518],"type":"Point"}
}