{
  "type": "Feature",
  "properties": {
    "iso:country":"US",
    "sg:address":"2335 Millers Ln",
    "sg:city":"Louisville",
    "sg:classifiers":[
        {
            "category":"Organizations",
            "subcategory":"Labor Organization",
            "type":"Services"
        }
    ],
    "sg:phone":"+1 502 778 3380",
    "sg:postcode":"40216",
    "sg:province":"KY",
    "sg:website":"http://www.lu502school.com",
    "wof:name":"Pipe Fitters Joint Educational & Training Fund Local 522",
    "wof:placetype":"venue"
},
  "geometry": {"coordinates":[-85.80122299999999,38.215078],"type":"Point"}
}