{
  "type": "Feature",
  "properties": {
    "iso:country":"US",
    "sg:address":"5750 Limaburg Rd",
    "sg:city":"Burlington",
    "sg:classifiers":[
        {
            "category":"Wholesale",
            "subcategory":"Medical Equipment & Supplies",
            "type":"Manufacturing & Wholesale Goods"
        }
    ],
    "sg:phone":"+1 859 282 3400",
    "sg:postcode":"41005",
    "sg:province":"KY",
    "sg:tags":[
        "hospital"
    ],
    "sg:website":"www.nationallinen.com",
    "wof:name":"National Linen Svc",
    "wof:placetype":"venue"
},
  "geometry": {"coordinates":[-84.689429,39.024173],"type":"Point"}
}