{
  "type": "Feature",
  "properties": {
    "addr:full":"516 E High St Springfield KY 40069",
    "addr:housenumber":"516",
    "addr:postcode":"40069",
    "addr:street":"E High St",
    "iso:country":"US",
    "sg:address":"516 E High St",
    "sg:city":"Springfield",
    "sg:classifiers":[
        {
            "category":"Food & Beverages",
            "subcategory":"Liquor & Beverages",
            "type":"Retail Goods"
        }
    ],
    "sg:phone":"+1 859 336 9422",
    "sg:postcode":"40069",
    "sg:province":"KY",
    "wof:name":"Cooper's Liquor",
    "wof:placetype":"venue"
},
  "geometry": {"coordinates":[-85.21412599999999,37.683608],"type":"Point"}
}