{
  "type": "Feature",
  "properties": {
    "iso:country":"US",
    "sg:address":"3472 Scottsville Rd",
    "sg:city":"Glasgow",
    "sg:classifiers":[
        {
            "category":"Retail",
            "subcategory":"Repair Shop",
            "type":"Services"
        }
    ],
    "sg:phone":"+1 270 678 7604",
    "sg:postcode":"42141",
    "sg:province":"KY",
    "wof:name":"Scooby Power Racing",
    "wof:placetype":"venue"
},
  "geometry": {"coordinates":[-85.95374099999999,36.960169],"type":"Point"}
}