{
  "type": "Feature",
  "properties": {
    "addr:full":"1327 E Broadway St Campbellsville KY 42718",
    "addr:housenumber":"1327",
    "addr:postcode":"42718",
    "addr:street":"E Broadway St",
    "iso:country":"US",
    "sg:address":"1327 E Broadway St",
    "sg:city":"Campbellsville",
    "sg:classifiers":[
        {
            "category":"Government",
            "subcategory":"Office",
            "type":"Public Place"
        }
    ],
    "sg:phone":"+1 270 465 6621",
    "sg:postcode":"42718",
    "sg:province":"KY",
    "sg:tags":[
        "state",
        "resource"
    ],
    "wof:name":"Food Stamp Ofc",
    "wof:placetype":"venue"
},
  "geometry": {"coordinates":[-85.330427,37.35261],"type":"Point"}
}