{
  "type": "Feature",
  "properties": {
    "iso:country":"US",
    "sg:address":"192 Redmar Blvd",
    "sg:city":"Radcliff",
    "sg:classifiers":[
        {
            "category":"Personal",
            "subcategory":"Shoe Repair & Shine",
            "type":"Services"
        }
    ],
    "sg:phone":"+1 270 351 3735",
    "sg:postcode":"40160",
    "sg:province":"KY",
    "sg:tags":[
        "parlor"
    ],
    "wof:name":"Lees Shoe Repair",
    "wof:placetype":"venue"
},
  "geometry": {"coordinates":[-85.948246,37.857698],"type":"Point"}
}