{
  "type": "Feature",
  "properties": {
    "iso:country":"US",
    "sg:address":"1941 Bishop Ln Ste 511",
    "sg:city":"Louisville",
    "sg:classifiers":[
        {
            "category":"Professional",
            "subcategory":"Research",
            "type":"Services"
        }
    ],
    "sg:phone":"+1 502 456 1440",
    "sg:postcode":"40218",
    "sg:province":"KY",
    "sg:tags":[
        "information",
        "medical"
    ],
    "sg:website":"http://www.mdausa.org",
    "wof:name":"Muscular Dystrophy Association, Inc.",
    "wof:placetype":"venue"
},
  "geometry": {"coordinates":[-85.685034,38.201598],"type":"Point"}
}