{
  "type": "Feature",
  "properties": {
    "addr:full":"176 Lisa Dr Wickliffe KY 42087",
    "addr:housenumber":"176",
    "addr:postcode":"42087",
    "addr:street":"Lisa Dr",
    "iso:country":"US",
    "sg:address":"176 Lisa Dr",
    "sg:city":"Wickliffe",
    "sg:classifiers":[
        {
            "category":"Education",
            "subcategory":"Special Training",
            "type":"Public Place"
        }
    ],
    "sg:phone":"+1 270 442 2078",
    "sg:postcode":"42087",
    "sg:province":"KY",
    "wof:name":"Hitting Zone Driving Rang",
    "wof:placetype":"venue"
},
  "geometry": {"coordinates":[-89.071288,36.972005],"type":"Point"}
}