{
  "type": "Feature",
  "properties": {
    "addr:full":"4250 Wayne-Ennis Rd New Haven KY 40051",
    "addr:housenumber":"4250",
    "addr:postcode":"40051",
    "addr:street":"Wayne-Ennis Rd",
    "iso:country":"US",
    "sg:address":"4250 Wayne-Ennis Rd",
    "sg:city":"New Haven",
    "sg:classifiers":[
        {
            "category":"Farming",
            "subcategory":"Farm",
            "type":"Manufacturing & Wholesale Goods"
        }
    ],
    "sg:phone":"+1 270 325 3832",
    "sg:postcode":"40051",
    "sg:province":"KY",
    "sg:tags":[
        "crop",
        "general"
    ],
    "wof:name":"Jackie Jones",
    "wof:placetype":"venue"
},
  "geometry": {"coordinates":[-85.626966,37.547183],"type":"Point"}
}