{
  "type": "Feature",
  "properties": {
    "iso:country":"US",
    "sg:address":"11502 Maple Way",
    "sg:city":"Louisville",
    "sg:classifiers":[
        {
            "category":"Wholesale",
            "subcategory":"Medical Equipment & Supplies",
            "type":"Manufacturing & Wholesale Goods"
        }
    ],
    "sg:phone":"+1 502 962 8977",
    "sg:postcode":"40229",
    "sg:province":"KY",
    "wof:name":"Medrad Inc",
    "wof:placetype":"venue"
},
  "geometry": {"coordinates":[-85.661063,38.097492],"type":"Point"}
}