{
  "type": "Feature",
  "properties": {
    "iso:country":"US",
    "sg:address":"1 Sterling Ave",
    "sg:city":"Mt Sterling",
    "sg:classifiers":[
        {
            "category":"Health Services",
            "subcategory":"Optometrist",
            "type":"Services"
        }
    ],
    "sg:phone":"+1 859 498 6001",
    "sg:postcode":"40353",
    "sg:province":"KY",
    "wof:name":"Helderman Vision Ctr",
    "wof:placetype":"venue"
},
  "geometry": {"coordinates":[-83.946355,38.062484],"type":"Point"}
}