{
  "type": "Feature",
  "properties": {
    "iso:country":"US",
    "sg:address":"1655 Raccoon Creek",
    "sg:city":"London",
    "sg:classifiers":[
        {
            "category":"Building & Trades",
            "subcategory":"Construction",
            "type":"Services"
        }
    ],
    "sg:phone":"+1 606 878 8329",
    "sg:postcode":"40741",
    "sg:province":"KY",
    "sg:tags":[
        "steel",
        "erectors"
    ],
    "sg:website":"www.kentuckysteelerectors.com",
    "wof:name":"Kentucky Erectors",
    "wof:placetype":"venue"
},
  "geometry": {"coordinates":[-84.00796699999999,37.191006],"type":"Point"}
}