{
  "type": "Feature",
  "properties": {
    "iso:country":"US",
    "sg:address":"1883 Southfork Rd",
    "sg:city":"Glasgow",
    "sg:classifiers":[
        {
            "category":"Retail",
            "subcategory":"Auto Repair",
            "type":"Services"
        }
    ],
    "sg:phone":"+1 270 678 6210",
    "sg:postcode":"42141",
    "sg:province":"KY",
    "sg:tags":[
        "automotive"
    ],
    "wof:name":"Hugh Houchens Garage",
    "wof:placetype":"venue"
},
  "geometry": {"coordinates":[-85.97172500000001,36.96948],"type":"Point"}
}