{
  "type": "Feature",
  "properties": {
    "iso:country":"US",
    "sg:address":"1403 E 2nd St",
    "sg:city":"Maysville",
    "sg:classifiers":[
        {
            "category":"Bars & Pubs",
            "type":"Food & Drink"
        }
    ],
    "sg:phone":"+1 606 564 9210",
    "sg:postcode":"41056",
    "sg:province":"KY",
    "sg:tags":[
        "drinking"
    ],
    "wof:name":"Maysville Lions Club",
    "wof:placetype":"venue"
},
  "geometry": {"coordinates":[-83.73573,38.642187],"type":"Point"}
}