{
  "type": "Feature",
  "properties": {
    "iso:country":"US",
    "sg:address":"603 North Dr",
    "sg:city":"Hopkinsville",
    "sg:classifiers":[
        {
            "category":"Local Transit",
            "type":"Transportation"
        }
    ],
    "sg:phone":"+1 270 887 1321",
    "sg:postcode":"42240",
    "sg:province":"KY",
    "sg:tags":[
        "passenger"
    ],
    "wof:name":"Transportation Services",
    "wof:placetype":"venue"
},
  "geometry": {"coordinates":[-87.498403,36.8726],"type":"Point"}
}