{
  "type": "Feature",
  "properties": {
    "addr:full":"8775 US Highway 42 Union KY 41091",
    "addr:housenumber":"8775",
    "addr:postcode":"41091",
    "addr:street":"Us Highway 42",
    "iso:country":"US",
    "sg:address":"8775 US Highway 42",
    "sg:city":"Union",
    "sg:classifiers":[
        {
            "category":"Food & Beverages",
            "subcategory":"Groceries & Convenience Stores",
            "type":"Retail Goods"
        }
    ],
    "sg:phone":"+1 859 384 6761",
    "sg:postcode":"41091",
    "sg:province":"KY",
    "sg:website":"www.kroger.com",
    "wof:name":"Kroger",
    "wof:placetype":"venue"
},
  "geometry": {"coordinates":[-84.67407300000001,38.966645],"type":"Point"}
}