{
  "type": "Feature",
  "properties": {
    "addr:full":"421 Richmond Rd Manchester KY 40962",
    "addr:housenumber":"421",
    "addr:postcode":"40962",
    "addr:street":"Richmond Rd",
    "iso:country":"US",
    "sg:address":"421 Richmond Rd",
    "sg:city":"Manchester",
    "sg:classifiers":[
        {
            "category":"Government",
            "subcategory":"Office",
            "type":"Public Place"
        }
    ],
    "sg:phone":"+1 606 598 3541",
    "sg:postcode":"40962",
    "sg:province":"KY",
    "wof:name":"Maintenance Garage",
    "wof:placetype":"venue"
},
  "geometry": {"coordinates":[-83.76618499999999,37.159583],"type":"Point"}
}