{
  "type": "Feature",
  "properties": {
    "addr:full":"168 Madonna Dr Nicholasville KY 40356",
    "addr:housenumber":"168",
    "addr:postcode":"40356",
    "addr:street":"Madonna Dr",
    "iso:country":"US",
    "sg:address":"168 Madonna Dr",
    "sg:city":"Nicholasville",
    "sg:classifiers":[
        {
            "category":"Building & Trades",
            "subcategory":"Construction",
            "type":"Services"
        }
    ],
    "sg:phone":"+1 859 885 1149",
    "sg:postcode":"40356",
    "sg:province":"KY",
    "sg:tags":[
        "residential"
    ],
    "wof:name":"James Click",
    "wof:placetype":"venue"
},
  "geometry": {"coordinates":[-84.55860300000001,37.893904],"type":"Point"}
}