{
  "type": "Feature",
  "properties": {
    "addr:full":"4015 Preston Hwy Louisville KY 40213",
    "addr:housenumber":"4015",
    "addr:postcode":"40213",
    "addr:street":"Preston Hwy",
    "iso:country":"US",
    "sg:address":"4015 Preston Hwy",
    "sg:city":"Louisville",
    "sg:classifiers":[
        {
            "category":"Home & Garden",
            "subcategory":"Furniture",
            "type":"Retail Goods"
        }
    ],
    "sg:phone":"+1 502 361 3838",
    "sg:postcode":"40213",
    "sg:province":"KY",
    "sg:tags":[
        "equipment",
        "kitchen",
        "cabinet"
    ],
    "wof:name":"Cabinetpak Kitchens",
    "wof:placetype":"venue"
},
  "geometry": {"coordinates":[-85.729249,38.194317],"type":"Point"}
}