{
  "type": "Feature",
  "properties": {
    "iso:country":"US",
    "sg:address":"7214 Isaac Ln",
    "sg:city":"Florence",
    "sg:classifiers":[
        {
            "category":"Professional",
            "subcategory":"Art Services",
            "type":"Services"
        }
    ],
    "sg:phone":"+1 859 647 6338",
    "sg:postcode":"41042",
    "sg:province":"KY",
    "sg:tags":[
        "commercial",
        "design"
    ],
    "wof:name":"Paint Jar Productions",
    "wof:placetype":"venue"
},
  "geometry": {"coordinates":[-84.620537,39.009856],"type":"Point"}
}