{
  "type": "Feature",
  "properties": {
    "addr:full":"751 Vineyard Rd Nicholasville KY 40356",
    "addr:housenumber":"751",
    "addr:postcode":"40356",
    "addr:street":"Vineyard Rd",
    "iso:country":"US",
    "sg:address":"751 Vineyard Rd",
    "sg:city":"Nicholasville",
    "sg:classifiers":[
        {
            "category":"Shopping",
            "subcategory":"Books",
            "type":"Retail Goods"
        }
    ],
    "sg:phone":"+1 859 881 8446",
    "sg:postcode":"40356",
    "sg:province":"KY",
    "wof:name":"All Things Possible",
    "wof:placetype":"venue"
},
  "geometry": {"coordinates":[-84.602777,37.844087],"type":"Point"}
}