{
  "type": "Feature",
  "properties": {
    "iso:country":"US",
    "sg:address":"6703 Foxcroft Rd",
    "sg:city":"Prospect",
    "sg:classifiers":[
        {
            "category":"Banks & Credit Unions",
            "subcategory":"Investment Brokerage",
            "type":"Services"
        }
    ],
    "sg:phone":"+1 502 228 9330",
    "sg:postcode":"40059",
    "sg:province":"KY",
    "sg:tags":[
        "security"
    ],
    "wof:name":"Legg Mason",
    "wof:placetype":"venue"
},
  "geometry": {"coordinates":[-85.604141,38.342515],"type":"Point"}
}