{
  "type": "Feature",
  "properties": {
    "addr:full":"5070 Reidland Rd Paducah KY 42003",
    "addr:housenumber":"5070",
    "addr:postcode":"42003",
    "addr:street":"Reidland Rd",
    "iso:country":"US",
    "sg:address":"5070 Reidland Rd",
    "sg:city":"Paducah",
    "sg:classifiers":[
        {
            "category":"Building & Trades",
            "subcategory":"Plumbing",
            "type":"Services"
        }
    ],
    "sg:phone":"+1 270 898 1500",
    "sg:postcode":"42003",
    "sg:province":"KY",
    "sg:tags":[
        "conditioning",
        "air",
        "system",
        "contractor"
    ],
    "wof:name":"J & L Mobile Home Parts",
    "wof:placetype":"venue"
},
  "geometry": {"coordinates":[-88.53301399999999,37.028088],"type":"Point"}
}