{
  "type": "Feature",
  "properties": {
    "addr:full":"3805 Dylan Pl Ste 120 Lexington KY 40514",
    "addr:housenumber":"3805",
    "addr:postcode":"40514",
    "addr:street":"Dylan Pl Ste 120",
    "iso:country":"US",
    "sg:address":"3805 Dylan Pl Ste 120",
    "sg:city":"Lexington",
    "sg:classifiers":[
        {
            "category":"Restaurant",
            "type":"Food & Drink"
        }
    ],
    "sg:phone":"+1 859 296 2625",
    "sg:postcode":"40514",
    "sg:province":"KY",
    "sg:tags":[
        "asian",
        "pan",
        "japanese"
    ],
    "wof:name":"Osaka Restaurant",
    "wof:placetype":"venue"
},
  "geometry": {"coordinates":[-84.55204000000001,37.981258],"type":"Point"}
}