{
  "type": "Feature",
  "properties": {
    "addr:full":"399 Fowler Ln Elizabethtown KY 42701",
    "addr:housenumber":"399",
    "addr:postcode":"42701",
    "addr:street":"Fowler Ln",
    "iso:country":"US",
    "sg:address":"399 Fowler Ln",
    "sg:city":"Elizabethtown",
    "sg:classifiers":[
        {
            "category":"Health Services",
            "subcategory":"Hospital",
            "type":"Services"
        }
    ],
    "sg:phone":"+1 270 234 9810",
    "sg:postcode":"42701",
    "sg:province":"KY",
    "sg:tags":[
        "mental"
    ],
    "wof:name":"Spectrum Care Academy/Kids",
    "wof:placetype":"venue"
},
  "geometry": {"coordinates":[-85.812517,37.71689],"type":"Point"}
}