{
  "type": "Feature",
  "properties": {
    "iso:country":"US",
    "sg:address":"400 Dixie Hwy N",
    "sg:city":"Radcliff",
    "sg:classifiers":[
        {
            "category":"Autos & Motor Vehicles",
            "subcategory":"Auto Supplies",
            "type":"Retail Goods"
        }
    ],
    "sg:phone":"+1 270 352 0800",
    "sg:postcode":"40160",
    "sg:province":"KY",
    "sg:tags":[
        "automobile",
        "parts"
    ],
    "wof:name":"Advance Auto Parts Inc",
    "wof:placetype":"venue"
},
  "geometry": {"coordinates":[-85.941928,37.843793],"type":"Point"}
}