{
  "type": "Feature",
  "properties": {
    "addr:full":"8222 Shelbyville Rd Louisville KY 40222",
    "addr:housenumber":"8222",
    "addr:postcode":"40222",
    "addr:street":"Shelbyville Rd",
    "iso:country":"US",
    "sg:address":"8222 Shelbyville Rd",
    "sg:city":"Louisville",
    "sg:classifiers":[
        {
            "category":"Organizations",
            "subcategory":"Community Association",
            "type":"Services"
        }
    ],
    "sg:phone":"+1 502 420 1772",
    "sg:postcode":"40222",
    "sg:province":"KY",
    "sg:tags":[
        "club"
    ],
    "wof:name":"Hurstbourne Country Club",
    "wof:placetype":"venue"
},
  "geometry": {"coordinates":[-85.600627,38.248263],"type":"Point"}
}