{
  "type": "Feature",
  "properties": {
    "iso:country":"US",
    "sg:address":"100 W Mercer St",
    "sg:city":"Reynolds Station",
    "sg:classifiers":[
        {
            "category":"Organizations",
            "subcategory":"Religious Organization",
            "type":"Services"
        }
    ],
    "sg:phone":"+1 270 927 6253",
    "sg:postcode":"42367",
    "sg:province":"KY",
    "sg:tags":[
        "church"
    ],
    "wof:name":"Roseville Baptist Church",
    "wof:placetype":"venue"
},
  "geometry": {"coordinates":[-87.159341,37.23576],"type":"Point"}
}