{
  "type": "Feature",
  "properties": {
    "iso:country":"US",
    "sg:address":"1655 Clark Line Rd",
    "sg:city":"Paducah",
    "sg:classifiers":[
        {
            "category":"Building & Trades",
            "subcategory":"Construction",
            "type":"Services"
        }
    ],
    "sg:phone":"+1 270 559 6252",
    "sg:postcode":"42003",
    "sg:province":"KY",
    "sg:tags":[
        "masonry",
        "contractor"
    ],
    "wof:name":"Peifer Masonry",
    "wof:placetype":"venue"
},
  "geometry": {"coordinates":[-88.619399,37.002108],"type":"Point"}
}