{
  "type": "Feature",
  "properties": {
    "addr:full":"201 Forest Ave Winchester KY 40391",
    "addr:housenumber":"201",
    "addr:postcode":"40391",
    "addr:street":"Forest Ave",
    "iso:country":"US",
    "sg:address":"201 Forest Ave",
    "sg:city":"Winchester",
    "sg:classifiers":[
        {
            "category":"Sports & Exercise",
            "subcategory":"Bowling",
            "type":"Entertainment"
        }
    ],
    "sg:phone":"+1 859 745 1901",
    "sg:postcode":"40391",
    "sg:province":"KY",
    "sg:tags":[
        "center"
    ],
    "wof:name":"Forest Park Lanes",
    "wof:placetype":"venue"
},
  "geometry": {"coordinates":[-84.19267499999999,38.000531],"type":"Point"}
}