{
  "type": "Feature",
  "properties": {
    "iso:country":"US",
    "sg:address":"9906 Janet Lee Ct",
    "sg:city":"Louisville",
    "sg:classifiers":[
        {
            "category":"Shopping",
            "subcategory":"Musical Instruments",
            "type":"Retail Goods"
        }
    ],
    "sg:phone":"+1 502 231 5040",
    "sg:postcode":"40291",
    "sg:province":"KY",
    "wof:name":"Accurate Piano Service",
    "wof:placetype":"venue"
},
  "geometry": {"coordinates":[-85.574906,38.161668],"type":"Point"}
}