{
  "type": "Feature",
  "properties": {
    "iso:country":"US",
    "sg:address":"923 E Muhammad Ali Blvd",
    "sg:city":"Louisville",
    "sg:classifiers":[
        {
            "category":"Social Services",
            "subcategory":"Child Care",
            "type":"Services"
        }
    ],
    "sg:phone":"+1 502 561 8674",
    "sg:postcode":"40204",
    "sg:province":"KY",
    "wof:name":"Thomas Mackey Child Dev",
    "wof:placetype":"venue"
},
  "geometry": {"coordinates":[-85.735061,38.248781],"type":"Point"}
}