{
  "type": "Feature",
  "properties": {
    "addr:full":"316 Versailles Rd Frankfort KY 40601",
    "addr:housenumber":"316",
    "addr:postcode":"40601",
    "addr:street":"Versailles Rd",
    "iso:country":"US",
    "sg:address":"316 Versailles Rd",
    "sg:city":"Frankfort",
    "sg:classifiers":[
        {
            "category":"Shopping",
            "subcategory":"Used Merchandise",
            "type":"Retail Goods"
        }
    ],
    "sg:phone":"+1 502 695 1100",
    "sg:postcode":"40601",
    "sg:province":"KY",
    "sg:tags":[
        "shop",
        "thrift"
    ],
    "wof:name":"Goodwill Industries",
    "wof:placetype":"venue"
},
  "geometry": {"coordinates":[-84.830557,38.198068],"type":"Point"}
}