{
  "type": "Feature",
  "properties": {
    "iso:country":"US",
    "sg:address":"2981 Hurricane Rd",
    "sg:city":"Pikeville",
    "sg:classifiers":[
        {
            "category":"Government",
            "subcategory":"Fire Station",
            "type":"Public Place"
        }
    ],
    "sg:phone":"+1 606 478 2222",
    "sg:postcode":"41501",
    "sg:province":"KY",
    "sg:tags":[
        "department"
    ],
    "wof:name":"Fire Department Hurricane Crk",
    "wof:placetype":"venue"
},
  "geometry": {"coordinates":[-82.58831600000001,37.50077],"type":"Point"}
}