{
  "type": "Feature",
  "properties": {
    "iso:country":"US",
    "sg:address":"724 E Lyon St Apt D2",
    "sg:city":"Morganfield",
    "sg:classifiers":[
        {
            "category":"Real Estate",
            "subcategory":"Real Estate Operator",
            "type":"Services"
        }
    ],
    "sg:phone":"+1 270 389 0217",
    "sg:postcode":"42437",
    "sg:province":"KY",
    "sg:tags":[
        "apartment"
    ],
    "wof:name":"Holly Park Apartments",
    "wof:placetype":"venue"
},
  "geometry": {"coordinates":[-87.904526,37.683558],"type":"Point"}
}