{
  "type": "Feature",
  "properties": {
    "iso:country":"US",
    "sg:address":"215 Rose Hill Ave",
    "sg:city":"Versailles",
    "sg:classifiers":[
        {
            "category":"Professional",
            "subcategory":"Lawyer & Legal Services",
            "type":"Services"
        }
    ],
    "sg:phone":"+1 859 873 3001",
    "sg:postcode":"40383",
    "sg:province":"KY",
    "sg:tags":[
        "attorney"
    ],
    "wof:name":"Thomas E O'Shaughnessy",
    "wof:placetype":"venue"
},
  "geometry": {"coordinates":[-84.732767,38.051733],"type":"Point"}
}