{
  "type": "Feature",
  "properties": {
    "addr:full":"417 Capp Harlan Rd Tompkinsville KY 42167",
    "addr:housenumber":"417",
    "addr:postcode":"42167",
    "addr:street":"Capp Harlan Rd",
    "iso:country":"US",
    "sg:address":"417 Capp Harlan Rd",
    "sg:city":"Tompkinsville",
    "sg:classifiers":[
        {
            "category":"Government",
            "subcategory":"Office",
            "type":"Public Place"
        }
    ],
    "sg:phone":"+1 270 487 5905",
    "sg:postcode":"42167",
    "sg:province":"KY",
    "wof:name":"Monroe County Home Health Agcy",
    "wof:placetype":"venue"
},
  "geometry": {"coordinates":[-85.68028200000001,36.70174],"type":"Point"}
}