{
  "type": "Feature",
  "properties": {
    "iso:country":"US",
    "sg:address":"4757 Rockford Plz",
    "sg:city":"Shively",
    "sg:classifiers":[
        {
            "category":"Retail",
            "subcategory":"Auto Rental",
            "type":"Services"
        }
    ],
    "sg:phone":"+1 502 447 4833",
    "sg:postcode":"40216",
    "sg:province":"KY",
    "sg:tags":[
        "renting",
        "truck",
        "leasing"
    ],
    "wof:name":"U-Haul Co",
    "wof:placetype":"venue"
},
  "geometry": {"coordinates":[-85.827882,38.177713],"type":"Point"}
}