{
  "type": "Feature",
  "properties": {
    "iso:country":"US",
    "sg:address":"5525 US Hwy 60",
    "sg:city":"Owensboro",
    "sg:classifiers":[
        {
            "category":"Banks & Credit Unions",
            "subcategory":"Bank",
            "type":"Services"
        }
    ],
    "sg:phone":"+1 270 686 3032",
    "sg:postcode":"42303",
    "sg:province":"KY",
    "wof:name":"Daco Federal Credit Union",
    "wof:placetype":"venue"
},
  "geometry": {"coordinates":[-87.045445,37.810021],"type":"Point"}
}