{
  "type": "Feature",
  "properties": {
    "addr:full":"3957 Park Dr Shively KY 40216",
    "addr:housenumber":"3957",
    "addr:postcode":"40216",
    "addr:street":"Park Dr",
    "iso:country":"US",
    "sg:address":"3957 Park Dr",
    "sg:city":"Shively",
    "sg:classifiers":[
        {
            "category":"Sports & Exercise",
            "subcategory":"Bowling",
            "type":"Entertainment"
        }
    ],
    "sg:phone":"+1 502 447 6216",
    "sg:postcode":"40216",
    "sg:province":"KY",
    "sg:tags":[
        "center"
    ],
    "wof:name":"Greater Louisville Bowling",
    "wof:placetype":"venue"
},
  "geometry": {"coordinates":[-85.80910799999999,38.194291],"type":"Point"}
}