{
  "type": "Feature",
  "properties": {
    "iso:country":"US",
    "sg:address":"110 S Cave St",
    "sg:city":"Princeton",
    "sg:classifiers":[
        {
            "category":"Health Services",
            "subcategory":"Doctor",
            "type":"Services"
        }
    ],
    "sg:phone":"+1 270 365 5579",
    "sg:postcode":"42445",
    "sg:province":"KY",
    "sg:tags":[
        "dentist"
    ],
    "wof:name":"Frank A Moller DDS",
    "wof:placetype":"venue"
},
  "geometry": {"coordinates":[-87.88516300000001,37.109921],"type":"Point"}
}