{
  "type": "Feature",
  "properties": {
    "addr:full":"948 Keeneland Green Dr Union KY 41091",
    "addr:housenumber":"948",
    "addr:postcode":"41091",
    "addr:street":"Keeneland Green Dr",
    "iso:country":"US",
    "sg:address":"948 Keeneland Green Dr",
    "sg:city":"Union",
    "sg:classifiers":[
        {
            "category":"Wholesale",
            "subcategory":"Non-durable Goods",
            "type":"Manufacturing & Wholesale Goods"
        }
    ],
    "sg:phone":"+1 859 657 6088",
    "sg:postcode":"41091",
    "sg:province":"KY",
    "sg:tags":[
        "advertising"
    ],
    "wof:name":"Corporate Buying Svc",
    "wof:placetype":"venue"
},
  "geometry": {"coordinates":[-84.64663400000001,38.916803],"type":"Point"}
}