{
  "type": "Feature",
  "properties": {
    "iso:country":"US",
    "sg:address":"416 W Oak St",
    "sg:city":"Louisville",
    "sg:classifiers":[
        {
            "category":"Restaurant",
            "type":"Food & Drink"
        }
    ],
    "sg:phone":"+1 502 636 3361",
    "sg:postcode":"40203",
    "sg:province":"KY",
    "wof:name":"Jamaame Restaurant",
    "wof:placetype":"venue"
},
  "geometry": {"coordinates":[-85.761782,38.235066],"type":"Point"}
}