{
  "type": "Feature",
  "properties": {
    "iso:country":"US",
    "sg:address":"208 Rutherford Ave",
    "sg:city":"Franklin",
    "sg:classifiers":[
        {
            "category":"Retail",
            "subcategory":"Repair Shop",
            "type":"Services"
        }
    ],
    "sg:phone":"+1 270 598 0973",
    "sg:postcode":"42134",
    "sg:province":"KY",
    "wof:name":"Dunmor Tractor Equipment",
    "wof:placetype":"venue"
},
  "geometry": {"coordinates":[-86.57575799999999,36.746299],"type":"Point"}
}