{
  "type": "Feature",
  "properties": {
    "iso:country":"US",
    "sg:address":"202 River Rd",
    "sg:city":"Silver Grove",
    "sg:classifiers":[
        {
            "category":"Restaurant",
            "type":"Food & Drink"
        }
    ],
    "sg:phone":"+1 859 781 2211",
    "sg:postcode":"41075",
    "sg:province":"KY",
    "wof:name":"Pizza Plus",
    "wof:placetype":"venue"
},
  "geometry": {"coordinates":[-84.445941,39.061876],"type":"Point"}
}