{
  "type": "Feature",
  "properties": {
    "iso:country":"US",
    "sg:address":"314 N 19th St",
    "sg:city":"Middlesboro",
    "sg:classifiers":[
        {
            "category":"Organizations",
            "subcategory":"Religious Organization",
            "type":"Services"
        }
    ],
    "sg:phone":"+1 606 248 5228",
    "sg:postcode":"40965",
    "sg:province":"KY",
    "sg:tags":[
        "church"
    ],
    "wof:name":"Mount Moriah Baptist Church",
    "wof:placetype":"venue"
},
  "geometry": {"coordinates":[-83.71307299999999,36.611248],"type":"Point"}
}