{
  "type": "Feature",
  "properties": {
    "iso:country":"US",
    "sg:address":"2308 N Middletown Rd",
    "sg:city":"Paris",
    "sg:classifiers":[
        {
            "category":"Recreation",
            "type":"Entertainment"
        }
    ],
    "sg:phone":"+1 859 231 0400",
    "sg:postcode":"40361",
    "sg:province":"KY",
    "sg:tags":[
        "stable"
    ],
    "wof:name":"Xalapa Stables",
    "wof:placetype":"venue"
},
  "geometry": {"coordinates":[-84.152451,38.167303],"type":"Point"}
}