{
  "type": "Feature",
  "properties": {
    "iso:country":"US",
    "sg:address":"155 College St",
    "sg:city":"Pikeville",
    "sg:classifiers":[
        {
            "category":"Professional",
            "subcategory":"Accounting & Tax Preparation",
            "type":"Services"
        }
    ],
    "sg:phone":"+1 606 432 3577",
    "sg:postcode":"41501",
    "sg:province":"KY",
    "sg:tags":[
        "bookkeeping",
        "general"
    ],
    "wof:name":"Johnny L Denison CPA",
    "wof:placetype":"venue"
},
  "geometry": {"coordinates":[-82.520872,37.476833],"type":"Point"}
}