{
  "type": "Feature",
  "properties": {
    "iso:country":"US",
    "sg:address":"1607 Irvine Rd",
    "sg:city":"Richmond",
    "sg:phone":"+1 859 623 5151",
    "sg:postcode":"40475",
    "sg:province":"KY",
    "sg:tags":[
        "bulk",
        "bottled",
        "gas"
    ],
    "wof:name":"Hacker Bottled Gas",
    "wof:placetype":"venue"
},
  "geometry": {"coordinates":[-84.26031500000001,37.743648],"type":"Point"}
}