{
  "type": "Feature",
  "properties": {
    "addr:full":"312 E Main St Vine Grove KY 40175",
    "addr:housenumber":"312",
    "addr:postcode":"40175",
    "addr:street":"E Main St Vine Grove",
    "iso:country":"US",
    "sg:address":"312 E Main St",
    "sg:city":"Vine Grove",
    "sg:classifiers":[
        {
            "category":"Organizations",
            "subcategory":"Community Association",
            "type":"Services"
        }
    ],
    "sg:phone":"+1 270 877 2194",
    "sg:postcode":"40175",
    "sg:province":"KY",
    "sg:tags":[
        "fraternal"
    ],
    "wof:name":"Knights Of Columbus",
    "wof:placetype":"venue"
},
  "geometry": {"coordinates":[-85.978444,37.809529],"type":"Point"}
}