{
  "type": "Feature",
  "properties": {
    "iso:country":"US",
    "sg:address":"546 E Main St",
    "sg:city":"Morehead",
    "sg:classifiers":[
        {
            "category":"Autos & Motor Vehicles",
            "subcategory":"Motorcycle Sales",
            "type":"Retail Goods"
        }
    ],
    "sg:phone":"+1 606 780 0170",
    "sg:postcode":"40351",
    "sg:province":"KY",
    "sg:tags":[
        "scooter"
    ],
    "wof:name":"Morehead Cycle",
    "wof:placetype":"venue"
},
  "geometry": {"coordinates":[-83.428712,38.188082],"type":"Point"}
}