{
  "type": "Feature",
  "properties": {
    "addr:full":"1490 E New Circle Rd Lexington KY 40509",
    "addr:housenumber":"1490",
    "addr:postcode":"40509",
    "addr:street":"E New Circle Rd",
    "iso:country":"US",
    "sg:address":"1490 E New Circle Rd",
    "sg:city":"Lexington",
    "sg:classifiers":[
        {
            "category":"Autos & Motor Vehicles",
            "subcategory":"Automobile Sales",
            "type":"Retail Goods"
        }
    ],
    "sg:phone":"+1 859 266 2161",
    "sg:postcode":"40509",
    "sg:province":"KY",
    "sg:tags":[
        "car",
        "dealer"
    ],
    "sg:website":"www.quantrellvolvo.com",
    "wof:name":"Quantrell Cadillac-Volvo",
    "wof:placetype":"venue"
},
  "geometry": {"coordinates":[-84.45406199999999,38.024589],"type":"Point"}
}