{
  "type": "Feature",
  "properties": {
    "addr:full":"2554 US Hwy 127 Russell Springs KY 42642",
    "addr:housenumber":"2554",
    "addr:postcode":"42642",
    "addr:street":"Us Hwy 127",
    "iso:country":"US",
    "sg:address":"2554 US Hwy 127",
    "sg:city":"Russell Springs",
    "sg:classifiers":[
        {
            "category":"Banks & Credit Unions",
            "subcategory":"Bank",
            "type":"Services"
        }
    ],
    "sg:phone":"+1 270 866 7322",
    "sg:postcode":"42642",
    "sg:province":"KY",
    "wof:name":"Monticello Banking Co Russell",
    "wof:placetype":"venue"
},
  "geometry": {"coordinates":[-85.05860800000001,37.104119],"type":"Point"}
}