{
  "type": "Feature",
  "properties": {
    "iso:country":"US",
    "sg:address":"708 13th St",
    "sg:city":"Ashland",
    "sg:classifiers":[
        {
            "category":"Health Services",
            "subcategory":"Doctor",
            "type":"Services"
        }
    ],
    "sg:phone":"+1 606 325 4231",
    "sg:postcode":"41101",
    "sg:province":"KY",
    "sg:tags":[
        "dentist"
    ],
    "wof:name":"Joseph W Frazier DDS",
    "wof:placetype":"venue"
},
  "geometry": {"coordinates":[-82.64656600000001,38.475792],"type":"Point"}
}