{
  "type": "Feature",
  "properties": {
    "iso:country":"US",
    "sg:address":"7926 Preston Hwy",
    "sg:city":"Louisville",
    "sg:classifiers":[
        {
            "category":"Health Services",
            "subcategory":"Doctor",
            "type":"Services"
        }
    ],
    "sg:phone":"+1 502 966 8675",
    "sg:postcode":"40219",
    "sg:province":"KY",
    "sg:tags":[
        "physician",
        "surgeon"
    ],
    "wof:name":"John Hines MD",
    "wof:placetype":"venue"
},
  "geometry": {"coordinates":[-85.68593199999999,38.136914],"type":"Point"}
}