{
  "type": "Feature",
  "properties": {
    "iso:country":"US",
    "sg:address":"1242 Inverary Ct",
    "sg:city":"Louisville",
    "sg:classifiers":[
        {
            "category":"Shopping",
            "subcategory":"Used Merchandise",
            "type":"Retail Goods"
        }
    ],
    "sg:phone":"+1 502 426 8275",
    "sg:postcode":"40222",
    "sg:province":"KY",
    "wof:name":"Pams Thrift Store and Baby Wo",
    "wof:placetype":"venue"
},
  "geometry": {"coordinates":[-85.579075,38.227484],"type":"Point"}
}