{
  "type": "Feature",
  "properties": {
    "addr:full":"612 S Main St Smiths Grove KY 42171",
    "addr:housenumber":"612",
    "addr:postcode":"42171",
    "addr:street":"S Main St",
    "iso:country":"US",
    "sg:address":"612 S Main St",
    "sg:city":"Smiths Grove",
    "sg:classifiers":[
        {
            "category":"Shopping",
            "subcategory":"Used Merchandise",
            "type":"Retail Goods"
        }
    ],
    "sg:phone":"+1 270 563 2272",
    "sg:postcode":"42171",
    "sg:province":"KY",
    "sg:tags":[
        "antique"
    ],
    "wof:name":"Smiths Grove Antiques",
    "wof:placetype":"venue"
},
  "geometry": {"coordinates":[-86.209588,37.044435],"type":"Point"}
}