{
  "type": "Feature",
  "properties": {
    "iso:country":"US",
    "sg:address":"309 Reynolds Rd",
    "sg:city":"Glasgow",
    "sg:classifiers":[
        {
            "category":"Home & Garden",
            "subcategory":"Furniture",
            "type":"Retail Goods"
        }
    ],
    "sg:phone":"+1 270 678 5069",
    "sg:postcode":"42141",
    "sg:province":"KY",
    "sg:website":"www.seasonshomeandhearth.com",
    "wof:name":"Seasons Home & Hearth Inc",
    "wof:placetype":"venue"
},
  "geometry": {"coordinates":[-85.932058,37.013301],"type":"Point"}
}