{
  "type": "Feature",
  "properties": {
    "addr:full":"4047 Iron Works Pkwy Lexington KY 40511",
    "addr:housenumber":"4047",
    "addr:postcode":"40511",
    "addr:street":"Iron Works Pkwy",
    "iso:country":"US",
    "sg:address":"4047 Iron Works Pkwy",
    "sg:city":"Lexington",
    "sg:classifiers":[
        {
            "category":"Organizations",
            "subcategory":"Membership Organization",
            "type":"Services"
        }
    ],
    "sg:phone":"+1 859 225 2472",
    "sg:postcode":"40511",
    "sg:province":"KY",
    "sg:tags":[
        "national",
        "equestrian",
        "federation"
    ],
    "wof:name":"USA Equestrian Inc",
    "wof:placetype":"venue"
},
  "geometry": {"coordinates":[-84.518669,38.14747],"type":"Point"}
}