{
  "type": "Feature",
  "properties": {
    "iso:country":"US",
    "sg:address":"8250 Port Rd",
    "sg:city":"Louisville",
    "sg:classifiers":[
        {
            "category":"Building & Trades",
            "subcategory":"Cleaning & Sanitation",
            "type":"Services"
        }
    ],
    "sg:phone":"+1 502 933 1932",
    "sg:postcode":"40258",
    "sg:province":"KY",
    "sg:tags":[
        "sandblasting"
    ],
    "wof:name":"Universal Minerals International Inc",
    "wof:placetype":"venue"
},
  "geometry": {"coordinates":[-85.89583,38.163917],"type":"Point"}
}