{
  "type": "Feature",
  "properties": {
    "iso:country":"US",
    "sg:address":"110 E Main St",
    "sg:city":"Georgetown",
    "sg:classifiers":[
        {
            "category":"Professional",
            "subcategory":"Engineering",
            "type":"Services"
        }
    ],
    "sg:phone":"+1 502 863 1756",
    "sg:postcode":"40324",
    "sg:province":"KY",
    "sg:tags":[
        "engineer"
    ],
    "wof:name":"Thoroughbred Engineering Inc",
    "wof:placetype":"venue"
},
  "geometry": {"coordinates":[-84.559603,38.209857],"type":"Point"}
}