{
  "type": "Feature",
  "properties": {
    "addr:full":"128 N Main St Elizabethtown KY 42701",
    "addr:housenumber":"128",
    "addr:postcode":"42701",
    "addr:street":"N Main St",
    "iso:country":"US",
    "sg:address":"128 N Main St",
    "sg:city":"Elizabethtown",
    "sg:classifiers":[
        {
            "category":"Personal",
            "type":"Services"
        }
    ],
    "sg:phone":"+1 270 765 2515",
    "sg:postcode":"42701",
    "sg:province":"KY",
    "sg:tags":[
        "genealogist"
    ],
    "wof:name":"Brown Pusey House",
    "wof:placetype":"venue"
},
  "geometry": {"coordinates":[-85.85709900000001,37.694159],"type":"Point"}
}