{
  "type": "Feature",
  "properties": {
    "iso:country":"US",
    "sg:address":"2350 Woodhill Dr",
    "sg:city":"Lexington",
    "sg:classifiers":[
        {
            "category":"Home & Garden",
            "subcategory":"Garden Supply",
            "type":"Retail Goods"
        },
        {
            "category":"Shopping",
            "subcategory":"Gifts & Souvenirs",
            "type":"Retail Goods"
        },
        {
            "category":"Shopping",
            "subcategory":"Crafts & Fabrics",
            "type":"Retail Goods"
        },
        {
            "category":"Shopping",
            "subcategory":"Florist",
            "type":"Retail Goods"
        }
    ],
    "sg:phone":"+1 859 269 9674",
    "sg:postcode":"40509",
    "sg:province":"KY",
    "sg:tags":[
        "plant",
        "etc-retail",
        "dried",
        "basket",
        "trees-silk",
        "flowers"
    ],
    "sg:website":"http://www.flowersfrommyers.com",
    "wof:name":"Flowers From Myers",
    "wof:placetype":"venue"
},
  "geometry": {"coordinates":[-84.45493,38.017413],"type":"Point"}
}