{
  "type": "Feature",
  "properties": {
    "iso:country":"US",
    "sg:address":"8002 New Lagrange Rd",
    "sg:city":"Louisville",
    "sg:classifiers":[
        {
            "category":"Personal",
            "subcategory":"Beauty Salon",
            "type":"Services"
        }
    ],
    "sg:phone":"+1 502 423 1343",
    "sg:postcode":"40222",
    "sg:province":"KY",
    "wof:name":"Headz Inc",
    "wof:placetype":"venue"
},
  "geometry": {"coordinates":[-85.60485799999999,38.258082],"type":"Point"}
}