{
  "type": "Feature",
  "properties": {
    "iso:country":"US",
    "sg:address":"4105 US Hwy 41A",
    "sg:city":"Henderson",
    "sg:classifiers":[
        {
            "category":"Retail",
            "subcategory":"Repair Shop",
            "type":"Services"
        }
    ],
    "sg:phone":"+1 270 826 8115",
    "sg:postcode":"42420",
    "sg:province":"KY",
    "wof:name":"Mason S Wldlife Txdermy Studio",
    "wof:placetype":"venue"
},
  "geometry": {"coordinates":[-87.61462299999999,37.795853],"type":"Point"}
}