{
  "type": "Feature",
  "properties": {
    "iso:country":"US",
    "sg:address":"1158 Fort Campbell Blvd",
    "sg:city":"Clarksville",
    "sg:classifiers":[
        {
            "category":"Professional",
            "subcategory":"Business Services",
            "type":"Services"
        }
    ],
    "sg:phone":"+1 931 645 5888",
    "sg:postcode":"37042",
    "sg:province":"KY",
    "sg:tags":[
        "merchandise"
    ],
    "wof:name":"Auction World",
    "wof:placetype":"venue"
},
  "geometry": {"coordinates":[-87.396502,36.555768],"type":"Point"}
}