{
  "type": "Feature",
  "properties": {
    "addr:full":"207 15th St Ashland KY 41101",
    "addr:housenumber":"207",
    "addr:postcode":"41101",
    "addr:street":"15Th St",
    "iso:country":"US",
    "sg:address":"207 15th St",
    "sg:city":"Ashland",
    "sg:classifiers":[
        {
            "category":"Social Services",
            "type":"Services"
        }
    ],
    "sg:phone":"+1 606 325 1626",
    "sg:postcode":"41101",
    "sg:province":"KY",
    "sg:tags":[
        "organization",
        "welfare"
    ],
    "wof:name":"American Red Cross",
    "wof:placetype":"venue"
},
  "geometry": {"coordinates":[-82.640353,38.479824],"type":"Point"}
}