{
  "type": "Feature",
  "properties": {
    "addr:full":"3398 Bardstown Rd Louisville KY 40218",
    "addr:housenumber":"3398",
    "addr:postcode":"40218",
    "addr:street":"Bardstown Rd",
    "iso:country":"US",
    "sg:address":"3398 Bardstown Rd",
    "sg:city":"Louisville",
    "sg:classifiers":[
        {
            "category":"Restaurant",
            "type":"Food & Drink"
        }
    ],
    "sg:menulink":"http://www.allmenus.com/ky/jefferson-central/56361-fiesta-mexicana-2/menu/",
    "sg:phone":"+1 502 762 0840",
    "sg:postcode":"40218",
    "sg:province":"KY",
    "sg:tags":[
        "mexican"
    ],
    "wof:name":"Fiesta Mexicana #2",
    "wof:placetype":"venue"
},
  "geometry": {"coordinates":[-85.666748,38.205618],"type":"Point"}
}