{
  "type": "Feature",
  "properties": {
    "iso:country":"US",
    "sg:address":"226 Thomas More Pkwy",
    "sg:city":"Crestview Hills",
    "sg:classifiers":[
        {
            "category":"Health Services",
            "subcategory":"Health Practitioner",
            "type":"Services"
        }
    ],
    "sg:phone":"+1 859 341 9888",
    "sg:postcode":"41017",
    "sg:province":"KY",
    "sg:tags":[
        "psychologist"
    ],
    "wof:name":"Peter Ganshirt",
    "wof:placetype":"venue"
},
  "geometry": {"coordinates":[-84.57202100000001,39.022447],"type":"Point"}
}