{
  "type": "Feature",
  "properties": {
    "addr:full":"1021 E Broadway Louisville KY 40204",
    "addr:housenumber":"1021",
    "addr:postcode":"40204",
    "addr:street":"E Broadway",
    "iso:country":"US",
    "sg:address":"1021 E Broadway",
    "sg:city":"Louisville",
    "sg:classifiers":[
        {
            "category":"Personal",
            "type":"Services"
        }
    ],
    "sg:phone":"+1 502 584 4534",
    "sg:postcode":"40204",
    "sg:province":"KY",
    "sg:tags":[
        "therapist",
        "massage"
    ],
    "wof:name":"Greenspa",
    "wof:placetype":"venue"
},
  "geometry": {"coordinates":[-85.73420400000001,38.24435],"type":"Point"}
}