{
  "type": "Feature",
  "properties": {
    "addr:full":"525 Harts Ferry Ct Lebanon Junction KY 40150",
    "addr:housenumber":"525",
    "addr:postcode":"40150",
    "addr:street":"Harts Ferry Ct",
    "iso:country":"US",
    "sg:address":"525 Harts Ferry Ct",
    "sg:city":"Lebanon Junction",
    "sg:classifiers":[
        {
            "category":"Building & Trades",
            "subcategory":"Construction",
            "type":"Services"
        }
    ],
    "sg:phone":"+1 502 741 3882",
    "sg:postcode":"40150",
    "sg:province":"KY",
    "sg:tags":[
        "hanging",
        "contractor"
    ],
    "wof:name":"Keith Whalin",
    "wof:placetype":"venue"
},
  "geometry": {"coordinates":[-85.747867,37.852516],"type":"Point"}
}