{
  "type": "Feature",
  "properties": {
    "addr:full":"1847 Mercer Rd Lexington KY 40511",
    "addr:housenumber":"1847",
    "addr:postcode":"40511",
    "addr:street":"Mercer Rd",
    "iso:country":"US",
    "sg:address":"1847 Mercer Rd",
    "sg:city":"Lexington",
    "sg:classifiers":[
        {
            "category":"Wholesale",
            "subcategory":"Stationery",
            "type":"Manufacturing & Wholesale Goods"
        }
    ],
    "sg:phone":"+1 859 259 1477",
    "sg:postcode":"40511",
    "sg:province":"KY",
    "sg:tags":[
        "processing",
        "datum",
        "supply"
    ],
    "wof:name":"Hamilton/Avnet Electronics",
    "wof:placetype":"venue"
},
  "geometry": {"coordinates":[-84.52941800000001,38.07698],"type":"Point"}
}