{
  "type": "Feature",
  "properties": {
    "iso:country":"US",
    "sg:address":"1100 US-27",
    "sg:city":"Cynthiana",
    "sg:classifiers":[
        {
            "category":"Restaurant",
            "type":"Food & Drink"
        }
    ],
    "sg:menulink":"http://www.allmenus.com/ky/cynthiana/214747-ponderosa-steak-house/menu/",
    "sg:phone":"+1 859 234 6881",
    "sg:postcode":"41031",
    "sg:province":"KY",
    "sg:tags":[
        "american",
        "steakhouse"
    ],
    "wof:name":"Ponderosa Steak House",
    "wof:placetype":"venue"
},
  "geometry": {"coordinates":[-84.312742,38.376378],"type":"Point"}
}