{
  "type": "Feature",
  "properties": {
    "addr:full":"4350 Robards Ln Louisville KY 40218",
    "addr:housenumber":"4350",
    "addr:postcode":"40218",
    "addr:street":"Robards Ln",
    "iso:country":"US",
    "sg:address":"4350 Robards Ln",
    "sg:city":"Louisville",
    "sg:classifiers":[
        {
            "category":"Manufacturing",
            "subcategory":"Tools & Machinery",
            "type":"Manufacturing & Wholesale Goods"
        }
    ],
    "sg:phone":"+1 502 451 8319",
    "sg:postcode":"40218",
    "sg:province":"KY",
    "sg:tags":[
        "equipment",
        "electric"
    ],
    "wof:name":"GE Co",
    "wof:placetype":"venue"
},
  "geometry": {"coordinates":[-85.691959,38.197419],"type":"Point"}
}