{
  "type": "Feature",
  "properties": {
    "iso:country":"US",
    "sg:address":"2560 Dell Rd",
    "sg:city":"Louisville",
    "sg:classifiers":[
        {
            "category":"Professional",
            "subcategory":"Management & Consulting",
            "type":"Services"
        }
    ],
    "sg:phone":"+1 502 456 2125",
    "sg:postcode":"40205",
    "sg:province":"KY",
    "sg:tags":[
        "consultant",
        "business"
    ],
    "wof:name":"Stroud Inc",
    "wof:placetype":"venue"
},
  "geometry": {"coordinates":[-85.677437,38.228535],"type":"Point"}
}