{
  "type": "Feature",
  "properties": {
    "iso:country":"US",
    "sg:address":"1101 E Burnett Ave",
    "sg:city":"Louisville",
    "sg:classifiers":[
        {
            "category":"Restaurant",
            "type":"Food & Drink"
        }
    ],
    "sg:phone":"+1 502 637 9515",
    "sg:postcode":"40217",
    "sg:province":"KY",
    "wof:name":"Check's Cafe",
    "wof:placetype":"venue"
},
  "geometry": {"coordinates":[-85.737505,38.221722],"type":"Point"}
}