{
  "type": "Feature",
  "properties": {
    "iso:country":"US",
    "sg:address":"212 Cundiff Sq",
    "sg:city":"Somerset",
    "sg:classifiers":[
        {
            "category":"Organizations",
            "subcategory":"Religious Organization",
            "type":"Services"
        }
    ],
    "sg:phone":"+1 606 678 8153",
    "sg:postcode":"42501",
    "sg:province":"KY",
    "sg:tags":[
        "church"
    ],
    "wof:name":"Pulaski Emergency Relief Ctr",
    "wof:placetype":"venue"
},
  "geometry": {"coordinates":[-84.606056,37.088617],"type":"Point"}
}