{
  "type": "Feature",
  "properties": {
    "iso:country":"US",
    "sg:address":"4236 Old Scottsville Rd",
    "sg:city":"Alvaton",
    "sg:classifiers":[
        {
            "category":"Professional",
            "type":"Services"
        }
    ],
    "sg:phone":"+1 270 782 9043",
    "sg:postcode":"42122",
    "sg:province":"KY",
    "sg:tags":[
        "establishment"
    ],
    "wof:name":"Animals & Accessories",
    "wof:placetype":"venue"
},
  "geometry": {"coordinates":[-86.36909199999999,36.905212],"type":"Point"}
}