{
  "type": "Feature",
  "properties": {
    "addr:full":"64 Fairmount Rd Brandenburg KY 40108",
    "addr:housenumber":"64",
    "addr:postcode":"40108",
    "addr:street":"Fairmount Rd",
    "iso:country":"US",
    "sg:address":"64 Fairmount Rd",
    "sg:city":"Brandenburg",
    "sg:classifiers":[
        {
            "category":"Building & Trades",
            "subcategory":"Cleaning & Sanitation",
            "type":"Services"
        }
    ],
    "sg:phone":"+1 270 422 5258",
    "sg:postcode":"40108",
    "sg:province":"KY",
    "sg:tags":[
        "janitor"
    ],
    "wof:name":"Cleaning By Robin",
    "wof:placetype":"venue"
},
  "geometry": {"coordinates":[-86.266408,37.964523],"type":"Point"}
}