{
  "type": "Feature",
  "properties": {
    "iso:country":"US",
    "sg:address":"10400 Linn Station Rd",
    "sg:city":"Louisville",
    "sg:classifiers":[
        {
            "category":"Professional",
            "subcategory":"Lawyer & Legal Services",
            "type":"Services"
        }
    ],
    "sg:phone":"+1 502 540 5700",
    "sg:postcode":"40223",
    "sg:province":"KY",
    "sg:tags":[
        "attorney"
    ],
    "wof:name":"Thomas Swicegood",
    "wof:placetype":"venue"
},
  "geometry": {"coordinates":[-85.563766,38.224448],"type":"Point"}
}