{
  "type": "Feature",
  "properties": {
    "iso:country":"US",
    "sg:address":"4400 Ole Brickyard Cir",
    "sg:city":"Louisville",
    "sg:classifiers":[
        {
            "category":"Health Services",
            "subcategory":"Clinic",
            "type":"Services"
        }
    ],
    "sg:phone":"+1 502 459 3887",
    "sg:postcode":"40218",
    "sg:province":"KY",
    "sg:tags":[
        "home"
    ],
    "sg:website":"www.drpharmacare.com",
    "wof:name":"D & R Pharmaceutical Svc Inc",
    "wof:placetype":"venue"
},
  "geometry": {"coordinates":[-85.682169,38.191447],"type":"Point"}
}