{
  "type": "Feature",
  "properties": {
    "iso:country":"US",
    "sg:address":"4807 Outer Loop",
    "sg:city":"Louisville",
    "sg:classifiers":[
        {
            "category":"Restaurant",
            "type":"Food & Drink"
        }
    ],
    "sg:phone":"+1 502 969 2230",
    "sg:postcode":"40219",
    "sg:province":"KY",
    "wof:name":"Teriyaki Express BBQ",
    "wof:placetype":"venue"
},
  "geometry": {"coordinates":[-85.671447,38.137926],"type":"Point"}
}