{
  "type": "Feature",
  "properties": {
    "iso:country":"US",
    "sg:address":"618 Woodduck Ln",
    "sg:city":"Georgetown",
    "sg:classifiers":[
        {
            "category":"Real Estate",
            "subcategory":"Real Estate Services",
            "type":"Services"
        },
        {
            "category":"Real Estate",
            "subcategory":"Real Estate Agent",
            "type":"Services"
        }
    ],
    "sg:phone":"+1 502 863 6216",
    "sg:postcode":"40324",
    "sg:province":"KY",
    "sg:tags":[
        "buyer",
        "broker"
    ],
    "sg:website":"http://www.frankmasonrealtor.com",
    "wof:name":"Frank Mason Realtor Inc",
    "wof:placetype":"venue"
},
  "geometry": {"coordinates":[-84.575154,38.324335],"type":"Point"}
}