{
  "type": "Feature",
  "properties": {
    "iso:country":"US",
    "sg:address":"928 Grey Stable Ln",
    "sg:city":"Newport",
    "sg:classifiers":[
        {
            "category":"Professional",
            "subcategory":"Business Services",
            "type":"Services"
        }
    ],
    "sg:phone":"+1 859 781 2760",
    "sg:postcode":"41076",
    "sg:province":"KY",
    "wof:name":"Aj General Contracting",
    "wof:placetype":"venue"
},
  "geometry": {"coordinates":[-84.457857,39.027049],"type":"Point"}
}