{
  "type": "Feature",
  "properties": {
    "iso:country":"US",
    "sg:address":"1315 W 2nd St",
    "sg:city":"Owensboro",
    "sg:classifiers":[
        {
            "category":"Restaurant",
            "type":"Food & Drink"
        }
    ],
    "sg:phone":"+1 270 685 1020",
    "sg:postcode":"42301",
    "sg:province":"KY",
    "wof:name":"Cadillac Restaurant & Grecian",
    "wof:placetype":"venue"
},
  "geometry": {"coordinates":[-87.126334,37.77413],"type":"Point"}
}