{
  "type": "Feature",
  "properties": {
    "addr:full":"924 Greenup Ave Ashland KY 41101",
    "addr:housenumber":"924",
    "addr:postcode":"41101",
    "addr:street":"Greenup Ave",
    "iso:country":"US",
    "sg:address":"924 Greenup Ave",
    "sg:city":"Ashland",
    "sg:classifiers":[
        {
            "category":"Organizations",
            "subcategory":"Professional Association",
            "type":"Services"
        }
    ],
    "sg:phone":"+1 606 325 2544",
    "sg:postcode":"41101",
    "sg:province":"KY",
    "wof:name":"Plumbers & Steam Fitters",
    "wof:placetype":"venue"
},
  "geometry": {"coordinates":[-82.64585099999999,38.483035],"type":"Point"}
}