{
  "type": "Feature",
  "properties": {
    "iso:country":"US",
    "sg:address":"7811 Short Station Rd",
    "sg:city":"Philpot",
    "sg:classifiers":[
        {
            "category":"Building & Trades",
            "subcategory":"Plumbing",
            "type":"Services"
        }
    ],
    "sg:phone":"+1 270 233 4287",
    "sg:postcode":"42366",
    "sg:province":"KY",
    "sg:tags":[
        "plumbing",
        "contractor"
    ],
    "wof:name":"Clark & Mills Plumbing Inc",
    "wof:placetype":"venue"
},
  "geometry": {"coordinates":[-86.916709,37.735452],"type":"Point"}
}