{
  "type": "Feature",
  "properties": {
    "iso:country":"US",
    "sg:address":"207 W Lexington Ave",
    "sg:city":"Danville",
    "sg:classifiers":[
        {
            "category":"Health Services",
            "subcategory":"Doctor",
            "type":"Services"
        }
    ],
    "sg:phone":"+1 859 236 1951",
    "sg:postcode":"40422",
    "sg:province":"KY",
    "sg:tags":[
        "physician",
        "surgeon"
    ],
    "wof:name":"Larry Scott MD",
    "wof:placetype":"venue"
},
  "geometry": {"coordinates":[-84.771083,37.648973],"type":"Point"}
}