{
  "type": "Feature",
  "properties": {
    "iso:country":"US",
    "sg:address":"7904 Hall Farm Dr",
    "sg:city":"Louisville",
    "sg:classifiers":[
        {
            "category":"Retail",
            "subcategory":"Laundry & Dry Cleaning",
            "type":"Services"
        }
    ],
    "sg:phone":"+1 502 231 5807",
    "sg:postcode":"40291",
    "sg:province":"KY",
    "sg:tags":[
        "cleaner",
        "rug",
        "carpet"
    ],
    "wof:name":"Spec Chem",
    "wof:placetype":"venue"
},
  "geometry": {"coordinates":[-85.56371300000001,38.128811],"type":"Point"}
}