{
  "type": "Feature",
  "properties": {
    "addr:full":"12625 Shelbyville Rd Louisville KY 40243",
    "addr:housenumber":"12625",
    "addr:postcode":"40243",
    "addr:street":"Shelbyville Rd",
    "iso:country":"US",
    "sg:address":"12625 Shelbyville Rd",
    "sg:city":"Louisville",
    "sg:classifiers":[
        {
            "category":"Shopping",
            "subcategory":"Jewelry",
            "type":"Retail Goods"
        }
    ],
    "sg:phone":"+1 502 253 9111",
    "sg:postcode":"40243",
    "sg:province":"KY",
    "sg:tags":[
        "jeweler"
    ],
    "wof:name":"Diamond Mine",
    "wof:placetype":"venue"
},
  "geometry": {"coordinates":[-85.523686,38.245237],"type":"Point"}
}