{
  "type": "Feature",
  "properties": {
    "iso:country":"US",
    "sg:address":"1201 Birch St",
    "sg:city":"Benton",
    "sg:classifiers":[
        {
            "category":"Health Services",
            "subcategory":"Chiropractor",
            "type":"Services"
        }
    ],
    "sg:phone":"+1 270 527 5898",
    "sg:postcode":"42025",
    "sg:province":"KY",
    "wof:name":"Pitman Chiropractic Ctr",
    "wof:placetype":"venue"
},
  "geometry": {"coordinates":[-88.347303,36.857147],"type":"Point"}
}