{
  "type": "Feature",
  "properties": {
    "iso:country":"US",
    "sg:address":"4316 Gaudet Rd",
    "sg:city":"Louisville",
    "sg:classifiers":[
        {
            "category":"Building & Trades",
            "subcategory":"Cleaning & Sanitation",
            "type":"Services"
        }
    ],
    "sg:phone":"+1 502 267 2322",
    "sg:postcode":"40299",
    "sg:province":"KY",
    "sg:tags":[
        "maintenance"
    ],
    "wof:name":"Blue Chip Janitorial Services",
    "wof:placetype":"venue"
},
  "geometry": {"coordinates":[-85.56438900000001,38.181683],"type":"Point"}
}