{
  "type": "Feature",
  "properties": {
    "iso:country":"US",
    "sg:address":"8014 Blue Lick Rd",
    "sg:city":"Louisville",
    "sg:classifiers":[
        {
            "category":"Personal",
            "subcategory":"Beauty Salon",
            "type":"Services"
        }
    ],
    "sg:phone":"+1 502 969 7634",
    "sg:postcode":"40219",
    "sg:province":"KY",
    "wof:name":"A Trusting Touch Hair Salon",
    "wof:placetype":"venue"
},
  "geometry": {"coordinates":[-85.684286,38.13361],"type":"Point"}
}