{
  "type": "Feature",
  "properties": {
    "addr:full":"9819 Winged Foot Dr Louisville KY 40223",
    "addr:housenumber":"9819",
    "addr:postcode":"40223",
    "addr:street":"Winged Foot Dr",
    "iso:country":"US",
    "sg:address":"9819 Winged Foot Dr",
    "sg:city":"Louisville",
    "sg:classifiers":[
        {
            "category":"Shopping",
            "subcategory":"Florist",
            "type":"Retail Goods"
        }
    ],
    "sg:phone":"+1 502 339 1024",
    "sg:postcode":"40223",
    "sg:province":"KY",
    "wof:name":"Kabloom",
    "wof:placetype":"venue"
},
  "geometry": {"coordinates":[-85.574258,38.256069],"type":"Point"}
}