{
  "type": "Feature",
  "properties": {
    "addr:full":"200 Schollsville Rd Winchester KY 40391",
    "addr:housenumber":"200",
    "addr:postcode":"40391",
    "addr:street":"Schollsville Rd",
    "iso:country":"US",
    "sg:address":"200 Schollsville Rd",
    "sg:city":"Winchester",
    "sg:classifiers":[
        {
            "category":"Communications",
            "type":"Services"
        }
    ],
    "sg:phone":"+1 859 842 3353",
    "sg:postcode":"40391",
    "sg:province":"KY",
    "wof:name":"New South Communications",
    "wof:placetype":"venue"
},
  "geometry": {"coordinates":[-84.02055900000001,37.988447],"type":"Point"}
}