{
  "type": "Feature",
  "properties": {
    "addr:full":"6904 Creston Dr Louisville KY 40258",
    "addr:housenumber":"6904",
    "addr:postcode":"40258",
    "addr:street":"Creston Dr",
    "iso:country":"US",
    "sg:address":"6904 Creston Dr",
    "sg:city":"Louisville",
    "sg:classifiers":[
        {
            "category":"Personal",
            "subcategory":"Beauty Salon",
            "type":"Services"
        }
    ],
    "sg:phone":"+1 502 937 3877",
    "sg:postcode":"40258",
    "sg:province":"KY",
    "wof:name":"First Impression Hair Studio",
    "wof:placetype":"venue"
},
  "geometry": {"coordinates":[-85.882898,38.143364],"type":"Point"}
}