{
  "type": "Feature",
  "properties": {
    "iso:country":"US",
    "sg:address":"1350 Westen St",
    "sg:city":"Bowling Green",
    "sg:classifiers":[
        {
            "category":"Shopping",
            "subcategory":"Bicycles & Sporting Goods",
            "type":"Retail Goods"
        }
    ],
    "sg:phone":"+1 270 842 6725",
    "sg:postcode":"42104",
    "sg:province":"KY",
    "sg:tags":[
        "apparel",
        "bowling",
        "accessory"
    ],
    "wof:name":"Bowling Green Business Forms",
    "wof:placetype":"venue"
},
  "geometry": {"coordinates":[-86.440377,36.968173],"type":"Point"}
}