{
  "type": "Feature",
  "properties": {
    "iso:country":"US",
    "sg:address":"4125 Springwater Dr",
    "sg:city":"Lexington",
    "sg:classifiers":[
        {
            "category":"Building & Trades",
            "subcategory":"Landscaping Services",
            "type":"Services"
        }
    ],
    "sg:phone":"+1 859 272 3609",
    "sg:postcode":"40515",
    "sg:province":"KY",
    "wof:name":"Land Art Ltd",
    "wof:placetype":"venue"
},
  "geometry": {"coordinates":[-84.505546,37.964933],"type":"Point"}
}