{
  "type": "Feature",
  "properties": {
    "addr:full":"10862 State Hwy 1428 Martin KY 41649",
    "addr:housenumber":"10862",
    "addr:postcode":"41649",
    "addr:street":"State Hwy 1428 Martin",
    "iso:country":"US",
    "sg:address":"10862 State Hwy 1428",
    "sg:city":"Martin",
    "sg:classifiers":[
        {
            "category":"Government",
            "subcategory":"Fire Station",
            "type":"Public Place"
        }
    ],
    "sg:phone":"+1 606 285 3162",
    "sg:postcode":"41649",
    "sg:province":"KY",
    "sg:tags":[
        "department"
    ],
    "wof:name":"Martin City Fire Dept",
    "wof:placetype":"venue"
},
  "geometry": {"coordinates":[-82.749419,37.57974],"type":"Point"}
}