{
  "type": "Feature",
  "properties": {
    "iso:country":"US",
    "sg:address":"3454 New Hartford Rd",
    "sg:city":"Owensboro",
    "sg:phone":"+1 270 729 9786",
    "sg:postcode":"42303",
    "sg:province":"KY",
    "sg:tags":[
        "farm",
        "corn",
        "soybean"
    ],
    "wof:name":"Stephen Wink",
    "wof:placetype":"venue"
},
  "geometry": {"coordinates":[-87.09144000000001,37.736928],"type":"Point"}
}