{
  "type": "Feature",
  "properties": {
    "iso:country":"US",
    "sg:address":"400 Etter Dr",
    "sg:city":"Nicholasville",
    "sg:classifiers":[
        {
            "category":"Building & Trades",
            "subcategory":"Construction",
            "type":"Services"
        }
    ],
    "sg:phone":"+1 859 885 5020",
    "sg:postcode":"40356",
    "sg:province":"KY",
    "sg:tags":[
        "builder",
        "patio",
        "deck"
    ],
    "wof:name":"Deck Medic",
    "wof:placetype":"venue"
},
  "geometry": {"coordinates":[-84.58952600000001,37.888728],"type":"Point"}
}