{
  "type": "Feature",
  "properties": {
    "addr:full":"1221 Bardstown Rd Louisville KY 40204",
    "addr:housenumber":"1221",
    "addr:postcode":"40204",
    "addr:street":"Bardstown Rd",
    "iso:country":"US",
    "sg:address":"1221 Bardstown Rd",
    "sg:city":"Louisville",
    "sg:classifiers":[
        {
            "category":"Health Services",
            "subcategory":"Doctor",
            "type":"Services"
        }
    ],
    "sg:phone":"+1 502 452 1877",
    "sg:postcode":"40204",
    "sg:province":"KY",
    "sg:tags":[
        "dentist"
    ],
    "wof:name":"Gentle Dental",
    "wof:placetype":"venue"
},
  "geometry": {"coordinates":[-85.71866199999999,38.23726],"type":"Point"}
}