{
  "type": "Feature",
  "properties": {
    "iso:country":"US",
    "sg:address":"3510 Winchester Ave",
    "sg:city":"Ashland",
    "sg:classifiers":[
        {
            "category":"Retail",
            "subcategory":"Auto Repair",
            "type":"Services"
        }
    ],
    "sg:phone":"+1 606 325 9954",
    "sg:postcode":"41101",
    "sg:province":"KY",
    "sg:tags":[
        "automobile",
        "lubrication"
    ],
    "wof:name":"Fast Change Lube & Oil Inc",
    "wof:placetype":"venue"
},
  "geometry": {"coordinates":[-82.617204,38.464687],"type":"Point"}
}