{
  "type": "Feature",
  "properties": {
    "iso:country":"US",
    "sg:address":"118 Court St",
    "sg:city":"Greenville",
    "sg:classifiers":[
        {
            "category":"Government",
            "subcategory":"Office",
            "type":"Public Place"
        }
    ],
    "sg:phone":"+1 270 338 3966",
    "sg:postcode":"42345",
    "sg:province":"KY",
    "sg:tags":[
        "city"
    ],
    "wof:name":"Greenville City Clerk",
    "wof:placetype":"venue"
},
  "geometry": {"coordinates":[-87.177514,37.20103],"type":"Point"}
}