{
  "type": "Feature",
  "properties": {
    "iso:country":"US",
    "sg:address":"2490 W Laurel Rd",
    "sg:city":"London",
    "sg:classifiers":[
        {
            "category":"Organizations",
            "subcategory":"Religious Organization",
            "type":"Services"
        }
    ],
    "sg:phone":"+1 606 862 8916",
    "sg:postcode":"40741",
    "sg:province":"KY",
    "sg:tags":[
        "church"
    ],
    "wof:name":"Laurel Chapel Christian Church",
    "wof:placetype":"venue"
},
  "geometry": {"coordinates":[-84.137283,37.076488],"type":"Point"}
}