{
  "type": "Feature",
  "properties": {
    "iso:country":"US",
    "sg:address":"239 Lovern St",
    "sg:city":"Hazard",
    "sg:classifiers":[
        {
            "category":"Government",
            "subcategory":"Office",
            "type":"Public Place"
        }
    ],
    "sg:phone":"+1 606 436 2198",
    "sg:postcode":"41701",
    "sg:province":"KY",
    "sg:tags":[
        "county",
        "program",
        "health"
    ],
    "wof:name":"Health DEPT-Wic",
    "wof:placetype":"venue"
},
  "geometry": {"coordinates":[-83.19490399999999,37.248542],"type":"Point"}
}