{
  "type": "Feature",
  "properties": {
    "addr:full":"201 E Woodford St Lawrenceburg KY 40342",
    "addr:housenumber":"201",
    "addr:postcode":"40342",
    "addr:street":"E Woodford St",
    "iso:country":"US",
    "sg:address":"201 E Woodford St",
    "sg:city":"Lawrenceburg",
    "sg:classifiers":[
        {
            "category":"Professional",
            "subcategory":"Accounting & Tax Preparation",
            "type":"Services"
        }
    ],
    "sg:phone":"+1 502 839 0780",
    "sg:postcode":"40342",
    "sg:province":"KY",
    "sg:tags":[
        "bookkeeping",
        "general"
    ],
    "wof:name":"Taxes & More Inc",
    "wof:placetype":"venue"
},
  "geometry": {"coordinates":[-84.89415,38.037588],"type":"Point"}
}