{
  "type": "Feature",
  "properties": {
    "iso:country":"US",
    "sg:address":"2703 Richmond Rd",
    "sg:city":"Lexington",
    "sg:classifiers":[
        {
            "category":"Retail",
            "subcategory":"Auto Rental",
            "type":"Services"
        }
    ],
    "sg:phone":"+1 859 225 0331",
    "sg:postcode":"40509",
    "sg:province":"KY",
    "sg:tags":[
        "renting",
        "automobile"
    ],
    "wof:name":"Hertz Rent A Car",
    "wof:placetype":"venue"
},
  "geometry": {"coordinates":[-84.452844,38.00813],"type":"Point"}
}