{
  "type": "Feature",
  "properties": {
    "iso:country":"US",
    "sg:address":"9306 New Lagrange Rd",
    "sg:city":"Louisville",
    "sg:classifiers":[
        {
            "category":"Insurance",
            "subcategory":"Insurance Agent",
            "type":"Services"
        }
    ],
    "sg:phone":"+1 502 425 5576",
    "sg:postcode":"40242",
    "sg:province":"KY",
    "wof:name":"John E Delaney Insurance Inc",
    "wof:placetype":"venue"
},
  "geometry": {"coordinates":[-85.583172,38.26805],"type":"Point"}
}