{
  "type": "Feature",
  "properties": {
    "addr:full":"1862 Sparksville Rd Columbia KY 42728",
    "addr:housenumber":"1862",
    "addr:postcode":"42728",
    "addr:street":"Sparksville Rd",
    "iso:country":"US",
    "sg:address":"1862 Sparksville Rd",
    "sg:city":"Columbia",
    "sg:classifiers":[
        {
            "category":"Wholesale",
            "subcategory":"Non-durable Goods",
            "type":"Manufacturing & Wholesale Goods"
        }
    ],
    "sg:phone":"+1 270 378 6810",
    "sg:postcode":"42728",
    "sg:province":"KY",
    "wof:name":"Value Marketing",
    "wof:placetype":"venue"
},
  "geometry": {"coordinates":[-85.37145599999999,37.010649],"type":"Point"}
}