{
  "type": "Feature",
  "properties": {
    "addr:full":"221 S 12th St Murray KY 42071",
    "addr:housenumber":"221",
    "addr:postcode":"42071",
    "addr:street":"S 12Th St",
    "iso:country":"US",
    "sg:address":"221 S 12th St",
    "sg:city":"Murray",
    "sg:classifiers":[
        {
            "category":"Autos & Motor Vehicles",
            "subcategory":"Auto Supplies",
            "type":"Retail Goods"
        }
    ],
    "sg:phone":"+1 270 753 8971",
    "sg:postcode":"42071",
    "sg:province":"KY",
    "sg:tags":[
        "automobile",
        "parts"
    ],
    "wof:name":"Autozone",
    "wof:placetype":"venue"
},
  "geometry": {"coordinates":[-88.31514,36.606833],"type":"Point"}
}