{
  "type": "Feature",
  "properties": {
    "iso:country":"US",
    "sg:address":"6805 Alexandria Pike",
    "sg:city":"Alexandria",
    "sg:classifiers":[
        {
            "category":"Shopping",
            "subcategory":"Shoes",
            "type":"Retail Goods"
        }
    ],
    "sg:phone":"+1 859 635 7371",
    "sg:postcode":"41001",
    "sg:province":"KY",
    "sg:tags":[
        "store"
    ],
    "wof:name":"Payless Shoe Source",
    "wof:placetype":"venue"
},
  "geometry": {"coordinates":[-84.401901,38.985001],"type":"Point"}
}