{
  "type": "Feature",
  "properties": {
    "iso:country":"US",
    "sg:address":"14893 Cool Springs Blvd",
    "sg:city":"Union",
    "sg:classifiers":[
        {
            "category":"Professional",
            "type":"Services"
        }
    ],
    "sg:phone":"+1 859 384 1829",
    "sg:postcode":"41091",
    "sg:province":"KY",
    "sg:tags":[
        "establishment"
    ],
    "wof:name":"Sugarbay Daylilies",
    "wof:placetype":"venue"
},
  "geometry": {"coordinates":[-84.67222,38.928448],"type":"Point"}
}