{
  "type": "Feature",
  "properties": {
    "iso:country":"US",
    "sg:address":"2405 Pierson Dr",
    "sg:city":"Lexington",
    "sg:classifiers":[
        {
            "category":"Retail",
            "subcategory":"Repair Shop",
            "type":"Services"
        }
    ],
    "sg:phone":"+1 859 312 2961",
    "sg:postcode":"40505",
    "sg:province":"KY",
    "wof:name":"Aline B Jones Cleaning",
    "wof:placetype":"venue"
},
  "geometry": {"coordinates":[-84.45496900000001,38.091252],"type":"Point"}
}