{
  "type": "Feature",
  "properties": {
    "iso:country":"US",
    "sg:address":"216 Main St",
    "sg:city":"Manchester",
    "sg:classifiers":[
        {
            "category":"Government",
            "subcategory":"Police Station",
            "type":"Public Place"
        }
    ],
    "sg:phone":"+1 606 598 3471",
    "sg:postcode":"40962",
    "sg:province":"KY",
    "sg:tags":[
        "sheriff"
    ],
    "wof:name":"Clay County Sheriff's Office",
    "wof:placetype":"venue"
},
  "geometry": {"coordinates":[-83.760746,37.155566],"type":"Point"}
}