{
  "type": "Feature",
  "properties": {
    "iso:country":"US",
    "sg:address":"10231 Peterson Branch Rd",
    "sg:city":"Ashland",
    "sg:classifiers":[
        {
            "category":"Building & Trades",
            "subcategory":"Equipment Rental",
            "type":"Services"
        }
    ],
    "sg:phone":"+1 606 928 5910",
    "sg:postcode":"41102",
    "sg:province":"KY",
    "sg:tags":[
        "contractor"
    ],
    "wof:name":"Bill's Backhoe Rental",
    "wof:placetype":"venue"
},
  "geometry": {"coordinates":[-82.786441,38.395115],"type":"Point"}
}