{
  "type": "Feature",
  "properties": {
    "iso:country":"US",
    "sg:address":"108 Sturgis Rd",
    "sg:city":"Marion",
    "sg:classifiers":[
        {
            "category":"Personal",
            "subcategory":"Beauty Salon",
            "type":"Services"
        }
    ],
    "sg:phone":"+1 270 965 2380",
    "sg:postcode":"42064",
    "sg:province":"KY",
    "wof:name":"Professional Touch",
    "wof:placetype":"venue"
},
  "geometry": {"coordinates":[-88.07355,37.341769],"type":"Point"}
}