{
  "type": "Feature",
  "properties": {
    "iso:country":"US",
    "sg:address":"526 Frederica St",
    "sg:city":"Owensboro",
    "sg:classifiers":[
        {
            "category":"Banks & Credit Unions",
            "subcategory":"Investment Brokerage",
            "type":"Services"
        },
        {
            "category":"Professional",
            "subcategory":"Management & Consulting",
            "type":"Services"
        }
    ],
    "sg:phone":"+1 270 691 0470",
    "sg:postcode":"42301",
    "sg:province":"KY",
    "sg:tags":[
        "consultant",
        "planning",
        "financial"
    ],
    "wof:name":"Nina M Wyatt & Associates LLC",
    "wof:placetype":"venue"
},
  "geometry": {"coordinates":[-87.11318799999999,37.77003],"type":"Point"}
}