{
  "type": "Feature",
  "properties": {
    "iso:country":"US",
    "sg:address":"1614 N Bend Rd",
    "sg:city":"Hebron",
    "sg:classifiers":[
        {
            "category":"Professional",
            "subcategory":"Business Services",
            "type":"Services"
        }
    ],
    "sg:phone":"+1 859 689 2389",
    "sg:postcode":"41048",
    "sg:province":"KY",
    "sg:tags":[
        "fund",
        "promotion",
        "raising"
    ],
    "wof:name":"Promotions By Design Inc",
    "wof:placetype":"venue"
},
  "geometry": {"coordinates":[-84.71508,39.09756],"type":"Point"}
}