{
  "type": "Feature",
  "properties": {
    "addr:full":"3654 Frames Branch Rd Clay City KY 40312",
    "addr:housenumber":"3654",
    "addr:postcode":"40312",
    "addr:street":"Frames Branch Rd",
    "iso:country":"US",
    "sg:address":"3654 Frames Branch Rd",
    "sg:city":"Clay City",
    "sg:classifiers":[
        {
            "category":"Building & Trades",
            "subcategory":"Construction",
            "type":"Services"
        }
    ],
    "sg:phone":"+1 606 663 2055",
    "sg:postcode":"40312",
    "sg:province":"KY",
    "sg:tags":[
        "masonry",
        "contractor"
    ],
    "wof:name":"David Morton Inc",
    "wof:placetype":"venue"
},
  "geometry": {"coordinates":[-83.94465700000001,37.810523],"type":"Point"}
}