{
  "type": "Feature",
  "properties": {
    "iso:country":"US",
    "sg:address":"4801 Jolynn Wolf Way",
    "sg:city":"Fisherville",
    "sg:classifiers":[
        {
            "category":"Professional",
            "subcategory":"Management & Consulting",
            "type":"Services"
        }
    ],
    "sg:phone":"+1 502 266 0976",
    "sg:postcode":"40023",
    "sg:province":"KY",
    "sg:tags":[
        "selling",
        "establishment",
        "direct"
    ],
    "wof:name":"Mary Lynn Kempf",
    "wof:placetype":"venue"
},
  "geometry": {"coordinates":[-85.461156,38.166236],"type":"Point"}
}