{
  "type": "Feature",
  "properties": {
    "addr:full":"4613 Stanford Rd Danville KY 40422",
    "addr:housenumber":"4613",
    "addr:postcode":"40422",
    "addr:street":"Stanford Rd",
    "iso:country":"US",
    "sg:address":"4613 Stanford Rd",
    "sg:city":"Danville",
    "sg:classifiers":[
        {
            "category":"Professional",
            "subcategory":"Accounting & Tax Preparation",
            "type":"Services"
        }
    ],
    "sg:phone":"+1 859 236 8196",
    "sg:postcode":"40422",
    "sg:province":"KY",
    "sg:tags":[
        "accountant"
    ],
    "wof:name":"Scotty J Vanderpool",
    "wof:placetype":"venue"
},
  "geometry": {"coordinates":[-84.72675099999999,37.59488],"type":"Point"}
}