{
  "type": "Feature",
  "properties": {
    "addr:full":"198 Industry Pkwy Nicholasville KY 40356",
    "addr:housenumber":"198",
    "addr:postcode":"40356",
    "addr:street":"Industry Pkwy",
    "iso:country":"US",
    "sg:address":"198 Industry Pkwy",
    "sg:city":"Nicholasville",
    "sg:classifiers":[
        {
            "category":"Autos & Motor Vehicles",
            "subcategory":"Automobile Sales",
            "type":"Retail Goods"
        }
    ],
    "sg:phone":"+1 859 887 2521",
    "sg:postcode":"40356",
    "sg:province":"KY",
    "sg:tags":[
        "car",
        "dealer"
    ],
    "wof:name":"Luxury Motors",
    "wof:placetype":"venue"
},
  "geometry": {"coordinates":[-84.54357299999999,37.940182],"type":"Point"}
}