{
  "type": "Feature",
  "properties": {
    "iso:country":"US",
    "sg:address":"89 Marrowbone St",
    "sg:city":"Elkhorn City",
    "sg:classifiers":[
        {
            "category":"Organizations",
            "subcategory":"Religious Organization",
            "type":"Services"
        }
    ],
    "sg:phone":"+1 606 754 4144",
    "sg:postcode":"41522",
    "sg:province":"KY",
    "sg:tags":[
        "church"
    ],
    "wof:name":"Cornerstone Freewill Bapt Chr",
    "wof:placetype":"venue"
},
  "geometry": {"coordinates":[-82.414025,37.365426],"type":"Point"}
}