{
  "type": "Feature",
  "properties": {
    "iso:country":"US",
    "sg:address":"108 C C Lowry Dr",
    "sg:city":"Murray",
    "sg:classifiers":[
        {
            "category":"Home & Garden",
            "subcategory":"Building Materials",
            "type":"Retail Goods"
        }
    ],
    "sg:phone":"+1 270 753 3355",
    "sg:postcode":"42071",
    "sg:province":"KY",
    "sg:tags":[
        "mixed",
        "concrete"
    ],
    "wof:name":"Federal Materials Co",
    "wof:placetype":"venue"
},
  "geometry": {"coordinates":[-88.298903,36.623454],"type":"Point"}
}