{
  "type": "Feature",
  "properties": {
    "iso:country":"US",
    "sg:address":"416 W Jefferson St",
    "sg:city":"Louisville",
    "sg:classifiers":[
        {
            "category":"Retail",
            "subcategory":"Repair Shop",
            "type":"Services"
        },
        {
            "category":"Communications",
            "type":"Services"
        },
        {
            "category":"Communications",
            "subcategory":"Television Station",
            "type":"Services"
        }
    ],
    "sg:phone":"+1 502 778 4999",
    "sg:postcode":"40202",
    "sg:province":"KY",
    "sg:tags":[
        "satellite",
        "systems-repair",
        "cable",
        "tv",
        "system",
        "equipment"
    ],
    "sg:website":"http://www.directdishsatellite.tv",
    "wof:name":"A Direct Dish Satellite Tv",
    "wof:placetype":"venue"
},
  "geometry": {"coordinates":[-85.75726299999999,38.253885],"type":"Point"}
}