{
  "type": "Feature",
  "properties": {
    "iso:country":"US",
    "sg:address":"506 West St",
    "sg:city":"Franklin",
    "sg:classifiers":[
        {
            "category":"Organizations",
            "subcategory":"Religious Organization",
            "type":"Services"
        }
    ],
    "sg:phone":"+1 270 586 1746",
    "sg:postcode":"42134",
    "sg:province":"KY",
    "sg:tags":[
        "church"
    ],
    "wof:name":"Mt Zion Apostolic Church Inc",
    "wof:placetype":"venue"
},
  "geometry": {"coordinates":[-86.588697,36.727182],"type":"Point"}
}