{
  "type": "Feature",
  "properties": {
    "iso:country":"US",
    "sg:address":"9003 Dorjean Dr",
    "sg:city":"Louisville",
    "sg:classifiers":[
        {
            "category":"Wholesale",
            "subcategory":"Vending Machines",
            "type":"Manufacturing & Wholesale Goods"
        }
    ],
    "sg:phone":"+1 502 933 3416",
    "sg:postcode":"40272",
    "sg:province":"KY",
    "sg:tags":[
        "operator"
    ],
    "wof:name":"Dave Rgalinski Distributorship",
    "wof:placetype":"venue"
},
  "geometry": {"coordinates":[-85.84449499999999,38.125016],"type":"Point"}
}