{
  "type": "Feature",
  "properties": {
    "iso:country":"US",
    "sg:address":"240 Cherrywood Dr",
    "sg:city":"Covington",
    "sg:classifiers":[
        {
            "category":"Professional",
            "subcategory":"Management & Consulting",
            "type":"Services"
        }
    ],
    "sg:phone":"+1 859 344 1322",
    "sg:postcode":"41011",
    "sg:province":"KY",
    "wof:name":"Thomas A Koenig LLC",
    "wof:placetype":"venue"
},
  "geometry": {"coordinates":[-84.54730000000001,39.061938],"type":"Point"}
}