{
  "type": "Feature",
  "properties": {
    "addr:full":"8410 US Highway 42 Florence KY 41042",
    "addr:housenumber":"8410",
    "addr:postcode":"41042",
    "addr:street":"Us Highway 42",
    "iso:country":"US",
    "sg:address":"8410 US Highway 42",
    "sg:city":"Florence",
    "sg:classifiers":[
        {
            "category":"Building & Trades",
            "subcategory":"Pest Control",
            "type":"Services"
        }
    ],
    "sg:phone":"+1 812 537 2037",
    "sg:postcode":"41042",
    "sg:province":"KY",
    "sg:website":"www.orkin.com",
    "wof:name":"Orkin Exterminating Co Inc",
    "wof:placetype":"venue"
},
  "geometry": {"coordinates":[-84.65540300000001,38.978802],"type":"Point"}
}