{
  "type": "Feature",
  "properties": {
    "addr:full":"755 W Broadway St Lawrenceburg KY 40342",
    "addr:housenumber":"755",
    "addr:postcode":"40342",
    "addr:street":"W Broadway St",
    "iso:country":"US",
    "sg:address":"755 W Broadway St",
    "sg:city":"Lawrenceburg",
    "sg:classifiers":[
        {
            "category":"Shopping",
            "subcategory":"Discount & Variety Stores",
            "type":"Retail Goods"
        }
    ],
    "sg:phone":"+1 502 839 7166",
    "sg:postcode":"40342",
    "sg:province":"KY",
    "wof:name":"Dollar Eagle",
    "wof:placetype":"venue"
},
  "geometry": {"coordinates":[-84.908433,38.021428],"type":"Point"}
}