{
  "type": "Feature",
  "properties": {
    "iso:country":"US",
    "sg:address":"5152 State Hwy 384",
    "sg:city":"Mayfield",
    "sg:classifiers":[
        {
            "category":"Organizations",
            "subcategory":"Religious Organization",
            "type":"Services"
        }
    ],
    "sg:phone":"+1 270 623 8890",
    "sg:postcode":"42066",
    "sg:province":"KY",
    "wof:name":"Unity Baptist Church Parsonage",
    "wof:placetype":"venue"
},
  "geometry": {"coordinates":[-88.78385900000001,36.732985],"type":"Point"}
}