{
  "type": "Feature",
  "properties": {
    "iso:country":"US",
    "sg:address":"8587 Railroad Dr",
    "sg:city":"Taylor Mill",
    "sg:classifiers":[
        {
            "category":"Manufacturing",
            "subcategory":"Motor Vehicles & Parts",
            "type":"Manufacturing & Wholesale Goods"
        }
    ],
    "sg:phone":"+1 859 291 5564",
    "sg:postcode":"41015",
    "sg:province":"KY",
    "sg:tags":[
        "equipment",
        "railroad"
    ],
    "sg:website":"www.progressrail.com",
    "wof:name":"Progress Rail Svc",
    "wof:placetype":"venue"
},
  "geometry": {"coordinates":[-84.462834,38.99648],"type":"Point"}
}