{
  "type": "Feature",
  "properties": {
    "addr:full":"1151 Donldsn Hwy Florence KY 41042",
    "addr:housenumber":"1151",
    "addr:postcode":"41042",
    "addr:street":"Donldsn Hwy",
    "iso:country":"US",
    "sg:address":"1151 Donldsn Hwy",
    "sg:city":"Florence",
    "sg:classifiers":[
        {
            "category":"Education",
            "subcategory":"School",
            "type":"Public Place"
        }
    ],
    "sg:phone":"+1 859 371 8568",
    "sg:postcode":"41042",
    "sg:province":"KY",
    "wof:name":"Passionists Nuns",
    "wof:placetype":"venue"
},
  "geometry": {"coordinates":[-84.65389999999999,38.9879],"type":"Point"}
}