{
  "type": "Feature",
  "properties": {
    "iso:country":"US",
    "sg:address":"3308 Chauncey Ave",
    "sg:city":"Louisville",
    "sg:classifiers":[
        {
            "category":"Education",
            "subcategory":"School",
            "type":"Public Place"
        }
    ],
    "sg:phone":"+1 502 778 9684",
    "sg:postcode":"40211",
    "sg:province":"KY",
    "wof:name":"Immaculate Heart Of Mary Schl",
    "wof:placetype":"venue"
},
  "geometry": {"coordinates":[-85.81073499999999,38.231118],"type":"Point"}
}