{
  "type": "Feature",
  "properties": {
    "iso:country":"US",
    "sg:address":"71 1st St",
    "sg:city":"Harold",
    "sg:classifiers":[
        {
            "category":"Retail",
            "subcategory":"Repair Shop",
            "type":"Services"
        }
    ],
    "sg:phone":"+1 606 478 9517",
    "sg:postcode":"41635",
    "sg:province":"KY",
    "sg:tags":[
        "related"
    ],
    "wof:name":"Appalachian Starter Repair",
    "wof:placetype":"venue"
},
  "geometry": {"coordinates":[-82.622637,37.528663],"type":"Point"}
}