{
  "type": "Feature",
  "properties": {
    "iso:country":"US",
    "sg:address":"4981 Jack Hinton Rd",
    "sg:city":"Philpot",
    "sg:classifiers":[
        {
            "category":"Professional",
            "type":"Services"
        }
    ],
    "sg:phone":"+1 270 729 9619",
    "sg:postcode":"42366",
    "sg:province":"KY",
    "sg:tags":[
        "establishment"
    ],
    "wof:name":"Employee Breakroom",
    "wof:placetype":"venue"
},
  "geometry": {"coordinates":[-86.978369,37.734202],"type":"Point"}
}