{
  "type": "Feature",
  "properties": {
    "iso:country":"US",
    "sg:address":"629 N Broadway Rd",
    "sg:city":"Lexington",
    "sg:classifiers":[
        {
            "category":"Professional",
            "subcategory":"Engineering",
            "type":"Services"
        }
    ],
    "sg:phone":"+1 859 259 1173",
    "sg:postcode":"40508",
    "sg:province":"KY",
    "sg:tags":[
        "transportation",
        "engineer"
    ],
    "sg:website":"www.sayreengineering.com",
    "wof:name":"Sayre & Assoc Engineering",
    "wof:placetype":"venue"
},
  "geometry": {"coordinates":[-84.48883499999999,38.056645],"type":"Point"}
}