{
  "type": "Feature",
  "properties": {
    "iso:country":"US",
    "sg:address":"117 N 20th St",
    "sg:city":"Louisville",
    "sg:classifiers":[
        {
            "category":"Building & Trades",
            "subcategory":"Construction",
            "type":"Services"
        }
    ],
    "sg:phone":"+1 502 778 2383",
    "sg:postcode":"40203",
    "sg:province":"KY",
    "sg:tags":[
        "residential"
    ],
    "wof:name":"Broch Enterprises Inc",
    "wof:placetype":"venue"
},
  "geometry": {"coordinates":[-85.782763,38.260898],"type":"Point"}
}