{
  "type": "Feature",
  "properties": {
    "addr:full":"175 Center Dr Georgetown KY 40391",
    "addr:housenumber":"175",
    "addr:postcode":"40391",
    "addr:street":"Center Dr",
    "iso:country":"US",
    "sg:address":"175 Center Dr",
    "sg:city":"Georgetown",
    "sg:classifiers":[
        {
            "category":"Restaurant",
            "type":"Food & Drink"
        }
    ],
    "sg:phone":"+1 502 868 0659",
    "sg:postcode":"40391",
    "sg:province":"KY",
    "sg:website":"www.wafflehouse.com",
    "wof:name":"Waffle House",
    "wof:placetype":"venue"
},
  "geometry": {"coordinates":[-84.152635,37.99676],"type":"Point"}
}