{
  "type": "Feature",
  "properties": {
    "addr:full":"412 Madison Ave Covington KY 41011",
    "addr:housenumber":"412",
    "addr:postcode":"41011",
    "addr:street":"Madison Ave",
    "iso:country":"US",
    "sg:address":"412 Madison Ave",
    "sg:city":"Covington",
    "sg:classifiers":[
        {
            "category":"Insurance",
            "subcategory":"Insurance Agent",
            "type":"Services"
        }
    ],
    "sg:phone":"+1 859 431 1235",
    "sg:postcode":"41011",
    "sg:province":"KY",
    "sg:website":"www.bilzinsurance.com",
    "wof:name":"Bilz Insurance",
    "wof:placetype":"venue"
},
  "geometry": {"coordinates":[-84.510895,39.086852],"type":"Point"}
}