{
  "type": "Feature",
  "properties": {
    "iso:country":"US",
    "sg:address":"207 S 3rd St",
    "sg:city":"Bardstown",
    "sg:classifiers":[
        {
            "category":"Food & Beverages",
            "subcategory":"Specialty",
            "type":"Retail Goods"
        }
    ],
    "sg:phone":"+1 502 348 7441",
    "sg:postcode":"40004",
    "sg:province":"KY",
    "sg:tags":[
        "gourmet",
        "shop"
    ],
    "wof:name":"Kentucky Emporium",
    "wof:placetype":"venue"
},
  "geometry": {"coordinates":[-85.46721700000001,37.807655],"type":"Point"}
}