{
  "type": "Feature",
  "properties": {
    "iso:country":"US",
    "sg:address":"123 Driftwood Dr",
    "sg:city":"Somerset",
    "sg:classifiers":[
        {
            "category":"Building & Trades",
            "subcategory":"Construction",
            "type":"Services"
        }
    ],
    "sg:phone":"+1 606 678 2641",
    "sg:postcode":"42503",
    "sg:province":"KY",
    "sg:tags":[
        "general",
        "contractor"
    ],
    "wof:name":"Power's Home Improvement",
    "wof:placetype":"venue"
},
  "geometry": {"coordinates":[-84.679878,37.074324],"type":"Point"}
}