{
  "type": "Feature",
  "properties": {
    "iso:country":"US",
    "sg:address":"1801 Woodsboro Rd",
    "sg:city":"Crestwood",
    "sg:classifiers":[
        {
            "category":"Wholesale",
            "subcategory":"Electrical",
            "type":"Manufacturing & Wholesale Goods"
        }
    ],
    "sg:phone":"+1 502 241 5944",
    "sg:postcode":"40014",
    "sg:province":"KY",
    "sg:tags":[
        "meter"
    ],
    "wof:name":"Micro Motion Inc",
    "wof:placetype":"venue"
},
  "geometry": {"coordinates":[-85.386382,38.351766],"type":"Point"}
}