{
  "type": "Feature",
  "properties": {
    "iso:country":"US",
    "sg:address":"3700 Lexington Rd",
    "sg:city":"St Matthews",
    "sg:classifiers":[
        {
            "category":"Shopping",
            "subcategory":"Used Merchandise",
            "type":"Retail Goods"
        }
    ],
    "sg:phone":"+1 502 899 5335",
    "sg:postcode":"40207",
    "sg:province":"KY",
    "sg:tags":[
        "antique"
    ],
    "sg:website":"www.tracemayerantiques.com",
    "wof:name":"Trace Mayer Antiques",
    "wof:placetype":"venue"
},
  "geometry": {"coordinates":[-85.659841,38.252061],"type":"Point"}
}