{
  "type": "Feature",
  "properties": {
    "iso:country":"US",
    "sg:address":"1460 Cumberland Falls Hwy",
    "sg:city":"Corbin",
    "sg:classifiers":[
        {
            "category":"Banks & Credit Unions",
            "subcategory":"Bank",
            "type":"Services"
        }
    ],
    "sg:phone":"+1 606 526 9184",
    "sg:postcode":"40701",
    "sg:province":"KY",
    "sg:tags":[
        "loan",
        "real estate"
    ],
    "wof:name":"Absolute Mortgage Solutions",
    "wof:placetype":"venue"
},
  "geometry": {"coordinates":[-84.111013,36.926412],"type":"Point"}
}