{
  "type": "Feature",
  "properties": {
    "addr:full":"3802 Glenwillow Way Louisville KY 40299",
    "addr:housenumber":"3802",
    "addr:postcode":"40299",
    "addr:street":"Glenwillow Way",
    "iso:country":"US",
    "sg:address":"3802 Glenwillow Way",
    "sg:city":"Louisville",
    "sg:classifiers":[
        {
            "category":"Professional",
            "subcategory":"Computer Services",
            "type":"Services"
        }
    ],
    "sg:phone":"+1 502 266 8534",
    "sg:postcode":"40299",
    "sg:province":"KY",
    "sg:tags":[
        "publisher",
        "developer",
        "software"
    ],
    "sg:website":"http://www.pbjetc.com",
    "wof:name":"Pbj",
    "wof:placetype":"venue"
},
  "geometry": {"coordinates":[-85.58255699999999,38.190106],"type":"Point"}
}