{
  "type": "Feature",
  "properties": {
    "iso:country":"US",
    "sg:address":"12706 Dixie Hwy",
    "sg:city":"Valley Station",
    "sg:classifiers":[
        {
            "category":"Shopping",
            "subcategory":"Bicycles & Sporting Goods",
            "type":"Retail Goods"
        }
    ],
    "sg:phone":"+1 502 937 1996",
    "sg:postcode":"40272",
    "sg:province":"KY",
    "sg:tags":[
        "gun",
        "gunsmith"
    ],
    "wof:name":"Biff's Gun World",
    "wof:placetype":"venue"
},
  "geometry": {"coordinates":[-85.88506099999999,38.068807],"type":"Point"}
}