{
  "type": "Feature",
  "properties": {
    "addr:full":"5724 Greensburg Rd Columbia KY 42728",
    "addr:housenumber":"5724",
    "addr:postcode":"42728",
    "addr:street":"Greensburg Rd",
    "iso:country":"US",
    "sg:address":"5724 Greensburg Rd",
    "sg:city":"Columbia",
    "sg:classifiers":[
        {
            "category":"Autos & Motor Vehicles",
            "subcategory":"Automobile Sales",
            "type":"Retail Goods"
        },
        {
            "category":"Autos & Motor Vehicles",
            "subcategory":"Auto Supplies",
            "type":"Retail Goods"
        },
        {
            "category":"Retail",
            "subcategory":"Car Wash",
            "type":"Services"
        }
    ],
    "sg:phone":"+1 270 384 2311",
    "sg:postcode":"42728",
    "sg:province":"KY",
    "sg:tags":[
        "dealers-used",
        "used",
        "cars-wholesale",
        "accessory"
    ],
    "wof:name":"Valleyview Motors",
    "wof:placetype":"venue"
},
  "geometry": {"coordinates":[-85.39317,37.118558],"type":"Point"}
}