{
  "type": "Feature",
  "properties": {
    "addr:full":"8788 Tompkinsville Rd Glasgow KY 42141",
    "addr:housenumber":"8788",
    "addr:postcode":"42141",
    "addr:street":"Tompkinsville Rd",
    "iso:country":"US",
    "sg:address":"8788 Tompkinsville Rd",
    "sg:city":"Glasgow",
    "sg:classifiers":[
        {
            "category":"Education",
            "subcategory":"School",
            "type":"Public Place"
        }
    ],
    "sg:phone":"+1 270 427 2611",
    "sg:postcode":"42141",
    "sg:province":"KY",
    "sg:website":"www.trojan2000.org",
    "wof:name":"Temple Hill School",
    "wof:placetype":"venue"
},
  "geometry": {"coordinates":[-85.84732700000001,36.886439],"type":"Point"}
}