{
  "type": "Feature",
  "properties": {
    "iso:country":"US",
    "sg:address":"150 Liters Ln",
    "sg:city":"Paris",
    "sg:classifiers":[
        {
            "category":"Wholesale",
            "subcategory":"Meat",
            "type":"Manufacturing & Wholesale Goods"
        }
    ],
    "sg:phone":"+1 859 987 1414",
    "sg:postcode":"40361",
    "sg:province":"KY",
    "sg:tags":[
        "packer"
    ],
    "wof:name":"Bourbon County Packing Co",
    "wof:placetype":"venue"
},
  "geometry": {"coordinates":[-84.25514800000001,38.224177],"type":"Point"}
}