{
  "type": "Feature",
  "properties": {
    "addr:full":"4211 Hillview Ave Shively KY 40216",
    "addr:housenumber":"4211",
    "addr:postcode":"40216",
    "addr:street":"Hillview Ave",
    "iso:country":"US",
    "sg:address":"4211 Hillview Ave",
    "sg:city":"Shively",
    "sg:classifiers":[
        {
            "category":"Personal",
            "subcategory":"Beauty Salon",
            "type":"Services"
        }
    ],
    "sg:phone":"+1 502 449 1291",
    "sg:postcode":"40216",
    "sg:province":"KY",
    "wof:name":"Hair V",
    "wof:placetype":"venue"
},
  "geometry": {"coordinates":[-85.812673,38.187998],"type":"Point"}
}