{
  "type": "Feature",
  "properties": {
    "iso:country":"US",
    "sg:address":"101 Hardison Rd",
    "sg:city":"Auburn",
    "sg:classifiers":[
        {
            "category":"Building & Trades",
            "subcategory":"Construction",
            "type":"Services"
        }
    ],
    "sg:phone":"+1 270 542 6623",
    "sg:postcode":"42265",
    "sg:province":"KY",
    "sg:tags":[
        "concrete",
        "contractor"
    ],
    "wof:name":"Bowling Green Concrete",
    "wof:placetype":"venue"
},
  "geometry": {"coordinates":[-87.054288,36.785007],"type":"Point"}
}