{
  "type": "Feature",
  "properties": {
    "iso:country":"US",
    "sg:address":"5330 S 3rd St",
    "sg:city":"Louisville",
    "sg:classifiers":[
        {
            "category":"Banks & Credit Unions",
            "subcategory":"Bank",
            "type":"Services"
        }
    ],
    "sg:phone":"+1 502 368 2022",
    "sg:postcode":"40214",
    "sg:province":"KY",
    "sg:tags":[
        "cashing",
        "check"
    ],
    "wof:name":"Express Check",
    "wof:placetype":"venue"
},
  "geometry": {"coordinates":[-85.768179,38.170944],"type":"Point"}
}