{
  "type": "Feature",
  "properties": {
    "addr:full":"6440 US Hwy 27 Somerset KY 42501",
    "addr:housenumber":"6440",
    "addr:postcode":"42501",
    "addr:street":"Us Hwy 27",
    "iso:country":"US",
    "sg:address":"6440 US Hwy 27",
    "sg:city":"Somerset",
    "sg:classifiers":[
        {
            "category":"Autos & Motor Vehicles",
            "subcategory":"Automobile Sales",
            "type":"Retail Goods"
        }
    ],
    "sg:phone":"+1 606 561 3861",
    "sg:postcode":"42501",
    "sg:province":"KY",
    "sg:tags":[
        "car",
        "dealer"
    ],
    "wof:name":"Tomlison Auto Sales",
    "wof:placetype":"venue"
},
  "geometry": {"coordinates":[-84.622073,37.008093],"type":"Point"}
}