{
  "type": "Feature",
  "properties": {
    "iso:country":"US",
    "sg:address":"9 W Lexington Ave",
    "sg:city":"Winchester",
    "sg:classifiers":[
        {
            "category":"Restaurant",
            "type":"Food & Drink"
        }
    ],
    "sg:phone":"+1 859 737 0560",
    "sg:postcode":"40391",
    "sg:province":"KY",
    "wof:name":"Engine House Deli",
    "wof:placetype":"venue"
},
  "geometry": {"coordinates":[-84.178271,37.992029],"type":"Point"}
}