{
  "type": "Feature",
  "properties": {
    "iso:country":"US",
    "sg:address":"521 2nd St",
    "sg:city":"Vanceburg",
    "sg:classifiers":[
        {
            "category":"Health Services",
            "subcategory":"Doctor",
            "type":"Services"
        }
    ],
    "sg:phone":"+1 606 796 6400",
    "sg:postcode":"41179",
    "sg:province":"KY",
    "sg:tags":[
        "medical"
    ],
    "wof:name":"Valley Hope Centre",
    "wof:placetype":"venue"
},
  "geometry": {"coordinates":[-83.316548,38.601255],"type":"Point"}
}