{
  "type": "Feature",
  "properties": {
    "addr:full":"261 Ruccio Way Lexington KY 40503",
    "addr:housenumber":"261",
    "addr:postcode":"40503",
    "addr:street":"Ruccio Way",
    "iso:country":"US",
    "sg:address":"261 Ruccio Way",
    "sg:city":"Lexington",
    "sg:classifiers":[
        {
            "category":"Health Services",
            "subcategory":"Health Practitioner",
            "type":"Services"
        }
    ],
    "sg:phone":"+1 859 266 0404",
    "sg:postcode":"40503",
    "sg:province":"KY",
    "sg:tags":[
        "therapist",
        "physical"
    ],
    "sg:website":"www.associatesinrehab.com",
    "wof:name":"Hit Center",
    "wof:placetype":"venue"
},
  "geometry": {"coordinates":[-84.529071,37.995865],"type":"Point"}
}