{
  "type": "Feature",
  "properties": {
    "iso:country":"US",
    "sg:address":"1673 Zion Church Rd",
    "sg:city":"Reynolds Station",
    "sg:classifiers":[
        {
            "category":"Professional",
            "type":"Services"
        }
    ],
    "sg:phone":"+1 270 233 4975",
    "sg:postcode":"42368",
    "sg:province":"KY",
    "wof:name":"Phillips & Wallace",
    "wof:placetype":"venue"
},
  "geometry": {"coordinates":[-86.78391499999999,37.668483],"type":"Point"}
}