{
  "type": "Feature",
  "properties": {
    "iso:country":"US",
    "sg:address":"67 Driftwood Dr",
    "sg:city":"Somerset",
    "sg:classifiers":[
        {
            "category":"Government",
            "subcategory":"Office",
            "type":"Public Place"
        }
    ],
    "sg:phone":"+1 606 677 4086",
    "sg:postcode":"42503",
    "sg:province":"KY",
    "sg:tags":[
        "state",
        "resource"
    ],
    "wof:name":"Social Service Dept",
    "wof:placetype":"venue"
},
  "geometry": {"coordinates":[-84.67885699999999,37.072708],"type":"Point"}
}