{
  "type": "Feature",
  "properties": {
    "iso:country":"US",
    "sg:address":"1000 N Main St",
    "sg:city":"Tompkinsville",
    "sg:classifiers":[
        {
            "category":"Wholesale",
            "subcategory":"Durable Goods & Equipment",
            "type":"Manufacturing & Wholesale Goods"
        }
    ],
    "sg:phone":"+1 270 487 6343",
    "sg:postcode":"42167",
    "sg:province":"KY",
    "sg:tags":[
        "representative",
        "manufacturer"
    ],
    "wof:name":"Sample Source",
    "wof:placetype":"venue"
},
  "geometry": {"coordinates":[-85.687342,36.711894],"type":"Point"}
}