{
  "type": "Feature",
  "properties": {
    "addr:full":"801 Church St Bowling Green KY 42101",
    "addr:housenumber":"801",
    "addr:postcode":"42101",
    "addr:street":"Church St",
    "iso:country":"US",
    "sg:address":"801 Church St",
    "sg:city":"Bowling Green",
    "sg:classifiers":[
        {
            "category":"Organizations",
            "subcategory":"Religious Organization",
            "type":"Services"
        }
    ],
    "sg:phone":"+1 270 842 5221",
    "sg:postcode":"42101",
    "sg:province":"KY",
    "wof:name":"New Bethel Baptist Church",
    "wof:placetype":"venue"
},
  "geometry": {"coordinates":[-86.449951,37.006228],"type":"Point"}
}