{
  "type": "Feature",
  "properties": {
    "addr:full":"405 E Main St Georgetown KY 40324",
    "addr:housenumber":"405",
    "addr:postcode":"40324",
    "addr:street":"E Main St",
    "iso:country":"US",
    "sg:address":"405 E Main St",
    "sg:city":"Georgetown",
    "sg:classifiers":[
        {
            "category":"Social Services",
            "type":"Services"
        }
    ],
    "sg:phone":"+1 502 863 9655",
    "sg:postcode":"40324",
    "sg:province":"KY",
    "wof:name":"J CB Consultant Services",
    "wof:placetype":"venue"
},
  "geometry": {"coordinates":[-84.555194,38.209728],"type":"Point"}
}