{
  "type": "Feature",
  "properties": {
    "addr:full":"3940 Grandview Ave St Matthews KY 40207",
    "addr:housenumber":"3940",
    "addr:postcode":"40207",
    "addr:street":"Grandview Ave",
    "iso:country":"US",
    "sg:address":"3940 Grandview Ave",
    "sg:city":"St Matthews",
    "sg:classifiers":[
        {
            "category":"Government",
            "subcategory":"Police Station",
            "type":"Public Place"
        }
    ],
    "sg:phone":"+1 502 000 1111",
    "sg:postcode":"40207",
    "sg:province":"KY",
    "sg:tags":[
        "department"
    ],
    "wof:name":"St Matthews Police Dept",
    "wof:placetype":"venue"
},
  "geometry": {"coordinates":[-85.649469,38.249821],"type":"Point"}
}