{
  "type": "Feature",
  "properties": {
    "iso:country":"US",
    "sg:address":"7696 Harrodsburg Rd",
    "sg:city":"Nicholasville",
    "sg:classifiers":[
        {
            "category":"Building & Trades",
            "subcategory":"Electrical",
            "type":"Services"
        }
    ],
    "sg:phone":"+1 859 885 3227",
    "sg:postcode":"40356",
    "sg:province":"KY",
    "sg:tags":[
        "electric",
        "contractor"
    ],
    "wof:name":"Dobson Power Line Construction",
    "wof:placetype":"venue"
},
  "geometry": {"coordinates":[-84.621634,37.904899],"type":"Point"}
}