{
  "type": "Feature",
  "properties": {
    "iso:country":"US",
    "sg:address":"11969 S Dixie Hwy",
    "sg:city":"Sonora",
    "sg:classifiers":[
        {
            "category":"Local Transit",
            "type":"Transportation"
        }
    ],
    "sg:phone":"+1 270 369 9601",
    "sg:postcode":"42776",
    "sg:province":"KY",
    "sg:tags":[
        "ambulance"
    ],
    "wof:name":"Hardin County Ambulance",
    "wof:placetype":"venue"
},
  "geometry": {"coordinates":[-85.879203,37.525356],"type":"Point"}
}