{
  "type": "Feature",
  "properties": {
    "iso:country":"US",
    "sg:address":"1412 N Broadway Rd",
    "sg:city":"Lexington",
    "sg:classifiers":[
        {
            "category":"Organizations",
            "subcategory":"Religious Organization",
            "type":"Services"
        }
    ],
    "sg:phone":"+1 859 233 2957",
    "sg:postcode":"40505",
    "sg:province":"KY",
    "sg:tags":[
        "church"
    ],
    "wof:name":"Lexington Church Of Christ",
    "wof:placetype":"venue"
},
  "geometry": {"coordinates":[-84.477924,38.063968],"type":"Point"}
}