{
  "type": "Feature",
  "properties": {
    "iso:country":"US",
    "sg:address":"549 Lafayette Ave",
    "sg:city":"Bellevue",
    "sg:classifiers":[
        {
            "category":"Health Services",
            "subcategory":"Chiropractor",
            "type":"Services"
        }
    ],
    "sg:phone":"+1 859 431 4430",
    "sg:postcode":"41073",
    "sg:province":"KY",
    "wof:name":"Thompson Chiropractic",
    "wof:placetype":"venue"
},
  "geometry": {"coordinates":[-84.479558,39.099569],"type":"Point"}
}