{
  "type": "Feature",
  "properties": {
    "addr:full":"638 E Market St Louisville KY 40202",
    "addr:housenumber":"638",
    "addr:postcode":"40202",
    "addr:street":"E Market St",
    "iso:country":"US",
    "sg:address":"638 E Market St",
    "sg:city":"Louisville",
    "sg:classifiers":[
        {
            "category":"Shopping",
            "type":"Retail Goods"
        }
    ],
    "sg:phone":"+1 502 589 5466",
    "sg:postcode":"40202",
    "sg:province":"KY",
    "sg:tags":[
        "art",
        "gallery",
        "dealer"
    ],
    "wof:name":"Swanson Reed Contemporary",
    "wof:placetype":"venue"
},
  "geometry": {"coordinates":[-85.74067100000001,38.253415],"type":"Point"}
}