{
  "type": "Feature",
  "properties": {
    "addr:full":"312 W 5th St Benton KY 42025",
    "addr:housenumber":"312",
    "addr:postcode":"42025",
    "addr:street":"W 5Th St",
    "iso:country":"US",
    "sg:address":"312 W 5th St",
    "sg:city":"Benton",
    "sg:classifiers":[
        {
            "category":"Restaurant",
            "type":"Food & Drink"
        }
    ],
    "sg:menulink":"http://www.allmenus.com/ky/benton/173573-wendys/menu/",
    "sg:phone":"+1 270 527 2137",
    "sg:postcode":"42025",
    "sg:province":"KY",
    "sg:tags":[
        "burger",
        "american",
        "soup"
    ],
    "wof:name":"Wendy's",
    "wof:placetype":"venue"
},
  "geometry": {"coordinates":[-88.360393,36.86716],"type":"Point"}
}