{
  "type": "Feature",
  "properties": {
    "iso:country":"US",
    "sg:address":"100 W Broadway St",
    "sg:city":"Frankfort",
    "sg:classifiers":[
        {
            "category":"Professional",
            "subcategory":"Management & Consulting",
            "type":"Services"
        }
    ],
    "sg:phone":"+1 502 564 3016",
    "sg:postcode":"40601",
    "sg:province":"KY",
    "sg:tags":[
        "consultant",
        "restoration",
        "historical"
    ],
    "wof:name":"Oral History Commission",
    "wof:placetype":"venue"
},
  "geometry": {"coordinates":[-84.874842,38.198738],"type":"Point"}
}