{
  "type": "Feature",
  "properties": {
    "iso:country":"US",
    "sg:address":"1940 Pershing Rd",
    "sg:city":"Lexington",
    "sg:classifiers":[
        {
            "category":"Building & Trades",
            "subcategory":"Construction",
            "type":"Services"
        }
    ],
    "sg:phone":"+1 859 276 2068",
    "sg:postcode":"40504",
    "sg:province":"KY",
    "sg:tags":[
        "house"
    ],
    "wof:name":"B&E Construction",
    "wof:placetype":"venue"
},
  "geometry": {"coordinates":[-84.532574,38.025437],"type":"Point"}
}