{
  "type": "Feature",
  "properties": {
    "iso:country":"US",
    "sg:address":"400 N Adams St",
    "sg:city":"Henderson",
    "sg:classifiers":[
        {
            "category":"Professional",
            "subcategory":"Research",
            "type":"Services"
        }
    ],
    "sg:phone":"+1 270 826 0081",
    "sg:postcode":"42420",
    "sg:province":"KY",
    "sg:tags":[
        "environmental",
        "ecological"
    ],
    "wof:name":"Air & H2o Technologies Inc",
    "wof:placetype":"venue"
},
  "geometry": {"coordinates":[-87.58313099999999,37.842106],"type":"Point"}
}