{
  "type": "Feature",
  "properties": {
    "iso:country":"US",
    "sg:address":"3800 Springhurst Blvd",
    "sg:city":"Louisville",
    "sg:classifiers":[
        {
            "category":"Health Services",
            "subcategory":"Doctor",
            "type":"Services"
        }
    ],
    "sg:phone":"+1 502 425 4666",
    "sg:postcode":"40241",
    "sg:province":"KY",
    "sg:tags":[
        "physician",
        "family",
        "practice",
        "surgeons",
        "internal",
        "medicine",
        "surgeon"
    ],
    "wof:name":"Springhurst Medical Ctr",
    "wof:placetype":"venue"
},
  "geometry": {"coordinates":[-85.559387,38.30212],"type":"Point"}
}