{
  "type": "Feature",
  "properties": {
    "iso:country":"US",
    "sg:address":"555 S Floyd St",
    "sg:city":"Louisville",
    "sg:classifiers":[
        {
            "category":"Organizations",
            "subcategory":"Professional Association",
            "type":"Services"
        }
    ],
    "sg:phone":"+1 502 852 2038",
    "sg:postcode":"40202",
    "sg:province":"KY",
    "wof:name":"Richard Baumgartner",
    "wof:placetype":"venue"
},
  "geometry": {"coordinates":[-85.749117,38.248558],"type":"Point"}
}