{
  "type": "Feature",
  "properties": {
    "iso:country":"US",
    "sg:address":"620 Park Plaza Dr",
    "sg:city":"Owensboro",
    "sg:classifiers":[
        {
            "category":"Insurance",
            "subcategory":"Insurance Agent",
            "type":"Services"
        }
    ],
    "sg:phone":"+1 270 688 5800",
    "sg:postcode":"42301",
    "sg:province":"KY",
    "wof:name":"Anthem Blue Cross Blue Shield",
    "wof:placetype":"venue"
},
  "geometry": {"coordinates":[-87.11703900000001,37.750554],"type":"Point"}
}