{
  "type": "Feature",
  "properties": {
    "iso:country":"US",
    "sg:address":"703 3rd St",
    "sg:city":"Shelbyville",
    "sg:classifiers":[
        {
            "category":"Wholesale",
            "subcategory":"Computers",
            "type":"Manufacturing & Wholesale Goods"
        }
    ],
    "sg:phone":"+1 502 633 5700",
    "sg:postcode":"40065",
    "sg:province":"KY",
    "sg:tags":[
        "equipment",
        "processing",
        "datum"
    ],
    "wof:name":"Mid-American Control Corp",
    "wof:placetype":"venue"
},
  "geometry": {"coordinates":[-85.21288699999999,38.209246],"type":"Point"}
}