{
  "type": "Feature",
  "properties": {
    "addr:full":"3363 Madison Pike Covington KY 41017",
    "addr:housenumber":"3363",
    "addr:postcode":"41017",
    "addr:street":"Madison Pike",
    "iso:country":"US",
    "sg:address":"3363 Madison Pike",
    "sg:city":"Covington",
    "sg:classifiers":[
        {
            "category":"Food & Beverages",
            "subcategory":"Liquor & Beverages",
            "type":"Retail Goods"
        }
    ],
    "sg:phone":"+1 859 331 0200",
    "sg:postcode":"41017",
    "sg:province":"KY",
    "wof:name":"Deters & Daughters Market",
    "wof:placetype":"venue"
},
  "geometry": {"coordinates":[-84.525316,39.041611],"type":"Point"}
}