{
  "type": "Feature",
  "properties": {
    "iso:country":"US",
    "sg:address":"2245 Holt Rd",
    "sg:city":"Paducah",
    "sg:classifiers":[
        {
            "category":"Retail",
            "subcategory":"Repair Shop",
            "type":"Services"
        }
    ],
    "sg:phone":"+1 270 554 4899",
    "sg:postcode":"42001",
    "sg:province":"KY",
    "sg:tags":[
        "equipment",
        "conditioning",
        "air"
    ],
    "wof:name":"Gaines Refrigeration & AC",
    "wof:placetype":"venue"
},
  "geometry": {"coordinates":[-88.69269300000001,37.05991],"type":"Point"}
}