{
  "type": "Feature",
  "properties": {
    "iso:country":"US",
    "sg:address":"9003 Alley Branch Rd",
    "sg:city":"Catlettsburg",
    "sg:classifiers":[
        {
            "category":"Autos & Motor Vehicles",
            "subcategory":"Auto Supplies",
            "type":"Retail Goods"
        }
    ],
    "sg:phone":"+1 606 739 4407",
    "sg:postcode":"41129",
    "sg:province":"KY",
    "sg:tags":[
        "automobile",
        "parts"
    ],
    "wof:name":"Bates Speed Shop",
    "wof:placetype":"venue"
},
  "geometry": {"coordinates":[-82.619263,38.361054],"type":"Point"}
}