{
  "type": "Feature",
  "properties": {
    "iso:country":"US",
    "sg:address":"3820 Leland Rd",
    "sg:city":"Louisville",
    "sg:classifiers":[
        {
            "category":"Professional",
            "subcategory":"Management & Consulting",
            "type":"Services"
        }
    ],
    "sg:phone":"+1 502 454 7545",
    "sg:postcode":"40207",
    "sg:province":"KY",
    "sg:tags":[
        "consultant",
        "business"
    ],
    "wof:name":"Entrepreneurial Consulting Inc",
    "wof:placetype":"venue"
},
  "geometry": {"coordinates":[-85.661192,38.259744],"type":"Point"}
}