{
  "type": "Feature",
  "properties": {
    "addr:full":"310 Southview Dr Nicholasville KY 40356",
    "addr:housenumber":"310",
    "addr:postcode":"40356",
    "addr:street":"Southview Dr",
    "iso:country":"US",
    "sg:address":"310 Southview Dr",
    "sg:city":"Nicholasville",
    "sg:classifiers":[
        {
            "category":"Social Services",
            "subcategory":"Child Care",
            "type":"Services"
        }
    ],
    "sg:phone":"+1 859 887 1952",
    "sg:postcode":"40356",
    "sg:province":"KY",
    "wof:name":"Kid's Connection Learning Ctr",
    "wof:placetype":"venue"
},
  "geometry": {"coordinates":[-84.580484,37.867369],"type":"Point"}
}