{
  "type": "Feature",
  "properties": {
    "iso:country":"US",
    "sg:address":"125 Church St",
    "sg:city":"Lexington",
    "sg:classifiers":[
        {
            "category":"Professional",
            "subcategory":"Lawyer & Legal Services",
            "type":"Services"
        }
    ],
    "sg:phone":"+1 859 254 2550",
    "sg:postcode":"40507",
    "sg:province":"KY",
    "wof:name":"Diana L Beard",
    "wof:placetype":"venue"
},
  "geometry": {"coordinates":[-84.496212,38.048057],"type":"Point"}
}