{
  "type": "Feature",
  "properties": {
    "iso:country":"US",
    "sg:address":"4410 Outer Loop",
    "sg:city":"Louisville",
    "sg:classifiers":[
        {
            "category":"Manufacturing",
            "subcategory":"Chemicals & Compounds",
            "type":"Manufacturing & Wholesale Goods"
        },
        {
            "category":"Manufacturing",
            "subcategory":"Tools & Machinery",
            "type":"Manufacturing & Wholesale Goods"
        },
        {
            "category":"Building & Trades",
            "subcategory":"Construction",
            "type":"Services"
        },
        {
            "category":"Home & Garden",
            "subcategory":"Building Materials",
            "type":"Retail Goods"
        },
        {
            "category":"Wholesale",
            "subcategory":"Painting Supplies",
            "type":"Manufacturing & Wholesale Goods"
        },
        {
            "category":"Autos & Motor Vehicles",
            "subcategory":"Auto Supplies",
            "type":"Retail Goods"
        },
        {
            "category":"Building & Trades",
            "subcategory":"Equipment Rental",
            "type":"Services"
        },
        {
            "category":"Manufacturing",
            "subcategory":"Building Materials",
            "type":"Manufacturing & Wholesale Goods"
        }
    ],
    "sg:phone":"+1 502 969 4724",
    "sg:postcode":"40219",
    "sg:province":"KY",
    "sg:tags":[
        "shop",
        "body",
        "paint",
        "wall",
        "automobile",
        "wallpaper",
        "coating",
        "improvement",
        "paint-wholesale",
        "spraying",
        "wallcoverings-installation",
        "wallcoverings",
        "contractor",
        "equipment-renting",
        "painter",
        "manufacturer"
    ],
    "sg:website":"http://www.sherwin-williams.com/index.jsp?WT.mc_id=SW_Store1358",
    "wof:name":"Sherwin-Williams",
    "wof:placetype":"venue"
},
  "geometry": {"coordinates":[-85.680527,38.138153],"type":"Point"}
}