{
  "type": "Feature",
  "properties": {
    "addr:full":"252 E Market St Louisville KY 40202",
    "addr:housenumber":"252",
    "addr:postcode":"40202",
    "addr:street":"E Market St",
    "iso:country":"US",
    "sg:address":"252 E Market St",
    "sg:city":"Louisville",
    "sg:classifiers":[
        {
            "category":"Restaurant",
            "type":"Food & Drink"
        }
    ],
    "sg:phone":"+1 502 581 1222",
    "sg:postcode":"40202",
    "sg:province":"KY",
    "wof:name":"Oscar Brown's South Beach Sta",
    "wof:placetype":"venue"
},
  "geometry": {"coordinates":[-85.748981,38.254322],"type":"Point"}
}