{
  "type": "Feature",
  "properties": {
    "addr:full":"206 Madison Square Dr Madisonville KY 42431",
    "addr:housenumber":"206",
    "addr:postcode":"42431",
    "addr:street":"Madison Square Dr",
    "iso:country":"US",
    "sg:address":"206 Madison Square Dr",
    "sg:city":"Madisonville",
    "sg:classifiers":[
        {
            "category":"Restaurant",
            "type":"Food & Drink"
        }
    ],
    "sg:phone":"+1 270 825 3150",
    "sg:postcode":"42431",
    "sg:province":"KY",
    "sg:tags":[
        "parlor",
        "ice",
        "cream"
    ],
    "wof:name":"Scoops N' Mor",
    "wof:placetype":"venue"
},
  "geometry": {"coordinates":[-87.47970100000001,37.324461],"type":"Point"}
}