{
  "type": "Feature",
  "properties": {
    "addr:full":"421 Happy Valley Rd Glasgow KY 42141",
    "addr:housenumber":"421",
    "addr:postcode":"42141",
    "addr:street":"Happy Valley Rd",
    "iso:country":"US",
    "sg:address":"421 Happy Valley Rd",
    "sg:city":"Glasgow",
    "sg:classifiers":[
        {
            "category":"Home & Garden",
            "subcategory":"Household Appliances",
            "type":"Retail Goods"
        }
    ],
    "sg:phone":"+1 270 651 3329",
    "sg:postcode":"42141",
    "sg:province":"KY",
    "sg:tags":[
        "machine",
        "sewing"
    ],
    "wof:name":"Sewing Machine Ctr",
    "wof:placetype":"venue"
},
  "geometry": {"coordinates":[-85.91084499999999,37.005146],"type":"Point"}
}