{
  "type": "Feature",
  "properties": {
    "iso:country":"US",
    "sg:address":"2017 Cherokee Pkwy",
    "sg:city":"Louisville",
    "sg:classifiers":[
        {
            "category":"Insurance",
            "subcategory":"Life Insurance",
            "type":"Services"
        }
    ],
    "sg:phone":"+1 502 473 7929",
    "sg:postcode":"40204",
    "sg:province":"KY",
    "wof:name":"Ralph Koslik",
    "wof:placetype":"venue"
},
  "geometry": {"coordinates":[-85.71265099999999,38.235176],"type":"Point"}
}