{
  "type": "Feature",
  "properties": {
    "iso:country":"US",
    "sg:address":"5101 Hinkleville Rd",
    "sg:city":"Paducah",
    "sg:classifiers":[
        {
            "category":"Restaurant",
            "type":"Food & Drink"
        }
    ],
    "sg:menulink":"http://www.allmenus.com/ky/paducah/83015-villa-pizza/menu/",
    "sg:phone":"+1 270 415 9459",
    "sg:postcode":"42001",
    "sg:province":"KY",
    "sg:tags":[
        "american",
        "italian",
        "pizza"
    ],
    "wof:name":"Villa Pizza",
    "wof:placetype":"venue"
},
  "geometry": {"coordinates":[-88.685034,37.078337],"type":"Point"}
}