{
  "type": "Feature",
  "properties": {
    "iso:country":"US",
    "sg:address":"418 Hudson St",
    "sg:city":"Columbia",
    "sg:classifiers":[
        {
            "category":"Shopping",
            "subcategory":"Clothing, Apparel, & Fashions",
            "type":"Retail Goods"
        }
    ],
    "sg:phone":"+1 270 384 6314",
    "sg:postcode":"42728",
    "sg:province":"KY",
    "sg:tags":[
        "salvage",
        "surplus",
        "merchandise"
    ],
    "wof:name":"Haskin Coomer & Son",
    "wof:placetype":"venue"
},
  "geometry": {"coordinates":[-85.31442699999999,37.098885],"type":"Point"}
}