{
  "type": "Feature",
  "properties": {
    "iso:country":"US",
    "sg:address":"2350 Lilac Rd",
    "sg:city":"Leitchfield",
    "sg:classifiers":[
        {
            "category":"Real Estate",
            "subcategory":"Real Estate Agent",
            "type":"Services"
        }
    ],
    "sg:phone":"+1 270 287 9423",
    "sg:postcode":"42754",
    "sg:province":"KY",
    "sg:tags":[
        "agency",
        "rental"
    ],
    "wof:name":"HHT Rental",
    "wof:placetype":"venue"
},
  "geometry": {"coordinates":[-86.32713800000001,37.512863],"type":"Point"}
}