{
  "type": "Feature",
  "properties": {
    "iso:country":"US",
    "sg:address":"325 Wildwood Ave",
    "sg:city":"London",
    "sg:classifiers":[
        {
            "category":"Professional",
            "subcategory":"Business Services",
            "type":"Services"
        }
    ],
    "sg:phone":"+1 606 864 4176",
    "sg:postcode":"40744",
    "sg:province":"KY",
    "sg:tags":[
        "appraiser"
    ],
    "wof:name":"Mike Humfleet Appraisal Svc",
    "wof:placetype":"venue"
},
  "geometry": {"coordinates":[-84.09209300000001,37.078834],"type":"Point"}
}