{
  "type": "Feature",
  "properties": {
    "iso:country":"US",
    "sg:address":"1505 S 25th St",
    "sg:city":"Louisville",
    "sg:classifiers":[
        {
            "category":"Personal",
            "subcategory":"Beauty Salon",
            "type":"Services"
        }
    ],
    "sg:phone":"+1 502 772 1993",
    "sg:postcode":"40210",
    "sg:province":"KY",
    "sg:tags":[
        "shop"
    ],
    "wof:name":"Jackie's Mane Event",
    "wof:placetype":"venue"
},
  "geometry": {"coordinates":[-85.79732199999999,38.229076],"type":"Point"}
}