{
  "type": "Feature",
  "properties": {
    "iso:country":"US",
    "sg:address":"10951 US Hwy 60",
    "sg:city":"Ashland",
    "sg:classifiers":[
        {
            "category":"Food & Beverages",
            "subcategory":"Groceries & Convenience Stores",
            "type":"Retail Goods"
        }
    ],
    "sg:phone":"+1 606 928 0012",
    "sg:postcode":"41102",
    "sg:province":"KY",
    "wof:name":"Galleria Tiger Mart",
    "wof:placetype":"venue"
},
  "geometry": {"coordinates":[-82.710914,38.396197],"type":"Point"}
}