{
  "type": "Feature",
  "properties": {
    "iso:country":"US",
    "sg:address":"45 Bald Knob Rd",
    "sg:city":"Beaver Dam",
    "sg:classifiers":[
        {
            "category":"Professional",
            "subcategory":"Engineering",
            "type":"Services"
        }
    ],
    "sg:phone":"+1 270 274 3356",
    "sg:postcode":"42320",
    "sg:province":"KY",
    "sg:tags":[
        "engineer"
    ],
    "wof:name":"Mc Ewen Engineering & Mining",
    "wof:placetype":"venue"
},
  "geometry": {"coordinates":[-86.805932,37.356542],"type":"Point"}
}