{
  "type": "Feature",
  "properties": {
    "iso:country":"US",
    "sg:address":"2105 Lexington Rd",
    "sg:city":"Louisville",
    "sg:classifiers":[
        {
            "category":"Animal Shelter",
            "type":"Public Place"
        }
    ],
    "sg:phone":"+1 502 583 2498",
    "sg:postcode":"40206",
    "sg:province":"KY",
    "sg:tags":[
        "kennel"
    ],
    "wof:name":"Waggin Tail Kennels Inc",
    "wof:placetype":"venue"
},
  "geometry": {"coordinates":[-85.71650200000001,38.25042],"type":"Point"}
}