{
  "type": "Feature",
  "properties": {
    "iso:country":"US",
    "sg:address":"6628 US Hwy 60",
    "sg:city":"Ashland",
    "sg:classifiers":[
        {
            "category":"Banks & Credit Unions",
            "subcategory":"Bank",
            "type":"Services"
        }
    ],
    "sg:phone":"+1 606 928 0268",
    "sg:postcode":"41102",
    "sg:province":"KY",
    "sg:tags":[
        "savings",
        "loan",
        "association"
    ],
    "wof:name":"Home Federal Savings & Loan",
    "wof:placetype":"venue"
},
  "geometry": {"coordinates":[-82.693952,38.431569],"type":"Point"}
}