{
  "type": "Feature",
  "properties": {
    "iso:country":"US",
    "sg:address":"11 S Main St",
    "sg:city":"Henderson",
    "sg:classifiers":[
        {
            "category":"Real Estate",
            "subcategory":"Real Estate Agent",
            "type":"Services"
        }
    ],
    "sg:phone":"+1 270 827 5624",
    "sg:postcode":"42420",
    "sg:province":"KY",
    "wof:name":"Collier & Co",
    "wof:placetype":"venue"
},
  "geometry": {"coordinates":[-87.593163,37.838695],"type":"Point"}
}