{
  "type": "Feature",
  "properties": {
    "iso:country":"US",
    "sg:address":"116 S 5th St",
    "sg:city":"Murray",
    "sg:classifiers":[
        {
            "category":"Personal",
            "subcategory":"Beauty Salon",
            "type":"Services"
        }
    ],
    "sg:phone":"+1 270 753 9942",
    "sg:postcode":"42071",
    "sg:province":"KY",
    "wof:name":"Hair Grafiks",
    "wof:placetype":"venue"
},
  "geometry": {"coordinates":[-88.303057,36.611459],"type":"Point"}
}