{
  "type": "Feature",
  "properties": {
    "iso:country":"US",
    "sg:address":"320 13th St",
    "sg:city":"Henderson",
    "sg:classifiers":[
        {
            "category":"Arts & Performance",
            "subcategory":"Theater",
            "type":"Entertainment"
        }
    ],
    "sg:phone":"+1 270 826 0722",
    "sg:postcode":"42420",
    "sg:province":"KY",
    "sg:tags":[
        "live",
        "music"
    ],
    "wof:name":"Songbird Entertainment",
    "wof:placetype":"venue"
},
  "geometry": {"coordinates":[-87.581067,37.85356],"type":"Point"}
}