{
  "type": "Feature",
  "properties": {
    "addr:full":"7606 Rockingham Rd Prospect KY 40059",
    "addr:housenumber":"7606",
    "addr:postcode":"40059",
    "addr:street":"Rockingham Rd",
    "iso:country":"US",
    "sg:address":"7606 Rockingham Rd",
    "sg:city":"Prospect",
    "sg:classifiers":[
        {
            "category":"Professional",
            "subcategory":"Engineering",
            "type":"Services"
        }
    ],
    "sg:phone":"+1 502 228 8026",
    "sg:postcode":"40059",
    "sg:province":"KY",
    "sg:tags":[
        "consulting",
        "engineer"
    ],
    "wof:name":"Vandevelde Engineering Co",
    "wof:placetype":"venue"
},
  "geometry": {"coordinates":[-85.60334,38.338848],"type":"Point"}
}