{
  "type": "Feature",
  "properties": {
    "iso:country":"US",
    "sg:address":"515 Elm St",
    "sg:city":"Ludlow",
    "sg:classifiers":[
        {
            "category":"Education",
            "subcategory":"School",
            "type":"Public Place"
        }
    ],
    "sg:phone":"+1 859 261 8211",
    "sg:postcode":"41016",
    "sg:province":"KY",
    "sg:website":"www.ludlow.k12.ky.us",
    "wof:name":"Ludlow High School",
    "wof:placetype":"venue"
},
  "geometry": {"coordinates":[-84.553665,39.091767],"type":"Point"}
}