{
  "type": "Feature",
  "properties": {
    "iso:country":"US",
    "sg:address":"489 McGill Ln",
    "sg:city":"Lewisport",
    "sg:classifiers":[
        {
            "category":"Personal",
            "subcategory":"Beauty Salon",
            "type":"Services"
        }
    ],
    "sg:phone":"+1 270 295 4113",
    "sg:postcode":"42351",
    "sg:province":"KY",
    "wof:name":"Rose Mary's Beauty Shop",
    "wof:placetype":"venue"
},
  "geometry": {"coordinates":[-86.913828,37.931579],"type":"Point"}
}