{
  "type": "Feature",
  "properties": {
    "addr:full":"6633 Dixie Hwy Pleasure Rdg Pk KY 40258",
    "addr:housenumber":"6633",
    "addr:postcode":"40258",
    "addr:street":"Dixie Hwy Pleasure Rdg Pk",
    "iso:country":"US",
    "sg:address":"6633 Dixie Hwy",
    "sg:city":"Pleasure Rdg Pk",
    "sg:classifiers":[
        {
            "category":"Organizations",
            "subcategory":"Religious Organization",
            "type":"Services"
        }
    ],
    "sg:phone":"+1 502 935 5223",
    "sg:postcode":"40258",
    "sg:province":"KY",
    "sg:tags":[
        "church"
    ],
    "wof:name":"Aldersgate United Methodist",
    "wof:placetype":"venue"
},
  "geometry": {"coordinates":[-85.83492,38.155183],"type":"Point"}
}