{
  "type": "Feature",
  "properties": {
    "iso:country":"US",
    "sg:address":"3005 Gleeson Ln",
    "sg:city":"Louisville",
    "sg:classifiers":[
        {
            "category":"Cinema",
            "subcategory":"Movie Rental",
            "type":"Entertainment"
        }
    ],
    "sg:phone":"+1 502 314 6298",
    "sg:postcode":"40299",
    "sg:province":"KY",
    "sg:tags":[
        "motion",
        "picture",
        "distributor",
        "film",
        "exchange"
    ],
    "wof:name":"Ironbridge Productions",
    "wof:placetype":"venue"
},
  "geometry": {"coordinates":[-85.589079,38.202629],"type":"Point"}
}