{
  "type": "Feature",
  "properties": {
    "iso:country":"US",
    "sg:address":"2141 Sycamore Ave",
    "sg:city":"Louisville",
    "sg:classifiers":[
        {
            "category":"Health Services",
            "subcategory":"Nursing And Care Facility",
            "type":"Services"
        }
    ],
    "sg:phone":"+1 502 895 5417",
    "sg:postcode":"40206",
    "sg:province":"KY",
    "sg:tags":[
        "home",
        "convalescent"
    ],
    "wof:name":"Brownsboro Hills Nursing Home",
    "wof:placetype":"venue"
},
  "geometry": {"coordinates":[-85.705243,38.255745],"type":"Point"}
}