{
  "type": "Feature",
  "properties": {
    "addr:full":"1575 Cow Creek Rd Ravenna KY 40472",
    "addr:housenumber":"1575",
    "addr:postcode":"40472",
    "addr:street":"Cow Creek Rd",
    "iso:country":"US",
    "sg:address":"1575 Cow Creek Rd",
    "sg:city":"Ravenna",
    "sg:classifiers":[
        {
            "category":"Organizations",
            "subcategory":"Religious Organization",
            "type":"Services"
        }
    ],
    "sg:phone":"+1 606 723 6183",
    "sg:postcode":"40472",
    "sg:province":"KY",
    "sg:tags":[
        "church"
    ],
    "wof:name":"Cow Creek Baptist Church",
    "wof:placetype":"venue"
},
  "geometry": {"coordinates":[-83.924667,37.701051],"type":"Point"}
}