{
  "type": "Feature",
  "properties": {
    "iso:country":"US",
    "sg:address":"733 Poland Rd",
    "sg:city":"Scottsville",
    "sg:classifiers":[
        {
            "category":"Health Services",
            "subcategory":"Chiropractor",
            "type":"Services"
        }
    ],
    "sg:phone":"+1 270 487 8687",
    "sg:postcode":"42164",
    "sg:province":"KY",
    "wof:name":"B C Lane DC",
    "wof:placetype":"venue"
},
  "geometry": {"coordinates":[-86.132908,36.746414],"type":"Point"}
}