{
  "type": "Feature",
  "properties": {
    "iso:country":"US",
    "sg:address":"8605 Haines Dr",
    "sg:city":"Florence",
    "sg:classifiers":[
        {
            "category":"Autos & Motor Vehicles",
            "subcategory":"Automobile Sales",
            "type":"Retail Goods"
        }
    ],
    "sg:phone":"+1 513 671 5466",
    "sg:postcode":"41042",
    "sg:province":"KY",
    "sg:tags":[
        "limo"
    ],
    "wof:name":"L & L Limousine Serv",
    "wof:placetype":"venue"
},
  "geometry": {"coordinates":[-84.664497,38.972698],"type":"Point"}
}