{
  "type": "Feature",
  "properties": {
    "addr:full":"600 N Limestone Lexington KY 40508",
    "addr:housenumber":"600",
    "addr:postcode":"40508",
    "addr:street":"N Limestone",
    "iso:country":"US",
    "sg:address":"600 N Limestone",
    "sg:city":"Lexington",
    "sg:classifiers":[
        {
            "category":"Food & Beverages",
            "subcategory":"Specialty",
            "type":"Retail Goods"
        },
        {
            "category":"Food & Beverages",
            "subcategory":"Groceries & Convenience Stores",
            "type":"Retail Goods"
        }
    ],
    "sg:phone":"+1 859 254 3381",
    "sg:postcode":"40508",
    "sg:province":"KY",
    "sg:tags":[
        "grocers-specialty"
    ],
    "wof:name":"Progress Food Mart",
    "wof:placetype":"venue"
},
  "geometry": {"coordinates":[-84.486397,38.053902],"type":"Point"}
}