{
  "type": "Feature",
  "properties": {
    "addr:full":"2317 Rockford Ln Shively KY 40216",
    "addr:housenumber":"2317",
    "addr:postcode":"40216",
    "addr:street":"Rockford Ln",
    "iso:country":"US",
    "sg:address":"2317 Rockford Ln",
    "sg:city":"Shively",
    "sg:classifiers":[
        {
            "category":"Food & Beverages",
            "subcategory":"Liquor & Beverages",
            "type":"Retail Goods"
        }
    ],
    "sg:phone":"+1 502 448 0721",
    "sg:postcode":"40216",
    "sg:province":"KY",
    "wof:name":"Whistle Stop Liquors",
    "wof:placetype":"venue"
},
  "geometry": {"coordinates":[-85.836524,38.176092],"type":"Point"}
}