{
  "type": "Feature",
  "properties": {
    "iso:country":"US",
    "sg:address":"7633 Alexandria Pike",
    "sg:city":"Alexandria",
    "sg:classifiers":[
        {
            "category":"Home & Garden",
            "subcategory":"Garden Supply",
            "type":"Retail Goods"
        }
    ],
    "sg:phone":"+1 859 635 5555",
    "sg:postcode":"41001",
    "sg:province":"KY",
    "sg:tags":[
        "center"
    ],
    "wof:name":"Alexandria Garden Ctr",
    "wof:placetype":"venue"
},
  "geometry": {"coordinates":[-84.393857,38.979165],"type":"Point"}
}