{
  "type": "Feature",
  "properties": {
    "iso:country":"US",
    "sg:address":"13101 Raider Hollow Rd",
    "sg:city":"Upton",
    "sg:classifiers":[
        {
            "category":"Communications",
            "subcategory":"Radio Station",
            "type":"Services"
        }
    ],
    "sg:phone":"+1 270 369 8614",
    "sg:postcode":"42784",
    "sg:province":"KY",
    "sg:tags":[
        "company",
        "broadcasting"
    ],
    "wof:name":"WJCR Radio",
    "wof:placetype":"venue"
},
  "geometry": {"coordinates":[-86.041313,37.442342],"type":"Point"}
}