{
  "type": "Feature",
  "properties": {
    "iso:country":"US",
    "sg:address":"440 Hickory Ln",
    "sg:city":"Berea",
    "sg:classifiers":[
        {
            "category":"Manufacturing",
            "subcategory":"Tools & Machinery",
            "type":"Manufacturing & Wholesale Goods"
        }
    ],
    "sg:phone":"+1 859 985 8665",
    "sg:postcode":"40403",
    "sg:province":"KY",
    "sg:tags":[
        "die",
        "maker"
    ],
    "wof:name":"Superior Tool Works",
    "wof:placetype":"venue"
},
  "geometry": {"coordinates":[-84.277047,37.6059],"type":"Point"}
}