{
  "type": "Feature",
  "properties": {
    "addr:full":"1610 Leestown Rd Lexington KY 40511",
    "addr:housenumber":"1610",
    "addr:postcode":"40511",
    "addr:street":"Leestown Rd",
    "iso:country":"US",
    "sg:address":"1610 Leestown Rd",
    "sg:city":"Lexington",
    "sg:classifiers":[
        {
            "category":"Cinema",
            "subcategory":"Movie Rental",
            "type":"Entertainment"
        }
    ],
    "sg:phone":"+1 859 278 1515",
    "sg:postcode":"40511",
    "sg:province":"KY",
    "sg:tags":[
        "leasing",
        "video",
        "disc",
        "tape"
    ],
    "wof:name":"Video Vending North America",
    "wof:placetype":"venue"
},
  "geometry": {"coordinates":[-84.527596,38.06815],"type":"Point"}
}