{
  "type": "Feature",
  "properties": {
    "iso:country":"US",
    "sg:address":"1260 Industry Rd",
    "sg:city":"Lexington",
    "sg:classifiers":[
        {
            "category":"Social Services",
            "type":"Services"
        }
    ],
    "sg:phone":"+1 859 252 2224",
    "sg:postcode":"40505",
    "sg:province":"KY",
    "sg:tags":[
        "organization",
        "welfare"
    ],
    "sg:website":"www.lexhabitat.org",
    "wof:name":"Habitat For Humanity",
    "wof:placetype":"venue"
},
  "geometry": {"coordinates":[-84.45513200000001,38.049759],"type":"Point"}
}