{
  "type": "Feature",
  "properties": {
    "iso:country":"US",
    "sg:address":"12338 Shelbyville Rd",
    "sg:city":"Louisville",
    "sg:classifiers":[
        {
            "category":"Home & Garden",
            "subcategory":"Building Materials",
            "type":"Retail Goods"
        }
    ],
    "sg:phone":"+1 502 253 9950",
    "sg:postcode":"40243",
    "sg:province":"KY",
    "sg:tags":[
        "windows"
    ],
    "sg:website":"www.pella.com",
    "wof:name":"Pella Window & Door Co",
    "wof:placetype":"venue"
},
  "geometry": {"coordinates":[-85.52715000000001,38.246759],"type":"Point"}
}