{
  "type": "Feature",
  "properties": {
    "iso:country":"US",
    "sg:address":"218 Edgewood Dr",
    "sg:city":"Nicholasville",
    "sg:classifiers":[
        {
            "category":"Manufacturing",
            "subcategory":"Printing",
            "type":"Manufacturing & Wholesale Goods"
        }
    ],
    "sg:phone":"+1 859 885 6354",
    "sg:postcode":"40356",
    "sg:province":"KY",
    "sg:tags":[
        "printer"
    ],
    "wof:name":"Printer's Ink Of Nicholasville",
    "wof:placetype":"venue"
},
  "geometry": {"coordinates":[-84.57937699999999,37.868425],"type":"Point"}
}