{
  "type": "Feature",
  "properties": {
    "iso:country":"US",
    "sg:address":"2885 State Hwy 198",
    "sg:city":"Hustonville",
    "sg:classifiers":[
        {
            "category":"Wholesale",
            "subcategory":"Construction Materials",
            "type":"Manufacturing & Wholesale Goods"
        }
    ],
    "sg:phone":"+1 606 346 4796",
    "sg:postcode":"42541",
    "sg:province":"KY",
    "sg:tags":[
        "concrete",
        "product"
    ],
    "wof:name":"Griffins Concrete Products",
    "wof:placetype":"venue"
},
  "geometry": {"coordinates":[-84.81401200000001,37.368623],"type":"Point"}
}