{
  "type": "Feature",
  "properties": {
    "iso:country":"US",
    "sg:address":"115 E 9th St",
    "sg:city":"Hopkinsville",
    "sg:classifiers":[
        {
            "category":"Restaurant",
            "type":"Food & Drink"
        }
    ],
    "sg:phone":"+1 270 707 0200",
    "sg:postcode":"42240",
    "sg:province":"KY",
    "sg:tags":[
        "eating"
    ],
    "wof:name":"Country Girl Cafe",
    "wof:placetype":"venue"
},
  "geometry": {"coordinates":[-87.488051,36.8651],"type":"Point"}
}