{
  "type": "Feature",
  "properties": {
    "addr:full":"815 E Broadway Louisville KY 40204",
    "addr:housenumber":"815",
    "addr:postcode":"40204",
    "addr:street":"E Broadway",
    "iso:country":"US",
    "sg:address":"815 E Broadway",
    "sg:city":"Louisville",
    "sg:classifiers":[
        {
            "category":"Autos & Motor Vehicles",
            "subcategory":"Automobile Sales",
            "type":"Retail Goods"
        }
    ],
    "sg:phone":"+1 502 587 7868",
    "sg:postcode":"40204",
    "sg:province":"KY",
    "sg:tags":[
        "car",
        "dealer"
    ],
    "wof:name":"Super Auto Sales",
    "wof:placetype":"venue"
},
  "geometry": {"coordinates":[-85.73874000000001,38.244709],"type":"Point"}
}