{
  "type": "Feature",
  "properties": {
    "iso:country":"US",
    "sg:address":"4115 Dixie Hwy",
    "sg:city":"Louisville",
    "sg:classifiers":[
        {
            "category":"Health Services",
            "subcategory":"Medical Lab",
            "type":"Services"
        },
        {
            "category":"Health Services",
            "subcategory":"Dentist",
            "type":"Services"
        }
    ],
    "sg:phone":"+1 502 448 5050",
    "sg:postcode":"40216",
    "sg:province":"KY",
    "sg:tags":[
        "denture",
        "laboratory",
        "dental",
        "dentists-prosthodontists"
    ],
    "sg:website":"http://www.surefitdentures.com",
    "wof:name":"Sure-Fit Dentures",
    "wof:placetype":"venue"
},
  "geometry": {"coordinates":[-85.810389,38.188903],"type":"Point"}
}