{
  "type": "Feature",
  "properties": {
    "iso:country":"US",
    "sg:address":"1375 Clearfork Rd",
    "sg:city":"Morehead",
    "sg:classifiers":[
        {
            "category":"Wholesale",
            "subcategory":"Construction Materials",
            "type":"Manufacturing & Wholesale Goods"
        }
    ],
    "sg:phone":"+1 606 784 7586",
    "sg:postcode":"40351",
    "sg:province":"KY",
    "sg:tags":[
        "pallet",
        "skid"
    ],
    "wof:name":"Daniel Boone Lumber Industries",
    "wof:placetype":"venue"
},
  "geometry": {"coordinates":[-83.450678,38.274653],"type":"Point"}
}