{
  "type": "Feature",
  "properties": {
    "addr:full":"9785 State Hwy 45 S Wingo KY 42088",
    "addr:housenumber":"9785",
    "addr:postcode":"42088",
    "addr:street":"State Hwy 45 S",
    "iso:country":"US",
    "sg:address":"9785 State Hwy 45 S",
    "sg:city":"Wingo",
    "sg:classifiers":[
        {
            "category":"Autos & Motor Vehicles",
            "subcategory":"Fuel & Gas Station",
            "type":"Retail Goods"
        }
    ],
    "sg:phone":"+1 270 376 2221",
    "sg:postcode":"42088",
    "sg:province":"KY",
    "sg:tags":[
        "oil"
    ],
    "wof:name":"Dubs Pit Stop",
    "wof:placetype":"venue"
},
  "geometry": {"coordinates":[-88.73879700000001,36.642803],"type":"Point"}
}