{
  "type": "Feature",
  "properties": {
    "iso:country":"US",
    "sg:address":"854 E High St",
    "sg:city":"Lexington",
    "sg:classifiers":[
        {
            "category":"Restaurant",
            "type":"Food & Drink"
        }
    ],
    "sg:phone":"+1 859 422 7697",
    "sg:postcode":"40502",
    "sg:province":"KY",
    "wof:name":"Roy's E High Diner",
    "wof:placetype":"venue"
},
  "geometry": {"coordinates":[-84.489986,38.029891],"type":"Point"}
}