{
  "type": "Feature",
  "properties": {
    "iso:country":"US",
    "sg:address":"110 Riverfront Dr",
    "sg:city":"Hopkinsville",
    "sg:classifiers":[
        {
            "category":"Government",
            "subcategory":"Office",
            "type":"Public Place"
        }
    ],
    "sg:phone":"+1 270 889 6509",
    "sg:postcode":"42240",
    "sg:province":"KY",
    "sg:tags":[
        "state"
    ],
    "sg:website":"www.hopkinsville.des.ky.gov",
    "wof:name":"Employment & Training Office",
    "wof:placetype":"venue"
},
  "geometry": {"coordinates":[-87.488399,36.870055],"type":"Point"}
}