{
  "type": "Feature",
  "properties": {
    "addr:full":"2362 US Hwy 641 Marion KY 42064",
    "addr:housenumber":"2362",
    "addr:postcode":"42064",
    "addr:street":"Us Hwy 641",
    "iso:country":"US",
    "sg:address":"2362 US Hwy 641",
    "sg:city":"Marion",
    "sg:classifiers":[
        {
            "category":"Travel",
            "subcategory":"Hotels & Motels",
            "type":"Entertainment"
        }
    ],
    "sg:phone":"+1 270 965 5391",
    "sg:postcode":"42064",
    "sg:province":"KY",
    "sg:tags":[
        "operation"
    ],
    "wof:name":"Marion Inn",
    "wof:placetype":"venue"
},
  "geometry": {"coordinates":[-88.07875,37.299454],"type":"Point"}
}