{
  "type": "Feature",
  "properties": {
    "addr:full":"1538 Midland Trl Shelbyville KY 40065",
    "addr:housenumber":"1538",
    "addr:postcode":"40065",
    "addr:street":"Midland Trl",
    "iso:country":"US",
    "sg:address":"1538 Midland Trl",
    "sg:city":"Shelbyville",
    "sg:classifiers":[
        {
            "category":"Restaurant",
            "type":"Food & Drink"
        }
    ],
    "sg:menulink":"http://www.allmenus.com/ky/shelbyville/200425-long-john-silvers/menu/",
    "sg:phone":"+1 502 633 6384",
    "sg:postcode":"40065",
    "sg:province":"KY",
    "sg:tags":[
        "seafood",
        "american"
    ],
    "wof:name":"Long John Silver's",
    "wof:placetype":"venue"
},
  "geometry": {"coordinates":[-85.236924,38.212428],"type":"Point"}
}