{
  "type": "Feature",
  "properties": {
    "iso:country":"US",
    "sg:address":"227 E Main St",
    "sg:city":"Lebanon",
    "sg:classifiers":[
        {
            "category":"Food & Beverages",
            "subcategory":"Fruits & Vegetables",
            "type":"Retail Goods"
        }
    ],
    "sg:phone":"+1 270 699 2774",
    "sg:postcode":"40033",
    "sg:province":"KY",
    "sg:tags":[
        "produce"
    ],
    "wof:name":"West Michigan Produce",
    "wof:placetype":"venue"
},
  "geometry": {"coordinates":[-85.249083,37.571123],"type":"Point"}
}