{
  "type": "Feature",
  "properties": {
    "addr:full":"1851 Bracht-Piner Rd Morning View KY 41063",
    "addr:housenumber":"1851",
    "addr:postcode":"41063",
    "addr:street":"Bracht-Piner Rd",
    "iso:country":"US",
    "sg:address":"1851 Bracht-Piner Rd",
    "sg:city":"Morning View",
    "sg:classifiers":[
        {
            "category":"Government",
            "subcategory":"Fire Station",
            "type":"Public Place"
        }
    ],
    "sg:phone":"+1 859 356 6916",
    "sg:postcode":"41063",
    "sg:province":"KY",
    "sg:tags":[
        "department"
    ],
    "wof:name":"Fire Department",
    "wof:placetype":"venue"
},
  "geometry": {"coordinates":[-84.538293,38.831325],"type":"Point"}
}