{
  "type": "Feature",
  "properties": {
    "addr:full":"8669 Valley Circle Dr Florence KY 41042",
    "addr:housenumber":"8669",
    "addr:postcode":"41042",
    "addr:street":"Valley Circle Dr",
    "iso:country":"US",
    "sg:address":"8669 Valley Circle Dr",
    "sg:city":"Florence",
    "sg:classifiers":[
        {
            "category":"Building & Trades",
            "subcategory":"Construction",
            "type":"Services"
        }
    ],
    "sg:phone":"+1 859 525 1153",
    "sg:postcode":"41042",
    "sg:province":"KY",
    "sg:tags":[
        "house"
    ],
    "wof:name":"Tsj Homes LLC",
    "wof:placetype":"venue"
},
  "geometry": {"coordinates":[-84.66562,38.981527],"type":"Point"}
}