{
  "type": "Feature",
  "properties": {
    "iso:country":"US",
    "sg:address":"3231 Ruckriegel Pkwy",
    "sg:city":"Louisville",
    "sg:classifiers":[
        {
            "category":"Utilities",
            "subcategory":"Water",
            "type":"Services"
        },
        {
            "category":"Retail",
            "subcategory":"Laundry & Dry Cleaning",
            "type":"Services"
        },
        {
            "category":"Building & Trades",
            "subcategory":"Cleaning & Sanitation",
            "type":"Services"
        },
        {
            "category":"Home & Garden",
            "subcategory":"Household Appliances",
            "type":"Retail Goods"
        }
    ],
    "sg:phone":"+1 502 261 1755",
    "sg:postcode":"40299",
    "sg:province":"KY",
    "sg:tags":[
        "cleaner",
        "upholstery",
        "emergency",
        "duct",
        "house",
        "damage",
        "rug",
        "ventilation",
        "cleaning-industrial",
        "vacuum",
        "curtain",
        "air",
        "drapery",
        "carpet"
    ],
    "sg:website":"http://www.servicemasterclean.com/reslf/smclean_leadform.asp?url=http://www.servicemasterclean.com/reslf/smclean_leadform.asp&partnerName=YellowPages.com&adName=yptl&HGProp=SMClean",
    "wof:name":"ServiceMaster Clean",
    "wof:placetype":"venue"
},
  "geometry": {"coordinates":[-85.558397,38.198495],"type":"Point"}
}