{
  "type": "Feature",
  "properties": {
    "iso:country":"US",
    "sg:address":"1218 S Main St",
    "sg:city":"London",
    "sg:classifiers":[
        {
            "category":"Autos & Motor Vehicles",
            "subcategory":"Auto Supplies",
            "type":"Retail Goods"
        }
    ],
    "sg:phone":"+1 606 862 1649",
    "sg:postcode":"40741",
    "sg:province":"KY",
    "sg:tags":[
        "automobile",
        "parts"
    ],
    "wof:name":"O'Reilly Auto Parts",
    "wof:placetype":"venue"
},
  "geometry": {"coordinates":[-84.075166,37.117461],"type":"Point"}
}