{
  "type": "Feature",
  "properties": {
    "iso:country":"US",
    "sg:address":"9965 Levee Rd",
    "sg:city":"Jeffersonville",
    "sg:classifiers":[
        {
            "category":"Organizations",
            "subcategory":"Religious Organization",
            "type":"Services"
        }
    ],
    "sg:phone":"+1 859 497 2223",
    "sg:postcode":"40337",
    "sg:province":"KY",
    "wof:name":"Pine Grove Church",
    "wof:placetype":"venue"
},
  "geometry": {"coordinates":[-83.938912,37.958805],"type":"Point"}
}