{
  "type": "Feature",
  "properties": {
    "addr:full":"10711 Easum Rd Louisville KY 40299",
    "addr:housenumber":"10711",
    "addr:postcode":"40299",
    "addr:street":"Easum Rd",
    "iso:country":"US",
    "sg:address":"10711 Easum Rd",
    "sg:city":"Louisville",
    "sg:classifiers":[
        {
            "category":"Travel",
            "subcategory":"Travel Agent",
            "type":"Entertainment"
        }
    ],
    "sg:phone":"+1 502 267 1580",
    "sg:postcode":"40299",
    "sg:province":"KY",
    "sg:tags":[
        "agency",
        "services-commercial"
    ],
    "wof:name":"Blanford Travel",
    "wof:placetype":"venue"
},
  "geometry": {"coordinates":[-85.55640200000001,38.16569],"type":"Point"}
}