{
  "type": "Feature",
  "properties": {
    "iso:country":"US",
    "sg:address":"934 Allen Schoolhouse Rd",
    "sg:city":"Columbia",
    "sg:classifiers":[
        {
            "category":"Farming",
            "subcategory":"Dairy Farm",
            "type":"Manufacturing & Wholesale Goods"
        }
    ],
    "sg:phone":"+1 270 384 2109",
    "sg:postcode":"42728",
    "sg:province":"KY",
    "wof:name":"Tim Baker",
    "wof:placetype":"venue"
},
  "geometry": {"coordinates":[-85.185721,37.121718],"type":"Point"}
}