{
  "type": "Feature",
  "properties": {
    "addr:full":"1401 Cecil Ln Bardstown KY 40004",
    "addr:housenumber":"1401",
    "addr:postcode":"40004",
    "addr:street":"Cecil Ln",
    "iso:country":"US",
    "sg:address":"1401 Cecil Ln",
    "sg:city":"Bardstown",
    "sg:classifiers":[
        {
            "category":"Real Estate",
            "subcategory":"Real Estate Agent",
            "type":"Services"
        }
    ],
    "sg:phone":"+1 502 350 3633",
    "sg:postcode":"40004",
    "sg:province":"KY",
    "wof:name":"Dianne Culv Borders",
    "wof:placetype":"venue"
},
  "geometry": {"coordinates":[-85.509413,37.767688],"type":"Point"}
}