{
  "type": "Feature",
  "properties": {
    "iso:country":"US",
    "sg:address":"811 Euclid Ave",
    "sg:city":"Lexington",
    "sg:classifiers":[
        {
            "category":"Food & Beverages",
            "subcategory":"Groceries & Convenience Stores",
            "type":"Retail Goods"
        }
    ],
    "sg:phone":"+1 859 268 8822",
    "sg:postcode":"40502",
    "sg:province":"KY",
    "sg:tags":[
        "grocer"
    ],
    "wof:name":"Visha International Sprmrkt",
    "wof:placetype":"venue"
},
  "geometry": {"coordinates":[-84.490545,38.029737],"type":"Point"}
}