{
  "type": "Feature",
  "properties": {
    "iso:country":"US",
    "sg:address":"1158 US Hwy 25E",
    "sg:city":"Barbourville",
    "sg:classifiers":[
        {
            "category":"Autos & Motor Vehicles",
            "subcategory":"Automobile Sales",
            "type":"Retail Goods"
        }
    ],
    "sg:phone":"+1 606 546 8119",
    "sg:postcode":"40977",
    "sg:province":"KY",
    "sg:tags":[
        "car",
        "dealer"
    ],
    "wof:name":"Gray's Motor Sales",
    "wof:placetype":"venue"
},
  "geometry": {"coordinates":[-83.69385,36.755647],"type":"Point"}
}