{
  "type": "Feature",
  "properties": {
    "addr:full":"2785 Mannington Loop Nortonville KY 42442",
    "addr:housenumber":"2785",
    "addr:postcode":"42442",
    "addr:street":"Mannington Loop",
    "iso:country":"US",
    "sg:address":"2785 Mannington Loop",
    "sg:city":"Nortonville",
    "sg:classifiers":[
        {
            "category":"Professional",
            "type":"Services"
        }
    ],
    "sg:phone":"+1 270 676 3972",
    "sg:postcode":"42442",
    "sg:province":"KY",
    "sg:tags":[
        "establishment"
    ],
    "wof:name":"Acme Tower Group",
    "wof:placetype":"venue"
},
  "geometry": {"coordinates":[-87.48115799999999,37.126068],"type":"Point"}
}