{
  "type": "Feature",
  "properties": {
    "addr:full":"1008 Mary Laidley Dr Covington KY 41017",
    "addr:housenumber":"1008",
    "addr:postcode":"41017",
    "addr:street":"Mary Laidley Dr",
    "iso:country":"US",
    "sg:address":"1008 Mary Laidley Dr",
    "sg:city":"Covington",
    "sg:classifiers":[
        {
            "category":"Retail",
            "subcategory":"Auto Rental",
            "type":"Services"
        },
        {
            "category":"Building & Trades",
            "subcategory":"Equipment Rental",
            "type":"Services"
        },
        {
            "category":"Retail",
            "subcategory":"Storage",
            "type":"Services"
        }
    ],
    "sg:phone":"+1 859 356 1054",
    "sg:postcode":"41017",
    "sg:province":"KY",
    "sg:tags":[
        "renting",
        "moving-self",
        "leasing",
        "truck",
        "van",
        "moving",
        "trailer"
    ],
    "sg:website":"http://www.budgettruck.com",
    "wof:name":"Budget Truck Rental",
    "wof:placetype":"venue"
},
  "geometry": {"coordinates":[-84.535521,39.002752],"type":"Point"}
}