{
  "type": "Feature",
  "properties": {
    "addr:full":"896 Fenley Ave Louisville KY 40222",
    "addr:housenumber":"896",
    "addr:postcode":"40222",
    "addr:street":"Fenley Ave",
    "iso:country":"US",
    "sg:address":"896 Fenley Ave",
    "sg:city":"Louisville",
    "sg:classifiers":[
        {
            "category":"Professional",
            "subcategory":"Business Services",
            "type":"Services"
        }
    ],
    "sg:phone":"+1 502 339 7321",
    "sg:postcode":"40222",
    "sg:province":"KY",
    "wof:name":"South Wind Design",
    "wof:placetype":"venue"
},
  "geometry": {"coordinates":[-85.615433,38.262269],"type":"Point"}
}