{
  "type": "Feature",
  "properties": {
    "iso:country":"US",
    "sg:address":"4617 Illinois Ave",
    "sg:city":"Louisville",
    "sg:classifiers":[
        {
            "category":"Professional",
            "subcategory":"Art Services",
            "type":"Services"
        },
        {
            "category":"Building & Trades",
            "subcategory":"Construction",
            "type":"Services"
        },
        {
            "category":"Military Area",
            "subcategory":"Armory",
            "type":"Public Place"
        }
    ],
    "sg:phone":"+1 502 459 1509",
    "sg:postcode":"40213",
    "sg:province":"KY",
    "sg:tags":[
        "ornamental",
        "fence",
        "repair",
        "work",
        "metal",
        "contractor",
        "fence-sales"
    ],
    "wof:name":"T & J Fence Co",
    "wof:placetype":"venue"
},
  "geometry": {"coordinates":[-85.699978,38.187989],"type":"Point"}
}