{
  "type": "Feature",
  "properties": {
    "iso:country":"US",
    "sg:address":"708 Powell Ln",
    "sg:city":"Flatwoods",
    "sg:classifiers":[
        {
            "category":"Insurance",
            "subcategory":"Insurance Agent",
            "type":"Services"
        }
    ],
    "sg:phone":"+1 606 834 0131",
    "sg:postcode":"41139",
    "sg:province":"KY",
    "wof:name":"Insurance Solutions Of Ky Inc",
    "wof:placetype":"venue"
},
  "geometry": {"coordinates":[-82.710238,38.51837],"type":"Point"}
}