{
  "type": "Feature",
  "properties": {
    "addr:full":"648 Dixie Hwy E Elizabethtown KY 42701",
    "addr:housenumber":"648",
    "addr:postcode":"42701",
    "addr:street":"Dixie Hwy E",
    "iso:country":"US",
    "sg:address":"648 Dixie Hwy E",
    "sg:city":"Elizabethtown",
    "sg:classifiers":[
        {
            "category":"Farming",
            "subcategory":"Dairy Farm",
            "type":"Manufacturing & Wholesale Goods"
        }
    ],
    "sg:phone":"+1 270 769 3539",
    "sg:postcode":"42701",
    "sg:province":"KY",
    "wof:name":"Southern Belle Dairy",
    "wof:placetype":"venue"
},
  "geometry": {"coordinates":[-85.84864399999999,37.680097],"type":"Point"}
}