{
  "type": "Feature",
  "properties": {
    "iso:country":"US",
    "sg:address":"270 State Hwy 131",
    "sg:city":"Mayfield",
    "sg:classifiers":[
        {
            "category":"Organizations",
            "subcategory":"Community Association",
            "type":"Services"
        }
    ],
    "sg:phone":"+1 270 247 9110",
    "sg:postcode":"42066",
    "sg:province":"KY",
    "sg:tags":[
        "fraternal"
    ],
    "wof:name":"Loyal Order Of Moose",
    "wof:placetype":"venue"
},
  "geometry": {"coordinates":[-88.59598099999999,36.763318],"type":"Point"}
}