{
  "type": "Feature",
  "properties": {
    "addr:full":"132 Woodward Ave Brooksville KY 41004",
    "addr:housenumber":"132",
    "addr:postcode":"41004",
    "addr:street":"Woodward Ave",
    "iso:country":"US",
    "sg:address":"132 Woodward Ave",
    "sg:city":"Brooksville",
    "sg:classifiers":[
        {
            "category":"Insurance",
            "subcategory":"Insurance Agent",
            "type":"Services"
        }
    ],
    "sg:phone":"+1 606 735 2408",
    "sg:postcode":"41004",
    "sg:province":"KY",
    "wof:name":"Farm Bureau Insurance",
    "wof:placetype":"venue"
},
  "geometry": {"coordinates":[-84.06477099999999,38.681527],"type":"Point"}
}