{
  "type": "Feature",
  "properties": {
    "addr:full":"1977 Cumberland Falls Hwy Corbin KY 40701",
    "addr:housenumber":"1977",
    "addr:postcode":"40701",
    "addr:street":"Cumberland Falls Hwy",
    "iso:country":"US",
    "sg:address":"1977 Cumberland Falls Hwy",
    "sg:city":"Corbin",
    "sg:classifiers":[
        {
            "category":"Restaurant",
            "type":"Food & Drink"
        }
    ],
    "sg:menulink":"http://www.allmenus.com/ky/corbin/186782-mcdonalds/menu/",
    "sg:phone":"+1 606 526 9002",
    "sg:postcode":"40701",
    "sg:province":"KY",
    "sg:tags":[
        "burger",
        "american"
    ],
    "wof:name":"McDonald's",
    "wof:placetype":"venue"
},
  "geometry": {"coordinates":[-84.115483,36.920465],"type":"Point"}
}