{
  "type": "Feature",
  "properties": {
    "iso:country":"US",
    "sg:address":"509 Obyrne Ave",
    "sg:city":"Louisville",
    "sg:classifiers":[
        {
            "category":"Professional",
            "type":"Services"
        }
    ],
    "sg:phone":"+1 502 253 6999",
    "sg:postcode":"40223",
    "sg:province":"KY",
    "sg:tags":[
        "establishment"
    ],
    "wof:name":"BBJ Enterprises LLC",
    "wof:placetype":"venue"
},
  "geometry": {"coordinates":[-85.513801,38.248194],"type":"Point"}
}