{
  "type": "Feature",
  "properties": {
    "iso:country":"US",
    "sg:address":"365 Rose Ln",
    "sg:city":"Harrodsburg",
    "sg:classifiers":[
        {
            "category":"Personal",
            "type":"Services"
        }
    ],
    "sg:phone":"+1 859 734 2781",
    "sg:postcode":"40330",
    "sg:province":"KY",
    "wof:name":"Tan Time",
    "wof:placetype":"venue"
},
  "geometry": {"coordinates":[-84.88296,37.737934],"type":"Point"}
}