{
  "type": "Feature",
  "properties": {
    "iso:country":"US",
    "sg:address":"3037 Dixie Hwy",
    "sg:city":"Edgewood",
    "sg:classifiers":[
        {
            "category":"Real Estate",
            "subcategory":"Real Estate Agent",
            "type":"Services"
        }
    ],
    "sg:phone":"+1 859 341 1980",
    "sg:postcode":"41017",
    "sg:province":"KY",
    "sg:tags":[
        "appraiser"
    ],
    "wof:name":"Appraisal Co",
    "wof:placetype":"venue"
},
  "geometry": {"coordinates":[-84.58438,39.023515],"type":"Point"}
}