{
  "type": "Feature",
  "properties": {
    "iso:country":"US",
    "sg:address":"257 Regency Cir",
    "sg:city":"Lexington",
    "sg:classifiers":[
        {
            "category":"Building & Trades",
            "subcategory":"Electrical",
            "type":"Services"
        }
    ],
    "sg:phone":"+1 859 275 1166",
    "sg:postcode":"40503",
    "sg:province":"KY",
    "sg:tags":[
        "electric",
        "contractor"
    ],
    "wof:name":"Kentucky Professional Assssmnt",
    "wof:placetype":"venue"
},
  "geometry": {"coordinates":[-84.52292199999999,38.011875],"type":"Point"}
}