{
  "type": "Feature",
  "properties": {
    "iso:country":"US",
    "sg:address":"538 US Hwy 68 E",
    "sg:city":"Benton",
    "sg:classifiers":[
        {
            "category":"Food & Beverages",
            "subcategory":"Groceries & Convenience Stores",
            "type":"Retail Goods"
        }
    ],
    "sg:phone":"+1 270 527 3090",
    "sg:postcode":"42025",
    "sg:province":"KY",
    "sg:tags":[
        "grocer"
    ],
    "wof:name":"King Brothers Super Market",
    "wof:placetype":"venue"
},
  "geometry": {"coordinates":[-88.340335,36.922276],"type":"Point"}
}