{
  "type": "Feature",
  "properties": {
    "iso:country":"US",
    "sg:address":"8748 State Hwy 7",
    "sg:city":"Viper",
    "sg:classifiers":[
        {
            "category":"Shopping",
            "subcategory":"Tobacco",
            "type":"Retail Goods"
        }
    ],
    "sg:phone":"+1 606 476 8229",
    "sg:postcode":"41774",
    "sg:province":"KY",
    "sg:tags":[
        "cigarette",
        "cigar",
        "dealer"
    ],
    "wof:name":"Joe's Video & Tobacco Outlet",
    "wof:placetype":"venue"
},
  "geometry": {"coordinates":[-83.087968,37.157036],"type":"Point"}
}