{
  "type": "Feature",
  "properties": {
    "iso:country":"US",
    "sg:address":"147 Combs Ct",
    "sg:city":"Shepherdsville",
    "sg:classifiers":[
        {
            "category":"Professional",
            "subcategory":"Lawyer & Legal Services",
            "type":"Services"
        }
    ],
    "sg:phone":"+1 502 957 3318",
    "sg:postcode":"40165",
    "sg:province":"KY",
    "sg:tags":[
        "attorney"
    ],
    "wof:name":"Patrick B Mc Clure",
    "wof:placetype":"venue"
},
  "geometry": {"coordinates":[-85.716857,37.989546],"type":"Point"}
}