{
  "type": "Feature",
  "properties": {
    "addr:full":"401 W Main St Lexington KY 40507",
    "addr:housenumber":"401",
    "addr:postcode":"40507",
    "addr:street":"W Main St",
    "iso:country":"US",
    "sg:address":"401 W Main St",
    "sg:city":"Lexington",
    "sg:classifiers":[
        {
            "category":"Shopping",
            "subcategory":"Jewelry",
            "type":"Retail Goods"
        }
    ],
    "sg:phone":"+1 859 455 8111",
    "sg:postcode":"40507",
    "sg:province":"KY",
    "sg:tags":[
        "platinum",
        "silver",
        "gold"
    ],
    "wof:name":"Savane Silver",
    "wof:placetype":"venue"
},
  "geometry": {"coordinates":[-84.50038000000001,38.049396],"type":"Point"}
}