{
  "type": "Feature",
  "properties": {
    "iso:country":"US",
    "sg:address":"7010 Sky Blue Ave",
    "sg:city":"Louisville",
    "sg:classifiers":[
        {
            "category":"Professional",
            "subcategory":"Accounting & Tax Preparation",
            "type":"Services"
        }
    ],
    "sg:phone":"+1 502 935 2110",
    "sg:postcode":"40258",
    "sg:province":"KY",
    "sg:tags":[
        "bookkeeping",
        "billing"
    ],
    "wof:name":"Kentuckiana Billing Solutions Inc",
    "wof:placetype":"venue"
},
  "geometry": {"coordinates":[-85.851551,38.149113],"type":"Point"}
}