{
  "type": "Feature",
  "properties": {
    "iso:country":"US",
    "sg:address":"1151 S Shelby St",
    "sg:city":"Louisville",
    "sg:classifiers":[
        {
            "category":"Building & Trades",
            "subcategory":"Construction",
            "type":"Services"
        }
    ],
    "sg:phone":"+1 502 634 9673",
    "sg:postcode":"40203",
    "sg:province":"KY",
    "sg:tags":[
        "builder",
        "patio",
        "deck"
    ],
    "wof:name":"Petersen Inc",
    "wof:placetype":"venue"
},
  "geometry": {"coordinates":[-85.741299,38.234044],"type":"Point"}
}