{
  "type": "Feature",
  "properties": {
    "iso:country":"US",
    "sg:address":"1104 Willow Springs Dr",
    "sg:city":"Louisville",
    "sg:classifiers":[
        {
            "category":"Professional",
            "subcategory":"Business Services",
            "type":"Services"
        }
    ],
    "sg:phone":"+1 502 425 4623",
    "sg:postcode":"40242",
    "sg:province":"KY",
    "wof:name":"Ogre Business Solutions LLC",
    "wof:placetype":"venue"
},
  "geometry": {"coordinates":[-85.594052,38.26391],"type":"Point"}
}