{
  "type": "Feature",
  "properties": {
    "iso:country":"US",
    "sg:address":"8700 Stockport Rd",
    "sg:city":"Louisville",
    "sg:classifiers":[
        {
            "category":"Manufacturing",
            "subcategory":"Building Materials",
            "type":"Manufacturing & Wholesale Goods"
        }
    ],
    "sg:phone":"+1 502 426 4296",
    "sg:postcode":"40222",
    "sg:province":"KY",
    "sg:tags":[
        "metal",
        "work",
        "sheet"
    ],
    "wof:name":"Miller Sheet Metal Corporation",
    "wof:placetype":"venue"
},
  "geometry": {"coordinates":[-85.594818,38.232071],"type":"Point"}
}