{
  "type": "Feature",
  "properties": {
    "addr:full":"17 W 8th St Covington KY 41011",
    "addr:housenumber":"17",
    "addr:postcode":"41011",
    "addr:street":"W 8Th St",
    "iso:country":"US",
    "sg:address":"17 W 8th St",
    "sg:city":"Covington",
    "sg:classifiers":[
        {
            "category":"Retail",
            "subcategory":"Auto Repair",
            "type":"Services"
        }
    ],
    "sg:phone":"+1 859 491 4200",
    "sg:postcode":"41011",
    "sg:province":"KY",
    "sg:tags":[
        "body",
        "automobile",
        "painting"
    ],
    "wof:name":"Mike Foulk's Auto Body",
    "wof:placetype":"venue"
},
  "geometry": {"coordinates":[-84.511135,39.081955],"type":"Point"}
}