{
  "type": "Feature",
  "properties": {
    "addr:full":"4970 US Hwy 27 Somerset KY 42501",
    "addr:housenumber":"4970",
    "addr:postcode":"42501",
    "addr:street":"Us Hwy 27",
    "iso:country":"US",
    "sg:address":"4970 US Hwy 27",
    "sg:city":"Somerset",
    "sg:classifiers":[
        {
            "category":"Home & Garden",
            "subcategory":"Building Materials",
            "type":"Retail Goods"
        }
    ],
    "sg:phone":"+1 606 676 0710",
    "sg:postcode":"42501",
    "sg:province":"KY",
    "sg:tags":[
        "wallpaper"
    ],
    "wof:name":"Wallpaper Outlet",
    "wof:placetype":"venue"
},
  "geometry": {"coordinates":[-84.62633,37.039715],"type":"Point"}
}