{
  "type": "Feature",
  "properties": {
    "addr:full":"2100 Millvale Rd Louisville KY 40205",
    "addr:housenumber":"2100",
    "addr:postcode":"40205",
    "addr:street":"Millvale Rd",
    "iso:country":"US",
    "sg:address":"2100 Millvale Rd",
    "sg:city":"Louisville",
    "sg:classifiers":[
        {
            "category":"Health Services",
            "subcategory":"Nursing And Care Facility",
            "type":"Services"
        }
    ],
    "sg:phone":"+1 502 451 0990",
    "sg:postcode":"40205",
    "sg:province":"KY",
    "sg:tags":[
        "home",
        "convalescent"
    ],
    "wof:name":"Four Courts Senior Ctr",
    "wof:placetype":"venue"
},
  "geometry": {"coordinates":[-85.684243,38.230658],"type":"Point"}
}