{
  "type": "Feature",
  "properties": {
    "iso:country":"US",
    "sg:address":"6226 Clark Station Rd",
    "sg:city":"Finchville",
    "sg:classifiers":[
        {
            "category":"Building & Trades",
            "subcategory":"Plumbing",
            "type":"Services"
        }
    ],
    "sg:phone":"+1 502 834 7436",
    "sg:postcode":"40022",
    "sg:province":"KY",
    "sg:tags":[
        "plumbing",
        "contractor"
    ],
    "wof:name":"G Blansett Plumbing",
    "wof:placetype":"venue"
},
  "geometry": {"coordinates":[-85.367575,38.167018],"type":"Point"}
}