{
  "type": "Feature",
  "properties": {
    "addr:full":"200 Christian St Whitesville KY 42337",
    "addr:housenumber":"200",
    "addr:postcode":"42337",
    "addr:street":"Christian St",
    "iso:country":"US",
    "sg:address":"200 Christian St",
    "sg:city":"Whitesville",
    "sg:classifiers":[
        {
            "category":"Building & Trades",
            "subcategory":"Construction",
            "type":"Services"
        }
    ],
    "sg:phone":"+1 270 275 4500",
    "sg:postcode":"42337",
    "sg:province":"KY",
    "sg:tags":[
        "masonry",
        "contractor"
    ],
    "wof:name":"Charles Masonry",
    "wof:placetype":"venue"
},
  "geometry": {"coordinates":[-87.050445,37.218246],"type":"Point"}
}