{
  "type": "Feature",
  "properties": {
    "iso:country":"US",
    "sg:address":"1226 Highland Ave",
    "sg:city":"Louisville",
    "sg:classifiers":[
        {
            "category":"Home & Garden",
            "subcategory":"Building Materials",
            "type":"Retail Goods"
        }
    ],
    "sg:phone":"+1 502 583 7745",
    "sg:postcode":"40204",
    "sg:province":"KY",
    "sg:tags":[
        "windows"
    ],
    "wof:name":"Ketuckiana Window & Doors LLC",
    "wof:placetype":"venue"
},
  "geometry": {"coordinates":[-85.729598,38.237881],"type":"Point"}
}