{
  "type": "Feature",
  "properties": {
    "addr:full":"510 Maple Crest Way Elizabethtown KY 42701",
    "addr:housenumber":"510",
    "addr:postcode":"42701",
    "addr:street":"Maple Crest Way",
    "iso:country":"US",
    "sg:address":"510 Maple Crest Way",
    "sg:city":"Elizabethtown",
    "sg:classifiers":[
        {
            "category":"Organizations",
            "subcategory":"Religious Organization",
            "type":"Services"
        }
    ],
    "sg:phone":"+1 270 765 6991",
    "sg:postcode":"42701",
    "sg:province":"KY",
    "sg:tags":[
        "church"
    ],
    "wof:name":"Church Of God Of Prophecy Ofc",
    "wof:placetype":"venue"
},
  "geometry": {"coordinates":[-85.869795,37.744036],"type":"Point"}
}