{
  "type": "Feature",
  "properties": {
    "iso:country":"US",
    "sg:address":"1111 Shive Ln",
    "sg:city":"Bowling Green",
    "sg:classifiers":[
        {
            "category":"Building & Trades",
            "subcategory":"Construction",
            "type":"Services"
        }
    ],
    "sg:phone":"+1 270 782 2420",
    "sg:postcode":"42103",
    "sg:province":"KY",
    "sg:tags":[
        "general",
        "contractor"
    ],
    "wof:name":"Associated General Contractor",
    "wof:placetype":"venue"
},
  "geometry": {"coordinates":[-86.421404,36.946293],"type":"Point"}
}