{
  "type": "Feature",
  "properties": {
    "addr:full":"712 Kentucky Ave Paducah KY 42003",
    "addr:housenumber":"712",
    "addr:postcode":"42003",
    "addr:street":"Kentucky Ave",
    "iso:country":"US",
    "sg:address":"712 Kentucky Ave",
    "sg:city":"Paducah",
    "sg:classifiers":[
        {
            "category":"Professional",
            "subcategory":"Advertising",
            "type":"Services"
        }
    ],
    "sg:phone":"+1 270 444 0402",
    "sg:postcode":"42003",
    "sg:province":"KY",
    "sg:tags":[
        "distribution"
    ],
    "wof:name":"T & M Distributing Div",
    "wof:placetype":"venue"
},
  "geometry": {"coordinates":[-88.60127900000001,37.084076],"type":"Point"}
}