{
  "type": "Feature",
  "properties": {
    "addr:full":"12236 Ridgemont Rd Louisville KY 40229",
    "addr:housenumber":"12236",
    "addr:postcode":"40229",
    "addr:street":"Ridgemont Rd",
    "iso:country":"US",
    "sg:address":"12236 Ridgemont Rd",
    "sg:city":"Louisville",
    "sg:classifiers":[
        {
            "category":"Retail",
            "subcategory":"Animal Services",
            "type":"Services"
        }
    ],
    "sg:phone":"+1 502 957 6119",
    "sg:postcode":"40229",
    "sg:province":"KY",
    "wof:name":"Fancee Paws Dog Grooming",
    "wof:placetype":"venue"
},
  "geometry": {"coordinates":[-85.680994,38.066532],"type":"Point"}
}