{
  "type": "Feature",
  "properties": {
    "addr:full":"910 S Main St Hopkinsville KY 42240",
    "addr:housenumber":"910",
    "addr:postcode":"42240",
    "addr:street":"S Main St",
    "iso:country":"US",
    "sg:address":"910 S Main St",
    "sg:city":"Hopkinsville",
    "sg:classifiers":[
        {
            "category":"Shopping",
            "type":"Retail Goods"
        }
    ],
    "sg:phone":"+1 270 889 0434",
    "sg:postcode":"42240",
    "sg:province":"KY",
    "sg:tags":[
        "cosmetic",
        "perfume"
    ],
    "wof:name":"Merle Norman Cosmetics",
    "wof:placetype":"venue"
},
  "geometry": {"coordinates":[-87.48914000000001,36.865028],"type":"Point"}
}