{
  "type": "Feature",
  "properties": {
    "iso:country":"US",
    "sg:address":"561 Blankenbaker Ln",
    "sg:city":"St Matthews",
    "sg:classifiers":[
        {
            "category":"Museum",
            "type":"Entertainment"
        }
    ],
    "sg:phone":"+1 502 897 9845",
    "sg:postcode":"40207",
    "sg:province":"KY",
    "sg:website":"www.locustgrove.org",
    "wof:name":"Locust Grove Historic Site",
    "wof:placetype":"venue"
},
  "geometry": {"coordinates":[-85.66369299999999,38.28649],"type":"Point"}
}