{
  "type": "Feature",
  "properties": {
    "iso:country":"US",
    "sg:address":"4619 Astor Rd",
    "sg:city":"Louisville",
    "sg:classifiers":[
        {
            "category":"Building & Trades",
            "subcategory":"Construction",
            "type":"Services"
        }
    ],
    "sg:phone":"+1 502 966 4019",
    "sg:postcode":"40218",
    "sg:province":"KY",
    "sg:tags":[
        "paving",
        "contractor"
    ],
    "wof:name":"All Pro Paving",
    "wof:placetype":"venue"
},
  "geometry": {"coordinates":[-85.691473,38.187549],"type":"Point"}
}