{
  "type": "Feature",
  "properties": {
    "iso:country":"US",
    "sg:address":"100 Tiger Way",
    "sg:city":"Georgetown",
    "sg:classifiers":[
        {
            "category":"Restaurant",
            "type":"Food & Drink"
        }
    ],
    "sg:phone":"+1 502 570 9959",
    "sg:postcode":"40324",
    "sg:province":"KY",
    "sg:tags":[
        "style",
        "american",
        "family"
    ],
    "sg:website":"http://www.rubytuesday.com",
    "wof:name":"Ruby Tuesday Restaurant",
    "wof:placetype":"venue"
},
  "geometry": {"coordinates":[-84.540192,38.222],"type":"Point"}
}