{
  "type": "Feature",
  "properties": {
    "addr:full":"830 Eastern Byp Richmond KY 40475",
    "addr:housenumber":"830",
    "addr:postcode":"40475",
    "addr:street":"Eastern Byp",
    "iso:country":"US",
    "sg:address":"830 Eastern Byp",
    "sg:city":"Richmond",
    "sg:classifiers":[
        {
            "category":"Shopping",
            "subcategory":"Books",
            "type":"Retail Goods"
        }
    ],
    "sg:phone":"+1 859 626 5078",
    "sg:postcode":"40475",
    "sg:province":"KY",
    "sg:tags":[
        "dealer"
    ],
    "wof:name":"Hastings Books Music Video",
    "wof:placetype":"venue"
},
  "geometry": {"coordinates":[-84.273802,37.733636],"type":"Point"}
}