{
  "type": "Feature",
  "properties": {
    "addr:full":"10790 Alexandria Pike Alexandria KY 41001",
    "addr:housenumber":"10790",
    "addr:postcode":"41001",
    "addr:street":"Alexandria Pike",
    "iso:country":"US",
    "sg:address":"10790 Alexandria Pike",
    "sg:city":"Alexandria",
    "sg:classifiers":[
        {
            "category":"Building & Trades",
            "subcategory":"Landscaping Services",
            "type":"Services"
        }
    ],
    "sg:phone":"+1 859 635 3073",
    "sg:postcode":"41001",
    "sg:province":"KY",
    "sg:tags":[
        "landscape",
        "contractor"
    ],
    "wof:name":"Richie Trucking",
    "wof:placetype":"venue"
},
  "geometry": {"coordinates":[-84.38646900000001,38.903805],"type":"Point"}
}