{
  "type": "Feature",
  "properties": {
    "iso:country":"US",
    "sg:address":"504 S 4th St",
    "sg:city":"Danville",
    "sg:classifiers":[
        {
            "category":"Retail",
            "subcategory":"Laundry & Dry Cleaning",
            "type":"Services"
        }
    ],
    "sg:phone":"+1 859 236 4274",
    "sg:postcode":"40422",
    "sg:province":"KY",
    "sg:tags":[
        "cleaners"
    ],
    "wof:name":"Rainbow Cleaners & Draperies",
    "wof:placetype":"venue"
},
  "geometry": {"coordinates":[-84.774624,37.638749],"type":"Point"}
}