{
  "type": "Feature",
  "properties": {
    "iso:country":"US",
    "sg:address":"327 Windy Ridge",
    "sg:city":"Bedford",
    "sg:classifiers":[
        {
            "category":"Retail",
            "subcategory":"Repair Shop",
            "type":"Services"
        }
    ],
    "sg:phone":"+1 502 732 6322",
    "sg:postcode":"40006",
    "sg:province":"KY",
    "sg:tags":[
        "scooter",
        "motorcycle",
        "motor"
    ],
    "wof:name":"American At Large",
    "wof:placetype":"venue"
},
  "geometry": {"coordinates":[-85.252538,38.65906],"type":"Point"}
}