{
  "type": "Feature",
  "properties": {
    "addr:full":"122 N Allison Ave Barbourville KY 40906",
    "addr:housenumber":"122",
    "addr:postcode":"40906",
    "addr:street":"N Allison Ave",
    "iso:country":"US",
    "sg:address":"122 N Allison Ave",
    "sg:city":"Barbourville",
    "sg:classifiers":[
        {
            "category":"Government",
            "subcategory":"Post Office",
            "type":"Public Place"
        }
    ],
    "sg:phone":"+1 606 546 3777",
    "sg:postcode":"40906",
    "sg:province":"KY",
    "wof:name":"US Post Office",
    "wof:placetype":"venue"
},
  "geometry": {"coordinates":[-83.883262,36.869551],"type":"Point"}
}