{
  "type": "Feature",
  "properties": {
    "iso:country":"US",
    "sg:address":"1622 E Cumberland Ave",
    "sg:city":"Middlesboro",
    "sg:classifiers":[
        {
            "category":"Government",
            "subcategory":"Court House",
            "type":"Public Place"
        }
    ],
    "sg:phone":"+1 606 248 1172",
    "sg:postcode":"40965",
    "sg:province":"KY",
    "sg:tags":[
        "county"
    ],
    "wof:name":"Bell County Court Clerk",
    "wof:placetype":"venue"
},
  "geometry": {"coordinates":[-83.708968,36.607713],"type":"Point"}
}