{
  "type": "Feature",
  "properties": {
    "addr:full":"825 Nashville St Russellville KY 42276",
    "addr:housenumber":"825",
    "addr:postcode":"42276",
    "addr:street":"Nashville St",
    "iso:country":"US",
    "sg:address":"825 Nashville St",
    "sg:city":"Russellville",
    "sg:classifiers":[
        {
            "category":"Organizations",
            "subcategory":"Religious Organization",
            "type":"Services"
        }
    ],
    "sg:phone":"+1 270 726 6298",
    "sg:postcode":"42276",
    "sg:province":"KY",
    "sg:tags":[
        "clergy"
    ],
    "wof:name":"Craig Jackson",
    "wof:placetype":"venue"
},
  "geometry": {"coordinates":[-86.88982900000001,36.835795],"type":"Point"}
}