{
  "type": "Feature",
  "properties": {
    "iso:country":"US",
    "sg:address":"33 Montgomery St",
    "sg:city":"Erlanger",
    "sg:classifiers":[
        {
            "category":"Autos & Motor Vehicles",
            "subcategory":"Auto Supplies",
            "type":"Retail Goods"
        }
    ],
    "sg:phone":"+1 859 341 2728",
    "sg:postcode":"41018",
    "sg:province":"KY",
    "sg:tags":[
        "tire"
    ],
    "sg:website":"www.sumereltire.com",
    "wof:name":"Bob Sumerel Tire & Svc",
    "wof:placetype":"venue"
},
  "geometry": {"coordinates":[-84.59191300000001,39.023638],"type":"Point"}
}