{
  "type": "Feature",
  "properties": {
    "iso:country":"US",
    "sg:address":"483 Hart Rd",
    "sg:city":"Lexington",
    "sg:classifiers":[
        {
            "category":"Health Services",
            "subcategory":"Doctor",
            "type":"Services"
        }
    ],
    "sg:phone":"+1 859 278 9536",
    "sg:postcode":"40502",
    "sg:province":"KY",
    "sg:tags":[
        "physician",
        "surgeon"
    ],
    "wof:name":"Robert W Shier MD",
    "wof:placetype":"venue"
},
  "geometry": {"coordinates":[-84.485772,38.025126],"type":"Point"}
}