{
  "type": "Feature",
  "properties": {
    "iso:country":"US",
    "sg:address":"810 W Stephen Foster Ave",
    "sg:city":"Bardstown",
    "sg:classifiers":[
        {
            "category":"Government",
            "subcategory":"Jail",
            "type":"Public Place"
        }
    ],
    "sg:phone":"+1 502 348 1860",
    "sg:postcode":"40004",
    "sg:province":"KY",
    "sg:tags":[
        "county",
        "govt",
        "institution"
    ],
    "wof:name":"Nelson County Jail",
    "wof:placetype":"venue"
},
  "geometry": {"coordinates":[-85.47878300000001,37.810686],"type":"Point"}
}