{
  "type": "Feature",
  "properties": {
    "addr:full":"1385 Pole Bridge School Rd Nancy KY 42544",
    "addr:housenumber":"1385",
    "addr:postcode":"42544",
    "addr:street":"Pole Bridge School Rd",
    "iso:country":"US",
    "sg:address":"1385 Pole Bridge School Rd",
    "sg:city":"Nancy",
    "sg:classifiers":[
        {
            "category":"Manufacturing",
            "subcategory":"Signs",
            "type":"Manufacturing & Wholesale Goods"
        }
    ],
    "sg:phone":"+1 606 636 6197",
    "sg:postcode":"42544",
    "sg:province":"KY",
    "wof:name":"Cross Creek Designs",
    "wof:placetype":"venue"
},
  "geometry": {"coordinates":[-84.723331,37.001995],"type":"Point"}
}