{
  "type": "Feature",
  "properties": {
    "iso:country":"US",
    "sg:address":"299 Briggs Ln",
    "sg:city":"Vine Grove",
    "sg:classifiers":[
        {
            "category":"Organizations",
            "subcategory":"Community Association",
            "type":"Services"
        }
    ],
    "sg:phone":"+1 270 877 2138",
    "sg:postcode":"40175",
    "sg:province":"KY",
    "sg:tags":[
        "club"
    ],
    "wof:name":"Veterans Of Foreign Wars",
    "wof:placetype":"venue"
},
  "geometry": {"coordinates":[-85.986395,37.854929],"type":"Point"}
}