{
  "type": "Feature",
  "properties": {
    "iso:country":"US",
    "sg:address":"198 Computrex Dr",
    "sg:city":"Nicholasville",
    "sg:classifiers":[
        {
            "category":"Building & Trades",
            "subcategory":"Plumbing",
            "type":"Services"
        }
    ],
    "sg:phone":"+1 859 881 9721",
    "sg:postcode":"40356",
    "sg:province":"KY",
    "sg:tags":[
        "plumbing",
        "contractor"
    ],
    "wof:name":"Metcalf Plumbing",
    "wof:placetype":"venue"
},
  "geometry": {"coordinates":[-84.554323,37.935678],"type":"Point"}
}