{
  "type": "Feature",
  "properties": {
    "iso:country":"US",
    "sg:address":"3919 Bardstown Rd",
    "sg:city":"Louisville",
    "sg:classifiers":[
        {
            "category":"Autos & Motor Vehicles",
            "subcategory":"Automobile Sales",
            "type":"Retail Goods"
        }
    ],
    "sg:phone":"+1 502 499 0120",
    "sg:postcode":"40218",
    "sg:province":"KY",
    "sg:tags":[
        "car",
        "dealer"
    ],
    "wof:name":"Louisville Motors",
    "wof:placetype":"venue"
},
  "geometry": {"coordinates":[-85.649365,38.193335],"type":"Point"}
}