{
  "type": "Feature",
  "properties": {
    "addr:full":"2209 Fort Campbell Blvd Hopkinsville KY 42240",
    "addr:housenumber":"2209",
    "addr:postcode":"42240",
    "addr:street":"Fort Campbell Blvd",
    "iso:country":"US",
    "sg:address":"2209 Fort Campbell Blvd",
    "sg:city":"Hopkinsville",
    "sg:classifiers":[
        {
            "category":"Shopping",
            "type":"Retail Goods"
        }
    ],
    "sg:phone":"+1 270 886 0720",
    "sg:postcode":"42240",
    "sg:province":"KY",
    "sg:tags":[
        "church",
        "supply"
    ],
    "wof:name":"Shepherd's Shop",
    "wof:placetype":"venue"
},
  "geometry": {"coordinates":[-87.487307,36.850239],"type":"Point"}
}