{
  "type": "Feature",
  "properties": {
    "addr:full":"414 Main St Murray KY 42071",
    "addr:housenumber":"414",
    "addr:postcode":"42071",
    "addr:street":"Main St",
    "iso:country":"US",
    "sg:address":"414 Main St",
    "sg:city":"Murray",
    "sg:classifiers":[
        {
            "category":"Banks & Credit Unions",
            "subcategory":"Investment Brokerage",
            "type":"Services"
        }
    ],
    "sg:phone":"+1 270 753 3366",
    "sg:postcode":"42071",
    "sg:province":"KY",
    "sg:tags":[
        "security"
    ],
    "wof:name":"Hilliard Lyons Inc",
    "wof:placetype":"venue"
},
  "geometry": {"coordinates":[-88.30286,36.610649],"type":"Point"}
}