{
  "type": "Feature",
  "properties": {
    "addr:full":"921 Beasley St Lexington KY 40509",
    "addr:housenumber":"921",
    "addr:postcode":"40509",
    "addr:street":"Beasley St",
    "iso:country":"US",
    "sg:address":"921 Beasley St",
    "sg:city":"Lexington",
    "sg:classifiers":[
        {
            "category":"Health Services",
            "subcategory":"Nursing And Care Facility",
            "type":"Services"
        }
    ],
    "sg:phone":"+1 859 294 7440",
    "sg:postcode":"40509",
    "sg:province":"KY",
    "sg:tags":[
        "hospice"
    ],
    "wof:name":"Hospice-D & R Pharmacy",
    "wof:placetype":"venue"
},
  "geometry": {"coordinates":[-84.45017799999999,38.042166],"type":"Point"}
}