{
  "type": "Feature",
  "properties": {
    "iso:country":"US",
    "sg:address":"8118 Old Gate Rd",
    "sg:city":"Louisville",
    "sg:classifiers":[
        {
            "category":"Manufacturing",
            "subcategory":"Signs",
            "type":"Manufacturing & Wholesale Goods"
        }
    ],
    "sg:phone":"+1 502 425 5622",
    "sg:postcode":"40241",
    "sg:province":"KY",
    "sg:tags":[
        "distributor",
        "specialty"
    ],
    "wof:name":"Emprint",
    "wof:placetype":"venue"
},
  "geometry": {"coordinates":[-85.598271,38.302472],"type":"Point"}
}