{
  "type": "Feature",
  "properties": {
    "iso:country":"US",
    "sg:address":"135 Cecil Dr",
    "sg:city":"Rineyville",
    "sg:classifiers":[
        {
            "category":"Freight",
            "type":"Transportation"
        }
    ],
    "sg:phone":"+1 270 234 9074",
    "sg:postcode":"40162",
    "sg:province":"KY",
    "sg:tags":[
        "operator",
        "trucking"
    ],
    "wof:name":"Landstar",
    "wof:placetype":"venue"
},
  "geometry": {"coordinates":[-85.992943,37.767464],"type":"Point"}
}