{
  "type": "Feature",
  "properties": {
    "addr:full":"10974 US Hwy 41A Henderson KY 42420",
    "addr:housenumber":"10974",
    "addr:postcode":"42420",
    "addr:street":"Us Hwy 41A",
    "iso:country":"US",
    "sg:address":"10974 US Hwy 41A",
    "sg:city":"Henderson",
    "sg:classifiers":[
        {
            "category":"Building & Trades",
            "subcategory":"Plumbing",
            "type":"Services"
        }
    ],
    "sg:phone":"+1 270 533 6323",
    "sg:postcode":"42420",
    "sg:province":"KY",
    "sg:tags":[
        "mechanical",
        "contractor"
    ],
    "wof:name":"Mlj Svc",
    "wof:placetype":"venue"
},
  "geometry": {"coordinates":[-87.657456,37.733291],"type":"Point"}
}