{
  "type": "Feature",
  "properties": {
    "addr:full":"1144 S Main St Madisonville KY 42431",
    "addr:housenumber":"1144",
    "addr:postcode":"42431",
    "addr:street":"S Main St",
    "iso:country":"US",
    "sg:address":"1144 S Main St",
    "sg:city":"Madisonville",
    "sg:classifiers":[
        {
            "category":"Shopping",
            "subcategory":"Clothing, Apparel, & Fashions",
            "type":"Retail Goods"
        }
    ],
    "sg:phone":"+1 270 825 2149",
    "sg:postcode":"42431",
    "sg:province":"KY",
    "sg:tags":[
        "uniform"
    ],
    "wof:name":"Uniforms Plus",
    "wof:placetype":"venue"
},
  "geometry": {"coordinates":[-87.50492800000001,37.311515],"type":"Point"}
}