{
  "type": "Feature",
  "properties": {
    "iso:country":"US",
    "sg:address":"401 Kentucky Ave",
    "sg:city":"Paducah",
    "sg:classifiers":[
        {
            "category":"Real Estate",
            "subcategory":"Architect",
            "type":"Services"
        }
    ],
    "sg:phone":"+1 270 442 6661",
    "sg:postcode":"42003",
    "sg:province":"KY",
    "wof:name":"Sherman-Carter-Barnhart",
    "wof:placetype":"venue"
},
  "geometry": {"coordinates":[-88.59743400000001,37.08571],"type":"Point"}
}