{
  "type": "Feature",
  "properties": {
    "addr:full":"905 S Limestone St Lexington KY 40503",
    "addr:housenumber":"905",
    "addr:postcode":"40503",
    "addr:street":"S Limestone St",
    "iso:country":"US",
    "sg:address":"905 S Limestone St",
    "sg:city":"Lexington",
    "sg:classifiers":[
        {
            "category":"Food & Beverages",
            "subcategory":"Groceries & Convenience Stores",
            "type":"Retail Goods"
        }
    ],
    "sg:phone":"+1 859 254 9453",
    "sg:postcode":"40503",
    "sg:province":"KY",
    "wof:name":"South Limestone Shell",
    "wof:placetype":"venue"
},
  "geometry": {"coordinates":[-84.509534,38.031608],"type":"Point"}
}