{
  "type": "Feature",
  "properties": {
    "addr:full":"425 Connector Rd Georgetown KY 40324",
    "addr:housenumber":"425",
    "addr:postcode":"40324",
    "addr:street":"Connector Rd",
    "iso:country":"US",
    "sg:address":"425 Connector Rd",
    "sg:city":"Georgetown",
    "sg:classifiers":[
        {
            "category":"Home & Garden",
            "subcategory":"Building Materials",
            "type":"Retail Goods"
        }
    ],
    "sg:phone":"+1 502 570 2060",
    "sg:postcode":"40324",
    "sg:province":"KY",
    "sg:tags":[
        "center"
    ],
    "wof:name":"Lowe's",
    "wof:placetype":"venue"
},
  "geometry": {"coordinates":[-84.53548000000001,38.225755],"type":"Point"}
}