{
  "type": "Feature",
  "properties": {
    "iso:country":"US",
    "sg:address":"861 Charles Ave",
    "sg:city":"Lexington",
    "sg:classifiers":[
        {
            "category":"Organizations",
            "subcategory":"Religious Organization",
            "type":"Services"
        }
    ],
    "sg:phone":"+1 859 231 5163",
    "sg:postcode":"40508",
    "sg:province":"KY",
    "sg:tags":[
        "church"
    ],
    "wof:name":"Main Street Bapt Chr Misson",
    "wof:placetype":"venue"
},
  "geometry": {"coordinates":[-84.504306,38.062182],"type":"Point"}
}