{
  "type": "Feature",
  "properties": {
    "iso:country":"US",
    "sg:address":"405 Wilkinson Blvd",
    "sg:city":"Frankfort",
    "sg:classifiers":[
        {
            "category":"Travel",
            "subcategory":"Hotels & Motels",
            "type":"Entertainment"
        }
    ],
    "sg:phone":"+1 502 227 5100",
    "sg:postcode":"40601",
    "sg:province":"KY",
    "wof:name":"Holiday Inn Frankfort-Cptl Plz",
    "wof:placetype":"venue"
},
  "geometry": {"coordinates":[-84.879037,38.202006],"type":"Point"}
}