{
  "type": "Feature",
  "properties": {
    "iso:country":"US",
    "sg:address":"1902 Campus Pl Ste 8",
    "sg:city":"Louisville",
    "sg:classifiers":[
        {
            "category":"Home & Garden",
            "subcategory":"Building Materials",
            "type":"Retail Goods"
        },
        {
            "category":"Building & Trades",
            "subcategory":"Construction",
            "type":"Services"
        },
        {
            "category":"Military Area",
            "subcategory":"Armory",
            "type":"Public Place"
        }
    ],
    "sg:phone":"+1 502 228 9339",
    "sg:postcode":"40299",
    "sg:province":"KY",
    "sg:tags":[
        "repair",
        "fence-sales",
        "fence",
        "contractor"
    ],
    "sg:website":"http://www.goyard.com",
    "wof:name":"Invisible Fence of Greater Louisville",
    "wof:placetype":"venue"
},
  "geometry": {"coordinates":[-85.53516,38.213556],"type":"Point"}
}