{
  "type": "Feature",
  "properties": {
    "addr:full":"445 E Factory St Harrodsburg KY 40330",
    "addr:housenumber":"445",
    "addr:postcode":"40330",
    "addr:street":"E Factory St",
    "iso:country":"US",
    "sg:address":"445 E Factory St",
    "sg:city":"Harrodsburg",
    "sg:classifiers":[
        {
            "category":"Real Estate",
            "subcategory":"Real Estate Operator",
            "type":"Services"
        }
    ],
    "sg:phone":"+1 859 734 6222",
    "sg:postcode":"40330",
    "sg:province":"KY",
    "sg:tags":[
        "apartment"
    ],
    "wof:name":"Cypress Hills Apartments",
    "wof:placetype":"venue"
},
  "geometry": {"coordinates":[-84.835785,37.765801],"type":"Point"}
}