{
  "type": "Feature",
  "properties": {
    "addr:full":"720 State St Guthrie KY 42234",
    "addr:housenumber":"720",
    "addr:postcode":"42234",
    "addr:street":"State St",
    "iso:country":"US",
    "sg:address":"720 State St",
    "sg:city":"Guthrie",
    "sg:classifiers":[
        {
            "category":"Retail",
            "subcategory":"Repair Shop",
            "type":"Services"
        }
    ],
    "sg:phone":"+1 270 483 8809",
    "sg:postcode":"42234",
    "sg:province":"KY",
    "sg:tags":[
        "farm",
        "equipment",
        "parts"
    ],
    "wof:name":"Bob's Ag Svc",
    "wof:placetype":"venue"
},
  "geometry": {"coordinates":[-87.161112,36.643555],"type":"Point"}
}