{
  "type": "Feature",
  "properties": {
    "addr:full":"10610 Old Taylorsville Rd Jeffersontown KY 40299",
    "addr:housenumber":"10610",
    "addr:postcode":"40299",
    "addr:street":"Old Taylorsville Rd",
    "iso:country":"US",
    "sg:address":"10610 Old Taylorsville Rd",
    "sg:city":"Jeffersontown",
    "sg:classifiers":[
        {
            "category":"Retail",
            "subcategory":"Auto Repair",
            "type":"Services"
        }
    ],
    "sg:phone":"+1 502 267 7561",
    "sg:postcode":"40299",
    "sg:province":"KY",
    "sg:tags":[
        "repairing",
        "automobile"
    ],
    "wof:name":"Bob Knipp Transmission Svc",
    "wof:placetype":"venue"
},
  "geometry": {"coordinates":[-85.560163,38.19417],"type":"Point"}
}