{
  "type": "Feature",
  "properties": {
    "addr:full":"7743 National Tpke Louisville KY 40214",
    "addr:housenumber":"7743",
    "addr:postcode":"40214",
    "addr:street":"National Tpke",
    "iso:country":"US",
    "sg:address":"7743 National Tpke",
    "sg:city":"Louisville",
    "sg:classifiers":[
        {
            "category":"Manufacturing",
            "subcategory":"Paper Products",
            "type":"Manufacturing & Wholesale Goods"
        }
    ],
    "sg:phone":"+1 502 368 2066",
    "sg:postcode":"40214",
    "sg:province":"KY",
    "sg:tags":[
        "box",
        "partition"
    ],
    "wof:name":"Pinnacle Packaging Inc",
    "wof:placetype":"venue"
},
  "geometry": {"coordinates":[-85.754043,38.140278],"type":"Point"}
}