{
  "type": "Feature",
  "properties": {
    "addr:full":"4600 Pinewood Rd Louisville KY 40218",
    "addr:housenumber":"4600",
    "addr:postcode":"40218",
    "addr:street":"Pinewood Rd",
    "iso:country":"US",
    "sg:address":"4600 Pinewood Rd",
    "sg:city":"Louisville",
    "sg:classifiers":[
        {
            "category":"Manufacturing",
            "subcategory":"Metals",
            "type":"Manufacturing & Wholesale Goods"
        }
    ],
    "sg:phone":"+1 502 964 0555",
    "sg:postcode":"40218",
    "sg:province":"KY",
    "sg:tags":[
        "fabricator",
        "sheet"
    ],
    "wof:name":"Continuous Guttering",
    "wof:placetype":"venue"
},
  "geometry": {"coordinates":[-85.69173000000001,38.185756],"type":"Point"}
}