{
  "type": "Feature",
  "properties": {
    "iso:country":"US",
    "sg:address":"606 Bloomfield Rd",
    "sg:city":"Bardstown",
    "sg:classifiers":[
        {
            "category":"Retail",
            "subcategory":"Auto Repair",
            "type":"Services"
        }
    ],
    "sg:phone":"+1 502 348 1180",
    "sg:postcode":"40004",
    "sg:province":"KY",
    "sg:tags":[
        "machine",
        "automobile",
        "shop"
    ],
    "wof:name":"Mattingly Machine Shop",
    "wof:placetype":"venue"
},
  "geometry": {"coordinates":[-85.45133199999999,37.81288],"type":"Point"}
}