{
  "type": "Feature",
  "properties": {
    "iso:country":"US",
    "sg:address":"800 Minette Cir",
    "sg:city":"Pleasure Rdg Pk",
    "sg:classifiers":[
        {
            "category":"Real Estate",
            "subcategory":"Real Estate Operator",
            "type":"Services"
        }
    ],
    "sg:phone":"+1 502 935 7368",
    "sg:postcode":"40258",
    "sg:province":"KY",
    "sg:tags":[
        "apartment"
    ],
    "wof:name":"Eden Apartments",
    "wof:placetype":"venue"
},
  "geometry": {"coordinates":[-85.85176,38.128669],"type":"Point"}
}