{
  "type": "Feature",
  "properties": {
    "iso:country":"US",
    "sg:address":"103 Kensington Way",
    "sg:city":"Campbellsville",
    "sg:classifiers":[
        {
            "category":"Insurance",
            "subcategory":"Insurance Agent",
            "type":"Services"
        }
    ],
    "sg:phone":"+1 270 465 6190",
    "sg:postcode":"42718",
    "sg:province":"KY",
    "wof:name":"ME Pollock Inc",
    "wof:placetype":"venue"
},
  "geometry": {"coordinates":[-85.37240300000001,37.354316],"type":"Point"}
}