{
  "type": "Feature",
  "properties": {
    "addr:full":"3307 College Dr Jeffersontown KY 40299",
    "addr:housenumber":"3307",
    "addr:postcode":"40299",
    "addr:street":"College Dr",
    "iso:country":"US",
    "sg:address":"3307 College Dr",
    "sg:city":"Jeffersontown",
    "sg:classifiers":[
        {
            "category":"Insurance",
            "subcategory":"Insurance Agent",
            "type":"Services"
        }
    ],
    "sg:phone":"+1 502 267 6056",
    "sg:postcode":"40299",
    "sg:province":"KY",
    "wof:name":"French Kiesler O'Donnell",
    "wof:placetype":"venue"
},
  "geometry": {"coordinates":[-85.56899199999999,38.194688],"type":"Point"}
}