{
  "type": "Feature",
  "properties": {
    "iso:country":"US",
    "sg:address":"106 S Lafayette Dr",
    "sg:city":"Georgetown",
    "sg:classifiers":[
        {
            "category":"Personal",
            "subcategory":"Beauty Salon",
            "type":"Services"
        }
    ],
    "sg:phone":"+1 502 863 6156",
    "sg:postcode":"40324",
    "sg:province":"KY",
    "wof:name":"House Of Style II",
    "wof:placetype":"venue"
},
  "geometry": {"coordinates":[-84.57897800000001,38.226293],"type":"Point"}
}