{
  "type": "Feature",
  "properties": {
    "iso:country":"US",
    "sg:address":"495 W Main St",
    "sg:city":"Lebanon",
    "sg:classifiers":[
        {
            "category":"Shopping",
            "subcategory":"Jewelry",
            "type":"Retail Goods"
        }
    ],
    "sg:phone":"+1 270 692 9413",
    "sg:postcode":"40033",
    "sg:province":"KY",
    "sg:tags":[
        "jeweler"
    ],
    "wof:name":"Lebanon Jewelry & Gift",
    "wof:placetype":"venue"
},
  "geometry": {"coordinates":[-85.261692,37.565531],"type":"Point"}
}