{
  "type": "Feature",
  "properties": {
    "iso:country":"US",
    "sg:address":"250 Chenault Rd",
    "sg:city":"Lexington",
    "sg:classifiers":[
        {
            "category":"Real Estate",
            "subcategory":"Real Estate Agent",
            "type":"Services"
        }
    ],
    "sg:phone":"+1 859 266 6999",
    "sg:postcode":"40502",
    "sg:province":"KY",
    "wof:name":"Fairway Properties LLC",
    "wof:placetype":"venue"
},
  "geometry": {"coordinates":[-84.48427700000001,38.025328],"type":"Point"}
}