{
  "type": "Feature",
  "properties": {
    "iso:country":"US",
    "sg:address":"3707 Young Ave",
    "sg:city":"Louisville",
    "sg:classifiers":[
        {
            "category":"Organizations",
            "subcategory":"Religious Organization",
            "type":"Services"
        }
    ],
    "sg:phone":"+1 502 778 4527",
    "sg:postcode":"40211",
    "sg:province":"KY",
    "wof:name":"Brown Temple AME Zion Church",
    "wof:placetype":"venue"
},
  "geometry": {"coordinates":[-85.818198,38.231102],"type":"Point"}
}