{
  "type": "Feature",
  "properties": {
    "iso:country":"US",
    "sg:address":"410 E Arch St",
    "sg:city":"Madisonville",
    "sg:classifiers":[
        {
            "category":"Shopping",
            "type":"Retail Goods"
        }
    ],
    "sg:phone":"+1 270 821 2528",
    "sg:postcode":"42431",
    "sg:province":"KY",
    "sg:tags":[
        "picture",
        "frame"
    ],
    "wof:name":"Matinee",
    "wof:placetype":"venue"
},
  "geometry": {"coordinates":[-87.491793,37.329198],"type":"Point"}
}