{
  "type": "Feature",
  "properties": {
    "iso:country":"US",
    "sg:address":"3601 Glencreek Ln",
    "sg:city":"Louisville",
    "sg:classifiers":[
        {
            "category":"Professional",
            "subcategory":"Management & Consulting",
            "type":"Services"
        }
    ],
    "sg:phone":"+1 502 456 1411",
    "sg:postcode":"40218",
    "sg:province":"KY",
    "sg:tags":[
        "marketing"
    ],
    "wof:name":"Caesars",
    "wof:placetype":"venue"
},
  "geometry": {"coordinates":[-85.65188499999999,38.204108],"type":"Point"}
}