{
  "type": "Feature",
  "properties": {
    "addr:full":"85 N Grand Ave Fort Thomas KY 41075",
    "addr:housenumber":"85",
    "addr:postcode":"41075",
    "addr:street":"N Grand Ave",
    "iso:country":"US",
    "sg:address":"85 N Grand Ave",
    "sg:city":"Fort Thomas",
    "sg:classifiers":[
        {
            "category":"Health Services",
            "subcategory":"Hospital",
            "type":"Services"
        }
    ],
    "sg:phone":"+1 859 572 3535",
    "sg:postcode":"41075",
    "sg:province":"KY",
    "wof:name":"Sleep Disorders Center",
    "wof:placetype":"venue"
},
  "geometry": {"coordinates":[-84.464401,39.0779],"type":"Point"}
}