{
  "type": "Feature",
  "properties": {
    "addr:full":"155 Washington Ct Mt Washington KY 40047",
    "addr:housenumber":"155",
    "addr:postcode":"40047",
    "addr:street":"Washington Ct",
    "iso:country":"US",
    "sg:address":"155 Washington Ct",
    "sg:city":"Mt Washington",
    "sg:classifiers":[
        {
            "category":"Recreation",
            "type":"Entertainment"
        }
    ],
    "sg:phone":"+1 502 538 3887",
    "sg:postcode":"40047",
    "sg:province":"KY",
    "sg:tags":[
        "martial",
        "arts",
        "instruction"
    ],
    "wof:name":"Three Dragons Martial Arts",
    "wof:placetype":"venue"
},
  "geometry": {"coordinates":[-85.558212,38.05903],"type":"Point"}
}