{
  "type": "Feature",
  "properties": {
    "addr:full":"370 Trotters Ln Franklin KY 42134",
    "addr:housenumber":"370",
    "addr:postcode":"42134",
    "addr:street":"Trotters Ln",
    "iso:country":"US",
    "sg:address":"370 Trotters Ln",
    "sg:city":"Franklin",
    "sg:classifiers":[
        {
            "category":"Wholesale",
            "subcategory":"Motor Vehicles",
            "type":"Manufacturing & Wholesale Goods"
        }
    ],
    "sg:phone":"+1 270 586 8288",
    "sg:postcode":"42134",
    "sg:province":"KY",
    "sg:tags":[
        "auction",
        "automobile"
    ],
    "wof:name":"Kirby Auto Auction & Realty",
    "wof:placetype":"venue"
},
  "geometry": {"coordinates":[-86.523848,36.716261],"type":"Point"}
}