{
  "type": "Feature",
  "properties": {
    "iso:country":"US",
    "sg:address":"4120 Halls Store Rd",
    "sg:city":"Russellville",
    "sg:classifiers":[
        {
            "category":"Manufacturing",
            "subcategory":"Buildings",
            "type":"Manufacturing & Wholesale Goods"
        }
    ],
    "sg:phone":"+1 270 726 7948",
    "sg:postcode":"42276",
    "sg:province":"KY",
    "sg:tags":[
        "prefab"
    ],
    "wof:name":"Overholt & Sons Inc",
    "wof:placetype":"venue"
},
  "geometry": {"coordinates":[-86.806027,36.737848],"type":"Point"}
}