{
  "type": "Feature",
  "properties": {
    "addr:full":"705 Franklin Ave Lexington KY 40508",
    "addr:housenumber":"705",
    "addr:postcode":"40508",
    "addr:street":"Franklin Ave",
    "iso:country":"US",
    "sg:address":"705 Franklin Ave",
    "sg:city":"Lexington",
    "sg:classifiers":[
        {
            "category":"Retail",
            "subcategory":"Portrait Studio",
            "type":"Services"
        }
    ],
    "sg:phone":"+1 859 253 3784",
    "sg:postcode":"40508",
    "sg:province":"KY",
    "sg:tags":[
        "photo"
    ],
    "wof:name":"John Helfenberger Photography",
    "wof:placetype":"venue"
},
  "geometry": {"coordinates":[-84.48208200000001,38.036919],"type":"Point"}
}