{
  "type": "Feature",
  "properties": {
    "iso:country":"US",
    "sg:address":"605 Baughman Ave",
    "sg:city":"Danville",
    "sg:classifiers":[
        {
            "category":"Real Estate",
            "subcategory":"Real Estate Operator",
            "type":"Services"
        }
    ],
    "sg:phone":"+1 859 236 3813",
    "sg:postcode":"40422",
    "sg:province":"KY",
    "sg:tags":[
        "mobile",
        "home",
        "community"
    ],
    "wof:name":"Imperial Mobile Home Park",
    "wof:placetype":"venue"
},
  "geometry": {"coordinates":[-84.766448,37.628522],"type":"Point"}
}