{
  "type": "Feature",
  "properties": {
    "addr:full":"939 US Hwy 27 Cynthiana KY 41031",
    "addr:housenumber":"939",
    "addr:postcode":"41031",
    "addr:street":"Us Hwy 27",
    "iso:country":"US",
    "sg:address":"939 US Hwy 27",
    "sg:city":"Cynthiana",
    "sg:classifiers":[
        {
            "category":"Banks & Credit Unions",
            "subcategory":"Bank",
            "type":"Services"
        }
    ],
    "sg:phone":"+1 859 234 3363",
    "sg:postcode":"41031",
    "sg:province":"KY",
    "sg:website":"www.kybank.com",
    "wof:name":"Kentucky Bank",
    "wof:placetype":"venue"
},
  "geometry": {"coordinates":[-84.29623100000001,38.395766],"type":"Point"}
}