{
  "type": "Feature",
  "properties": {
    "iso:country":"US",
    "sg:address":"9431 Westport Rd",
    "sg:city":"Louisville",
    "sg:classifiers":[
        {
            "category":"Communications",
            "subcategory":"News Services",
            "type":"Services"
        },
        {
            "category":"Transit Center",
            "subcategory":"Freight",
            "type":"Transportation"
        },
        {
            "category":"Professional",
            "subcategory":"Business Services",
            "type":"Services"
        },
        {
            "category":"Professional",
            "subcategory":"Printing & Photocopies",
            "type":"Services"
        },
        {
            "category":"Government",
            "subcategory":"Post Office",
            "type":"Public Place"
        }
    ],
    "sg:phone":"+1 502 426 1412",
    "sg:postcode":"40241",
    "sg:province":"KY",
    "sg:tags":[
        "cargo",
        "fax",
        "transparency",
        "package",
        "color",
        "express",
        "duplicating",
        "shipping",
        "mailbox-rental",
        "air",
        "copying",
        "mail",
        "print",
        "notary",
        "receiving",
        "photographic"
    ],
    "sg:website":"http://www.upsstore.com",
    "wof:name":"The UPS Store",
    "wof:placetype":"venue"
},
  "geometry": {"coordinates":[-85.576221,38.286099],"type":"Point"}
}