{
  "type": "Feature",
  "properties": {
    "iso:country":"US",
    "sg:address":"2580 Barnes Mountain Rd",
    "sg:city":"Irvine",
    "sg:classifiers":[
        {
            "category":"Food & Beverages",
            "subcategory":"Groceries & Convenience Stores",
            "type":"Retail Goods"
        }
    ],
    "sg:phone":"+1 606 723 6085",
    "sg:postcode":"40336",
    "sg:province":"KY",
    "sg:tags":[
        "grocer"
    ],
    "wof:name":"Chaney's Grocery",
    "wof:placetype":"venue"
},
  "geometry": {"coordinates":[-83.915032,37.64507],"type":"Point"}
}