{
  "type": "Feature",
  "properties": {
    "iso:country":"US",
    "sg:address":"322 Dixie Hwy E",
    "sg:city":"Elizabethtown",
    "sg:classifiers":[
        {
            "category":"Professional",
            "subcategory":"Business Services",
            "type":"Services"
        }
    ],
    "sg:phone":"+1 270 763 9484",
    "sg:postcode":"42701",
    "sg:province":"KY",
    "sg:tags":[
        "appraiser"
    ],
    "wof:name":"Deveau Appraisals",
    "wof:placetype":"venue"
},
  "geometry": {"coordinates":[-85.85524100000001,37.690698],"type":"Point"}
}