{
  "type": "Feature",
  "properties": {
    "addr:full":"3101 S 2nd St Louisville KY 40208",
    "addr:housenumber":"3101",
    "addr:postcode":"40208",
    "addr:street":"S 2Nd St",
    "iso:country":"US",
    "sg:address":"3101 S 2nd St",
    "sg:city":"Louisville",
    "sg:classifiers":[
        {
            "category":"Restaurant",
            "type":"Food & Drink"
        }
    ],
    "sg:menulink":"http://www.allmenus.com/ky/louisville-south/99373-beef-obradys/menu/",
    "sg:phone":"+1 502 637 3737",
    "sg:postcode":"40208",
    "sg:province":"KY",
    "sg:tags":[
        "burger",
        "american",
        "wing",
        "pub"
    ],
    "wof:name":"Beef O'Brady's",
    "wof:placetype":"venue"
},
  "geometry": {"coordinates":[-85.763212,38.204457],"type":"Point"}
}