{
  "type": "Feature",
  "properties": {
    "iso:country":"US",
    "sg:address":"426 N Main St",
    "sg:city":"Franklin",
    "sg:classifiers":[
        {
            "category":"Building & Trades",
            "subcategory":"Equipment Rental",
            "type":"Services"
        }
    ],
    "sg:phone":"+1 270 586 6000",
    "sg:postcode":"42134",
    "sg:province":"KY",
    "sg:tags":[
        "yard"
    ],
    "wof:name":"Rent-A-Center",
    "wof:placetype":"venue"
},
  "geometry": {"coordinates":[-86.57791,36.727484],"type":"Point"}
}