{
  "type": "Feature",
  "properties": {
    "addr:full":"151 Main St Irvine KY 40336",
    "addr:housenumber":"151",
    "addr:postcode":"40336",
    "addr:street":"Main St",
    "iso:country":"US",
    "sg:address":"151 Main St",
    "sg:city":"Irvine",
    "sg:classifiers":[
        {
            "category":"Education",
            "subcategory":"Special Training",
            "type":"Public Place"
        }
    ],
    "sg:phone":"+1 606 723 8200",
    "sg:postcode":"40336",
    "sg:province":"KY",
    "sg:tags":[
        "school",
        "instruction",
        "art"
    ],
    "wof:name":"Artrageous Inc",
    "wof:placetype":"venue"
},
  "geometry": {"coordinates":[-83.97543400000001,37.701019],"type":"Point"}
}