{
  "type": "Feature",
  "properties": {
    "iso:country":"US",
    "sg:address":"131 E Main St",
    "sg:city":"Waverly",
    "sg:classifiers":[
        {
            "category":"Recreation",
            "type":"Entertainment"
        }
    ],
    "sg:phone":"+1 270 389 9402",
    "sg:postcode":"42462",
    "sg:province":"KY",
    "sg:tags":[
        "club",
        "gun"
    ],
    "wof:name":"Blue Grass Rangers",
    "wof:placetype":"venue"
},
  "geometry": {"coordinates":[-87.815388,37.706098],"type":"Point"}
}