{
  "type": "Feature",
  "properties": {
    "addr:full":"7908 Beulah Church Rd Louisville KY 40228",
    "addr:housenumber":"7908",
    "addr:postcode":"40228",
    "addr:street":"Beulah Church Rd",
    "iso:country":"US",
    "sg:address":"7908 Beulah Church Rd",
    "sg:city":"Louisville",
    "sg:classifiers":[
        {
            "category":"Retail",
            "subcategory":"Auto Repair",
            "type":"Services"
        }
    ],
    "sg:phone":"+1 502 807 5408",
    "sg:postcode":"40228",
    "sg:province":"KY",
    "sg:tags":[
        "body"
    ],
    "wof:name":"Extreme Hot Rod Werks",
    "wof:placetype":"venue"
},
  "geometry": {"coordinates":[-85.61386,38.133786],"type":"Point"}
}