{
  "type": "Feature",
  "properties": {
    "iso:country":"US",
    "sg:address":"1321 S Preston St",
    "sg:city":"Louisville",
    "sg:classifiers":[
        {
            "category":"Social Services",
            "type":"Services"
        }
    ],
    "sg:phone":"+1 502 636 0816",
    "sg:postcode":"40208",
    "sg:province":"KY",
    "sg:tags":[
        "organization",
        "welfare"
    ],
    "wof:name":"Family Emergency Shelter",
    "wof:placetype":"venue"
},
  "geometry": {"coordinates":[-85.749987,38.230807],"type":"Point"}
}