{
  "type": "Feature",
  "properties": {
    "addr:full":"3955 River Bluff Rd Union KY 41091",
    "addr:housenumber":"3955",
    "addr:postcode":"41091",
    "addr:street":"River Bluff Rd",
    "iso:country":"US",
    "sg:address":"3955 River Bluff Rd",
    "sg:city":"Union",
    "sg:classifiers":[
        {
            "category":"Wholesale",
            "subcategory":"Electrical",
            "type":"Manufacturing & Wholesale Goods"
        }
    ],
    "sg:phone":"+1 859 384 7713",
    "sg:postcode":"41091",
    "sg:province":"KY",
    "sg:tags":[
        "sound",
        "equipment",
        "system"
    ],
    "wof:name":"Cornerstone Communications",
    "wof:placetype":"venue"
},
  "geometry": {"coordinates":[-84.78217600000001,38.865104],"type":"Point"}
}