{
  "type": "Feature",
  "properties": {
    "iso:country":"US",
    "sg:address":"75 Creekstone Ln",
    "sg:city":"London",
    "sg:classifiers":[
        {
            "category":"Building & Trades",
            "subcategory":"Construction",
            "type":"Services"
        }
    ],
    "sg:phone":"+1 606 862 9257",
    "sg:postcode":"40741",
    "sg:province":"KY",
    "sg:tags":[
        "company"
    ],
    "wof:name":"Lawson Construction",
    "wof:placetype":"venue"
},
  "geometry": {"coordinates":[-84.152141,37.070792],"type":"Point"}
}