{
  "type": "Feature",
  "properties": {
    "addr:full":"11722 Main St Louisville KY 40243",
    "addr:housenumber":"11722",
    "addr:postcode":"40243",
    "addr:street":"Main St",
    "iso:country":"US",
    "sg:address":"11722 Main St",
    "sg:city":"Louisville",
    "sg:classifiers":[
        {
            "category":"Food & Beverages",
            "subcategory":"Meat & Fish",
            "type":"Retail Goods"
        }
    ],
    "sg:phone":"+1 502 245 2197",
    "sg:postcode":"40243",
    "sg:province":"KY",
    "sg:tags":[
        "sausage"
    ],
    "sg:website":"www.unclesmileys.com",
    "wof:name":"Uncle Smiley's Premium Beef",
    "wof:placetype":"venue"
},
  "geometry": {"coordinates":[-85.538477,38.245561],"type":"Point"}
}