{
  "type": "Feature",
  "properties": {
    "iso:country":"US",
    "sg:address":"813 Valley Creek Rd",
    "sg:city":"Elizabethtown",
    "sg:classifiers":[
        {
            "category":"Building & Trades",
            "subcategory":"Construction",
            "type":"Services"
        }
    ],
    "sg:phone":"+1 270 737 5888",
    "sg:postcode":"42701",
    "sg:province":"KY",
    "sg:tags":[
        "carpentry",
        "contractor"
    ],
    "wof:name":"Rays Cabinets",
    "wof:placetype":"venue"
},
  "geometry": {"coordinates":[-85.82553799999999,37.676724],"type":"Point"}
}