{
  "type": "Feature",
  "properties": {
    "addr:full":"629 Main St Shelbyville KY 40065",
    "addr:housenumber":"629",
    "addr:postcode":"40065",
    "addr:street":"Main St",
    "iso:country":"US",
    "sg:address":"629 Main St",
    "sg:city":"Shelbyville",
    "sg:classifiers":[
        {
            "category":"Organizations",
            "subcategory":"Religious Organization",
            "type":"Services"
        }
    ],
    "sg:phone":"+1 502 633 2693",
    "sg:postcode":"40065",
    "sg:province":"KY",
    "sg:tags":[
        "church"
    ],
    "sg:website":"www.presbyterian-church.com",
    "wof:name":"First Presbyterian Church",
    "wof:placetype":"venue"
},
  "geometry": {"coordinates":[-85.218467,38.2112],"type":"Point"}
}