{
  "type": "Feature",
  "properties": {
    "iso:country":"US",
    "sg:address":"52 W 2nd St",
    "sg:city":"Maysville",
    "sg:classifiers":[
        {
            "category":"Home & Garden",
            "subcategory":"Building Materials",
            "type":"Retail Goods"
        }
    ],
    "sg:phone":"+1 606 564 5734",
    "sg:postcode":"41056",
    "sg:province":"KY",
    "sg:tags":[
        "paint"
    ],
    "wof:name":"Hendrickson's",
    "wof:placetype":"venue"
},
  "geometry": {"coordinates":[-83.766306,38.648457],"type":"Point"}
}