{
  "type": "Feature",
  "properties": {
    "iso:country":"US",
    "sg:address":"467 Erlanger Rd",
    "sg:city":"Erlanger",
    "sg:classifiers":[
        {
            "category":"Shopping",
            "subcategory":"Gifts & Souvenirs",
            "type":"Retail Goods"
        }
    ],
    "sg:phone":"+1 859 342 5973",
    "sg:postcode":"41018",
    "sg:province":"KY",
    "sg:tags":[
        "party",
        "supply"
    ],
    "wof:name":"Kenton Cty Democratic Party",
    "wof:placetype":"venue"
},
  "geometry": {"coordinates":[-84.604388,39.021763],"type":"Point"}
}