{
  "type": "Feature",
  "properties": {
    "iso:country":"US",
    "sg:address":"2250 Taylorsville Rd",
    "sg:city":"Louisville",
    "sg:classifiers":[
        {
            "category":"Recreation",
            "type":"Entertainment"
        }
    ],
    "sg:phone":"+1 502 454 5243",
    "sg:postcode":"40205",
    "sg:province":"KY",
    "sg:tags":[
        "instruction",
        "gymnastic"
    ],
    "wof:name":"Coach's Fitness Club",
    "wof:placetype":"venue"
},
  "geometry": {"coordinates":[-85.682106,38.223574],"type":"Point"}
}