{
  "type": "Feature",
  "properties": {
    "iso:country":"US",
    "sg:address":"424 Wheatley Rd",
    "sg:city":"Ashland",
    "sg:classifiers":[
        {
            "category":"Organizations",
            "subcategory":"Religious Organization",
            "type":"Services"
        }
    ],
    "sg:phone":"+1 606 329 2151",
    "sg:postcode":"41101",
    "sg:province":"KY",
    "sg:tags":[
        "church"
    ],
    "wof:name":"Westwood Christian Church",
    "wof:placetype":"venue"
},
  "geometry": {"coordinates":[-82.670238,38.482804],"type":"Point"}
}