{
  "type": "Feature",
  "properties": {
    "addr:full":"120 Liberty St Liberty KY 42501",
    "addr:housenumber":"120",
    "addr:postcode":"42501",
    "addr:street":"Liberty St",
    "iso:country":"US",
    "sg:address":"120 Liberty St",
    "sg:city":"Liberty",
    "sg:classifiers":[
        {
            "category":"Shopping",
            "subcategory":"Shoes",
            "type":"Retail Goods"
        }
    ],
    "sg:phone":"+1 606 787 7139",
    "sg:postcode":"42501",
    "sg:province":"KY",
    "wof:name":"Grant Shoe Store",
    "wof:placetype":"venue"
},
  "geometry": {"coordinates":[-84.59217700000001,37.095705],"type":"Point"}
}