{
  "type": "Feature",
  "properties": {
    "iso:country":"US",
    "sg:address":"206 Richmond Rd N",
    "sg:city":"Berea",
    "sg:classifiers":[
        {
            "category":"Health Services",
            "subcategory":"Doctor",
            "type":"Services"
        }
    ],
    "sg:phone":"+1 859 986 8491",
    "sg:postcode":"40403",
    "sg:province":"KY",
    "sg:tags":[
        "dentist"
    ],
    "wof:name":"Paul Wong Family Dentistry",
    "wof:placetype":"venue"
},
  "geometry": {"coordinates":[-84.28407,37.580788],"type":"Point"}
}