{
  "type": "Feature",
  "properties": {
    "iso:country":"US",
    "sg:address":"344 E Main St",
    "sg:city":"Lexington",
    "sg:classifiers":[
        {
            "category":"Professional",
            "subcategory":"Art Services",
            "type":"Services"
        }
    ],
    "sg:phone":"+1 859 253 9319",
    "sg:postcode":"40507",
    "sg:province":"KY",
    "sg:tags":[
        "graphic",
        "designer"
    ],
    "sg:website":"www.williamsmcbride.com",
    "wof:name":"Williams Mc Bride Group",
    "wof:placetype":"venue"
},
  "geometry": {"coordinates":[-84.49185900000001,38.041757],"type":"Point"}
}