{
  "type": "Feature",
  "properties": {
    "iso:country":"US",
    "sg:address":"543 S Shelby St",
    "sg:city":"Louisville",
    "sg:classifiers":[
        {
            "category":"Professional",
            "type":"Services"
        }
    ],
    "sg:phone":"+1 502 587 7709",
    "sg:postcode":"40202",
    "sg:province":"KY",
    "sg:tags":[
        "art",
        "fine",
        "artist"
    ],
    "sg:website":"http://www.edhamiltonworks.com",
    "wof:name":"Hamilton Ed Studios Inc",
    "wof:placetype":"venue"
},
  "geometry": {"coordinates":[-85.739008,38.247559],"type":"Point"}
}