{
  "type": "Feature",
  "properties": {
    "iso:country":"US",
    "sg:address":"3925 Produce Rd",
    "sg:city":"Louisville",
    "sg:classifiers":[
        {
            "category":"Freight",
            "type":"Transportation"
        }
    ],
    "sg:phone":"+1 502 968 8711",
    "sg:postcode":"40218",
    "sg:province":"KY",
    "sg:tags":[
        "trucking"
    ],
    "wof:name":"Product Distribution Co",
    "wof:placetype":"venue"
},
  "geometry": {"coordinates":[-85.683622,38.183943],"type":"Point"}
}