{
  "type": "Feature",
  "properties": {
    "iso:country":"US",
    "sg:address":"269 Lawwill Rd",
    "sg:city":"Kuttawa",
    "sg:classifiers":[
        {
            "category":"Building & Trades",
            "subcategory":"Construction",
            "type":"Services"
        }
    ],
    "sg:phone":"+1 270 388 7102",
    "sg:postcode":"42055",
    "sg:province":"KY",
    "sg:tags":[
        "general",
        "contractor"
    ],
    "wof:name":"Espie Construction Co",
    "wof:placetype":"venue"
},
  "geometry": {"coordinates":[-88.154415,37.021854],"type":"Point"}
}