{
  "type": "Feature",
  "properties": {
    "addr:full":"5393 New Cut Rd Louisville KY 40214",
    "addr:housenumber":"5393",
    "addr:postcode":"40214",
    "addr:street":"New Cut Rd",
    "iso:country":"US",
    "sg:address":"5393 New Cut Rd",
    "sg:city":"Louisville",
    "sg:classifiers":[
        {
            "category":"Banks & Credit Unions",
            "subcategory":"Bank",
            "type":"Services"
        }
    ],
    "sg:phone":"+1 502 366 9709",
    "sg:postcode":"40214",
    "sg:province":"KY",
    "sg:tags":[
        "commercial",
        "saving"
    ],
    "sg:website":"https://www.53.com/",
    "wof:name":"Fifth Third Bank",
    "wof:placetype":"venue"
},
  "geometry": {"coordinates":[-85.776444,38.151052],"type":"Point"}
}