{
  "type": "Feature",
  "properties": {
    "iso:country":"US",
    "sg:address":"500 S Central Ave",
    "sg:city":"Campbellsville",
    "sg:classifiers":[
        {
            "category":"Home & Garden",
            "subcategory":"Furniture",
            "type":"Retail Goods"
        }
    ],
    "sg:phone":"+1 270 465 5854",
    "sg:postcode":"42718",
    "sg:province":"KY",
    "wof:name":"Harmon Furniture Co",
    "wof:placetype":"venue"
},
  "geometry": {"coordinates":[-85.33543299999999,37.336029],"type":"Point"}
}