{
  "type": "Feature",
  "properties": {
    "iso:country":"US",
    "sg:address":"191 US Hwy 68 E",
    "sg:city":"Benton",
    "sg:classifiers":[
        {
            "category":"Autos & Motor Vehicles",
            "subcategory":"Automobile Sales",
            "type":"Retail Goods"
        }
    ],
    "sg:phone":"+1 270 252 0002",
    "sg:postcode":"42025",
    "sg:province":"KY",
    "sg:tags":[
        "car",
        "dealer"
    ],
    "wof:name":"Southern Auto Sales",
    "wof:placetype":"venue"
},
  "geometry": {"coordinates":[-88.34247000000001,36.924697],"type":"Point"}
}