{
  "type": "Feature",
  "properties": {
    "addr:full":"125 S 3rd St Richmond KY 40475",
    "addr:housenumber":"125",
    "addr:postcode":"40475",
    "addr:street":"S 3Rd St",
    "iso:country":"US",
    "sg:address":"125 S 3rd St",
    "sg:city":"Richmond",
    "sg:classifiers":[
        {
            "category":"Professional",
            "subcategory":"Lawyer & Legal Services",
            "type":"Services"
        }
    ],
    "sg:phone":"+1 859 624 2252",
    "sg:postcode":"40475",
    "sg:province":"KY",
    "sg:tags":[
        "attorney"
    ],
    "wof:name":"Melinda C Harhai",
    "wof:placetype":"venue"
},
  "geometry": {"coordinates":[-84.296486,37.747994],"type":"Point"}
}