{
  "type": "Feature",
  "properties": {
    "addr:full":"736 Russellville Gallatin Rd Franklin KY 42134",
    "addr:housenumber":"736",
    "addr:postcode":"42134",
    "addr:street":"Gallatin Rd",
    "iso:country":"US",
    "sg:address":"736 Russellville Gallatin Rd",
    "sg:city":"Franklin",
    "sg:classifiers":[
        {
            "category":"Farming",
            "subcategory":"Dairy Farm",
            "type":"Manufacturing & Wholesale Goods"
        }
    ],
    "sg:phone":"+1 270 586 7291",
    "sg:postcode":"42134",
    "sg:province":"KY",
    "wof:name":"Ben Jepson",
    "wof:placetype":"venue"
},
  "geometry": {"coordinates":[-86.66428999999999,36.698707],"type":"Point"}
}