{
  "type": "Feature",
  "properties": {
    "iso:country":"US",
    "sg:address":"143 Towne Dr",
    "sg:city":"Elizabethtown",
    "sg:classifiers":[
        {
            "category":"Government",
            "subcategory":"Office",
            "type":"Public Place"
        }
    ],
    "sg:phone":"+1 270 765 6177",
    "sg:postcode":"42701",
    "sg:province":"KY",
    "sg:tags":[
        "armed",
        "force",
        "recruiting"
    ],
    "wof:name":"US Air Force Recruiting",
    "wof:placetype":"venue"
},
  "geometry": {"coordinates":[-85.88790899999999,37.73387],"type":"Point"}
}