{
  "type": "Feature",
  "properties": {
    "addr:full":"9822 3rd Street Rd Louisville KY 40272",
    "addr:housenumber":"9822",
    "addr:postcode":"40272",
    "addr:street":"3Rd Street Rd",
    "iso:country":"US",
    "sg:address":"9822 3rd Street Rd",
    "sg:city":"Louisville",
    "sg:classifiers":[
        {
            "category":"Health Services",
            "subcategory":"Doctor",
            "type":"Services"
        }
    ],
    "sg:phone":"+1 502 937 3133",
    "sg:postcode":"40272",
    "sg:province":"KY",
    "sg:tags":[
        "physician",
        "surgeon"
    ],
    "wof:name":"University Child Health Spec",
    "wof:placetype":"venue"
},
  "geometry": {"coordinates":[-85.83768499999999,38.112174],"type":"Point"}
}