{
  "type": "Feature",
  "properties": {
    "iso:country":"US",
    "sg:address":"350 Christy Creek Rd",
    "sg:city":"Morehead",
    "sg:classifiers":[
        {
            "category":"Real Estate",
            "subcategory":"Real Estate Operator",
            "type":"Services"
        }
    ],
    "sg:phone":"+1 606 784 7575",
    "sg:postcode":"40351",
    "sg:province":"KY",
    "sg:tags":[
        "apartment"
    ],
    "wof:name":"Mabry's Apartment Rentals",
    "wof:placetype":"venue"
},
  "geometry": {"coordinates":[-83.40347300000001,38.193227],"type":"Point"}
}