{
  "type": "Feature",
  "properties": {
    "iso:country":"US",
    "sg:address":"4634 Echo Valley Dr",
    "sg:city":"Crestwood",
    "sg:classifiers":[
        {
            "category":"Manufacturing",
            "subcategory":"Signs",
            "type":"Manufacturing & Wholesale Goods"
        }
    ],
    "sg:phone":"+1 502 241 1630",
    "sg:postcode":"40014",
    "sg:province":"KY",
    "sg:tags":[
        "advertising",
        "specialty"
    ],
    "wof:name":"Wilding Industries Inc",
    "wof:placetype":"venue"
},
  "geometry": {"coordinates":[-85.47775300000001,38.35598],"type":"Point"}
}