{
  "type": "Feature",
  "properties": {
    "iso:country":"US",
    "sg:address":"4614 Bittersweet Rd",
    "sg:city":"Louisville",
    "sg:classifiers":[
        {
            "category":"Wholesale",
            "subcategory":"Auto Parts",
            "type":"Manufacturing & Wholesale Goods"
        }
    ],
    "sg:phone":"+1 502 966 5086",
    "sg:postcode":"40218",
    "sg:province":"KY",
    "sg:tags":[
        "speedometer"
    ],
    "wof:name":"Capco Automotive Inc",
    "wof:placetype":"venue"
},
  "geometry": {"coordinates":[-85.690422,38.187936],"type":"Point"}
}