{
  "type": "Feature",
  "properties": {
    "iso:country":"US",
    "sg:address":"236 Christi Dr",
    "sg:city":"Berea",
    "sg:classifiers":[
        {
            "category":"Communications",
            "type":"Services"
        }
    ],
    "sg:phone":"+1 859 986 7938",
    "sg:postcode":"40403",
    "sg:province":"KY",
    "wof:name":"Adelphia Communications",
    "wof:placetype":"venue"
},
  "geometry": {"coordinates":[-84.26740100000001,37.602592],"type":"Point"}
}