{
  "type": "Feature",
  "properties": {
    "iso:country":"US",
    "sg:address":"709 Mount Eden Rd",
    "sg:city":"Shelbyville",
    "sg:classifiers":[
        {
            "category":"Building & Trades",
            "subcategory":"Electrical",
            "type":"Services"
        }
    ],
    "sg:phone":"+1 502 633 9034",
    "sg:postcode":"40065",
    "sg:province":"KY",
    "sg:tags":[
        "electric",
        "contractor"
    ],
    "wof:name":"M D Electrical/Mechanical Co",
    "wof:placetype":"venue"
},
  "geometry": {"coordinates":[-85.20370800000001,38.204526],"type":"Point"}
}