{
  "type": "Feature",
  "properties": {
    "addr:full":"109 Chevy Chase Pl Elizabethtown KY 42701",
    "addr:housenumber":"109",
    "addr:postcode":"42701",
    "addr:street":"Chevy Chase Pl",
    "iso:country":"US",
    "sg:address":"109 Chevy Chase Pl",
    "sg:city":"Elizabethtown",
    "sg:classifiers":[
        {
            "category":"Building & Trades",
            "subcategory":"Construction",
            "type":"Services"
        }
    ],
    "sg:phone":"+1 270 735 1350",
    "sg:postcode":"42701",
    "sg:province":"KY",
    "sg:tags":[
        "house"
    ],
    "wof:name":"Tru Releaf Home Design LLC",
    "wof:placetype":"venue"
},
  "geometry": {"coordinates":[-85.867375,37.746621],"type":"Point"}
}