{
  "type": "Feature",
  "properties": {
    "iso:country":"US",
    "sg:address":"8 Youell St",
    "sg:city":"Florence",
    "sg:classifiers":[
        {
            "category":"Building & Trades",
            "subcategory":"Landscaping Services",
            "type":"Services"
        }
    ],
    "sg:phone":"+1 859 283 5296",
    "sg:postcode":"41042",
    "sg:province":"KY",
    "sg:tags":[
        "lawn",
        "maintenance",
        "grounds"
    ],
    "wof:name":"Lawncrafters USA",
    "wof:placetype":"venue"
},
  "geometry": {"coordinates":[-84.625017,39.000369],"type":"Point"}
}