{
  "type": "Feature",
  "properties": {
    "iso:country":"US",
    "sg:address":"601 S Dixie St",
    "sg:city":"London",
    "sg:classifiers":[
        {
            "category":"Freight",
            "type":"Transportation"
        }
    ],
    "sg:phone":"+1 606 878 1581",
    "sg:postcode":"40741",
    "sg:province":"KY",
    "sg:tags":[
        "trucking"
    ],
    "wof:name":"Riley Trucking",
    "wof:placetype":"venue"
},
  "geometry": {"coordinates":[-84.079362,37.117084],"type":"Point"}
}