{
  "type": "Feature",
  "properties": {
    "addr:full":"2705 Pioneer Dr Bowling Green KY 42101",
    "addr:housenumber":"2705",
    "addr:postcode":"42101",
    "addr:street":"Pioneer Dr",
    "iso:country":"US",
    "sg:address":"2705 Pioneer Dr",
    "sg:city":"Bowling Green",
    "sg:classifiers":[
        {
            "category":"Building & Trades",
            "subcategory":"Equipment Rental",
            "type":"Services"
        }
    ],
    "sg:phone":"+1 270 843 9723",
    "sg:postcode":"42101",
    "sg:province":"KY",
    "sg:tags":[
        "yard"
    ],
    "wof:name":"Southern Kentucky Trailer",
    "wof:placetype":"venue"
},
  "geometry": {"coordinates":[-86.485229,36.956997],"type":"Point"}
}