{
  "type": "Feature",
  "properties": {
    "iso:country":"US",
    "sg:address":"109 Montgomery Ave",
    "sg:city":"Providence",
    "sg:classifiers":[
        {
            "category":"Home & Garden",
            "subcategory":"Hardware",
            "type":"Retail Goods"
        }
    ],
    "sg:phone":"+1 270 667 7603",
    "sg:postcode":"42450",
    "sg:province":"KY",
    "wof:name":"Providence True Value Hardware",
    "wof:placetype":"venue"
},
  "geometry": {"coordinates":[-87.757069,37.399548],"type":"Point"}
}