{
  "type": "Feature",
  "properties": {
    "addr:full":"2150 Lexington Rd Richmond KY 40475",
    "addr:housenumber":"2150",
    "addr:postcode":"40475",
    "addr:street":"Lexington Rd",
    "iso:country":"US",
    "sg:address":"2150 Lexington Rd",
    "sg:city":"Richmond",
    "sg:classifiers":[
        {
            "category":"Professional",
            "subcategory":"Accounting & Tax Preparation",
            "type":"Services"
        }
    ],
    "sg:phone":"+1 859 623 4027",
    "sg:postcode":"40475",
    "sg:province":"KY",
    "sg:tags":[
        "accountant"
    ],
    "wof:name":"Craft Noble & Co",
    "wof:placetype":"venue"
},
  "geometry": {"coordinates":[-84.31862099999999,37.77575],"type":"Point"}
}