{
  "type": "Feature",
  "properties": {
    "addr:full":"897 Nandino Blvd Lexington KY 40511",
    "addr:housenumber":"897",
    "addr:postcode":"40511",
    "addr:street":"Nandino Blvd",
    "iso:country":"US",
    "sg:address":"897 Nandino Blvd",
    "sg:city":"Lexington",
    "sg:classifiers":[
        {
            "category":"Autos & Motor Vehicles",
            "subcategory":"Auto Supplies",
            "type":"Retail Goods"
        }
    ],
    "sg:phone":"+1 859 254 0404",
    "sg:postcode":"40511",
    "sg:province":"KY",
    "sg:tags":[
        "alternator",
        "generator"
    ],
    "wof:name":"Nandino Industrial Electric",
    "wof:placetype":"venue"
},
  "geometry": {"coordinates":[-84.496691,38.07865],"type":"Point"}
}