{
  "type": "Feature",
  "properties": {
    "addr:full":"1004 E Main St Cumberland KY 40823",
    "addr:housenumber":"1004",
    "addr:postcode":"40823",
    "addr:street":"E Main St",
    "iso:country":"US",
    "sg:address":"1004 E Main St",
    "sg:city":"Cumberland",
    "sg:classifiers":[
        {
            "category":"Personal",
            "subcategory":"Beauty Salon",
            "type":"Services"
        }
    ],
    "sg:phone":"+1 606 589 2880",
    "sg:postcode":"40823",
    "sg:province":"KY",
    "wof:name":"Family Hair Care",
    "wof:placetype":"venue"
},
  "geometry": {"coordinates":[-82.986996,36.977288],"type":"Point"}
}