{
  "type": "Feature",
  "properties": {
    "addr:full":"3350 Poole Mill Rd Crofton KY 42217",
    "addr:housenumber":"3350",
    "addr:postcode":"42217",
    "addr:street":"Poole Mill Rd",
    "iso:country":"US",
    "sg:address":"3350 Poole Mill Rd",
    "sg:city":"Crofton",
    "sg:classifiers":[
        {
            "category":"Freight",
            "type":"Transportation"
        }
    ],
    "sg:phone":"+1 270 424 5906",
    "sg:postcode":"42217",
    "sg:province":"KY",
    "sg:tags":[
        "operator",
        "trucking"
    ],
    "wof:name":"Doug Meredeth Trucking",
    "wof:placetype":"venue"
},
  "geometry": {"coordinates":[-87.542356,37.064011],"type":"Point"}
}