{
  "type": "Feature",
  "properties": {
    "iso:country":"US",
    "sg:address":"7 N McKinley St",
    "sg:city":"Henderson",
    "sg:classifiers":[
        {
            "category":"Home & Garden",
            "subcategory":"Building Materials",
            "type":"Retail Goods"
        }
    ],
    "sg:phone":"+1 270 844 0090",
    "sg:postcode":"42420",
    "sg:province":"KY",
    "sg:tags":[
        "windows"
    ],
    "wof:name":"THV",
    "wof:placetype":"venue"
},
  "geometry": {"coordinates":[-87.575211,37.832242],"type":"Point"}
}