{
  "type": "Feature",
  "properties": {
    "addr:full":"267 S Laurel Rd London KY 40744",
    "addr:housenumber":"267",
    "addr:postcode":"40744",
    "addr:street":"S Laurel Rd",
    "iso:country":"US",
    "sg:address":"267 S Laurel Rd",
    "sg:city":"London",
    "sg:classifiers":[
        {
            "category":"Manufacturing",
            "subcategory":"Chemicals & Compounds",
            "type":"Manufacturing & Wholesale Goods"
        }
    ],
    "sg:phone":"+1 606 864 2831",
    "sg:postcode":"40744",
    "sg:province":"KY",
    "sg:tags":[
        "gas"
    ],
    "wof:name":"Scott-Gross Co Inc",
    "wof:placetype":"venue"
},
  "geometry": {"coordinates":[-84.07129999999999,37.105069],"type":"Point"}
}