{
  "type": "Feature",
  "properties": {
    "iso:country":"US",
    "sg:address":"10486 Bradshaw Rd",
    "sg:city":"Pembroke",
    "sg:classifiers":[
        {
            "category":"Retail",
            "subcategory":"Repair Shop",
            "type":"Services"
        }
    ],
    "sg:phone":"+1 270 475 4181",
    "sg:postcode":"42266",
    "sg:province":"KY",
    "sg:tags":[
        "taxidermist"
    ],
    "wof:name":"Phil Faulkner Taxidermy",
    "wof:placetype":"venue"
},
  "geometry": {"coordinates":[-87.40413599999999,36.727154],"type":"Point"}
}