{
  "type": "Feature",
  "properties": {
    "addr:full":"35 Susan Cook Dr Whitesburg KY 41858",
    "addr:housenumber":"35",
    "addr:postcode":"41858",
    "addr:street":"Susan Cook Dr",
    "iso:country":"US",
    "sg:address":"35 Susan Cook Dr",
    "sg:city":"Whitesburg",
    "sg:classifiers":[
        {
            "category":"Food & Beverages",
            "subcategory":"Groceries & Convenience Stores",
            "type":"Retail Goods"
        }
    ],
    "sg:phone":"+1 606 633 8327",
    "sg:postcode":"41858",
    "sg:province":"KY",
    "wof:name":"Double KWIK Markets",
    "wof:placetype":"venue"
},
  "geometry": {"coordinates":[-82.843452,37.121973],"type":"Point"}
}