{
  "type": "Feature",
  "properties": {
    "iso:country":"US",
    "sg:address":"726 S Preston St",
    "sg:city":"Louisville",
    "sg:classifiers":[
        {
            "category":"Health Services",
            "subcategory":"Nursing And Care Facility",
            "type":"Services"
        }
    ],
    "sg:phone":"+1 502 585 2426",
    "sg:postcode":"40203",
    "sg:province":"KY",
    "sg:tags":[
        "home",
        "convalescent"
    ],
    "wof:name":"W W Spradling Rest Home",
    "wof:placetype":"venue"
},
  "geometry": {"coordinates":[-85.74763799999999,38.245136],"type":"Point"}
}