{
  "type": "Feature",
  "properties": {
    "iso:country":"US",
    "sg:address":"108 S Park Cir",
    "sg:city":"Elizabethtown",
    "sg:classifiers":[
        {
            "category":"Building & Trades",
            "subcategory":"Construction",
            "type":"Services"
        }
    ],
    "sg:phone":"+1 270 737 2224",
    "sg:postcode":"42701",
    "sg:province":"KY",
    "sg:tags":[
        "roofing",
        "contractor"
    ],
    "wof:name":"Swift Roofing Of E-Town",
    "wof:placetype":"venue"
},
  "geometry": {"coordinates":[-85.838533,37.675018],"type":"Point"}
}