{
  "type": "Feature",
  "properties": {
    "addr:full":"644 North Dr Hopkinsville KY 42240",
    "addr:housenumber":"644",
    "addr:postcode":"42240",
    "addr:street":"North Dr",
    "iso:country":"US",
    "sg:address":"644 North Dr",
    "sg:city":"Hopkinsville",
    "sg:classifiers":[
        {
            "category":"Social Services",
            "type":"Services"
        }
    ],
    "sg:phone":"+1 270 889 6512",
    "sg:postcode":"42240",
    "sg:province":"KY",
    "sg:tags":[
        "government"
    ],
    "wof:name":"Family Support",
    "wof:placetype":"venue"
},
  "geometry": {"coordinates":[-87.496228,36.876361],"type":"Point"}
}