{
  "type": "Feature",
  "properties": {
    "iso:country":"US",
    "sg:address":"301 E 16th St",
    "sg:city":"Owensboro",
    "sg:classifiers":[
        {
            "category":"Shopping",
            "subcategory":"Discount & Variety Stores",
            "type":"Retail Goods"
        }
    ],
    "sg:phone":"+1 270 685 2290",
    "sg:postcode":"42303",
    "sg:province":"KY",
    "sg:tags":[
        "merchandise",
        "general"
    ],
    "wof:name":"Earth Products By Gaddis",
    "wof:placetype":"venue"
},
  "geometry": {"coordinates":[-87.106898,37.761747],"type":"Point"}
}