{
  "type": "Feature",
  "properties": {
    "iso:country":"US",
    "sg:address":"335 16th St",
    "sg:city":"Ashland",
    "sg:classifiers":[
        {
            "category":"Government",
            "subcategory":"Office",
            "type":"Public Place"
        }
    ],
    "sg:phone":"+1 606 325 3547",
    "sg:postcode":"41101",
    "sg:province":"KY",
    "sg:tags":[
        "county"
    ],
    "wof:name":"Boyd County Clerk",
    "wof:placetype":"venue"
},
  "geometry": {"coordinates":[-82.640139,38.478115],"type":"Point"}
}