{
  "type": "Feature",
  "properties": {
    "addr:full":"8319 Preston Hwy Okolona KY 40219",
    "addr:housenumber":"8319",
    "addr:postcode":"40219",
    "addr:street":"Preston Hwy",
    "iso:country":"US",
    "sg:address":"8319 Preston Hwy",
    "sg:city":"Okolona",
    "sg:classifiers":[
        {
            "category":"Health Services",
            "subcategory":"Doctor",
            "type":"Services"
        }
    ],
    "sg:phone":"+1 502 966 4031",
    "sg:postcode":"40219",
    "sg:province":"KY",
    "sg:tags":[
        "dentist"
    ],
    "wof:name":"Burnette & George Family Dntst",
    "wof:placetype":"venue"
},
  "geometry": {"coordinates":[-85.68367600000001,38.133201],"type":"Point"}
}