{
  "type": "Feature",
  "properties": {
    "addr:full":"101 Morningside Dr Marion KY 42025",
    "addr:housenumber":"101",
    "addr:postcode":"42025",
    "addr:street":"Morningside Dr",
    "iso:country":"US",
    "sg:address":"101 Morningside Dr",
    "sg:city":"Marion",
    "sg:classifiers":[
        {
            "category":"Personal",
            "subcategory":"Beauty Salon",
            "type":"Services"
        }
    ],
    "sg:phone":"+1 270 965 3007",
    "sg:postcode":"42025",
    "sg:province":"KY",
    "wof:name":"Expressions Hair Studio",
    "wof:placetype":"venue"
},
  "geometry": {"coordinates":[-88.357956,36.863113],"type":"Point"}
}