{
  "type": "Feature",
  "properties": {
    "iso:country":"US",
    "sg:address":"729 E Main St",
    "sg:city":"Lexington",
    "sg:classifiers":[
        {
            "category":"Professional",
            "subcategory":"Lawyer & Legal Services",
            "type":"Services"
        }
    ],
    "sg:phone":"+1 859 268 2770",
    "sg:postcode":"40502",
    "sg:province":"KY",
    "sg:tags":[
        "attorney"
    ],
    "wof:name":"Jennifer Mc Vay Martin Law",
    "wof:placetype":"venue"
},
  "geometry": {"coordinates":[-84.48595400000001,38.036556],"type":"Point"}
}