{
  "type": "Feature",
  "properties": {
    "iso:country":"US",
    "sg:address":"610 S Columbia Ave",
    "sg:city":"Campbellsville",
    "sg:classifiers":[
        {
            "category":"Personal",
            "subcategory":"Tanning Parlor",
            "type":"Services"
        }
    ],
    "sg:phone":"+1 270 465 8189",
    "sg:postcode":"42718",
    "sg:province":"KY",
    "sg:tags":[
        "salon"
    ],
    "wof:name":"C & C Tan Shack",
    "wof:placetype":"venue"
},
  "geometry": {"coordinates":[-85.346653,37.333733],"type":"Point"}
}