{
  "type": "Feature",
  "properties": {
    "iso:country":"US",
    "sg:address":"4006 Dutchmans Ln",
    "sg:city":"Louisville",
    "sg:classifiers":[
        {
            "category":"Health Services",
            "subcategory":"Doctor",
            "type":"Services"
        },
        {
            "category":"Health Services",
            "subcategory":"Clinic",
            "type":"Services"
        },
        {
            "category":"Personal",
            "type":"Services"
        },
        {
            "category":"Health Services",
            "subcategory":"Health Practitioner",
            "type":"Services"
        }
    ],
    "sg:phone":"+1 502 896 6900",
    "sg:postcode":"40207",
    "sg:province":"KY",
    "sg:tags":[
        "physician",
        "information",
        "surgeons",
        "drug",
        "abuse",
        "counselors-licensed",
        "medicine",
        "professional",
        "addiction",
        "alcoholism",
        "treatment"
    ],
    "wof:name":"Aa & Associates Approved Alcohol Drug Program",
    "wof:placetype":"venue"
},
  "geometry": {"coordinates":[-85.634939,38.233657],"type":"Point"}
}