{
  "type": "Feature",
  "properties": {
    "iso:country":"US",
    "sg:address":"8911 Greeneway Commons Pl",
    "sg:city":"Louisville",
    "sg:classifiers":[
        {
            "category":"Real Estate",
            "subcategory":"Real Estate Agent",
            "type":"Services"
        }
    ],
    "sg:phone":"+1 502 491 5353",
    "sg:postcode":"40220",
    "sg:province":"KY",
    "wof:name":"Louisville Home Store Realtors",
    "wof:placetype":"venue"
},
  "geometry": {"coordinates":[-85.598056,38.21386],"type":"Point"}
}