{
  "type": "Feature",
  "properties": {
    "iso:country":"US",
    "sg:address":"2896 Goodnight-Hiseville Rd",
    "sg:city":"Cave City",
    "sg:classifiers":[
        {
            "category":"Farming",
            "subcategory":"Dairy Farm",
            "type":"Manufacturing & Wholesale Goods"
        }
    ],
    "sg:phone":"+1 270 453 2895",
    "sg:postcode":"42127",
    "sg:province":"KY",
    "wof:name":"Glen Jones Dairy Farm",
    "wof:placetype":"venue"
},
  "geometry": {"coordinates":[-85.835379,37.091377],"type":"Point"}
}