{
  "type": "Feature",
  "properties": {
    "iso:country":"US",
    "sg:address":"1316 Columbia Ave",
    "sg:city":"Monticello",
    "sg:classifiers":[
        {
            "category":"Shopping",
            "subcategory":"Pharmacy",
            "type":"Retail Goods"
        }
    ],
    "sg:phone":"+1 606 348 4455",
    "sg:postcode":"42633",
    "sg:province":"KY",
    "wof:name":"Daffron KWIK-Script",
    "wof:placetype":"venue"
},
  "geometry": {"coordinates":[-84.865983,36.842774],"type":"Point"}
}