{
  "type": "Feature",
  "properties": {
    "addr:full":"4012 Dupont Cir Suite # 109 Louisville KY 40207",
    "addr:housenumber":"4012",
    "addr:postcode":"40207",
    "addr:street":"Dupont Cir Suite # 109",
    "iso:country":"US",
    "sg:address":"4012 Dupont Cir Suite # 109",
    "sg:city":"Louisville",
    "sg:classifiers":[
        {
            "category":"Health Services",
            "subcategory":"Doctor",
            "type":"Services"
        },
        {
            "category":"Health Services",
            "subcategory":"Health Practitioner",
            "type":"Services"
        }
    ],
    "sg:phone":"+1 502 693 4494",
    "sg:postcode":"40207",
    "sg:province":"KY",
    "sg:tags":[
        "control",
        "physician",
        "management",
        "weight",
        "loss",
        "surgeons",
        "hypnotherapy",
        "hypnotist"
    ],
    "sg:website":"http://www.hypnoticoasis1.com",
    "wof:name":"The Hypnotic Oasis",
    "wof:placetype":"venue"
},
  "geometry": {"coordinates":[-85.630785,38.233349],"type":"Point"}
}