{
  "type": "Feature",
  "properties": {
    "addr:full":"1900 Eastern Ave Covington KY 41014",
    "addr:housenumber":"1900",
    "addr:postcode":"41014",
    "addr:street":"Eastern Ave",
    "iso:country":"US",
    "sg:address":"1900 Eastern Ave",
    "sg:city":"Covington",
    "sg:classifiers":[
        {
            "category":"Bars & Pubs",
            "type":"Food & Drink"
        }
    ],
    "sg:phone":"+1 859 491 6444",
    "sg:postcode":"41014",
    "sg:province":"KY",
    "wof:name":"Whiskey Flats",
    "wof:placetype":"venue"
},
  "geometry": {"coordinates":[-84.49862299999999,39.068996],"type":"Point"}
}