{
  "type": "Feature",
  "properties": {
    "iso:country":"US",
    "sg:address":"122 Barnes Knob Rd",
    "sg:city":"Nancy",
    "sg:classifiers":[
        {
            "category":"Building & Trades",
            "subcategory":"Construction",
            "type":"Services"
        }
    ],
    "sg:phone":"+1 606 871 0035",
    "sg:postcode":"42544",
    "sg:province":"KY",
    "sg:tags":[
        "house"
    ],
    "wof:name":"Home Improvement By Bruno",
    "wof:placetype":"venue"
},
  "geometry": {"coordinates":[-84.85307299999999,37.012534],"type":"Point"}
}