{
  "type": "Feature",
  "properties": {
    "iso:country":"US",
    "sg:address":"6203 Greenwood Rd",
    "sg:city":"Louisville",
    "sg:classifiers":[
        {
            "category":"Organizations",
            "subcategory":"Religious Organization",
            "type":"Services"
        }
    ],
    "sg:phone":"+1 502 995 0850",
    "sg:postcode":"40258",
    "sg:province":"KY",
    "wof:name":"In Jesus Name Spirit Fill",
    "wof:placetype":"venue"
},
  "geometry": {"coordinates":[-85.86742599999999,38.14466],"type":"Point"}
}