{
  "type": "Feature",
  "properties": {
    "addr:full":"5275 State Hwy 80 Wooton KY 41776",
    "addr:housenumber":"5275",
    "addr:postcode":"41776",
    "addr:street":"State Hwy 80",
    "iso:country":"US",
    "sg:address":"5275 State Hwy 80",
    "sg:city":"Wooton",
    "sg:classifiers":[
        {
            "category":"Government",
            "subcategory":"Post Office",
            "type":"Public Place"
        }
    ],
    "sg:phone":"+1 606 279 4571",
    "sg:postcode":"41776",
    "sg:province":"KY",
    "wof:name":"US Post Office",
    "wof:placetype":"venue"
},
  "geometry": {"coordinates":[-83.307652,37.166325],"type":"Point"}
}