{
  "type": "Feature",
  "properties": {
    "iso:country":"US",
    "sg:address":"12216 Ledges Dr",
    "sg:city":"Louisville",
    "sg:classifiers":[
        {
            "category":"Health Services",
            "subcategory":"Chiropractor",
            "type":"Services"
        }
    ],
    "sg:phone":"+1 502 254 1321",
    "sg:postcode":"40243",
    "sg:province":"KY",
    "wof:name":"Thomas Kramer",
    "wof:placetype":"venue"
},
  "geometry": {"coordinates":[-85.527455,38.234691],"type":"Point"}
}