{
  "type": "Feature",
  "properties": {
    "iso:country":"US",
    "sg:address":"1222 Holsworth Ln",
    "sg:city":"Louisville",
    "sg:classifiers":[
        {
            "category":"Organizations",
            "subcategory":"Professional Association",
            "type":"Services"
        }
    ],
    "sg:phone":"+1 502 423 0469",
    "sg:postcode":"40222",
    "sg:province":"KY",
    "sg:tags":[
        "business"
    ],
    "wof:name":"Conchologists of America",
    "wof:placetype":"venue"
},
  "geometry": {"coordinates":[-85.621554,38.269222],"type":"Point"}
}