{
  "type": "Feature",
  "properties": {
    "iso:country":"US",
    "sg:address":"410 E Main St",
    "sg:city":"Danville",
    "sg:classifiers":[
        {
            "category":"Education",
            "subcategory":"School",
            "type":"Public Place"
        }
    ],
    "sg:phone":"+1 859 238 1316",
    "sg:postcode":"40422",
    "sg:province":"KY",
    "wof:name":"Jennie Rogers School",
    "wof:placetype":"venue"
},
  "geometry": {"coordinates":[-84.765547,37.645339],"type":"Point"}
}