{
  "type": "Feature",
  "properties": {
    "iso:country":"US",
    "sg:address":"417 N Main St",
    "sg:city":"Franklin",
    "sg:classifiers":[
        {
            "category":"Insurance",
            "subcategory":"Insurance Agent",
            "type":"Services"
        }
    ],
    "sg:phone":"+1 270 586 4757",
    "sg:postcode":"42134",
    "sg:province":"KY",
    "wof:name":"Cook-Grogan Insurance Inc",
    "wof:placetype":"venue"
},
  "geometry": {"coordinates":[-86.578067,36.727488],"type":"Point"}
}