{
  "type": "Feature",
  "properties": {
    "iso:country":"US",
    "sg:address":"4428 Hustonville Rd",
    "sg:city":"Danville",
    "sg:classifiers":[
        {
            "category":"Restaurant",
            "type":"Food & Drink"
        }
    ],
    "sg:phone":"+1 859 854 9278",
    "sg:postcode":"40422",
    "sg:province":"KY",
    "wof:name":"El Chaparro",
    "wof:placetype":"venue"
},
  "geometry": {"coordinates":[-84.780227,37.583116],"type":"Point"}
}