{
  "type": "Feature",
  "properties": {
    "iso:country":"US",
    "sg:address":"102 S 12th St",
    "sg:city":"Murray",
    "sg:classifiers":[
        {
            "category":"Retail",
            "subcategory":"Auto Repair",
            "type":"Services"
        }
    ],
    "sg:phone":"+1 270 759 3278",
    "sg:postcode":"42071",
    "sg:province":"KY",
    "sg:tags":[
        "lubricating"
    ],
    "wof:name":"Express Care",
    "wof:placetype":"venue"
},
  "geometry": {"coordinates":[-88.315224,36.609994],"type":"Point"}
}