{
  "type": "Feature",
  "properties": {
    "addr:full":"10101 Dixie Hwy Louisville KY 40272",
    "addr:housenumber":"10101",
    "addr:postcode":"40272",
    "addr:street":"Dixie Hwy",
    "iso:country":"US",
    "sg:address":"10101 Dixie Hwy",
    "sg:city":"Louisville",
    "sg:classifiers":[
        {
            "category":"Restaurant",
            "type":"Food & Drink"
        }
    ],
    "sg:menulink":"http://www.allmenus.com/ky/jefferson-southwest/100764-captain-ds-seafood/menu/",
    "sg:phone":"+1 502 935 7350",
    "sg:postcode":"40272",
    "sg:province":"KY",
    "sg:tags":[
        "seafood",
        "american"
    ],
    "wof:name":"Captain D's Seafood",
    "wof:placetype":"venue"
},
  "geometry": {"coordinates":[-85.865624,38.109288],"type":"Point"}
}