{
  "type": "Feature",
  "properties": {
    "iso:country":"US",
    "sg:address":"1408 Bur Oak Ct",
    "sg:city":"Hebron",
    "sg:classifiers":[
        {
            "category":"Real Estate",
            "subcategory":"Real Estate Agent",
            "type":"Services"
        }
    ],
    "sg:phone":"+1 859 689 2111",
    "sg:postcode":"41048",
    "sg:province":"KY",
    "wof:name":"Ponce Inlet Condo",
    "wof:placetype":"venue"
},
  "geometry": {"coordinates":[-84.726316,39.099051],"type":"Point"}
}