{
  "type": "Feature",
  "properties": {
    "iso:country":"US",
    "sg:address":"10521 Franklin St",
    "sg:city":"Whitesville",
    "sg:classifiers":[
        {
            "category":"Professional",
            "type":"Services"
        }
    ],
    "sg:phone":"+1 270 233 5648",
    "sg:postcode":"42378",
    "sg:province":"KY",
    "sg:tags":[
        "establishment"
    ],
    "wof:name":"St Marys Lunchroom",
    "wof:placetype":"venue"
},
  "geometry": {"coordinates":[-86.87150800000001,37.677347],"type":"Point"}
}