{
  "type": "Feature",
  "properties": {
    "iso:country":"US",
    "sg:address":"4641 Illinois Ave",
    "sg:city":"Louisville",
    "sg:classifiers":[
        {
            "category":"Building & Trades",
            "subcategory":"Construction",
            "type":"Services"
        }
    ],
    "sg:phone":"+1 502 456 1230",
    "sg:postcode":"40213",
    "sg:province":"KY",
    "sg:tags":[
        "excavating",
        "contractor"
    ],
    "wof:name":"Foreman Brothers Backhoe Co",
    "wof:placetype":"venue"
},
  "geometry": {"coordinates":[-85.699285,38.187114],"type":"Point"}
}