{
  "type": "Feature",
  "properties": {
    "addr:full":"705 Broadway Paintsville KY 41240",
    "addr:housenumber":"705",
    "addr:postcode":"41240",
    "addr:street":"Broadway",
    "iso:country":"US",
    "sg:address":"705 Broadway",
    "sg:city":"Paintsville",
    "sg:classifiers":[
        {
            "category":"Retail",
            "subcategory":"Auto Repair",
            "type":"Services"
        }
    ],
    "sg:phone":"+1 606 789 9140",
    "sg:postcode":"41240",
    "sg:province":"KY",
    "sg:tags":[
        "repairing",
        "automobile"
    ],
    "wof:name":"RTB Auto Repair",
    "wof:placetype":"venue"
},
  "geometry": {"coordinates":[-82.800211,37.810806],"type":"Point"}
}