{
  "type": "Feature",
  "properties": {
    "iso:country":"US",
    "sg:address":"122 Autumn Ln",
    "sg:city":"Marion",
    "sg:classifiers":[
        {
            "category":"Government",
            "subcategory":"Office",
            "type":"Public Place"
        }
    ],
    "sg:phone":"+1 270 965 9833",
    "sg:postcode":"42064",
    "sg:province":"KY",
    "wof:name":"Family Resource Youth Ctr",
    "wof:placetype":"venue"
},
  "geometry": {"coordinates":[-88.095719,37.317144],"type":"Point"}
}