{
  "type": "Feature",
  "properties": {
    "iso:country":"US",
    "sg:address":"3938 Waddy Rd",
    "sg:city":"Waddy",
    "sg:classifiers":[
        {
            "category":"Recreation",
            "type":"Entertainment"
        }
    ],
    "sg:phone":"+1 502 829 0008",
    "sg:postcode":"40076",
    "sg:province":"KY",
    "sg:tags":[
        "amusement"
    ],
    "wof:name":"Artistic Aluminum Inc",
    "wof:placetype":"venue"
},
  "geometry": {"coordinates":[-85.07499900000001,38.13572],"type":"Point"}
}