{
  "type": "Feature",
  "properties": {
    "addr:full":"1968 Declaration Dr Independence KY 41051",
    "addr:housenumber":"1968",
    "addr:postcode":"41051",
    "addr:street":"Declaration Dr",
    "iso:country":"US",
    "sg:address":"1968 Declaration Dr",
    "sg:city":"Independence",
    "sg:classifiers":[
        {
            "category":"Fast Food",
            "type":"Food & Drink"
        },
        {
            "category":"Restaurant",
            "type":"Food & Drink"
        }
    ],
    "sg:phone":"+1 859 359 4700",
    "sg:postcode":"41051",
    "sg:province":"KY",
    "sg:tags":[
        "style",
        "family"
    ],
    "sg:website":"http://www.skylinechili.com",
    "wof:name":"Skyline Chili",
    "wof:placetype":"venue"
},
  "geometry": {"coordinates":[-84.546249,38.93227],"type":"Point"}
}