{
  "type": "Feature",
  "properties": {
    "iso:country":"US",
    "sg:address":"528 Happy Valley Rd",
    "sg:city":"Glasgow",
    "sg:classifiers":[
        {
            "category":"Autos & Motor Vehicles",
            "subcategory":"Fuel & Gas Station",
            "type":"Retail Goods"
        }
    ],
    "sg:phone":"+1 270 651 5840",
    "sg:postcode":"42141",
    "sg:province":"KY",
    "sg:tags":[
        "oil"
    ],
    "wof:name":"Swifty Gas",
    "wof:placetype":"venue"
},
  "geometry": {"coordinates":[-85.913939,37.006515],"type":"Point"}
}