{
  "type": "Feature",
  "properties": {
    "iso:country":"US",
    "sg:address":"2134 Petersburg Rd",
    "sg:city":"Hebron",
    "sg:classifiers":[
        {
            "category":"Retail",
            "subcategory":"Event Space",
            "type":"Services"
        }
    ],
    "sg:phone":"+1 859 689 4000",
    "sg:postcode":"41048",
    "sg:province":"KY",
    "sg:tags":[
        "venue"
    ],
    "sg:website":"www.briarwoodbanquetcenter.com/",
    "wof:name":"Briarwood the",
    "wof:placetype":"venue"
},
  "geometry": {"coordinates":[-84.708595,39.066258],"type":"Point"}
}