{
  "type": "Feature",
  "properties": {
    "addr:full":"147 Wilma Ave Louisville KY 40229",
    "addr:housenumber":"147",
    "addr:postcode":"40229",
    "addr:street":"Wilma Ave",
    "iso:country":"US",
    "sg:address":"147 Wilma Ave",
    "sg:city":"Louisville",
    "sg:classifiers":[
        {
            "category":"Social Services",
            "type":"Services"
        }
    ],
    "sg:phone":"+1 502 955 1750",
    "sg:postcode":"40229",
    "sg:province":"KY",
    "sg:tags":[
        "care",
        "center",
        "day"
    ],
    "wof:name":"Alternative Adult Day",
    "wof:placetype":"venue"
},
  "geometry": {"coordinates":[-85.66633899999999,38.080753],"type":"Point"}
}