{
  "type": "Feature",
  "properties": {
    "iso:country":"US",
    "sg:address":"8307 Preston Hwy",
    "sg:city":"Okolona",
    "sg:classifiers":[
        {
            "category":"Manufacturing",
            "subcategory":"Printing",
            "type":"Manufacturing & Wholesale Goods"
        }
    ],
    "sg:phone":"+1 502 964 0973",
    "sg:postcode":"40219",
    "sg:province":"KY",
    "sg:tags":[
        "commercial"
    ],
    "wof:name":"Allegra Print & Imaging",
    "wof:placetype":"venue"
},
  "geometry": {"coordinates":[-85.683638,38.133114],"type":"Point"}
}