{
  "type": "Feature",
  "properties": {
    "iso:country":"US",
    "sg:address":"1589 US Hwy 31 W Byp",
    "sg:city":"Bowling Green",
    "sg:classifiers":[
        {
            "category":"Food & Beverages",
            "subcategory":"Groceries & Convenience Stores",
            "type":"Retail Goods"
        }
    ],
    "sg:phone":"+1 270 842 3631",
    "sg:postcode":"42101",
    "sg:province":"KY",
    "sg:tags":[
        "grocer"
    ],
    "wof:name":"Houchens Market",
    "wof:placetype":"venue"
},
  "geometry": {"coordinates":[-86.44840600000001,36.980003],"type":"Point"}
}