{
  "type": "Feature",
  "properties": {
    "addr:full":"1164 Eastridge Cemetery Rd Casey Creek KY 42728",
    "addr:housenumber":"1164",
    "addr:postcode":"42728",
    "addr:street":"Eastridge Cemetery Rd",
    "iso:country":"US",
    "sg:address":"1164 Eastridge Cemetery Rd",
    "sg:city":"Casey Creek",
    "sg:classifiers":[
        {
            "category":"Wholesale",
            "subcategory":"Farm Supplies",
            "type":"Manufacturing & Wholesale Goods"
        }
    ],
    "sg:phone":"+1 270 465 8781",
    "sg:postcode":"42728",
    "sg:province":"KY",
    "wof:name":"Bar E Farm Feed Tack & Western",
    "wof:placetype":"venue"
},
  "geometry": {"coordinates":[-85.190923,37.273779],"type":"Point"}
}