{
  "type": "Feature",
  "properties": {
    "iso:country":"US",
    "sg:address":"5391 Dixie Hwy S",
    "sg:city":"Elizabethtown",
    "sg:classifiers":[
        {
            "category":"Home & Garden",
            "subcategory":"Furniture",
            "type":"Retail Goods"
        }
    ],
    "sg:phone":"+1 270 735 1515",
    "sg:postcode":"42701",
    "sg:province":"KY",
    "sg:tags":[
        "mattress"
    ],
    "wof:name":"Roy's Leather & Mattress Shop",
    "wof:placetype":"venue"
},
  "geometry": {"coordinates":[-85.899576,37.760296],"type":"Point"}
}