{
  "type": "Feature",
  "properties": {
    "iso:country":"US",
    "sg:address":"400 Athens Boonesboro Rd",
    "sg:city":"Winchester",
    "sg:classifiers":[
        {
            "category":"Recreation",
            "subcategory":"Marina",
            "type":"Entertainment"
        }
    ],
    "sg:phone":"+1 859 527 3800",
    "sg:postcode":"40391",
    "sg:province":"KY",
    "wof:name":"River View Marina",
    "wof:placetype":"venue"
},
  "geometry": {"coordinates":[-84.273245,37.918541],"type":"Point"}
}