{
  "type": "Feature",
  "properties": {
    "addr:full":"8516 Preston Hwy Louisville KY 40219",
    "addr:housenumber":"8516",
    "addr:postcode":"40219",
    "addr:street":"Preston Hwy",
    "iso:country":"US",
    "sg:address":"8516 Preston Hwy",
    "sg:city":"Louisville",
    "sg:classifiers":[
        {
            "category":"Health Services",
            "subcategory":"Dentist",
            "type":"Services"
        }
    ],
    "sg:phone":"+1 502 969 2523",
    "sg:postcode":"40219",
    "sg:province":"KY",
    "sg:tags":[
        "dentists-oral",
        "surgery",
        "maxillofacial"
    ],
    "sg:website":"http://www.josephmascarodmd.com",
    "wof:name":"Mascaro, Joseph J DMD",
    "wof:placetype":"venue"
},
  "geometry": {"coordinates":[-85.68089000000001,38.127822],"type":"Point"}
}