{
  "type": "Feature",
  "properties": {
    "addr:full":"221 E 3rd St Covington KY 41011",
    "addr:housenumber":"221",
    "addr:postcode":"41011",
    "addr:street":"E 3Rd St",
    "iso:country":"US",
    "sg:address":"221 E 3rd St",
    "sg:city":"Covington",
    "sg:classifiers":[
        {
            "category":"Shopping",
            "subcategory":"Computers & Home Electronics",
            "type":"Retail Goods"
        }
    ],
    "sg:phone":"+1 859 431 3400",
    "sg:postcode":"41011",
    "sg:province":"KY",
    "sg:tags":[
        "software"
    ],
    "wof:name":"Burns & Assoc",
    "wof:placetype":"venue"
},
  "geometry": {"coordinates":[-84.506528,39.088996],"type":"Point"}
}