{
  "type": "Feature",
  "properties": {
    "addr:full":"1890 Alexandria Dr Lexington KY 40504",
    "addr:housenumber":"1890",
    "addr:postcode":"40504",
    "addr:street":"Alexandria Dr",
    "iso:country":"US",
    "sg:address":"1890 Alexandria Dr",
    "sg:city":"Lexington",
    "sg:classifiers":[
        {
            "category":"Professional",
            "subcategory":"Secretarial Services",
            "type":"Services"
        }
    ],
    "sg:phone":"+1 859 277 8655",
    "sg:postcode":"40504",
    "sg:province":"KY",
    "sg:tags":[
        "court",
        "reporter"
    ],
    "wof:name":"Carla Montfort",
    "wof:placetype":"venue"
},
  "geometry": {"coordinates":[-84.55093100000001,38.035969],"type":"Point"}
}