{
  "type": "Feature",
  "properties": {
    "addr:full":"111 W Main St Campbellsville KY 42718",
    "addr:housenumber":"111",
    "addr:postcode":"42718",
    "addr:street":"W Main St",
    "iso:country":"US",
    "sg:address":"111 W Main St",
    "sg:city":"Campbellsville",
    "sg:classifiers":[
        {
            "category":"Government",
            "subcategory":"Office",
            "type":"Public Place"
        }
    ],
    "sg:phone":"+1 270 465 4164",
    "sg:postcode":"42718",
    "sg:province":"KY",
    "sg:tags":[
        "federal",
        "human"
    ],
    "wof:name":"US Social Security Adm",
    "wof:placetype":"venue"
},
  "geometry": {"coordinates":[-85.345957,37.340075],"type":"Point"}
}