{
  "type": "Feature",
  "properties": {
    "addr:full":"136 Southport Dr Somerset KY 42501",
    "addr:housenumber":"136",
    "addr:postcode":"42501",
    "addr:street":"Southport Dr",
    "iso:country":"US",
    "sg:address":"136 Southport Dr",
    "sg:city":"Somerset",
    "sg:classifiers":[
        {
            "category":"Professional",
            "subcategory":"Lawyer & Legal Services",
            "type":"Services"
        }
    ],
    "sg:phone":"+1 606 679 4942",
    "sg:postcode":"42501",
    "sg:province":"KY",
    "sg:tags":[
        "attorney"
    ],
    "wof:name":"Larry Whitaker",
    "wof:placetype":"venue"
},
  "geometry": {"coordinates":[-84.625052,37.0401],"type":"Point"}
}