{
  "type": "Feature",
  "properties": {
    "iso:country":"US",
    "sg:address":"200 Kentucky Ave",
    "sg:city":"Paducah",
    "sg:classifiers":[
        {
            "category":"Restaurant",
            "type":"Food & Drink"
        }
    ],
    "sg:phone":"+1 270 415 9216",
    "sg:postcode":"42003",
    "sg:province":"KY",
    "sg:tags":[
        "shop",
        "coffee"
    ],
    "wof:name":"Smiley's",
    "wof:placetype":"venue"
},
  "geometry": {"coordinates":[-88.594887,37.08672],"type":"Point"}
}