{
  "type": "Feature",
  "properties": {
    "addr:full":"11430 Watterson Ct Louisville KY 40299",
    "addr:housenumber":"11430",
    "addr:postcode":"40299",
    "addr:street":"Watterson Ct",
    "iso:country":"US",
    "sg:address":"11430 Watterson Ct",
    "sg:city":"Louisville",
    "sg:classifiers":[
        {
            "category":"Wholesale",
            "subcategory":"Medical Equipment & Supplies",
            "type":"Manufacturing & Wholesale Goods"
        }
    ],
    "sg:phone":"+1 502 636 0487",
    "sg:postcode":"40299",
    "sg:province":"KY",
    "sg:tags":[
        "x",
        "apparatus"
    ],
    "sg:website":"www.raynostix.com",
    "wof:name":"Raynostix Corp",
    "wof:placetype":"venue"
},
  "geometry": {"coordinates":[-85.55573099999999,38.214679],"type":"Point"}
}