{
  "type": "Feature",
  "properties": {
    "iso:country":"US",
    "sg:address":"10201 National Tpke",
    "sg:city":"Fairdale",
    "sg:classifiers":[
        {
            "category":"Real Estate",
            "subcategory":"Surveying",
            "type":"Services"
        }
    ],
    "sg:phone":"+1 502 363 2059",
    "sg:postcode":"40118",
    "sg:province":"KY",
    "sg:tags":[
        "instrument"
    ],
    "wof:name":"Schultz W T Co",
    "wof:placetype":"venue"
},
  "geometry": {"coordinates":[-85.73844699999999,38.101924],"type":"Point"}
}