{
  "type": "Feature",
  "properties": {
    "iso:country":"US",
    "sg:address":"911 US Hwy 31 W Byp",
    "sg:city":"Bowling Green",
    "sg:classifiers":[
        {
            "category":"Autos & Motor Vehicles",
            "subcategory":"Auto Supplies",
            "type":"Retail Goods"
        }
    ],
    "sg:phone":"+1 270 781 0029",
    "sg:postcode":"42101",
    "sg:province":"KY",
    "sg:tags":[
        "automobile",
        "stereo",
        "radio"
    ],
    "wof:name":"Bluegrass Car Audio",
    "wof:placetype":"venue"
},
  "geometry": {"coordinates":[-86.433661,36.984758],"type":"Point"}
}