{
  "type": "Feature",
  "properties": {
    "iso:country":"US",
    "sg:address":"210 May St",
    "sg:city":"Somerset",
    "sg:classifiers":[
        {
            "category":"Education",
            "subcategory":"School",
            "type":"Public Place"
        }
    ],
    "sg:phone":"+1 606 678 8707",
    "sg:postcode":"42501",
    "sg:province":"KY",
    "wof:name":"Hopkins Elementary School",
    "wof:placetype":"venue"
},
  "geometry": {"coordinates":[-84.599559,37.096222],"type":"Point"}
}