{
  "type": "Feature",
  "properties": {
    "iso:country":"US",
    "sg:address":"8270 Dixie Hwy",
    "sg:city":"Louisville",
    "sg:classifiers":[
        {
            "category":"Banks & Credit Unions",
            "subcategory":"Bank",
            "type":"Services"
        }
    ],
    "sg:phone":"+1 502 995 3999",
    "sg:postcode":"40258",
    "sg:province":"KY",
    "sg:tags":[
        "cashing",
        "check"
    ],
    "wof:name":"Advance Til Payday",
    "wof:placetype":"venue"
},
  "geometry": {"coordinates":[-85.84598099999999,38.133113],"type":"Point"}
}