{
  "type": "Feature",
  "properties": {
    "iso:country":"US",
    "sg:address":"10600 Timberwood Cir",
    "sg:city":"Louisville",
    "sg:classifiers":[
        {
            "category":"Insurance",
            "subcategory":"Insurance Agent",
            "type":"Services"
        }
    ],
    "sg:phone":"+1 502 327 0027",
    "sg:postcode":"40223",
    "sg:province":"KY",
    "wof:name":"Abernathy Insurance Inc",
    "wof:placetype":"venue"
},
  "geometry": {"coordinates":[-85.572577,38.233893],"type":"Point"}
}