{
  "type": "Feature",
  "properties": {
    "iso:country":"US",
    "sg:address":"8414 US Hwy 42",
    "sg:city":"Florence",
    "sg:classifiers":[
        {
            "category":"Shopping",
            "subcategory":"Used Merchandise",
            "type":"Retail Goods"
        }
    ],
    "sg:phone":"+1 859 647 7900",
    "sg:postcode":"41042",
    "sg:province":"KY",
    "wof:name":"Northern Kentucky Pawn",
    "wof:placetype":"venue"
},
  "geometry": {"coordinates":[-84.655338,38.978709],"type":"Point"}
}