{
  "type": "Feature",
  "properties": {
    "addr:full":"3900 E Hebron Ln Shepherdsville KY 40165",
    "addr:housenumber":"3900",
    "addr:postcode":"40165",
    "addr:street":"E Hebron Ln",
    "iso:country":"US",
    "sg:address":"3900 E Hebron Ln",
    "sg:city":"Shepherdsville",
    "sg:classifiers":[
        {
            "category":"Organizations",
            "subcategory":"Professional Association",
            "type":"Services"
        }
    ],
    "sg:phone":"+1 502 957 3920",
    "sg:postcode":"40165",
    "sg:province":"KY",
    "wof:name":"Girl Scouts Camp Shanituck",
    "wof:placetype":"venue"
},
  "geometry": {"coordinates":[-85.66080599999999,38.048286],"type":"Point"}
}