{
  "type": "Feature",
  "properties": {
    "addr:full":"647 E Main St Lexington KY 40508",
    "addr:housenumber":"647",
    "addr:postcode":"40508",
    "addr:street":"E Main St",
    "iso:country":"US",
    "sg:address":"647 E Main St",
    "sg:city":"Lexington",
    "sg:classifiers":[
        {
            "category":"Retail",
            "subcategory":"Laundry & Dry Cleaning",
            "type":"Services"
        }
    ],
    "sg:phone":"+1 859 254 6248",
    "sg:postcode":"40508",
    "sg:province":"KY",
    "sg:tags":[
        "drycleaning",
        "plant"
    ],
    "wof:name":"Chester David",
    "wof:placetype":"venue"
},
  "geometry": {"coordinates":[-84.485975,38.036694],"type":"Point"}
}