{
  "type": "Feature",
  "properties": {
    "addr:full":"609 S 11th St Paducah KY 42003",
    "addr:housenumber":"609",
    "addr:postcode":"42003",
    "addr:street":"S 11Th St",
    "iso:country":"US",
    "sg:address":"609 S 11th St",
    "sg:city":"Paducah",
    "sg:classifiers":[
        {
            "category":"Retail",
            "subcategory":"Laundry & Dry Cleaning",
            "type":"Services"
        },
        {
            "category":"Building & Trades",
            "subcategory":"Cleaning & Sanitation",
            "type":"Services"
        }
    ],
    "sg:phone":"+1 270 442 8450",
    "sg:postcode":"42003",
    "sg:province":"KY",
    "sg:tags":[
        "cleaner",
        "house"
    ],
    "wof:name":"I See You Cleaning Service",
    "wof:placetype":"venue"
},
  "geometry": {"coordinates":[-88.603425,37.077706],"type":"Point"}
}