{
  "type": "Feature",
  "properties": {
    "addr:full":"415 W Broadway St Frankfort KY 40601",
    "addr:housenumber":"415",
    "addr:postcode":"40601",
    "addr:street":"W Broadway St",
    "iso:country":"US",
    "sg:address":"415 W Broadway St",
    "sg:city":"Frankfort",
    "sg:classifiers":[
        {
            "category":"Shopping",
            "subcategory":"Used Merchandise",
            "type":"Retail Goods"
        }
    ],
    "sg:phone":"+1 502 875 5040",
    "sg:postcode":"40601",
    "sg:province":"KY",
    "sg:tags":[
        "antique"
    ],
    "wof:name":"Rail Fence Antiques",
    "wof:placetype":"venue"
},
  "geometry": {"coordinates":[-84.879356,38.200535],"type":"Point"}
}