{
  "type": "Feature",
  "properties": {
    "iso:country":"US",
    "sg:address":"21 Village Dr",
    "sg:city":"Winchester",
    "sg:classifiers":[
        {
            "category":"Professional",
            "subcategory":"Management & Consulting",
            "type":"Services"
        }
    ],
    "sg:phone":"+1 859 744 5412",
    "sg:postcode":"40391",
    "sg:province":"KY",
    "sg:tags":[
        "business"
    ],
    "wof:name":"John G Powell Inc",
    "wof:placetype":"venue"
},
  "geometry": {"coordinates":[-84.191087,37.992357],"type":"Point"}
}