{
  "type": "Feature",
  "properties": {
    "iso:country":"US",
    "sg:address":"101 Euclid Ave",
    "sg:city":"Paintsville",
    "sg:classifiers":[
        {
            "category":"Government",
            "subcategory":"Office",
            "type":"Public Place"
        }
    ],
    "sg:phone":"+1 606 789 2600",
    "sg:postcode":"41240",
    "sg:province":"KY",
    "sg:tags":[
        "village"
    ],
    "wof:name":"Paintsville City Offices",
    "wof:placetype":"venue"
},
  "geometry": {"coordinates":[-82.802279,37.814873],"type":"Point"}
}