{
  "type": "Feature",
  "properties": {
    "iso:country":"US",
    "sg:address":"2825 Alta Vista Ct",
    "sg:city":"Louisville",
    "sg:classifiers":[
        {
            "category":"Health Services",
            "subcategory":"Doctor",
            "type":"Services"
        }
    ],
    "sg:phone":"+1 502 491 3026",
    "sg:postcode":"40206",
    "sg:province":"KY",
    "sg:tags":[
        "dentist"
    ],
    "wof:name":"Breckinridge Plaza Dental Grp",
    "wof:placetype":"venue"
},
  "geometry": {"coordinates":[-85.683823,38.242746],"type":"Point"}
}