{
  "type": "Feature",
  "properties": {
    "iso:country":"US",
    "sg:address":"710 W 8th St",
    "sg:city":"Corbin",
    "sg:classifiers":[
        {
            "category":"Education",
            "subcategory":"School",
            "type":"Public Place"
        }
    ],
    "sg:phone":"+1 606 528 4367",
    "sg:postcode":"40701",
    "sg:province":"KY",
    "sg:website":"www.2geton.net",
    "wof:name":"Central Primary School",
    "wof:placetype":"venue"
},
  "geometry": {"coordinates":[-84.102564,36.941052],"type":"Point"}
}