{
  "type": "Feature",
  "properties": {
    "iso:country":"US",
    "sg:address":"131 N Main St",
    "sg:city":"Hopkinsville",
    "sg:classifiers":[
        {
            "category":"Travel",
            "subcategory":"Hotels & Motels",
            "type":"Entertainment"
        }
    ],
    "sg:phone":"+1 270 885 5484",
    "sg:postcode":"42240",
    "sg:province":"KY",
    "sg:tags":[
        "operation"
    ],
    "wof:name":"Little River Motel",
    "wof:placetype":"venue"
},
  "geometry": {"coordinates":[-87.48471499999999,36.871832],"type":"Point"}
}