{
  "type": "Feature",
  "properties": {
    "addr:full":"9 Whitebridge Ln Frankfort KY 40601",
    "addr:housenumber":"9",
    "addr:postcode":"40601",
    "addr:street":"Whitebridge Ln",
    "iso:country":"US",
    "sg:address":"9 Whitebridge Ln",
    "sg:city":"Frankfort",
    "sg:classifiers":[
        {
            "category":"Real Estate",
            "subcategory":"Real Estate Agent",
            "type":"Services"
        }
    ],
    "sg:phone":"+1 502 223 8042",
    "sg:postcode":"40601",
    "sg:province":"KY",
    "wof:name":"Morris Realty & Auction Svc",
    "wof:placetype":"venue"
},
  "geometry": {"coordinates":[-84.820227,38.194335],"type":"Point"}
}