{
  "type": "Feature",
  "properties": {
    "addr:full":"3021 River Rd Louisville KY 40207",
    "addr:housenumber":"3021",
    "addr:postcode":"40207",
    "addr:street":"River Rd",
    "iso:country":"US",
    "sg:address":"3021 River Rd",
    "sg:city":"Louisville",
    "sg:classifiers":[
        {
            "category":"Restaurant",
            "type":"Food & Drink"
        }
    ],
    "sg:menulink":"http://www.allmenus.com/ky/jefferson-northeast/4346-king-fish-restaurant/menu/",
    "sg:phone":"+1 502 895 0544",
    "sg:postcode":"40207",
    "sg:province":"KY",
    "sg:tags":[
        "seafood",
        "american"
    ],
    "wof:name":"King Fish Restaurant",
    "wof:placetype":"venue"
},
  "geometry": {"coordinates":[-85.69789400000001,38.278511],"type":"Point"}
}