{
  "type": "Feature",
  "properties": {
    "addr:full":"163 Milton Ave Elizabethtown KY 42701",
    "addr:housenumber":"163",
    "addr:postcode":"42701",
    "addr:street":"Milton Ave",
    "iso:country":"US",
    "sg:address":"163 Milton Ave",
    "sg:city":"Elizabethtown",
    "sg:classifiers":[
        {
            "category":"Professional",
            "subcategory":"Accounting & Tax Preparation",
            "type":"Services"
        }
    ],
    "sg:phone":"+1 270 765 7660",
    "sg:postcode":"42701",
    "sg:province":"KY",
    "sg:tags":[
        "return",
        "filing"
    ],
    "wof:name":"David F Cloud CPA",
    "wof:placetype":"venue"
},
  "geometry": {"coordinates":[-85.818799,37.726142],"type":"Point"}
}