{
  "type": "Feature",
  "properties": {
    "iso:country":"US",
    "sg:address":"570 Penns Chapel Rd",
    "sg:city":"Bowling Green",
    "sg:classifiers":[
        {
            "category":"Building & Trades",
            "subcategory":"Plumbing",
            "type":"Services"
        }
    ],
    "sg:phone":"+1 270 781 3567",
    "sg:postcode":"42101",
    "sg:province":"KY",
    "sg:tags":[
        "septic"
    ],
    "wof:name":"Commercial San Septic Tk Inc",
    "wof:placetype":"venue"
},
  "geometry": {"coordinates":[-86.34512700000001,37.082594],"type":"Point"}
}