{
  "type": "Feature",
  "properties": {
    "iso:country":"US",
    "sg:address":"240 Longview Dr",
    "sg:city":"Paducah",
    "sg:classifiers":[
        {
            "category":"Real Estate",
            "subcategory":"Real Estate Agent",
            "type":"Services"
        }
    ],
    "sg:phone":"+1 270 534 8774",
    "sg:postcode":"42001",
    "sg:province":"KY",
    "sg:tags":[
        "manager"
    ],
    "wof:name":"Dippy Residential Services LLC",
    "wof:placetype":"venue"
},
  "geometry": {"coordinates":[-88.680432,37.038496],"type":"Point"}
}