{
  "type": "Feature",
  "properties": {
    "addr:full":"150 Main St Elkhorn City KY 41522",
    "addr:housenumber":"150",
    "addr:postcode":"41522",
    "addr:street":"Main St",
    "iso:country":"US",
    "sg:address":"150 Main St",
    "sg:city":"Elkhorn City",
    "sg:classifiers":[
        {
            "category":"Education",
            "subcategory":"Library",
            "type":"Public Place"
        }
    ],
    "sg:phone":"+1 606 754 5451",
    "sg:postcode":"41522",
    "sg:province":"KY",
    "wof:name":"Elkhorn City Branch Library",
    "wof:placetype":"venue"
},
  "geometry": {"coordinates":[-82.353469,37.30472],"type":"Point"}
}