{
  "type": "Feature",
  "properties": {
    "addr:full":"1206 Paris Rd Mayfield KY 42066",
    "addr:housenumber":"1206",
    "addr:postcode":"42066",
    "addr:street":"Paris Rd",
    "iso:country":"US",
    "sg:address":"1206 Paris Rd",
    "sg:city":"Mayfield",
    "sg:classifiers":[
        {
            "category":"Home & Garden",
            "subcategory":"Furniture",
            "type":"Retail Goods"
        }
    ],
    "sg:phone":"+1 270 251 9959",
    "sg:postcode":"42066",
    "sg:province":"KY",
    "wof:name":"Oak-N-More",
    "wof:placetype":"venue"
},
  "geometry": {"coordinates":[-88.62737199999999,36.722949],"type":"Point"}
}