{
  "type": "Feature",
  "properties": {
    "addr:full":"1422 Poplar Level Rd Louisville KY 40217",
    "addr:housenumber":"1422",
    "addr:postcode":"40217",
    "addr:street":"Poplar Level Rd",
    "iso:country":"US",
    "sg:address":"1422 Poplar Level Rd",
    "sg:city":"Louisville",
    "sg:classifiers":[
        {
            "category":"Autos & Motor Vehicles",
            "subcategory":"Fuel & Gas Station",
            "type":"Retail Goods"
        }
    ],
    "sg:phone":"+1 502 637 7198",
    "sg:postcode":"40217",
    "sg:province":"KY",
    "sg:tags":[
        "oil"
    ],
    "wof:name":"Super America",
    "wof:placetype":"venue"
},
  "geometry": {"coordinates":[-85.72846699999999,38.219386],"type":"Point"}
}