{
  "type": "Feature",
  "properties": {
    "iso:country":"US",
    "sg:address":"102 Collins Ln",
    "sg:city":"Shelbiana",
    "sg:classifiers":[
        {
            "category":"Mining & Drilling",
            "type":"Manufacturing & Wholesale Goods"
        }
    ],
    "sg:phone":"+1 606 432 1231",
    "sg:postcode":"41501",
    "sg:province":"KY",
    "sg:tags":[
        "oil",
        "well"
    ],
    "wof:name":"Roberts Drilling Co",
    "wof:placetype":"venue"
},
  "geometry": {"coordinates":[-82.484465,37.433791],"type":"Point"}
}