{
  "type": "Feature",
  "properties": {
    "addr:full":"401 Riverboat Row Newport KY 41071",
    "addr:housenumber":"401",
    "addr:postcode":"41071",
    "addr:street":"Riverboat Row",
    "iso:country":"US",
    "sg:address":"401 Riverboat Row",
    "sg:city":"Newport",
    "sg:classifiers":[
        {
            "category":"Restaurant",
            "type":"Food & Drink"
        }
    ],
    "sg:menulink":"http://www.allmenus.com/ky/newport/9865-don-pablos/menu/",
    "sg:phone":"+1 859 261 7100",
    "sg:postcode":"41071",
    "sg:province":"KY",
    "sg:tags":[
        "sandwich",
        "mexican",
        "salad",
        "soup",
        "american",
        "wrap",
        "tex-mex"
    ],
    "wof:name":"Don Pablo's",
    "wof:placetype":"venue"
},
  "geometry": {"coordinates":[-84.492203,39.099436],"type":"Point"}
}