{
  "type": "Feature",
  "properties": {
    "iso:country":"US",
    "sg:address":"9337 Royal Oak Dr",
    "sg:city":"Alexandria",
    "sg:classifiers":[
        {
            "category":"Building & Trades",
            "subcategory":"Construction",
            "type":"Services"
        }
    ],
    "sg:phone":"+1 859 635 5550",
    "sg:postcode":"41001",
    "sg:province":"KY",
    "sg:tags":[
        "contractor"
    ],
    "wof:name":"Woeste Bldrs Inc",
    "wof:placetype":"venue"
},
  "geometry": {"coordinates":[-84.403443,38.935662],"type":"Point"}
}