{
  "type": "Feature",
  "properties": {
    "addr:full":"1718 McCloskey Ave Louisville KY 40210",
    "addr:housenumber":"1718",
    "addr:postcode":"40210",
    "addr:street":"Mccloskey Ave",
    "iso:country":"US",
    "sg:address":"1718 McCloskey Ave",
    "sg:city":"Louisville",
    "sg:classifiers":[
        {
            "category":"Wholesale",
            "subcategory":"Stationery",
            "type":"Manufacturing & Wholesale Goods"
        }
    ],
    "sg:phone":"+1 502 244 4165",
    "sg:postcode":"40210",
    "sg:province":"KY",
    "sg:tags":[
        "product",
        "paper"
    ],
    "wof:name":"Weyerhaeuser Co",
    "wof:placetype":"venue"
},
  "geometry": {"coordinates":[-85.78778699999999,38.225374],"type":"Point"}
}