{
  "type": "Feature",
  "properties": {
    "iso:country":"US",
    "sg:address":"10502 Southern Meadows",
    "sg:city":"Louisville",
    "sg:classifiers":[
        {
            "category":"Manufacturing",
            "subcategory":"Glass & Minerals",
            "type":"Manufacturing & Wholesale Goods"
        }
    ],
    "sg:phone":"+1 502 429 0501",
    "sg:postcode":"40241",
    "sg:province":"KY",
    "sg:tags":[
        "product",
        "nonmetallic",
        "mfg"
    ],
    "wof:name":"Edged In Stone LLC",
    "wof:placetype":"venue"
},
  "geometry": {"coordinates":[-85.560175,38.320095],"type":"Point"}
}