{
  "type": "Feature",
  "properties": {
    "iso:country":"US",
    "sg:address":"5940 Timber Ridge Dr",
    "sg:city":"Prospect",
    "sg:classifiers":[
        {
            "category":"Real Estate",
            "subcategory":"Real Estate Services",
            "type":"Services"
        }
    ],
    "sg:phone":"+1 502 228 4524",
    "sg:postcode":"40059",
    "sg:province":"KY",
    "sg:tags":[
        "company",
        "title"
    ],
    "wof:name":"Land Title Group LTD",
    "wof:placetype":"venue"
},
  "geometry": {"coordinates":[-85.62270100000001,38.338824],"type":"Point"}
}