{
  "type": "Feature",
  "properties": {
    "iso:country":"US",
    "sg:address":"8180 N Dilcrest Cir",
    "sg:city":"Florence",
    "sg:classifiers":[
        {
            "category":"Professional",
            "subcategory":"Accounting & Tax Preparation",
            "type":"Services"
        }
    ],
    "sg:phone":"+1 859 525 1109",
    "sg:postcode":"41042",
    "sg:province":"KY",
    "wof:name":"D W Tombragel CPA",
    "wof:placetype":"venue"
},
  "geometry": {"coordinates":[-84.647082,38.978996],"type":"Point"}
}