{
  "type": "Feature",
  "properties": {
    "iso:country":"US",
    "sg:address":"1427 Shawnee Trl",
    "sg:city":"Ironton",
    "sg:classifiers":[
        {
            "category":"Wholesale",
            "subcategory":"Construction Materials",
            "type":"Manufacturing & Wholesale Goods"
        },
        {
            "category":"Building & Trades",
            "subcategory":"Construction",
            "type":"Services"
        }
    ],
    "sg:phone":"+1 740 532 0509",
    "sg:postcode":"45638",
    "sg:province":"OH",
    "sg:tags":[
        "fence",
        "contractor"
    ],
    "wof:name":"Newman's Fencing",
    "wof:placetype":"venue"
},
  "geometry": {"coordinates":[-82.665789,38.52938],"type":"Point"}
}