{
  "type": "Feature",
  "properties": {
    "addr:full":"15503 Shelbyville Rd Louisville KY 40245",
    "addr:housenumber":"15503",
    "addr:postcode":"40245",
    "addr:street":"Shelbyville Rd",
    "iso:country":"US",
    "sg:address":"15503 Shelbyville Rd",
    "sg:city":"Louisville",
    "sg:classifiers":[
        {
            "category":"Organizations",
            "subcategory":"Community Association",
            "type":"Services"
        }
    ],
    "sg:phone":"+1 502 245 4475",
    "sg:postcode":"40245",
    "sg:province":"KY",
    "sg:tags":[
        "club"
    ],
    "wof:name":"Valhalla Golf Club",
    "wof:placetype":"venue"
},
  "geometry": {"coordinates":[-85.473066,38.236242],"type":"Point"}
}