{
  "type": "Feature",
  "properties": {
    "iso:country":"US",
    "sg:address":"269 Lyttle Blvd",
    "sg:city":"Hazard",
    "sg:classifiers":[
        {
            "category":"Manufacturing",
            "subcategory":"Printing",
            "type":"Manufacturing & Wholesale Goods"
        }
    ],
    "sg:phone":"+1 606 436 6060",
    "sg:postcode":"41701",
    "sg:province":"KY",
    "sg:tags":[
        "newspaper"
    ],
    "wof:name":"Courier Journal",
    "wof:placetype":"venue"
},
  "geometry": {"coordinates":[-83.192666,37.250571],"type":"Point"}
}