{
  "type": "Feature",
  "properties": {
    "iso:country":"US",
    "sg:address":"210 W Cemetery St",
    "sg:city":"Morgantown",
    "sg:classifiers":[
        {
            "category":"Education",
            "subcategory":"School",
            "type":"Public Place"
        }
    ],
    "sg:phone":"+1 270 526 3361",
    "sg:postcode":"42261",
    "sg:province":"KY",
    "wof:name":"Morgantown Elementary School",
    "wof:placetype":"venue"
},
  "geometry": {"coordinates":[-86.681817,37.231174],"type":"Point"}
}