{
  "type": "Feature",
  "properties": {
    "addr:full":"1103 N Main St Hopkinsville KY 42240",
    "addr:housenumber":"1103",
    "addr:postcode":"42240",
    "addr:street":"N Main St",
    "iso:country":"US",
    "sg:address":"1103 N Main St",
    "sg:city":"Hopkinsville",
    "sg:classifiers":[
        {
            "category":"Autos & Motor Vehicles",
            "subcategory":"Automobile Sales",
            "type":"Retail Goods"
        }
    ],
    "sg:phone":"+1 270 886 9524",
    "sg:postcode":"42240",
    "sg:province":"KY",
    "sg:tags":[
        "car",
        "dealer"
    ],
    "wof:name":"Graddy Auto Sales Inc",
    "wof:placetype":"venue"
},
  "geometry": {"coordinates":[-87.481238,36.889252],"type":"Point"}
}