{
  "type": "Feature",
  "properties": {
    "iso:country":"US",
    "sg:address":"1414 S Mayo Trl",
    "sg:city":"Pikeville",
    "sg:classifiers":[
        {
            "category":"Recreation",
            "type":"Entertainment"
        }
    ],
    "sg:phone":"+1 606 631 0012",
    "sg:postcode":"41501",
    "sg:province":"KY",
    "sg:tags":[
        "instruction",
        "gymnastic"
    ],
    "wof:name":"Appalachian Gymnastics Extreme",
    "wof:placetype":"venue"
},
  "geometry": {"coordinates":[-82.521868,37.442702],"type":"Point"}
}