{
  "type": "Feature",
  "properties": {
    "iso:country":"US",
    "sg:address":"3301 Pacific Ct",
    "sg:city":"Louisville",
    "sg:classifiers":[
        {
            "category":"Travel",
            "subcategory":"Travel Agent",
            "type":"Entertainment"
        }
    ],
    "sg:phone":"+1 502 774 8255",
    "sg:postcode":"40211",
    "sg:province":"KY",
    "sg:tags":[
        "agency",
        "services-commercial"
    ],
    "wof:name":"Have Fun Will Travel",
    "wof:placetype":"venue"
},
  "geometry": {"coordinates":[-85.80972300000001,38.22525],"type":"Point"}
}