{
  "type": "Feature",
  "properties": {
    "addr:full":"1410 Pringle St Henderson KY 42420",
    "addr:housenumber":"1410",
    "addr:postcode":"42420",
    "addr:street":"Pringle St",
    "iso:country":"US",
    "sg:address":"1410 Pringle St",
    "sg:city":"Henderson",
    "sg:classifiers":[
        {
            "category":"Building & Trades",
            "subcategory":"Construction",
            "type":"Services"
        }
    ],
    "sg:phone":"+1 270 830 7120",
    "sg:postcode":"42420",
    "sg:province":"KY",
    "sg:tags":[
        "contractor"
    ],
    "wof:name":"D & D Drywall",
    "wof:placetype":"venue"
},
  "geometry": {"coordinates":[-87.58391399999999,37.821576],"type":"Point"}
}