{
  "type": "Feature",
  "properties": {
    "addr:full":"2625 W Parrish Ave Owensboro KY 42301",
    "addr:housenumber":"2625",
    "addr:postcode":"42301",
    "addr:street":"W Parrish Ave",
    "iso:country":"US",
    "sg:address":"2625 W Parrish Ave",
    "sg:city":"Owensboro",
    "sg:classifiers":[
        {
            "category":"Autos & Motor Vehicles",
            "subcategory":"Auto Supplies",
            "type":"Retail Goods"
        }
    ],
    "sg:phone":"+1 270 683 6541",
    "sg:postcode":"42301",
    "sg:province":"KY",
    "sg:tags":[
        "automobile",
        "parts"
    ],
    "wof:name":"O'Reilly Auto Parts",
    "wof:placetype":"venue"
},
  "geometry": {"coordinates":[-87.14516399999999,37.757811],"type":"Point"}
}