{
  "type": "Feature",
  "properties": {
    "iso:country":"US",
    "sg:address":"828 Pointe Dr",
    "sg:city":"Covington",
    "sg:classifiers":[
        {
            "category":"Farming",
            "subcategory":"Farm",
            "type":"Manufacturing & Wholesale Goods"
        }
    ],
    "sg:phone":"+1 859 331 9294",
    "sg:postcode":"41017",
    "sg:province":"KY",
    "sg:tags":[
        "crop",
        "general"
    ],
    "wof:name":"Ash Holding Dennis Hirt",
    "wof:placetype":"venue"
},
  "geometry": {"coordinates":[-84.566807,39.071589],"type":"Point"}
}