{
  "type": "Feature",
  "properties": {
    "addr:full":"2381 Boyce Fairview Rd Alvaton KY 42122",
    "addr:housenumber":"2381",
    "addr:postcode":"42122",
    "addr:street":"Boyce Fairview Rd",
    "iso:country":"US",
    "sg:address":"2381 Boyce Fairview Rd",
    "sg:city":"Alvaton",
    "sg:classifiers":[
        {
            "category":"Building & Trades",
            "subcategory":"Landscaping Services",
            "type":"Services"
        }
    ],
    "sg:phone":"+1 270 782 5983",
    "sg:postcode":"42122",
    "sg:province":"KY",
    "sg:tags":[
        "landscape"
    ],
    "wof:name":"Landscape Design Consulti",
    "wof:placetype":"venue"
},
  "geometry": {"coordinates":[-86.353521,36.841386],"type":"Point"}
}