{
  "type": "Feature",
  "properties": {
    "iso:country":"US",
    "sg:address":"4940 Woodcock Cir",
    "sg:city":"Louisville",
    "sg:classifiers":[
        {
            "category":"Real Estate",
            "subcategory":"Real Estate Operator",
            "type":"Services"
        }
    ],
    "sg:phone":"+1 502 969 4455",
    "sg:postcode":"40213",
    "sg:province":"KY",
    "sg:tags":[
        "property",
        "lessor"
    ],
    "wof:name":"Evans Lewis",
    "wof:placetype":"venue"
},
  "geometry": {"coordinates":[-85.711082,38.177543],"type":"Point"}
}