{
  "type": "Feature",
  "properties": {
    "addr:full":"6541 Cairo Dixie Rd Corydon KY 42406",
    "addr:housenumber":"6541",
    "addr:postcode":"42406",
    "addr:street":"Cairo Dixie Rd",
    "iso:country":"US",
    "sg:address":"6541 Cairo Dixie Rd",
    "sg:city":"Corydon",
    "sg:classifiers":[
        {
            "category":"Insurance",
            "subcategory":"Insurance Agent",
            "type":"Services"
        }
    ],
    "sg:phone":"+1 270 533 6000",
    "sg:postcode":"42406",
    "sg:province":"KY",
    "wof:name":"Allstate Tower Inc",
    "wof:placetype":"venue"
},
  "geometry": {"coordinates":[-87.65840799999999,37.693443],"type":"Point"}
}