{
  "type": "Feature",
  "properties": {
    "iso:country":"US",
    "sg:address":"747 Harrison Ave",
    "sg:city":"Louisville",
    "sg:classifiers":[
        {
            "category":"Organizations",
            "subcategory":"Religious Organization",
            "type":"Services"
        }
    ],
    "sg:phone":"+1 502 637 7442",
    "sg:postcode":"40217",
    "sg:province":"KY",
    "sg:tags":[
        "place",
        "worship",
        "church"
    ],
    "sg:website":"www.omos.org",
    "wof:name":"Our Mother Of Sorrows",
    "wof:placetype":"venue"
},
  "geometry": {"coordinates":[-85.743928,38.212662],"type":"Point"}
}