{
  "type": "Feature",
  "properties": {
    "addr:full":"13725 Shelbyville Rd Louisville KY 40245",
    "addr:housenumber":"13725",
    "addr:postcode":"40245",
    "addr:street":"Shelbyville Rd",
    "iso:country":"US",
    "sg:address":"13725 Shelbyville Rd",
    "sg:city":"Louisville",
    "sg:classifiers":[
        {
            "category":"Social Services",
            "subcategory":"Child Care",
            "type":"Services"
        },
        {
            "category":"Education",
            "subcategory":"Preschool",
            "type":"Public Place"
        }
    ],
    "sg:phone":"+1 502 494 6997",
    "sg:postcode":"40245",
    "sg:province":"KY",
    "sg:tags":[
        "kindergarten"
    ],
    "sg:website":"http://www.openarmspreschool.org",
    "wof:name":"Open Arms Preschool",
    "wof:placetype":"venue"
},
  "geometry": {"coordinates":[-85.497782,38.24152],"type":"Point"}
}