{
  "type": "Feature",
  "properties": {
    "iso:country":"US",
    "sg:address":"601 Lynn Acres Rd",
    "sg:city":"Shelbyville",
    "sg:classifiers":[
        {
            "category":"Real Estate",
            "subcategory":"Real Estate Operator",
            "type":"Services"
        }
    ],
    "sg:phone":"+1 502 633 3251",
    "sg:postcode":"40065",
    "sg:province":"KY",
    "sg:tags":[
        "apartment"
    ],
    "wof:name":"Lynne Acres Apartments",
    "wof:placetype":"venue"
},
  "geometry": {"coordinates":[-85.241945,38.208965],"type":"Point"}
}