{
  "type": "Feature",
  "properties": {
    "iso:country":"US",
    "sg:address":"2169 Midland Trl",
    "sg:city":"Shelbyville",
    "sg:classifiers":[
        {
            "category":"Real Estate",
            "subcategory":"Real Estate Operator",
            "type":"Services"
        }
    ],
    "sg:phone":"+1 502 633 1620",
    "sg:postcode":"40065",
    "sg:province":"KY",
    "sg:tags":[
        "apartment"
    ],
    "wof:name":"Wesley Apartments",
    "wof:placetype":"venue"
},
  "geometry": {"coordinates":[-85.25586199999999,38.213021],"type":"Point"}
}