{
  "type": "Feature",
  "properties": {
    "iso:country":"US",
    "sg:address":"515 S 3rd St",
    "sg:city":"Ironton",
    "sg:classifiers":[
        {
            "category":"Retail",
            "subcategory":"Laundry & Dry Cleaning",
            "type":"Services"
        }
    ],
    "sg:phone":"+1 740 533 1985",
    "sg:postcode":"45638",
    "sg:province":"OH",
    "sg:tags":[
        "cleaners"
    ],
    "wof:name":"Cardinal Cleaners",
    "wof:placetype":"venue"
},
  "geometry": {"coordinates":[-82.682458,38.531548],"type":"Point"}
}