{
  "type": "Feature",
  "properties": {
    "iso:country":"US",
    "sg:address":"1050 Scarlett Ln",
    "sg:city":"Lawrenceburg",
    "sg:classifiers":[
        {
            "category":"Retail",
            "subcategory":"Animal Services",
            "type":"Services"
        }
    ],
    "sg:phone":"+1 502 839 1115",
    "sg:postcode":"40342",
    "sg:province":"KY",
    "wof:name":"Happy Pets",
    "wof:placetype":"venue"
},
  "geometry": {"coordinates":[-84.88909099999999,38.018793],"type":"Point"}
}