{
  "type": "Feature",
  "properties": {
    "iso:country":"US",
    "sg:address":"127 E Main St",
    "sg:city":"La Grange",
    "sg:classifiers":[
        {
            "category":"Shopping",
            "subcategory":"Used Merchandise",
            "type":"Retail Goods"
        }
    ],
    "sg:phone":"+1 502 222 0918",
    "sg:postcode":"40031",
    "sg:province":"KY",
    "sg:tags":[
        "book",
        "rare",
        "dealer"
    ],
    "wof:name":"Karen's Book Barn",
    "wof:placetype":"venue"
},
  "geometry": {"coordinates":[-85.377849,38.407655],"type":"Point"}
}