{
  "type": "Feature",
  "properties": {
    "iso:country":"US",
    "sg:address":"710 Pisgah Pike",
    "sg:city":"Versailles",
    "sg:classifiers":[
        {
            "category":"Organizations",
            "subcategory":"Religious Organization",
            "type":"Services"
        }
    ],
    "sg:phone":"+1 859 873 4161",
    "sg:postcode":"40383",
    "sg:province":"KY",
    "sg:tags":[
        "church"
    ],
    "wof:name":"Pisgah Presbyterian Church",
    "wof:placetype":"venue"
},
  "geometry": {"coordinates":[-84.655213,38.055819],"type":"Point"}
}