{
  "type": "Feature",
  "properties": {
    "iso:country":"US",
    "sg:address":"108 E Main St",
    "sg:city":"Midway",
    "sg:classifiers":[
        {
            "category":"Retail",
            "subcategory":"Repair Shop",
            "type":"Services"
        }
    ],
    "sg:phone":"+1 859 846 9334",
    "sg:postcode":"40347",
    "sg:province":"KY",
    "sg:tags":[
        "picture",
        "framing"
    ],
    "wof:name":"Railroad Street Annex Frame",
    "wof:placetype":"venue"
},
  "geometry": {"coordinates":[-84.683042,38.150609],"type":"Point"}
}