{
  "type": "Feature",
  "properties": {
    "addr:full":"1835 Old Preston Hwy N Louisville KY 40229",
    "addr:housenumber":"1835",
    "addr:postcode":"40229",
    "addr:street":"Old Preston Hwy N",
    "iso:country":"US",
    "sg:address":"1835 Old Preston Hwy N",
    "sg:city":"Louisville",
    "sg:classifiers":[
        {
            "category":"Restaurant",
            "type":"Food & Drink"
        }
    ],
    "sg:menulink":"http://www.allmenus.com/ky/shepherdsville-northwest/176028-kfc---kentucky-fried-chicken/menu/",
    "sg:phone":"+1 502 957 2151",
    "sg:postcode":"40229",
    "sg:province":"KY",
    "sg:tags":[
        "american",
        "chicken"
    ],
    "wof:name":"KFC - Kentucky Fried Chicken",
    "wof:placetype":"venue"
},
  "geometry": {"coordinates":[-85.667643,38.08205],"type":"Point"}
}