{
  "type": "Feature",
  "properties": {
    "iso:country":"US",
    "sg:address":"142 Deliahs Way",
    "sg:city":"Hardinsburg",
    "sg:classifiers":[
        {
            "category":"Organizations",
            "subcategory":"Religious Organization",
            "type":"Services"
        }
    ],
    "sg:phone":"+1 270 756 0474",
    "sg:postcode":"40165",
    "sg:province":"KY",
    "sg:tags":[
        "church"
    ],
    "wof:name":"First Baptist Church",
    "wof:placetype":"venue"
},
  "geometry": {"coordinates":[-85.759322,37.984964],"type":"Point"}
}