{
  "type": "Feature",
  "properties": {
    "iso:country":"US",
    "sg:address":"961 S 3rd St",
    "sg:city":"Louisville",
    "sg:classifiers":[
        {
            "category":"Home & Garden",
            "subcategory":"Furniture",
            "type":"Retail Goods"
        }
    ],
    "sg:phone":"+1 502 584 4152",
    "sg:postcode":"40203",
    "sg:province":"KY",
    "wof:name":"American Home Supply Co",
    "wof:placetype":"venue"
},
  "geometry": {"coordinates":[-85.757593,38.240551],"type":"Point"}
}