{
  "type": "Feature",
  "properties": {
    "iso:country":"US",
    "sg:address":"1151 Summitt Rd",
    "sg:city":"Ashland",
    "sg:classifiers":[
        {
            "category":"Freight",
            "type":"Transportation"
        }
    ],
    "sg:phone":"+1 606 928 0219",
    "sg:postcode":"41102",
    "sg:province":"KY",
    "sg:tags":[
        "commercial",
        "storage"
    ],
    "wof:name":"American Storage Ctr",
    "wof:placetype":"venue"
},
  "geometry": {"coordinates":[-82.699758,38.429459],"type":"Point"}
}