{
  "type": "Feature",
  "properties": {
    "addr:full":"600 Dr Martin Luther King Pl 1006 Martin Louisville KY 40202",
    "addr:housenumber":"600;1006",
    "addr:postcode":"40202",
    "addr:street":"Dr Martin Luther King Pl;Martin",
    "iso:country":"US",
    "sg:address":"600 Dr Martin Luther King Pl 1006 Martin",
    "sg:city":"Louisville",
    "sg:classifiers":[
        {
            "category":"Government",
            "subcategory":"Police Station",
            "type":"Public Place"
        },
        {
            "category":"Professional",
            "subcategory":"Detective & Security Services",
            "type":"Services"
        }
    ],
    "sg:phone":"+1 502 582 5908",
    "sg:postcode":"40202",
    "sg:province":"KY",
    "sg:tags":[
        "enforcement",
        "law",
        "agencies-government",
        "rescue"
    ],
    "wof:name":"Louisville Resident Office",
    "wof:placetype":"venue"
},
  "geometry": {"coordinates":[-85.761269,38.24884],"type":"Point"}
}