{
  "type": "Feature",
  "properties": {
    "iso:country":"US",
    "sg:address":"117 W 9th St",
    "sg:city":"Hopkinsville",
    "sg:classifiers":[
        {
            "category":"Real Estate",
            "subcategory":"Real Estate Agent",
            "type":"Services"
        }
    ],
    "sg:phone":"+1 270 889 0699",
    "sg:postcode":"42240",
    "sg:province":"KY",
    "wof:name":"Mc Coy Properties",
    "wof:placetype":"venue"
},
  "geometry": {"coordinates":[-87.489756,36.865833],"type":"Point"}
}