{
  "type": "Feature",
  "properties": {
    "iso:country":"US",
    "sg:address":"1475 E Millerstown Rd",
    "sg:city":"Upton",
    "sg:classifiers":[
        {
            "category":"Building & Trades",
            "subcategory":"Electrical",
            "type":"Services"
        }
    ],
    "sg:phone":"+1 270 369 7519",
    "sg:postcode":"42784",
    "sg:province":"KY",
    "sg:tags":[
        "electric",
        "contractor"
    ],
    "wof:name":"Greg Riggs Inc",
    "wof:placetype":"venue"
},
  "geometry": {"coordinates":[-86.023414,37.445138],"type":"Point"}
}