{
  "type": "Feature",
  "properties": {
    "iso:country":"US",
    "sg:address":"8055 Us Highway 42",
    "sg:city":"Florence",
    "sg:classifiers":[
        {
            "category":"Restaurant",
            "type":"Food & Drink"
        }
    ],
    "sg:menulink":"http://www.allmenus.com/ky/florence/176090-kfc---kentucky-fried-chicken/menu/",
    "sg:phone":"+1 606 371 4569",
    "sg:postcode":"41042",
    "sg:province":"KY",
    "sg:tags":[
        "american",
        "chicken"
    ],
    "wof:name":"KFC - Kentucky Fried Chicken",
    "wof:placetype":"venue"
},
  "geometry": {"coordinates":[-84.643198,38.983131],"type":"Point"}
}