{
  "type": "Feature",
  "properties": {
    "iso:country":"US",
    "sg:address":"2339 Rockford Ln",
    "sg:city":"Shively",
    "sg:classifiers":[
        {
            "category":"Retail",
            "subcategory":"Self-service Laundry",
            "type":"Services"
        }
    ],
    "sg:phone":"+1 502 447 4118",
    "sg:postcode":"40216",
    "sg:province":"KY",
    "wof:name":"Economy Cleaners",
    "wof:placetype":"venue"
},
  "geometry": {"coordinates":[-85.838711,38.176262],"type":"Point"}
}