{
  "type": "Feature",
  "properties": {
    "addr:full":"152 School St Lewisburg KY 42256",
    "addr:housenumber":"152",
    "addr:postcode":"42256",
    "addr:street":"School St",
    "iso:country":"US",
    "sg:address":"152 School St",
    "sg:city":"Lewisburg",
    "sg:classifiers":[
        {
            "category":"Social Services",
            "type":"Services"
        }
    ],
    "sg:phone":"+1 270 755 3463",
    "sg:postcode":"42256",
    "sg:province":"KY",
    "sg:tags":[
        "organization",
        "welfare"
    ],
    "wof:name":"Lewisburg Family Resource Ctr",
    "wof:placetype":"venue"
},
  "geometry": {"coordinates":[-86.948049,36.985725],"type":"Point"}
}