{
  "type": "Feature",
  "properties": {
    "iso:country":"US",
    "sg:address":"234 Broyles Ave",
    "sg:city":"Paducah",
    "sg:classifiers":[
        {
            "category":"Social Services",
            "subcategory":"Child Care",
            "type":"Services"
        }
    ],
    "sg:phone":"+1 270 554 2109",
    "sg:postcode":"42003",
    "sg:province":"KY",
    "sg:tags":[
        "day"
    ],
    "wof:name":"Frances Schmidt Day Care Home",
    "wof:placetype":"venue"
},
  "geometry": {"coordinates":[-88.62223,37.041441],"type":"Point"}
}