{
  "type": "Feature",
  "properties": {
    "iso:country":"US",
    "sg:address":"121 Kentucky Ave",
    "sg:city":"Princeton",
    "sg:classifiers":[
        {
            "category":"Organizations",
            "subcategory":"Religious Organization",
            "type":"Services"
        }
    ],
    "sg:phone":"+1 270 365 5606",
    "sg:postcode":"42445",
    "sg:province":"KY",
    "wof:name":"Calvery Baptist Church",
    "wof:placetype":"venue"
},
  "geometry": {"coordinates":[-87.89770799999999,37.116741],"type":"Point"}
}