{
  "type": "Feature",
  "properties": {
    "iso:country":"US",
    "sg:address":"262 Main St",
    "sg:city":"Lebanon Junction",
    "sg:classifiers":[
        {
            "category":"Shopping",
            "subcategory":"Florist",
            "type":"Retail Goods"
        }
    ],
    "sg:phone":"+1 502 833 0809",
    "sg:postcode":"40150",
    "sg:province":"KY",
    "wof:name":"Down Home Florist Gifts",
    "wof:placetype":"venue"
},
  "geometry": {"coordinates":[-85.73299299999999,37.834535],"type":"Point"}
}