{
  "type": "Feature",
  "properties": {
    "iso:country":"US",
    "sg:address":"4413 E Pages Ln",
    "sg:city":"Valley Station",
    "sg:classifiers":[
        {
            "category":"Social Services",
            "subcategory":"Child Care",
            "type":"Services"
        },
        {
            "category":"Organizations",
            "subcategory":"Religious Organization",
            "type":"Services"
        }
    ],
    "sg:phone":"+1 502 937 0932",
    "sg:postcode":"40272",
    "sg:province":"KY",
    "sg:tags":[
        "church"
    ],
    "wof:name":"Resurrection Life Church Dayca",
    "wof:placetype":"venue"
},
  "geometry": {"coordinates":[-85.84680400000001,38.129847],"type":"Point"}
}