{
  "type": "Feature",
  "properties": {
    "iso:country":"US",
    "sg:address":"1498 Dixie Hwy N",
    "sg:city":"Radcliff",
    "sg:classifiers":[
        {
            "category":"Professional",
            "type":"Services"
        }
    ],
    "sg:phone":"+1 270 351 8158",
    "sg:postcode":"40160",
    "sg:province":"KY",
    "sg:tags":[
        "establishment"
    ],
    "wof:name":"MPRI Inc",
    "wof:placetype":"venue"
},
  "geometry": {"coordinates":[-85.951182,37.854104],"type":"Point"}
}