{
  "type": "Feature",
  "properties": {
    "iso:country":"US",
    "sg:address":"239 S 5th St",
    "sg:city":"Louisville",
    "sg:classifiers":[
        {
            "category":"Building & Trades",
            "subcategory":"Cleaning & Sanitation",
            "type":"Services"
        }
    ],
    "sg:phone":"+1 502 581 1275",
    "sg:postcode":"40202",
    "sg:province":"KY",
    "sg:tags":[
        "janitor"
    ],
    "wof:name":"Absolute Janitoral Cleaning",
    "wof:placetype":"venue"
},
  "geometry": {"coordinates":[-85.75857000000001,38.254137],"type":"Point"}
}