{
  "type": "Feature",
  "properties": {
    "iso:country":"US",
    "sg:address":"8435 US Hwy 42",
    "sg:city":"Florence",
    "sg:classifiers":[
        {
            "category":"Professional",
            "subcategory":"Art Services",
            "type":"Services"
        }
    ],
    "sg:phone":"+1 859 282 8343",
    "sg:postcode":"41042",
    "sg:province":"KY",
    "sg:tags":[
        "graphic",
        "designer"
    ],
    "wof:name":"Hammerhead Graphix",
    "wof:placetype":"venue"
},
  "geometry": {"coordinates":[-84.65521699999999,38.978604],"type":"Point"}
}