{
  "type": "Feature",
  "properties": {
    "addr:full":"2441 Crittenden Dr Louisville KY 40217",
    "addr:housenumber":"2441",
    "addr:postcode":"40217",
    "addr:street":"Crittenden Dr",
    "iso:country":"US",
    "sg:address":"2441 Crittenden Dr",
    "sg:city":"Louisville",
    "sg:classifiers":[
        {
            "category":"Organizations",
            "subcategory":"Labor Organization",
            "type":"Services"
        }
    ],
    "sg:phone":"+1 502 637 8796",
    "sg:postcode":"40217",
    "sg:province":"KY",
    "wof:name":"Iron Workers Local Union",
    "wof:placetype":"venue"
},
  "geometry": {"coordinates":[-85.750992,38.208833],"type":"Point"}
}