{
  "type": "Feature",
  "properties": {
    "addr:full":"309 Shelby St Frankfort KY 40601",
    "addr:housenumber":"309",
    "addr:postcode":"40601",
    "addr:street":"Shelby St",
    "iso:country":"US",
    "sg:address":"309 Shelby St",
    "sg:city":"Frankfort",
    "sg:classifiers":[
        {
            "category":"Professional",
            "subcategory":"Lawyer & Legal Services",
            "type":"Services"
        }
    ],
    "sg:phone":"+1 502 223 1729",
    "sg:postcode":"40601",
    "sg:province":"KY",
    "sg:tags":[
        "attorney"
    ],
    "wof:name":"Castil Williams",
    "wof:placetype":"venue"
},
  "geometry": {"coordinates":[-84.87625800000001,38.193146],"type":"Point"}
}