{
  "type": "Feature",
  "properties": {
    "addr:full":"240 Clark St Lexington KY 40507",
    "addr:housenumber":"240",
    "addr:postcode":"40507",
    "addr:street":"Clark St",
    "iso:country":"US",
    "sg:address":"240 Clark St",
    "sg:city":"Lexington",
    "sg:classifiers":[
        {
            "category":"Government",
            "subcategory":"Office",
            "type":"Public Place"
        }
    ],
    "sg:phone":"+1 859 254 0315",
    "sg:postcode":"40507",
    "sg:province":"KY",
    "sg:tags":[
        "village"
    ],
    "wof:name":"Lexington Equipment Distr Ctr",
    "wof:placetype":"venue"
},
  "geometry": {"coordinates":[-84.492013,38.045232],"type":"Point"}
}