{
  "type": "Feature",
  "properties": {
    "iso:country":"US",
    "sg:address":"1069 Chasewood Way",
    "sg:city":"Lexington",
    "sg:classifiers":[
        {
            "category":"Professional",
            "subcategory":"Computer Services",
            "type":"Services"
        }
    ],
    "sg:phone":"+1 859 296 0379",
    "sg:postcode":"40513",
    "sg:province":"KY",
    "sg:tags":[
        "related"
    ],
    "wof:name":"EMC Group Inc",
    "wof:placetype":"venue"
},
  "geometry": {"coordinates":[-84.562415,38.0188],"type":"Point"}
}