{
  "type": "Feature",
  "properties": {
    "iso:country":"US",
    "sg:address":"9167 Fire Wood Ct",
    "sg:city":"Covington",
    "sg:classifiers":[
        {
            "category":"Travel",
            "subcategory":"Travel Agent",
            "type":"Entertainment"
        }
    ],
    "sg:phone":"+1 859 363 0684",
    "sg:postcode":"41017",
    "sg:province":"KY",
    "sg:tags":[
        "agency",
        "bureau"
    ],
    "wof:name":"Wayside Worldwide Travel",
    "wof:placetype":"venue"
},
  "geometry": {"coordinates":[-84.520004,38.987502],"type":"Point"}
}