{
  "type": "Feature",
  "properties": {
    "iso:country":"US",
    "sg:address":"2231 Payne St",
    "sg:city":"Louisville",
    "sg:classifiers":[
        {
            "category":"Organizations",
            "subcategory":"Religious Organization",
            "type":"Services"
        }
    ],
    "sg:phone":"+1 502 895 3189",
    "sg:postcode":"40206",
    "sg:province":"KY",
    "sg:tags":[
        "church"
    ],
    "sg:website":"www.cliftonunitarian.org",
    "wof:name":"Unitarian Church Of Clifton",
    "wof:placetype":"venue"
},
  "geometry": {"coordinates":[-85.703934,38.252243],"type":"Point"}
}