{
  "type": "Feature",
  "properties": {
    "iso:country":"US",
    "sg:address":"264 Big Run Rd",
    "sg:city":"Lexington",
    "sg:classifiers":[
        {
            "category":"Manufacturing",
            "subcategory":"Furniture",
            "type":"Manufacturing & Wholesale Goods"
        }
    ],
    "sg:phone":"+1 859 277 1233",
    "sg:postcode":"40503",
    "sg:province":"KY",
    "sg:tags":[
        "household",
        "wood",
        "mfg"
    ],
    "wof:name":"Cellar Door",
    "wof:placetype":"venue"
},
  "geometry": {"coordinates":[-84.528381,37.999259],"type":"Point"}
}