{
  "type": "Feature",
  "properties": {
    "iso:country":"US",
    "sg:address":"4505 Cumberland Falls Hwy",
    "sg:city":"Corbin",
    "sg:classifiers":[
        {
            "category":"Social Services",
            "type":"Services"
        }
    ],
    "sg:phone":"+1 606 523 0741",
    "sg:postcode":"40701",
    "sg:province":"KY",
    "sg:tags":[
        "info",
        "program",
        "referral"
    ],
    "wof:name":"Oak Grove Family Resource Ctr",
    "wof:placetype":"venue"
},
  "geometry": {"coordinates":[-84.15534599999999,36.908242],"type":"Point"}
}