{
  "type": "Feature",
  "properties": {
    "iso:country":"US",
    "sg:address":"1410 W 9th St",
    "sg:city":"Owensboro",
    "sg:classifiers":[
        {
            "category":"Building & Trades",
            "subcategory":"Plumbing",
            "type":"Services"
        }
    ],
    "sg:phone":"+1 270 691 1001",
    "sg:postcode":"42301",
    "sg:province":"KY",
    "sg:tags":[
        "conditioning",
        "air",
        "system",
        "contractor"
    ],
    "wof:name":"Schwartz Heating & Cooling Inc",
    "wof:placetype":"venue"
},
  "geometry": {"coordinates":[-87.127122,37.765947],"type":"Point"}
}