{
  "type": "Feature",
  "properties": {
    "iso:country":"US",
    "sg:address":"1401 Harrodsburg Rd",
    "sg:city":"Lexington",
    "sg:phone":"+1 859 277 2280",
    "sg:postcode":"40504",
    "sg:province":"KY",
    "wof:name":"Slabaugh Thomas K MD",
    "wof:placetype":"venue"
},
  "geometry": {"coordinates":[-84.523819,38.033581],"type":"Point"}
}