{
  "type": "Feature",
  "properties": {
    "iso:country":"US",
    "sg:address":"2742 Oscar Rd",
    "sg:city":"Barlow",
    "sg:classifiers":[
        {
            "category":"Farming",
            "subcategory":"Farm",
            "type":"Manufacturing & Wholesale Goods"
        }
    ],
    "sg:phone":"+1 270 334 3328",
    "sg:postcode":"42024",
    "sg:province":"KY",
    "sg:tags":[
        "crop",
        "general"
    ],
    "wof:name":"Rollings Farms",
    "wof:placetype":"venue"
},
  "geometry": {"coordinates":[-89.04199,37.078866],"type":"Point"}
}