{
  "type": "Feature",
  "properties": {
    "iso:country":"US",
    "sg:address":"102 S Walnut St",
    "sg:city":"Cynthiana",
    "sg:classifiers":[
        {
            "category":"Shopping",
            "type":"Retail Goods"
        }
    ],
    "sg:phone":"+1 859 234 5300",
    "sg:postcode":"41031",
    "sg:province":"KY",
    "sg:tags":[
        "spa",
        "hot",
        "tub"
    ],
    "wof:name":"Jetubs",
    "wof:placetype":"venue"
},
  "geometry": {"coordinates":[-84.29585899999999,38.388953],"type":"Point"}
}