{
  "type": "Feature",
  "properties": {
    "iso:country":"US",
    "sg:address":"1717 Airport Exchange Blvd",
    "sg:city":"Erlanger",
    "sg:classifiers":[
        {
            "category":"Travel",
            "subcategory":"Hotels & Motels",
            "type":"Entertainment"
        },
        {
            "category":"Retail",
            "subcategory":"Event Space",
            "type":"Services"
        },
        {
            "category":"Travel",
            "subcategory":"Resort",
            "type":"Entertainment"
        }
    ],
    "sg:phone":"+1 800 345 8082",
    "sg:postcode":"41018",
    "sg:province":"KY",
    "sg:tags":[
        "hall",
        "lodging",
        "banquet",
        "reception",
        "facility"
    ],
    "sg:website":"http://ad.doubleclick.net/clk;223371278;47096201;d?http://www.holidayinn.com/redirect?path=hd&brandCode=hi&hotelCode=cvgap&_PMID=99601036&cm_mmc=mdpr-_-yellowpages-_-hi-_-cvgap",
    "wof:name":"Holiday Inn Cincinnati-Airport",
    "wof:placetype":"venue"
},
  "geometry": {"coordinates":[-84.62647800000001,39.057653],"type":"Point"}
}