{
  "type": "Feature",
  "properties": {
    "iso:country":"US",
    "sg:address":"585 Catalpa Ln",
    "sg:city":"Shelbyville",
    "sg:classifiers":[
        {
            "category":"Building & Trades",
            "subcategory":"Construction",
            "type":"Services"
        }
    ],
    "sg:phone":"+1 502 633 0774",
    "sg:postcode":"40065",
    "sg:province":"KY",
    "sg:tags":[
        "contractor"
    ],
    "wof:name":"Mike Roberts Insulation",
    "wof:placetype":"venue"
},
  "geometry": {"coordinates":[-85.20983099999999,38.186207],"type":"Point"}
}