{
  "type": "Feature",
  "properties": {
    "iso:country":"US",
    "sg:address":"1015 Skyline Dr",
    "sg:city":"Hopkinsville",
    "sg:classifiers":[
        {
            "category":"Organizations",
            "subcategory":"Religious Organization",
            "type":"Services"
        }
    ],
    "sg:phone":"+1 270 886 6027",
    "sg:postcode":"42240",
    "sg:province":"KY",
    "sg:tags":[
        "church"
    ],
    "wof:name":"Hillcrest Baptist Annex",
    "wof:placetype":"venue"
},
  "geometry": {"coordinates":[-87.47497,36.847],"type":"Point"}
}