{
  "type": "Feature",
  "properties": {
    "iso:country":"US",
    "sg:address":"401 Main St",
    "sg:city":"Greenup",
    "sg:classifiers":[
        {
            "category":"Banks & Credit Unions",
            "subcategory":"Bank",
            "type":"Services"
        }
    ],
    "sg:phone":"+1 606 473 9835",
    "sg:postcode":"41144",
    "sg:province":"KY",
    "wof:name":"First Peoples Bank & Trust Co",
    "wof:placetype":"venue"
},
  "geometry": {"coordinates":[-82.836516,38.577793],"type":"Point"}
}