{
  "type": "Feature",
  "properties": {
    "iso:country":"US",
    "sg:address":"529 Keno Rd",
    "sg:city":"Burnside",
    "sg:classifiers":[
        {
            "category":"Government",
            "subcategory":"Office",
            "type":"Public Place"
        }
    ],
    "sg:phone":"+1 606 561 5192",
    "sg:postcode":"42519",
    "sg:province":"KY",
    "wof:name":"Burnside Group Home",
    "wof:placetype":"venue"
},
  "geometry": {"coordinates":[-84.545486,36.889035],"type":"Point"}
}