{
  "type": "Feature",
  "properties": {
    "iso:country":"US",
    "sg:address":"4202 Davco Way",
    "sg:city":"Louisville",
    "sg:classifiers":[
        {
            "category":"Professional",
            "subcategory":"Business Services",
            "type":"Services"
        }
    ],
    "sg:phone":"+1 502 807 7494",
    "sg:postcode":"40241",
    "sg:province":"KY",
    "sg:tags":[
        "party",
        "decorating",
        "convention"
    ],
    "wof:name":"Dagenbela Corp",
    "wof:placetype":"venue"
},
  "geometry": {"coordinates":[-85.601356,38.309958],"type":"Point"}
}