{
  "type": "Feature",
  "properties": {
    "addr:full":"429 Main St Shelbyville KY 40065",
    "addr:housenumber":"429",
    "addr:postcode":"40065",
    "addr:street":"Main St",
    "iso:country":"US",
    "sg:address":"429 Main St",
    "sg:city":"Shelbyville",
    "sg:classifiers":[
        {
            "category":"Organizations",
            "subcategory":"Religious Organization",
            "type":"Services"
        }
    ],
    "sg:phone":"+1 502 633 4510",
    "sg:postcode":"40065",
    "sg:province":"KY",
    "sg:tags":[
        "church"
    ],
    "wof:name":"Centenary United Methodist Chr",
    "wof:placetype":"venue"
},
  "geometry": {"coordinates":[-85.215423,38.211012],"type":"Point"}
}