{
  "type": "Feature",
  "properties": {
    "iso:country":"US",
    "sg:address":"3506 Taylor Blvd",
    "sg:city":"Louisville",
    "sg:classifiers":[
        {
            "category":"Shopping",
            "subcategory":"Used Merchandise",
            "type":"Retail Goods"
        }
    ],
    "sg:phone":"+1 502 368 0431",
    "sg:postcode":"40215",
    "sg:province":"KY",
    "sg:tags":[
        "furniture"
    ],
    "wof:name":"Emmett's New & Used Furniture",
    "wof:placetype":"venue"
},
  "geometry": {"coordinates":[-85.78307,38.195883],"type":"Point"}
}