{
  "type": "Feature",
  "properties": {
    "addr:full":"422 Frederica St Owensboro KY 42301",
    "addr:housenumber":"422",
    "addr:postcode":"42301",
    "addr:street":"Frederica St",
    "iso:country":"US",
    "sg:address":"422 Frederica St",
    "sg:city":"Owensboro",
    "sg:classifiers":[
        {
            "category":"Professional",
            "subcategory":"Lawyer & Legal Services",
            "type":"Services"
        }
    ],
    "sg:phone":"+1 270 993 8989",
    "sg:postcode":"42301",
    "sg:province":"KY",
    "sg:tags":[
        "attorney"
    ],
    "wof:name":"Daniel A Clark III Law Offices",
    "wof:placetype":"venue"
},
  "geometry": {"coordinates":[-87.113338,37.771723],"type":"Point"}
}