{
  "type": "Feature",
  "properties": {
    "iso:country":"US",
    "sg:address":"22 Theatre Sq",
    "sg:city":"Louisville",
    "sg:classifiers":[
        {
            "category":"Restaurant",
            "type":"Food & Drink"
        }
    ],
    "sg:phone":"+1 502 584 0364",
    "sg:postcode":"40202",
    "sg:province":"KY",
    "wof:name":"Anthony's 4th St Deli",
    "wof:placetype":"venue"
},
  "geometry": {"coordinates":[-85.758574,38.247591],"type":"Point"}
}