{
  "type": "Feature",
  "properties": {
    "iso:country":"US",
    "sg:address":"1915 Petersburg Rd",
    "sg:city":"Hebron",
    "sg:classifiers":[
        {
            "category":"Organizations",
            "subcategory":"Religious Organization",
            "type":"Services"
        }
    ],
    "sg:phone":"+1 859 689 4782",
    "sg:postcode":"41048",
    "sg:province":"KY",
    "sg:tags":[
        "church"
    ],
    "wof:name":"Hebron Gospel Fellowship",
    "wof:placetype":"venue"
},
  "geometry": {"coordinates":[-84.69980099999999,39.065989],"type":"Point"}
}