{
  "type": "Feature",
  "properties": {
    "addr:full":"8390 Benson Pike Bagdad KY 40003",
    "addr:housenumber":"8390",
    "addr:postcode":"40003",
    "addr:street":"Benson Pike",
    "iso:country":"US",
    "sg:address":"8390 Benson Pike",
    "sg:city":"Bagdad",
    "sg:phone":"+1 502 747 5238",
    "sg:postcode":"40003",
    "sg:province":"KY",
    "sg:tags":[
        "farm",
        "tobacco",
        "beef",
        "feedlot",
        "cattle"
    ],
    "wof:name":"Wrights Wramblin Ridge",
    "wof:placetype":"venue"
},
  "geometry": {"coordinates":[-85.060232,38.225717],"type":"Point"}
}