{
  "type": "Feature",
  "properties": {
    "addr:full":"107 W 2nd St Morehead KY 40351",
    "addr:housenumber":"107",
    "addr:postcode":"40351",
    "addr:street":"W 2Nd St",
    "iso:country":"US",
    "sg:address":"107 W 2nd St",
    "sg:city":"Morehead",
    "sg:classifiers":[
        {
            "category":"Organizations",
            "subcategory":"Religious Organization",
            "type":"Services"
        }
    ],
    "sg:phone":"+1 606 784 8001",
    "sg:postcode":"40351",
    "sg:province":"KY",
    "sg:tags":[
        "church"
    ],
    "wof:name":"Church Of Christ",
    "wof:placetype":"venue"
},
  "geometry": {"coordinates":[-83.436733,38.182151],"type":"Point"}
}