{
  "type": "Feature",
  "properties": {
    "addr:full":"1850 Louisville Rd Coxs Creek KY 40013",
    "addr:housenumber":"1850",
    "addr:postcode":"40013",
    "addr:street":"Louisville Rd",
    "iso:country":"US",
    "sg:address":"1850 Louisville Rd",
    "sg:city":"Coxs Creek",
    "sg:classifiers":[
        {
            "category":"Organizations",
            "subcategory":"Religious Organization",
            "type":"Services"
        }
    ],
    "sg:phone":"+1 502 538 4966",
    "sg:postcode":"40013",
    "sg:province":"KY",
    "sg:tags":[
        "church"
    ],
    "wof:name":"Riverview Baptist Church",
    "wof:placetype":"venue"
},
  "geometry": {"coordinates":[-85.485995,37.997404],"type":"Point"}
}