{
  "type": "Feature",
  "properties": {
    "addr:full":"220 Buttermilk Rd Hopkinsville KY 42240",
    "addr:housenumber":"220",
    "addr:postcode":"42240",
    "addr:street":"Buttermilk Rd",
    "iso:country":"US",
    "sg:address":"220 Buttermilk Rd",
    "sg:city":"Hopkinsville",
    "sg:classifiers":[
        {
            "category":"Communications",
            "subcategory":"Radio Station",
            "type":"Services"
        }
    ],
    "sg:phone":"+1 270 885 5331",
    "sg:postcode":"42240",
    "sg:province":"KY",
    "sg:tags":[
        "company",
        "broadcasting"
    ],
    "sg:website":"www.lite987whop.com",
    "wof:name":"WHOP",
    "wof:placetype":"venue"
},
  "geometry": {"coordinates":[-87.51127,36.880224],"type":"Point"}
}