{
  "type": "Feature",
  "properties": {
    "addr:full":"47 W Railroad St Stanton KY 40380",
    "addr:housenumber":"47",
    "addr:postcode":"40380",
    "addr:street":"W Railroad St",
    "iso:country":"US",
    "sg:address":"47 W Railroad St",
    "sg:city":"Stanton",
    "sg:classifiers":[
        {
            "category":"Personal",
            "subcategory":"Beauty Salon",
            "type":"Services"
        }
    ],
    "sg:phone":"+1 606 663 5383",
    "sg:postcode":"40380",
    "sg:province":"KY",
    "wof:name":"Ginger's Hair Design",
    "wof:placetype":"venue"
},
  "geometry": {"coordinates":[-83.85972599999999,37.848579],"type":"Point"}
}