{
  "type": "Feature",
  "properties": {
    "iso:country":"US",
    "sg:address":"3072 US Hwy 60",
    "sg:city":"Morganfield",
    "sg:classifiers":[
        {
            "category":"Wholesale",
            "subcategory":"Farm Supplies",
            "type":"Manufacturing & Wholesale Goods"
        }
    ],
    "sg:phone":"+1 270 389 2211",
    "sg:postcode":"42437",
    "sg:province":"KY",
    "sg:tags":[
        "fertilizer"
    ],
    "wof:name":"Meacham's Hybrids",
    "wof:placetype":"venue"
},
  "geometry": {"coordinates":[-87.947157,37.648128],"type":"Point"}
}