{
  "type": "Feature",
  "properties": {
    "addr:full":"960 Nandino Blvd Lexington KY 40511",
    "addr:housenumber":"960",
    "addr:postcode":"40511",
    "addr:street":"Nandino Blvd",
    "iso:country":"US",
    "sg:address":"960 Nandino Blvd",
    "sg:city":"Lexington",
    "sg:classifiers":[
        {
            "category":"Retail",
            "subcategory":"Car Wash",
            "type":"Services"
        }
    ],
    "sg:phone":"+1 859 255 7272",
    "sg:postcode":"40511",
    "sg:province":"KY",
    "sg:tags":[
        "truck",
        "cleaning"
    ],
    "wof:name":"Spit Shine",
    "wof:placetype":"venue"
},
  "geometry": {"coordinates":[-84.500907,38.077711],"type":"Point"}
}