{
  "type": "Feature",
  "properties": {
    "iso:country":"US",
    "sg:address":"507 W Main St",
    "sg:city":"Cumberland",
    "sg:classifiers":[
        {
            "category":"Retail",
            "subcategory":"Auto Repair",
            "type":"Services"
        }
    ],
    "sg:phone":"+1 606 589 4140",
    "sg:postcode":"40823",
    "sg:province":"KY",
    "sg:tags":[
        "repairing",
        "automobile"
    ],
    "wof:name":"Frank's Automotive",
    "wof:placetype":"venue"
},
  "geometry": {"coordinates":[-82.993731,36.974665],"type":"Point"}
}