{
  "type": "Feature",
  "properties": {
    "addr:full":"2589 Plato Vanhook Rd Somerset KY 42503",
    "addr:postcode":"2589;42503",
    "addr:street":"Vanhook Rd",
    "iso:country":"US",
    "sg:address":"2589 Plato Vanhook Rd",
    "sg:city":"Somerset",
    "sg:classifiers":[
        {
            "category":"Manufacturing",
            "subcategory":"Tools & Machinery",
            "type":"Manufacturing & Wholesale Goods"
        }
    ],
    "sg:phone":"+1 606 274 4455",
    "sg:postcode":"42503",
    "sg:province":"KY",
    "sg:tags":[
        "engine",
        "internal",
        "combustion",
        "mfg"
    ],
    "wof:name":"Bullock Racing & Performance",
    "wof:placetype":"venue"
},
  "geometry": {"coordinates":[-84.41492599999999,37.221815],"type":"Point"}
}