{
  "type": "Feature",
  "properties": {
    "iso:country":"US",
    "sg:address":"9141 US Hwy 60",
    "sg:city":"Henderson",
    "sg:classifiers":[
        {
            "category":"Shopping",
            "type":"Retail Goods"
        }
    ],
    "sg:phone":"+1 270 826 4134",
    "sg:postcode":"42458",
    "sg:province":"KY",
    "sg:tags":[
        "monument"
    ],
    "wof:name":"Henry & Henry Monuments",
    "wof:placetype":"venue"
},
  "geometry": {"coordinates":[-87.671824,37.79063],"type":"Point"}
}