{
  "type": "Feature",
  "properties": {
    "iso:country":"US",
    "sg:address":"201 N Main St",
    "sg:city":"Morgantown",
    "sg:classifiers":[
        {
            "category":"Banks & Credit Unions",
            "subcategory":"Financial Services",
            "type":"Services"
        }
    ],
    "sg:phone":"+1 270 526 3881",
    "sg:postcode":"42261",
    "sg:province":"KY",
    "sg:tags":[
        "company",
        "holding"
    ],
    "wof:name":"Melton & Wirth Inc",
    "wof:placetype":"venue"
},
  "geometry": {"coordinates":[-86.68221699999999,37.226889],"type":"Point"}
}