{
  "type": "Feature",
  "properties": {
    "iso:country":"US",
    "sg:address":"127 Riverside Dr",
    "sg:city":"Cynthiana",
    "sg:classifiers":[
        {
            "category":"Health Services",
            "subcategory":"Clinic",
            "type":"Services"
        }
    ],
    "sg:phone":"+1 859 234 2600",
    "sg:postcode":"41011",
    "sg:province":"KY",
    "sg:tags":[
        "home"
    ],
    "wof:name":"Harrison Physical Thrpy Assoc",
    "wof:placetype":"venue"
},
  "geometry": {"coordinates":[-84.508803,39.090783],"type":"Point"}
}