{
  "type": "Feature",
  "properties": {
    "iso:country":"US",
    "sg:address":"3170 Dixie Hwy",
    "sg:city":"Erlanger",
    "sg:classifiers":[
        {
            "category":"Shopping",
            "subcategory":"Clothing, Apparel, & Fashions",
            "type":"Retail Goods"
        },
        {
            "category":"Banks & Credit Unions",
            "subcategory":"Bank",
            "type":"Services"
        },
        {
            "category":"Shopping",
            "subcategory":"Used Merchandise",
            "type":"Retail Goods"
        }
    ],
    "sg:phone":"+1 859 344 1635",
    "sg:postcode":"41018",
    "sg:province":"KY",
    "sg:tags":[
        "shop",
        "resale",
        "second",
        "consignment",
        "hand"
    ],
    "sg:website":"http://www.shopsnooty.com",
    "wof:name":"Snooty Fox Furniture Den",
    "wof:placetype":"venue"
},
  "geometry": {"coordinates":[-84.59311,39.020031],"type":"Point"}
}