{
  "type": "Feature",
  "properties": {
    "addr:full":"5410 US Hwy 60 Vine Grove KY 40175",
    "addr:housenumber":"5410",
    "addr:postcode":"40175",
    "addr:street":"Us Hwy 60 Vine Grove",
    "iso:country":"US",
    "sg:address":"5410 US Hwy 60",
    "sg:city":"Vine Grove",
    "sg:classifiers":[
        {
            "category":"Wholesale",
            "subcategory":"Chemicals & Plastics",
            "type":"Manufacturing & Wholesale Goods"
        }
    ],
    "sg:phone":"+1 270 828 3875",
    "sg:postcode":"40175",
    "sg:province":"KY",
    "sg:tags":[
        "treating",
        "concrete",
        "curing"
    ],
    "wof:name":"Concrete By Wade",
    "wof:placetype":"venue"
},
  "geometry": {"coordinates":[-86.079413,37.883663],"type":"Point"}
}