{
  "type": "Feature",
  "properties": {
    "addr:full":"9965 Wild Cherry Dr Union KY 41091",
    "addr:housenumber":"9965",
    "addr:postcode":"41091",
    "addr:street":"Wild Cherry Dr",
    "iso:country":"US",
    "sg:address":"9965 Wild Cherry Dr",
    "sg:city":"Union",
    "sg:classifiers":[
        {
            "category":"Professional",
            "subcategory":"Art Services",
            "type":"Services"
        }
    ],
    "sg:phone":"+1 859 384 1983",
    "sg:postcode":"41091",
    "sg:province":"KY",
    "sg:tags":[
        "artist"
    ],
    "wof:name":"David Sheldon Productions Inc",
    "wof:placetype":"venue"
},
  "geometry": {"coordinates":[-84.64625599999999,38.941385],"type":"Point"}
}