{
  "type": "Feature",
  "properties": {
    "addr:full":"4425 Greenwood Ave Louisville KY 40211",
    "addr:housenumber":"4425",
    "addr:postcode":"40211",
    "addr:street":"Greenwood Ave",
    "iso:country":"US",
    "sg:address":"4425 Greenwood Ave",
    "sg:city":"Louisville",
    "sg:classifiers":[
        {
            "category":"Recreation",
            "type":"Entertainment"
        }
    ],
    "sg:phone":"+1 502 574 2821",
    "sg:postcode":"40211",
    "sg:province":"KY",
    "sg:tags":[
        "hall",
        "auditorium"
    ],
    "wof:name":"Flaget Community Ctr",
    "wof:placetype":"venue"
},
  "geometry": {"coordinates":[-85.826988,38.244768],"type":"Point"}
}