{
  "type": "Feature",
  "properties": {
    "iso:country":"US",
    "sg:address":"3233 Main St",
    "sg:city":"Stamping Ground",
    "sg:classifiers":[
        {
            "category":"Education",
            "subcategory":"School",
            "type":"Public Place"
        }
    ],
    "sg:phone":"+1 502 535 6611",
    "sg:postcode":"40379",
    "sg:province":"KY",
    "wof:name":"Scott County Family Resource",
    "wof:placetype":"venue"
},
  "geometry": {"coordinates":[-84.68212,38.268654],"type":"Point"}
}