{
  "type": "Feature",
  "properties": {
    "iso:country":"US",
    "sg:address":"815 Fairway Dr",
    "sg:city":"Brandenburg",
    "sg:classifiers":[
        {
            "category":"Health Services",
            "subcategory":"Doctor",
            "type":"Services"
        }
    ],
    "sg:phone":"+1 270 422 4111",
    "sg:postcode":"40108",
    "sg:province":"KY",
    "sg:tags":[
        "physician",
        "surgeon"
    ],
    "wof:name":"Brandenburg Family Medicine",
    "wof:placetype":"venue"
},
  "geometry": {"coordinates":[-86.188624,37.997569],"type":"Point"}
}