{
  "type": "Feature",
  "properties": {
    "iso:country":"US",
    "sg:address":"701 E Main St",
    "sg:city":"Georgetown",
    "sg:classifiers":[
        {
            "category":"Food & Beverages",
            "subcategory":"Groceries & Convenience Stores",
            "type":"Retail Goods"
        }
    ],
    "sg:phone":"+1 502 868 9488",
    "sg:postcode":"40324",
    "sg:province":"KY",
    "wof:name":"Traxx Main Street Shell",
    "wof:placetype":"venue"
},
  "geometry": {"coordinates":[-84.54952299999999,38.209379],"type":"Point"}
}