{
  "type": "Feature",
  "properties": {
    "addr:full":"300 Buttermilk Pike Fort Mitchell KY 41017",
    "addr:housenumber":"300",
    "addr:postcode":"41017",
    "addr:street":"Buttermilk Pike",
    "iso:country":"US",
    "sg:address":"300 Buttermilk Pike",
    "sg:city":"Fort Mitchell",
    "sg:classifiers":[
        {
            "category":"Banks & Credit Unions",
            "subcategory":"Bank",
            "type":"Services"
        }
    ],
    "sg:phone":"+1 859 578 0888",
    "sg:postcode":"41017",
    "sg:province":"KY",
    "sg:tags":[
        "loan",
        "real estate"
    ],
    "sg:website":"www.myloanline.com",
    "wof:name":"Anchor Mortgage Lending Inc",
    "wof:placetype":"venue"
},
  "geometry": {"coordinates":[-84.571376,39.043063],"type":"Point"}
}