{
  "type": "Feature",
  "properties": {
    "iso:country":"US",
    "sg:address":"173 Levias Rd",
    "sg:city":"Marion",
    "sg:classifiers":[
        {
            "category":"Organizations",
            "subcategory":"Religious Organization",
            "type":"Services"
        }
    ],
    "sg:phone":"+1 270 965 9823",
    "sg:postcode":"42064",
    "sg:province":"KY",
    "wof:name":"Union Baptist Church",
    "wof:placetype":"venue"
},
  "geometry": {"coordinates":[-88.18298,37.304374],"type":"Point"}
}