{
  "type": "Feature",
  "properties": {
    "iso:country":"US",
    "sg:address":"12434 US Hwy 60",
    "sg:city":"Olive Hill",
    "sg:classifiers":[
        {
            "category":"Building & Trades",
            "subcategory":"Construction",
            "type":"Services"
        }
    ],
    "sg:phone":"+1 606 286 4337",
    "sg:postcode":"41164",
    "sg:province":"KY",
    "sg:tags":[
        "paving",
        "contractor"
    ],
    "wof:name":"Mountain Enterprises Inc",
    "wof:placetype":"venue"
},
  "geometry": {"coordinates":[-83.130503,38.311692],"type":"Point"}
}