{
  "type": "Feature",
  "properties": {
    "addr:full":"420 Branch St Madisonville KY 42431",
    "addr:housenumber":"420",
    "addr:postcode":"42431",
    "addr:street":"Branch St",
    "iso:country":"US",
    "sg:address":"420 Branch St",
    "sg:city":"Madisonville",
    "sg:classifiers":[
        {
            "category":"Personal",
            "subcategory":"Barber",
            "type":"Services"
        }
    ],
    "sg:phone":"+1 270 825 1145",
    "sg:postcode":"42431",
    "sg:province":"KY",
    "sg:tags":[
        "shop"
    ],
    "wof:name":"Fresh Look Barber Shop",
    "wof:placetype":"venue"
},
  "geometry": {"coordinates":[-87.49146500000001,37.330364],"type":"Point"}
}