{
  "type": "Feature",
  "properties": {
    "iso:country":"US",
    "sg:address":"307 McLean Ave",
    "sg:city":"Hopkinsville",
    "sg:classifiers":[
        {
            "category":"Wholesale",
            "subcategory":"Machinery & Supplies",
            "type":"Manufacturing & Wholesale Goods"
        }
    ],
    "sg:phone":"+1 270 885 9999",
    "sg:postcode":"42240",
    "sg:province":"KY",
    "sg:tags":[
        "equipment",
        "welding"
    ],
    "wof:name":"Airgas Mid-America",
    "wof:placetype":"venue"
},
  "geometry": {"coordinates":[-87.474172,36.861248],"type":"Point"}
}