{
  "type": "Feature",
  "properties": {
    "iso:country":"US",
    "sg:address":"10500 Shadow Ridge Ln",
    "sg:city":"Louisville",
    "sg:classifiers":[
        {
            "category":"Professional",
            "type":"Services"
        }
    ],
    "sg:phone":"+1 502 327 9084",
    "sg:postcode":"40241",
    "sg:province":"KY",
    "wof:name":"Lewis Expedited Services Inc",
    "wof:placetype":"venue"
},
  "geometry": {"coordinates":[-85.556003,38.318199],"type":"Point"}
}