{
  "type": "Feature",
  "properties": {
    "iso:country":"US",
    "sg:address":"105 S Lyndon Ln",
    "sg:city":"Louisville",
    "sg:classifiers":[
        {
            "category":"Social Services",
            "type":"Services"
        }
    ],
    "sg:phone":"+1 502 423 0220",
    "sg:postcode":"40222",
    "sg:province":"KY",
    "sg:tags":[
        "counselor",
        "marriage",
        "family"
    ],
    "wof:name":"Anne Milligan",
    "wof:placetype":"venue"
},
  "geometry": {"coordinates":[-85.598955,38.246998],"type":"Point"}
}