{
  "type": "Feature",
  "properties": {
    "iso:country":"US",
    "sg:address":"1254 Dixie Hwy",
    "sg:city":"Louisville",
    "sg:classifiers":[
        {
            "category":"Organizations",
            "subcategory":"Religious Organization",
            "type":"Services"
        }
    ],
    "sg:phone":"+1 502 776 2822",
    "sg:postcode":"40210",
    "sg:province":"KY",
    "sg:tags":[
        "church"
    ],
    "wof:name":"Sweetleaf Primitive Baptist",
    "wof:placetype":"venue"
},
  "geometry": {"coordinates":[-85.78754000000001,38.235797],"type":"Point"}
}