{
  "type": "Feature",
  "properties": {
    "addr:full":"2450 Holt Rd Paducah KY 42001",
    "addr:housenumber":"2450",
    "addr:postcode":"42001",
    "addr:street":"Holt Rd",
    "iso:country":"US",
    "sg:address":"2450 Holt Rd",
    "sg:city":"Paducah",
    "sg:classifiers":[
        {
            "category":"Home & Garden",
            "subcategory":"Garden Supply",
            "type":"Retail Goods"
        }
    ],
    "sg:phone":"+1 270 554 5031",
    "sg:postcode":"42001",
    "sg:province":"KY",
    "sg:tags":[
        "nurseryman"
    ],
    "wof:name":"Bob Williams Nursery Holt Rd",
    "wof:placetype":"venue"
},
  "geometry": {"coordinates":[-88.692368,37.06608],"type":"Point"}
}