{
  "type": "Feature",
  "properties": {
    "addr:full":"8 Highland Ave Fort Thomas KY 41075",
    "addr:housenumber":"8",
    "addr:postcode":"41075",
    "addr:street":"Highland Ave",
    "iso:country":"US",
    "sg:address":"8 Highland Ave",
    "sg:city":"Fort Thomas",
    "sg:classifiers":[
        {
            "category":"Education",
            "subcategory":"Dance Studio",
            "type":"Public Place"
        }
    ],
    "sg:phone":"+1 859 441 4588",
    "sg:postcode":"41075",
    "sg:province":"KY",
    "sg:tags":[
        "art",
        "performing",
        "instruction",
        "dancing"
    ],
    "wof:name":"Pearman Dance",
    "wof:placetype":"venue"
},
  "geometry": {"coordinates":[-84.4487,39.078602],"type":"Point"}
}