{
  "type": "Feature",
  "properties": {
    "iso:country":"US",
    "sg:address":"316 N 7th St",
    "sg:city":"Mayfield",
    "sg:classifiers":[
        {
            "category":"Banks & Credit Unions",
            "subcategory":"Investment Brokerage",
            "type":"Services"
        }
    ],
    "sg:phone":"+1 270 247 4771",
    "sg:postcode":"42066",
    "sg:province":"KY",
    "sg:tags":[
        "security"
    ],
    "sg:website":"www.johncmuir.com",
    "wof:name":"John C Muir & Co",
    "wof:placetype":"venue"
},
  "geometry": {"coordinates":[-88.63568100000001,36.74517],"type":"Point"}
}