{
  "type": "Feature",
  "properties": {
    "iso:country":"US",
    "sg:address":"1535 Scotts Ferry Rd",
    "sg:city":"Versailles",
    "sg:classifiers":[
        {
            "category":"Retail",
            "subcategory":"Animal Services",
            "type":"Services"
        }
    ],
    "sg:phone":"+1 859 873 6400",
    "sg:postcode":"40383",
    "sg:province":"KY",
    "sg:tags":[
        "breeder",
        "horse"
    ],
    "wof:name":"Parkway Farm",
    "wof:placetype":"venue"
},
  "geometry": {"coordinates":[-84.78659399999999,38.008237],"type":"Point"}
}