{
  "type": "Feature",
  "properties": {
    "iso:country":"US",
    "sg:address":"300 Sherwood Dr",
    "sg:city":"Elizabethtown",
    "sg:classifiers":[
        {
            "category":"Freight",
            "type":"Transportation"
        }
    ],
    "sg:phone":"+1 270 234 8232",
    "sg:postcode":"42701",
    "sg:province":"KY",
    "sg:tags":[
        "operator",
        "local",
        "trucking"
    ],
    "wof:name":"McCray Trucking Co",
    "wof:placetype":"venue"
},
  "geometry": {"coordinates":[-85.75503,37.746459],"type":"Point"}
}