{
  "type": "Feature",
  "properties": {
    "iso:country":"US",
    "sg:address":"607 Oak Branch Rd",
    "sg:city":"Louisville",
    "sg:classifiers":[
        {
            "category":"Professional",
            "subcategory":"Business Services",
            "type":"Services"
        }
    ],
    "sg:phone":"+1 502 254 3161",
    "sg:postcode":"40245",
    "sg:province":"KY",
    "wof:name":"Steven Block",
    "wof:placetype":"venue"
},
  "geometry": {"coordinates":[-85.488692,38.250041],"type":"Point"}
}