{
  "type": "Feature",
  "properties": {
    "addr:full":"4113 Roxbury Rd Louisville KY 40218",
    "addr:housenumber":"4113",
    "addr:postcode":"40218",
    "addr:street":"Roxbury Rd",
    "iso:country":"US",
    "sg:address":"4113 Roxbury Rd",
    "sg:city":"Louisville",
    "sg:classifiers":[
        {
            "category":"Professional",
            "subcategory":"Management & Consulting",
            "type":"Services"
        }
    ],
    "sg:phone":"+1 502 491 7810",
    "sg:postcode":"40218",
    "sg:province":"KY",
    "sg:tags":[
        "door",
        "cosmetic",
        "perfume"
    ],
    "wof:name":"Ronna J Dalton",
    "wof:placetype":"venue"
},
  "geometry": {"coordinates":[-85.639432,38.198667],"type":"Point"}
}