{
  "type": "Feature",
  "properties": {
    "addr:full":"8111 Shelbyville Rd Louisville KY 40222",
    "addr:housenumber":"8111",
    "addr:postcode":"40222",
    "addr:street":"Shelbyville Rd",
    "iso:country":"US",
    "sg:address":"8111 Shelbyville Rd",
    "sg:city":"Louisville",
    "sg:classifiers":[
        {
            "category":"Real Estate",
            "subcategory":"Real Estate Agent",
            "type":"Services"
        }
    ],
    "sg:phone":"+1 502 426 2726",
    "sg:postcode":"40222",
    "sg:province":"KY",
    "sg:tags":[
        "management"
    ],
    "wof:name":"Farmer Automotive Group",
    "wof:placetype":"venue"
},
  "geometry": {"coordinates":[-85.60304600000001,38.248481],"type":"Point"}
}