{
  "type": "Feature",
  "properties": {
    "iso:country":"US",
    "sg:address":"9332 Shelbyville Rd",
    "sg:city":"Simpsonville",
    "sg:classifiers":[
        {
            "category":"Home & Garden",
            "subcategory":"Garden Supply",
            "type":"Retail Goods"
        }
    ],
    "sg:phone":"+1 502 722 9900",
    "sg:postcode":"40067",
    "sg:province":"KY",
    "sg:tags":[
        "nurseryman"
    ],
    "wof:name":"Marty's Garden",
    "wof:placetype":"venue"
},
  "geometry": {"coordinates":[-85.38278200000001,38.225147],"type":"Point"}
}