{
  "type": "Feature",
  "properties": {
    "iso:country":"US",
    "sg:address":"10300 Bluegrass Pkwy",
    "sg:city":"Louisville",
    "sg:classifiers":[
        {
            "category":"Home & Garden",
            "subcategory":"Furniture",
            "type":"Retail Goods"
        }
    ],
    "sg:phone":"+1 502 671 7006",
    "sg:postcode":"40299",
    "sg:province":"KY",
    "wof:name":"Great American Furniture",
    "wof:placetype":"venue"
},
  "geometry": {"coordinates":[-85.562066,38.222423],"type":"Point"}
}