{
  "type": "Feature",
  "properties": {
    "addr:full":"230 Smith Creek Rd Tompkinsville KY 42167",
    "addr:housenumber":"230",
    "addr:postcode":"42167",
    "addr:street":"Smith Creek Rd",
    "iso:country":"US",
    "sg:address":"230 Smith Creek Rd",
    "sg:city":"Tompkinsville",
    "sg:classifiers":[
        {
            "category":"Recreation",
            "type":"Entertainment"
        }
    ],
    "sg:phone":"+1 270 487 1020",
    "sg:postcode":"42167",
    "sg:province":"KY",
    "sg:tags":[
        "pond",
        "fishing",
        "lake"
    ],
    "wof:name":"Fishermans Paradise",
    "wof:placetype":"venue"
},
  "geometry": {"coordinates":[-85.45818199999999,36.625974],"type":"Point"}
}