{
  "type": "Feature",
  "properties": {
    "addr:full":"266 Pond Creek Rd Huddy KY 41535",
    "addr:housenumber":"266",
    "addr:postcode":"41535",
    "addr:street":"Pond Creek Rd",
    "iso:country":"US",
    "sg:address":"266 Pond Creek Rd",
    "sg:city":"Huddy",
    "sg:classifiers":[
        {
            "category":"Retail",
            "subcategory":"Laundry & Dry Cleaning",
            "type":"Services"
        },
        {
            "category":"Shopping",
            "subcategory":"Clothing, Apparel, & Fashions",
            "type":"Retail Goods"
        }
    ],
    "sg:phone":"+1 606 353 9468",
    "sg:postcode":"41535",
    "sg:province":"KY",
    "sg:tags":[
        "alteration"
    ],
    "wof:name":"Debbie's Alterations & Sewing",
    "wof:placetype":"venue"
},
  "geometry": {"coordinates":[-82.27435,37.595654],"type":"Point"}
}