{
  "type": "Feature",
  "properties": {
    "addr:full":"9310 Holiday Dr Louisville KY 40272",
    "addr:housenumber":"9310",
    "addr:postcode":"40272",
    "addr:street":"Holiday Dr",
    "iso:country":"US",
    "sg:address":"9310 Holiday Dr",
    "sg:city":"Louisville",
    "sg:classifiers":[
        {
            "category":"Building & Trades",
            "subcategory":"Plumbing",
            "type":"Services"
        }
    ],
    "sg:phone":"+1 502 935 8151",
    "sg:postcode":"40272",
    "sg:province":"KY",
    "sg:tags":[
        "conditioning",
        "air",
        "system",
        "contractor"
    ],
    "wof:name":"Wheeler Heating & Air Cond",
    "wof:placetype":"venue"
},
  "geometry": {"coordinates":[-85.825766,38.118418],"type":"Point"}
}