{
  "type": "Feature",
  "properties": {
    "iso:country":"US",
    "sg:address":"400 Powell Ln",
    "sg:city":"Flatwoods",
    "sg:classifiers":[
        {
            "category":"Personal",
            "subcategory":"Beauty Salon",
            "type":"Services"
        }
    ],
    "sg:phone":"+1 606 834 8515",
    "sg:postcode":"41139",
    "sg:province":"KY",
    "wof:name":"Classic Cuts By Chris",
    "wof:placetype":"venue"
},
  "geometry": {"coordinates":[-82.70465799999999,38.516234],"type":"Point"}
}