{
  "type": "Feature",
  "properties": {
    "iso:country":"US",
    "sg:address":"200 Carpenter Pike",
    "sg:city":"Versailles",
    "sg:classifiers":[
        {
            "category":"Retail",
            "subcategory":"Animal Services",
            "type":"Services"
        }
    ],
    "sg:phone":"+1 859 873 4204",
    "sg:postcode":"40383",
    "sg:province":"KY",
    "sg:tags":[
        "breeder",
        "horse"
    ],
    "wof:name":"Little River Farm",
    "wof:placetype":"venue"
},
  "geometry": {"coordinates":[-84.73182,37.991156],"type":"Point"}
}