{
  "type": "Feature",
  "properties": {
    "iso:country":"US",
    "sg:address":"2404 Holt St",
    "sg:city":"Ashland",
    "sg:classifiers":[
        {
            "category":"Wholesale",
            "subcategory":"Chemicals & Plastics",
            "type":"Manufacturing & Wholesale Goods"
        }
    ],
    "sg:phone":"+1 606 325 1582",
    "sg:postcode":"41101",
    "sg:province":"KY",
    "wof:name":"Benetech Inc",
    "wof:placetype":"venue"
},
  "geometry": {"coordinates":[-82.64407799999999,38.463505],"type":"Point"}
}