{
  "type": "Feature",
  "properties": {
    "iso:country":"US",
    "sg:address":"103 Hayden Dr",
    "sg:city":"Lawrenceburg",
    "sg:classifiers":[
        {
            "category":"Shopping",
            "subcategory":"Clothing, Apparel, & Fashions",
            "type":"Retail Goods"
        }
    ],
    "sg:phone":"+1 859 879 2169",
    "sg:postcode":"40342",
    "sg:province":"KY",
    "wof:name":"Rags To The Max Clothing Store",
    "wof:placetype":"venue"
},
  "geometry": {"coordinates":[-84.880762,38.036367],"type":"Point"}
}