{
  "type": "Feature",
  "properties": {
    "iso:country":"US",
    "sg:address":"1471 Stinnett Rd",
    "sg:city":"Maceo",
    "sg:classifiers":[
        {
            "category":"Building & Trades",
            "subcategory":"Construction",
            "type":"Services"
        }
    ],
    "sg:phone":"+1 270 264 1103",
    "sg:postcode":"42355",
    "sg:province":"KY",
    "sg:tags":[
        "carpentry",
        "contractor"
    ],
    "wof:name":"Robert Heade",
    "wof:placetype":"venue"
},
  "geometry": {"coordinates":[-86.952985,37.851065],"type":"Point"}
}