{
  "type": "Feature",
  "properties": {
    "iso:country":"US",
    "sg:address":"411 E Muhammad Ali Blvd",
    "sg:city":"Louisville",
    "sg:classifiers":[
        {
            "category":"Social Services",
            "type":"Services"
        }
    ],
    "sg:phone":"+1 502 583 8012",
    "sg:postcode":"40202",
    "sg:province":"KY",
    "sg:tags":[
        "senior",
        "citizen"
    ],
    "sg:website":"www.elderserveinc.org",
    "wof:name":"Elderserve Inc",
    "wof:placetype":"venue"
},
  "geometry": {"coordinates":[-85.745842,38.24987],"type":"Point"}
}