{
  "type": "Feature",
  "properties": {
    "iso:country":"US",
    "sg:address":"626 Kentucky Ave",
    "sg:city":"Paducah",
    "sg:classifiers":[
        {
            "category":"Professional",
            "subcategory":"Accounting & Tax Preparation",
            "type":"Services"
        }
    ],
    "sg:phone":"+1 270 444 0558",
    "sg:postcode":"42003",
    "sg:province":"KY",
    "sg:tags":[
        "accountant"
    ],
    "wof:name":"Moffitt & Co",
    "wof:placetype":"venue"
},
  "geometry": {"coordinates":[-88.600183,37.084493],"type":"Point"}
}