{
  "type": "Feature",
  "properties": {
    "addr:full":"301 E Muhammad Ali Blvd Louisville KY 40202",
    "addr:housenumber":"301",
    "addr:postcode":"40202",
    "addr:street":"E Muhammad Ali Blvd",
    "iso:country":"US",
    "sg:address":"301 E Muhammad Ali Blvd",
    "sg:city":"Louisville",
    "sg:classifiers":[
        {
            "category":"Shopping",
            "type":"Retail Goods"
        },
        {
            "category":"Organizations",
            "subcategory":"Non-profit Organization",
            "type":"Services"
        }
    ],
    "sg:phone":"+1 502 583 0564",
    "sg:postcode":"40202",
    "sg:province":"KY",
    "sg:tags":[
        "fund",
        "games",
        "raising",
        "merchandise",
        "supply"
    ],
    "wof:name":"Kentucky Lions Eye Foundation Inc",
    "wof:placetype":"venue"
},
  "geometry": {"coordinates":[-85.74884,38.250198],"type":"Point"}
}