{
  "type": "Feature",
  "properties": {
    "iso:country":"US",
    "sg:address":"212 E Mount Vernon St",
    "sg:city":"Somerset",
    "sg:classifiers":[
        {
            "category":"Personal",
            "subcategory":"Beauty Salon",
            "type":"Services"
        }
    ],
    "sg:phone":"+1 606 679 3397",
    "sg:postcode":"42501",
    "sg:province":"KY",
    "sg:tags":[
        "school"
    ],
    "wof:name":"Somerset Beauty College Inc",
    "wof:placetype":"venue"
},
  "geometry": {"coordinates":[-84.602604,37.092668],"type":"Point"}
}