{
  "type": "Feature",
  "properties": {
    "iso:country":"US",
    "sg:address":"99 Little Creek Rd",
    "sg:city":"Somerset",
    "sg:classifiers":[
        {
            "category":"Health Services",
            "subcategory":"Doctor",
            "type":"Services"
        }
    ],
    "sg:phone":"+1 606 679 3698",
    "sg:postcode":"42503",
    "sg:province":"KY",
    "sg:tags":[
        "physician",
        "surgeon"
    ],
    "wof:name":"James D Crase MD",
    "wof:placetype":"venue"
},
  "geometry": {"coordinates":[-84.605512,37.128258],"type":"Point"}
}