{
  "type": "Feature",
  "properties": {
    "iso:country":"US",
    "sg:address":"500 Winchester Ave",
    "sg:city":"Ashland",
    "sg:classifiers":[
        {
            "category":"Professional",
            "type":"Services"
        }
    ],
    "sg:phone":"+1 606 324 3591",
    "sg:postcode":"41101",
    "sg:province":"KY",
    "sg:tags":[
        "establishment"
    ],
    "wof:name":"Madsen Karter Construction",
    "wof:placetype":"venue"
},
  "geometry": {"coordinates":[-82.651725,38.484733],"type":"Point"}
}