{
  "type": "Feature",
  "properties": {
    "iso:country":"US",
    "sg:address":"5394 Belleview Rd",
    "sg:city":"Petersburg",
    "sg:classifiers":[
        {
            "category":"Home & Garden",
            "subcategory":"Household Appliances",
            "type":"Retail Goods"
        }
    ],
    "sg:phone":"+1 859 586 7164",
    "sg:postcode":"41080",
    "sg:province":"KY",
    "sg:tags":[
        "refrigerator",
        "freezer"
    ],
    "wof:name":"All About Appliance Svc",
    "wof:placetype":"venue"
},
  "geometry": {"coordinates":[-84.833794,39.010336],"type":"Point"}
}