{
  "type": "Feature",
  "properties": {
    "iso:country":"US",
    "sg:address":"1500 Kenton St",
    "sg:city":"Bowling Green",
    "sg:classifiers":[
        {
            "category":"Mining & Drilling",
            "type":"Manufacturing & Wholesale Goods"
        }
    ],
    "sg:phone":"+1 270 846 9946",
    "sg:postcode":"42101",
    "sg:province":"KY",
    "sg:tags":[
        "oil",
        "gas",
        "producer"
    ],
    "sg:website":"www.bgoil.com",
    "wof:name":"B G Independent Oil",
    "wof:placetype":"venue"
},
  "geometry": {"coordinates":[-86.44548899999999,36.982163],"type":"Point"}
}