{
  "type": "Feature",
  "properties": {
    "addr:full":"1320 Madison Ave Covington KY 41011",
    "addr:housenumber":"1320",
    "addr:postcode":"41011",
    "addr:street":"Madison Ave",
    "iso:country":"US",
    "sg:address":"1320 Madison Ave",
    "sg:city":"Covington",
    "sg:classifiers":[
        {
            "category":"Utilities",
            "subcategory":"Mobile Phone",
            "type":"Services"
        }
    ],
    "sg:phone":"+1 859 491 2100",
    "sg:postcode":"41011",
    "sg:province":"KY",
    "sg:tags":[
        "telephone",
        "cellular"
    ],
    "wof:name":"Wireless Connection",
    "wof:placetype":"venue"
},
  "geometry": {"coordinates":[-84.507789,39.074852],"type":"Point"}
}