{
  "type": "Feature",
  "properties": {
    "iso:country":"US",
    "sg:address":"1001 Center St",
    "sg:city":"Bowling Green",
    "sg:classifiers":[
        {
            "category":"Government",
            "subcategory":"Office",
            "type":"Public Place"
        }
    ],
    "sg:phone":"+1 270 746 7417",
    "sg:postcode":"42101",
    "sg:province":"KY",
    "sg:tags":[
        "state",
        "program"
    ],
    "wof:name":"Driver's License Examining",
    "wof:placetype":"venue"
},
  "geometry": {"coordinates":[-86.443906,36.994046],"type":"Point"}
}