{
  "type": "Feature",
  "properties": {
    "iso:country":"US",
    "sg:address":"90 Ballpark Rd",
    "sg:city":"Harlan",
    "sg:classifiers":[
        {
            "category":"Health Services",
            "subcategory":"Doctor",
            "type":"Services"
        }
    ],
    "sg:phone":"+1 606 573 7121",
    "sg:postcode":"40831",
    "sg:province":"KY",
    "sg:tags":[
        "physician",
        "surgeon"
    ],
    "wof:name":"Alan Freid MD",
    "wof:placetype":"venue"
},
  "geometry": {"coordinates":[-83.31356599999999,36.810236],"type":"Point"}
}