{
  "type": "Feature",
  "properties": {
    "addr:full":"1455 Dixie Hwy N Radcliff KY 40160",
    "addr:housenumber":"1455",
    "addr:postcode":"40160",
    "addr:street":"Dixie Hwy N",
    "iso:country":"US",
    "sg:address":"1455 Dixie Hwy N",
    "sg:city":"Radcliff",
    "sg:classifiers":[
        {
            "category":"Autos & Motor Vehicles",
            "subcategory":"Automobile Sales",
            "type":"Retail Goods"
        }
    ],
    "sg:phone":"+1 270 877 2321",
    "sg:postcode":"40160",
    "sg:province":"KY",
    "wof:name":"Cost U Less Auto Sales",
    "wof:placetype":"venue"
},
  "geometry": {"coordinates":[-85.95240099999999,37.855031],"type":"Point"}
}