{
  "type": "Feature",
  "properties": {
    "iso:country":"US",
    "sg:address":"816 High Bridge Rd",
    "sg:city":"Wilmore",
    "sg:classifiers":[
        {
            "category":"Building & Trades",
            "subcategory":"Construction",
            "type":"Services"
        }
    ],
    "sg:phone":"+1 859 858 8937",
    "sg:postcode":"40390",
    "sg:province":"KY",
    "sg:tags":[
        "house"
    ],
    "wof:name":"Denger Home Exteriors",
    "wof:placetype":"venue"
},
  "geometry": {"coordinates":[-84.67075800000001,37.851334],"type":"Point"}
}