{
  "type": "Feature",
  "properties": {
    "iso:country":"US",
    "sg:address":"2813 Patti Ln",
    "sg:city":"Louisville",
    "sg:classifiers":[
        {
            "category":"Autos & Motor Vehicles",
            "subcategory":"Automobile Sales",
            "type":"Retail Goods"
        }
    ],
    "sg:phone":"+1 502 491 7944",
    "sg:postcode":"40299",
    "sg:province":"KY",
    "sg:tags":[
        "car",
        "dealer"
    ],
    "wof:name":"Auto Latinos",
    "wof:placetype":"venue"
},
  "geometry": {"coordinates":[-85.580725,38.20423],"type":"Point"}
}