{
  "type": "Feature",
  "properties": {
    "iso:country":"US",
    "sg:address":"213 E Main St",
    "sg:city":"Morganfield",
    "sg:classifiers":[
        {
            "category":"Real Estate",
            "subcategory":"Real Estate Services",
            "type":"Services"
        },
        {
            "category":"Real Estate",
            "subcategory":"Real Estate Agent",
            "type":"Services"
        }
    ],
    "sg:phone":"+1 270 389 0370",
    "sg:postcode":"42437",
    "sg:province":"KY",
    "sg:tags":[
        "management",
        "auctioneer"
    ],
    "wof:name":"Red Hat Realty & Auction",
    "wof:placetype":"venue"
},
  "geometry": {"coordinates":[-87.915513,37.68308],"type":"Point"}
}