{
  "type": "Feature",
  "properties": {
    "iso:country":"US",
    "sg:address":"5523 New Cut Rd",
    "sg:city":"Louisville",
    "sg:classifiers":[
        {
            "category":"Banks & Credit Unions",
            "subcategory":"Bank",
            "type":"Services"
        }
    ],
    "sg:phone":"+1 502 581 7734",
    "sg:postcode":"40214",
    "sg:province":"KY",
    "wof:name":"National City Bank",
    "wof:placetype":"venue"
},
  "geometry": {"coordinates":[-85.774609,38.143388],"type":"Point"}
}