{
  "type": "Feature",
  "properties": {
    "iso:country":"US",
    "sg:address":"1324 Madison Ave",
    "sg:city":"Covington",
    "sg:classifiers":[
        {
            "category":"Real Estate",
            "subcategory":"Real Estate Agent",
            "type":"Services"
        }
    ],
    "sg:phone":"+1 859 431 5310",
    "sg:postcode":"41011",
    "sg:province":"KY",
    "wof:name":"Rebelawn Realty Co",
    "wof:placetype":"venue"
},
  "geometry": {"coordinates":[-84.50779300000001,39.074871],"type":"Point"}
}