{
  "type": "Feature",
  "properties": {
    "addr:full":"300 High Rise Dr Louisville KY 40213",
    "addr:housenumber":"300",
    "addr:postcode":"40213",
    "addr:street":"High Rise Dr",
    "iso:country":"US",
    "sg:address":"300 High Rise Dr",
    "sg:city":"Louisville",
    "sg:classifiers":[
        {
            "category":"Professional",
            "subcategory":"Business Services",
            "type":"Services"
        }
    ],
    "sg:phone":"+1 502 968 9395",
    "sg:postcode":"40213",
    "sg:province":"KY",
    "sg:tags":[
        "inventory"
    ],
    "sg:website":"www.rgis.com",
    "wof:name":"RGIS Inventory Specialist",
    "wof:placetype":"venue"
},
  "geometry": {"coordinates":[-85.715131,38.158935],"type":"Point"}
}