{
  "type": "Feature",
  "properties": {
    "iso:country":"US",
    "sg:address":"3542 Lovelaceville Rd",
    "sg:city":"Paducah",
    "sg:classifiers":[
        {
            "category":"Freight",
            "type":"Transportation"
        }
    ],
    "sg:phone":"+1 270 554 0114",
    "sg:postcode":"42001",
    "sg:province":"KY",
    "sg:tags":[
        "commercial",
        "storage"
    ],
    "wof:name":"Lone Oak Self Storage",
    "wof:placetype":"venue"
},
  "geometry": {"coordinates":[-88.673528,37.03174],"type":"Point"}
}