{
  "type": "Feature",
  "properties": {
    "iso:country":"US",
    "sg:address":"2929 Campbellsville Rd",
    "sg:city":"Greensburg",
    "sg:classifiers":[
        {
            "category":"Wholesale",
            "subcategory":"Furniture",
            "type":"Manufacturing & Wholesale Goods"
        }
    ],
    "sg:phone":"+1 270 932 4605",
    "sg:postcode":"42743",
    "sg:province":"KY",
    "sg:tags":[
        "buyer"
    ],
    "wof:name":"Central Furniture Co",
    "wof:placetype":"venue"
},
  "geometry": {"coordinates":[-85.46764899999999,37.293968],"type":"Point"}
}