{
  "type": "Feature",
  "properties": {
    "addr:full":"1440 Mobley Mill Rd Coxs Creek KY 40013",
    "addr:housenumber":"1440",
    "addr:postcode":"40013",
    "addr:street":"Mobley Mill Rd",
    "iso:country":"US",
    "sg:address":"1440 Mobley Mill Rd",
    "sg:city":"Coxs Creek",
    "sg:classifiers":[
        {
            "category":"Retail",
            "subcategory":"Animal Services",
            "type":"Services"
        }
    ],
    "sg:phone":"+1 502 348 1219",
    "sg:postcode":"40013",
    "sg:province":"KY",
    "sg:tags":[
        "merchandise"
    ],
    "wof:name":"Kountry Kennel & Pet Supply",
    "wof:placetype":"venue"
},
  "geometry": {"coordinates":[-85.505663,37.906896],"type":"Point"}
}