{
  "type": "Feature",
  "properties": {
    "addr:full":"11530 Alexandria Pike Alexandria KY 41001",
    "addr:housenumber":"11530",
    "addr:postcode":"41001",
    "addr:street":"Alexandria Pike",
    "iso:country":"US",
    "sg:address":"11530 Alexandria Pike",
    "sg:city":"Alexandria",
    "sg:classifiers":[
        {
            "category":"Personal",
            "subcategory":"Beauty Salon",
            "type":"Services"
        }
    ],
    "sg:phone":"+1 859 448 0180",
    "sg:postcode":"41001",
    "sg:province":"KY",
    "sg:tags":[
        "shop"
    ],
    "wof:name":"Special Cuts",
    "wof:placetype":"venue"
},
  "geometry": {"coordinates":[-84.38800000000001,38.884045],"type":"Point"}
}