{
  "type": "Feature",
  "properties": {
    "iso:country":"US",
    "sg:address":"5600 S 3rd St",
    "sg:city":"Louisville",
    "sg:classifiers":[
        {
            "category":"Restaurant",
            "type":"Food & Drink"
        }
    ],
    "sg:phone":"+1 502 363 2211",
    "sg:postcode":"40214",
    "sg:province":"KY",
    "wof:name":"Mr Gatti's Pizza",
    "wof:placetype":"venue"
},
  "geometry": {"coordinates":[-85.76855399999999,38.16833],"type":"Point"}
}