{
  "type": "Feature",
  "properties": {
    "addr:full":"5171 N Mayo Trl Pikeville KY 41501",
    "addr:housenumber":"5171",
    "addr:postcode":"41501",
    "addr:street":"N Mayo Trl",
    "iso:country":"US",
    "sg:address":"5171 N Mayo Trl",
    "sg:city":"Pikeville",
    "sg:classifiers":[
        {
            "category":"Shopping",
            "subcategory":"Florist",
            "type":"Retail Goods"
        }
    ],
    "sg:phone":"+1 606 432 9177",
    "sg:postcode":"41501",
    "sg:province":"KY",
    "wof:name":"Flowers By Angie",
    "wof:placetype":"venue"
},
  "geometry": {"coordinates":[-82.579725,37.536264],"type":"Point"}
}