{
  "type": "Feature",
  "properties": {
    "iso:country":"US",
    "sg:address":"2700 US Hwy 27",
    "sg:city":"Somerset",
    "sg:classifiers":[
        {
            "category":"Shopping",
            "subcategory":"Computers & Home Electronics",
            "type":"Retail Goods"
        }
    ],
    "sg:phone":"+1 606 679 7251",
    "sg:postcode":"42503",
    "sg:province":"KY",
    "sg:tags":[
        "equipment",
        "electronic",
        "supply"
    ],
    "wof:name":"Hall Electric",
    "wof:placetype":"venue"
},
  "geometry": {"coordinates":[-84.623114,37.111948],"type":"Point"}
}