{
  "type": "Feature",
  "properties": {
    "addr:full":"2212 Long St Flatwoods KY 41139",
    "addr:housenumber":"2212",
    "addr:postcode":"41139",
    "addr:street":"Long St",
    "iso:country":"US",
    "sg:address":"2212 Long St",
    "sg:city":"Flatwoods",
    "sg:classifiers":[
        {
            "category":"Real Estate",
            "subcategory":"Developer",
            "type":"Services"
        }
    ],
    "sg:phone":"+1 606 836 3943",
    "sg:postcode":"41139",
    "sg:province":"KY",
    "sg:tags":[
        "mobile",
        "home"
    ],
    "wof:name":"Lowe's Mobile Home Park",
    "wof:placetype":"venue"
},
  "geometry": {"coordinates":[-82.71139700000001,38.518742],"type":"Point"}
}