{
  "type": "Feature",
  "properties": {
    "addr:full":"3126 Dixie Hwy Erlanger KY 41018",
    "addr:housenumber":"3126",
    "addr:postcode":"41018",
    "addr:street":"Dixie Hwy",
    "iso:country":"US",
    "sg:address":"3126 Dixie Hwy",
    "sg:city":"Erlanger",
    "sg:classifiers":[
        {
            "category":"Professional",
            "type":"Services"
        }
    ],
    "sg:phone":"+1 859 331 2808",
    "sg:postcode":"41018",
    "sg:province":"KY",
    "sg:tags":[
        "establishment"
    ],
    "wof:name":"F Si Firestop Inc",
    "wof:placetype":"venue"
},
  "geometry": {"coordinates":[-84.591347,39.020488],"type":"Point"}
}