{
  "type": "Feature",
  "properties": {
    "iso:country":"US",
    "sg:address":"1707 2nd St",
    "sg:city":"Henderson",
    "sg:classifiers":[
        {
            "category":"Education",
            "subcategory":"School",
            "type":"Public Place"
        }
    ],
    "sg:phone":"+1 270 831 5060",
    "sg:postcode":"42420",
    "sg:province":"KY",
    "wof:name":"North Junior High School",
    "wof:placetype":"venue"
},
  "geometry": {"coordinates":[-87.57002,37.831747],"type":"Point"}
}