{
  "type": "Feature",
  "properties": {
    "iso:country":"US",
    "sg:address":"207 W 11th St",
    "sg:city":"Benton",
    "sg:classifiers":[
        {
            "category":"Food & Beverages",
            "subcategory":"Bakery",
            "type":"Retail Goods"
        }
    ],
    "sg:phone":"+1 270 527 2847",
    "sg:postcode":"42025",
    "sg:province":"KY",
    "wof:name":"A Piece of Cake",
    "wof:placetype":"venue"
},
  "geometry": {"coordinates":[-88.35210499999999,36.857797],"type":"Point"}
}