{
  "type": "Feature",
  "properties": {
    "iso:country":"US",
    "sg:address":"424 E Main St",
    "sg:city":"Hazard",
    "sg:classifiers":[
        {
            "category":"Insurance",
            "subcategory":"Insurance Agent",
            "type":"Services"
        }
    ],
    "sg:phone":"+1 606 439 0092",
    "sg:postcode":"41701",
    "sg:province":"KY",
    "sg:website":"www.agla.com",
    "wof:name":"American General Life Ins Co",
    "wof:placetype":"venue"
},
  "geometry": {"coordinates":[-83.186339,37.246324],"type":"Point"}
}