{
  "type": "Feature",
  "properties": {
    "iso:country":"US",
    "sg:address":"3115 N Main St",
    "sg:city":"Hazard",
    "sg:classifiers":[
        {
            "category":"Health Services",
            "subcategory":"Clinic",
            "type":"Services"
        }
    ],
    "sg:phone":"+1 606 439 0262",
    "sg:postcode":"41701",
    "sg:province":"KY",
    "sg:tags":[
        "home"
    ],
    "wof:name":"Extra Care Private Duty Nurse",
    "wof:placetype":"venue"
},
  "geometry": {"coordinates":[-83.194029,37.277382],"type":"Point"}
}