{
  "type": "Feature",
  "properties": {
    "iso:country":"US",
    "sg:address":"22728 US Hwy 421",
    "sg:city":"Hyden",
    "sg:classifiers":[
        {
            "category":"Building & Trades",
            "subcategory":"Construction",
            "type":"Services"
        }
    ],
    "sg:phone":"+1 606 672 5437",
    "sg:postcode":"41749",
    "sg:province":"KY",
    "sg:tags":[
        "handyman"
    ],
    "wof:name":"Helping Hands Helping Others",
    "wof:placetype":"venue"
},
  "geometry": {"coordinates":[-83.39006500000001,37.152207],"type":"Point"}
}