{
  "type": "Feature",
  "properties": {
    "addr:full":"883 Heaton Ford Rd Science Hill KY 42553",
    "addr:housenumber":"883",
    "addr:postcode":"42553",
    "addr:street":"Heaton Ford Rd",
    "iso:country":"US",
    "sg:address":"883 Heaton Ford Rd",
    "sg:city":"Science Hill",
    "sg:classifiers":[
        {
            "category":"Manufacturing",
            "subcategory":"Signs",
            "type":"Manufacturing & Wholesale Goods"
        }
    ],
    "sg:phone":"+1 606 423 5267",
    "sg:postcode":"42553",
    "sg:province":"KY",
    "sg:tags":[
        "advertising",
        "specialty"
    ],
    "wof:name":"Middleton Signs & Screen Prnt",
    "wof:placetype":"venue"
},
  "geometry": {"coordinates":[-84.617335,37.182557],"type":"Point"}
}