{
  "type": "Feature",
  "properties": {
    "iso:country":"US",
    "sg:address":"3179 Irvine Rd",
    "sg:city":"Richmond",
    "sg:classifiers":[
        {
            "category":"Organizations",
            "subcategory":"Professional Association",
            "type":"Services"
        }
    ],
    "sg:phone":"+1 859 369 7923",
    "sg:postcode":"40475",
    "sg:province":"KY",
    "wof:name":"Jackpot Charity Bingo",
    "wof:placetype":"venue"
},
  "geometry": {"coordinates":[-84.15160899999999,37.741937],"type":"Point"}
}