{
  "type": "Feature",
  "properties": {
    "iso:country":"US",
    "sg:address":"801 York St",
    "sg:city":"Newport",
    "sg:classifiers":[
        {
            "category":"Organizations",
            "subcategory":"Religious Organization",
            "type":"Services"
        }
    ],
    "sg:phone":"+1 859 261 3328",
    "sg:postcode":"41071",
    "sg:province":"KY",
    "sg:tags":[
        "church"
    ],
    "wof:name":"First Baptist Church-Newport",
    "wof:placetype":"venue"
},
  "geometry": {"coordinates":[-84.49221799999999,39.087872],"type":"Point"}
}