{
  "type": "Feature",
  "properties": {
    "iso:country":"US",
    "sg:address":"2408 Plantside Dr",
    "sg:city":"Louisville",
    "sg:classifiers":[
        {
            "category":"Building & Trades",
            "subcategory":"Equipment Rental",
            "type":"Services"
        }
    ],
    "sg:phone":"+1 502 491 2277",
    "sg:postcode":"40299",
    "sg:province":"KY",
    "sg:tags":[
        "contractor"
    ],
    "wof:name":"United Rentals Heavy Machinery",
    "wof:placetype":"venue"
},
  "geometry": {"coordinates":[-85.564443,38.20966],"type":"Point"}
}