{
  "type": "Feature",
  "properties": {
    "iso:country":"US",
    "sg:address":"321 E Broadway St",
    "sg:city":"Campbellsville",
    "sg:classifiers":[
        {
            "category":"Building & Trades",
            "subcategory":"Construction",
            "type":"Services"
        }
    ],
    "sg:phone":"+1 270 465 8675",
    "sg:postcode":"42718",
    "sg:province":"KY",
    "sg:tags":[
        "general",
        "contractor"
    ],
    "wof:name":"Saver Systems Inc",
    "wof:placetype":"venue"
},
  "geometry": {"coordinates":[-85.34392099999999,37.342449],"type":"Point"}
}