{
  "type": "Feature",
  "properties": {
    "iso:country":"US",
    "sg:address":"221 Hawthorne Dr",
    "sg:city":"Nicholasville",
    "sg:classifiers":[
        {
            "category":"Communications",
            "subcategory":"Film & Video Production",
            "type":"Services"
        }
    ],
    "sg:phone":"+1 859 885 7251",
    "sg:postcode":"40356",
    "sg:province":"KY",
    "sg:tags":[
        "taping"
    ],
    "wof:name":"Omni Video Productions",
    "wof:placetype":"venue"
},
  "geometry": {"coordinates":[-84.598775,37.892284],"type":"Point"}
}