{
  "type": "Feature",
  "properties": {
    "addr:full":"85 Leisure Ln Morehead KY 40351",
    "addr:housenumber":"85",
    "addr:postcode":"40351",
    "addr:street":"Leisure Ln",
    "iso:country":"US",
    "sg:address":"85 Leisure Ln",
    "sg:city":"Morehead",
    "sg:classifiers":[
        {
            "category":"Personal",
            "subcategory":"Beauty Salon",
            "type":"Services"
        }
    ],
    "sg:phone":"+1 606 784 2176",
    "sg:postcode":"40351",
    "sg:province":"KY",
    "sg:tags":[
        "shop"
    ],
    "wof:name":"Rhonda's Hair Fashions",
    "wof:placetype":"venue"
},
  "geometry": {"coordinates":[-83.424843,38.157364],"type":"Point"}
}