{
  "type": "Feature",
  "properties": {
    "addr:full":"2140 Gardiner Ln Louisville KY 40205",
    "addr:housenumber":"2140",
    "addr:postcode":"40205",
    "addr:street":"Gardiner Ln",
    "iso:country":"US",
    "sg:address":"2140 Gardiner Ln",
    "sg:city":"Louisville",
    "sg:classifiers":[
        {
            "category":"Retail",
            "subcategory":"Laundry & Dry Cleaning",
            "type":"Services"
        }
    ],
    "sg:phone":"+1 502 451 2626",
    "sg:postcode":"40205",
    "sg:province":"KY",
    "sg:tags":[
        "cleaners"
    ],
    "wof:name":"Gardiner Lane One Hour Clnrs",
    "wof:placetype":"venue"
},
  "geometry": {"coordinates":[-85.675766,38.210594],"type":"Point"}
}