{
  "type": "Feature",
  "properties": {
    "addr:full":"1053 Chetford Dr Lexington KY 40509",
    "addr:housenumber":"1053",
    "addr:postcode":"40509",
    "addr:street":"Chetford Dr",
    "iso:country":"US",
    "sg:address":"1053 Chetford Dr",
    "sg:city":"Lexington",
    "sg:classifiers":[
        {
            "category":"Building & Trades",
            "subcategory":"Electrical",
            "type":"Services"
        }
    ],
    "sg:phone":"+1 859 263 5686",
    "sg:postcode":"40509",
    "sg:province":"KY",
    "sg:tags":[
        "electric",
        "contractor"
    ],
    "wof:name":"JTS Contractors",
    "wof:placetype":"venue"
},
  "geometry": {"coordinates":[-84.41540500000001,38.005118],"type":"Point"}
}