{
  "type": "Feature",
  "properties": {
    "iso:country":"US",
    "sg:address":"1700 Bagdad Rd",
    "sg:city":"Bagdad",
    "sg:classifiers":[
        {
            "category":"Building & Trades",
            "subcategory":"Construction",
            "type":"Services"
        }
    ],
    "sg:phone":"+1 502 747 8998",
    "sg:postcode":"40003",
    "sg:province":"KY",
    "sg:tags":[
        "excavating",
        "contractor"
    ],
    "wof:name":"Bobby Goullon Trucking",
    "wof:placetype":"venue"
},
  "geometry": {"coordinates":[-85.071787,38.263819],"type":"Point"}
}