{
  "type": "Feature",
  "properties": {
    "addr:full":"236 S Buell St Perryville KY 40468",
    "addr:housenumber":"236",
    "addr:postcode":"40468",
    "addr:street":"S Buell St",
    "iso:country":"US",
    "sg:address":"236 S Buell St",
    "sg:city":"Perryville",
    "sg:classifiers":[
        {
            "category":"Professional",
            "subcategory":"Management & Consulting",
            "type":"Services"
        }
    ],
    "sg:phone":"+1 859 332 1862",
    "sg:postcode":"40468",
    "sg:province":"KY",
    "sg:tags":[
        "consultant",
        "restoration",
        "historical"
    ],
    "sg:website":"www.perryville.net",
    "wof:name":"Perryville Enhancement Project",
    "wof:placetype":"venue"
},
  "geometry": {"coordinates":[-84.951729,37.649922],"type":"Point"}
}