{
  "type": "Feature",
  "properties": {
    "iso:country":"US",
    "sg:address":"2544 Mackville Rd",
    "sg:city":"Springfield",
    "sg:classifiers":[
        {
            "category":"Farming",
            "subcategory":"Farm",
            "type":"Manufacturing & Wholesale Goods"
        }
    ],
    "sg:phone":"+1 859 336 3566",
    "sg:postcode":"40069",
    "sg:province":"KY",
    "sg:tags":[
        "crop",
        "general"
    ],
    "wof:name":"Homeplace Farm",
    "wof:placetype":"venue"
},
  "geometry": {"coordinates":[-85.205839,37.683825],"type":"Point"}
}