{
  "type": "Feature",
  "properties": {
    "iso:country":"US",
    "sg:address":"3152 Maysville Rd",
    "sg:city":"Mount Sterling",
    "sg:classifiers":[
        {
            "category":"Retail",
            "subcategory":"Repair Shop",
            "type":"Services"
        }
    ],
    "sg:phone":"+1 859 498 6704",
    "sg:postcode":"40353",
    "sg:province":"KY",
    "sg:tags":[
        "contractor"
    ],
    "wof:name":"Setters Septic Tank Service",
    "wof:placetype":"venue"
},
  "geometry": {"coordinates":[-83.95361699999999,38.102338],"type":"Point"}
}