{
  "type": "Feature",
  "properties": {
    "iso:country":"US",
    "sg:address":"3909 State Hwy 11",
    "sg:city":"Bethel",
    "sg:classifiers":[
        {
            "category":"Freight",
            "type":"Transportation"
        }
    ],
    "sg:phone":"+1 606 247 2286",
    "sg:postcode":"40374",
    "sg:province":"KY",
    "sg:tags":[
        "broker",
        "trucking"
    ],
    "wof:name":"Thompson Transportation Svc",
    "wof:placetype":"venue"
},
  "geometry": {"coordinates":[-83.878196,38.24272],"type":"Point"}
}