{
  "type": "Feature",
  "properties": {
    "addr:full":"121 Matthew Dr Paducah KY 42001",
    "addr:housenumber":"121",
    "addr:postcode":"42001",
    "addr:street":"Matthew Dr",
    "iso:country":"US",
    "sg:address":"121 Matthew Dr",
    "sg:city":"Paducah",
    "sg:classifiers":[
        {
            "category":"Building & Trades",
            "subcategory":"Equipment Rental",
            "type":"Services"
        }
    ],
    "sg:phone":"+1 270 554 8420",
    "sg:postcode":"42001",
    "sg:province":"KY",
    "sg:tags":[
        "personal",
        "credit",
        "institution"
    ],
    "wof:name":"Helm Rail Equipment",
    "wof:placetype":"venue"
},
  "geometry": {"coordinates":[-88.70197,37.059385],"type":"Point"}
}