{
  "type": "Feature",
  "properties": {
    "iso:country":"US",
    "sg:address":"400 College Street Rd",
    "sg:city":"Elizabethtown",
    "sg:classifiers":[
        {
            "category":"Building & Trades",
            "subcategory":"Construction",
            "type":"Services"
        }
    ],
    "sg:phone":"+1 270 763 0782",
    "sg:postcode":"42701",
    "sg:province":"KY",
    "sg:tags":[
        "fire",
        "restoration",
        "damage"
    ],
    "wof:name":"Servpro Of Hardin/Mead Cnty",
    "wof:placetype":"venue"
},
  "geometry": {"coordinates":[-85.866872,37.692968],"type":"Point"}
}