{
  "type": "Feature",
  "properties": {
    "addr:full":"501 N Skyline Dr Louisville KY 40229",
    "addr:housenumber":"501",
    "addr:postcode":"40229",
    "addr:street":"N Skyline Dr",
    "iso:country":"US",
    "sg:address":"501 N Skyline Dr",
    "sg:city":"Louisville",
    "sg:classifiers":[
        {
            "category":"Manufacturing",
            "subcategory":"Electronics",
            "type":"Manufacturing & Wholesale Goods"
        }
    ],
    "sg:phone":"+1 502 957 4116",
    "sg:postcode":"40229",
    "sg:province":"KY",
    "sg:tags":[
        "semiconductor",
        "device",
        "related"
    ],
    "wof:name":"Midred A Allen",
    "wof:placetype":"venue"
},
  "geometry": {"coordinates":[-85.67414100000001,38.083061],"type":"Point"}
}