{
  "type": "Feature",
  "properties": {
    "addr:full":"100 W Broadway St Frankfort KY 40601",
    "addr:housenumber":"100",
    "addr:postcode":"40601",
    "addr:street":"W Broadway St",
    "iso:country":"US",
    "sg:address":"100 W Broadway St",
    "sg:city":"Frankfort",
    "sg:classifiers":[
        {
            "category":"Education",
            "subcategory":"Library",
            "type":"Public Place"
        }
    ],
    "sg:phone":"+1 502 564 1792",
    "sg:postcode":"40601",
    "sg:province":"KY",
    "sg:website":"www.kyoralhistory.org",
    "wof:name":"Historical Preservation",
    "wof:placetype":"venue"
},
  "geometry": {"coordinates":[-84.874842,38.198738],"type":"Point"}
}