{
  "type": "Feature",
  "properties": {
    "iso:country":"US",
    "sg:address":"12238 Shelbyville Rd",
    "sg:city":"Louisville",
    "sg:classifiers":[
        {
            "category":"Shopping",
            "subcategory":"Bicycles & Sporting Goods",
            "type":"Retail Goods"
        }
    ],
    "sg:phone":"+1 502 245 4567",
    "sg:postcode":"40243",
    "sg:province":"KY",
    "wof:name":"Oakwood The",
    "wof:placetype":"venue"
},
  "geometry": {"coordinates":[-85.52836000000001,38.247325],"type":"Point"}
}