{
  "type": "Feature",
  "properties": {
    "iso:country":"US",
    "sg:address":"2230 Middleground Dr",
    "sg:city":"Owensboro",
    "sg:classifiers":[
        {
            "category":"Shopping",
            "subcategory":"Gifts & Souvenirs",
            "type":"Retail Goods"
        }
    ],
    "sg:phone":"+1 270 685 2639",
    "sg:postcode":"42301",
    "sg:province":"KY",
    "wof:name":"Balloon Carousel of Owenboro",
    "wof:placetype":"venue"
},
  "geometry": {"coordinates":[-87.138704,37.744266],"type":"Point"}
}