{
  "type": "Feature",
  "properties": {
    "iso:country":"US",
    "sg:address":"322 N 3rd St",
    "sg:city":"Paducah",
    "sg:classifiers":[
        {
            "category":"Wholesale",
            "subcategory":"Drugs",
            "type":"Manufacturing & Wholesale Goods"
        }
    ],
    "sg:phone":"+1 270 444 7300",
    "sg:postcode":"42001",
    "sg:province":"KY",
    "sg:tags":[
        "pharmaceutical",
        "product"
    ],
    "sg:website":"www.amerisourcebergen.com",
    "wof:name":"Ameri Source Bergen Corp",
    "wof:placetype":"venue"
},
  "geometry": {"coordinates":[-88.59849699999999,37.090082],"type":"Point"}
}