{
  "type": "Feature",
  "properties": {
    "iso:country":"US",
    "sg:address":"101 S Lincoln Ave",
    "sg:city":"Henderson",
    "sg:classifiers":[
        {
            "category":"Social Services",
            "type":"Services"
        }
    ],
    "sg:phone":"+1 270 826 1328",
    "sg:postcode":"42420",
    "sg:province":"KY",
    "sg:tags":[
        "youth",
        "organization",
        "center"
    ],
    "wof:name":"Henderson Pee Wee League",
    "wof:placetype":"venue"
},
  "geometry": {"coordinates":[-87.57192000000001,37.824587],"type":"Point"}
}