{
  "type": "Feature",
  "properties": {
    "addr:full":"1121 Shagbark Ln Lexington KY 40515",
    "addr:housenumber":"1121",
    "addr:postcode":"40515",
    "addr:street":"Shagbark Ln",
    "iso:country":"US",
    "sg:address":"1121 Shagbark Ln",
    "sg:city":"Lexington",
    "sg:classifiers":[
        {
            "category":"Real Estate",
            "subcategory":"Real Estate Agent",
            "type":"Services"
        }
    ],
    "sg:phone":"+1 859 273 7766",
    "sg:postcode":"40515",
    "sg:province":"KY",
    "sg:tags":[
        "management"
    ],
    "wof:name":"Harry Jones Jr Building Mgmt",
    "wof:placetype":"venue"
},
  "geometry": {"coordinates":[-84.493111,37.967048],"type":"Point"}
}