{
  "type": "Feature",
  "properties": {
    "iso:country":"US",
    "sg:address":"3415 Bardstown Rd",
    "sg:city":"Louisville",
    "sg:classifiers":[
        {
            "category":"Banks & Credit Unions",
            "subcategory":"Bank",
            "type":"Services"
        }
    ],
    "sg:phone":"+1 502 451 9614",
    "sg:postcode":"40218",
    "sg:province":"KY",
    "sg:tags":[
        "loan",
        "real estate"
    ],
    "wof:name":"Primary Mortgage",
    "wof:placetype":"venue"
},
  "geometry": {"coordinates":[-85.66533099999999,38.204166],"type":"Point"}
}