{
  "type": "Feature",
  "properties": {
    "iso:country":"US",
    "sg:address":"1819 Yale Dr",
    "sg:city":"Louisville",
    "sg:classifiers":[
        {
            "category":"Professional",
            "subcategory":"Printing & Photocopies",
            "type":"Services"
        }
    ],
    "sg:phone":"+1 502 451 8316",
    "sg:postcode":"40205",
    "sg:province":"KY",
    "sg:tags":[
        "photographers-commercial"
    ],
    "wof:name":"Martin E Biemer Editor",
    "wof:placetype":"venue"
},
  "geometry": {"coordinates":[-85.69613699999999,38.219671],"type":"Point"}
}