{
  "type": "Feature",
  "properties": {
    "addr:full":"114 Bauer Ave Louisville KY 40207",
    "addr:housenumber":"114",
    "addr:postcode":"40207",
    "addr:street":"Bauer Ave",
    "iso:country":"US",
    "sg:address":"114 Bauer Ave",
    "sg:city":"Louisville",
    "sg:classifiers":[
        {
            "category":"Shopping",
            "subcategory":"Used Merchandise",
            "type":"Retail Goods"
        }
    ],
    "sg:phone":"+1 502 896 2705",
    "sg:postcode":"40207",
    "sg:province":"KY",
    "sg:tags":[
        "antique",
        "collectible"
    ],
    "wof:name":"Country Critic",
    "wof:placetype":"venue"
},
  "geometry": {"coordinates":[-85.661494,38.252442],"type":"Point"}
}