{
  "type": "Feature",
  "properties": {
    "iso:country":"US",
    "sg:address":"10623 W Manslick Rd",
    "sg:city":"Fairdale",
    "sg:classifiers":[
        {
            "category":"Education",
            "subcategory":"Dance Studio",
            "type":"Public Place"
        }
    ],
    "sg:phone":"+1 502 367 3996",
    "sg:postcode":"40118",
    "sg:province":"KY",
    "sg:tags":[
        "instruction",
        "dancing"
    ],
    "wof:name":"Step-N-Out Dance Studio",
    "wof:placetype":"venue"
},
  "geometry": {"coordinates":[-85.75868,38.105067],"type":"Point"}
}