{
  "type": "Feature",
  "properties": {
    "iso:country":"US",
    "sg:address":"7100 Dixie Hwy",
    "sg:city":"Florence",
    "sg:classifiers":[
        {
            "category":"Organizations",
            "subcategory":"Religious Organization",
            "type":"Services"
        }
    ],
    "sg:phone":"+1 859 746 8672",
    "sg:postcode":"41042",
    "sg:province":"KY",
    "wof:name":"Lord's House Ministries",
    "wof:placetype":"venue"
},
  "geometry": {"coordinates":[-84.62659600000001,38.998874],"type":"Point"}
}