{
  "type": "Feature",
  "properties": {
    "iso:country":"US",
    "sg:address":"3704 Lexington Rd",
    "sg:city":"Louisville",
    "sg:classifiers":[
        {
            "category":"Shopping",
            "subcategory":"Clothing, Apparel, & Fashions",
            "type":"Retail Goods"
        }
    ],
    "sg:phone":"+1 502 458 6060",
    "sg:postcode":"40207",
    "sg:province":"KY",
    "wof:name":"Nest LLC",
    "wof:placetype":"venue"
},
  "geometry": {"coordinates":[-85.659976,38.251919],"type":"Point"}
}