{
  "type": "Feature",
  "properties": {
    "addr:full":"440 Old Vine St Lexington KY 40507",
    "addr:housenumber":"440",
    "addr:postcode":"40507",
    "addr:street":"Old Vine St",
    "iso:country":"US",
    "sg:address":"440 Old Vine St",
    "sg:city":"Lexington",
    "sg:classifiers":[
        {
            "category":"Insurance",
            "subcategory":"Insurance Agent",
            "type":"Services"
        }
    ],
    "sg:phone":"+1 859 335 6364",
    "sg:postcode":"40507",
    "sg:province":"KY",
    "wof:name":"A I N Lexington Group",
    "wof:placetype":"venue"
},
  "geometry": {"coordinates":[-84.49102600000001,38.039215],"type":"Point"}
}