{
  "type": "Feature",
  "properties": {
    "addr:full":"6510 Robinson Creek Rd Robinson Creek KY 41560",
    "addr:housenumber":"6510",
    "addr:postcode":"41560",
    "addr:street":"Robinson Creek Rd",
    "iso:country":"US",
    "sg:address":"6510 Robinson Creek Rd",
    "sg:city":"Robinson Creek",
    "sg:classifiers":[
        {
            "category":"Retail",
            "subcategory":"Repair Shop",
            "type":"Services"
        }
    ],
    "sg:phone":"+1 606 639 2613",
    "sg:postcode":"41560",
    "sg:province":"KY",
    "sg:tags":[
        "welding"
    ],
    "wof:name":"Black Arc Enterprises Inc",
    "wof:placetype":"venue"
},
  "geometry": {"coordinates":[-82.557901,37.390115],"type":"Point"}
}