{
  "type": "Feature",
  "properties": {
    "addr:full":"157 Main St Pikeville KY 41501",
    "addr:housenumber":"157",
    "addr:postcode":"41501",
    "addr:street":"Main St",
    "iso:country":"US",
    "sg:address":"157 Main St",
    "sg:city":"Pikeville",
    "sg:classifiers":[
        {
            "category":"Insurance",
            "subcategory":"Insurance Agent",
            "type":"Services"
        }
    ],
    "sg:phone":"+1 606 437 4086",
    "sg:postcode":"41501",
    "sg:province":"KY",
    "wof:name":"Chrisman Insurance Inc",
    "wof:placetype":"venue"
},
  "geometry": {"coordinates":[-82.517071,37.480109],"type":"Point"}
}