{
  "type": "Feature",
  "properties": {
    "iso:country":"US",
    "sg:address":"611 W Jefferson St",
    "sg:city":"Louisville",
    "sg:classifiers":[
        {
            "category":"Government",
            "subcategory":"Office",
            "type":"Public Place"
        }
    ],
    "sg:phone":"+1 502 574 3222",
    "sg:postcode":"40202",
    "sg:province":"KY",
    "sg:tags":[
        "policy"
    ],
    "wof:name":"City of Lsville Dept Fin Budgt",
    "wof:placetype":"venue"
},
  "geometry": {"coordinates":[-85.761832,38.254435],"type":"Point"}
}