{
  "type": "Feature",
  "properties": {
    "addr:full":"521 N Main St Nicholasville KY 40356",
    "addr:housenumber":"521",
    "addr:postcode":"40356",
    "addr:street":"N Main St",
    "iso:country":"US",
    "sg:address":"521 N Main St",
    "sg:city":"Nicholasville",
    "sg:classifiers":[
        {
            "category":"Restaurant",
            "type":"Food & Drink"
        }
    ],
    "sg:menulink":"http://www.allmenus.com/ky/nicholasville/79665-pizza-hut/menu/",
    "sg:phone":"+1 859 885 6201",
    "sg:postcode":"40356",
    "sg:province":"KY",
    "sg:tags":[
        "american",
        "pizza"
    ],
    "wof:name":"Pizza Hut",
    "wof:placetype":"venue"
},
  "geometry": {"coordinates":[-84.570519,37.886357],"type":"Point"}
}