{
  "type": "Feature",
  "properties": {
    "addr:full":"784 W Main St Lebanon KY 40033",
    "addr:housenumber":"784",
    "addr:postcode":"40033",
    "addr:street":"W Main St",
    "iso:country":"US",
    "sg:address":"784 W Main St",
    "sg:city":"Lebanon",
    "sg:classifiers":[
        {
            "category":"Restaurant",
            "type":"Food & Drink"
        }
    ],
    "sg:phone":"+1 270 692 9507",
    "sg:postcode":"40033",
    "sg:province":"KY",
    "wof:name":"Rio's Steakhouse Of Lebanon",
    "wof:placetype":"venue"
},
  "geometry": {"coordinates":[-85.272785,37.559056],"type":"Point"}
}