{
  "type": "Feature",
  "properties": {
    "iso:country":"US",
    "sg:address":"1142 S 15th St",
    "sg:city":"Louisville",
    "sg:classifiers":[
        {
            "category":"Social Services",
            "type":"Services"
        }
    ],
    "sg:phone":"+1 502 582 1888",
    "sg:postcode":"40210",
    "sg:province":"KY",
    "sg:tags":[
        "organization",
        "welfare"
    ],
    "wof:name":"ITA Homes",
    "wof:placetype":"venue"
},
  "geometry": {"coordinates":[-85.778249,38.23737],"type":"Point"}
}