{
  "type": "Feature",
  "properties": {
    "iso:country":"US",
    "sg:address":"8412 Ferndale Rd",
    "sg:city":"Louisville",
    "sg:classifiers":[
        {
            "category":"Building & Trades",
            "subcategory":"Construction",
            "type":"Services"
        }
    ],
    "sg:phone":"+1 502 239 3208",
    "sg:postcode":"40291",
    "sg:province":"KY",
    "sg:tags":[
        "house"
    ],
    "wof:name":"Warden Home Builders LLC",
    "wof:placetype":"venue"
},
  "geometry": {"coordinates":[-85.603024,38.155584],"type":"Point"}
}