{
  "type": "Feature",
  "properties": {
    "iso:country":"US",
    "sg:address":"637 Dowell St",
    "sg:city":"Campbellsville",
    "sg:classifiers":[
        {
            "category":"Building & Trades",
            "subcategory":"Construction",
            "type":"Services"
        }
    ],
    "sg:phone":"+1 270 465 4944",
    "sg:postcode":"42718",
    "sg:province":"KY",
    "sg:tags":[
        "contractor"
    ],
    "wof:name":"Newcomb Plumbing & Building",
    "wof:placetype":"venue"
},
  "geometry": {"coordinates":[-85.335114,37.29377],"type":"Point"}
}