{
  "type": "Feature",
  "properties": {
    "iso:country":"US",
    "sg:address":"298 Happyville Rd",
    "sg:city":"Greensburg",
    "sg:classifiers":[
        {
            "category":"Building & Trades",
            "subcategory":"Construction",
            "type":"Services"
        }
    ],
    "sg:phone":"+1 270 932 7539",
    "sg:postcode":"42743",
    "sg:province":"KY",
    "wof:name":"Stor Mor Inc",
    "wof:placetype":"venue"
},
  "geometry": {"coordinates":[-85.5127,37.276312],"type":"Point"}
}