{
  "type": "Feature",
  "properties": {
    "iso:country":"US",
    "sg:address":"7128 Ridge Creek Rd",
    "sg:city":"Louisville",
    "sg:classifiers":[
        {
            "category":"Professional",
            "subcategory":"Art Services",
            "type":"Services"
        }
    ],
    "sg:phone":"+1 502 499 7621",
    "sg:postcode":"40291",
    "sg:province":"KY",
    "sg:tags":[
        "commercial",
        "design"
    ],
    "wof:name":"Folio LLC",
    "wof:placetype":"venue"
},
  "geometry": {"coordinates":[-85.62672000000001,38.160624],"type":"Point"}
}