{
  "type": "Feature",
  "properties": {
    "iso:country":"US",
    "sg:address":"147 Tolley Ln",
    "sg:city":"Science Hill",
    "sg:classifiers":[
        {
            "category":"Retail",
            "subcategory":"Repair Shop",
            "type":"Services"
        }
    ],
    "sg:phone":"+1 606 423 3257",
    "sg:postcode":"42553",
    "sg:province":"KY",
    "sg:tags":[
        "electrical"
    ],
    "wof:name":"Tolleys Appliance Repair",
    "wof:placetype":"venue"
},
  "geometry": {"coordinates":[-84.683477,37.191534],"type":"Point"}
}