{
  "type": "Feature",
  "properties": {
    "addr:full":"200 Glass Ave Hopkinsville KY 42240",
    "addr:housenumber":"200",
    "addr:postcode":"42240",
    "addr:street":"Glass Ave",
    "iso:country":"US",
    "sg:address":"200 Glass Ave",
    "sg:city":"Hopkinsville",
    "sg:classifiers":[
        {
            "category":"Education",
            "subcategory":"Special Training",
            "type":"Public Place"
        }
    ],
    "sg:phone":"+1 270 887 1319",
    "sg:postcode":"42240",
    "sg:province":"KY",
    "sg:tags":[
        "educational"
    ],
    "wof:name":"GED-Adult Education",
    "wof:placetype":"venue"
},
  "geometry": {"coordinates":[-87.489131,36.877649],"type":"Point"}
}