{
  "type": "Feature",
  "properties": {
    "iso:country":"US",
    "sg:address":"7701 Barnwood Rd",
    "sg:city":"Louisville",
    "sg:classifiers":[
        {
            "category":"Building & Trades",
            "subcategory":"Construction",
            "type":"Services"
        }
    ],
    "sg:phone":"+1 502 594 4912",
    "sg:postcode":"40291",
    "sg:province":"KY",
    "sg:tags":[
        "contractor"
    ],
    "wof:name":"Elite Tile",
    "wof:placetype":"venue"
},
  "geometry": {"coordinates":[-85.596929,38.132549],"type":"Point"}
}