{
  "type": "Feature",
  "properties": {
    "iso:country":"US",
    "sg:address":"921 Louisville Rd",
    "sg:city":"Frankfort",
    "sg:classifiers":[
        {
            "category":"Retail",
            "subcategory":"Car Wash",
            "type":"Services"
        }
    ],
    "sg:phone":"+1 502 226 4124",
    "sg:postcode":"40601",
    "sg:province":"KY",
    "sg:tags":[
        "carwash"
    ],
    "wof:name":"Raymonds 24 Hour Car Wash",
    "wof:placetype":"venue"
},
  "geometry": {"coordinates":[-84.891268,38.182126],"type":"Point"}
}