{
  "type": "Feature",
  "properties": {
    "addr:full":"8751 Gene Paulin Way Fairdale KY 40118",
    "addr:housenumber":"8751",
    "addr:postcode":"40118",
    "addr:street":"Gene Paulin Way",
    "iso:country":"US",
    "sg:address":"8751 Gene Paulin Way",
    "sg:city":"Fairdale",
    "sg:classifiers":[
        {
            "category":"Retail",
            "subcategory":"Auto Repair",
            "type":"Services"
        }
    ],
    "sg:phone":"+1 502 361 2050",
    "sg:postcode":"40118",
    "sg:province":"KY",
    "sg:tags":[
        "repairing",
        "automobile"
    ],
    "wof:name":"Southside Automotive",
    "wof:placetype":"venue"
},
  "geometry": {"coordinates":[-85.746793,38.123398],"type":"Point"}
}