{
  "type": "Feature",
  "properties": {
    "iso:country":"US",
    "sg:address":"1650 Bryan Station Rd",
    "sg:city":"Lexington",
    "sg:classifiers":[
        {
            "category":"Banks & Credit Unions",
            "subcategory":"Bank",
            "type":"Services"
        }
    ],
    "sg:phone":"+1 859 294 7295",
    "sg:postcode":"40505",
    "sg:province":"KY",
    "sg:tags":[
        "financing"
    ],
    "wof:name":"Wells Fargo Financial Accptnce",
    "wof:placetype":"venue"
},
  "geometry": {"coordinates":[-84.46335999999999,38.060458],"type":"Point"}
}