{
  "type": "Feature",
  "properties": {
    "iso:country":"US",
    "sg:address":"9852 State Hwy 80 W",
    "sg:city":"Mayfield",
    "sg:classifiers":[
        {
            "category":"Home & Garden",
            "subcategory":"Hardware",
            "type":"Retail Goods"
        }
    ],
    "sg:phone":"+1 270 623 6381",
    "sg:postcode":"42066",
    "sg:province":"KY",
    "wof:name":"Hobb's Feed & Supply",
    "wof:placetype":"venue"
},
  "geometry": {"coordinates":[-88.78492300000001,36.795949],"type":"Point"}
}