{
  "type": "Feature",
  "properties": {
    "iso:country":"US",
    "sg:address":"103 Markwell Ct",
    "sg:city":"Louisville",
    "sg:classifiers":[
        {
            "category":"Shopping",
            "subcategory":"Music",
            "type":"Retail Goods"
        }
    ],
    "sg:phone":"+1 502 962 9781",
    "sg:postcode":"40219",
    "sg:province":"KY",
    "sg:tags":[
        "compact",
        "record",
        "disc",
        "tape"
    ],
    "wof:name":"Video's To Go",
    "wof:placetype":"venue"
},
  "geometry": {"coordinates":[-85.691244,38.140022],"type":"Point"}
}