{
  "type": "Feature",
  "properties": {
    "iso:country":"US",
    "sg:address":"4364 E Blue Lick Rd",
    "sg:city":"Louisville",
    "sg:classifiers":[
        {
            "category":"Autos & Motor Vehicles",
            "subcategory":"Auto Supplies",
            "type":"Retail Goods"
        },
        {
            "category":"Wholesale",
            "subcategory":"Electrical",
            "type":"Manufacturing & Wholesale Goods"
        }
    ],
    "sg:phone":"+1 502 364 9805",
    "sg:postcode":"40229",
    "sg:province":"KY",
    "sg:tags":[
        "battery",
        "batteries-storage-wholesale",
        "batteries-storage",
        "manufacturer"
    ],
    "wof:name":"Kentucky Battery Outlet",
    "wof:placetype":"venue"
},
  "geometry": {"coordinates":[-85.69399199999999,38.064016],"type":"Point"}
}