{
  "type": "Feature",
  "properties": {
    "iso:country":"US",
    "sg:address":"1027 College St",
    "sg:city":"Bowling Green",
    "sg:classifiers":[
        {
            "category":"Professional",
            "subcategory":"Accounting & Tax Preparation",
            "type":"Services"
        }
    ],
    "sg:phone":"+1 270 843 0244",
    "sg:postcode":"42101",
    "sg:province":"KY",
    "sg:tags":[
        "accountant"
    ],
    "wof:name":"Kirby & Kirby",
    "wof:placetype":"venue"
},
  "geometry": {"coordinates":[-86.44326700000001,36.992794],"type":"Point"}
}