{
  "type": "Feature",
  "properties": {
    "addr:full":"135 Roby Rd Reynolds Station KY 42368",
    "addr:housenumber":"135",
    "addr:postcode":"42368",
    "addr:street":"Roby Rd",
    "iso:country":"US",
    "sg:address":"135 Roby Rd",
    "sg:city":"Reynolds Station",
    "sg:classifiers":[
        {
            "category":"Professional",
            "type":"Services"
        }
    ],
    "sg:phone":"+1 270 233 9968",
    "sg:postcode":"42368",
    "sg:province":"KY",
    "sg:tags":[
        "establishment"
    ],
    "wof:name":"Kimberly Robey-Mary Kay Cnsltn",
    "wof:placetype":"venue"
},
  "geometry": {"coordinates":[-86.759784,37.738546],"type":"Point"}
}