{
  "type": "Feature",
  "properties": {
    "iso:country":"US",
    "sg:address":"3900 Burning Bush Rd",
    "sg:city":"Louisville",
    "sg:classifiers":[
        {
            "category":"Professional",
            "type":"Services"
        }
    ],
    "sg:phone":"+1 502 394 9198",
    "sg:postcode":"40241",
    "sg:province":"KY",
    "wof:name":"Reliable Services Inc",
    "wof:placetype":"venue"
},
  "geometry": {"coordinates":[-85.593124,38.306149],"type":"Point"}
}