{
  "type": "Feature",
  "properties": {
    "addr:full":"1126 Larchmont Ave Louisville KY 40215",
    "addr:housenumber":"1126",
    "addr:postcode":"40215",
    "addr:street":"Larchmont Ave",
    "iso:country":"US",
    "sg:address":"1126 Larchmont Ave",
    "sg:city":"Louisville",
    "sg:classifiers":[
        {
            "category":"Health Services",
            "subcategory":"Hospital",
            "type":"Services"
        }
    ],
    "sg:phone":"+1 502 361 9805",
    "sg:postcode":"40215",
    "sg:province":"KY",
    "wof:name":"Hospital Audit Locus Inc",
    "wof:placetype":"venue"
},
  "geometry": {"coordinates":[-85.777215,38.205678],"type":"Point"}
}