{
  "type": "Feature",
  "properties": {
    "addr:full":"7772 State Hwy 1241 Hickory KY 42051",
    "addr:housenumber":"7772",
    "addr:postcode":"42051",
    "addr:street":"State Hwy 1241",
    "iso:country":"US",
    "sg:address":"7772 State Hwy 1241",
    "sg:city":"Hickory",
    "sg:classifiers":[
        {
            "category":"Real Estate",
            "subcategory":"Real Estate Agent",
            "type":"Services"
        }
    ],
    "sg:phone":"+1 270 856 3926",
    "sg:postcode":"42051",
    "sg:province":"KY",
    "sg:tags":[
        "appraiser"
    ],
    "wof:name":"Miller & Assoc",
    "wof:placetype":"venue"
},
  "geometry": {"coordinates":[-88.682828,36.89639],"type":"Point"}
}