{
  "type": "Feature",
  "properties": {
    "iso:country":"US",
    "sg:address":"10250 State Hwy 44 E",
    "sg:city":"Mt Washington",
    "sg:classifiers":[
        {
            "category":"Insurance",
            "subcategory":"Insurance Agent",
            "type":"Services"
        }
    ],
    "sg:phone":"+1 502 538 7422",
    "sg:postcode":"40047",
    "sg:province":"KY",
    "wof:name":"State Farm Insurance",
    "wof:placetype":"venue"
},
  "geometry": {"coordinates":[-85.556613,38.058253],"type":"Point"}
}