{
  "type": "Feature",
  "properties": {
    "iso:country":"US",
    "sg:address":"9920 Corporate Campus Dr Ste 2200",
    "sg:city":"Louisville",
    "sg:classifiers":[
        {
            "category":"Real Estate",
            "subcategory":"Real Estate Services",
            "type":"Services"
        },
        {
            "category":"Professional",
            "subcategory":"Research",
            "type":"Services"
        },
        {
            "category":"Insurance",
            "subcategory":"Title Insurance",
            "type":"Services"
        }
    ],
    "sg:phone":"+1 502 327 7778",
    "sg:postcode":"40223",
    "sg:province":"KY",
    "sg:tags":[
        "abstracter"
    ],
    "sg:website":"http://www.executivetitlecompany.com",
    "wof:name":"Executive Title Company",
    "wof:placetype":"venue"
},
  "geometry": {"coordinates":[-85.57544300000001,38.265043],"type":"Point"}
}