{
  "type": "Feature",
  "properties": {
    "iso:country":"US",
    "sg:address":"1300 Southgate Ave",
    "sg:city":"Louisville",
    "sg:classifiers":[
        {
            "category":"Personal",
            "subcategory":"Barber",
            "type":"Services"
        }
    ],
    "sg:phone":"+1 502 367 2889",
    "sg:postcode":"40215",
    "sg:province":"KY",
    "sg:tags":[
        "shop"
    ],
    "wof:name":"Mills Barber Shop",
    "wof:placetype":"venue"
},
  "geometry": {"coordinates":[-85.78319399999999,38.200857],"type":"Point"}
}