{
  "type": "Feature",
  "properties": {
    "iso:country":"US",
    "sg:address":"1823 Berry Blvd",
    "sg:city":"Louisville",
    "sg:classifiers":[
        {
            "category":"Home & Garden",
            "subcategory":"Furniture",
            "type":"Retail Goods"
        }
    ],
    "sg:phone":"+1 502 368 7310",
    "sg:postcode":"40215",
    "sg:province":"KY",
    "sg:tags":[
        "top",
        "counter"
    ],
    "wof:name":"Alpha & Omega Cabinetry LLC",
    "wof:placetype":"venue"
},
  "geometry": {"coordinates":[-85.798652,38.196826],"type":"Point"}
}