{
  "type": "Feature",
  "properties": {
    "iso:country":"US",
    "sg:address":"2501 Alexander Rd",
    "sg:city":"Louisville",
    "sg:classifiers":[
        {
            "category":"Sports & Exercise",
            "subcategory":"Golf",
            "type":"Entertainment"
        }
    ],
    "sg:phone":"+1 502 458 9450",
    "sg:postcode":"40204",
    "sg:province":"KY",
    "sg:tags":[
        "course"
    ],
    "wof:name":"Cherokee Golf Course",
    "wof:placetype":"venue"
},
  "geometry": {"coordinates":[-85.70942700000001,38.23666],"type":"Point"}
}