{
  "type": "Feature",
  "properties": {
    "iso:country":"US",
    "sg:address":"6304 Edmonton Rd",
    "sg:city":"Glasgow",
    "sg:classifiers":[
        {
            "category":"Building & Trades",
            "subcategory":"Plumbing",
            "type":"Services"
        }
    ],
    "sg:phone":"+1 270 678 3333",
    "sg:postcode":"42141",
    "sg:province":"KY",
    "sg:tags":[
        "conditioning",
        "air",
        "system",
        "contractor"
    ],
    "wof:name":"Central Air Systems Inc",
    "wof:placetype":"venue"
},
  "geometry": {"coordinates":[-85.80483700000001,37.017057],"type":"Point"}
}