{
  "type": "Feature",
  "properties": {
    "iso:country":"US",
    "sg:address":"43 Channel Ct",
    "sg:city":"Canton",
    "sg:classifiers":[
        {
            "category":"Travel",
            "subcategory":"Hotels & Motels",
            "type":"Entertainment"
        }
    ],
    "sg:phone":"+1 270 924 1094",
    "sg:postcode":"42211",
    "sg:province":"KY",
    "sg:tags":[
        "breakfast",
        "accommodation",
        "bed"
    ],
    "wof:name":"Whispering Winds Inn",
    "wof:placetype":"venue"
},
  "geometry": {"coordinates":[-87.968182,36.834255],"type":"Point"}
}