{
  "type": "Feature",
  "properties": {
    "iso:country":"US",
    "sg:address":"820 S Main St",
    "sg:city":"Greenville",
    "sg:classifiers":[
        {
            "category":"Shopping",
            "subcategory":"Department Store",
            "type":"Retail Goods"
        }
    ],
    "sg:phone":"+1 270 338 5866",
    "sg:postcode":"42345",
    "sg:province":"KY",
    "sg:website":"www.unclelees.com",
    "wof:name":"Uncle Lee's",
    "wof:placetype":"venue"
},
  "geometry": {"coordinates":[-87.17286799999999,37.193525],"type":"Point"}
}