{
  "type": "Feature",
  "properties": {
    "iso:country":"US",
    "sg:address":"460 Farley Ln",
    "sg:city":"Glendale",
    "sg:classifiers":[
        {
            "category":"Retail",
            "subcategory":"Laundry & Dry Cleaning",
            "type":"Services"
        }
    ],
    "sg:phone":"+1 270 369 0247",
    "sg:postcode":"42740",
    "sg:province":"KY",
    "sg:tags":[
        "cleaners",
        "rug",
        "carpet"
    ],
    "wof:name":"Bright Ideals Carpet & Uplstry",
    "wof:placetype":"venue"
},
  "geometry": {"coordinates":[-85.943324,37.598175],"type":"Point"}
}