{
  "type": "Feature",
  "properties": {
    "addr:full":"1501 S 1st St Louisville KY 40208",
    "addr:housenumber":"1501",
    "addr:postcode":"40208",
    "addr:street":"S 1St St",
    "iso:country":"US",
    "sg:address":"1501 S 1st St",
    "sg:city":"Louisville",
    "sg:classifiers":[
        {
            "category":"Organizations",
            "subcategory":"Non-profit Organization",
            "type":"Services"
        }
    ],
    "sg:phone":"+1 502 634 9067",
    "sg:postcode":"40208",
    "sg:province":"KY",
    "sg:tags":[
        "deaf"
    ],
    "wof:name":"Donohue Signs",
    "wof:placetype":"venue"
},
  "geometry": {"coordinates":[-85.756927,38.22559],"type":"Point"}
}