{
  "type": "Feature",
  "properties": {
    "addr:full":"11421 Main St Louisville KY 40243",
    "addr:housenumber":"11421",
    "addr:postcode":"40243",
    "addr:street":"Main St",
    "iso:country":"US",
    "sg:address":"11421 Main St",
    "sg:city":"Louisville",
    "sg:classifiers":[
        {
            "category":"Personal",
            "subcategory":"Beauty Salon",
            "type":"Services"
        }
    ],
    "sg:phone":"+1 502 254 7112",
    "sg:postcode":"40243",
    "sg:province":"KY",
    "wof:name":"Friends Salon Inc",
    "wof:placetype":"venue"
},
  "geometry": {"coordinates":[-85.54406,38.244171],"type":"Point"}
}