{
  "type": "Feature",
  "properties": {
    "iso:country":"US",
    "sg:address":"4250 Troy Pike",
    "sg:city":"Versailles",
    "sg:classifiers":[
        {
            "category":"Real Estate",
            "subcategory":"Real Estate Operator",
            "type":"Services"
        }
    ],
    "sg:phone":"+1 859 873 1993",
    "sg:postcode":"40383",
    "sg:province":"KY",
    "sg:tags":[
        "building",
        "apartment"
    ],
    "wof:name":"Southern Cross Construction Co",
    "wof:placetype":"venue"
},
  "geometry": {"coordinates":[-84.72321100000001,38.001774],"type":"Point"}
}