{
  "type": "Feature",
  "properties": {
    "addr:full":"603 College St Bowling Green KY 42101",
    "addr:housenumber":"603",
    "addr:postcode":"42101",
    "addr:street":"College",
    "iso:country":"US",
    "sg:address":"603 College St",
    "sg:city":"Bowling Green",
    "sg:classifiers":[
        {
            "category":"Real Estate",
            "subcategory":"Real Estate Agent",
            "type":"Services"
        }
    ],
    "sg:phone":"+1 270 782 6250",
    "sg:postcode":"42101",
    "sg:province":"KY",
    "wof:name":"RND Properties",
    "wof:placetype":"venue"
},
  "geometry": {"coordinates":[-86.43787399999999,36.996402],"type":"Point"}
}