{
  "type": "Feature",
  "properties": {
    "addr:full":"1700 Eastern Ave Covington KY 41014",
    "addr:housenumber":"1700",
    "addr:postcode":"41014",
    "addr:street":"Eastern Ave",
    "iso:country":"US",
    "sg:address":"1700 Eastern Ave",
    "sg:city":"Covington",
    "sg:classifiers":[
        {
            "category":"Manufacturing",
            "subcategory":"Signs",
            "type":"Manufacturing & Wholesale Goods"
        }
    ],
    "sg:phone":"+1 859 491 0645",
    "sg:postcode":"41014",
    "sg:province":"KY",
    "wof:name":"Todd Engraving",
    "wof:placetype":"venue"
},
  "geometry": {"coordinates":[-84.498593,39.071141],"type":"Point"}
}