{
  "type": "Feature",
  "properties": {
    "addr:full":"102 William E Lobb Dr Greensburg KY 42743",
    "addr:housenumber":"102",
    "addr:postcode":"42743",
    "addr:street":"William E Lobb Dr",
    "iso:country":"US",
    "sg:address":"102 William E Lobb Dr",
    "sg:city":"Greensburg",
    "sg:classifiers":[
        {
            "category":"Health Services",
            "subcategory":"Nursing And Care Facility",
            "type":"Services"
        }
    ],
    "sg:phone":"+1 270 932 9630",
    "sg:postcode":"42743",
    "sg:province":"KY",
    "wof:name":"Green County Adult Day Health",
    "wof:placetype":"venue"
},
  "geometry": {"coordinates":[-85.54948,37.326774],"type":"Point"}
}