{
  "type": "Feature",
  "properties": {
    "addr:full":"308 E 25th St Owensboro KY 42303",
    "addr:housenumber":"308",
    "addr:postcode":"42303",
    "addr:street":"E 25Th St",
    "iso:country":"US",
    "sg:address":"308 E 25th St",
    "sg:city":"Owensboro",
    "sg:phone":"+1 270 683 6218",
    "sg:postcode":"42303",
    "sg:province":"KY",
    "sg:tags":[
        "gas"
    ],
    "wof:name":"Suburban Propane",
    "wof:placetype":"venue"
},
  "geometry": {"coordinates":[-87.104983,37.751304],"type":"Point"}
}