{
  "type": "Feature",
  "properties": {
    "addr:full":"4717 Boca Ln Lexington KY 40515",
    "addr:housenumber":"4717",
    "addr:postcode":"40515",
    "addr:street":"Boca Ln",
    "iso:country":"US",
    "sg:address":"4717 Boca Ln",
    "sg:city":"Lexington",
    "sg:classifiers":[
        {
            "category":"Building & Trades",
            "subcategory":"Construction",
            "type":"Services"
        }
    ],
    "sg:phone":"+1 859 259 0499",
    "sg:postcode":"40515",
    "sg:province":"KY",
    "sg:tags":[
        "roofing",
        "contractor"
    ],
    "wof:name":"Leak Pro",
    "wof:placetype":"venue"
},
  "geometry": {"coordinates":[-84.507583,37.952959],"type":"Point"}
}