{
  "type": "Feature",
  "properties": {
    "iso:country":"US",
    "sg:address":"403 Stanford St",
    "sg:city":"Lancaster",
    "sg:classifiers":[
        {
            "category":"Food & Beverages",
            "subcategory":"Groceries & Convenience Stores",
            "type":"Retail Goods"
        }
    ],
    "sg:phone":"+1 859 792 6003",
    "sg:postcode":"40444",
    "sg:province":"KY",
    "sg:tags":[
        "grocer"
    ],
    "wof:name":"VIP Express Store",
    "wof:placetype":"venue"
},
  "geometry": {"coordinates":[-84.579776,37.612305],"type":"Point"}
}