{
  "type": "Feature",
  "properties": {
    "iso:country":"US",
    "sg:address":"387 Edgewood Ln",
    "sg:city":"Prestonsburg",
    "sg:classifiers":[
        {
            "category":"Government",
            "subcategory":"Office",
            "type":"Public Place"
        }
    ],
    "sg:phone":"+1 606 886 8861",
    "sg:postcode":"41653",
    "sg:province":"KY",
    "sg:tags":[
        "government-united",
        "state"
    ],
    "sg:website":"http://www.ssa.gov",
    "wof:name":"Office Of Hearings & Appeals",
    "wof:placetype":"venue"
},
  "geometry": {"coordinates":[-82.76213300000001,37.727977],"type":"Point"}
}