{
  "type": "Feature",
  "properties": {
    "iso:country":"US",
    "sg:address":"3600 Chamberlain Ln",
    "sg:city":"Louisville",
    "sg:classifiers":[
        {
            "category":"Food & Beverages",
            "subcategory":"Bakery",
            "type":"Retail Goods"
        }
    ],
    "sg:phone":"+1 502 339 9135",
    "sg:postcode":"40241",
    "sg:province":"KY",
    "sg:tags":[
        "doughnut"
    ],
    "wof:name":"Fresh Serve Bakeries Inc",
    "wof:placetype":"venue"
},
  "geometry": {"coordinates":[-85.541704,38.299315],"type":"Point"}
}