{
  "type": "Feature",
  "properties": {
    "iso:country":"US",
    "sg:address":"9154 Taylorsville Rd",
    "sg:city":"Louisville",
    "sg:classifiers":[
        {
            "category":"Personal",
            "type":"Services"
        }
    ],
    "sg:phone":"+1 502 493 2701",
    "sg:postcode":"40299",
    "sg:province":"KY",
    "sg:tags":[
        "control",
        "weight"
    ],
    "wof:name":"L A Weight Loss",
    "wof:placetype":"venue"
},
  "geometry": {"coordinates":[-85.58844000000001,38.213348],"type":"Point"}
}