{
  "type": "Feature",
  "properties": {
    "addr:full":"430 W Muhammad Ali Blvd Louisville KY 40202",
    "addr:housenumber":"430",
    "addr:postcode":"louisville;40202",
    "addr:street":"W Muhammad Ali Blvd",
    "iso:country":"US",
    "sg:address":"430 W Muhammad Ali Blvd",
    "sg:city":"Louisville",
    "sg:classifiers":[
        {
            "category":"Professional",
            "subcategory":"Accounting & Tax Preparation",
            "type":"Services"
        }
    ],
    "sg:phone":"+1 502 589 6326",
    "sg:postcode":"40202",
    "sg:province":"KY",
    "sg:tags":[
        "return",
        "filing"
    ],
    "wof:name":"Tax & Acctg Professionals Inc",
    "wof:placetype":"venue"
},
  "geometry": {"coordinates":[-85.75819799999999,38.251214],"type":"Point"}
}