{
  "type": "Feature",
  "properties": {
    "addr:full":"2250 Cane Valley Rd Columbia KY 42728",
    "addr:housenumber":"2250",
    "addr:postcode":"42728",
    "addr:street":"Cane Valley Rd",
    "iso:country":"US",
    "sg:address":"2250 Cane Valley Rd",
    "sg:city":"Columbia",
    "sg:classifiers":[
        {
            "category":"Organizations",
            "subcategory":"Religious Organization",
            "type":"Services"
        }
    ],
    "sg:phone":"+1 270 384 9271",
    "sg:postcode":"42728",
    "sg:province":"KY",
    "sg:tags":[
        "church"
    ],
    "wof:name":"Cane Valley Christian Church",
    "wof:placetype":"venue"
},
  "geometry": {"coordinates":[-85.318617,37.179664],"type":"Point"}
}