{
  "type": "Feature",
  "properties": {
    "addr:full":"2825 Dumesnil St Louisville KY 40211",
    "addr:housenumber":"2825",
    "addr:postcode":"40211",
    "addr:street":"Dumesnil St",
    "iso:country":"US",
    "sg:address":"2825 Dumesnil St",
    "sg:city":"Louisville",
    "sg:classifiers":[
        {
            "category":"Organizations",
            "subcategory":"Religious Organization",
            "type":"Services"
        }
    ],
    "sg:phone":"+1 502 778 5010",
    "sg:postcode":"40211",
    "sg:province":"KY",
    "sg:tags":[
        "church"
    ],
    "wof:name":"River Of Life Christian Church",
    "wof:placetype":"venue"
},
  "geometry": {"coordinates":[-85.801554,38.236938],"type":"Point"}
}