{
  "type": "Feature",
  "properties": {
    "iso:country":"US",
    "sg:address":"46 Choate Dr",
    "sg:city":"Wingo",
    "sg:classifiers":[
        {
            "category":"Wholesale",
            "subcategory":"Machinery & Supplies",
            "type":"Manufacturing & Wholesale Goods"
        }
    ],
    "sg:phone":"+1 270 376 2213",
    "sg:postcode":"42088",
    "sg:province":"KY",
    "sg:tags":[
        "dock",
        "loading",
        "equipment"
    ],
    "wof:name":"Hutchins Pallet Svc",
    "wof:placetype":"venue"
},
  "geometry": {"coordinates":[-88.73685,36.643914],"type":"Point"}
}