{
  "type": "Feature",
  "properties": {
    "iso:country":"US",
    "sg:address":"7900 Tanners Gate Ln",
    "sg:city":"Florence",
    "sg:classifiers":[
        {
            "category":"Freight",
            "type":"Transportation"
        }
    ],
    "sg:phone":"+1 859 283 1919",
    "sg:postcode":"41042",
    "sg:province":"KY",
    "wof:name":"MSA",
    "wof:placetype":"venue"
},
  "geometry": {"coordinates":[-84.64305899999999,38.995052],"type":"Point"}
}