{
  "type": "Feature",
  "properties": {
    "iso:country":"US",
    "sg:address":"86 Meyers St",
    "sg:city":"Hazel",
    "sg:classifiers":[
        {
            "category":"Wholesale",
            "subcategory":"Scrap",
            "type":"Manufacturing & Wholesale Goods"
        }
    ],
    "sg:phone":"+1 270 492 8183",
    "sg:postcode":"42049",
    "sg:province":"KY",
    "sg:tags":[
        "recycling",
        "center"
    ],
    "wof:name":"KGA Recycling",
    "wof:placetype":"venue"
},
  "geometry": {"coordinates":[-88.314121,36.517969],"type":"Point"}
}