{
  "type": "Feature",
  "properties": {
    "addr:full":"1015 W Lexington Ave Winchester KY 40391",
    "addr:housenumber":"1015",
    "addr:postcode":"40391",
    "addr:street":"W Lexington Ave",
    "iso:country":"US",
    "sg:address":"1015 W Lexington Ave",
    "sg:city":"Winchester",
    "sg:classifiers":[
        {
            "category":"Shopping",
            "subcategory":"Hobbies, Toys, & Games",
            "type":"Retail Goods"
        }
    ],
    "sg:phone":"+1 859 745 0064",
    "sg:postcode":"40391",
    "sg:province":"KY",
    "wof:name":"Butterflies Fine Arts & Crafts",
    "wof:placetype":"venue"
},
  "geometry": {"coordinates":[-84.194653,37.998831],"type":"Point"}
}