{
  "type": "Feature",
  "properties": {
    "iso:country":"US",
    "sg:address":"1277 Old Zion Church Rd",
    "sg:city":"Woodburn",
    "sg:classifiers":[
        {
            "category":"Farming",
            "subcategory":"Farm",
            "type":"Manufacturing & Wholesale Goods"
        }
    ],
    "sg:phone":"+1 270 529 3432",
    "sg:postcode":"42170",
    "sg:province":"KY",
    "sg:tags":[
        "crop",
        "general"
    ],
    "wof:name":"Hershel Sampson",
    "wof:placetype":"venue"
},
  "geometry": {"coordinates":[-86.560068,36.838011],"type":"Point"}
}