{
  "type": "Feature",
  "properties": {
    "addr:full":"413 Terrell Ridge Rd Willisburg KY 40078",
    "addr:housenumber":"413",
    "addr:postcode":"40078",
    "addr:street":"Terrell Ridge Rd",
    "iso:country":"US",
    "sg:address":"413 Terrell Ridge Rd",
    "sg:city":"Willisburg",
    "sg:classifiers":[
        {
            "category":"Wholesale",
            "subcategory":"Chemicals & Plastics",
            "type":"Manufacturing & Wholesale Goods"
        }
    ],
    "sg:phone":"+1 859 375 2421",
    "sg:postcode":"40078",
    "sg:province":"KY",
    "sg:tags":[
        "explosive"
    ],
    "wof:name":"Austin Powder Co",
    "wof:placetype":"venue"
},
  "geometry": {"coordinates":[-85.156142,37.878854],"type":"Point"}
}