{
  "type": "Feature",
  "properties": {
    "iso:country":"US",
    "sg:address":"4408 Abbott Grove Dr",
    "sg:city":"Crestwood",
    "sg:classifiers":[
        {
            "category":"Building & Trades",
            "subcategory":"Construction",
            "type":"Services"
        }
    ],
    "sg:phone":"+1 502 243 0243",
    "sg:postcode":"40014",
    "sg:province":"KY",
    "sg:tags":[
        "wallpaper"
    ],
    "wof:name":"Wallcare",
    "wof:placetype":"venue"
},
  "geometry": {"coordinates":[-85.438844,38.315763],"type":"Point"}
}