{
  "type": "Feature",
  "properties": {
    "addr:full":"14344 Walton-Verona Rd Verona KY 41092",
    "addr:housenumber":"14344",
    "addr:postcode":"41092",
    "addr:street":"Walton-Verona Rd",
    "iso:country":"US",
    "sg:address":"14344 Walton-Verona Rd",
    "sg:city":"Verona",
    "sg:classifiers":[
        {
            "category":"Building & Trades",
            "subcategory":"Plumbing",
            "type":"Services"
        }
    ],
    "sg:phone":"+1 859 485 7500",
    "sg:postcode":"41092",
    "sg:province":"KY",
    "sg:tags":[
        "heating",
        "contractor"
    ],
    "wof:name":"Blain Workman Htg & AC",
    "wof:placetype":"venue"
},
  "geometry": {"coordinates":[-84.647408,38.828326],"type":"Point"}
}