{
  "type": "Feature",
  "properties": {
    "addr:full":"901 Richmond Rd Irvine KY 40336",
    "addr:housenumber":"901",
    "addr:postcode":"40336",
    "addr:street":"Richmond Rd",
    "iso:country":"US",
    "sg:address":"901 Richmond Rd",
    "sg:city":"Irvine",
    "sg:classifiers":[
        {
            "category":"Restaurant",
            "type":"Food & Drink"
        }
    ],
    "sg:menulink":"http://www.allmenus.com/ky/red-lick/186839-mcdonalds/menu/",
    "sg:phone":"+1 606 723 1013",
    "sg:postcode":"40336",
    "sg:province":"KY",
    "sg:tags":[
        "burger",
        "american"
    ],
    "wof:name":"McDonald's",
    "wof:placetype":"venue"
},
  "geometry": {"coordinates":[-83.99325399999999,37.698998],"type":"Point"}
}