{
  "type": "Feature",
  "properties": {
    "addr:full":"633 Monmouth St Newport KY 41071",
    "addr:housenumber":"633",
    "addr:postcode":"41071",
    "addr:street":"Monmouth St",
    "iso:country":"US",
    "sg:address":"633 Monmouth St",
    "sg:city":"Newport",
    "sg:classifiers":[
        {
            "category":"Personal",
            "subcategory":"Beauty Salon",
            "type":"Services"
        }
    ],
    "sg:phone":"+1 859 261 8915",
    "sg:postcode":"41071",
    "sg:province":"KY",
    "sg:tags":[
        "shop",
        "manicuring"
    ],
    "wof:name":"City Nails",
    "wof:placetype":"venue"
},
  "geometry": {"coordinates":[-84.49261799999999,39.090762],"type":"Point"}
}