{
  "type": "Feature",
  "properties": {
    "addr:full":"125 Market St Maysville KY 41056",
    "addr:housenumber":"125",
    "addr:postcode":"41056",
    "addr:street":"Market St",
    "iso:country":"US",
    "sg:address":"125 Market St",
    "sg:city":"Maysville",
    "sg:classifiers":[
        {
            "category":"Insurance",
            "subcategory":"Insurance Agent",
            "type":"Services"
        }
    ],
    "sg:phone":"+1 606 564 6826",
    "sg:postcode":"41056",
    "sg:province":"KY",
    "wof:name":"Downing Insurance",
    "wof:placetype":"venue"
},
  "geometry": {"coordinates":[-83.76424799999999,38.648203],"type":"Point"}
}