{
  "type": "Feature",
  "properties": {
    "iso:country":"US",
    "sg:address":"1113 Aviation Blvd",
    "sg:city":"Hebron",
    "sg:classifiers":[
        {
            "category":"Freight",
            "type":"Transportation"
        }
    ],
    "sg:phone":"+1 859 689 5514",
    "sg:postcode":"41048",
    "sg:province":"KY",
    "sg:tags":[
        "storage"
    ],
    "wof:name":"Anex",
    "wof:placetype":"venue"
},
  "geometry": {"coordinates":[-84.676322,39.079815],"type":"Point"}
}