{
  "type": "Feature",
  "properties": {
    "addr:full":"708 Shelby St Junction City KY 40440",
    "addr:housenumber":"708",
    "addr:postcode":"40440",
    "addr:street":"Shelby St",
    "iso:country":"US",
    "sg:address":"708 Shelby St",
    "sg:city":"Junction City",
    "sg:classifiers":[
        {
            "category":"Restaurant",
            "type":"Food & Drink"
        }
    ],
    "sg:phone":"+1 859 854 9232",
    "sg:postcode":"40440",
    "sg:province":"KY",
    "wof:name":"Lovett's Restaurant",
    "wof:placetype":"venue"
},
  "geometry": {"coordinates":[-84.792368,37.585475],"type":"Point"}
}