{
  "type": "Feature",
  "properties": {
    "iso:country":"US",
    "sg:address":"1230 Waterworks Rd",
    "sg:city":"Danville",
    "sg:classifiers":[
        {
            "category":"Real Estate",
            "subcategory":"Surveying",
            "type":"Services"
        }
    ],
    "sg:phone":"+1 859 236 1438",
    "sg:postcode":"40422",
    "sg:province":"KY",
    "sg:tags":[
        "surveyor"
    ],
    "wof:name":"Lynch Surveying Inc",
    "wof:placetype":"venue"
},
  "geometry": {"coordinates":[-84.739739,37.680802],"type":"Point"}
}