{
  "type": "Feature",
  "properties": {
    "iso:country":"US",
    "sg:address":"610 S Lewis St",
    "sg:city":"Glasgow",
    "sg:classifiers":[
        {
            "category":"Home & Garden",
            "subcategory":"Furniture",
            "type":"Retail Goods"
        }
    ],
    "sg:phone":"+1 270 651 1505",
    "sg:postcode":"42141",
    "sg:province":"KY",
    "wof:name":"Furniture Outlet",
    "wof:placetype":"venue"
},
  "geometry": {"coordinates":[-85.913404,36.988781],"type":"Point"}
}