{
  "type": "Feature",
  "properties": {
    "iso:country":"US",
    "sg:address":"15390 Herndon Oak Grove Rd",
    "sg:city":"Oak Grove",
    "sg:phone":"+1 270 640 3528",
    "sg:postcode":"42262",
    "sg:province":"KY",
    "sg:tags":[
        "farm",
        "corn"
    ],
    "wof:name":"Mark Mills",
    "wof:placetype":"venue"
},
  "geometry": {"coordinates":[-87.520338,36.706938],"type":"Point"}
}