{
  "type": "Feature",
  "properties": {
    "addr:full":"521 W Short St Lexington KY 40507",
    "addr:housenumber":"521",
    "addr:postcode":"40507",
    "addr:street":"W Short St",
    "iso:country":"US",
    "sg:address":"521 W Short St",
    "sg:city":"Lexington",
    "sg:classifiers":[
        {
            "category":"Shopping",
            "subcategory":"Used Merchandise",
            "type":"Retail Goods"
        }
    ],
    "sg:phone":"+1 859 455 9660",
    "sg:postcode":"40507",
    "sg:province":"KY",
    "sg:tags":[
        "antique"
    ],
    "wof:name":"Greentree Antiques & Tearoom",
    "wof:placetype":"venue"
},
  "geometry": {"coordinates":[-84.500302,38.050513],"type":"Point"}
}