{
  "type": "Feature",
  "properties": {
    "iso:country":"US",
    "sg:address":"1034 Story Ave",
    "sg:city":"Louisville",
    "sg:classifiers":[
        {
            "category":"Building & Trades",
            "subcategory":"Construction",
            "type":"Services"
        }
    ],
    "sg:phone":"+1 502 587 1034",
    "sg:postcode":"40206",
    "sg:province":"KY",
    "sg:tags":[
        "roofing",
        "contractor"
    ],
    "sg:website":"www.steinrockroofing.com",
    "wof:name":"Steinrock Roofing & Sheet Inc",
    "wof:placetype":"venue"
},
  "geometry": {"coordinates":[-85.730452,38.254807],"type":"Point"}
}