{
  "type": "Feature",
  "properties": {
    "iso:country":"US",
    "sg:address":"617 Fairfield Ave",
    "sg:city":"Bellevue",
    "sg:classifiers":[
        {
            "category":"Personal",
            "subcategory":"Beauty Salon",
            "type":"Services"
        }
    ],
    "sg:phone":"+1 859 581 4700",
    "sg:postcode":"41073",
    "sg:province":"KY",
    "wof:name":"A New Look",
    "wof:placetype":"venue"
},
  "geometry": {"coordinates":[-84.480784,39.108421],"type":"Point"}
}