{
  "type": "Feature",
  "properties": {
    "iso:country":"US",
    "sg:address":"151 E Main St",
    "sg:city":"Morehead",
    "sg:classifiers":[
        {
            "category":"Wholesale",
            "subcategory":"Books, Periodicals, & Newspapers",
            "type":"Manufacturing & Wholesale Goods"
        },
        {
            "category":"Shopping",
            "subcategory":"Books",
            "type":"Retail Goods"
        }
    ],
    "sg:phone":"+1 606 784 4895",
    "sg:postcode":"40351",
    "sg:province":"KY",
    "sg:tags":[
        "dealer"
    ],
    "sg:website":"www.varsityeagle.com",
    "wof:name":"Varsity Eagle Inc",
    "wof:placetype":"venue"
},
  "geometry": {"coordinates":[-83.434276,38.182792],"type":"Point"}
}