{
  "type": "Feature",
  "properties": {
    "addr:full":"9316 Trenta Ln Louisville KY 40291",
    "addr:housenumber":"9316",
    "addr:postcode":"40291",
    "addr:street":"Trenta Ln",
    "iso:country":"US",
    "sg:address":"9316 Trenta Ln",
    "sg:city":"Louisville",
    "sg:classifiers":[
        {
            "category":"Building & Trades",
            "subcategory":"Landscaping Services",
            "type":"Services"
        }
    ],
    "sg:phone":"+1 502 939 4772",
    "sg:postcode":"40291",
    "sg:province":"KY",
    "sg:tags":[
        "lawn",
        "chimney"
    ],
    "wof:name":"Sullivans Lawnscaping",
    "wof:placetype":"venue"
},
  "geometry": {"coordinates":[-85.58788699999999,38.173662],"type":"Point"}
}