{
  "type": "Feature",
  "properties": {
    "iso:country":"US",
    "sg:address":"1222 Bates Ave",
    "sg:city":"Okolona",
    "sg:classifiers":[
        {
            "category":"Organizations",
            "subcategory":"Religious Organization",
            "type":"Services"
        }
    ],
    "sg:phone":"+1 502 966 2000",
    "sg:postcode":"40219",
    "sg:province":"KY",
    "sg:tags":[
        "church"
    ],
    "wof:name":"Okolona General Baptist Church",
    "wof:placetype":"venue"
},
  "geometry": {"coordinates":[-85.68668099999999,38.140844],"type":"Point"}
}