{
  "type": "Feature",
  "properties": {
    "iso:country":"US",
    "sg:address":"9826 State Hwy 945",
    "sg:city":"Boaz",
    "sg:classifiers":[
        {
            "category":"Personal",
            "type":"Services"
        }
    ],
    "sg:phone":"+1 270 856 3248",
    "sg:postcode":"42027",
    "sg:province":"KY",
    "wof:name":"Herbal Health",
    "wof:placetype":"venue"
},
  "geometry": {"coordinates":[-88.728003,36.929161],"type":"Point"}
}