{
  "type": "Feature",
  "properties": {
    "iso:country":"US",
    "sg:address":"130 Fairfax Ave",
    "sg:city":"Louisville",
    "sg:classifiers":[
        {
            "category":"Health Services",
            "subcategory":"Hospital",
            "type":"Services"
        },
        {
            "category":"Health Services",
            "subcategory":"Health Practitioner",
            "type":"Services"
        }
    ],
    "sg:phone":"+1 502 894 0100",
    "sg:postcode":"40207",
    "sg:province":"KY",
    "sg:tags":[
        "holistic",
        "sleep",
        "treatment",
        "disorders-information"
    ],
    "wof:name":"Center For Structural Int",
    "wof:placetype":"venue"
},
  "geometry": {"coordinates":[-85.65044899999999,38.251441],"type":"Point"}
}