{
  "type": "Feature",
  "properties": {
    "iso:country":"US",
    "sg:address":"5113 Madison Pike",
    "sg:city":"Independence",
    "sg:classifiers":[
        {
            "category":"Utilities",
            "type":"Services"
        }
    ],
    "sg:phone":"+1 859 363 8500",
    "sg:postcode":"41051",
    "sg:province":"KY",
    "sg:tags":[
        "sanitary"
    ],
    "wof:name":"All About Trees",
    "wof:placetype":"venue"
},
  "geometry": {"coordinates":[-84.541481,38.9537],"type":"Point"}
}