{
  "type": "Feature",
  "properties": {
    "iso:country":"US",
    "sg:address":"2303 Green Acres Dr",
    "sg:city":"Clarksville",
    "sg:classifiers":[
        {
            "category":"Retail",
            "subcategory":"Repair Shop",
            "type":"Services"
        }
    ],
    "sg:phone":"+1 931 431 5100",
    "sg:postcode":"37042",
    "sg:province":"KY",
    "wof:name":"Quality Mobile",
    "wof:placetype":"venue"
},
  "geometry": {"coordinates":[-87.42807000000001,36.638198],"type":"Point"}
}