{
  "type": "Feature",
  "properties": {
    "addr:full":"1026 Doriel Dr Covington KY 41017",
    "addr:housenumber":"1026",
    "addr:postcode":"41017",
    "addr:street":"Doriel Dr",
    "iso:country":"US",
    "sg:address":"1026 Doriel Dr",
    "sg:city":"Covington",
    "sg:classifiers":[
        {
            "category":"Wholesale",
            "subcategory":"Medical Equipment & Supplies",
            "type":"Manufacturing & Wholesale Goods"
        }
    ],
    "sg:phone":"+1 859 341 5677",
    "sg:postcode":"41017",
    "sg:province":"KY",
    "wof:name":"Nickel Medical Inc",
    "wof:placetype":"venue"
},
  "geometry": {"coordinates":[-84.586817,39.06897],"type":"Point"}
}