{
  "type": "Feature",
  "properties": {
    "iso:country":"US",
    "sg:address":"606 Henton St",
    "sg:city":"Livermore",
    "sg:classifiers":[
        {
            "category":"Autos & Motor Vehicles",
            "subcategory":"Auto Supplies",
            "type":"Retail Goods"
        }
    ],
    "sg:phone":"+1 270 278 9032",
    "sg:postcode":"42352",
    "sg:province":"KY",
    "sg:tags":[
        "automobile",
        "parts"
    ],
    "wof:name":"Livermore Auto Parts",
    "wof:placetype":"venue"
},
  "geometry": {"coordinates":[-87.126548,37.493038],"type":"Point"}
}