{
  "type": "Feature",
  "properties": {
    "addr:full":"1067 Quarry Rd Upton KY 42784",
    "addr:housenumber":"1067",
    "addr:postcode":"42784",
    "addr:street":"Quarry Rd",
    "iso:country":"US",
    "sg:address":"1067 Quarry Rd",
    "sg:city":"Upton",
    "sg:classifiers":[
        {
            "category":"Autos & Motor Vehicles",
            "subcategory":"Fuel & Gas Station",
            "type":"Retail Goods"
        }
    ],
    "sg:phone":"+1 270 369 8300",
    "sg:postcode":"42784",
    "sg:province":"KY",
    "sg:tags":[
        "station",
        "gasoline"
    ],
    "wof:name":"Hawkes Service Station",
    "wof:placetype":"venue"
},
  "geometry": {"coordinates":[-85.893348,37.436796],"type":"Point"}
}