{
  "type": "Feature",
  "properties": {
    "addr:full":"10312 Mayo Trail Rd Catlettsburg KY 41129",
    "addr:postcode":"10312;41129",
    "addr:street":"Mayo Trail Rd",
    "iso:country":"US",
    "sg:address":"10312 Mayo Trail Rd",
    "sg:city":"Catlettsburg",
    "sg:classifiers":[
        {
            "category":"Wholesale",
            "subcategory":"Electrical",
            "type":"Manufacturing & Wholesale Goods"
        }
    ],
    "sg:phone":"+1 606 739 4383",
    "sg:postcode":"41129",
    "sg:province":"KY",
    "sg:tags":[
        "fire",
        "equipment",
        "protection"
    ],
    "wof:name":"River Cities Fire Equipment",
    "wof:placetype":"venue"
},
  "geometry": {"coordinates":[-82.603622,38.393262],"type":"Point"}
}