{
  "type": "Feature",
  "properties": {
    "iso:country":"US",
    "sg:address":"501 Meriwether Ave",
    "sg:city":"Louisville",
    "sg:classifiers":[
        {
            "category":"Building & Trades",
            "subcategory":"Electrical",
            "type":"Services"
        }
    ],
    "sg:phone":"+1 502 895 5497",
    "sg:postcode":"40217",
    "sg:province":"KY",
    "sg:tags":[
        "industrial",
        "electrician",
        "contractors-commercial",
        "electric"
    ],
    "wof:name":"Windhorst Electric Co Inc",
    "wof:placetype":"venue"
},
  "geometry": {"coordinates":[-85.748909,38.225948],"type":"Point"}
}