{
  "type": "Feature",
  "properties": {
    "iso:country":"US",
    "sg:address":"3307 State Hwy 2385",
    "sg:city":"Sacramento",
    "sg:classifiers":[
        {
            "category":"Professional",
            "subcategory":"Research",
            "type":"Services"
        }
    ],
    "sg:phone":"+1 270 736 5903",
    "sg:postcode":"42372",
    "sg:province":"KY",
    "sg:tags":[
        "environmental",
        "ecological"
    ],
    "wof:name":"Geo-Pro",
    "wof:placetype":"venue"
},
  "geometry": {"coordinates":[-87.277568,37.458147],"type":"Point"}
}