{
  "type": "Feature",
  "properties": {
    "addr:full":"232 Mark Trl Bowling Green KY 42101",
    "addr:housenumber":"232",
    "addr:postcode":"42101",
    "addr:street":"Mark Trl",
    "iso:country":"US",
    "sg:address":"232 Mark Trl",
    "sg:city":"Bowling Green",
    "sg:classifiers":[
        {
            "category":"Retail",
            "subcategory":"Repair Shop",
            "type":"Services"
        }
    ],
    "sg:phone":"+1 270 842 1331",
    "sg:postcode":"42101",
    "sg:province":"KY",
    "sg:tags":[
        "scooter",
        "motorcycle",
        "motor"
    ],
    "wof:name":"Doug Burton Motor Cycle & Atv",
    "wof:placetype":"venue"
},
  "geometry": {"coordinates":[-86.508762,36.995564],"type":"Point"}
}