{
  "type": "Feature",
  "properties": {
    "iso:country":"US",
    "sg:address":"5993 Merchants St",
    "sg:city":"Florence",
    "sg:classifiers":[
        {
            "category":"Banks & Credit Unions",
            "subcategory":"Bank",
            "type":"Services"
        }
    ],
    "sg:phone":"+1 859 746 3888",
    "sg:postcode":"41042",
    "sg:province":"KY",
    "sg:website":"www.nationalcity.com",
    "wof:name":"National City Bank",
    "wof:placetype":"venue"
},
  "geometry": {"coordinates":[-84.657265,39.007238],"type":"Point"}
}