{
  "type": "Feature",
  "properties": {
    "iso:country":"US",
    "sg:address":"449 S 16th St",
    "sg:city":"Paducah",
    "sg:classifiers":[
        {
            "category":"Shopping",
            "subcategory":"Used Merchandise",
            "type":"Retail Goods"
        }
    ],
    "sg:phone":"+1 270 442 4246",
    "sg:postcode":"42003",
    "sg:province":"KY",
    "sg:tags":[
        "shop",
        "consignment"
    ],
    "wof:name":"K K's Attic",
    "wof:placetype":"venue"
},
  "geometry": {"coordinates":[-88.61321599999999,37.075481],"type":"Point"}
}