{
  "type": "Feature",
  "properties": {
    "iso:country":"US",
    "sg:address":"50 Victoria Dr",
    "sg:city":"Shelbyville",
    "sg:classifiers":[
        {
            "category":"Building & Trades",
            "subcategory":"Construction",
            "type":"Services"
        }
    ],
    "sg:phone":"+1 502 647 0042",
    "sg:postcode":"40065",
    "sg:province":"KY",
    "sg:tags":[
        "blacktopping"
    ],
    "wof:name":"Affordable Blacktop",
    "wof:placetype":"venue"
},
  "geometry": {"coordinates":[-85.25151,38.202034],"type":"Point"}
}