{
  "type": "Feature",
  "properties": {
    "addr:full":"106 W Woodford St Lawrenceburg KY 40342",
    "addr:housenumber":"106",
    "addr:postcode":"40342",
    "addr:street":"W Woodford St",
    "iso:country":"US",
    "sg:address":"106 W Woodford St",
    "sg:city":"Lawrenceburg",
    "sg:classifiers":[
        {
            "category":"Insurance",
            "subcategory":"Insurance Agent",
            "type":"Services"
        }
    ],
    "sg:phone":"+1 502 839 4251",
    "sg:postcode":"40342",
    "sg:province":"KY",
    "wof:name":"Humston Insurance",
    "wof:placetype":"venue"
},
  "geometry": {"coordinates":[-84.898453,38.036692],"type":"Point"}
}