{
  "type": "Feature",
  "properties": {
    "iso:country":"US",
    "sg:address":"2615 W Broadway",
    "sg:city":"Louisville",
    "sg:classifiers":[
        {
            "category":"Insurance",
            "subcategory":"Insurance Agent",
            "type":"Services"
        }
    ],
    "sg:phone":"+1 502 776 1155",
    "sg:postcode":"40211",
    "sg:province":"KY",
    "wof:name":"Charles Arnold Insurance",
    "wof:placetype":"venue"
},
  "geometry": {"coordinates":[-85.796364,38.24958],"type":"Point"}
}