{
  "type": "Feature",
  "properties": {
    "iso:country":"US",
    "sg:address":"1210 Winding Creek Pl",
    "sg:city":"Louisville",
    "sg:classifiers":[
        {
            "category":"Professional",
            "subcategory":"Detective & Security Services",
            "type":"Services"
        }
    ],
    "sg:phone":"+1 502 245 3649",
    "sg:postcode":"40245",
    "sg:province":"KY",
    "sg:tags":[
        "telecasting",
        "television",
        "systems-closed",
        "circuit"
    ],
    "wof:name":"Multiview Corp",
    "wof:placetype":"venue"
},
  "geometry": {"coordinates":[-85.492786,38.259924],"type":"Point"}
}