{
  "type": "Feature",
  "properties": {
    "iso:country":"US",
    "sg:address":"121 N Main St",
    "sg:city":"Henderson",
    "sg:classifiers":[
        {
            "category":"Shopping",
            "subcategory":"Jewelry",
            "type":"Retail Goods"
        }
    ],
    "sg:phone":"+1 270 827 5034",
    "sg:postcode":"42420",
    "sg:province":"KY",
    "sg:tags":[
        "jeweler"
    ],
    "wof:name":"Balfour Rings & Things",
    "wof:placetype":"venue"
},
  "geometry": {"coordinates":[-87.591802,37.840526],"type":"Point"}
}