{
  "type": "Feature",
  "properties": {
    "addr:full":"240 E Indian Stone Rd Shepherdsville KY 40165",
    "addr:housenumber":"240",
    "addr:postcode":"40165",
    "addr:street":"E Indian Stone Rd",
    "iso:country":"US",
    "sg:address":"240 E Indian Stone Rd",
    "sg:city":"Shepherdsville",
    "sg:classifiers":[
        {
            "category":"Building & Trades",
            "subcategory":"Landscaping Services",
            "type":"Services"
        }
    ],
    "sg:phone":"+1 502 543 5678",
    "sg:postcode":"40165",
    "sg:province":"KY",
    "wof:name":"Hunter Green Lawn Care",
    "wof:placetype":"venue"
},
  "geometry": {"coordinates":[-85.653901,37.96786],"type":"Point"}
}