{
  "type": "Feature",
  "properties": {
    "iso:country":"US",
    "sg:address":"3405 Robards Ct",
    "sg:city":"Louisville",
    "sg:classifiers":[
        {
            "category":"Building & Trades",
            "subcategory":"Plumbing",
            "type":"Services"
        }
    ],
    "sg:phone":"+1 502 363 2654",
    "sg:postcode":"40218",
    "sg:province":"KY",
    "sg:tags":[
        "sheet",
        "work",
        "metal",
        "contractor"
    ],
    "sg:website":"www.comfortsystemsusa.com",
    "wof:name":"J & J Mechanical Inc",
    "wof:placetype":"venue"
},
  "geometry": {"coordinates":[-85.69588299999999,38.192922],"type":"Point"}
}