{
  "type": "Feature",
  "properties": {
    "addr:full":"2845 Coral Hill Rd Glasgow KY 42141",
    "addr:housenumber":"2845",
    "addr:postcode":"42141",
    "addr:street":"Coral Hill Rd",
    "iso:country":"US",
    "sg:address":"2845 Coral Hill Rd",
    "sg:city":"Glasgow",
    "sg:classifiers":[
        {
            "category":"Building & Trades",
            "subcategory":"Construction",
            "type":"Services"
        }
    ],
    "sg:phone":"+1 270 453 3457",
    "sg:postcode":"42141",
    "sg:province":"KY",
    "sg:tags":[
        "excavating",
        "contractor"
    ],
    "wof:name":"Likens Back Hoe Svc",
    "wof:placetype":"venue"
},
  "geometry": {"coordinates":[-85.859283,37.045186],"type":"Point"}
}