{
  "type": "Feature",
  "properties": {
    "iso:country":"US",
    "sg:address":"2029 Alexandria Pike",
    "sg:city":"Newport",
    "sg:classifiers":[
        {
            "category":"Retail",
            "subcategory":"Auto Repair",
            "type":"Services"
        }
    ],
    "sg:phone":"+1 859 781 0848",
    "sg:postcode":"41076",
    "sg:province":"KY",
    "wof:name":"Bud's J & M Service Inc",
    "wof:placetype":"venue"
},
  "geometry": {"coordinates":[-84.445503,39.0452],"type":"Point"}
}