{
  "type": "Feature",
  "properties": {
    "iso:country":"US",
    "sg:address":"751 State Hwy 1729",
    "sg:city":"Russell Springs",
    "sg:classifiers":[
        {
            "category":"Manufacturing",
            "subcategory":"Tools & Machinery",
            "type":"Manufacturing & Wholesale Goods"
        }
    ],
    "sg:phone":"+1 270 866 5784",
    "sg:postcode":"42642",
    "sg:province":"KY",
    "sg:tags":[
        "machine",
        "shop"
    ],
    "wof:name":"Frost Machine Shop",
    "wof:placetype":"venue"
},
  "geometry": {"coordinates":[-85.102808,37.075525],"type":"Point"}
}