{
  "type": "Feature",
  "properties": {
    "iso:country":"US",
    "sg:address":"206 Ruoff Dr",
    "sg:city":"Paducah",
    "sg:classifiers":[
        {
            "category":"Building & Trades",
            "subcategory":"Construction",
            "type":"Services"
        }
    ],
    "sg:phone":"+1 270 554 7204",
    "sg:postcode":"42003",
    "sg:province":"KY",
    "sg:tags":[
        "general",
        "contractor"
    ],
    "wof:name":"Brad Davis Construction Co",
    "wof:placetype":"venue"
},
  "geometry": {"coordinates":[-88.509185,37.019819],"type":"Point"}
}