{
  "type": "Feature",
  "properties": {
    "addr:full":"2424 Concord Dr Louisville KY 40217",
    "addr:housenumber":"2424",
    "addr:postcode":"40217",
    "addr:street":"Concord Dr",
    "iso:country":"US",
    "sg:address":"2424 Concord Dr",
    "sg:city":"Louisville",
    "sg:classifiers":[
        {
            "category":"Professional",
            "subcategory":"Lawyer & Legal Services",
            "type":"Services"
        }
    ],
    "sg:phone":"+1 502 637 6157",
    "sg:postcode":"40217",
    "sg:province":"KY",
    "wof:name":"Catherine M Ward",
    "wof:placetype":"venue"
},
  "geometry": {"coordinates":[-85.749065,38.20946],"type":"Point"}
}