{
  "type": "Feature",
  "properties": {
    "iso:country":"US",
    "sg:address":"330 Tanglewood Dr",
    "sg:city":"Science Hill",
    "sg:classifiers":[
        {
            "category":"Organizations",
            "subcategory":"Religious Organization",
            "type":"Services"
        }
    ],
    "sg:phone":"+1 606 423 5145",
    "sg:postcode":"42553",
    "sg:province":"KY",
    "sg:tags":[
        "clergy"
    ],
    "wof:name":"Benny Hatfield",
    "wof:placetype":"venue"
},
  "geometry": {"coordinates":[-84.62074200000001,37.183344],"type":"Point"}
}