{
  "type": "Feature",
  "properties": {
    "iso:country":"US",
    "sg:address":"2475 Shumate Rd",
    "sg:city":"Ekron",
    "sg:classifiers":[
        {
            "category":"Building & Trades",
            "subcategory":"Landscaping Services",
            "type":"Services"
        }
    ],
    "sg:phone":"+1 270 828 4160",
    "sg:postcode":"40117",
    "sg:province":"KY",
    "sg:tags":[
        "landscape",
        "contractor"
    ],
    "wof:name":"Gogol Landscaping",
    "wof:placetype":"venue"
},
  "geometry": {"coordinates":[-86.153288,37.910752],"type":"Point"}
}