{
  "type": "Feature",
  "properties": {
    "iso:country":"US",
    "sg:address":"600 W 3rd St",
    "sg:city":"Owensboro",
    "sg:classifiers":[
        {
            "category":"Professional",
            "subcategory":"Business Services",
            "type":"Services"
        }
    ],
    "sg:phone":"+1 270 684 9569",
    "sg:postcode":"42301",
    "sg:province":"KY",
    "sg:tags":[
        "recording",
        "studio"
    ],
    "wof:name":"Sunlite Studios",
    "wof:placetype":"venue"
},
  "geometry": {"coordinates":[-87.11809,37.773373],"type":"Point"}
}