{
  "type": "Feature",
  "properties": {
    "addr:full":"2 Highway Ave Ludlow KY 41016",
    "addr:housenumber":"2",
    "addr:postcode":"41016",
    "addr:street":"Highway Ave",
    "iso:country":"US",
    "sg:address":"2 Highway Ave",
    "sg:city":"Ludlow",
    "sg:classifiers":[
        {
            "category":"Building & Trades",
            "subcategory":"Construction",
            "type":"Services"
        }
    ],
    "sg:phone":"+1 859 491 8400",
    "sg:postcode":"41016",
    "sg:province":"KY",
    "sg:tags":[
        "general",
        "contractor"
    ],
    "wof:name":"Beckman Construction Inc",
    "wof:placetype":"venue"
},
  "geometry": {"coordinates":[-84.541872,39.095062],"type":"Point"}
}