{
  "type": "Feature",
  "properties": {
    "iso:country":"US",
    "sg:address":"6510 State Hwy 56",
    "sg:city":"Owensboro",
    "sg:classifiers":[
        {
            "category":"Building & Trades",
            "subcategory":"Construction",
            "type":"Services"
        }
    ],
    "sg:phone":"+1 270 771 4999",
    "sg:postcode":"42301",
    "sg:province":"KY",
    "sg:tags":[
        "home",
        "builder"
    ],
    "wof:name":"J D's Hammer",
    "wof:placetype":"venue"
},
  "geometry": {"coordinates":[-87.232772,37.757339],"type":"Point"}
}