{
  "type": "Feature",
  "properties": {
    "iso:country":"US",
    "sg:address":"12484 US Hwy 60",
    "sg:city":"Ashland",
    "sg:classifiers":[
        {
            "category":"Autos & Motor Vehicles",
            "subcategory":"Automobile Sales",
            "type":"Retail Goods"
        }
    ],
    "sg:phone":"+1 606 928 4872",
    "sg:postcode":"41102",
    "sg:province":"KY",
    "sg:tags":[
        "car",
        "dealer"
    ],
    "wof:name":"Deluxe Auto Sales",
    "wof:placetype":"venue"
},
  "geometry": {"coordinates":[-82.715075,38.38924],"type":"Point"}
}