{
  "type": "Feature",
  "properties": {
    "iso:country":"US",
    "sg:address":"8201 Port Royal Rd",
    "sg:city":"Port Royal",
    "sg:classifiers":[
        {
            "category":"Wholesale",
            "subcategory":"Farm Supplies",
            "type":"Manufacturing & Wholesale Goods"
        }
    ],
    "sg:phone":"+1 502 947 5160",
    "sg:postcode":"40075",
    "sg:province":"KY",
    "sg:tags":[
        "fertilizer"
    ],
    "wof:name":"Hawkins Farm Ctr Inc",
    "wof:placetype":"venue"
},
  "geometry": {"coordinates":[-85.086276,38.552534],"type":"Point"}
}