{
  "type": "Feature",
  "properties": {
    "iso:country":"US",
    "sg:address":"9217 US Hwy 42",
    "sg:city":"Prospect",
    "sg:classifiers":[
        {
            "category":"Health Services",
            "subcategory":"Doctor",
            "type":"Services"
        }
    ],
    "sg:phone":"+1 502 228 2709",
    "sg:postcode":"40059",
    "sg:province":"KY",
    "sg:tags":[
        "dentist"
    ],
    "wof:name":"Mortenson Family Dental Ctr",
    "wof:placetype":"venue"
},
  "geometry": {"coordinates":[-85.618898,38.340357],"type":"Point"}
}