{
  "type": "Feature",
  "properties": {
    "addr:full":"9750 Lebanon Rd Parksville KY 40464",
    "addr:housenumber":"9750",
    "addr:postcode":"40464",
    "addr:street":"Lebanon Rd",
    "iso:country":"US",
    "sg:address":"9750 Lebanon Rd",
    "sg:city":"Parksville",
    "sg:classifiers":[
        {
            "category":"Retail",
            "subcategory":"Repair Shop",
            "type":"Services"
        }
    ],
    "sg:phone":"+1 859 854 0111",
    "sg:postcode":"40464",
    "sg:province":"KY",
    "sg:tags":[
        "related"
    ],
    "wof:name":"Blue Grass Bath Tub Repair",
    "wof:placetype":"venue"
},
  "geometry": {"coordinates":[-84.926946,37.596506],"type":"Point"}
}