{
  "type": "Feature",
  "properties": {
    "addr:full":"177 Burt Rd Lexington KY 40503",
    "addr:housenumber":"177",
    "addr:postcode":"40503",
    "addr:street":"Burt Rd",
    "iso:country":"US",
    "sg:address":"177 Burt Rd",
    "sg:city":"Lexington",
    "sg:classifiers":[
        {
            "category":"Health Services",
            "subcategory":"Doctor",
            "type":"Services"
        },
        {
            "category":"Personal",
            "subcategory":"Hair Removal",
            "type":"Services"
        },
        {
            "category":"Personal",
            "subcategory":"Skin Care",
            "type":"Services"
        }
    ],
    "sg:phone":"+1 859 276 2556",
    "sg:postcode":"40503",
    "sg:province":"KY",
    "sg:tags":[
        "physician",
        "reconstructive",
        "surgeons",
        "cosmetic",
        "plastic",
        "surgery",
        "surgeon",
        "surgery-general"
    ],
    "sg:website":"http://www.lexingtoncsc.com",
    "wof:name":"Cosmetic Surgery Center",
    "wof:placetype":"venue"
},
  "geometry": {"coordinates":[-84.519901,38.007646],"type":"Point"}
}