{
  "type": "Feature",
  "properties": {
    "addr:full":"4588 Kellogg Ave Cincinnati OH 45226",
    "addr:housenumber":"4588",
    "addr:postcode":"45226",
    "addr:street":"Kellogg Ave",
    "iso:country":"US",
    "sg:address":"4588 Kellogg Ave",
    "sg:city":"Cincinnati",
    "sg:classifiers":[
        {
            "category":"Wholesale",
            "subcategory":"Auto Parts",
            "type":"Manufacturing & Wholesale Goods"
        }
    ],
    "sg:phone":"+1 513 321 5748",
    "sg:postcode":"45226",
    "sg:province":"OH",
    "sg:tags":[
        "automobile",
        "rebuilt",
        "used"
    ],
    "wof:name":"Bob's Used Auto Parts",
    "wof:placetype":"venue"
},
  "geometry": {"coordinates":[-84.429897,39.097144],"type":"Point"}
}