{
  "type": "Feature",
  "properties": {
    "addr:full":"8089 State Hwy 416 Robards KY 42452",
    "addr:housenumber":"8089",
    "addr:postcode":"42452",
    "addr:street":"State Hwy 416",
    "iso:country":"US",
    "sg:address":"8089 State Hwy 416",
    "sg:city":"Robards",
    "sg:classifiers":[
        {
            "category":"Organizations",
            "subcategory":"Religious Organization",
            "type":"Services"
        }
    ],
    "sg:phone":"+1 270 521 7028",
    "sg:postcode":"42452",
    "sg:province":"KY",
    "sg:tags":[
        "church"
    ],
    "wof:name":"Robards Baptist Church",
    "wof:placetype":"venue"
},
  "geometry": {"coordinates":[-87.549972,37.673398],"type":"Point"}
}