{
  "type": "Feature",
  "properties": {
    "iso:country":"US",
    "sg:address":"1891 Parkers Mill Rd",
    "sg:city":"Lexington",
    "sg:classifiers":[
        {
            "category":"Organizations",
            "subcategory":"Religious Organization",
            "type":"Services"
        }
    ],
    "sg:phone":"+1 859 255 4987",
    "sg:postcode":"40504",
    "sg:province":"KY",
    "sg:tags":[
        "church"
    ],
    "wof:name":"St Raphael's Episcopal Church",
    "wof:placetype":"venue"
},
  "geometry": {"coordinates":[-84.560464,38.039229],"type":"Point"}
}