{
  "type": "Feature",
  "properties": {
    "addr:full":"426 W 4th St London KY 40741",
    "addr:housenumber":"426",
    "addr:postcode":"40741",
    "addr:street":"W 4Th St",
    "iso:country":"US",
    "sg:address":"426 W 4th St",
    "sg:city":"London",
    "sg:classifiers":[
        {
            "category":"Shopping",
            "subcategory":"Clothing, Apparel, & Fashions",
            "type":"Retail Goods"
        }
    ],
    "sg:phone":"+1 606 864 2156",
    "sg:postcode":"40741",
    "sg:province":"KY",
    "sg:tags":[
        "uniform",
        "supply"
    ],
    "sg:website":"www.coyne.textileservices.com",
    "wof:name":"Coyne Textile Svc",
    "wof:placetype":"venue"
},
  "geometry": {"coordinates":[-84.085497,37.126815],"type":"Point"}
}