{
  "type": "Feature",
  "properties": {
    "iso:country":"US",
    "sg:address":"2600 Allen Ln",
    "sg:city":"La Grange",
    "sg:classifiers":[
        {
            "category":"Wholesale",
            "subcategory":"Machinery & Supplies",
            "type":"Manufacturing & Wholesale Goods"
        }
    ],
    "sg:phone":"+1 502 222 5859",
    "sg:postcode":"40031",
    "sg:province":"KY",
    "sg:tags":[
        "trailer"
    ],
    "wof:name":"Lakeview Truck & Trailer Sales",
    "wof:placetype":"venue"
},
  "geometry": {"coordinates":[-85.394249,38.392626],"type":"Point"}
}