{
  "type": "Feature",
  "properties": {
    "addr:full":"2410 Ampere Dr Jeffersontown KY 40299",
    "addr:housenumber":"2410",
    "addr:postcode":"40299",
    "addr:street":"Ampere Dr",
    "iso:country":"US",
    "sg:address":"2410 Ampere Dr",
    "sg:city":"Jeffersontown",
    "sg:classifiers":[
        {
            "category":"Retail",
            "subcategory":"Auto Repair",
            "type":"Services"
        }
    ],
    "sg:phone":"+1 502 266 5795",
    "sg:postcode":"40299",
    "sg:province":"KY",
    "sg:tags":[
        "automobile",
        "testing",
        "emission"
    ],
    "sg:website":"www.gordon-darby.com",
    "wof:name":"Gordon-Darby Inc",
    "wof:placetype":"venue"
},
  "geometry": {"coordinates":[-85.549954,38.203054],"type":"Point"}
}