{
  "type": "Feature",
  "properties": {
    "iso:country":"US",
    "sg:address":"33 3rd Ave SW",
    "sg:city":"Calvert City",
    "sg:classifiers":[
        {
            "category":"Retail",
            "subcategory":"Auto Repair",
            "type":"Services"
        }
    ],
    "sg:phone":"+1 270 395 7524",
    "sg:postcode":"42029",
    "sg:province":"KY",
    "sg:tags":[
        "wheel",
        "axle",
        "alignment"
    ],
    "wof:name":"Lee's Alignment & Exhaust Ctr",
    "wof:placetype":"venue"
},
  "geometry": {"coordinates":[-88.352547,37.028985],"type":"Point"}
}