{
  "type": "Feature",
  "properties": {
    "iso:country":"US",
    "sg:address":"3914 Blackburn Ave",
    "sg:city":"Ashland",
    "sg:classifiers":[
        {
            "category":"Personal",
            "subcategory":"Beauty Salon",
            "type":"Services"
        }
    ],
    "sg:phone":"+1 606 325 1717",
    "sg:postcode":"41101",
    "sg:province":"KY",
    "sg:tags":[
        "shop"
    ],
    "wof:name":"C & M Appliance Service",
    "wof:placetype":"venue"
},
  "geometry": {"coordinates":[-82.634196,38.451923],"type":"Point"}
}