{
  "type": "Feature",
  "properties": {
    "iso:country":"US",
    "sg:address":"3304 Springstead Cir",
    "sg:city":"Louisville",
    "sg:classifiers":[
        {
            "category":"Professional",
            "subcategory":"Management & Consulting",
            "type":"Services"
        }
    ],
    "sg:phone":"+1 502 426 6037",
    "sg:postcode":"40241",
    "sg:province":"KY",
    "sg:tags":[
        "business"
    ],
    "wof:name":"J&C & Assoc LLC",
    "wof:placetype":"venue"
},
  "geometry": {"coordinates":[-85.576667,38.29346],"type":"Point"}
}