{
  "type": "Feature",
  "properties": {
    "iso:country":"US",
    "sg:address":"954 E Kentucky St Ste 3",
    "sg:city":"Louisville",
    "sg:classifiers":[
        {
            "category":"Health Services",
            "subcategory":"Doctor",
            "type":"Services"
        }
    ],
    "sg:phone":"+1 888 349 6767",
    "sg:postcode":"40204",
    "sg:province":"KY",
    "sg:tags":[
        "medicine",
        "physician",
        "forensic",
        "surgeons"
    ],
    "wof:name":"Ac Forensics, Inc.",
    "wof:placetype":"venue"
},
  "geometry": {"coordinates":[-85.738371,38.236137],"type":"Point"}
}