{
  "type": "Feature",
  "properties": {
    "addr:full":"609 Clear Springs Rd Columbia KY 42728",
    "addr:housenumber":"609",
    "addr:postcode":"42728",
    "addr:street":"Clear Springs Rd",
    "iso:country":"US",
    "sg:address":"609 Clear Springs Rd",
    "sg:city":"Columbia",
    "sg:classifiers":[
        {
            "category":"Shopping",
            "subcategory":"Bicycles & Sporting Goods",
            "type":"Retail Goods"
        }
    ],
    "sg:phone":"+1 270 384 2653",
    "sg:postcode":"42728",
    "sg:province":"KY",
    "sg:tags":[
        "gun",
        "gunsmith"
    ],
    "wof:name":"Bill's Gun Shop",
    "wof:placetype":"venue"
},
  "geometry": {"coordinates":[-85.21620799999999,37.079829],"type":"Point"}
}