{
  "type": "Feature",
  "properties": {
    "iso:country":"US",
    "sg:address":"4701 State Hwy 1694",
    "sg:city":"Goshen",
    "sg:classifiers":[
        {
            "category":"Sports & Exercise",
            "subcategory":"Race Track",
            "type":"Entertainment"
        }
    ],
    "sg:phone":"+1 502 241 8071",
    "sg:postcode":"40026",
    "sg:province":"KY",
    "wof:name":"Smithwick Racing",
    "wof:placetype":"venue"
},
  "geometry": {"coordinates":[-85.526262,38.413545],"type":"Point"}
}