{
  "type": "Feature",
  "properties": {
    "iso:country":"US",
    "sg:address":"1164 Woodbridge Dr",
    "sg:city":"Clarksville",
    "sg:classifiers":[
        {
            "category":"Personal",
            "type":"Services"
        }
    ],
    "sg:phone":"+1 931 645 4493",
    "sg:postcode":"37042",
    "sg:province":"KY",
    "wof:name":"L & S Elegant Wedding",
    "wof:placetype":"venue"
},
  "geometry": {"coordinates":[-87.39325100000001,36.580201],"type":"Point"}
}