{
  "type": "Feature",
  "properties": {
    "addr:full":"654 Highland Ave Fort Thomas KY 41075",
    "addr:housenumber":"654",
    "addr:postcode":"41075",
    "addr:street":"Highland Ave",
    "iso:country":"US",
    "sg:address":"654 Highland Ave",
    "sg:city":"Fort Thomas",
    "sg:classifiers":[
        {
            "category":"Communications",
            "subcategory":"Newspaper",
            "type":"Services"
        }
    ],
    "sg:phone":"+1 859 781 4421",
    "sg:postcode":"41075",
    "sg:province":"KY",
    "sg:tags":[
        "print",
        "medium"
    ],
    "wof:name":"Community Recorder",
    "wof:placetype":"venue"
},
  "geometry": {"coordinates":[-84.46142,39.075766],"type":"Point"}
}