{
  "type": "Feature",
  "properties": {
    "addr:full":"302 Morentown Rd London KY 40741",
    "addr:housenumber":"302",
    "addr:postcode":"40741",
    "addr:street":"Morentown Rd",
    "iso:country":"US",
    "sg:address":"302 Morentown Rd",
    "sg:city":"London",
    "sg:classifiers":[
        {
            "category":"Retail",
            "subcategory":"Auto Repair",
            "type":"Services"
        }
    ],
    "sg:phone":"+1 606 864 2217",
    "sg:postcode":"40741",
    "sg:province":"KY",
    "sg:tags":[
        "general"
    ],
    "wof:name":"Hollywoods Bug Shop",
    "wof:placetype":"venue"
},
  "geometry": {"coordinates":[-84.086947,37.145125],"type":"Point"}
}