{
  "type": "Feature",
  "properties": {
    "addr:full":"3412 Baker St Erlanger KY 41018",
    "addr:housenumber":"3412",
    "addr:postcode":"41018",
    "addr:street":"Baker St",
    "iso:country":"US",
    "sg:address":"3412 Baker St",
    "sg:city":"Erlanger",
    "sg:classifiers":[
        {
            "category":"Insurance",
            "subcategory":"Insurance Agent",
            "type":"Services"
        }
    ],
    "sg:phone":"+1 859 727 7000",
    "sg:postcode":"41018",
    "sg:province":"KY",
    "wof:name":"Jubilee Products",
    "wof:placetype":"venue"
},
  "geometry": {"coordinates":[-84.60666399999999,39.023641],"type":"Point"}
}