{
  "type": "Feature",
  "properties": {
    "iso:country":"US",
    "sg:address":"700 Main St",
    "sg:city":"Elsmere",
    "sg:classifiers":[
        {
            "category":"Building & Trades",
            "subcategory":"Landscaping Services",
            "type":"Services"
        }
    ],
    "sg:phone":"+1 859 342 5800",
    "sg:postcode":"41018",
    "sg:province":"KY",
    "sg:tags":[
        "lawn",
        "maintenance",
        "grounds"
    ],
    "wof:name":"Master Care",
    "wof:placetype":"venue"
},
  "geometry": {"coordinates":[-84.602997,39.004917],"type":"Point"}
}