{
  "type": "Feature",
  "properties": {
    "addr:full":"905 Lily Dr Lexington KY 40504",
    "addr:housenumber":"905",
    "addr:postcode":"40504",
    "addr:street":"Lily Dr",
    "iso:country":"US",
    "sg:address":"905 Lily Dr",
    "sg:city":"Lexington",
    "sg:classifiers":[
        {
            "category":"Shopping",
            "type":"Retail Goods"
        }
    ],
    "sg:phone":"+1 859 229 1867",
    "sg:postcode":"40504",
    "sg:province":"KY",
    "sg:tags":[
        "merchandise"
    ],
    "wof:name":"Mobility Specialist",
    "wof:placetype":"venue"
},
  "geometry": {"coordinates":[-84.553425,38.024769],"type":"Point"}
}