{
  "type": "Feature",
  "properties": {
    "addr:full":"6125 Brandenburg Rd Ekron KY 40117",
    "addr:housenumber":"6125",
    "addr:postcode":"40117",
    "addr:street":"Brandenburg Rd",
    "iso:country":"US",
    "sg:address":"6125 Brandenburg Rd",
    "sg:city":"Ekron",
    "sg:classifiers":[
        {
            "category":"Real Estate",
            "subcategory":"Real Estate Operator",
            "type":"Services"
        }
    ],
    "sg:phone":"+1 270 828 3334",
    "sg:postcode":"40117",
    "sg:province":"KY",
    "sg:tags":[
        "apartment"
    ],
    "wof:name":"Barr Apartments",
    "wof:placetype":"venue"
},
  "geometry": {"coordinates":[-86.130737,37.922548],"type":"Point"}
}