{
  "type": "Feature",
  "properties": {
    "iso:country":"US",
    "sg:address":"8460 US Hwy 42",
    "sg:city":"Florence",
    "sg:classifiers":[
        {
            "category":"Banks & Credit Unions",
            "subcategory":"Bank",
            "type":"Services"
        }
    ],
    "sg:phone":"+1 859 746 2340",
    "sg:postcode":"41042",
    "sg:province":"KY",
    "sg:tags":[
        "financing"
    ],
    "wof:name":"Washington Mutual Finance",
    "wof:placetype":"venue"
},
  "geometry": {"coordinates":[-84.65784499999999,38.977523],"type":"Point"}
}