{
  "type": "Feature",
  "properties": {
    "iso:country":"US",
    "sg:address":"630 Kentucky Ave",
    "sg:city":"Pineville",
    "sg:classifiers":[
        {
            "category":"Professional",
            "type":"Services"
        }
    ],
    "sg:phone":"+1 606 337 8135",
    "sg:postcode":"40977",
    "sg:province":"KY",
    "sg:tags":[
        "establishment"
    ],
    "wof:name":"CPMC",
    "wof:placetype":"venue"
},
  "geometry": {"coordinates":[-83.702237,36.763662],"type":"Point"}
}