{
  "type": "Feature",
  "properties": {
    "addr:full":"332 S Mayo Trl Pikeville KY 41501",
    "addr:housenumber":"332",
    "addr:postcode":"41501",
    "addr:street":"S Mayo Trl",
    "iso:country":"US",
    "sg:address":"332 S Mayo Trl",
    "sg:city":"Pikeville",
    "sg:classifiers":[
        {
            "category":"Autos & Motor Vehicles",
            "subcategory":"Auto Supplies",
            "type":"Retail Goods"
        }
    ],
    "sg:phone":"+1 606 432 0131",
    "sg:postcode":"41501",
    "sg:province":"KY",
    "sg:tags":[
        "tire"
    ],
    "wof:name":"Appalachian Tire Products Inc",
    "wof:placetype":"venue"
},
  "geometry": {"coordinates":[-82.532853,37.467666],"type":"Point"}
}