{
  "type": "Feature",
  "properties": {
    "iso:country":"US",
    "sg:address":"3940 Bardstown Rd",
    "sg:city":"Louisville",
    "sg:classifiers":[
        {
            "category":"Manufacturing",
            "subcategory":"Metals",
            "type":"Manufacturing & Wholesale Goods"
        }
    ],
    "sg:phone":"+1 502 491 8517",
    "sg:postcode":"40218",
    "sg:province":"KY",
    "sg:tags":[
        "firearm"
    ],
    "wof:name":"Atf Defense Svc",
    "wof:placetype":"venue"
},
  "geometry": {"coordinates":[-85.650272,38.193849],"type":"Point"}
}