{
  "type": "Feature",
  "properties": {
    "addr:full":"910 Main St Benton KY 42025",
    "addr:housenumber":"910",
    "addr:postcode":"42025",
    "addr:street":"Main St",
    "iso:country":"US",
    "sg:address":"910 Main St",
    "sg:city":"Benton",
    "sg:classifiers":[
        {
            "category":"Organizations",
            "subcategory":"Religious Organization",
            "type":"Services"
        }
    ],
    "sg:phone":"+1 270 527 7575",
    "sg:postcode":"42025",
    "sg:province":"KY",
    "sg:tags":[
        "church"
    ],
    "sg:website":"www.bentonkyfbc.org",
    "wof:name":"First Baptist Church",
    "wof:placetype":"venue"
},
  "geometry": {"coordinates":[-88.35082,36.860012],"type":"Point"}
}