{
  "type": "Feature",
  "properties": {
    "addr:full":"701 Greenlawn Ave Bowling Green KY 42103",
    "addr:housenumber":"701",
    "addr:postcode":"42103",
    "addr:street":"Greenlawn Ave",
    "iso:country":"US",
    "sg:address":"701 Greenlawn Ave",
    "sg:city":"Bowling Green",
    "sg:phone":"+1 270 842 5450",
    "sg:postcode":"42103",
    "sg:province":"KY",
    "sg:tags":[
        "farm",
        "tobacco"
    ],
    "wof:name":"Larry Hays",
    "wof:placetype":"venue"
},
  "geometry": {"coordinates":[-86.421853,36.988378],"type":"Point"}
}