{
  "type": "Feature",
  "properties": {
    "iso:country":"US",
    "sg:address":"800 Stone Creek Pkwy",
    "sg:city":"Louisville",
    "sg:classifiers":[
        {
            "category":"Professional",
            "subcategory":"Lawyer & Legal Services",
            "type":"Services"
        }
    ],
    "sg:phone":"+1 502 429 9250",
    "sg:postcode":"40223",
    "sg:province":"KY",
    "sg:tags":[
        "attorney"
    ],
    "wof:name":"O'Bryan Brown & Toner",
    "wof:placetype":"venue"
},
  "geometry": {"coordinates":[-85.574257,38.233973],"type":"Point"}
}