{
  "type": "Feature",
  "properties": {
    "addr:full":"940 Happy Valley Rd Glasgow KY 42141",
    "addr:housenumber":"940",
    "addr:postcode":"42141",
    "addr:street":"Happy Valley Rd",
    "iso:country":"US",
    "sg:address":"940 Happy Valley Rd",
    "sg:city":"Glasgow",
    "sg:classifiers":[
        {
            "category":"Real Estate",
            "subcategory":"Real Estate Agent",
            "type":"Services"
        }
    ],
    "sg:phone":"+1 270 659 0550",
    "sg:postcode":"42141",
    "sg:province":"KY",
    "sg:tags":[
        "agency",
        "rental"
    ],
    "wof:name":"Colorama Rental Ctr",
    "wof:placetype":"venue"
},
  "geometry": {"coordinates":[-85.924712,37.011509],"type":"Point"}
}