{
  "type": "Feature",
  "properties": {
    "addr:full":"3410 Burkland Blvd Shepherdsville KY 40165",
    "addr:housenumber":"3410",
    "addr:postcode":"40165",
    "addr:street":"Burkland Blvd",
    "iso:country":"US",
    "sg:address":"3410 Burkland Blvd",
    "sg:city":"Shepherdsville",
    "sg:classifiers":[
        {
            "category":"Freight",
            "type":"Transportation"
        }
    ],
    "sg:phone":"+1 502 955 9433",
    "sg:postcode":"40165",
    "sg:province":"KY",
    "sg:tags":[
        "hauling",
        "trucking"
    ],
    "wof:name":"Kendrick Trucking Corp",
    "wof:placetype":"venue"
},
  "geometry": {"coordinates":[-85.670536,38.051936],"type":"Point"}
}