{
  "type": "Feature",
  "properties": {
    "iso:country":"US",
    "sg:address":"337 N Church St",
    "sg:city":"Madisonville",
    "sg:classifiers":[
        {
            "category":"Social Services",
            "subcategory":"Child Care",
            "type":"Services"
        }
    ],
    "sg:phone":"+1 270 821 2270",
    "sg:postcode":"42431",
    "sg:province":"KY",
    "wof:name":"Christy's Sitter Svc",
    "wof:placetype":"venue"
},
  "geometry": {"coordinates":[-87.504949,37.334436],"type":"Point"}
}