{
  "type": "Feature",
  "properties": {
    "iso:country":"US",
    "sg:address":"57 J E Ellis Rd",
    "sg:city":"Madisonville",
    "sg:classifiers":[
        {
            "category":"Utilities",
            "subcategory":"Fuel Oil & Lpg",
            "type":"Services"
        }
    ],
    "sg:phone":"+1 270 825 4560",
    "sg:postcode":"42431",
    "sg:province":"KY",
    "sg:tags":[
        "coal",
        "coke"
    ],
    "wof:name":"Warrior Coal LLC",
    "wof:placetype":"venue"
},
  "geometry": {"coordinates":[-87.611654,37.384759],"type":"Point"}
}