{
  "type": "Feature",
  "properties": {
    "iso:country":"US",
    "sg:address":"6400 Dutchmans Pkwy",
    "sg:city":"Louisville",
    "sg:classifiers":[
        {
            "category":"Health Services",
            "subcategory":"Doctor",
            "type":"Services"
        }
    ],
    "sg:phone":"+1 502 895 0524",
    "sg:postcode":"40205",
    "sg:province":"KY",
    "sg:tags":[
        "physician",
        "surgeon"
    ],
    "sg:website":"www.springspediatrics.com",
    "wof:name":"Springs Pediatrics",
    "wof:placetype":"venue"
},
  "geometry": {"coordinates":[-85.643834,38.230111],"type":"Point"}
}