{
  "type": "Feature",
  "properties": {
    "iso:country":"US",
    "sg:address":"1804 Bryan Station Rd",
    "sg:city":"Lexington",
    "sg:classifiers":[
        {
            "category":"Health Services",
            "subcategory":"Doctor",
            "type":"Services"
        }
    ],
    "sg:phone":"+1 859 299 0441",
    "sg:postcode":"40505",
    "sg:province":"KY",
    "sg:tags":[
        "dentist"
    ],
    "wof:name":"Alan D Ward DDS",
    "wof:placetype":"venue"
},
  "geometry": {"coordinates":[-84.453885,38.063494],"type":"Point"}
}