{
  "type": "Feature",
  "properties": {
    "iso:country":"US",
    "sg:address":"1541 S Main St",
    "sg:city":"London",
    "sg:classifiers":[
        {
            "category":"Health Services",
            "subcategory":"Chiropractor",
            "type":"Services"
        }
    ],
    "sg:phone":"+1 606 862 6986",
    "sg:postcode":"40741",
    "sg:province":"KY",
    "wof:name":"Miller Chiropractic Office Inc",
    "wof:placetype":"venue"
},
  "geometry": {"coordinates":[-84.074569,37.111617],"type":"Point"}
}