{
  "type": "Feature",
  "properties": {
    "addr:full":"526 Silverbrook Dr Danville KY 40422",
    "addr:housenumber":"526",
    "addr:postcode":"40422",
    "addr:street":"Silverbrook Dr",
    "iso:country":"US",
    "sg:address":"526 Silverbrook Dr",
    "sg:city":"Danville",
    "sg:classifiers":[
        {
            "category":"Professional",
            "subcategory":"Employment Agencies",
            "type":"Services"
        }
    ],
    "sg:phone":"+1 859 239 0096",
    "sg:postcode":"40422",
    "sg:province":"KY",
    "sg:tags":[
        "consultant",
        "search",
        "executive"
    ],
    "wof:name":"Binder Hospitality Group",
    "wof:placetype":"venue"
},
  "geometry": {"coordinates":[-84.776698,37.670989],"type":"Point"}
}