{
  "type": "Feature",
  "properties": {
    "addr:full":"620 E Center St Madisonville KY 42431",
    "addr:housenumber":"620",
    "addr:postcode":"42431",
    "addr:street":"E Center St",
    "iso:country":"US",
    "sg:address":"620 E Center St",
    "sg:city":"Madisonville",
    "sg:classifiers":[
        {
            "category":"Shopping",
            "subcategory":"Department Store",
            "type":"Retail Goods"
        }
    ],
    "sg:phone":"+1 270 821 1278",
    "sg:postcode":"42431",
    "sg:province":"KY",
    "sg:tags":[
        "shop"
    ],
    "wof:name":"Dollar General",
    "wof:placetype":"venue"
},
  "geometry": {"coordinates":[-87.48752899999999,37.327362],"type":"Point"}
}