{
  "type": "Feature",
  "properties": {
    "addr:full":"1511 Versailles Rd Lexington KY 40504",
    "addr:housenumber":"1511",
    "addr:postcode":"40504",
    "addr:street":"Versailles Rd",
    "iso:country":"US",
    "sg:address":"1511 Versailles Rd",
    "sg:city":"Lexington",
    "sg:classifiers":[
        {
            "category":"Professional",
            "subcategory":"Secretarial Services",
            "type":"Services"
        }
    ],
    "sg:phone":"+1 859 255 9234",
    "sg:postcode":"40504",
    "sg:province":"KY",
    "sg:tags":[
        "reporter",
        "court",
        "for",
        "hearing"
    ],
    "wof:name":"Betty A Whitt",
    "wof:placetype":"venue"
},
  "geometry": {"coordinates":[-84.531673,38.049013],"type":"Point"}
}