{
  "type": "Feature",
  "properties": {
    "iso:country":"US",
    "sg:address":"3634A Brownsboro Rd",
    "sg:city":"Louisville",
    "sg:classifiers":[
        {
            "category":"Shopping",
            "subcategory":"Jewelry",
            "type":"Retail Goods"
        }
    ],
    "sg:phone":"+1 502 896 2707",
    "sg:postcode":"40207",
    "sg:province":"KY",
    "sg:tags":[
        "precious",
        "semi-precious",
        "stone"
    ],
    "sg:website":"http://www.lawsonjewelry.com",
    "wof:name":"Lawson Jewelry And Repairs Inc",
    "wof:placetype":"venue"
},
  "geometry": {"coordinates":[-85.669449,38.264881],"type":"Point"}
}