{
  "type": "Feature",
  "properties": {
    "addr:full":"6111 Burgundy Hill Dr. Burlington KY 41005",
    "addr:housenumber":"6111",
    "addr:postcode":"41005",
    "addr:street":"Burgundy Hill Dr.",
    "iso:country":"US",
    "sg:address":"6111 Burgundy Hill Dr.",
    "sg:city":"Burlington",
    "sg:classifiers":[
        {
            "category":"Restaurant",
            "type":"Food & Drink"
        }
    ],
    "sg:phone":"+1 859 586 9090",
    "sg:postcode":"41005",
    "sg:province":"KY",
    "sg:tags":[
        "pizza"
    ],
    "sg:website":"www.snappytomato.com",
    "wof:name":"Snappy Tomato Pizza Co.",
    "wof:placetype":"venue"
},
  "geometry": {"coordinates":[-84.69220199999999,39.01513],"type":"Point"}
}