{
  "type": "Feature",
  "properties": {
    "addr:full":"162 N Ashland Ave Lexington KY 40502",
    "addr:housenumber":"162",
    "addr:postcode":"40502",
    "addr:street":"N Ashland Ave",
    "iso:country":"US",
    "sg:address":"162 N Ashland Ave",
    "sg:city":"Lexington",
    "sg:classifiers":[
        {
            "category":"Health Services",
            "subcategory":"Health Practitioner",
            "type":"Services"
        }
    ],
    "sg:phone":"+1 859 268 4545",
    "sg:postcode":"40502",
    "sg:province":"KY",
    "sg:tags":[
        "speech",
        "therapy",
        "hearing"
    ],
    "sg:website":"www.lhscky.org",
    "wof:name":"Lexington Hearing & Speech Ctr",
    "wof:placetype":"venue"
},
  "geometry": {"coordinates":[-84.48115,38.037442],"type":"Point"}
}