{
  "type": "Feature",
  "properties": {
    "addr:full":"5330 S 3rd St Louisville KY 40214",
    "addr:housenumber":"5330",
    "addr:postcode":"40214",
    "addr:street":"S 3Rd St",
    "iso:country":"US",
    "sg:address":"5330 S 3rd St",
    "sg:city":"Louisville",
    "sg:classifiers":[
        {
            "category":"Personal",
            "subcategory":"Barber",
            "type":"Services"
        }
    ],
    "sg:phone":"+1 502 361 9123",
    "sg:postcode":"40214",
    "sg:province":"KY",
    "wof:name":"Irquois Manor Barber Shop",
    "wof:placetype":"venue"
},
  "geometry": {"coordinates":[-85.768179,38.170944],"type":"Point"}
}