{
  "type": "Feature",
  "properties": {
    "iso:country":"US",
    "sg:address":"7005 Stewartsville Rd",
    "sg:city":"Williamstown",
    "sg:classifiers":[
        {
            "category":"Building & Trades",
            "subcategory":"Electrical",
            "type":"Services"
        }
    ],
    "sg:phone":"+1 859 824 5853",
    "sg:postcode":"41097",
    "sg:province":"KY",
    "sg:tags":[
        "electrical",
        "contractor"
    ],
    "wof:name":"Walters Electric Service LLC",
    "wof:placetype":"venue"
},
  "geometry": {"coordinates":[-84.665378,38.633876],"type":"Point"}
}