{
  "type": "Feature",
  "properties": {
    "iso:country":"US",
    "sg:address":"1008 Richmond Rd N",
    "sg:city":"Berea",
    "sg:classifiers":[
        {
            "category":"Professional",
            "subcategory":"Lawyer & Legal Services",
            "type":"Services"
        }
    ],
    "sg:phone":"+1 859 986 1941",
    "sg:postcode":"40403",
    "sg:province":"KY",
    "sg:tags":[
        "attorney"
    ],
    "wof:name":"Roger M Oliver",
    "wof:placetype":"venue"
},
  "geometry": {"coordinates":[-84.28378499999999,37.58819],"type":"Point"}
}