{
  "type": "Feature",
  "properties": {
    "addr:full":"1605 Fortune Dr Winchester KY 40391",
    "addr:housenumber":"1605",
    "addr:postcode":"40391",
    "addr:street":"Fortune Dr",
    "iso:country":"US",
    "sg:address":"1605 Fortune Dr",
    "sg:city":"Winchester",
    "sg:classifiers":[
        {
            "category":"Manufacturing",
            "subcategory":"Rubber & Plastics",
            "type":"Manufacturing & Wholesale Goods"
        }
    ],
    "sg:phone":"+1 859 737 1600",
    "sg:postcode":"40391",
    "sg:province":"KY",
    "sg:tags":[
        "product"
    ],
    "wof:name":"Ainak Inc",
    "wof:placetype":"venue"
},
  "geometry": {"coordinates":[-84.185438,38.023552],"type":"Point"}
}