{
  "type": "Feature",
  "properties": {
    "iso:country":"US",
    "sg:address":"9108 Dixie Hwy",
    "sg:city":"Louisville",
    "sg:classifiers":[
        {
            "category":"Autos & Motor Vehicles",
            "subcategory":"Automobile Sales",
            "type":"Retail Goods"
        }
    ],
    "sg:phone":"+1 502 935 4284",
    "sg:postcode":"40258",
    "sg:province":"KY",
    "sg:tags":[
        "dealers-used",
        "car",
        "used",
        "cars-wholesale",
        "new"
    ],
    "wof:name":"Rocky's Auto Sales",
    "wof:placetype":"venue"
},
  "geometry": {"coordinates":[-85.85488599999999,38.122137],"type":"Point"}
}