{
  "type": "Feature",
  "properties": {
    "iso:country":"US",
    "sg:address":"4103 Rivulet Ct",
    "sg:city":"Louisville",
    "sg:classifiers":[
        {
            "category":"Building & Trades",
            "subcategory":"Construction",
            "type":"Services"
        }
    ],
    "sg:phone":"+1 502 266 5222",
    "sg:postcode":"40299",
    "sg:province":"KY",
    "sg:tags":[
        "painter"
    ],
    "wof:name":"Dan Brumback Painting Inc",
    "wof:placetype":"venue"
},
  "geometry": {"coordinates":[-85.54715899999999,38.187945],"type":"Point"}
}