{
  "type": "Feature",
  "properties": {
    "addr:full":"10117 Taylorsville Rd Louisville KY 40299",
    "addr:housenumber":"10117",
    "addr:postcode":"40299",
    "addr:street":"Taylorsville Rd",
    "iso:country":"US",
    "sg:address":"10117 Taylorsville Rd",
    "sg:city":"Louisville",
    "sg:classifiers":[
        {
            "category":"Restaurant",
            "type":"Food & Drink"
        }
    ],
    "sg:menulink":"http://www.allmenus.com/ky/jefferson-southeast/35513-bearnos/menu/",
    "sg:phone":"+1 502 267 2549",
    "sg:postcode":"40299",
    "sg:province":"KY",
    "sg:tags":[
        "american",
        "pizza"
    ],
    "wof:name":"Bearnos",
    "wof:placetype":"venue"
},
  "geometry": {"coordinates":[-85.57033,38.198436],"type":"Point"}
}