{
  "type": "Feature",
  "properties": {
    "addr:full":"1396 Dixie Hwy S Radcliff KY 40160",
    "addr:housenumber":"1396",
    "addr:postcode":"40160",
    "addr:street":"Dixie Hwy S",
    "iso:country":"US",
    "sg:address":"1396 Dixie Hwy S",
    "sg:city":"Radcliff",
    "sg:classifiers":[
        {
            "category":"Restaurant",
            "type":"Food & Drink"
        }
    ],
    "sg:phone":"+1 270 351 5309",
    "sg:postcode":"40160",
    "sg:province":"KY",
    "wof:name":"Oriental House",
    "wof:placetype":"venue"
},
  "geometry": {"coordinates":[-85.92673600000001,37.823545],"type":"Point"}
}