{
  "type": "Feature",
  "properties": {
    "iso:country":"US",
    "sg:address":"2301 River Rd",
    "sg:city":"Louisville",
    "sg:classifiers":[
        {
            "category":"Wholesale",
            "subcategory":"Durable Goods & Equipment",
            "type":"Manufacturing & Wholesale Goods"
        }
    ],
    "sg:phone":"+1 502 394 9298",
    "sg:postcode":"40206",
    "sg:province":"KY",
    "sg:tags":[
        "importer"
    ],
    "sg:website":"www.demptos.com",
    "wof:name":"Demptos Glass Co LLC",
    "wof:placetype":"venue"
},
  "geometry": {"coordinates":[-85.708764,38.271695],"type":"Point"}
}