{
  "type": "Feature",
  "properties": {
    "iso:country":"US",
    "sg:address":"125 Cynthiana Rd",
    "sg:city":"Paris",
    "sg:classifiers":[
        {
            "category":"Farming",
            "subcategory":"Farm",
            "type":"Manufacturing & Wholesale Goods"
        }
    ],
    "sg:phone":"+1 859 987 8415",
    "sg:postcode":"40361",
    "sg:province":"KY",
    "wof:name":"Raceland Farm Barn 4",
    "wof:placetype":"venue"
},
  "geometry": {"coordinates":[-84.276048,38.224608],"type":"Point"}
}