{
  "type": "Feature",
  "properties": {
    "addr:full":"2371 Russellville Rd Bowling Green KY 42101",
    "addr:housenumber":"2371",
    "addr:postcode":"42101",
    "addr:street":"Russellville Rd",
    "iso:country":"US",
    "sg:address":"2371 Russellville Rd",
    "sg:city":"Bowling Green",
    "sg:classifiers":[
        {
            "category":"Building & Trades",
            "subcategory":"Landscaping Services",
            "type":"Services"
        }
    ],
    "sg:phone":"+1 270 782 5900",
    "sg:postcode":"42101",
    "sg:province":"KY",
    "sg:tags":[
        "landscape",
        "contractor"
    ],
    "wof:name":"Ponds Plus Inc",
    "wof:placetype":"venue"
},
  "geometry": {"coordinates":[-86.47886800000001,36.970105],"type":"Point"}
}