{
  "type": "Feature",
  "properties": {
    "iso:country":"US",
    "sg:address":"130 Winslow St",
    "sg:city":"Lexington",
    "sg:classifiers":[
        {
            "category":"Restaurant",
            "type":"Food & Drink"
        }
    ],
    "sg:menulink":"http://www.allmenus.com/ky/fayette/121581-fazolis/menu/",
    "sg:phone":"+1 859 233 0022",
    "sg:postcode":"40508",
    "sg:province":"KY",
    "sg:tags":[
        "italian"
    ],
    "wof:name":"Fazoli's",
    "wof:placetype":"venue"
},
  "geometry": {"coordinates":[-84.50486100000001,38.041997],"type":"Point"}
}