{
  "type": "Feature",
  "properties": {
    "iso:country":"US",
    "sg:address":"7300 Global Dr",
    "sg:city":"Louisville",
    "sg:classifiers":[
        {
            "category":"Train Station",
            "subcategory":"Light Rail",
            "type":"Transportation"
        }
    ],
    "sg:phone":"+1 502 937 0514",
    "sg:postcode":"40258",
    "sg:province":"KY",
    "sg:tags":[
        "steel",
        "processing"
    ],
    "wof:name":"Itochu International",
    "wof:placetype":"venue"
},
  "geometry": {"coordinates":[-85.89060000000001,38.139657],"type":"Point"}
}