{
  "type": "Feature",
  "properties": {
    "iso:country":"US",
    "sg:address":"238 State Hwy 160",
    "sg:city":"Hindman",
    "sg:classifiers":[
        {
            "category":"Education",
            "subcategory":"Special Training",
            "type":"Public Place"
        }
    ],
    "sg:phone":"+1 606 785 0819",
    "sg:postcode":"41822",
    "sg:province":"KY",
    "sg:tags":[
        "information",
        "school",
        "college"
    ],
    "wof:name":"Adult Learning Ctr",
    "wof:placetype":"venue"
},
  "geometry": {"coordinates":[-82.969393,37.331626],"type":"Point"}
}