{
  "type": "Feature",
  "properties": {
    "addr:full":"709 E Burnett Ave Louisville KY 40217",
    "addr:housenumber":"709",
    "addr:postcode":"40217",
    "addr:street":"E Burnett Ave",
    "iso:country":"US",
    "sg:address":"709 E Burnett Ave",
    "sg:city":"Louisville",
    "sg:classifiers":[
        {
            "category":"Building & Trades",
            "subcategory":"Construction",
            "type":"Services"
        }
    ],
    "sg:phone":"+1 502 634 3660",
    "sg:postcode":"40217",
    "sg:province":"KY",
    "sg:tags":[
        "wallcoverings-installation",
        "wallpaper",
        "painting",
        "contractor"
    ],
    "wof:name":"Mclaughlin Painting",
    "wof:placetype":"venue"
},
  "geometry": {"coordinates":[-85.743649,38.225352],"type":"Point"}
}