{
  "type": "Feature",
  "properties": {
    "iso:country":"US",
    "sg:address":"6375 Joppa Landing Rd",
    "sg:city":"Kevil",
    "sg:classifiers":[
        {
            "category":"Wholesale",
            "subcategory":"Machinery & Supplies",
            "type":"Manufacturing & Wholesale Goods"
        }
    ],
    "sg:phone":"+1 270 462 2191",
    "sg:postcode":"42053",
    "sg:province":"KY",
    "sg:tags":[
        "equipment",
        "parts",
        "tractor"
    ],
    "wof:name":"West Kentucky Tractor Parts",
    "wof:placetype":"venue"
},
  "geometry": {"coordinates":[-88.874821,37.143234],"type":"Point"}
}