{
  "type": "Feature",
  "properties": {
    "iso:country":"US",
    "sg:address":"107 Burkesville St",
    "sg:city":"Columbia",
    "sg:classifiers":[
        {
            "category":"Real Estate",
            "subcategory":"Real Estate Agent",
            "type":"Services"
        }
    ],
    "sg:phone":"+1 270 384 3661",
    "sg:postcode":"42728",
    "sg:province":"KY",
    "wof:name":"Walker Real Estate & Auction",
    "wof:placetype":"venue"
},
  "geometry": {"coordinates":[-85.306408,37.102458],"type":"Point"}
}