{
  "type": "Feature",
  "properties": {
    "addr:full":"801 E 25th St Owensboro KY 42303",
    "addr:housenumber":"801",
    "addr:postcode":"42303",
    "addr:street":"E 25Th St",
    "iso:country":"US",
    "sg:address":"801 E 25th St",
    "sg:city":"Owensboro",
    "sg:classifiers":[
        {
            "category":"Banks & Credit Unions",
            "subcategory":"Bank",
            "type":"Services"
        }
    ],
    "sg:phone":"+1 270 686 3050",
    "sg:postcode":"42303",
    "sg:province":"KY",
    "wof:name":"Old National Bank",
    "wof:placetype":"venue"
},
  "geometry": {"coordinates":[-87.097837,37.752001],"type":"Point"}
}