{
  "type": "Feature",
  "properties": {
    "addr:full":"3165 Brookwood Dr Edgewood KY 41017",
    "addr:housenumber":"3165",
    "addr:postcode":"41017",
    "addr:street":"Brookwood Dr",
    "iso:country":"US",
    "sg:address":"3165 Brookwood Dr",
    "sg:city":"Edgewood",
    "sg:classifiers":[
        {
            "category":"Professional",
            "type":"Services"
        }
    ],
    "sg:phone":"+1 859 331 4950",
    "sg:postcode":"41017",
    "sg:province":"KY",
    "sg:website":"www.spiffservices.com",
    "wof:name":"Spiff Services",
    "wof:placetype":"venue"
},
  "geometry": {"coordinates":[-84.550028,39.004541],"type":"Point"}
}