{
  "type": "Feature",
  "properties": {
    "addr:full":"1035 Mount Olive-Girkin Rd Bowling Green KY 42101",
    "addr:housenumber":"1035",
    "addr:postcode":"42101",
    "addr:street":"Mount Olive-Girkin Rd",
    "iso:country":"US",
    "sg:address":"1035 Mount Olive-Girkin Rd",
    "sg:city":"Bowling Green",
    "sg:classifiers":[
        {
            "category":"Organizations",
            "subcategory":"Religious Organization",
            "type":"Services"
        }
    ],
    "sg:phone":"+1 270 842 9629",
    "sg:postcode":"42101",
    "sg:province":"KY",
    "sg:tags":[
        "church"
    ],
    "wof:name":"Jehovah's Witnesses-North Con",
    "wof:placetype":"venue"
},
  "geometry": {"coordinates":[-86.37917299999999,37.05732],"type":"Point"}
}