{
  "type": "Feature",
  "properties": {
    "addr:full":"543 Damron Mayo Rd Grayson KY 41143",
    "addr:housenumber":"543",
    "addr:postcode":"41143",
    "addr:street":"Damron Mayo Rd",
    "iso:country":"US",
    "sg:address":"543 Damron Mayo Rd",
    "sg:city":"Grayson",
    "sg:classifiers":[
        {
            "category":"Shopping",
            "subcategory":"Crafts & Fabrics",
            "type":"Retail Goods"
        }
    ],
    "sg:phone":"+1 606 475 3577",
    "sg:postcode":"41143",
    "sg:province":"KY",
    "sg:tags":[
        "shop"
    ],
    "wof:name":"Patchwork Basket",
    "wof:placetype":"venue"
},
  "geometry": {"coordinates":[-82.89212000000001,38.351094],"type":"Point"}
}