{
  "type": "Feature",
  "properties": {
    "addr:full":"13100 Middletown Ind Blvd Louisville KY 40223",
    "addr:housenumber":"13100",
    "addr:postcode":"40223",
    "addr:street":"Middletown Ind Blvd",
    "iso:country":"US",
    "sg:address":"13100 Middletown Ind Blvd",
    "sg:city":"Louisville",
    "sg:classifiers":[
        {
            "category":"Freight",
            "type":"Transportation"
        }
    ],
    "sg:phone":"+1 502 245 4210",
    "sg:postcode":"40223",
    "sg:province":"KY",
    "sg:tags":[
        "courier"
    ],
    "wof:name":"Security Courier Corp",
    "wof:placetype":"venue"
},
  "geometry": {"coordinates":[-85.507662,38.252046],"type":"Point"}
}