{
  "type": "Feature",
  "properties": {
    "iso:country":"US",
    "sg:address":"851 Jackson Pike",
    "sg:city":"Harrodsburg",
    "sg:classifiers":[
        {
            "category":"Building & Trades",
            "subcategory":"Construction",
            "type":"Services"
        }
    ],
    "sg:phone":"+1 859 366 5585",
    "sg:postcode":"40330",
    "sg:province":"KY",
    "sg:tags":[
        "carpentry",
        "contractor"
    ],
    "wof:name":"Scott Grider",
    "wof:placetype":"venue"
},
  "geometry": {"coordinates":[-84.885533,37.825652],"type":"Point"}
}