{
  "type": "Feature",
  "properties": {
    "addr:full":"68 S Main St Dry Ridge KY 41035",
    "addr:housenumber":"68",
    "addr:postcode":"41035",
    "addr:street":"S Main St",
    "iso:country":"US",
    "sg:address":"68 S Main St",
    "sg:city":"Dry Ridge",
    "sg:classifiers":[
        {
            "category":"Food & Beverages",
            "subcategory":"Groceries & Convenience Stores",
            "type":"Retail Goods"
        }
    ],
    "sg:phone":"+1 859 824 5614",
    "sg:postcode":"41035",
    "sg:province":"KY",
    "sg:tags":[
        "grocer"
    ],
    "sg:website":"www.foodline.com",
    "wof:name":"Food Lion",
    "wof:placetype":"venue"
},
  "geometry": {"coordinates":[-84.587051,38.680829],"type":"Point"}
}