{
  "type": "Feature",
  "properties": {
    "iso:country":"US",
    "sg:address":"1244 Indian Mound Rd",
    "sg:city":"Lexington",
    "sg:classifiers":[
        {
            "category":"Health Services",
            "subcategory":"Doctor",
            "type":"Services"
        }
    ],
    "sg:phone":"+1 859 266 1880",
    "sg:postcode":"40502",
    "sg:province":"KY",
    "sg:tags":[
        "physician",
        "surgeon"
    ],
    "wof:name":"Orr James A Jr MD",
    "wof:placetype":"venue"
},
  "geometry": {"coordinates":[-84.48656800000001,38.016948],"type":"Point"}
}