{
  "type": "Feature",
  "properties": {
    "iso:country":"US",
    "sg:address":"116 N Main St",
    "sg:city":"Henderson",
    "sg:classifiers":[
        {
            "category":"Shopping",
            "subcategory":"Shoes",
            "type":"Retail Goods"
        }
    ],
    "sg:phone":"+1 270 827 3442",
    "sg:postcode":"42420",
    "sg:province":"KY",
    "wof:name":"Wilkerson's Shoes",
    "wof:placetype":"venue"
},
  "geometry": {"coordinates":[-87.591641,37.840506],"type":"Point"}
}