{
  "type": "Feature",
  "properties": {
    "iso:country":"US",
    "sg:address":"1226 E Cumberland Ave",
    "sg:city":"Middlesboro",
    "sg:classifiers":[
        {
            "category":"Autos & Motor Vehicles",
            "subcategory":"Auto Supplies",
            "type":"Retail Goods"
        }
    ],
    "sg:phone":"+1 606 242 2153",
    "sg:postcode":"40965",
    "sg:province":"KY",
    "sg:tags":[
        "automobile",
        "parts"
    ],
    "wof:name":"O'Reilly Auto Parts",
    "wof:placetype":"venue"
},
  "geometry": {"coordinates":[-83.702051,36.608284],"type":"Point"}
}