{
  "type": "Feature",
  "properties": {
    "iso:country":"US",
    "sg:address":"537 Ireland School Rd",
    "sg:city":"Radcliff",
    "sg:classifiers":[
        {
            "category":"Building & Trades",
            "subcategory":"Plumbing",
            "type":"Services"
        }
    ],
    "sg:phone":"+1 270 877 2954",
    "sg:postcode":"40160",
    "sg:province":"KY",
    "sg:tags":[
        "air",
        "heating",
        "conditioning",
        "contractor"
    ],
    "wof:name":"Yerkes Heating & Cooling LLC",
    "wof:placetype":"venue"
},
  "geometry": {"coordinates":[-85.952006,37.785543],"type":"Point"}
}