{
  "type": "Feature",
  "properties": {
    "iso:country":"US",
    "sg:address":"1501 S 6th St",
    "sg:city":"Ironton",
    "sg:classifiers":[
        {
            "category":"Shopping",
            "subcategory":"Florist",
            "type":"Retail Goods"
        }
    ],
    "sg:phone":"+1 740 532 0664",
    "sg:postcode":"45638",
    "sg:province":"OH",
    "wof:name":"Weber's Florists & Gifts",
    "wof:placetype":"venue"
},
  "geometry": {"coordinates":[-82.67232799999999,38.52462],"type":"Point"}
}