{
  "type": "Feature",
  "properties": {
    "iso:country":"US",
    "sg:address":"6111 Burgundy Hill Dr",
    "sg:city":"Burlington",
    "sg:classifiers":[
        {
            "category":"Personal",
            "subcategory":"Massage",
            "type":"Services"
        }
    ],
    "sg:phone":"+1 859 534 5666",
    "sg:postcode":"41005",
    "sg:province":"KY",
    "wof:name":"Trend the",
    "wof:placetype":"venue"
},
  "geometry": {"coordinates":[-84.691655,39.016895],"type":"Point"}
}