{
  "type": "Feature",
  "properties": {
    "iso:country":"US",
    "sg:address":"1609 Riverside Dr",
    "sg:city":"Prospect",
    "sg:classifiers":[
        {
            "category":"Shopping",
            "subcategory":"Computers & Home Electronics",
            "type":"Retail Goods"
        }
    ],
    "sg:phone":"+1 502 905 5869",
    "sg:postcode":"40059",
    "sg:province":"KY",
    "sg:tags":[
        "stereo",
        "high",
        "stereophonic",
        "video",
        "equipment-dealers",
        "fidelity",
        "audio"
    ],
    "wof:name":"Custom Home Theatres, Inc.",
    "wof:placetype":"venue"
},
  "geometry": {"coordinates":[-85.620762,38.401959],"type":"Point"}
}