{
  "type": "Feature",
  "properties": {
    "iso:country":"US",
    "sg:address":"5601 Johnsontown Rd",
    "sg:city":"Louisville",
    "sg:classifiers":[
        {
            "category":"Education",
            "subcategory":"School",
            "type":"Public Place"
        }
    ],
    "sg:phone":"+1 502 485 8351",
    "sg:postcode":"40272",
    "sg:province":"KY",
    "wof:name":"Wilkerson Elementary School",
    "wof:placetype":"venue"
},
  "geometry": {"coordinates":[-85.871689,38.121685],"type":"Point"}
}