{
  "type": "Feature",
  "properties": {
    "iso:country":"US",
    "sg:address":"461 Lincoln Park Rd",
    "sg:city":"Springfield",
    "sg:classifiers":[
        {
            "category":"Government",
            "subcategory":"Office",
            "type":"Public Place"
        }
    ],
    "sg:phone":"+1 859 336 7774",
    "sg:postcode":"40069",
    "sg:province":"KY",
    "sg:tags":[
        "federal"
    ],
    "wof:name":"US Consolidated Farm Svc Agcy",
    "wof:placetype":"venue"
},
  "geometry": {"coordinates":[-85.21972700000001,37.688677],"type":"Point"}
}