{
  "type": "Feature",
  "properties": {
    "iso:country":"US",
    "sg:address":"273 Midland Trl",
    "sg:city":"Mt Sterling",
    "sg:classifiers":[
        {
            "category":"Shopping",
            "type":"Retail Goods"
        }
    ],
    "sg:phone":"+1 859 498 4225",
    "sg:postcode":"40353",
    "sg:province":"KY",
    "sg:tags":[
        "equipment",
        "telephone",
        "supply"
    ],
    "wof:name":"American Technolgies",
    "wof:placetype":"venue"
},
  "geometry": {"coordinates":[-83.923466,38.079357],"type":"Point"}
}