{
  "type": "Feature",
  "properties": {
    "iso:country":"US",
    "sg:address":"1265 Paris Rd",
    "sg:city":"Mayfield",
    "sg:classifiers":[
        {
            "category":"Restaurant",
            "type":"Food & Drink"
        }
    ],
    "sg:menulink":"http://www.allmenus.com/ky/mayfield/83772-papa-johns-pizza/menu/",
    "sg:phone":"+1 270 247 5600",
    "sg:postcode":"42066",
    "sg:province":"KY",
    "sg:tags":[
        "american",
        "pizza"
    ],
    "wof:name":"Papa John's Pizza",
    "wof:placetype":"venue"
},
  "geometry": {"coordinates":[-88.629161,36.725933],"type":"Point"}
}