{
  "type": "Feature",
  "properties": {
    "addr:full":"9 W Southern Ave Covington KY 41015",
    "addr:housenumber":"9",
    "addr:postcode":"41015",
    "addr:street":"W Southern Ave",
    "iso:country":"US",
    "sg:address":"9 W Southern Ave",
    "sg:city":"Covington",
    "sg:classifiers":[
        {
            "category":"Building & Trades",
            "subcategory":"Construction",
            "type":"Services"
        }
    ],
    "sg:phone":"+1 859 331 5777",
    "sg:postcode":"41015",
    "sg:province":"KY",
    "sg:tags":[
        "woodworker"
    ],
    "wof:name":"Custom Woodworking Unlimited",
    "wof:placetype":"venue"
},
  "geometry": {"coordinates":[-84.50429099999999,39.047424],"type":"Point"}
}