{
  "type": "Feature",
  "properties": {
    "iso:country":"US",
    "sg:address":"259 Saw Mill Rd",
    "sg:city":"Bethlehem",
    "sg:classifiers":[
        {
            "category":"Wholesale",
            "subcategory":"Farm Supplies",
            "type":"Manufacturing & Wholesale Goods"
        }
    ],
    "sg:phone":"+1 502 845 1283",
    "sg:postcode":"40007",
    "sg:province":"KY",
    "wof:name":"Gardeners Dream",
    "wof:placetype":"venue"
},
  "geometry": {"coordinates":[-85.005353,38.443705],"type":"Point"}
}