{
  "type": "Feature",
  "properties": {
    "addr:full":"510 W 9th St Russellville KY 42276",
    "addr:housenumber":"510",
    "addr:postcode":"42276",
    "addr:street":"W 9Th St",
    "iso:country":"US",
    "sg:address":"510 W 9th St",
    "sg:city":"Russellville",
    "sg:classifiers":[
        {
            "category":"Autos & Motor Vehicles",
            "subcategory":"Automobile Sales",
            "type":"Retail Goods"
        }
    ],
    "sg:phone":"+1 270 726 2677",
    "sg:postcode":"42276",
    "sg:province":"KY",
    "sg:tags":[
        "car",
        "dealer"
    ],
    "wof:name":"Alan Young Auto Sales",
    "wof:placetype":"venue"
},
  "geometry": {"coordinates":[-86.893951,36.838772],"type":"Point"}
}