{
  "type": "Feature",
  "properties": {
    "iso:country":"US",
    "sg:address":"3305 Dixie Hwy",
    "sg:city":"Erlanger",
    "sg:classifiers":[
        {
            "category":"Professional",
            "subcategory":"Accounting & Tax Preparation",
            "type":"Services"
        }
    ],
    "sg:phone":"+1 859 331 5333",
    "sg:postcode":"41018",
    "sg:province":"KY",
    "sg:tags":[
        "accountant"
    ],
    "wof:name":"Allie Jackson & Assoc",
    "wof:placetype":"venue"
},
  "geometry": {"coordinates":[-84.59804699999999,39.017712],"type":"Point"}
}