{
  "type": "Feature",
  "properties": {
    "iso:country":"US",
    "sg:address":"428 S College St",
    "sg:city":"Marion",
    "sg:classifiers":[
        {
            "category":"Personal",
            "subcategory":"Beauty Salon",
            "type":"Services"
        }
    ],
    "sg:phone":"+1 270 965 9385",
    "sg:postcode":"42064",
    "sg:province":"KY",
    "sg:tags":[
        "shop"
    ],
    "wof:name":"Beauty Shop",
    "wof:placetype":"venue"
},
  "geometry": {"coordinates":[-88.080189,37.32864],"type":"Point"}
}