{
  "type": "Feature",
  "properties": {
    "iso:country":"US",
    "sg:address":"183 Moore Dr",
    "sg:city":"Lexington",
    "sg:classifiers":[
        {
            "category":"Shopping",
            "subcategory":"Clothing, Apparel, & Fashions",
            "type":"Retail Goods"
        },
        {
            "category":"Banks & Credit Unions",
            "subcategory":"Bank",
            "type":"Services"
        }
    ],
    "sg:phone":"+1 859 277 9418",
    "sg:postcode":"40503",
    "sg:province":"KY",
    "sg:tags":[
        "second",
        "consignment",
        "hand"
    ],
    "wof:name":"Over The Moon",
    "wof:placetype":"venue"
},
  "geometry": {"coordinates":[-84.523849,38.000484],"type":"Point"}
}