{
  "type": "Feature",
  "properties": {
    "addr:full":"6275 US Hwy 27 Somerset KY 42501",
    "addr:housenumber":"6275",
    "addr:postcode":"42501",
    "addr:street":"Us Hwy 27",
    "iso:country":"US",
    "sg:address":"6275 US Hwy 27",
    "sg:city":"Somerset",
    "sg:classifiers":[
        {
            "category":"Professional",
            "subcategory":"Advertising",
            "type":"Services"
        }
    ],
    "sg:phone":"+1 606 561 4299",
    "sg:postcode":"42501",
    "sg:province":"KY",
    "sg:tags":[
        "distribution"
    ],
    "wof:name":"Cruzin Auto Sales",
    "wof:placetype":"venue"
},
  "geometry": {"coordinates":[-84.62505299999999,37.009792],"type":"Point"}
}