{
  "type": "Feature",
  "properties": {
    "addr:full":"438 S 3rd St Louisville KY 40202",
    "addr:housenumber":"438",
    "addr:postcode":"40202",
    "addr:street":"S 3Rd St",
    "iso:country":"US",
    "sg:address":"438 S 3rd St",
    "sg:city":"Louisville",
    "sg:classifiers":[
        {
            "category":"Professional",
            "subcategory":"Art Services",
            "type":"Services"
        }
    ],
    "sg:phone":"+1 502 562 0060",
    "sg:postcode":"40202",
    "sg:province":"KY",
    "sg:tags":[
        "designer",
        "companies-film",
        "tv",
        "production",
        "graphic",
        "radio"
    ],
    "sg:website":"http://www.solidlightinc.com",
    "wof:name":"Solid Light Inc",
    "wof:placetype":"venue"
},
  "geometry": {"coordinates":[-85.755715,38.251458],"type":"Point"}
}