{
  "type": "Feature",
  "properties": {
    "iso:country":"US",
    "sg:address":"736 National Ave",
    "sg:city":"Lexington",
    "sg:classifiers":[
        {
            "category":"Education",
            "subcategory":"Dance Studio",
            "type":"Public Place"
        }
    ],
    "sg:phone":"+1 859 252 5245",
    "sg:postcode":"40502",
    "sg:province":"KY",
    "sg:tags":[
        "instruction",
        "dancing"
    ],
    "wof:name":"Kentucky Ballet Theatre",
    "wof:placetype":"venue"
},
  "geometry": {"coordinates":[-84.477847,38.039714],"type":"Point"}
}