{
  "type": "Feature",
  "properties": {
    "iso:country":"US",
    "sg:address":"477 W Main St",
    "sg:city":"Danville",
    "sg:classifiers":[
        {
            "category":"Autos & Motor Vehicles",
            "subcategory":"Fuel & Gas Station",
            "type":"Retail Goods"
        }
    ],
    "sg:phone":"+1 859 236 8817",
    "sg:postcode":"40422",
    "sg:province":"KY",
    "sg:tags":[
        "oil"
    ],
    "wof:name":"Main Street Marathon",
    "wof:placetype":"venue"
},
  "geometry": {"coordinates":[-84.774486,37.646025],"type":"Point"}
}