{
  "type": "Feature",
  "properties": {
    "addr:full":"487 N Lake Dr Prestonsburg KY 41653",
    "addr:housenumber":"487",
    "addr:postcode":"41653",
    "addr:street":"N Lake Dr",
    "iso:country":"US",
    "sg:address":"487 N Lake Dr",
    "sg:city":"Prestonsburg",
    "sg:classifiers":[
        {
            "category":"Restaurant",
            "type":"Food & Drink"
        }
    ],
    "sg:menulink":"http://www.allmenus.com/ky/prestonsburg/83789-papa-johns-pizza/menu/",
    "sg:phone":"+1 606 886 2800",
    "sg:postcode":"41653",
    "sg:province":"KY",
    "sg:tags":[
        "american",
        "pizza"
    ],
    "wof:name":"Papa John's Pizza",
    "wof:placetype":"venue"
},
  "geometry": {"coordinates":[-82.775182,37.670629],"type":"Point"}
}