{
  "type": "Feature",
  "properties": {
    "iso:country":"US",
    "sg:address":"9300 Shelbyville Rd",
    "sg:city":"Louisville",
    "sg:classifiers":[
        {
            "category":"Insurance",
            "subcategory":"Insurance Agent",
            "type":"Services"
        }
    ],
    "sg:phone":"+1 502 327 8589",
    "sg:postcode":"40222",
    "sg:province":"KY",
    "sg:website":"www.newyorklife.com",
    "wof:name":"New York Life Insurance Co",
    "wof:placetype":"venue"
},
  "geometry": {"coordinates":[-85.579438,38.24661],"type":"Point"}
}