{
  "type": "Feature",
  "properties": {
    "iso:country":"US",
    "sg:address":"225 W Center St",
    "sg:city":"Madisonville",
    "sg:classifiers":[
        {
            "category":"Food & Beverages",
            "subcategory":"Liquor & Beverages",
            "type":"Retail Goods"
        }
    ],
    "sg:phone":"+1 270 825 0360",
    "sg:postcode":"42431",
    "sg:province":"KY",
    "wof:name":"Coyle's Liquor Inc",
    "wof:placetype":"venue"
},
  "geometry": {"coordinates":[-87.50366,37.328817],"type":"Point"}
}