{
  "type": "Feature",
  "properties": {
    "iso:country":"US",
    "sg:address":"112 N Main St",
    "sg:city":"Elizabethtown",
    "sg:classifiers":[
        {
            "category":"Professional",
            "type":"Services"
        }
    ],
    "sg:phone":"+1 270 360 1441",
    "sg:postcode":"42701",
    "sg:province":"KY",
    "sg:tags":[
        "establishment"
    ],
    "wof:name":"ERA Canaan Assoc Inc",
    "wof:placetype":"venue"
},
  "geometry": {"coordinates":[-85.857698,37.693491],"type":"Point"}
}