{
  "type": "Feature",
  "properties": {
    "iso:country":"US",
    "sg:address":"6990 Happy Valley Rd",
    "sg:city":"Cave City",
    "sg:classifiers":[
        {
            "category":"Health Services",
            "subcategory":"Doctor",
            "type":"Services"
        }
    ],
    "sg:phone":"+1 270 773 5750",
    "sg:postcode":"42127",
    "sg:province":"KY",
    "sg:tags":[
        "physician",
        "surgeon"
    ],
    "wof:name":"William C Wells MD",
    "wof:placetype":"venue"
},
  "geometry": {"coordinates":[-85.971621,37.089087],"type":"Point"}
}