{
  "type": "Feature",
  "properties": {
    "iso:country":"US",
    "sg:address":"2275 Nicholasville Rd",
    "sg:city":"Lexington",
    "sg:classifiers":[
        {
            "category":"Restaurant",
            "type":"Food & Drink"
        }
    ],
    "sg:phone":"+1 859 277 2077",
    "sg:postcode":"40503",
    "sg:province":"KY",
    "wof:name":"Felton Company",
    "wof:placetype":"venue"
},
  "geometry": {"coordinates":[-84.51866200000001,38.005766],"type":"Point"}
}