{
  "type": "Feature",
  "properties": {
    "iso:country":"US",
    "sg:address":"729 W 3rd St",
    "sg:city":"Lexington",
    "sg:classifiers":[
        {
            "category":"Wholesale",
            "subcategory":"Fruits & Vegetables",
            "type":"Manufacturing & Wholesale Goods"
        }
    ],
    "sg:phone":"+1 859 254 3444",
    "sg:postcode":"40508",
    "sg:province":"KY",
    "wof:name":"Lexington Food Svc Inc",
    "wof:placetype":"venue"
},
  "geometry": {"coordinates":[-84.50238899999999,38.058319],"type":"Point"}
}