{
  "type": "Feature",
  "properties": {
    "iso:country":"US",
    "sg:address":"102 S Maplewood Dr",
    "sg:city":"Somerset",
    "sg:classifiers":[
        {
            "category":"Real Estate",
            "subcategory":"Real Estate Operator",
            "type":"Services"
        }
    ],
    "sg:phone":"+1 606 678 8974",
    "sg:postcode":"42501",
    "sg:province":"KY",
    "sg:tags":[
        "contractor"
    ],
    "wof:name":"George W Ping",
    "wof:placetype":"venue"
},
  "geometry": {"coordinates":[-84.579787,37.083422],"type":"Point"}
}