{
  "type": "Feature",
  "properties": {
    "iso:country":"US",
    "sg:address":"10699 US Hwy 60",
    "sg:city":"Ashland",
    "sg:classifiers":[
        {
            "category":"Shopping",
            "subcategory":"Crafts & Fabrics",
            "type":"Retail Goods"
        }
    ],
    "sg:phone":"+1 606 928 6898",
    "sg:postcode":"41102",
    "sg:province":"KY",
    "sg:tags":[
        "shop"
    ],
    "sg:website":"www.joann.com",
    "wof:name":"Jo-Ann Fabrics & Crafts",
    "wof:placetype":"venue"
},
  "geometry": {"coordinates":[-82.711229,38.398129],"type":"Point"}
}