{
  "type": "Feature",
  "properties": {
    "iso:country":"US",
    "sg:address":"2551 Bradley Dr",
    "sg:city":"Ashland",
    "sg:classifiers":[
        {
            "category":"Personal",
            "subcategory":"Beauty Salon",
            "type":"Services"
        }
    ],
    "sg:phone":"+1 606 325 2697",
    "sg:postcode":"41101",
    "sg:province":"KY",
    "sg:tags":[
        "shop"
    ],
    "wof:name":"Scissors Salon",
    "wof:placetype":"venue"
},
  "geometry": {"coordinates":[-82.628078,38.447614],"type":"Point"}
}