{
  "type": "Feature",
  "properties": {
    "iso:country":"US",
    "sg:address":"355 Charles Dr",
    "sg:city":"Mayfield",
    "sg:classifiers":[
        {
            "category":"Shopping",
            "subcategory":"Shoes",
            "type":"Retail Goods"
        }
    ],
    "sg:phone":"+1 270 247 8377",
    "sg:postcode":"42066",
    "sg:province":"KY",
    "wof:name":"Shoe Show",
    "wof:placetype":"venue"
},
  "geometry": {"coordinates":[-88.628315,36.718519],"type":"Point"}
}