{
  "type": "Feature",
  "properties": {
    "iso:country":"US",
    "sg:address":"116 Dennis Dr",
    "sg:city":"Lexington",
    "sg:classifiers":[
        {
            "category":"Professional",
            "type":"Services"
        }
    ],
    "sg:phone":"+1 859 278 7374",
    "sg:postcode":"40503",
    "sg:province":"KY",
    "sg:tags":[
        "establishment"
    ],
    "wof:name":"Frontline Support Solutions",
    "wof:placetype":"venue"
},
  "geometry": {"coordinates":[-84.52202200000001,38.003194],"type":"Point"}
}