{
  "type": "Feature",
  "properties": {
    "iso:country":"US",
    "sg:address":"357 River Rd",
    "sg:city":"Fort Thomas",
    "sg:classifiers":[
        {
            "category":"Shopping",
            "subcategory":"Stationery & Office Supplies",
            "type":"Retail Goods"
        }
    ],
    "sg:phone":"+1 859 442 5855",
    "sg:postcode":"41075",
    "sg:province":"KY",
    "sg:tags":[
        "map"
    ],
    "wof:name":"E-Qual Inc",
    "wof:placetype":"venue"
},
  "geometry": {"coordinates":[-84.445151,39.060292],"type":"Point"}
}