{
  "type": "Feature",
  "properties": {
    "addr:full":"1301 Winchester Rd Lexington KY 40505",
    "addr:housenumber":"1301",
    "addr:postcode":"40505",
    "addr:street":"Winchester Rd",
    "iso:country":"US",
    "sg:address":"1301 Winchester Rd",
    "sg:city":"Lexington",
    "sg:classifiers":[
        {
            "category":"Shopping",
            "subcategory":"Clothing, Apparel, & Fashions",
            "type":"Retail Goods"
        }
    ],
    "sg:phone":"+1 859 252 1089",
    "sg:postcode":"40505",
    "sg:province":"KY",
    "wof:name":"Final Cstm Sttch Tlrg Altering",
    "wof:placetype":"venue"
},
  "geometry": {"coordinates":[-84.456604,38.042972],"type":"Point"}
}