{
  "type": "Feature",
  "properties": {
    "iso:country":"US",
    "sg:address":"5370 Harrodsburg Rd",
    "sg:city":"Nicholasville",
    "sg:classifiers":[
        {
            "category":"Farming",
            "subcategory":"Farm",
            "type":"Manufacturing & Wholesale Goods"
        }
    ],
    "sg:phone":"+1 859 296 6691",
    "sg:postcode":"40356",
    "sg:province":"KY",
    "wof:name":"Kingswood Farm",
    "wof:placetype":"venue"
},
  "geometry": {"coordinates":[-84.597487,37.956064],"type":"Point"}
}