{
  "type": "Feature",
  "properties": {
    "iso:country":"US",
    "sg:address":"1035 Vandercar Way Ste 800",
    "sg:city":"Florence",
    "sg:classifiers":[
        {
            "category":"Restaurant",
            "type":"Food & Drink"
        }
    ],
    "sg:phone":"+1 859 371 6888",
    "sg:postcode":"41042",
    "sg:province":"KY",
    "sg:website":"www.memoriesofchina.com",
    "wof:name":"Memories Of China",
    "wof:placetype":"venue"
},
  "geometry": {"coordinates":[-84.65097,39.009223],"type":"Point"}
}