{
  "type": "Feature",
  "properties": {
    "iso:country":"US",
    "sg:address":"836 Northview St",
    "sg:city":"Paducah",
    "sg:classifiers":[
        {
            "category":"Freight",
            "type":"Transportation"
        }
    ],
    "sg:phone":"+1 270 442 1444",
    "sg:postcode":"42001",
    "sg:province":"KY",
    "sg:tags":[
        "operator",
        "trucking"
    ],
    "wof:name":"Estes Express Lines Inc",
    "wof:placetype":"venue"
},
  "geometry": {"coordinates":[-88.61801699999999,37.095092],"type":"Point"}
}