{
  "type": "Feature",
  "properties": {
    "iso:country":"US",
    "sg:address":"2619 H C Mathis Dr",
    "sg:city":"Paducah",
    "sg:classifiers":[
        {
            "category":"Banks & Credit Unions",
            "subcategory":"Bank",
            "type":"Services"
        }
    ],
    "sg:phone":"+1 270 415 9953",
    "sg:postcode":"42001",
    "sg:province":"KY",
    "sg:tags":[
        "cashing",
        "check"
    ],
    "wof:name":"Advance America",
    "wof:placetype":"venue"
},
  "geometry": {"coordinates":[-88.63364199999999,37.083165],"type":"Point"}
}