{
  "type": "Feature",
  "properties": {
    "iso:country":"US",
    "sg:address":"5155 Marrowbone Creek Rd",
    "sg:city":"Elkhorn City",
    "sg:classifiers":[
        {
            "category":"Retail",
            "subcategory":"Repair Shop",
            "type":"Services"
        }
    ],
    "sg:phone":"+1 606 754 8730",
    "sg:postcode":"41522",
    "sg:province":"KY",
    "sg:tags":[
        "related"
    ],
    "wof:name":"Bob Perrines Diesel Svc",
    "wof:placetype":"venue"
},
  "geometry": {"coordinates":[-82.458405,37.323469],"type":"Point"}
}