{
  "type": "Feature",
  "properties": {
    "iso:country":"US",
    "sg:address":"59 Paragon Dr",
    "sg:city":"Henderson",
    "sg:classifiers":[
        {
            "category":"Wholesale",
            "subcategory":"Furniture",
            "type":"Manufacturing & Wholesale Goods"
        }
    ],
    "sg:phone":"+1 270 826 6149",
    "sg:postcode":"42420",
    "sg:province":"KY",
    "wof:name":"Walden's Office Equipment Dstr",
    "wof:placetype":"venue"
},
  "geometry": {"coordinates":[-87.639703,37.800534],"type":"Point"}
}