{
  "type": "Feature",
  "properties": {
    "addr:full":"102 Sterling Ave Mt Sterling KY 40353",
    "addr:housenumber":"102",
    "addr:postcode":"40353",
    "addr:street":"Sterling Ave",
    "iso:country":"US",
    "sg:address":"102 Sterling Ave",
    "sg:city":"Mt Sterling",
    "sg:classifiers":[
        {
            "category":"Food & Beverages",
            "subcategory":"Liquor & Beverages",
            "type":"Retail Goods"
        }
    ],
    "sg:phone":"+1 859 498 1976",
    "sg:postcode":"40353",
    "sg:province":"KY",
    "wof:name":"Big Reds Liquors",
    "wof:placetype":"venue"
},
  "geometry": {"coordinates":[-83.947318,38.061658],"type":"Point"}
}