{
  "type": "Feature",
  "properties": {
    "addr:full":"500 W Main St Danville KY 40422",
    "addr:housenumber":"500",
    "addr:postcode":"40422",
    "addr:street":"W Main St",
    "iso:country":"US",
    "sg:address":"500 W Main St",
    "sg:city":"Danville",
    "sg:classifiers":[
        {
            "category":"Organizations",
            "subcategory":"Religious Organization",
            "type":"Services"
        }
    ],
    "sg:phone":"+1 859 236 6692",
    "sg:postcode":"40422",
    "sg:province":"KY",
    "sg:tags":[
        "church"
    ],
    "sg:website":"www.presbydan.org",
    "wof:name":"Presbyterian Church-Danville",
    "wof:placetype":"venue"
},
  "geometry": {"coordinates":[-84.77704799999999,37.646119],"type":"Point"}
}