{
  "type": "Feature",
  "properties": {
    "addr:full":"105 Main St Owenton KY 40359",
    "addr:housenumber":"105",
    "addr:postcode":"40359",
    "addr:street":"Main St",
    "iso:country":"US",
    "sg:address":"105 Main St",
    "sg:city":"Owenton",
    "sg:classifiers":[
        {
            "category":"Professional",
            "type":"Services"
        }
    ],
    "sg:phone":"+1 502 484 9121",
    "sg:postcode":"40359",
    "sg:province":"KY",
    "sg:tags":[
        "establishment"
    ],
    "wof:name":"Ghc Inc",
    "wof:placetype":"venue"
},
  "geometry": {"coordinates":[-84.953504,38.473753],"type":"Point"}
}