{
  "type": "Feature",
  "properties": {
    "iso:country":"US",
    "sg:address":"204 S Main St",
    "sg:city":"Harrodsburg",
    "sg:classifiers":[
        {
            "category":"Insurance",
            "subcategory":"Insurance Agent",
            "type":"Services"
        }
    ],
    "sg:phone":"+1 859 734 4358",
    "sg:postcode":"40330",
    "sg:province":"KY",
    "sg:website":"www.whitenacksouder.com",
    "wof:name":"Whitenack & Souder Insurance",
    "wof:placetype":"venue"
},
  "geometry": {"coordinates":[-84.843486,37.761188],"type":"Point"}
}