{
  "type": "Feature",
  "properties": {
    "addr:full":"911 S Brook St Louisville KY 40203",
    "addr:housenumber":"911",
    "addr:postcode":"40203",
    "addr:street":"S Brook St",
    "iso:country":"US",
    "sg:address":"911 S Brook St",
    "sg:city":"Louisville",
    "sg:classifiers":[
        {
            "category":"Building & Trades",
            "subcategory":"Cleaning & Sanitation",
            "type":"Services"
        },
        {
            "category":"Retail",
            "subcategory":"Laundry & Dry Cleaning",
            "type":"Services"
        }
    ],
    "sg:phone":"+1 502 595 8899",
    "sg:postcode":"40203",
    "sg:province":"KY",
    "sg:tags":[
        "cleaner",
        "contractor",
        "cleaning-industrial",
        "janitorial",
        "house"
    ],
    "wof:name":"Ward Edison Cleaning Service",
    "wof:placetype":"venue"
},
  "geometry": {"coordinates":[-85.752762,38.239738],"type":"Point"}
}