{
  "type": "Feature",
  "properties": {
    "iso:country":"US",
    "sg:address":"1346 S 3rd St",
    "sg:city":"Louisville",
    "sg:classifiers":[
        {
            "category":"Banks & Credit Unions",
            "subcategory":"Investment Brokerage",
            "type":"Services"
        }
    ],
    "sg:phone":"+1 502 636 5282",
    "sg:postcode":"40208",
    "sg:province":"KY",
    "sg:tags":[
        "advisory",
        "financial"
    ],
    "sg:website":"www.sachs-co.com",
    "wof:name":"Sachs Co",
    "wof:placetype":"venue"
},
  "geometry": {"coordinates":[-85.759703,38.228972],"type":"Point"}
}