{
  "type": "Feature",
  "properties": {
    "iso:country":"US",
    "sg:address":"4214 State Hwy 379",
    "sg:city":"Russell Springs",
    "sg:classifiers":[
        {
            "category":"Organizations",
            "subcategory":"Community Association",
            "type":"Services"
        }
    ],
    "sg:phone":"+1 270 343 3921",
    "sg:postcode":"42642",
    "sg:province":"KY",
    "sg:tags":[
        "club"
    ],
    "wof:name":"Lakewood Country Club",
    "wof:placetype":"venue"
},
  "geometry": {"coordinates":[-85.12124,37.015342],"type":"Point"}
}