{
  "type": "Feature",
  "properties": {
    "addr:full":"3730 Frankfort Ave Louisville KY 40207",
    "addr:housenumber":"3730",
    "addr:postcode":"40207",
    "addr:street":"Frankfort",
    "iso:country":"US",
    "sg:address":"3730 Frankfort Ave",
    "sg:city":"Louisville",
    "sg:classifiers":[
        {
            "category":"Sports & Exercise",
            "subcategory":"Gym",
            "type":"Entertainment"
        }
    ],
    "sg:phone":"+1 502 894 0601",
    "sg:postcode":"40207",
    "sg:province":"KY",
    "sg:tags":[
        "instruction",
        "yoga"
    ],
    "wof:name":"Bikram Yoga College Of India",
    "wof:placetype":"venue"
},
  "geometry": {"coordinates":[-85.65933200000001,38.25322],"type":"Point"}
}