{
  "type": "Feature",
  "properties": {
    "addr:full":"4101 Forsythe Dr Lexington KY 40514",
    "addr:housenumber":"4101",
    "addr:postcode":"40514",
    "addr:street":"Forsythe Dr",
    "iso:country":"US",
    "sg:address":"4101 Forsythe Dr",
    "sg:city":"Lexington",
    "sg:classifiers":[
        {
            "category":"Wholesale",
            "subcategory":"Photographic Equipment",
            "type":"Manufacturing & Wholesale Goods"
        }
    ],
    "sg:phone":"+1 859 224 3524",
    "sg:postcode":"40514",
    "sg:province":"KY",
    "sg:tags":[
        "identification"
    ],
    "wof:name":"Synergy Technologies Group",
    "wof:placetype":"venue"
},
  "geometry": {"coordinates":[-84.57311,38.001075],"type":"Point"}
}