{
  "type": "Feature",
  "properties": {
    "iso:country":"US",
    "sg:address":"227 Saint Ann St",
    "sg:city":"Owensboro",
    "sg:classifiers":[
        {
            "category":"Professional",
            "subcategory":"Lawyer & Legal Services",
            "type":"Services"
        }
    ],
    "sg:phone":"+1 270 926 2525",
    "sg:postcode":"42303",
    "sg:province":"KY",
    "sg:tags":[
        "attorney"
    ],
    "wof:name":"Wilson Wilson & Plain",
    "wof:placetype":"venue"
},
  "geometry": {"coordinates":[-87.11220400000001,37.774015],"type":"Point"}
}