{
  "type": "Feature",
  "properties": {
    "addr:full":"2220 Nicholasville Rd Lexington KY 40503",
    "addr:housenumber":"2220",
    "addr:postcode":"40503",
    "addr:street":"Nicholasville Rd",
    "iso:country":"US",
    "sg:address":"2220 Nicholasville Rd",
    "sg:city":"Lexington",
    "sg:classifiers":[
        {
            "category":"Cinema",
            "subcategory":"Movie Rental",
            "type":"Entertainment"
        }
    ],
    "sg:phone":"+1 859 373 1361",
    "sg:postcode":"40503",
    "sg:province":"KY",
    "sg:tags":[
        "leasing",
        "video",
        "disc",
        "tape"
    ],
    "wof:name":"Video Depot",
    "wof:placetype":"venue"
},
  "geometry": {"coordinates":[-84.517889,38.007383],"type":"Point"}
}