{
  "type": "Feature",
  "properties": {
    "iso:country":"US",
    "sg:address":"1800 Newtown Pike",
    "sg:city":"Lexington",
    "sg:classifiers":[
        {
            "category":"Retail",
            "subcategory":"Auto Rental",
            "type":"Services"
        }
    ],
    "sg:phone":"+1 859 225 5403",
    "sg:postcode":"40511",
    "sg:province":"KY",
    "sg:tags":[
        "passenger",
        "car"
    ],
    "wof:name":"Hertz",
    "wof:placetype":"venue"
},
  "geometry": {"coordinates":[-84.486352,38.095506],"type":"Point"}
}