{
  "type": "Feature",
  "properties": {
    "addr:full":"347 S Clay St Louisville KY 40202",
    "addr:housenumber":"347",
    "addr:postcode":"40202",
    "addr:street":"S Clay St",
    "iso:country":"US",
    "sg:address":"347 S Clay St",
    "sg:city":"Louisville",
    "sg:classifiers":[
        {
            "category":"Real Estate",
            "subcategory":"Real Estate Agent",
            "type":"Services"
        }
    ],
    "sg:phone":"+1 502 569 4088",
    "sg:postcode":"40202",
    "sg:province":"KY",
    "sg:tags":[
        "authorities",
        "housing"
    ],
    "wof:name":"Clarksdale East",
    "wof:placetype":"venue"
},
  "geometry": {"coordinates":[-85.740431,38.25082],"type":"Point"}
}