{
  "type": "Feature",
  "properties": {
    "addr:full":"1806 S 3rd St Louisville KY 40208",
    "addr:housenumber":"1806",
    "addr:postcode":"40208",
    "addr:street":"S 3Rd St",
    "iso:country":"US",
    "sg:address":"1806 S 3rd St",
    "sg:city":"Louisville",
    "sg:classifiers":[
        {
            "category":"Professional",
            "subcategory":"Research",
            "type":"Services"
        }
    ],
    "sg:phone":"+1 502 634 9124",
    "sg:postcode":"40208",
    "sg:province":"KY",
    "sg:tags":[
        "development",
        "laboratory"
    ],
    "wof:name":"ACB Inc",
    "wof:placetype":"venue"
},
  "geometry": {"coordinates":[-85.761239,38.220645],"type":"Point"}
}