{
  "type": "Feature",
  "properties": {
    "iso:country":"US",
    "sg:address":"3686 H Taylor Rd",
    "sg:city":"Kenton",
    "sg:classifiers":[
        {
            "category":"Shopping",
            "subcategory":"Florist",
            "type":"Retail Goods"
        }
    ],
    "sg:phone":"+1 731 749 5502",
    "sg:postcode":"38233",
    "sg:province":"TN",
    "wof:name":"Kenton Flower Shoppe",
    "wof:placetype":"venue"
},
  "geometry": {"coordinates":[-89.033879,36.239841],"type":"Point"}
}