{
  "type": "Feature",
  "properties": {
    "addr:full":"426 Memorial Dr Hazard KY 41701",
    "addr:housenumber":"426",
    "addr:postcode":"41701",
    "addr:street":"Memorial Dr",
    "iso:country":"US",
    "sg:address":"426 Memorial Dr",
    "sg:city":"Hazard",
    "sg:classifiers":[
        {
            "category":"Food & Beverages",
            "subcategory":"Groceries & Convenience Stores",
            "type":"Retail Goods"
        }
    ],
    "sg:phone":"+1 606 436 6117",
    "sg:postcode":"41701",
    "sg:province":"KY",
    "wof:name":"Pantry",
    "wof:placetype":"venue"
},
  "geometry": {"coordinates":[-83.193448,37.249312],"type":"Point"}
}