{
  "type": "Feature",
  "properties": {
    "iso:country":"US",
    "sg:address":"10531 Main Cross St",
    "sg:city":"Whitesville",
    "sg:classifiers":[
        {
            "category":"Restaurant",
            "type":"Food & Drink"
        }
    ],
    "sg:phone":"+1 270 233 9250",
    "sg:postcode":"42378",
    "sg:province":"KY",
    "wof:name":"Leaning Tower Of Pizza",
    "wof:placetype":"venue"
},
  "geometry": {"coordinates":[-86.87182,37.682148],"type":"Point"}
}