{
  "type": "Feature",
  "properties": {
    "addr:full":"4007 Dixie Hwy Louisville KY 40216",
    "addr:housenumber":"4007",
    "addr:postcode":"40216",
    "addr:street":"Dixie Hwy",
    "iso:country":"US",
    "sg:address":"4007 Dixie Hwy",
    "sg:city":"Louisville",
    "sg:classifiers":[
        {
            "category":"Organizations",
            "subcategory":"Religious Organization",
            "type":"Services"
        }
    ],
    "sg:phone":"+1 502 448 8546",
    "sg:postcode":"40216",
    "sg:province":"KY",
    "sg:tags":[
        "church"
    ],
    "wof:name":"St Helen Parish",
    "wof:placetype":"venue"
},
  "geometry": {"coordinates":[-85.80976,38.189579],"type":"Point"}
}