{
  "type": "Feature",
  "properties": {
    "iso:country":"US",
    "sg:address":"900 S Broadway St",
    "sg:city":"Georgetown",
    "sg:classifiers":[
        {
            "category":"Autos & Motor Vehicles",
            "subcategory":"Fuel & Gas Station",
            "type":"Retail Goods"
        }
    ],
    "sg:phone":"+1 502 868 9486",
    "sg:postcode":"40324",
    "sg:province":"KY",
    "sg:tags":[
        "oil"
    ],
    "wof:name":"Showalter Shell",
    "wof:placetype":"venue"
},
  "geometry": {"coordinates":[-84.56185600000001,38.192554],"type":"Point"}
}