{
  "type": "Feature",
  "properties": {
    "iso:country":"US",
    "sg:address":"853 Cardwell Ln",
    "sg:city":"Frankfort",
    "sg:classifiers":[
        {
            "category":"Real Estate",
            "subcategory":"Real Estate Operator",
            "type":"Services"
        }
    ],
    "sg:phone":"+1 502 875 1822",
    "sg:postcode":"40601",
    "sg:province":"KY",
    "sg:tags":[
        "apartment"
    ],
    "wof:name":"Sarah Apartments",
    "wof:placetype":"venue"
},
  "geometry": {"coordinates":[-84.918454,38.160856],"type":"Point"}
}