{
  "type": "Feature",
  "properties": {
    "addr:full":"315 Barricks Rd Louisville KY 40229",
    "addr:housenumber":"315",
    "addr:postcode":"40229",
    "addr:street":"Barricks Rd",
    "iso:country":"US",
    "sg:address":"315 Barricks Rd",
    "sg:city":"Louisville",
    "sg:classifiers":[
        {
            "category":"Professional",
            "type":"Services"
        }
    ],
    "sg:phone":"+1 502 955 4841",
    "sg:postcode":"40229",
    "sg:province":"KY",
    "sg:tags":[
        "establishment"
    ],
    "wof:name":"Handy Masters",
    "wof:placetype":"venue"
},
  "geometry": {"coordinates":[-85.701137,38.080425],"type":"Point"}
}