{
  "type": "Feature",
  "properties": {
    "addr:full":"3410 Montavesta Rd Lexington KY 40502",
    "addr:housenumber":"3410",
    "addr:postcode":"40502",
    "addr:street":"Montavesta Rd",
    "iso:country":"US",
    "sg:address":"3410 Montavesta Rd",
    "sg:city":"Lexington",
    "sg:classifiers":[
        {
            "category":"Building & Trades",
            "subcategory":"Construction",
            "type":"Services"
        }
    ],
    "sg:phone":"+1 859 494 3535",
    "sg:postcode":"40502",
    "sg:province":"KY",
    "sg:tags":[
        "house"
    ],
    "wof:name":"Hassloch Homes",
    "wof:placetype":"venue"
},
  "geometry": {"coordinates":[-84.48853699999999,37.997676],"type":"Point"}
}