{
  "type": "Feature",
  "properties": {
    "addr:full":"18830 E Big Creek Rd Sidney KY 41564",
    "addr:housenumber":"18830",
    "addr:postcode":"41564",
    "addr:street":"E Big Creek Rd",
    "iso:country":"US",
    "sg:address":"18830 E Big Creek Rd",
    "sg:city":"Sidney",
    "sg:classifiers":[
        {
            "category":"Shopping",
            "subcategory":"Florist",
            "type":"Retail Goods"
        }
    ],
    "sg:phone":"+1 606 353 1400",
    "sg:postcode":"41564",
    "sg:province":"KY",
    "wof:name":"Jean Ann's",
    "wof:placetype":"venue"
},
  "geometry": {"coordinates":[-82.332318,37.609586],"type":"Point"}
}