{
  "type": "Feature",
  "properties": {
    "addr:full":"4 W Washington St Winchester KY 40391",
    "addr:housenumber":"4",
    "addr:postcode":"40391",
    "addr:street":"W Washington St",
    "iso:country":"US",
    "sg:address":"4 W Washington St",
    "sg:city":"Winchester",
    "sg:classifiers":[
        {
            "category":"Food & Beverages",
            "subcategory":"Groceries & Convenience Stores",
            "type":"Retail Goods"
        }
    ],
    "sg:phone":"+1 859 744 1130",
    "sg:postcode":"40391",
    "sg:province":"KY",
    "wof:name":"J & B Foodmart",
    "wof:placetype":"venue"
},
  "geometry": {"coordinates":[-84.176789,37.995403],"type":"Point"}
}