{
  "type": "Feature",
  "properties": {
    "iso:country":"US",
    "sg:address":"114 Rainbow Dr",
    "sg:city":"Nicholasville",
    "sg:classifiers":[
        {
            "category":"Shopping",
            "subcategory":"Used Merchandise",
            "type":"Retail Goods"
        }
    ],
    "sg:phone":"+1 859 885 5995",
    "sg:postcode":"40356",
    "sg:province":"KY",
    "wof:name":"Vintage South Music & Pawn",
    "wof:placetype":"venue"
},
  "geometry": {"coordinates":[-84.57808199999999,37.896366],"type":"Point"}
}