{
  "type": "Feature",
  "properties": {
    "iso:country":"US",
    "sg:address":"2103 S Lake Dr",
    "sg:city":"Prestonsburg",
    "sg:classifiers":[
        {
            "category":"Utilities",
            "subcategory":"Sewage",
            "type":"Services"
        }
    ],
    "sg:phone":"+1 606 886 6181",
    "sg:postcode":"41653",
    "sg:province":"KY",
    "sg:tags":[
        "system",
        "sewerage"
    ],
    "wof:name":"Prestonsburg Utilities Coty",
    "wof:placetype":"venue"
},
  "geometry": {"coordinates":[-82.739954,37.668229],"type":"Point"}
}