{
  "type": "Feature",
  "properties": {
    "iso:country":"US",
    "sg:address":"115 Logsdon Rd",
    "sg:city":"Sonora",
    "sg:classifiers":[
        {
            "category":"Building & Trades",
            "subcategory":"Landscaping Services",
            "type":"Services"
        }
    ],
    "sg:phone":"+1 270 369 9057",
    "sg:postcode":"42776",
    "sg:province":"KY",
    "wof:name":"Ward Brother Mowing",
    "wof:placetype":"venue"
},
  "geometry": {"coordinates":[-85.862116,37.495105],"type":"Point"}
}