{
  "type": "Feature",
  "properties": {
    "iso:country":"US",
    "sg:address":"2360 Progress Dr",
    "sg:city":"Hebron",
    "sg:classifiers":[
        {
            "category":"Professional",
            "subcategory":"Business Services",
            "type":"Services"
        }
    ],
    "sg:phone":"+1 859 334 8500",
    "sg:postcode":"41048",
    "sg:province":"KY",
    "sg:tags":[
        "packaging"
    ],
    "wof:name":"Design Within Reach",
    "wof:placetype":"venue"
},
  "geometry": {"coordinates":[-84.654937,39.075547],"type":"Point"}
}