{
  "type": "Feature",
  "properties": {
    "iso:country":"US",
    "sg:address":"727 US Hwy 31 W Byp",
    "sg:city":"Bowling Green",
    "sg:classifiers":[
        {
            "category":"Health Services",
            "subcategory":"Doctor",
            "type":"Services"
        }
    ],
    "sg:phone":"+1 270 842 5300",
    "sg:postcode":"42101",
    "sg:province":"KY",
    "sg:tags":[
        "dentist"
    ],
    "wof:name":"Kelley Cherry DDS",
    "wof:placetype":"venue"
},
  "geometry": {"coordinates":[-86.43043299999999,36.986554],"type":"Point"}
}