{
  "type": "Feature",
  "properties": {
    "iso:country":"US",
    "sg:address":"1001 Millcreek Ct",
    "sg:city":"Lexington",
    "sg:classifiers":[
        {
            "category":"Communications",
            "type":"Services"
        }
    ],
    "sg:phone":"+1 859 273 1068",
    "sg:postcode":"40517",
    "sg:province":"KY",
    "wof:name":"Leisure Creek Communications",
    "wof:placetype":"venue"
},
  "geometry": {"coordinates":[-84.490832,37.978885],"type":"Point"}
}