{
  "type": "Feature",
  "properties": {
    "addr:full":"7510 US Hwy 42 Florence KY 41042",
    "addr:housenumber":"7510",
    "addr:postcode":"41042",
    "addr:street":"Us Hwy 42",
    "iso:country":"US",
    "sg:address":"7510 US Hwy 42",
    "sg:city":"Florence",
    "sg:classifiers":[
        {
            "category":"Health Services",
            "subcategory":"Doctor",
            "type":"Services"
        }
    ],
    "sg:phone":"+1 859 525 6215",
    "sg:postcode":"41042",
    "sg:province":"KY",
    "sg:tags":[
        "physician",
        "surgeon"
    ],
    "wof:name":"Mid West Eye Ctr",
    "wof:placetype":"venue"
},
  "geometry": {"coordinates":[-84.632356,38.995415],"type":"Point"}
}