{
  "type": "Feature",
  "properties": {
    "addr:full":"43 Arrowhead Dr Alexandria KY 41001",
    "addr:housenumber":"43",
    "addr:postcode":"41001",
    "addr:street":"Arrowhead Dr",
    "iso:country":"US",
    "sg:address":"43 Arrowhead Dr",
    "sg:city":"Alexandria",
    "sg:classifiers":[
        {
            "category":"Professional",
            "subcategory":"Management & Consulting",
            "type":"Services"
        }
    ],
    "sg:phone":"+1 859 635 2668",
    "sg:postcode":"41001",
    "sg:province":"KY",
    "wof:name":"Glenn Walter & Assoc Inc",
    "wof:placetype":"venue"
},
  "geometry": {"coordinates":[-84.389241,38.975347],"type":"Point"}
}