{
  "type": "Feature",
  "properties": {
    "addr:full":"101 Ponder Ct Danville KY 40422",
    "addr:housenumber":"101",
    "addr:postcode":"40422",
    "addr:street":"Ponder Ct",
    "iso:country":"US",
    "sg:address":"101 Ponder Ct",
    "sg:city":"Danville",
    "sg:classifiers":[
        {
            "category":"Insurance",
            "subcategory":"Insurance Agent",
            "type":"Services"
        }
    ],
    "sg:phone":"+1 859 236 6771",
    "sg:postcode":"40422",
    "sg:province":"KY",
    "wof:name":"Monumental Life Insurance Co",
    "wof:placetype":"venue"
},
  "geometry": {"coordinates":[-84.80094699999999,37.654931],"type":"Point"}
}