{
  "type": "Feature",
  "properties": {
    "iso:country":"US",
    "sg:address":"402 W College St",
    "sg:city":"Wilmore",
    "sg:classifiers":[
        {
            "category":"Social Services",
            "type":"Services"
        }
    ],
    "sg:phone":"+1 859 858 3734",
    "sg:postcode":"40390",
    "sg:province":"KY",
    "sg:tags":[
        "organization",
        "welfare"
    ],
    "wof:name":"Salvation Army Student Ctr",
    "wof:placetype":"venue"
},
  "geometry": {"coordinates":[-84.66535500000001,37.865014],"type":"Point"}
}