{
  "type": "Feature",
  "properties": {
    "addr:full":"3317 Fern Valley Rd Louisville KY 40213",
    "addr:housenumber":"3317",
    "addr:postcode":"40213",
    "addr:street":"Fern Valley Rd",
    "iso:country":"US",
    "sg:address":"3317 Fern Valley Rd",
    "sg:city":"Louisville",
    "sg:classifiers":[
        {
            "category":"Travel",
            "subcategory":"Hotels & Motels",
            "type":"Entertainment"
        }
    ],
    "sg:phone":"+1 502 964 3311",
    "sg:postcode":"40213",
    "sg:province":"KY",
    "wof:name":"Holiday Inn",
    "wof:placetype":"venue"
},
  "geometry": {"coordinates":[-85.702749,38.157039],"type":"Point"}
}