{
  "type": "Feature",
  "properties": {
    "iso:country":"US",
    "sg:address":"874 Bypass Rd",
    "sg:city":"Winchester",
    "sg:classifiers":[
        {
            "category":"Personal",
            "subcategory":"Tanning Parlor",
            "type":"Services"
        }
    ],
    "sg:phone":"+1 859 745 1157",
    "sg:postcode":"40391",
    "sg:province":"KY",
    "sg:tags":[
        "salon"
    ],
    "wof:name":"Sun Hut Tanning Salon",
    "wof:placetype":"venue"
},
  "geometry": {"coordinates":[-84.212766,38.001868],"type":"Point"}
}