{
  "type": "Feature",
  "properties": {
    "addr:full":"2100 29th St Ashland KY 41101",
    "addr:housenumber":"2100",
    "addr:postcode":"41101",
    "addr:street":"29Th St",
    "iso:country":"US",
    "sg:address":"2100 29th St",
    "sg:city":"Ashland",
    "sg:classifiers":[
        {
            "category":"Wholesale",
            "subcategory":"Furniture",
            "type":"Manufacturing & Wholesale Goods"
        }
    ],
    "sg:phone":"+1 606 329 1400",
    "sg:postcode":"41101",
    "sg:province":"KY",
    "sg:website":"www.ashlandoffice.com",
    "wof:name":"Ashland Office Supply Inc",
    "wof:placetype":"venue"
},
  "geometry": {"coordinates":[-82.643215,38.459434],"type":"Point"}
}