{
  "type": "Feature",
  "properties": {
    "addr:full":"1489 Dixie Hwy N Radcliff KY 40160",
    "addr:housenumber":"1489",
    "addr:postcode":"40160",
    "addr:street":"Dixie Hwy N",
    "iso:country":"US",
    "sg:address":"1489 Dixie Hwy N",
    "sg:city":"Radcliff",
    "sg:classifiers":[
        {
            "category":"Organizations",
            "subcategory":"Religious Organization",
            "type":"Services"
        }
    ],
    "sg:phone":"+1 270 352 0771",
    "sg:postcode":"40160",
    "sg:province":"KY",
    "sg:tags":[
        "church"
    ],
    "wof:name":"Hope Temple Church-God-Christ",
    "wof:placetype":"venue"
},
  "geometry": {"coordinates":[-85.952066,37.85466],"type":"Point"}
}