{
  "type": "Feature",
  "properties": {
    "iso:country":"US",
    "sg:address":"8111A la Grange Rd",
    "sg:city":"Louisville",
    "sg:classifiers":[
        {
            "category":"Arts & Performance",
            "subcategory":"Dance",
            "type":"Entertainment"
        }
    ],
    "sg:phone":"+1 502 425 6700",
    "sg:postcode":"40222",
    "sg:province":"KY",
    "sg:tags":[
        "instruction",
        "dancing"
    ],
    "sg:website":"http://www.eliteacademyofdanceandperformingarts.com",
    "wof:name":"Elite Academy Of Dance & Performing Arts",
    "wof:placetype":"venue"
},
  "geometry": {"coordinates":[-85.605512,38.262387],"type":"Point"}
}