{
  "type": "Feature",
  "properties": {
    "iso:country":"US",
    "sg:address":"8419 Biggin Hill Ln",
    "sg:city":"Louisville",
    "sg:classifiers":[
        {
            "category":"Recreation",
            "type":"Entertainment"
        }
    ],
    "sg:phone":"+1 502 493 9247",
    "sg:postcode":"40220",
    "sg:province":"KY",
    "wof:name":"Rhythmic Gymnastics",
    "wof:placetype":"venue"
},
  "geometry": {"coordinates":[-85.598208,38.209587],"type":"Point"}
}