{
  "type": "Feature",
  "properties": {
    "addr:full":"6106 Dutchmans Ln Louisville KY 40205",
    "addr:housenumber":"6106",
    "addr:postcode":"40205",
    "addr:street":"Dutchmans Ln",
    "iso:country":"US",
    "sg:address":"6106 Dutchmans Ln",
    "sg:city":"Louisville",
    "sg:classifiers":[
        {
            "category":"Banks & Credit Unions",
            "subcategory":"Bank",
            "type":"Services"
        }
    ],
    "sg:phone":"+1 502 000 1111",
    "sg:postcode":"40205",
    "sg:province":"KY",
    "wof:name":"Citizens Union Bank",
    "wof:placetype":"venue"
},
  "geometry": {"coordinates":[-85.641696,38.227827],"type":"Point"}
}