{
  "type": "Feature",
  "properties": {
    "addr:full":"228 Brownsville Rd Morgantown KY 42261",
    "addr:housenumber":"228",
    "addr:postcode":"42261",
    "addr:street":"Brownsville Rd",
    "iso:country":"US",
    "sg:address":"228 Brownsville Rd",
    "sg:city":"Morgantown",
    "sg:classifiers":[
        {
            "category":"Travel",
            "subcategory":"Travel Agent",
            "type":"Entertainment"
        }
    ],
    "sg:phone":"+1 270 526 2605",
    "sg:postcode":"42261",
    "sg:province":"KY",
    "sg:tags":[
        "agency",
        "bureau"
    ],
    "wof:name":"Vactrav Inc",
    "wof:placetype":"venue"
},
  "geometry": {"coordinates":[-86.68652899999999,37.267925],"type":"Point"}
}