{
  "type": "Feature",
  "properties": {
    "addr:full":"875 Woodman Creek Rd Freeburn KY 41547",
    "addr:housenumber":"875",
    "addr:postcode":"41547",
    "addr:street":"Woodman Creek Rd",
    "iso:country":"US",
    "sg:address":"875 Woodman Creek Rd",
    "sg:city":"Freeburn",
    "sg:classifiers":[
        {
            "category":"Professional",
            "type":"Services"
        }
    ],
    "sg:phone":"+1 606 456 7444",
    "sg:postcode":"41547",
    "sg:province":"KY",
    "sg:tags":[
        "establishment"
    ],
    "wof:name":"Universal Compression Inc",
    "wof:placetype":"venue"
},
  "geometry": {"coordinates":[-82.08865299999999,37.55483],"type":"Point"}
}