{
  "type": "Feature",
  "properties": {
    "addr:full":"121 W Daugherty Ave Bardstown KY 40004",
    "addr:housenumber":"121",
    "addr:postcode":"40004",
    "addr:street":"W Daugherty Ave",
    "iso:country":"US",
    "sg:address":"121 W Daugherty Ave",
    "sg:city":"Bardstown",
    "sg:classifiers":[
        {
            "category":"Home & Garden",
            "subcategory":"Furniture",
            "type":"Retail Goods"
        }
    ],
    "sg:phone":"+1 502 331 9699",
    "sg:postcode":"40004",
    "sg:province":"KY",
    "wof:name":"Peddler's Paradise",
    "wof:placetype":"venue"
},
  "geometry": {"coordinates":[-85.463892,37.819633],"type":"Point"}
}