{
  "type": "Feature",
  "properties": {
    "addr:full":"1902 Russellville Rd Bowling Green KY 42101",
    "addr:housenumber":"1902",
    "addr:postcode":"42101",
    "addr:street":"Russellville Rd",
    "iso:country":"US",
    "sg:address":"1902 Russellville Rd",
    "sg:city":"Bowling Green",
    "sg:classifiers":[
        {
            "category":"Autos & Motor Vehicles",
            "subcategory":"Automobile Sales",
            "type":"Retail Goods"
        }
    ],
    "sg:phone":"+1 270 843 6841",
    "sg:postcode":"42101",
    "sg:province":"KY",
    "sg:tags":[
        "car",
        "dealer"
    ],
    "wof:name":"West Side Motors",
    "wof:placetype":"venue"
},
  "geometry": {"coordinates":[-86.467636,36.979781],"type":"Point"}
}