{
  "type": "Feature",
  "properties": {
    "iso:country":"US",
    "sg:address":"433 Big Hill Ave",
    "sg:city":"Richmond",
    "sg:classifiers":[
        {
            "category":"Retail",
            "subcategory":"Auto Repair",
            "type":"Services"
        }
    ],
    "sg:phone":"+1 859 626 5674",
    "sg:postcode":"40475",
    "sg:province":"KY",
    "sg:tags":[
        "wheel",
        "axle",
        "alignment"
    ],
    "wof:name":"A1 Alignment",
    "wof:placetype":"venue"
},
  "geometry": {"coordinates":[-84.28217100000001,37.738864],"type":"Point"}
}