{
  "type": "Feature",
  "properties": {
    "iso:country":"US",
    "sg:address":"4105 Metropolis Lake Rd",
    "sg:city":"West Paducah",
    "sg:classifiers":[
        {
            "category":"Building & Trades",
            "subcategory":"Construction",
            "type":"Services"
        }
    ],
    "sg:phone":"+1 270 488 2005",
    "sg:postcode":"42086",
    "sg:province":"KY",
    "sg:tags":[
        "residential",
        "commercial",
        "painting"
    ],
    "wof:name":"Don Driver Painting",
    "wof:placetype":"venue"
},
  "geometry": {"coordinates":[-88.79667000000001,37.075225],"type":"Point"}
}