{
  "type": "Feature",
  "properties": {
    "addr:full":"9555 Taylorsville Rd Louisville KY 40299",
    "addr:housenumber":"9555",
    "addr:postcode":"40299",
    "addr:street":"Taylorsville Rd",
    "iso:country":"US",
    "sg:address":"9555 Taylorsville Rd",
    "sg:city":"Louisville",
    "sg:classifiers":[
        {
            "category":"Personal",
            "subcategory":"Barber",
            "type":"Services"
        }
    ],
    "sg:phone":"+1 502 267 2004",
    "sg:postcode":"40299",
    "sg:province":"KY",
    "wof:name":"Cutting It Close",
    "wof:placetype":"venue"
},
  "geometry": {"coordinates":[-85.577122,38.203866],"type":"Point"}
}