{
  "type": "Feature",
  "properties": {
    "addr:full":"123 E 6th St Lexington KY 40508",
    "addr:housenumber":"123",
    "addr:postcode":"40508",
    "addr:street":"E 6Th St",
    "iso:country":"US",
    "sg:address":"123 E 6th St",
    "sg:city":"Lexington",
    "sg:classifiers":[
        {
            "category":"Education",
            "subcategory":"School",
            "type":"Public Place"
        }
    ],
    "sg:phone":"+1 859 381 3162",
    "sg:postcode":"40508",
    "sg:province":"KY",
    "wof:name":"Johnson Elementary School",
    "wof:placetype":"venue"
},
  "geometry": {"coordinates":[-84.484797,38.05259],"type":"Point"}
}