{
  "type": "Feature",
  "properties": {
    "iso:country":"US",
    "sg:address":"1000 Cumberland Falls Hwy",
    "sg:city":"Corbin",
    "sg:classifiers":[
        {
            "category":"Personal",
            "subcategory":"Beauty Salon",
            "type":"Services"
        }
    ],
    "sg:phone":"+1 606 528 5406",
    "sg:postcode":"40701",
    "sg:province":"KY",
    "sg:tags":[
        "manicuring"
    ],
    "wof:name":"Le's Nails",
    "wof:placetype":"venue"
},
  "geometry": {"coordinates":[-84.10227999999999,36.930136],"type":"Point"}
}