{
  "type": "Feature",
  "properties": {
    "addr:full":"2824 Farrell Cres Owensboro KY 42303",
    "addr:housenumber":"2824",
    "addr:postcode":"42303",
    "addr:street":"Farrell Cres",
    "iso:country":"US",
    "sg:address":"2824 Farrell Cres",
    "sg:city":"Owensboro",
    "sg:classifiers":[
        {
            "category":"Health Services",
            "subcategory":"Doctor",
            "type":"Services"
        }
    ],
    "sg:phone":"+1 270 684 1184",
    "sg:postcode":"42303",
    "sg:province":"KY",
    "sg:tags":[
        "dentist"
    ],
    "wof:name":"Michael S Austin DDS",
    "wof:placetype":"venue"
},
  "geometry": {"coordinates":[-87.09551,37.746948],"type":"Point"}
}