{
  "type": "Feature",
  "properties": {
    "addr:full":"3410 Revere St Greenup KY 41144",
    "addr:housenumber":"3410",
    "addr:postcode":"41144",
    "addr:street":"Revere St",
    "iso:country":"US",
    "sg:address":"3410 Revere St",
    "sg:city":"Greenup",
    "sg:classifiers":[
        {
            "category":"Professional",
            "subcategory":"Business Services",
            "type":"Services"
        }
    ],
    "sg:phone":"+1 606 473 0707",
    "sg:postcode":"41144",
    "sg:province":"KY",
    "wof:name":"Marth and Company",
    "wof:placetype":"venue"
},
  "geometry": {"coordinates":[-82.867688,38.622326],"type":"Point"}
}