{
  "type": "Feature",
  "properties": {
    "iso:country":"US",
    "sg:address":"1510 Ring Rd",
    "sg:city":"Elizabethtown",
    "sg:classifiers":[
        {
            "category":"Home & Garden",
            "subcategory":"Building Materials",
            "type":"Retail Goods"
        }
    ],
    "sg:phone":"+1 270 763 1107",
    "sg:postcode":"42701",
    "sg:province":"KY",
    "sg:tags":[
        "center"
    ],
    "sg:website":"www.homedepot.com",
    "wof:name":"Home Depot",
    "wof:placetype":"venue"
},
  "geometry": {"coordinates":[-85.886471,37.727571],"type":"Point"}
}