{
  "type": "Feature",
  "properties": {
    "iso:country":"US",
    "sg:address":"2304 Algonquin Pkwy",
    "sg:city":"Louisville",
    "sg:classifiers":[
        {
            "category":"Professional",
            "type":"Services"
        }
    ],
    "sg:phone":"+1 502 774 1838",
    "sg:postcode":"40210",
    "sg:province":"KY",
    "sg:tags":[
        "establishment"
    ],
    "wof:name":"Pastor's Study",
    "wof:placetype":"venue"
},
  "geometry": {"coordinates":[-85.80015299999999,38.223632],"type":"Point"}
}