{
  "type": "Feature",
  "properties": {
    "iso:country":"US",
    "sg:address":"78 E Main St",
    "sg:city":"Fordsville",
    "sg:classifiers":[
        {
            "category":"Banks & Credit Unions",
            "subcategory":"Bank",
            "type":"Services"
        }
    ],
    "sg:phone":"+1 270 926 6079",
    "sg:postcode":"42343",
    "sg:province":"KY",
    "sg:website":"www.cwcbank.com",
    "wof:name":"Commonwealth Community Bank",
    "wof:placetype":"venue"
},
  "geometry": {"coordinates":[-86.716267,37.635434],"type":"Point"}
}