{
  "type": "Feature",
  "properties": {
    "iso:country":"US",
    "sg:address":"3502 Ridge Top Ct",
    "sg:city":"Louisville",
    "sg:classifiers":[
        {
            "category":"Professional",
            "subcategory":"Management & Consulting",
            "type":"Services"
        }
    ],
    "sg:phone":"+1 502 327 8260",
    "sg:postcode":"40241",
    "sg:province":"KY",
    "sg:tags":[
        "consultant",
        "business"
    ],
    "wof:name":"Consultwave Inc",
    "wof:placetype":"venue"
},
  "geometry": {"coordinates":[-85.618876,38.301708],"type":"Point"}
}