{
  "type": "Feature",
  "properties": {
    "iso:country":"US",
    "sg:address":"429 W Muhammad Ali Blvd",
    "sg:city":"Louisville",
    "sg:classifiers":[
        {
            "category":"Professional",
            "subcategory":"Lawyer & Legal Services",
            "type":"Services"
        }
    ],
    "sg:phone":"+1 502 585 5800",
    "sg:postcode":"40202",
    "sg:province":"KY",
    "sg:tags":[
        "attorney"
    ],
    "wof:name":"Gardner Ewing & Souza",
    "wof:placetype":"venue"
},
  "geometry": {"coordinates":[-85.757796,38.251231],"type":"Point"}
}