{
  "type": "Feature",
  "properties": {
    "iso:country":"US",
    "sg:address":"10786 Dixie Hwy",
    "sg:city":"Walton",
    "sg:classifiers":[
        {
            "category":"Bars & Pubs",
            "type":"Food & Drink"
        }
    ],
    "sg:phone":"+1 859 371 0707",
    "sg:postcode":"41094",
    "sg:province":"KY",
    "sg:tags":[
        "club",
        "night"
    ],
    "wof:name":"Special K's Sports Cafe",
    "wof:placetype":"venue"
},
  "geometry": {"coordinates":[-84.62649999999999,38.932204],"type":"Point"}
}