{
  "type": "Feature",
  "properties": {
    "addr:full":"3215 Cairo Rd Paducah KY 42001",
    "addr:housenumber":"3215",
    "addr:postcode":"42001",
    "addr:street":"Cairo Rd",
    "iso:country":"US",
    "sg:address":"3215 Cairo Rd",
    "sg:city":"Paducah",
    "sg:classifiers":[
        {
            "category":"Place Of Worship",
            "subcategory":"Church",
            "type":"Public Place"
        },
        {
            "category":"Place Of Worship",
            "type":"Public Place"
        },
        {
            "category":"Organizations",
            "subcategory":"Religious Organization",
            "type":"Services"
        }
    ],
    "sg:phone":"+1 270 442 4513",
    "sg:postcode":"42001",
    "sg:province":"KY",
    "sg:tags":[
        "god",
        "churches-church",
        "churches-pentecostal"
    ],
    "wof:name":"Northside Church",
    "wof:placetype":"venue"
},
  "geometry": {"coordinates":[-88.651804,37.099011],"type":"Point"}
}