{
  "type": "Feature",
  "properties": {
    "addr:full":"9108 Loch Lea Ln Louisville KY 40291",
    "addr:housenumber":"9108",
    "addr:postcode":"40291",
    "addr:street":"Loch Lea Ln",
    "iso:country":"US",
    "sg:address":"9108 Loch Lea Ln",
    "sg:city":"Louisville",
    "sg:classifiers":[
        {
            "category":"Personal",
            "subcategory":"Beauty Salon",
            "type":"Services"
        }
    ],
    "sg:phone":"+1 502 231 9987",
    "sg:postcode":"40291",
    "sg:province":"KY",
    "sg:tags":[
        "shop"
    ],
    "wof:name":"Suburban Beauty Shop",
    "wof:placetype":"venue"
},
  "geometry": {"coordinates":[-85.590152,38.174896],"type":"Point"}
}