{
  "type": "Feature",
  "properties": {
    "iso:country":"US",
    "sg:address":"700 Wales Run Rd",
    "sg:city":"Mount Washington",
    "sg:classifiers":[
        {
            "category":"Building & Trades",
            "subcategory":"Plumbing",
            "type":"Services"
        }
    ],
    "sg:phone":"+1 502 538 3017",
    "sg:postcode":"40047",
    "sg:province":"KY",
    "sg:tags":[
        "contractor"
    ],
    "wof:name":"Energy Systems",
    "wof:placetype":"venue"
},
  "geometry": {"coordinates":[-85.572102,38.054622],"type":"Point"}
}