{
  "type": "Feature",
  "properties": {
    "iso:country":"US",
    "sg:address":"1815 Island Creek Rd",
    "sg:city":"Pikeville",
    "sg:classifiers":[
        {
            "category":"Professional",
            "subcategory":"Testing Lab",
            "type":"Services"
        }
    ],
    "sg:phone":"+1 606 432 2511",
    "sg:postcode":"41501",
    "sg:province":"KY",
    "sg:tags":[
        "laboratory"
    ],
    "sg:website":"www.comteco.com",
    "wof:name":"SGS North America Inc",
    "wof:placetype":"venue"
},
  "geometry": {"coordinates":[-82.53375,37.45265],"type":"Point"}
}