{
  "type": "Feature",
  "properties": {
    "iso:country":"US",
    "sg:address":"4001 Kelly Ave",
    "sg:city":"Crestwood",
    "sg:classifiers":[
        {
            "category":"Building & Trades",
            "subcategory":"Construction",
            "type":"Services"
        }
    ],
    "sg:phone":"+1 502 241 5044",
    "sg:postcode":"40014",
    "sg:province":"KY",
    "sg:tags":[
        "carpentry",
        "contractor"
    ],
    "wof:name":"Jeff Owens Contracting",
    "wof:placetype":"venue"
},
  "geometry": {"coordinates":[-85.42089199999999,38.316004],"type":"Point"}
}