{
  "type": "Feature",
  "properties": {
    "addr:full":"912 S Main St Madisonville KY 42431",
    "addr:housenumber":"912",
    "addr:postcode":"42431",
    "addr:street":"S Main St",
    "iso:country":"US",
    "sg:address":"912 S Main St",
    "sg:city":"Madisonville",
    "sg:classifiers":[
        {
            "category":"Food & Beverages",
            "subcategory":"Groceries & Convenience Stores",
            "type":"Retail Goods"
        }
    ],
    "sg:phone":"+1 270 821 0431",
    "sg:postcode":"42431",
    "sg:province":"KY",
    "sg:tags":[
        "grocer"
    ],
    "wof:name":"Tienda LA Familiar",
    "wof:placetype":"venue"
},
  "geometry": {"coordinates":[-87.502422,37.314321],"type":"Point"}
}