{
  "type": "Feature",
  "properties": {
    "iso:country":"US",
    "sg:address":"900 Coldwater Rd",
    "sg:city":"Murray",
    "sg:classifiers":[
        {
            "category":"Personal",
            "subcategory":"Beauty Salon",
            "type":"Services"
        }
    ],
    "sg:phone":"+1 270 759 1100",
    "sg:postcode":"42071",
    "sg:province":"KY",
    "wof:name":"Attidues Hair Design",
    "wof:placetype":"venue"
},
  "geometry": {"coordinates":[-88.327134,36.619065],"type":"Point"}
}