{
  "type": "Feature",
  "properties": {
    "iso:country":"US",
    "sg:address":"12282 Hodgenville Rd",
    "sg:city":"Mount Sherman",
    "sg:classifiers":[
        {
            "category":"Real Estate",
            "subcategory":"Real Estate Agent",
            "type":"Services"
        }
    ],
    "sg:phone":"+1 270 932 5247",
    "sg:postcode":"42764",
    "sg:province":"KY",
    "wof:name":"Pldr Properties LLC",
    "wof:placetype":"venue"
},
  "geometry": {"coordinates":[-85.611982,37.39147],"type":"Point"}
}