{
  "type": "Feature",
  "properties": {
    "addr:full":"10507 Edgewater Rd Louisville KY 40223",
    "addr:housenumber":"10507",
    "addr:postcode":"40223",
    "addr:street":"Edgewater Rd",
    "iso:country":"US",
    "sg:address":"10507 Edgewater Rd",
    "sg:city":"Louisville",
    "sg:classifiers":[
        {
            "category":"Shopping",
            "subcategory":"Gifts & Souvenirs",
            "type":"Retail Goods"
        }
    ],
    "sg:phone":"+1 502 244 9290",
    "sg:postcode":"40223",
    "sg:province":"KY",
    "wof:name":"Rogers Stephane",
    "wof:placetype":"venue"
},
  "geometry": {"coordinates":[-85.559016,38.229119],"type":"Point"}
}