{
  "type": "Feature",
  "properties": {
    "iso:country":"US",
    "sg:address":"1599 Union Chapel Rd",
    "sg:city":"Scottsville",
    "sg:classifiers":[
        {
            "category":"Organizations",
            "subcategory":"Religious Organization",
            "type":"Services"
        }
    ],
    "sg:phone":"+1 270 622 8379",
    "sg:postcode":"42164",
    "sg:province":"KY",
    "sg:tags":[
        "church"
    ],
    "wof:name":"Union Chapel United Methodist",
    "wof:placetype":"venue"
},
  "geometry": {"coordinates":[-86.18752600000001,36.678948],"type":"Point"}
}