{
  "type": "Feature",
  "properties": {
    "addr:full":"287 Richwood Rd Walton KY 41094",
    "addr:housenumber":"287",
    "addr:postcode":"41094",
    "addr:street":"Richwood Rd",
    "iso:country":"US",
    "sg:address":"287 Richwood Rd",
    "sg:city":"Walton",
    "sg:classifiers":[
        {
            "category":"Banks & Credit Unions",
            "subcategory":"Bank",
            "type":"Services"
        }
    ],
    "sg:phone":"+1 859 485 6611",
    "sg:postcode":"41094",
    "sg:province":"KY",
    "wof:name":"Huntington National Bank",
    "wof:placetype":"venue"
},
  "geometry": {"coordinates":[-84.63234799999999,38.916589],"type":"Point"}
}