{
  "type": "Feature",
  "properties": {
    "addr:full":"3679 Niagara Dr Lexington KY 40517",
    "addr:housenumber":"3679",
    "addr:postcode":"40517",
    "addr:street":"Niagara Dr",
    "iso:country":"US",
    "sg:address":"3679 Niagara Dr",
    "sg:city":"Lexington",
    "sg:classifiers":[
        {
            "category":"Professional",
            "type":"Services"
        }
    ],
    "sg:phone":"+1 859 245 2041",
    "sg:postcode":"40517",
    "sg:province":"KY",
    "sg:tags":[
        "establishment"
    ],
    "wof:name":"W & B Enterprises",
    "wof:placetype":"venue"
},
  "geometry": {"coordinates":[-84.477796,37.968748],"type":"Point"}
}