{
  "type": "Feature",
  "properties": {
    "iso:country":"US",
    "sg:address":"3606 Klondike Ln",
    "sg:city":"Louisville",
    "sg:classifiers":[
        {
            "category":"Health Services",
            "subcategory":"Doctor",
            "type":"Services"
        }
    ],
    "sg:phone":"+1 502 895 8218",
    "sg:postcode":"40218",
    "sg:province":"KY",
    "sg:tags":[
        "physician",
        "endocrinology",
        "surgeons",
        "surgeon",
        "metabolism",
        "diabetes"
    ],
    "wof:name":"Endocrine Associates",
    "wof:placetype":"venue"
},
  "geometry": {"coordinates":[-85.640102,38.210538],"type":"Point"}
}