{
  "type": "Feature",
  "properties": {
    "addr:full":"138 Washington Ct Mt Washington KY 40047",
    "addr:housenumber":"138",
    "addr:postcode":"40047",
    "addr:street":"Washington Ct",
    "iso:country":"US",
    "sg:address":"138 Washington Ct",
    "sg:city":"Mt Washington",
    "sg:classifiers":[
        {
            "category":"Real Estate",
            "subcategory":"Surveying",
            "type":"Services"
        }
    ],
    "sg:phone":"+1 502 538 6616",
    "sg:postcode":"40047",
    "sg:province":"KY",
    "sg:tags":[
        "surveyor"
    ],
    "wof:name":"St Clair Land Surveying",
    "wof:placetype":"venue"
},
  "geometry": {"coordinates":[-85.558136,38.059159],"type":"Point"}
}