{
  "type": "Feature",
  "properties": {
    "iso:country":"US",
    "sg:address":"110 W 3rd St",
    "sg:city":"Tompkinsville",
    "sg:classifiers":[
        {
            "category":"Professional",
            "subcategory":"Lawyer & Legal Services",
            "type":"Services"
        }
    ],
    "sg:phone":"+1 270 487 6932",
    "sg:postcode":"42167",
    "sg:province":"KY",
    "sg:tags":[
        "attorney"
    ],
    "wof:name":"Douglas Carter",
    "wof:placetype":"venue"
},
  "geometry": {"coordinates":[-85.693026,36.701945],"type":"Point"}
}