{
  "type": "Feature",
  "properties": {
    "iso:country":"US",
    "sg:address":"3934 Shelbyville Rd",
    "sg:city":"St Matthews",
    "sg:classifiers":[
        {
            "category":"Personal",
            "subcategory":"Shoe Repair & Shine",
            "type":"Services"
        }
    ],
    "sg:phone":"+1 502 893 2331",
    "sg:postcode":"40207",
    "sg:province":"KY",
    "sg:tags":[
        "repairing",
        "boot"
    ],
    "wof:name":"Village Cobbler Shoe Repair",
    "wof:placetype":"venue"
},
  "geometry": {"coordinates":[-85.654111,38.252883],"type":"Point"}
}