{
  "type": "Feature",
  "properties": {
    "iso:country":"US",
    "sg:address":"900 Cherokee Rd",
    "sg:city":"Raceland",
    "sg:classifiers":[
        {
            "category":"Personal",
            "type":"Services"
        }
    ],
    "sg:phone":"+1 606 836 0808",
    "sg:postcode":"41169",
    "sg:province":"KY",
    "sg:tags":[
        "program",
        "physical",
        "exercise",
        "fitness"
    ],
    "wof:name":"Fitness World Inc",
    "wof:placetype":"venue"
},
  "geometry": {"coordinates":[-82.718604,38.535324],"type":"Point"}
}