{
  "type": "Feature",
  "properties": {
    "iso:country":"US",
    "sg:address":"2417 Branning Rd",
    "sg:city":"Louisville",
    "sg:classifiers":[
        {
            "category":"Retail",
            "subcategory":"Portrait Studio",
            "type":"Services"
        }
    ],
    "sg:phone":"+1 502 423 7698",
    "sg:postcode":"40222",
    "sg:province":"KY",
    "sg:tags":[
        "photo"
    ],
    "wof:name":"Southrn Photog Imag Design",
    "wof:placetype":"venue"
},
  "geometry": {"coordinates":[-85.62495800000001,38.289177],"type":"Point"}
}