{
  "type": "Feature",
  "properties": {
    "iso:country":"US",
    "sg:address":"3904 Bishop Ln",
    "sg:city":"Louisville",
    "sg:classifiers":[
        {
            "category":"Retail",
            "subcategory":"Auto Repair",
            "type":"Services"
        }
    ],
    "sg:phone":"+1 502 966 8282",
    "sg:postcode":"40218",
    "sg:province":"KY",
    "sg:tags":[
        "body",
        "automobile",
        "painting"
    ],
    "wof:name":"Raap Auto Body",
    "wof:placetype":"venue"
},
  "geometry": {"coordinates":[-85.695779,38.18676],"type":"Point"}
}