{
  "type": "Feature",
  "properties": {
    "iso:country":"US",
    "sg:address":"11844 Capital Way",
    "sg:city":"Louisville",
    "sg:classifiers":[
        {
            "category":"Retail",
            "subcategory":"Funeral Services",
            "type":"Services"
        },
        {
            "category":"Home & Garden",
            "subcategory":"Building Materials",
            "type":"Retail Goods"
        },
        {
            "category":"Building & Trades",
            "subcategory":"Construction",
            "type":"Services"
        },
        {
            "category":"Utilities",
            "subcategory":"Natural Gas",
            "type":"Services"
        }
    ],
    "sg:phone":"+1 502 272 0574",
    "sg:postcode":"40299",
    "sg:province":"KY",
    "sg:tags":[
        "stone",
        "marble-natural",
        "top",
        "counter",
        "stone-retail",
        "tile-contractors",
        "granite"
    ],
    "sg:website":"http://www.yext.com/p/superpages/craft-made-kitchen-and-counters-louisville-kentucky.html",
    "wof:name":"Craft Made Kitchen Encounters",
    "wof:placetype":"venue"
},
  "geometry": {"coordinates":[-85.53779900000001,38.207183],"type":"Point"}
}