{
  "type": "Feature",
  "properties": {
    "iso:country":"US",
    "sg:address":"6 Legion Rd",
    "sg:city":"Paris",
    "sg:classifiers":[
        {
            "category":"Retail",
            "subcategory":"Animal Services",
            "type":"Services"
        }
    ],
    "sg:phone":"+1 859 988 9800",
    "sg:postcode":"40361",
    "sg:province":"KY",
    "sg:tags":[
        "shelter"
    ],
    "wof:name":"Paws Animal Shelter",
    "wof:placetype":"venue"
},
  "geometry": {"coordinates":[-84.24003,38.218196],"type":"Point"}
}