{
  "type": "Feature",
  "properties": {
    "iso:country":"US",
    "sg:address":"1100 S Central Ave",
    "sg:city":"Campbellsville",
    "sg:classifiers":[
        {
            "category":"Autos & Motor Vehicles",
            "subcategory":"Automobile Sales",
            "type":"Retail Goods"
        }
    ],
    "sg:phone":"+1 270 465 2306",
    "sg:postcode":"42718",
    "sg:province":"KY",
    "sg:tags":[
        "car",
        "dealer"
    ],
    "wof:name":"Nolley Auto Sales",
    "wof:placetype":"venue"
},
  "geometry": {"coordinates":[-85.329921,37.332783],"type":"Point"}
}