{
  "type": "Feature",
  "properties": {
    "addr:full":"10001 Taylorsville Rd Jeffersontown KY 40299",
    "addr:housenumber":"10001",
    "addr:postcode":"40299",
    "addr:street":"Taylorsville Rd",
    "iso:country":"US",
    "sg:address":"10001 Taylorsville Rd",
    "sg:city":"Jeffersontown",
    "sg:classifiers":[
        {
            "category":"Building & Trades",
            "subcategory":"Construction",
            "type":"Services"
        }
    ],
    "sg:phone":"+1 502 266 6202",
    "sg:postcode":"40299",
    "sg:province":"KY",
    "sg:tags":[
        "contractor"
    ],
    "sg:website":"www.brightbuilt.com",
    "wof:name":"Bright Built Homes Inc",
    "wof:placetype":"venue"
},
  "geometry": {"coordinates":[-85.57070400000001,38.198667],"type":"Point"}
}