{
  "type": "Feature",
  "properties": {
    "iso:country":"US",
    "sg:address":"2530 Scottsville Rd",
    "sg:city":"Bowling Green",
    "sg:classifiers":[
        {
            "category":"Real Estate",
            "subcategory":"Real Estate Agent",
            "type":"Services"
        }
    ],
    "sg:phone":"+1 270 781 5504",
    "sg:postcode":"42104",
    "sg:province":"KY",
    "wof:name":"Old Hickory Building",
    "wof:placetype":"venue"
},
  "geometry": {"coordinates":[-86.42588000000001,36.952342],"type":"Point"}
}