{
  "type": "Feature",
  "properties": {
    "addr:full":"1340 Lexington Rd Wilmore KY 40390",
    "addr:housenumber":"1340",
    "addr:postcode":"40390",
    "addr:street":"Lexington Rd",
    "iso:country":"US",
    "sg:address":"1340 Lexington Rd",
    "sg:city":"Wilmore",
    "sg:classifiers":[
        {
            "category":"Professional",
            "subcategory":"Computer Services",
            "type":"Services"
        }
    ],
    "sg:phone":"+1 859 858 4063",
    "sg:postcode":"40390",
    "sg:province":"KY",
    "sg:tags":[
        "programing",
        "custom"
    ],
    "wof:name":"Tura Technologies",
    "wof:placetype":"venue"
},
  "geometry": {"coordinates":[-84.655705,37.869549],"type":"Point"}
}