{
  "type": "Feature",
  "properties": {
    "addr:full":"103 W Public Sq Glasgow KY 42141",
    "addr:housenumber":"103",
    "addr:postcode":"42141",
    "addr:street":"W Public Sq",
    "iso:country":"US",
    "sg:address":"103 W Public Sq",
    "sg:city":"Glasgow",
    "sg:classifiers":[
        {
            "category":"Insurance",
            "subcategory":"Insurance Agent",
            "type":"Services"
        }
    ],
    "sg:phone":"+1 270 651 6655",
    "sg:postcode":"42141",
    "sg:province":"KY",
    "wof:name":"Larry Jewell Insurance Inc",
    "wof:placetype":"venue"
},
  "geometry": {"coordinates":[-85.91296,36.996319],"type":"Point"}
}