{
  "type": "Feature",
  "properties": {
    "iso:country":"US",
    "sg:address":"410 Southtown Blvd",
    "sg:city":"Owensboro",
    "sg:classifiers":[
        {
            "category":"Personal",
            "subcategory":"Beauty Salon",
            "type":"Services"
        }
    ],
    "sg:phone":"+1 270 926 1533",
    "sg:postcode":"42301",
    "sg:province":"KY",
    "sg:tags":[
        "manicuring"
    ],
    "wof:name":"Perfect Nails",
    "wof:placetype":"venue"
},
  "geometry": {"coordinates":[-87.11668,37.720688],"type":"Point"}
}