{
  "type": "Feature",
  "properties": {
    "iso:country":"US",
    "sg:address":"1410 N Forbes Rd",
    "sg:city":"Lexington",
    "sg:classifiers":[
        {
            "category":"Social Services",
            "subcategory":"Child Care",
            "type":"Services"
        }
    ],
    "sg:phone":"+1 859 231 1527",
    "sg:postcode":"40511",
    "sg:province":"KY",
    "wof:name":"Mother's Love Day Care",
    "wof:placetype":"venue"
},
  "geometry": {"coordinates":[-84.51957400000001,38.065062],"type":"Point"}
}