{
  "type": "Feature",
  "properties": {
    "addr:full":"2410 New Hartford Rd Owensboro KY 42303",
    "addr:housenumber":"2410",
    "addr:postcode":"42303",
    "addr:street":"New Hartford Rd",
    "iso:country":"US",
    "sg:address":"2410 New Hartford Rd",
    "sg:city":"Owensboro",
    "sg:classifiers":[
        {
            "category":"Professional",
            "subcategory":"Detective & Security Services",
            "type":"Services"
        }
    ],
    "sg:phone":"+1 270 683 4814",
    "sg:postcode":"42303",
    "sg:province":"KY",
    "sg:tags":[
        "installation"
    ],
    "wof:name":"Advanced Communications & SEC",
    "wof:placetype":"venue"
},
  "geometry": {"coordinates":[-87.10090099999999,37.752623],"type":"Point"}
}