{
  "type": "Feature",
  "properties": {
    "iso:country":"US",
    "sg:address":"175 College St",
    "sg:city":"Pikeville",
    "sg:classifiers":[
        {
            "category":"Professional",
            "subcategory":"Lawyer & Legal Services",
            "type":"Services"
        }
    ],
    "sg:phone":"+1 606 432 3116",
    "sg:postcode":"41501",
    "sg:province":"KY",
    "sg:tags":[
        "attorney"
    ],
    "wof:name":"Thompson Law Offices",
    "wof:placetype":"venue"
},
  "geometry": {"coordinates":[-82.51933200000001,37.477923],"type":"Point"}
}