{
  "type": "Feature",
  "properties": {
    "addr:full":"911 Hustonville Rd Danville KY 40422",
    "addr:housenumber":"911",
    "addr:postcode":"40422",
    "addr:street":"Hustonville Rd",
    "iso:country":"US",
    "sg:address":"911 Hustonville Rd",
    "sg:city":"Danville",
    "sg:classifiers":[
        {
            "category":"Autos & Motor Vehicles",
            "subcategory":"Auto Supplies",
            "type":"Retail Goods"
        }
    ],
    "sg:phone":"+1 859 236 1540",
    "sg:postcode":"40422",
    "sg:province":"KY",
    "sg:tags":[
        "automobile",
        "parts"
    ],
    "wof:name":"Advance Auto Parts Inc",
    "wof:placetype":"venue"
},
  "geometry": {"coordinates":[-84.77494900000001,37.631205],"type":"Point"}
}