{
  "type": "Feature",
  "properties": {
    "iso:country":"US",
    "sg:address":"10489 State Hwy 44 E",
    "sg:city":"Mt Washington",
    "sg:classifiers":[
        {
            "category":"Home & Garden",
            "subcategory":"Carpets & Floor Coverings",
            "type":"Retail Goods"
        }
    ],
    "sg:phone":"+1 502 538 7393",
    "sg:postcode":"40047",
    "sg:province":"KY",
    "sg:tags":[
        "dealer",
        "rug"
    ],
    "wof:name":"Harbin's Floor Covering",
    "wof:placetype":"venue"
},
  "geometry": {"coordinates":[-85.556613,38.058253],"type":"Point"}
}