{
  "type": "Feature",
  "properties": {
    "addr:full":"4137 Quinns Landing Rd Robards KY 42452",
    "addr:postcode":"4137;42452",
    "addr:street":"Quinns Landing Rd",
    "iso:country":"US",
    "sg:address":"4137 Quinns Landing Rd",
    "sg:city":"Robards",
    "sg:classifiers":[
        {
            "category":"Government",
            "subcategory":"Office",
            "type":"Public Place"
        }
    ],
    "sg:phone":"+1 270 521 7695",
    "sg:postcode":"42452",
    "sg:province":"KY",
    "sg:tags":[
        "govt",
        "city"
    ],
    "wof:name":"Henderson Water Treatment Plnt",
    "wof:placetype":"venue"
},
  "geometry": {"coordinates":[-87.51284200000001,37.64846],"type":"Point"}
}