{
  "type": "Feature",
  "properties": {
    "addr:full":"900 Hospital Dr Madisonville KY 42431",
    "addr:housenumber":"900",
    "addr:postcode":"42431",
    "addr:street":"Hospital",
    "iso:country":"US",
    "sg:address":"900 Hospital Dr",
    "sg:city":"Madisonville",
    "sg:classifiers":[
        {
            "category":"Health Services",
            "subcategory":"Doctor",
            "type":"Services"
        }
    ],
    "sg:phone":"+1 270 825 5178",
    "sg:postcode":"42431",
    "sg:province":"KY",
    "sg:tags":[
        "physician",
        "surgeon"
    ],
    "wof:name":"Trover Foundation",
    "wof:placetype":"venue"
},
  "geometry": {"coordinates":[-87.489384,37.338933],"type":"Point"}
}