{
  "type": "Feature",
  "properties": {
    "iso:country":"US",
    "sg:address":"715 W Stephen Foster Ave",
    "sg:city":"Bardstown",
    "sg:classifiers":[
        {
            "category":"Retail",
            "subcategory":"Auto Repair",
            "type":"Services"
        }
    ],
    "sg:phone":"+1 502 348 3487",
    "sg:postcode":"40004",
    "sg:province":"KY",
    "sg:tags":[
        "body"
    ],
    "wof:name":"Lydian Body Shop",
    "wof:placetype":"venue"
},
  "geometry": {"coordinates":[-85.47847299999999,37.810623],"type":"Point"}
}