{
  "type": "Feature",
  "properties": {
    "addr:full":"806 Scott Blvd Covington KY 41011",
    "addr:housenumber":"806",
    "addr:postcode":"41011",
    "addr:street":"Scott Blvd",
    "iso:country":"US",
    "sg:address":"806 Scott Blvd",
    "sg:city":"Covington",
    "sg:classifiers":[
        {
            "category":"Health Services",
            "subcategory":"Doctor",
            "type":"Services"
        }
    ],
    "sg:phone":"+1 859 491 6411",
    "sg:postcode":"41011",
    "sg:province":"KY",
    "sg:tags":[
        "physician",
        "surgeon"
    ],
    "wof:name":"Allan Seales MD",
    "wof:placetype":"venue"
},
  "geometry": {"coordinates":[-84.508065,39.082389],"type":"Point"}
}