{
  "type": "Feature",
  "properties": {
    "iso:country":"US",
    "sg:address":"849 S 6th St",
    "sg:city":"Louisville",
    "sg:classifiers":[
        {
            "category":"Home & Garden",
            "subcategory":"Home Furnishings",
            "type":"Retail Goods"
        },
        {
            "category":"Manufacturing",
            "subcategory":"Glass & Minerals",
            "type":"Manufacturing & Wholesale Goods"
        },
        {
            "category":"Manufacturing",
            "subcategory":"Building Materials",
            "type":"Manufacturing & Wholesale Goods"
        }
    ],
    "sg:phone":"+1 502 585 4256",
    "sg:postcode":"40203",
    "sg:province":"KY",
    "sg:tags":[
        "plate",
        "repair",
        "glazier",
        "glass-auto",
        "window",
        "mirror",
        "replacement"
    ],
    "sg:website":"http://www.stanleyschultze.com",
    "wof:name":"Stanley Schultze And Company",
    "wof:placetype":"venue"
},
  "geometry": {"coordinates":[-85.76218,38.243551],"type":"Point"}
}