{
  "type": "Feature",
  "properties": {
    "iso:country":"US",
    "sg:address":"1796 Owensboro Rd",
    "sg:city":"Leitchfield",
    "sg:classifiers":[
        {
            "category":"Farming",
            "subcategory":"Livestock Farm",
            "type":"Manufacturing & Wholesale Goods"
        }
    ],
    "sg:phone":"+1 270 259 4831",
    "sg:postcode":"42754",
    "sg:province":"KY",
    "sg:tags":[
        "beef",
        "feedlot",
        "tobacco",
        "cattle"
    ],
    "wof:name":"Ray Ragland",
    "wof:placetype":"venue"
},
  "geometry": {"coordinates":[-86.334239,37.480148],"type":"Point"}
}