{
  "type": "Feature",
  "properties": {
    "addr:full":"313 Old Gates Rd Midway KY 40351",
    "addr:housenumber":"313",
    "addr:postcode":"40351",
    "addr:street":"Old Gates Rd",
    "iso:country":"US",
    "sg:address":"313 Old Gates Rd",
    "sg:city":"Midway",
    "sg:classifiers":[
        {
            "category":"Professional",
            "subcategory":"Business Services",
            "type":"Services"
        }
    ],
    "sg:phone":"+1 859 846 4163",
    "sg:postcode":"40351",
    "sg:province":"KY",
    "sg:tags":[
        "balance",
        "air"
    ],
    "wof:name":"Home Environmental Balance Co",
    "wof:placetype":"venue"
},
  "geometry": {"coordinates":[-83.369561,38.232189],"type":"Point"}
}