{
  "type": "Feature",
  "properties": {
    "iso:country":"US",
    "sg:address":"1440 Nashville Rd",
    "sg:city":"Franklin",
    "sg:classifiers":[
        {
            "category":"Restaurant",
            "type":"Food & Drink"
        }
    ],
    "sg:phone":"+1 270 586 5600",
    "sg:postcode":"42134",
    "sg:province":"KY",
    "wof:name":"China Buffet",
    "wof:placetype":"venue"
},
  "geometry": {"coordinates":[-86.571629,36.697451],"type":"Point"}
}