{
  "type": "Feature",
  "properties": {
    "iso:country":"US",
    "sg:address":"201 W Main St",
    "sg:city":"Vine Grove",
    "sg:classifiers":[
        {
            "category":"Professional",
            "subcategory":"Engineering",
            "type":"Services"
        }
    ],
    "sg:phone":"+1 270 877 2815",
    "sg:postcode":"40175",
    "sg:province":"KY",
    "sg:tags":[
        "engineer"
    ],
    "wof:name":"Hawkins Engineering",
    "wof:placetype":"venue"
},
  "geometry": {"coordinates":[-85.98384799999999,37.810623],"type":"Point"}
}