{
  "type": "Feature",
  "properties": {
    "iso:country":"US",
    "sg:address":"614 Master St",
    "sg:city":"Corbin",
    "sg:classifiers":[
        {
            "category":"Government",
            "subcategory":"Office",
            "type":"Public Place"
        }
    ],
    "sg:phone":"+1 606 528 1806",
    "sg:postcode":"40701",
    "sg:province":"KY",
    "sg:tags":[
        "federal",
        "human"
    ],
    "wof:name":"US Social Security Adm",
    "wof:placetype":"venue"
},
  "geometry": {"coordinates":[-84.086699,36.952912],"type":"Point"}
}