{
  "type": "Feature",
  "properties": {
    "addr:full":"2291 Alexandria Pike Southgate KY 41071",
    "addr:housenumber":"2291",
    "addr:postcode":"41071",
    "addr:street":"Alexandria Pike",
    "iso:country":"US",
    "sg:address":"2291 Alexandria Pike",
    "sg:city":"Southgate",
    "sg:classifiers":[
        {
            "category":"Health Services",
            "subcategory":"Chiropractor",
            "type":"Services"
        }
    ],
    "sg:phone":"+1 859 572 0029",
    "sg:postcode":"41071",
    "sg:province":"KY",
    "wof:name":"Southgate Chiropractic",
    "wof:placetype":"venue"
},
  "geometry": {"coordinates":[-84.477953,39.076769],"type":"Point"}
}