{
  "type": "Feature",
  "properties": {
    "addr:full":"901 Bellefonte Rd Flatwoods KY 41139",
    "addr:housenumber":"901",
    "addr:postcode":"41139",
    "addr:street":"Bellefonte Rd",
    "iso:country":"US",
    "sg:address":"901 Bellefonte Rd",
    "sg:city":"Flatwoods",
    "sg:classifiers":[
        {
            "category":"Autos & Motor Vehicles",
            "subcategory":"Auto Supplies",
            "type":"Retail Goods"
        }
    ],
    "sg:phone":"+1 606 836 3126",
    "sg:postcode":"41139",
    "sg:province":"KY",
    "sg:tags":[
        "automobile",
        "parts"
    ],
    "wof:name":"Harvey's Inc",
    "wof:placetype":"venue"
},
  "geometry": {"coordinates":[-82.71867899999999,38.513231],"type":"Point"}
}