{
  "type": "Feature",
  "properties": {
    "iso:country":"US",
    "sg:address":"1200 S Broadway Rd",
    "sg:city":"Lexington",
    "sg:classifiers":[
        {
            "category":"Shopping",
            "subcategory":"Used Merchandise",
            "type":"Retail Goods"
        }
    ],
    "sg:phone":"+1 859 231 7707",
    "sg:postcode":"40504",
    "sg:province":"KY",
    "sg:tags":[
        "shop",
        "consignment"
    ],
    "wof:name":"Stephen Lawrence LTD",
    "wof:placetype":"venue"
},
  "geometry": {"coordinates":[-84.519493,38.036077],"type":"Point"}
}