{
  "type": "Feature",
  "properties": {
    "addr:full":"1699 N Preston Hwy Shepherdsville KY 40165",
    "addr:housenumber":"1699",
    "addr:postcode":"40165",
    "addr:street":"N Preston Hwy",
    "iso:country":"US",
    "sg:address":"1699 N Preston Hwy",
    "sg:city":"Shepherdsville",
    "sg:classifiers":[
        {
            "category":"Autos & Motor Vehicles",
            "subcategory":"Automobile Sales",
            "type":"Retail Goods"
        }
    ],
    "sg:phone":"+1 502 921 0472",
    "sg:postcode":"40165",
    "sg:province":"KY",
    "sg:tags":[
        "car",
        "dealer"
    ],
    "wof:name":"Stockyard Auto Sales",
    "wof:placetype":"venue"
},
  "geometry": {"coordinates":[-85.697484,38.021418],"type":"Point"}
}