{
  "type": "Feature",
  "properties": {
    "iso:country":"US",
    "sg:address":"816 Washburn Ave",
    "sg:city":"Louisville",
    "sg:classifiers":[
        {
            "category":"Professional",
            "subcategory":"Management & Consulting",
            "type":"Services"
        }
    ],
    "sg:phone":"+1 502 426 0899",
    "sg:postcode":"40222",
    "sg:province":"KY",
    "wof:name":"Hammontree Management Inc",
    "wof:placetype":"venue"
},
  "geometry": {"coordinates":[-85.619417,38.262894],"type":"Point"}
}