{
  "type": "Feature",
  "properties": {
    "addr:full":"124 N Reed St Columbia KY 42728",
    "addr:housenumber":"124",
    "addr:postcode":"42728",
    "addr:street":"N Reed St",
    "iso:country":"US",
    "sg:address":"124 N Reed St",
    "sg:city":"Columbia",
    "sg:classifiers":[
        {
            "category":"Banks & Credit Unions",
            "subcategory":"Bank",
            "type":"Services"
        }
    ],
    "sg:phone":"+1 270 384 4814",
    "sg:postcode":"42728",
    "sg:province":"KY",
    "wof:name":"Bank Of Columbia",
    "wof:placetype":"venue"
},
  "geometry": {"coordinates":[-85.30525799999999,37.102337],"type":"Point"}
}