{
  "type": "Feature",
  "properties": {
    "iso:country":"US",
    "sg:address":"1473 Pine Needles Ln",
    "sg:city":"Lexington",
    "sg:classifiers":[
        {
            "category":"Professional",
            "type":"Services"
        }
    ],
    "sg:phone":"+1 859 296 0045",
    "sg:postcode":"40513",
    "sg:province":"KY",
    "wof:name":"Mvp Systems Inc",
    "wof:placetype":"venue"
},
  "geometry": {"coordinates":[-84.57598299999999,38.024203],"type":"Point"}
}