{
  "type": "Feature",
  "properties": {
    "iso:country":"US",
    "sg:address":"707 Ahland Rd",
    "sg:city":"Louisville",
    "sg:classifiers":[
        {
            "category":"Building & Trades",
            "subcategory":"Cleaning & Sanitation",
            "type":"Services"
        }
    ],
    "sg:phone":"+1 502 290 7339",
    "sg:postcode":"40207",
    "sg:province":"KY",
    "sg:tags":[
        "window"
    ],
    "wof:name":"Everything New Cleaning",
    "wof:placetype":"venue"
},
  "geometry": {"coordinates":[-85.631683,38.25881],"type":"Point"}
}