{
  "type": "Feature",
  "properties": {
    "iso:country":"US",
    "sg:address":"1378 Estates Hill Cir",
    "sg:city":"Lexington",
    "sg:classifiers":[
        {
            "category":"Real Estate",
            "subcategory":"Real Estate Operator",
            "type":"Services"
        }
    ],
    "sg:phone":"+1 859 254 3959",
    "sg:postcode":"40511",
    "sg:province":"KY",
    "sg:tags":[
        "commercial"
    ],
    "wof:name":"Prestige Investments",
    "wof:placetype":"venue"
},
  "geometry": {"coordinates":[-84.481116,38.084875],"type":"Point"}
}