{
  "type": "Feature",
  "properties": {
    "iso:country":"US",
    "sg:address":"9396 Camp Ernst Rd",
    "sg:city":"Union",
    "sg:classifiers":[
        {
            "category":"Insurance",
            "subcategory":"Insurance Agent",
            "type":"Services"
        }
    ],
    "sg:phone":"+1 859 750 1748",
    "sg:postcode":"41091",
    "sg:province":"KY",
    "wof:name":"Polaris Financial Group",
    "wof:placetype":"venue"
},
  "geometry": {"coordinates":[-84.725739,38.960601],"type":"Point"}
}