{
  "type": "Feature",
  "properties": {
    "iso:country":"US",
    "sg:address":"2814 de Mel Ave",
    "sg:city":"Louisville",
    "sg:classifiers":[
        {
            "category":"Real Estate",
            "subcategory":"Real Estate Operator",
            "type":"Services"
        }
    ],
    "sg:phone":"+1 502 361 0885",
    "sg:postcode":"40214",
    "sg:province":"KY",
    "sg:tags":[
        "apartment"
    ],
    "wof:name":"Summitt Apartments",
    "wof:placetype":"venue"
},
  "geometry": {"coordinates":[-85.80022200000001,38.170038],"type":"Point"}
}