{
  "type": "Feature",
  "properties": {
    "iso:country":"US",
    "sg:address":"2950 Breckenridge Ln",
    "sg:city":"Louisville",
    "sg:classifiers":[
        {
            "category":"Professional",
            "subcategory":"Accounting & Tax Preparation",
            "type":"Services"
        }
    ],
    "sg:phone":"+1 502 451 5000",
    "sg:postcode":"40220",
    "sg:province":"KY",
    "sg:tags":[
        "accountant"
    ],
    "wof:name":"Dennis L O'Brien CPA",
    "wof:placetype":"venue"
},
  "geometry": {"coordinates":[-85.63217400000001,38.22185],"type":"Point"}
}