{
  "type": "Feature",
  "properties": {
    "addr:full":"8409 Saint Andrews Church Rd Louisville KY 40258",
    "addr:housenumber":"8409",
    "addr:postcode":"40258",
    "addr:street":"Saint Andrews Church Rd",
    "iso:country":"US",
    "sg:address":"8409 Saint Andrews Church Rd",
    "sg:city":"Louisville",
    "sg:classifiers":[
        {
            "category":"Government",
            "subcategory":"Post Office",
            "type":"Public Place"
        }
    ],
    "sg:phone":"+1 502 937 4154",
    "sg:postcode":"40258",
    "sg:province":"KY",
    "wof:name":"US Post Office",
    "wof:placetype":"venue"
},
  "geometry": {"coordinates":[-85.837774,38.143582],"type":"Point"}
}