{
  "type": "Feature",
  "properties": {
    "addr:full":"114 Thompson St Frankfort KY 40601",
    "addr:housenumber":"114",
    "addr:postcode":"40601",
    "addr:street":"Thompson St",
    "iso:country":"US",
    "sg:address":"114 Thompson St",
    "sg:city":"Frankfort",
    "sg:classifiers":[
        {
            "category":"Insurance",
            "subcategory":"Insurance Agent",
            "type":"Services"
        }
    ],
    "sg:phone":"+1 502 695 1799",
    "sg:postcode":"40601",
    "sg:province":"KY",
    "wof:name":"State Farm Insurance",
    "wof:placetype":"venue"
},
  "geometry": {"coordinates":[-84.835094,38.203827],"type":"Point"}
}