{
  "type": "Feature",
  "properties": {
    "iso:country":"US",
    "sg:address":"208 N Lincoln Blvd",
    "sg:city":"Hodgenville",
    "sg:classifiers":[
        {
            "category":"Government",
            "subcategory":"Office",
            "type":"Public Place"
        }
    ],
    "sg:phone":"+1 270 358 3832",
    "sg:postcode":"42748",
    "sg:province":"KY",
    "sg:tags":[
        "city"
    ],
    "wof:name":"Hodgenville City Hall",
    "wof:placetype":"venue"
},
  "geometry": {"coordinates":[-85.74043399999999,37.575156],"type":"Point"}
}