{
  "type": "Feature",
  "properties": {
    "iso:country":"US",
    "sg:address":"305 S Central Ave",
    "sg:city":"Campbellsville",
    "sg:classifiers":[
        {
            "category":"Home & Garden",
            "subcategory":"Garden Supply",
            "type":"Retail Goods"
        }
    ],
    "sg:phone":"+1 270 465 2834",
    "sg:postcode":"42718",
    "sg:province":"KY",
    "sg:tags":[
        "lawn",
        "mower"
    ],
    "wof:name":"Bill's Campers & Dixon Mowers",
    "wof:placetype":"venue"
},
  "geometry": {"coordinates":[-85.34039,37.338558],"type":"Point"}
}