{
  "type": "Feature",
  "properties": {
    "iso:country":"US",
    "sg:address":"10742 Sedco Dr",
    "sg:city":"Union",
    "sg:classifiers":[
        {
            "category":"Professional",
            "subcategory":"Lawyer & Legal Services",
            "type":"Services"
        }
    ],
    "sg:phone":"+1 859 384 7000",
    "sg:postcode":"41091",
    "sg:province":"KY",
    "sg:tags":[
        "attorney"
    ],
    "sg:website":"www.edwinkagin.com",
    "wof:name":"Edwin F Kagin",
    "wof:placetype":"venue"
},
  "geometry": {"coordinates":[-84.66710500000001,38.92351],"type":"Point"}
}