{
  "type": "Feature",
  "properties": {
    "iso:country":"US",
    "sg:address":"3051 Rio Dosa Dr",
    "sg:city":"Lexington",
    "sg:classifiers":[
        {
            "category":"Shopping",
            "type":"Retail Goods"
        },
        {
            "category":"Shopping",
            "subcategory":"Beauty & Cosmetics",
            "type":"Retail Goods"
        }
    ],
    "sg:phone":"+1 859 266 1089",
    "sg:postcode":"40509",
    "sg:province":"KY",
    "sg:tags":[
        "merchandise",
        "perfume"
    ],
    "wof:name":"Luzier Cosmetics",
    "wof:placetype":"venue"
},
  "geometry": {"coordinates":[-84.44198400000001,38.005548],"type":"Point"}
}