{
  "type": "Feature",
  "properties": {
    "addr:full":"11933 Creel Lodge Dr Louisville KY 40223",
    "addr:housenumber":"11933",
    "addr:postcode":"40223",
    "addr:street":"Creel Lodge Dr",
    "iso:country":"US",
    "sg:address":"11933 Creel Lodge Dr",
    "sg:city":"Louisville",
    "sg:classifiers":[
        {
            "category":"Professional",
            "subcategory":"Accounting & Tax Preparation",
            "type":"Services"
        }
    ],
    "sg:phone":"+1 502 244 0001",
    "sg:postcode":"40223",
    "sg:province":"KY",
    "wof:name":"Lynn W Wilkerson",
    "wof:placetype":"venue"
},
  "geometry": {"coordinates":[-85.531402,38.270588],"type":"Point"}
}