{
  "type": "Feature",
  "properties": {
    "iso:country":"US",
    "sg:address":"1415 Lexington Rd",
    "sg:city":"Richmond",
    "sg:classifiers":[
        {
            "category":"Food & Beverages",
            "subcategory":"Groceries & Convenience Stores",
            "type":"Retail Goods"
        }
    ],
    "sg:phone":"+1 859 623 6472",
    "sg:postcode":"40475",
    "sg:province":"KY",
    "sg:tags":[
        "grocer"
    ],
    "wof:name":"Priceless Foods",
    "wof:placetype":"venue"
},
  "geometry": {"coordinates":[-84.306944,37.758654],"type":"Point"}
}