{
  "type": "Feature",
  "properties": {
    "iso:country":"US",
    "sg:address":"1900 Gholson Rd",
    "sg:city":"West Paducah",
    "sg:classifiers":[
        {
            "category":"Building & Trades",
            "subcategory":"Construction",
            "type":"Services"
        }
    ],
    "sg:phone":"+1 270 488 3364",
    "sg:postcode":"42086",
    "sg:province":"KY",
    "sg:tags":[
        "contractor"
    ],
    "wof:name":"Ormes Construction",
    "wof:placetype":"venue"
},
  "geometry": {"coordinates":[-88.793261,37.036693],"type":"Point"}
}