{
  "type": "Feature",
  "properties": {
    "iso:country":"US",
    "sg:address":"21670 Main St",
    "sg:city":"Hyden",
    "sg:classifiers":[
        {
            "category":"Shopping",
            "subcategory":"Florist",
            "type":"Retail Goods"
        }
    ],
    "sg:phone":"+1 606 672 2852",
    "sg:postcode":"41749",
    "sg:province":"KY",
    "wof:name":"Napier's Florist",
    "wof:placetype":"venue"
},
  "geometry": {"coordinates":[-83.370769,37.157075],"type":"Point"}
}