{
  "type": "Feature",
  "properties": {
    "iso:country":"US",
    "sg:address":"4600 S Hwy 53",
    "sg:city":"Crestwood",
    "sg:classifiers":[
        {
            "category":"Government",
            "subcategory":"Fire Station",
            "type":"Public Place"
        }
    ],
    "sg:phone":"+1 502 222 1593",
    "sg:postcode":"40014",
    "sg:province":"KY",
    "sg:tags":[
        "department"
    ],
    "wof:name":"Ballardsville Fire Dept",
    "wof:placetype":"venue"
},
  "geometry": {"coordinates":[-85.31736600000001,38.336231],"type":"Point"}
}