{
  "type": "Feature",
  "properties": {
    "addr:full":"3881 Bus Park Dr Louisville KY 40213",
    "addr:housenumber":"3881",
    "addr:postcode":"40213",
    "addr:street":"Bus Park Dr",
    "iso:country":"US",
    "sg:address":"3881 Bus Park Dr",
    "sg:city":"Louisville",
    "sg:classifiers":[
        {
            "category":"Health Services",
            "subcategory":"Clinic",
            "type":"Services"
        }
    ],
    "sg:phone":"+1 502 266 5001",
    "sg:postcode":"40213",
    "sg:province":"KY",
    "sg:tags":[
        "home"
    ],
    "sg:website":"www.lincareinc.com",
    "wof:name":"Lincare",
    "wof:placetype":"venue"
},
  "geometry": {"coordinates":[-85.6905,38.177539],"type":"Point"}
}