{
  "type": "Feature",
  "properties": {
    "iso:country":"US",
    "sg:address":"867 Dreyfus Rd",
    "sg:city":"Berea",
    "sg:classifiers":[
        {
            "category":"Organizations",
            "subcategory":"Religious Organization",
            "type":"Services"
        }
    ],
    "sg:phone":"+1 859 986 7823",
    "sg:postcode":"40403",
    "sg:province":"KY",
    "wof:name":"Faith Based Surgical Assisting",
    "wof:placetype":"venue"
},
  "geometry": {"coordinates":[-84.186053,37.63288],"type":"Point"}
}