{
  "type": "Feature",
  "properties": {
    "iso:country":"US",
    "sg:address":"201 E 2nd St",
    "sg:city":"Beaver Dam",
    "sg:classifiers":[
        {
            "category":"Building & Trades",
            "subcategory":"Electrical",
            "type":"Services"
        }
    ],
    "sg:phone":"+1 270 274 4784",
    "sg:postcode":"42320",
    "sg:province":"KY",
    "sg:tags":[
        "electric",
        "contractor"
    ],
    "wof:name":"Martrice Electric",
    "wof:placetype":"venue"
},
  "geometry": {"coordinates":[-86.875236,37.403414],"type":"Point"}
}