{
  "type": "Feature",
  "properties": {
    "iso:country":"US",
    "sg:address":"112 North St",
    "sg:city":"Wilder",
    "sg:phone":"+1 859 581 1651",
    "sg:postcode":"41071",
    "sg:province":"KY",
    "sg:tags":[
        "equipment",
        "station"
    ],
    "wof:name":"Harry Grau & Sons Inc",
    "wof:placetype":"venue"
},
  "geometry": {"coordinates":[-84.49018100000001,39.05927],"type":"Point"}
}