{
  "type": "Feature",
  "properties": {
    "iso:country":"US",
    "sg:address":"10400 Bunsen Way",
    "sg:city":"Jeffersontown",
    "sg:classifiers":[
        {
            "category":"Wholesale",
            "subcategory":"Home Furnishings",
            "type":"Manufacturing & Wholesale Goods"
        }
    ],
    "sg:phone":"+1 502 491 3370",
    "sg:postcode":"40299",
    "sg:province":"KY",
    "sg:tags":[
        "bedding"
    ],
    "sg:website":"www.loubed.com",
    "wof:name":"Louisville Bedding Co",
    "wof:placetype":"venue"
},
  "geometry": {"coordinates":[-85.561328,38.21373],"type":"Point"}
}