{
  "type": "Feature",
  "properties": {
    "addr:full":"441 S Ashland Ave Lexington KY 40502",
    "addr:housenumber":"441",
    "addr:postcode":"40502",
    "addr:street":"S Ashland Ave",
    "iso:country":"US",
    "sg:address":"441 S Ashland Ave",
    "sg:city":"Lexington",
    "sg:classifiers":[
        {
            "category":"Shopping",
            "type":"Retail Goods"
        }
    ],
    "sg:phone":"+1 859 269 1614",
    "sg:postcode":"40502",
    "sg:province":"KY",
    "sg:tags":[
        "coin",
        "dealer",
        "supply"
    ],
    "sg:website":"www.jkerncoins.com",
    "wof:name":"Jonathan K KERN Co",
    "wof:placetype":"venue"
},
  "geometry": {"coordinates":[-84.49168299999999,38.030182],"type":"Point"}
}