{
  "type": "Feature",
  "properties": {
    "iso:country":"US",
    "sg:address":"95 Park St",
    "sg:city":"Clay",
    "sg:classifiers":[
        {
            "category":"Personal",
            "subcategory":"Beauty Salon",
            "type":"Services"
        }
    ],
    "sg:phone":"+1 270 664 9783",
    "sg:postcode":"42404",
    "sg:province":"KY",
    "sg:tags":[
        "shop"
    ],
    "wof:name":"Cuttin Up",
    "wof:placetype":"venue"
},
  "geometry": {"coordinates":[-87.81804,37.483288],"type":"Point"}
}