{
  "type": "Feature",
  "properties": {
    "iso:country":"US",
    "sg:address":"1403 E Mount Vernon St",
    "sg:city":"Somerset",
    "sg:classifiers":[
        {
            "category":"Organizations",
            "subcategory":"Religious Organization",
            "type":"Services"
        }
    ],
    "sg:phone":"+1 606 678 8591",
    "sg:postcode":"42501",
    "sg:province":"KY",
    "sg:tags":[
        "church"
    ],
    "wof:name":"Calvary Baptist Church",
    "wof:placetype":"venue"
},
  "geometry": {"coordinates":[-84.581378,37.099485],"type":"Point"}
}