{
  "type": "Feature",
  "properties": {
    "addr:full":"4090 Cedarmore Rd Pleasureville KY 40057",
    "addr:housenumber":"4090",
    "addr:postcode":"40057",
    "addr:street":"Cedarmore Rd",
    "iso:country":"US",
    "sg:address":"4090 Cedarmore Rd",
    "sg:city":"Pleasureville",
    "sg:classifiers":[
        {
            "category":"Organizations",
            "subcategory":"Religious Organization",
            "type":"Services"
        }
    ],
    "sg:phone":"+1 502 747 5867",
    "sg:postcode":"40057",
    "sg:province":"KY",
    "wof:name":"Union Baptist Church Inc",
    "wof:placetype":"venue"
},
  "geometry": {"coordinates":[-85.047791,38.338746],"type":"Point"}
}