{
  "type": "Feature",
  "properties": {
    "iso:country":"US",
    "sg:address":"2119 Greenup Ave",
    "sg:city":"Ashland",
    "sg:classifiers":[
        {
            "category":"Autos & Motor Vehicles",
            "subcategory":"Automobile Sales",
            "type":"Retail Goods"
        }
    ],
    "sg:phone":"+1 606 329 2120",
    "sg:postcode":"41101",
    "sg:province":"KY",
    "sg:tags":[
        "car",
        "dealer"
    ],
    "sg:website":"www.boydcountyford.com",
    "wof:name":"Boyd County Ford",
    "wof:placetype":"venue"
},
  "geometry": {"coordinates":[-82.632839,38.476694],"type":"Point"}
}