{
  "type": "Feature",
  "properties": {
    "addr:full":"204 Elm St Murray KY 42071",
    "addr:housenumber":"204",
    "addr:postcode":"42071",
    "addr:street":"Elm St",
    "iso:country":"US",
    "sg:address":"204 Elm St",
    "sg:city":"Murray",
    "sg:classifiers":[
        {
            "category":"Freight",
            "type":"Transportation"
        }
    ],
    "sg:phone":"+1 270 753 9110",
    "sg:postcode":"42071",
    "sg:province":"KY",
    "sg:tags":[
        "warehouse",
        "merchandise"
    ],
    "wof:name":"Blue Ridge Enterprises",
    "wof:placetype":"venue"
},
  "geometry": {"coordinates":[-88.300287,36.607629],"type":"Point"}
}