{
  "type": "Feature",
  "properties": {
    "iso:country":"US",
    "sg:address":"337 S Buckman St",
    "sg:city":"Shepherdsville",
    "sg:classifiers":[
        {
            "category":"Shopping",
            "subcategory":"Used Merchandise",
            "type":"Retail Goods"
        }
    ],
    "sg:phone":"+1 502 921 1833",
    "sg:postcode":"40165",
    "sg:province":"KY",
    "sg:tags":[
        "shop",
        "thrift"
    ],
    "wof:name":"Outreach Thrift Shop",
    "wof:placetype":"venue"
},
  "geometry": {"coordinates":[-85.716644,37.9881],"type":"Point"}
}