{
  "type": "Feature",
  "properties": {
    "iso:country":"US",
    "sg:address":"2362 Irvine Rd",
    "sg:city":"Richmond",
    "sg:classifiers":[
        {
            "category":"Freight",
            "type":"Transportation"
        }
    ],
    "sg:phone":"+1 859 623 4167",
    "sg:postcode":"40475",
    "sg:province":"KY",
    "sg:tags":[
        "commercial",
        "storage"
    ],
    "wof:name":"ALR Storage Ctr",
    "wof:placetype":"venue"
},
  "geometry": {"coordinates":[-84.20658,37.738251],"type":"Point"}
}