{
  "type": "Feature",
  "properties": {
    "iso:country":"US",
    "sg:address":"268 Grand Central Blvd",
    "sg:city":"Somerset",
    "sg:classifiers":[
        {
            "category":"Restaurant",
            "type":"Food & Drink"
        }
    ],
    "sg:phone":"+1 606 679 0045",
    "sg:postcode":"42503",
    "sg:province":"KY",
    "wof:name":"Cruiser's Cafe",
    "wof:placetype":"venue"
},
  "geometry": {"coordinates":[-84.63495899999999,37.060529],"type":"Point"}
}