{
  "type": "Feature",
  "properties": {
    "addr:full":"701 E Main St Warsaw KY 41095",
    "addr:housenumber":"701",
    "addr:postcode":"41095",
    "addr:street":"E Main St",
    "iso:country":"US",
    "sg:address":"701 E Main St",
    "sg:city":"Warsaw",
    "sg:classifiers":[
        {
            "category":"Education",
            "subcategory":"Junior College",
            "type":"Public Place"
        }
    ],
    "sg:phone":"+1 859 567 5799",
    "sg:postcode":"41095",
    "sg:province":"KY",
    "sg:tags":[
        "technical",
        "institute"
    ],
    "wof:name":"H & R Block Tax Svc",
    "wof:placetype":"venue"
},
  "geometry": {"coordinates":[-84.892583,38.787],"type":"Point"}
}