{
  "type": "Feature",
  "properties": {
    "iso:country":"US",
    "sg:address":"218 W Oak St",
    "sg:city":"Louisville",
    "sg:classifiers":[
        {
            "category":"Landmark",
            "subcategory":"Tourist Information",
            "type":"Public Place"
        }
    ],
    "sg:phone":"+1 502 637 2922",
    "sg:postcode":"40203",
    "sg:province":"KY",
    "sg:tags":[
        "promoter",
        "tours-operators"
    ],
    "wof:name":"Tour Louisville.Com",
    "wof:placetype":"venue"
},
  "geometry": {"coordinates":[-85.757851,38.234798],"type":"Point"}
}