{
  "type": "Feature",
  "properties": {
    "addr:full":"2204 By-Pass Rd Paris KY 40361",
    "addr:housenumber":"2204",
    "addr:postcode":"40361",
    "addr:street":"By-Pass Rd",
    "iso:country":"US",
    "sg:address":"2204 By-Pass Rd",
    "sg:city":"Paris",
    "sg:classifiers":[
        {
            "category":"Restaurant",
            "type":"Food & Drink"
        }
    ],
    "sg:phone":"+1 859 987 7827",
    "sg:postcode":"40361",
    "sg:province":"KY",
    "wof:name":"Subway Sandwiches & Salads",
    "wof:placetype":"venue"
},
  "geometry": {"coordinates":[-84.276871,38.215176],"type":"Point"}
}