{
  "type": "Feature",
  "properties": {
    "iso:country":"US",
    "sg:address":"1907 Plaudit Pl",
    "sg:city":"Lexington",
    "sg:classifiers":[
        {
            "category":"Restaurant",
            "type":"Food & Drink"
        }
    ],
    "sg:menulink":"http://www.allmenus.com/ky/fayette/173525-wendys/menu/",
    "sg:phone":"+1 859 263 2414",
    "sg:postcode":"40509",
    "sg:province":"KY",
    "sg:tags":[
        "burger",
        "american",
        "soup"
    ],
    "wof:name":"Wendy's",
    "wof:placetype":"venue"
},
  "geometry": {"coordinates":[-84.41586599999999,38.018719],"type":"Point"}
}