{
  "type": "Feature",
  "properties": {
    "addr:full":"204 N Main St Elkton KY 42220",
    "addr:housenumber":"204",
    "addr:postcode":"42220",
    "addr:street":"N Main St",
    "iso:country":"US",
    "sg:address":"204 N Main St",
    "sg:city":"Elkton",
    "sg:classifiers":[
        {
            "category":"Autos & Motor Vehicles",
            "subcategory":"Auto Supplies",
            "type":"Retail Goods"
        }
    ],
    "sg:phone":"+1 270 265 2527",
    "sg:postcode":"42220",
    "sg:province":"KY",
    "sg:tags":[
        "automobile",
        "parts"
    ],
    "wof:name":"Elkton Auto Parts",
    "wof:placetype":"venue"
},
  "geometry": {"coordinates":[-87.153561,36.81171],"type":"Point"}
}