{
  "type": "Feature",
  "properties": {
    "addr:full":"11219 Seatonville Rd Louisville KY 40291",
    "addr:housenumber":"11219",
    "addr:postcode":"40291",
    "addr:street":"Seatonville Rd",
    "iso:country":"US",
    "sg:address":"11219 Seatonville Rd",
    "sg:city":"Louisville",
    "sg:phone":"+1 502 239 9107",
    "sg:postcode":"40291",
    "sg:province":"KY",
    "wof:name":"AMS",
    "wof:placetype":"venue"
},
  "geometry": {"coordinates":[-85.550061,38.139286],"type":"Point"}
}