{
  "type": "Feature",
  "properties": {
    "iso:country":"US",
    "sg:address":"721 Kentucky Ave",
    "sg:city":"Paducah",
    "sg:classifiers":[
        {
            "category":"Shopping",
            "subcategory":"Used Merchandise",
            "type":"Retail Goods"
        }
    ],
    "sg:phone":"+1 270 442 5979",
    "sg:postcode":"42003",
    "sg:province":"KY",
    "sg:tags":[
        "shop",
        "consignment"
    ],
    "wof:name":"Second Time Around",
    "wof:placetype":"venue"
},
  "geometry": {"coordinates":[-88.601426,37.084169],"type":"Point"}
}