{
  "type": "Feature",
  "properties": {
    "iso:country":"US",
    "sg:address":"10420 Shelbyville Rd",
    "sg:city":"Anchorage",
    "sg:classifiers":[
        {
            "category":"Personal",
            "subcategory":"Beauty Salon",
            "type":"Services"
        }
    ],
    "sg:phone":"+1 502 245 4113",
    "sg:postcode":"40223",
    "sg:province":"KY",
    "wof:name":"Hair Salon",
    "wof:placetype":"venue"
},
  "geometry": {"coordinates":[-85.56263800000001,38.245266],"type":"Point"}
}