{
  "type": "Feature",
  "properties": {
    "addr:full":"2300 Nicholasville Rd Lexington KY 40503",
    "addr:housenumber":"2300",
    "addr:postcode":"40503",
    "addr:street":"Nicholasville Rd",
    "iso:country":"US",
    "sg:address":"2300 Nicholasville Rd",
    "sg:city":"Lexington",
    "sg:classifiers":[
        {
            "category":"Autos & Motor Vehicles",
            "subcategory":"Auto Supplies",
            "type":"Retail Goods"
        },
        {
            "category":"Wholesale",
            "subcategory":"Electrical",
            "type":"Manufacturing & Wholesale Goods"
        },
        {
            "category":"Wholesale",
            "subcategory":"Auto Parts",
            "type":"Manufacturing & Wholesale Goods"
        },
        {
            "category":"Retail",
            "subcategory":"Auto Repair",
            "type":"Services"
        }
    ],
    "sg:phone":"+1 859 276 6222",
    "sg:postcode":"40503",
    "sg:province":"KY",
    "sg:tags":[
        "engines-rebuild",
        "exchange",
        "battery",
        "automobile",
        "accessory",
        "equipment",
        "supplies-used",
        "truck",
        "rebuilt",
        "batteries-storage"
    ],
    "sg:website":"http://www.advanceautoparts.com",
    "wof:name":"Advance Auto Parts",
    "wof:placetype":"venue"
},
  "geometry": {"coordinates":[-84.51860000000001,38.00573],"type":"Point"}
}