{
  "type": "Feature",
  "properties": {
    "addr:full":"2404 Woodfield Cir Lexington KY 40515",
    "addr:housenumber":"2404",
    "addr:postcode":"40515",
    "addr:street":"Woodfield Cir",
    "iso:country":"US",
    "sg:address":"2404 Woodfield Cir",
    "sg:city":"Lexington",
    "sg:classifiers":[
        {
            "category":"Building & Trades",
            "subcategory":"Construction",
            "type":"Services"
        }
    ],
    "sg:phone":"+1 859 272 8088",
    "sg:postcode":"40515",
    "sg:province":"KY",
    "sg:tags":[
        "contractor"
    ],
    "wof:name":"George Peurach",
    "wof:placetype":"venue"
},
  "geometry": {"coordinates":[-84.466492,37.960508],"type":"Point"}
}