{
  "type": "Feature",
  "properties": {
    "iso:country":"US",
    "sg:address":"3420 Merrick Dr",
    "sg:city":"Lexington",
    "sg:classifiers":[
        {
            "category":"Health Services",
            "subcategory":"Doctor",
            "type":"Services"
        }
    ],
    "sg:phone":"+1 859 335 5634",
    "sg:postcode":"40502",
    "sg:province":"KY",
    "sg:tags":[
        "physician",
        "surgeon"
    ],
    "wof:name":"Raul Heredia MD",
    "wof:placetype":"venue"
},
  "geometry": {"coordinates":[-84.490842,37.994161],"type":"Point"}
}