{
  "type": "Feature",
  "properties": {
    "iso:country":"US",
    "sg:address":"503 5th St",
    "sg:city":"Cloverport",
    "sg:classifiers":[
        {
            "category":"Organizations",
            "subcategory":"Religious Organization",
            "type":"Services"
        }
    ],
    "sg:phone":"+1 270 788 3753",
    "sg:postcode":"40111",
    "sg:province":"KY",
    "wof:name":"Missionary Church Inc",
    "wof:placetype":"venue"
},
  "geometry": {"coordinates":[-86.636002,37.832287],"type":"Point"}
}