{
  "type": "Feature",
  "properties": {
    "iso:country":"US",
    "sg:address":"2100 W Oak St",
    "sg:city":"Louisville",
    "sg:classifiers":[
        {
            "category":"Organizations",
            "subcategory":"Religious Organization",
            "type":"Services"
        }
    ],
    "sg:phone":"+1 502 778 6107",
    "sg:postcode":"40210",
    "sg:province":"KY",
    "sg:tags":[
        "church"
    ],
    "wof:name":"Greater St James A M E Church",
    "wof:placetype":"venue"
},
  "geometry": {"coordinates":[-85.790268,38.237451],"type":"Point"}
}