{
  "type": "Feature",
  "properties": {
    "iso:country":"US",
    "sg:address":"1939 Dixie Hwy",
    "sg:city":"Fort Wright",
    "sg:classifiers":[
        {
            "category":"Organizations",
            "subcategory":"Political Organization",
            "type":"Services"
        }
    ],
    "sg:phone":"+1 859 344 0831",
    "sg:postcode":"41011",
    "sg:province":"KY",
    "wof:name":"Republican Headquarters-Nrthrn",
    "wof:placetype":"venue"
},
  "geometry": {"coordinates":[-84.54863,39.054595],"type":"Point"}
}