{
  "type": "Feature",
  "properties": {
    "iso:country":"US",
    "sg:address":"11316 Angelina Rd",
    "sg:city":"Louisville",
    "sg:classifiers":[
        {
            "category":"Professional",
            "type":"Services"
        }
    ],
    "sg:phone":"+1 502 955 8442",
    "sg:postcode":"40229",
    "sg:province":"KY",
    "sg:tags":[
        "personal",
        "assistant"
    ],
    "wof:name":"Downing Waitressing Service Inc",
    "wof:placetype":"venue"
},
  "geometry": {"coordinates":[-85.692898,38.076021],"type":"Point"}
}