{
  "type": "Feature",
  "properties": {
    "iso:country":"US",
    "sg:address":"4406 Camargo Rd",
    "sg:city":"Mt Sterling",
    "sg:classifiers":[
        {
            "category":"Utilities",
            "subcategory":"Water",
            "type":"Services"
        }
    ],
    "sg:phone":"+1 859 498 0521",
    "sg:postcode":"40353",
    "sg:province":"KY",
    "sg:tags":[
        "company",
        "sewage"
    ],
    "wof:name":"Montgomery County Water Dist",
    "wof:placetype":"venue"
},
  "geometry": {"coordinates":[-83.895385,37.997746],"type":"Point"}
}