{
  "type": "Feature",
  "properties": {
    "iso:country":"US",
    "sg:address":"3950 Lovelaceville Rd",
    "sg:city":"Paducah",
    "sg:classifiers":[
        {
            "category":"Organizations",
            "subcategory":"Religious Organization",
            "type":"Services"
        }
    ],
    "sg:phone":"+1 270 554 3572",
    "sg:postcode":"42001",
    "sg:province":"KY",
    "wof:name":"Highland Cmbrland Prsbt Church",
    "wof:placetype":"venue"
},
  "geometry": {"coordinates":[-88.68543099999999,37.030248],"type":"Point"}
}