{
  "type": "Feature",
  "properties": {
    "addr:full":"501 S Preston St Louisville KY 40202",
    "addr:housenumber":"501",
    "addr:postcode":"40202",
    "addr:street":"S Preston St",
    "iso:country":"US",
    "sg:address":"501 S Preston St",
    "sg:city":"Louisville",
    "sg:classifiers":[
        {
            "category":"Education",
            "subcategory":"Library",
            "type":"Public Place"
        }
    ],
    "sg:phone":"+1 502 852 1278",
    "sg:postcode":"40202",
    "sg:province":"KY",
    "sg:website":"http://www.louisville.edu",
    "wof:name":"Kornhuser Library",
    "wof:placetype":"venue"
},
  "geometry": {"coordinates":[-85.74685700000001,38.249962],"type":"Point"}
}