{
  "type": "Feature",
  "properties": {
    "iso:country":"US",
    "sg:address":"3009 W Broadway",
    "sg:city":"Louisville",
    "sg:classifiers":[
        {
            "category":"Personal",
            "subcategory":"Beauty Salon",
            "type":"Services"
        }
    ],
    "sg:phone":"+1 502 774 5581",
    "sg:postcode":"40211",
    "sg:province":"KY",
    "wof:name":"Oohs & Ahhs Hair & Nail Salon",
    "wof:placetype":"venue"
},
  "geometry": {"coordinates":[-85.80210599999999,38.249767],"type":"Point"}
}