{
  "type": "Feature",
  "properties": {
    "addr:full":"130 N Chiles St Harrodsburg KY 40330",
    "addr:housenumber":"130",
    "addr:postcode":"40330",
    "addr:street":"N Chiles St",
    "iso:country":"US",
    "sg:address":"130 N Chiles St",
    "sg:city":"Harrodsburg",
    "sg:classifiers":[
        {
            "category":"Shopping",
            "subcategory":"Pharmacy",
            "type":"Retail Goods"
        }
    ],
    "sg:phone":"+1 859 734 5476",
    "sg:postcode":"40330",
    "sg:province":"KY",
    "wof:name":"CVS Pharmacy",
    "wof:placetype":"venue"
},
  "geometry": {"coordinates":[-84.844431,37.763249],"type":"Point"}
}