{
  "type": "Feature",
  "properties": {
    "addr:full":"303 Sycamore Dr Clinton KY 42031",
    "addr:housenumber":"303",
    "addr:postcode":"42031",
    "addr:street":"Sycamore Dr",
    "iso:country":"US",
    "sg:address":"303 Sycamore Dr",
    "sg:city":"Clinton",
    "sg:classifiers":[
        {
            "category":"Personal",
            "subcategory":"Tattoo Parlor",
            "type":"Services"
        }
    ],
    "sg:phone":"+1 270 653 7217",
    "sg:postcode":"42031",
    "sg:province":"KY",
    "sg:tags":[
        "tattooing"
    ],
    "wof:name":"Jennifer Hicks",
    "wof:placetype":"venue"
},
  "geometry": {"coordinates":[-88.999132,36.669384],"type":"Point"}
}