{
  "type": "Feature",
  "properties": {
    "addr:full":"717 S Main St Nicholasville KY 40356",
    "addr:housenumber":"717",
    "addr:postcode":"40356",
    "addr:street":"S Main St",
    "iso:country":"US",
    "sg:address":"717 S Main St",
    "sg:city":"Nicholasville",
    "sg:classifiers":[
        {
            "category":"Organizations",
            "subcategory":"Religious Organization",
            "type":"Services"
        }
    ],
    "sg:phone":"+1 859 885 6211",
    "sg:postcode":"40356",
    "sg:province":"KY",
    "sg:tags":[
        "church"
    ],
    "sg:website":"www.edgewoodbaptistchurch.com",
    "wof:name":"Edgewood Baptist Church",
    "wof:placetype":"venue"
},
  "geometry": {"coordinates":[-84.576999,37.870217],"type":"Point"}
}