{
  "type": "Feature",
  "properties": {
    "iso:country":"US",
    "sg:address":"5317 Dixie Hwy",
    "sg:city":"Louisville",
    "sg:classifiers":[
        {
            "category":"Retail",
            "subcategory":"Funeral Services",
            "type":"Services"
        }
    ],
    "sg:phone":"+1 502 447 2600",
    "sg:postcode":"40216",
    "sg:province":"KY",
    "sg:tags":[
        "director",
        "burial",
        "casket",
        "vault"
    ],
    "sg:website":"http://owenfuneralhome.com",
    "wof:name":"Owen Funeral Home",
    "wof:placetype":"venue"
},
  "geometry": {"coordinates":[-85.832767,38.159888],"type":"Point"}
}