{
  "type": "Feature",
  "properties": {
    "iso:country":"US",
    "sg:address":"21470 State Hwy 30",
    "sg:city":"Jackson",
    "sg:classifiers":[
        {
            "category":"Freight",
            "type":"Transportation"
        }
    ],
    "sg:phone":"+1 606 666 5618",
    "sg:postcode":"41339",
    "sg:province":"KY",
    "sg:tags":[
        "operator",
        "local",
        "trucking"
    ],
    "wof:name":"Brown Essie",
    "wof:placetype":"venue"
},
  "geometry": {"coordinates":[-83.174616,37.623702],"type":"Point"}
}