{
  "type": "Feature",
  "properties": {
    "addr:full":"6040 Dutchmans Ln Louisville KY 40205",
    "addr:housenumber":"6040",
    "addr:postcode":"40205",
    "addr:street":"Dutchmans Ln",
    "iso:country":"US",
    "sg:address":"6040 Dutchmans Ln",
    "sg:city":"Louisville",
    "sg:classifiers":[
        {
            "category":"Personal",
            "type":"Services"
        }
    ],
    "sg:phone":"+1 502 451 6060",
    "sg:postcode":"40205",
    "sg:province":"KY",
    "sg:tags":[
        "credit",
        "debt",
        "counseling"
    ],
    "wof:name":"William S Reisz",
    "wof:placetype":"venue"
},
  "geometry": {"coordinates":[-85.64021700000001,38.228485],"type":"Point"}
}