{
  "type": "Feature",
  "properties": {
    "iso:country":"US",
    "sg:address":"5341 Taylorsville Rd",
    "sg:city":"Finchville",
    "sg:classifiers":[
        {
            "category":"Social Services",
            "subcategory":"Child Care",
            "type":"Services"
        },
        {
            "category":"Education",
            "subcategory":"Special Training",
            "type":"Public Place"
        }
    ],
    "sg:phone":"+1 502 647 5200",
    "sg:postcode":"40022",
    "sg:province":"KY",
    "sg:tags":[
        "center"
    ],
    "wof:name":"Bright Horizons Learning Ctr",
    "wof:placetype":"venue"
},
  "geometry": {"coordinates":[-85.317823,38.149008],"type":"Point"}
}