{
  "type": "Feature",
  "properties": {
    "iso:country":"US",
    "sg:address":"161 College St",
    "sg:city":"Pikeville",
    "sg:classifiers":[
        {
            "category":"Health Services",
            "subcategory":"Chiropractor",
            "type":"Services"
        }
    ],
    "sg:phone":"+1 606 432 8395",
    "sg:postcode":"41501",
    "sg:province":"KY",
    "wof:name":"Akers Family Chiropractic",
    "wof:placetype":"venue"
},
  "geometry": {"coordinates":[-82.520645,37.476979],"type":"Point"}
}