{
  "type": "Feature",
  "properties": {
    "addr:full":"100 Turtle Creek Dr Hopkinsville KY 42240",
    "addr:housenumber":"100",
    "addr:postcode":"42240",
    "addr:street":"Turtle Creek Dr",
    "iso:country":"US",
    "sg:address":"100 Turtle Creek Dr",
    "sg:city":"Hopkinsville",
    "sg:classifiers":[
        {
            "category":"Recreation",
            "type":"Entertainment"
        }
    ],
    "sg:phone":"+1 270 887 0479",
    "sg:postcode":"42240",
    "sg:province":"KY",
    "sg:tags":[
        "instruction",
        "gymnastic"
    ],
    "wof:name":"Angel's School Of Dance",
    "wof:placetype":"venue"
},
  "geometry": {"coordinates":[-87.50687000000001,36.825124],"type":"Point"}
}