{
  "type": "Feature",
  "properties": {
    "iso:country":"US",
    "sg:address":"3170 Industrial Dr",
    "sg:city":"Bowling Green",
    "sg:phone":"+1 270 781 2590",
    "sg:postcode":"42101",
    "sg:province":"KY",
    "sg:tags":[
        "oil"
    ],
    "wof:name":"Key Oil Co",
    "wof:placetype":"venue"
},
  "geometry": {"coordinates":[-86.478627,36.95653],"type":"Point"}
}