{
  "type": "Feature",
  "properties": {
    "addr:full":"101 S 8th St Louisville KY 40202",
    "addr:housenumber":"101",
    "addr:postcode":"40202",
    "addr:street":"S 8Th St",
    "iso:country":"US",
    "sg:address":"101 S 8th St",
    "sg:city":"Louisville",
    "sg:classifiers":[
        {
            "category":"Government",
            "subcategory":"Office",
            "type":"Public Place"
        }
    ],
    "sg:phone":"+1 502 574 4900",
    "sg:postcode":"40202",
    "sg:province":"KY",
    "sg:tags":[
        "county",
        "taxation"
    ],
    "wof:name":"Jefferson County Revenue",
    "wof:placetype":"venue"
},
  "geometry": {"coordinates":[-85.76326899999999,38.256651],"type":"Point"}
}