{
  "type": "Feature",
  "properties": {
    "addr:full":"3361 Taylor Blvd Louisville KY 40215",
    "addr:housenumber":"3361",
    "addr:postcode":"40215",
    "addr:street":"Taylor Blvd",
    "iso:country":"US",
    "sg:address":"3361 Taylor Blvd",
    "sg:city":"Louisville",
    "sg:classifiers":[
        {
            "category":"Real Estate",
            "subcategory":"Real Estate Agent",
            "type":"Services"
        }
    ],
    "sg:phone":"+1 502 366 0206",
    "sg:postcode":"40215",
    "sg:province":"KY",
    "wof:name":"Louisville Rentals LLC",
    "wof:placetype":"venue"
},
  "geometry": {"coordinates":[-85.782523,38.200123],"type":"Point"}
}