{
  "type": "Feature",
  "properties": {
    "iso:country":"US",
    "sg:address":"3061 Fieldstone Way",
    "sg:city":"Lexington",
    "sg:classifiers":[
        {
            "category":"Restaurant",
            "type":"Food & Drink"
        }
    ],
    "sg:phone":"+1 859 296 0888",
    "sg:postcode":"40513",
    "sg:province":"KY",
    "wof:name":"Oriental Garden",
    "wof:placetype":"venue"
},
  "geometry": {"coordinates":[-84.5573,38.013749],"type":"Point"}
}