{
  "type": "Feature",
  "properties": {
    "addr:full":"220 E Maple St Nicholasville KY 40356",
    "addr:housenumber":"220",
    "addr:postcode":"40356",
    "addr:street":"E Maple St",
    "iso:country":"US",
    "sg:address":"220 E Maple St",
    "sg:city":"Nicholasville",
    "sg:classifiers":[
        {
            "category":"Social Services",
            "type":"Services"
        }
    ],
    "sg:phone":"+1 859 885 5013",
    "sg:postcode":"40356",
    "sg:province":"KY",
    "sg:tags":[
        "organization",
        "welfare"
    ],
    "wof:name":"YMCA",
    "wof:placetype":"venue"
},
  "geometry": {"coordinates":[-84.57103499999999,37.87986],"type":"Point"}
}