{
  "type": "Feature",
  "properties": {
    "iso:country":"US",
    "sg:address":"4926 Unseld Blvd",
    "sg:city":"Louisville",
    "sg:classifiers":[
        {
            "category":"Professional",
            "type":"Services"
        }
    ],
    "sg:phone":"+1 502 452 6733",
    "sg:postcode":"40218",
    "sg:province":"KY",
    "sg:tags":[
        "establishment"
    ],
    "wof:name":"Cancer Survivors Foundation",
    "wof:placetype":"venue"
},
  "geometry": {"coordinates":[-85.671522,38.177271],"type":"Point"}
}