{
  "type": "Feature",
  "properties": {
    "addr:full":"144 Pasadena Dr Lexington KY 40503",
    "addr:housenumber":"144",
    "addr:postcode":"40503",
    "addr:street":"Pasadena Dr",
    "iso:country":"US",
    "sg:address":"144 Pasadena Dr",
    "sg:city":"Lexington",
    "sg:classifiers":[
        {
            "category":"Retail",
            "subcategory":"Portrait Studio",
            "type":"Services"
        }
    ],
    "sg:phone":"+1 859 277 6671",
    "sg:postcode":"40503",
    "sg:province":"KY",
    "sg:tags":[
        "photographer"
    ],
    "wof:name":"Portrait Shoppe",
    "wof:placetype":"venue"
},
  "geometry": {"coordinates":[-84.523723,38.004838],"type":"Point"}
}