{
  "type": "Feature",
  "properties": {
    "addr:full":"628 Henton St Livermore KY 42352",
    "addr:housenumber":"628",
    "addr:postcode":"42352",
    "addr:street":"Henton St",
    "iso:country":"US",
    "sg:address":"628 Henton St",
    "sg:city":"Livermore",
    "sg:classifiers":[
        {
            "category":"Shopping",
            "subcategory":"Music",
            "type":"Retail Goods"
        }
    ],
    "sg:phone":"+1 270 278 5036",
    "sg:postcode":"42352",
    "sg:province":"KY",
    "sg:tags":[
        "video",
        "disc",
        "tape",
        "cassette"
    ],
    "wof:name":"Movie Madness",
    "wof:placetype":"venue"
},
  "geometry": {"coordinates":[-87.126668,37.492953],"type":"Point"}
}