{
  "type": "Feature",
  "properties": {
    "iso:country":"US",
    "sg:address":"2402 Nopper Ct",
    "sg:city":"Louisville",
    "sg:classifiers":[
        {
            "category":"Professional",
            "type":"Services"
        }
    ],
    "sg:phone":"+1 502 439 2298",
    "sg:postcode":"40220",
    "sg:province":"KY",
    "wof:name":"Safety Education",
    "wof:placetype":"venue"
},
  "geometry": {"coordinates":[-85.594014,38.209217],"type":"Point"}
}