{
  "type": "Feature",
  "properties": {
    "iso:country":"US",
    "sg:address":"3254 Taylor Blvd",
    "sg:city":"Louisville",
    "sg:classifiers":[
        {
            "category":"Health Services",
            "subcategory":"Chiropractor",
            "type":"Services"
        }
    ],
    "sg:phone":"+1 502 366 9966",
    "sg:postcode":"40215",
    "sg:province":"KY",
    "wof:name":"Taylor Blvd Chiropractic Ofc",
    "wof:placetype":"venue"
},
  "geometry": {"coordinates":[-85.78025100000001,38.203235],"type":"Point"}
}