{
  "type": "Feature",
  "properties": {
    "iso:country":"US",
    "sg:address":"487 Carrick Rd",
    "sg:city":"Georgetown",
    "sg:classifiers":[
        {
            "category":"Farming",
            "subcategory":"Farm",
            "type":"Manufacturing & Wholesale Goods"
        }
    ],
    "sg:phone":"+1 502 868 5272",
    "sg:postcode":"40324",
    "sg:province":"KY",
    "wof:name":"Bona Terra Farm LLC",
    "wof:placetype":"venue"
},
  "geometry": {"coordinates":[-84.452285,38.20647],"type":"Point"}
}