{
  "type": "Feature",
  "properties": {
    "iso:country":"US",
    "sg:address":"804 W Main St",
    "sg:city":"Glasgow",
    "sg:classifiers":[
        {
            "category":"Personal",
            "subcategory":"Tanning Parlor",
            "type":"Services"
        }
    ],
    "sg:phone":"+1 270 629 5442",
    "sg:postcode":"42141",
    "sg:province":"KY",
    "sg:tags":[
        "salon"
    ],
    "wof:name":"Electric Beach Coffee & Juice",
    "wof:placetype":"venue"
},
  "geometry": {"coordinates":[-85.923776,37.000417],"type":"Point"}
}