{
  "type": "Feature",
  "properties": {
    "iso:country":"US",
    "sg:address":"110 N 11th St",
    "sg:city":"Middlesboro",
    "sg:classifiers":[
        {
            "category":"Communications",
            "subcategory":"Newspaper",
            "type":"Services"
        }
    ],
    "sg:phone":"+1 606 248 2274",
    "sg:postcode":"40965",
    "sg:province":"KY",
    "wof:name":"Trading Post",
    "wof:placetype":"venue"
},
  "geometry": {"coordinates":[-83.700203,36.608311],"type":"Point"}
}