{
  "type": "Feature",
  "properties": {
    "iso:country":"US",
    "sg:address":"209 E Main St",
    "sg:city":"Glasgow",
    "sg:classifiers":[
        {
            "category":"Personal",
            "subcategory":"Beauty Salon",
            "type":"Services"
        }
    ],
    "sg:phone":"+1 270 651 5711",
    "sg:postcode":"42141",
    "sg:province":"KY",
    "wof:name":"Patricia's Beauty Ctr",
    "wof:placetype":"venue"
},
  "geometry": {"coordinates":[-85.910658,36.99547],"type":"Point"}
}