{
  "type": "Feature",
  "properties": {
    "iso:country":"US",
    "sg:address":"806 S Dogwood Dr",
    "sg:city":"Berea",
    "sg:classifiers":[
        {
            "category":"Building & Trades",
            "subcategory":"Landscaping Services",
            "type":"Services"
        }
    ],
    "sg:phone":"+1 859 985 0246",
    "sg:postcode":"40403",
    "sg:province":"KY",
    "wof:name":"County Wide Enterprises Inc",
    "wof:placetype":"venue"
},
  "geometry": {"coordinates":[-84.32114199999999,37.551069],"type":"Point"}
}