{
  "type": "Feature",
  "properties": {
    "addr:full":"3900 Calgary Way Louisville KY 40241",
    "addr:housenumber":"3900",
    "addr:postcode":"40241",
    "addr:street":"Calgary Way",
    "iso:country":"US",
    "sg:address":"3900 Calgary Way",
    "sg:city":"Louisville",
    "sg:classifiers":[
        {
            "category":"Professional",
            "subcategory":"Advertising",
            "type":"Services"
        }
    ],
    "sg:phone":"+1 502 558 1591",
    "sg:postcode":"40241",
    "sg:province":"KY",
    "sg:tags":[
        "promotion",
        "sale"
    ],
    "wof:name":"A G Promotions",
    "wof:placetype":"venue"
},
  "geometry": {"coordinates":[-85.59017900000001,38.300732],"type":"Point"}
}