{
  "type": "Feature",
  "properties": {
    "iso:country":"US",
    "sg:address":"984 Frys-Oldburg Rd",
    "sg:city":"Bagdad",
    "sg:classifiers":[
        {
            "category":"Shopping",
            "subcategory":"Computers & Home Electronics",
            "type":"Retail Goods"
        }
    ],
    "sg:phone":"+1 502 747 5079",
    "sg:postcode":"40003",
    "sg:province":"KY",
    "sg:tags":[
        "repair"
    ],
    "wof:name":"Browns Satellite Systems",
    "wof:placetype":"venue"
},
  "geometry": {"coordinates":[-85.08546,38.280443],"type":"Point"}
}