{
  "type": "Feature",
  "properties": {
    "iso:country":"US",
    "sg:address":"3923 Bardstown Rd",
    "sg:city":"Louisville",
    "sg:classifiers":[
        {
            "category":"Real Estate",
            "subcategory":"Surveying",
            "type":"Services"
        }
    ],
    "sg:phone":"+1 502 491 7010",
    "sg:postcode":"40218",
    "sg:province":"KY",
    "sg:tags":[
        "surveyor"
    ],
    "sg:website":"www.mikeseely.com",
    "wof:name":"Seely & Assoc Land Surveyors",
    "wof:placetype":"venue"
},
  "geometry": {"coordinates":[-85.64945,38.193482],"type":"Point"}
}