{
  "type": "Feature",
  "properties": {
    "addr:full":"2338 Frankfort Ave Louisville KY 40206",
    "addr:housenumber":"2338",
    "addr:postcode":"40206",
    "addr:street":"Frankfort",
    "iso:country":"US",
    "sg:address":"2338 Frankfort Ave",
    "sg:city":"Louisville",
    "sg:classifiers":[
        {
            "category":"Professional",
            "subcategory":"Advertising",
            "type":"Services"
        }
    ],
    "sg:phone":"+1 502 895 4881",
    "sg:postcode":"40206",
    "sg:province":"KY",
    "sg:tags":[
        "counselor"
    ],
    "sg:website":"www.danburch.com",
    "wof:name":"Burch Associates Inc",
    "wof:placetype":"venue"
},
  "geometry": {"coordinates":[-85.70174400000001,38.253423],"type":"Point"}
}