{
  "type": "Feature",
  "properties": {
    "addr:full":"5258 State Hwy 1428 Allen KY 41601",
    "addr:housenumber":"5258",
    "addr:postcode":"1428;41601",
    "addr:street":"State Hwy",
    "iso:country":"US",
    "sg:address":"5258 State Hwy 1428",
    "sg:city":"Allen",
    "sg:classifiers":[
        {
            "category":"Mining & Drilling",
            "type":"Manufacturing & Wholesale Goods"
        }
    ],
    "sg:phone":"+1 606 874 1074",
    "sg:postcode":"41601",
    "sg:province":"KY",
    "sg:tags":[
        "oil",
        "well"
    ],
    "wof:name":"Meeks Wireline Svc",
    "wof:placetype":"venue"
},
  "geometry": {"coordinates":[-82.727789,37.61135],"type":"Point"}
}