{
  "type": "Feature",
  "properties": {
    "addr:full":"2053 Salem School Rd Rineyville KY 40162",
    "addr:housenumber":"2053",
    "addr:postcode":"40162",
    "addr:street":"Salem School Rd",
    "iso:country":"US",
    "sg:address":"2053 Salem School Rd",
    "sg:city":"Rineyville",
    "sg:classifiers":[
        {
            "category":"Farming",
            "subcategory":"Livestock Farm",
            "type":"Manufacturing & Wholesale Goods"
        }
    ],
    "sg:phone":"+1 270 877 5737",
    "sg:postcode":"40162",
    "sg:province":"KY",
    "sg:tags":[
        "feedlot",
        "field",
        "crop",
        "beef",
        "cattle"
    ],
    "wof:name":"Joe Lucas",
    "wof:placetype":"venue"
},
  "geometry": {"coordinates":[-86.05519700000001,37.774631],"type":"Point"}
}