{
  "type": "Feature",
  "properties": {
    "addr:full":"205 Jefferies Ln Hustonville KY 40437",
    "addr:housenumber":"205",
    "addr:postcode":"40437",
    "addr:street":"Jefferies Ln",
    "iso:country":"US",
    "sg:address":"205 Jefferies Ln",
    "sg:city":"Hustonville",
    "sg:classifiers":[
        {
            "category":"Autos & Motor Vehicles",
            "subcategory":"Boat Sales",
            "type":"Retail Goods"
        }
    ],
    "sg:phone":"+1 606 346 2628",
    "sg:postcode":"40437",
    "sg:province":"KY",
    "sg:tags":[
        "dealer",
        "sales"
    ],
    "wof:name":"Sargeant's Marine",
    "wof:placetype":"venue"
},
  "geometry": {"coordinates":[-84.810462,37.502132],"type":"Point"}
}