{
  "type": "Feature",
  "properties": {
    "addr:full":"2297 Morgantown Rd Russellville KY 42276",
    "addr:housenumber":"2297",
    "addr:postcode":"42276",
    "addr:street":"Morgantown Rd",
    "iso:country":"US",
    "sg:address":"2297 Morgantown Rd",
    "sg:city":"Russellville",
    "sg:classifiers":[
        {
            "category":"Retail",
            "subcategory":"Repair Shop",
            "type":"Services"
        }
    ],
    "sg:phone":"+1 270 726 9100",
    "sg:postcode":"42276",
    "sg:province":"KY",
    "sg:tags":[
        "equipment",
        "hydraulic"
    ],
    "wof:name":"Industrial Hydraulic Svc",
    "wof:placetype":"venue"
},
  "geometry": {"coordinates":[-86.862894,36.870501],"type":"Point"}
}