{
  "type": "Feature",
  "properties": {
    "addr:full":"1142 Paint Lick Rd Berea KY 40403",
    "addr:housenumber":"1142",
    "addr:postcode":"40403",
    "addr:street":"Paint Lick Rd",
    "iso:country":"US",
    "sg:address":"1142 Paint Lick Rd",
    "sg:city":"Berea",
    "sg:classifiers":[
        {
            "category":"Home & Garden",
            "subcategory":"Hardware",
            "type":"Retail Goods"
        }
    ],
    "sg:phone":"+1 859 986 4544",
    "sg:postcode":"40403",
    "sg:province":"KY",
    "wof:name":"True Value Hardware",
    "wof:placetype":"venue"
},
  "geometry": {"coordinates":[-84.322755,37.565931],"type":"Point"}
}