{
  "type": "Feature",
  "properties": {
    "addr:full":"315 N Main St Harrodsburg KY 40330",
    "addr:housenumber":"315",
    "addr:postcode":"40330",
    "addr:street":"N Main St",
    "iso:country":"US",
    "sg:address":"315 N Main St",
    "sg:city":"Harrodsburg",
    "sg:classifiers":[
        {
            "category":"Wholesale",
            "subcategory":"Durable Goods & Equipment",
            "type":"Manufacturing & Wholesale Goods"
        }
    ],
    "sg:phone":"+1 859 734 9682",
    "sg:postcode":"40330",
    "sg:province":"KY",
    "sg:tags":[
        "exporter"
    ],
    "wof:name":"Mercer Association Of Kentucky",
    "wof:placetype":"venue"
},
  "geometry": {"coordinates":[-84.842797,37.766327],"type":"Point"}
}