{
  "type": "Feature",
  "properties": {
    "iso:country":"US",
    "sg:address":"340 North Dr",
    "sg:city":"Hopkinsville",
    "sg:classifiers":[
        {
            "category":"Building & Trades",
            "subcategory":"Equipment Rental",
            "type":"Services"
        }
    ],
    "sg:phone":"+1 270 886 4401",
    "sg:postcode":"42240",
    "sg:province":"KY",
    "sg:tags":[
        "contractor"
    ],
    "wof:name":"Leveelift Inc",
    "wof:placetype":"venue"
},
  "geometry": {"coordinates":[-87.50233799999999,36.867661],"type":"Point"}
}