{
  "type": "Feature",
  "properties": {
    "iso:country":"US",
    "sg:address":"630 R Grider Rd",
    "sg:city":"Russell Springs",
    "sg:classifiers":[
        {
            "category":"Retail",
            "subcategory":"Auto Repair",
            "type":"Services"
        }
    ],
    "sg:phone":"+1 270 384 0422",
    "sg:postcode":"42642",
    "sg:province":"KY",
    "sg:tags":[
        "body",
        "automobile",
        "painting"
    ],
    "wof:name":"Joe Brown Autobody Repair",
    "wof:placetype":"venue"
},
  "geometry": {"coordinates":[-85.168999,37.069934],"type":"Point"}
}