{
  "type": "Feature",
  "properties": {
    "iso:country":"US",
    "sg:address":"2349 Russellville Rd",
    "sg:city":"Bowling Green",
    "sg:classifiers":[
        {
            "category":"Retail",
            "subcategory":"Repair Shop",
            "type":"Services"
        }
    ],
    "sg:phone":"+1 270 843 9441",
    "sg:postcode":"42101",
    "sg:province":"KY",
    "sg:tags":[
        "body",
        "auto"
    ],
    "wof:name":"Kinser Upholstery & Trim Inc",
    "wof:placetype":"venue"
},
  "geometry": {"coordinates":[-86.478146,36.970682],"type":"Point"}
}