{
  "type": "Feature",
  "properties": {
    "iso:country":"US",
    "sg:address":"247 Evans Dr",
    "sg:city":"Mt Sterling",
    "sg:classifiers":[
        {
            "category":"Wholesale",
            "subcategory":"Sporting Goods",
            "type":"Manufacturing & Wholesale Goods"
        }
    ],
    "sg:phone":"+1 859 498 7727",
    "sg:postcode":"40353",
    "sg:province":"KY",
    "sg:tags":[
        "equipment",
        "pool",
        "swimming"
    ],
    "wof:name":"Paris Pool Supply",
    "wof:placetype":"venue"
},
  "geometry": {"coordinates":[-83.951078,38.075528],"type":"Point"}
}