{
  "type": "Feature",
  "properties": {
    "iso:country":"US",
    "sg:address":"160 Locust Grove Rd",
    "sg:city":"Carlisle",
    "sg:classifiers":[
        {
            "category":"Personal",
            "subcategory":"Barber",
            "type":"Services"
        }
    ],
    "sg:phone":"+1 859 289 7085",
    "sg:postcode":"40311",
    "sg:province":"KY",
    "wof:name":"Hair Hut",
    "wof:placetype":"venue"
},
  "geometry": {"coordinates":[-83.963852,38.306915],"type":"Point"}
}