{
  "type": "Feature",
  "properties": {
    "addr:full":"157 W 5th St Russellville KY 42276",
    "addr:housenumber":"157",
    "addr:postcode":"42276",
    "addr:street":"W 5Th St",
    "iso:country":"US",
    "sg:address":"157 W 5th St",
    "sg:city":"Russellville",
    "sg:classifiers":[
        {
            "category":"Professional",
            "subcategory":"Lawyer & Legal Services",
            "type":"Services"
        }
    ],
    "sg:phone":"+1 270 726 9604",
    "sg:postcode":"42276",
    "sg:province":"KY",
    "sg:tags":[
        "attorney"
    ],
    "wof:name":"C Robert Hedges",
    "wof:placetype":"venue"
},
  "geometry": {"coordinates":[-86.887281,36.844368],"type":"Point"}
}