{
  "type": "Feature",
  "properties": {
    "iso:country":"US",
    "sg:address":"981 Campbell Ln",
    "sg:city":"Bowling Green",
    "sg:classifiers":[
        {
            "category":"Personal",
            "subcategory":"Beauty Salon",
            "type":"Services"
        }
    ],
    "sg:phone":"+1 270 393 7171",
    "sg:postcode":"42104",
    "sg:province":"KY",
    "wof:name":"Moorningside Styling Salon",
    "wof:placetype":"venue"
},
  "geometry": {"coordinates":[-86.458648,36.960991],"type":"Point"}
}