{
  "type": "Feature",
  "properties": {
    "iso:country":"US",
    "sg:address":"389 Landis Ln",
    "sg:city":"Mt Washington",
    "sg:classifiers":[
        {
            "category":"Manufacturing",
            "subcategory":"Glass & Minerals",
            "type":"Manufacturing & Wholesale Goods"
        }
    ],
    "sg:phone":"+1 502 955 5382",
    "sg:postcode":"40047",
    "sg:province":"KY",
    "sg:tags":[
        "ready"
    ],
    "wof:name":"Irving Materials Inc",
    "wof:placetype":"venue"
},
  "geometry": {"coordinates":[-85.556017,38.064595],"type":"Point"}
}