{
  "type": "Feature",
  "properties": {
    "iso:country":"US",
    "sg:address":"2917 Bloomfield Rd",
    "sg:city":"Taylorsville",
    "sg:classifiers":[
        {
            "category":"Professional",
            "subcategory":"Business Services",
            "type":"Services"
        }
    ],
    "sg:phone":"+1 502 477 8689",
    "sg:postcode":"40071",
    "sg:province":"KY",
    "wof:name":"Web Design Pro",
    "wof:placetype":"venue"
},
  "geometry": {"coordinates":[-85.342889,38.027411],"type":"Point"}
}