{
  "type": "Feature",
  "properties": {
    "iso:country":"US",
    "sg:address":"707 Chestnut St",
    "sg:city":"Berea",
    "sg:classifiers":[
        {
            "category":"Food & Beverages",
            "subcategory":"Groceries & Convenience Stores",
            "type":"Retail Goods"
        }
    ],
    "sg:phone":"+1 859 986 9573",
    "sg:postcode":"40403",
    "sg:province":"KY",
    "wof:name":"Dairy Mart",
    "wof:placetype":"venue"
},
  "geometry": {"coordinates":[-84.303129,37.568116],"type":"Point"}
}