{
  "type": "Feature",
  "properties": {
    "addr:full":"2325 Bardstown Rd Louisville KY 40205",
    "addr:housenumber":"2325",
    "addr:postcode":"40205",
    "addr:street":"Bardstown Rd",
    "iso:country":"US",
    "sg:address":"2325 Bardstown Rd",
    "sg:city":"Louisville",
    "sg:classifiers":[
        {
            "category":"Government",
            "subcategory":"Post Office",
            "type":"Public Place"
        }
    ],
    "sg:phone":"+1 502 458 4259",
    "sg:postcode":"40205",
    "sg:province":"KY",
    "sg:tags":[
        "poster"
    ],
    "sg:website":"http://www.electricladyland.net",
    "wof:name":"Electric Ladyland",
    "wof:placetype":"venue"
},
  "geometry": {"coordinates":[-85.68991200000001,38.223959],"type":"Point"}
}