{
  "type": "Feature",
  "properties": {
    "iso:country":"US",
    "sg:address":"7711 Breeding Rd",
    "sg:city":"Edmonton",
    "sg:classifiers":[
        {
            "category":"Retail",
            "subcategory":"Animal Services",
            "type":"Services"
        }
    ],
    "sg:phone":"+1 270 432 2140",
    "sg:postcode":"42129",
    "sg:province":"KY",
    "sg:tags":[
        "pet",
        "boarding",
        "sitting"
    ],
    "wof:name":"Ezile Arabian Stud Farm",
    "wof:placetype":"venue"
},
  "geometry": {"coordinates":[-85.482038,36.956068],"type":"Point"}
}