{
  "type": "Feature",
  "properties": {
    "addr:full":"1816 Patrick Dr Burlington KY 41005",
    "addr:housenumber":"1816",
    "addr:postcode":"41005",
    "addr:street":"Patrick Dr",
    "iso:country":"US",
    "sg:address":"1816 Patrick Dr",
    "sg:city":"Burlington",
    "sg:classifiers":[
        {
            "category":"Restaurant",
            "type":"Food & Drink"
        }
    ],
    "sg:menulink":"http://www.allmenus.com/ky/florence/197358-burger-king/menu/",
    "sg:phone":"+1 606 586 0190",
    "sg:postcode":"41005",
    "sg:province":"KY",
    "sg:tags":[
        "burger",
        "american"
    ],
    "wof:name":"Burger King",
    "wof:placetype":"venue"
},
  "geometry": {"coordinates":[-84.695796,39.019518],"type":"Point"}
}