{
  "type": "Feature",
  "properties": {
    "iso:country":"US",
    "sg:address":"5028 Old Taylor Mill Rd",
    "sg:city":"Taylor Mill",
    "sg:classifiers":[
        {
            "category":"Real Estate",
            "subcategory":"Real Estate Agent",
            "type":"Services"
        }
    ],
    "sg:phone":"+1 859 442 1400",
    "sg:postcode":"41015",
    "sg:province":"KY",
    "sg:website":"www.realtyexecutivesky.com",
    "wof:name":"Realty Executive Of Kentucky",
    "wof:placetype":"venue"
},
  "geometry": {"coordinates":[-84.508139,39.017036],"type":"Point"}
}