{
  "type": "Feature",
  "properties": {
    "iso:country":"US",
    "sg:address":"2900 Dolphin Dr",
    "sg:city":"Elizabethtown",
    "sg:classifiers":[
        {
            "category":"Banks & Credit Unions",
            "subcategory":"Investment Brokerage",
            "type":"Services"
        }
    ],
    "sg:phone":"+1 270 737 4224",
    "sg:postcode":"42701",
    "sg:province":"KY",
    "wof:name":"A L Dennis Wealth Management",
    "wof:placetype":"venue"
},
  "geometry": {"coordinates":[-85.837926,37.720166],"type":"Point"}
}