{
  "type": "Feature",
  "properties": {
    "iso:country":"US",
    "sg:address":"5389 New Cut Rd",
    "sg:city":"Louisville",
    "sg:classifiers":[
        {
            "category":"Autos & Motor Vehicles",
            "subcategory":"Fuel & Gas Station",
            "type":"Retail Goods"
        }
    ],
    "sg:phone":"+1 502 361 9121",
    "sg:postcode":"40214",
    "sg:province":"KY",
    "sg:tags":[
        "oil"
    ],
    "wof:name":"Swifty Service Station",
    "wof:placetype":"venue"
},
  "geometry": {"coordinates":[-85.77634500000001,38.151033],"type":"Point"}
}