{
  "type": "Feature",
  "properties": {
    "addr:full":"1845 Plantside Dr Louisville KY 40299",
    "addr:housenumber":"1845",
    "addr:postcode":"40299",
    "addr:street":"Plantside Dr",
    "iso:country":"US",
    "sg:address":"1845 Plantside Dr",
    "sg:city":"Louisville",
    "sg:classifiers":[
        {
            "category":"Building & Trades",
            "subcategory":"Cleaning & Sanitation",
            "type":"Services"
        }
    ],
    "sg:phone":"+1 502 495 6491",
    "sg:postcode":"40299",
    "sg:province":"KY",
    "sg:tags":[
        "house"
    ],
    "sg:website":"www.mollymaid.com",
    "wof:name":"Molly Maids",
    "wof:placetype":"venue"
},
  "geometry": {"coordinates":[-85.57325,38.217927],"type":"Point"}
}