{
  "type": "Feature",
  "properties": {
    "iso:country":"US",
    "sg:address":"1830 McBrayer Rd",
    "sg:city":"Clearfield",
    "sg:classifiers":[
        {
            "category":"Organizations",
            "subcategory":"Religious Organization",
            "type":"Services"
        }
    ],
    "sg:phone":"+1 606 784 3888",
    "sg:postcode":"40313",
    "sg:province":"KY",
    "sg:tags":[
        "church"
    ],
    "wof:name":"Grace Assembly Of God",
    "wof:placetype":"venue"
},
  "geometry": {"coordinates":[-83.456549,38.152508],"type":"Point"}
}