{
  "type": "Feature",
  "properties": {
    "addr:full":"485 Shady Rest Rd Hodgenville KY 42748",
    "addr:housenumber":"485",
    "addr:postcode":"42748",
    "addr:street":"Shady Rest Rd",
    "iso:country":"US",
    "sg:address":"485 Shady Rest Rd",
    "sg:city":"Hodgenville",
    "sg:classifiers":[
        {
            "category":"Organizations",
            "subcategory":"Religious Organization",
            "type":"Services"
        }
    ],
    "sg:phone":"+1 270 324 3421",
    "sg:postcode":"42748",
    "sg:province":"KY",
    "wof:name":"Gideons International",
    "wof:placetype":"venue"
},
  "geometry": {"coordinates":[-85.773867,37.469744],"type":"Point"}
}