{
  "type": "Feature",
  "properties": {
    "iso:country":"US",
    "sg:address":"309 Steel Dr",
    "sg:city":"Elizabethtown",
    "sg:classifiers":[
        {
            "category":"Retail",
            "subcategory":"Auto Repair",
            "type":"Services"
        }
    ],
    "sg:phone":"+1 270 737 2611",
    "sg:postcode":"42701",
    "sg:province":"KY",
    "sg:tags":[
        "truck"
    ],
    "wof:name":"Orville's Diesel Svc",
    "wof:placetype":"venue"
},
  "geometry": {"coordinates":[-85.839517,37.680988],"type":"Point"}
}