{
  "type": "Feature",
  "properties": {
    "addr:full":"12317 la Grange Rd Louisville Louisville KY 40222",
    "addr:housenumber":"12317",
    "addr:postcode":"40222",
    "addr:street":"La Grange Rd",
    "iso:country":"US",
    "sg:address":"12317 la Grange Rd Louisville",
    "sg:city":"Louisville",
    "sg:classifiers":[
        {
            "category":"Retail",
            "subcategory":"Veterinary Services",
            "type":"Services"
        },
        {
            "category":"Retail",
            "subcategory":"Animal Services",
            "type":"Services"
        }
    ],
    "sg:phone":"+1 502 243 3226",
    "sg:postcode":"40222",
    "sg:province":"KY",
    "sg:tags":[
        "pet",
        "hospital",
        "specialty",
        "clinic",
        "veterinarian",
        "grooming"
    ],
    "sg:website":"http://www.anchorageanimal.com",
    "wof:name":"Anchorage Animal Hospital",
    "wof:placetype":"venue"
},
  "geometry": {"coordinates":[-85.602524,38.26318],"type":"Point"}
}