{
  "type": "Feature",
  "properties": {
    "iso:country":"US",
    "sg:address":"2300 Lexington Rd",
    "sg:city":"Richmond",
    "sg:classifiers":[
        {
            "category":"Organizations",
            "subcategory":"Religious Organization",
            "type":"Services"
        }
    ],
    "sg:phone":"+1 859 623 6868",
    "sg:postcode":"40475",
    "sg:province":"KY",
    "wof:name":"Trinity Mssonary Baptst Church",
    "wof:placetype":"venue"
},
  "geometry": {"coordinates":[-84.326752,37.780989],"type":"Point"}
}