{
  "type": "Feature",
  "properties": {
    "iso:country":"US",
    "sg:address":"287 N Hubbards Ln",
    "sg:city":"Louisville",
    "sg:classifiers":[
        {
            "category":"Restaurant",
            "type":"Food & Drink"
        }
    ],
    "sg:menulink":"http://www.allmenus.com/ky/jefferson-northeast/186886-mcdonalds/menu/",
    "sg:phone":"+1 502 897 0963",
    "sg:postcode":"40207",
    "sg:province":"KY",
    "sg:tags":[
        "burger",
        "american"
    ],
    "wof:name":"McDonald's",
    "wof:placetype":"venue"
},
  "geometry": {"coordinates":[-85.640761,38.25944],"type":"Point"}
}