{
  "type": "Feature",
  "properties": {
    "iso:country":"US",
    "sg:address":"1215 S Hurstbourne Pkwy",
    "sg:city":"Louisville",
    "sg:classifiers":[
        {
            "category":"Retail",
            "subcategory":"Auto Rental",
            "type":"Services"
        }
    ],
    "sg:phone":"+1 502 326 1351",
    "sg:postcode":"40222",
    "sg:province":"KY",
    "sg:tags":[
        "renting",
        "automobile"
    ],
    "wof:name":"Hertz Local Edition",
    "wof:placetype":"venue"
},
  "geometry": {"coordinates":[-85.57759,38.227072],"type":"Point"}
}