{
  "type": "Feature",
  "properties": {
    "addr:full":"123 S 7th St Louisville KY 40202",
    "addr:housenumber":"123",
    "addr:postcode":"40202",
    "addr:street":"S 7Th St",
    "iso:country":"US",
    "sg:address":"123 S 7th St",
    "sg:city":"Louisville",
    "sg:classifiers":[
        {
            "category":"Professional",
            "subcategory":"Lawyer & Legal Services",
            "type":"Services"
        }
    ],
    "sg:phone":"+1 502 585 3979",
    "sg:postcode":"40202",
    "sg:province":"KY",
    "sg:tags":[
        "attorney"
    ],
    "wof:name":"Maple & Assoc",
    "wof:placetype":"venue"
},
  "geometry": {"coordinates":[-85.76149700000001,38.256774],"type":"Point"}
}