{
  "type": "Feature",
  "properties": {
    "iso:country":"US",
    "sg:address":"1006 Cuba Rd",
    "sg:city":"Mayfield",
    "sg:classifiers":[
        {
            "category":"Restaurant",
            "type":"Food & Drink"
        }
    ],
    "sg:menulink":"http://www.allmenus.com/ky/mayfield/186912-mcdonalds/menu/",
    "sg:phone":"+1 270 247 4780",
    "sg:postcode":"42066",
    "sg:province":"KY",
    "sg:tags":[
        "burger",
        "american"
    ],
    "wof:name":"McDonald's",
    "wof:placetype":"venue"
},
  "geometry": {"coordinates":[-88.631905,36.729197],"type":"Point"}
}