{
  "type": "Feature",
  "properties": {
    "iso:country":"US",
    "sg:address":"203 W Kenwood Way",
    "sg:city":"Louisville",
    "sg:classifiers":[
        {
            "category":"Professional",
            "subcategory":"Business Services",
            "type":"Services"
        }
    ],
    "sg:phone":"+1 502 363 5798",
    "sg:postcode":"40214",
    "sg:province":"KY",
    "wof:name":"Interact Design & Develop",
    "wof:placetype":"venue"
},
  "geometry": {"coordinates":[-85.766702,38.178884],"type":"Point"}
}