{
  "type": "Feature",
  "properties": {
    "iso:country":"US",
    "sg:address":"10401 Linn Station Rd",
    "sg:city":"Louisville",
    "sg:classifiers":[
        {
            "category":"Insurance",
            "subcategory":"Insurance Agent",
            "type":"Services"
        }
    ],
    "sg:phone":"+1 502 425 6668",
    "sg:postcode":"40223",
    "sg:province":"KY",
    "wof:name":"Medical Protective Co",
    "wof:placetype":"venue"
},
  "geometry": {"coordinates":[-85.56340299999999,38.224616],"type":"Point"}
}