{
  "type": "Feature",
  "properties": {
    "addr:full":"866 Wilkinson Blvd Frankfort KY 40601",
    "addr:housenumber":"866",
    "addr:postcode":"40601",
    "addr:street":"Wilkinson Blvd",
    "iso:country":"US",
    "sg:address":"866 Wilkinson Blvd",
    "sg:city":"Frankfort",
    "sg:classifiers":[
        {
            "category":"Manufacturing",
            "subcategory":"Printing",
            "type":"Manufacturing & Wholesale Goods"
        }
    ],
    "sg:phone":"+1 502 223 3100",
    "sg:postcode":"40601",
    "sg:province":"KY",
    "sg:tags":[
        "commercial"
    ],
    "wof:name":"Goins Printing Svc",
    "wof:placetype":"venue"
},
  "geometry": {"coordinates":[-84.871923,38.209696],"type":"Point"}
}