{
  "type": "Feature",
  "properties": {
    "iso:country":"US",
    "sg:address":"13124 Eastpoint Park Blvd",
    "sg:city":"Louisville",
    "sg:classifiers":[
        {
            "category":"Education",
            "subcategory":"Special Training",
            "type":"Public Place"
        },
        {
            "category":"Arena",
            "subcategory":"Sports Club",
            "type":"Entertainment"
        }
    ],
    "sg:phone":"+1 502 489 5444",
    "sg:postcode":"40223",
    "sg:province":"KY",
    "sg:tags":[
        "instruction",
        "equipment",
        "self defense",
        "health",
        "martial art"
    ],
    "sg:website":"http://www.corelouisville.com",
    "wof:name":"Core Combat Sports",
    "wof:placetype":"venue"
},
  "geometry": {"coordinates":[-85.514836,38.279898],"type":"Point"}
}