{
  "type": "Feature",
  "properties": {
    "addr:full":"2667 Sand Hill Rd Irvine KY 40336",
    "addr:housenumber":"2667",
    "addr:postcode":"40336",
    "addr:street":"Sand Hill Rd",
    "iso:country":"US",
    "sg:address":"2667 Sand Hill Rd",
    "sg:city":"Irvine",
    "sg:classifiers":[
        {
            "category":"Retail",
            "subcategory":"Auto Repair",
            "type":"Services"
        }
    ],
    "sg:phone":"+1 606 723 3881",
    "sg:postcode":"40336",
    "sg:province":"KY",
    "sg:tags":[
        "repairing",
        "automobile"
    ],
    "wof:name":"Arthur Frank Garage",
    "wof:placetype":"venue"
},
  "geometry": {"coordinates":[-84.024655,37.726757],"type":"Point"}
}