{
  "type": "Feature",
  "properties": {
    "iso:country":"US",
    "sg:address":"2338 Stuart Chapel Rd",
    "sg:city":"Lewisburg",
    "sg:classifiers":[
        {
            "category":"Home & Garden",
            "subcategory":"Carpets & Floor Coverings",
            "type":"Retail Goods"
        }
    ],
    "sg:phone":"+1 270 755 2510",
    "sg:postcode":"42256",
    "sg:province":"KY",
    "wof:name":"Taylor Remnants",
    "wof:placetype":"venue"
},
  "geometry": {"coordinates":[-87.00182100000001,36.891288],"type":"Point"}
}