{
  "type": "Feature",
  "properties": {
    "addr:full":"4410 Alexandria Pike Cold Spring KY 41076",
    "addr:housenumber":"4410",
    "addr:postcode":"41076",
    "addr:street":"Alexandria Pike",
    "iso:country":"US",
    "sg:address":"4410 Alexandria Pike",
    "sg:city":"Cold Spring",
    "sg:classifiers":[
        {
            "category":"Education",
            "subcategory":"School",
            "type":"Public Place"
        }
    ],
    "sg:phone":"+1 859 442 0671",
    "sg:postcode":"41076",
    "sg:province":"KY",
    "sg:tags":[
        "high",
        "middle",
        "elementary"
    ],
    "wof:name":"First Bapt Church of Cold Spring",
    "wof:placetype":"venue"
},
  "geometry": {"coordinates":[-84.434799,39.016899],"type":"Point"}
}