{
  "type": "Feature",
  "properties": {
    "iso:country":"US",
    "sg:address":"1295 Post Oak Rd",
    "sg:city":"Lexington",
    "sg:classifiers":[
        {
            "category":"Building & Trades",
            "subcategory":"Construction",
            "type":"Services"
        }
    ],
    "sg:phone":"+1 859 271 3126",
    "sg:postcode":"40517",
    "sg:province":"KY",
    "sg:tags":[
        "residential"
    ],
    "wof:name":"Earnest Brothers Inc",
    "wof:placetype":"venue"
},
  "geometry": {"coordinates":[-84.46727199999999,37.991334],"type":"Point"}
}