{
  "type": "Feature",
  "properties": {
    "addr:full":"2140 W Horizon Dr Hebron KY 41048",
    "addr:housenumber":"2140",
    "addr:postcode":"41048",
    "addr:street":"W Horizon Dr",
    "iso:country":"US",
    "sg:address":"2140 W Horizon Dr",
    "sg:city":"Hebron",
    "sg:classifiers":[
        {
            "category":"Cinema",
            "subcategory":"Movie Rental",
            "type":"Entertainment"
        },
        {
            "category":"Communications",
            "type":"Services"
        }
    ],
    "sg:phone":"+1 859 586 6434",
    "sg:postcode":"41048",
    "sg:province":"KY",
    "sg:tags":[
        "recording",
        "rehearsal",
        "game",
        "video",
        "studio"
    ],
    "wof:name":"Czarnik Mark",
    "wof:placetype":"venue"
},
  "geometry": {"coordinates":[-84.711304,39.0718],"type":"Point"}
}