{
  "type": "Feature",
  "properties": {
    "iso:country":"US",
    "sg:address":"1657 Dixie Hwy",
    "sg:city":"Fort Wright",
    "sg:classifiers":[
        {
            "category":"Retail",
            "subcategory":"Laundry & Dry Cleaning",
            "type":"Services"
        }
    ],
    "sg:phone":"+1 859 431 9034",
    "sg:postcode":"41011",
    "sg:province":"KY",
    "sg:tags":[
        "cleaners"
    ],
    "wof:name":"Lookout Heights Laundry",
    "wof:placetype":"venue"
},
  "geometry": {"coordinates":[-84.53661099999999,39.063384],"type":"Point"}
}