{
  "type": "Feature",
  "properties": {
    "addr:full":"1102 Paris Rd Mayfield KY 42066",
    "addr:housenumber":"1102",
    "addr:postcode":"42066",
    "addr:street":"Paris Rd",
    "iso:country":"US",
    "sg:address":"1102 Paris Rd",
    "sg:city":"Mayfield",
    "sg:classifiers":[
        {
            "category":"Professional",
            "subcategory":"Management & Consulting",
            "type":"Services"
        }
    ],
    "sg:phone":"+1 270 247 4033",
    "sg:postcode":"42066",
    "sg:province":"KY",
    "sg:tags":[
        "consultant",
        "business"
    ],
    "wof:name":"Cdg Management",
    "wof:placetype":"venue"
},
  "geometry": {"coordinates":[-88.628772,36.72546],"type":"Point"}
}