{
  "type": "Feature",
  "properties": {
    "addr:full":"1200 Falls Trce Louisville KY 40223",
    "addr:housenumber":"1200",
    "addr:postcode":"40223",
    "addr:street":"Falls Trce",
    "iso:country":"US",
    "sg:address":"1200 Falls Trce",
    "sg:city":"Louisville",
    "sg:classifiers":[
        {
            "category":"Building & Trades",
            "subcategory":"Construction",
            "type":"Services"
        }
    ],
    "sg:phone":"+1 502 244 2620",
    "sg:postcode":"40223",
    "sg:province":"KY",
    "sg:tags":[
        "bathroom",
        "remodeling"
    ],
    "wof:name":"Dave Klapheke Co",
    "wof:placetype":"venue"
},
  "geometry": {"coordinates":[-85.57087799999999,38.227698],"type":"Point"}
}