{
  "type": "Feature",
  "properties": {
    "iso:country":"US",
    "sg:address":"301 N Hurstbourne Pkwy",
    "sg:city":"Louisville",
    "sg:classifiers":[
        {
            "category":"Insurance",
            "subcategory":"Insurance Agent",
            "type":"Services"
        }
    ],
    "sg:phone":"+1 502 339 5700",
    "sg:postcode":"40222",
    "sg:province":"KY",
    "sg:website":"www.apcapital.com",
    "wof:name":"American Physicians Assurance",
    "wof:placetype":"venue"
},
  "geometry": {"coordinates":[-85.577755,38.248376],"type":"Point"}
}