{
  "type": "Feature",
  "properties": {
    "addr:full":"4906 Bardstown Rd Louisville KY 40291",
    "addr:housenumber":"4906",
    "addr:postcode":"40291",
    "addr:street":"Bardstown Rd",
    "iso:country":"US",
    "sg:address":"4906 Bardstown Rd",
    "sg:city":"Louisville",
    "sg:classifiers":[
        {
            "category":"Insurance",
            "subcategory":"Insurance Agent",
            "type":"Services"
        }
    ],
    "sg:phone":"+1 502 491 9111",
    "sg:postcode":"40291",
    "sg:province":"KY",
    "wof:name":"Shelter Insurance",
    "wof:placetype":"venue"
},
  "geometry": {"coordinates":[-85.61972299999999,38.177241],"type":"Point"}
}