{
  "type": "Feature",
  "properties": {
    "iso:country":"US",
    "sg:address":"407 Charlestown Ct",
    "sg:city":"Louisville",
    "sg:classifiers":[
        {
            "category":"Real Estate",
            "subcategory":"Real Estate Agent",
            "type":"Services"
        }
    ],
    "sg:phone":"+1 502 244 7966",
    "sg:postcode":"40243",
    "sg:province":"KY",
    "wof:name":"Ledic Management Group Inc",
    "wof:placetype":"venue"
},
  "geometry": {"coordinates":[-85.552325,38.24283],"type":"Point"}
}