{
  "type": "Feature",
  "properties": {
    "addr:full":"1643 Laurel Lake Rd N London KY 40744",
    "addr:housenumber":"1643",
    "addr:postcode":"40744",
    "addr:street":"Laurel Lake Rd N",
    "iso:country":"US",
    "sg:address":"1643 Laurel Lake Rd N",
    "sg:city":"London",
    "sg:classifiers":[
        {
            "category":"Organizations",
            "subcategory":"Religious Organization",
            "type":"Services"
        }
    ],
    "sg:phone":"+1 606 864 5708",
    "sg:postcode":"40744",
    "sg:province":"KY",
    "wof:name":"Level Green Church of Christ",
    "wof:placetype":"venue"
},
  "geometry": {"coordinates":[-84.13661399999999,37.030754],"type":"Point"}
}