{
  "type": "Feature",
  "properties": {
    "addr:full":"1542 Frederica St Owensboro KY 42301",
    "addr:housenumber":"1542",
    "addr:postcode":"42301",
    "addr:street":"Frederica St",
    "iso:country":"US",
    "sg:address":"1542 Frederica St",
    "sg:city":"Owensboro",
    "sg:classifiers":[
        {
            "category":"Organizations",
            "subcategory":"Religious Organization",
            "type":"Services"
        }
    ],
    "sg:phone":"+1 270 684 4474",
    "sg:postcode":"42301",
    "sg:province":"KY",
    "sg:tags":[
        "church"
    ],
    "wof:name":"One Thousand Missionary",
    "wof:placetype":"venue"
},
  "geometry": {"coordinates":[-87.11237300000001,37.761301],"type":"Point"}
}