{
  "type": "Feature",
  "properties": {
    "iso:country":"US",
    "sg:address":"822 Madison Ave",
    "sg:city":"Covington",
    "sg:classifiers":[
        {
            "category":"Shopping",
            "subcategory":"Department Store",
            "type":"Retail Goods"
        }
    ],
    "sg:phone":"+1 859 291 2171",
    "sg:postcode":"41011",
    "sg:province":"KY",
    "wof:name":"Envys",
    "wof:placetype":"venue"
},
  "geometry": {"coordinates":[-84.509654,39.08204],"type":"Point"}
}