{
  "type": "Feature",
  "properties": {
    "iso:country":"US",
    "sg:address":"2046 Westborough Dr",
    "sg:city":"Hebron",
    "sg:classifiers":[
        {
            "category":"Professional",
            "subcategory":"Business Services",
            "type":"Services"
        }
    ],
    "sg:phone":"+1 859 689 9252",
    "sg:postcode":"41048",
    "sg:province":"KY",
    "wof:name":"Relocations Plus LLC",
    "wof:placetype":"venue"
},
  "geometry": {"coordinates":[-84.732888,39.11088],"type":"Point"}
}