{
  "type": "Feature",
  "properties": {
    "iso:country":"US",
    "sg:address":"600 Bergman St",
    "sg:city":"Louisville",
    "sg:classifiers":[
        {
            "category":"Manufacturing",
            "subcategory":"Chemicals & Compounds",
            "type":"Manufacturing & Wholesale Goods"
        }
    ],
    "sg:phone":"+1 502 637 4553",
    "sg:postcode":"40203",
    "sg:province":"KY",
    "sg:tags":[
        "inorganic",
        "industrial"
    ],
    "sg:website":"www.forthtech.com",
    "wof:name":"Forth Technologies Inc",
    "wof:placetype":"venue"
},
  "geometry": {"coordinates":[-85.744597,38.229186],"type":"Point"}
}