{
  "type": "Feature",
  "properties": {
    "iso:country":"US",
    "sg:address":"1783 Bypass Rd",
    "sg:city":"Lawrenceburg",
    "sg:classifiers":[
        {
            "category":"Wholesale",
            "subcategory":"Farm Supplies",
            "type":"Manufacturing & Wholesale Goods"
        }
    ],
    "sg:phone":"+1 502 839 8355",
    "sg:postcode":"40391",
    "sg:province":"KY",
    "sg:tags":[
        "livestock"
    ],
    "wof:name":"Sargents Livestock",
    "wof:placetype":"venue"
},
  "geometry": {"coordinates":[-84.210427,37.989799],"type":"Point"}
}