{
  "type": "Feature",
  "properties": {
    "iso:country":"US",
    "sg:address":"630 US Hwy 27",
    "sg:city":"Cynthiana",
    "sg:classifiers":[
        {
            "category":"Restaurant",
            "type":"Food & Drink"
        }
    ],
    "sg:phone":"+1 859 234 2517",
    "sg:postcode":"41031",
    "sg:province":"KY",
    "sg:tags":[
        "pizza"
    ],
    "wof:name":"Leono's Restaurant",
    "wof:placetype":"venue"
},
  "geometry": {"coordinates":[-84.29616900000001,38.39584],"type":"Point"}
}