{
  "type": "Feature",
  "properties": {
    "iso:country":"US",
    "sg:address":"13060 Middletown Ind Blvd",
    "sg:city":"Louisville",
    "sg:classifiers":[
        {
            "category":"Banks & Credit Unions",
            "subcategory":"Bank",
            "type":"Services"
        }
    ],
    "sg:phone":"+1 502 515 1234",
    "sg:postcode":"40223",
    "sg:province":"KY",
    "sg:tags":[
        "loan",
        "real estate"
    ],
    "wof:name":"Capitol Mortgage",
    "wof:placetype":"venue"
},
  "geometry": {"coordinates":[-85.50591799999999,38.252206],"type":"Point"}
}