{
  "type": "Feature",
  "properties": {
    "iso:country":"US",
    "sg:address":"716 E Broadway",
    "sg:city":"Louisville",
    "sg:classifiers":[
        {
            "category":"Banks & Credit Unions",
            "subcategory":"Financial Services",
            "type":"Services"
        }
    ],
    "sg:phone":"+1 502 587 6762",
    "sg:postcode":"40202",
    "sg:province":"KY",
    "sg:tags":[
        "payday",
        "loan"
    ],
    "wof:name":"Cash Tyme",
    "wof:placetype":"venue"
},
  "geometry": {"coordinates":[-85.74117200000001,38.244822],"type":"Point"}
}