{
  "type": "Feature",
  "properties": {
    "addr:full":"1415 N 3rd St Bardstown KY 40004",
    "addr:housenumber":"1415",
    "addr:postcode":"40004",
    "addr:street":"N 3Rd St",
    "iso:country":"US",
    "sg:address":"1415 N 3rd St",
    "sg:city":"Bardstown",
    "sg:classifiers":[
        {
            "category":"Wholesale",
            "subcategory":"Groceries",
            "type":"Manufacturing & Wholesale Goods"
        }
    ],
    "sg:phone":"+1 502 348 1196",
    "sg:postcode":"40004",
    "sg:province":"KY",
    "sg:tags":[
        "food",
        "product"
    ],
    "wof:name":"Frito-Lay Ind",
    "wof:placetype":"venue"
},
  "geometry": {"coordinates":[-85.460266,37.83878],"type":"Point"}
}