{
  "type": "Feature",
  "properties": {
    "addr:full":"6210 Preston Hwy Louisville KY 40219",
    "addr:housenumber":"6210",
    "addr:postcode":"40219",
    "addr:street":"Preston Hwy",
    "iso:country":"US",
    "sg:address":"6210 Preston Hwy",
    "sg:city":"Louisville",
    "sg:classifiers":[
        {
            "category":"Retail",
            "subcategory":"Auto Repair",
            "type":"Services"
        }
    ],
    "sg:phone":"+1 502 810 6500",
    "sg:postcode":"40219",
    "sg:province":"KY",
    "sg:tags":[
        "automotive",
        "consultant"
    ],
    "wof:name":"Freedom Auto Source",
    "wof:placetype":"venue"
},
  "geometry": {"coordinates":[-85.69844500000001,38.159354],"type":"Point"}
}