{
  "type": "Feature",
  "properties": {
    "addr:full":"1838 Ballardsville Rd Eminence KY 40019",
    "addr:housenumber":"1838",
    "addr:postcode":"40019",
    "addr:street":"Ballardsville Rd",
    "iso:country":"US",
    "sg:address":"1838 Ballardsville Rd",
    "sg:city":"Eminence",
    "sg:classifiers":[
        {
            "category":"Freight",
            "type":"Transportation"
        }
    ],
    "sg:phone":"+1 502 845 7410",
    "sg:postcode":"40019",
    "sg:province":"KY",
    "sg:tags":[
        "special"
    ],
    "wof:name":"Devarys U-Store-It",
    "wof:placetype":"venue"
},
  "geometry": {"coordinates":[-85.199839,38.366555],"type":"Point"}
}