{
  "type": "Feature",
  "properties": {
    "addr:full":"7660 Lagrange Rd Smithfield KY 40068",
    "addr:housenumber":"7660",
    "addr:postcode":"40068",
    "addr:street":"Lagrange Rd",
    "iso:country":"US",
    "sg:address":"7660 Lagrange Rd",
    "sg:city":"Smithfield",
    "sg:classifiers":[
        {
            "category":"Wholesale",
            "subcategory":"Construction Materials",
            "type":"Manufacturing & Wholesale Goods"
        }
    ],
    "sg:phone":"+1 502 473 1223",
    "sg:postcode":"40068",
    "sg:province":"KY",
    "sg:tags":[
        "fence"
    ],
    "sg:website":"www.nationwidesalesonline.com",
    "wof:name":"Nationwide Fence Co",
    "wof:placetype":"venue"
},
  "geometry": {"coordinates":[-85.28230499999999,38.451769],"type":"Point"}
}