{
  "type": "Feature",
  "properties": {
    "addr:full":"1040 Hansel Ave Florence KY 41042",
    "addr:housenumber":"1040",
    "addr:postcode":"41042",
    "addr:street":"Hansel Ave",
    "iso:country":"US",
    "sg:address":"1040 Hansel Ave",
    "sg:city":"Florence",
    "sg:classifiers":[
        {
            "category":"Utilities",
            "subcategory":"Mobile Phone",
            "type":"Services"
        },
        {
            "category":"Shopping",
            "subcategory":"Mobile Phones",
            "type":"Retail Goods"
        },
        {
            "category":"Utilities",
            "subcategory":"Telephone",
            "type":"Services"
        },
        {
            "category":"Professional",
            "subcategory":"Computer Services",
            "type":"Services"
        }
    ],
    "sg:phone":"+1 859 282 1907",
    "sg:postcode":"41042",
    "sg:province":"KY",
    "sg:tags":[
        "telecommunication",
        "supply",
        "communication",
        "system",
        "wireless",
        "equipment",
        "cellular"
    ],
    "sg:website":"http://clickserve.dartsearch.net/link/click?lid=43000000308049899",
    "wof:name":"T-Mobile",
    "wof:placetype":"venue"
},
  "geometry": {"coordinates":[-84.631084,39.016172],"type":"Point"}
}