{
  "type": "Feature",
  "properties": {
    "addr:full":"2017 29th St Ashland KY 41101",
    "addr:housenumber":"2017",
    "addr:postcode":"41101",
    "addr:street":"29Th St",
    "iso:country":"US",
    "sg:address":"2017 29th St",
    "sg:city":"Ashland",
    "sg:classifiers":[
        {
            "category":"Insurance",
            "subcategory":"Insurance Agent",
            "type":"Services"
        }
    ],
    "sg:phone":"+1 606 324 1295",
    "sg:postcode":"41101",
    "sg:province":"KY",
    "wof:name":"Harold D Miller Insurance",
    "wof:placetype":"venue"
},
  "geometry": {"coordinates":[-82.64194999999999,38.460267],"type":"Point"}
}