{
  "type": "Feature",
  "properties": {
    "iso:country":"US",
    "sg:address":"6416 Black Oak Ln",
    "sg:city":"Louisville",
    "sg:classifiers":[
        {
            "category":"Organizations",
            "subcategory":"Membership Organization",
            "type":"Services"
        }
    ],
    "sg:phone":"+1 502 448 5757",
    "sg:postcode":"40216",
    "sg:province":"KY",
    "sg:tags":[
        "softball"
    ],
    "wof:name":"Louisville Stunners 12 & Under",
    "wof:placetype":"venue"
},
  "geometry": {"coordinates":[-85.842738,38.159997],"type":"Point"}
}