{
  "type": "Feature",
  "properties": {
    "addr:full":"7633 Dixie Hwy Florence KY 41042",
    "addr:housenumber":"7633",
    "addr:postcode":"41042",
    "addr:street":"Dixie Hwy",
    "iso:country":"US",
    "sg:address":"7633 Dixie Hwy",
    "sg:city":"Florence",
    "sg:classifiers":[
        {
            "category":"Professional",
            "type":"Services"
        },
        {
            "category":"Restaurant",
            "type":"Food & Drink"
        }
    ],
    "sg:phone":"+1 859 525 0771",
    "sg:postcode":"41042",
    "sg:province":"KY",
    "sg:tags":[
        "barbeque",
        "southern",
        "caterer"
    ],
    "wof:name":"Eddie's Southern Style Bar-B-Q & Caterg",
    "wof:placetype":"venue"
},
  "geometry": {"coordinates":[-84.623497,38.991402],"type":"Point"}
}