{
  "type": "Feature",
  "properties": {
    "addr:full":"300 N Mayo Trl Pikeville KY 41501",
    "addr:housenumber":"300",
    "addr:postcode":"41501",
    "addr:street":"N Mayo Trl",
    "iso:country":"US",
    "sg:address":"300 N Mayo Trl",
    "sg:city":"Pikeville",
    "sg:classifiers":[
        {
            "category":"Health Services",
            "subcategory":"Doctor",
            "type":"Services"
        }
    ],
    "sg:phone":"+1 606 437 1461",
    "sg:postcode":"41501",
    "sg:province":"KY",
    "sg:tags":[
        "dentist"
    ],
    "wof:name":"Al Pelphrey DDS",
    "wof:placetype":"venue"
},
  "geometry": {"coordinates":[-82.54289799999999,37.486402],"type":"Point"}
}