{
  "type": "Feature",
  "properties": {
    "iso:country":"US",
    "sg:address":"108 S Main St",
    "sg:city":"Madisonville",
    "sg:classifiers":[
        {
            "category":"Professional",
            "subcategory":"Accounting & Tax Preparation",
            "type":"Services"
        }
    ],
    "sg:phone":"+1 270 825 4578",
    "sg:postcode":"42431",
    "sg:province":"KY",
    "sg:tags":[
        "accountant"
    ],
    "wof:name":"York Neel & Co",
    "wof:placetype":"venue"
},
  "geometry": {"coordinates":[-87.49900700000001,37.326751],"type":"Point"}
}