{
  "type": "Feature",
  "properties": {
    "iso:country":"US",
    "sg:address":"504 Main St",
    "sg:city":"Greenup",
    "sg:classifiers":[
        {
            "category":"Social Services",
            "type":"Services"
        }
    ],
    "sg:phone":"+1 606 473 6244",
    "sg:postcode":"41144",
    "sg:province":"KY",
    "sg:tags":[
        "organization",
        "welfare"
    ],
    "wof:name":"Greenup County Senior Citizens",
    "wof:placetype":"venue"
},
  "geometry": {"coordinates":[-82.83492699999999,38.57654],"type":"Point"}
}