{
  "type": "Feature",
  "properties": {
    "iso:country":"US",
    "sg:address":"165 Douglas St",
    "sg:city":"Brownsville",
    "sg:classifiers":[
        {
            "category":"Professional",
            "subcategory":"Computer Services",
            "type":"Services"
        }
    ],
    "sg:phone":"+1 270 286 9553",
    "sg:postcode":"42240",
    "sg:province":"KY",
    "sg:tags":[
        "related"
    ],
    "wof:name":"Twin Lakes Computers",
    "wof:placetype":"venue"
},
  "geometry": {"coordinates":[-87.480751,36.870818],"type":"Point"}
}