{
  "type": "Feature",
  "properties": {
    "iso:country":"US",
    "sg:address":"1881 Stockton Rd",
    "sg:city":"Frankfort",
    "sg:phone":"+1 502 227 2191",
    "sg:postcode":"40601",
    "sg:province":"KY",
    "sg:tags":[
        "farm",
        "field",
        "crop"
    ],
    "wof:name":"Smith Buan",
    "wof:placetype":"venue"
},
  "geometry": {"coordinates":[-84.984228,38.213799],"type":"Point"}
}