{
  "type": "Feature",
  "properties": {
    "iso:country":"US",
    "sg:address":"608 Baxter Ave",
    "sg:city":"Louisville",
    "sg:classifiers":[
        {
            "category":"Personal",
            "subcategory":"Beauty Salon",
            "type":"Services"
        }
    ],
    "sg:phone":"+1 502 582 9090",
    "sg:postcode":"40204",
    "sg:province":"KY",
    "wof:name":"Hair Gallery",
    "wof:placetype":"venue"
},
  "geometry": {"coordinates":[-85.72856299999999,38.245677],"type":"Point"}
}