{
  "type": "Feature",
  "properties": {
    "iso:country":"US",
    "sg:address":"3170 Mapleleaf Dr",
    "sg:city":"Lexington",
    "sg:classifiers":[
        {
            "category":"Autos & Motor Vehicles",
            "subcategory":"Automobile Sales",
            "type":"Retail Goods"
        }
    ],
    "sg:phone":"+1 859 263 3198",
    "sg:postcode":"40509",
    "sg:province":"KY",
    "sg:tags":[
        "car",
        "dealer"
    ],
    "wof:name":"Tsusho America Inc Toyota",
    "wof:placetype":"venue"
},
  "geometry": {"coordinates":[-84.423689,38.004771],"type":"Point"}
}