{
  "type": "Feature",
  "properties": {
    "addr:full":"41 Ferry St Milton KY 40045",
    "addr:housenumber":"41",
    "addr:postcode":"40045",
    "addr:street":"Ferry St",
    "iso:country":"US",
    "sg:address":"41 Ferry St",
    "sg:city":"Milton",
    "sg:classifiers":[
        {
            "category":"Banks & Credit Unions",
            "subcategory":"Bank",
            "type":"Services"
        }
    ],
    "sg:phone":"+1 502 268 3587",
    "sg:postcode":"40045",
    "sg:province":"KY",
    "wof:name":"FDIC At Farmers Bank-Milton",
    "wof:placetype":"venue"
},
  "geometry": {"coordinates":[-85.369147,38.723853],"type":"Point"}
}