{
  "type": "Feature",
  "properties": {
    "iso:country":"US",
    "sg:address":"3408 Bardstown Rd",
    "sg:city":"Louisville",
    "sg:classifiers":[
        {
            "category":"Cinema",
            "subcategory":"Movie Theater",
            "type":"Entertainment"
        }
    ],
    "sg:phone":"+1 502 499 6656",
    "sg:postcode":"40218",
    "sg:province":"KY",
    "wof:name":"Showcase Cinemas Louisville",
    "wof:placetype":"venue"
},
  "geometry": {"coordinates":[-85.66532100000001,38.203871],"type":"Point"}
}