{
  "type": "Feature",
  "properties": {
    "addr:full":"201 Breckenridge Ln Louisville KY 40207",
    "addr:housenumber":"201",
    "addr:postcode":"40207",
    "addr:street":"Breckenridge Ln",
    "iso:country":"US",
    "sg:address":"201 Breckenridge Ln",
    "sg:city":"Louisville",
    "sg:classifiers":[
        {
            "category":"Shopping",
            "subcategory":"Used Merchandise",
            "type":"Retail Goods"
        },
        {
            "category":"Shopping",
            "type":"Retail Goods"
        }
    ],
    "sg:phone":"+1 502 897 7744",
    "sg:postcode":"40207",
    "sg:province":"KY",
    "sg:tags":[
        "wedding",
        "supply"
    ],
    "wof:name":"A Class Act Consignments",
    "wof:placetype":"venue"
},
  "geometry": {"coordinates":[-85.65271199999999,38.24959],"type":"Point"}
}