{
  "type": "Feature",
  "properties": {
    "addr:full":"1661 Gayle Dr Lexington KY 40505",
    "addr:housenumber":"1661",
    "addr:postcode":"40505",
    "addr:street":"Gayle Dr",
    "iso:country":"US",
    "sg:address":"1661 Gayle Dr",
    "sg:city":"Lexington",
    "sg:classifiers":[
        {
            "category":"Organizations",
            "subcategory":"Membership Organization",
            "type":"Services"
        }
    ],
    "sg:phone":"+1 859 299 2277",
    "sg:postcode":"40505",
    "sg:province":"KY",
    "wof:name":"Mid American Boating Assn",
    "wof:placetype":"venue"
},
  "geometry": {"coordinates":[-84.441114,38.04904],"type":"Point"}
}