{
  "type": "Feature",
  "properties": {
    "iso:country":"US",
    "sg:address":"105 N Ralphs Rd",
    "sg:city":"Garrett",
    "sg:classifiers":[
        {
            "category":"Autos & Motor Vehicles",
            "subcategory":"Auto Supplies",
            "type":"Retail Goods"
        }
    ],
    "sg:phone":"+1 606 358 4286",
    "sg:postcode":"41630",
    "sg:province":"KY",
    "sg:tags":[
        "tire"
    ],
    "wof:name":"Economy Tire",
    "wof:placetype":"venue"
},
  "geometry": {"coordinates":[-82.83500100000001,37.475435],"type":"Point"}
}