{
  "type": "Feature",
  "properties": {
    "addr:full":"101 Malabu Dr Lexington KY 40503",
    "addr:housenumber":"101",
    "addr:postcode":"40503",
    "addr:street":"Malabu Dr",
    "iso:country":"US",
    "sg:address":"101 Malabu Dr",
    "sg:city":"Lexington",
    "sg:classifiers":[
        {
            "category":"Health Services",
            "subcategory":"Chiropractor",
            "type":"Services"
        }
    ],
    "sg:phone":"+1 859 277 7521",
    "sg:postcode":"40503",
    "sg:province":"KY",
    "sg:website":"www.kernchiro.com",
    "wof:name":"KERN Chiropractic",
    "wof:placetype":"venue"
},
  "geometry": {"coordinates":[-84.517377,38.00253],"type":"Point"}
}