{
  "type": "Feature",
  "properties": {
    "iso:country":"US",
    "sg:address":"170 Jackie Hollow Rd",
    "sg:city":"Liberty",
    "sg:classifiers":[
        {
            "category":"Wholesale",
            "subcategory":"Petroleum",
            "type":"Manufacturing & Wholesale Goods"
        }
    ],
    "sg:phone":"+1 606 787 7421",
    "sg:postcode":"42539",
    "sg:province":"KY",
    "sg:tags":[
        "pipe",
        "line",
        "company"
    ],
    "wof:name":"Columbia Gulf Transmission Co",
    "wof:placetype":"venue"
},
  "geometry": {"coordinates":[-85.05851199999999,37.313361],"type":"Point"}
}