{
  "type": "Feature",
  "properties": {
    "addr:full":"4714 E Pages Ln Valley Station KY 40272",
    "addr:housenumber":"4714",
    "addr:postcode":"40272",
    "addr:street":"E Pages Ln Valley",
    "iso:country":"US",
    "sg:address":"4714 E Pages Ln",
    "sg:city":"Valley Station",
    "sg:classifiers":[
        {
            "category":"Organizations",
            "subcategory":"Religious Organization",
            "type":"Services"
        }
    ],
    "sg:phone":"+1 502 935 4533",
    "sg:postcode":"40272",
    "sg:province":"KY",
    "sg:tags":[
        "church"
    ],
    "wof:name":"Hillsdale Baptist Church",
    "wof:placetype":"venue"
},
  "geometry": {"coordinates":[-85.84370699999999,38.126121],"type":"Point"}
}