{
  "type": "Feature",
  "properties": {
    "addr:full":"105 W White Oak St Leitchfield KY 42754",
    "addr:housenumber":"105",
    "addr:postcode":"42754",
    "addr:street":"W White Oak St",
    "iso:country":"US",
    "sg:address":"105 W White Oak St",
    "sg:city":"Leitchfield",
    "sg:classifiers":[
        {
            "category":"Personal",
            "subcategory":"Beauty Salon",
            "type":"Services"
        }
    ],
    "sg:phone":"+1 270 259 5064",
    "sg:postcode":"42754",
    "sg:province":"KY",
    "wof:name":"Hair Studio",
    "wof:placetype":"venue"
},
  "geometry": {"coordinates":[-86.29499199999999,37.477475],"type":"Point"}
}