{
  "type": "Feature",
  "properties": {
    "iso:country":"US",
    "sg:address":"124 W Todd St",
    "sg:city":"Frankfort",
    "sg:classifiers":[
        {
            "category":"Professional",
            "subcategory":"Lawyer & Legal Services",
            "type":"Services"
        }
    ],
    "sg:phone":"+1 502 227 7270",
    "sg:postcode":"40601",
    "sg:province":"KY",
    "sg:tags":[
        "attorney"
    ],
    "wof:name":"John N Hughes",
    "wof:placetype":"venue"
},
  "geometry": {"coordinates":[-84.87636500000001,38.189809],"type":"Point"}
}