{
  "type": "Feature",
  "properties": {
    "iso:country":"US",
    "sg:address":"285 W Water St",
    "sg:city":"Flemingsburg",
    "sg:classifiers":[
        {
            "category":"Autos & Motor Vehicles",
            "subcategory":"Automobile Sales",
            "type":"Retail Goods"
        }
    ],
    "sg:phone":"+1 606 849 2311",
    "sg:postcode":"41041",
    "sg:province":"KY",
    "sg:tags":[
        "car",
        "dealer"
    ],
    "wof:name":"Bobby's Auto Sales",
    "wof:placetype":"venue"
},
  "geometry": {"coordinates":[-83.737943,38.426196],"type":"Point"}
}