{
  "type": "Feature",
  "properties": {
    "addr:full":"2631 Scottsville Rd Bowling Green KY 42104",
    "addr:housenumber":"2631",
    "addr:postcode":"42104",
    "addr:street":"Scottsville Rd",
    "iso:country":"US",
    "sg:address":"2631 Scottsville Rd",
    "sg:city":"Bowling Green",
    "sg:classifiers":[
        {
            "category":"Restaurant",
            "type":"Food & Drink"
        }
    ],
    "sg:menulink":"http://www.allmenus.com/ky/bowling-green/79715-pizza-hut/menu/",
    "sg:phone":"+1 270 782 9056",
    "sg:postcode":"42104",
    "sg:province":"KY",
    "sg:tags":[
        "american",
        "pizza"
    ],
    "wof:name":"Pizza Hut",
    "wof:placetype":"venue"
},
  "geometry": {"coordinates":[-86.425044,36.949984],"type":"Point"}
}