{
  "type": "Feature",
  "properties": {
    "iso:country":"US",
    "sg:address":"621 Park Ave",
    "sg:city":"Ironton",
    "sg:classifiers":[
        {
            "category":"Restaurant",
            "type":"Food & Drink"
        }
    ],
    "sg:phone":"+1 740 532 4222",
    "sg:postcode":"45638",
    "sg:province":"OH",
    "sg:tags":[
        "eating",
        "pizza"
    ],
    "wof:name":"Domino's Pizza",
    "wof:placetype":"venue"
},
  "geometry": {"coordinates":[-82.680987,38.536727],"type":"Point"}
}