{
  "type": "Feature",
  "properties": {
    "iso:country":"US",
    "sg:address":"279 Burke Rd",
    "sg:city":"Lexington",
    "sg:classifiers":[
        {
            "category":"Building & Trades",
            "subcategory":"Construction",
            "type":"Services"
        }
    ],
    "sg:phone":"+1 859 559 6409",
    "sg:postcode":"40511",
    "sg:province":"KY",
    "sg:tags":[
        "system",
        "specialty",
        "heating",
        "contractor",
        "air conditioning"
    ],
    "sg:website":"http://www.advantageairlex.com",
    "wof:name":"Advantage Air Mechanical",
    "wof:placetype":"venue"
},
  "geometry": {"coordinates":[-84.521091,38.069547],"type":"Point"}
}