{
  "type": "Feature",
  "properties": {
    "addr:full":"371 Center St New Haven KY 40051",
    "addr:housenumber":"371",
    "addr:postcode":"40051",
    "addr:street":"Center St",
    "iso:country":"US",
    "sg:address":"371 Center St",
    "sg:city":"New Haven",
    "sg:classifiers":[
        {
            "category":"Shopping",
            "subcategory":"Department Store",
            "type":"Retail Goods"
        }
    ],
    "sg:phone":"+1 502 549 9828",
    "sg:postcode":"40051",
    "sg:province":"KY",
    "sg:tags":[
        "shop"
    ],
    "wof:name":"Dollar General",
    "wof:placetype":"venue"
},
  "geometry": {"coordinates":[-85.579622,37.655061],"type":"Point"}
}