{
  "type": "Feature",
  "properties": {
    "iso:country":"US",
    "sg:address":"294 Peterson Ave",
    "sg:city":"Auburn",
    "sg:classifiers":[
        {
            "category":"Building & Trades",
            "subcategory":"Landscaping Services",
            "type":"Services"
        }
    ],
    "sg:phone":"+1 270 542 6469",
    "sg:postcode":"42206",
    "sg:province":"KY",
    "sg:tags":[
        "lawn",
        "maintenance"
    ],
    "wof:name":"Covington Lawn Care",
    "wof:placetype":"venue"
},
  "geometry": {"coordinates":[-86.72572700000001,36.861021],"type":"Point"}
}