{
  "type": "Feature",
  "properties": {
    "iso:country":"US",
    "sg:address":"4607 Bellevue Ave",
    "sg:city":"Louisville",
    "sg:classifiers":[
        {
            "category":"Professional",
            "subcategory":"Computer Services",
            "type":"Services"
        }
    ],
    "sg:phone":"+1 502 368 7422",
    "sg:postcode":"40215",
    "sg:province":"KY",
    "wof:name":"Russell W Crenshaw",
    "wof:placetype":"venue"
},
  "geometry": {"coordinates":[-85.77451600000001,38.18272],"type":"Point"}
}