{
  "type": "Feature",
  "properties": {
    "iso:country":"US",
    "sg:address":"768 Winchester Rd",
    "sg:city":"Lexington",
    "sg:classifiers":[
        {
            "category":"Food & Beverages",
            "subcategory":"Groceries & Convenience Stores",
            "type":"Retail Goods"
        }
    ],
    "sg:phone":"+1 859 254 5302",
    "sg:postcode":"40505",
    "sg:province":"KY",
    "wof:name":"Clarks Pump N Shop Inc",
    "wof:placetype":"venue"
},
  "geometry": {"coordinates":[-84.475498,38.041274],"type":"Point"}
}