{
  "type": "Feature",
  "properties": {
    "addr:full":"3620 Walden Dr Lexington KY 40517",
    "addr:housenumber":"3620",
    "addr:postcode":"40517",
    "addr:street":"Walden Dr",
    "iso:country":"US",
    "sg:address":"3620 Walden Dr",
    "sg:city":"Lexington",
    "sg:classifiers":[
        {
            "category":"Professional",
            "subcategory":"Management & Consulting",
            "type":"Services"
        }
    ],
    "sg:phone":"+1 859 272 8527",
    "sg:postcode":"40517",
    "sg:province":"KY",
    "sg:tags":[
        "fuel"
    ],
    "wof:name":"Midwest Management",
    "wof:placetype":"venue"
},
  "geometry": {"coordinates":[-84.50026099999999,37.979148],"type":"Point"}
}