{
  "type": "Feature",
  "properties": {
    "addr:full":"3023 Wickland Rd Louisville KY 40205",
    "addr:housenumber":"3023",
    "addr:postcode":"40205",
    "addr:street":"Wickland Rd",
    "iso:country":"US",
    "sg:address":"3023 Wickland Rd",
    "sg:city":"Louisville",
    "sg:classifiers":[
        {
            "category":"Health Services",
            "subcategory":"Doctor",
            "type":"Services"
        }
    ],
    "sg:phone":"+1 502 456 2123",
    "sg:postcode":"40205",
    "sg:province":"KY",
    "sg:tags":[
        "medical"
    ],
    "wof:name":"Skolnick Judah Dr",
    "wof:placetype":"venue"
},
  "geometry": {"coordinates":[-85.687839,38.207612],"type":"Point"}
}