{
  "type": "Feature",
  "properties": {
    "addr:full":"9330 Blandville Rd West Paducah KY 42086",
    "addr:postcode":"9330;42086",
    "addr:street":"Blandville Rd",
    "iso:country":"US",
    "sg:address":"9330 Blandville Rd",
    "sg:city":"West Paducah",
    "sg:classifiers":[
        {
            "category":"Retail",
            "subcategory":"Portrait Studio",
            "type":"Services"
        }
    ],
    "sg:phone":"+1 270 534 8286",
    "sg:postcode":"42086",
    "sg:province":"KY",
    "sg:tags":[
        "photo"
    ],
    "wof:name":"Signature Prof Phtgraphy By Je",
    "wof:placetype":"venue"
},
  "geometry": {"coordinates":[-88.768789,37.024955],"type":"Point"}
}