{
  "type": "Feature",
  "properties": {
    "addr:full":"10977 Lafayette Rd Herndon KY 42236",
    "addr:housenumber":"10977",
    "addr:postcode":"42236",
    "addr:street":"Rd",
    "iso:country":"US",
    "sg:address":"10977 Lafayette Rd",
    "sg:city":"Herndon",
    "sg:classifiers":[
        {
            "category":"Shopping",
            "subcategory":"Bicycles & Sporting Goods",
            "type":"Retail Goods"
        }
    ],
    "sg:phone":"+1 270 839 1955",
    "sg:postcode":"42236",
    "sg:province":"KY",
    "wof:name":"C & M Enterprises",
    "wof:placetype":"venue"
},
  "geometry": {"coordinates":[-87.568732,36.731398],"type":"Point"}
}