{
  "type": "Feature",
  "properties": {
    "addr:full":"170 W New Circle Rd Lexington KY 40505",
    "addr:housenumber":"170",
    "addr:postcode":"40505",
    "addr:street":"W New Circle Rd",
    "iso:country":"US",
    "sg:address":"170 W New Circle Rd",
    "sg:city":"Lexington",
    "sg:classifiers":[
        {
            "category":"Building & Trades",
            "subcategory":"Construction",
            "type":"Services"
        }
    ],
    "sg:phone":"+1 859 367 7516",
    "sg:postcode":"40505",
    "sg:province":"KY",
    "sg:tags":[
        "general",
        "contractor"
    ],
    "wof:name":"Hranicky Construction",
    "wof:placetype":"venue"
},
  "geometry": {"coordinates":[-84.472176,38.066967],"type":"Point"}
}