{
  "type": "Feature",
  "properties": {
    "iso:country":"US",
    "sg:address":"5611 Preston Hwy",
    "sg:city":"Louisville",
    "sg:classifiers":[
        {
            "category":"Shopping",
            "subcategory":"Optical Goods",
            "type":"Retail Goods"
        }
    ],
    "sg:phone":"+1 502 969 6222",
    "sg:postcode":"40219",
    "sg:province":"KY",
    "wof:name":"SVS Vision",
    "wof:placetype":"venue"
},
  "geometry": {"coordinates":[-85.70417,38.166613],"type":"Point"}
}