{
  "type": "Feature",
  "properties": {
    "iso:country":"US",
    "sg:address":"105 E Public Sq",
    "sg:city":"Scottsville",
    "sg:classifiers":[
        {
            "category":"Banks & Credit Unions",
            "subcategory":"Investment Brokerage",
            "type":"Services"
        }
    ],
    "sg:phone":"+1 270 237 4558",
    "sg:postcode":"42141",
    "sg:province":"KY",
    "sg:tags":[
        "advisory",
        "financial"
    ],
    "wof:name":"Southern Financial Life Ins Co",
    "wof:placetype":"venue"
},
  "geometry": {"coordinates":[-85.91192599999999,36.995876],"type":"Point"}
}