{
  "type": "Feature",
  "properties": {
    "addr:full":"4500 Bowling Blvd Louisville KY 40207",
    "addr:housenumber":"4500",
    "addr:postcode":"40207",
    "addr:street":"Bowling Blvd",
    "iso:country":"US",
    "sg:address":"4500 Bowling Blvd",
    "sg:city":"Louisville",
    "sg:classifiers":[
        {
            "category":"Personal",
            "subcategory":"Nail Salon",
            "type":"Services"
        }
    ],
    "sg:phone":"+1 502 891 4474",
    "sg:postcode":"40207",
    "sg:province":"KY",
    "wof:name":"Beauty First Store & Salon",
    "wof:placetype":"venue"
},
  "geometry": {"coordinates":[-85.63131,38.240528],"type":"Point"}
}