{
  "type": "Feature",
  "properties": {
    "addr:full":"1401 Spring Bank Dr Owensboro KY 42303",
    "addr:housenumber":"1401",
    "addr:postcode":"42303",
    "addr:street":"Spring Bank Dr",
    "iso:country":"US",
    "sg:address":"1401 Spring Bank Dr",
    "sg:city":"Owensboro",
    "sg:classifiers":[
        {
            "category":"Insurance",
            "subcategory":"Insurance Agent",
            "type":"Services"
        }
    ],
    "sg:phone":"+1 270 689 0080",
    "sg:postcode":"42303",
    "sg:province":"KY",
    "wof:name":"Miles Ag Insurance",
    "wof:placetype":"venue"
},
  "geometry": {"coordinates":[-87.08685800000001,37.72971],"type":"Point"}
}