{
  "type": "Feature",
  "properties": {
    "iso:country":"US",
    "sg:address":"38 E Main St",
    "sg:city":"Paris",
    "sg:classifiers":[
        {
            "category":"Organizations",
            "subcategory":"Community Association",
            "type":"Services"
        }
    ],
    "sg:phone":"+1 859 987 0025",
    "sg:postcode":"40361",
    "sg:province":"KY",
    "sg:tags":[
        "club"
    ],
    "wof:name":"Stoner Creek Country Club",
    "wof:placetype":"venue"
},
  "geometry": {"coordinates":[-84.248318,38.213958],"type":"Point"}
}