{
  "type": "Feature",
  "properties": {
    "iso:country":"US",
    "sg:address":"690 Wallace Wilkerson Blvd",
    "sg:city":"Liberty",
    "sg:classifiers":[
        {
            "category":"Professional",
            "subcategory":"Management & Consulting",
            "type":"Services"
        }
    ],
    "sg:phone":"+1 606 787 4732",
    "sg:postcode":"42539",
    "sg:province":"KY",
    "sg:tags":[
        "consultant",
        "educational"
    ],
    "wof:name":"Casey County Adult Education",
    "wof:placetype":"venue"
},
  "geometry": {"coordinates":[-84.940614,37.310155],"type":"Point"}
}