{
  "type": "Feature",
  "properties": {
    "iso:country":"US",
    "sg:address":"450 N Limestone St",
    "sg:city":"Lexington",
    "sg:classifiers":[
        {
            "category":"Manufacturing",
            "subcategory":"Printing",
            "type":"Manufacturing & Wholesale Goods"
        }
    ],
    "sg:phone":"+1 859 231 7966",
    "sg:postcode":"40508",
    "sg:province":"KY",
    "sg:tags":[
        "publisher"
    ],
    "wof:name":"Rockbridge Enterprises",
    "wof:placetype":"venue"
},
  "geometry": {"coordinates":[-84.48939799999999,38.051621],"type":"Point"}
}