{
  "type": "Feature",
  "properties": {
    "iso:country":"US",
    "sg:address":"5538 S Jackson Hwy",
    "sg:city":"Horse Cave",
    "sg:classifiers":[
        {
            "category":"Organizations",
            "subcategory":"Religious Organization",
            "type":"Services"
        }
    ],
    "sg:phone":"+1 270 786 1567",
    "sg:postcode":"42749",
    "sg:province":"KY",
    "sg:tags":[
        "church"
    ],
    "wof:name":"Bear Wallow Baptist Church",
    "wof:placetype":"venue"
},
  "geometry": {"coordinates":[-85.82887599999999,37.1834],"type":"Point"}
}