{
  "type": "Feature",
  "properties": {
    "iso:country":"US",
    "sg:address":"140 Cartertown Rd",
    "sg:city":"Scottsville",
    "sg:classifiers":[
        {
            "category":"Manufacturing",
            "subcategory":"Lumber",
            "type":"Manufacturing & Wholesale Goods"
        }
    ],
    "sg:phone":"+1 270 237 3660",
    "sg:postcode":"42164",
    "sg:province":"KY",
    "wof:name":"Woodstock Mills Inc",
    "wof:placetype":"venue"
},
  "geometry": {"coordinates":[-86.225692,36.72854],"type":"Point"}
}