{
  "type": "Feature",
  "properties": {
    "iso:country":"US",
    "sg:address":"205 E Main St",
    "sg:city":"Grayson",
    "sg:classifiers":[
        {
            "category":"Professional",
            "subcategory":"Art Services",
            "type":"Services"
        }
    ],
    "sg:phone":"+1 606 475 9324",
    "sg:postcode":"41143",
    "sg:province":"KY",
    "sg:tags":[
        "photographer"
    ],
    "wof:name":"Metcalf Photography",
    "wof:placetype":"venue"
},
  "geometry": {"coordinates":[-82.94674500000001,38.332109],"type":"Point"}
}