{
  "type": "Feature",
  "properties": {
    "iso:country":"US",
    "sg:address":"3304 Linda Ln",
    "sg:city":"Louisville",
    "sg:classifiers":[
        {
            "category":"Building & Trades",
            "subcategory":"Landscaping Services",
            "type":"Services"
        }
    ],
    "sg:phone":"+1 502 776 5972",
    "sg:postcode":"40211",
    "sg:province":"KY",
    "sg:tags":[
        "lawn",
        "maintenance",
        "grounds"
    ],
    "wof:name":"Picture Perfect Lawn Care",
    "wof:placetype":"venue"
},
  "geometry": {"coordinates":[-85.823733,38.211491],"type":"Point"}
}