{
  "type": "Feature",
  "properties": {
    "iso:country":"US",
    "sg:address":"2807 Town Center Blvd",
    "sg:city":"Ft Mitchell",
    "sg:classifiers":[
        {
            "category":"Restaurant",
            "type":"Food & Drink"
        }
    ],
    "sg:menulink":"http://www.allmenus.com/ky/covington/18959-hoggys/menu/",
    "sg:phone":"+1 859 331 3528",
    "sg:postcode":"41017",
    "sg:province":"KY",
    "sg:tags":[
        "american"
    ],
    "wof:name":"Hoggy's",
    "wof:placetype":"venue"
},
  "geometry": {"coordinates":[-84.555027,39.021981],"type":"Point"}
}