{
  "type": "Feature",
  "properties": {
    "addr:full":"100 United Dr Versailles KY 40383",
    "addr:housenumber":"100",
    "addr:postcode":"40383",
    "addr:street":"United Dr",
    "iso:country":"US",
    "sg:address":"100 United Dr",
    "sg:city":"Versailles",
    "sg:classifiers":[
        {
            "category":"Banks & Credit Unions",
            "subcategory":"Bank",
            "type":"Services"
        }
    ],
    "sg:phone":"+1 859 873 3136",
    "sg:postcode":"40383",
    "sg:province":"KY",
    "sg:website":"www.unitedbankwoodford.com",
    "wof:name":"United Bank & Trust Co",
    "wof:placetype":"venue"
},
  "geometry": {"coordinates":[-84.715537,38.052558],"type":"Point"}
}