{
  "type": "Feature",
  "properties": {
    "addr:full":"3208 Preston Hwy Louisville KY 40213",
    "addr:housenumber":"3208",
    "addr:postcode":"40213",
    "addr:street":"Preston Hwy",
    "iso:country":"US",
    "sg:address":"3208 Preston Hwy",
    "sg:city":"Louisville",
    "sg:classifiers":[
        {
            "category":"Shopping",
            "subcategory":"Musical Instruments",
            "type":"Retail Goods"
        }
    ],
    "sg:phone":"+1 502 634 8010",
    "sg:postcode":"40213",
    "sg:province":"KY",
    "wof:name":"Showcase Music & Productions",
    "wof:placetype":"venue"
},
  "geometry": {"coordinates":[-85.734143,38.201487],"type":"Point"}
}