{
  "type": "Feature",
  "properties": {
    "iso:country":"US",
    "sg:address":"1575 Production Dr",
    "sg:city":"Burlington",
    "sg:classifiers":[
        {
            "category":"Freight",
            "type":"Transportation"
        }
    ],
    "sg:phone":"+1 859 525 9181",
    "sg:postcode":"41005",
    "sg:province":"KY",
    "sg:tags":[
        "trucking"
    ],
    "wof:name":"Jerry Wilson Trucking Inc",
    "wof:placetype":"venue"
},
  "geometry": {"coordinates":[-84.687787,39.022047],"type":"Point"}
}