{
  "type": "Feature",
  "properties": {
    "iso:country":"US",
    "sg:address":"1320 N Race St",
    "sg:city":"Glasgow",
    "sg:classifiers":[
        {
            "category":"Shopping",
            "subcategory":"Pharmacy",
            "type":"Retail Goods"
        }
    ],
    "sg:phone":"+1 270 651 7030",
    "sg:postcode":"42141",
    "sg:province":"KY",
    "wof:name":"Medical Arts Pharmacy",
    "wof:placetype":"venue"
},
  "geometry": {"coordinates":[-85.903436,37.010958],"type":"Point"}
}