{
  "type": "Feature",
  "properties": {
    "iso:country":"US",
    "sg:address":"200 Highland Ave",
    "sg:city":"Monticello",
    "sg:classifiers":[
        {
            "category":"Farming",
            "subcategory":"Farm",
            "type":"Manufacturing & Wholesale Goods"
        }
    ],
    "sg:phone":"+1 606 348 8697",
    "sg:postcode":"42633",
    "sg:province":"KY",
    "sg:tags":[
        "crop",
        "general"
    ],
    "wof:name":"Js Farms",
    "wof:placetype":"venue"
},
  "geometry": {"coordinates":[-84.842776,36.833492],"type":"Point"}
}