{
  "type": "Feature",
  "properties": {
    "iso:country":"US",
    "sg:address":"540 E Lakeshore Dr",
    "sg:city":"Burnside",
    "sg:classifiers":[
        {
            "category":"Health Services",
            "subcategory":"Doctor",
            "type":"Services"
        }
    ],
    "sg:phone":"+1 606 561 4044",
    "sg:postcode":"42519",
    "sg:province":"KY",
    "sg:tags":[
        "physician",
        "surgeon"
    ],
    "wof:name":"Allen Gregory MD",
    "wof:placetype":"venue"
},
  "geometry": {"coordinates":[-84.56027899999999,36.990541],"type":"Point"}
}