{
  "type": "Feature",
  "properties": {
    "addr:full":"227 W Main St Danville KY 40422",
    "addr:housenumber":"227",
    "addr:postcode":"40422",
    "addr:street":"W Main St",
    "iso:country":"US",
    "sg:address":"227 W Main St",
    "sg:city":"Danville",
    "sg:classifiers":[
        {
            "category":"Wholesale",
            "subcategory":"Office Equipment",
            "type":"Manufacturing & Wholesale Goods"
        }
    ],
    "sg:phone":"+1 859 238 7154",
    "sg:postcode":"40422",
    "sg:province":"KY",
    "sg:tags":[
        "machine",
        "duplicating",
        "copying"
    ],
    "wof:name":"Nu Life Toner Inc",
    "wof:placetype":"venue"
},
  "geometry": {"coordinates":[-84.772435,37.645816],"type":"Point"}
}