{
  "type": "Feature",
  "properties": {
    "iso:country":"US",
    "sg:address":"1040 Lack Rd",
    "sg:city":"Elkton",
    "sg:classifiers":[
        {
            "category":"Insurance",
            "subcategory":"Insurance Agent",
            "type":"Services"
        }
    ],
    "sg:phone":"+1 270 265 0535",
    "sg:postcode":"42220",
    "sg:province":"KY",
    "wof:name":"Pewitt Insurance Svc",
    "wof:placetype":"venue"
},
  "geometry": {"coordinates":[-87.172051,36.905653],"type":"Point"}
}