{
  "type": "Feature",
  "properties": {
    "iso:country":"US",
    "sg:address":"2117 Payne St",
    "sg:city":"Louisville",
    "sg:classifiers":[
        {
            "category":"Recreation",
            "type":"Entertainment"
        }
    ],
    "sg:phone":"+1 502 893 8550",
    "sg:postcode":"40206",
    "sg:province":"KY",
    "sg:tags":[
        "martial",
        "arts",
        "instruction"
    ],
    "wof:name":"Taoist Tai Chi Society",
    "wof:placetype":"venue"
},
  "geometry": {"coordinates":[-85.70619600000001,38.252539],"type":"Point"}
}