{
  "type": "Feature",
  "properties": {
    "addr:full":"4119 Browns Ln Louisville KY 40220",
    "addr:housenumber":"4119",
    "addr:postcode":"40220",
    "addr:street":"Browns Ln",
    "iso:country":"US",
    "sg:address":"4119 Browns Ln",
    "sg:city":"Louisville",
    "sg:classifiers":[
        {
            "category":"Shopping",
            "subcategory":"Pharmacy",
            "type":"Retail Goods"
        }
    ],
    "sg:phone":"+1 502 473 1540",
    "sg:postcode":"40220",
    "sg:province":"KY",
    "wof:name":"Roubens Long Term Care Pharm",
    "wof:placetype":"venue"
},
  "geometry": {"coordinates":[-85.622787,38.221462],"type":"Point"}
}