{
  "type": "Feature",
  "properties": {
    "addr:full":"206 W Main St Princeton KY 42445",
    "addr:housenumber":"206",
    "addr:postcode":"42445",
    "addr:street":"W Main St",
    "iso:country":"US",
    "sg:address":"206 W Main St",
    "sg:city":"Princeton",
    "sg:classifiers":[
        {
            "category":"Health Services",
            "subcategory":"Doctor",
            "type":"Services"
        }
    ],
    "sg:phone":"+1 270 365 0901",
    "sg:postcode":"42445",
    "sg:province":"KY",
    "sg:tags":[
        "clinic"
    ],
    "wof:name":"Caldwell County Free Clinic",
    "wof:placetype":"venue"
},
  "geometry": {"coordinates":[-87.884156,37.109656],"type":"Point"}
}