{
  "type": "Feature",
  "properties": {
    "addr:full":"112 S Public Sq Glasgow KY 42141",
    "addr:housenumber":"112",
    "addr:postcode":"42141",
    "addr:street":"S Public Sq",
    "iso:country":"US",
    "sg:address":"112 S Public Sq",
    "sg:city":"Glasgow",
    "sg:classifiers":[
        {
            "category":"Shopping",
            "subcategory":"Jewelry",
            "type":"Retail Goods"
        }
    ],
    "sg:phone":"+1 270 651 3344",
    "sg:postcode":"42141",
    "sg:province":"KY",
    "sg:tags":[
        "jeweler"
    ],
    "wof:name":"George Ford Jeweler",
    "wof:placetype":"venue"
},
  "geometry": {"coordinates":[-85.913352,36.995323],"type":"Point"}
}