{
  "type": "Feature",
  "properties": {
    "iso:country":"US",
    "sg:address":"134 E Main St",
    "sg:city":"Morehead",
    "sg:classifiers":[
        {
            "category":"Personal",
            "type":"Services"
        }
    ],
    "sg:phone":"+1 606 784 4933",
    "sg:postcode":"40351",
    "sg:province":"KY",
    "sg:tags":[
        "wear",
        "formal"
    ],
    "wof:name":"All Seasons Flowers & Gifts",
    "wof:placetype":"venue"
},
  "geometry": {"coordinates":[-83.43462700000001,38.182388],"type":"Point"}
}