{
  "type": "Feature",
  "properties": {
    "iso:country":"US",
    "sg:address":"2821 Burlington Pike",
    "sg:city":"Burlington",
    "sg:classifiers":[
        {
            "category":"Personal",
            "type":"Services"
        }
    ],
    "sg:phone":"+1 859 586 8999",
    "sg:postcode":"41005",
    "sg:province":"KY",
    "sg:tags":[
        "towing"
    ],
    "wof:name":"Smith's High Tech Automotv Serv Inc",
    "wof:placetype":"venue"
},
  "geometry": {"coordinates":[-84.720001,39.027699],"type":"Point"}
}