{
  "type": "Feature",
  "properties": {
    "addr:full":"806 Columbia Ave Glasgow KY 42141",
    "addr:housenumber":"806",
    "addr:postcode":"42141",
    "addr:street":"Columbia Ave",
    "iso:country":"US",
    "sg:address":"806 Columbia Ave",
    "sg:city":"Glasgow",
    "sg:classifiers":[
        {
            "category":"Food & Beverages",
            "subcategory":"Specialty",
            "type":"Retail Goods"
        }
    ],
    "sg:phone":"+1 270 651 6204",
    "sg:postcode":"42141",
    "sg:province":"KY",
    "sg:tags":[
        "health",
        "diet"
    ],
    "wof:name":"Pioneer Health Foods",
    "wof:placetype":"venue"
},
  "geometry": {"coordinates":[-85.897498,37.002542],"type":"Point"}
}