{
  "type": "Feature",
  "properties": {
    "iso:country":"US",
    "sg:address":"1418 Old Dover Rd",
    "sg:city":"Clarksville",
    "sg:classifiers":[
        {
            "category":"Building & Trades",
            "subcategory":"Construction",
            "type":"Services"
        }
    ],
    "sg:phone":"+1 931 552 2770",
    "sg:postcode":"37042",
    "sg:province":"KY",
    "sg:tags":[
        "contractor"
    ],
    "wof:name":"Harrison Seamless Guttering",
    "wof:placetype":"venue"
},
  "geometry": {"coordinates":[-87.46795299999999,36.546974],"type":"Point"}
}