{
  "type": "Feature",
  "properties": {
    "addr:full":"1140 W Noel Ave Madisonville KY 42431",
    "addr:housenumber":"1140",
    "addr:postcode":"42431",
    "addr:street":"W Noel Ave",
    "iso:country":"US",
    "sg:address":"1140 W Noel Ave",
    "sg:city":"Madisonville",
    "sg:classifiers":[
        {
            "category":"Organizations",
            "subcategory":"Religious Organization",
            "type":"Services"
        }
    ],
    "sg:phone":"+1 270 821 9129",
    "sg:postcode":"42431",
    "sg:province":"KY",
    "sg:tags":[
        "church"
    ],
    "wof:name":"Miracle Temple Church Of God",
    "wof:placetype":"venue"
},
  "geometry": {"coordinates":[-87.520172,37.33728],"type":"Point"}
}