{
  "type": "Feature",
  "properties": {
    "addr:full":"1375 S 3rd St Paducah KY 42003",
    "addr:housenumber":"1375",
    "addr:postcode":"42003",
    "addr:street":"S 3Rd St",
    "iso:country":"US",
    "sg:address":"1375 S 3rd St",
    "sg:city":"Paducah",
    "sg:classifiers":[
        {
            "category":"Freight",
            "type":"Transportation"
        }
    ],
    "sg:phone":"+1 270 898 7095",
    "sg:postcode":"42003",
    "sg:province":"KY",
    "sg:tags":[
        "commercial",
        "storage"
    ],
    "wof:name":"Mini Systems Of 3rd Street",
    "wof:placetype":"venue"
},
  "geometry": {"coordinates":[-88.58788,37.072872],"type":"Point"}
}