{
  "type": "Feature",
  "properties": {
    "addr:full":"1301 Weyler Ave Louisville KY 40215",
    "addr:housenumber":"1301",
    "addr:postcode":"40215",
    "addr:street":"Weyler Ave",
    "iso:country":"US",
    "sg:address":"1301 Weyler Ave",
    "sg:city":"Louisville",
    "sg:classifiers":[
        {
            "category":"Professional",
            "type":"Services"
        }
    ],
    "sg:phone":"+1 502 361 2509",
    "sg:postcode":"40215",
    "sg:province":"KY",
    "wof:name":"Wills Recycler",
    "wof:placetype":"venue"
},
  "geometry": {"coordinates":[-85.78470299999999,38.204175],"type":"Point"}
}