{
  "type": "Feature",
  "properties": {
    "iso:country":"US",
    "sg:address":"622 N 3rd St",
    "sg:city":"Bardstown",
    "sg:classifiers":[
        {
            "category":"Professional",
            "subcategory":"Accounting & Tax Preparation",
            "type":"Services"
        }
    ],
    "sg:phone":"+1 502 349 6710",
    "sg:postcode":"40004",
    "sg:province":"KY",
    "sg:tags":[
        "return",
        "filing"
    ],
    "wof:name":"Tax Service",
    "wof:placetype":"venue"
},
  "geometry": {"coordinates":[-85.46339399999999,37.819628],"type":"Point"}
}