{
  "type": "Feature",
  "properties": {
    "iso:country":"US",
    "sg:address":"609 W Jefferson St",
    "sg:city":"Louisville",
    "sg:classifiers":[
        {
            "category":"Government",
            "subcategory":"Office",
            "type":"Public Place"
        }
    ],
    "sg:phone":"+1 502 574 3031",
    "sg:postcode":"40202",
    "sg:province":"KY",
    "sg:tags":[
        "village"
    ],
    "wof:name":"Louisville Budget",
    "wof:placetype":"venue"
},
  "geometry": {"coordinates":[-85.761859,38.254439],"type":"Point"}
}