{
  "type": "Feature",
  "properties": {
    "addr:full":"106 Shane St Glasgow KY 42141",
    "addr:housenumber":"106",
    "addr:postcode":"42141",
    "addr:street":"Shane St",
    "iso:country":"US",
    "sg:address":"106 Shane St",
    "sg:city":"Glasgow",
    "sg:classifiers":[
        {
            "category":"Shopping",
            "subcategory":"Music",
            "type":"Retail Goods"
        }
    ],
    "sg:phone":"+1 270 651 5945",
    "sg:postcode":"42141",
    "sg:province":"KY",
    "sg:tags":[
        "compact",
        "record",
        "disc",
        "tape"
    ],
    "wof:name":"Sam Goody",
    "wof:placetype":"venue"
},
  "geometry": {"coordinates":[-85.92652,37.005561],"type":"Point"}
}