{
  "type": "Feature",
  "properties": {
    "addr:full":"1725 Shelby Rd Louisville KY 40213",
    "addr:housenumber":"1725",
    "addr:postcode":"40213",
    "addr:street":"Shelby Rd",
    "iso:country":"US",
    "sg:address":"1725 Shelby Rd",
    "sg:city":"Louisville",
    "sg:classifiers":[
        {
            "category":"Building & Trades",
            "subcategory":"Construction",
            "type":"Services"
        }
    ],
    "sg:phone":"+1 502 458 3358",
    "sg:postcode":"40213",
    "sg:province":"KY",
    "sg:tags":[
        "project"
    ],
    "wof:name":"HBD Construction",
    "wof:placetype":"venue"
},
  "geometry": {"coordinates":[-85.71205500000001,38.208924],"type":"Point"}
}