{
  "type": "Feature",
  "properties": {
    "iso:country":"US",
    "sg:address":"104 W Cherry St",
    "sg:city":"Glasgow",
    "sg:classifiers":[
        {
            "category":"Shopping",
            "subcategory":"Florist",
            "type":"Retail Goods"
        }
    ],
    "sg:phone":"+1 270 651 3582",
    "sg:postcode":"42141",
    "sg:province":"KY",
    "wof:name":"Glasgow Flower Shop",
    "wof:placetype":"venue"
},
  "geometry": {"coordinates":[-85.909503,37.001596],"type":"Point"}
}