{
  "type": "Feature",
  "properties": {
    "iso:country":"US",
    "sg:address":"1025 US Hwy 62",
    "sg:city":"Princeton",
    "sg:classifiers":[
        {
            "category":"Government",
            "subcategory":"Office",
            "type":"Public Place"
        }
    ],
    "sg:phone":"+1 270 365 2787",
    "sg:postcode":"42445",
    "sg:province":"KY",
    "wof:name":"Caldwell Cnty Extension Office",
    "wof:placetype":"venue"
},
  "geometry": {"coordinates":[-87.89716199999999,37.117464],"type":"Point"}
}