{
  "type": "Feature",
  "properties": {
    "iso:country":"US",
    "sg:address":"4020 Georgetown Rd",
    "sg:city":"Lexington",
    "sg:classifiers":[
        {
            "category":"Restaurant",
            "type":"Food & Drink"
        }
    ],
    "sg:phone":"+1 859 233 7898",
    "sg:postcode":"40511",
    "sg:province":"KY",
    "sg:tags":[
        "house",
        "steak",
        "barbecue"
    ],
    "wof:name":"Red State Bbq",
    "wof:placetype":"venue"
},
  "geometry": {"coordinates":[-84.532533,38.135371],"type":"Point"}
}