{
  "type": "Feature",
  "properties": {
    "iso:country":"US",
    "sg:address":"243 Regency Cir",
    "sg:city":"Lexington",
    "sg:classifiers":[
        {
            "category":"Insurance",
            "subcategory":"Insurance Agent",
            "type":"Services"
        }
    ],
    "sg:phone":"+1 859 276 1413",
    "sg:postcode":"40503",
    "sg:province":"KY",
    "wof:name":"Lifetime Financial Svc",
    "wof:placetype":"venue"
},
  "geometry": {"coordinates":[-84.52292199999999,38.011875],"type":"Point"}
}