{
  "type": "Feature",
  "properties": {
    "iso:country":"US",
    "sg:address":"113 S 42nd St",
    "sg:city":"Louisville",
    "sg:classifiers":[
        {
            "category":"Personal",
            "subcategory":"Beauty Salon",
            "type":"Services"
        }
    ],
    "sg:phone":"+1 502 778 4742",
    "sg:postcode":"40212",
    "sg:province":"KY",
    "sg:tags":[
        "shop"
    ],
    "wof:name":"Future Nails",
    "wof:placetype":"venue"
},
  "geometry": {"coordinates":[-85.81823199999999,38.263428],"type":"Point"}
}