{
  "type": "Feature",
  "properties": {
    "addr:full":"2179 6th Vein Rd Dawson Springs KY 42408",
    "addr:housenumber":"2179",
    "addr:postcode":"42408",
    "addr:street":"6Th Vein Rd",
    "iso:country":"US",
    "sg:address":"2179 6th Vein Rd",
    "sg:city":"Dawson Springs",
    "sg:classifiers":[
        {
            "category":"Manufacturing",
            "subcategory":"Lumber",
            "type":"Manufacturing & Wholesale Goods"
        }
    ],
    "sg:phone":"+1 270 797 8669",
    "sg:postcode":"42408",
    "sg:province":"KY",
    "sg:tags":[
        "sawmill"
    ],
    "wof:name":"Blessed Hardwood",
    "wof:placetype":"venue"
},
  "geometry": {"coordinates":[-87.668375,37.240389],"type":"Point"}
}