{
  "type": "Feature",
  "properties": {
    "iso:country":"US",
    "sg:address":"1387 Lakewood Rd",
    "sg:city":"Princeton",
    "sg:classifiers":[
        {
            "category":"Personal",
            "type":"Services"
        }
    ],
    "sg:phone":"+1 270 365 0255",
    "sg:postcode":"42445",
    "sg:province":"KY",
    "wof:name":"Wolff System Tanning Center",
    "wof:placetype":"venue"
},
  "geometry": {"coordinates":[-87.860741,37.239122],"type":"Point"}
}