{
  "type": "Feature",
  "properties": {
    "addr:full":"102 Miller Ln Crittenden KY 41075",
    "addr:housenumber":"102",
    "addr:postcode":"41075",
    "addr:street":"Miller Ln",
    "iso:country":"US",
    "sg:address":"102 Miller Ln",
    "sg:city":"Crittenden",
    "sg:classifiers":[
        {
            "category":"Real Estate",
            "subcategory":"Real Estate Agent",
            "type":"Services"
        }
    ],
    "sg:phone":"+1 859 428 3989",
    "sg:postcode":"41075",
    "sg:province":"KY",
    "sg:tags":[
        "cooperative"
    ],
    "wof:name":"Eastern Kentucky Power Co Op",
    "wof:placetype":"venue"
},
  "geometry": {"coordinates":[-84.446046,39.08028],"type":"Point"}
}