{
  "type": "Feature",
  "properties": {
    "addr:full":"1210 Gilmore Ln Louisville KY 40213",
    "addr:housenumber":"1210",
    "addr:postcode":"40213",
    "addr:street":"Gilmore Ln",
    "iso:country":"US",
    "sg:address":"1210 Gilmore Ln",
    "sg:city":"Louisville",
    "sg:classifiers":[
        {
            "category":"Shopping",
            "subcategory":"Department Store",
            "type":"Retail Goods"
        }
    ],
    "sg:phone":"+1 502 962 8695",
    "sg:postcode":"40213",
    "sg:province":"KY",
    "sg:tags":[
        "shop"
    ],
    "wof:name":"Dollar General",
    "wof:placetype":"venue"
},
  "geometry": {"coordinates":[-85.712565,38.174657],"type":"Point"}
}