{
  "type": "Feature",
  "properties": {
    "iso:country":"US",
    "sg:address":"4522 Algonquin Pkwy",
    "sg:city":"Louisville",
    "sg:classifiers":[
        {
            "category":"Retail",
            "subcategory":"Auto Repair",
            "type":"Services"
        }
    ],
    "sg:phone":"+1 502 774 5156",
    "sg:postcode":"40211",
    "sg:province":"KY",
    "sg:tags":[
        "wrecker"
    ],
    "wof:name":"Spirtas Wrecking",
    "wof:placetype":"venue"
},
  "geometry": {"coordinates":[-85.828002,38.232248],"type":"Point"}
}