{
  "type": "Feature",
  "properties": {
    "iso:country":"US",
    "sg:address":"60 S Main St",
    "sg:city":"Dry Ridge",
    "sg:classifiers":[
        {
            "category":"Restaurant",
            "type":"Food & Drink"
        }
    ],
    "sg:phone":"+1 859 824 9533",
    "sg:postcode":"41035",
    "sg:province":"KY",
    "sg:tags":[
        "eating"
    ],
    "wof:name":"China King",
    "wof:placetype":"venue"
},
  "geometry": {"coordinates":[-84.587101,38.68089],"type":"Point"}
}