{
  "type": "Feature",
  "properties": {
    "iso:country":"US",
    "sg:address":"522 N Mulberry St",
    "sg:city":"Elizabethtown",
    "sg:classifiers":[
        {
            "category":"Education",
            "subcategory":"School",
            "type":"Public Place"
        }
    ],
    "sg:phone":"+1 270 234 0007",
    "sg:postcode":"42701",
    "sg:province":"KY",
    "wof:name":"Music & Arts Ctr",
    "wof:placetype":"venue"
},
  "geometry": {"coordinates":[-85.853919,37.700083],"type":"Point"}
}