{
  "type": "Feature",
  "properties": {
    "iso:country":"US",
    "sg:address":"3315 Bardstown Rd",
    "sg:city":"Louisville",
    "sg:classifiers":[
        {
            "category":"Travel",
            "subcategory":"Hotels & Motels",
            "type":"Entertainment"
        },
        {
            "category":"Travel",
            "subcategory":"Bed & Breakfast",
            "type":"Entertainment"
        }
    ],
    "sg:phone":"+1 502 452 1598",
    "sg:postcode":"40218",
    "sg:province":"KY",
    "sg:tags":[
        "inn"
    ],
    "wof:name":"Best Inns & Suites",
    "wof:placetype":"venue"
},
  "geometry": {"coordinates":[-85.66833099999999,38.207671],"type":"Point"}
}