{
  "type": "Feature",
  "properties": {
    "iso:country":"US",
    "sg:address":"7704 Morgantown Rd",
    "sg:city":"Bowling Green",
    "sg:classifiers":[
        {
            "category":"Organizations",
            "subcategory":"Religious Organization",
            "type":"Services"
        }
    ],
    "sg:phone":"+1 270 781 2768",
    "sg:postcode":"42101",
    "sg:province":"KY",
    "sg:tags":[
        "church"
    ],
    "wof:name":"Bible Center Assembly",
    "wof:placetype":"venue"
},
  "geometry": {"coordinates":[-86.555705,37.017411],"type":"Point"}
}