{
  "type": "Feature",
  "properties": {
    "iso:country":"US",
    "sg:address":"1303 E Broadway St",
    "sg:city":"Campbellsville",
    "sg:classifiers":[
        {
            "category":"Restaurant",
            "type":"Food & Drink"
        }
    ],
    "sg:menulink":"http://www.allmenus.com/ky/campbellsville/155874-hardees/menu/",
    "sg:phone":"+1 270 789 1386",
    "sg:postcode":"42718",
    "sg:province":"KY",
    "sg:tags":[
        "burger",
        "american"
    ],
    "wof:name":"Hardee's",
    "wof:placetype":"venue"
},
  "geometry": {"coordinates":[-85.328154,37.354454],"type":"Point"}
}