{
  "type": "Feature",
  "properties": {
    "iso:country":"US",
    "sg:address":"1990 Bridgeport-Benson Rd",
    "sg:city":"Frankfort",
    "sg:classifiers":[
        {
            "category":"Building & Trades",
            "subcategory":"Construction",
            "type":"Services"
        }
    ],
    "sg:phone":"+1 502 875 2115",
    "sg:postcode":"40601",
    "sg:province":"KY",
    "sg:tags":[
        "house"
    ],
    "wof:name":"Redding Construction LLC",
    "wof:placetype":"venue"
},
  "geometry": {"coordinates":[-84.961288,38.192594],"type":"Point"}
}