{
  "type": "Feature",
  "properties": {
    "addr:full":"110 E Main St Georgetown KY 40324",
    "addr:housenumber":"110",
    "addr:postcode":"40324",
    "addr:street":"E Main St",
    "iso:country":"US",
    "sg:address":"110 E Main St",
    "sg:city":"Georgetown",
    "sg:classifiers":[
        {
            "category":"Banks & Credit Unions",
            "subcategory":"Bank",
            "type":"Services"
        }
    ],
    "sg:phone":"+1 502 867 0077",
    "sg:postcode":"40324",
    "sg:province":"KY",
    "sg:tags":[
        "loan",
        "real estate"
    ],
    "wof:name":"Calloway Financial",
    "wof:placetype":"venue"
},
  "geometry": {"coordinates":[-84.559603,38.209857],"type":"Point"}
}