{
  "type": "Feature",
  "properties": {
    "addr:full":"333 N Ashland Ave Lexington KY 40502",
    "addr:housenumber":"333",
    "addr:postcode":"40502",
    "addr:street":"N Ashland Ave",
    "iso:country":"US",
    "sg:address":"333 N Ashland Ave",
    "sg:city":"Lexington",
    "sg:classifiers":[
        {
            "category":"Professional",
            "subcategory":"Business Services",
            "type":"Services"
        }
    ],
    "sg:phone":"+1 859 266 6661",
    "sg:postcode":"40502",
    "sg:province":"KY",
    "wof:name":"Seasons Catering",
    "wof:placetype":"venue"
},
  "geometry": {"coordinates":[-84.478212,38.039481],"type":"Point"}
}