{
  "type": "Feature",
  "properties": {
    "addr:full":"624 E 3rd St Owensboro KY 42303",
    "addr:housenumber":"624",
    "addr:postcode":"42303",
    "addr:street":"E 3Rd St",
    "iso:country":"US",
    "sg:address":"624 E 3rd St",
    "sg:city":"Owensboro",
    "sg:classifiers":[
        {
            "category":"Autos & Motor Vehicles",
            "subcategory":"Auto Supplies",
            "type":"Retail Goods"
        }
    ],
    "sg:phone":"+1 270 683 7365",
    "sg:postcode":"42303",
    "sg:province":"KY",
    "sg:tags":[
        "tire"
    ],
    "wof:name":"Tire Mart",
    "wof:placetype":"venue"
},
  "geometry": {"coordinates":[-87.104422,37.774071],"type":"Point"}
}