{
  "type": "Feature",
  "properties": {
    "addr:full":"2061 Lexington Rd Nicholasville KY 40356",
    "addr:housenumber":"2061",
    "addr:postcode":"40356",
    "addr:street":"Lexington Rd",
    "iso:country":"US",
    "sg:address":"2061 Lexington Rd",
    "sg:city":"Nicholasville",
    "sg:classifiers":[
        {
            "category":"Recreation",
            "type":"Entertainment"
        }
    ],
    "sg:phone":"+1 859 881 0524",
    "sg:postcode":"40356",
    "sg:province":"KY",
    "sg:tags":[
        "amusement"
    ],
    "wof:name":"Champions Lexington LLC",
    "wof:placetype":"venue"
},
  "geometry": {"coordinates":[-84.558869,37.91316],"type":"Point"}
}