{
  "type": "Feature",
  "properties": {
    "addr:full":"878 Eastern Byp Richmond KY 40475",
    "addr:housenumber":"878",
    "addr:postcode":"40475",
    "addr:street":"Eastern Byp",
    "iso:country":"US",
    "sg:address":"878 Eastern Byp",
    "sg:city":"Richmond",
    "sg:classifiers":[
        {
            "category":"Banks & Credit Unions",
            "subcategory":"Bank",
            "type":"Services"
        }
    ],
    "sg:phone":"+1 859 625 0555",
    "sg:postcode":"40475",
    "sg:province":"KY",
    "sg:tags":[
        "cashing",
        "check"
    ],
    "wof:name":"Advance America",
    "wof:placetype":"venue"
},
  "geometry": {"coordinates":[-84.271997,37.734674],"type":"Point"}
}