{
  "type": "Feature",
  "properties": {
    "iso:country":"US",
    "sg:address":"1711 Bardstown Rd",
    "sg:city":"Louisville",
    "sg:classifiers":[
        {
            "category":"Social Services",
            "type":"Services"
        }
    ],
    "sg:phone":"+1 502 458 1158",
    "sg:postcode":"40205",
    "sg:province":"KY",
    "sg:tags":[
        "counselor",
        "marriage",
        "family"
    ],
    "wof:name":"Dottie M Doyle",
    "wof:placetype":"venue"
},
  "geometry": {"coordinates":[-85.702866,38.229721],"type":"Point"}
}