{
  "type": "Feature",
  "properties": {
    "iso:country":"US",
    "sg:address":"11023 Radleigh Ln",
    "sg:city":"Louisville",
    "sg:classifiers":[
        {
            "category":"Freight",
            "type":"Transportation"
        }
    ],
    "sg:phone":"+1 502 937 8618",
    "sg:postcode":"40291",
    "sg:province":"KY",
    "sg:tags":[
        "operator",
        "local",
        "trucking"
    ],
    "wof:name":"Willard Trucking LLC",
    "wof:placetype":"venue"
},
  "geometry": {"coordinates":[-85.569017,38.094721],"type":"Point"}
}