{
  "type": "Feature",
  "properties": {
    "addr:full":"1920 Greenup Ave Ashland KY 41101",
    "addr:housenumber":"1920",
    "addr:postcode":"41101",
    "addr:street":"Greenup Ave",
    "iso:country":"US",
    "sg:address":"1920 Greenup Ave",
    "sg:city":"Ashland",
    "sg:classifiers":[
        {
            "category":"Home & Garden",
            "subcategory":"Building Materials",
            "type":"Retail Goods"
        }
    ],
    "sg:phone":"+1 606 326 1994",
    "sg:postcode":"41101",
    "sg:province":"KY",
    "sg:tags":[
        "glass",
        "window",
        "plate"
    ],
    "wof:name":"Guardian Auto Glass",
    "wof:placetype":"venue"
},
  "geometry": {"coordinates":[-82.634542,38.477323],"type":"Point"}
}