{
  "type": "Feature",
  "properties": {
    "addr:full":"44 Licking Pike Wilder KY 41071",
    "addr:housenumber":"44",
    "addr:postcode":"41071",
    "addr:street":"Licking Pike",
    "iso:country":"US",
    "sg:address":"44 Licking Pike",
    "sg:city":"Wilder",
    "sg:classifiers":[
        {
            "category":"Bars & Pubs",
            "type":"Food & Drink"
        }
    ],
    "sg:phone":"+1 859 431 5588",
    "sg:postcode":"41071",
    "sg:province":"KY",
    "sg:tags":[
        "club",
        "night"
    ],
    "wof:name":"Bobby Mackey's Music World Inc",
    "wof:placetype":"venue"
},
  "geometry": {"coordinates":[-84.492403,39.072968],"type":"Point"}
}