{
  "type": "Feature",
  "properties": {
    "iso:country":"US",
    "sg:address":"4434 Cane Run Rd",
    "sg:city":"Louisville",
    "sg:classifiers":[
        {
            "category":"Food & Beverages",
            "subcategory":"Specialty",
            "type":"Retail Goods"
        },
        {
            "category":"Shopping",
            "subcategory":"Pharmacy",
            "type":"Retail Goods"
        }
    ],
    "sg:phone":"+1 502 447 1611",
    "sg:postcode":"40216",
    "sg:province":"KY",
    "sg:tags":[
        "medical",
        "vitamin",
        "drug",
        "equipment",
        "rental",
        "store"
    ],
    "wof:name":"All Care Natural Alternatives",
    "wof:placetype":"venue"
},
  "geometry": {"coordinates":[-85.842012,38.195925],"type":"Point"}
}