{
  "type": "Feature",
  "properties": {
    "iso:country":"US",
    "sg:address":"102 Portman Ave",
    "sg:city":"Stanford",
    "sg:classifiers":[
        {
            "category":"Health Services",
            "subcategory":"Health Practitioner",
            "type":"Services"
        }
    ],
    "sg:phone":"+1 606 365 9070",
    "sg:postcode":"40484",
    "sg:province":"KY",
    "sg:tags":[
        "therapist",
        "physical"
    ],
    "wof:name":"Fort Logan Outpatient Rehab",
    "wof:placetype":"venue"
},
  "geometry": {"coordinates":[-84.66293899999999,37.532435],"type":"Point"}
}