{
  "type": "Feature",
  "properties": {
    "addr:full":"252 Summit St Richmond KY 40475",
    "addr:housenumber":"252",
    "addr:postcode":"40475",
    "addr:street":"Summit St",
    "iso:country":"US",
    "sg:address":"252 Summit St",
    "sg:city":"Richmond",
    "sg:classifiers":[
        {
            "category":"Social Services",
            "type":"Services"
        }
    ],
    "sg:phone":"+1 859 625 0213",
    "sg:postcode":"40475",
    "sg:province":"KY",
    "sg:tags":[
        "crisis",
        "intervention"
    ],
    "wof:name":"Rape Crisis Ctr",
    "wof:placetype":"venue"
},
  "geometry": {"coordinates":[-84.29468,37.743578],"type":"Point"}
}