{
  "type": "Feature",
  "properties": {
    "addr:full":"200 Lakeview Dr Shepherdsville KY 40165",
    "addr:housenumber":"200",
    "addr:postcode":"40165",
    "addr:street":"Lakeview Dr",
    "iso:country":"US",
    "sg:address":"200 Lakeview Dr",
    "sg:city":"Shepherdsville",
    "sg:classifiers":[
        {
            "category":"Restaurant",
            "type":"Food & Drink"
        }
    ],
    "sg:phone":"+1 502 921 2332",
    "sg:postcode":"40165",
    "sg:province":"KY",
    "wof:name":"Denny's",
    "wof:placetype":"venue"
},
  "geometry": {"coordinates":[-85.648568,38.064393],"type":"Point"}
}