{
  "type": "Feature",
  "properties": {
    "iso:country":"US",
    "sg:address":"90 Old Bloomfield Pike",
    "sg:city":"Bardstown",
    "sg:classifiers":[
        {
            "category":"Food & Beverages",
            "subcategory":"Liquor & Beverages",
            "type":"Retail Goods"
        }
    ],
    "sg:phone":"+1 502 348 3164",
    "sg:postcode":"40004",
    "sg:province":"KY",
    "wof:name":"State Liquor",
    "wof:placetype":"venue"
},
  "geometry": {"coordinates":[-85.460836,37.809298],"type":"Point"}
}