{
  "type": "Feature",
  "properties": {
    "addr:full":"3430 Preston Hwy Louisville KY 40213",
    "addr:housenumber":"3430",
    "addr:postcode":"40213",
    "addr:street":"Preston Hwy",
    "iso:country":"US",
    "sg:address":"3430 Preston Hwy",
    "sg:city":"Louisville",
    "sg:classifiers":[
        {
            "category":"Utilities",
            "subcategory":"Mobile Phone",
            "type":"Services"
        }
    ],
    "sg:phone":"+1 502 375 1786",
    "sg:postcode":"40213",
    "sg:province":"KY",
    "sg:tags":[
        "telephone",
        "cellular"
    ],
    "wof:name":"Voice Technology",
    "wof:placetype":"venue"
},
  "geometry": {"coordinates":[-85.73031400000001,38.195575],"type":"Point"}
}