{
  "type": "Feature",
  "properties": {
    "addr:full":"435 Jefferson St Lexington KY 40508",
    "addr:housenumber":"435",
    "addr:postcode":"40508",
    "addr:street":"Jefferson St",
    "iso:country":"US",
    "sg:address":"435 Jefferson St",
    "sg:city":"Lexington",
    "sg:classifiers":[
        {
            "category":"Wholesale",
            "subcategory":"Non-durable Goods",
            "type":"Manufacturing & Wholesale Goods"
        }
    ],
    "sg:phone":"+1 859 455 9253",
    "sg:postcode":"40508",
    "sg:province":"KY",
    "sg:tags":[
        "candle",
        "equipment"
    ],
    "sg:website":"www.mccandles.com",
    "wof:name":"Moskovitz Candles LLC",
    "wof:placetype":"venue"
},
  "geometry": {"coordinates":[-84.495159,38.057479],"type":"Point"}
}