{
  "type": "Feature",
  "properties": {
    "iso:country":"US",
    "sg:address":"8197 Riley Rd",
    "sg:city":"Alexandria",
    "sg:classifiers":[
        {
            "category":"Banks & Credit Unions",
            "subcategory":"Bank",
            "type":"Services"
        }
    ],
    "sg:phone":"+1 859 448 0999",
    "sg:postcode":"41001",
    "sg:province":"KY",
    "sg:tags":[
        "financing"
    ],
    "wof:name":"National Family Funding",
    "wof:placetype":"venue"
},
  "geometry": {"coordinates":[-84.378141,38.963625],"type":"Point"}
}