{
  "type": "Feature",
  "properties": {
    "addr:full":"1111 Swan St Louisville KY 40204",
    "addr:housenumber":"1111",
    "addr:postcode":"40204",
    "addr:street":"Swan St",
    "iso:country":"US",
    "sg:address":"1111 Swan St",
    "sg:city":"Louisville",
    "sg:classifiers":[
        {
            "category":"Organizations",
            "subcategory":"Community Association",
            "type":"Services"
        }
    ],
    "sg:phone":"+1 502 635 6911",
    "sg:postcode":"40204",
    "sg:province":"KY",
    "sg:tags":[
        "club"
    ],
    "wof:name":"Amvets Daniel Boone Post 1",
    "wof:placetype":"venue"
},
  "geometry": {"coordinates":[-85.73697799999999,38.234297],"type":"Point"}
}