{
  "type": "Feature",
  "properties": {
    "iso:country":"US",
    "sg:address":"130 Troon Rd",
    "sg:city":"Paducah",
    "sg:classifiers":[
        {
            "category":"Professional",
            "subcategory":"Management & Consulting",
            "type":"Services"
        }
    ],
    "sg:phone":"+1 270 554 7420",
    "sg:postcode":"42001",
    "sg:province":"KY",
    "sg:tags":[
        "consultant"
    ],
    "wof:name":"Human Resource Consultants Inc",
    "wof:placetype":"venue"
},
  "geometry": {"coordinates":[-88.704787,37.046948],"type":"Point"}
}