{
  "type": "Feature",
  "properties": {
    "iso:country":"US",
    "sg:address":"250 Quisenberry Ln",
    "sg:city":"Hopkinsville",
    "sg:classifiers":[
        {
            "category":"Building & Trades",
            "subcategory":"Construction",
            "type":"Services"
        }
    ],
    "sg:phone":"+1 270 235 8001",
    "sg:postcode":"42240",
    "sg:province":"KY",
    "sg:tags":[
        "restoration",
        "cleaning",
        "patio",
        "deck"
    ],
    "wof:name":"D & P Clean Up",
    "wof:placetype":"venue"
},
  "geometry": {"coordinates":[-87.621959,36.88583],"type":"Point"}
}