{
  "type": "Feature",
  "properties": {
    "iso:country":"US",
    "sg:address":"12668 Cub Run Hwy",
    "sg:city":"Cub Run",
    "sg:classifiers":[
        {
            "category":"Professional",
            "type":"Services"
        }
    ],
    "sg:phone":"+1 270 524 9882",
    "sg:postcode":"42729",
    "sg:province":"KY",
    "sg:tags":[
        "establishment"
    ],
    "wof:name":"Sharyn's Silk Creations",
    "wof:placetype":"venue"
},
  "geometry": {"coordinates":[-86.056909,37.306037],"type":"Point"}
}