{
  "type": "Feature",
  "properties": {
    "iso:country":"US",
    "sg:address":"330 E Oak St",
    "sg:city":"Louisville",
    "sg:classifiers":[
        {
            "category":"Health Services",
            "subcategory":"Doctor",
            "type":"Services"
        }
    ],
    "sg:phone":"+1 502 636 1805",
    "sg:postcode":"40203",
    "sg:province":"KY",
    "sg:tags":[
        "physician",
        "surgeon"
    ],
    "wof:name":"Family Doctors",
    "wof:placetype":"venue"
},
  "geometry": {"coordinates":[-85.749679,38.233971],"type":"Point"}
}