{
  "type": "Feature",
  "properties": {
    "iso:country":"US",
    "sg:address":"691 Breckinridge St",
    "sg:city":"Stanton",
    "sg:classifiers":[
        {
            "category":"Education",
            "subcategory":"School",
            "type":"Public Place"
        }
    ],
    "sg:phone":"+1 606 663 3300",
    "sg:postcode":"40380",
    "sg:province":"KY",
    "sg:website":"www.powell.k12.ky.us",
    "wof:name":"Powell County Board Of Educ",
    "wof:placetype":"venue"
},
  "geometry": {"coordinates":[-83.85978299999999,37.854247],"type":"Point"}
}