{
  "type": "Feature",
  "properties": {
    "iso:country":"US",
    "sg:address":"10136 Dixie Hwy",
    "sg:city":"Florence",
    "sg:classifiers":[
        {
            "category":"Health Services",
            "subcategory":"Doctor",
            "type":"Services"
        }
    ],
    "sg:phone":"+1 859 283 1986",
    "sg:postcode":"41042",
    "sg:province":"KY",
    "sg:tags":[
        "dentist"
    ],
    "wof:name":"Ken Wallace DDS",
    "wof:placetype":"venue"
},
  "geometry": {"coordinates":[-84.620904,38.95458],"type":"Point"}
}