{
  "type": "Feature",
  "properties": {
    "iso:country":"US",
    "sg:address":"623 Herndon Cir",
    "sg:city":"Cadiz",
    "sg:classifiers":[
        {
            "category":"Professional",
            "type":"Services"
        }
    ],
    "sg:phone":"+1 270 522 5104",
    "sg:postcode":"42211",
    "sg:province":"KY",
    "wof:name":"Leslie & Co",
    "wof:placetype":"venue"
},
  "geometry": {"coordinates":[-87.823853,36.905954],"type":"Point"}
}