{
  "type": "Feature",
  "properties": {
    "iso:country":"US",
    "sg:address":"9112 Leesgate Rd",
    "sg:city":"Louisville",
    "sg:classifiers":[
        {
            "category":"Health Services",
            "subcategory":"Doctor",
            "type":"Services"
        }
    ],
    "sg:phone":"+1 502 329 8190",
    "sg:postcode":"40222",
    "sg:province":"KY",
    "sg:tags":[
        "physician",
        "surgeon"
    ],
    "wof:name":"Kentuckiana Allergy Research",
    "wof:placetype":"venue"
},
  "geometry": {"coordinates":[-85.580681,38.243431],"type":"Point"}
}