{
  "type": "Feature",
  "properties": {
    "iso:country":"US",
    "sg:address":"304 Gordon Ave",
    "sg:city":"Bowling Green",
    "sg:classifiers":[
        {
            "category":"Home & Garden",
            "subcategory":"Hardware",
            "type":"Retail Goods"
        }
    ],
    "sg:phone":"+1 270 842 4851",
    "sg:postcode":"42101",
    "sg:province":"KY",
    "sg:tags":[
        "electrical",
        "supply"
    ],
    "wof:name":"O Reilly Auto Parts",
    "wof:placetype":"venue"
},
  "geometry": {"coordinates":[-86.443781,37.000908],"type":"Point"}
}