{
  "type": "Feature",
  "properties": {
    "iso:country":"US",
    "sg:address":"101 S 5th St",
    "sg:city":"Louisville",
    "sg:classifiers":[
        {
            "category":"Professional",
            "subcategory":"Lawyer & Legal Services",
            "type":"Services"
        }
    ],
    "sg:phone":"+1 502 581 8000",
    "sg:postcode":"40202",
    "sg:province":"KY",
    "sg:tags":[
        "attorney",
        "practice",
        "labor",
        "plan",
        "law",
        "employment"
    ],
    "wof:name":"Dinsmore & Shohl LLP",
    "wof:placetype":"venue"
},
  "geometry": {"coordinates":[-85.758171,38.256802],"type":"Point"}
}