{
  "type": "Feature",
  "properties": {
    "addr:full":"500 W Jefferson St Louisville KY 40202",
    "addr:housenumber":"500",
    "addr:postcode":"40202",
    "addr:street":"W Jefferson St",
    "iso:country":"US",
    "sg:address":"500 W Jefferson St",
    "sg:city":"Louisville",
    "sg:classifiers":[
        {
            "category":"Professional",
            "subcategory":"Lawyer & Legal Services",
            "type":"Services"
        }
    ],
    "sg:phone":"+1 502 581 1630",
    "sg:postcode":"40202",
    "sg:province":"KY",
    "sg:tags":[
        "attorney"
    ],
    "wof:name":"O'Koon & Hintermeister",
    "wof:placetype":"venue"
},
  "geometry": {"coordinates":[-85.76031999999999,38.254199],"type":"Point"}
}