{
  "type": "Feature",
  "properties": {
    "iso:country":"US",
    "sg:address":"107 S Willow St",
    "sg:city":"Providence",
    "sg:classifiers":[
        {
            "category":"Retail",
            "subcategory":"Laundry & Dry Cleaning",
            "type":"Services"
        }
    ],
    "sg:phone":"+1 270 667 5892",
    "sg:postcode":"42450",
    "sg:province":"KY",
    "sg:tags":[
        "cleaners"
    ],
    "wof:name":"Versakleen Dry Cleaners",
    "wof:placetype":"venue"
},
  "geometry": {"coordinates":[-87.76073,37.397921],"type":"Point"}
}