{
  "type": "Feature",
  "properties": {
    "iso:country":"US",
    "sg:address":"1400 High Bridge Rd",
    "sg:city":"Wilmore",
    "sg:classifiers":[
        {
            "category":"Organizations",
            "subcategory":"Religious Organization",
            "type":"Services"
        }
    ],
    "sg:phone":"+1 859 858 4578",
    "sg:postcode":"40390",
    "sg:province":"KY",
    "wof:name":"Cornerstone Intl",
    "wof:placetype":"venue"
},
  "geometry": {"coordinates":[-84.676794,37.84187],"type":"Point"}
}