{
  "type": "Feature",
  "properties": {
    "iso:country":"US",
    "sg:address":"761 E New Circle Rd",
    "sg:city":"Lexington",
    "sg:classifiers":[
        {
            "category":"Shopping",
            "type":"Retail Goods"
        }
    ],
    "sg:phone":"+1 859 299 6899",
    "sg:postcode":"40505",
    "sg:province":"KY",
    "sg:tags":[
        "spa",
        "hot",
        "tub"
    ],
    "wof:name":"Hot Springs Of Lexington",
    "wof:placetype":"venue"
},
  "geometry": {"coordinates":[-84.453789,38.046518],"type":"Point"}
}