{
  "type": "Feature",
  "properties": {
    "iso:country":"US",
    "sg:address":"521 W Front St",
    "sg:city":"Glasgow",
    "sg:classifiers":[
        {
            "category":"Personal",
            "subcategory":"Beauty Salon",
            "type":"Services"
        }
    ],
    "sg:phone":"+1 270 651 5038",
    "sg:postcode":"42141",
    "sg:province":"KY",
    "wof:name":"Rene's Beauty Salon",
    "wof:placetype":"venue"
},
  "geometry": {"coordinates":[-85.916833,36.999997],"type":"Point"}
}