{
  "type": "Feature",
  "properties": {
    "addr:full":"306 N Main St Monticello KY 42633",
    "addr:housenumber":"306",
    "addr:postcode":"42633",
    "addr:street":"N Main St",
    "iso:country":"US",
    "sg:address":"306 N Main St",
    "sg:city":"Monticello",
    "sg:classifiers":[
        {
            "category":"Wholesale",
            "subcategory":"Medical Equipment & Supplies",
            "type":"Manufacturing & Wholesale Goods"
        }
    ],
    "sg:phone":"+1 606 348 8948",
    "sg:postcode":"42633",
    "sg:province":"KY",
    "sg:tags":[
        "physician",
        "surgeon"
    ],
    "wof:name":"Monticello Medical Supply",
    "wof:placetype":"venue"
},
  "geometry": {"coordinates":[-84.84601600000001,36.832532],"type":"Point"}
}