{
  "type": "Feature",
  "properties": {
    "iso:country":"US",
    "sg:address":"525 W 5th St",
    "sg:city":"Covington",
    "sg:classifiers":[
        {
            "category":"Communications",
            "subcategory":"Film & Video Production",
            "type":"Services"
        }
    ],
    "sg:phone":"+1 859 581 0033",
    "sg:postcode":"41011",
    "sg:province":"KY",
    "sg:tags":[
        "audio"
    ],
    "sg:website":"www.mwg.org",
    "wof:name":"Media Working Group Inc",
    "wof:placetype":"venue"
},
  "geometry": {"coordinates":[-84.51995700000001,39.085285],"type":"Point"}
}