{
  "type": "Feature",
  "properties": {
    "addr:full":"301 N Hurstbourne Pkwy Louisville KY 40222",
    "addr:housenumber":"301",
    "addr:postcode":"40222",
    "addr:street":"N Hurstbourne Pkwy",
    "iso:country":"US",
    "sg:address":"301 N Hurstbourne Pkwy",
    "sg:city":"Louisville",
    "sg:classifiers":[
        {
            "category":"Utilities",
            "subcategory":"Natural Gas",
            "type":"Services"
        }
    ],
    "sg:phone":"+1 502 425 6741",
    "sg:postcode":"40222",
    "sg:province":"KY",
    "wof:name":"Texas Gas Transmission LLC",
    "wof:placetype":"venue"
},
  "geometry": {"coordinates":[-85.577755,38.248376],"type":"Point"}
}