{
  "type": "Feature",
  "properties": {
    "addr:full":"1461 Campbellsville Rd Hodgenville KY 42748",
    "addr:housenumber":"1461",
    "addr:postcode":"42748",
    "addr:street":"Campbellsville Rd",
    "iso:country":"US",
    "sg:address":"1461 Campbellsville Rd",
    "sg:city":"Hodgenville",
    "sg:classifiers":[
        {
            "category":"Retail",
            "subcategory":"Auto Rental",
            "type":"Services"
        }
    ],
    "sg:phone":"+1 270 358 3531",
    "sg:postcode":"42748",
    "sg:province":"KY",
    "sg:tags":[
        "renting",
        "truck",
        "leasing"
    ],
    "wof:name":"U-Haul Co",
    "wof:placetype":"venue"
},
  "geometry": {"coordinates":[-85.72057100000001,37.560637],"type":"Point"}
}