{
  "type": "Feature",
  "properties": {
    "addr:full":"5800 Fern Valley Rd Louisville KY 40219",
    "addr:housenumber":"5800",
    "addr:postcode":"40219",
    "addr:street":"Fern Valley Rd",
    "iso:country":"US",
    "sg:address":"5800 Fern Valley Rd",
    "sg:city":"Louisville",
    "sg:classifiers":[
        {
            "category":"Government",
            "subcategory":"Office",
            "type":"Public Place"
        }
    ],
    "sg:phone":"+1 502 966 8111",
    "sg:postcode":"40219",
    "sg:province":"KY",
    "sg:tags":[
        "program",
        "administrative"
    ],
    "wof:name":"Health Service Agency",
    "wof:placetype":"venue"
},
  "geometry": {"coordinates":[-85.65785200000001,38.156056],"type":"Point"}
}