{
  "type": "Feature",
  "properties": {
    "addr:full":"16846 State Hwy 45 S Water Valley KY 42085",
    "addr:housenumber":"16846",
    "addr:postcode":"42085",
    "addr:street":"State Hwy 45 S Water",
    "iso:country":"US",
    "sg:address":"16846 State Hwy 45 S",
    "sg:city":"Water Valley",
    "sg:classifiers":[
        {
            "category":"Government",
            "subcategory":"Post Office",
            "type":"Public Place"
        }
    ],
    "sg:phone":"+1 270 355 2355",
    "sg:postcode":"42085",
    "sg:province":"KY",
    "wof:name":"US Post Office",
    "wof:placetype":"venue"
},
  "geometry": {"coordinates":[-88.81204099999999,36.564456],"type":"Point"}
}