{
  "type": "Feature",
  "properties": {
    "addr:full":"231 Breckenridge Ln St Matthews KY 40207",
    "addr:housenumber":"231",
    "addr:postcode":"40207",
    "addr:street":"Breckenridge Ln",
    "iso:country":"US",
    "sg:address":"231 Breckenridge Ln",
    "sg:city":"St Matthews",
    "sg:classifiers":[
        {
            "category":"Banks & Credit Unions",
            "subcategory":"Bank",
            "type":"Services"
        }
    ],
    "sg:phone":"+1 502 896 2616",
    "sg:postcode":"40207",
    "sg:province":"KY",
    "sg:tags":[
        "loan",
        "real estate"
    ],
    "wof:name":"Borrowers Choice Mortgage",
    "wof:placetype":"venue"
},
  "geometry": {"coordinates":[-85.652428,38.249516],"type":"Point"}
}