{
  "type": "Feature",
  "properties": {
    "iso:country":"US",
    "sg:address":"1708 Gardiner Ln",
    "sg:city":"Louisville",
    "sg:classifiers":[
        {
            "category":"Professional",
            "subcategory":"Detective & Security Services",
            "type":"Services"
        }
    ],
    "sg:phone":"+1 502 473 8703",
    "sg:postcode":"40205",
    "sg:province":"KY",
    "sg:tags":[
        "private",
        "investigator"
    ],
    "wof:name":"Brewer & Martin Investigative",
    "wof:placetype":"venue"
},
  "geometry": {"coordinates":[-85.68764299999999,38.204262],"type":"Point"}
}