{
  "type": "Feature",
  "properties": {
    "iso:country":"US",
    "sg:address":"810 Morton Ave",
    "sg:city":"Bardstown",
    "sg:classifiers":[
        {
            "category":"Shopping",
            "subcategory":"Computers & Home Electronics",
            "type":"Retail Goods"
        }
    ],
    "sg:phone":"+1 502 348 5520",
    "sg:postcode":"40004",
    "sg:province":"KY",
    "sg:tags":[
        "equipment",
        "dealer"
    ],
    "wof:name":"Central Kentucky Internet Svc",
    "wof:placetype":"venue"
},
  "geometry": {"coordinates":[-85.47423000000001,37.827318],"type":"Point"}
}