{
  "type": "Feature",
  "properties": {
    "addr:full":"121 N 21st St Louisville KY 40203",
    "addr:housenumber":"121",
    "addr:postcode":"40203",
    "addr:street":"N 21St St",
    "iso:country":"US",
    "sg:address":"121 N 21st St",
    "sg:city":"Louisville",
    "sg:classifiers":[
        {
            "category":"Social Services",
            "subcategory":"Child Care",
            "type":"Services"
        }
    ],
    "sg:phone":"+1 502 774 2402",
    "sg:postcode":"40203",
    "sg:province":"KY",
    "wof:name":"Shy's Place",
    "wof:placetype":"venue"
},
  "geometry": {"coordinates":[-85.784356,38.260999],"type":"Point"}
}