{
  "type": "Feature",
  "properties": {
    "addr:full":"236 S L Rogers Wells Blvd Glasgow KY 42141",
    "addr:housenumber":"236",
    "addr:postcode":"42141",
    "addr:street":"S L;Wells Blvd",
    "iso:country":"US",
    "sg:address":"236 S L Rogers Wells Blvd",
    "sg:city":"Glasgow",
    "sg:classifiers":[
        {
            "category":"Retail",
            "subcategory":"Auto Repair",
            "type":"Services"
        }
    ],
    "sg:phone":"+1 270 659 9966",
    "sg:postcode":"42141",
    "sg:province":"KY",
    "sg:tags":[
        "automobile",
        "lubrication"
    ],
    "wof:name":"Highland Express Lube",
    "wof:placetype":"venue"
},
  "geometry": {"coordinates":[-85.928507,36.998166],"type":"Point"}
}