{
  "type": "Feature",
  "properties": {
    "iso:country":"US",
    "sg:address":"216 N Hurstbourne Pkwy",
    "sg:city":"Louisville",
    "sg:classifiers":[
        {
            "category":"Deli",
            "type":"Food & Drink"
        }
    ],
    "sg:menulink":"http://www.allmenus.com/ky/jefferson-northeast/60685-dooleys-bagels--deli/menu/",
    "sg:phone":"+1 502 394 0021",
    "sg:postcode":"40222",
    "sg:province":"KY",
    "sg:tags":[
        "american"
    ],
    "wof:name":"Dooley's Bagels & Deli",
    "wof:placetype":"venue"
},
  "geometry": {"coordinates":[-85.578119,38.249125],"type":"Point"}
}