{
  "type": "Feature",
  "properties": {
    "iso:country":"US",
    "sg:address":"75 N Main St",
    "sg:city":"Walton",
    "sg:classifiers":[
        {
            "category":"Health Services",
            "subcategory":"Doctor",
            "type":"Services"
        }
    ],
    "sg:phone":"+1 859 485 4095",
    "sg:postcode":"41094",
    "sg:province":"KY",
    "sg:tags":[
        "dentist"
    ],
    "wof:name":"Huey Dental Assoc",
    "wof:placetype":"venue"
},
  "geometry": {"coordinates":[-84.612798,38.868749],"type":"Point"}
}