{
  "type": "Feature",
  "properties": {
    "addr:full":"1654 Thompson Dr Owensboro KY 42301",
    "addr:housenumber":"1654",
    "addr:postcode":"42301",
    "addr:street":"Thompson Dr",
    "iso:country":"US",
    "sg:address":"1654 Thompson Dr",
    "sg:city":"Owensboro",
    "sg:classifiers":[
        {
            "category":"Health Services",
            "subcategory":"Doctor",
            "type":"Services"
        }
    ],
    "sg:phone":"+1 270 686 7907",
    "sg:postcode":"42301",
    "sg:province":"KY",
    "sg:tags":[
        "physician",
        "surgeon"
    ],
    "wof:name":"River Valley Behavioral Health",
    "wof:placetype":"venue"
},
  "geometry": {"coordinates":[-87.15237999999999,37.75297],"type":"Point"}
}