{
  "type": "Feature",
  "properties": {
    "addr:full":"1750 Scottsville Rd Bowling Green KY 42104",
    "addr:housenumber":"1750",
    "addr:postcode":"42104",
    "addr:street":"Scottsville Rd",
    "iso:country":"US",
    "sg:address":"1750 Scottsville Rd",
    "sg:city":"Bowling Green",
    "sg:classifiers":[
        {
            "category":"Insurance",
            "subcategory":"Insurance Agent",
            "type":"Services"
        }
    ],
    "sg:phone":"+1 270 781 6200",
    "sg:postcode":"42104",
    "sg:province":"KY",
    "sg:website":"www.centerofinsurance.com",
    "wof:name":"Center Of Insurance Inc",
    "wof:placetype":"venue"
},
  "geometry": {"coordinates":[-86.43304500000001,36.968008],"type":"Point"}
}