{
  "type": "Feature",
  "properties": {
    "addr:full":"36 Bassett Ave Madisonville KY 42431",
    "addr:housenumber":"36",
    "addr:postcode":"42431",
    "addr:street":"Bassett Ave",
    "iso:country":"US",
    "sg:address":"36 Bassett Ave",
    "sg:city":"Madisonville",
    "sg:classifiers":[
        {
            "category":"Food & Beverages",
            "subcategory":"Liquor & Beverages",
            "type":"Retail Goods"
        }
    ],
    "sg:phone":"+1 270 821 5078",
    "sg:postcode":"42431",
    "sg:province":"KY",
    "wof:name":"Father & Son's Liquors",
    "wof:placetype":"venue"
},
  "geometry": {"coordinates":[-87.484077,37.328658],"type":"Point"}
}