{
  "type": "Feature",
  "properties": {
    "addr:full":"620 Robinson Creek Rd London KY 40744",
    "addr:housenumber":"620",
    "addr:postcode":"40744",
    "addr:street":"Robinson Creek Rd",
    "iso:country":"US",
    "sg:address":"620 Robinson Creek Rd",
    "sg:city":"London",
    "sg:classifiers":[
        {
            "category":"Professional",
            "subcategory":"Art Services",
            "type":"Services"
        }
    ],
    "sg:phone":"+1 606 877 9444",
    "sg:postcode":"40744",
    "sg:province":"KY",
    "sg:tags":[
        "graphic",
        "designer"
    ],
    "wof:name":"Miller House Of London",
    "wof:placetype":"venue"
},
  "geometry": {"coordinates":[-83.963194,37.012556],"type":"Point"}
}