{
  "type": "Feature",
  "properties": {
    "addr:full":"203 W Columbia St Somerset KY 42501",
    "addr:housenumber":"203",
    "addr:postcode":"42501",
    "addr:street":"W Columbia St",
    "iso:country":"US",
    "sg:address":"203 W Columbia St",
    "sg:city":"Somerset",
    "sg:classifiers":[
        {
            "category":"Professional",
            "subcategory":"Lawyer & Legal Services",
            "type":"Services"
        }
    ],
    "sg:phone":"+1 606 679 2214",
    "sg:postcode":"42501",
    "sg:province":"KY",
    "sg:tags":[
        "attorney"
    ],
    "wof:name":"Richard W Hay Law Office",
    "wof:placetype":"venue"
},
  "geometry": {"coordinates":[-84.606391,37.092376],"type":"Point"}
}