{
  "type": "Feature",
  "properties": {
    "iso:country":"US",
    "sg:address":"Treme At Orleans",
    "sg:city":"Florence",
    "sg:classifiers":[
        {
            "category":"Building & Trades",
            "subcategory":"Construction",
            "type":"Services"
        }
    ],
    "sg:phone":"+1 859 384 0700",
    "sg:postcode":"41042",
    "sg:province":"KY",
    "sg:tags":[
        "contractor"
    ],
    "wof:name":"Maple Street Homes",
    "wof:placetype":"venue"
},
  "geometry": {"coordinates":[-84.65389999999999,38.9879],"type":"Point"}
}