{
  "type": "Feature",
  "properties": {
    "addr:full":"1632 Kentucky Ave Paducah KY 42003",
    "addr:housenumber":"1632",
    "addr:postcode":"42003",
    "addr:street":"Kentucky Ave",
    "iso:country":"US",
    "sg:address":"1632 Kentucky Ave",
    "sg:city":"Paducah",
    "sg:classifiers":[
        {
            "category":"Manufacturing",
            "subcategory":"Tools & Machinery",
            "type":"Manufacturing & Wholesale Goods"
        }
    ],
    "sg:phone":"+1 270 443 9110",
    "sg:postcode":"42003",
    "sg:province":"KY",
    "sg:tags":[
        "computer",
        "maintenance",
        "sales",
        "related",
        "mfg"
    ],
    "wof:name":"H N Bull Information Systems",
    "wof:placetype":"venue"
},
  "geometry": {"coordinates":[-88.615538,37.078318],"type":"Point"}
}