{
  "type": "Feature",
  "properties": {
    "iso:country":"US",
    "sg:address":"9935 West St",
    "sg:city":"Whitesville",
    "sg:classifiers":[
        {
            "category":"Shopping",
            "subcategory":"Department Store",
            "type":"Retail Goods"
        }
    ],
    "sg:phone":"+1 270 233 1711",
    "sg:postcode":"42378",
    "sg:province":"KY",
    "sg:tags":[
        "shop"
    ],
    "wof:name":"Dollar General",
    "wof:placetype":"venue"
},
  "geometry": {"coordinates":[-86.874757,37.683389],"type":"Point"}
}