{
  "type": "Feature",
  "properties": {
    "iso:country":"US",
    "sg:address":"2217 Goldsmith Ln",
    "sg:city":"Louisville",
    "sg:classifiers":[
        {
            "category":"Sports & Exercise",
            "subcategory":"Bowling",
            "type":"Entertainment"
        },
        {
            "category":"Shopping",
            "subcategory":"Party Supplies",
            "type":"Retail Goods"
        },
        {
            "category":"Bars & Pubs",
            "type":"Food & Drink"
        },
        {
            "category":"Sports & Exercise",
            "subcategory":"Sports Center",
            "type":"Entertainment"
        },
        {
            "category":"Personal",
            "type":"Services"
        },
        {
            "category":"Recreation",
            "subcategory":"Picnic Area",
            "type":"Entertainment"
        }
    ],
    "sg:phone":"+1 502 451 5717",
    "sg:postcode":"40218",
    "sg:province":"KY",
    "sg:tags":[
        "arcade",
        "children's",
        "planning",
        "place",
        "event",
        "amusement"
    ],
    "sg:website":"http://www.amf.com",
    "wof:name":"AMF Rose Bowl Lanes",
    "wof:placetype":"venue"
},
  "geometry": {"coordinates":[-85.668899,38.208455],"type":"Point"}
}