{
  "type": "Feature",
  "properties": {
    "addr:full":"1575 McCauley Rd Wilmore KY 40390",
    "addr:housenumber":"1575",
    "addr:postcode":"40390",
    "addr:street":"Mccauley Rd",
    "iso:country":"US",
    "sg:address":"1575 McCauley Rd",
    "sg:city":"Wilmore",
    "sg:classifiers":[
        {
            "category":"Farming",
            "subcategory":"Livestock Farm",
            "type":"Manufacturing & Wholesale Goods"
        }
    ],
    "sg:phone":"+1 859 858 3955",
    "sg:postcode":"40390",
    "sg:province":"KY",
    "sg:tags":[
        "beef",
        "feedlot",
        "cattle"
    ],
    "wof:name":"Lena Wade",
    "wof:placetype":"venue"
},
  "geometry": {"coordinates":[-84.672775,37.906029],"type":"Point"}
}