{
  "type": "Feature",
  "properties": {
    "iso:country":"US",
    "sg:address":"2943 Eastern Ave",
    "sg:city":"Cincinnati",
    "sg:classifiers":[
        {
            "category":"Communications",
            "subcategory":"Film & Video Production",
            "type":"Services"
        }
    ],
    "sg:phone":"+1 513 871 1932",
    "sg:postcode":"45226",
    "sg:province":"OH",
    "sg:tags":[
        "audio"
    ],
    "sg:website":"www.northsidefilms.com",
    "wof:name":"Northside Films & Co",
    "wof:placetype":"venue"
},
  "geometry": {"coordinates":[-84.448342,39.120683],"type":"Point"}
}