{
  "type": "Feature",
  "properties": {
    "addr:full":"115 Jackson St Mc Kee KY 40403",
    "addr:housenumber":"115",
    "addr:postcode":"40403",
    "addr:street":"Jackson St Mc Kee",
    "iso:country":"US",
    "sg:address":"115 Jackson St",
    "sg:city":"Mc Kee",
    "sg:classifiers":[
        {
            "category":"Organizations",
            "subcategory":"Non-profit Organization",
            "type":"Services"
        }
    ],
    "sg:phone":"+1 606 364 1000",
    "sg:postcode":"40403",
    "sg:province":"KY",
    "wof:name":"Jackson Energy Cooperative",
    "wof:placetype":"venue"
},
  "geometry": {"coordinates":[-84.286759,37.572657],"type":"Point"}
}