{
  "type": "Feature",
  "properties": {
    "addr:full":"139 Russellville Gallatin Rd Franklin KY 42134",
    "addr:housenumber":"139",
    "addr:postcode":"42134",
    "addr:street":"Gallatin Rd",
    "iso:country":"US",
    "sg:address":"139 Russellville Gallatin Rd",
    "sg:city":"Franklin",
    "sg:classifiers":[
        {
            "category":"Real Estate",
            "subcategory":"Real Estate Operator",
            "type":"Services"
        }
    ],
    "sg:phone":"+1 270 586 5613",
    "sg:postcode":"42134",
    "sg:province":"KY",
    "sg:tags":[
        "property",
        "lessor"
    ],
    "wof:name":"Scrub Farms",
    "wof:placetype":"venue"
},
  "geometry": {"coordinates":[-86.668457,36.699232],"type":"Point"}
}