{
  "type": "Feature",
  "properties": {
    "iso:country":"US",
    "sg:address":"131 S 4th St",
    "sg:city":"Murray",
    "sg:classifiers":[
        {
            "category":"Personal",
            "subcategory":"Tanning Parlor",
            "type":"Services"
        }
    ],
    "sg:phone":"+1 270 334 3918",
    "sg:postcode":"42071",
    "sg:province":"KY",
    "sg:tags":[
        "salon"
    ],
    "wof:name":"Sun Sational",
    "wof:placetype":"venue"
},
  "geometry": {"coordinates":[-88.30202300000001,36.610367],"type":"Point"}
}