{
  "type": "Feature",
  "properties": {
    "iso:country":"US",
    "sg:address":"4055 Millshed Rd",
    "sg:city":"Morgantown",
    "sg:phone":"+1 270 526 4996",
    "sg:postcode":"42261",
    "sg:province":"KY",
    "sg:tags":[
        "farm",
        "corn",
        "soybean"
    ],
    "wof:name":"Robert Fields",
    "wof:placetype":"venue"
},
  "geometry": {"coordinates":[-86.54848,37.245774],"type":"Point"}
}