{
  "type": "Feature",
  "properties": {
    "iso:country":"US",
    "sg:address":"410 W Chestnut St",
    "sg:city":"Louisville",
    "sg:classifiers":[
        {
            "category":"Professional",
            "type":"Services"
        }
    ],
    "sg:phone":"+1 502 581 1961",
    "sg:postcode":"40202",
    "sg:province":"KY",
    "sg:tags":[
        "mediation"
    ],
    "sg:website":"http://www.just-solutions.org",
    "wof:name":"Just Solutions",
    "wof:placetype":"venue"
},
  "geometry": {"coordinates":[-85.75805,38.248959],"type":"Point"}
}