{
  "type": "Feature",
  "properties": {
    "iso:country":"US",
    "sg:address":"301 S Green St",
    "sg:city":"Henderson",
    "sg:classifiers":[
        {
            "category":"Professional",
            "subcategory":"Accounting & Tax Preparation",
            "type":"Services"
        }
    ],
    "sg:phone":"+1 270 827 3966",
    "sg:postcode":"42420",
    "sg:province":"KY",
    "sg:tags":[
        "return",
        "filing"
    ],
    "wof:name":"Dumas Tax Svc",
    "wof:placetype":"venue"
},
  "geometry": {"coordinates":[-87.593058,37.834002],"type":"Point"}
}