{
  "type": "Feature",
  "properties": {
    "addr:full":"7425 W Orchard Grass Blvd Crestwood KY 40014",
    "addr:housenumber":"7425",
    "addr:postcode":"40014",
    "addr:street":"W Orchard Grass Blvd",
    "iso:country":"US",
    "sg:address":"7425 W Orchard Grass Blvd",
    "sg:city":"Crestwood",
    "sg:classifiers":[
        {
            "category":"Health Services",
            "subcategory":"Health Practitioner",
            "type":"Services"
        }
    ],
    "sg:phone":"+1 502 241 7224",
    "sg:postcode":"40014",
    "sg:province":"KY",
    "wof:name":"Mary Beth Herberg PSC",
    "wof:placetype":"venue"
},
  "geometry": {"coordinates":[-85.52193,38.32642],"type":"Point"}
}