{
  "type": "Feature",
  "properties": {
    "iso:country":"US",
    "sg:address":"757 Bellefonte Rd",
    "sg:city":"Flatwoods",
    "sg:classifiers":[
        {
            "category":"Autos & Motor Vehicles",
            "subcategory":"Fuel & Gas Station",
            "type":"Retail Goods"
        }
    ],
    "sg:phone":"+1 606 836 8209",
    "sg:postcode":"41139",
    "sg:province":"KY",
    "sg:tags":[
        "oil"
    ],
    "wof:name":"Doty's Shell Mart",
    "wof:placetype":"venue"
},
  "geometry": {"coordinates":[-82.717794,38.512961],"type":"Point"}
}