{
  "type": "Feature",
  "properties": {
    "addr:full":"2151 Scottsville Rd Bowling Green KY 42104",
    "addr:housenumber":"2151",
    "addr:postcode":"42104",
    "addr:street":"Scottsville Rd",
    "iso:country":"US",
    "sg:address":"2151 Scottsville Rd",
    "sg:city":"Bowling Green",
    "sg:classifiers":[
        {
            "category":"Autos & Motor Vehicles",
            "subcategory":"Automobile Sales",
            "type":"Retail Goods"
        }
    ],
    "sg:phone":"+1 270 781 7000",
    "sg:postcode":"42104",
    "sg:province":"KY",
    "sg:tags":[
        "car",
        "dealer"
    ],
    "sg:website":"www.campbellchevrolet.com",
    "wof:name":"Campbell Chevrolet",
    "wof:placetype":"venue"
},
  "geometry": {"coordinates":[-86.42961099999999,36.96001],"type":"Point"}
}