{
  "type": "Feature",
  "properties": {
    "iso:country":"US",
    "sg:address":"14122 Shelbyville Rd",
    "sg:city":"Louisville",
    "sg:classifiers":[
        {
            "category":"Education",
            "subcategory":"Music School",
            "type":"Public Place"
        }
    ],
    "sg:phone":"+1 502 253 1493",
    "sg:postcode":"40245",
    "sg:province":"KY",
    "sg:tags":[
        "instruction-instrumental"
    ],
    "wof:name":"Tiemann Academy Of Music",
    "wof:placetype":"venue"
},
  "geometry": {"coordinates":[-85.48782199999999,38.238353],"type":"Point"}
}