{
  "type": "Feature",
  "properties": {
    "addr:full":"4004 Houston Antioch Rd Lexington KY 40516",
    "addr:housenumber":"4004",
    "addr:postcode":"40516",
    "addr:street":"Houston Antioch Rd",
    "iso:country":"US",
    "sg:address":"4004 Houston Antioch Rd",
    "sg:city":"Lexington",
    "sg:classifiers":[
        {
            "category":"Building & Trades",
            "subcategory":"Construction",
            "type":"Services"
        }
    ],
    "sg:phone":"+1 859 299 3226",
    "sg:postcode":"40516",
    "sg:province":"KY",
    "sg:tags":[
        "residential",
        "commercial",
        "contracting"
    ],
    "wof:name":"Bever Contracting",
    "wof:placetype":"venue"
},
  "geometry": {"coordinates":[-84.34232299999999,38.104561],"type":"Point"}
}