{
  "type": "Feature",
  "properties": {
    "addr:full":"2025 Clore Jackson Rd Shelbyville KY 40065",
    "addr:housenumber":"2025",
    "addr:postcode":"40065",
    "addr:street":"Clore Jackson Rd",
    "iso:country":"US",
    "sg:address":"2025 Clore Jackson Rd",
    "sg:city":"Shelbyville",
    "sg:classifiers":[
        {
            "category":"Wholesale",
            "subcategory":"Meat",
            "type":"Manufacturing & Wholesale Goods"
        }
    ],
    "sg:phone":"+1 502 633 5476",
    "sg:postcode":"40065",
    "sg:province":"KY",
    "sg:tags":[
        "prod",
        "prepared"
    ],
    "wof:name":"Millstone Place Inc",
    "wof:placetype":"venue"
},
  "geometry": {"coordinates":[-85.233807,38.32264],"type":"Point"}
}