{
  "type": "Feature",
  "properties": {
    "iso:country":"US",
    "sg:address":"533 N 22nd St",
    "sg:city":"Louisville",
    "sg:classifiers":[
        {
            "category":"Restaurant",
            "type":"Food & Drink"
        }
    ],
    "sg:menulink":"http://www.allmenus.com/ky/louisville-west/89089-subway/menu/",
    "sg:phone":"+1 502 775 6070",
    "sg:postcode":"40203",
    "sg:province":"KY",
    "sg:tags":[
        "american",
        "sandwich"
    ],
    "wof:name":"Subway",
    "wof:placetype":"venue"
},
  "geometry": {"coordinates":[-85.783034,38.26749],"type":"Point"}
}