{
  "type": "Feature",
  "properties": {
    "addr:full":"743 W Main St Morehead KY 40351",
    "addr:housenumber":"743",
    "addr:postcode":"40351",
    "addr:street":"W Main St",
    "iso:country":"US",
    "sg:address":"743 W Main St",
    "sg:city":"Morehead",
    "sg:classifiers":[
        {
            "category":"Organizations",
            "subcategory":"Religious Organization",
            "type":"Services"
        }
    ],
    "sg:phone":"+1 606 780 1291",
    "sg:postcode":"40351",
    "sg:province":"KY",
    "sg:tags":[
        "church"
    ],
    "wof:name":"Grace Fellowship",
    "wof:placetype":"venue"
},
  "geometry": {"coordinates":[-83.440184,38.173634],"type":"Point"}
}