{
  "type": "Feature",
  "properties": {
    "iso:country":"US",
    "sg:address":"5555 US Hwy 460",
    "sg:city":"Staffordsville",
    "sg:classifiers":[
        {
            "category":"Freight",
            "type":"Transportation"
        }
    ],
    "sg:phone":"+1 606 297 1765",
    "sg:postcode":"41256",
    "sg:province":"KY",
    "sg:tags":[
        "hauling",
        "trucking"
    ],
    "wof:name":"Kenneth R Brown Trucking",
    "wof:placetype":"venue"
},
  "geometry": {"coordinates":[-82.891211,37.805229],"type":"Point"}
}