{
  "type": "Feature",
  "properties": {
    "addr:full":"123 W Seminary St Owenton KY 40359",
    "addr:housenumber":"123",
    "addr:postcode":"40359",
    "addr:street":"W Seminary St",
    "iso:country":"US",
    "sg:address":"123 W Seminary St",
    "sg:city":"Owenton",
    "sg:classifiers":[
        {
            "category":"Home & Garden",
            "subcategory":"Hardware",
            "type":"Retail Goods"
        }
    ],
    "sg:phone":"+1 502 484 3327",
    "sg:postcode":"40359",
    "sg:province":"KY",
    "wof:name":"Minch Hardware & Appliance Co",
    "wof:placetype":"venue"
},
  "geometry": {"coordinates":[-84.83619299999999,38.535849],"type":"Point"}
}