{
  "type": "Feature",
  "properties": {
    "addr:full":"931 Kentucky Ave Kevil KY 42053",
    "addr:housenumber":"931",
    "addr:postcode":"42053",
    "addr:street":"Kentucky Ave",
    "iso:country":"US",
    "sg:address":"931 Kentucky Ave",
    "sg:city":"Kevil",
    "sg:classifiers":[
        {
            "category":"Building & Trades",
            "subcategory":"Electrical",
            "type":"Services"
        }
    ],
    "sg:phone":"+1 270 462 2003",
    "sg:postcode":"42053",
    "sg:province":"KY",
    "sg:tags":[
        "electric",
        "contractor"
    ],
    "wof:name":"D Ci Electric",
    "wof:placetype":"venue"
},
  "geometry": {"coordinates":[-88.86923,37.076764],"type":"Point"}
}