{
  "type": "Feature",
  "properties": {
    "iso:country":"US",
    "sg:address":"4615 Bittersweet Rd",
    "sg:city":"Louisville",
    "sg:classifiers":[
        {
            "category":"Building & Trades",
            "subcategory":"Plumbing",
            "type":"Services"
        }
    ],
    "sg:phone":"+1 502 969 8100",
    "sg:postcode":"40218",
    "sg:province":"KY",
    "sg:tags":[
        "contractor",
        "heating",
        "mechanical"
    ],
    "sg:website":"http://scarboroughmechanical.com",
    "wof:name":"Scarborough Mechanical Service",
    "wof:placetype":"venue"
},
  "geometry": {"coordinates":[-85.690793,38.188286],"type":"Point"}
}