{
  "type": "Feature",
  "properties": {
    "addr:full":"4218 Saron Dr Lexington KY 40515",
    "addr:housenumber":"4218",
    "addr:postcode":"40515",
    "addr:street":"Saron Dr",
    "iso:country":"US",
    "sg:address":"4218 Saron Dr",
    "sg:city":"Lexington",
    "sg:classifiers":[
        {
            "category":"Fast Food",
            "type":"Food & Drink"
        },
        {
            "category":"Restaurant",
            "type":"Food & Drink"
        },
        {
            "category":"Food & Beverages",
            "subcategory":"Groceries & Convenience Stores",
            "type":"Retail Goods"
        }
    ],
    "sg:phone":"+1 859 271 8793",
    "sg:postcode":"40515",
    "sg:province":"KY",
    "sg:tags":[
        "shop",
        "american",
        "sandwich",
        "take"
    ],
    "sg:website":"http://www.subway.com",
    "wof:name":"Subway",
    "wof:placetype":"venue"
},
  "geometry": {"coordinates":[-84.502257,37.967197],"type":"Point"}
}