{
  "type": "Feature",
  "properties": {
    "iso:country":"US",
    "sg:address":"3240 Office Pointe Pl",
    "sg:city":"Louisville",
    "sg:classifiers":[
        {
            "category":"Insurance",
            "subcategory":"Insurance Agent",
            "type":"Services"
        }
    ],
    "sg:phone":"+1 502 495 2055",
    "sg:postcode":"40220",
    "sg:province":"KY",
    "sg:tags":[
        "processing"
    ],
    "wof:name":"Maximum Services",
    "wof:placetype":"venue"
},
  "geometry": {"coordinates":[-85.603611,38.201753],"type":"Point"}
}