{
  "type": "Feature",
  "properties": {
    "iso:country":"US",
    "sg:address":"106 W 5th St",
    "sg:city":"Owensboro",
    "sg:classifiers":[
        {
            "category":"Professional",
            "type":"Services"
        }
    ],
    "sg:phone":"+1 270 684 2144",
    "sg:postcode":"42303",
    "sg:province":"KY",
    "sg:tags":[
        "establishment"
    ],
    "wof:name":"Rath Orvy",
    "wof:placetype":"venue"
},
  "geometry": {"coordinates":[-87.112002,37.771473],"type":"Point"}
}