{
  "type": "Feature",
  "properties": {
    "iso:country":"US",
    "sg:address":"214 Edgewood Dr",
    "sg:city":"Nicholasville",
    "sg:classifiers":[
        {
            "category":"Real Estate",
            "subcategory":"Real Estate Agent",
            "type":"Services"
        }
    ],
    "sg:phone":"+1 859 885 1775",
    "sg:postcode":"40356",
    "sg:province":"KY",
    "wof:name":"Gooch & Co Real Estate & Auctn",
    "wof:placetype":"venue"
},
  "geometry": {"coordinates":[-84.579463,37.868449],"type":"Point"}
}