{
  "type": "Feature",
  "properties": {
    "addr:full":"414 Glenwood Dr Georgetown KY 40324",
    "addr:housenumber":"414",
    "addr:postcode":"40324",
    "addr:street":"Glenwood Dr",
    "iso:country":"US",
    "sg:address":"414 Glenwood Dr",
    "sg:city":"Georgetown",
    "sg:classifiers":[
        {
            "category":"Freight",
            "type":"Transportation"
        }
    ],
    "sg:phone":"+1 502 863 3690",
    "sg:postcode":"40324",
    "sg:province":"KY",
    "sg:tags":[
        "operator",
        "local",
        "trucking"
    ],
    "wof:name":"Ruth Trucking Inc",
    "wof:placetype":"venue"
},
  "geometry": {"coordinates":[-84.564688,38.179107],"type":"Point"}
}