{
  "type": "Feature",
  "properties": {
    "iso:country":"US",
    "sg:address":"595 Water Works Rd",
    "sg:city":"Nicholasville",
    "sg:classifiers":[
        {
            "category":"Government",
            "subcategory":"Office",
            "type":"Public Place"
        }
    ],
    "sg:phone":"+1 859 885 6974",
    "sg:postcode":"40356",
    "sg:province":"KY",
    "sg:tags":[
        "village"
    ],
    "wof:name":"Nicholasville Water Plant",
    "wof:placetype":"venue"
},
  "geometry": {"coordinates":[-84.48866700000001,37.840549],"type":"Point"}
}