{
  "type": "Feature",
  "properties": {
    "iso:country":"US",
    "sg:address":"2708 Sycamore Woods Ct",
    "sg:city":"Louisville",
    "sg:classifiers":[
        {
            "category":"Professional",
            "subcategory":"Business Services",
            "type":"Services"
        }
    ],
    "sg:phone":"+1 502 458 3940",
    "sg:postcode":"40241",
    "sg:province":"KY",
    "sg:tags":[
        "packaging"
    ],
    "wof:name":"Complete Package Inc",
    "wof:placetype":"venue"
},
  "geometry": {"coordinates":[-85.622,38.290326],"type":"Point"}
}