{
  "type": "Feature",
  "properties": {
    "iso:country":"US",
    "sg:address":"2491 Dixie Hwy",
    "sg:city":"Covington",
    "sg:classifiers":[
        {
            "category":"Manufacturing",
            "subcategory":"Printing",
            "type":"Manufacturing & Wholesale Goods"
        }
    ],
    "sg:phone":"+1 859 341 4774",
    "sg:postcode":"41017",
    "sg:province":"KY",
    "sg:tags":[
        "commercial"
    ],
    "wof:name":"Klein Printing",
    "wof:placetype":"venue"
},
  "geometry": {"coordinates":[-84.559932,39.036962],"type":"Point"}
}