{
  "type": "Feature",
  "properties": {
    "addr:full":"703 Park Ave Newport KY 41071",
    "addr:housenumber":"703",
    "addr:postcode":"41071",
    "addr:street":"Park Ave",
    "iso:country":"US",
    "sg:address":"703 Park Ave",
    "sg:city":"Newport",
    "sg:classifiers":[
        {
            "category":"Shopping",
            "subcategory":"Used Merchandise",
            "type":"Retail Goods"
        }
    ],
    "sg:phone":"+1 859 581 9100",
    "sg:postcode":"41071",
    "sg:province":"KY",
    "sg:tags":[
        "book",
        "rare",
        "dealer"
    ],
    "wof:name":"Collector Book & Print Gallery",
    "wof:placetype":"venue"
},
  "geometry": {"coordinates":[-84.485899,39.092535],"type":"Point"}
}