{
  "type": "Feature",
  "properties": {
    "iso:country":"US",
    "sg:address":"1776 State Hwy 121 S",
    "sg:city":"Mayfield",
    "sg:classifiers":[
        {
            "category":"Home & Garden",
            "subcategory":"Building Materials",
            "type":"Retail Goods"
        }
    ],
    "sg:phone":"+1 270 247 2364",
    "sg:postcode":"42066",
    "sg:province":"KY",
    "sg:tags":[
        "equipment",
        "electric",
        "supply"
    ],
    "wof:name":"Youngblood's True Value Home",
    "wof:placetype":"venue"
},
  "geometry": {"coordinates":[-88.62536,36.719139],"type":"Point"}
}