{
  "type": "Feature",
  "properties": {
    "addr:full":"3445 Pleasant Valley Rd Owensboro KY 42303",
    "addr:housenumber":"3445",
    "addr:postcode":"42303",
    "addr:street":"Pleasant Valley Rd",
    "iso:country":"US",
    "sg:address":"3445 Pleasant Valley Rd",
    "sg:city":"Owensboro",
    "sg:classifiers":[
        {
            "category":"Government",
            "subcategory":"Office",
            "type":"Public Place"
        }
    ],
    "sg:phone":"+1 270 685 0391",
    "sg:postcode":"42303",
    "sg:province":"KY",
    "sg:tags":[
        "sector",
        "regulation",
        "commercial"
    ],
    "wof:name":"Negotiators International",
    "wof:placetype":"venue"
},
  "geometry": {"coordinates":[-87.028875,37.763699],"type":"Point"}
}