{
  "type": "Feature",
  "properties": {
    "addr:full":"7125 Turfway Rd Florence KY 41042",
    "addr:housenumber":"7125",
    "addr:postcode":"41042",
    "addr:street":"Turfway Rd",
    "iso:country":"US",
    "sg:address":"7125 Turfway Rd",
    "sg:city":"Florence",
    "sg:classifiers":[
        {
            "category":"Shopping",
            "subcategory":"Computers & Home Electronics",
            "type":"Retail Goods"
        }
    ],
    "sg:phone":"+1 859 282 8222",
    "sg:postcode":"41042",
    "sg:province":"KY",
    "sg:tags":[
        "renting",
        "equipment",
        "leasing"
    ],
    "wof:name":"Uhr Rents",
    "wof:placetype":"venue"
},
  "geometry": {"coordinates":[-84.622424,39.006287],"type":"Point"}
}