{
  "type": "Feature",
  "properties": {
    "addr:full":"457 Summer Hill Dr Somerset KY 42503",
    "addr:housenumber":"457",
    "addr:postcode":"42503",
    "addr:street":"Summer Hill Dr",
    "iso:country":"US",
    "sg:address":"457 Summer Hill Dr",
    "sg:city":"Somerset",
    "sg:classifiers":[
        {
            "category":"Organizations",
            "subcategory":"Religious Organization",
            "type":"Services"
        }
    ],
    "sg:phone":"+1 606 678 7170",
    "sg:postcode":"42503",
    "sg:province":"KY",
    "sg:tags":[
        "clergy"
    ],
    "wof:name":"Michael Hammond",
    "wof:placetype":"venue"
},
  "geometry": {"coordinates":[-84.64041899999999,37.043771],"type":"Point"}
}