{
  "type": "Feature",
  "properties": {
    "iso:country":"US",
    "sg:address":"10765 US Hwy 431",
    "sg:city":"Utica",
    "sg:classifiers":[
        {
            "category":"Building & Trades",
            "subcategory":"Construction",
            "type":"Services"
        }
    ],
    "sg:phone":"+1 270 733 2203",
    "sg:postcode":"42376",
    "sg:province":"KY",
    "sg:tags":[
        "home",
        "builder"
    ],
    "wof:name":"Taylor Building Corp",
    "wof:placetype":"venue"
},
  "geometry": {"coordinates":[-87.10548300000001,37.604612],"type":"Point"}
}