{
  "type": "Feature",
  "properties": {
    "iso:country":"US",
    "sg:address":"180 Bold Venture Dr",
    "sg:city":"Danville",
    "sg:classifiers":[
        {
            "category":"Organizations",
            "subcategory":"Religious Organization",
            "type":"Services"
        }
    ],
    "sg:phone":"+1 859 236 9137",
    "sg:postcode":"40422",
    "sg:province":"KY",
    "sg:tags":[
        "church"
    ],
    "wof:name":"Grace Presbyterian",
    "wof:placetype":"venue"
},
  "geometry": {"coordinates":[-84.767112,37.660088],"type":"Point"}
}