{
  "type": "Feature",
  "properties": {
    "addr:full":"520 Hitchens Rd Grayson KY 41143",
    "addr:housenumber":"520",
    "addr:postcode":"41143",
    "addr:street":"Hitchens Rd",
    "iso:country":"US",
    "sg:address":"520 Hitchens Rd",
    "sg:city":"Grayson",
    "sg:classifiers":[
        {
            "category":"Recreation",
            "type":"Entertainment"
        }
    ],
    "sg:phone":"+1 606 474 2287",
    "sg:postcode":"41143",
    "sg:province":"KY",
    "sg:tags":[
        "instruction",
        "gymnastic"
    ],
    "wof:name":"Cheer & Tumble Studio Inc",
    "wof:placetype":"venue"
},
  "geometry": {"coordinates":[-82.930739,38.32413],"type":"Point"}
}