{
  "type": "Feature",
  "properties": {
    "iso:country":"US",
    "sg:address":"236 E Mount Vernon St",
    "sg:city":"Somerset",
    "sg:classifiers":[
        {
            "category":"Government",
            "subcategory":"Office",
            "type":"Public Place"
        }
    ],
    "sg:phone":"+1 606 677 4100",
    "sg:postcode":"42501",
    "sg:province":"KY",
    "wof:name":"Commonwealth's Attorney",
    "wof:placetype":"venue"
},
  "geometry": {"coordinates":[-84.602834,37.09243],"type":"Point"}
}