{
  "type": "Feature",
  "properties": {
    "addr:full":"8953 Sacra Dr Maceo KY 42355",
    "addr:postcode":"8953;42355",
    "addr:street":"Sacra Dr",
    "iso:country":"US",
    "sg:address":"8953 Sacra Dr",
    "sg:city":"Maceo",
    "sg:classifiers":[
        {
            "category":"Building & Trades",
            "subcategory":"Plumbing",
            "type":"Services"
        }
    ],
    "sg:phone":"+1 270 264 1077",
    "sg:postcode":"42355",
    "sg:province":"KY",
    "sg:tags":[
        "conditioning",
        "air",
        "system",
        "contractor"
    ],
    "wof:name":"White's Service Co",
    "wof:placetype":"venue"
},
  "geometry": {"coordinates":[-86.997696,37.859431],"type":"Point"}
}