{
  "type": "Feature",
  "properties": {
    "addr:full":"264 Saint Anthony Rd Utica KY 42376",
    "addr:housenumber":"264",
    "addr:postcode":"42376",
    "addr:street":"Saint Anthony Rd",
    "iso:country":"US",
    "sg:address":"264 Saint Anthony Rd",
    "sg:city":"Utica",
    "sg:classifiers":[
        {
            "category":"Organizations",
            "subcategory":"Religious Organization",
            "type":"Services"
        }
    ],
    "sg:phone":"+1 270 733 4341",
    "sg:postcode":"42376",
    "sg:province":"KY",
    "sg:tags":[
        "church"
    ],
    "wof:name":"St Anthony's Church",
    "wof:placetype":"venue"
},
  "geometry": {"coordinates":[-87.117728,37.642963],"type":"Point"}
}