{
  "type": "Feature",
  "properties": {
    "iso:country":"US",
    "sg:address":"2830 Lone Oak Rd",
    "sg:city":"Paducah",
    "sg:classifiers":[
        {
            "category":"Health Services",
            "subcategory":"Chiropractor",
            "type":"Services"
        }
    ],
    "sg:phone":"+1 270 554 2141",
    "sg:postcode":"42003",
    "sg:province":"KY",
    "wof:name":"Winters Chiropractic Office",
    "wof:placetype":"venue"
},
  "geometry": {"coordinates":[-88.660419,37.04026],"type":"Point"}
}