{
  "type": "Feature",
  "properties": {
    "iso:country":"US",
    "sg:address":"650 Owls Nest Rd",
    "sg:city":"Hyden",
    "sg:classifiers":[
        {
            "category":"Utilities",
            "subcategory":"Cable",
            "type":"Services"
        }
    ],
    "sg:phone":"+1 606 672 3479",
    "sg:postcode":"41749",
    "sg:province":"KY",
    "sg:tags":[
        "television"
    ],
    "wof:name":"Bowling Cable TV",
    "wof:placetype":"venue"
},
  "geometry": {"coordinates":[-83.369293,37.156448],"type":"Point"}
}