{
  "type": "Feature",
  "properties": {
    "iso:country":"US",
    "sg:address":"273 City Dam Rd",
    "sg:city":"Keavy",
    "sg:classifiers":[
        {
            "category":"Freight",
            "type":"Transportation"
        }
    ],
    "sg:phone":"+1 606 528 3182",
    "sg:postcode":"40737",
    "sg:province":"KY",
    "sg:tags":[
        "commercial",
        "storage"
    ],
    "wof:name":"Stor-E-Z",
    "wof:placetype":"venue"
},
  "geometry": {"coordinates":[-84.135425,36.984669],"type":"Point"}
}