{
  "type": "Feature",
  "properties": {
    "iso:country":"US",
    "sg:address":"2171 Airport Rd",
    "sg:city":"Owensboro",
    "sg:classifiers":[
        {
            "category":"Ferry",
            "type":"Transportation"
        }
    ],
    "sg:phone":"+1 270 688 9080",
    "sg:postcode":"42301",
    "sg:province":"KY",
    "sg:tags":[
        "boat"
    ],
    "wof:name":"Watts Brothers Cable Constr",
    "wof:placetype":"venue"
},
  "geometry": {"coordinates":[-87.161805,37.750464],"type":"Point"}
}