{
  "type": "Feature",
  "properties": {
    "iso:country":"US",
    "sg:address":"4115 E Indian Trl",
    "sg:city":"Louisville",
    "sg:phone":"+1 502 968 5611",
    "sg:postcode":"40213",
    "sg:province":"KY",
    "wof:name":"Hi-Tech Automotive Inc",
    "wof:placetype":"venue"
},
  "geometry": {"coordinates":[-85.68486799999999,38.17161],"type":"Point"}
}