{
  "type": "Feature",
  "properties": {
    "addr:full":"7464 Edmonton Rd Glasgow KY 42141",
    "addr:housenumber":"7464",
    "addr:postcode":"42141",
    "addr:street":"Edmonton Rd",
    "iso:country":"US",
    "sg:address":"7464 Edmonton Rd",
    "sg:city":"Glasgow",
    "sg:classifiers":[
        {
            "category":"Organizations",
            "subcategory":"Religious Organization",
            "type":"Services"
        }
    ],
    "sg:phone":"+1 270 678 3437",
    "sg:postcode":"42141",
    "sg:province":"KY",
    "sg:website":"www.slickrockchurch.org",
    "wof:name":"Slick Rock Church",
    "wof:placetype":"venue"
},
  "geometry": {"coordinates":[-85.78456199999999,37.015454],"type":"Point"}
}