{
  "type": "Feature",
  "properties": {
    "addr:full":"208 Sylvan Dr Bardstown KY 40004",
    "addr:housenumber":"208",
    "addr:postcode":"40004",
    "addr:street":"Sylvan Dr",
    "iso:country":"US",
    "sg:address":"208 Sylvan Dr",
    "sg:city":"Bardstown",
    "sg:classifiers":[
        {
            "category":"Professional",
            "subcategory":"Business Services",
            "type":"Services"
        }
    ],
    "sg:phone":"+1 502 349 6186",
    "sg:postcode":"40004",
    "sg:province":"KY",
    "wof:name":"Gnm Enterprises LLC",
    "wof:placetype":"venue"
},
  "geometry": {"coordinates":[-85.455865,37.81034],"type":"Point"}
}