{
  "type": "Feature",
  "properties": {
    "iso:country":"US",
    "sg:address":"8017 Catherine Ln",
    "sg:city":"Louisville",
    "sg:classifiers":[
        {
            "category":"Home & Garden",
            "subcategory":"Kitchen Supply",
            "type":"Retail Goods"
        }
    ],
    "sg:phone":"+1 502 339 4668",
    "sg:postcode":"40222",
    "sg:province":"KY",
    "sg:tags":[
        "equipment",
        "restaurant"
    ],
    "wof:name":"Escola Enterprises",
    "wof:placetype":"venue"
},
  "geometry": {"coordinates":[-85.60637699999999,38.258917],"type":"Point"}
}