{
  "type": "Feature",
  "properties": {
    "iso:country":"US",
    "sg:address":"1406 N 12th St",
    "sg:city":"Murray",
    "sg:classifiers":[
        {
            "category":"Professional",
            "subcategory":"Employment Agencies",
            "type":"Services"
        }
    ],
    "sg:phone":"+1 270 753 0017",
    "sg:postcode":"42071",
    "sg:province":"KY",
    "wof:name":"People Lease Inc",
    "wof:placetype":"venue"
},
  "geometry": {"coordinates":[-88.312725,36.62974],"type":"Point"}
}