{
  "type": "Feature",
  "properties": {
    "iso:country":"US",
    "sg:address":"275 Bell Hollow Rd",
    "sg:city":"Lebanon",
    "sg:classifiers":[
        {
            "category":"Retail",
            "subcategory":"Portrait Studio",
            "type":"Services"
        }
    ],
    "sg:phone":"+1 270 692 4717",
    "sg:postcode":"40033",
    "sg:province":"KY",
    "sg:tags":[
        "photographer"
    ],
    "wof:name":"Bramel's Photosource/Phtgrphy",
    "wof:placetype":"venue"
},
  "geometry": {"coordinates":[-85.321271,37.537775],"type":"Point"}
}