{
  "type": "Feature",
  "properties": {
    "iso:country":"US",
    "sg:address":"540 Noel Dr",
    "sg:city":"Hopkinsville",
    "sg:classifiers":[
        {
            "category":"Health Services",
            "subcategory":"Clinic",
            "type":"Services"
        }
    ],
    "sg:phone":"+1 270 885 7887",
    "sg:postcode":"42240",
    "sg:province":"KY",
    "sg:tags":[
        "home"
    ],
    "wof:name":"Gentiva Health Svc",
    "wof:placetype":"venue"
},
  "geometry": {"coordinates":[-87.516598,36.856363],"type":"Point"}
}