{
  "type": "Feature",
  "properties": {
    "iso:country":"US",
    "sg:address":"5235 Taylor Mill Rd",
    "sg:city":"Taylor Mill",
    "sg:classifiers":[
        {
            "category":"Education",
            "subcategory":"School",
            "type":"Public Place"
        }
    ],
    "sg:phone":"+1 859 431 9933",
    "sg:postcode":"41015",
    "sg:province":"KY",
    "wof:name":"Seventh Day Adventist School",
    "wof:placetype":"venue"
},
  "geometry": {"coordinates":[-84.49716600000001,39.015626],"type":"Point"}
}