{
  "type": "Feature",
  "properties": {
    "iso:country":"US",
    "sg:address":"200 N Main St",
    "sg:city":"Monticello",
    "sg:classifiers":[
        {
            "category":"Shopping",
            "subcategory":"Pharmacy",
            "type":"Retail Goods"
        }
    ],
    "sg:phone":"+1 606 348 9263",
    "sg:postcode":"42633",
    "sg:province":"KY",
    "wof:name":"F & H Drug Store",
    "wof:placetype":"venue"
},
  "geometry": {"coordinates":[-84.847753,36.831539],"type":"Point"}
}