{
  "type": "Feature",
  "properties": {
    "iso:country":"US",
    "sg:address":"544 W Broadway St",
    "sg:city":"Madisonville",
    "sg:classifiers":[
        {
            "category":"Building & Trades",
            "subcategory":"Cleaning & Sanitation",
            "type":"Services"
        }
    ],
    "sg:phone":"+1 270 821 8864",
    "sg:postcode":"42431",
    "sg:province":"KY",
    "sg:tags":[
        "butler",
        "maid"
    ],
    "wof:name":"D & E Maid Svc",
    "wof:placetype":"venue"
},
  "geometry": {"coordinates":[-87.513231,37.32713],"type":"Point"}
}