{
  "type": "Feature",
  "properties": {
    "iso:country":"US",
    "sg:address":"302 Bellefonte St",
    "sg:city":"Russell",
    "sg:classifiers":[
        {
            "category":"Insurance",
            "subcategory":"Insurance Agent",
            "type":"Services"
        }
    ],
    "sg:phone":"+1 606 836 4455",
    "sg:postcode":"41169",
    "sg:province":"KY",
    "sg:tags":[
        "accident"
    ],
    "wof:name":"Reneau Insurance Inc",
    "wof:placetype":"venue"
},
  "geometry": {"coordinates":[-82.69237099999999,38.529267],"type":"Point"}
}