{
  "type": "Feature",
  "properties": {
    "iso:country":"US",
    "sg:address":"500 Eastwood Ave",
    "sg:city":"Bowling Green",
    "sg:classifiers":[
        {
            "category":"Organizations",
            "subcategory":"Religious Organization",
            "type":"Services"
        }
    ],
    "sg:phone":"+1 270 842 7867",
    "sg:postcode":"42103",
    "sg:province":"KY",
    "sg:tags":[
        "church"
    ],
    "sg:website":"www.eastwoodbc.org",
    "wof:name":"Eastwood Baptist Church",
    "wof:placetype":"venue"
},
  "geometry": {"coordinates":[-86.421853,36.988378],"type":"Point"}
}