{
  "type": "Feature",
  "properties": {
    "iso:country":"US",
    "sg:address":"950 Breckenridge Ln",
    "sg:city":"Louisville",
    "sg:classifiers":[
        {
            "category":"Health Services",
            "subcategory":"Doctor",
            "type":"Services"
        },
        {
            "category":"Shopping",
            "subcategory":"Pharmacy",
            "type":"Retail Goods"
        }
    ],
    "sg:phone":"+1 502 708 2940",
    "sg:postcode":"40207",
    "sg:province":"KY",
    "sg:tags":[
        "physician",
        "educational",
        "supply",
        "endocrinology",
        "support",
        "surgeons",
        "equipment",
        "diabetes",
        "home",
        "surgeon",
        "referral",
        "metabolism",
        "care"
    ],
    "wof:name":"Diabetes Control Center",
    "wof:placetype":"venue"
},
  "geometry": {"coordinates":[-85.640778,38.234901],"type":"Point"}
}