{
  "type": "Feature",
  "properties": {
    "iso:country":"US",
    "sg:address":"2341 Anton Rd",
    "sg:city":"Madisonville",
    "sg:classifiers":[
        {
            "category":"Autos & Motor Vehicles",
            "subcategory":"Automobile Sales",
            "type":"Retail Goods"
        }
    ],
    "sg:phone":"+1 270 824 9005",
    "sg:postcode":"42431",
    "sg:province":"KY",
    "sg:tags":[
        "car",
        "dealer"
    ],
    "wof:name":"Eastview Motors",
    "wof:placetype":"venue"
},
  "geometry": {"coordinates":[-87.455155,37.325832],"type":"Point"}
}