{
  "type": "Feature",
  "properties": {
    "iso:country":"US",
    "sg:address":"1524 Banklick St",
    "sg:city":"Covington",
    "sg:classifiers":[
        {
            "category":"Wholesale",
            "subcategory":"Construction Materials",
            "type":"Manufacturing & Wholesale Goods"
        },
        {
            "category":"Shopping",
            "subcategory":"Crafts & Fabrics",
            "type":"Retail Goods"
        },
        {
            "category":"Wholesale",
            "subcategory":"Books, Periodicals, & Newspapers",
            "type":"Manufacturing & Wholesale Goods"
        }
    ],
    "sg:phone":"+1 859 261 7245",
    "sg:postcode":"41011",
    "sg:province":"KY",
    "sg:tags":[
        "canvas",
        "manufacturer",
        "sailmaker",
        "canvas-wholesale"
    ],
    "wof:name":"River City Sails",
    "wof:placetype":"venue"
},
  "geometry": {"coordinates":[-84.51175000000001,39.072843],"type":"Point"}
}