{
  "type": "Feature",
  "properties": {
    "addr:full":"475 S Highway 27 Somerset KY 42501",
    "addr:housenumber":"475",
    "addr:postcode":"42501",
    "addr:street":"S Highway 27",
    "iso:country":"US",
    "sg:address":"475 S Highway 27",
    "sg:city":"Somerset",
    "sg:classifiers":[
        {
            "category":"Ice Cream",
            "type":"Food & Drink"
        }
    ],
    "sg:menulink":"http://www.allmenus.com/ky/somerset/161474-dairy-queen/menu/",
    "sg:phone":"+1 606 679 4104",
    "sg:postcode":"42501",
    "sg:province":"KY",
    "sg:tags":[
        "burger",
        "american"
    ],
    "wof:name":"Dairy Queen",
    "wof:placetype":"venue"
},
  "geometry": {"coordinates":[-84.616753,37.087515],"type":"Point"}
}