{
  "type": "Feature",
  "properties": {
    "iso:country":"US",
    "sg:address":"6111 Chinaberry Ct",
    "sg:city":"Prospect",
    "sg:classifiers":[
        {
            "category":"Building & Trades",
            "subcategory":"Construction",
            "type":"Services"
        }
    ],
    "sg:phone":"+1 502 426 5015",
    "sg:postcode":"40059",
    "sg:province":"KY",
    "sg:tags":[
        "house"
    ],
    "wof:name":"Home Updates",
    "wof:placetype":"venue"
},
  "geometry": {"coordinates":[-85.548733,38.334589],"type":"Point"}
}