{
  "type": "Feature",
  "properties": {
    "iso:country":"US",
    "sg:address":"1244 S 4th St",
    "sg:city":"Louisville",
    "sg:classifiers":[
        {
            "category":"Real Estate",
            "subcategory":"Real Estate Operator",
            "type":"Services"
        }
    ],
    "sg:phone":"+1 502 638 9600",
    "sg:postcode":"40203",
    "sg:province":"KY",
    "sg:tags":[
        "apartment"
    ],
    "wof:name":"NDC Management",
    "wof:placetype":"venue"
},
  "geometry": {"coordinates":[-85.760694,38.233461],"type":"Point"}
}