{
  "type": "Feature",
  "properties": {
    "addr:full":"440 Eastern Byp Richmond KY 40475",
    "addr:housenumber":"440",
    "addr:postcode":"40475",
    "addr:street":"Eastern Byp",
    "iso:country":"US",
    "sg:address":"440 Eastern Byp",
    "sg:city":"Richmond",
    "sg:classifiers":[
        {
            "category":"Restaurant",
            "type":"Food & Drink"
        }
    ],
    "sg:phone":"+1 859 626 0467",
    "sg:postcode":"40475",
    "sg:province":"KY",
    "wof:name":"Krystal",
    "wof:placetype":"venue"
},
  "geometry": {"coordinates":[-84.30002899999999,37.734265],"type":"Point"}
}