{
  "type": "Feature",
  "properties": {
    "addr:full":"235 N 2nd St Richmond KY 40475",
    "addr:housenumber":"235",
    "addr:postcode":"40475",
    "addr:street":"N 2Nd St",
    "iso:country":"US",
    "sg:address":"235 N 2nd St",
    "sg:city":"Richmond",
    "sg:classifiers":[
        {
            "category":"Organizations",
            "subcategory":"Religious Organization",
            "type":"Services"
        }
    ],
    "sg:phone":"+1 859 624 2427",
    "sg:postcode":"40475",
    "sg:province":"KY",
    "sg:tags":[
        "church"
    ],
    "wof:name":"University Church Of Christ",
    "wof:placetype":"venue"
},
  "geometry": {"coordinates":[-84.294267,37.748703],"type":"Point"}
}