{
  "type": "Feature",
  "properties": {
    "addr:full":"200 Seminole Ct Shepherdsville KY 40165",
    "addr:housenumber":"200",
    "addr:postcode":"40165",
    "addr:street":"Seminole Ct",
    "iso:country":"US",
    "sg:address":"200 Seminole Ct",
    "sg:city":"Shepherdsville",
    "sg:classifiers":[
        {
            "category":"Shopping",
            "type":"Retail Goods"
        }
    ],
    "sg:phone":"+1 502 921 0373",
    "sg:postcode":"40165",
    "sg:province":"KY",
    "sg:tags":[
        "merchandise"
    ],
    "wof:name":"Fine Art Creations",
    "wof:placetype":"venue"
},
  "geometry": {"coordinates":[-85.732097,37.979011],"type":"Point"}
}