{
  "type": "Feature",
  "properties": {
    "addr:full":"1430 S 2nd St Louisville KY 40208",
    "addr:housenumber":"1430",
    "addr:postcode":"40208",
    "addr:street":"S 2Nd St",
    "iso:country":"US",
    "sg:address":"1430 S 2nd St",
    "sg:city":"Louisville",
    "sg:classifiers":[
        {
            "category":"Building & Trades",
            "subcategory":"Construction",
            "type":"Services"
        }
    ],
    "sg:phone":"+1 502 418 3238",
    "sg:postcode":"40208",
    "sg:province":"KY",
    "sg:tags":[
        "house"
    ],
    "wof:name":"Sweet Homes",
    "wof:placetype":"venue"
},
  "geometry": {"coordinates":[-85.758278,38.228143],"type":"Point"}
}