{
  "type": "Feature",
  "properties": {
    "addr:full":"12123 Shelbyville Rd Louisville KY 40243",
    "addr:housenumber":"12123",
    "addr:postcode":"40243",
    "addr:street":"Shelbyville Rd",
    "iso:country":"US",
    "sg:address":"12123 Shelbyville Rd",
    "sg:city":"Louisville",
    "sg:classifiers":[
        {
            "category":"Professional",
            "subcategory":"Management & Consulting",
            "type":"Services"
        }
    ],
    "sg:phone":"+1 502 254 3029",
    "sg:postcode":"40243",
    "sg:province":"KY",
    "sg:tags":[
        "automotive",
        "sales",
        "custom",
        "ar",
        "designed",
        "distribution"
    ],
    "wof:name":"Carartwork Inc",
    "wof:placetype":"venue"
},
  "geometry": {"coordinates":[-85.529228,38.24788],"type":"Point"}
}