{
  "type": "Feature",
  "properties": {
    "addr:full":"989 Pedigo Way Bowling Green KY 42103",
    "addr:housenumber":"989",
    "addr:postcode":"42103",
    "addr:street":"Pedigo Way",
    "iso:country":"US",
    "sg:address":"989 Pedigo Way",
    "sg:city":"Bowling Green",
    "sg:classifiers":[
        {
            "category":"Building & Trades",
            "subcategory":"Electrical",
            "type":"Services"
        }
    ],
    "sg:phone":"+1 270 782 9992",
    "sg:postcode":"42103",
    "sg:province":"KY",
    "sg:tags":[
        "electric",
        "contractor"
    ],
    "sg:website":"www.4teamkd.com",
    "wof:name":"K D Electric Inc",
    "wof:placetype":"venue"
},
  "geometry": {"coordinates":[-86.420422,36.952351],"type":"Point"}
}