{
  "type": "Feature",
  "properties": {
    "iso:country":"US",
    "sg:address":"205 Runway Blvd",
    "sg:city":"Somerset",
    "sg:classifiers":[
        {
            "category":"Insurance",
            "subcategory":"Insurance Agent",
            "type":"Services"
        }
    ],
    "sg:phone":"+1 606 679 3141",
    "sg:postcode":"42503",
    "sg:province":"KY",
    "wof:name":"Woodmen Of The World Life Ins",
    "wof:placetype":"venue"
},
  "geometry": {"coordinates":[-84.58525,37.124853],"type":"Point"}
}