{
  "type": "Feature",
  "properties": {
    "addr:full":"600 6th St Burkesville KY 42717",
    "addr:housenumber":"600",
    "addr:postcode":"42717",
    "addr:street":"6Th St",
    "iso:country":"US",
    "sg:address":"600 6th St",
    "sg:city":"Burkesville",
    "sg:classifiers":[
        {
            "category":"Government",
            "subcategory":"Court House",
            "type":"Public Place"
        }
    ],
    "sg:phone":"+1 270 864 3726",
    "sg:postcode":"42717",
    "sg:province":"KY",
    "sg:tags":[
        "county"
    ],
    "wof:name":"Cumberland County Court Clerk",
    "wof:placetype":"venue"
},
  "geometry": {"coordinates":[-85.369818,36.801818],"type":"Point"}
}