{
  "type": "Feature",
  "properties": {
    "addr:full":"54 Dundee-Narrows Rd Dundee KY 42338",
    "addr:housenumber":"54",
    "addr:postcode":"42338",
    "addr:street":"Dundee-Narrows Rd",
    "iso:country":"US",
    "sg:address":"54 Dundee-Narrows Rd",
    "sg:city":"Dundee",
    "sg:classifiers":[
        {
            "category":"Organizations",
            "subcategory":"Religious Organization",
            "type":"Services"
        }
    ],
    "sg:phone":"+1 270 276 5015",
    "sg:postcode":"42338",
    "sg:province":"KY",
    "sg:tags":[
        "church"
    ],
    "wof:name":"Dundee Baptist Church",
    "wof:placetype":"venue"
},
  "geometry": {"coordinates":[-86.772994,37.560174],"type":"Point"}
}