{
  "type": "Feature",
  "properties": {
    "iso:country":"US",
    "sg:address":"10207 Taylorsville Rd",
    "sg:city":"Jeffersontown",
    "sg:classifiers":[
        {
            "category":"Wholesale",
            "subcategory":"Auto Parts",
            "type":"Manufacturing & Wholesale Goods"
        }
    ],
    "sg:phone":"+1 502 267 9684",
    "sg:postcode":"40299",
    "sg:province":"KY",
    "sg:tags":[
        "tire"
    ],
    "wof:name":"NTB-National Tire & Battery",
    "wof:placetype":"venue"
},
  "geometry": {"coordinates":[-85.56678100000001,38.195645],"type":"Point"}
}