{
  "type": "Feature",
  "properties": {
    "addr:full":"1115 S Laurel Rd London KY 40744",
    "addr:housenumber":"1115",
    "addr:postcode":"40744",
    "addr:street":"S Laurel Rd",
    "iso:country":"US",
    "sg:address":"1115 S Laurel Rd",
    "sg:city":"London",
    "sg:classifiers":[
        {
            "category":"Wholesale",
            "subcategory":"Farm Supplies",
            "type":"Manufacturing & Wholesale Goods"
        }
    ],
    "sg:phone":"+1 606 877 3333",
    "sg:postcode":"40744",
    "sg:province":"KY",
    "sg:tags":[
        "feed"
    ],
    "sg:website":"www.eliminatoronline.com",
    "wof:name":"Burkmann Feeds-London",
    "wof:placetype":"venue"
},
  "geometry": {"coordinates":[-84.068628,37.099777],"type":"Point"}
}