{
  "type": "Feature",
  "properties": {
    "iso:country":"US",
    "sg:address":"603 Welborn St",
    "sg:city":"Central City",
    "sg:classifiers":[
        {
            "category":"Retail",
            "subcategory":"Repair Shop",
            "type":"Services"
        }
    ],
    "sg:phone":"+1 270 754 4186",
    "sg:postcode":"42330",
    "sg:province":"KY",
    "sg:tags":[
        "television",
        "radio"
    ],
    "wof:name":"Victor's Stereo Svc",
    "wof:placetype":"venue"
},
  "geometry": {"coordinates":[-87.114991,37.288496],"type":"Point"}
}