{
  "type": "Feature",
  "properties": {
    "iso:country":"US",
    "sg:address":"975 Hustonville Rd",
    "sg:city":"Danville",
    "sg:classifiers":[
        {
            "category":"Personal",
            "subcategory":"Beauty Salon",
            "type":"Services"
        }
    ],
    "sg:phone":"+1 859 236 5491",
    "sg:postcode":"40422",
    "sg:province":"KY",
    "wof:name":"Five & Dime Family Hair Ctr",
    "wof:placetype":"venue"
},
  "geometry": {"coordinates":[-84.774911,37.630336],"type":"Point"}
}