{
  "type": "Feature",
  "properties": {
    "addr:full":"200 Airport Rd Clarksville KY 37042",
    "addr:housenumber":"200",
    "addr:postcode":"37042",
    "addr:street":"Airport Rd",
    "iso:country":"US",
    "sg:address":"200 Airport Rd",
    "sg:city":"Clarksville",
    "sg:classifiers":[
        {
            "category":"Education",
            "subcategory":"Special Training",
            "type":"Public Place"
        }
    ],
    "sg:phone":"+1 931 431 4080",
    "sg:postcode":"37042",
    "sg:province":"KY",
    "sg:tags":[
        "aircraft",
        "school"
    ],
    "wof:name":"Air Teen Flight Svc",
    "wof:placetype":"venue"
},
  "geometry": {"coordinates":[-87.42085,36.621509],"type":"Point"}
}