{
  "type": "Feature",
  "properties": {
    "iso:country":"US",
    "sg:address":"230 S Hite Ave",
    "sg:city":"Louisville",
    "sg:classifiers":[
        {
            "category":"Real Estate",
            "subcategory":"Architect",
            "type":"Services"
        }
    ],
    "sg:phone":"+1 502 899 9680",
    "sg:postcode":"40206",
    "sg:province":"KY",
    "wof:name":"Bressoud Architecture Inc",
    "wof:placetype":"venue"
},
  "geometry": {"coordinates":[-85.693175,38.251364],"type":"Point"}
}