{
  "type": "Feature",
  "properties": {
    "iso:country":"US",
    "sg:address":"1090 Eastland Dr",
    "sg:city":"Lexington",
    "sg:classifiers":[
        {
            "category":"Building & Trades",
            "subcategory":"Construction",
            "type":"Services"
        }
    ],
    "sg:phone":"+1 859 252 2444",
    "sg:postcode":"40505",
    "sg:province":"KY",
    "sg:tags":[
        "general",
        "contractor"
    ],
    "wof:name":"Marshall General Contr",
    "wof:placetype":"venue"
},
  "geometry": {"coordinates":[-84.46234,38.04618],"type":"Point"}
}