{
  "type": "Feature",
  "properties": {
    "iso:country":"US",
    "sg:address":"1860 Arlington Ave",
    "sg:city":"Louisville",
    "sg:classifiers":[
        {
            "category":"Home & Garden",
            "subcategory":"Building Materials",
            "type":"Retail Goods"
        }
    ],
    "sg:phone":"+1 502 895 8708",
    "sg:postcode":"40206",
    "sg:province":"KY",
    "sg:tags":[
        "door"
    ],
    "sg:website":"www.willisklein.com",
    "wof:name":"Klein Willis Commercial",
    "wof:placetype":"venue"
},
  "geometry": {"coordinates":[-85.713809,38.254364],"type":"Point"}
}