{
  "type": "Feature",
  "properties": {
    "iso:country":"US",
    "sg:address":"667 Capp Harlan Rd",
    "sg:city":"Tompkinsville",
    "sg:classifiers":[
        {
            "category":"Manufacturing",
            "subcategory":"Metals",
            "type":"Manufacturing & Wholesale Goods"
        }
    ],
    "sg:phone":"+1 270 487 6105",
    "sg:postcode":"42167",
    "sg:province":"KY",
    "sg:tags":[
        "product",
        "wire"
    ],
    "sg:website":"www.belden.com",
    "wof:name":"Belden Wire & Cable Co",
    "wof:placetype":"venue"
},
  "geometry": {"coordinates":[-85.676355,36.69754],"type":"Point"}
}