{
  "type": "Feature",
  "properties": {
    "addr:full":"806 Cindy Blair Way Lexington KY 40503",
    "addr:housenumber":"806",
    "addr:postcode":"40503",
    "addr:street":"Cindy Blair Way",
    "iso:country":"US",
    "sg:address":"806 Cindy Blair Way",
    "sg:city":"Lexington",
    "sg:classifiers":[
        {
            "category":"Utilities",
            "subcategory":"Fuel Oil & Lpg",
            "type":"Services"
        }
    ],
    "sg:phone":"+1 859 223 9190",
    "sg:postcode":"40503",
    "sg:province":"KY",
    "sg:tags":[
        "dealer"
    ],
    "wof:name":"Smoot Coal Land Corp",
    "wof:placetype":"venue"
},
  "geometry": {"coordinates":[-84.565015,37.99982],"type":"Point"}
}