{
  "type": "Feature",
  "properties": {
    "addr:full":"3976 Barnard Dr Lexington KY 40509",
    "addr:housenumber":"3976",
    "addr:postcode":"40509",
    "addr:street":"Barnard Dr",
    "iso:country":"US",
    "sg:address":"3976 Barnard Dr",
    "sg:city":"Lexington",
    "sg:classifiers":[
        {
            "category":"Professional",
            "subcategory":"Business Services",
            "type":"Services"
        }
    ],
    "sg:phone":"+1 859 263 8013",
    "sg:postcode":"40509",
    "sg:province":"KY",
    "wof:name":"Absolute Solutions Inc",
    "wof:placetype":"venue"
},
  "geometry": {"coordinates":[-84.399697,37.997575],"type":"Point"}
}