{
  "type": "Feature",
  "properties": {
    "iso:country":"US",
    "sg:address":"1812 Taylor Ave",
    "sg:city":"Louisville",
    "sg:classifiers":[
        {
            "category":"Professional",
            "subcategory":"Management & Consulting",
            "type":"Services"
        }
    ],
    "sg:phone":"+1 502 479 5661",
    "sg:postcode":"40213",
    "sg:province":"KY",
    "sg:tags":[
        "report",
        "construction"
    ],
    "wof:name":"Reed Construction Data",
    "wof:placetype":"venue"
},
  "geometry": {"coordinates":[-85.70400100000001,38.200688],"type":"Point"}
}