{
  "type": "Feature",
  "properties": {
    "iso:country":"US",
    "sg:address":"1600 N Main St",
    "sg:city":"Hopkinsville",
    "sg:classifiers":[
        {
            "category":"Shopping",
            "subcategory":"Tobacco",
            "type":"Retail Goods"
        }
    ],
    "sg:phone":"+1 270 707 1700",
    "sg:postcode":"42240",
    "sg:province":"KY",
    "sg:tags":[
        "cigarette",
        "cigar",
        "dealer"
    ],
    "wof:name":"US Smokeless Tobacco Co",
    "wof:placetype":"venue"
},
  "geometry": {"coordinates":[-87.480576,36.897083],"type":"Point"}
}