{
  "type": "Feature",
  "properties": {
    "iso:country":"US",
    "sg:address":"1100 Hansel Ave",
    "sg:city":"Florence",
    "sg:classifiers":[
        {
            "category":"Shopping",
            "subcategory":"Department Store",
            "type":"Retail Goods"
        },
        {
            "category":"Shopping",
            "subcategory":"Pharmacy",
            "type":"Retail Goods"
        }
    ],
    "sg:phone":"+1 859 371 2245",
    "sg:postcode":"41042",
    "sg:province":"KY",
    "sg:tags":[
        "drugstore"
    ],
    "sg:website":"www.target.com",
    "wof:name":"Target Stores",
    "wof:placetype":"venue"
},
  "geometry": {"coordinates":[-84.63341200000001,39.018517],"type":"Point"}
}