{
  "type": "Feature",
  "properties": {
    "addr:full":"1200 Master St Corbin KY 40701",
    "addr:housenumber":"1200",
    "addr:postcode":"40701",
    "addr:street":"Master St",
    "iso:country":"US",
    "sg:address":"1200 Master St",
    "sg:city":"Corbin",
    "sg:classifiers":[
        {
            "category":"Wholesale",
            "subcategory":"Machinery & Supplies",
            "type":"Manufacturing & Wholesale Goods"
        }
    ],
    "sg:phone":"+1 606 528 8861",
    "sg:postcode":"40701",
    "sg:province":"KY",
    "sg:tags":[
        "equipment",
        "conveyor",
        "conveying"
    ],
    "wof:name":"Continental Conveyor & Equip",
    "wof:placetype":"venue"
},
  "geometry": {"coordinates":[-84.082808,36.953666],"type":"Point"}
}