{
  "type": "Feature",
  "properties": {
    "iso:country":"US",
    "sg:address":"1217 S Green St",
    "sg:city":"Glasgow",
    "sg:classifiers":[
        {
            "category":"Organizations",
            "subcategory":"Religious Organization",
            "type":"Services"
        }
    ],
    "sg:phone":"+1 270 651 6343",
    "sg:postcode":"42141",
    "sg:province":"KY",
    "sg:tags":[
        "church"
    ],
    "wof:name":"Glasgow First Assembly Of God",
    "wof:placetype":"venue"
},
  "geometry": {"coordinates":[-85.926062,36.985105],"type":"Point"}
}