{
  "type": "Feature",
  "properties": {
    "iso:country":"US",
    "sg:address":"9789 Ironworks Rd",
    "sg:city":"Winchester",
    "sg:classifiers":[
        {
            "category":"Arts & Performance",
            "subcategory":"Theater",
            "type":"Entertainment"
        }
    ],
    "sg:phone":"+1 859 842 4454",
    "sg:postcode":"40391",
    "sg:province":"KY",
    "sg:tags":[
        "live",
        "music"
    ],
    "wof:name":"Big D Entertainment",
    "wof:placetype":"venue"
},
  "geometry": {"coordinates":[-84.04772199999999,37.946077],"type":"Point"}
}