{
  "type": "Feature",
  "properties": {
    "iso:country":"US",
    "sg:address":"2625 Bardstown Rd",
    "sg:city":"St Catharine",
    "sg:classifiers":[
        {
            "category":"Health Services",
            "subcategory":"Nursing And Care Facility",
            "type":"Services"
        }
    ],
    "sg:phone":"+1 859 336 3974",
    "sg:postcode":"40069",
    "sg:province":"KY",
    "sg:tags":[
        "home",
        "convalescent"
    ],
    "wof:name":"Sansbury Care Ctr",
    "wof:placetype":"venue"
},
  "geometry": {"coordinates":[-85.261245,37.710825],"type":"Point"}
}