{
  "type": "Feature",
  "properties": {
    "iso:country":"US",
    "sg:address":"180 Country View Ct",
    "sg:city":"Campbellsville",
    "sg:classifiers":[
        {
            "category":"Farming",
            "subcategory":"Livestock Farm",
            "type":"Manufacturing & Wholesale Goods"
        }
    ],
    "sg:phone":"+1 270 465 3478",
    "sg:postcode":"42718",
    "sg:province":"KY",
    "sg:tags":[
        "specialty",
        "animal"
    ],
    "wof:name":"Roy Seaborne",
    "wof:placetype":"venue"
},
  "geometry": {"coordinates":[-85.324724,37.333393],"type":"Point"}
}