{
  "type": "Feature",
  "properties": {
    "iso:country":"US",
    "sg:address":"508 Main St",
    "sg:city":"Greenup",
    "sg:classifiers":[
        {
            "category":"Autos & Motor Vehicles",
            "subcategory":"Automobile Sales",
            "type":"Retail Goods"
        }
    ],
    "sg:phone":"+1 606 473 7536",
    "sg:postcode":"41144",
    "sg:province":"KY",
    "sg:tags":[
        "car",
        "dealer"
    ],
    "wof:name":"Greenup Chevrolet Buick Inc",
    "wof:placetype":"venue"
},
  "geometry": {"coordinates":[-82.834919,38.576532],"type":"Point"}
}