{
  "type": "Feature",
  "properties": {
    "iso:country":"US",
    "sg:address":"3337 Newburg Rd",
    "sg:city":"Louisville",
    "sg:classifiers":[
        {
            "category":"Banks & Credit Unions",
            "subcategory":"Bank",
            "type":"Services"
        }
    ],
    "sg:phone":"+1 502 581 5242",
    "sg:postcode":"40218",
    "sg:province":"KY",
    "wof:name":"National City Bank",
    "wof:placetype":"venue"
},
  "geometry": {"coordinates":[-85.684155,38.199514],"type":"Point"}
}