{
  "type": "Feature",
  "properties": {
    "iso:country":"US",
    "sg:address":"506 Brookview Rd",
    "sg:city":"Louisville",
    "sg:classifiers":[
        {
            "category":"Real Estate",
            "subcategory":"Real Estate Services",
            "type":"Services"
        }
    ],
    "sg:phone":"+1 502 896 0170",
    "sg:postcode":"40207",
    "sg:province":"KY",
    "sg:tags":[
        "vacancy",
        "rental",
        "listing"
    ],
    "wof:name":"Howard & Howard Properties",
    "wof:placetype":"venue"
},
  "geometry": {"coordinates":[-85.637496,38.267757],"type":"Point"}
}