{
  "type": "Feature",
  "properties": {
    "iso:country":"US",
    "sg:address":"2312 Reid Rd",
    "sg:city":"Owensboro",
    "sg:classifiers":[
        {
            "category":"Autos & Motor Vehicles",
            "subcategory":"Automobile Sales",
            "type":"Retail Goods"
        }
    ],
    "sg:phone":"+1 270 684 5128",
    "sg:postcode":"42303",
    "sg:province":"KY",
    "sg:tags":[
        "used"
    ],
    "wof:name":"Barnett Motors",
    "wof:placetype":"venue"
},
  "geometry": {"coordinates":[-87.025628,37.781043],"type":"Point"}
}