{
  "type": "Feature",
  "properties": {
    "iso:country":"US",
    "sg:address":"314 Barton Ln",
    "sg:city":"Pleasureville",
    "sg:classifiers":[
        {
            "category":"Banks & Credit Unions",
            "subcategory":"Bank",
            "type":"Services"
        }
    ],
    "sg:phone":"+1 502 845 0444",
    "sg:postcode":"40057",
    "sg:province":"KY",
    "sg:tags":[
        "lender",
        "agricultural"
    ],
    "wof:name":"US Agbank Fcb",
    "wof:placetype":"venue"
},
  "geometry": {"coordinates":[-85.098743,38.440811],"type":"Point"}
}