{
  "type": "Feature",
  "properties": {
    "iso:country":"US",
    "sg:address":"1906 W Cumberland Ave",
    "sg:city":"Middlesboro",
    "sg:classifiers":[
        {
            "category":"Personal",
            "type":"Services"
        }
    ],
    "sg:phone":"+1 606 248 6789",
    "sg:postcode":"40965",
    "sg:province":"KY",
    "wof:name":"Sun Palace",
    "wof:placetype":"venue"
},
  "geometry": {"coordinates":[-83.712733,36.607292],"type":"Point"}
}