{
  "type": "Feature",
  "properties": {
    "iso:country":"US",
    "sg:address":"311 S Dixie Blvd",
    "sg:city":"Radcliff",
    "sg:classifiers":[
        {
            "category":"Restaurant",
            "type":"Food & Drink"
        }
    ],
    "sg:menulink":"http://www.allmenus.com/ky/radcliff/208573-taco-bell/menu/",
    "sg:phone":"+1 270 351 5554",
    "sg:postcode":"40160",
    "sg:province":"KY",
    "sg:tags":[
        "mexican"
    ],
    "wof:name":"Taco Bell",
    "wof:placetype":"venue"
},
  "geometry": {"coordinates":[-85.934781,37.836268],"type":"Point"}
}