{
  "type": "Feature",
  "properties": {
    "iso:country":"US",
    "sg:address":"1301 Clear Springs Trce",
    "sg:city":"Louisville",
    "sg:classifiers":[
        {
            "category":"Professional",
            "subcategory":"Accounting & Tax Preparation",
            "type":"Services"
        }
    ],
    "sg:phone":"+1 502 426 0000",
    "sg:postcode":"40223",
    "sg:province":"KY",
    "sg:tags":[
        "accountant"
    ],
    "sg:website":"www.cox-oldham.com",
    "wof:name":"Cox & Oldham",
    "wof:placetype":"venue"
},
  "geometry": {"coordinates":[-85.567532,38.225437],"type":"Point"}
}