{
  "type": "Feature",
  "properties": {
    "iso:country":"US",
    "sg:address":"407 N 2nd St",
    "sg:city":"Nicholasville",
    "sg:classifiers":[
        {
            "category":"Real Estate",
            "subcategory":"Real Estate Operator",
            "type":"Services"
        }
    ],
    "sg:phone":"+1 859 881 0592",
    "sg:postcode":"40356",
    "sg:province":"KY",
    "sg:tags":[
        "apartment"
    ],
    "wof:name":"Creekside Senior Apartments",
    "wof:placetype":"venue"
},
  "geometry": {"coordinates":[-84.573061,37.885727],"type":"Point"}
}