{
  "type": "Feature",
  "properties": {
    "iso:country":"US",
    "sg:address":"105 Daventry Ln",
    "sg:city":"Louisville",
    "sg:classifiers":[
        {
            "category":"Professional",
            "subcategory":"Research",
            "type":"Services"
        }
    ],
    "sg:phone":"+1 502 326 5021",
    "sg:postcode":"40223",
    "sg:province":"KY",
    "sg:tags":[
        "environmental",
        "ecological"
    ],
    "wof:name":"Enviroplan Consulting",
    "wof:placetype":"venue"
},
  "geometry": {"coordinates":[-85.575248,38.247633],"type":"Point"}
}