{
  "type": "Feature",
  "properties": {
    "addr:full":"1914 Magazine St Louisville KY 40203",
    "addr:housenumber":"1914",
    "addr:postcode":"40203",
    "addr:street":"Magazine St",
    "iso:country":"US",
    "sg:address":"1914 Magazine St",
    "sg:city":"Louisville",
    "sg:classifiers":[
        {
            "category":"Social Services",
            "subcategory":"Child Care",
            "type":"Services"
        }
    ],
    "sg:phone":"+1 502 778 8084",
    "sg:postcode":"40203",
    "sg:province":"KY",
    "sg:tags":[
        "day"
    ],
    "wof:name":"Angela Lewis",
    "wof:placetype":"venue"
},
  "geometry": {"coordinates":[-85.785065,38.250535],"type":"Point"}
}