{
  "type": "Feature",
  "properties": {
    "addr:full":"2707 Fleming Ave Louisville KY 40206",
    "addr:housenumber":"2707",
    "addr:postcode":"40206",
    "addr:street":"Fleming Ave",
    "iso:country":"US",
    "sg:address":"2707 Fleming Ave",
    "sg:city":"Louisville",
    "sg:classifiers":[
        {
            "category":"Banks & Credit Unions",
            "subcategory":"Bank",
            "type":"Services"
        }
    ],
    "sg:phone":"+1 502 897 0322",
    "sg:postcode":"40206",
    "sg:province":"KY",
    "sg:tags":[
        "cashing",
        "check"
    ],
    "wof:name":"Cash Plus",
    "wof:placetype":"venue"
},
  "geometry": {"coordinates":[-85.697711,38.261834],"type":"Point"}
}