{
  "type": "Feature",
  "properties": {
    "iso:country":"US",
    "sg:address":"2225 Douglass Blvd",
    "sg:city":"Louisville",
    "sg:classifiers":[
        {
            "category":"Real Estate",
            "subcategory":"Real Estate Operator",
            "type":"Services"
        }
    ],
    "sg:phone":"+1 502 456 9049",
    "sg:postcode":"40205",
    "sg:province":"KY",
    "sg:tags":[
        "building",
        "apartment"
    ],
    "wof:name":"Valley Vista Ventures LLC",
    "wof:placetype":"venue"
},
  "geometry": {"coordinates":[-85.686447,38.228466],"type":"Point"}
}