{
  "type": "Feature",
  "properties": {
    "iso:country":"US",
    "sg:address":"214 W John Fitch Ave",
    "sg:city":"Bardstown",
    "sg:classifiers":[
        {
            "category":"Health Services",
            "subcategory":"Doctor",
            "type":"Services"
        }
    ],
    "sg:phone":"+1 502 348 4388",
    "sg:postcode":"40004",
    "sg:province":"KY",
    "sg:tags":[
        "dentist"
    ],
    "wof:name":"David A Graves DDS",
    "wof:placetype":"venue"
},
  "geometry": {"coordinates":[-85.470505,37.808463],"type":"Point"}
}