{
  "type": "Feature",
  "properties": {
    "addr:full":"1256 Campbell Ln Bowling Green KY 42104",
    "addr:housenumber":"1256",
    "addr:postcode":"42104",
    "addr:street":"Campbell Ln",
    "iso:country":"US",
    "sg:address":"1256 Campbell Ln",
    "sg:city":"Bowling Green",
    "sg:classifiers":[
        {
            "category":"Professional",
            "subcategory":"Employment Agencies",
            "type":"Services"
        }
    ],
    "sg:phone":"+1 270 842 2906",
    "sg:postcode":"42104",
    "sg:province":"KY",
    "sg:tags":[
        "help",
        "contractor"
    ],
    "wof:name":"Kelly Services Inc",
    "wof:placetype":"venue"
},
  "geometry": {"coordinates":[-86.449922,36.959142],"type":"Point"}
}