{
  "type": "Feature",
  "properties": {
    "addr:full":"325 W Cumberland Gap Pkwy Corbin KY 40701",
    "addr:housenumber":"325",
    "addr:postcode":"40701",
    "addr:street":"W Cumberland Gap Pkwy",
    "iso:country":"US",
    "sg:address":"325 W Cumberland Gap Pkwy",
    "sg:city":"Corbin",
    "sg:classifiers":[
        {
            "category":"Restaurant",
            "type":"Food & Drink"
        }
    ],
    "sg:menulink":"http://www.allmenus.com/ky/north-corbin/101764-huddle-house/menu/",
    "sg:phone":"+1 606 258 7101",
    "sg:postcode":"40701",
    "sg:province":"KY",
    "sg:tags":[
        "american",
        "diner"
    ],
    "wof:name":"Huddle House",
    "wof:placetype":"venue"
},
  "geometry": {"coordinates":[-84.08907600000001,36.97022],"type":"Point"}
}