{
  "type": "Feature",
  "properties": {
    "iso:country":"US",
    "sg:address":"760 River Rd",
    "sg:city":"Lockport",
    "sg:classifiers":[
        {
            "category":"Manufacturing",
            "subcategory":"Petroleum Products",
            "type":"Manufacturing & Wholesale Goods"
        }
    ],
    "sg:phone":"+1 502 845 4556",
    "sg:postcode":"40007",
    "sg:province":"KY",
    "sg:tags":[
        "asphalt"
    ],
    "wof:name":"Mago Construction Co",
    "wof:placetype":"venue"
},
  "geometry": {"coordinates":[-84.95911599999999,38.461102],"type":"Point"}
}