{
  "type": "Feature",
  "properties": {
    "iso:country":"US",
    "sg:address":"2345 Carton Dr",
    "sg:city":"Jeffersontown",
    "sg:classifiers":[
        {
            "category":"Professional",
            "type":"Services"
        }
    ],
    "sg:phone":"+1 502 495 5520",
    "sg:postcode":"40299",
    "sg:province":"KY",
    "sg:tags":[
        "establishment"
    ],
    "wof:name":"Life",
    "wof:placetype":"venue"
},
  "geometry": {"coordinates":[-85.56089900000001,38.214628],"type":"Point"}
}